Workbook

Sheet Overview
A1: BISHOPS WALTHAM | B1: Total in £ | C1: Error | D1: Note
A2: CASH ACCOUNT
A3: RECEIPTS
A4: Arrears total
A5: Rents of assize total
A6: Quittances total
A7: Defaults of rent total
A8: Defaults of rent through the pestilence total
A9: Cotlands defaults total
A10: Cotlands total
A11: Total of quittances and defaults of rent total
A12: Total of rents remaining clear total
A13: Farms total
... A22: Farm of the demesne land total
A23: Total of all receipts (calculated here) | B23: =Receipts!F251 -> 210.17833
A24: Total of all receipts (calculated here) incl arrears | B24: =Receipts!F252 -> 282.08833
A25: Total recorded in the accounts excl. arrears | B25: =Receipts!F250 -> 230.19 | C25: =B25-B23 -> 20.011667
A26: Total recorded in the accounts incl. arrears
A29: EXPENSES
A30: Cost of ploughs total
A31: Purchase of corn total
A32: Cost of carts and wagons total
A33: Cost of dairy total
A34: Purchase of stock total
A35: Sheepcote total
A36: Cost of buildings total
A37: Threshing total
A38: Barley expenses
A39: Expenses of the harvest total
... A43: Annual fees
A44: Total of all expenses per account | B44: =Expenses!F163 -> 54.45
A45: Total of all expenses (calculated here) | B45: =Expenses!F164 -> 53.956667
A46: Total fixed investment | B46: =Expenses!F165 -> 12.888333
A47: Total Demesne fixed investment | B47: =Expenses!F166 -> 8.7883333
A49: Owed by the reeve
A50: From accounts
A52: Allowances
A53: Cash deliveries
A54: Sum of the above
A55: Total of all allowances and cash deliveries in accounts
A57: Net amount owed
A58: Net amount owed in accounts
A60: GRANGE ACCOUNT | B60: Total Production
A61: Grange | B61: qrs | E61: Value of total gross production in £ | F61: Value of total net production in £
A62: wheat | B62: ='Issues of the Grange'!B2 -> 132.25 | E62: ='Issues of the Grange'!I2 -> 40.99825 | F62: ='Issues of the Grange'!O11 -> 22.785417
A63: curall | B63: ='Issues of the Grange'!B3 -> 10 | E63: ='Issues of the Grange'!I3 -> 1.089372 | F63: ='Issues of the Grange'!O12 -> 0.93958333
A64: barley | B64: ='Issues of the Grange'!B4 -> 83.375 | E64: ='Issues of the Grange'!I4 -> 16.675 | F64: ='Issues of the Grange'!O13 -> 1.15
A65: oats | B65: ='Issues of the Grange'!B5 -> 205.0625 | E65: ='Issues of the Grange'!I5 -> 23.307174 | F65: ='Issues of the Grange'!O14 -> 6.6987703
A66: peas | B66: ='Issues of the Grange'!B6 -> 3.8125 | E66: ='Issues of the Grange'!I6 -> 0.50833333 | F66: ='Issues of the Grange'!O15 -> 0.033333333
A67: vetches | B67: ='Issues of the Grange'!B7 -> 11.375 | E67: ='Issues of the Grange'!I7 -> 1.1375 | F67: ='Issues of the Grange'!O16 -> 0.225
A68: Total value of gross production (sum of the above) | E68: =SUM(E62:E67) -> 83.715629
A69: Total value of net production | E69: =SUM(F62:F67) -> 31.832104
A70: Value of sales | E70: =Receipts!F175+Receipts!F170+Receipts!F184 -> 23.028333
A72: MILL ACCOUNT
A73: Issues of the mill
A74: Wheat
A75: Oatmeal
A76: 1st grade malt
A77: 2nd grade malt
A78: Maslin
A79: Total value of production (sum of the above)
A80: Value of sales
A82: STOCK ACCOUNT
A83: Livestock | B83: Sales value in £
A84: Cart-horses | B84: =Stock!R5 -> 0
A85: Mares | B85: =Stock!R6 -> 0
A86: Plough horses | B86: =Stock!R7 -> 0.57
A87: Colts (2 years) | B87: =Stock!R8 -> 0
A88: Colts (2 years) | B88: =Stock!R9 -> 0
A89: Colts (1 year) | B89: =Stock!R10 -> 0
A90: Foals | B90: =Stock!R11 -> 0
A91: Oxen | B91: =Stock!R12 -> 2.8
A92: Bulls | B92: =Stock!R13 -> 0
A93: Cows | B93: =Stock!R14 -> 1.8
A94: Steers | B94: =Stock!R15 -> 0
A95: Bullocks | B95: =Stock!R16 -> 0
... A109: Peacocks | B109: =Stock!R30 -> 0
A110: Total value of stock (sum of the above)
A111: Total value of production
A112: Value of sales | B112: =Stock!R31 -> 7.68
A114: Wool | B114: Value of production at sales prices £
A115: Coarse wool | B115: =Stock!T35 -> 8.56
A116: Lamb's wool | B116: =Stock!T36 -> 1.22
A117: Wool locks | B117: =Stock!T37 -> 0.2625
A118: Wool sold at shearing | B118: =Stock!T38 -> 0
A119: Total value of production (sum of the above) | B119: =Stock!T39 -> 10.0425
A120: Value of sales | B120: 0
A122: Hides | B122: Value of production at sales prices £
A123: Ox hides | B123: =Stock!T43 -> 0
A124: Cow hides | B124: =Stock!T44 -> 0
A125: Mare hides | B125: =Stock!T45 -> 0
A126: Steer hides | B126: =Stock!T46 -> 0
A127: Yearling Calf hides | B127: =Stock!T47 -> 0
A128: Calf hides | B128: =Stock!T48 -> 0
A129: Pig hides | B129: =Stock!T49 -> 0
A130: Wether woolskins | B130: =Stock!T50 -> 0
A131: Ram woolskins | B131: =Stock!T51 -> 0
A132: Ewe woolskins | B132: =Stock!T52 -> 0
A133: Hogg woolskins | B133: =Stock!T53 -> 0
A134: Woolskins (total) | B134: =Stock!T54 -> 0
...

Sheet Receipts
A1: BISHOPS WALTHAM RECEIPT
A2: Heading | B2: £ | C2: s | D2: d | F2: Total in £ | G2: Error | H2: Notes
A3: Arrears | B3: 71 | C3: 18 | D3: 3.5 | F3: 71.91 | H3: Robert de Froyle, bailiff, and Robert Stretthe, reeve, render account for £71 18 shilling 3.5pence of arrears from the previous year.
A4: Arrears | B4: 0 | C4: 0 | D4: 0 | F4: 0 | H4: All delivered to Sir Geoffrey, treasurer of Wolvesey, by 1 tally, and they are quit.
A5: Arrears | F5: 71.91 | G5: =F5-F3 -> 0 | H5: Total
A7: Rents | B7: 14 | C7: 10 | D7: 10.75 | F7: 14.54 | H7: The same render account for £14 10 shilling 10.75pence for all rents of assize at Christmas.
A8: Rents | B8: 23 | C8: 0 | D8: 8.75 | F8: 23.04 | H8: £23 8.75pence at Easter (22 April).
A9: Rents | B9: 14 | C9: 10 | D9: 10.5 | F9: 14.54 | H9: £14 10 shilling 10.5pence at the Nativity of St John the Baptist (24 June).
A10: Rents | B10: 23 | C10: 19 | D10: 3.5 | F10: 23.96 | H10: £23 19 shilling 3.5pence at Michaelmas (29 September).
A11: Rents | B11: 76 | C11: 1 | D11: 9.5 | F11: 76.09 | H11: Total, £76 1 shilling 9.5pence
A12: Rents | F12: 76.08 | G12: -0.01 | H12: Total
A14: Quittances | B14: 0 | C14: 5 | D14: 0 | F14: 0.25 | H14: In quittance of 1 reeve for the year 5 shilling.
A15: Quittances | B15: 0 | C15: 5 | D15: 0 | F15: 0.25 | H15: 1 beadle for the year 5 shilling.
A16: Quittances | B16: 0 | C16: 10 | D16: 0 | F16: 0.5 | H16: 1 swineherd, 1 smith, 1 hayward who kept the lord's corn and pasture and sowed the wheat and barley, 1 shepherd of wethers, and 1 keeper of ewes, 10 shilling, or 2 shilling each.
A17: Quittances | B17: 0 | C17: 8 | D17: 6 | F17: 0.43 | H17: 4 ploughmen for the year, and 1 ploughman for 1 term, 8 shilling 6pence.
A18: Quittances | B18: 0 | C18: 18 | D18: 0 | F18: 0.9 | H18: 9 workers, each of whom are bound to reap everyday at harvest-time 1 acre as it lies and after the harvest are bound to work twice a week, 18 shilling, or 2 shilling each.
A19: Quittances | B19: 0 | C19: 3 | D19: 0 | F19: 0.15 | H19: 3 cottars for the year, each of whom are bound to reap everyday .5 acre as it lies and after the harvest are bound to work once a week, 3 shilling.
A20: Quittances | B20: 0 | C20: 6 | D20: 0 | F20: 0.3 | H20: 2 workers who are bound to reap everyday at harvest-time 1 acre as it lies and after the harvest are bound to work twice a week with their carts, working at the lord's pleasure, besides carrying dung, 6 shilling for the year.
A21: Quittances | B21: 0 | C21: 2 | D21: 0 | F21: =B21+C21/20+D21/240 -> 0.1 | H21: 1 granary-keeper for the year 2 shilling
A22: Quittances | B22: 2 | C22: 17 | D22: 6 | F22: 2.88 | H22: Total, £2 17 shilling 6pence
A23: Quittances | F23: =SUM(F14:F21) -> 2.88 | G23: =F23-F22 -> 0 | H23: Total
A25: Defaults of rent | B25: 1 | C25: 2 | D25: 8 | F25: 1.13 | H25: In default of the land between the Barton and garden drawn into demesne, £1 2 shilling 8pence for the year.
A26: Defaults of rent | B26: 0 | C26: 0 | D26: 8 | F26: 0.03 | H26: the land of Osbert de Langely, 8pence for the year.
A27: Defaults of rent | B27: 0 | C27: 0 | D27: 6 | F27: 0.03 | H27: the land of Richard Baton, 6pence for the year.
A28: Defaults of rent | B28: 0 | C28: 0 | D28: 6 | F28: 0.03 | H28: the land of Hugh son of Agnes, 6pence for the year.
A29: Defaults of rent | B29: 0 | C29: 0 | D29: 3 | F29: 0.01 | H29: the land of Richard Swanemere, 3pence for the year.
A30: Defaults of rent | B30: 0 | C30: 6 | D30: 5 | F30: 0.32 | H30: the land of the mill drawn into the park, 6 shilling 5pence for the year.
A31: Defaults of rent | B31: 0 | C31: 1 | D31: 6 | F31: 0.08 | H31: the rent of Peter Clericus, 1 shilling 6pence for the year.
A32: Defaults of rent | B32: 1 | C32: 12 | D32: 6 | F32: 1.62 | H32: Total, £1 12 shilling 6pence
A33: Defaults of rent | F33: 1.63 | G33: 0.01 | H33: Total
A35: Total of quittances and defaults of rent | B35: 4 | C35: 10 | D35: 0 | F35: 4.5 | H35: Total of quittances and defaults of rent, £4 10 shilling
A36: Total of quittances and defaults of rent | F36: 4.5 | G36: =F36-F35 -> 0 | H36: Total
A38: Total of rents remaining | B38: 71 | C38: 0 | D38: 0 | F38: 71 | H38: Total of rents remaining, £71 11 s. 9.5pence
A39: Total of rents remaining | F39: 71 | G39: =F39-F38 -> 0 | H39: Total
A41: Cumin | B41: 0 | C41: 0 | D41: 0 | F41: 0 | H41: The same render account for 1 lb of cumin from Peter Clericus for a certain messuage.
A42: Cumin | B42: 0 | C42: 0 | D42: 0 | F42: 0 | H42: 1 lb from John Suneburn and Thomas Canon for the same.
A43: Cumin | B43: 0 | C43: 0 | D43: 0 | F43: 0 | H43: 1 lb from Robert Faber to have 1 plot beside the fishpond.
A44: Cumin | B44: 0 | C44: 0 | D44: 0 | F44: 0 | H44: 1 lb from William Burg' for the same.
A45: Cumin | B45: 0 | C45: 0 | D45: 0 | F45: 0 | H45: 1 lb from Robert Ude for the same.
A46: Cumin | B46: 0 | C46: 0 | D46: 0 | F46: 0 | H46: 1 lb from Richard Doggecherl for the same.
A47: Cumin | B47: 0 | C47: 0 | D47: 0 | F47: 0 | H47: Total, 6 lbs.
A48: Cumin | B48: 0 | C48: 0 | D48: 0 | F48: 0 | H48: All delivered to Wolvesey.
A49: Cumin | F49: 0 | G49: 0 | H49: Total
A51: Pepper | B51: 0 | C51: 0 | D51: 0 | F51: 0 | H51: The same render account for 0.5 lb of pepper from Roger Everard for certain land which his father bought from Henry Philipp'.
A52: Pepper | B52: 0 | C52: 0 | D52: 0 | F52: 0 | H52: All delivered to Wolvesey.
A53: Pepper | F53: 0 | G53: 0 | H53: Total
A55: Annual recognizance | B55: 0 | C55: 0 | D55: 6 | F55: 0.03 | H55: The same render account for 6pence from Adam de Marwell' for annual recognizance.
A56: Annual recognizance | B56: 0 | C56: 0 | D56: 6 | F56: 0.03 | H56: 6pence from Geoffrey le Warernyr for the same.
A57: Annual recognizance | B57: 0 | C57: 0 | D57: 6 | F57: 0.03 | H57: 6pence from Richard de Deily, clerk,1 whilst he wishes to remain outside the manor.
A58: Annual recognizance | B58: 0 | C58: 0 | D58: 6 | F58: 0.03 | H58: 6pence from John Pyk for annual recognizance.
A59: Annual recognizance | B59: 0 | C59: 0 | D59: 6 | F59: 0.03 | H59: 6pence from Geoffrey de Ecclesia for the same.
A60: Annual recognizance | B60: 0 | C60: 0 | D60: 6 | F60: 0.03 | H60: 6pence from Henry Wldred' for not being in a tithing.
A61: Annual recognizance | B61: 0 | C61: 0 | D61: 3 | F61: 0.01 | H61: 3pence from John, son of Robert Marescal, for annual recognizance.
A62: Annual recognizance | B62: 0 | C62: 0 | D62: 3 | F62: 0.01 | H62: 3pence from John Gyles for no longer being prosecuted by the tithing.
A63: Annual recognizance | B63: 0 | C63: 0 | D63: 3 | F63: 0.01 | H63: 3pence from John Smermongar' for the same.
A64: Annual recognizance | B64: 0 | C64: 0 | D64: 6 | F64: 0.03 | H64: 6pence from William de Bottely for no longer being prosecuted for tithingpenny, but he will come to court for the two law-days only, and this during the lord's pleasure.
A65: Annual recognizance | B65: 0 | C65: 0 | D65: 3 | F65: 0.01 | H65: 3pence from Henry Burden for annual recognizance.
A66: Annual recognizance | B66: 0 | C66: 4 | D66: 6 | F66: 0.23 | H66: Total, 4 shilling 6pence
A67: Annual recognizance | F67: 0.25 | G67: 0.02 | H67: Total
A69: Issues of the manor | B69: 2 | C69: 12 | D69: 7 | F69: 2.63 | H69: The same render account for £2 12 shilling 7pence from pannage of pigs within this year.
A70: Issues of the manor | B70: 0 | C70: 0 | D70: 0 | F70: 0 | H70: nothing from foreign pannage of pigs this year.
A71: Issues of the manor | B71: 5 | C71: 3 | D71: 2 | F71: 5.16 | H71: £5 3 shilling 2pence from pannage of pigs in the park this year.
A72: Issues of the manor | B72: 5 | C72: 15 | D72: 6 | F72: 5.78 | H72: £5 15 shilling 6pence from the agistment of livestock in the park, as made clear in the details.
A73: Issues of the manor | B73: 0 | C73: 8 | D73: 0 | F73: 0.4 | H73: 8 shilling from 1 old plough-horse sold.
A74: Issues of the manor | B74: 0 | C74: 3 | D74: 4 | F74: 0.17 | H74: 3 shilling 4pence from 1 feeble plough-horse from the heriot of John Schore sold.
A75: Issues of the manor | B75: 2 | C75: 16 | D75: 0 | F75: 2.8 | H75: £2 16 shilling from 6 old oxen sold, at 8 shilling for 1, 9 shilling each for 2, and 10 shilling each for 3.
A76: Issues of the manor | B76: 1 | C76: 16 | D76: 0 | F76: 1.8 | H76: £1 16 shilling from 6 feeble cows sold, at 6 shilling each.
A77: Issues of the manor | B77: 0 | C77: 6 | D77: 0 | F77: 0.3 | H77: 6 shilling from 6 late-born calves sold, at 1 shilling each.
A78: Issues of the manor | B78: 0 | C78: 7 | D78: 0 | F78: 0.35 | H78: 7 shilling from 7 old wethers sold at Martinmas.
A79: Issues of the manor | B79: 0 | C79: 5 | D79: 10 | F79: 0.29 | H79: 5 shilling 10pence from 7 old ewes sold at the same feast.
A80: Issues of the manor | B80: 0 | C80: 13 | D80: 6 | F80: 0.68 | H80: 13 shilling from 26 hoggs sold, at 6pence each.
... A107: Issues of the manor | B107: 7 | C107: 6 | D107: 3 | F107: 7.31 | H107: £7 6 shilling 3pence from 292.5 sesters of salt from the arrears of the last account.
A108: Issues of the manor | B108: 0 | C108: 12 | D108: 10 | F108: =B108+C108/12+D108/20 -> 1.5 | H108: 12 shilling 10 pence from 154 hens from churchscot sold.
A109: Issues of the manor | B109: 0 | C109: 9 | D109: 0 | F109: 0.45 | H109: 9 shilling from the hundred for the mowing of Cribelescrofte.
A110: Issues of the manor | B110: 0 | C110: 6 | D110: 4 | F110: 0.32 | H110: 6 shilling 4pence from the pasturage sold in various places, that is, 5 shilling from la Worth' and 1 shilling 4pence from various remnants around Orkelestret.
A111: Issues of the manor | B111: 0 | C111: 1 | D111: 6 | F111: 0.08 | H111: 1 shilling 6pence from the hundred for the mowing of the meadow of Bitterne.
A112: Issues of the manor | B112: 0 | C112: 6 | D112: 8 | F112: 0.33 | H112: 6 shilling 8pence from heath in the park sold this year.
A113: Issues of the manor | B113: 0 | C113: 0 | D113: 0 | F113: 0 | H113: nothing from nuts collected in the park this year.
A114: Issues of the manor | B114: 0 | C114: 10 | D114: 6 | F114: 0.53 | H114: 10 shilling 6pence from the loppings of oaks felled to mend the palisade.
A115: Issues of the manor | B115: 0 | C115: 5 | D115: 0 | F115: 0.25 | H115: 5 shilling from cablish in the park sold this year.
A116: Issues of the manor | B116: 0 | C116: 2 | D116: 2 | F116: 0.11 | H116: 2 shilling 2pence from 2 dead trees sold felled in le Hordareswod' for the bees.
A117: Issues of the manor | B117: 0 | C117: 0 | D117: 0 | F117: 0 | H117: nothing from dead trees in the wood of Parkhurst this year.
A118: Issues of the manor | B118: 0 | C118: 0 | D118: 0 | F118: 0 | H118: nothing from wood in Holemor' this year.
A119: Issues of the manor | B119: 0 | C119: 1 | D119: 3 | F119: 0.06 | H119: 1 shilling 3pence from honey sold this year.
A120: Issues of the manor | B120: 0 | C120: 3 | D120: 0 | F120: 0.15 | H120: 3 shilling from plough-services sold this year.
... A159: Issues of the manor | B159: 19 | C159: 7 | D159: 7 | F159: 19.38 | H159: £19 7 shilling 7pence from 50 Yearlings bought and agisted in the park the previous year and afterwards solpence
A160: Issues of the manor | B160: 77 | C160: 8 | D160: 1 | F160: =B160+C160/20+D160/240 -> 77.404167 | H160: Total, £77 8 shilling 1pence
A161: Issues of the manor | F161: 77.4 | G161: =F161-F160 -> -0.0041666667 | H161: Total
A163: Sale of corn | B163: 22 | C163: 15 | D163: 8.5 | F163: 22.79 | H163: The same render account for £22 15 shilling 8.5pence from 73.5 quarters of wheat sold, at 5 shilling a qr for 7.5 quarters 1 bushels, 5 shilling 4pence a qr for 6.5 quarters, 6 shilling a qr for 19 quarters 3 bushels, and 6 shilling 8pence a qr for 40 quarters..
A164: Sale of corn | B164: 0 | C164: 17 | D164: 5.75 | F164: 0.87 | H164: 17 shilling 5.75pence from 8 quarters' bushels of curall sold, at 2 shilling a qr for 4 quarters, and 2 shilling 4pence a qr for 4 quarters .5 bushels.
A165: Sale of corn | B165: 1 | C165: 1 | D165: 3 | F165: 1.06 | H165: £1 1 shilling 3pence from 5 quarters 2.5 bushels of barley sold, at 4 shilling a qr.
A166: Sale of corn | B166: 6 | C166: 13 | D166: 10 | F166: 6.69 | H166: £6 13 shilling 10pence from 58.5 quarters 3 bus, of oats sold, at 2 shilling a qr for 31 quarters, 2 shilling 4pence a qr for 7.5 quarters, and 2 shilling 8pence a qr for 20 quarters 3 bushels.
A167: Sale of corn | B167: 0 | C167: 0 | D167: 8 | F167: 0.03 | H167: 8pence from 2 bushels of peas sold.
A168: Sale of corn | B168: 0 | C168: 4 | D168: 3 | F168: 0.21 | H168: 4 shilling 3pence from 2 quarters 1 bushels of vetches sold, at 2 shilling a qr.
A169: Sale of corn | B169: 31 | C169: 13 | D169: 2.25 | F169: 31.66 | H169: Total, £31 13 shilling 2.25pence
A170: Sale of corn | F170: =+F175+F184 -> 11.514167 | G170: -0.01 | H170: Total
A172: East mill | B172: 0 | C172: 7 | D172: 7 | F172: 0.38 | H172: The same render account for 7 shilling 7pence from 1 qr 3 bushels of wheat sold, at 5 shilling 4pence for 1 qr, and 9pence a bushels for 3 bushels.
A173: East mill | B173: 3 | C173: 3 | D173: 6 | F173: 3.17 | H173: £3 3 shilling 6pence from 18 quarters 1 bushels of maslin sold, at 3 shilling 4pence a qr for 7 quarters, and 4 shilling a qr for 8 quarters 1 bushels
A174: East mill | B174: 3 | C174: 11 | D174: 1 | F174: =B174+C174/20+D174/240 -> 3.5541667 | H174: Total, £3 11 shilling 1pence
A175: East mill | F175: 3.55 | G175: =F175-F174 -> -0.0041666667 | H175: Total
...

Sheet Expenses
A1: BISHOPS WALTHAM EXPENSES
A2: Heading | B2: £ | C2: s | D2: d | F2: Total in £ | G2: Error | H2: Notes | J2: Fixed investment | K2: Demesne fixed investment
A3: Cost of ploughs | B3: 0 | C3: 9 | D3: 10 | F3: =B3+C3/20+D3/240 -> 0.49166667 | H3: In iron and steel bought for 4 ploughs for the year and 1 plough for' year 9 shilling 10pence | J3: =F3 -> 0.49166667 | K3: =J3 -> 0.49166667
A4: Cost of ploughs | B4: 0 | C4: 0 | D4: 8 | F4: 0.03 | H4: 4 ploughs made anew 8pence. | J4: =F4 -> 0.03 | K4: =J4 -> 0.03
A5: Cost of ploughs | B5: 0 | C5: 1 | D5: 4 | F5: 0.07 | H5: 4 pairs of wheels bought for ploughs 1 shilling 4pence. | J5: =F5 -> 0.07 | K5: =J5 -> 0.07
A6: Cost of ploughs | B6: 0 | C6: 0 | D6: 5.5 | F6: 0.02 | H6: fitting ploughs with iron tyres 5.5pence. | J6: =F6 -> 0.02 | K6: =J6 -> 0.02
A7: Cost of ploughs | B7: 0 | C7: 3 | D7: 0 | F7: 0.15 | H7: 4 ploughshares bought 3 shilling. | J7: =F7 -> 0.15 | K7: =J7 -> 0.15
A8: Cost of ploughs | B8: 0 | C8: 2 | D8: 6 | F8: 0.12 | H8: 5 plough feet bought 2 shilling 6pence. | J8: =F8 -> 0.12 | K8: =J8 -> 0.12
A9: Cost of ploughs | B9: 0 | C9: 1 | D9: 4 | F9: 0.07 | H9: 1 coulter bought for ploughs 1 shilling 4pence. | J9: =F9 -> 0.07 | K9: =J9 -> 0.07
A10: Cost of ploughs | B10: 0 | C10: 0 | D10: 1.5 | F10: 0.01 | H10: 3 halters of hemp bought for the plough-horses 1.5pence. | J10: =F10 -> 0.01 | K10: =J10 -> 0.01
A11: Cost of ploughs | B11: 0 | C11: 0 | D11: 4 | F11: 0.02 | H11: mending old ploughs 4pence. | J11: =F11 -> 0.02 | K11: =J11 -> 0.02
A12: Cost of ploughs | B12: 0 | C12: 3 | D12: 0 | F12: 0.15 | H12: shoeing 4 plough-horses for the year 3 shilling, because in between times I when they were not ploughing they carried the dung. | J12: =F12 -> 0.15 | K12: =J12 -> 0.15
A13: Cost of ploughs | B13: 0 | C13: 4 | D13: 0 | F13: 0.2 | H13: boon-works of 48 ploughmen from within the hundred 4 shilling, and each ploughman will plough 2 acres as they lie.
A14: Cost of ploughs | B14: 0 | C14: 0 | D14: 0 | F14: 0 | H14: Moreover, within the hundred they are bound to plough 52 acres as they lie for landrighe without the cost of the lorpence.
A15: Cost of ploughs | B15: 0 | C15: 1 | D15: 11 | F15: 0.1 | H15: winter boon-works of 23 ploughmen from Droxford this year 1 shilling 11pence, or 1pence a ploughman, and each ploughman will plough 2 acres as they lie.
A16: Cost of ploughs | B16: 0 | C16: 4 | D16: 1 | F16: 0.2 | H16: Lenten boon-works of 48 ploughmen from within the hundred 4 shilling, or 1pence a ploughman, and each ploughman will plough acre as it lies.
A17: Cost of ploughs | B17: 0 | C17: 13 | D17: 10 | F17: 0.69 | H17: stipend of 4 ploughmen for 8 Saturday ploughings at the time of the winter sowing, 11 Saturdays at the summer sowing, and 10 Saturdays at the fallowing, with the stipend of 1 ploughman for 8 Saturday ploughings at the sowing of the barley, 13 shilling 10pence, or 1.5pence each when ploughing for sowing, and 1pence when fallowing.
A18: Cost of ploughs | B18: 0 | C18: 13 | D18: 6 | F18: 0.68 | H18: stipend of 4 drovers for the year and 1 drover for' year 13 shilling 6pence, or 3 shilling each.
A19: Cost of ploughs | B19: 0 | C19: 9 | D19: 6 | F19: 0.48 | H19: 1 plough-horse bought 9 shilling 6pence.
A20: Cost of ploughs | B20: 5 | C20: 0 | D20: 8 | F20: 5.03 | H20: 9 oxen bought £5 8pence, at 9 shilling 6pence for 1,10 shilling 1pence each for 2, 11 shilling 6pence each for 2, and 12 shilling each for 4..
A21: Cost of ploughs | B21: 0 | C21: 1 | D21: 4 | F21: 0.07 | H21: 4 bushels of peas bought for sowing 1 shilling 4pence.
A22: Cost of ploughs | B22: 0 | C22: 5 | D22: 5 | F22: 0.27 | H22: 3 quarters 2 bushels of vetches bought 5 shilling 5pence, at 1 shilling 8pence a qr.
A23: Cost of ploughs | B23: 1 | C23: 4 | D23: 0 | F23: 1.2 | H23: forage bought to support the lord's stock £1 4 shilling
A24: Cost of ploughs | B24: 10 | C24: 1 | D24: 5 | F24: =B24+C24/20+D24/240 -> 10.070833 | H24: Total, £10 1 shilling 5pence
A25: Cost of ploughs | F25: =SUM(F3:F23) -> 10.051667 | G25: =F25-F24 -> -0.019166667 | H25: Total
A27: Cost of carts | B27: 0 | C27: 14 | D27: 0 | F27: 0.7 | H27: In 1 new cart with iron tyres with all equipment bought 14 shilling. | J27: =F27 -> 0.7 | K27: =J27 -> 0.7
A28: Cost of carts | B28: 0 | C28: 0 | D28: 0.5 | F28: =B28+C28/20+D28/240 -> 0.0020833333 | H28: mending the old cart 1 .5pence. | J28: =F28 -> 0.0020833333 | K28: =J28 -> 0.0020833333
A29: Cost of carts | B29: 0 | C29: 1 | D29: 10 | F29: 0.09 | H29: clouts, nails and grease bought 1 shilling 10pence. | J29: =F29 -> 0.09 | K29: =J29 -> 0.09
A30: Cost of carts | B30: 0 | C30: 0 | D30: 6.25 | F30: 0.03 | H30: fitting the carts with axles at various times with axles bought for the same 6.25pence. | J30: =F30 -> 0.03 | K30: =J30 -> 0.03
A31: Cost of carts | B31: 0 | C31: 0 | D31: 3 | F31: 0.01 | H31: 1 cart-rail made anew for the cart 3pence. | J31: =F31 -> 0.01 | K31: =J31 -> 0.01
A32: Cost of carts | B32: 0 | C32: 0 | D32: 5.5 | F32: 0.02 | H32: 1 pair of traces bought 5.5pence. | J32: =F32 -> 0.02 | K32: =J32 -> 0.02
A33: Cost of carts | B33: 0 | C33: 2 | D33: 4 | F33: 0.12 | H33: 3 collars and 1 pair of saddle-pads bought 2 shilling 4pence. | J33: =F33 -> 0.12 | K33: =J33 -> 0.12
A34: Cost of carts | B34: 0 | C34: 0 | D34: 11 | F34: 0.05 | H34: a hemp rope bought 11pence. | J34: =F34 -> 0.05 | K34: =J34 -> 0.05
A35: Cost of carts | B35: 0 | C35: 0 | D35: 4 | F35: 0.02 | H35: white leather bought 4pence. | J35: =F35 -> 0.02 | K35: =J35 -> 0.02
A36: Cost of carts | B36: 0 | C36: 0 | D36: 2 | F36: 0.01 | H36: 2 pairs of swingletrees 2pence. | J36: =F36 -> 0.01 | K36: =J36 -> 0.01
A37: Cost of carts | B37: 0 | C37: 0 | D37: 2.5 | F37: 0.01 | H37: 1 saddle for the same 2.5pence. | J37: =F37 -> 0.01 | K37: =J37 -> 0.01
A38: Cost of carts | B38: 0 | C38: 0 | D38: 1.25 | F38: 0.01 | H38: 1 thill-rope (tilropt') bought 1.25pence. | J38: =F38 -> 0.01 | K38: =J38 -> 0.01
A39: Cost of carts | B39: 0 | C39: 0 | D39: 2 | F39: 0.01 | H39: hooping wooden frets to the hubs of the old cart 2pence. | J39: =F39 -> 0.01 | K39: =J39 -> 0.01
A40: Cost of carts | B40: 0 | C40: 3 | D40: 0 | F40: 0.15 | H40: forage for 2 cart-horses for the year 3 shilling.
A41: Cost of carts | B41: 0 | C41: 3 | D41: 0 | F41: 0.15 | H41: stipend of 1 carter for the year 3 shilling.
A42: Cost of carts | B42: 0 | C42: 1 | D42: 6 | F42: 0.08 | H42: stipend of 1 carter leading the other cart to the dung for 0.5 year 1 shilling 6pence, because for the other 0.5 year he held the horse-plough.
A43: Cost of carts | B43: 1 | C43: 9 | D43: 0 | F43: 1.45 | H43: Total, £1 9 shilling
A44: Cost of carts | F44: =SUM(F27:F42) -> 1.4620833 | G44: =F44-F43 -> 0.012083333 | H44: Total
A46: Cost of the dairy | B46: 0 | C46: 0 | D46: 8.5 | F46: 0.04 | H46: In woollen and linen cloth bought for the dairy 8.5pence. | J46: =F46 -> 0.04 | K46: =J46 -> 0.04
A47: Cost of the dairy | B47: 0 | C47: 0 | D47: 6 | F47: 0.03 | H47: a press bought for the same 6pence. | J47: =F47 -> 0.03 | K47: =J47 -> 0.03
A48: Cost of the dairy | B48: 0 | C48: 0 | D48: 10.5 | F48: 0.04 | H48: 7 bushels of salt bought 10.5pence. | J48: =F48 -> 0.04 | K48: =J48 -> 0.04
A49: Cost of the dairy | B49: 0 | C49: 0 | D49: 9 | F49: 0.04 | H49: 2 buckets and 1 tub bought anew for the same 9pence. | J49: =F49 -> 0.04 | K49: =J49 -> 0.04
A50: Cost of the dairy | B50: 0 | C50: 0 | D50: 4 | F50: 0.02 | H50: earthenware pots and pans 4pence. | J50: =F50 -> 0.02 | K50: =J50 -> 0.02
A51: Cost of the dairy | B51: 0 | C51: 11 | D51: 4 | F51: 0.57 | H51: grease bought for greasing sheep 11 shilling 4pence. | J51: =F51 -> 0.57 | K51: =J51 -> 0.57
A52: Cost of the dairy | B52: 0 | C52: 2 | D52: 11 | F52: 0.15 | H52: 10 ells of canvas bought for packing wool 2 shilling 11pence, at 3.5pence an ell. | J52: =F52 -> 0.15 | K52: =J52 -> 0.15
A53: Cost of the dairy | B53: 0 | C53: 0 | D53: 3 | F53: 0.01 | H53: castrating 9 piglets 3pence. | K53: =J53 -> 0
A54: Cost of the dairy | B54: 0 | C54: 2 | D54: 6 | F54: 0.12 | H54: wattling anew the sheepcote at Langeheg' 2 shilling 6pence. | J54: =F54 -> 0.12 | K54: =J54 -> 0.12
A55: Cost of the dairy | B55: 0 | C55: 3 | D55: 0 | F55: 0.15 | H55: re-roofing in places the said sheepcote which had been unroofed 3 shilling. | J55: =F55 -> 0.15 | K55: =J55 -> 0.15
A56: Cost of the dairy | B56: 0 | C56: 0 | D56: 6 | F56: 0.03 | H56: roofing in places the sheepcote at Legsted' 6pence. | J56: =F56 -> 0.03 | K56: =J56 -> 0.03
A57: Cost of the dairy | B57: 3 | C57: 13 | D57: 6 | F57: 3.67 | H57: 8 cows bought after calving £3 13 shilling 6pence, at 8 shilling 10pence each for 3, 9 shilling 4pence each for 3, and 9 shilling 6pence each for 2. | K57: =J57 -> 0
A58: Cost of the dairy | B58: 0 | C58: 0 | D58: 8 | F58: 0.03 | H58: a tripod bought 8pence. | J58: =F58 -> 0.03 | K58: =J58 -> 0.03
A59: Cost of the dairy | B59: 0 | C59: 3 | D59: 0 | F59: 0.15 | H59: stipend of 1 cowherd for the year 3 shilling.
A60: Cost of the dairy | B60: 0 | C60: 2 | D60: 0 | F60: =B60+C60/20+D60/240 -> 0.1 | H60: stipend of 1 dairymaid for the year 2 shilling
A61: Cost of the dairy | B61: 5 | C61: 2 | D61: 10 | F61: 5.14 | H61: Total, £5 2 shilling 10pence
A62: Cost of the dairy | F62: =SUM(F46:F60) -> 5.15 | G62: =F62-F61 -> 0.01 | H62: Total
A64: Cost of buildings at Berth' | B64: 0 | C64: 4 | D64: 10 | F64: 0.24 | H64: In re-roofing the barn in places 4 shilling 10pence. | J64: =F64 -> 0.24 | K64: =J64 -> 0.24
A65: Cost of buildings at Berth' | B65: 0 | C65: 0 | D65: 3 | F65: 0.01 | H65: mending the gate of the same 3pence. | J65: =F65 -> 0.01 | K65: =J65 -> 0.01
A66: Cost of buildings at Berth' | B66: 0 | C66: 0 | D66: 3.5 | F66: =B66+C66/20+D66/240 -> 0.014583333 | H66: fencing for the enclosure 3.5pence | J66: =F66 -> 0.014583333 | K66: =J66 -> 0.014583333
A67: Cost of buildings at Berth' | B67: 0 | C67: 5 | D67: 4.5 | F67: =B67+C67/20+D67/240 -> 0.26875 | H67: Total, 5 shilling 4.5pence
A68: Cost of buildings at Berth' | F68: =SUM(F64:F66) -> 0.26458333 | G68: =F68-F67 -> -0.0041666667 | H68: Total
A70: Cost of buildings in the curia | B70: 0 | C70: 14 | D70: 8 | F70: 0.73 | H70: In rebuilding anew the great barn which had partly collapsed through rotten timber with a carpenter to do this and laths made for the same 14 shilling 8pence. | J70: =F70 -> 0.73 | K70: =J70 -> 0.73
A71: Cost of buildings in the curia | B71: 0 | C71: 0 | D71: 3 | F71: 0.01 | H71: large nails to fasten the rafters of the barn 3pence. | J71: =F71 -> 0.01 | K71: =J71 -> 0.01
A72: Cost of buildings in the curia | B72: 0 | C72: 6 | D72: 8 | F72: 0.33 | H72: 10,000 nails bought for laths 6 shilling 8pence. | J72: =F72 -> 0.33 | K72: =J72 -> 0.33
A73: Cost of buildings in the curia | B73: 1 | C73: 0 | D73: 0 | F73: 1 | H73: 15,000 large slates bought for the said barn £1, at 1 shilling 4pence a 1,000.. | J73: =F73 -> 1 | K73: =J73 -> 1
A74: Cost of buildings in the curia | B74: 0 | C74: 1 | D74: 3 | F74: 0.06 | H74: pegs bought for the same 1 shilling 3pence. | J74: =F74 -> 0.06 | K74: =J74 -> 0.06
A75: Cost of buildings in the curia | B75: 0 | C75: 18 | D75: 1 | F75: 0.9 | H75: re-roofing the said part of the barn anew and roofing the whole of the barn in places 18 shilling 1pence. | J75: =F75 -> 0.9 | K75: =J75 -> 0.9
A76: Cost of buildings in the curia | B76: 0 | C76: 6 | D76: 6 | F76: 0.33 | H76: 13 quarters of lime bought for the same 6 shilling 6pence. | J76: =F76 -> 0.33 | K76: =J76 -> 0.33
A77: Cost of buildings in the curia | B77: 0 | C77: 0 | D77: 4 | F77: 0.02 | H77: sand bought 4pence. | J77: =F77 -> 0.02 | K77: =J77 -> 0.02
A78: Cost of buildings in the curia | B78: 0 | C78: 1 | D78: 11 | F78: 0.1 | H78: re-roofing the granary in places and the gate inside and re-roofing the great stable in places 1 shilling 11pence. | J78: =F78 -> 0.1 | K78: =J78 -> 0.1
A79: Cost of buildings in the curia | B79: 0 | C79: 4 | D79: 0 | F79: 0.2 | H79: 3,000 large slates bought for the same 4 shilling. | J79: =F79 -> 0.2 | K79: =J79 -> 0.2
A80: Cost of buildings in the curia | B80: 0 | C80: 1 | D80: 0 | F80: 0.05 | H80: 2 quarters of lime bought for the same 1 shilling. | J80: =F80 -> 0.05 | K80: =J80 -> 0.05
A81: Cost of buildings in the curia | B81: 0 | C81: 0 | D81: 3.5 | F81: 0.01 | H81: nails bought for laths 3.5pence. | J81: =F81 -> 0.01 | K81: =J81 -> 0.01
... A84: Cost of buildings in the curia | B84: 0 | C84: 2 | D84: 0 | F84: 0.1 | H84: mending the palisade around the curia in parts 2 shilling. | J84: =F84 -> 0.1 | K84: =J84 -> 0.1
A85: Cost of buildings in the curia | B85: 0 | C85: 6 | D85: 9 | F85: 0.34 | H85: 54 quarters' of charcoal made and sent to Wolvesey 6 shilling 9pence, at 1.5pence a qr.
A86: Cost of buildings in the curia | B86: 4 | C86: 7 | D86: 1 | F86: 4.35 | H86: Total, £4 7 shilling 1pence
A87: Cost of buildings in the curia | F87: 4.35 | G87: 0 | H87: Total
A89: Cost of the park | B89: 1 | C89: 8 | D89: 10 | F89: 1.44 | H89: In making the palisade of the park anew in places and mending it elsewhere £1 8 shilling 10pence | J89: =F89 -> 1.44 | L89: not agricultural?
A90: Cost of the park | F90: 1.44 | H90: Total, £1 8 shilling 10pence
A91: Cost of the park | F91: 1.44 | G91: 0 | H91: Total
A93: Threshing | B93: 0 | C93: 0 | D93: 0 | F93: 0 | H93: Nothing for the threshing of peas and vetches because they were threshed by labour service.
A94: Threshing | B94: 0 | C94: 1 | D94: 1 | F94: 0.05 | H94: 2 sacks bought 1 shilling 1pence.
A95: Threshing | B95: 0 | C95: 0 | D95: 3 | F95: =B95+C95/20+D95/240 -> 0.0125 | H95: 1 basket for corn bought 3pence
A96: Threshing | B96: 0 | C96: 1 | D96: 4 | F96: =B96+C96/20+D96/240 -> 0.066666667 | H96: Total, 1 shilling 4pence
A97: Threshing | F97: =SUM(F93:F95) -> 0.0625 | G97: =F97-F96 -> -0.0041666667 | H97: Total
A99: Hay harvest (Autumpn') | B99: 0 | C99: 1 | D99: 0 | F99: 0.05 | H99: in mowing the meadow of Bitterne according to custom 1 shilling.
A100: Hay harvest (Autumpn') | B100: 0 | C100: 1 | D100: 6 | F100: 0.08 | H100: tossing the hay of the same 1 shilling 6pence.
A101: Hay harvest (Autumpn') | B101: 0 | C101: 2 | D101: 6 | F101: 0.12 | H101: mowing the new meadow 2 shilling 6pence.
A102: Hay harvest (Autumpn') | B102: 0 | C102: 0 | D102: 4 | F102: 0.02 | H102: tossing the hay 4pence.
A103: Hay harvest (Autumpn') | B103: 0 | C103: 1 | D103: 6 | F103: 0.08 | H103: mowing Ballesmed 1 shilling 6pence.
A104: Hay harvest (Autumpn') | B104: 0 | C104: 0 | D104: 2 | F104: 0.01 | H104: tossing the hay 2pence.
A105: Hay harvest (Autumpn') | B105: 0 | C105: 1 | D105: 0 | F105: 0.05 | H105: mowing the meadow of la Mere 1 shilling
A106: Hay harvest (Autumpn') | B106: 0 | C106: 8 | D106: 0 | F106: =B106+C106/20+D106/240 -> 0.4 | H106: Total, 8 shilling
A107: Hay harvest (Autumpn') | F107: 0.41 | G107: =F107-F106 -> 0.01 | H107: Total
A109: Corn harvest (Autumpn') | B109: 0 | C109: 14 | D109: 5.5 | F109: 0.72 | H109: In bread bought for 347 men at two harvest boon-works 14 shilling 5.5pence, and each has bread worth .5pence.
A110: Corn harvest (Autumpn') | B110: 0 | C110: 6 | D110: 1 | F110: 0.3 | H110: 1,041 herrings bought for the same 6 shilling 1pence, at 8pence a hundred, and each has 3 herrings.
...

Sheet Issues of the Grange
A1: Gross Output | B1: Total Quantity | C1: Account Total Quarters | D1: Bought in Total Quarters | E1: Received from churchscot | F1: Sold Total Quarters | G1: Difference Produced+Bought-Sold | H1: Weighted Average Price per Quarter | I1: Value of Total Production weighted
A2: wheat | B2: 132.25 | D2: 0 | F2: 73.5 | G2: =B2-F2 -> 58.75 | H2: 0.31000567 | I2: =H2*B2 -> 40.99825
A3: curall | B3: 10 | D3: 0 | F3: 8 | G3: =B3-F3 -> 2 | H3: 0.1089372 | I3: =H3*B3 -> 1.089372
A4: barley | B4: 83.375 | D4: 0 | F4: 5.3125 | G4: =B4-F4 -> 78.0625 | H4: 0.2 | I4: =H4*B4 -> 16.675
A5: oats | B5: 205.0625 | D5: 0 | F5: 58.875 | G5: =B5-F5 -> 146.1875 | H5: 0.11365888 | I5: =H5*B5 -> 23.307174
A6: peas | B6: 3.8125 | D6: 0.5 | F6: 0.25 | G6: =B6-F6 -> 3.5625 | H6: 0.13333333 | I6: =H6*B6 -> 0.50833333
A7: vetches | B7: 11.375 | D7: 3.25 | F7: 2.125 | G7: =B7-F7 -> 9.25 | H7: 0.1 | I7: =H7*B7 -> 1.1375
A10: Net output | B10: Gross output | C10: Seed quarters | D10: Seed bushels | E10: Seed total quarters | F10: tithe quarters | G10: tithe bushels | H10: tithe total | I10: manorial servants quarters | J10: manorial servants bushels | K10: manorial servants total quarters | L10: output net of tithe, seed, liveries | M10: in stock from last year | N10: Price in £ | O10: Value of net output in £ | P10: Value of sales (in "Sale of Corn") in £
A11: wheat | B11: =B2 -> 132.25 | C11: 47 | D11: 1 | E11: =C11+D11/8 -> 47.125 | I11: =1+4.5+4+2 -> 11.5 | J11: 1 | K11: =I11+J11/8 -> 11.625 | L11: =B11-E11-K11 -> 73.5 | N11: =H2 -> 0.31000567 | O11: =N11*L11 -> 22.785417
A12: curall | B12: =B3 -> 10 | E12: =C12+D12/8 -> 0 | I12: 1 | J12: 3 | K12: =I12+J12/8 -> 1.375 | L12: =B12-E12-K12 -> 8.625 | N12: =H3 -> 0.1089372 | O12: =N12*L12 -> 0.93958333
A13: barley | B13: =B4 -> 83.375 | C13: 20 | E13: =C13+D13/8 -> 20 | I13: =26+6.5+6.5+4+5+4+1+2+2 -> 57 | J13: =2.5+1.5+1 -> 5 | K13: =I13+J13/8 -> 57.625 | L13: =B13-E13-K13 -> 5.75 | N13: =H4 -> 0.2 | O13: =N13*L13 -> 1.15
A14: oats | B14: =B5 -> 205.0625 | C14: 88.5 | D14: 0.5 | E14: =C14+D14/8 -> 88.5625 | I14: =15.5+5.5+2+4+5+25 -> 57 | J14: =2+2.5 -> 4.5 | K14: =I14+J14/8 -> 57.5625 | L14: =B14-E14-K14 -> 58.9375 | N14: =H5 -> 0.11365888 | O14: =N14*L14 -> 6.6987703
A15: peas | B15: =B6 -> 3.8125 | C15: 2 | D15: 3.5 | E15: =C15+D15/8 -> 2.4375 | I15: 1 | J15: 1 | K15: =I15+J15/8 -> 1.125 | L15: =B15-E15-K15 -> 0.25 | N15: =H6 -> 0.13333333 | O15: =N15*L15 -> 0.033333333
A16: vetches | B16: =B7 -> 11.375 | C16: 5.5 | E16: =C16+D16/8 -> 5.5 | I16: =2+1.5 -> 3.5 | J16: 1 | K16: =I16+J16/8 -> 3.625 | L16: =B16-E16-K16 -> 2.25 | N16: =H7 -> 0.1 | O16: =N16*L16 -> 0.225

Sheet Issues of the Mills

Sheet Stock
A1: BISHOPS WALTHAM STOCK ACCOUNT
C3: added | G3: subtracted
A4: Livestock | B4: Inherited stock | C4: added | D4: strays | E4: herbage | F4: churchscot | G4: of which in default | H4: sold | I4: in murrain | J4: accounted for elsewhere | K4: End-period stock | L4: cross-check | M4: stock building | N4: raw production | O4: Unit price (£) | P4: Value of stock (£) at given value | Q4: Value of stock (£) at sales prices | R4: Sales in (£) | S4: Value of stock building (£) | T4: Value of production (£) at sales prices | U4: Details
A5: Cart-horses | B5: 2 | K5: 2
A6: Mares
A7: Plough horses | B7: 3 | C7: =1+1+1 -> 3 | H7: 2 | K7: 4 | O7: =R7/H7 -> 0.285 | R7: =Receipts!F73+Receipts!F74 -> 0.57
A8: Colts (unspecified years)
A9: Colts (2 years)
A10: Colts (1 year)
A11: Foals
A12: Oxen | B12: 48 | C12: =3+1+1+9 -> 14 | H12: 6 | I12: 2 | K12: 54 | O12: =R12/H12 -> 0.46666667 | R12: =Receipts!F75 -> 2.8
A13: Bulls | B13: 1 | K13: 1
A14: Cows | B14: 27 | C14: =8+8 -> 16 | H14: 6 | I14: 1 | K14: 40 | O14: =R14/H14 -> 0.3 | R14: =Receipts!F76 -> 1.8
A15: Steers | B15: 12 | C15: 1 | I15: 2 | J15: =3+8 -> 11 | K15: 0
A16: Bullocks | B16: 11 | I16: 3 | K16: 8
A17: Yearlings | B17: 11 | I17: 4 | K17: 7
A18: Calves | B18: 19 | C18: =8 -> 8 | H18: 6 | I18: 1 | J18: =2 -> 2 | K18: 11 | O18: =R18/H18 -> 0.05 | R18: =Receipts!F77 -> 0.3
A19: Wethers | B19: 249 | H19: 7 | I19: =18+11 -> 29 | K19: 271 | O19: =R19/H19 -> 0.05 | R19: =Receipts!F78 -> 0.35
A20: Rams | B20: 2 | C20: 6 | K20: 8
A21: Ewes | B21: 226 | C21: 50 | H21: 7 | I21: =30+1+2 -> 33 | K21: 236 | O21: =R21/H21 -> 0.041428571 | R21: =Receipts!F79 -> 0.29
A22: Hoggs | B22: 145 | H22: 26 | I22: 5 | J22: =58+6+50 -> 114 | K22: 0 | O22: =R22/H22 -> 0.026153846 | R22: =Receipts!F80 -> 0.68
A23: Lambs | C23: 172 | H23: 12 | I23: =16+3 -> 19 | J23: =16+3 -> 19 | K23: 122 | O23: =R23/H23 -> 0.018333333 | R23: =Receipts!F81 -> 0.22
A24: Boars | B24: 1 | C24: 1 | H24: 1 | K24: 1 | O24: =R24/H24 -> 0.05 | R24: =Receipts!F82 -> 0.05
A25: Sows | B25: 2 | K25: 2
A26: Pigs | B26: 12 | C26: =30+1 -> 31 | H26: 5 | I26: =3+2 -> 5 | K26: 33 | O26: =R26/H26 -> 0.124 | R26: =Receipts!F83 -> 0.62
A27: Hoggets | B27: 37 | I27: 6 | J27: =1+30 -> 31 | K27: 0
A28: Piglets | C28: 17 | I28: 3 | J28: 1 | K28: 13
A29: Swans | B29: 13 | C29: 3 | K29: 16
A30: Peacocks | B30: 6 | C30: 1 | I30: 5 | K30: 5 | U30: accounting doesnt add up
A31: Total Value | R31: =SUM(R5:R29) -> 7.68
A34: Wool
A35: Coarse wool | C35: 528 | J35: =53+375 -> 428 | O35: 0.02 | T35: =O35*J35 -> 8.56
A36: Lamb's wool | C36: 122 | J36: 122 | O36: 0.01 | T36: =O36*J36 -> 1.22
A37: Wool locks | C37: 6 | H37: 6 | O37: =10.5/240 -> 0.04375 | T37: =O37*H37 -> 0.2625 | U37: measured in cloves
A38: Wool sold at shearing
A39: Total wool | T39: =SUM(T35:T38) -> 10.0425
A42: Hides
A43: Ox hides
A44: Mare
A45: Steer
A46: calves
A47: pigs
A48: Woolskins (incl. 10 in tithe)
A49: wethers
A50: rams
A51: ewes
A52: hoggs
A53: Woolskins (excl. 10 in tithe)
... A75: Eggs
A76: Cocks & hens from churchscot of customary tenants | F76: 172 | G76: 18 | H76: 154 | O76: =R76/H76 -> 0.0097402597 | R76: =Receipts!F108 -> 1.5 | T76: =O76*H76 -> 1.5
A77: Sum of above
A78: Total | R78: =SUM(R75:R77) -> 1.5 | T78: =T76 -> 1.5
A81: Meat
A82: Beef
A83: Mutton
A84: Pork
A85: Total
A87: Cheese
A88: Winter cheese | C88: 41 | J88: 41 | O88: =R88/J88 -> 0.0051219512 | R88: =Receipts!F102 -> 0.21 | T88: =O88*C88 -> 0.21 | U88: not recorded as sold in stock but recorded as sold in issues
A89: Summer cheese | C89: 162 | H89: 141 | J89: =16+3 -> 19 | O89: =R89/H89 -> 0.033191489 | R89: =Receipts!F103 -> 4.68 | T89: =O89*C89 -> 5.3770213
A90: Total | R90: =SUM(R88:R89) -> 4.89 | T90: =SUM(T88:T89) -> 5.5870213
A92: Butter
A93: Butter | C93: 22 | H93: 22 | O93: =R93/H93 -> 0.015454545 | R93: =Receipts!F104 -> 0.34 | T93: =O93*H93 -> 0.34 | U93: measured in cloves
A94: Total | R94: =SUM(R93) -> 0.34 | T94: =T93 -> 0.34
A96: Total Dairy Sales
A99: Cider | B99: 60 | C99: 2 | J99: 60 | K99: 2 | U99: measured in casks
A102: Additional Information (not necessarily useful)
A103: Utensils
A104: ploughs
A105: carts
A106: cart-ropes
A107: corn baskets
A108: seed-sacks
A109: seed basket
A110: locks for the doors
A111: lead vessel
A112: brass pots
A113: pans
... A128: brass posnets

Sheet Issues of the Grange raw
A1: Heading | B1: Sentence | C1: Quarters 1_x | D1: Bushels 1_x | E1: Sown Quarters | F1: Sown Bushels | G1: Sown Total Quarters | H1: Bought in Quarters | I1: Bought in Bushels | J1: Bought in Total Quarters | K1: Tithe Quarters | L1: Tithe Bushels | M1: Tithe Total Quarters | N1: Manorial servants & livestock Quarters | O1: Manorial servants & livestock Bushels | P1: Manorial servants & livestock Total Quarters | Q1: Sold Quarters | R1: Sold Bushels | S1: Sold Total Quarters | T1: Account Quarters | U1: Account Bushels | V1: Account Total Quarters | W1: bought only | X1: Total Quarters Except 1 | Y1: Total Bushels Except 1 | Z1: Total Corn Cross-Check | AA1: Total Corn Manorial Account | AB1: Corn Quantity Error | AC1: Quarters 1_y | AD1: Bushels 1_y | AE1: Quarters 2 | AF1: Bushels 2 | AG1: Quarters 3 | AH1: Bushels 3 | AI1: Quarters 4 | AJ1: Bushels 4 | AK1: Quarters 5 | AL1: Bushels 5
A2: And thus he owes clear | B2: Total | C2: 0 | D2: 0 | E2: 0 | F2: 0 | G2: 0 | H2: 0 | I2: 0 | J2: 0 | K2: 0 | L2: 0 | M2: 0 | N2: 0 | O2: 0 | P2: 0 | Q2: 0 | R2: 0 | S2: 0 | T2: 0 | U2: 0 | V2: 0 | W2: 0
A3: Wheat | B3: {yield: three-fold plus 5 quarters 1.5 bushels} | C3: 0 | D3: 0 | E3: 0 | F3: 0 | G3: 0 | H3: 0 | I3: 0 | J3: 0 | K3: 0 | L3: 0 | M3: 0 | N3: 0 | O3: 0 | P3: 0 | Q3: 0 | R3: 0 | S3: 0 | T3: 0 | U3: 0 | V3: 0 | W3: 0 | X3: 5 | Y3: 1.5 | Z3: 5.1875 | AA3: 5.1875 | AB3: 0 | AC3: 5 | AD3: 1.5
A4: Wheat | B4: The same render account for 131.5 quarters from the whole issue of wheat by struck measure. | C4: 0 | D4: 0 | E4: 0 | F4: 0 | G4: 0 | H4: 0 | I4: 0 | J4: 0 | K4: 0 | L4: 0 | M4: 0 | N4: 0 | O4: 0 | P4: 0 | Q4: 0 | R4: 0 | S4: 0 | T4: 131.5 | U4: 0 | V4: 131.5 | W4: 0 | X4: 131.5 | Y4: 0 | Z4: 131.5 | AA4: 131.5 | AB4: 0 | AC4: 131.5 | AD4: 0
A5: Wheat | B5: 6 bushels from churchscot. | C5: 0 | D5: 0 | E5: 0 | F5: 0 | G5: 0 | H5: 0 | I5: 0 | J5: 0 | K5: 0 | L5: 0 | M5: 0 | N5: 0 | O5: 0 | P5: 0 | Q5: 0 | R5: 0 | S5: 0 | T5: 0 | U5: 0 | V5: 0 | W5: 0 | X5: 0 | Y5: 6 | Z5: 0.75 | AA5: 0.75 | AB5: 0 | AC5: 0 | AD5: 6
A6: Wheat | B6: Total, 1.32 quarters 2 bushels | C6: 0 | D6: 0 | E6: 0 | F6: 0 | G6: 0 | H6: 0 | I6: 0 | J6: 0 | K6: 0 | L6: 0 | M6: 0 | N6: 0 | O6: 0 | P6: 0 | Q6: 0 | R6: 0 | S6: 0 | T6: 0 | U6: 0 | V6: 0 | W6: 0 | X6: 1.32 | Y6: 2 | Z6: 1.57 | AA6: 1.57 | AB6: 0 | AC6: 1.32 | AD6: 2
A7: Wheat | B7: Sown over 453 acres as they lie in Rouerigg', la Mere and la Woth', 47 quarters 1 bushels. | C7: 0 | D7: 0 | E7: 47 | F7: 1 | G7: 47.125 | H7: 0 | I7: 0 | J7: 0 | K7: 0 | L7: 0 | M7: 0 | N7: 0 | O7: 0 | P7: 0 | Q7: 0 | R7: 0 | S7: 0 | T7: 0 | U7: 0 | V7: 0 | W7: 0 | X7: 47 | Y7: 1 | Z7: 47.125 | AA7: 47.125 | AB7: 0 | AC7: 47 | AD7: 1
A8: Wheat | B8: that is, 5 bushels over 6 acres, less'' bushels in all. | C8: 0 | D8: 0 | E8: 0 | F8: 0 | G8: 0 | H8: 0 | I8: 0 | J8: 0 | K8: 0 | L8: 0 | M8: 0 | N8: 0 | O8: 0 | P8: 0 | Q8: 0 | R8: 0 | S8: 0 | T8: 0 | U8: 0 | V8: 0 | W8: 0 | X8: 0 | Y8: 5 | Z8: 0.625 | AA8: 0.625 | AB8: 0 | AC8: 0 | AD8: 5
A9: Wheat | B9: . | C9: 0 | D9: 0 | E9: 0 | F9: 0 | G9: 0 | H9: 0 | I9: 0 | J9: 0 | K9: 0 | L9: 0 | M9: 0 | N9: 0 | O9: 0 | P9: 0 | Q9: 0 | R9: 0 | S9: 0 | T9: 0 | U9: 0 | V9: 0 | W9: 0 | X9: 0 | Y9: 0 | Z9: 0 | AA9: 0 | AB9: 0 | AC9: 0 | AD9: 0
A10: Wheat | B10: . | C10: 0 | D10: 0 | E10: 0 | F10: 0 | G10: 0 | H10: 0 | I10: 0 | J10: 0 | K10: 0 | L10: 0 | M10: 0 | N10: 0 | O10: 0 | P10: 0 | Q10: 0 | R10: 0 | S10: 0 | T10: 0 | U10: 0 | V10: 0 | W10: 0 | X10: 0 | Y10: 0 | Z10: 0 | AA10: 0 | AB10: 0 | AC10: 0 | AD10: 0
A11: Wheat | B11: . | C11: 0 | D11: 0 | E11: 0 | F11: 0 | G11: 0 | H11: 0 | I11: 0 | J11: 0 | K11: 0 | L11: 0 | M11: 0 | N11: 0 | O11: 0 | P11: 0 | Q11: 0 | R11: 0 | S11: 0 | T11: 0 | U11: 0 | V11: 0 | W11: 0 | X11: 0 | Y11: 0 | Z11: 0 | AA11: 0 | AB11: 0 | AC11: 0 | AD11: 0
A12: Wheat | B12: provision of the steward for his visits by 2 tallies, 1 qr. | C12: 0 | D12: 0 | E12: 0 | F12: 0 | G12: 0 | H12: 0 | I12: 0 | J12: 0 | K12: 0 | L12: 0 | M12: 0 | N12: 0 | O12: 0 | P12: 0 | Q12: 0 | R12: 0 | S12: 0 | T12: 0 | U12: 0 | V12: 0 | W12: 0
A13: Wheat | B13: . | C13: 0 | D13: 0 | E13: 0 | F13: 0 | G13: 0 | H13: 0 | I13: 0 | J13: 0 | K13: 0 | L13: 0 | M13: 0 | N13: 0 | O13: 0 | P13: 0 | Q13: 0 | R13: 0 | S13: 0 | T13: 0 | U13: 0 | V13: 0 | W13: 0 | X13: 0 | Y13: 0 | Z13: 0 | AA13: 0 | AB13: 0 | AC13: 0 | AD13: 0
A14: Wheat | B14: . | C14: 0 | D14: 0 | E14: 0 | F14: 0 | G14: 0 | H14: 0 | I14: 0 | J14: 0 | K14: 0 | L14: 0 | M14: 0 | N14: 0 | O14: 0 | P14: 0 | Q14: 0 | R14: 0 | S14: 0 | T14: 0 | U14: 0 | V14: 0 | W14: 0 | X14: 0 | Y14: 0 | Z14: 0 | AA14: 0 | AB14: 0 | AC14: 0 | AD14: 0
A15: Wheat | B15: . | C15: 0 | D15: 0 | E15: 0 | F15: 0 | G15: 0 | H15: 0 | I15: 0 | J15: 0 | K15: 0 | L15: 0 | M15: 0 | N15: 0 | O15: 0 | P15: 0 | Q15: 0 | R15: 0 | S15: 0 | T15: 0 | U15: 0 | V15: 0 | W15: 0 | X15: 0 | Y15: 0 | Z15: 0 | AA15: 0 | AB15: 0 | AC15: 0 | AD15: 0
A16: Wheat | B16: provision of Roger, bailiff from Michaelmas until Christmas, 4.5 quarters. | C16: 0 | D16: 0 | E16: 0 | F16: 0 | G16: 0 | H16: 0 | I16: 0 | J16: 0 | K16: 0 | L16: 0 | M16: 0 | N16: 0 | O16: 0 | P16: 0 | Q16: 0 | R16: 0 | S16: 0 | T16: 0 | U16: 0 | V16: 0 | W16: 0 | X16: 4.5 | Y16: 0 | Z16: 4.5 | AA16: 4.5 | AB16: 0 | AC16: 4.5 | AD16: 0
A17: Wheat | B17: . | C17: 0 | D17: 0 | E17: 0 | F17: 0 | G17: 0 | H17: 0 | I17: 0 | J17: 0 | K17: 0 | L17: 0 | M17: 0 | N17: 0 | O17: 0 | P17: 0 | Q17: 0 | R17: 0 | S17: 0 | T17: 0 | U17: 0 | V17: 0 | W17: 0 | X17: 0 | Y17: 0 | Z17: 0 | AA17: 0 | AB17: 0 | AC17: 0 | AD17: 0
A18: Wheat | B18: . | C18: 0 | D18: 0 | E18: 0 | F18: 0 | G18: 0 | H18: 0 | I18: 0 | J18: 0 | K18: 0 | L18: 0 | M18: 0 | N18: 0 | O18: 0 | P18: 0 | Q18: 0 | R18: 0 | S18: 0 | T18: 0 | U18: 0 | V18: 0 | W18: 0 | X18: 0 | Y18: 0 | Z18: 0 | AA18: 0 | AB18: 0 | AC18: 0 | AD18: 0
A19: Wheat | B19: . | C19: 0 | D19: 0 | E19: 0 | F19: 0 | G19: 0 | H19: 0 | I19: 0 | J19: 0 | K19: 0 | L19: 0 | M19: 0 | N19: 0 | O19: 0 | P19: 0 | Q19: 0 | R19: 0 | S19: 0 | T19: 0 | U19: 0 | V19: 0 | W19: 0 | X19: 0 | Y19: 0 | Z19: 0 | AA19: 0 | AB19: 0 | AC19: 0 | AD19: 0
A20: Wheat | B20: provision of Robert the bailiff for his visits from Christmas until Michaelmas, 4 quarters. | C20: 0 | D20: 0 | E20: 0 | F20: 0 | G20: 0 | H20: 0 | I20: 0 | J20: 0 | K20: 0 | L20: 0 | M20: 0 | N20: 0 | O20: 0 | P20: 0 | Q20: 0 | R20: 0 | S20: 0 | T20: 0 | U20: 0 | V20: 0 | W20: 0 | X20: 4 | Y20: 0 | Z20: 4 | AA20: 4 | AB20: 0 | AC20: 4 | AD20: 0
A21: Wheat | B21: Delivered to 1 hayward from the Circumcision (1 January) until Lammas (1 August), for 30 weeks, and from the Decollation of St John (29 August) until Michaelmas (29 September), for 4 weeks, 2 quarters 1 bushels, because he takes the rest in barley. | C21: 0 | D21: 0 | E21: 0 | F21: 0 | G21: 0 | H21: 0 | I21: 0 | J21: 0 | K21: 0 | L21: 0 | M21: 0 | N21: 0 | O21: 0 | P21: 0 | Q21: 0 | R21: 0 | S21: 0 | T21: 0 | U21: 0 | V21: 0 | W21: 0 | X21: 2 | Y21: 1 | Z21: 2.125 | AA21: 2.125 | AB21: 0 | AC21: 2 | AD21: 1
A22: Wheat | B22: he takes a quarter every 8 weeks and in between times sits at table. | C22: 0 | D22: 0 | E22: 0 | F22: 0 | G22: 0 | H22: 0 | I22: 0 | J22: 0 | K22: 0 | L22: 0 | M22: 0 | N22: 0 | O22: 0 | P22: 0 | Q22: 0 | R22: 0 | S22: 0 | T22: 0 | U22: 0 | V22: 0 | W22: 0 | X22: 0 | Y22: 0 | Z22: 0 | AA22: 0 | AB22: 0 | AC22: 0 | AD22: 0
A23: Wheat | B23: Sold, 73 quarters 4 bushels It balances. | C23: 0 | D23: 0 | E23: 0 | F23: 0 | G23: 0 | H23: 0 | I23: 0 | J23: 0 | K23: 0 | L23: 0 | M23: 0 | N23: 0 | O23: 0 | P23: 0 | Q23: 73 | R23: 4 | S23: 73.5 | T23: 0 | U23: 0 | V23: 0 | W23: 0 | X23: 73 | Y23: 4 | Z23: 73.5 | AA23: 73.5 | AB23: 0 | AC23: 73 | AD23: 4
A24: Wheat | B24: Total | C24: 0 | D24: 0 | E24: 0 | F24: 0 | G24: 0 | H24: 0 | I24: 0 | J24: 0 | K24: 0 | L24: 0 | M24: 0 | N24: 0 | O24: 0 | P24: 0 | Q24: 0 | R24: 0 | S24: 0 | T24: 0 | U24: 0 | V24: 0 | W24: 0
A25: Curall | B25: The same render account for 9 quarters 3.5 bushels from the whole issue of curall by struck measure. | C25: 0 | D25: 0 | E25: 0 | F25: 0 | G25: 0 | H25: 0 | I25: 0 | J25: 0 | K25: 0 | L25: 0 | M25: 0 | N25: 0 | O25: 0 | P25: 0 | Q25: 0 | R25: 0 | S25: 0 | T25: 9 | U25: 3.5 | V25: 9.4375 | W25: 0 | X25: 9 | Y25: 3.5 | Z25: 9.4375 | AA25: 9.4375 | AB25: 0 | AC25: 9 | AD25: 3.5
A26: Curall | B26: Mixed with barley for the liveries of the manorial servants, 1 qr 3 bushels Sold, 8 quarters .5 bushels It balances. | C26: 0 | D26: 0 | E26: 0 | F26: 0 | G26: 0 | H26: 0 | I26: 0 | J26: 0 | K26: 0 | L26: 0 | M26: 0 | N26: 8 | O26: 0 | P26: 8 | Q26: 8 | R26: 0 | S26: 8 | T26: 0 | U26: 0 | V26: 0 | W26: 0
A27: Curall | B27: Total | C27: 0 | D27: 0 | E27: 0 | F27: 0 | G27: 0 | H27: 0 | I27: 0 | J27: 0 | K27: 0 | L27: 0 | M27: 0 | N27: 0 | O27: 0 | P27: 0 | Q27: 0 | R27: 0 | S27: 0 | T27: 0 | U27: 0 | V27: 0 | W27: 0
A28: Barley | B28: {yield: four-fold less 4 quarters 5 bushels} | C28: 0 | D28: 0 | E28: 0 | F28: 0 | G28: 0 | H28: 0 | I28: 0 | J28: 0 | K28: 0 | L28: 0 | M28: 0 | N28: 0 | O28: 0 | P28: 0 | Q28: 0 | R28: 0 | S28: 0 | T28: 0 | U28: 0 | V28: 0 | W28: 0 | X28: 4 | Y28: 5 | Z28: 4.625 | AA28: 4.625 | AB28: 0 | AC28: 4 | AD28: 5
A29: Barley | B29: The same render account for 77 quarters 3 bushels from the whole issue of barley by struck measure. | C29: 0 | D29: 0 | E29: 0 | F29: 0 | G29: 0 | H29: 0 | I29: 0 | J29: 0 | K29: 0 | L29: 0 | M29: 0 | N29: 0 | O29: 0 | P29: 0 | Q29: 0 | R29: 0 | S29: 0 | T29: 77 | U29: 3 | V29: 77.375 | W29: 0 | X29: 77 | Y29: 3 | Z29: 77.375 | AA29: 77.375 | AB29: 0 | AC29: 77 | AD29: 3
A30: Barley | B30: 1 qr 3 bushels received above from curall. | C30: 0 | D30: 0 | E30: 0 | F30: 0 | G30: 0 | H30: 0 | I30: 0 | J30: 0 | K30: 0 | L30: 0 | M30: 0 | N30: 0 | O30: 0 | P30: 0 | Q30: 0 | R30: 0 | S30: 0 | T30: 0 | U30: 0 | V30: 0 | W30: 0
A31: Barley | B31: 1 qr 1 bushels received below from peas. | C31: 0 | D31: 0 | E31: 0 | F31: 0 | G31: 0 | H31: 0 | I31: 0 | J31: 0 | K31: 0 | L31: 0 | M31: 0 | N31: 0 | O31: 0 | P31: 0 | Q31: 0 | R31: 0 | S31: 0 | T31: 0 | U31: 0 | V31: 0 | W31: 0
A32: Barley | B32: 2 quarters 1 bushels received from vetches. | C32: 0 | D32: 0 | E32: 0 | F32: 0 | G32: 0 | H32: 0 | I32: 0 | J32: 0 | K32: 0 | L32: 0 | M32: 0 | N32: 0 | O32: 0 | P32: 0 | Q32: 0 | R32: 0 | S32: 0 | T32: 0 | U32: 0 | V32: 0 | W32: 0 | X32: 2 | Y32: 1 | Z32: 2.125 | AA32: 2.125 | AB32: 0 | AC32: 2 | AD32: 1
A33: Barley | B33: Total, 82 quarters. | C33: 0 | D33: 0 | E33: 0 | F33: 0 | G33: 0 | H33: 0 | I33: 0 | J33: 0 | K33: 0 | L33: 0 | M33: 0 | N33: 0 | O33: 0 | P33: 0 | Q33: 0 | R33: 0 | S33: 0 | T33: 0 | U33: 0 | V33: 0 | W33: 0 | X33: 82 | Y33: 0 | Z33: 82 | AA33: 82 | AB33: 0 | AC33: 82 | AD33: 0
A34: Barley | B34: Sown over 98 acres as they lie on both sides of la Longehegg' and in Crikelescrofte, 20 quarters. | C34: 0 | D34: 0 | E34: 20 | F34: 0 | G34: 20 | H34: 0 | I34: 0 | J34: 0 | K34: 0 | L34: 0 | M34: 0 | N34: 0 | O34: 0 | P34: 0 | Q34: 0 | R34: 0 | S34: 0 | T34: 0 | U34: 0 | V34: 0 | W34: 0 | X34: 20 | Y34: 0 | Z34: 20 | AA34: 20 | AB34: 0 | AC34: 20 | AD34: 0
A35: Barley | B35: that is, 3 bushels 1 peck an acre, plus .5 bushels 1 peck in all. | C35: 0 | D35: 0 | E35: 0 | F35: 0 | G35: 0 | H35: 0 | I35: 0 | J35: 0 | K35: 0 | L35: 0 | M35: 0 | N35: 0 | O35: 0 | P35: 0 | Q35: 0 | R35: 0 | S35: 0 | T35: 0 | U35: 0 | V35: 0 | W35: 0 | X35: 0 | Y35: 5 | Z35: 0.625 | AA35: 0.375 | AB35: 0.25 | AC35: 0 | AD35: 3 | AE35: 0 | AF35: 5
A36: Barley | B36: Delivered to 4 drovers for the year, 26 quarters, taking a quarter every 8 weeks. | C36: 0 | D36: 0 | E36: 0 | F36: 0 | G36: 0 | H36: 0 | I36: 0 | J36: 0 | K36: 0 | L36: 0 | M36: 0 | N36: 0 | O36: 0 | P36: 0 | Q36: 0 | R36: 0 | S36: 0 | T36: 0 | U36: 0 | V36: 0 | W36: 0 | X36: 26 | Y36: 0 | Z36: 26 | AA36: 26 | AB36: 0 | AC36: 26 | AD36: 0
A37: Barley | B37: Delivered to 1 carter for the year, 6.5 quarters, who takes as before. | C37: 0 | D37: 0 | E37: 0 | F37: 0 | G37: 0 | H37: 0 | I37: 0 | J37: 0 | K37: 0 | L37: 0 | M37: 0 | N37: 0 | O37: 0 | P37: 0 | Q37: 0 | R37: 0 | S37: 0 | T37: 0 | U37: 0 | V37: 0 | W37: 0 | X37: 6.5 | Y37: 0 | Z37: 6.5 | AA37: 6.5 | AB37: 0 | AC37: 6.5 | AD37: 0
A38: Barley | B38: Delivered to 1 drover who drove the horse-plough for .5 year and the other cart for the other .5 year, 6.5 quarters, and he takes as before. | C38: 0 | D38: 0 | E38: 0 | F38: 0 | G38: 0 | H38: 0 | I38: 0 | J38: 0 | K38: 0 | L38: 0 | M38: 0 | N38: 0 | O38: 0 | P38: 0 | Q38: 0 | R38: 0 | S38: 0 | T38: 0 | U38: 0 | V38: 0 | W38: 0 | X38: 6.5 | Y38: 0 | Z38: 6.5 | AA38: 6.5 | AB38: 0 | AC38: 6.5 | AD38: 0
A39: Barley | B39: Delivered to 1 cowherd for the year, 4 quarters 2.5 bushels, taking a quarter every 12 weeks. | C39: 0 | D39: 0 | E39: 0 | F39: 0 | G39: 0 | H39: 0 | I39: 0 | J39: 0 | K39: 0 | L39: 0 | M39: 0 | N39: 0 | O39: 0 | P39: 0 | Q39: 0 | R39: 0 | S39: 0 | T39: 0 | U39: 0 | V39: 0 | W39: 0 | X39: 4 | Y39: 2.5 | Z39: 4.3125 | AA39: 4.3125 | AB39: 0 | AC39: 4 | AD39: 2.5
A40: Barley | B40: Delivered to to 1 dairymaid for the year, 5 quarters 1.5 bushels, taking a quarter every 10 weeks. {Henceforth the dairymaid should take nothing except a quarter every 12 weeks. | C40: 0 | D40: 0 | E40: 0 | F40: 0 | G40: 0 | H40: 0 | I40: 0 | J40: 0 | K40: 0 | L40: 0 | M40: 0 | N40: 0 | O40: 0 | P40: 0 | Q40: 0 | R40: 0 | S40: 0 | T40: 0 | U40: 0 | V40: 0 | W40: 0 | X40: 5 | Y40: 1.5 | Z40: 5.1875 | AA40: 5.1875 | AB40: 0 | AC40: 5 | AD40: 1.5
A41: Barley | B41: also hereafter the dairymaid should answer for the offspring of geese and hens}. | C41: 0 | D41: 0 | E41: 0 | F41: 0 | G41: 0 | H41: 0 | I41: 0 | J41: 0 | K41: 0 | L41: 0 | M41: 0 | N41: 0 | O41: 0 | P41: 0 | Q41: 0 | R41: 0 | S41: 0 | T41: 0 | U41: 0 | V41: 0 | W41: 0 | X41: 0 | Y41: 0 | Z41: 0 | AA41: 0 | AB41: 0 | AC41: 0 | AD41: 0
A42: Barley | B42: . | C42: 0 | D42: 0 | E42: 0 | F42: 0 | G42: 0 | H42: 0 | I42: 0 | J42: 0 | K42: 0 | L42: 0 | M42: 0 | N42: 0 | O42: 0 | P42: 0 | Q42: 0 | R42: 0 | S42: 0 | T42: 0 | U42: 0 | V42: 0 | W42: 0 | X42: 0 | Y42: 0 | Z42: 0 | AA42: 0 | AB42: 0 | AC42: 0 | AD42: 0
A43: Barley | B43: . | C43: 0 | D43: 0 | E43: 0 | F43: 0 | G43: 0 | H43: 0 | I43: 0 | J43: 0 | K43: 0 | L43: 0 | M43: 0 | N43: 0 | O43: 0 | P43: 0 | Q43: 0 | R43: 0 | S43: 0 | T43: 0 | U43: 0 | V43: 0 | W43: 0 | X43: 0 | Y43: 0 | Z43: 0 | AA43: 0 | AB43: 0 | AC43: 0 | AD43: 0
A44: Barley | B44: corrody of 1 swineherd and 1 shepherd with the ewes, 4 quarters. | C44: 0 | D44: 0 | E44: 0 | F44: 0 | G44: 0 | H44: 0 | I44: 0 | J44: 0 | K44: 0 | L44: 0 | M44: 0 | N44: 0 | O44: 0 | P44: 0 | Q44: 0 | R44: 0 | S44: 0 | T44: 0 | U44: 0 | V44: 0 | W44: 0 | X44: 4 | Y44: 0 | Z44: 4 | AA44: 4 | AB44: 0 | AC44: 4 | AD44: 0
A45: Barley | B45: . | C45: 0 | D45: 0 | E45: 0 | F45: 0 | G45: 0 | H45: 0 | I45: 0 | J45: 0 | K45: 0 | L45: 0 | M45: 0 | N45: 0 | O45: 0 | P45: 0 | Q45: 0 | R45: 0 | S45: 0 | T45: 0 | U45: 0 | V45: 0 | W45: 0 | X45: 0 | Y45: 0 | Z45: 0 | AA45: 0 | AB45: 0 | AC45: 0 | AD45: 0
A46: Barley | B46: . | C46: 0 | D46: 0 | E46: 0 | F46: 0 | G46: 0 | H46: 0 | I46: 0 | J46: 0 | K46: 0 | L46: 0 | M46: 0 | N46: 0 | O46: 0 | P46: 0 | Q46: 0 | R46: 0 | S46: 0 | T46: 0 | U46: 0 | V46: 0 | W46: 0 | X46: 0 | Y46: 0 | Z46: 0 | AA46: 0 | AB46: 0 | AC46: 0 | AD46: 0
A47: Barley | B47: corrody of 1 keeper of lambs for .5 year, 1 qr. | C47: 0 | D47: 0 | E47: 0 | F47: 0 | G47: 0 | H47: 0 | I47: 0 | J47: 0 | K47: 0 | L47: 0 | M47: 0 | N47: 0 | O47: 0 | P47: 0 | Q47: 0 | R47: 0 | S47: 0 | T47: 0 | U47: 0 | V47: 0 | W47: 0
A48: Barley | B48: Delivered to the same for the other .5 year because he kept the lambs of Bishops Waltham and Droxford, 2 quarters, taking a quarter every 13 weeks. | C48: 0 | D48: 0 | E48: 0 | F48: 0 | G48: 0 | H48: 0 | I48: 0 | J48: 0 | K48: 0 | L48: 0 | M48: 0 | N48: 0 | O48: 0 | P48: 0 | Q48: 0 | R48: 0 | S48: 0 | T48: 0 | U48: 0 | V48: 0 | W48: 0 | X48: 2 | Y48: 0 | Z48: 2 | AA48: 2 | AB48: 0 | AC48: 2 | AD48: 0
A49: Barley | B49: Delivered to 1 hayward from the Circumcision until Lammas, for 30 weeks, and from the Decollation of St John the Baptist until Michaelmas, for 4 weeks, 2 quarters 1 bushels, because he takes the rest in wheat. | C49: 0 | D49: 0 | E49: 0 | F49: 0 | G49: 0 | H49: 0 | I49: 0 | J49: 0 | K49: 0 | L49: 0 | M49: 0 | N49: 0 | O49: 0 | P49: 0 | Q49: 0 | R49: 0 | S49: 0 | T49: 0 | U49: 0 | V49: 0 | W49: 0 | X49: 2 | Y49: 1 | Z49: 2.125 | AA49: 2.125 | AB49: 0 | AC49: 2 | AD49: 1
A50: Barley | B50: he takes a quarter every 8 weeks and in between times at harvest-time he sits at table. | C50: 0 | D50: 0 | E50: 0 | F50: 0 | G50: 0 | H50: 0 | I50: 0 | J50: 0 | K50: 0 | L50: 0 | M50: 0 | N50: 0 | O50: 0 | P50: 0 | Q50: 0 | R50: 0 | S50: 0 | T50: 0 | U50: 0 | V50: 0 | W50: 0 | X50: 0 | Y50: 0 | Z50: 0 | AA50: 0 | AB50: 0 | AC50: 0 | AD50: 0
A51: Barley | B51: Sold, 5 quarters 2.5 bushels Sold at the audit, 0.5 bushels It balances. | C51: 0 | D51: 0 | E51: 0 | F51: 0 | G51: 0 | H51: 0 | I51: 0 | J51: 0 | K51: 0 | L51: 0 | M51: 0 | N51: 0 | O51: 0 | P51: 0 | Q51: 5 | R51: 2.5 | S51: 5.3125 | T51: 0 | U51: 0 | V51: 0 | W51: 0 | X51: 5 | Y51: 0.5 | Z51: 5.0625 | AA51: 5.3125 | AB51: -0.25 | AC51: 5 | AD51: 2.5 | AE51: 0 | AF51: 0.5
A52: Barley | B52: Total | C52: 0 | D52: 0 | E52: 0 | F52: 0 | G52: 0 | H52: 0 | I52: 0 | J52: 0 | K52: 0 | L52: 0 | M52: 0 | N52: 0 | O52: 0 | P52: 0 | Q52: 0 | R52: 0 | S52: 0 | T52: 0 | U52: 0 | V52: 0 | W52: 0
A53: Oats | B53: (yield: two-fold plus 5 quarters .5 bushels) | C53: 0 | D53: 0 | E53: 0 | F53: 0 | G53: 0 | H53: 0 | I53: 0 | J53: 0 | K53: 0 | L53: 0 | M53: 0 | N53: 0 | O53: 0 | P53: 0 | Q53: 0 | R53: 0 | S53: 0 | T53: 0 | U53: 0 | V53: 0 | W53: 0 | X53: 5 | Y53: 5 | Z53: 5.625 | AA53: 5 | AB53: 0.625 | AC53: 5 | AD53: 0 | AE53: 0 | AF53: 5
A54: Oats | B54: The same render account for 180 quarters .5 bushels from the whole issue of oats by struck measure. | C54: 0 | D54: 0 | E54: 0 | F54: 0 | G54: 0 | H54: 0 | I54: 0 | J54: 0 | K54: 0 | L54: 0 | M54: 0 | N54: 0 | O54: 0 | P54: 0 | Q54: 0 | R54: 0 | S54: 0 | T54: 180 | U54: 0 | V54: 180 | W54: 0 | X54: 180 | Y54: 5 | Z54: 180.625 | AA54: 180 | AB54: 0.625 | AC54: 180 | AD54: 0 | AE54: 0 | AF54: 5
A55: Oats | B55: 25 quarters by estimation in sheaves. | C55: 0 | D55: 0 | E55: 0 | F55: 0 | G55: 0 | H55: 0 | I55: 0 | J55: 0 | K55: 0 | L55: 0 | M55: 0 | N55: 0 | O55: 0 | P55: 0 | Q55: 0 | R55: 0 | S55: 0 | T55: 0 | U55: 0 | V55: 0 | W55: 0 | X55: 25 | Y55: 0 | Z55: 25 | AA55: 25 | AB55: 0 | AC55: 25 | AD55: 0
A56: Oats | B56: Total, 205 quarters .5 bushels | C56: 0 | D56: 0 | E56: 0 | F56: 0 | G56: 0 | H56: 0 | I56: 0 | J56: 0 | K56: 0 | L56: 0 | M56: 0 | N56: 0 | O56: 0 | P56: 0 | Q56: 0 | R56: 0 | S56: 0 | T56: 0 | U56: 0 | V56: 0 | W56: 0 | X56: 205 | Y56: 5 | Z56: 205.625 | AA56: 205 | AB56: 0.625 | AC56: 205 | AD56: 0 | AE56: 0 | AF56: 5
A57: Oats | B57: Sown over 405 acres as they lie at Langehegg', Hok', Crikelescrofte and at Legsted', 88.5 quarters bushels. | C57: 0 | D57: 0 | E57: 88.5 | F57: 0 | G57: 88.5 | H57: 0 | I57: 0 | J57: 0 | K57: 0 | L57: 0 | M57: 0 | N57: 0 | O57: 0 | P57: 0 | Q57: 0 | R57: 0 | S57: 0 | T57: 0 | U57: 0 | V57: 0 | W57: 0 | X57: 88.5 | Y57: 0 | Z57: 88.5 | AA57: 88.5 | AB57: 0 | AC57: 88.5 | AD57: 0
A58: Oats | B58: that is, 1 bushels 1 peck an acre, plus 1 peck in all. | C58: 0 | D58: 0 | E58: 0 | F58: 0 | G58: 0 | H58: 0 | I58: 0 | J58: 0 | K58: 0 | L58: 0 | M58: 0 | N58: 0 | O58: 0 | P58: 0 | Q58: 0 | R58: 0 | S58: 0 | T58: 0 | U58: 0 | V58: 0 | W58: 0 | X58: 0 | Y58: 1 | Z58: 0.125 | AA58: 0.125 | AB58: 0 | AC58: 0 | AD58: 1
A59: Oats | B59: . | C59: 0 | D59: 0 | E59: 0 | F59: 0 | G59: 0 | H59: 0 | I59: 0 | J59: 0 | K59: 0 | L59: 0 | M59: 0 | N59: 0 | O59: 0 | P59: 0 | Q59: 0 | R59: 0 | S59: 0 | T59: 0 | U59: 0 | V59: 0 | W59: 0 | X59: 0 | Y59: 0 | Z59: 0 | AA59: 0 | AB59: 0 | AC59: 0 | AD59: 0
A60: Oats | B60: . | C60: 0 | D60: 0 | E60: 0 | F60: 0 | G60: 0 | H60: 0 | I60: 0 | J60: 0 | K60: 0 | L60: 0 | M60: 0 | N60: 0 | O60: 0 | P60: 0 | Q60: 0 | R60: 0 | S60: 0 | T60: 0 | U60: 0 | V60: 0 | W60: 0 | X60: 0 | Y60: 0 | Z60: 0 | AA60: 0 | AB60: 0 | AC60: 0 | AD60: 0
A61: Oats | B61: . | C61: 0 | D61: 0 | E61: 0 | F61: 0 | G61: 0 | H61: 0 | I61: 0 | J61: 0 | K61: 0 | L61: 0 | M61: 0 | N61: 0 | O61: 0 | P61: 0 | Q61: 0 | R61: 0 | S61: 0 | T61: 0 | U61: 0 | V61: 0 | W61: 0 | X61: 0 | Y61: 0 | Z61: 0 | AA61: 0 | AB61: 0 | AC61: 0 | AD61: 0
A62: Oats | B62: . | C62: 0 | D62: 0 | E62: 0 | F62: 0 | G62: 0 | H62: 0 | I62: 0 | J62: 0 | K62: 0 | L62: 0 | M62: 0 | N62: 0 | O62: 0 | P62: 0 | Q62: 0 | R62: 0 | S62: 0 | T62: 0 | U62: 0 | V62: 0 | W62: 0 | X62: 0 | Y62: 0 | Z62: 0 | AA62: 0 | AB62: 0 | AC62: 0 | AD62: 0
A63: Oats | B63: fodder of 2 cart-horses for the year, 15.5 quarters. | C63: 0 | D63: 0 | E63: 0 | F63: 0 | G63: 0 | H63: 0 | I63: 0 | J63: 0 | K63: 0 | L63: 0 | M63: 0 | N63: 15.5 | O63: 0 | P63: 15.5 | Q63: 0 | R63: 0 | S63: 0 | T63: 0 | U63: 0 | V63: 0 | W63: 0 | X63: 15.5 | Y63: 0 | Z63: 15.5 | AA63: 15.5 | AB63: 0 | AC63: 15.5 | AD63: 0
A64: Oats | B64: . | C64: 0 | D64: 0 | E64: 0 | F64: 0 | G64: 0 | H64: 0 | I64: 0 | J64: 0 | K64: 0 | L64: 0 | M64: 0 | N64: 0 | O64: 0 | P64: 0 | Q64: 0 | R64: 0 | S64: 0 | T64: 0 | U64: 0 | V64: 0 | W64: 0 | X64: 0 | Y64: 0 | Z64: 0 | AA64: 0 | AB64: 0 | AC64: 0 | AD64: 0
A65: Oats | B65: . | C65: 0 | D65: 0 | E65: 0 | F65: 0 | G65: 0 | H65: 0 | I65: 0 | J65: 0 | K65: 0 | L65: 0 | M65: 0 | N65: 0 | O65: 0 | P65: 0 | Q65: 0 | R65: 0 | S65: 0 | T65: 0 | U65: 0 | V65: 0 | W65: 0 | X65: 0 | Y65: 0 | Z65: 0 | AA65: 0 | AB65: 0 | AC65: 0 | AD65: 0
A66: Oats | B66: . | C66: 0 | D66: 0 | E66: 0 | F66: 0 | G66: 0 | H66: 0 | I66: 0 | J66: 0 | K66: 0 | L66: 0 | M66: 0 | N66: 0 | O66: 0 | P66: 0 | Q66: 0 | R66: 0 | S66: 0 | T66: 0 | U66: 0 | V66: 0 | W66: 0 | X66: 0 | Y66: 0 | Z66: 0 | AA66: 0 | AB66: 0 | AC66: 0 | AD66: 0
A67: Oats | B67: . | C67: 0 | D67: 0 | E67: 0 | F67: 0 | G67: 0 | H67: 0 | I67: 0 | J67: 0 | K67: 0 | L67: 0 | M67: 0 | N67: 0 | O67: 0 | P67: 0 | Q67: 0 | R67: 0 | S67: 0 | T67: 0 | U67: 0 | V67: 0 | W67: 0 | X67: 0 | Y67: 0 | Z67: 0 | AA67: 0 | AB67: 0 | AC67: 0 | AD67: 0
A68: Oats | B68: fodder of the plough-horses at sowing time, 5.5 quarters. | C68: 0 | D68: 0 | E68: 0 | F68: 0 | G68: 0 | H68: 0 | I68: 0 | J68: 0 | K68: 0 | L68: 0 | M68: 0 | N68: 5.5 | O68: 0 | P68: 5.5 | Q68: 0 | R68: 0 | S68: 0 | T68: 0 | U68: 0 | V68: 0 | W68: 0 | X68: 5.5 | Y68: 0 | Z68: 5.5 | AA68: 5.5 | AB68: 0 | AC68: 5.5 | AD68: 0
... A81: Oats | B81: Sold, 58.5 quarters 3 bushels It balances. | C81: 0 | D81: 0 | E81: 0 | F81: 0 | G81: 0 | H81: 0 | I81: 0 | J81: 0 | K81: 0 | L81: 0 | M81: 0 | N81: 0 | O81: 0 | P81: 0 | Q81: 58.5 | R81: 3 | S81: 58.875 | T81: 0 | U81: 0 | V81: 0 | W81: 0 | X81: 58.5 | Y81: 3 | Z81: 58.875 | AA81: 58.875 | AB81: 0 | AC81: 58.5 | AD81: 3
A82: Oats | B82: Total | C82: 0 | D82: 0 | E82: 0 | F82: 0 | G82: 0 | H82: 0 | I82: 0 | J82: 0 | K82: 0 | L82: 0 | M82: 0 | N82: 0 | O82: 0 | P82: 0 | Q82: 0 | R82: 0 | S82: 0 | T82: 0 | U82: 0 | V82: 0 | W82: 0
A83: Peas | B83: {yield: three-fold plus 2.5 bushels} | C83: 0 | D83: 0 | E83: 0 | F83: 0 | G83: 0 | H83: 0 | I83: 0 | J83: 0 | K83: 0 | L83: 0 | M83: 0 | N83: 0 | O83: 0 | P83: 0 | Q83: 0 | R83: 0 | S83: 0 | T83: 0 | U83: 0 | V83: 0 | W83: 0 | X83: 0 | Y83: 2.5 | Z83: 0.3125 | AA83: 0.3125 | AB83: 0 | AC83: 0 | AD83: 2.5
A84: Peas | B84: The same render account for 3 quarters 2.5 bushels from the whole issue of peas. | C84: 0 | D84: 0 | E84: 0 | F84: 0 | G84: 0 | H84: 0 | I84: 0 | J84: 0 | K84: 0 | L84: 0 | M84: 0 | N84: 0 | O84: 0 | P84: 0 | Q84: 0 | R84: 0 | S84: 0 | T84: 3 | U84: 2.5 | V84: 3.3125 | W84: 0 | X84: 3 | Y84: 2.5 | Z84: 3.3125 | AA84: 3.3125 | AB84: 0 | AC84: 3 | AD84: 2.5
A85: Peas | B85: 4 bushels bought. | C85: 0 | D85: 0 | E85: 0 | F85: 0 | G85: 0 | H85: 0 | I85: 0 | J85: 0 | K85: 0 | L85: 0 | M85: 0 | N85: 0 | O85: 0 | P85: 0 | Q85: 0 | R85: 0 | S85: 0 | T85: 0 | U85: 0 | V85: 0 | W85: 0 | X85: 0 | Y85: 4 | Z85: 0.5 | AA85: 0.5 | AB85: 0 | AC85: 0 | AD85: 4
A86: Peas | B86: Total, 3.5 quarters 2.5 bushels | C86: 0 | D86: 0 | E86: 0 | F86: 0 | G86: 0 | H86: 0 | I86: 0 | J86: 0 | K86: 0 | L86: 0 | M86: 0 | N86: 0 | O86: 0 | P86: 0 | Q86: 0 | R86: 0 | S86: 0 | T86: 0 | U86: 0 | V86: 0 | W86: 0 | X86: 3.5 | Y86: 2.5 | Z86: 3.8125 | AA86: 3.8125 | AB86: 0 | AC86: 3.5 | AD86: 2.5
A87: Peas | B87: Sown over 20 acres as they lie in la Worth', 2 quarters 3.5 bushels. | C87: 0 | D87: 0 | E87: 2 | F87: 3.5 | G87: 2.4375 | H87: 0 | I87: 0 | J87: 0 | K87: 0 | L87: 0 | M87: 0 | N87: 0 | O87: 0 | P87: 0 | Q87: 0 | R87: 0 | S87: 0 | T87: 0 | U87: 0 | V87: 0 | W87: 0 | X87: 2 | Y87: 3.5 | Z87: 2.4375 | AA87: 2.4375 | AB87: 0 | AC87: 2 | AD87: 3.5
A88: Peas | B88: that is, 1 bushels an acre, less 0.5 bushels in all. | C88: 0 | D88: 0 | E88: 0 | F88: 0 | G88: 0 | H88: 0 | I88: 0 | J88: 0 | K88: 0 | L88: 0 | M88: 0 | N88: 0 | O88: 0 | P88: 0 | Q88: 0 | R88: 0 | S88: 0 | T88: 0 | U88: 0 | V88: 0 | W88: 0 | X88: 0 | Y88: 0.5 | Z88: 0.0625 | AA88: 0.125 | AB88: -0.0625 | AC88: 0 | AD88: 1 | AE88: 0 | AF88: 0.5
A89: Peas | B89: Mixed with barley for the liveries of the manorial servants, 1 qr 1 bushels Sold, 2 bushels It balances. | C89: 0 | D89: 0 | E89: 0 | F89: 0 | G89: 0 | H89: 0 | I89: 0 | J89: 0 | K89: 0 | L89: 0 | M89: 0 | N89: 0 | O89: 0 | P89: 0 | Q89: 0 | R89: 0 | S89: 0 | T89: 0 | U89: 0 | V89: 0 | W89: 0
A90: Peas | B90: Total | C90: 0 | D90: 0 | E90: 0 | F90: 0 | G90: 0 | H90: 0 | I90: 0 | J90: 0 | K90: 0 | L90: 0 | M90: 0 | N90: 0 | O90: 0 | P90: 0 | Q90: 0 | R90: 0 | S90: 0 | T90: 0 | U90: 0 | V90: 0 | W90: 0
A91: Vetches | B91: (yield: three-and-a-half-fold plus 1 bushels) | C91: 0 | D91: 0 | E91: 0 | F91: 0 | G91: 0 | H91: 0 | I91: 0 | J91: 0 | K91: 0 | L91: 0 | M91: 0 | N91: 0 | O91: 0 | P91: 0 | Q91: 0 | R91: 0 | S91: 0 | T91: 0 | U91: 0 | V91: 0 | W91: 0 | X91: 0 | Y91: 1 | Z91: 0.125 | AA91: 0.125 | AB91: 0 | AC91: 0 | AD91: 1
A92: Vetches | B92: The same render account for 8 quarters from the whole issue of vetches by struck measure. | C92: 0 | D92: 0 | E92: 0 | F92: 0 | G92: 0 | H92: 0 | I92: 0 | J92: 0 | K92: 0 | L92: 0 | M92: 0 | N92: 0 | O92: 0 | P92: 0 | Q92: 0 | R92: 0 | S92: 0 | T92: 8 | U92: 0 | V92: 8 | W92: 0 | X92: 8 | Y92: 0 | Z92: 8 | AA92: 8 | AB92: 0 | AC92: 8 | AD92: 0
A93: Vetches | B93: 3 quarters 2 bushels bought. | C93: 0 | D93: 0 | E93: 0 | F93: 0 | G93: 0 | H93: 3 | I93: 2 | J93: 3.25 | K93: 0 | L93: 0 | M93: 0 | N93: 0 | O93: 0 | P93: 0 | Q93: 0 | R93: 0 | S93: 0 | T93: 0 | U93: 0 | V93: 0 | W93: 0 | X93: 3 | Y93: 2 | Z93: 3.25 | AA93: 3.25 | AB93: 0 | AC93: 3 | AD93: 2
A94: Vetches | B94: Total, 11 quarters 2 bushels | C94: 0 | D94: 0 | E94: 0 | F94: 0 | G94: 0 | H94: 0 | I94: 0 | J94: 0 | K94: 0 | L94: 0 | M94: 0 | N94: 0 | O94: 0 | P94: 0 | Q94: 0 | R94: 0 | S94: 0 | T94: 0 | U94: 0 | V94: 0 | W94: 0 | X94: 11 | Y94: 2 | Z94: 11.25 | AA94: 11.25 | AB94: 0 | AC94: 11 | AD94: 2
A95: Vetches | B95: Sown over 59 acres as they lie in la Worth' and beside Trtboddestret', 5.5 quarters. | C95: 0 | D95: 0 | E95: 5.5 | F95: 0 | G95: 5.5 | H95: 0 | I95: 0 | J95: 0 | K95: 0 | L95: 0 | M95: 0 | N95: 0 | O95: 0 | P95: 0 | Q95: 0 | R95: 0 | S95: 0 | T95: 0 | U95: 0 | V95: 0 | W95: 0 | X95: 5.5 | Y95: 0 | Z95: 5.5 | AA95: 5.5 | AB95: 0 | AC95: 5.5 | AD95: 0
A96: Vetches | B96: that is, 1 bushels and 1 peck an acre, less I peck in all. | C96: 0 | D96: 0 | E96: 0 | F96: 0 | G96: 0 | H96: 0 | I96: 0 | J96: 0 | K96: 0 | L96: 0 | M96: 0 | N96: 0 | O96: 0 | P96: 0 | Q96: 0 | R96: 0 | S96: 0 | T96: 0 | U96: 0 | V96: 0 | W96: 0 | X96: 0 | Y96: 1 | Z96: 0.125 | AA96: 0.125 | AB96: 0 | AC96: 0 | AD96: 1
A97: Vetches | B97: Mixed above with barley, 2 quarters 1 bushels. | C97: 0 | D97: 0 | E97: 0 | F97: 0 | G97: 0 | H97: 0 | I97: 0 | J97: 0 | K97: 0 | L97: 0 | M97: 0 | N97: 0 | O97: 0 | P97: 0 | Q97: 0 | R97: 0 | S97: 0 | T97: 0 | U97: 0 | V97: 0 | W97: 0 | X97: 2 | Y97: 1 | Z97: 2.125 | AA97: 2.125 | AB97: 0 | AC97: 2 | AD97: 1
A98: Vetches | B98: supporting pigs, 1.5 quarters. | C98: 0 | D98: 0 | E98: 0 | F98: 0 | G98: 0 | H98: 0 | I98: 0 | J98: 0 | K98: 0 | L98: 0 | M98: 0 | N98: 0 | O98: 0 | P98: 0 | Q98: 0 | R98: 0 | S98: 0 | T98: 0 | U98: 0 | V98: 0 | W98: 0 | X98: 1.5 | Y98: 0 | Z98: 1.5 | AA98: 1.5 | AB98: 0 | AC98: 1.5 | AD98: 0
A99: Vetches | B99: Sold, 2 quarters 1 bushels It balances. | C99: 0 | D99: 0 | E99: 0 | F99: 0 | G99: 0 | H99: 0 | I99: 0 | J99: 0 | K99: 0 | L99: 0 | M99: 0 | N99: 0 | O99: 0 | P99: 0 | Q99: 2 | R99: 1 | S99: 2.125 | T99: 0 | U99: 0 | V99: 0 | W99: 0 | X99: 2 | Y99: 1 | Z99: 2.125 | AA99: 2.125 | AB99: 0 | AC99: 2 | AD99: 1

Sheet Sale of Corn Prices
A1: Heading | B1: Sentence | C1: Total in Pounds | D1: Pounds | E1: Shillings | F1: Pence | G1: Corn | H1: Total Quarters Except 1 | I1: Total Bushels Except 1 | J1: Total Corn Cross-Check | K1: Total Corn Manorial Account | L1: Corn Quantity Error | M1: Quarters 0 | N1: Bushels 0 | O1: shilling a quarter 1 | P1: pence a quarter 1 | Q1: Quarters 1 | R1: Bushels 1 | S1: shilling a quarter 2 | T1: pence a quarter 2 | U1: Quarters 2 | V1: Bushels 2 | W1: shilling a quarter 3 | X1: pence a quarter 3 | Y1: Quarters 3 | Z1: Bushels 3 | AA1: shilling a quarter 4 | AB1: pence a quarter 4 | AC1: Quarters 4 | AD1: Bushels 4 | AE1: £ a quarter 1 | AF1: £ a quarter 2 | AG1: £ a quarter 3 | AH1: £ a quarter 4 | AI1: Quarters Sold | AJ1: Weighted Average Price per Quarter | AK1: Non-Weighted Average Price per Quarter | AL1: Corn lowercase
A2: Sale of corn | B2: The same render account for £22 15 shilling 8.5pence from 73.5 quarters of wheat sold, at 5 shilling a quarters for 7.5 quarters 1 bushels, 5 shilling 4pence a quarters for 6.5 quarters, 6 shilling a quarters for 19 quarters 3 bushels, and 6 shilling 8pence a quarters for 40 quarters.. | C2: 22.79 | D2: 22 | E2: 15 | F2: 8.5 | G2: wheat | H2: 73 | I2: 4 | J2: 73.5 | K2: 73.5 | L2: 0 | M2: 73.5 | N2: 0 | O2: 5 | P2: 0 | Q2: 7.5 | R2: 1 | S2: 5 | T2: 4 | U2: 6.5 | V2: 0 | W2: 6 | X2: 0 | Y2: 19 | Z2: 3 | AA2: 6 | AB2: 8 | AC2: 40 | AD2: 0 | AE2: 0.25 | AF2: 0.26666667 | AG2: 0.3 | AH2: 0.33333333 | AI2: 73.5 | AJ2: 0.31000567 | AK2: 0.2875 | AL2: wheat
A3: Sale of corn | B3: 17 shilling 5.75pence from 8 quarters' bushels of curall sold, at 2 shilling a quarters for 4 quarters, and 2 shilling 4pence a quarters for 4 quarters .5 bushels. | C3: 0.87 | D3: 0 | E3: 17 | F3: 5.75 | G3: curall | H3: 8 | I3: 5 | J3: 8.625 | K3: 8 | L3: 0.625 | M3: 8 | N3: 0 | O3: 2 | P3: 0 | Q3: 4 | R3: 0 | S3: 2 | T3: 4 | U3: 4 | V3: 0 | Y3: 0 | Z3: 5 | AE3: 0.1 | AF3: 0.11666667 | AI3: 8 | AJ3: 0.10833333 | AK3: 0.10833333 | AL3: curall
A4: Sale of corn | B4: £1 1 shilling 3pence from 5 quarters 2.5 bushels of barley sold, at 4 shilling a quarters. | C4: 1.06 | D4: 1 | E4: 1 | F4: 3 | G4: barley | H4: 5 | I4: 2.5 | J4: 5.3125 | K4: 5.3125 | L4: 0 | M4: 5 | N4: 2.5 | O4: 4 | P4: 0 | AE4: 0.2 | AI4: 5.3125 | AJ4: 0.2 | AK4: 0.2 | AL4: barley
A5: Sale of corn | B5: £6 13 shilling 10pence from 58.5 quarters 3 bushels, of oats sold, at 2 shilling a quarters for 31 quarters, 2 shilling 4pence a quarters for 7.5 quarters, and 2 shilling 8pence a quarters for 20 quarters 3 bushels. | C5: 6.69 | D5: 6 | E5: 13 | F5: 10 | G5: oats | H5: 58.5 | I5: 3 | J5: 58.875 | K5: 58.875 | L5: 0 | M5: 58.5 | N5: 3 | O5: 2 | P5: 0 | Q5: 31 | R5: 0 | S5: 2 | T5: 4 | U5: 7.5 | V5: 0 | W5: 2 | X5: 8 | Y5: 20 | Z5: 3 | AE5: 0.1 | AF5: 0.11666667 | AG5: 0.13333333 | AI5: 58.875 | AJ5: 0.11365888 | AK5: 0.11666667 | AL5: oats
A6: Sale of corn | B6: 8pence from 2 bushels of peas sold. | C6: 0.03 | D6: 0 | E6: 0 | F6: 8 | G6: peas | H6: 0 | I6: 2 | J6: 0.25 | K6: 0.25 | L6: 0 | M6: 0 | N6: 2 | AE6: 0.12 | AI6: 0.25 | AJ6: 0.12 | AK6: 0.12 | AL6: peas
A7: Sale of corn | B7: 4 shilling 3pence from 2 quarters 1 bushels of vetches sold, at 2 shilling a quarters. | C7: 0.21 | D7: 0 | E7: 4 | F7: 3 | G7: vetches | H7: 2 | I7: 1 | J7: 2.125 | K7: 2.125 | L7: 0 | M7: 2 | N7: 1 | O7: 2 | P7: 0 | AE7: 0.1 | AI7: 2.125 | AJ7: 0.1 | AK7: 0.1 | AL7: vetches
A8: Sale of corn | B8: Total, £31 13 shilling 2.25pence | C8: 31.66 | D8: 31 | E8: 13 | F8: 2.25 | H8: 0 | I8: 0 | J8: 0 | K8: 0 | L8: 0 | M8: 0 | N8: 0 | AE8: inf | AI8: 0 | AJ8: inf | AK8: inf

Sheet raw data
A1: Heading | B1: Sentence | C1: Total in Pounds | D1: Pounds | E1: Shillings | F1: Pence | G1: Corn | H1: Total Quarters Except 1 | I1: Total Bushels Except 1 | J1: Total Corn Cross-Check | K1: Total Corn Manorial Account | L1: Corn Quantity Error | M1: Quarters 1 | N1: Bushels 1 | O1: Quarters 2 | P1: Bushels 2 | Q1: Quarters 3 | R1: Bushels 3 | S1: Quarters 4 | T1: Bushels 4 | U1: Quarters 5 | V1: Bushels 5 | W1: shilling a quarter 1 | X1: pence a quarter 1 | Y1: shilling a quarter 2 | Z1: pence a quarter 2 | AA1: shilling a quarter 3 | AB1: pence a quarter 3 | AC1: shilling a quarter 4 | AD1: pence a quarter 4 | AE1: shilling a bushel 1 | AF1: pence a bushel 1 | AG1: shilling a bushel 2 | AH1: pence a bushel 2 | AI1: shilling a bushel 3 | AJ1: pence a bushel 3 | AK1: shilling a bushel 4 | AL1: pence a bushel 4
A2: Arrears | B2: Robert de Froyle, bailiff, and Robert Stretthe, reeve, render account for £71 18 shilling 3.5pence of arrears from the previous year. | C2: 71.91 | D2: 71 | E2: 18 | F2: 3.5 | H2: 0 | I2: 0 | J2: 0 | K2: 0 | L2: 0 | M2: 0 | N2: 0
A3: Arrears | B3: All delivered to Sir Geoffrey, treasurer of Wolvesey, by 1 tally, and they are quit. | C3: 0 | D3: 0 | E3: 0 | F3: 0 | H3: 0 | I3: 0 | J3: 0 | K3: 0 | L3: 0 | M3: 0 | N3: 0
A4: Rents | B4: The same render account for £14 10 shilling 10.75pence for all rents of assize at Christmas. | C4: 14.54 | D4: 14 | E4: 10 | F4: 10.75 | H4: 0 | I4: 0 | J4: 0 | K4: 0 | L4: 0 | M4: 0 | N4: 0
A5: Rents | B5: £23 8.75pence at Easter (22 April). | C5: 23.04 | D5: 23 | E5: 0 | F5: 8.75 | H5: 0 | I5: 0 | J5: 0 | K5: 0 | L5: 0 | M5: 0 | N5: 0
A6: Rents | B6: £14 10 shilling 10.5pence at the Nativity of St John the Baptist (24 June). | C6: 14.54 | D6: 14 | E6: 10 | F6: 10.5 | H6: 0 | I6: 0 | J6: 0 | K6: 0 | L6: 0 | M6: 0 | N6: 0
A7: Rents | B7: £23 19 shilling 3.5pence at Michaelmas (29 September). | C7: 23.96 | D7: 23 | E7: 19 | F7: 3.5 | H7: 0 | I7: 0 | J7: 0 | K7: 0 | L7: 0 | M7: 0 | N7: 0
A8: Rents | B8: Total, £76 1 shilling 9.5pence | C8: 76.09 | D8: 76 | E8: 1 | F8: 9.5 | H8: 0 | I8: 0 | J8: 0 | K8: 0 | L8: 0 | M8: 0 | N8: 0
A9: Quittances | B9: In quittance of 1 reeve for the year 5 shilling. | C9: 0.25 | D9: 0 | E9: 5 | F9: 0 | H9: 0 | I9: 0 | J9: 0 | K9: 0 | L9: 0 | M9: 0 | N9: 0
A10: Quittances | B10: 1 beadle for the year 5 shilling. | C10: 0.25 | D10: 0 | E10: 5 | F10: 0 | H10: 0 | I10: 0 | J10: 0 | K10: 0 | L10: 0 | M10: 0 | N10: 0
A11: Quittances | B11: 1 swineherd, 1 smith, 1 hayward who kept the lord's corn and pasture and sowed the wheat and barley, 1 shepherd of wethers, and 1 keeper of ewes, 10 shilling, or 2 shilling each. | C11: 0.5 | D11: 0 | E11: 10 | F11: 0 | G11: barley, wheat | H11: 0 | I11: 0 | J11: 0 | K11: 0 | L11: 0 | M11: 0 | N11: 0
A12: Quittances | B12: 4 ploughmen for the year, and 1 ploughman for 1 term, 8 shilling 6pence. | C12: 0.43 | D12: 0 | E12: 8 | F12: 6 | H12: 0 | I12: 0 | J12: 0 | K12: 0 | L12: 0 | M12: 0 | N12: 0
A13: Quittances | B13: 9 workers, each of whom are bound to reap everyday at harvest-time 1 acre as it lies and after the harvest are bound to work twice a week, 18 shilling, or 2 shilling each. | C13: 0.9 | D13: 0 | E13: 18 | F13: 0 | H13: 0 | I13: 0 | J13: 0 | K13: 0 | L13: 0 | M13: 0 | N13: 0
A14: Quittances | B14: 3 cottars for the year, each of whom are bound to reap everyday .5 acre as it lies and after the harvest are bound to work once a week, 3 shilling. | C14: 0.15 | D14: 0 | E14: 3 | F14: 0 | H14: 0 | I14: 0 | J14: 0 | K14: 0 | L14: 0 | M14: 0 | N14: 0
A15: Quittances | B15: 2 workers who are bound to reap everyday at harvest-time 1 acre as it lies and after the harvest are bound to work twice a week with their carts, working at the lord's pleasure, besides carrying dung, 6 shilling for the year. | C15: 0.3 | D15: 0 | E15: 6 | F15: 0 | H15: 0 | I15: 0 | J15: 0 | K15: 0 | L15: 0 | M15: 0 | N15: 0
A16: Quittances | B16: 1 granary-keeper for the year 2 shilling Total, £2 17 shilling 6pence | C16: 2.88 | D16: 2 | E16: 17 | F16: 6 | H16: 0 | I16: 0 | J16: 0 | K16: 0 | L16: 0 | M16: 0 | N16: 0
A17: Defaults of rent | B17: In default of the land between the Barton and garden drawn into demesne, £1 2 shilling 8pence for the year. | C17: 1.13 | D17: 1 | E17: 2 | F17: 8 | H17: 0 | I17: 0 | J17: 0 | K17: 0 | L17: 0 | M17: 0 | N17: 0
A18: Defaults of rent | B18: the land of Osbert de Langely, 8pence for the year. | C18: 0.03 | D18: 0 | E18: 0 | F18: 8 | H18: 0 | I18: 0 | J18: 0 | K18: 0 | L18: 0 | M18: 0 | N18: 0
A19: Defaults of rent | B19: the land of Richard Baton, 6pence for the year. | C19: 0.03 | D19: 0 | E19: 0 | F19: 6 | H19: 0 | I19: 0 | J19: 0 | K19: 0 | L19: 0 | M19: 0 | N19: 0
A20: Defaults of rent | B20: the land of Hugh son of Agnes, 6pence for the year. | C20: 0.03 | D20: 0 | E20: 0 | F20: 6 | H20: 0 | I20: 0 | J20: 0 | K20: 0 | L20: 0 | M20: 0 | N20: 0
A21: Defaults of rent | B21: the land of Richard Swanemere, 3pence for the year. | C21: 0.01 | D21: 0 | E21: 0 | F21: 3 | H21: 0 | I21: 0 | J21: 0 | K21: 0 | L21: 0 | M21: 0 | N21: 0
A22: Defaults of rent | B22: the land of the mill drawn into the park, 6 shilling 5pence for the year. | C22: 0.32 | D22: 0 | E22: 6 | F22: 5 | H22: 0 | I22: 0 | J22: 0 | K22: 0 | L22: 0 | M22: 0 | N22: 0
A23: Defaults of rent | B23: the rent of Peter Clericus, 1 shilling 6pence for the year. | C23: 0.08 | D23: 0 | E23: 1 | F23: 6 | H23: 0 | I23: 0 | J23: 0 | K23: 0 | L23: 0 | M23: 0 | N23: 0
... A144: Issues of the manor | B144: £19 7 shilling 7pence from 50 Yearlings bought and agisted in the park the previous year and afterwards solpence Total, £77 8 shilling 1pence | C144: 19.38 | D144: 19 | E144: 7 | F144: 7 | H144: 0 | I144: 0 | J144: 0 | K144: 0 | L144: 0 | M144: 0 | N144: 0
A145: Sale of corn | B145: The same render account for £22 15 shilling 8.5pence from 73.5 quarters of wheat sold, at 5 shilling a quarters for 7.5 quarters 1 bushels, 5 shilling 4pence a quarters for 6.5 quarters, 6 shilling a quarters for 19 quarters 3 bushels, and 6 shilling 8pence a quarters for 40 quarters.. | C145: 22.79 | D145: 22 | E145: 15 | F145: 8.5 | G145: wheat | H145: 73 | I145: 4 | J145: 73.5 | K145: 73.5 | L145: 0 | M145: 73.5 | N145: 0 | O145: 7.5 | P145: 1 | Q145: 6.5 | R145: 0 | S145: 19 | T145: 3 | U145: 40 | V145: 0 | W145: 5 | X145: 0 | Y145: 5 | Z145: 4 | AA145: 6 | AB145: 0 | AC145: 6 | AD145: 8
A146: Sale of corn | B146: 17 shilling 5.75pence from 8 quarters' bushels of curall sold, at 2 shilling a quarters for 4 quarters, and 2 shilling 4pence a quarters for 4 quarters .5 bushels. | C146: 0.87 | D146: 0 | E146: 17 | F146: 5.75 | G146: curall | H146: 8 | I146: 5 | J146: 8.625 | K146: 8 | L146: 0.625 | M146: 8 | N146: 0 | O146: 4 | P146: 0 | Q146: 4 | R146: 0 | S146: 0 | T146: 5 | W146: 2 | X146: 0 | Y146: 2 | Z146: 4
A147: Sale of corn | B147: £1 1 shilling 3pence from 5 quarters 2.5 bushels of barley sold, at 4 shilling a quarters. | C147: 1.06 | D147: 1 | E147: 1 | F147: 3 | G147: barley | H147: 5 | I147: 2.5 | J147: 5.3125 | K147: 5.3125 | L147: 0 | M147: 5 | N147: 2.5 | W147: 4 | X147: 0
A148: Sale of corn | B148: £6 13 shilling 10pence from 58.5 quarters 3 bushels, of oats sold, at 2 shilling a quarters for 31 quarters, 2 shilling 4pence a quarters for 7.5 quarters, and 2 shilling 8pence a quarters for 20 quarters 3 bushels. | C148: 6.69 | D148: 6 | E148: 13 | F148: 10 | G148: oats | H148: 58.5 | I148: 3 | J148: 58.875 | K148: 58.875 | L148: 0 | M148: 58.5 | N148: 3 | O148: 31 | P148: 0 | Q148: 7.5 | R148: 0 | S148: 20 | T148: 3 | W148: 2 | X148: 0 | Y148: 2 | Z148: 4 | AA148: 2 | AB148: 8
A149: Sale of corn | B149: 8pence from 2 bushels of peas sold. | C149: 0.03 | D149: 0 | E149: 0 | F149: 8 | G149: peas | H149: 0 | I149: 2 | J149: 0.25 | K149: 0.25 | L149: 0 | M149: 0 | N149: 2
A150: Sale of corn | B150: 4 shilling 3pence from 2 quarters 1 bushels of vetches sold, at 2 shilling a quarters. | C150: 0.21 | D150: 0 | E150: 4 | F150: 3 | G150: vetches | H150: 2 | I150: 1 | J150: 2.125 | K150: 2.125 | L150: 0 | M150: 2 | N150: 1 | W150: 2 | X150: 0
A151: Sale of corn | B151: Total, £31 13 shilling 2.25pence | C151: 31.66 | D151: 31 | E151: 13 | F151: 2.25 | H151: 0 | I151: 0 | J151: 0 | K151: 0 | L151: 0 | M151: 0 | N151: 0
A152: East mill | B152: The same render account for 7 shilling 7pence from 1 quarters 3 bushels of wheat sold, at 5 shilling 4pence for 1 quarters, and 9pence a bushels for 3 bushels. | C152: 0.38 | D152: 0 | E152: 7 | F152: 7 | G152: wheat | H152: 1 | I152: 3 | J152: 1.375 | K152: 1.375 | L152: 0 | M152: 1 | N152: 3 | O152: 1 | P152: 0 | Q152: 0 | R152: 3 | AE152: 0 | AF152: 9
A153: East mill | B153: £3 3 shilling 6pence from 18 quarters 1 bushels of maslin sold, at 3 shilling 4pence a quarters for 7 quarters, and 4 shilling a quarters for 8 quarters 1 bushels Total, £3 11 shilling 1pence | C153: 3.17 | D153: 3 | E153: 3 | F153: 6 | G153: maslin | H153: 15 | I153: 1 | J153: 15.125 | K153: 18.125 | L153: -3 | M153: 18 | N153: 1 | O153: 7 | P153: 0 | Q153: 8 | R153: 1 | W153: 3 | X153: 4 | Y153: 4 | Z153: 0
A154: Mill outside the gate | B154: The same render account for 6 shilling 3pence from 1 quarters 1 bushels of wheat sold, at 7pence for 1 bushels, 8pence a bushels for 4 bushels, and 9pence a bushels for 3 bushels. | C154: 0.31 | D154: 0 | E154: 6 | F154: 3 | G154: wheat | H154: 1 | I154: 8 | J154: 2 | K154: 1.125 | L154: 0.875 | M154: 1 | N154: 1 | O154: 0 | P154: 1 | Q154: 0 | R154: 4 | S154: 0 | T154: 3 | AE154: 0 | AF154: 8 | AG154: 0 | AH154: 9
A155: Mill outside the gate | B155: 9 shilling 2r.5-1pence from 2 quarters 5 bushels of maslin sold, at 4.5pence a bushels for 5 bushels, 3 shilling 4pence for 1 quarters, and 4 shilling for 1 quarters. | C155: 0.45 | D155: 0 | E155: 9 | F155: 1 | G155: maslin | H155: 2 | I155: 5 | J155: 2.625 | K155: 2.625 | L155: 0 | M155: 2 | N155: 5 | O155: 0 | P155: 5 | Q155: 1 | R155: 0 | S155: 1 | T155: 0 | AE155: 0 | AF155: 4.5
A156: Mill outside the gate | B156: £1 12 shilling 4pence from 5 quarters 5.5 bushels of coarse-ground corn sold, at 5 shilling 4pence a quarters for 2 quarters 5.5 bushels, and 6 shilling a quarters for 3 quarters. | C156: 1.62 | D156: 1 | E156: 12 | F156: 4 | H156: 5 | I156: 5.5 | J156: 5.6875 | K156: 5.6875 | L156: 0 | M156: 5 | N156: 5.5 | O156: 2 | P156: 5.5 | Q156: 3 | R156: 0 | W156: 5 | X156: 4 | Y156: 6 | Z156: 0
A157: Mill outside the gate | B157: £1 13 shilling 8pence from 13.5 quarters of malt sold, at 2 shilling 4pence a quarters for 5 quarters, 2 shilling 6pence a quarters for 4 quarters, and 2 shilling 8pence a quarters for 4.5 quarters. | C157: 1.68 | D157: 1 | E157: 13 | F157: 8 | H157: 13.5 | I157: 0 | J157: 13.5 | K157: 13.5 | L157: 0 | M157: 13.5 | N157: 0 | O157: 5 | P157: 0 | Q157: 4 | R157: 0 | S157: 4.5 | T157: 0 | W157: 2 | X157: 4 | Y157: 2 | Z157: 6 | AA157: 2 | AB157: 8
A158: Mill outside the gate | B158: 6 shilling 8pence from 1 quarters of oatmeal solpence Total, £4 8 shilling 1.5pence Total of both, £7 19 shilling 2.5pence | C158: 4.41 | D158: 4 | E158: 8 | F158: 1.5 | G158: oatmeal | H158: 1 | I158: 0 | J158: 1 | K158: 1 | L158: 0 | M158: 1 | N158: 0
A159: Entry and marriage fines | B159: The same render account for 10 shilling from the 2 tithings of Bishops Waltham for tithingpenny at the hundred-court of Martinmas (11 November). | C159: 0.5 | D159: 0 | E159: 10 | F159: 0 | H159: 0 | I159: 0 | J159: 0 | K159: 0 | L159: 0 | M159: 0 | N159: 0
A160: Entry and marriage fines | B160: 4 shilling from the tithing of Mensingefeld' for the same. | C160: 0.2 | D160: 0 | E160: 4 | F160: 0 | H160: 0 | I160: 0 | J160: 0 | K160: 0 | L160: 0 | M160: 0 | N160: 0
A161: Entry and marriage fines | B161: 4 shilling from the tithing of Bursledon for the same. | C161: 0.2 | D161: 0 | E161: 4 | F161: 0 | H161: 0 | I161: 0 | J161: 0 | K161: 0 | L161: 0 | M161: 0 | N161: 0
A162: Entry and marriage fines | B162: 1 shilling 6pence from the tithing of Hou for the same. | C162: 0.08 | D162: 0 | E162: 1 | F162: 6 | H162: 0 | I162: 0 | J162: 0 | K162: 0 | L162: 0 | M162: 0 | N162: 0
A163: Entry and marriage fines | B163: 4 shilling from the tithing of Wangefeld' for the same. | C163: 0.2 | D163: 0 | E163: 4 | F163: 0 | H163: 0 | I163: 0 | J163: 0 | K163: 0 | L163: 0 | M163: 0 | N163: 0
A164: Entry and marriage fines | B164: 3 shilling from the tithing of Durley for the same. | C164: 0.15 | D164: 0 | E164: 3 | F164: 0 | H164: 0 | I164: 0 | J164: 0 | K164: 0 | L164: 0 | M164: 0 | N164: 0
A165: Entry and marriage fines | B165: 2 shilling 6pence from the tithing of Wyntershll' for the same. | C165: 0.12 | D165: 0 | E165: 2 | F165: 6 | H165: 0 | I165: 0 | J165: 0 | K165: 0 | L165: 0 | M165: 0 | N165: 0
A166: Entry and marriage fines | B166: 3 shilling from the tithing of Upham for the same. | C166: 0.15 | D166: 0 | E166: 3 | F166: 0 | H166: 0 | I166: 0 | J166: 0 | K166: 0 | L166: 0 | M166: 0 | N166: 0
A167: Entry and marriage fines | B167: 3 shilling from the tithing of Wodekot' for the same. | C167: 0.15 | D167: 0 | E167: 3 | F167: 0 | H167: 0 | I167: 0 | J167: 0 | K167: 0 | L167: 0 | M167: 0 | N167: 0
A168: Entry and marriage fines | B168: 3 shilling from the tithing of Ashton for the same. | C168: 0.15 | D168: 0 | E168: 3 | F168: 0 | H168: 0 | I168: 0 | J168: 0 | K168: 0 | L168: 0 | M168: 0 | N168: 0
A169: Entry and marriage fines | B169: £1 18 shilling from the same tithings for tithingpenny at the hundred-court of Hockday (1 May). | C169: 1.9 | D169: 1 | E169: 18 | F169: 0 | H169: 0 | I169: 0 | J169: 0 | K169: 0 | L169: 0 | M169: 0 | N169: 0
A170: Entry and marriage fines | B170: 6 shilling 8pence from Mork to have a third of .5 virgate of land which belonged to Agnes his mother. | C170: 0.33 | D170: 0 | E170: 6 | F170: 8 | H170: 0 | I170: 0 | J170: 0 | K170: 0 | L170: 0 | M170: 0 | N170: 0
... A233: Cost of ploughs | B233: . | C233: 0 | D233: 0 | E233: 0 | F233: 0 | H233: 0 | I233: 0 | J233: 0 | K233: 0 | L233: 0 | M233: 0 | N233: 0
A234: Cost of ploughs | B234: stipend of 4 ploughmen for 8 Saturday ploughings at the time of the winter sowing, 11 Saturdays at the summer sowing, and 10 Saturdays at the fallowing, with the stipend of 1 ploughman for 8 Saturday ploughings at the sowing of the barley, 13 shilling 10pence, or 1.5pence each when ploughing for sowing, and 1pence when fallowing. | C234: 0.69 | D234: 0 | E234: 13 | F234: 10 | G234: barley | H234: 0 | I234: 0 | J234: 0 | K234: 0 | L234: 0 | M234: 0 | N234: 0
A235: Cost of ploughs | B235: . | C235: 0 | D235: 0 | E235: 0 | F235: 0 | H235: 0 | I235: 0 | J235: 0 | K235: 0 | L235: 0 | M235: 0 | N235: 0
A236: Cost of ploughs | B236: stipend of 4 drovers for the year and 1 drover for' year 13 shilling 6pence, or 3 shilling each. | C236: 0.68 | D236: 0 | E236: 13 | F236: 6 | H236: 0 | I236: 0 | J236: 0 | K236: 0 | L236: 0 | M236: 0 | N236: 0
A237: Cost of ploughs | B237: . | C237: 0 | D237: 0 | E237: 0 | F237: 0 | H237: 0 | I237: 0 | J237: 0 | K237: 0 | L237: 0 | M237: 0 | N237: 0
A238: Cost of ploughs | B238: 1 plough-horse bought 9 shilling 6pence. | C238: 0.48 | D238: 0 | E238: 9 | F238: 6 | H238: 0 | I238: 0 | J238: 0 | K238: 0 | L238: 0 | M238: 0 | N238: 0
A239: Cost of ploughs | B239: 9 oxen bought £5 8pence, at 9 shilling 6pence for 1,10 shilling 1pence each for 2, 11 shilling 6pence each for 2, and 12 shilling each for 4.. | C239: 5.03 | D239: 5 | E239: 0 | F239: 8 | H239: 0 | I239: 0 | J239: 0 | K239: 0 | L239: 0 | M239: 0 | N239: 0
A240: Cost of ploughs | B240: 4 bushels of peas bought for sowing 1 shilling 4pence. | C240: 0.07 | D240: 0 | E240: 1 | F240: 4 | G240: peas | H240: 0 | I240: 4 | J240: 0.5 | K240: 0.5 | L240: 0 | M240: 0 | N240: 4
A241: Cost of ploughs | B241: 3 quarters 2 bushels of vetches bought 5 shilling 5pence, at 1 shilling 8pence a quarters. | C241: 0.27 | D241: 0 | E241: 5 | F241: 5 | G241: vetches | H241: 3 | I241: 2 | J241: 3.25 | K241: 3.25 | L241: 0 | M241: 3 | N241: 2 | W241: 1 | X241: 8
A242: Cost of ploughs | B242: . | C242: 0 | D242: 0 | E242: 0 | F242: 0 | H242: 0 | I242: 0 | J242: 0 | K242: 0 | L242: 0 | M242: 0 | N242: 0
A243: Cost of ploughs | B243: forage bought to support the lord's stock £1 4 shilling Total, £10 1 shilling 5pence | C243: 1.2 | D243: 1 | E243: 4 | F243: 0 | H243: 0 | I243: 0 | J243: 0 | K243: 0 | L243: 0 | M243: 0 | N243: 0
A244: Cost of carts | B244: In 1 new cart with iron tyres with all equipment bought 14 shilling. | C244: 0.7 | D244: 0 | E244: 14 | F244: 0 | H244: 0 | I244: 0 | J244: 0 | K244: 0 | L244: 0 | M244: 0 | N244: 0
A245: Cost of carts | B245: mending the old cart 1 .5pence. | C245: 0.02 | D245: 0 | E245: 0 | F245: 5 | H245: 0 | I245: 0 | J245: 0 | K245: 0 | L245: 0 | M245: 0 | N245: 0
A246: Cost of carts | B246: clouts, nails and grease bought 1 shilling 10pence. | C246: 0.09 | D246: 0 | E246: 1 | F246: 10 | H246: 0 | I246: 0 | J246: 0 | K246: 0 | L246: 0 | M246: 0 | N246: 0
A247: Cost of carts | B247: fitting the carts with axles at various times with axles bought for the same 6.25pence. | C247: 0.03 | D247: 0 | E247: 0 | F247: 6.25 | H247: 0 | I247: 0 | J247: 0 | K247: 0 | L247: 0 | M247: 0 | N247: 0
A248: Cost of carts | B248: 1 cart-rail made anew for the cart 3pence. | C248: 0.01 | D248: 0 | E248: 0 | F248: 3 | H248: 0 | I248: 0 | J248: 0 | K248: 0 | L248: 0 | M248: 0 | N248: 0
A249: Cost of carts | B249: 1 pair of traces bought 5.5pence. | C249: 0.02 | D249: 0 | E249: 0 | F249: 5.5 | H249: 0 | I249: 0 | J249: 0 | K249: 0 | L249: 0 | M249: 0 | N249: 0
A250: Cost of carts | B250: 3 collars and 1 pair of saddle-pads bought 2 shilling 4pence. | C250: 0.12 | D250: 0 | E250: 2 | F250: 4 | H250: 0 | I250: 0 | J250: 0 | K250: 0 | L250: 0 | M250: 0 | N250: 0
A251: Cost of carts | B251: a hemp rope bought 11pence. | C251: 0.05 | D251: 0 | E251: 0 | F251: 11 | H251: 0 | I251: 0 | J251: 0 | K251: 0 | L251: 0 | M251: 0 | N251: 0
A252: Cost of carts | B252: white leather bought 4pence. | C252: 0.02 | D252: 0 | E252: 0 | F252: 4 | H252: 0 | I252: 0 | J252: 0 | K252: 0 | L252: 0 | M252: 0 | N252: 0
A253: Cost of carts | B253: 2 pairs of swingletrees 2pence. | C253: 0.01 | D253: 0 | E253: 0 | F253: 2 | H253: 0 | I253: 0 | J253: 0 | K253: 0 | L253: 0 | M253: 0 | N253: 0
... A297: Cost of the park | B297: In making the palisade of the park anew in places and mending it elsewhere £1 8 shilling 10pence Total, £1 8 shilling 10pence | C297: 1.44 | D297: 1 | E297: 8 | F297: 10 | H297: 0 | I297: 0 | J297: 0 | K297: 0 | L297: 0 | M297: 0 | N297: 0
A298: Threshing | B298: Nothing for the threshing of peas and vetches because they were threshed by labour service. | C298: 0 | D298: 0 | E298: 0 | F298: 0 | G298: vetches, peas | H298: 0 | I298: 0 | J298: 0 | K298: 0 | L298: 0 | M298: 0 | N298: 0
A299: Threshing | B299: . | C299: 0 | D299: 0 | E299: 0 | F299: 0 | H299: 0 | I299: 0 | J299: 0 | K299: 0 | L299: 0 | M299: 0 | N299: 0
A300: Threshing | B300: 2 sacks bought 1 shilling 1pence. | C300: 0.05 | D300: 0 | E300: 1 | F300: 1 | H300: 0 | I300: 0 | J300: 0 | K300: 0 | L300: 0 | M300: 0 | N300: 0
A301: Threshing | B301: 1 basket for corn bought 3pence Total, 1 shilling 4pence | C301: 0.06 | D301: 0 | E301: 1 | F301: 3 | H301: 0 | I301: 0 | J301: 0 | K301: 0 | L301: 0 | M301: 0 | N301: 0
A302: Hay harvest (Autumpn') | B302: in mowing the meadow of Bitterne according to custom 1 shilling. | C302: 0.05 | D302: 0 | E302: 1 | F302: 0 | H302: 0 | I302: 0 | J302: 0 | K302: 0 | L302: 0 | M302: 0 | N302: 0
A303: Hay harvest (Autumpn') | B303: tossing the hay of the same 1 shilling 6pence. | C303: 0.08 | D303: 0 | E303: 1 | F303: 6 | H303: 0 | I303: 0 | J303: 0 | K303: 0 | L303: 0 | M303: 0 | N303: 0
A304: Hay harvest (Autumpn') | B304: mowing the new meadow 2 shilling 6pence. | C304: 0.12 | D304: 0 | E304: 2 | F304: 6 | H304: 0 | I304: 0 | J304: 0 | K304: 0 | L304: 0 | M304: 0 | N304: 0
A305: Hay harvest (Autumpn') | B305: tossing the hay 4pence. | C305: 0.02 | D305: 0 | E305: 0 | F305: 4 | H305: 0 | I305: 0 | J305: 0 | K305: 0 | L305: 0 | M305: 0 | N305: 0
A306: Hay harvest (Autumpn') | B306: mowing Ballesmed 1 shilling 6pence. | C306: 0.08 | D306: 0 | E306: 1 | F306: 6 | H306: 0 | I306: 0 | J306: 0 | K306: 0 | L306: 0 | M306: 0 | N306: 0
A307: Hay harvest (Autumpn') | B307: tossing the hay 2pence. | C307: 0.01 | D307: 0 | E307: 0 | F307: 2 | H307: 0 | I307: 0 | J307: 0 | K307: 0 | L307: 0 | M307: 0 | N307: 0
A308: Hay harvest (Autumpn') | B308: mowing the meadow of la Mere 1 shilling Total, 8 shilling | C308: 0.05 | D308: 0 | E308: 1 | F308: 0 | H308: 0 | I308: 0 | J308: 0 | K308: 0 | L308: 0 | M308: 0 | N308: 0
A309: Corn harvest (Autumpn') | B309: In bread bought for 347 men at two harvest boon-works 14 shilling 5.5pence, and each has bread worth .5pence. | C309: 0.72 | D309: 0 | E309: 14 | F309: 5.5 | H309: 0 | I309: 0 | J309: 0 | K309: 0 | L309: 0 | M309: 0 | N309: 0
A310: Corn harvest (Autumpn') | B310: 1,041 herrings bought for the same 6 shilling 1pence, at 8pence a hundred, and each has 3 herrings. | C310: 0.3 | D310: 0 | E310: 6 | F310: 1 | H310: 0 | I310: 0 | J310: 0 | K310: 0 | L310: 0 | M310: 0 | N310: 0
... A316: Corn harvest (Autumpn') | B316: . | C316: 0 | D316: 0 | E316: 0 | F316: 0 | H316: 0 | I316: 0 | J316: 0 | K316: 0 | L316: 0 | M316: 0 | N316: 0
A317: Corn harvest (Autumpn') | B317: mowing 14 acres of vetches 4 shilling 8pence, at 4pence an acre. | C317: 0.23 | D317: 0 | E317: 4 | F317: 8 | G317: vetches | H317: 0 | I317: 0 | J317: 0 | K317: 0 | L317: 0 | M317: 0 | N317: 0
A318: Corn harvest (Autumpn') | B318: Total, £2 11 shilling 0.5pence | C318: 2.55 | D318: 2 | E318: 11 | F318: 0.5 | H318: 0 | I318: 0 | J318: 0 | K318: 0 | L318: 0 | M318: 0 | N318: 0
A319: Cost of mills | B319: In iron bought for mending and lengthening the spindle of the mill outside the gate 5pence. | C319: 0.02 | D319: 0 | E319: 0 | F319: 5 | H319: 0 | I319: 0 | J319: 0 | K319: 0 | L319: 0 | M319: 0 | N319: 0
A320: Cost of mills | B320: steel bought for the bills of both mills 5pence. | C320: 0.02 | D320: 0 | E320: 0 | F320: 5 | H320: 0 | I320: 0 | J320: 0 | K320: 0 | L320: 0 | M320: 0 | N320: 0
A321: Cost of mills | B321: making anew the outer wheel and trough of the east mill 2 shilling 6pence. | C321: 0.12 | D321: 0 | E321: 2 | F321: 6 | H321: 0 | I321: 0 | J321: 0 | K321: 0 | L321: 0 | M321: 0 | N321: 0
A322: Cost of mills | B322: timber sawn for the same 2 shilling 6pence. | C322: 0.12 | D322: 0 | E322: 2 | F322: 6 | H322: 0 | I322: 0 | J322: 0 | K322: 0 | L322: 0 | M322: 0 | N322: 0
A323: Cost of mills | B323: nails bought for the same 8.5pence. | C323: 0.04 | D323: 0 | E323: 0 | F323: 8.5 | H323: 0 | I323: 0 | J323: 0 | K323: 0 | L323: 0 | M323: 0 | N323: 0
A324: Cost of mills | B324: mending the sluice beside the east mill with the digging of earth and carrying of turf for the same and making stakes for the same 3 shilling 4pence Total, 9 shilling 9.5pence | C324: 0.17 | D324: 0 | E324: 3 | F324: 4 | H324: 0 | I324: 0 | J324: 0 | K324: 0 | L324: 0 | M324: 0 | N324: 0
A325: Expenses of the steward | B325: In expenses of the steward for his visits at 2 tourns by 2 tallies £1 2 shilling l1pence. | C325: 1.1 | D325: 1 | E325: 2 | F325: 0 | H325: 0 | I325: 0 | J325: 0 | K325: 0 | L325: 0 | M325: 0 | N325: 0
A326: Expenses of the steward | B326: expenses of Roger, bailiff from Michaelmas until Christmas, £1 12 shilling 1pence. | C326: 1.6 | D326: 1 | E326: 12 | F326: 1 | H326: 0 | I326: 0 | J326: 0 | K326: 0 | L326: 0 | M326: 0 | N326: 0
A327: Expenses of the steward | B327: fur bought for the same bailiff 3 shilling. | C327: 0.15 | D327: 0 | E327: 3 | F327: 0 | H327: 0 | I327: 0 | J327: 0 | K327: 0 | L327: 0 | M327: 0 | N327: 0
A328: Expenses of the steward | B328: expenses of Robert, bailiff and clerk, for his visits from Christmas until the following Michaelmas £2.. | C328: 2 | D328: 2 | E328: 0 | F328: 0 | H328: 0 | I328: 0 | J328: 0 | K328: 0 | L328: 0 | M328: 0 | N328: 0
A329: Expenses of the steward | B329: 1 fur bought for the summer livery of Robert the bailiff 3 shilling Total, £5 1 shilling | C329: 5.05 | D329: 5 | E329: 1 | F329: 0 | H329: 0 | I329: 0 | J329: 0 | K329: 0 | L329: 0 | M329: 0 | N329: 0
... A350: Wheat | B350: {yield: three-fold plus 5 quarters 1.5 bushels} | C350: 0 | D350: 0 | E350: 0 | F350: 0 | H350: 5 | I350: 1.5 | J350: 5.1875 | K350: 5.1875 | L350: 0 | M350: 5 | N350: 1.5
...
