Workbook

Sheet Bishopstone Overview
A1: BISHOPSTONE | B1: £ | C1: s | D1: d | G1: Total in £ | H1: Error
A3: CASH ACCOUNT
A4: RECEIPTS
A5: Arrears | G5: ='Bishopstone Receipts'!F5 -> 10.934375
A6: Rents of assize | G6: ='Bishopstone Receipts'!F14 -> 12.275
A7: Quittances | G7: ='Bishopstone Receipts'!F22 -> 0.7625
A8: Defaults of rent | G8: ='Bishopstone Receipts'!F27 -> 0.025
A9: Annual reconizances | G9: ='Bishopstone Receipts'!F36 -> 0.075
A10: Rents remaining | G10: ='Bishopstone Receipts'!F29 -> 11.4875
A11: Issues of the Manor | G11: ='Bishopstone Receipts'!F65 -> 14.485417
A12: Sale of corn | G12: ='Bishopstone Receipts'!F77 -> 36.342708
A13: Entry and marriage fines | G13: ='Bishopstone Receipts'!F89 -> 2.0166667
A14: Pleas & Perquisites | G14: ='Bishopstone Receipts'!F96 -> 2.3
A15: Sum of the above (incl. arrears) | G15: =G5+G9+G10+G11+G12+G13+G14 -> 77.641667
A16: Total recorded in the accounts excl. arrears | G16: ='Bishopstone Receipts'!F100 -> 66.707292
A17: Total recorded in the accounts incl. arrears | G17: n/a
A20: EXPENSES
A21: Cost of ploughs | G21: ='Bishopstone Expenses'!F13 -> 1.7583333
A22: Purchase of corn
A23: Cost of carts and wagons | G23: ='Bishopstone Expenses'!F22 -> 0.085416667
A24: Cost of dairy | G24: ='Bishopstone Expenses'!F32 -> 0.25833333
A25: Purchase of stock
A26: Sheepcote | G26: ='Bishopstone Expenses'!F42 -> 1.2604167
A27: Cost of buildings | G27: ='Bishopstone Expenses'!F51 -> 0.066666667
A28: Threshing | G28: ='Bishopstone Expenses'!F62 -> 1.7979167
A29: Expenses of the harvest | G29: ='Bishopstone Expenses'!F70 -> 0.61041667
A30: Stewards expenses | G30: =
A31: Sum of the above | G31: =SUM(G21:G30) -> 5.8375
A32: Total of all expenses | G32: ='Bishopstone Expenses'!F80 -> 7.8395833 | H32: =G31-G32 -> -2.0020833
A33: Total Demesne fixed investment | G33: ='Bishopstone Expenses'!F85 -> 2.7208333
A35: Owed by the reeve | G35: ='Bishopstone Expenses'!F82 -> 58.867708
A36: From accounts
A38: Cash deliveries | G38: ='Bishopstone Expenses'!F83 -> 47.4
A39: Sum of the above | B39: =SUM(B38:B38) -> 0 | C39: =SUM(C38:C38) -> 0 | D39: =SUM(D38:D38) -> 0 | E39: =SUM(E38:E38) -> 0 | G39: =SUM(G38:G38) -> 47.4
A40: Total of all allowances and cash deliveries in accounts | B40: n/a
A42: Net amount owed | G42: ='Bishopstone Expenses'!F84 -> 11.467708
A43: Net amount owed in accounts | H43: =G42-G43 -> 11.467708
A45: GRANGE ACCOUNT | B45: Net Production
A46: Grange | B46: qrs | C46: bus | F46: Value of total gross production in £ | G46: Value of total net production in £
A47: Wheat | B47: ='Issues of the Grange'!J18 -> 49.25 | F47: ='Issues of the Grange'!P5 -> 17.867132 | G47: ='Issues of the Grange'!M18 -> 12.39375
A48: Curall | B48: ='Issues of the Grange'!J19 -> 7 | F48: ='Issues of the Grange'!P6 -> 1.0760417 | G48: ='Issues of the Grange'!M19 -> 0.9719086
A49: Barley | B49: ='Issues of the Grange'!J20 -> 75.25 | F49: ='Issues of the Grange'!P7 -> 24.066583 | G49: ='Issues of the Grange'!M20 -> 15.029132
A50: Oats | B50: ='Issues of the Grange'!J21 -> 34.875 | F50: ='Issues of the Grange'!P8 -> 8.0166667 | G50: ='Issues of the Grange'!M21 -> 4.65
A51: Peas | B51: ='Issues of the Grange'!J22 -> 17.5 | F51: ='Issues of the Grange'!P9 -> 3.6458333 | G51: ='Issues of the Grange'!M22 -> 2.9166667
A52: Vetches | B52: ='Issues of the Grange'!J23 -> 6.5 | F52: ='Issues of the Grange'!P10 -> 0 | G52: ='Issues of the Grange'!M23 -> 0
A53: Total value of gross production (sum of the above) | F53: =SUM(F47:F52) -> 54.672257
A54: Total value of net production | F54: =SUM(G47:G52) -> 35.961457
A55: Value of sales | F55: =SUM('Issues of the Grange'!N18:N23) -> 35.390625
A57: MILL ACCOUNT | B57: n/a
A58: Issues of the mill | B58: qrs | C58: bus | G58: £
A59: Wheat
A60: Oatmeal
A61: 1st grade malt
A62: 2nd grade malt
A63: Maslin
A64: Total value of production (sum of the above)
A65: Value of sales | G65: n/a
A67: STOCK ACCOUNT
A68: Livestock | B68: Inherited stock | C68: End-period stock | D68: Stockbuilding | F68: Sales in (£) | G68: Value of production (£) at sales prices
A69: Cart-horses | B69: =IFERROR(INDEX(Stock!$A$3:$T$91,MATCH('Bishopstone Overview'!$A69,Stock!$A$3:$A$91,0),MATCH('Bishopstone Overview'!B$68,Stock!$A$3:$T$3,0)),0) -> 0 | C69: =IFERROR(INDEX(Stock!$A$3:$T$91,MATCH('Bishopstone Overview'!$A69,Stock!$A$3:$A$91,0),MATCH('Bishopstone Overview'!C$68,Stock!$A$3:$T$3,0)),0) -> 0 | D69: =C69-B69 -> 0 | F69: =IFERROR(INDEX(Stock!$A$3:$T$91,MATCH('Bishopstone Overview'!$A69,Stock!$A$3:$A$91,0),MATCH('Bishopstone Overview'!F$68,Stock!$A$3:$T$3,0)),0) | G69: =IFERROR(INDEX(Stock!$A$3:$T$91,MATCH('Bishopstone Overview'!$A69,Stock!$A$3:$A$91,0),MATCH('Bishopstone Overview'!G$68,Stock!$A$3:$T$3,0)),0)
A70: Mares | B70: =IFERROR(INDEX(Stock!$A$3:$T$91,MATCH('Bishopstone Overview'!$A70,Stock!$A$3:$A$91,0),MATCH('Bishopstone Overview'!B$68,Stock!$A$3:$T$3,0)),0) -> 0 | C70: =IFERROR(INDEX(Stock!$A$3:$T$91,MATCH('Bishopstone Overview'!$A70,Stock!$A$3:$A$91,0),MATCH('Bishopstone Overview'!C$68,Stock!$A$3:$T$3,0)),0) -> 0 | D70: =C70-B70 -> 0 | F70: =IFERROR(INDEX(Stock!$A$3:$T$91,MATCH('Bishopstone Overview'!$A70,Stock!$A$3:$A$91,0),MATCH('Bishopstone Overview'!F$68,Stock!$A$3:$T$3,0)),0) | G70: =IFERROR(INDEX(Stock!$A$3:$T$91,MATCH('Bishopstone Overview'!$A70,Stock!$A$3:$A$91,0),MATCH('Bishopstone Overview'!G$68,Stock!$A$3:$T$3,0)),0)
A71: Plough horses | B71: =IFERROR(INDEX(Stock!$A$3:$T$91,MATCH('Bishopstone Overview'!$A71,Stock!$A$3:$A$91,0),MATCH('Bishopstone Overview'!B$68,Stock!$A$3:$T$3,0)),0) -> 1 | C71: =IFERROR(INDEX(Stock!$A$3:$T$91,MATCH('Bishopstone Overview'!$A71,Stock!$A$3:$A$91,0),MATCH('Bishopstone Overview'!C$68,Stock!$A$3:$T$3,0)),0) -> 1 | D71: =C71-B71 -> 0 | F71: =IFERROR(INDEX(Stock!$A$3:$T$91,MATCH('Bishopstone Overview'!$A71,Stock!$A$3:$A$91,0),MATCH('Bishopstone Overview'!F$68,Stock!$A$3:$T$3,0)),0) | G71: =IFERROR(INDEX(Stock!$A$3:$T$91,MATCH('Bishopstone Overview'!$A71,Stock!$A$3:$A$91,0),MATCH('Bishopstone Overview'!G$68,Stock!$A$3:$T$3,0)),0)
A72: Colts (2 years) | B72: =IFERROR(INDEX(Stock!$A$3:$T$91,MATCH('Bishopstone Overview'!$A72,Stock!$A$3:$A$91,0),MATCH('Bishopstone Overview'!B$68,Stock!$A$3:$T$3,0)),0) -> 0 | C72: =IFERROR(INDEX(Stock!$A$3:$T$91,MATCH('Bishopstone Overview'!$A72,Stock!$A$3:$A$91,0),MATCH('Bishopstone Overview'!C$68,Stock!$A$3:$T$3,0)),0) -> 0 | D72: =C72-B72 -> 0 | F72: =IFERROR(INDEX(Stock!$A$3:$T$91,MATCH('Bishopstone Overview'!$A72,Stock!$A$3:$A$91,0),MATCH('Bishopstone Overview'!F$68,Stock!$A$3:$T$3,0)),0) | G72: =IFERROR(INDEX(Stock!$A$3:$T$91,MATCH('Bishopstone Overview'!$A72,Stock!$A$3:$A$91,0),MATCH('Bishopstone Overview'!G$68,Stock!$A$3:$T$3,0)),0)
A73: Colts (2 years) | B73: =IFERROR(INDEX(Stock!$A$3:$T$91,MATCH('Bishopstone Overview'!$A73,Stock!$A$3:$A$91,0),MATCH('Bishopstone Overview'!B$68,Stock!$A$3:$T$3,0)),0) -> 0 | C73: =IFERROR(INDEX(Stock!$A$3:$T$91,MATCH('Bishopstone Overview'!$A73,Stock!$A$3:$A$91,0),MATCH('Bishopstone Overview'!C$68,Stock!$A$3:$T$3,0)),0) -> 0 | D73: =C73-B73 -> 0 | F73: =IFERROR(INDEX(Stock!$A$3:$T$91,MATCH('Bishopstone Overview'!$A73,Stock!$A$3:$A$91,0),MATCH('Bishopstone Overview'!F$68,Stock!$A$3:$T$3,0)),0) | G73: =IFERROR(INDEX(Stock!$A$3:$T$91,MATCH('Bishopstone Overview'!$A73,Stock!$A$3:$A$91,0),MATCH('Bishopstone Overview'!G$68,Stock!$A$3:$T$3,0)),0)
A74: Colts (1 year) | B74: =IFERROR(INDEX(Stock!$A$3:$T$91,MATCH('Bishopstone Overview'!$A74,Stock!$A$3:$A$91,0),MATCH('Bishopstone Overview'!B$68,Stock!$A$3:$T$3,0)),0) -> 0 | C74: =IFERROR(INDEX(Stock!$A$3:$T$91,MATCH('Bishopstone Overview'!$A74,Stock!$A$3:$A$91,0),MATCH('Bishopstone Overview'!C$68,Stock!$A$3:$T$3,0)),0) -> 0 | D74: =C74-B74 -> 0 | F74: =IFERROR(INDEX(Stock!$A$3:$T$91,MATCH('Bishopstone Overview'!$A74,Stock!$A$3:$A$91,0),MATCH('Bishopstone Overview'!F$68,Stock!$A$3:$T$3,0)),0) | G74: =IFERROR(INDEX(Stock!$A$3:$T$91,MATCH('Bishopstone Overview'!$A74,Stock!$A$3:$A$91,0),MATCH('Bishopstone Overview'!G$68,Stock!$A$3:$T$3,0)),0)
A75: Foals | B75: =IFERROR(INDEX(Stock!$A$3:$T$91,MATCH('Bishopstone Overview'!$A75,Stock!$A$3:$A$91,0),MATCH('Bishopstone Overview'!B$68,Stock!$A$3:$T$3,0)),0) -> 0 | C75: =IFERROR(INDEX(Stock!$A$3:$T$91,MATCH('Bishopstone Overview'!$A75,Stock!$A$3:$A$91,0),MATCH('Bishopstone Overview'!C$68,Stock!$A$3:$T$3,0)),0) -> 0 | D75: =C75-B75 -> 0 | F75: =IFERROR(INDEX(Stock!$A$3:$T$91,MATCH('Bishopstone Overview'!$A75,Stock!$A$3:$A$91,0),MATCH('Bishopstone Overview'!F$68,Stock!$A$3:$T$3,0)),0) | G75: =IFERROR(INDEX(Stock!$A$3:$T$91,MATCH('Bishopstone Overview'!$A75,Stock!$A$3:$A$91,0),MATCH('Bishopstone Overview'!G$68,Stock!$A$3:$T$3,0)),0)
A76: Oxen | B76: =IFERROR(INDEX(Stock!$A$3:$T$91,MATCH('Bishopstone Overview'!$A76,Stock!$A$3:$A$91,0),MATCH('Bishopstone Overview'!B$68,Stock!$A$3:$T$3,0)),0) -> 16 | C76: =IFERROR(INDEX(Stock!$A$3:$T$91,MATCH('Bishopstone Overview'!$A76,Stock!$A$3:$A$91,0),MATCH('Bishopstone Overview'!C$68,Stock!$A$3:$T$3,0)),0) -> 18 | D76: =C76-B76 -> 2 | F76: =IFERROR(INDEX(Stock!$A$3:$T$91,MATCH('Bishopstone Overview'!$A76,Stock!$A$3:$A$91,0),MATCH('Bishopstone Overview'!F$68,Stock!$A$3:$T$3,0)),0) -> 0.275 | G76: =IFERROR(INDEX(Stock!$A$3:$T$91,MATCH('Bishopstone Overview'!$A76,Stock!$A$3:$A$91,0),MATCH('Bishopstone Overview'!G$68,Stock!$A$3:$T$3,0)),0) -> 0.275
A77: Bulls | B77: =IFERROR(INDEX(Stock!$A$3:$T$91,MATCH('Bishopstone Overview'!$A77,Stock!$A$3:$A$91,0),MATCH('Bishopstone Overview'!B$68,Stock!$A$3:$T$3,0)),0) -> 1 | C77: =IFERROR(INDEX(Stock!$A$3:$T$91,MATCH('Bishopstone Overview'!$A77,Stock!$A$3:$A$91,0),MATCH('Bishopstone Overview'!C$68,Stock!$A$3:$T$3,0)),0) -> 1 | D77: =C77-B77 -> 0 | F77: =IFERROR(INDEX(Stock!$A$3:$T$91,MATCH('Bishopstone Overview'!$A77,Stock!$A$3:$A$91,0),MATCH('Bishopstone Overview'!F$68,Stock!$A$3:$T$3,0)),0) | G77: =IFERROR(INDEX(Stock!$A$3:$T$91,MATCH('Bishopstone Overview'!$A77,Stock!$A$3:$A$91,0),MATCH('Bishopstone Overview'!G$68,Stock!$A$3:$T$3,0)),0)
A78: Cows | B78: =IFERROR(INDEX(Stock!$A$3:$T$91,MATCH('Bishopstone Overview'!$A78,Stock!$A$3:$A$91,0),MATCH('Bishopstone Overview'!B$68,Stock!$A$3:$T$3,0)),0) -> 11 | C78: =IFERROR(INDEX(Stock!$A$3:$T$91,MATCH('Bishopstone Overview'!$A78,Stock!$A$3:$A$91,0),MATCH('Bishopstone Overview'!C$68,Stock!$A$3:$T$3,0)),0) -> 11 | D78: =C78-B78 -> 0 | F78: =IFERROR(INDEX(Stock!$A$3:$T$91,MATCH('Bishopstone Overview'!$A78,Stock!$A$3:$A$91,0),MATCH('Bishopstone Overview'!F$68,Stock!$A$3:$T$3,0)),0) | G78: =IFERROR(INDEX(Stock!$A$3:$T$91,MATCH('Bishopstone Overview'!$A78,Stock!$A$3:$A$91,0),MATCH('Bishopstone Overview'!G$68,Stock!$A$3:$T$3,0)),0)
A79: Steers | B79: =IFERROR(INDEX(Stock!$A$3:$T$91,MATCH('Bishopstone Overview'!$A79,Stock!$A$3:$A$91,0),MATCH('Bishopstone Overview'!B$68,Stock!$A$3:$T$3,0)),0) -> 4 | C79: =IFERROR(INDEX(Stock!$A$3:$T$91,MATCH('Bishopstone Overview'!$A79,Stock!$A$3:$A$91,0),MATCH('Bishopstone Overview'!C$68,Stock!$A$3:$T$3,0)),0) -> 0 | D79: =C79-B79 -> -4 | F79: =IFERROR(INDEX(Stock!$A$3:$T$91,MATCH('Bishopstone Overview'!$A79,Stock!$A$3:$A$91,0),MATCH('Bishopstone Overview'!F$68,Stock!$A$3:$T$3,0)),0) | G79: =IFERROR(INDEX(Stock!$A$3:$T$91,MATCH('Bishopstone Overview'!$A79,Stock!$A$3:$A$91,0),MATCH('Bishopstone Overview'!G$68,Stock!$A$3:$T$3,0)),0)
A80: Bullocks | B80: =IFERROR(INDEX(Stock!$A$3:$T$91,MATCH('Bishopstone Overview'!$A80,Stock!$A$3:$A$91,0),MATCH('Bishopstone Overview'!B$68,Stock!$A$3:$T$3,0)),0) -> 2 | C80: =IFERROR(INDEX(Stock!$A$3:$T$91,MATCH('Bishopstone Overview'!$A80,Stock!$A$3:$A$91,0),MATCH('Bishopstone Overview'!C$68,Stock!$A$3:$T$3,0)),0) -> 3 | D80: =C80-B80 -> 1 | F80: =IFERROR(INDEX(Stock!$A$3:$T$91,MATCH('Bishopstone Overview'!$A80,Stock!$A$3:$A$91,0),MATCH('Bishopstone Overview'!F$68,Stock!$A$3:$T$3,0)),0) | G80: =IFERROR(INDEX(Stock!$A$3:$T$91,MATCH('Bishopstone Overview'!$A80,Stock!$A$3:$A$91,0),MATCH('Bishopstone Overview'!G$68,Stock!$A$3:$T$3,0)),0)
... A94: Peacocks | B94: =IFERROR(INDEX(Stock!$A$3:$T$91,MATCH('Bishopstone Overview'!$A94,Stock!$A$3:$A$91,0),MATCH('Bishopstone Overview'!B$68,Stock!$A$3:$T$3,0)),0) -> 0 | C94: =IFERROR(INDEX(Stock!$A$3:$T$91,MATCH('Bishopstone Overview'!$A94,Stock!$A$3:$A$91,0),MATCH('Bishopstone Overview'!C$68,Stock!$A$3:$T$3,0)),0) -> 0 | D94: =C94-B94 -> 0 | F94: =IFERROR(INDEX(Stock!$A$3:$T$91,MATCH('Bishopstone Overview'!$A94,Stock!$A$3:$A$91,0),MATCH('Bishopstone Overview'!F$68,Stock!$A$3:$T$3,0)),0) | G94: =IFERROR(INDEX(Stock!$A$3:$T$91,MATCH('Bishopstone Overview'!$A94,Stock!$A$3:$A$91,0),MATCH('Bishopstone Overview'!G$68,Stock!$A$3:$T$3,0)),0)
A95: Total | G95: =SUM(G69:G94) -> 7.0709286
A96: Value of sales | G96: =SUM(F69:F94) -> 4.6625
A98: Wool | B98: Inherited stock | C98: End-period stock | D98: Stockbuilding | F98: Sales in (£) | G98: Value of production (£) at sales prices
A99: Fleeces | B99: =IFERROR(INDEX(Stock!$A$3:$T$91,MATCH('Bishopstone Overview'!$A99,Stock!$A$3:$A$91,0),MATCH('Bishopstone Overview'!B$68,Stock!$A$3:$T$3,0)),0) -> 0 | C99: =IFERROR(INDEX(Stock!$A$3:$T$91,MATCH('Bishopstone Overview'!$A99,Stock!$A$3:$A$91,0),MATCH('Bishopstone Overview'!C$68,Stock!$A$3:$T$3,0)),0) -> 0 | D99: =C99-B99 -> 0 | F99: =IFERROR(INDEX(Stock!$A$3:$T$91,MATCH('Bishopstone Overview'!$A99,Stock!$A$3:$A$91,0),MATCH('Bishopstone Overview'!F$68,Stock!$A$3:$T$3,0)),0) -> 0 | G99: =IFERROR(INDEX(Stock!$A$3:$T$91,MATCH('Bishopstone Overview'!$A99,Stock!$A$3:$A$91,0),MATCH('Bishopstone Overview'!G$68,Stock!$A$3:$T$3,0)),0) -> 13.68
A100: Coarse wool | B100: =IFERROR(INDEX(Stock!$A$3:$T$91,MATCH('Bishopstone Overview'!$A100,Stock!$A$3:$A$91,0),MATCH('Bishopstone Overview'!B$68,Stock!$A$3:$T$3,0)),0) -> 0 | C100: =IFERROR(INDEX(Stock!$A$3:$T$91,MATCH('Bishopstone Overview'!$A100,Stock!$A$3:$A$91,0),MATCH('Bishopstone Overview'!C$68,Stock!$A$3:$T$3,0)),0) -> 0 | D100: =C100-B100 -> 0 | F100: =IFERROR(INDEX(Stock!$A$3:$T$91,MATCH('Bishopstone Overview'!$A100,Stock!$A$3:$A$91,0),MATCH('Bishopstone Overview'!F$68,Stock!$A$3:$T$3,0)),0) | G100: =IFERROR(INDEX(Stock!$A$3:$T$91,MATCH('Bishopstone Overview'!$A100,Stock!$A$3:$A$91,0),MATCH('Bishopstone Overview'!G$68,Stock!$A$3:$T$3,0)),0)
A101: Lamb's wool | B101: =IFERROR(INDEX(Stock!$A$3:$T$91,MATCH('Bishopstone Overview'!$A101,Stock!$A$3:$A$91,0),MATCH('Bishopstone Overview'!B$68,Stock!$A$3:$T$3,0)),0) -> 0 | C101: =IFERROR(INDEX(Stock!$A$3:$T$91,MATCH('Bishopstone Overview'!$A101,Stock!$A$3:$A$91,0),MATCH('Bishopstone Overview'!C$68,Stock!$A$3:$T$3,0)),0) -> 0 | D101: =C101-B101 -> 0 | F101: =IFERROR(INDEX(Stock!$A$3:$T$91,MATCH('Bishopstone Overview'!$A101,Stock!$A$3:$A$91,0),MATCH('Bishopstone Overview'!F$68,Stock!$A$3:$T$3,0)),0) -> 0 | G101: =IFERROR(INDEX(Stock!$A$3:$T$91,MATCH('Bishopstone Overview'!$A101,Stock!$A$3:$A$91,0),MATCH('Bishopstone Overview'!G$68,Stock!$A$3:$T$3,0)),0) -> 2.37
A102: Wool locks | B102: =IFERROR(INDEX(Stock!$A$3:$T$91,MATCH('Bishopstone Overview'!$A102,Stock!$A$3:$A$91,0),MATCH('Bishopstone Overview'!B$68,Stock!$A$3:$T$3,0)),0) -> 0 | C102: =IFERROR(INDEX(Stock!$A$3:$T$91,MATCH('Bishopstone Overview'!$A102,Stock!$A$3:$A$91,0),MATCH('Bishopstone Overview'!C$68,Stock!$A$3:$T$3,0)),0) -> 0 | D102: =C102-B102 -> 0 | F102: =IFERROR(INDEX(Stock!$A$3:$T$91,MATCH('Bishopstone Overview'!$A102,Stock!$A$3:$A$91,0),MATCH('Bishopstone Overview'!F$68,Stock!$A$3:$T$3,0)),0) -> 0.53333333 | G102: =IFERROR(INDEX(Stock!$A$3:$T$91,MATCH('Bishopstone Overview'!$A102,Stock!$A$3:$A$91,0),MATCH('Bishopstone Overview'!G$68,Stock!$A$3:$T$3,0)),0) -> 0.53333333
A103: Wool sold at shearing | B103: =IFERROR(INDEX(Stock!$A$3:$T$91,MATCH('Bishopstone Overview'!$A103,Stock!$A$3:$A$91,0),MATCH('Bishopstone Overview'!B$68,Stock!$A$3:$T$3,0)),0) -> 0 | C103: =IFERROR(INDEX(Stock!$A$3:$T$91,MATCH('Bishopstone Overview'!$A103,Stock!$A$3:$A$91,0),MATCH('Bishopstone Overview'!C$68,Stock!$A$3:$T$3,0)),0) -> 0 | D103: =C103-B103 -> 0 | F103: =IFERROR(INDEX(Stock!$A$3:$T$91,MATCH('Bishopstone Overview'!$A103,Stock!$A$3:$A$91,0),MATCH('Bishopstone Overview'!F$68,Stock!$A$3:$T$3,0)),0) | G103: =IFERROR(INDEX(Stock!$A$3:$T$91,MATCH('Bishopstone Overview'!$A103,Stock!$A$3:$A$91,0),MATCH('Bishopstone Overview'!G$68,Stock!$A$3:$T$3,0)),0)
A104: Total value of production (sum of the above) | G104: =SUM(G99:G103) -> 16.583333
A105: Value of sales | G105: =SUM(F99:F103) -> 0.53333333
A107: Hides | B107: Inherited stock | C107: End-period stock | D107: Stockbuilding | F107: Sales in (£) | G107: Value of production (£) at sales prices
A108: Ox hides | B108: =IFERROR(INDEX(Stock!$A$3:$T$91,MATCH('Bishopstone Overview'!$A108,Stock!$A$3:$A$91,0),MATCH('Bishopstone Overview'!B$68,Stock!$A$3:$T$3,0)),0) -> 0 | C108: =IFERROR(INDEX(Stock!$A$3:$T$91,MATCH('Bishopstone Overview'!$A108,Stock!$A$3:$A$91,0),MATCH('Bishopstone Overview'!C$68,Stock!$A$3:$T$3,0)),0) -> 0 | D108: =C108-B108 -> 0 | F108: =IFERROR(INDEX(Stock!$A$3:$T$91,MATCH('Bishopstone Overview'!$A108,Stock!$A$3:$A$91,0),MATCH('Bishopstone Overview'!F$68,Stock!$A$3:$T$3,0)),0) | G108: =IFERROR(INDEX(Stock!$A$3:$T$91,MATCH('Bishopstone Overview'!$A108,Stock!$A$3:$A$91,0),MATCH('Bishopstone Overview'!G$68,Stock!$A$3:$T$3,0)),0)
A109: Cow hides | B109: =IFERROR(INDEX(Stock!$A$3:$T$91,MATCH('Bishopstone Overview'!$A109,Stock!$A$3:$A$91,0),MATCH('Bishopstone Overview'!B$68,Stock!$A$3:$T$3,0)),0) -> 0 | C109: =IFERROR(INDEX(Stock!$A$3:$T$91,MATCH('Bishopstone Overview'!$A109,Stock!$A$3:$A$91,0),MATCH('Bishopstone Overview'!C$68,Stock!$A$3:$T$3,0)),0) -> 0 | D109: =C109-B109 -> 0 | F109: =IFERROR(INDEX(Stock!$A$3:$T$91,MATCH('Bishopstone Overview'!$A109,Stock!$A$3:$A$91,0),MATCH('Bishopstone Overview'!F$68,Stock!$A$3:$T$3,0)),0) -> 0.091666667 | G109: =IFERROR(INDEX(Stock!$A$3:$T$91,MATCH('Bishopstone Overview'!$A109,Stock!$A$3:$A$91,0),MATCH('Bishopstone Overview'!G$68,Stock!$A$3:$T$3,0)),0) -> 0.091666667
A110: Bullock hides | B110: =IFERROR(INDEX(Stock!$A$3:$T$91,MATCH('Bishopstone Overview'!$A110,Stock!$A$3:$A$91,0),MATCH('Bishopstone Overview'!B$68,Stock!$A$3:$T$3,0)),0) -> 0 | C110: =IFERROR(INDEX(Stock!$A$3:$T$91,MATCH('Bishopstone Overview'!$A110,Stock!$A$3:$A$91,0),MATCH('Bishopstone Overview'!C$68,Stock!$A$3:$T$3,0)),0) -> 0 | D110: =C110-B110 -> 0 | F110: =IFERROR(INDEX(Stock!$A$3:$T$91,MATCH('Bishopstone Overview'!$A110,Stock!$A$3:$A$91,0),MATCH('Bishopstone Overview'!F$68,Stock!$A$3:$T$3,0)),0) -> 0.10416667 | G110: =IFERROR(INDEX(Stock!$A$3:$T$91,MATCH('Bishopstone Overview'!$A110,Stock!$A$3:$A$91,0),MATCH('Bishopstone Overview'!G$68,Stock!$A$3:$T$3,0)),0) -> 0.10416667
A111: Steer hides | B111: =IFERROR(INDEX(Stock!$A$3:$T$91,MATCH('Bishopstone Overview'!$A111,Stock!$A$3:$A$91,0),MATCH('Bishopstone Overview'!B$68,Stock!$A$3:$T$3,0)),0) -> 0 | C111: =IFERROR(INDEX(Stock!$A$3:$T$91,MATCH('Bishopstone Overview'!$A111,Stock!$A$3:$A$91,0),MATCH('Bishopstone Overview'!C$68,Stock!$A$3:$T$3,0)),0) -> 0 | D111: =C111-B111 -> 0 | F111: =IFERROR(INDEX(Stock!$A$3:$T$91,MATCH('Bishopstone Overview'!$A111,Stock!$A$3:$A$91,0),MATCH('Bishopstone Overview'!F$68,Stock!$A$3:$T$3,0)),0) | G111: =IFERROR(INDEX(Stock!$A$3:$T$91,MATCH('Bishopstone Overview'!$A111,Stock!$A$3:$A$91,0),MATCH('Bishopstone Overview'!G$68,Stock!$A$3:$T$3,0)),0)
A112: Yearling Calf hides | B112: =IFERROR(INDEX(Stock!$A$3:$T$91,MATCH('Bishopstone Overview'!$A112,Stock!$A$3:$A$91,0),MATCH('Bishopstone Overview'!B$68,Stock!$A$3:$T$3,0)),0) -> 0 | C112: =IFERROR(INDEX(Stock!$A$3:$T$91,MATCH('Bishopstone Overview'!$A112,Stock!$A$3:$A$91,0),MATCH('Bishopstone Overview'!C$68,Stock!$A$3:$T$3,0)),0) -> 0 | D112: =C112-B112 -> 0 | F112: =IFERROR(INDEX(Stock!$A$3:$T$91,MATCH('Bishopstone Overview'!$A112,Stock!$A$3:$A$91,0),MATCH('Bishopstone Overview'!F$68,Stock!$A$3:$T$3,0)),0) | G112: =IFERROR(INDEX(Stock!$A$3:$T$91,MATCH('Bishopstone Overview'!$A112,Stock!$A$3:$A$91,0),MATCH('Bishopstone Overview'!G$68,Stock!$A$3:$T$3,0)),0)
A113: Calf hides | B113: =IFERROR(INDEX(Stock!$A$3:$T$91,MATCH('Bishopstone Overview'!$A113,Stock!$A$3:$A$91,0),MATCH('Bishopstone Overview'!B$68,Stock!$A$3:$T$3,0)),0) -> 0 | C113: =IFERROR(INDEX(Stock!$A$3:$T$91,MATCH('Bishopstone Overview'!$A113,Stock!$A$3:$A$91,0),MATCH('Bishopstone Overview'!C$68,Stock!$A$3:$T$3,0)),0) -> 0 | D113: =C113-B113 -> 0 | F113: =IFERROR(INDEX(Stock!$A$3:$T$91,MATCH('Bishopstone Overview'!$A113,Stock!$A$3:$A$91,0),MATCH('Bishopstone Overview'!F$68,Stock!$A$3:$T$3,0)),0) | G113: =IFERROR(INDEX(Stock!$A$3:$T$91,MATCH('Bishopstone Overview'!$A113,Stock!$A$3:$A$91,0),MATCH('Bishopstone Overview'!G$68,Stock!$A$3:$T$3,0)),0)
A114: Pig hides | B114: =IFERROR(INDEX(Stock!$A$3:$T$91,MATCH('Bishopstone Overview'!$A114,Stock!$A$3:$A$91,0),MATCH('Bishopstone Overview'!B$68,Stock!$A$3:$T$3,0)),0) -> 0 | C114: =IFERROR(INDEX(Stock!$A$3:$T$91,MATCH('Bishopstone Overview'!$A114,Stock!$A$3:$A$91,0),MATCH('Bishopstone Overview'!C$68,Stock!$A$3:$T$3,0)),0) -> 0 | D114: =C114-B114 -> 0 | F114: =IFERROR(INDEX(Stock!$A$3:$T$91,MATCH('Bishopstone Overview'!$A114,Stock!$A$3:$A$91,0),MATCH('Bishopstone Overview'!F$68,Stock!$A$3:$T$3,0)),0) | G114: =IFERROR(INDEX(Stock!$A$3:$T$91,MATCH('Bishopstone Overview'!$A114,Stock!$A$3:$A$91,0),MATCH('Bishopstone Overview'!G$68,Stock!$A$3:$T$3,0)),0)
A115: Weather woolskins | B115: =IFERROR(INDEX(Stock!$A$3:$T$91,MATCH('Bishopstone Overview'!$A115,Stock!$A$3:$A$91,0),MATCH('Bishopstone Overview'!B$68,Stock!$A$3:$T$3,0)),0) -> 0 | C115: =IFERROR(INDEX(Stock!$A$3:$T$91,MATCH('Bishopstone Overview'!$A115,Stock!$A$3:$A$91,0),MATCH('Bishopstone Overview'!C$68,Stock!$A$3:$T$3,0)),0) -> 0 | D115: =C115-B115 -> 0 | F115: =IFERROR(INDEX(Stock!$A$3:$T$91,MATCH('Bishopstone Overview'!$A115,Stock!$A$3:$A$91,0),MATCH('Bishopstone Overview'!F$68,Stock!$A$3:$T$3,0)),0) | G115: =IFERROR(INDEX(Stock!$A$3:$T$91,MATCH('Bishopstone Overview'!$A115,Stock!$A$3:$A$91,0),MATCH('Bishopstone Overview'!G$68,Stock!$A$3:$T$3,0)),0)
A116: Ram woolskins | B116: =IFERROR(INDEX(Stock!$A$3:$T$91,MATCH('Bishopstone Overview'!$A116,Stock!$A$3:$A$91,0),MATCH('Bishopstone Overview'!B$68,Stock!$A$3:$T$3,0)),0) -> 0 | C116: =IFERROR(INDEX(Stock!$A$3:$T$91,MATCH('Bishopstone Overview'!$A116,Stock!$A$3:$A$91,0),MATCH('Bishopstone Overview'!C$68,Stock!$A$3:$T$3,0)),0) -> 0 | D116: =C116-B116 -> 0 | F116: =IFERROR(INDEX(Stock!$A$3:$T$91,MATCH('Bishopstone Overview'!$A116,Stock!$A$3:$A$91,0),MATCH('Bishopstone Overview'!F$68,Stock!$A$3:$T$3,0)),0) | G116: =IFERROR(INDEX(Stock!$A$3:$T$91,MATCH('Bishopstone Overview'!$A116,Stock!$A$3:$A$91,0),MATCH('Bishopstone Overview'!G$68,Stock!$A$3:$T$3,0)),0)
A117: Ewe woolskins | B117: =IFERROR(INDEX(Stock!$A$3:$T$91,MATCH('Bishopstone Overview'!$A117,Stock!$A$3:$A$91,0),MATCH('Bishopstone Overview'!B$68,Stock!$A$3:$T$3,0)),0) -> 0 | C117: =IFERROR(INDEX(Stock!$A$3:$T$91,MATCH('Bishopstone Overview'!$A117,Stock!$A$3:$A$91,0),MATCH('Bishopstone Overview'!C$68,Stock!$A$3:$T$3,0)),0) -> 0 | D117: =C117-B117 -> 0 | F117: =IFERROR(INDEX(Stock!$A$3:$T$91,MATCH('Bishopstone Overview'!$A117,Stock!$A$3:$A$91,0),MATCH('Bishopstone Overview'!F$68,Stock!$A$3:$T$3,0)),0) | G117: =IFERROR(INDEX(Stock!$A$3:$T$91,MATCH('Bishopstone Overview'!$A117,Stock!$A$3:$A$91,0),MATCH('Bishopstone Overview'!G$68,Stock!$A$3:$T$3,0)),0)
A118: Hogg woolskins | B118: =IFERROR(INDEX(Stock!$A$3:$T$91,MATCH('Bishopstone Overview'!$A118,Stock!$A$3:$A$91,0),MATCH('Bishopstone Overview'!B$68,Stock!$A$3:$T$3,0)),0) -> 0 | C118: =IFERROR(INDEX(Stock!$A$3:$T$91,MATCH('Bishopstone Overview'!$A118,Stock!$A$3:$A$91,0),MATCH('Bishopstone Overview'!C$68,Stock!$A$3:$T$3,0)),0) -> 0 | D118: =C118-B118 -> 0 | F118: =IFERROR(INDEX(Stock!$A$3:$T$91,MATCH('Bishopstone Overview'!$A118,Stock!$A$3:$A$91,0),MATCH('Bishopstone Overview'!F$68,Stock!$A$3:$T$3,0)),0) | G118: =IFERROR(INDEX(Stock!$A$3:$T$91,MATCH('Bishopstone Overview'!$A118,Stock!$A$3:$A$91,0),MATCH('Bishopstone Overview'!G$68,Stock!$A$3:$T$3,0)),0)
A119: Woolskins (total) | B119: =IFERROR(INDEX(Stock!$A$3:$T$91,MATCH('Bishopstone Overview'!$A119,Stock!$A$3:$A$91,0),MATCH('Bishopstone Overview'!B$68,Stock!$A$3:$T$3,0)),0) -> 0 | C119: =IFERROR(INDEX(Stock!$A$3:$T$91,MATCH('Bishopstone Overview'!$A119,Stock!$A$3:$A$91,0),MATCH('Bishopstone Overview'!C$68,Stock!$A$3:$T$3,0)),0) -> 0 | D119: =C119-B119 -> 0 | F119: =IFERROR(INDEX(Stock!$A$3:$T$91,MATCH('Bishopstone Overview'!$A119,Stock!$A$3:$A$91,0),MATCH('Bishopstone Overview'!F$68,Stock!$A$3:$T$3,0)),0) -> 0.34583333 | G119: =IFERROR(INDEX(Stock!$A$3:$T$91,MATCH('Bishopstone Overview'!$A119,Stock!$A$3:$A$91,0),MATCH('Bishopstone Overview'!G$68,Stock!$A$3:$T$3,0)),0) -> 0.34583333
... A127: Shorn skins | B127: =IFERROR(INDEX(Stock!$A$3:$T$91,MATCH('Bishopstone Overview'!$A127,Stock!$A$3:$A$91,0),MATCH('Bishopstone Overview'!B$68,Stock!$A$3:$T$3,0)),0) -> 0 | C127: =IFERROR(INDEX(Stock!$A$3:$T$91,MATCH('Bishopstone Overview'!$A127,Stock!$A$3:$A$91,0),MATCH('Bishopstone Overview'!C$68,Stock!$A$3:$T$3,0)),0) -> 0 | D127: =C127-B127 -> 0 | F127: =IFERROR(INDEX(Stock!$A$3:$T$91,MATCH('Bishopstone Overview'!$A127,Stock!$A$3:$A$91,0),MATCH('Bishopstone Overview'!F$68,Stock!$A$3:$T$3,0)),0) | G127: =IFERROR(INDEX(Stock!$A$3:$T$91,MATCH('Bishopstone Overview'!$A127,Stock!$A$3:$A$91,0),MATCH('Bishopstone Overview'!G$68,Stock!$A$3:$T$3,0)),0)
A128: Total value of production (sum of the above) | G128: =SUM(G108:G127) -> 0.58578431
A129: Value of sales | G129: =SUM(F108:F127) -> 0.58333333
A131: Poultry stock | B131: Inherited stock | C131: End-period stock | D131: Stockbuilding | F131: Sales in (£) | G131: Value of production (£) at sales prices
A132: Hens | B132: =IFERROR(INDEX(Stock!$A$3:$T$91,MATCH('Bishopstone Overview'!$A132,Stock!$A$3:$A$91,0),MATCH('Bishopstone Overview'!B$68,Stock!$A$3:$T$3,0)),0) -> 0 | C132: =IFERROR(INDEX(Stock!$A$3:$T$91,MATCH('Bishopstone Overview'!$A132,Stock!$A$3:$A$91,0),MATCH('Bishopstone Overview'!C$68,Stock!$A$3:$T$3,0)),0) -> 0 | D132: =C132-B132 -> 0 | F132: =IFERROR(INDEX(Stock!$A$3:$T$91,MATCH('Bishopstone Overview'!$A132,Stock!$A$3:$A$91,0),MATCH('Bishopstone Overview'!F$68,Stock!$A$3:$T$3,0)),0) -> 0.26666667 | G132: =IFERROR(INDEX(Stock!$A$3:$T$91,MATCH('Bishopstone Overview'!$A132,Stock!$A$3:$A$91,0),MATCH('Bishopstone Overview'!G$68,Stock!$A$3:$T$3,0)),0) -> 0.36666667
...

Sheet Bishopstone Receipts
A1: BISHOPSTONE RECEIPTS
B2: £ | C2: s | D2: d | F2: Total in £ | G2: Error | H2: Notes
A4: Arrears
A5: arrears from previous year | B5: 10 | C5: 18 | D5: 8.25 | F5: =B5+C5/20+D5/240 -> 10.934375
A6: of which delivered to treasurer of Wolvesey | B6: 10 | C6: 18 | D6: 8.25 | F6: =B6+C6/20+D6/240 -> 10.934375
A8: Rents of assize
A9: Christmas | B9: 3 | C9: 1 | D9: 8.5 | F9: =B9+C9/20+D9/240 -> 3.0854167
A10: Easter | B10: 3 | C10: 1 | D10: 8.5 | F10: =B10+C10/20+D10/240 -> 3.0854167
A11: Nativity of John the Baptist | B11: 3 | C11: 1 | D11: 8.5 | F11: =B11+C11/20+D11/240 -> 3.0854167
A12: Michaelmas | B12: 3 | D12: 4.5 | F12: =B12+C12/20+D12/240 -> 3.01875
A13: Total recorded in accounts | B13: 12 | C13: 5 | D13: 6 | F13: =B13+C13/20+D13/240 -> 12.275
A14: Total | B14: =SUM(B9:B12) -> 12 | C14: =SUM(C9:C12) -> 3 | D14: =SUM(D9:D12) -> 30 | F14: =B14+C14/20+D14/240 -> 12.275 | G14: =F14-F13 -> 0
A16: Quittances
A17: 1 reeve for year | C17: 4 | F17: =B17+C17/20+D17/240 -> 0.2
A18: 2 ploughmen for year | C18: 5 | F18: =B18+C18/20+D18/240 -> 0.25
A19: 1 hayward for 1/2 year | C19: 1 | D19: 3 | F19: =B19+C19/20+D19/240 -> 0.0625
A20: 2 shephers for the year | C20: 5 | F20: =B20+C20/20+D20/240 -> 0.25
A21: Total recorded in accounts | C21: 15 | D21: 3 | F21: =B21+C21/20+D21/240 -> 0.7625
A22: Total | B22: =SUM(B17:B20) -> 0 | C22: =SUM(C17:C20) -> 15 | D22: =SUM(D17:D20) -> 3 | F22: =B22+C22/20+D22/240 -> 0.7625 | G22: =F22-F21 -> 0
A24: Defaults of rent
A25: default of a plot formerly belonging to John Vicar' | D25: 6 | F25: =B25+C25/20+D25/240 -> 0.025
A26: Total recorded in accounts | D26: 6 | F26: =B26+C26/20+D26/240 -> 0.025
A27: Total | B27: =SUM(B25:B25) -> 0 | C27: =SUM(C25:C25) -> 0 | D27: =SUM(D25:D25) -> 6 | F27: =B27+C27/20+D27/240 -> 0.025 | G27: =F27-F26 -> 0
A29: Total of rents remaining | B29: 11 | C29: 9 | D29: 9 | F29: =B29+C29/20+D29/240 -> 11.4875
A31: Annual recognizances
A32: from John Pavel | D32: 6 | F32: =B32+C32/20+D32/240 -> 0.025
A33: from John Scherewynd | D33: 6 | F33: =B33+C33/20+D33/240 -> 0.025
A34: from Roger le Dregh to come to 2 tous and pay suit for his tithing | D34: 6 | F34: =B34+C34/20+D34/240 -> 0.025
A35: Total recorded in accounts | C35: 1 | D35: 6 | F35: =B35+C35/20+D35/240 -> 0.075
A36: Total | B36: =SUM(B32:B34) -> 0 | C36: =SUM(C32:C34) -> 0 | D36: =SUM(D32:D34) -> 18 | F36: =B36+C36/20+D36/240 -> 0.075 | G36: =F36-F35 -> 0
A38: Issues of the manor
A39: from panage of pigs | C39: 3 | D39: 11 | F39: =B39+C39/20+D39/240 -> 0.19583333
A40: from pannage of oxen (at Martinmas) | C40: 10 | F40: =B40+C40/20+D40/240 -> 0.5
A41: from panage of oxen (at Hockday) | C41: 10 | D41: 4 | F41: =B41+C41/20+D41/240 -> 0.51666667
A42: from panage of sheep | D42: 8.5 | F42: =B42+C42/20+D42/240 -> 0.035416667
A43: from hay sold | B43: 1 | C43: 4 | F43: =B43+C43/20+D43/240 -> 1.2
A44: from the residue of Peter's Pence | C44: 4 | D44: 8 | F44: =B44+C44/20+D44/240 -> 0.23333333
A45: from 1 feeble and sick ox sold | C45: 5 | D45: 6 | F45: =B45+C45/20+D45/240 -> 0.275
A46: from 7 late-born calves sold | C46: 7 | D46: 9 | F46: =B46+C46/20+D46/240 -> 0.3875
A47: from 21 kebb wethers and 40 ewes sold | B47: 2 | C47: 14 | D47: 1 | F47: =B47+C47/20+D47/240 -> 2.7041667
A48: from 6 old kebb wethers | C48: 3 | D48: 6 | F48: =B48+C48/20+D48/240 -> 0.175
A49: from 50 lambs sold after shearing | B49: 1 | C49: 2 | D49: 5 | F49: =B49+C49/20+D49/240 -> 1.1208333
A50: from the hide sold of 1 cow in murrain | C50: 1 | D50: 10 | F50: =B50+C50/20+D50/240 -> 0.091666667
A51: from the hides sold of 2 bullocks in murrain | C51: 2 | D51: 1 | F51: =B51+C51/20+D51/240 -> 0.10416667
A52: from the skins sold of 9 wethers 11 ewes and 6 hoggs in murrain | C52: 5 | D52: 3 | F52: =B52+C52/20+D52/240 -> 0.2625
A53: from the bare skins sold of 20 wethers and ewes after shearing | C53: 1 | D53: 8 | F53: =B53+C53/20+D53/240 -> 0.083333333
A54: form the skins sold of 11 lambs in murrrain before weaning | D54: 9 | F54: =B54+C54/20+D54/240 -> 0.0375
A55: from the skins sold of 6 rotted sheep in murrain after shearing | D55: 1 | F55: =B55+C55/20+D55/240 -> 0.0041666667
A56: from 7.5 stone of wool locks sold | C56: 10 | D56: 8 | F56: =B56+C56/20+D56/240 -> 0.53333333
A57: from 0.5 weys of winter cheese sold | C57: 4 | D57: 6 | F57: =B57+C57/20+D57/240 -> 0.225
A58: from 8 weys of summer cheese sold | B58: 3 | C58: 12 | F58: =B58+C58/20+D58/240 -> 3.6
A59: from 1 wey of butter sold | C59: 9 | F59: =B59+C59/20+D59/240 -> 0.45
A60: from 64 hens from churchscot | C60: 5 | D60: 4 | F60: =B60+C60/20+D60/240 -> 0.26666667
A61: from the whole hundred for refusing to stack | B61: 1 | F61: =B61+C61/20+D61/240 -> 1
A62: form the hall which was leased to John Vicar for the year | C62: 5 | D62: 3 | F62: =B62+C62/20+D62/240 -> 0.2625
A63: from dairy produce sold at audit | C63: 4 | D63: 5 | F63: =B63+C63/20+D63/240 -> 0.22083333
A64: Total recorded in accounts | B64: 14 | C64: 9 | D64: 8.5 | F64: =B64+C64/20+D64/240 -> 14.485417
A65: Total | B65: =SUM(B39:B63) -> 8 | C65: =SUM(C39:C63) -> 120 | D65: =SUM(D39:D63) -> 116.5 | F65: =B65+C65/20+D65/240 -> 14.485417 | G65: =F65-F64 -> 0
A67: Sale of corn
A68: from 48 qrs 7 bus of wheat sold | B68: 12 | C68: 6 | D68: 4.5 | F68: =B68+C68/20+D68/240 -> 12.31875
A69: from 3 bus of wheat sold at audit | C69: 1 | D69: 6 | F69: =B69+C69/20+D69/240 -> 0.075
A70: from 7.5 qrs 1 peck of curall sold | B70: 1 | C70: 1 | D70: 6.25 | F70: =B70+C70/20+D70/240 -> 1.0760417
A71: from 1.5 bus of curall sold at audit | D71: 4.5 | F71: =B71+C71/20+D71/240 -> 0.01875
A72: from 75 qrs 1.5 bus of barley sold | B72: 15 | D72: 1 | F72: =B72+C72/20+D72/240 -> 15.004167
A73: from 35 qrs of oats sold | B73: 4 | C73: 13 | D73: 4 | F73: =B73+C73/20+D73/240 -> 4.6666667
A74: from 13.5 qrs of peas sold | B74: 2 | C74: 5 | F74: =B74+C74/20+D74/240 -> 2.25
A75: from 7 qrs of vetches sold | C75: 18 | D75: 8 | F75: =B75+C75/20+D75/240 -> 0.93333333
A76: Total recorded in accounts | B76: 36 | C76: 6 | D76: 10.25 | F76: =B76+C76/20+D76/240 -> 36.342708
A77: Total | B77: =SUM(B68:B75) -> 34 | C77: =SUM(C68:C75) -> 44 | D77: =SUM(D68:D75) -> 34.25 | F77: =B77+C77/20+D77/240 -> 36.342708 | G77: =F77-F76 -> 0
A79: Entry and marriage fines
A80: from tithing of bishopstone at the hundred court of Michaelmas | C80: 3 | F80: =B80+C80/20+D80/240 -> 0.15
A81: from the tithing of Flamston for the same | C81: 3 | F81: =B81+C81/20+D81/240 -> 0.15
A82: from the tithing of Faulston for the same | C82: 2 | F82: =B82+C82/20+D82/240 -> 0.1
A83: from the aforesaid tithings at the hundred-court of Hockday for the same | C83: 8 | F83: =B83+C83/20+D83/240 -> 0.4
A84: from John Stacy to have 8 acres of land | C84: 6 | D84: 8 | F84: =B84+C84/20+D84/240 -> 0.33333333
A85: from Joan to retain 1 virgate | C85: 10 | F85: =B85+C85/20+D85/240 -> 0.5
A86: from Thomas Osbsbern for 8 acres of land | C86: 6 | D86: 8 | F86: =B86+C86/20+D86/240 -> 0.33333333
A87: from Thomas Faber for 1 messeuage | C87: 1 | F87: =B87+C87/20+D87/240 -> 0.05
A88: Total recorded in accounts | B88: 2 | C88: 4 | F88: =B88+C88/20+D88/240 -> 2.2
A89: Total | B89: =SUM(B80:B87) -> 0 | C89: =SUM(C80:C87) -> 39 | D89: =SUM(D80:D87) -> 16 | F89: =B89+C89/20+D89/240 -> 2.0166667 | G89: =F89-F88 -> -0.18333333
A91: Pleas and perquisites
A92: from the pleas and perquisites of the court | B92: 2 | C92: 3 | F92: =B92+C92/20+D92/240 -> 2.15
A93: from Thomas reeve because he sowed the lord's land with bad seed | C93: 2 | F93: =B93+C93/20+D93/240 -> 0.1
A94: from John Perour for the same | C94: 1 | F94: =B94+C94/20+D94/240 -> 0.05
A95: Total recorded in accounts | B95: 2 | C95: 6 | F95: =B95+C95/20+D95/240 -> 2.3
A96: Total | B96: =SUM(B92:B94) -> 2 | C96: =SUM(C92:C94) -> 6 | D96: =SUM(D92:D94) -> 0 | F96: =B96+C96/20+D96/240 -> 2.3 | G96: =F96-F95 -> 0
A98: Total of all receipts (sum of above excl. arrears) | B98: =SUM(B96,B89,B77,B65,B36,B27,B22,B14) -> 56 | C98: =SUM(C96,C89,C77,C65,C36,C27,C22,C14) -> 227 | D98: =SUM(D96,D89,D77,D65,D36,D27,D22,D14) -> 223.75 | F98: =B98+C98/20+D98/240 -> 68.282292
A99: Total of all receipts (sum of above incl. arrears) | B99: =SUM(B96,B89,B77,B65,B36,B27,B22,B14,B5) -> 66 | C99: =SUM(C96,C89,C77,C65,C36,C27,C22,C14,C5) -> 245 | D99: =SUM(D96,D89,D77,D65,D36,D27,D22,D14,D5) -> 232 | F99: =B99+C99/20+D99/240 -> 79.216667
A100: Total of all receipts in account excl. arrears | B100: 66 | C100: 14 | D100: 1.75 | F100: =B100+C100/20+D100/240 -> 66.707292 | G100: =F100-F98 -> -1.575
A101: Total of all receipts in account incl. arrears | F101: =B101+C101/20+D101/240 -> 0

Sheet Bishopstone Expenses
A1: BISHOPSTONE EXPENSES
B2: £ | C2: s | D2: d | F2: Total in £ | G2: Error | H2: Notes
A3: Cost of Ploughs
A4: in ironwork of 2 ploughs for the year with stipend of smith | C4: 12 | D4: 6 | F4: =B4+C4/20+D4/240 -> 0.625
A5: in 2 ploughfeet | D5: 6 | F5: =B5+C5/20+D5/240 -> 0.025
A6: in 2 yokes | D6: 2 | F6: =B6+C6/20+D6/240 -> 0.0083333333
A7: in 4 wheels | D7: 6 | F7: =B7+C7/20+D7/240 -> 0.025
A8: in 1 boon-work of 16 ploughmen in winter and 14 in lent | C8: 5 | F8: =B8+C8/20+D8/240 -> 0.25
A9: in stipend of 2 ploughmen for the year | C9: 6 | F9: =B9+C9/20+D9/240 -> 0.3
A10: in allowance of Thomas reeve for making a plough which ihe is bound to do according to custom | C10: 1 | D10: 6 | F10: =B10+C10/20+D10/240 -> 0.075
A11: in 1 ox bought for the plough | C11: 9 | F11: =B11+C11/20+D11/240 -> 0.45
A12: Total recorded in accounts | B12: 1 | C12: 15 | D12: 2 | F12: =B12+C12/20+D12/240 -> 1.7583333
A13: Total | B13: =SUM(B4:B11) -> 0 | C13: =SUM(C4:C11) -> 33 | D13: =SUM(D4:D11) -> 26 | F13: =B13+C13/20+D13/240 -> 1.7583333 | G13: =F13-F12 -> 0
A14: Total capital expenses | B14: =SUM(B10:B11,B4:B7) -> 0 | C14: =SUM(C10:C11,C4:C7) -> 22 | D14: =SUM(D10:D11,D4:D7) -> 26 | F14: =B14+C14/20+D14/240 -> 1.2083333
F15: =B15+C15/20+D15/240 -> 0
A16: Cost of Carts and Wagons
A17: in 4 clouts | D17: 3 | F17: =B17+C17/20+D17/240 -> 0.0125
A18: in 1 halter | D18: 1 | F18: =B18+C18/20+D18/240 -> 0.0041666667
A19: in shoeing the carthorse | C19: 1 | D19: 3 | F19: =B19+C19/20+D19/240 -> 0.0625
A20: in white leather bought | D20: 1.5 | F20: =B20+C20/20+D20/240 -> 0.00625
A21: Total recorded in accounts | C21: 1 | D21: 8.5 | F21: =B21+C21/20+D21/240 -> 0.085416667
A22: Total | B22: =SUM(B17:B20) -> 0 | C22: =SUM(C17:C20) -> 1 | D22: =SUM(D17:D20) -> 8.5 | F22: =B22+C22/20+D22/240 -> 0.085416667 | G22: =F22-F21 -> 0
A23: Total capital expenses | B23: =SUM(B17:B20) -> 0 | C23: =SUM(C17:C20) -> 1 | D23: =SUM(D17:D20) -> 8.5 | F23: =B23+C23/20+D23/240 -> 0.085416667
A25: Cost of Dairy
A26: in 5 bus of salt bought for salting cheese and butter | C26: 1 | D26: 3 | F26: =B26+C26/20+D26/240 -> 0.0625
A27: in linen and woollen cloth bought for cheese | D27: 8.5 | F27: =B27+C27/20+D27/240 -> 0.035416667
A28: in earthenware pots and pans | D28: 2.5 | F28: =B28+C28/20+D28/240 -> 0.010416667
A29: in a press bought | D29: 6 | F29: =B29+C29/20+D29/240 -> 0.025
A30: in stipend of 1 dairymaid for the year | C30: 2 | D30: 6 | F30: =B30+C30/20+D30/240 -> 0.125
A31: Total recorded in accounts | C31: 5 | D31: 2 | F31: =B31+C31/20+D31/240 -> 0.25833333
A32: Total | B32: =SUM(B26:B30) -> 0 | C32: =SUM(C26:C30) -> 3 | D32: =SUM(D26:D30) -> 26 | F32: =B32+C32/20+D32/240 -> 0.25833333 | G32: =F32-F31 -> 0
A33: Total capital expenses | B33: =SUM(B26:B29) -> 0 | C33: =SUM(C26:C29) -> 1 | D33: =SUM(D26:D29) -> 20 | F33: =B33+C33/20+D33/240 -> 0.13333333
A35: Sheepcote
A36: in grease, vinegar and copperas bought for greasing sheep | C36: 16 | D36: 8.5 | F36: =B36+C36/20+D36/240 -> 0.83541667
A37: in 1 stake bought | D37: 10 | F37: =B37+C37/20+D37/240 -> 0.041666667
A38: in 27 hurdles bought | C38: 2 | D38: 8 | F38: =B38+C38/20+D38/240 -> 0.13333333
A39: in 16 ells of canvas bought for packing wool | C39: 4 | D39: 4 | F39: =B39+C39/20+D39/240 -> 0.21666667
A40: in packing the said wool and making sacks with the thread bought for the same | D40: 8 | F40: =B40+C40/20+D40/240 -> 0.033333333
A41: Total recorded in accounts | B41: 1 | C41: 5 | D41: 2.5 | F41: =B41+C41/20+D41/240 -> 1.2604167
A42: Total | B42: =SUM(B36:B40) -> 0 | C42: =SUM(C36:C40) -> 22 | D42: =SUM(D36:D40) -> 38.5 | F42: =B42+C42/20+D42/240 -> 1.2604167 | G42: =F42-F41 -> 0
A43: Total capital expenses | B43: =SUM(B36:B39) -> 0 | C43: =SUM(C36:C39) -> 22 | D43: =SUM(D36:D39) -> 30.5 | F43: =B43+C43/20+D43/240 -> 1.2270833
A45: Cost of Buildings
A46: in stipend of 1 man repairing door of byre | D46: 1 | F46: =B46+C46/20+D46/240 -> 0.0041666667
A47: in repairing and restoring the walls around the curia | D47: 5 | F47: =B47+C47/20+D47/240 -> 0.020833333
A48: in stipend of 1 man covering the stack of vetches | D48: 5.5 | F48: =B48+C48/20+D48/240 -> 0.022916667
A49: in 1 sack bought | D49: 4.5 | F49: =B49+C49/20+D49/240 -> 0.01875
A50: Total recorded in accounts | C50: 1 | D50: 4 | F50: =B50+C50/20+D50/240 -> 0.066666667
A51: Total | B51: =SUM(B46:B49) -> 0 | C51: =SUM(C46:C49) -> 0 | D51: =SUM(D46:D49) -> 16 | F51: =B51+C51/20+D51/240 -> 0.066666667 | G51: =F51-F50 -> 0
A52: Total capital expenses | B52: =SUM(B46:B49) -> 0 | C52: =SUM(C46:C49) -> 0 | D52: =SUM(D46:D49) -> 16 | F52: =B52+C52/20+D52/240 -> 0.066666667
A54: Threshing
A55: in threshing 68 qrs 1 bus of wheat, 7 qrs 7 bus of curral, 21 qrs 7 bus of peas and 9.5 qrs of vetches | C55: 17 | D55: 10.75 | F55: =B55+C55/20+D55/240 -> 0.89479167
A56: in winnowing the same | C56: 1 | D56: 9.5 | F56: =B56+C56/20+D56/240 -> 0.089583333
A57: in threshing 120.5 qrs of barley | C57: 12 | F57: =B57+C57/20+D57/240 -> 0.6
A58: in winnowing the same | C58: 1 | D58: 3 | F58: =B58+C58/20+D58/240 -> 0.0625
A59: in threshing 60 qrs 1 bus of oats | C59: 2 | D59: 6.25 | F59: =B59+C59/20+D59/240 -> 0.12604167
A60: in winnowing the same | D60: 6
A61: Total recorded in accounts | B61: 1 | C61: 16 | F61: =B61+C61/20+D61/240 -> 1.8
A62: Total | B62: =SUM(B55:B60) -> 0 | C62: =SUM(C55:C60) -> 33 | D62: =SUM(D55:D60) -> 35.5 | F62: =B62+C62/20+D62/240 -> 1.7979167 | G62: =F62-F61 -> -0.0020833333
A64: Expenses of the Harvest
A65: in weeding corn | D65: 8 | F65: =B65+C65/20+D65/240 -> 0.033333333
A66: in customary payment for the mowing of the meadow | D66: 8 | F66: =B66+C66/20+D66/240 -> 0.033333333
A67: in 2 boon-works of 200 men who reaped and bound 104 acres | C67: 9 | D67: 6.5 | F67: =B67+C67/20+D67/240 -> 0.47708333
A68: in customary payment to 6 carters for carrying corn | C68: 1 | D68: 4 | F68: =B68+C68/20+D68/240 -> 0.066666667
A69: Total recorded in accounts | C69: 12 | D69: 2.5 | F69: =B69+C69/20+D69/240 -> 0.61041667
A70: Total | B70: =SUM(B65:B68) -> 0 | C70: =SUM(C65:C68) -> 10 | D70: =SUM(D65:D68) -> 26.5 | F70: =B70+C70/20+D70/240 -> 0.61041667 | G70: =F70-F69 -> 0
A72: Bailiff's expenses
A73: in expense of the bailiff for his visits with the expenses of the previous bailiff for holding the tourn and court and performing other business | C73: 9 | D73: 6 | F73: =B73+C73/20+D73/240 -> 0.475
A74: in wages of 1 overseer of harvest | C74: 10 | D74: 6 | F74: =B74+C74/20+D74/240 -> 0.525
A75: in wages of other overseer of harvest | C75: 13 | D75: 4 | F75: =B75+C75/20+D75/240 -> 0.66666667
A76: in stipend of same overseer | C76: 6 | D76: 8
A77: Total recorded in accounts | B77: 2 | F77: =B77+C77/20+D77/240 -> 2
A78: Total | B78: =SUM(B73:B76) -> 0 | C78: =SUM(C73:C76) -> 38 | D78: =SUM(D73:D76) -> 24 | F78: =B78+C78/20+D78/240 -> 2 | G78: =F78-F77 -> 0
A80: Total of all Expenses | B80: 7 | C80: 16 | D80: 9.5 | F80: =B80+C80/20+D80/240 -> 7.8395833
A81: Total of all Expenses (calculated) | B81: =SUM(B13,B22,B32,B42,B51,B62,B70,B78) -> 0 | C81: =SUM(C13,C22,C32,C42,C51,C62,C70,C78) -> 140 | D81: =SUM(D13,D22,D32,D42,D51,D62,D70,D78) -> 201 | F81: =B81+C81/20+D81/240 -> 7.8375 | G81: =F81-F80 -> -0.0020833333
A82: And thus he owes | B82: 58 | C82: 17 | D82: 4.25 | F82: =B82+C82/20+D82/240 -> 58.867708
A83: Delivered to Sir Geoffrey, treasurer of Wolvesey | B83: 47 | C83: 8 | F83: =B83+C83/20+D83/240 -> 47.4
A84: and thus he owes clear | B84: 11 | C84: 9 | D84: 4.25 | F84: =B84+C84/20+D84/240 -> 11.467708
A85: Total capital expenses | B85: =SUM(B14,B23,B33,B43,B52,) -> 0 | C85: =SUM(C14,C23,C33,C43,C52,) -> 46 | D85: =SUM(D14,D23,D33,D43,D52,) -> 101 | F85: =B85+C85/20+D85/240 -> 2.7208333

Sheet Issues of the Grange
B1: The issue of the grange account gives the total "yield" at the top of each heading in curly brackets, measurements used: fold, qrs, bus
B2: In "Issues of the grange" (p.xx) | G2: In "Sale of Corn" (p.x) | P2: Value of Total Production
A3: Gross output | B3: Quantity | D3: Additional bought-in | F3: Quantity | G3: Quantity noted as sold | J3: Difference Produced vs. Sold | K3: Price 1 | L3: Quantity 1 | M3: Price 2 | N3: Quantity 2 | O3: Unit price | P3: Value
B4: qrs | C4: bus | D4: qrs | E4: bus | F4: qrs | G4: qrs | H4: bus | I4: qrs | K4: £ | L4: qrs | M4: £ | N4: qrs | O4: £ per qr | P4: £
A5: Wheat | B5: 71 | F5: =B5+D5+C5/8+E5/8 -> 71 | G5: 48 | H5: 10 | I5: =G5+H5/8 -> 49.25 | J5: =F5-I5 -> 21.75 | K5: ='Bishopstone Receipts'!F68 -> 12.31875 | L5: =48+7/8 -> 48.875 | M5: ='Bishopstone Receipts'!F69 -> 0.075 | N5: =3/8 -> 0.375 | O5: =IFERROR((K5+M5)/(L5+N5),0) -> 0.25164975 | P5: =O5*F5 -> 17.867132
A6: Curall | B6: 7 | C6: 6 | F6: =B6+D6+C6/8+E6/8 -> 7.75 | G6: 7 | H6: 6 | I6: =G6+H6/8 -> 7.75 | J6: =F6-I6 -> 0 | K6: ='Bishopstone Receipts'!F70 -> 1.0760417 | L6: =I6 -> 7.75 | O6: =IFERROR((K6+M6)/(L6+N6),0) -> 0.13884409 | P6: =O6*F6 -> 1.0760417
A7: Barley | B7: 120.5 | F7: =B7+D7+C7/8+E7/8 -> 120.5 | G7: 75 | H7: 1 | I7: =G7+H7/8 -> 75.125 | J7: =F7-I7 -> 45.375 | K7: ='Bishopstone Receipts'!F72 -> 15.004167 | L7: =I7 -> 75.125 | O7: =IFERROR((K7+M7)/(L7+N7),0) -> 0.19972268 | P7: =O7*F7 -> 24.066583
A8: Oats | B8: 60 | C8: 1 | F8: =B8+D8+C8/8+E8/8 -> 60.125 | G8: 35 | I8: =G8+H8/8 -> 35 | J8: =F8-I8 -> 25.125 | K8: ='Bishopstone Receipts'!F73 -> 4.6666667 | L8: =I8 -> 35 | O8: =IFERROR((K8+M8)/(L8+N8),0) -> 0.13333333 | P8: =O8*F8 -> 8.0166667
A9: Peas | B9: 21 | C9: 7 | F9: =B9+D9+C9/8+E9/8 -> 21.875 | G9: 13.5 | I9: =G9+H9/8 -> 13.5 | J9: =F9-I9 -> 8.375 | K9: ='Bishopstone Receipts'!F74 -> 2.25 | L9: =G9 -> 13.5 | O9: =IFERROR((K9+M9)/(L9+N9),0) -> 0.16666667 | P9: =O9*F9 -> 3.6458333
A10: Vetches | B10: 9 | C10: 4 | F10: =B10+D10+C10/8+E10/8 -> 9.5 | G10: 7 | I10: =G10+H10/8 -> 7 | J10: =F10-I10 -> 2.5 | K10: ='Bishopstone Receipts'!F75 -> 0.93333333 | L10: =I10 -> 7 | O10: =IFERROR((#REF!+M10)/(K10+N10),0) -> 0 | P10: =O10*F10 -> 0
A12: Total Production | F12: =SUM(F5:F10) -> 290.75 | P12: =SUM(P5:P10) -> 54.672257 | Q12: Production value is significantly more, as much less was sold than what was produced
A13: Sales of corn (as recorded in accounts) | F13: =SUM(I5:I10) -> 187.625 | P13: =SUM(K5:K10,M5:M10) -> 36.323958
A16: Net output | B16: Gross output | C16: Seed | F16: tithe | G16: to manorial servants & livestock | J16: Output net of tithe & seed & liveries to manorial servants | K16: in stock from last year | L16: Price | M16: Value of net output | N16: Value of sales (in "Sale of Corn")
B17: qrs | C17: qrs | D17: bus | E17: qrs | F17: qrs | G17: qrs | H17: bus | I17: qrs | J17: qrs | K17: qrs | L17: £ per qr | M17: £ | N17: £
A18: Wheat | B18: =B5 -> 71 | C18: 18 | D18: 1 | E18: =C18+D18/8 -> 18.125 | G18: 2.5 | H18: 9 | I18: =G18+H18/8 -> 3.625 | J18: =B18-(E18+F18+I18) -> 49.25 | L18: =O5 -> 0.25164975 | M18: =L18*J18 -> 12.39375 | N18: =I5*O5 -> 12.39375
A19: Curall | B19: =B6 -> 7 | E19: =C19+D19/8 -> 0 | I19: =G19+H19/8 -> 0 | J19: =B19-(E19+F19+I19) -> 7 | L19: =O6 -> 0.13884409 | M19: =L19*J19 -> 0.9719086 | N19: =I6*O6 -> 1.0760417
A20: Barley | B20: =B7 -> 120.5 | C20: 22 | D20: 6 | E20: =C20+D20/8 -> 22.75 | G20: 21.5 | H20: 8 | I20: =G20+H20/8 -> 22.5 | J20: =B20-(E20+F20+I20) -> 75.25 | L20: =O7 -> 0.19972268 | M20: =L20*J20 -> 15.029132 | N20: =I7*O7 -> 15.004167
A21: Oats | B21: =B8 -> 60 | C21: 21 | D21: 6 | E21: =C21+D21/8 -> 21.75 | G21: 3 | H21: 3 | I21: =G21+H21/8 -> 3.375 | J21: =B21-(E21+F21+I21) -> 34.875 | L21: =O8 -> 0.13333333 | M21: =L21*J21 -> 4.65 | N21: =I8*O8 -> 4.6666667
A22: Peas | B22: =B9 -> 21 | C22: 3 | D22: 2 | E22: =C22+D22/8 -> 3.25 | H22: 2 | I22: =G22+H22/8 -> 0.25 | J22: =B22-(E22+F22+I22) -> 17.5 | L22: =O9 -> 0.16666667 | M22: =L22*J22 -> 2.9166667 | N22: =I9*O9 -> 2.25
A23: Vetches | B23: =B10 -> 9 | C23: 2 | D23: 4 | E23: =C23+D23/8 -> 2.5 | J23: =B23-(E23+F23+I23) -> 6.5 | L23: =O10 -> 0 | M23: =L23*J23 -> 0 | N23: =I10*O10 -> 0
A24: Liveries of manorial servants
A25: Total | B25: =SUM(B18:B23) -> 288.5 | E25: =SUM(E18:E23) -> 68.375 | J25: =SUM(J18:J23) -> 190.375 | M25: =SUM(M18:M23) -> 35.961457

Sheet Stock
A1: EAST KNOYLE STOCK ACCOUNT
A3: Livestock | B3: Inherited stock | C3: Bought / added not produced | D3: Produced | E3: strays | F3: herbage | G3: sold | H3: in murrain | I3: accounted for elsewhere | J3: End-period stock | K3: cross-check | L3: price 1 | M3: units 1 | N3: price 2 | O3: units 2 | P3: Weight (weys) | Q3: Unit price (£) | R3: Value of production (£) at sales prices | S3: Sales in (£) | T3: Details
A4: Cart-horses | K4: =B4+C4+D4-E4-F4-G4-H4-I4 -> 0 | Q4: =IFERROR((L4+N4)/(M4+O4),"") | R4: =IFERROR(D4*Q4,"") | S4: =IFERROR(Q4*G4,"")
A5: Mares | K5: =B5+C5+D5-E5-F5-G5-H5-I5 -> 0 | Q5: =IFERROR((L5+N5)/(M5+O5),"") | R5: =IFERROR(D5*Q5,"") | S5: =IFERROR(Q5*G5,"")
A6: Plough horses | B6: 1 | J6: 1 | K6: =B6+C6+D6-E6-F6-G6-H6-I6 -> 1 | Q6: =IFERROR((L6+N6)/(M6+O6),"") | R6: =IFERROR(D6*Q6,"") | S6: =IFERROR(Q6*G6,"")
A7: Colts (2 years) | K7: =B7+C7+D7-E7-F7-G7-H7-I7 -> 0 | Q7: =IFERROR((L7+N7)/(M7+O7),"") | R7: =IFERROR(D7*Q7,"") | S7: =IFERROR(Q7*G7,"")
A8: Colts (2 years) | K8: =B8+C8+D8-E8-F8-G8-H8-I8 -> 0 | Q8: =IFERROR((L8+N8)/(M8+O8),"") | R8: =IFERROR(D8*Q8,"") | S8: =IFERROR(Q8*G8,"")
A9: Colts (1 year) | K9: =B9+C9+D9-E9-F9-G9-H9-I9 -> 0 | Q9: =IFERROR((L9+N9)/(M9+O9),"") | R9: =IFERROR(D9*Q9,"") | S9: =IFERROR(Q9*G9,"")
A10: Foals | K10: =B10+C10+D10-E10-F10-G10-H10-I10 -> 0 | Q10: =IFERROR((L10+N10)/(M10+O10),"") | R10: =IFERROR(D10*Q10,"") | S10: =IFERROR(Q10*G10,"")
A11: Oxen | B11: 16 | C11: 2 | D11: 1 | G11: 1 | J11: 18 | K11: =B11+C11+D11-E11-F11-G11-H11-I11 -> 18 | L11: ='Bishopstone Receipts'!F45 -> 0.275 | M11: 1 | Q11: =IFERROR((L11+N11)/(M11+O11),"") -> 0.275 | R11: =IFERROR(D11*Q11,"") -> 0.275 | S11: =IFERROR(Q11*G11,"") -> 0.275
A12: Bulls | B12: 1 | C12: 1 | I12: 1 | J12: 1 | K12: =B12+C12+D12-E12-F12-G12-H12-I12 -> 1 | Q12: =IFERROR((L12+N12)/(M12+O12),"") | R12: =IFERROR(D12*Q12,"") | S12: =IFERROR(Q12*G12,"")
A13: Cows | B13: 11 | C13: 1 | H13: 1 | J13: 11 | K13: =B13+C13+D13-E13-F13-G13-H13-I13 -> 11 | Q13: =IFERROR((L13+N13)/(M13+O13),"") | R13: =IFERROR(D13*Q13,"") | S13: =IFERROR(Q13*G13,"")
A14: Steers | B14: 4 | H14: 1 | I14: 3 | K14: =B14+C14+D14-E14-F14-G14-H14-I14 -> 0 | Q14: =IFERROR((L14+N14)/(M14+O14),"") | R14: =IFERROR(D14*Q14,"") | S14: =IFERROR(Q14*G14,"")
A15: Bullocks | B15: 2 | C15: 2 | H15: 1 | J15: 3 | K15: =B15+C15+D15-E15-F15-G15-H15-I15 -> 3 | Q15: =IFERROR((L15+N15)/(M15+O15),"") | R15: =IFERROR(D15*Q15,"") | S15: =IFERROR(Q15*G15,"")
A16: Yearlings | B16: 3 | J16: 3 | K16: =B16+C16+D16-E16-F16-G16-H16-I16 -> 3 | Q16: =IFERROR((L16+N16)/(M16+O16),"") | R16: =IFERROR(D16*Q16,"") | S16: =IFERROR(Q16*G16,"")
A17: Calves | D17: 11 | G17: 7 | H17: 1 | I17: 1 | J17: 2 | K17: =B17+C17+D17-E17-F17-G17-H17-I17 -> 2 | L17: ='Bishopstone Receipts'!F46 -> 0.3875 | M17: 7 | Q17: =IFERROR((L17+N17)/(M17+O17),"") -> 0.055357143 | R17: =IFERROR(D17*Q17,"") -> 0.60892857 | S17: =IFERROR(Q17*G17,"") -> 0.3875
A18: Wethers | B18: 275 | C18: 81 | G18: 27 | H18: 26 | I18: 2 | J18: 301 | K18: =B18+C18+D18-E18-F18-G18-H18-I18 -> 301 | L18: ='Bishopstone Receipts'!F48 -> 0.175 | M18: 6 | N18: ='Bishopstone Receipts'!F47/3 -> 0.90138889 | O18: 21 | Q18: =IFERROR((L18+N18)/(M18+O18),"") -> 0.039866255 | R18: =IFERROR(D18*Q18,"") -> 0 | S18: =IFERROR(Q18*G18,"") -> 1.0763889 | T18: Price of ewes and wethers conflated in receipts - assume same price
A19: Rams | B19: 4 | J19: 4 | K19: =B19+C19+D19-E19-F19-G19-H19-I19 -> 4 | Q19: =IFERROR((L19+N19)/(M19+O19),"") | R19: =IFERROR(D19*Q19,"") | S19: =IFERROR(Q19*G19,"")
A20: Ewes | B20: 340 | C20: 71 | G20: 40 | H20: 14 | J20: 357 | K20: =B20+C20+D20-E20-F20-G20-H20-I20 -> 357 | L20: ='Bishopstone Receipts'!F47*2/3 -> 1.8027778 | M20: 40 | Q20: =IFERROR((L20+N20)/(M20+O20),"") -> 0.045069444 | R20: =IFERROR(D20*Q20,"") -> 0 | S20: =IFERROR(Q20*G20,"") -> 1.8027778 | T20: Price of ewes and wethers conflated in receipts - assume same price
A21: Hoggs | B21: 158 | H21: 6 | I21: 152 | J21: 0 | K21: =B21+C21+D21-E21-F21-G21-H21-I21 -> 0 | Q21: =IFERROR((L21+N21)/(M21+O21),"") | R21: =IFERROR(D21*Q21,"") | S21: =IFERROR(Q21*G21,"")
A22: Lambs | D22: 276 | F22: 7 | G22: 50 | H22: 18 | I22: 30 | J22: 171 | K22: =B22+C22+D22-E22-F22-G22-H22-I22 -> 171 | L22: ='Bishopstone Receipts'!F49 -> 1.1208333 | M22: 50 | Q22: =IFERROR((L22+N22)/(M22+O22),"") -> 0.022416667 | R22: =IFERROR(D22*Q22,"") -> 6.187 | S22: =IFERROR(Q22*G22,"") -> 1.1208333 | T22: account states 185 remain
A23: Boars | K23: =B23+C23+D23-E23-F23-G23-H23-I23 -> 0 | Q23: =IFERROR((L23+N23)/(M23+O23),"") | R23: =IFERROR(D23*Q23,"") | S23: =IFERROR(Q23*G23,"")
A24: Sows | K24: =B24+C24+D24-E24-F24-G24-H24-I24 -> 0 | Q24: =IFERROR((L24+N24)/(M24+O24),"") | R24: =IFERROR(D24*Q24,"") | S24: =IFERROR(Q24*G24,"")
A25: Pigs | K25: =B25+C25+D25-E25-F25-G25-H25-I25 -> 0 | Q25: =IFERROR((L25+N25)/(M25+O25),"") | R25: =IFERROR(D25*Q25,"") | S25: =IFERROR(Q25*G25,"")
A26: Hoggets | K26: =B26+C26+D26-E26-F26-G26-H26-I26 -> 0 | Q26: =IFERROR((L26+N26)/(M26+O26),"") | R26: =IFERROR(D26*Q26,"") | S26: =IFERROR(Q26*G26,"")
A27: Piglets | K27: =B27+C27+D27-E27-F27-G27-H27-I27 -> 0 | Q27: =IFERROR((L27+N27)/(M27+O27),"") | R27: =IFERROR(D27*Q27,"") | S27: =IFERROR(Q27*G27,"")
A28: Swans | K28: =B28+C28+D28-E28-F28-G28-H28-I28 -> 0 | Q28: =IFERROR((L28+N28)/(M28+O28),"") | R28: =IFERROR(D28*Q28,"") | S28: =IFERROR(Q28*G28,"")
A29: Peacocks | K29: =B29+C29+D29-E29-F29-G29-H29-I29 -> 0 | Q29: =IFERROR((L29+N29)/(M29+O29),"") | R29: =IFERROR(D29*Q29,"") | S29: =IFERROR(Q29*G29,"")
A30: Total | K30: =B30+C30+D30-E30-F30-G30-H30-I30 -> 0 | Q30: =IFERROR((L30+N30)/(M30+O30),"") | R30: =IFERROR(D30*Q30,"") | S30: =SUM(S4:S29) -> 4.6625
A32: Wool | K32: =B32+C32+D32-E32-F32-G32-H32-I32 -> 0 | Q32: =IFERROR((L32+N32)/(M32+O32),"") | R32: =IFERROR(D32*Q32,"") | S32: =IFERROR(Q32*G32,"")
A33: Fleeces | D33: 684 | I33: =615+69 -> 684 | J33: 0 | K33: =B33+C33+D33-E33-F33-G33-H33-I33 -> 0 | Q33: 0.02 | R33: =IFERROR(D33*Q33,"") -> 13.68 | S33: =IFERROR(Q33*G33,"") -> 0 | T33: 615 sent to Wolvesey which made 4 weys and 5 cloves
A34: Coarse wool | K34: =B34+C34+D34-E34-F34-G34-H34-I34 -> 0 | Q34: =IFERROR((L34+N34)/(M34+O34),"") | R34: =IFERROR(D34*Q34,"") | S34: =IFERROR(Q34*G34,"")
A35: Lamb's wool | D35: 237 | I35: 237 | J35: 0 | K35: =B35+C35+D35-E35-F35-G35-H35-I35 -> 0 | Q35: 0.01 | R35: =IFERROR(D35*Q35,"") -> 2.37 | S35: =IFERROR(Q35*G35,"") -> 0 | T35: 273 sent to Wolvesey which made 0.5 weys
A36: Wool locks | D36: =7.5*Assumptions!E7 -> 0.53571429 | G36: =D36 -> 0.53571429 | J36: 0 | K36: =B36+C36+D36-E36-F36-G36-H36-I36 -> 0 | L36: ='Bishopstone Receipts'!F56 -> 0.53333333 | M36: =P36 -> 0.53571429 | P36: =G36 -> 0.53571429 | Q36: =IFERROR((L36+N36)/(M36+O36),"") -> 0.99555556 | R36: =IFERROR(D36*Q36,"") -> 0.53333333 | S36: =IFERROR(Q36*G36,"") -> 0.53333333
A37: Wool sold at shearing | K37: =B37+C37+D37-E37-F37-G37-H37-I37 -> 0 | Q37: =IFERROR((L37+N37)/(M37+O37),"") | R37: =IFERROR(D37*Q37,"") | S37: =IFERROR(Q37*G37,"")
A38: Total | K38: =B38+C38+D38-E38-F38-G38-H38-I38 -> 0 | Q38: =IFERROR((L38+N38)/(M38+O38),"") | R38: =SUM(R33:R37) -> 16.583333
A41: Hides | K41: =B41+C41+D41-E41-F41-G41-H41-I41 -> 0 | Q41: =IFERROR((L41+N41)/(M41+O41),"") | R41: =IFERROR(D41*Q41,"") | S41: =IFERROR(Q41*G41,"")
A42: Ox hides | K42: =B42+C42+D42-E42-F42-G42-H42-I42 -> 0 | Q42: =IFERROR((L42+N42)/(M42+O42),"") | R42: =IFERROR(D42*Q42,"") | S42: =IFERROR(Q42*G42,"")
A43: Cow hides | D43: 1 | G43: 1 | J43: 0 | K43: =B43+C43+D43-E43-F43-G43-H43-I43 -> 0 | L43: ='Bishopstone Receipts'!F50 -> 0.091666667 | M43: 1 | Q43: =IFERROR((L43+N43)/(M43+O43),"") -> 0.091666667 | R43: =IFERROR(D43*Q43,"") -> 0.091666667 | S43: =IFERROR(Q43*G43,"") -> 0.091666667
A44: Mare hides | K44: =B44+C44+D44-E44-F44-G44-H44-I44 -> 0 | Q44: =IFERROR((L44+N44)/(M44+O44),"") | R44: =IFERROR(D44*Q44,"") | S44: =IFERROR(Q44*G44,"")
A45: Bullock Hides | D45: 2 | G45: 2 | J45: 0 | K45: =B45+C45+D45-E45-F45-G45-H45-I45 -> 0 | L45: ='Bishopstone Receipts'!F51 -> 0.10416667 | M45: 2 | Q45: =IFERROR((L45+N45)/(M45+O45),"") -> 0.052083333 | R45: =IFERROR(D45*Q45,"") -> 0.10416667 | S45: =IFERROR(Q45*G45,"") -> 0.10416667
A46: Steer hides | K46: =B46+C46+D46-E46-F46-G46-H46-I46 -> 0 | Q46: =IFERROR((L46+N46)/(M46+O46),"") | R46: =IFERROR(D46*Q46,"") | S46: =IFERROR(Q46*G46,"")
A47: Yearling Calf hides | K47: =B47+C47+D47-E47-F47-G47-H47-I47 -> 0 | Q47: =IFERROR((L47+N47)/(M47+O47),"") | R47: =IFERROR(D47*Q47,"") | S47: =IFERROR(Q47*G47,"")
A48: Calf hides | K48: =B48+C48+D48-E48-F48-G48-H48-I48 -> 0 | Q48: =IFERROR((L48+N48)/(M48+O48),"") | R48: =IFERROR(D48*Q48,"") | S48: =IFERROR(Q48*G48,"")
A49: Pig hides | K49: =B49+C49+D49-E49-F49-G49-H49-I49 -> 0 | Q49: =IFERROR((L49+N49)/(M49+O49),"") | R49: =IFERROR(D49*Q49,"") | S49: =IFERROR(Q49*G49,"")
A50: Weather woolskins | K50: =B50+C50+D50-E50-F50-G50-H50-I50 -> 0 | Q50: =IFERROR((L50+N50)/(M50+O50),"") | R50: =IFERROR(D50*Q50,"") | S50: =IFERROR(Q50*G50,"")
A51: Ram woolskins | K51: =B51+C51+D51-E51-F51-G51-H51-I51 -> 0 | Q51: =IFERROR((L51+N51)/(M51+O51),"") | R51: =IFERROR(D51*Q51,"") | S51: =IFERROR(Q51*G51,"")
A52: Ewe woolskins | K52: =B52+C52+D52-E52-F52-G52-H52-I52 -> 0 | Q52: =IFERROR((L52+N52)/(M52+O52),"") | R52: =IFERROR(D52*Q52,"") | S52: =IFERROR(Q52*G52,"")
A53: Hogg woolskins | K53: =B53+C53+D53-E53-F53-G53-H53-I53 -> 0 | Q53: =IFERROR((L53+N53)/(M53+O53),"") | R53: =IFERROR(D53*Q53,"") | S53: =IFERROR(Q53*G53,"")
A54: Woolskins (total) | D54: 46 | G54: 46 | J54: 0 | K54: =B54+C54+D54-E54-F54-G54-H54-I54 -> 0 | L54: ='Bishopstone Receipts'!F52 -> 0.2625 | M54: 26 | N54: ='Bishopstone Receipts'!F53 -> 0.083333333 | O54: 20 | Q54: =IFERROR((L54+N54)/(M54+O54),"") -> 0.0075181159 | R54: =IFERROR(D54*Q54,"") -> 0.34583333 | S54: =IFERROR(Q54*G54,"") -> 0.34583333
A55: Wether bareskins | K55: =B55+C55+D55-E55-F55-G55-H55-I55 -> 0 | Q55: =IFERROR((L55+N55)/(M55+O55),"") | R55: =IFERROR(D55*Q55,"") | S55: =IFERROR(Q55*G55,"")
A56: Ram bareskins | K56: =B56+C56+D56-E56-F56-G56-H56-I56 -> 0 | Q56: =IFERROR((L56+N56)/(M56+O56),"") | R56: =IFERROR(D56*Q56,"") | S56: =IFERROR(Q56*G56,"")
A57: Ewe bareskins | K57: =B57+C57+D57-E57-F57-G57-H57-I57 -> 0 | Q57: =IFERROR((L57+N57)/(M57+O57),"") | R57: =IFERROR(D57*Q57,"") | S57: =IFERROR(Q57*G57,"")
A58: Hogg bareskins | K58: =B58+C58+D58-E58-F58-G58-H58-I58 -> 0 | Q58: =IFERROR((L58+N58)/(M58+O58),"") | R58: =IFERROR(D58*Q58,"") | S58: =IFERROR(Q58*G58,"")
A59: Bareskins (total) | K59: =B59+C59+D59-E59-F59-G59-H59-I59 -> 0 | Q59: =IFERROR((L59+N59)/(M59+O59),"") | R59: =IFERROR(D59*Q59,"") | S59: =IFERROR(Q59*G59,"")
A60: Lambskins | D60: 18 | G60: 17 | I60: 1 | J60: 0 | K60: =B60+C60+D60-E60-F60-G60-H60-I60 -> 0 | L60: ='Bishopstone Receipts'!F54 -> 0.0375 | M60: 11 | N60: ='Bishopstone Receipts'!F55 -> 0.0041666667 | O60: 6 | Q60: =IFERROR((L60+N60)/(M60+O60),"") -> 0.0024509804 | R60: =IFERROR(D60*Q60,"") -> 0.044117647 | S60: =IFERROR(Q60*G60,"") -> 0.041666667
A61: Rotted skins | K61: =B61+C61+D61-E61-F61-G61-H61-I61 -> 0 | Q61: =IFERROR((L61+N61)/(M61+O61),"") | R61: =IFERROR(D61*Q61,"") | S61: =IFERROR(Q61*G61,"")
A62: Shorn skins | K62: =B62+C62+D62-E62-F62-G62-H62-I62 -> 0 | Q62: =IFERROR((L62+N62)/(M62+O62),"") | R62: =IFERROR(D62*Q62,"") | S62: =IFERROR(Q62*G62,"")
A63: Total | K63: =B63+C63+D63-E63-F63-G63-H63-I63 -> 0 | Q63: =IFERROR((L63+N63)/(M63+O63),"") | R63: =IFERROR(D63*Q63,"") | S63: =SUM(S42:S62) -> 0.58333333
A65: Poultry stock | K65: =B65+C65+D65-E65-F65-G65-H65-I65 -> 0 | Q65: =IFERROR((L65+N65)/(M65+O65),"") | R65: =IFERROR(D65*Q65,"") | S65: =IFERROR(Q65*G65,"")
A66: Hens | D66: 88 | G66: 64 | I66: 24 | J66: 0 | K66: =B66+C66+D66-E66-F66-G66-H66-I66 -> 0 | L66: ='Bishopstone Receipts'!F60 -> 0.26666667 | M66: 64 | Q66: =IFERROR((L66+N66)/(M66+O66),"") -> 0.0041666667 | R66: =IFERROR(D66*Q66,"") -> 0.36666667 | S66: =IFERROR(Q66*G66,"") -> 0.26666667
A67: Geese | K67: =B67+C67+D67-E67-F67-G67-H67-I67 -> 0 | Q67: =IFERROR((L67+N67)/(M67+O67),"") | R67: =IFERROR(D67*Q67,"") | S67: =IFERROR(Q67*G67,"")
A68: Capons (from chickens) | K68: =B68+C68+D68-E68-F68-G68-H68-I68 -> 0 | Q68: =IFERROR((L68+N68)/(M68+O68),"") | R68: =IFERROR(D68*Q68,"") | S68: =IFERROR(Q68*G68,"")
A69: Cocks & hens | K69: =B69+C69+D69-E69-F69-G69-H69-I69 -> 0 | Q69: =IFERROR((L69+N69)/(M69+O69),"") | R69: =IFERROR(D69*Q69,"") | S69: =IFERROR(Q69*G69,"")
A70: Total | S70: =SUM(S66:S69) -> 0.26666667
A72: Poultry production | K72: =B72+C72+D72-E72-F72-G72-H72-I72 -> 0 | Q72: =IFERROR((L72+N72)/(M72+O72),"") | R72: =IFERROR(D72*Q72,"") | S72: =IFERROR(Q72*G72,"")
A73: Eggs | K73: =B73+C73+D73-E73-F73-G73-H73-I73 -> 0 | Q73: =IFERROR((L73+N73)/(M73+O73),"") | R73: =IFERROR(D73*Q73,"") | S73: =IFERROR(Q73*G73,"")
A74: Cocks & hens from churchscot of customary tenants | K74: =B74+C74+D74-E74-F74-G74-H74-I74 -> 0 | Q74: =IFERROR((L74+N74)/(M74+O74),"") | R74: =IFERROR(D74*Q74,"") | S74: =IFERROR(Q74*G74,"")
A77: Meat | K77: =B77+C77+D77-E77-F77-G77-H77-I77 -> 0 | Q77: =IFERROR((L77+N77)/(M77+O77),"") | R77: =IFERROR(D77*Q77,"") | S77: =IFERROR(Q77*G77,"")
A78: Beef | K78: =B78+C78+D78-E78-F78-G78-H78-I78 -> 0 | Q78: =IFERROR((L78+N78)/(M78+O78),"") | R78: =IFERROR(D78*Q78,"") | S78: =IFERROR(Q78*G78,"")
A79: Mutton | K79: =B79+C79+D79-E79-F79-G79-H79-I79 -> 0 | Q79: =IFERROR((L79+N79)/(M79+O79),"") | R79: =IFERROR(D79*Q79,"") | S79: =IFERROR(Q79*G79,"")
A80: Pork | K80: =B80+C80+D80-E80-F80-G80-H80-I80 -> 0 | Q80: =IFERROR((L80+N80)/(M80+O80),"") | R80: =IFERROR(D80*Q80,"") | S80: =IFERROR(Q80*G80,"")
A83: Cheese | K83: =B83+C83+D83-E83-F83-G83-H83-I83 -> 0 | Q83: =IFERROR((L83+N83)/(M83+O83),"") | R83: =IFERROR(D83*Q83,"") | S83: =IFERROR(Q83*G83,"")
A84: Winter cheese | D84: 0.5 | G84: 0.5 | J84: 0 | K84: =B84+C84+D84-E84-F84-G84-H84-I84 -> 0 | L84: ='Bishopstone Receipts'!F57 -> 0.225 | M84: =G84 -> 0.5 | P84: 0.5 | Q84: =IFERROR((L84+N84)/(M84+O84),"") -> 0.45 | R84: =IFERROR(#REF!*Q84,"") | S84: =IFERROR(Q84*G84,"") -> 0.225
A85: Summer cheese | D85: 179 | G85: 159 | I85: 20 | K85: =B85+C85+D85-E85-F85-G85-H85-I85 -> 0 | L85: ='Bishopstone Receipts'!F58 -> 3.6 | M85: =G85 -> 159 | Q85: =IFERROR((L85+N85)/(M85+O85),"") -> 0.022641509 | R85: =IFERROR(D85*Q85,"") -> 4.0528302 | S85: =IFERROR(Q85*G85,"") -> 3.6 | T85: 159 cheeses sold made 8 weys
A86: Total | K86: =B86+C86+D86-E86-F86-G86-H86-I86 -> 0 | Q86: =IFERROR((L86+N86)/(M86+O86),"") | R86: =IFERROR(D86*Q86,"") | S86: =SUM(S84:S85) -> 3.825
K87: =B87+C87+D87-E87-F87-G87-H87-I87 -> 0 | Q87: =IFERROR((L87+N87)/(M87+O87),"") | R87: =IFERROR(D87*Q87,"") | S87: =IFERROR(Q87*G87,"")
A88: Butter | D88: 1 | G88: 1 | J88: 0 | K88: =B88+C88+D88-E88-F88-G88-H88-I88 -> 0 | L88: ='Bishopstone Receipts'!F59 -> 0.45 | M88: 1 | P88: 1 | Q88: =IFERROR((L88+N88)/(M88+O88),"") -> 0.45 | R88: =IFERROR(D88*Q88,"") -> 0.45 | S88: =IFERROR(Q88*G88,"") -> 0.45
A89: Total | S89: =S88 -> 0.45
A91: Cider | K91: =B91+C91+D91-E91-F91-G91-H91-I91 -> 0 | Q91: =IFERROR((L91+N91)/(M91+O91),"") | R91: =IFERROR(D91*Q91,"") | S91: =IFERROR(Q91*G91,"")
K92: =B92+C92+D92-E92-F92-G92-H92-I92 -> 0 | Q92: =IFERROR((L92+N92)/(M92+O92),"") | R92: =IFERROR(D92*Q92,"") | S92: =IFERROR(Q92*G92,"")
K93: =B93+C93+D93-E93-F93-G93-H93-I93 -> 0 | Q93: =IFERROR((L93+N93)/(M93+O93),"") | R93: =IFERROR(D93*Q93,"") | S93: =IFERROR(Q93*G93,"")
K94: =B94+C94+D94-E94-F94-G94-H94-I94 -> 0 | Q94: =IFERROR((L94+N94)/(M94+O94),"") | R94: =IFERROR(D94*Q94,"") | S94: =IFERROR(Q94*G94,"")
Q95: =IFERROR((L95+N95)/(M95+O95),"") | R95: =IFERROR(D95*Q95,"") | S95: =IFERROR(Q95*G95,"")
Q96: =IFERROR((L96+N96)/(M96+O96),"") | R96: =IFERROR(D96*Q96,"") | S96: =IFERROR(Q96*G96,"")

Sheet Assumptions
A1: ASSUMPTIONS
B3: Weights | C3: Value (in lbs) | D3: Value (in cloves) | E3: Value (in weys) | F3: Value (in stone)
B4: Lbs | C4: 1 | D4: =C4/C5 -> 0.14285714 | E4: =C4/C6 -> 0.0057142857 | F4: =C4/C7 -> 0.08
B5: Cloves | C5: 7 | D5: 1 | E5: =C5/C6 -> 0.04 | F5: =C7/C5 -> 1.7857143
B6: Wey | C6: 175 | D6: =C6/C5 -> 25 | E6: =C6/C6 -> 1 | F6: =C7/C6 -> 0.071428571
B7: Stone | C7: =175/14 -> 12.5 | D7: =C5/C7 -> 0.56 | E7: =C7/C6 -> 0.071428571 | F7: 1
