Workbook

Sheet Overview
A1: BURGHCLERE | B1: Total in £ | C1: Error | D1: Note
A2: CASH ACCOUNT
A3: RECEIPTS
A4: Arrears total
A5: Rents of assize total
A6: Quittances total
A7: Defaults of rent total
A8: Defaults of rent through the pestilence total
A9: Cotlands defaults total
A10: Cotlands total
A11: Total of quittances and defaults of rent total
A12: Total of rents remaining clear total
A13: Farms total
... A22: Farm of the demesne land total
A23: Total of all receipts (calculated here) | B23: =Receipts!F145 -> 84.02
A24: Total of all receipts (calculated here) incl arrears | B24: =Receipts!F146 -> 84.5275
A25: Total recorded in the accounts excl. arrears | B25: =Receipts!F145 -> 84.02 | C25: =B25-B23 -> 0
A26: Total recorded in the accounts incl. arrears
A29: EXPENSES
A30: Cost of ploughs total
A31: Purchase of corn total
A32: Cost of carts and wagons total
A33: Cost of dairy total
A34: Purchase of stock total
A35: Sheepcote total
A36: Cost of buildings total
A37: Threshing total
A38: Barley expenses
A39: Expenses of the harvest total
... A43: Annual fees
A44: Total of all expenses per account | B44: =Expenses!F94 -> 26.13
A45: Total of all expenses (calculated here) | B45: =Expenses!F95 -> 27.045 | C45: =B45-B44 -> 0.915
A46: Total fixed investment | B46: =Expenses!F96 -> 3.5058333
A47: Total Demesne fixed investment | B47: =Expenses!F97 -> 2.4308333
A49: Owed by the reeve
A50: From accounts
A52: Allowances
A53: Cash deliveries
A54: Sum of the above
A55: Total of all allowances and cash deliveries in accounts
A57: Net amount owed
A58: Net amount owed in accounts
A60: GRANGE ACCOUNT | B60: Total Production
A61: Grange | B61: qrs | E61: Value of total gross production in £ | F61: Value of total net production in £
A62: wheat | B62: ='Issues of the Grange'!B2 -> 135.625 | E62: ='Issues of the Grange'!I2 -> 45.208333 | F62: ='Issues of the Grange'!O11 -> 30.166667
A63: bere | B63: ='Issues of the Grange'!B3 -> 60.875 | E63: ='Issues of the Grange'!I3 -> 12.175 | F63: ='Issues of the Grange'!O12 -> 5.375
A64: barley | B64: ='Issues of the Grange'!B4 -> 13.75 | E64: ='Issues of the Grange'!I4 -> 2.75 | F64: ='Issues of the Grange'!O13 -> 0.925
A65: oats | B65: ='Issues of the Grange'!B5 -> 181.125 | E65: ='Issues of the Grange'!I5 -> 21.159729 | F65: ='Issues of the Grange'!O14 -> 4.9358097
A66: Total value of gross production (sum of the above) | E66: =SUM(E62:E65) -> 81.293062
A67: Total value of net production | E67: =SUM(F62:F65) -> 41.402476
A68: Value of sales | E68: =Receipts!F84 -> 41.12
A70: MILL ACCOUNT
A71: Issues of the mill
A72: Wheat
A73: Oatmeal
A74: 1st grade malt
A75: 2nd grade malt
A76: Maslin
A77: Total value of production (sum of the above)
A78: Value of sales
A80: STOCK ACCOUNT
A81: Livestock | B81: Sales value in £
A82: Cart-horses | B82: =Stock!R5 -> 0
A83: Mares | B83: =Stock!R6 -> 0.2
A84: Plough horses | B84: =Stock!R7 -> 0
A85: Colts (2 years) | B85: =Stock!R8 -> 0
A86: Colts (2 years) | B86: =Stock!R9 -> 0
A87: Colts (1 year) | B87: =Stock!R10 -> 0
A88: Foals | B88: =Stock!R11 -> 0
A89: Oxen | B89: =Stock!R12 -> 6.35
A90: Bulls | B90: =Stock!R13 -> 0
A91: Cows | B91: =Stock!R14 -> 0
A92: Steers | B92: =Stock!R15 -> 0
A93: Bullocks | B93: =Stock!R16 -> 0
... A107: Peacocks | B107: =Stock!R30 -> 0
A108: Total value of stock (sum of the above)
A109: Total value of production
A110: Value of sales | B110: =Stock!R31 -> 9.64
A112: Wool | B112: Value of production at sales prices £
A113: Fleeces | B113: =Stock!T35 -> 7.1
A114: from rams | B114: =Stock!T36 -> 0
A115: from ewes | B115: =Stock!T37 -> 0
A116: Coarse wool | B116: =Stock!T38 -> 0
A117: Lamb's wool | B117: =Stock!T39 -> 0
A118: Wool locks | B118: =Stock!T40 -> 0
A119: Wool sold at shearing | B119: =Stock!T41 -> 0
A120: Total value of production (sum of the above) | B120: =Stock!T42 -> 7.1
A121: Value of sales
A123: Hides | B123: Value of production at sales prices £
A124: Ox hides | B124: =Stock!T46 -> 0
A125: Cow hides | B125: =Stock!T47 -> 0
A126: Mare hides | B126: =Stock!T48 -> 0
A127: Steer hides | B127: =Stock!T49 -> 0
A128: Yearling Calf hides | B128: =Stock!T50 -> 0
A129: Calf hides | B129: =Stock!T51 -> 0
A130: Pig hides | B130: =Stock!T52 -> 0
A131: Wether woolskins | B131: =Stock!T53 -> 0
A132: Ram woolskins | B132: =Stock!T54 -> 0
A133: Ewe woolskins | B133: =Stock!T55 -> 0
A134: Hogg woolskins | B134: =Stock!T56 -> 0.34875
...

Sheet Receipts
A1: BURGHCLERE RECEIPTS
A2: Heading | B2: £ | C2: s | D2: d | F2: Total in £ | G2: Error | H2: Notes
A3: Arrears | B3: 37 | C3: 19 | D3: 10.5 | F3: 37.99 | H3: Henry la Wayte, bailiff, and John le Sone, reeve, render account for £37 19 shilling 10.5pence of arrears from the previous year.
A4: Arrears | B4: 0 | C4: 0 | D4: 0 | F4: 0 | H4: All delivered to Sir Geoffrey, treasurer of Wolvesey, by 1 tally.
A5: Arrears | B5: 0 | C5: 0 | D5: 0 | F5: 0 | H5: They are quit.
A6: Arrears | F6: 37.99 | G6: =F6-F3 -> 0 | H6: Total
A8: Rents | B8: 2 | C8: 7 | D8: 0 | F8: 2.35 | H8: The same render account for £2 7 shilling for all rents of assize at Christmas.
A9: Rents | B9: 2 | C9: 7 | D9: 0 | F9: 2.35 | H9: £2 7 shilling at Easter (22 April).
A10: Rents | B10: 2 | C10: 7 | D10: 0 | F10: 2.35 | H10: £2 7 shilling at the Nativity of St John the Baptist (24 June).
A11: Rents | B11: 16 | C11: 4 | D11: 6 | F11: 16.22 | H11: £16 4 shilling 6pence at Michaelmas (29 September).
A12: Rents | B12: 23 | C12: 5 | D12: 6 | F12: 23.27 | H12: Total, £23 5 shilling 6pence
A13: Rents | F13: =SUM(F8:F11) -> 23.27 | G13: 0 | H13: Total
A15: Increment | B15: 0 | C15: 0 | D15: 1 | F15: 0 | H15: The same render account for 1pence from John Scissor' for increment of rent to have entry to 1 plot, 36 feet long and 24 feet wide, beside the forge of la Wydegate.
A16: Increment | B16: 0 | C16: 0 | D16: 1 | F16: 0 | H16: Total, 1pence
A17: Increment | F17: 0 | G17: 0 | H17: Total
A19: Total of rents with increment | B19: 23 | C19: 15 | D19: 7 | F19: 23.78 | H19: Total of rents with increment, £23 15 shilling 7pence1
A20: Total of rents with increment | F20: 23.78 | G20: =F20-F19 -> 0 | H20: Total
A22: Quittances | B22: 0 | C22: 4 | D22: 8 | F22: 0.23 | H22: In quittance of 1 reeve for the year 4 shilling 8pence.
A23: Quittances | B23: 0 | C23: 3 | D23: 0 | F23: 0.15 | H23: 1 hayward for the year 3 shilling.
A24: Quittances | B24: 1 | C24: 1 | D24: 0 | F24: 1.05 | H24: 7 ploughmen for the year £1 1 shilling.
A25: Quittances | B25: 0 | C25: 1 | D25: 0 | F25: 0.05 | H25: 2 ploughmen for 1 term 1 shilling.
A26: Quittances | B26: 0 | C26: 1 | D26: 3 | F26: =B26+C26/20+D26/240 -> 0.0625 | H26: 1 shepherd for 2.5 terms 1 shilling 3pence
A27: Quittances | B27: 1 | C27: 10 | D27: 11 | F27: 1.55 | H27: Total, £1 10 shilling 11pence
A28: Quittances | F28: =SUM(F22:F26) -> 1.5425 | G28: =F28-F27 -> -0.0075 | H28: Total
A30: Defaults of rent | B30: 1 | C30: 17 | D30: 0 | F30: 1.85 | H30: In default of 335 acres of land drawn into demesne, £1 17 shilling for the year.
A31: Defaults of rent | B31: 0 | C31: 3 | D31: 0 | F31: 0.15 | H31: the land of Alwyn' drawn into demesne, 3 shilling for the year.
A32: Defaults of rent | B32: 0 | C32: 1 | D32: 8 | F32: 0.08 | H32: 10 acres of land of Roger Mainpetyt drawn into demesne, 1 shilling 8pence for the year.
A33: Defaults of rent | B33: 0 | C33: 2 | D33: 6 | F33: 0.12 | H33: 10 acres of land of Osmund' drawn into demesne, 2 shilling 6pence for the year.
A34: Defaults of rent | B34: 0 | C34: 1 | D34: 8 | F34: 0.08 | H34: 10 acres of land of Simon Clericus drawn into demesne, 1 shilling 8pence for the year.
A35: Defaults of rent | B35: 0 | C35: 1 | D35: 0 | F35: 0.05 | H35: the land of Alwyn drawn into demesne, 1 shilling for the year.
A36: Defaults of rent | B36: 0 | C36: 1 | D36: 0 | F36: 0.05 | H36: the land of Osmund Dustr' drawn into demesne, 1 shilling for the year.
A37: Defaults of rent | B37: 2 | C37: 7 | D37: 10 | F37: 2.39 | H37: Total, £2 7 shilling 10pence
A38: Defaults of rent | F38: =SUM(F30:F36) -> 2.38 | G38: =F38-F37 -> -0.01 | H38: Total
A40: Total of quittances and defaults of rent | B40: 3 | C40: 18 | D40: 9 | F40: 3.94 | H40: Total of quittances and defaults of rent, £3 18 shilling 9pence
A42: Release from labour service | B42: 0 | C42: 7 | D42: 0 | F42: 0.35 | H42: The same render account for 7 shilling from Richard le Eyr for release from his labour service for 1 virgate of land for the year.
A43: Release from labour service | B43: 0 | C43: 7 | D43: 0 | F43: 0.35 | H43: Total, 7 shilling
A44: Release from labour service | F44: 0.35 | G44: 0 | H44: Total
A46: Issues of the manor | B46: 1 | C46: 1 | D46: 9.5 | F46: 1.09 | H46: The same render account for £1 1 shilling 9.5pence from pannage of pigs within, that is, from 253 pigs and 13 piglets, at 1pence a pig and .5pence a piglet.
A47: Issues of the manor | B47: 0 | C47: 0 | D47: 0 | F47: 0 | H47: nothing from foreign pannage this year for a want of mast.
A48: Issues of the manor | B48: 1 | C48: 0 | D48: 0 | F48: 1 | H48: £1 from the pasturage of Oldehull' at Michaelmas.
A49: Issues of the manor | B49: 0 | C49: 5 | D49: 0 | F49: 0.25 | H49: 5 shilling1 from the men of Earlstone according to custom at the Nativity of St John the Baptist for herbage.
A50: Issues of the manor | B50: 0 | C50: 5 | D50: 0 | F50: 0.25 | H50: 5 shilling for the farm of the quarry at Michaelmas.
A51: Issues of the manor | B51: 0 | C51: 3 | D51: 0 | F51: 0.15 | H51: 3 shilling from the men of Addebury for not making charcoal at Christmas.
A52: Issues of the manor | B52: 0 | C52: 3 | D52: 0 | F52: 0.15 | H52: 3 shilling from the free men of Earlstone for release from ploughing at Michaelmas because the villeins plough for the winter sowing and fallow.
A53: Issues of the manor | B53: 0 | C53: 2 | D53: 0 | F53: 0.1 | H53: 2 shilling from honey according to custom at Michaelmas for land which Thomas Gerard holds.
A54: Issues of the manor | B54: 0 | C54: 7 | D54: 0 | F54: 0.35 | H54: 7 shilling from the pasturage of la Garston sold at Mic¬haelmas.
A55: Issues of the manor | B55: 0 | C55: 0 | D55: 0 | F55: 0 | H55: nothing from winter pasturage on account of the lord's stock.
A56: Issues of the manor | B56: 0 | C56: 0 | D56: 0 | F56: 0 | H56: nothing from summer pasturage for the same reason.
A57: Issues of the manor | B57: 0 | C57: 4 | D57: 0 | F57: 0.2 | H57: 4 shilling from 1 plough-horse from a heriot sold.
... A70: Issues of the manor | B70: 14 | C70: 15 | D70: 8 | F70: 14.78 | H70: Total, £14 15 shilling 8pence
A71: Issues of the manor | F71: 14.79 | G71: 0.01 | H71: Total
A73: Annual recognizance | B73: 0 | C73: 0 | D73: 0 | F73: 0 | H73: Nothing from Roger Mareschal because he is dead.
A74: Annual recognizance | B74: 0 | C74: 0 | D74: 3 | F74: 0.01 | H74: 3pence from Richard atte Heth' for annual recognizance.
A75: Annual recognizance | B75: 0 | C75: 0 | D75: 0 | F75: =B75+C75/20+D75/240 -> 0 | H75: nothing from John Lunt because he is dead
A76: Annual recognizance | B76: 0 | C76: 0 | D76: 3 | F76: =B76+C76/20+D76/240 -> 0.0125 | H76: Total, 3pence
A77: Annual recognizance | F77: =SUM(F73:F75) -> 0.01 | G77: =F77-F76 -> -0.0025 | H77: Total
A79: Sale of corn | B79: 30 | C79: 3 | D79: 4 | F79: 30.17 | H79: The same render account for £30 3 shilling 4pence from 90.5 quarters of wheat sold, at 6 shilling 8pence a qr.
A80: Sale of corn | B80: 5 | C80: 7 | D80: 6 | F80: 5.38 | H80: £5 7 shilling 6pence from 26 quarters 7 bushels of bere sold, at 4 shilling a qr.
A81: Sale of corn | B81: 0 | C81: 18 | D81: 6 | F81: 0.93 | H81: 18 shilling 6pence from 4 quarters 5 bushels of barley sold, at 4 shilling a qr.
A82: Sale of corn | B82: 4 | C82: 12 | D82: 10.5 | F82: 4.64 | H82: £4 12 shilling 10.5pence from 39 quarters 6 bushels of oats sold, at 2 shilling a qr for 13 quarters, and 2 shilling 6pence a qr for 26 quarters 6 bushels
A83: Sale of corn | B83: 41 | C83: 2 | D83: 2.5 | F83: =B83+C83/20+D83/240 -> 41.110417 | H83: Total of all corn sold, £41 2 shilling 2.5pence
A84: Sale of corn | F84: 41.12 | G84: =F84-F83 -> 0.0095833333 | H84: Total
A86: Sale of the mill's corn | B86: 0 | C86: 1 | D86: 6 | F86: 0.08 | H86: The same render account for 1 shilling 6pence from 2 bushels of wheat from the issue of the mill sold, at 9pence a bushels.
A87: Sale of the mill's corn | B87: 2 | C87: 8 | D87: 9 | F87: 2.44 | H87: £2 8 shilling 9pence from 14 quarters 5 bushels of maslin sold, at 3 shilling 4pence a qr.
A88: Sale of the mill's corn | B88: 0 | C88: 10 | D88: 6 | F88: 0.53 | H88: 10 shilling from 4 quarters of malt sold, at 2 shilling 6pence a qr.
A89: Sale of the mill's corn | B89: 3 | C89: 0 | D89: 3 | F89: 3.01 | H89: Total, £3 3pence
A90: Sale of the mill's corn | F90: 3.05 | G90: 0.04 | H90: Total
A92: Entry and marriage fines | B92: 1 | C92: 6 | D92: 8 | F92: 1.33 | H92: The same render account for £1 6 shilling 8pence from tithingpenny at the two hundred-courts for the year.
A93: Entry and marriage fines | B93: 0 | C93: 13 | D93: 4 | F93: 0.67 | H93: 13 shilling 4pence from Cecilia Marescall' to retain 0.5 virgate of land which belonged to her husband.
A94: Entry and marriage fines | B94: 0 | C94: 1 | D94: 0 | F94: 0.05 | H94: 1 shilling from John le Sone for marrying Agnes his daughter outside.
A95: Entry and marriage fines | B95: 0 | C95: 5 | D95: 0 | F95: 0.25 | H95: 5 shilling from Roger atte Garston to have 1 messuage 6.5 acres' of purpresture which belonged to Robert atte Garston' his uncle.
A96: Entry and marriage fines | B96: 0 | C96: 2 | D96: 0 | F96: 0.1 | H96: 2 shilling from Walter le Son' for marrying Isabel his daughter outside.
A97: Entry and marriage fines | B97: 0 | C97: 1 | D97: 0 | F97: 0.05 | H97: 1 shilling from John le Tayllor to have entry to a certain small plot, 36 feet long and 24 feet wide, beside the forge of la Wydegate.
A98: Entry and marriage fines | B98: 0 | C98: 1 | D98: 0 | F98: 0.05 | H98: 1 shilling from Edith (Aldich') Cuteles for marrying herself outside the manor.
A99: Entry and marriage fines | B99: 0 | C99: 5 | D99: 0 | F99: 0.25 | H99: 5 shilling from John Cutel of Whitway to have land which belonged to Adam Kutel his father by resignation of Edith Cutel his stepmother.
A100: Entry and marriage fines | B100: 2 | C100: 15 | D100: 0 | F100: 2.75 | H100: Total, £2 15 shilling
A101: Entry and marriage fines | F101: 2.75 | G101: 0 | H101: Total
A103: Perquisites | B103: 0 | C103: 2 | D103: 0 | F103: 0.1 | H103: The same render account for 2 shilling from Juliana Sone, John atte Park' and their fellows for trespass of pasture.
A104: Perquisites | B104: 0 | C104: 0 | D104: 2 | F104: 0.01 | H104: 2pence from William Tokelyn because he is convicted.
A105: Perquisites | B105: 0 | C105: 0 | D105: 6 | F105: 0.03 | H105: 6pence from William Frensch' and his fellows for concealment.
A106: Perquisites | B106: 0 | C106: 1 | D106: 3 | F106: 0.06 | H106: 1 shilling 3pence from Richard Kuppe and his fellows for trespass of pasture.
A107: Perquisites | B107: 0 | C107: 1 | D107: 3 | F107: 0.06 | H107: 1 shilling 3pence from John Lunt, Stephen Rotelond and Robert Lot for bad ploughing.
A108: Perquisites | B108: 0 | C108: 2 | D108: 3 | F108: 0.11 | H108: 2 shilling 3pence from John Cutel, Robert Lot and their fellows for trespass of pasture.
A109: Perquisites | B109: 0 | C109: 0 | D109: 6 | F109: 0.03 | H109: 6pence from Nicholas Tritur' and Stephen Bercarius for transgression.
A110: Perquisites | B110: 0 | C110: 3 | D110: 0 | F110: 0.15 | H110: 3 shilling from Ralph le Koc for carrying off 1 oak.
A111: Perquisites | B111: 0 | C111: 0 | D111: 3 | F111: 0.01 | H111: 3pence from William Bykemere and Richard le Sone for transgression.
A112: Perquisites | B112: 0 | C112: 0 | D112: 3 | F112: 0.01 | H112: 3pence from Stephen de Aul' for unjustly withholding.
A113: Perquisites | B113: 0 | C113: 3 | D113: 0 | F113: 0.15 | H113: 3 shilling from John Burch' and his fellows for breaking the assize.
A114: Perquisites | B114: 0 | C114: 2 | D114: 0 | F114: 0.1 | H114: 2 shilling from John Druery for bloodshed.
... A141: Perquisites | B141: 2 | C141: 13 | D141: 3 | F141: 2.66 | H141: Total, £2 13 shilling 3pence
A142: Perquisites | F142: 2.61 | G142: -0.05 | H142: Total
A145: Total of all receipts recorded in accounts | B145: 84 | C145: 0 | D145: 5.5 | F145: 84.02 | H145: Total of all receipts, £84 5.5pence
A146: Total cross-check without arrears | F146: =F142++F101+F90+F84+F77+F71+F44+F20-F28-F37 -> 84.5275 | G146: =F146-F145 -> 0.5075
A147: Total cross-check with arrears | F147: =F146+F6 -> 122.5175

Sheet Expenses
A1: BURGHCLERE RECEIPTS
A2: Heading | B2: £ | C2: s | D2: d | F2: Total in £ | G2: Error | H2: Notes | J2: Fixed investment | K2: Demesne fixed investment
A3: Cost of ploughs | B3: 0 | C3: 6 | D3: 3 | F3: 0.31 | H3: In the ironwork of 5 ploughs for the year and 1 plough for 1 term 6 shilling 3pence. | J3: =F3 -> 0.31 | K3: =J3 -> 0.31
A4: Cost of ploughs | B4: 0 | C4: 0 | D4: 0 | F4: 0 | H4: stipend of 1 smith, nothing, because he takes 1 acre of wheat for his stipenpence.
A5: Cost of ploughs | B5: 0 | C5: 1 | D5: 6 | F5: =B5+C5/20+D5/240 -> 0.075 | H5: 6 plough-irons bought 1 shilling, 6pence. | J5: =F5 -> 0.075 | K5: =J5 -> 0.075
A6: Cost of ploughs | B6: 0 | C6: 0 | D6: 10 | F6: 0.04 | H6: 1 coulter bought 10pence. | J6: =F6 -> 0.04 | K6: =J6 -> 0.04
A7: Cost of ploughs | B7: 0 | C7: 3 | D7: 4 | F7: 0.17 | H7: 4 ploughshares 3 shilling 4pence. | J7: =F7 -> 0.17 | K7: =J7 -> 0.17
A8: Cost of ploughs | B8: 0 | C8: 1 | D8: 4 | F8: 0.07 | H8: 3 ploughs made anew and others mended, fitted with share-beams, and covered with boards for the year, 1 shilling 4pence. | J8: =F8 -> 0.07 | K8: =J8 -> 0.07
A9: Cost of ploughs | B9: 0 | C9: 0 | D9: 6 | F9: 0.03 | H9: yokes and wooden halters made 6pence. | J9: =F9 -> 0.03 | K9: =J9 -> 0.03
A10: Cost of ploughs | B10: 0 | C10: 1 | D10: 0 | F10: 0.05 | H10: 4 pairs of wheels bought 1 shilling. | J10: =F10 -> 0.05 | K10: =J10 -> 0.05
A11: Cost of ploughs | B11: 0 | C11: 13 | D11: 4 | F11: 0.67 | H11: boon-works of 40 ploughmen in winter and as many in Lent who ploughed as many acres as they lie 13 shilling 4pence, or 2pence a ploughman a day.
A12: Cost of ploughs | B12: 0 | C12: 0 | D12: 0 | F12: 0 | H12: Moreover, each ploughman will plough 1 acre in summer for fallow without food according to custom.
A13: Cost of ploughs | B13: 0 | C13: 19 | D13: 3 | F13: 0.96 | H13: reward of 8 ploughmen for the year and 2 for 1 term for their Saturday ploughings 19 shilling 3pence, each taking 2 shilling less than they are accustomed, because more than accustomed was delivered to one sergeant who is there, and besides this they should each remove 1 horse which they are accustomed to have in the lord's pasture.
A14: Cost of ploughs | B14: 0 | C14: 0 | D14: 4 | F14: 0.02 | H14: healing (medicinand) oxen 4pence.
A15: Cost of ploughs | B15: 13 | C15: 19 | D15: 5 | F15: 13.97 | H15: 24 oxen bought for ploughs £13 19 shilling 5pence, at 10 shilling 3pence each for 2, 11 shilling 2pence each for 15, and 13 shilling each for 7, plus 5pence in all.
A16: Cost of ploughs | B16: 0 | C16: 9 | D16: 0 | F16: 0.45 | H16: stipend of 3 oxherds for the year 9 shilling.
A17: Cost of ploughs | B17: 1 | C17: 15 | D17: 10 | F17: 1.79 | H17: 10 quarters 6 bushels of maslin bought for the liveries of the manorial servants £1 15 shilling 10pence, at 3 shilling 4pence a qr.
A18: Cost of ploughs | B18: 0 | C18: 12 | D18: 0 | F18: 0.6 | H18: 3 quarters of barley bought for sowing 12 shilling, at 4 shilling a qr.
A19: Cost of ploughs | B19: 19 | C19: 3 | D19: 11 | F19: 19.2 | H19: Total, £19 3 shilling 11pence
A20: Cost of ploughs | F20: =SUM(F3:F18) -> 19.205 | G20: =F20-F19 -> 0.005 | H20: Total
A22: Cost of carts | B22: 0 | C22: 2 | D22: 0 | F22: 0.1 | H22: In clouts, nails, grease and white leather bought for the carts for the year, and fitting 3 carts with axles at various times, 2 shilling. | J22: =F22 -> 0.1 | K22: =F22 -> 0.1
A23: Cost of carts | B23: 0 | C23: 1 | D23: 1 | F23: 0.05 | H23: 2 collars bought 1 shilling 1pence. | J23: =F23 -> 0.05 | K23: =F23 -> 0.05
A24: Cost of carts | B24: 0 | C24: 0 | D24: 6 | F24: 0.03 | H24: 1 pair of tie-beams 6pence. | J24: =F24 -> 0.03 | K24: =F24 -> 0.03
A25: Cost of carts | B25: 0 | C25: 1 | D25: 1 | F25: 0.05 | H25: 2 pairs of traces bought 1 shilling 1pence. | J25: =F25 -> 0.05 | K25: =F25 -> 0.05
A26: Cost of carts | B26: 0 | C26: 0 | D26: 5 | F26: 0.02 | H26: 2 halters bought 5pence. | J26: =F26 -> 0.02 | K26: =F26 -> 0.02
A27: Cost of carts | B27: 0 | C27: 0 | D27: 4 | F27: 0.02 | H27: 1 saddle-base bought 4pence. | J27: =F27 -> 0.02 | K27: =F27 -> 0.02
A28: Cost of carts | B28: 0 | C28: 1 | D28: 2 | F28: 0.06 | H28: 1 cart-rope 1 shilling 2pence. | J28: =F28 -> 0.06 | K28: =F28 -> 0.06
A29: Cost of carts | B29: 0 | C29: 3 | D29: 6 | F29: 0.17 | H29: shoeing 3 cart-horses for the year and 1 for 1 term 3 shilling 6pence. | J29: =F29 -> 0.17 | K29: =F29 -> 0.17
A30: Cost of carts | B30: 0 | C30: 3 | D30: 0 | F30: =B30+C30/20+D30/240 -> 0.15 | H30: stipend of 1 carter for the year 3 shilling | J30: =F30 -> 0.15 | K30: =J30/2 -> 0.075
A31: Cost of carts | B31: 0 | C31: 13 | D31: 1 | F31: =B31+C31/20+D31/240 -> 0.65416667 | H31: Total, 13 shilling 1pence
A32: Cost of carts | F32: 0.65 | G32: =F32-F31 -> -0.0041666667 | H32: Total
A34: Cost of buildings | B34: 0 | C34: 1 | D34: 6 | F34: =B34+C34/20+D34/240 -> 0.075 | H34: In roofing the wheat-barn in places 1 shilling 6pence. | J34: =F34 -> 0.075 | K34: =J34 -> 0.075
A35: Cost of buildings | B35: 0 | C35: 3 | D35: 0 | F35: =B35+C35/20+D35/240 -> 0.15 | H35: roofing and mending the byre and sheepcote beside the church in places 3 shilling. | J35: =F35 -> 0.15 | K35: =J35 -> 0.15
A36: Cost of buildings | B36: 0 | C36: 1 | D36: 3 | F36: =B36+C36/20+D36/240 -> 0.0625 | H36: roofing the sheepcote of Landecumbe 1 shilling 3pence. | J36: =F36 -> 0.0625 | K36: =J36 -> 0.0625
A37: Cost of buildings | B37: 0 | C37: 1 | D37: 6 | F37: =B37+C37/20+D37/240 -> 0.075 | H37: constructing 2 perches of palisade between the curia and the cemetery 1 shilling 6pence. | J37: =F37 -> 0.075 | K37: =J37 -> 0.075
A38: Cost of buildings | B38: 0 | C38: 1 | D38: 0 | F38: =B38+C38/20+D38/240 -> 0.05 | H38: pulling down the old byre 1 shilling. | J38: =F38 -> 0.05 | K38: =J38 -> 0.05
A39: Cost of buildings | B39: 0 | C39: 4 | D39: 0 | F39: =B39+C39/20+D39/240 -> 0.2 | H39: cleaning the grips in the field 4 shilling.
A40: Cost of buildings | B40: 0 | C40: 1 | D40: 6 | F40: =B40+C40/20+D40/240 -> 0.075 | H40: marling the land sown with barley 1 shilling 6pence.
A41: Cost of buildings | B41: 0 | C41: 13 | D41: 10 | F41: =B41+C41/20+D41/240 -> 0.69166667 | H41: forage bought 13 shilling 10pence.
A42: Cost of buildings | B42: 0 | C42: 5 | D42: 0 | F42: =B42+C42/20+D42/240 -> 0.25 | H42: 3 pigs bought 5 shilling
A43: Cost of buildings | B43: 1 | C43: 8 | D43: 11 | F43: =B43+C43/20+D43/240 -> 1.4458333 | H43: Total, £1 8 shilling 11pence
A44: Cost of buildings | F44: =SUM(F34:F42) -> 1.6291667 | G44: =F44-F43 -> 0.18333333 | H44: Total
A46: Sheepcote and sheepfold | B46: 0 | C46: 12 | D46: 4 | F46: 0.62 | H46: In grease bought for greasing sheep 12 shilling 4pence. | J46: =F46 -> 0.62 | K46: =J46 -> 0.62
A47: Sheepcote and sheepfold | B47: 0 | C47: 1 | D47: 0 | F47: 0.05 | H47: stipend of 1 shepherd for' year 1 shilling. | J47: =F47 -> 0.05 | K47: =J47 -> 0.05
A48: Sheepcote and sheepfold | B48: 0 | C48: 0 | D48: 5 | F48: 0.02 | H48: wattling the fold 5pence. | J48: =F48 -> 0.02 | K48: =J48 -> 0.02
A49: Sheepcote and sheepfold | B49: 0 | C49: 0 | D49: 2 | F49: =B49+C49/20+D49/240 -> 0.0083333333 | H49: mending hurdles bought 2pence | J49: =F49 -> 0.0083333333 | K49: =J49 -> 0.0083333333
A50: Sheepcote and sheepfold | B50: 0 | C50: 13 | D50: 11 | F50: =B50+C50/20+D50/240 -> 0.69583333 | H50: Total, 13 shilling 11pence
A51: Sheepcote and sheepfold | F51: =SUM(F46:F49) -> 0.69833333 | G51: =F51-F50 -> 0.0025 | H51: Total
A53: Threshing and winnowing | B53: 0 | C53: 17 | D53: 4 | F53: 0.87 | H53: In threshing and winnowing 104 quarters of wheat by piece-work 17 shilling 4pence, at 2pence a qr.
A54: Threshing and winnowing | B54: 0 | C54: 5 | D54: 8.5 | F54: 0.29 | H54: threshing 39 quarters 1 bushels of bere by piece-work 5 shilling 8.5pence, at 1.75pence a qr.
A55: Threshing and winnowing | B55: 0 | C55: 0 | D55: 10.25 | F55: 0.04 | H55: threshing and winnowing 8 quarters 2 bushels of barley by piece-work 10.25pence, at 1.25pence a qr.
A56: Threshing and winnowing | B56: 0 | C56: 5 | D56: 1.75 | F56: 0.26 | H56: threshing 123.5 quarters of oats by piece-work 5 shilling 1.75pence, at .5pence a qr.
A57: Threshing and winnowing | B57: 0 | C57: 1 | D57: 3.5 | F57: 0.06 | H57: winnowing the same 1 shilling 3.5pence, at 1pence per 8 quarters.
A58: Threshing and winnowing | B58: 0 | C58: 1 | D58: 9.75 | F58: 0.09 | H58: 4 sacks bought 1 shilling 9.75pence.
A59: Threshing and winnowing | B59: 0 | C59: 0 | D59: 3 | F59: =B59+C59/20+D59/240 -> 0.0125 | H59: 1 basket bought 3pence
A60: Threshing and winnowing | B60: 1 | C60: 12 | D60: 4.75 | F60: =B60+C60/20+D60/240 -> 1.6197917 | H60: Total, £1 12 shilling 4.75pence
A61: Threshing and winnowing | F61: =SUM(F53:F59) -> 1.6225 | G61: =F61-F60 -> 0.0027083333 | H61: Total
A63: Weeding | B63: 0 | C63: 3 | D63: 4 | F63: 0.17 | H63: In weeding corn this year 3 shilling 4pence
A64: Weeding | F64: 0.17 | H64: Total, 3 shilling 4pence
A65: Weeding | F65: 0.17 | G65: 0 | H65: Total
A67: Harvest-time | B67: 0 | C67: 0 | D67: 6 | F67: 0.03 | H67: In mowing 10 acres of meadow according to custom 6pence.
A68: Harvest-time | B68: 0 | C68: 13 | D68: 4 | F68: 0.67 | H68: 2 boon-works of 167 men with the officials of the curia who reaped 65 acres of wheat and 66 acres of oats as they lie 13 shilling 4pence.
A69: Harvest-time | B69: 0 | C69: 6 | D69: 9 | F69: 0.34 | H69: 1 boon-work of 81 free men of Eneburn and Earlstone who reaped 33 acres of wheat as they lie 6 shilling 9pence, as in bread, ale and relish.
A70: Harvest-time | B70: 0 | C70: 6 | D70: 2 | F70: 0.31 | H70: 36 acres of oats reaped by piece-work 6 shilling, at 2pence an acre.
A71: Harvest-time | B71: 1 | C71: 6 | D71: 7 | F71: 1.33 | H71: Total, £1 6 shilling 7pence
A72: Harvest-time | F72: 1.35 | G72: =F72-F71 -> 0.02 | H72: Total
A74: Cost of the mill | B74: 0 | C74: 0 | D74: 4 | F74: 0.02 | H74: In roofing the mill-building 4pence. | J74: =F74 -> 0.02
A75: Cost of the mill | B75: 0 | C75: 0 | D75: 4 | F75: 0.02 | H75: steeling and mending bills 4pence. | J75: =F75 -> 0.02
A76: Cost of the mill | B76: 0 | C76: 0 | D76: 3 | F76: 0.01 | H76: 1 gudgeon for the driving-shaft of the mill 3pence. | J76: =F76 -> 0.01
A77: Cost of the mill | B77: 0 | C77: 2 | D77: 1.5 | F77: 0.11 | H77: 1 large mill-iron made under the driving-shaft of the mill with iron bought for the same 2 shilling 1.5pence. | J77: =F77 -> 0.11
A78: Cost of the mill | B78: 0 | C78: 10 | D78: 2 | F78: 0.51 | H78: 40 ells of canvas bought for the mill's sails 10 shilling 2pence, at 3.25pence an ell. | J78: =F78 -> 0.51
A79: Cost of the mill | B79: 0 | C79: 0 | D79: 6 | F79: 0.03 | H79: grease bought 6pence. | J79: =F79 -> 0.03
A80: Cost of the mill | B80: 0 | C80: 6 | D80: 0 | F80: =B80+C80/20+D80/240 -> 0.3 | H80: stipend of 1 miller for the year 6 shilling | J80: =F80 -> 0.3
A81: Cost of the mill | B81: 1 | C81: 0 | D81: 4.5 | F81: =B81+C81/20+D81/240 -> 1.01875 | H81: Total, £1 4.5pence
A82: Cost of the mill | F82: 1.72 | G82: =F82-F81 -> 0.70125 | H82: Total
A84: Total of all expenses | B84: 26 | C84: 2 | D84: 6.25 | F84: 26.13 | H84: Total of all expenses, £26 2 shilling 6.25pence
A85: Total of all expenses | F85: 26.13 | G85: =F85-F84 -> 0 | H85: Total
A88: And he owes | B88: 57 | C88: 17 | D88: 11.25 | F88: 57.9 | H88: And he owes, £57 17 shilling 11.25pence
A89: And he owes | F89: 57.9 | G89: 0 | H89: Total
A92: Cash deliveries | B92: 30 | C92: 13 | D92: 4 | F92: 30.67 | H92: Delivered to Sir Geoffrey, treasurer of Wolvesey, by 1 tally, £30 13 shilling 4pence
A94: Total of all expenses per account | F94: =F85 -> 26.13
A95: Total of all expenses (calculated here) | F95: =F82+F72+F65+F61+F51+F44+F32+F20 -> 27.045 | G95: =F95-F94 -> 0.915
A96: Total fixed investment | F96: =SUM(J3:J81) -> 3.5058333
A97: Total Demesne fixed investment | F97: =SUM(K3:K80) -> 2.4308333

Sheet Issues of the Grange
A1: Gross Output | B1: Total Quantity | C1: Account Total Quarters | D1: Bought in Total Quarters | E1: Received from churchscot | F1: Sold Total Quarters | G1: Difference Produced+Bought-Sold | H1: Weighted Average Price per Quarter | I1: Value of Total Production weighted
A2: wheat | B2: 135.625 | D2: 0 | F2: 90.5 | G2: =B2-F2 -> 45.125 | H2: 0.33333333 | I2: =H2*B2 -> 45.208333
A3: bere | B3: 60.875 | D3: 10.75 | F3: 26.875 | G3: =B3-F3 -> 34 | H3: 0.2 | I3: =H3*B3 -> 12.175
A4: barley | B4: 13.75 | D4: 3 | F4: 4.625 | G4: =B4-F4 -> 9.125 | H4: 0.2 | I4: =H4*B4 -> 2.75
A5: oats | B5: 181.125 | D5: 0 | F5: 39.75 | G5: =B5-F5 -> 141.375 | H5: 0.1168239 | I5: =H5*B5 -> 21.159729
A7: Total Production
A8: Sales of corn (as recorded in accounts)
A10: Net output | B10: Gross output | C10: Seed quarters | D10: Seed bushels | E10: Seed total quarters | F10: tithe quarters | G10: tithe bushels | H10: tithe total | I10: manorial servants quarters | J10: manorial servants bushels | K10: manorial servants total quarters | L10: output net of tithe, seed, liveries | M10: in stock from last year | N10: Price in £ | O10: Value of net output in £ | P10: Value of sales (in "Sale of Corn") in £
A11: wheat | B11: =B2 -> 135.625 | C11: 31 | D11: 1 | E11: =C11+D11/8 -> 31.125 | I11: =1.5+4+7.5 -> 13 | J11: =1+6+1 -> 8 | K11: =I11+J11/8 -> 14 | L11: =B11-E11-H11-K11 -> 90.5 | N11: =H2 -> 0.33333333 | O11: =N11*L11 -> 30.166667
A12: bere | B12: =B3 -> 60.875 | C12: 4 | D12: 5 | E12: =C12+D12/8 -> 4.625 | I12: =20+2.5+1+4 -> 27.5 | J12: =6+4+3+2 -> 15 | K12: =I12+J12/8 -> 29.375 | L12: =B12-E12-H12-K12 -> 26.875 | N12: =H3 -> 0.2 | O12: =N12*L12 -> 5.375
A13: barley | B13: =B4 -> 13.75 | C13: 8.5 | D13: 1 | E13: =C13+D13/8 -> 8.625 | J13: 4 | K13: =I13+J13/8 -> 0.5 | L13: =B13-E13-H13-K13 -> 4.625 | N13: =H4 -> 0.2 | O13: =N13*L13 -> 0.925
A14: oats | B14: =B5 -> 181.125 | C14: 90 | D14: 7 | E14: =C14+D14/8 -> 90.875 | I14: =6.5+4+24+12.5 -> 47 | J14: =1+5+2 -> 8 | K14: =I14+J14/8 -> 48 | L14: =B14-E14-H14-K14 -> 42.25 | N14: =H5 -> 0.1168239 | O14: =N14*L14 -> 4.9358097
A16: Total

Sheet Issues of the Mills

Sheet Stock
A1: BURGHCLERE STOCK ACCOUNT
C3: added | G3: subtracted
A4: Livestock | B4: Inherited stock | C4: added | D4: strays | E4: herbage | F4: churchscot | G4: of which in default | H4: sold | I4: in murrain | J4: accounted for elsewhere | K4: End-period stock | L4: cross-check | M4: stock building | N4: raw production | O4: Unit price (£) | P4: Value of stock (£) at given value | Q4: Value of stock (£) at sales prices | R4: Sales in (£) | S4: Value of stock building (£) | T4: Value of production (£) at sales prices | U4: Details
A5: Cart-horses | B5: 4 | K5: 4 | L5: =B5+C5+D5+E5+F5-G5-H5-I5-J5 -> 4 | M5: =K5-B5 -> 0
A6: Mares | C6: 1 | H6: 1 | K6: 0 | L6: =B6+C6+D6+E6+F6-G6-H6-I6-J6 -> 0 | M6: =K6-B6 -> 0 | R6: =Receipts!F57 -> 0.2 | U6: noted as a plough horse in issues
A7: Plough horses | L7: =B7+C7+D7+E7+F7-G7-H7-I7-J7 -> 0 | M7: =K7-B7 -> 0
A8: Colts (unspecified years) | L8: =B8+C8+D8+E8+F8-G8-H8-I8-J8 -> 0 | M8: =K8-B8 -> 0
A9: Colts (2 years) | L9: =B9+C9+D9+E9+F9-G9-H9-I9-J9 -> 0 | M9: =K9-B9 -> 0
A10: Colts (1 year) | L10: =B10+C10+D10+E10+F10-G10-H10-I10-J10 -> 0 | M10: =K10-B10 -> 0
A11: Foals | L11: =B11+C11+D11+E11+F11-G11-H11-I11-J11 -> 0 | M11: =K11-B11 -> 0
A12: Oxen | B12: 56 | C12: 24 | H12: 14 | I12: =7+2 -> 9 | K12: 57 | L12: =B12+C12+D12+E12+F12-G12-H12-I12-J12 -> 57 | M12: =K12-B12 -> 1 | R12: =Receipts!F58 -> 6.35
A13: Bulls | L13: =B13+C13+D13+E13+F13-G13-H13-I13-J13 -> 0 | M13: =K13-B13 -> 0
A14: Cows | L14: =B14+C14+D14+E14+F14-G14-H14-I14-J14 -> 0 | M14: =K14-B14 -> 0
A15: Steers | L15: =B15+C15+D15+E15+F15-G15-H15-I15-J15 -> 0 | M15: =K15-B15 -> 0
A16: Bullocks | L16: =B16+C16+D16+E16+F16-G16-H16-I16-J16 -> 0 | M16: =K16-B16 -> 0
A17: Yearlings | L17: =B17+C17+D17+E17+F17-G17-H17-I17-J17 -> 0 | M17: =K17-B17 -> 0
A18: Calves | L18: =B18+C18+D18+E18+F18-G18-H18-I18-J18 -> 0 | M18: =K18-B18 -> 0
A19: Wethers | L19: =B19+C19+D19+E19+F19-G19-H19-I19-J19 -> 0 | M19: =K19-B19 -> 0
A20: Rams | B20: 16 | C20: 4 | H20: 1 | I20: 2 | J20: 3 | K20: 14 | L20: =B20+C20+D20+E20+F20-G20-H20-I20-J20 -> 14 | M20: =K20-B20 -> -2 | O20: =R20/(H20+H21) -> 0.03325 | R20: =Receipts!F60 -> 1.33
A21: Ewes | B21: 409 | C21: 138 | H21: 39 | I21: =7+18+7 -> 32 | K21: 476 | L21: =B21+C21+D21+E21+F21-G21-H21-I21-J21 -> 476 | M21: =K21-B21 -> 67 | O21: =R20/(H20+H21) -> 0.03325 | R21: =Receipts!F60 -> 1.33
A22: Hoggs | L22: =B22+C22+D22+E22+F22-G22-H22-I22-J22 -> 0 | M22: =K22-B22 -> 0
A23: Lambs | C23: 345 | H23: 39 | I23: =7+57 -> 64 | J23: =28+3 -> 31 | K23: 257 | L23: =B23+C23+D23+E23+F23-G23-H23-I23-J23 -> 211 | M23: =K23-B23 -> 257 | U23: cannot be found in issues
A24: Boars | L24: =B24+C24+D24+E24+F24-G24-H24-I24-J24 -> 0 | M24: =K24-B24 -> 0
A25: Sows | L25: =B25+C25+D25+E25+F25-G25-H25-I25-J25 -> 0 | M25: =K25-B25 -> 0
A26: Pigs | C26: 3 | H26: 3 | K26: 0 | L26: =B26+C26+D26+E26+F26-G26-H26-I26-J26 -> 0 | M26: =K26-B26 -> 0 | O26: =R26/H26 -> 0.14333333 | R26: =Receipts!F68 -> 0.43
A27: Hoggets
A28: Piglets
A29: Swans
A30: Peacocks
A31: Total Value | R31: =SUM(R5:R29) -> 9.64
A34: Wool / Fleeces
A35: Fleeces | B35: =SUM(B36:B37) -> 355 | J35: =35+320 -> 355 | O35: 0.02 | T35: =O35*J35 -> 7.1
A36: from rams | B36: 10
A37: from ewes | B37: 345
A38: Coarse wool
A39: Lamb's wool
A40: Wool locks
A41: Wool sold at shearing
A42: Total wool | T42: =SUM(T35:T41) -> 7.1
A45: Hides
A46: Ox hides
A47: Mare
A48: Steer
A49: calves
A50: pigs
A51: Woolskins
A52: wethers
A53: rams | C53: 2
A54: ewes | C54: 25
A55: hoggs
A56: Woolskins | C56: =SUM(C53:C54) -> 27 | H56: 24 | J56: 3 | O56: =R56/H56 -> 0.012916667 | R56: =Receipts!F63 -> 0.31 | T56: =O56*C56 -> 0.34875
A57: Bareskins | T57: =O57*C57 -> 0
A58: wethers | T58: =O58*C58 -> 0
A59: rams | T59: =O59*C59 -> 0
A60: ewes | C60: 7 | T60: =O60*C60 -> 0
A61: hoggs | T61: =O61*C61 -> 0
A62: Bareskins (total) | T62: =O62*C62 -> 0
A63: Lambskins | C63: 57 | H63: 52 | J63: 5 | O63: =R63/H63 -> 0.0042307692 | R63: =Receipts!F65 -> 0.22 | T63: =O63*C63 -> 0.24115385
A64: Rotted skins | T64: =O64*C64 -> 0
A65: Shorn skins | T65: =O65*C65 -> 0
A66: Total | R66: =SUM(R46:R65) -> 0.53 | T66: =SUM(T56:T65) -> 0.58990385
A69: Poultry stock
A70: Hens
A71: Geese
A72: Capons (from chickens)
A73: Cocks & hens
A74: Total poultry stock
A75: Total poultry excluding churchscot
A77: Poultry production
A78: Eggs | F78: 1100 | H78: 1100 | O78: =R78/H78 -> 0.00014545455 | R78: =Receipts!F67 -> 0.16 | T78: =O78*H78 -> 0.16
A79: Cocks & hens from churchscot of customary tenants | F79: 172 | G79: 27 | H79: 145 | O79: =R79/H79 -> 0.004137931 | R79: =Receipts!F66 -> 0.6 | T79: =O79*H79 -> 0.6
A80: Sum of above
A81: Total | R81: =SUM(R78:R80) -> 0.76 | T81: =SUM(T78:T79) -> 0.76
A84: Meat
A85: Beef
A86: Mutton
A87: Pork
A88: Total
A90: Cheese
A91: Winter cheese
A92: Summer cheese
A93: Total
A95: Butter
A96: Butter
A97: Total
... A131: brass posnets

Sheet raw data
A1: Heading | B1: Sentence | C1: Total in Pounds | D1: Pounds | E1: Shillings | F1: Pence | G1: Corn | H1: Total Quarters Except 1 | I1: Total Bushels Except 1 | J1: Total Corn Cross-Check | K1: Total Corn Manorial Account | L1: Corn Quantity Error | M1: Quarters 1 | N1: Bushels 1 | O1: Quarters 2 | P1: Bushels 2 | Q1: Quarters 3 | R1: Bushels 3 | S1: shilling a quarter 1 | T1: pence a quarter 1 | U1: shilling a quarter 2 | V1: pence a quarter 2 | W1: shilling a quarter 3 | X1: pence a quarter 3 | Y1: shilling a quarter 4 | Z1: pence a quarter 4 | AA1: shilling a bushel 1 | AB1: pence a bushel 1 | AC1: shilling a bushel 2 | AD1: pence a bushel 2 | AE1: shilling a bushel 3 | AF1: pence a bushel 3 | AG1: shilling a bushel 4 | AH1: pence a bushel 4
A2: Arrears | B2: Henry la Wayte, bailiff, and John le Sone, reeve, render account for £37 19 shilling 10.5pence of arrears from the previous year. | C2: 37.99 | D2: 37 | E2: 19 | F2: 10.5 | H2: 0 | I2: 0 | J2: 0 | K2: 0 | L2: 0 | M2: 0 | N2: 0
A3: Arrears | B3: All delivered to Sir Geoffrey, treasurer of Wolvesey, by 1 tally. | C3: 0 | D3: 0 | E3: 0 | F3: 0 | H3: 0 | I3: 0 | J3: 0 | K3: 0 | L3: 0 | M3: 0 | N3: 0
A4: Arrears | B4: They are quit. | C4: 0 | D4: 0 | E4: 0 | F4: 0 | H4: 0 | I4: 0 | J4: 0 | K4: 0 | L4: 0 | M4: 0 | N4: 0
A5: Rents | B5: The same render account for £2 7 shilling for all rents of assize at Christmas. | C5: 2.35 | D5: 2 | E5: 7 | F5: 0 | H5: 0 | I5: 0 | J5: 0 | K5: 0 | L5: 0 | M5: 0 | N5: 0
A6: Rents | B6: £2 7 shilling at Easter (22 April). | C6: 2.35 | D6: 2 | E6: 7 | F6: 0 | H6: 0 | I6: 0 | J6: 0 | K6: 0 | L6: 0 | M6: 0 | N6: 0
A7: Rents | B7: £2 7 shilling at the Nativity of St John the Baptist (24 June). | C7: 2.35 | D7: 2 | E7: 7 | F7: 0 | H7: 0 | I7: 0 | J7: 0 | K7: 0 | L7: 0 | M7: 0 | N7: 0
A8: Rents | B8: £16 4 shilling 6pence at Michaelmas (29 September). | C8: 16.22 | D8: 16 | E8: 4 | F8: 6 | H8: 0 | I8: 0 | J8: 0 | K8: 0 | L8: 0 | M8: 0 | N8: 0
A9: Rents | B9: Total, £23 5 shilling 6pence | C9: 23.27 | D9: 23 | E9: 5 | F9: 6 | H9: 0 | I9: 0 | J9: 0 | K9: 0 | L9: 0 | M9: 0 | N9: 0
A10: Increment | B10: The same render account for 1pence from John Scissor' for increment of rent to have entry to 1 plot, 36 feet long and 24 feet wide, beside the forge of la Wydegate. | C10: 0 | D10: 0 | E10: 0 | F10: 1 | H10: 0 | I10: 0 | J10: 0 | K10: 0 | L10: 0 | M10: 0 | N10: 0
A11: Increment | B11: Total, 1pence | C11: 0 | D11: 0 | E11: 0 | F11: 1 | H11: 0 | I11: 0 | J11: 0 | K11: 0 | L11: 0 | M11: 0 | N11: 0
A12: Total of rents with increment | B12: Total of rents with increment, £23 15 shilling 7pence1 | C12: 23.78 | D12: 23 | E12: 15 | F12: 7 | H12: 0 | I12: 0 | J12: 0 | K12: 0 | L12: 0 | M12: 0 | N12: 0
A13: Quittances | B13: In quittance of 1 reeve for the year 4 shilling 8pence. | C13: 0.23 | D13: 0 | E13: 4 | F13: 8 | H13: 0 | I13: 0 | J13: 0 | K13: 0 | L13: 0 | M13: 0 | N13: 0
... A57: Annual recognizance | B57: nothing from John Lunt because he is deapence Total, 3pence | C57: 0.01 | D57: 0 | E57: 0 | F57: 3 | H57: 0 | I57: 0 | J57: 0 | K57: 0 | L57: 0 | M57: 0 | N57: 0
A58: Sale of corn | B58: The same render account for £30 3 shilling 4pence from 90.5 quarters of wheat sold, at 6 shilling 8pence a quarters. | C58: 30.17 | D58: 30 | E58: 3 | F58: 4 | G58: wheat | H58: 90.5 | I58: 0 | J58: 90.5 | K58: 90.5 | L58: 0 | M58: 90.5 | N58: 0 | S58: 6 | T58: 8
A59: Sale of corn | B59: £5 7 shilling 6pence from 26 quarters 7 bushels of bere sold, at 4 shilling a quarters. | C59: 5.38 | D59: 5 | E59: 7 | F59: 6 | H59: 26 | I59: 7 | J59: 26.875 | K59: 26.875 | L59: 0 | M59: 26 | N59: 7 | S59: 4 | T59: 0
A60: Sale of corn | B60: 18 shilling 6pence from 4 quarters 5 bushels of barley sold, at 4 shilling a quarters. | C60: 0.93 | D60: 0 | E60: 18 | F60: 6 | G60: barley | H60: 4 | I60: 5 | J60: 4.625 | K60: 4.625 | L60: 0 | M60: 4 | N60: 5 | S60: 4 | T60: 0
A61: Sale of corn | B61: £4 12 shilling 10.5pence from 39 quarters 6 bushels of oats sold, at 2 shilling a quarters for 13 quarters, and 2 shilling 6pence a quarters for 26 quarters 6 bushels Total of all corn sold, £41 2 shilling 2.5pence | C61: 4.64 | D61: 4 | E61: 12 | F61: 10.5 | G61: oats | H61: 39 | I61: 6 | J61: 39.75 | K61: 39.75 | L61: 0 | M61: 39 | N61: 6 | O61: 13 | P61: 0 | Q61: 26 | R61: 6 | S61: 2 | T61: 0 | U61: 2 | V61: 6
A62: Sale of the mill's corn | B62: The same render account for 1 shilling 6pence from 2 bushels of wheat from the issue of the mill sold, at 9pence a bushels. | C62: 0.08 | D62: 0 | E62: 1 | F62: 6 | G62: wheat | H62: 0 | I62: 2 | J62: 0.25 | K62: 0.25 | L62: 0 | M62: 0 | N62: 2 | AA62: 0 | AB62: 9
A63: Sale of the mill's corn | B63: £2 8 shilling 9pence from 14 quarters 5 bushels of maslin sold, at 3 shilling 4pence a quarters. | C63: 2.44 | D63: 2 | E63: 8 | F63: 9 | G63: maslin | H63: 14 | I63: 5 | J63: 14.625 | K63: 14.625 | L63: 0 | M63: 14 | N63: 5 | S63: 3 | T63: 4
A64: Sale of the mill's corn | B64: 10 shilling from 4 quarters of malt sold, at 2 shilling 6pence a quarters. | C64: 0.53 | D64: 0 | E64: 10 | F64: 6 | H64: 4 | I64: 0 | J64: 4 | K64: 4 | L64: 0 | M64: 4 | N64: 0 | S64: 2 | T64: 6
A65: Sale of the mill's corn | B65: Total, £3 3pence | C65: 3.01 | D65: 3 | E65: 0 | F65: 3 | H65: 0 | I65: 0 | J65: 0 | K65: 0 | L65: 0 | M65: 0 | N65: 0
A66: Entry and marriage fines | B66: The same render account for £1 6 shilling 8pence from tithingpenny at the two hundred-courts for the year. | C66: 1.33 | D66: 1 | E66: 6 | F66: 8 | H66: 0 | I66: 0 | J66: 0 | K66: 0 | L66: 0 | M66: 0 | N66: 0
A67: Entry and marriage fines | B67: 13 shilling 4pence from Cecilia Marescall' to retain 0.5 virgate of land which belonged to her husband. | C67: 0.67 | D67: 0 | E67: 13 | F67: 4 | H67: 0 | I67: 0 | J67: 0 | K67: 0 | L67: 0 | M67: 0 | N67: 0
A68: Entry and marriage fines | B68: 1 shilling from John le Sone for marrying Agnes his daughter outside. | C68: 0.05 | D68: 0 | E68: 1 | F68: 0 | H68: 0 | I68: 0 | J68: 0 | K68: 0 | L68: 0 | M68: 0 | N68: 0
A69: Entry and marriage fines | B69: 5 shilling from Roger atte Garston to have 1 messuage 6.5 acres' of purpresture which belonged to Robert atte Garston' his uncle. | C69: 0.25 | D69: 0 | E69: 5 | F69: 0 | H69: 0 | I69: 0 | J69: 0 | K69: 0 | L69: 0 | M69: 0 | N69: 0
A70: Entry and marriage fines | B70: 2 shilling from Walter le Son' for marrying Isabel his daughter outside. | C70: 0.1 | D70: 0 | E70: 2 | F70: 0 | H70: 0 | I70: 0 | J70: 0 | K70: 0 | L70: 0 | M70: 0 | N70: 0
A71: Entry and marriage fines | B71: 1 shilling from John le Tayllor to have entry to a certain small plot, 36 feet long and 24 feet wide, beside the forge of la Wydegate. | C71: 0.05 | D71: 0 | E71: 1 | F71: 0 | H71: 0 | I71: 0 | J71: 0 | K71: 0 | L71: 0 | M71: 0 | N71: 0
A72: Entry and marriage fines | B72: 1 shilling from Edith (Aldich') Cuteles for marrying herself outside the manor. | C72: 0.05 | D72: 0 | E72: 1 | F72: 0 | H72: 0 | I72: 0 | J72: 0 | K72: 0 | L72: 0 | M72: 0 | N72: 0
A73: Entry and marriage fines | B73: 5 shilling from John Cutel of Whitway to have land which belonged to Adam Kutel his father by resignation of Edith Cutel his stepmother. | C73: 0.25 | D73: 0 | E73: 5 | F73: 0 | H73: 0 | I73: 0 | J73: 0 | K73: 0 | L73: 0 | M73: 0 | N73: 0
A74: Entry and marriage fines | B74: Total, £2 15 shilling | C74: 2.75 | D74: 2 | E74: 15 | F74: 0 | H74: 0 | I74: 0 | J74: 0 | K74: 0 | L74: 0 | M74: 0 | N74: 0
A75: Perquisites | B75: The same render account for 2 shilling from Juliana Sone, John atte Park' and their fellows for trespass of pasture. | C75: 0.1 | D75: 0 | E75: 2 | F75: 0 | H75: 0 | I75: 0 | J75: 0 | K75: 0 | L75: 0 | M75: 0 | N75: 0
A76: Perquisites | B76: 2pence from William Tokelyn because he is convicted. | C76: 0.01 | D76: 0 | E76: 0 | F76: 2 | H76: 0 | I76: 0 | J76: 0 | K76: 0 | L76: 0 | M76: 0 | N76: 0
... A116: Cost of ploughs | B116: In the ironwork of 5 ploughs for the year and 1 plough for 1 term 6 shilling 3pence. | C116: 0.31 | D116: 0 | E116: 6 | F116: 3 | H116: 0 | I116: 0 | J116: 0 | K116: 0 | L116: 0 | M116: 0 | N116: 0
A117: Cost of ploughs | B117: stipend of 1 smith, nothing, because he takes 1 acre of wheat for his stipenpence. | C117: 0 | D117: 0 | E117: 0 | F117: 0 | G117: wheat | H117: 0 | I117: 0 | J117: 0 | K117: 0 | L117: 0 | M117: 0 | N117: 0
A118: Cost of ploughs | B118: 6 plough-irons bought Is, 6pence. | C118: 0.03 | D118: 0 | E118: 0 | F118: 6 | H118: 0 | I118: 0 | J118: 0 | K118: 0 | L118: 0 | M118: 0 | N118: 0
A119: Cost of ploughs | B119: 1 coulter bought 10pence. | C119: 0.04 | D119: 0 | E119: 0 | F119: 10 | H119: 0 | I119: 0 | J119: 0 | K119: 0 | L119: 0 | M119: 0 | N119: 0
A120: Cost of ploughs | B120: 4 ploughshares 3 shilling 4pence. | C120: 0.17 | D120: 0 | E120: 3 | F120: 4 | H120: 0 | I120: 0 | J120: 0 | K120: 0 | L120: 0 | M120: 0 | N120: 0
A121: Cost of ploughs | B121: 3 ploughs made anew and others mended, fitted with share-beams, and covered with boards for the year, 1 shilling 4pence. | C121: 0.07 | D121: 0 | E121: 1 | F121: 4 | H121: 0 | I121: 0 | J121: 0 | K121: 0 | L121: 0 | M121: 0 | N121: 0
A122: Cost of ploughs | B122: yokes and wooden halters made 6pence. | C122: 0.03 | D122: 0 | E122: 0 | F122: 6 | H122: 0 | I122: 0 | J122: 0 | K122: 0 | L122: 0 | M122: 0 | N122: 0
A123: Cost of ploughs | B123: 4 pairs of wheels bought 1 shilling. | C123: 0.05 | D123: 0 | E123: 1 | F123: 0 | H123: 0 | I123: 0 | J123: 0 | K123: 0 | L123: 0 | M123: 0 | N123: 0
A124: Cost of ploughs | B124: boon-works of 40 ploughmen in winter and as many in Lent who ploughed as many acres as they lie 13 shilling 4pence, or 2pence a ploughman a day. | C124: 0.67 | D124: 0 | E124: 13 | F124: 4 | H124: 0 | I124: 0 | J124: 0 | K124: 0 | L124: 0 | M124: 0 | N124: 0
A125: Cost of ploughs | B125: Moreover, each ploughman will plough 1 acre in summer for fallow without food according to custom. | C125: 0 | D125: 0 | E125: 0 | F125: 0 | H125: 0 | I125: 0 | J125: 0 | K125: 0 | L125: 0 | M125: 0 | N125: 0
A126: Cost of ploughs | B126: . | C126: 0 | D126: 0 | E126: 0 | F126: 0 | H126: 0 | I126: 0 | J126: 0 | K126: 0 | L126: 0 | M126: 0 | N126: 0
A127: Cost of ploughs | B127: reward of 8 ploughmen for the year and 2 for 1 term for their Saturday ploughings 19 shilling 3pence, each taking 2 shilling less than they are accustomed, because more than accustomed was delivered to one sergeant who is there, and besides this they should each remove 1 horse which they are accustomed to have in the lord's pasture. | C127: 0.96 | D127: 0 | E127: 19 | F127: 3 | H127: 0 | I127: 0 | J127: 0 | K127: 0 | L127: 0 | M127: 0 | N127: 0
A128: Cost of ploughs | B128: . | C128: 0 | D128: 0 | E128: 0 | F128: 0 | H128: 0 | I128: 0 | J128: 0 | K128: 0 | L128: 0 | M128: 0 | N128: 0
A129: Cost of ploughs | B129: healing (medicinand) oxen 4pence. | C129: 0.02 | D129: 0 | E129: 0 | F129: 4 | H129: 0 | I129: 0 | J129: 0 | K129: 0 | L129: 0 | M129: 0 | N129: 0
... A132: Cost of ploughs | B132: stipend of 3 oxherds for the year 9 shilling. | C132: 0.45 | D132: 0 | E132: 9 | F132: 0 | H132: 0 | I132: 0 | J132: 0 | K132: 0 | L132: 0 | M132: 0 | N132: 0
A133: Cost of ploughs | B133: 10 quarters 6 bushels of maslin bought for the liveries of the manorial servants £1 15 shilling 10pence, at 3 shilling 4pence a quarters. | C133: 1.79 | D133: 1 | E133: 15 | F133: 10 | G133: maslin | H133: 10 | I133: 6 | J133: 10.75 | K133: 10.75 | L133: 0 | M133: 10 | N133: 6 | S133: 3 | T133: 4
A134: Cost of ploughs | B134: . | C134: 0 | D134: 0 | E134: 0 | F134: 0 | H134: 0 | I134: 0 | J134: 0 | K134: 0 | L134: 0 | M134: 0 | N134: 0
A135: Cost of ploughs | B135: 3 quarters of barley bought for sowing 12 shilling, at 4 shilling a quarters. | C135: 0.6 | D135: 0 | E135: 12 | F135: 0 | G135: barley | H135: 3 | I135: 0 | J135: 3 | K135: 3 | L135: 0 | M135: 3 | N135: 0 | S135: 4 | T135: 0
A136: Cost of ploughs | B136: Total, £19 3 shilling 11pence | C136: 19.2 | D136: 19 | E136: 3 | F136: 11 | H136: 0 | I136: 0 | J136: 0 | K136: 0 | L136: 0 | M136: 0 | N136: 0
A137: Cost of carts | B137: In clouts, nails, grease and white leather bought for the carts for the year, and fitting 3 carts with axles at various times, 2 shilling. | C137: 0.1 | D137: 0 | E137: 2 | F137: 0 | H137: 0 | I137: 0 | J137: 0 | K137: 0 | L137: 0 | M137: 0 | N137: 0
A138: Cost of carts | B138: 2 collars bought 1 shilling 1pence. | C138: 0.05 | D138: 0 | E138: 1 | F138: 1 | H138: 0 | I138: 0 | J138: 0 | K138: 0 | L138: 0 | M138: 0 | N138: 0
A139: Cost of carts | B139: 1 pair of tie-beams 6pence. | C139: 0.03 | D139: 0 | E139: 0 | F139: 6 | H139: 0 | I139: 0 | J139: 0 | K139: 0 | L139: 0 | M139: 0 | N139: 0
A140: Cost of carts | B140: 2 pairs of traces bought 1 shilling 1pence. | C140: 0.05 | D140: 0 | E140: 1 | F140: 1 | H140: 0 | I140: 0 | J140: 0 | K140: 0 | L140: 0 | M140: 0 | N140: 0
A141: Cost of carts | B141: 2 halters bought 5pence. | C141: 0.02 | D141: 0 | E141: 0 | F141: 5 | H141: 0 | I141: 0 | J141: 0 | K141: 0 | L141: 0 | M141: 0 | N141: 0
A142: Cost of carts | B142: 1 saddle-base bought 4pence. | C142: 0.02 | D142: 0 | E142: 0 | F142: 4 | H142: 0 | I142: 0 | J142: 0 | K142: 0 | L142: 0 | M142: 0 | N142: 0
A143: Cost of carts | B143: 1 cart-rope 1 shilling 2pence. | C143: 0.06 | D143: 0 | E143: 1 | F143: 2 | H143: 0 | I143: 0 | J143: 0 | K143: 0 | L143: 0 | M143: 0 | N143: 0
A144: Cost of carts | B144: shoeing 3 cart-horses for the year and 1 for 1 term 3 shilling 6pence. | C144: 0.17 | D144: 0 | E144: 3 | F144: 6 | H144: 0 | I144: 0 | J144: 0 | K144: 0 | L144: 0 | M144: 0 | N144: 0
A145: Cost of carts | B145: stipend of 1 carter for the year 3 shilling Total, 13 shilling 1pence | C145: 0.15 | D145: 0 | E145: 3 | F145: 1 | H145: 0 | I145: 0 | J145: 0 | K145: 0 | L145: 0 | M145: 0 | N145: 0
A146: Cost of buildings | B146: In roofing the wheat-barn in places 1 shilling 6pence. | C146: 0.08 | D146: 0 | E146: 1 | F146: 6 | G146: wheat | H146: 0 | I146: 0 | J146: 0 | K146: 0 | L146: 0 | M146: 0 | N146: 0
A147: Cost of buildings | B147: roofing and mending the byre and sheepcote beside the church in places 3 shilling. | C147: 0.15 | D147: 0 | E147: 3 | F147: 0 | H147: 0 | I147: 0 | J147: 0 | K147: 0 | L147: 0 | M147: 0 | N147: 0
A148: Cost of buildings | B148: roofing the sheepcote of Landecumbe 1 shilling 3pence. | C148: 0.06 | D148: 0 | E148: 1 | F148: 3 | H148: 0 | I148: 0 | J148: 0 | K148: 0 | L148: 0 | M148: 0 | N148: 0
A149: Cost of buildings | B149: constructing 2 perches of palisade between the curia and the cemetery 1 shilling 6pence. | C149: 0.08 | D149: 0 | E149: 1 | F149: 6 | H149: 0 | I149: 0 | J149: 0 | K149: 0 | L149: 0 | M149: 0 | N149: 0
A150: Cost of buildings | B150: pulling down the old byre 1 shilling. | C150: 0.05 | D150: 0 | E150: 1 | F150: 0 | H150: 0 | I150: 0 | J150: 0 | K150: 0 | L150: 0 | M150: 0 | N150: 0
A151: Cost of buildings | B151: cleaning the grips in the field 4 shilling. | C151: 0.2 | D151: 0 | E151: 4 | F151: 0 | H151: 0 | I151: 0 | J151: 0 | K151: 0 | L151: 0 | M151: 0 | N151: 0
A152: Cost of buildings | B152: marling the land sown with barley 1 shilling 6pence. | C152: 0.08 | D152: 0 | E152: 1 | F152: 6 | G152: barley | H152: 0 | I152: 0 | J152: 0 | K152: 0 | L152: 0 | M152: 0 | N152: 0
A153: Cost of buildings | B153: forage bought 13 shilling 10pence. | C153: 0.69 | D153: 0 | E153: 13 | F153: 10 | H153: 0 | I153: 0 | J153: 0 | K153: 0 | L153: 0 | M153: 0 | N153: 0
A154: Cost of buildings | B154: 3 pigs bought 5 shilling Total, £1 8 shilling 11pence | C154: 1.45 | D154: 1 | E154: 8 | F154: 11 | H154: 0 | I154: 0 | J154: 0 | K154: 0 | L154: 0 | M154: 0 | N154: 0
A155: Sheepcote and sheepfold | B155: In grease bought for greasing sheep 12 shilling 4pence. | C155: 0.62 | D155: 0 | E155: 12 | F155: 4 | H155: 0 | I155: 0 | J155: 0 | K155: 0 | L155: 0 | M155: 0 | N155: 0
A156: Sheepcote and sheepfold | B156: stipend of 1 shepherd for' year 1 shilling. | C156: 0.05 | D156: 0 | E156: 1 | F156: 0 | H156: 0 | I156: 0 | J156: 0 | K156: 0 | L156: 0 | M156: 0 | N156: 0
A157: Sheepcote and sheepfold | B157: wattling the fold 5pence. | C157: 0.02 | D157: 0 | E157: 0 | F157: 5 | H157: 0 | I157: 0 | J157: 0 | K157: 0 | L157: 0 | M157: 0 | N157: 0
A158: Sheepcote and sheepfold | B158: mending hurdles bought 2pence Total, 13 shilling 11pence | C158: 0.66 | D158: 0 | E158: 13 | F158: 2 | H158: 0 | I158: 0 | J158: 0 | K158: 0 | L158: 0 | M158: 0 | N158: 0
A159: Threshing and winnowing | B159: In threshing and winnowing 104 quarters of wheat by piece-work 17 shilling 4pence, at 2pence a quarters. | C159: 0.87 | D159: 0 | E159: 17 | F159: 4 | G159: wheat | H159: 104 | I159: 0 | J159: 104 | K159: 104 | L159: 0 | M159: 104 | N159: 0
A160: Threshing and winnowing | B160: . | C160: 0 | D160: 0 | E160: 0 | F160: 0 | H160: 0 | I160: 0 | J160: 0 | K160: 0 | L160: 0 | M160: 0 | N160: 0
A161: Threshing and winnowing | B161: threshing 39 quarters 1 bushels of bere by piece-work 5 shilling 8.5pence, at 1.75pence a quarters. | C161: 0.29 | D161: 0 | E161: 5 | F161: 8.5 | H161: 39 | I161: 1 | J161: 39.125 | K161: 39.125 | L161: 0 | M161: 39 | N161: 1
A162: Threshing and winnowing | B162: . | C162: 0 | D162: 0 | E162: 0 | F162: 0 | H162: 0 | I162: 0 | J162: 0 | K162: 0 | L162: 0 | M162: 0 | N162: 0
A163: Threshing and winnowing | B163: threshing and winnowing 8 quarters 2 bushels of barley by piece-work 10.25pence, at 1.25pence a quarters. | C163: 0.04 | D163: 0 | E163: 0 | F163: 10.25 | G163: barley | H163: 8 | I163: 2 | J163: 8.25 | K163: 8.25 | L163: 0 | M163: 8 | N163: 2
A164: Threshing and winnowing | B164: . | C164: 0 | D164: 0 | E164: 0 | F164: 0 | H164: 0 | I164: 0 | J164: 0 | K164: 0 | L164: 0 | M164: 0 | N164: 0
A165: Threshing and winnowing | B165: threshing 123.5 quarters of oats by piece-work 5 shilling 1.75pence, at .5pence a quarters. | C165: 0.26 | D165: 0 | E165: 5 | F165: 1.75 | G165: oats | H165: 123.5 | I165: 0 | J165: 123.5 | K165: 123.5 | L165: 0 | M165: 123.5 | N165: 0
A166: Threshing and winnowing | B166: . | C166: 0 | D166: 0 | E166: 0 | F166: 0 | H166: 0 | I166: 0 | J166: 0 | K166: 0 | L166: 0 | M166: 0 | N166: 0
A167: Threshing and winnowing | B167: winnowing the same 1 shilling 3.5pence, at 1pence per 8 quarters. | C167: 0.06 | D167: 0 | E167: 1 | F167: 3.5 | H167: 8 | I167: 0 | J167: 8 | K167: 8 | L167: 0 | M167: 8 | N167: 0
A168: Threshing and winnowing | B168: . | C168: 0 | D168: 0 | E168: 0 | F168: 0 | H168: 0 | I168: 0 | J168: 0 | K168: 0 | L168: 0 | M168: 0 | N168: 0
A169: Threshing and winnowing | B169: 4 sacks bought 1 shilling 9.75pence. | C169: 0.09 | D169: 0 | E169: 1 | F169: 9.75 | H169: 0 | I169: 0 | J169: 0 | K169: 0 | L169: 0 | M169: 0 | N169: 0
A170: Threshing and winnowing | B170: 1 basket bought 3pence Total, £1 12 shilling 4.75pence | C170: 1.62 | D170: 1 | E170: 12 | F170: 4.75 | H170: 0 | I170: 0 | J170: 0 | K170: 0 | L170: 0 | M170: 0 | N170: 0
A171: Weeding | B171: In weeding corn this year 3 shilling 4pence Total, 3 shilling 4pence | C171: 0.17 | D171: 0 | E171: 3 | F171: 4 | H171: 0 | I171: 0 | J171: 0 | K171: 0 | L171: 0 | M171: 0 | N171: 0
A172: Harvest-time | B172: In mowing 10 acres of meadow according to custom 6pence. | C172: 0.03 | D172: 0 | E172: 0 | F172: 6 | H172: 0 | I172: 0 | J172: 0 | K172: 0 | L172: 0 | M172: 0 | N172: 0
A173: Harvest-time | B173: 2 boon-works of 167 men with the officials of the curia who reaped 65 acres of wheat and 66 acres of oats as they lie 13 shilling 4pence. | C173: 0.67 | D173: 0 | E173: 13 | F173: 4 | G173: oats, wheat | H173: 0 | I173: 0 | J173: 0 | K173: 0 | L173: 0 | M173: 0 | N173: 0
A174: Harvest-time | B174: 1 boon-work of 81 free men of Eneburn and Earlstone who reaped 33 acres of wheat as they lie 6 shilling 9pence, as in bread, ale and relish. | C174: 0.34 | D174: 0 | E174: 6 | F174: 9 | G174: wheat | H174: 0 | I174: 0 | J174: 0 | K174: 0 | L174: 0 | M174: 0 | N174: 0
A175: Harvest-time | B175: . | C175: 0 | D175: 0 | E175: 0 | F175: 0 | H175: 0 | I175: 0 | J175: 0 | K175: 0 | L175: 0 | M175: 0 | N175: 0
A176: Harvest-time | B176: 36 acres of oats reaped by piece-work 6 shilling, at 2pence an acre. | C176: 0.31 | D176: 0 | E176: 6 | F176: 2 | G176: oats | H176: 0 | I176: 0 | J176: 0 | K176: 0 | L176: 0 | M176: 0 | N176: 0
A177: Harvest-time | B177: Total, £1 6 shilling 7pence | C177: 1.33 | D177: 1 | E177: 6 | F177: 7 | H177: 0 | I177: 0 | J177: 0 | K177: 0 | L177: 0 | M177: 0 | N177: 0
A178: Cost of the mill | B178: In roofing the mill-building 4pence. | C178: 0.02 | D178: 0 | E178: 0 | F178: 4 | H178: 0 | I178: 0 | J178: 0 | K178: 0 | L178: 0 | M178: 0 | N178: 0
A179: Cost of the mill | B179: steeling and mending bills 4pence. | C179: 0.02 | D179: 0 | E179: 0 | F179: 4 | H179: 0 | I179: 0 | J179: 0 | K179: 0 | L179: 0 | M179: 0 | N179: 0
A180: Cost of the mill | B180: 1 gudgeon for the driving-shaft of the mill 3pence. | C180: 0.01 | D180: 0 | E180: 0 | F180: 3 | H180: 0 | I180: 0 | J180: 0 | K180: 0 | L180: 0 | M180: 0 | N180: 0
A181: Cost of the mill | B181: 1 large mill-iron made under the driving-shaft of the mill with iron bought for the same 2 shilling 1.5pence. | C181: 0.11 | D181: 0 | E181: 2 | F181: 1.5 | H181: 0 | I181: 0 | J181: 0 | K181: 0 | L181: 0 | M181: 0 | N181: 0
A182: Cost of the mill | B182: 40 ells of canvas bought for the mill's sails 10 shilling 2pence, at 3.25pence an ell. | C182: 0.51 | D182: 0 | E182: 10 | F182: 2 | H182: 0 | I182: 0 | J182: 0 | K182: 0 | L182: 0 | M182: 0 | N182: 0
A183: Cost of the mill | B183: . | C183: 0 | D183: 0 | E183: 0 | F183: 0 | H183: 0 | I183: 0 | J183: 0 | K183: 0 | L183: 0 | M183: 0 | N183: 0
A184: Cost of the mill | B184: grease bought 6pence. | C184: 0.03 | D184: 0 | E184: 0 | F184: 6 | H184: 0 | I184: 0 | J184: 0 | K184: 0 | L184: 0 | M184: 0 | N184: 0
...

Sheet Issues of the Grange raw
A1: Heading | B1: Sentence | C1: Quarters 1_x | D1: Bushels 1_x | E1: Sown Quarters | F1: Sown Bushels | G1: Sown Total Quarters | H1: Bought in Quarters | I1: Bought in Bushels | J1: Bought in Total Quarters | K1: Tithe Quarters | L1: Tithe Bushels | M1: Tithe Total Quarters | N1: Manorial servants & livestock Quarters | O1: Manorial servants & livestock Bushels | P1: Manorial servants & livestock Total Quarters | Q1: Sold Quarters | R1: Sold Bushels | S1: Sold Total Quarters | T1: Account Quarters | U1: Account Bushels | V1: Account Total Quarters | W1: bought only | X1: Total Quarters Except 1 | Y1: Total Bushels Except 1 | Z1: Total Corn Cross-Check | AA1: Total Corn Manorial Account | AB1: Corn Quantity Error | AC1: Quarters 1_y | AD1: Bushels 1_y | AE1: Quarters 2 | AF1: Bushels 2 | AG1: Quarters 3 | AH1: Bushels 3
A2: Cash deliveries | B2: Total | C2: 0 | D2: 0 | E2: 0 | F2: 0 | G2: 0 | H2: 0 | I2: 0 | J2: 0 | K2: 0 | L2: 0 | M2: 0 | N2: 0 | O2: 0 | P2: 0 | Q2: 0 | R2: 0 | S2: 0 | T2: 0 | U2: 0 | V2: 0 | W2: 0
A3: Wheat | B3: {yield: five-fold plus 4 quarters 3 bushels) | C3: 0 | D3: 0 | E3: 0 | F3: 0 | G3: 0 | H3: 0 | I3: 0 | J3: 0 | K3: 0 | L3: 0 | M3: 0 | N3: 0 | O3: 0 | P3: 0 | Q3: 0 | R3: 0 | S3: 0 | T3: 0 | U3: 0 | V3: 0 | W3: 0 | X3: 4 | Y3: 3 | Z3: 4.375 | AA3: 4.375 | AB3: 0 | AC3: 4 | AD3: 3
A4: Wheat | B4: The same render account for 130 quarters from the whole issue of wheat by struck measure. | C4: 0 | D4: 0 | E4: 0 | F4: 0 | G4: 0 | H4: 0 | I4: 0 | J4: 0 | K4: 0 | L4: 0 | M4: 0 | N4: 0 | O4: 0 | P4: 0 | Q4: 0 | R4: 0 | S4: 0 | T4: 130 | U4: 0 | V4: 130 | W4: 0 | X4: 130 | Y4: 0 | Z4: 130 | AA4: 130 | AB4: 0 | AC4: 130 | AD4: 0
A5: Wheat | B5: 1.5 quarters by estimation in 3 acres delivered to 1 reeve, 1 hayward and 1 smith according to custom. | C5: 0 | D5: 0 | E5: 0 | F5: 0 | G5: 0 | H5: 0 | I5: 0 | J5: 0 | K5: 0 | L5: 0 | M5: 0 | N5: 0 | O5: 0 | P5: 0 | Q5: 0 | R5: 0 | S5: 0 | T5: 0 | U5: 0 | V5: 0 | W5: 0 | X5: 1.5 | Y5: 0 | Z5: 1.5 | AA5: 1.5 | AB5: 0 | AC5: 1.5 | AD5: 0
A6: Wheat | B6: 4 quarters 1 bushels by estimation in 412 sheaves delivered to the reapers of 206 acres, at 2 sheaves an acre. | C6: 0 | D6: 0 | E6: 0 | F6: 0 | G6: 0 | H6: 0 | I6: 0 | J6: 0 | K6: 0 | L6: 0 | M6: 0 | N6: 0 | O6: 0 | P6: 0 | Q6: 0 | R6: 0 | S6: 0 | T6: 0 | U6: 0 | V6: 0 | W6: 0 | X6: 4 | Y6: 1 | Z6: 4.125 | AA6: 4.125 | AB6: 0 | AC6: 4 | AD6: 1
A7: Wheat | B7: Total, 135 quarters 5 bushels | C7: 0 | D7: 0 | E7: 0 | F7: 0 | G7: 0 | H7: 0 | I7: 0 | J7: 0 | K7: 0 | L7: 0 | M7: 0 | N7: 0 | O7: 0 | P7: 0 | Q7: 0 | R7: 0 | S7: 0 | T7: 0 | U7: 0 | V7: 0 | W7: 0 | X7: 135 | Y7: 5 | Z7: 135.625 | AA7: 135.625 | AB7: 0 | AC7: 135 | AD7: 5
A8: Wheat | B8: Sown over 252 acres as they lie in the fields of Stok' and Suthlond', 31 quarters 1 bushels. | C8: 0 | D8: 0 | E8: 31 | F8: 1 | G8: 31.125 | H8: 0 | I8: 0 | J8: 0 | K8: 0 | L8: 0 | M8: 0 | N8: 0 | O8: 0 | P8: 0 | Q8: 0 | R8: 0 | S8: 0 | T8: 0 | U8: 0 | V8: 0 | W8: 0 | X8: 31 | Y8: 1 | Z8: 31.125 | AA8: 31.125 | AB8: 0 | AC8: 31 | AD8: 1
A9: Wheat | B9: that is, 1 bushels an acre, less 3 bushels in all. | C9: 0 | D9: 0 | E9: 0 | F9: 0 | G9: 0 | H9: 0 | I9: 0 | J9: 0 | K9: 0 | L9: 0 | M9: 0 | N9: 0 | O9: 0 | P9: 0 | Q9: 0 | R9: 0 | S9: 0 | T9: 0 | U9: 0 | V9: 0 | W9: 0 | X9: 0 | Y9: 3 | Z9: 0.375 | AA9: 0.125 | AB9: 0.25 | AC9: 0 | AD9: 1 | AE9: 0 | AF9: 3
A10: Wheat | B10: . | C10: 0 | D10: 0 | E10: 0 | F10: 0 | G10: 0 | H10: 0 | I10: 0 | J10: 0 | K10: 0 | L10: 0 | M10: 0 | N10: 0 | O10: 0 | P10: 0 | Q10: 0 | R10: 0 | S10: 0 | T10: 0 | U10: 0 | V10: 0 | W10: 0 | X10: 0 | Y10: 0 | Z10: 0 | AA10: 0 | AB10: 0 | AC10: 0 | AD10: 0
A11: Wheat | B11: customary payment to the hayward, 1 bushels. | C11: 0 | D11: 0 | E11: 0 | F11: 0 | G11: 0 | H11: 0 | I11: 0 | J11: 0 | K11: 0 | L11: 0 | M11: 0 | N11: 0 | O11: 0 | P11: 0 | Q11: 0 | R11: 0 | S11: 0 | T11: 0 | U11: 0 | V11: 0 | W11: 0 | X11: 0 | Y11: 1 | Z11: 0.125 | AA11: 0.125 | AB11: 0 | AC11: 0 | AD11: 1
A12: Wheat | B12: customary payment for the mowing of the meadows, 6 bushels. | C12: 0 | D12: 0 | E12: 0 | F12: 0 | G12: 0 | H12: 0 | I12: 0 | J12: 0 | K12: 0 | L12: 0 | M12: 0 | N12: 0 | O12: 0 | P12: 0 | Q12: 0 | R12: 0 | S12: 0 | T12: 0 | U12: 0 | V12: 0 | W12: 0 | X12: 0 | Y12: 6 | Z12: 0.75 | AA12: 0.75 | AB12: 0 | AC12: 0 | AD12: 6
A13: Wheat | B13: customary payment to 1 reeve, 1 hayward, 1 smith by estimation in 3 acres according to custom, 1.5 quarters. | C13: 0 | D13: 0 | E13: 0 | F13: 0 | G13: 0 | H13: 0 | I13: 0 | J13: 0 | K13: 0 | L13: 0 | M13: 0 | N13: 0 | O13: 0 | P13: 0 | Q13: 0 | R13: 0 | S13: 0 | T13: 0 | U13: 0 | V13: 0 | W13: 0 | X13: 1.5 | Y13: 0 | Z13: 1.5 | AA13: 1.5 | AB13: 0 | AC13: 1.5 | AD13: 0
A14: Wheat | B14: Delivered to the reapers by estimation in 412 sheaves, 4 quarters 1 bushels. | C14: 0 | D14: 0 | E14: 0 | F14: 0 | G14: 0 | H14: 0 | I14: 0 | J14: 0 | K14: 0 | L14: 0 | M14: 0 | N14: 0 | O14: 0 | P14: 0 | Q14: 0 | R14: 0 | S14: 0 | T14: 0 | U14: 0 | V14: 0 | W14: 0 | X14: 4 | Y14: 1 | Z14: 4.125 | AA14: 4.125 | AB14: 0 | AC14: 4 | AD14: 1
A15: Wheat | B15: the bailiff's bread, 7.5 quarters, because he takes the rest at Ecchinswell. | C15: 0 | D15: 0 | E15: 0 | F15: 0 | G15: 0 | H15: 0 | I15: 0 | J15: 0 | K15: 0 | L15: 0 | M15: 0 | N15: 0 | O15: 0 | P15: 0 | Q15: 0 | R15: 0 | S15: 0 | T15: 0 | U15: 0 | V15: 0 | W15: 0 | X15: 7.5 | Y15: 0 | Z15: 7.5 | AA15: 7.5 | AB15: 0 | AC15: 7.5 | AD15: 0
A16: Wheat | B16: Sold, 90.5 quarters. | C16: 0 | D16: 0 | E16: 0 | F16: 0 | G16: 0 | H16: 0 | I16: 0 | J16: 0 | K16: 0 | L16: 0 | M16: 0 | N16: 0 | O16: 0 | P16: 0 | Q16: 90.5 | R16: 0 | S16: 90.5 | T16: 0 | U16: 0 | V16: 0 | W16: 0 | X16: 90.5 | Y16: 0 | Z16: 90.5 | AA16: 90.5 | AB16: 0 | AC16: 90.5 | AD16: 0
A17: Wheat | B17: Total | C17: 0 | D17: 0 | E17: 0 | F17: 0 | G17: 0 | H17: 0 | I17: 0 | J17: 0 | K17: 0 | L17: 0 | M17: 0 | N17: 0 | O17: 0 | P17: 0 | Q17: 0 | R17: 0 | S17: 0 | T17: 0 | U17: 0 | V17: 0 | W17: 0
A18: Barley | B18: {yield: two-fold less 2 bushels) | C18: 0 | D18: 0 | E18: 0 | F18: 0 | G18: 0 | H18: 0 | I18: 0 | J18: 0 | K18: 0 | L18: 0 | M18: 0 | N18: 0 | O18: 0 | P18: 0 | Q18: 0 | R18: 0 | S18: 0 | T18: 0 | U18: 0 | V18: 0 | W18: 0 | X18: 0 | Y18: 2 | Z18: 0.25 | AA18: 0.25 | AB18: 0 | AC18: 0 | AD18: 2
A19: Barley | B19: The same render account for 10 quarters 2 bushels from the whole issue of barley by struck measure. | C19: 0 | D19: 0 | E19: 0 | F19: 0 | G19: 0 | H19: 0 | I19: 0 | J19: 0 | K19: 0 | L19: 0 | M19: 0 | N19: 0 | O19: 0 | P19: 0 | Q19: 0 | R19: 0 | S19: 0 | T19: 10 | U19: 2 | V19: 10.25 | W19: 0 | X19: 10 | Y19: 2 | Z19: 10.25 | AA19: 10.25 | AB19: 0 | AC19: 10 | AD19: 2
A20: Barley | B20: 4 bushels by estimation in 44 sheaves delivered to the reapers of 32 acres, at 2 sheaves an acre. | C20: 0 | D20: 0 | E20: 0 | F20: 0 | G20: 0 | H20: 0 | I20: 0 | J20: 0 | K20: 0 | L20: 0 | M20: 0 | N20: 0 | O20: 0 | P20: 0 | Q20: 0 | R20: 0 | S20: 0 | T20: 0 | U20: 0 | V20: 0 | W20: 0 | X20: 0 | Y20: 4 | Z20: 0.5 | AA20: 0.5 | AB20: 0 | AC20: 0 | AD20: 4
A21: Barley | B21: 3 quarters bought. | C21: 0 | D21: 0 | E21: 0 | F21: 0 | G21: 0 | H21: 3 | I21: 0 | J21: 3 | K21: 0 | L21: 0 | M21: 0 | N21: 0 | O21: 0 | P21: 0 | Q21: 0 | R21: 0 | S21: 0 | T21: 0 | U21: 0 | V21: 0 | W21: 0 | X21: 3 | Y21: 0 | Z21: 3 | AA21: 3 | AB21: 0 | AC21: 3 | AD21: 0
A22: Barley | B22: Total, 13 quarters 6 bushels | C22: 0 | D22: 0 | E22: 0 | F22: 0 | G22: 0 | H22: 0 | I22: 0 | J22: 0 | K22: 0 | L22: 0 | M22: 0 | N22: 0 | O22: 0 | P22: 0 | Q22: 0 | R22: 0 | S22: 0 | T22: 0 | U22: 0 | V22: 0 | W22: 0 | X22: 13 | Y22: 6 | Z22: 13.75 | AA22: 13.75 | AB22: 0 | AC22: 13 | AD22: 6
A23: Barley | B23: Sown over 35 acres as they lie in the field of Legh', 8.5 quarters 1 bushels. | C23: 0 | D23: 0 | E23: 8.5 | F23: 1 | G23: 8.625 | H23: 0 | I23: 0 | J23: 0 | K23: 0 | L23: 0 | M23: 0 | N23: 0 | O23: 0 | P23: 0 | Q23: 0 | R23: 0 | S23: 0 | T23: 0 | U23: 0 | V23: 0 | W23: 0 | X23: 8.5 | Y23: 1 | Z23: 8.625 | AA23: 8.625 | AB23: 0 | AC23: 8.5 | AD23: 1
A24: Barley | B24: that is, 2 bushels an acre, less 1 bushels in all. | C24: 0 | D24: 0 | E24: 0 | F24: 0 | G24: 0 | H24: 0 | I24: 0 | J24: 0 | K24: 0 | L24: 0 | M24: 0 | N24: 0 | O24: 0 | P24: 0 | Q24: 0 | R24: 0 | S24: 0 | T24: 0 | U24: 0 | V24: 0 | W24: 0 | X24: 0 | Y24: 1 | Z24: 0.125 | AA24: 0.25 | AB24: -0.125 | AC24: 0 | AD24: 2 | AE24: 0 | AF24: 1
A25: Barley | B25: Delivered to the reapers by estimation in 44 sheaves, 4 bushels Sold, 4 quarters 5 bushels | C25: 0 | D25: 0 | E25: 0 | F25: 0 | G25: 0 | H25: 0 | I25: 0 | J25: 0 | K25: 0 | L25: 0 | M25: 0 | N25: 0 | O25: 0 | P25: 0 | Q25: 4 | R25: 5 | S25: 4.625 | T25: 0 | U25: 0 | V25: 0 | W25: 0 | X25: 4 | Y25: 5 | Z25: 4.625 | AA25: 0.5 | AB25: 4.125 | AC25: 0 | AD25: 4 | AE25: 4 | AF25: 5
A26: Barley | B26: Total | C26: 0 | D26: 0 | E26: 0 | F26: 0 | G26: 0 | H26: 0 | I26: 0 | J26: 0 | K26: 0 | L26: 0 | M26: 0 | N26: 0 | O26: 0 | P26: 0 | Q26: 0 | R26: 0 | S26: 0 | T26: 0 | U26: 0 | V26: 0 | W26: 0
A27: Oats | B27: {yield: two-fold plus 17 quarters 1 bushels) | C27: 0 | D27: 0 | E27: 0 | F27: 0 | G27: 0 | H27: 0 | I27: 0 | J27: 0 | K27: 0 | L27: 0 | M27: 0 | N27: 0 | O27: 0 | P27: 0 | Q27: 0 | R27: 0 | S27: 0 | T27: 0 | U27: 0 | V27: 0 | W27: 0 | X27: 17 | Y27: 1 | Z27: 17.125 | AA27: 17.125 | AB27: 0 | AC27: 17 | AD27: 1
A28: Oats | B28: The same render account for 154 quarters 3 bushels from the whole issue of oats by struck measure. | C28: 0 | D28: 0 | E28: 0 | F28: 0 | G28: 0 | H28: 0 | I28: 0 | J28: 0 | K28: 0 | L28: 0 | M28: 0 | N28: 0 | O28: 0 | P28: 0 | Q28: 0 | R28: 0 | S28: 0 | T28: 154 | U28: 3 | V28: 154.375 | W28: 0 | X28: 154 | Y28: 3 | Z28: 154.375 | AA28: 154.375 | AB28: 0 | AC28: 154 | AD28: 3
A29: Oats | B29: 24 quarters by estimation in sheaves given to oxen. | C29: 0 | D29: 0 | E29: 0 | F29: 0 | G29: 0 | H29: 0 | I29: 0 | J29: 0 | K29: 0 | L29: 0 | M29: 0 | N29: 0 | O29: 0 | P29: 0 | Q29: 0 | R29: 0 | S29: 0 | T29: 0 | U29: 0 | V29: 0 | W29: 0 | X29: 24 | Y29: 0 | Z29: 24 | AA29: 24 | AB29: 0 | AC29: 24 | AD29: 0
A30: Oats | B30: 2 bushels by estimation in 1.5 acres delivered to the hayward according to custom. | C30: 0 | D30: 0 | E30: 0 | F30: 0 | G30: 0 | H30: 0 | I30: 0 | J30: 0 | K30: 0 | L30: 0 | M30: 0 | N30: 0 | O30: 0 | P30: 0 | Q30: 0 | R30: 0 | S30: 0 | T30: 0 | U30: 0 | V30: 0 | W30: 0 | X30: 0 | Y30: 2 | Z30: 0.25 | AA30: 0.25 | AB30: 0 | AC30: 0 | AD30: 2
A31: Oats | B31: 2.5 quarters by estimation in 366 sheaves delivered to the reapers of 183 acres, at 2 sheaves an acre. | C31: 0 | D31: 0 | E31: 0 | F31: 0 | G31: 0 | H31: 0 | I31: 0 | J31: 0 | K31: 0 | L31: 0 | M31: 0 | N31: 0 | O31: 0 | P31: 0 | Q31: 0 | R31: 0 | S31: 0 | T31: 0 | U31: 0 | V31: 0 | W31: 0 | X31: 2.5 | Y31: 0 | Z31: 2.5 | AA31: 2.5 | AB31: 0 | AC31: 2.5 | AD31: 0
A32: Oats | B32: Total, 181 quarters 1 bushels | C32: 0 | D32: 0 | E32: 0 | F32: 0 | G32: 0 | H32: 0 | I32: 0 | J32: 0 | K32: 0 | L32: 0 | M32: 0 | N32: 0 | O32: 0 | P32: 0 | Q32: 0 | R32: 0 | S32: 0 | T32: 0 | U32: 0 | V32: 0 | W32: 0 | X32: 181 | Y32: 1 | Z32: 181.125 | AA32: 181.125 | AB32: 0 | AC32: 181 | AD32: 1
A33: Oats | B33: Sown over 364 acres as they lie in the fields of Ligh', Hareberd and la Nywelond', 90 quarters 7 bushels. | C33: 0 | D33: 0 | E33: 90 | F33: 7 | G33: 90.875 | H33: 0 | I33: 0 | J33: 0 | K33: 0 | L33: 0 | M33: 0 | N33: 0 | O33: 0 | P33: 0 | Q33: 0 | R33: 0 | S33: 0 | T33: 0 | U33: 0 | V33: 0 | W33: 0 | X33: 90 | Y33: 7 | Z33: 90.875 | AA33: 90.875 | AB33: 0 | AC33: 90 | AD33: 7
A34: Oats | B34: that is, 2 bushels an acre, less 1 bushels in all. | C34: 0 | D34: 0 | E34: 0 | F34: 0 | G34: 0 | H34: 0 | I34: 0 | J34: 0 | K34: 0 | L34: 0 | M34: 0 | N34: 0 | O34: 0 | P34: 0 | Q34: 0 | R34: 0 | S34: 0 | T34: 0 | U34: 0 | V34: 0 | W34: 0 | X34: 0 | Y34: 1 | Z34: 0.125 | AA34: 0.25 | AB34: -0.125 | AC34: 0 | AD34: 2 | AE34: 0 | AF34: 1
A35: Oats | B35: . | C35: 0 | D35: 0 | E35: 0 | F35: 0 | G35: 0 | H35: 0 | I35: 0 | J35: 0 | K35: 0 | L35: 0 | M35: 0 | N35: 0 | O35: 0 | P35: 0 | Q35: 0 | R35: 0 | S35: 0 | T35: 0 | U35: 0 | V35: 0 | W35: 0 | X35: 0 | Y35: 0 | Z35: 0 | AA35: 0 | AB35: 0 | AC35: 0 | AD35: 0
A36: Oats | B36: . | C36: 0 | D36: 0 | E36: 0 | F36: 0 | G36: 0 | H36: 0 | I36: 0 | J36: 0 | K36: 0 | L36: 0 | M36: 0 | N36: 0 | O36: 0 | P36: 0 | Q36: 0 | R36: 0 | S36: 0 | T36: 0 | U36: 0 | V36: 0 | W36: 0 | X36: 0 | Y36: 0 | Z36: 0 | AA36: 0 | AB36: 0 | AC36: 0 | AD36: 0
A37: Oats | B37: . | C37: 0 | D37: 0 | E37: 0 | F37: 0 | G37: 0 | H37: 0 | I37: 0 | J37: 0 | K37: 0 | L37: 0 | M37: 0 | N37: 0 | O37: 0 | P37: 0 | Q37: 0 | R37: 0 | S37: 0 | T37: 0 | U37: 0 | V37: 0 | W37: 0 | X37: 0 | Y37: 0 | Z37: 0 | AA37: 0 | AB37: 0 | AC37: 0 | AD37: 0
A38: Oats | B38: . | C38: 0 | D38: 0 | E38: 0 | F38: 0 | G38: 0 | H38: 0 | I38: 0 | J38: 0 | K38: 0 | L38: 0 | M38: 0 | N38: 0 | O38: 0 | P38: 0 | Q38: 0 | R38: 0 | S38: 0 | T38: 0 | U38: 0 | V38: 0 | W38: 0 | X38: 0 | Y38: 0 | Z38: 0 | AA38: 0 | AB38: 0 | AC38: 0 | AD38: 0
A39: Oats | B39: customary payment to the hayward, 1 bushels. | C39: 0 | D39: 0 | E39: 0 | F39: 0 | G39: 0 | H39: 0 | I39: 0 | J39: 0 | K39: 0 | L39: 0 | M39: 0 | N39: 0 | O39: 0 | P39: 0 | Q39: 0 | R39: 0 | S39: 0 | T39: 0 | U39: 0 | V39: 0 | W39: 0 | X39: 0 | Y39: 1 | Z39: 0.125 | AA39: 0.125 | AB39: 0 | AC39: 0 | AD39: 1
A40: Oats | B40: fodder of 2 cart-horses at sowing-time, 6.5 quarters. | C40: 0 | D40: 0 | E40: 0 | F40: 0 | G40: 0 | H40: 0 | I40: 0 | J40: 0 | K40: 0 | L40: 0 | M40: 0 | N40: 6.5 | O40: 0 | P40: 6.5 | Q40: 0 | R40: 0 | S40: 0 | T40: 0 | U40: 0 | V40: 0 | W40: 0 | X40: 6.5 | Y40: 0 | Z40: 6.5 | AA40: 6.5 | AB40: 0 | AC40: 6.5 | AD40: 0
A41: Oats | B41: . | C41: 0 | D41: 0 | E41: 0 | F41: 0 | G41: 0 | H41: 0 | I41: 0 | J41: 0 | K41: 0 | L41: 0 | M41: 0 | N41: 0 | O41: 0 | P41: 0 | Q41: 0 | R41: 0 | S41: 0 | T41: 0 | U41: 0 | V41: 0 | W41: 0 | X41: 0 | Y41: 0 | Z41: 0 | AA41: 0 | AB41: 0 | AC41: 0 | AD41: 0
A42: Oats | B42: . | C42: 0 | D42: 0 | E42: 0 | F42: 0 | G42: 0 | H42: 0 | I42: 0 | J42: 0 | K42: 0 | L42: 0 | M42: 0 | N42: 0 | O42: 0 | P42: 0 | Q42: 0 | R42: 0 | S42: 0 | T42: 0 | U42: 0 | V42: 0 | W42: 0 | X42: 0 | Y42: 0 | Z42: 0 | AA42: 0 | AB42: 0 | AC42: 0 | AD42: 0
A43: Oats | B43: . | C43: 0 | D43: 0 | E43: 0 | F43: 0 | G43: 0 | H43: 0 | I43: 0 | J43: 0 | K43: 0 | L43: 0 | M43: 0 | N43: 0 | O43: 0 | P43: 0 | Q43: 0 | R43: 0 | S43: 0 | T43: 0 | U43: 0 | V43: 0 | W43: 0 | X43: 0 | Y43: 0 | Z43: 0 | AA43: 0 | AB43: 0 | AC43: 0 | AD43: 0
A44: Oats | B44: . | C44: 0 | D44: 0 | E44: 0 | F44: 0 | G44: 0 | H44: 0 | I44: 0 | J44: 0 | K44: 0 | L44: 0 | M44: 0 | N44: 0 | O44: 0 | P44: 0 | Q44: 0 | R44: 0 | S44: 0 | T44: 0 | U44: 0 | V44: 0 | W44: 0 | X44: 0 | Y44: 0 | Z44: 0 | AA44: 0 | AB44: 0 | AC44: 0 | AD44: 0
A45: Oats | B45: fodder of horses harrowing at both sowings, 4 quarters 5 bushels. | C45: 0 | D45: 0 | E45: 0 | F45: 0 | G45: 0 | H45: 0 | I45: 0 | J45: 0 | K45: 0 | L45: 0 | M45: 0 | N45: 4 | O45: 5 | P45: 4.625 | Q45: 0 | R45: 0 | S45: 0 | T45: 0 | U45: 0 | V45: 0 | W45: 0 | X45: 4 | Y45: 5 | Z45: 4.625 | AA45: 4.625 | AB45: 0 | AC45: 4 | AD45: 5
A46: Oats | B46: supporting oxen by estimation in sheaves, 24 quarters. | C46: 0 | D46: 0 | E46: 0 | F46: 0 | G46: 0 | H46: 0 | I46: 0 | J46: 0 | K46: 0 | L46: 0 | M46: 0 | N46: 0 | O46: 0 | P46: 0 | Q46: 0 | R46: 0 | S46: 0 | T46: 0 | U46: 0 | V46: 0 | W46: 0 | X46: 24 | Y46: 0 | Z46: 24 | AA46: 24 | AB46: 0 | AC46: 24 | AD46: 0
... A55: Oats | B55: . | C55: 0 | D55: 0 | E55: 0 | F55: 0 | G55: 0 | H55: 0 | I55: 0 | J55: 0 | K55: 0 | L55: 0 | M55: 0 | N55: 0 | O55: 0 | P55: 0 | Q55: 0 | R55: 0 | S55: 0 | T55: 0 | U55: 0 | V55: 0 | W55: 0 | X55: 0 | Y55: 0 | Z55: 0 | AA55: 0 | AB55: 0 | AC55: 0 | AD55: 0
A56: Oats | B56: customary payment to the hayward in 1.5 acres, 2 bushels Delivered to the reapers by estimation in 366 sheaves, 2.5 quarters. | C56: 0 | D56: 0 | E56: 0 | F56: 0 | G56: 0 | H56: 0 | I56: 0 | J56: 0 | K56: 0 | L56: 0 | M56: 0 | N56: 0 | O56: 0 | P56: 0 | Q56: 0 | R56: 0 | S56: 0 | T56: 0 | U56: 0 | V56: 0 | W56: 0 | X56: 2.5 | Y56: 2 | Z56: 2.75 | AA56: 0.25 | AB56: 2.5 | AC56: 0 | AD56: 2 | AE56: 2.5 | AF56: 0
A57: Oats | B57: Sold, 39 quarters 6 bushels | C57: 0 | D57: 0 | E57: 0 | F57: 0 | G57: 0 | H57: 0 | I57: 0 | J57: 0 | K57: 0 | L57: 0 | M57: 0 | N57: 0 | O57: 0 | P57: 0 | Q57: 39 | R57: 6 | S57: 39.75 | T57: 0 | U57: 0 | V57: 0 | W57: 0 | X57: 39 | Y57: 6 | Z57: 39.75 | AA57: 39.75 | AB57: 0 | AC57: 39 | AD57: 6

Sheet Sale of Corn Prices
A1: Heading | B1: Sentence | C1: Total in Pounds | D1: Pounds | E1: Shillings | F1: Pence | G1: Corn | H1: Total Quarters Except 1 | I1: Total Bushels Except 1 | J1: Total Corn Cross-Check | K1: Total Corn Manorial Account | L1: Corn Quantity Error | M1: Quarters 0 | N1: Bushels 0 | O1: shilling a quarter 1 | P1: pence a quarter 1 | Q1: Quarters 1 | R1: Bushels 1 | S1: shilling a quarter 2 | T1: pence a quarter 2 | U1: Quarters 2 | V1: Bushels 2 | W1: shilling a quarter 3 | X1: pence a quarter 3 | Y1: shilling a quarter 4 | Z1: pence a quarter 4 | AA1: £ a quarter 1 | AB1: £ a quarter 2 | AC1: £ a quarter 3 | AD1: £ a quarter 4 | AE1: Quarters Sold | AF1: Weighted Average Price per Quarter | AG1: Non-Weighted Average Price per Quarter | AH1: Corn lowercase
A2: Sale of corn | B2: The same render account for £30 3 shilling 4pence from 90.5 quarters of wheat sold, at 6 shilling 8pence a quarters. | C2: 30.17 | D2: 30 | E2: 3 | F2: 4 | G2: wheat | H2: 90.5 | I2: 0 | J2: 90.5 | K2: 90.5 | L2: 0 | M2: 90.5 | N2: 0 | O2: 6 | P2: 8 | AA2: 0.33333333 | AE2: 90.5 | AF2: 0.33333333 | AG2: 0.33333333 | AH2: wheat
A3: Sale of corn | B3: £5 7 shilling 6pence from 26 quarters 7 bushels of bere sold, at 4 shilling a quarters. | C3: 5.38 | D3: 5 | E3: 7 | F3: 6 | H3: 26 | I3: 7 | J3: 26.875 | K3: 26.875 | L3: 0 | M3: 26 | N3: 7 | O3: 4 | P3: 0 | AA3: 0.2 | AE3: 26.875 | AF3: 0.2 | AG3: 0.2
A4: Sale of corn | B4: 18 shilling 6pence from 4 quarters 5 bushels of barley sold, at 4 shilling a quarters. | C4: 0.93 | D4: 0 | E4: 18 | F4: 6 | G4: barley | H4: 4 | I4: 5 | J4: 4.625 | K4: 4.625 | L4: 0 | M4: 4 | N4: 5 | O4: 4 | P4: 0 | AA4: 0.2 | AE4: 4.625 | AF4: 0.2 | AG4: 0.2 | AH4: barley
A5: Sale of corn | B5: £4 12 shilling 10.5pence from 39 quarters 6 bushels of oats sold, at 2 shilling a quarters for 13 quarters, and 2 shilling 6pence a quarters for 26 quarters 6 bushels Total of all corn sold, £41 2 shilling 2.5pence | C5: 4.64 | D5: 4 | E5: 12 | F5: 10.5 | G5: oats | H5: 39 | I5: 6 | J5: 39.75 | K5: 39.75 | L5: 0 | M5: 39 | N5: 6 | O5: 2 | P5: 0 | Q5: 13 | R5: 0 | S5: 2 | T5: 6 | U5: 26 | V5: 6 | AA5: 0.1 | AB5: 0.125 | AE5: 39.75 | AF5: 0.1168239 | AG5: 0.1125 | AH5: oats
