Workbook

Sheet Crawley Overview
A1: CRAWLEY | B1: £ | C1: s | D1: d | G1: Total in £ | H1: Error
A3: CASH ACCOUNT
A4: RECEIPTS
A5: Arrears total | G5: =IF(INDEX('Crawley Receipts'!$A$4:$F$110,MATCH('Crawley Overview'!$A5,'Crawley Receipts'!$A$4:$A$110,0),6)=0,"",INDEX('Crawley Receipts'!$A$4:$F$110,MATCH('Crawley Overview'!$A5,'Crawley Receipts'!$A$4:$A$110,0),6)) -> 7.4333333
A6: Rents of assize total | G6: =IF(INDEX('Crawley Receipts'!$A$4:$F$110,MATCH('Crawley Overview'!$A6,'Crawley Receipts'!$A$4:$A$110,0),6)=0,"",INDEX('Crawley Receipts'!$A$4:$F$110,MATCH('Crawley Overview'!$A6,'Crawley Receipts'!$A$4:$A$110,0),6)) -> 14.079167
A7: Quittances total | G7: =IF(INDEX('Crawley Receipts'!$A$4:$F$110,MATCH('Crawley Overview'!$A7,'Crawley Receipts'!$A$4:$A$110,0),6)=0,"",INDEX('Crawley Receipts'!$A$4:$F$110,MATCH('Crawley Overview'!$A7,'Crawley Receipts'!$A$4:$A$110,0),6)) -> 2.7833333
A8: Defaults of rent total | G8: =IF(INDEX('Crawley Receipts'!$A$4:$F$110,MATCH('Crawley Overview'!$A8,'Crawley Receipts'!$A$4:$A$110,0),6)=0,"",INDEX('Crawley Receipts'!$A$4:$F$110,MATCH('Crawley Overview'!$A8,'Crawley Receipts'!$A$4:$A$110,0),6)) -> 1.0166667
A9: Total of rents remaining | G9: ='Crawley Receipts'!F36 -> 10.279167
A10: Annual recognizances total | G10: =IF(INDEX('Crawley Receipts'!$A$4:$F$110,MATCH('Crawley Overview'!$A10,'Crawley Receipts'!$A$4:$A$110,0),6)=0,"",INDEX('Crawley Receipts'!$A$4:$F$110,MATCH('Crawley Overview'!$A10,'Crawley Receipts'!$A$4:$A$110,0),6)) -> 0.0875
A11: Issues of the Manor total | G11: =IF(INDEX('Crawley Receipts'!$A$4:$F$110,MATCH('Crawley Overview'!$A11,'Crawley Receipts'!$A$4:$A$110,0),6)=0,"",INDEX('Crawley Receipts'!$A$4:$F$110,MATCH('Crawley Overview'!$A11,'Crawley Receipts'!$A$4:$A$110,0),6)) -> 19.945833
A12: Sale of corn total | G12: =IF(INDEX('Crawley Receipts'!$A$4:$F$110,MATCH('Crawley Overview'!$A12,'Crawley Receipts'!$A$4:$A$110,0),6)=0,"",INDEX('Crawley Receipts'!$A$4:$F$110,MATCH('Crawley Overview'!$A12,'Crawley Receipts'!$A$4:$A$110,0),6)) -> 23.983333
A13: Entry and marriage fines total | G13: =IF(INDEX('Crawley Receipts'!$A$4:$F$110,MATCH('Crawley Overview'!$A13,'Crawley Receipts'!$A$4:$A$110,0),6)=0,"",INDEX('Crawley Receipts'!$A$4:$F$110,MATCH('Crawley Overview'!$A13,'Crawley Receipts'!$A$4:$A$110,0),6)) -> 0.86666667
A14: Pleas & perquisites total | G14: =IF(INDEX('Crawley Receipts'!$A$4:$F$110,MATCH('Crawley Overview'!$A14,'Crawley Receipts'!$A$4:$A$110,0),6)=0,"",INDEX('Crawley Receipts'!$A$4:$F$110,MATCH('Crawley Overview'!$A14,'Crawley Receipts'!$A$4:$A$110,0),6)) -> 0.99583333
A15: Sum of the above (incl. arrears) | G15: =G5+G9+G10+G11+G12+G13+G14 -> 63.591667
A16: Total recorded in the accounts excl. arrears | G16: ='Crawley Receipts'!F110 -> 56.1625 | H16: matches excl. arrear sum
A17: Total recorded in the accounts incl. arrears
A20: EXPENSES
A21: Cost of ploughs total | G21: =IF(INDEX('Crawley Expenses'!$A$2:$F$108,MATCH('Crawley Overview'!$A21,'Crawley Expenses'!$A$2:$A$108,0),6)=0,"",INDEX('Crawley Expenses'!$A$2:$F$108,MATCH('Crawley Overview'!$A21,'Crawley Expenses'!$A$2:$A$108,0),6)) -> 3.553125
A22: Purchase of corn total | G22: =IF(INDEX('Crawley Expenses'!$A$2:$F$108,MATCH('Crawley Overview'!$A22,'Crawley Expenses'!$A$2:$A$108,0),6)=0,"",INDEX('Crawley Expenses'!$A$2:$F$108,MATCH('Crawley Overview'!$A22,'Crawley Expenses'!$A$2:$A$108,0),6)) -> 0.84166667
A23: Cost of carts and wagons total | G23: =IF(INDEX('Crawley Expenses'!$A$2:$F$108,MATCH('Crawley Overview'!$A23,'Crawley Expenses'!$A$2:$A$108,0),6)=0,"",INDEX('Crawley Expenses'!$A$2:$F$108,MATCH('Crawley Overview'!$A23,'Crawley Expenses'!$A$2:$A$108,0),6)) -> 0.81875
A24: Cost of dairy total | G24: =IF(INDEX('Crawley Expenses'!$A$2:$F$108,MATCH('Crawley Overview'!$A24,'Crawley Expenses'!$A$2:$A$108,0),6)=0,"",INDEX('Crawley Expenses'!$A$2:$F$108,MATCH('Crawley Overview'!$A24,'Crawley Expenses'!$A$2:$A$108,0),6)) -> 3.9729167
A25: Cost of buildings total | G25: =IF(INDEX('Crawley Expenses'!$A$2:$F$108,MATCH('Crawley Overview'!$A25,'Crawley Expenses'!$A$2:$A$108,0),6)=0,"",INDEX('Crawley Expenses'!$A$2:$F$108,MATCH('Crawley Overview'!$A25,'Crawley Expenses'!$A$2:$A$108,0),6)) -> 0.321875
A26: Threshing total | G26: =IF(INDEX('Crawley Expenses'!$A$2:$F$108,MATCH('Crawley Overview'!$A26,'Crawley Expenses'!$A$2:$A$108,0),6)=0,"",INDEX('Crawley Expenses'!$A$2:$F$108,MATCH('Crawley Overview'!$A26,'Crawley Expenses'!$A$2:$A$108,0),6)) -> 1.0208333
A27: Expenses of the harvest total | G27: =IF(INDEX('Crawley Expenses'!$A$2:$F$108,MATCH('Crawley Overview'!$A27,'Crawley Expenses'!$A$2:$A$108,0),6)=0,"",INDEX('Crawley Expenses'!$A$2:$F$108,MATCH('Crawley Overview'!$A27,'Crawley Expenses'!$A$2:$A$108,0),6)) -> 1.6916667
A28: Steward's expenses total | G28: =IF(INDEX('Crawley Expenses'!$A$2:$F$108,MATCH('Crawley Overview'!$A28,'Crawley Expenses'!$A$2:$A$108,0),6)=0,"",INDEX('Crawley Expenses'!$A$2:$F$108,MATCH('Crawley Overview'!$A28,'Crawley Expenses'!$A$2:$A$108,0),6)) -> 1.2177083
A29: Sum of the above | G29: =SUM(G21:G28) -> 13.438542
A30: Total of all expenses | G30: ='Crawley Expenses'!F103 -> 13.403125 | H30: =G29-G30 -> 0.035416667
A31: Total Demesne fixed investment | G31: ='Crawley Expenses'!F108 -> 8.8708333
A33: Owed by the reeve | G33: ='Crawley Expenses'!F105 -> 42.726042
A34: From accounts
A36: Cash deliveries | G36: ='Crawley Expenses'!F106 -> 27.716667
A37: Total of all allowances and cash deliveries in accounts | B37: n/a
A39: Net amount owed | G39: =G33-G36 -> 15.009375
A40: Net amount owed in accounts | G40: ='Crawley Expenses'!F107 -> 15.009375 | H40: =G39-G40 -> 0
A42: GRANGE ACCOUNT | B42: Net Production
A43: Grange | B43: qrs | G43: £ | I43: Note: Columns indexed are hardcoded, do not alter number of columns in issues of grange
A44: Net wheat | B44: =IF(INDEX('Issues of the Grange'!$A$2:$P$26,MATCH('Crawley Overview'!$A44,'Issues of the Grange'!$A$2:$A$26,0),10)=0,"",INDEX('Issues of the Grange'!$A$2:$P$26,MATCH('Crawley Overview'!$A44,'Issues of the Grange'!$A$2:$A$26,0),10)) -> 40 | G44: =IF(INDEX('Issues of the Grange'!$A$2:$P$26,MATCH('Crawley Overview'!$A44,'Issues of the Grange'!$A$2:$A$26,0),13)=0,"",INDEX('Issues of the Grange'!$A$2:$P$26,MATCH('Crawley Overview'!$A44,'Issues of the Grange'!$A$2:$A$26,0),13)) -> 11.908333
A45: Net curall | B45: =IF(INDEX('Issues of the Grange'!$A$2:$P$26,MATCH('Crawley Overview'!$A45,'Issues of the Grange'!$A$2:$A$26,0),10)=0,"",INDEX('Issues of the Grange'!$A$2:$P$26,MATCH('Crawley Overview'!$A45,'Issues of the Grange'!$A$2:$A$26,0),10)) -> 12.0625 | G45: =IF(INDEX('Issues of the Grange'!$A$2:$P$26,MATCH('Crawley Overview'!$A45,'Issues of the Grange'!$A$2:$A$26,0),13)=0,"",INDEX('Issues of the Grange'!$A$2:$P$26,MATCH('Crawley Overview'!$A45,'Issues of the Grange'!$A$2:$A$26,0),13)) -> 2.2770833
A46: Net Bere | B46: =IF(INDEX('Issues of the Grange'!$A$2:$P$26,MATCH('Crawley Overview'!$A46,'Issues of the Grange'!$A$2:$A$26,0),10)=0,"",INDEX('Issues of the Grange'!$A$2:$P$26,MATCH('Crawley Overview'!$A46,'Issues of the Grange'!$A$2:$A$26,0),10)) | G46: =IF(INDEX('Issues of the Grange'!$A$2:$P$26,MATCH('Crawley Overview'!$A46,'Issues of the Grange'!$A$2:$A$26,0),13)=0,"",INDEX('Issues of the Grange'!$A$2:$P$26,MATCH('Crawley Overview'!$A46,'Issues of the Grange'!$A$2:$A$26,0),13))
A47: Net barley | B47: =IF(INDEX('Issues of the Grange'!$A$2:$P$26,MATCH('Crawley Overview'!$A47,'Issues of the Grange'!$A$2:$A$26,0),10)=0,"",INDEX('Issues of the Grange'!$A$2:$P$26,MATCH('Crawley Overview'!$A47,'Issues of the Grange'!$A$2:$A$26,0),10)) -> 22.1875 | G47: =IF(INDEX('Issues of the Grange'!$A$2:$P$26,MATCH('Crawley Overview'!$A47,'Issues of the Grange'!$A$2:$A$26,0),13)=0,"",INDEX('Issues of the Grange'!$A$2:$P$26,MATCH('Crawley Overview'!$A47,'Issues of the Grange'!$A$2:$A$26,0),13)) -> 4.4832046
A48: Net oats | B48: =IF(INDEX('Issues of the Grange'!$A$2:$P$26,MATCH('Crawley Overview'!$A48,'Issues of the Grange'!$A$2:$A$26,0),10)=0,"",INDEX('Issues of the Grange'!$A$2:$P$26,MATCH('Crawley Overview'!$A48,'Issues of the Grange'!$A$2:$A$26,0),10)) -> 43 | G48: =IF(INDEX('Issues of the Grange'!$A$2:$P$26,MATCH('Crawley Overview'!$A48,'Issues of the Grange'!$A$2:$A$26,0),13)=0,"",INDEX('Issues of the Grange'!$A$2:$P$26,MATCH('Crawley Overview'!$A48,'Issues of the Grange'!$A$2:$A$26,0),13)) -> 4.3833333
A49: Net peas | B49: =IF(INDEX('Issues of the Grange'!$A$2:$P$26,MATCH('Crawley Overview'!$A49,'Issues of the Grange'!$A$2:$A$26,0),10)=0,"",INDEX('Issues of the Grange'!$A$2:$P$26,MATCH('Crawley Overview'!$A49,'Issues of the Grange'!$A$2:$A$26,0),10)) -> 3.125 | G49: =IF(INDEX('Issues of the Grange'!$A$2:$P$26,MATCH('Crawley Overview'!$A49,'Issues of the Grange'!$A$2:$A$26,0),13)=0,"",INDEX('Issues of the Grange'!$A$2:$P$26,MATCH('Crawley Overview'!$A49,'Issues of the Grange'!$A$2:$A$26,0),13)) -> 0.46875
A50: Net vetches | B50: =IF(INDEX('Issues of the Grange'!$A$2:$P$26,MATCH('Crawley Overview'!$A50,'Issues of the Grange'!$A$2:$A$26,0),10)=0,"",INDEX('Issues of the Grange'!$A$2:$P$26,MATCH('Crawley Overview'!$A50,'Issues of the Grange'!$A$2:$A$26,0),10)) -> 4.5 | G50: =IF(INDEX('Issues of the Grange'!$A$2:$P$26,MATCH('Crawley Overview'!$A50,'Issues of the Grange'!$A$2:$A$26,0),13)=0,"",INDEX('Issues of the Grange'!$A$2:$P$26,MATCH('Crawley Overview'!$A50,'Issues of the Grange'!$A$2:$A$26,0),13)) -> 0.45
A51: Net value of production (sum of the above) | G51: =SUM(G44:G50) -> 23.970705
A52: Value of sales | G52: ='Issues of the Grange'!N26 -> 23.983333
A54: MILL ACCOUNT
A55: Issues of the mill | B55: qrs | C55: bus | G55: £ | I55: no mill account
A56: Wheat
A57: Oatmeal
A58: 1st grade malt
A59: 2nd grade malt
A60: Maslin
A61: Total value of production (sum of the above)
A62: Value of sales
A64: STOCK ACCOUNT
A65: Livestock | B65: Inherited stock | C65: End-period stock | D65: Stockbuilding | F65: Sales in (£) | G65: Value of production (£) at sales prices
A66: Cart-horses | B66: =IFERROR(INDEX(Stock!$A$3:$T$92,MATCH('Crawley Overview'!$A66,Stock!$A$3:$A$92,0),MATCH('Crawley Overview'!B$65,Stock!$A$3:$T$3,0)),0) -> 2 | C66: =IFERROR(INDEX(Stock!$A$3:$T$92,MATCH('Crawley Overview'!$A66,Stock!$A$3:$A$92,0),MATCH('Crawley Overview'!C$65,Stock!$A$3:$T$3,0)),0) -> 2 | D66: =C66-B66 -> 0 | F66: =IFERROR(INDEX(Stock!$A$3:$T$92,MATCH('Crawley Overview'!$A66,Stock!$A$3:$A$92,0),MATCH('Crawley Overview'!F$65,Stock!$A$3:$T$3,0)),0) | G66: =IFERROR(INDEX(Stock!$A$3:$T$92,MATCH('Crawley Overview'!$A66,Stock!$A$3:$A$92,0),MATCH('Crawley Overview'!G$65,Stock!$A$3:$T$3,0)),0)
A67: Mares | B67: =IFERROR(INDEX(Stock!$A$3:$T$92,MATCH('Crawley Overview'!$A67,Stock!$A$3:$A$92,0),MATCH('Crawley Overview'!B$65,Stock!$A$3:$T$3,0)),0) -> 0 | C67: =IFERROR(INDEX(Stock!$A$3:$T$92,MATCH('Crawley Overview'!$A67,Stock!$A$3:$A$92,0),MATCH('Crawley Overview'!C$65,Stock!$A$3:$T$3,0)),0) -> 0 | D67: =C67-B67 -> 0 | F67: =IFERROR(INDEX(Stock!$A$3:$T$92,MATCH('Crawley Overview'!$A67,Stock!$A$3:$A$92,0),MATCH('Crawley Overview'!F$65,Stock!$A$3:$T$3,0)),0) | G67: =IFERROR(INDEX(Stock!$A$3:$T$92,MATCH('Crawley Overview'!$A67,Stock!$A$3:$A$92,0),MATCH('Crawley Overview'!G$65,Stock!$A$3:$T$3,0)),0)
A68: Plough horses | B68: =IFERROR(INDEX(Stock!$A$3:$T$92,MATCH('Crawley Overview'!$A68,Stock!$A$3:$A$92,0),MATCH('Crawley Overview'!B$65,Stock!$A$3:$T$3,0)),0) -> 5 | C68: =IFERROR(INDEX(Stock!$A$3:$T$92,MATCH('Crawley Overview'!$A68,Stock!$A$3:$A$92,0),MATCH('Crawley Overview'!C$65,Stock!$A$3:$T$3,0)),0) -> 6 | D68: =C68-B68 -> 1 | F68: =IFERROR(INDEX(Stock!$A$3:$T$92,MATCH('Crawley Overview'!$A68,Stock!$A$3:$A$92,0),MATCH('Crawley Overview'!F$65,Stock!$A$3:$T$3,0)),0) | G68: =IFERROR(INDEX(Stock!$A$3:$T$92,MATCH('Crawley Overview'!$A68,Stock!$A$3:$A$92,0),MATCH('Crawley Overview'!G$65,Stock!$A$3:$T$3,0)),0)
A69: Colts (2 years) | B69: =IFERROR(INDEX(Stock!$A$3:$T$92,MATCH('Crawley Overview'!$A69,Stock!$A$3:$A$92,0),MATCH('Crawley Overview'!B$65,Stock!$A$3:$T$3,0)),0) -> 0 | C69: =IFERROR(INDEX(Stock!$A$3:$T$92,MATCH('Crawley Overview'!$A69,Stock!$A$3:$A$92,0),MATCH('Crawley Overview'!C$65,Stock!$A$3:$T$3,0)),0) -> 0 | D69: =C69-B69 -> 0 | F69: =IFERROR(INDEX(Stock!$A$3:$T$92,MATCH('Crawley Overview'!$A69,Stock!$A$3:$A$92,0),MATCH('Crawley Overview'!F$65,Stock!$A$3:$T$3,0)),0) | G69: =IFERROR(INDEX(Stock!$A$3:$T$92,MATCH('Crawley Overview'!$A69,Stock!$A$3:$A$92,0),MATCH('Crawley Overview'!G$65,Stock!$A$3:$T$3,0)),0)
A70: Colts (2 years) | B70: =IFERROR(INDEX(Stock!$A$3:$T$92,MATCH('Crawley Overview'!$A70,Stock!$A$3:$A$92,0),MATCH('Crawley Overview'!B$65,Stock!$A$3:$T$3,0)),0) -> 0 | C70: =IFERROR(INDEX(Stock!$A$3:$T$92,MATCH('Crawley Overview'!$A70,Stock!$A$3:$A$92,0),MATCH('Crawley Overview'!C$65,Stock!$A$3:$T$3,0)),0) -> 0 | D70: =C70-B70 -> 0 | F70: =IFERROR(INDEX(Stock!$A$3:$T$92,MATCH('Crawley Overview'!$A70,Stock!$A$3:$A$92,0),MATCH('Crawley Overview'!F$65,Stock!$A$3:$T$3,0)),0) | G70: =IFERROR(INDEX(Stock!$A$3:$T$92,MATCH('Crawley Overview'!$A70,Stock!$A$3:$A$92,0),MATCH('Crawley Overview'!G$65,Stock!$A$3:$T$3,0)),0)
A71: Colts (1 year) | B71: =IFERROR(INDEX(Stock!$A$3:$T$92,MATCH('Crawley Overview'!$A71,Stock!$A$3:$A$92,0),MATCH('Crawley Overview'!B$65,Stock!$A$3:$T$3,0)),0) -> 0 | C71: =IFERROR(INDEX(Stock!$A$3:$T$92,MATCH('Crawley Overview'!$A71,Stock!$A$3:$A$92,0),MATCH('Crawley Overview'!C$65,Stock!$A$3:$T$3,0)),0) -> 0 | D71: =C71-B71 -> 0 | F71: =IFERROR(INDEX(Stock!$A$3:$T$92,MATCH('Crawley Overview'!$A71,Stock!$A$3:$A$92,0),MATCH('Crawley Overview'!F$65,Stock!$A$3:$T$3,0)),0) | G71: =IFERROR(INDEX(Stock!$A$3:$T$92,MATCH('Crawley Overview'!$A71,Stock!$A$3:$A$92,0),MATCH('Crawley Overview'!G$65,Stock!$A$3:$T$3,0)),0)
A72: Foals | B72: =IFERROR(INDEX(Stock!$A$3:$T$92,MATCH('Crawley Overview'!$A72,Stock!$A$3:$A$92,0),MATCH('Crawley Overview'!B$65,Stock!$A$3:$T$3,0)),0) -> 0 | C72: =IFERROR(INDEX(Stock!$A$3:$T$92,MATCH('Crawley Overview'!$A72,Stock!$A$3:$A$92,0),MATCH('Crawley Overview'!C$65,Stock!$A$3:$T$3,0)),0) -> 0 | D72: =C72-B72 -> 0 | F72: =IFERROR(INDEX(Stock!$A$3:$T$92,MATCH('Crawley Overview'!$A72,Stock!$A$3:$A$92,0),MATCH('Crawley Overview'!F$65,Stock!$A$3:$T$3,0)),0) | G72: =IFERROR(INDEX(Stock!$A$3:$T$92,MATCH('Crawley Overview'!$A72,Stock!$A$3:$A$92,0),MATCH('Crawley Overview'!G$65,Stock!$A$3:$T$3,0)),0)
A73: Oxen | B73: =IFERROR(INDEX(Stock!$A$3:$T$92,MATCH('Crawley Overview'!$A73,Stock!$A$3:$A$92,0),MATCH('Crawley Overview'!B$65,Stock!$A$3:$T$3,0)),0) -> 30 | C73: =IFERROR(INDEX(Stock!$A$3:$T$92,MATCH('Crawley Overview'!$A73,Stock!$A$3:$A$92,0),MATCH('Crawley Overview'!C$65,Stock!$A$3:$T$3,0)),0) -> 35 | D73: =C73-B73 -> 5 | F73: =IFERROR(INDEX(Stock!$A$3:$T$92,MATCH('Crawley Overview'!$A73,Stock!$A$3:$A$92,0),MATCH('Crawley Overview'!F$65,Stock!$A$3:$T$3,0)),0) | G73: =IFERROR(INDEX(Stock!$A$3:$T$92,MATCH('Crawley Overview'!$A73,Stock!$A$3:$A$92,0),MATCH('Crawley Overview'!G$65,Stock!$A$3:$T$3,0)),0)
A74: Bulls | B74: =IFERROR(INDEX(Stock!$A$3:$T$92,MATCH('Crawley Overview'!$A74,Stock!$A$3:$A$92,0),MATCH('Crawley Overview'!B$65,Stock!$A$3:$T$3,0)),0) -> 1 | C74: =IFERROR(INDEX(Stock!$A$3:$T$92,MATCH('Crawley Overview'!$A74,Stock!$A$3:$A$92,0),MATCH('Crawley Overview'!C$65,Stock!$A$3:$T$3,0)),0) -> 1 | D74: =C74-B74 -> 0 | F74: =IFERROR(INDEX(Stock!$A$3:$T$92,MATCH('Crawley Overview'!$A74,Stock!$A$3:$A$92,0),MATCH('Crawley Overview'!F$65,Stock!$A$3:$T$3,0)),0) | G74: =IFERROR(INDEX(Stock!$A$3:$T$92,MATCH('Crawley Overview'!$A74,Stock!$A$3:$A$92,0),MATCH('Crawley Overview'!G$65,Stock!$A$3:$T$3,0)),0)
A75: Cows | B75: =IFERROR(INDEX(Stock!$A$3:$T$92,MATCH('Crawley Overview'!$A75,Stock!$A$3:$A$92,0),MATCH('Crawley Overview'!B$65,Stock!$A$3:$T$3,0)),0) -> 17 | C75: =IFERROR(INDEX(Stock!$A$3:$T$92,MATCH('Crawley Overview'!$A75,Stock!$A$3:$A$92,0),MATCH('Crawley Overview'!C$65,Stock!$A$3:$T$3,0)),0) -> 19 | D75: =C75-B75 -> 2 | F75: =IFERROR(INDEX(Stock!$A$3:$T$92,MATCH('Crawley Overview'!$A75,Stock!$A$3:$A$92,0),MATCH('Crawley Overview'!F$65,Stock!$A$3:$T$3,0)),0) | G75: =IFERROR(INDEX(Stock!$A$3:$T$92,MATCH('Crawley Overview'!$A75,Stock!$A$3:$A$92,0),MATCH('Crawley Overview'!G$65,Stock!$A$3:$T$3,0)),0)
A76: Steers | B76: =IFERROR(INDEX(Stock!$A$3:$T$92,MATCH('Crawley Overview'!$A76,Stock!$A$3:$A$92,0),MATCH('Crawley Overview'!B$65,Stock!$A$3:$T$3,0)),0) -> 4 | C76: =IFERROR(INDEX(Stock!$A$3:$T$92,MATCH('Crawley Overview'!$A76,Stock!$A$3:$A$92,0),MATCH('Crawley Overview'!C$65,Stock!$A$3:$T$3,0)),0) -> 0 | D76: =C76-B76 -> -4 | F76: =IFERROR(INDEX(Stock!$A$3:$T$92,MATCH('Crawley Overview'!$A76,Stock!$A$3:$A$92,0),MATCH('Crawley Overview'!F$65,Stock!$A$3:$T$3,0)),0) | G76: =IFERROR(INDEX(Stock!$A$3:$T$92,MATCH('Crawley Overview'!$A76,Stock!$A$3:$A$92,0),MATCH('Crawley Overview'!G$65,Stock!$A$3:$T$3,0)),0)
A77: Bullocks | B77: =IFERROR(INDEX(Stock!$A$3:$T$92,MATCH('Crawley Overview'!$A77,Stock!$A$3:$A$92,0),MATCH('Crawley Overview'!B$65,Stock!$A$3:$T$3,0)),0) -> 5 | C77: =IFERROR(INDEX(Stock!$A$3:$T$92,MATCH('Crawley Overview'!$A77,Stock!$A$3:$A$92,0),MATCH('Crawley Overview'!C$65,Stock!$A$3:$T$3,0)),0) -> 4 | D77: =C77-B77 -> -1 | F77: =IFERROR(INDEX(Stock!$A$3:$T$92,MATCH('Crawley Overview'!$A77,Stock!$A$3:$A$92,0),MATCH('Crawley Overview'!F$65,Stock!$A$3:$T$3,0)),0) | G77: =IFERROR(INDEX(Stock!$A$3:$T$92,MATCH('Crawley Overview'!$A77,Stock!$A$3:$A$92,0),MATCH('Crawley Overview'!G$65,Stock!$A$3:$T$3,0)),0)
... A91: Peacocks | B91: =IFERROR(INDEX(Stock!$A$3:$T$92,MATCH('Crawley Overview'!$A91,Stock!$A$3:$A$92,0),MATCH('Crawley Overview'!B$65,Stock!$A$3:$T$3,0)),0) -> 0 | C91: =IFERROR(INDEX(Stock!$A$3:$T$92,MATCH('Crawley Overview'!$A91,Stock!$A$3:$A$92,0),MATCH('Crawley Overview'!C$65,Stock!$A$3:$T$3,0)),0) -> 0 | D91: =C91-B91 -> 0 | F91: =IFERROR(INDEX(Stock!$A$3:$T$92,MATCH('Crawley Overview'!$A91,Stock!$A$3:$A$92,0),MATCH('Crawley Overview'!F$65,Stock!$A$3:$T$3,0)),0) | G91: =IFERROR(INDEX(Stock!$A$3:$T$92,MATCH('Crawley Overview'!$A91,Stock!$A$3:$A$92,0),MATCH('Crawley Overview'!G$65,Stock!$A$3:$T$3,0)),0)
A92: Total | G92: =SUM(G66:G91) -> 17.563462
A93: Value of sales | G93: =SUM(F66:F91) -> 8.65
A95: Wool | B95: Inherited stock | C95: End-period stock | D95: Stockbuilding | F95: Sales in (£) | G95: Value of production (£) at sales prices
A96: Fleeces | B96: =IFERROR(INDEX(Stock!$A$3:$T$92,MATCH('Crawley Overview'!$A96,Stock!$A$3:$A$92,0),MATCH('Crawley Overview'!B$65,Stock!$A$3:$T$3,0)),0) -> 0 | C96: =IFERROR(INDEX(Stock!$A$3:$T$92,MATCH('Crawley Overview'!$A96,Stock!$A$3:$A$92,0),MATCH('Crawley Overview'!C$65,Stock!$A$3:$T$3,0)),0) -> 0 | D96: =C96-B96 -> 0 | F96: =IFERROR(INDEX(Stock!$A$3:$T$92,MATCH('Crawley Overview'!$A96,Stock!$A$3:$A$92,0),MATCH('Crawley Overview'!F$65,Stock!$A$3:$T$3,0)),0) | G96: =IFERROR(INDEX(Stock!$A$3:$T$92,MATCH('Crawley Overview'!$A96,Stock!$A$3:$A$92,0),MATCH('Crawley Overview'!G$65,Stock!$A$3:$T$3,0)),0)
A97: Coarse wool | B97: =IFERROR(INDEX(Stock!$A$3:$T$92,MATCH('Crawley Overview'!$A97,Stock!$A$3:$A$92,0),MATCH('Crawley Overview'!B$65,Stock!$A$3:$T$3,0)),0) -> 0 | C97: =IFERROR(INDEX(Stock!$A$3:$T$92,MATCH('Crawley Overview'!$A97,Stock!$A$3:$A$92,0),MATCH('Crawley Overview'!C$65,Stock!$A$3:$T$3,0)),0) -> 0 | D97: =C97-B97 -> 0 | F97: =IFERROR(INDEX(Stock!$A$3:$T$92,MATCH('Crawley Overview'!$A97,Stock!$A$3:$A$92,0),MATCH('Crawley Overview'!F$65,Stock!$A$3:$T$3,0)),0) -> 18.58 | G97: =IFERROR(INDEX(Stock!$A$3:$T$92,MATCH('Crawley Overview'!$A97,Stock!$A$3:$A$92,0),MATCH('Crawley Overview'!G$65,Stock!$A$3:$T$3,0)),0) -> 20.7
A98: Lamb's wool | B98: =IFERROR(INDEX(Stock!$A$3:$T$92,MATCH('Crawley Overview'!$A98,Stock!$A$3:$A$92,0),MATCH('Crawley Overview'!B$65,Stock!$A$3:$T$3,0)),0) -> 0 | C98: =IFERROR(INDEX(Stock!$A$3:$T$92,MATCH('Crawley Overview'!$A98,Stock!$A$3:$A$92,0),MATCH('Crawley Overview'!C$65,Stock!$A$3:$T$3,0)),0) -> 0 | D98: =C98-B98 -> 0 | F98: =IFERROR(INDEX(Stock!$A$3:$T$92,MATCH('Crawley Overview'!$A98,Stock!$A$3:$A$92,0),MATCH('Crawley Overview'!F$65,Stock!$A$3:$T$3,0)),0) -> 2.83 | G98: =IFERROR(INDEX(Stock!$A$3:$T$92,MATCH('Crawley Overview'!$A98,Stock!$A$3:$A$92,0),MATCH('Crawley Overview'!G$65,Stock!$A$3:$T$3,0)),0) -> 2.83
A99: Wool locks | B99: =IFERROR(INDEX(Stock!$A$3:$T$92,MATCH('Crawley Overview'!$A99,Stock!$A$3:$A$92,0),MATCH('Crawley Overview'!B$65,Stock!$A$3:$T$3,0)),0) -> 0 | C99: =IFERROR(INDEX(Stock!$A$3:$T$92,MATCH('Crawley Overview'!$A99,Stock!$A$3:$A$92,0),MATCH('Crawley Overview'!C$65,Stock!$A$3:$T$3,0)),0) -> 0 | D99: =C99-B99 -> 0 | F99: =IFERROR(INDEX(Stock!$A$3:$T$92,MATCH('Crawley Overview'!$A99,Stock!$A$3:$A$92,0),MATCH('Crawley Overview'!F$65,Stock!$A$3:$T$3,0)),0) -> 0.21875 | G99: =IFERROR(INDEX(Stock!$A$3:$T$92,MATCH('Crawley Overview'!$A99,Stock!$A$3:$A$92,0),MATCH('Crawley Overview'!G$65,Stock!$A$3:$T$3,0)),0) -> 0.21875
A100: Wool sold at shearing | B100: =IFERROR(INDEX(Stock!$A$3:$T$92,MATCH('Crawley Overview'!$A100,Stock!$A$3:$A$92,0),MATCH('Crawley Overview'!B$65,Stock!$A$3:$T$3,0)),0) -> 0 | C100: =IFERROR(INDEX(Stock!$A$3:$T$92,MATCH('Crawley Overview'!$A100,Stock!$A$3:$A$92,0),MATCH('Crawley Overview'!C$65,Stock!$A$3:$T$3,0)),0) -> 0 | D100: =C100-B100 -> 0 | F100: =IFERROR(INDEX(Stock!$A$3:$T$92,MATCH('Crawley Overview'!$A100,Stock!$A$3:$A$92,0),MATCH('Crawley Overview'!F$65,Stock!$A$3:$T$3,0)),0) | G100: =IFERROR(INDEX(Stock!$A$3:$T$92,MATCH('Crawley Overview'!$A100,Stock!$A$3:$A$92,0),MATCH('Crawley Overview'!G$65,Stock!$A$3:$T$3,0)),0)
A101: Total value of production (sum of the above) | G101: =SUM(G96:G100) -> 23.74875
A102: Value of sales | G102: =SUM(F96:F100) -> 21.62875
A104: Hides | B104: Inherited stock | C104: End-period stock | D104: Stockbuilding | F104: Sales in (£) | G104: Value of production (£) at sales prices
A105: Ox hides | B105: =IFERROR(INDEX(Stock!$A$3:$T$92,MATCH('Crawley Overview'!$A105,Stock!$A$3:$A$92,0),MATCH('Crawley Overview'!B$65,Stock!$A$3:$T$3,0)),0) -> 0 | C105: =IFERROR(INDEX(Stock!$A$3:$T$92,MATCH('Crawley Overview'!$A105,Stock!$A$3:$A$92,0),MATCH('Crawley Overview'!C$65,Stock!$A$3:$T$3,0)),0) -> 0 | D105: =C105-B105 -> 0 | F105: =IFERROR(INDEX(Stock!$A$3:$T$92,MATCH('Crawley Overview'!$A105,Stock!$A$3:$A$92,0),MATCH('Crawley Overview'!F$65,Stock!$A$3:$T$3,0)),0) -> 0.22708333 | G105: =IFERROR(INDEX(Stock!$A$3:$T$92,MATCH('Crawley Overview'!$A105,Stock!$A$3:$A$92,0),MATCH('Crawley Overview'!G$65,Stock!$A$3:$T$3,0)),0) -> 0.22708333
A106: Cow hides | B106: =IFERROR(INDEX(Stock!$A$3:$T$92,MATCH('Crawley Overview'!$A106,Stock!$A$3:$A$92,0),MATCH('Crawley Overview'!B$65,Stock!$A$3:$T$3,0)),0) -> 0 | C106: =IFERROR(INDEX(Stock!$A$3:$T$92,MATCH('Crawley Overview'!$A106,Stock!$A$3:$A$92,0),MATCH('Crawley Overview'!C$65,Stock!$A$3:$T$3,0)),0) -> 0 | D106: =C106-B106 -> 0 | F106: =IFERROR(INDEX(Stock!$A$3:$T$92,MATCH('Crawley Overview'!$A106,Stock!$A$3:$A$92,0),MATCH('Crawley Overview'!F$65,Stock!$A$3:$T$3,0)),0) | G106: =IFERROR(INDEX(Stock!$A$3:$T$92,MATCH('Crawley Overview'!$A106,Stock!$A$3:$A$92,0),MATCH('Crawley Overview'!G$65,Stock!$A$3:$T$3,0)),0)
A107: Mare hides | B107: =IFERROR(INDEX(Stock!$A$3:$T$92,MATCH('Crawley Overview'!$A107,Stock!$A$3:$A$92,0),MATCH('Crawley Overview'!B$65,Stock!$A$3:$T$3,0)),0) -> 0 | C107: =IFERROR(INDEX(Stock!$A$3:$T$92,MATCH('Crawley Overview'!$A107,Stock!$A$3:$A$92,0),MATCH('Crawley Overview'!C$65,Stock!$A$3:$T$3,0)),0) -> 0 | D107: =C107-B107 -> 0 | F107: =IFERROR(INDEX(Stock!$A$3:$T$92,MATCH('Crawley Overview'!$A107,Stock!$A$3:$A$92,0),MATCH('Crawley Overview'!F$65,Stock!$A$3:$T$3,0)),0) -> 0.045833333 | G107: =IFERROR(INDEX(Stock!$A$3:$T$92,MATCH('Crawley Overview'!$A107,Stock!$A$3:$A$92,0),MATCH('Crawley Overview'!G$65,Stock!$A$3:$T$3,0)),0) -> 0.045833333
A108: Steer hides | B108: =IFERROR(INDEX(Stock!$A$3:$T$92,MATCH('Crawley Overview'!$A108,Stock!$A$3:$A$92,0),MATCH('Crawley Overview'!B$65,Stock!$A$3:$T$3,0)),0) -> 0 | C108: =IFERROR(INDEX(Stock!$A$3:$T$92,MATCH('Crawley Overview'!$A108,Stock!$A$3:$A$92,0),MATCH('Crawley Overview'!C$65,Stock!$A$3:$T$3,0)),0) -> 0 | D108: =C108-B108 -> 0 | F108: =IFERROR(INDEX(Stock!$A$3:$T$92,MATCH('Crawley Overview'!$A108,Stock!$A$3:$A$92,0),MATCH('Crawley Overview'!F$65,Stock!$A$3:$T$3,0)),0) -> 0.05 | G108: =IFERROR(INDEX(Stock!$A$3:$T$92,MATCH('Crawley Overview'!$A108,Stock!$A$3:$A$92,0),MATCH('Crawley Overview'!G$65,Stock!$A$3:$T$3,0)),0) -> 0.05
A109: Yearling Calf hides | B109: =IFERROR(INDEX(Stock!$A$3:$T$92,MATCH('Crawley Overview'!$A109,Stock!$A$3:$A$92,0),MATCH('Crawley Overview'!B$65,Stock!$A$3:$T$3,0)),0) -> 0 | C109: =IFERROR(INDEX(Stock!$A$3:$T$92,MATCH('Crawley Overview'!$A109,Stock!$A$3:$A$92,0),MATCH('Crawley Overview'!C$65,Stock!$A$3:$T$3,0)),0) -> 0 | D109: =C109-B109 -> 0 | F109: =IFERROR(INDEX(Stock!$A$3:$T$92,MATCH('Crawley Overview'!$A109,Stock!$A$3:$A$92,0),MATCH('Crawley Overview'!F$65,Stock!$A$3:$T$3,0)),0) -> 0.00625 | G109: =IFERROR(INDEX(Stock!$A$3:$T$92,MATCH('Crawley Overview'!$A109,Stock!$A$3:$A$92,0),MATCH('Crawley Overview'!G$65,Stock!$A$3:$T$3,0)),0) -> 0.00625
A110: Calf hides | B110: =IFERROR(INDEX(Stock!$A$3:$T$92,MATCH('Crawley Overview'!$A110,Stock!$A$3:$A$92,0),MATCH('Crawley Overview'!B$65,Stock!$A$3:$T$3,0)),0) -> 0 | C110: =IFERROR(INDEX(Stock!$A$3:$T$92,MATCH('Crawley Overview'!$A110,Stock!$A$3:$A$92,0),MATCH('Crawley Overview'!C$65,Stock!$A$3:$T$3,0)),0) -> 0 | D110: =C110-B110 -> 0 | F110: =IFERROR(INDEX(Stock!$A$3:$T$92,MATCH('Crawley Overview'!$A110,Stock!$A$3:$A$92,0),MATCH('Crawley Overview'!F$65,Stock!$A$3:$T$3,0)),0) -> 0.0041666667 | G110: =IFERROR(INDEX(Stock!$A$3:$T$92,MATCH('Crawley Overview'!$A110,Stock!$A$3:$A$92,0),MATCH('Crawley Overview'!G$65,Stock!$A$3:$T$3,0)),0) -> 0.0041666667
A111: Pig hides | B111: =IFERROR(INDEX(Stock!$A$3:$T$92,MATCH('Crawley Overview'!$A111,Stock!$A$3:$A$92,0),MATCH('Crawley Overview'!B$65,Stock!$A$3:$T$3,0)),0) -> 0 | C111: =IFERROR(INDEX(Stock!$A$3:$T$92,MATCH('Crawley Overview'!$A111,Stock!$A$3:$A$92,0),MATCH('Crawley Overview'!C$65,Stock!$A$3:$T$3,0)),0) -> 0 | D111: =C111-B111 -> 0 | F111: =IFERROR(INDEX(Stock!$A$3:$T$92,MATCH('Crawley Overview'!$A111,Stock!$A$3:$A$92,0),MATCH('Crawley Overview'!F$65,Stock!$A$3:$T$3,0)),0) | G111: =IFERROR(INDEX(Stock!$A$3:$T$92,MATCH('Crawley Overview'!$A111,Stock!$A$3:$A$92,0),MATCH('Crawley Overview'!G$65,Stock!$A$3:$T$3,0)),0)
A112: Weather woolskins | B112: =IFERROR(INDEX(Stock!$A$3:$T$92,MATCH('Crawley Overview'!$A112,Stock!$A$3:$A$92,0),MATCH('Crawley Overview'!B$65,Stock!$A$3:$T$3,0)),0) -> 0 | C112: =IFERROR(INDEX(Stock!$A$3:$T$92,MATCH('Crawley Overview'!$A112,Stock!$A$3:$A$92,0),MATCH('Crawley Overview'!C$65,Stock!$A$3:$T$3,0)),0) -> 0 | D112: =C112-B112 -> 0 | F112: =IFERROR(INDEX(Stock!$A$3:$T$92,MATCH('Crawley Overview'!$A112,Stock!$A$3:$A$92,0),MATCH('Crawley Overview'!F$65,Stock!$A$3:$T$3,0)),0) | G112: =IFERROR(INDEX(Stock!$A$3:$T$92,MATCH('Crawley Overview'!$A112,Stock!$A$3:$A$92,0),MATCH('Crawley Overview'!G$65,Stock!$A$3:$T$3,0)),0)
A113: Ram woolskins | B113: =IFERROR(INDEX(Stock!$A$3:$T$92,MATCH('Crawley Overview'!$A113,Stock!$A$3:$A$92,0),MATCH('Crawley Overview'!B$65,Stock!$A$3:$T$3,0)),0) -> 0 | C113: =IFERROR(INDEX(Stock!$A$3:$T$92,MATCH('Crawley Overview'!$A113,Stock!$A$3:$A$92,0),MATCH('Crawley Overview'!C$65,Stock!$A$3:$T$3,0)),0) -> 0 | D113: =C113-B113 -> 0 | F113: =IFERROR(INDEX(Stock!$A$3:$T$92,MATCH('Crawley Overview'!$A113,Stock!$A$3:$A$92,0),MATCH('Crawley Overview'!F$65,Stock!$A$3:$T$3,0)),0) | G113: =IFERROR(INDEX(Stock!$A$3:$T$92,MATCH('Crawley Overview'!$A113,Stock!$A$3:$A$92,0),MATCH('Crawley Overview'!G$65,Stock!$A$3:$T$3,0)),0)
A114: Ewe woolskins | B114: =IFERROR(INDEX(Stock!$A$3:$T$92,MATCH('Crawley Overview'!$A114,Stock!$A$3:$A$92,0),MATCH('Crawley Overview'!B$65,Stock!$A$3:$T$3,0)),0) -> 0 | C114: =IFERROR(INDEX(Stock!$A$3:$T$92,MATCH('Crawley Overview'!$A114,Stock!$A$3:$A$92,0),MATCH('Crawley Overview'!C$65,Stock!$A$3:$T$3,0)),0) -> 0 | D114: =C114-B114 -> 0 | F114: =IFERROR(INDEX(Stock!$A$3:$T$92,MATCH('Crawley Overview'!$A114,Stock!$A$3:$A$92,0),MATCH('Crawley Overview'!F$65,Stock!$A$3:$T$3,0)),0) | G114: =IFERROR(INDEX(Stock!$A$3:$T$92,MATCH('Crawley Overview'!$A114,Stock!$A$3:$A$92,0),MATCH('Crawley Overview'!G$65,Stock!$A$3:$T$3,0)),0)
A115: Hogg woolskins | B115: =IFERROR(INDEX(Stock!$A$3:$T$92,MATCH('Crawley Overview'!$A115,Stock!$A$3:$A$92,0),MATCH('Crawley Overview'!B$65,Stock!$A$3:$T$3,0)),0) -> 0 | C115: =IFERROR(INDEX(Stock!$A$3:$T$92,MATCH('Crawley Overview'!$A115,Stock!$A$3:$A$92,0),MATCH('Crawley Overview'!C$65,Stock!$A$3:$T$3,0)),0) -> 0 | D115: =C115-B115 -> 0 | F115: =IFERROR(INDEX(Stock!$A$3:$T$92,MATCH('Crawley Overview'!$A115,Stock!$A$3:$A$92,0),MATCH('Crawley Overview'!F$65,Stock!$A$3:$T$3,0)),0) | G115: =IFERROR(INDEX(Stock!$A$3:$T$92,MATCH('Crawley Overview'!$A115,Stock!$A$3:$A$92,0),MATCH('Crawley Overview'!G$65,Stock!$A$3:$T$3,0)),0)
A116: Woolskins (total) | B116: =IFERROR(INDEX(Stock!$A$3:$T$92,MATCH('Crawley Overview'!$A116,Stock!$A$3:$A$92,0),MATCH('Crawley Overview'!B$65,Stock!$A$3:$T$3,0)),0) -> 0 | C116: =IFERROR(INDEX(Stock!$A$3:$T$92,MATCH('Crawley Overview'!$A116,Stock!$A$3:$A$92,0),MATCH('Crawley Overview'!C$65,Stock!$A$3:$T$3,0)),0) -> 0 | D116: =C116-B116 -> 0 | F116: =IFERROR(INDEX(Stock!$A$3:$T$92,MATCH('Crawley Overview'!$A116,Stock!$A$3:$A$92,0),MATCH('Crawley Overview'!F$65,Stock!$A$3:$T$3,0)),0) -> 0.94166667 | G116: =IFERROR(INDEX(Stock!$A$3:$T$92,MATCH('Crawley Overview'!$A116,Stock!$A$3:$A$92,0),MATCH('Crawley Overview'!G$65,Stock!$A$3:$T$3,0)),0) -> 0.94166667
... A124: Shorn skins | B124: =IFERROR(INDEX(Stock!$A$3:$T$92,MATCH('Crawley Overview'!$A124,Stock!$A$3:$A$92,0),MATCH('Crawley Overview'!B$65,Stock!$A$3:$T$3,0)),0) -> 0 | C124: =IFERROR(INDEX(Stock!$A$3:$T$92,MATCH('Crawley Overview'!$A124,Stock!$A$3:$A$92,0),MATCH('Crawley Overview'!C$65,Stock!$A$3:$T$3,0)),0) -> 0 | D124: =C124-B124 -> 0 | F124: =IFERROR(INDEX(Stock!$A$3:$T$92,MATCH('Crawley Overview'!$A124,Stock!$A$3:$A$92,0),MATCH('Crawley Overview'!F$65,Stock!$A$3:$T$3,0)),0) | G124: =IFERROR(INDEX(Stock!$A$3:$T$92,MATCH('Crawley Overview'!$A124,Stock!$A$3:$A$92,0),MATCH('Crawley Overview'!G$65,Stock!$A$3:$T$3,0)),0)
A125: Total value of production (sum of the above) | G125: =SUM(G105:G124) -> 1.8219512
A126: Value of sales | G126: =SUM(F105:F124) -> 1.8
A128: Poultry stock | B128: Inherited stock | C128: End-period stock | D128: Stockbuilding | F128: Sales in (£) | G128: Value of production (£) at sales prices
A129: Hens | B129: =IFERROR(INDEX(Stock!$A$3:$T$92,MATCH('Crawley Overview'!$A129,Stock!$A$3:$A$92,0),MATCH('Crawley Overview'!B$65,Stock!$A$3:$T$3,0)),0) -> 0 | C129: =IFERROR(INDEX(Stock!$A$3:$T$92,MATCH('Crawley Overview'!$A129,Stock!$A$3:$A$92,0),MATCH('Crawley Overview'!C$65,Stock!$A$3:$T$3,0)),0) -> 0 | D129: =C129-B129 -> 0 | F129: =IFERROR(INDEX(Stock!$A$3:$T$92,MATCH('Crawley Overview'!$A129,Stock!$A$3:$A$92,0),MATCH('Crawley Overview'!F$65,Stock!$A$3:$T$3,0)),0) -> 0.39583333 | G129: =IFERROR(INDEX(Stock!$A$3:$T$92,MATCH('Crawley Overview'!$A129,Stock!$A$3:$A$92,0),MATCH('Crawley Overview'!G$65,Stock!$A$3:$T$3,0)),0) -> 0.52083333
A130: Geese | B130: =IFERROR(INDEX(Stock!$A$3:$T$92,MATCH('Crawley Overview'!$A130,Stock!$A$3:$A$92,0),MATCH('Crawley Overview'!B$65,Stock!$A$3:$T$3,0)),0) -> 0 | C130: =IFERROR(INDEX(Stock!$A$3:$T$92,MATCH('Crawley Overview'!$A130,Stock!$A$3:$A$92,0),MATCH('Crawley Overview'!C$65,Stock!$A$3:$T$3,0)),0) -> 0 | D130: =C130-B130 -> 0 | F130: =IFERROR(INDEX(Stock!$A$3:$T$92,MATCH('Crawley Overview'!$A130,Stock!$A$3:$A$92,0),MATCH('Crawley Overview'!F$65,Stock!$A$3:$T$3,0)),0) | G130: =IFERROR(INDEX(Stock!$A$3:$T$92,MATCH('Crawley Overview'!$A130,Stock!$A$3:$A$92,0),MATCH('Crawley Overview'!G$65,Stock!$A$3:$T$3,0)),0)
A131: Capons (from chickens) | B131: =IFERROR(INDEX(Stock!$A$3:$T$92,MATCH('Crawley Overview'!$A131,Stock!$A$3:$A$92,0),MATCH('Crawley Overview'!B$65,Stock!$A$3:$T$3,0)),0) -> 0 | C131: =IFERROR(INDEX(Stock!$A$3:$T$92,MATCH('Crawley Overview'!$A131,Stock!$A$3:$A$92,0),MATCH('Crawley Overview'!C$65,Stock!$A$3:$T$3,0)),0) -> 0 | D131: =C131-B131 -> 0 | F131: =IFERROR(INDEX(Stock!$A$3:$T$92,MATCH('Crawley Overview'!$A131,Stock!$A$3:$A$92,0),MATCH('Crawley Overview'!F$65,Stock!$A$3:$T$3,0)),0) | G131: =IFERROR(INDEX(Stock!$A$3:$T$92,MATCH('Crawley Overview'!$A131,Stock!$A$3:$A$92,0),MATCH('Crawley Overview'!G$65,Stock!$A$3:$T$3,0)),0)
A132: Cocks & hens | B132: =IFERROR(INDEX(Stock!$A$3:$T$92,MATCH('Crawley Overview'!$A132,Stock!$A$3:$A$92,0),MATCH('Crawley Overview'!B$65,Stock!$A$3:$T$3,0)),0) -> 0 | C132: =IFERROR(INDEX(Stock!$A$3:$T$92,MATCH('Crawley Overview'!$A132,Stock!$A$3:$A$92,0),MATCH('Crawley Overview'!C$65,Stock!$A$3:$T$3,0)),0) -> 0 | D132: =C132-B132 -> 0 | F132: =IFERROR(INDEX(Stock!$A$3:$T$92,MATCH('Crawley Overview'!$A132,Stock!$A$3:$A$92,0),MATCH('Crawley Overview'!F$65,Stock!$A$3:$T$3,0)),0) | G132: =IFERROR(INDEX(Stock!$A$3:$T$92,MATCH('Crawley Overview'!$A132,Stock!$A$3:$A$92,0),MATCH('Crawley Overview'!G$65,Stock!$A$3:$T$3,0)),0)
...

Sheet Crawley Receipts
A1: CRAWLEY RECEIPTS
B2: £ | C2: s | D2: d | F2: Total in £ | G2: Error | H2: Notes
A4: Arrears
A5: Arrears total | B5: 7 | C5: 8 | D5: 8 | F5: =B5+C5/20+D5/240 -> 7.4333333
A6: of which delivered to treasurer of Wolvesey | B6: 7 | C6: 8 | D6: 8 | F6: =B6+C6/20+D6/240 -> 7.4333333
A8: Rents of assize
A9: Christmas | B9: 3 | C9: 1 | D9: 4 | F9: =B9+C9/20+D9/240 -> 3.0666667
A10: Easter | B10: 3 | C10: 1 | D10: 4 | F10: =B10+C10/20+D10/240 -> 3.0666667
A11: John the Baptist | B11: 3 | C11: 1 | D11: 4 | F11: =B11+C11/20+D11/240 -> 3.0666667
A12: Michaelmas | B12: 4 | C12: 17 | D12: 7 | F12: =B12+C12/20+D12/240 -> 4.8791667
A13: Total recorded in accounts | B13: 14 | C13: 1 | D13: 7 | F13: =B13+C13/20+D13/240 -> 14.079167
A14: Rents of assize total | B14: =SUM(B9:B12) -> 13 | C14: =SUM(C9:C12) -> 20 | D14: =SUM(D9:D12) -> 19 | F14: =B14+C14/20+D14/240 -> 14.079167 | G14: =F14-F13 -> 0
A16: Quittances
A17: 1 reeve for the year | C17: 5 | F17: =B17+C17/20+D17/240 -> 0.25
A18: 6 ploughmen 1 smith for the year | C18: 18 | D18: 8 | F18: =B18+C18/20+D18/240 -> 0.93333333
A19: 2 shepherds for the year | C19: 5 | D19: 4 | F19: =B19+C19/20+D19/240 -> 0.26666667
A20: 8 workers | B20: 1 | C20: 1 | D20: 4 | F20: =B20+C20/20+D20/240 -> 1.0666667
A21: 1 swineherd and 1 cowherd | C21: 5 | D21: 4 | F21: =B21+C21/20+D21/240 -> 0.26666667
A22: Total recorded in accounts | B22: 2 | C22: 15 | D22: 8 | F22: =B22+C22/20+D22/240 -> 2.7833333
A23: Quittances total | B23: =SUM(B17:B21) -> 1 | C23: =SUM(C17:C21) -> 34 | D23: =SUM(D17:D21) -> 20 | F23: =B23+C23/20+D23/240 -> 2.7833333 | G23: =F23-F22 -> 0
A25: Defaults of rent
A26: in default of le stronge into demesne | C26: 2 | F26: =B26+C26/20+D26/240 -> 0.1
A27: land of william | C27: 2 | D27: 8 | F27: =B27+C27/20+D27/240 -> 0.13333333
A28: land of Alebrok | C28: 5 | F28: =B28+C28/20+D28/240 -> 0.25
A29: land of Robert | C29: 2 | D29: 8 | F29: =B29+C29/20+D29/240 -> 0.13333333
A30: land of Robert Coye | C30: 2 | D30: 8 | F30: =B30+C30/20+D30/240 -> 0.13333333
A31: land of Roger le Pokyr | C31: 2 | D31: 8 | F31: =B31+C31/20+D31/240 -> 0.13333333
A32: land of Richard Vaccar | C32: 2 | D32: 8 | F32: =B32+C32/20+D32/240 -> 0.13333333
A33: Total recorded in accounts | B33: 1 | D33: 4 | F33: =B33+C33/20+D33/240 -> 1.0166667
A34: Defaults of rent total | B34: =SUM(B26:B32) -> 0 | C34: =SUM(C26:C32) -> 17 | D34: =SUM(D26:D32) -> 40 | F34: =B34+C34/20+D34/240 -> 1.0166667 | G34: =F34-F33 -> 0
A36: Total of rents remaining | B36: 10 | C36: 5 | D36: 7 | F36: =B36+C36/20+D36/240 -> 10.279167 | H36: not included in receipts
A38: Annual recognizances
A39: from Walter | D39: 6 | F39: =B39+C39/20+D39/240 -> 0.025
A40: from Robert | D40: 6 | F40: =B40+C40/20+D40/240 -> 0.025
A41: from Robert le Pottere | D41: 6 | F41: =B41+C41/20+D41/240 -> 0.025
A42: from John | D42: 3 | F42: =B42+C42/20+D42/240 -> 0.0125
A43: Total recorded in accounts | C43: 1 | D43: 9 | F43: =B43+C43/20+D43/240 -> 0.0875
A44: Annual recognizances total | B44: =SUM(B39:B42) -> 0 | C44: =SUM(C39:C42) -> 0 | D44: =SUM(D39:D42) -> 21 | F44: =B44+C44/20+D44/240 -> 0.0875 | G44: =F44-F43 -> 0
A46: Issues of the manor
A47: panage of pigs | C47: 6 | D47: 2.5 | F47: =B47+C47/20+D47/240 -> 0.31041667
A48: panage of 77 cows, 8 steers, 21 bullocks and 16 calves | B48: 2 | C48: 5 | D48: 4 | F48: =B48+C48/20+D48/240 -> 2.2666667
A49: for 97 more of the mens sheep than the 25 maintained at the fold | C49: 2 | D49: 8 | F49: =B49+C49/20+D49/240 -> 0.13333333
A50: from pasturage of 44 lambs sold | D50: 11 | F50: =B50+C50/20+D50/240 -> 0.045833333
A51: from the pasturage of Trendly sold | C51: 8 | F51: =B51+C51/20+D51/240 -> 0.4
A52: from pasturage of Lokfurlang sold | C52: 1 | D52: 6 | F52: =B52+C52/20+D52/240 -> 0.075
A53: from the pasturage of Shret sold | C53: 1 | D53: 4 | F53: =B53+C53/20+D53/240 -> 0.066666667
A54: from 5 feeble late born calves | C54: 5 | F54: =B54+C54/20+D54/240 -> 0.25
A55: from 47 wethers | B55: 2 | C55: 14 | D55: 10 | F55: =B55+C55/20+D55/240 -> 2.7416667
A56: from 55 ewes sold | B56: 2 | C56: 5 | D56: 10 | F56: =B56+C56/20+D56/240 -> 2.2916667
A57: from 26 pigs sold | B57: 3 | C57: 7 | D57: 4 | F57: =B57+C57/20+D57/240 -> 3.3666667
A58: from the hide sold of 1 plough-horse in murrain | D58: 11 | F58: =B58+C58/20+D58/240 -> 0.045833333
A59: from the hides sold of 2 oxen dead from murrain | C59: 4 | D59: 6.5 | F59: =B59+C59/20+D59/240 -> 0.22708333
A60: from the hide and flesh sold of 1 steer in murrain | C60: 2 | D60: 8 | F60: =B60+C60/20+D60/240 -> 0.13333333
A61: from the hide sold of 1 bullock in murrain | D61: 6 | F61: =B61+C61/20+D61/240 -> 0.025
A62: fro the hide sold of 1 yearling in murrain | D62: 1.5 | F62: =B62+C62/20+D62/240 -> 0.00625
A63: from the hide sold of 1 calf in murrain | D63: 1 | F63: =B63+C63/20+D63/240 -> 0.0041666667
A64: from the skins sold of 21 wethers, 24 ewes, and 23 hoggs in murrain before shearing | C64: 18 | D64: 10 | F64: =B64+C64/20+D64/240 -> 0.94166667
A65: from the skins sold of 14 wethers and 13 ewes in murrain after shearing | C65: 4 | D65: 6 | F65: =B65+C65/20+D65/240 -> 0.225
A66: from skins sold of 62 lambs in murrain before weaning | C66: 5 | D66: 2 | F66: =B66+C66/20+D66/240 -> 0.25833333
A67: from the skins sold of 20 rotted sheep in murrain | D67: 10 | F67: =B67+C67/20+D67/240 -> 0.041666667
A68: from 5 cloves 1 lb of winter cheese sold | C68: 1 | D68: 6 | F68: =B68+C68/20+D68/240 -> 0.075
A69: from 7.5 weys 12 cloves of summer cheese sold | B69: 3 | C69: 6 | D69: 1 | F69: =B69+C69/20+D69/240 -> 3.3041667
A70: from 15 cloves 5 lb of butter sold | C70: 4 | D70: 8 | F70: =B70+C70/20+D70/240 -> 0.23333333
A71: from 95 hens at churchscot sold | C71: 7 | D71: 11 | F71: =B71+C71/20+D71/240 -> 0.39583333
A72: from richard for release from the labour service | C72: 2 | F72: =B72+C72/20+D72/240 -> 0.1
A73: from a curtilage which was hired to roger | C73: 1 | F73: =B73+C73/20+D73/240 -> 0.05
A74: from 23 acres of the lords land hired now accounted for in defaults of rent above | C74: 12 | F74: =B74+C74/20+D74/240 -> 0.6 | H74: Accounted for in defaults of rent already?
A75: from curtilage which belongs to Robert Couch | C75: 2 | F75: =B75+C75/20+D75/240 -> 0.1
A76: from 5 cloves of wool locks sold | C76: 4 | D76: 4.5 | F76: =B76+C76/20+D76/240 -> 0.21875
A77: from dairy produce sold at the audit | B77: 1 | D77: 3 | F77: =B77+C77/20+D77/240 -> 1.0125
A78: Total recorded in accounts | B78: 19 | C78: 19 | F78: =B78+C78/20+D78/240 -> 19.95
A79: Issues of the manor total | B79: =SUM(B47:B77) -> 13 | C79: =SUM(C47:C77) -> 126 | D79: =SUM(D47:D77) -> 155 | F79: =B79+C79/20+D79/240 -> 19.945833 | G79: =F79-F78 -> -0.0041666667
A81: Sale of corn
A82: from 40 qrs of wheat sold | B82: 11 | C82: 18 | D82: 2 | F82: =B82+C82/20+D82/240 -> 11.908333
A83: from 12 wrs 0.5 bus of curall sold | B83: 2 | C83: 5 | D83: 6.5 | F83: =B83+C83/20+D83/240 -> 2.2770833
A84: from 21 qrs 6 bus of barley sold | B84: 4 | C84: 7 | D84: 11 | F84: =B84+C84/20+D84/240 -> 4.3958333
A85: from 43 qrs of oats sold | B85: 4 | C85: 7 | D85: 8 | F85: =B85+C85/20+D85/240 -> 4.3833333
A86: from 3 qrs 1 bus of peas sold | C86: 9 | D86: 4.5 | F86: =B86+C86/20+D86/240 -> 0.46875
A87: from 4.5 qrs of vetches sold | C87: 9 | F87: =B87+C87/20+D87/240 -> 0.45
A88: from 4 bus of barley sold at the audit | C88: 2 | F88: =B88+C88/20+D88/240 -> 0.1
A89: Total recorded in accounts | B89: 23 | C89: 19 | D89: 8 | F89: =B89+C89/20+D89/240 -> 23.983333
A90: Sale of corn total | B90: =SUM(B82:B88) -> 21 | C90: =SUM(C82:C88) -> 57 | D90: =SUM(D82:D88) -> 32 | F90: =B90+C90/20+D90/240 -> 23.983333 | G90: =F90-F89 -> 0
A92: Entry and marriage fines
A93: from tithing of tithingpenny at martinmas | C93: 6 | D93: 8 | F93: =B93+C93/20+D93/240 -> 0.33333333
A94: from the same at hockday | C94: 6 | D94: 8 | F94: =B94+C94/20+D94/240 -> 0.33333333
A95: from Matilda for marrying her daughter outside | C95: 2 | F95: =B95+C95/20+D95/240 -> 0.1
A96: from Stephen for marrying his daughter outside | C96: 2 | F96: =B96+C96/20+D96/240 -> 0.1
A97: Total recorded in accounts | C97: 17 | D97: 4 | F97: =B97+C97/20+D97/240 -> 0.86666667
A98: Entry and marriage fines total | B98: =SUM(B93:B96) -> 0 | C98: =SUM(C93:C96) -> 16 | D98: =SUM(D93:D96) -> 16 | F98: =B98+C98/20+D98/240 -> 0.86666667 | G98: =F98-F97 -> 0
A100: Pleas and perquisites
A101: from tithing of Crawley for concealment | C101: 2 | F101: =B101+C101/20+D101/240 -> 0.1
A102: from the tithing of Crawley for not producing in court | C102: 2 | F102: =B102+C102/20+D102/240 -> 0.1
A103: from various transgressions of various men in various courts | C103: 15 | D103: 11 | F103: =B103+C103/20+D103/240 -> 0.79583333
A104: Total recorded in accounts | C104: 19 | D104: 11 | F104: =B104+C104/20+D104/240 -> 0.99583333
A105: Pleas & perquisites total | B105: =SUM(B101:B103) -> 0 | C105: =SUM(C101:C103) -> 19 | D105: =SUM(D101:D103) -> 11 | F105: =B105+C105/20+D105/240 -> 0.99583333
A107: Total of all receipts (sum of above excl. arrears) | B107: =SUM(B105,B98,B90,B79,B44,B34,B23,B14) -> 48 | C107: =SUM(C105,C98,C90,C79,C44,C34,C23,C14) -> 289 | D107: =SUM(D105,D98,D90,D79,D44,D34,D23,D14) -> 314 | F107: =B107+C107/20+D107/240 -> 63.758333
A108: Total of all receipts (sum of above incl. arrears) | B108: =SUM(B105,B98,B90,B79,B44,B34,B23,B14,B5) -> 55 | C108: =SUM(C105,C98,C90,C79,C44,C34,C23,C14,C5) -> 297 | D108: =SUM(D105,D98,D90,D79,D44,D34,D23,D14,D5) -> 322 | F108: =B108+C108/20+D108/240 -> 71.191667
A109: Total of all receipts in account excl. arrears | F109: =B109+C109/20+D109/240 -> 0 | G109: =F109-F107 -> -63.758333
A110: Total of all receipts in account incl. arrears | B110: 56 | C110: 3 | D110: 3 | F110: =B110+C110/20+D110/240 -> 56.1625 | G110: =F110-F108 -> -15.029167

Sheet Crawley Expenses
A1: CRAWLEY EXPENSES
B2: £ | C2: s | D2: d | F2: Total in £ | G2: Error | H2: Notes
A3: Cost of Ploughs
A4: in iron and steel bought for 4 ploughs | C4: 9 | F4: =B4+C4/20+D4/240 -> 0.45
A5: in 2 ploughshares bought | C5: 1 | D5: 8 | F5: =B5+C5/20+D5/240 -> 0.083333333
A6: in 1 coulter mended | D6: 2 | F6: =B6+C6/20+D6/240 -> 0.0083333333
A7: in 2 plough feet bought | D7: 7.5 | F7: =B7+C7/20+D7/240 -> 0.03125
A8: in 4 pairs of wheels bought | C8: 1 | D8: 4 | F8: =B8+C8/20+D8/240 -> 0.066666667
A9: in 2 ploughs made anew and other mending | C9: 1 | D9: 3 | F9: =B9+C9/20+D9/240 -> 0.0625
A10: in fitting ploughs with iron tyres | D10: 2.5 | F10: =B10+C10/20+D10/240 -> 0.010416667
A11: in shoeing 6 plough-horses | C11: 3 | D11: 11 | F11: =B11+C11/20+D11/240 -> 0.19583333
A12: in boon-works of 9 ploughmen | D12: 9 | F12: =B12+C12/20+D12/240 -> 0.0375
A13: in 5 halters made from the horeses own hair | D13: 1.75 | F13: =B13+C13/20+D13/240 -> 0.0072916667
A14: in stipend of 2 ploughmen for the year | C14: 6 | F14: =B14+C14/20+D14/240 -> 0.3
A15: in 5 oxen bought | B15: 2 | C15: 6 | F15: =B15+C15/20+D15/240 -> 2.3
A16: Total recorded in accounts | B16: 3 | C16: 11 | D16: 0.25 | F16: =B16+C16/20+D16/240 -> 3.5510417
A17: Cost of ploughs total | B17: =SUM(B4:B15) -> 2 | C17: =SUM(C4:C15) -> 27 | D17: =SUM(D4:D15) -> 48.75 | F17: =B17+C17/20+D17/240 -> 3.553125 | G17: =F17-F16 -> 0.0020833333
A18: Total capital expenses | B18: =SUM(B15,B13,B4:B11) -> 2 | C18: =SUM(C15,C13,C4:C11) -> 21 | D18: =SUM(D15,D13,D4:D11) -> 39.75 | F18: =B18+C18/20+D18/240 -> 3.215625
A20: Purchase of Corn
A21: in 6 bus of wheat bought for sowing | C21: 4 | D21: 6 | F21: =B21+C21/20+D21/240 -> 0.225
A22: in 3 qrs 6 bus of barley bought | C22: 12 | D22: 4 | F22: =B22+C22/20+D22/240 -> 0.61666667
A23: Total recorded in accounts | C23: 16 | D23: 10 | F23: =B23+C23/20+D23/240 -> 0.84166667
A24: Purchase of corn total | B24: =SUM(B21:B22) -> 0 | C24: =SUM(C21:C22) -> 16 | D24: =SUM(D21:D22) -> 10 | F24: =B24+C24/20+D24/240 -> 0.84166667 | G24: =F24-F23 -> 0
A26: Cost of Carts and Wagons
A27: in 1 pair of wheels bought | C27: 3 | D27: 4 | F27: =B27+C27/20+D27/240 -> 0.16666667
A28: in 1 old binding renewed and fitted | C28: 3 | F28: =B28+C28/20+D28/240 -> 0.15
A29: in fitting the cart with axles | D29: 8 | F29: =B29+C29/20+D29/240 -> 0.033333333
A30: in clouts nails and grease bought for the same | C30: 1 | F30: =B30+C30/20+D30/240 -> 0.05
A31: in 1 pair of traces bought | D31: 5.5 | F31: =B31+C31/20+D31/240 -> 0.022916667
A32: in 1 rope bought | D32: 2 | F32: =B32+C32/20+D32/240 -> 0.0083333333
A33: in shoeing 2 cart horses | C33: 2 | D33: 6 | F33: =B33+C33/20+D33/240 -> 0.125
A34: in white leather bought | D34: 4 | F34: =B34+C34/20+D34/240 -> 0.016666667
A35: in mending old harnesses | D35: 2 | F35: =B35+C35/20+D35/240 -> 0.0083333333
A36: in 1 collar bought | D36: 7 | F36: =B36+C36/20+D36/240 -> 0.029166667
A37: in stipend of 1 carter | C37: 3 | F37: =B37+C37/20+D37/240 -> 0.15
A38: in mending the cart at various times | D38: 2 | F38: =B38+C38/20+D38/240 -> 0.0083333333
A39: in 1 new cart-body bought | C39: 1 | F39: =B39+C39/20+D39/240 -> 0.05
A40: Total recorded in accounts | C40: 16 | D40: 4.5 | F40: =B40+C40/20+D40/240 -> 0.81875
A41: Cost of carts and wagons total | B41: =SUM(B27:B39) -> 0 | C41: =SUM(C27:C39) -> 13 | D41: =SUM(D27:D39) -> 40.5 | F41: =B41+C41/20+D41/240 -> 0.81875 | G41: =F41-F40 -> 0
A42: Total capital expenses | B42: =SUM(B38:B39,B27:B36) -> 0 | C42: =SUM(C38:C39,C27:C36) -> 10 | D42: =SUM(D38:D39,D27:D36) -> 40.5 | F42: =B42+C42/20+D42/240 -> 0.66875
A44: Cost of Dairy
A45: in woollen and linen cloth bought | D45: 6 | F45: =B45+C45/20+D45/240 -> 0.025
A46: in 6 bus of salt bought | C46: 1 | D46: 11 | F46: =B46+C46/20+D46/240 -> 0.095833333
A47: in a press bought | D47: 4.5 | F47: =B47+C47/20+D47/240 -> 0.01875
A48: in earthenware pots and pans bought | D48: 2.5 | F48: =B48+C48/20+D48/240 -> 0.010416667
A49: in mending the utensils of the dairy | D49: 1.5 | F49: =B49+C49/20+D49/240 -> 0.00625
A50: in 1 mould bought | D50: 7.5 | F50: =B50+C50/20+D50/240 -> 0.03125
A51: in 20 ells of canvas bought for packing wool | C51: 5 | D51: 2 | F51: =B51+C51/20+D51/240 -> 0.25833333
A52: in making the said sacks | D52: 4 | F52: =B52+C52/20+D52/240 -> 0.016666667
A53: in packing the said wool | D53: 8 | F53: =B53+C53/20+D53/240 -> 0.033333333
A54: in grease bought for greasing sheep | B54: 2 | D54: 9 | F54: =B54+C54/20+D54/240 -> 2.0375
A55: in re-roofing the ewe house | C55: 2 | D55: 6 | F55: =B55+C55/20+D55/240 -> 0.125
A56: in collecting stubble for the same | C56: 1 | D56: 0.5 | F56: =B56+C56/20+D56/240 -> 0.052083333
A57: in 40 hurdles bought for the fold | C57: 5 | F57: =B57+C57/20+D57/240 -> 0.25
A58: in hay bought for the sheep in lent | C58: 17 | D58: 11 | F58: =B58+C58/20+D58/240 -> 0.89583333
A59: in stipend of 1 dairymaid for the year | C59: 2 | F59: =B59+C59/20+D59/240 -> 0.1
A60: in 1 tub bought for the dairy | D60: 4 | F60: =B60+C60/20+D60/240 -> 0.016666667
A61: Total recorded in accounts | B61: 3 | C61: 19 | D61: 5.5 | F61: =B61+C61/20+D61/240 -> 3.9729167
A62: Cost of dairy total | B62: =SUM(B45:B60) -> 2 | C62: =SUM(C45:C60) -> 33 | D62: =SUM(D45:D60) -> 77.5 | F62: =B62+C62/20+D62/240 -> 3.9729167 | G62: =F62-F61 -> 0
A63: Total capital expenses | B63: =SUM(B60,B54:B58,B45:B52) -> 2 | C63: =SUM(C60,C54:C58,C45:C52) -> 31 | D63: =SUM(D60,D54:D58,D45:D52) -> 69.5 | F63: =B63+C63/20+D63/240 -> 3.8395833
A65: Cost of Buildings
A66: in wattling and reroofing the old barn | C66: 2 | D66: 9 | F66: =B66+C66/20+D66/240 -> 0.1375
A67: in plastering and mending the walls | D67: 10 | F67: =B67+C67/20+D67/240 -> 0.041666667
A68: in recovering the stack of vetches | C68: 1 | D68: 3 | F68: =B68+C68/20+D68/240 -> 0.0625
A69: in mending 1 cooking pot and 1 pan | D69: 1.25 | F69: =B69+C69/20+D69/240 -> 0.0052083333
A70: in wattling and re-roofing the wheat barn | D70: 9 | F70: =B70+C70/20+D70/240 -> 0.0375
A71: in 1 bushel measure bought | D71: 5 | F71: =B71+C71/20+D71/240 -> 0.020833333
A72: in castrating piglets | D72: 4 | F72: =B72+C72/20+D72/240 -> 0.016666667
A73: Total recorded in accounts | C73: 6 | D73: 5.25 | F73: =B73+C73/20+D73/240 -> 0.321875
A74: Cost of buildings total | B74: =SUM(B66:B72) -> 0 | C74: =SUM(C66:C72) -> 3 | D74: =SUM(D66:D72) -> 41.25 | F74: =B74+C74/20+D74/240 -> 0.321875 | G74: =F74-F73 -> 0
A75: Total capital expenses | B75: =SUM(B66:B71) -> 0 | C75: =SUM(C66:C71) -> 3 | D75: =SUM(D66:D71) -> 37.25 | F75: =B75+C75/20+D75/240 -> 0.30520833
A77: Threshing
A78: in threshing and winnowing 40 qrs of wheat | C78: 6 | D78: 8 | F78: =B78+C78/20+D78/240 -> 0.33333333
A79: in threshing and winnowing 45 qrs of barley | C79: 5 | D79: 7.5 | F79: =B79+C79/20+D79/240 -> 0.28125
A80: in threshing and winnowing 60 qrs of oats | C80: 4 | F80: =B80+C80/20+D80/240 -> 0.2
A81: in wages of William Kryre for carrying out issue of the grange | C81: 3 | D81: 1.5 | F81: =B81+C81/20+D81/240 -> 0.15625
A82: in stipend of the same | C82: 1 | F82: =B82+C82/20+D82/240 -> 0.05
A83: Total recorded in accounts | B83: 1 | D83: 5 | F83: =B83+C83/20+D83/240 -> 1.0208333
A84: Threshing total | B84: =SUM(B78:B82) -> 0 | C84: =SUM(C78:C82) -> 19 | D84: =SUM(D78:D82) -> 17 | F84: =B84+C84/20+D84/240 -> 1.0208333 | G84: =F84-F83 -> 0
A86: Expenses of the Harvest | H86: Have included provision of household servants at harvest time as expenses of harvest time although separate in accounts
A87: in weeding corn | C87: 4 | D87: 6 | F87: =B87+C87/20+D87/240 -> 0.225
A88: in 1000 herrings bought for 3 boonworks of 300 men | C88: 6 | D88: 4 | F88: =B88+C88/20+D88/240 -> 0.31666667
A89: in provisioning group that helped with harvest | B89: 1 | F89: =B89+C89/20+D89/240 -> 1
A90: in stipend of 1 man keeping the corn in the fields | C90: 3 | F90: =B90+C90/20+D90/240 -> 0.15
A91: Total recorded in accounts | B91: 1 | C91: 13 | D91: 10 | F91: =B91+C91/20+D91/240 -> 1.6916667
A92: Expenses of the harvest total | B92: =SUM(B87:B90) -> 1 | C92: =SUM(C87:C90) -> 13 | D92: =SUM(D87:D90) -> 10 | F92: =B92+C92/20+D92/240 -> 1.6916667 | G92: =F92-F91 -> 0
A94: Steward's Expenses
A95: in expenses of simon clerk at martinmas | C95: 3 | D95: 3 | F95: =B95+C95/20+D95/240 -> 0.1625
A96: in expenses of simon at hockday | C96: 1 | D96: 6 | F96: =B96+C96/20+D96/240 -> 0.075
A97: in expenses of the same for 1 visit | D97: 9.25 | F97: =B97+C97/20+D97/240 -> 0.038541667
A98: in expenses of the bailiff for his visits | C98: 12 | D98: 2 | F98: =B98+C98/20+D98/240 -> 0.60833333
A99: given by order of the steward and treasurer for the lord's business in the hundred of buddlesgate | C99: 6 | D99: 8 | F99: =B99+C99/20+D99/240 -> 0.33333333
A100: Total recorded in accounts | B100: 1 | C100: 4 | D100: 4.25 | F100: =B100+C100/20+D100/240 -> 1.2177083
A101: Steward's expenses total | B101: =SUM(B95:B99) -> 0 | C101: =SUM(C95:C99) -> 22 | D101: =SUM(D95:D99) -> 28.25 | F101: =B101+C101/20+D101/240 -> 1.2177083 | G101: =F101-F100 -> 0
A103: Total of all Expenses | B103: 13 | C103: 8 | D103: 0.75 | F103: =B103+C103/20+D103/240 -> 13.403125
A104: Total of all Expenses (calculated) | B104: =SUM(B101,B92,B84,B74,,B62,B41,B24,B17) -> 5 | C104: =SUM(C101,C92,C84,C74,,C62,C41,C24,C17) -> 146 | D104: =SUM(D101,D92,D84,D74,,D62,D41,D24,D17) -> 273.25 | F104: =B104+C104/20+D104/240 -> 13.438542 | G104: =F104-F103 -> 0.035416667
A105: And thus he owes | B105: 42 | C105: 14 | D105: 6.25 | F105: =B105+C105/20+D105/240 -> 42.726042
A106: Delivered to Sir Geoffrey, treasurer of Wolvesey | B106: 27 | C106: 14 | D106: 4 | F106: =B106+C106/20+D106/240 -> 27.716667
A107: and thus he owes clear | B107: 15 | D107: 2.25 | F107: =B107+C107/20+D107/240 -> 15.009375
A108: Total capital expenses | B108: =SUM(B18,B42,B63,B75,B24) -> 4 | C108: =SUM(C18,C42,C63,C75,C24) -> 81 | D108: =SUM(D18,D42,D63,D75,D24) -> 197 | F108: =B108+C108/20+D108/240 -> 8.8708333

Sheet Issues of the Grange
B1: The issue of the grange account gives the total "yield" at the top of each heading in curly brackets, measurements used: fold, qrs, bus
B2: In "Issues of the grange" (p.xx) | G2: In "Sale of Corn" (p.x) | P2: Value of Total Production
A3: Gross output | B3: Quantity | D3: Additional bought-in | F3: Quantity | G3: Quantity noted as sold | J3: Difference Produced vs. Sold | K3: Price 1 | L3: Quantity 1 | M3: Price 2 | N3: Quantity 2 | O3: Unit price | P3: Value
B4: qrs | C4: bus | D4: qrs | E4: bus | F4: qrs | G4: qrs | H4: bus | I4: qrs | K4: £ | L4: qrs | M4: £ | N4: qrs | O4: £ per qr | P4: £
A5: Wheat | B5: 58 | C5: 6 | E5: 6 | F5: =B5+D5+C5/8+E5/8 -> 59.5 | G5: 40 | I5: =G5+H5/8 -> 40 | J5: =F5-I5 -> 19.5 | K5: ='Crawley Receipts'!F82 -> 11.908333 | L5: 40 | O5: =IFERROR((K5+M5)/(L5+N5),0) -> 0.29770833 | P5: =O5*F5 -> 17.713646
A6: Curall | B6: 12 | C6: 0.5 | F6: =B6+D6+C6/8+E6/8 -> 12.0625 | G6: 12 | H6: 0.5 | I6: =G6+H6/8 -> 12.0625 | J6: =F6-I6 -> 0 | K6: ='Crawley Receipts'!F83 -> 2.2770833 | L6: =I6 -> 12.0625 | O6: =IFERROR((K6+M6)/(L6+N6),0) -> 0.18877375 | P6: =O6*F6 -> 2.2770833
A7: Bere | B7: 4 | C7: 2 | F7: =B7+D7+C7/8+E7/8 -> 4.25 | I7: =G7+H7/8 -> 0 | J7: =F7-I7 -> 4.25 | O7: =IFERROR((K7+M7)/(L7+N7),0) -> 0 | P7: =O7*F7 -> 0
A8: Barley | B8: 91 | C8: 5 | D8: 3 | E8: 6 | F8: =B8+D8+C8/8+E8/8 -> 95.375 | G8: 21.5 | H8: 6 | I8: =G8+H8/8 -> 22.25 | J8: =F8-I8 -> 73.125 | K8: ='Crawley Receipts'!F84 -> 4.3958333 | L8: =21+6/8 -> 21.75 | M8: ='Crawley Receipts'!F88 -> 0.1 | N8: 0.5 | O8: =IFERROR((K8+M8)/(L8+N8),0) -> 0.20205993 | P8: =O8*F8 -> 19.271465
A9: Oats | B9: 170 | F9: =B9+D9+C9/8+E9/8 -> 170 | G9: 43 | I9: =G9+H9/8 -> 43 | J9: =F9-I9 -> 127 | K9: ='Crawley Receipts'!F85 -> 4.3833333 | L9: 43 | O9: =IFERROR((K9+M9)/(L9+N9),0) -> 0.10193798 | P9: =O9*F9 -> 17.329457
A10: Peas | B10: 6.5 | F10: =B10+D10+C10/8+E10/8 -> 6.5 | G10: 3 | H10: 1 | I10: =G10+H10/8 -> 3.125 | J10: =F10-I10 -> 3.375 | K10: ='Crawley Receipts'!F86 -> 0.46875 | L10: =I10 -> 3.125 | O10: =IFERROR((K10+M10)/(L10+N10),0) -> 0.15 | P10: =O10*F10 -> 0.975
A11: Vetches | B11: 7 | C11: 6 | F11: =B11+D11+C11/8+E11/8 -> 7.75 | G11: 4.5 | I11: =G11+H11/8 -> 4.5 | J11: =F11-I11 -> 3.25 | K11: ='Crawley Receipts'!F87 -> 0.45 | L11: 4.5 | O11: =IFERROR((K11+M11)/(L11+N11),0) -> 0.1 | P11: =O11*F11 -> 0.775
A13: Total Production | F13: =SUM(F5:F11) -> 355.4375 | P13: =SUM(P5:P11) -> 58.341652 | Q13: Production value is significantly more, as much less was sold than what was produced
A14: Sales of corn (as recorded in accounts) | F14: =SUM(I5:I11) -> 124.9375 | P14: =SUM(K5:K11,M5:M11) -> 23.983333
A17: Net output | B17: Gross output | C17: Seed | F17: tithe | G17: to manorial servants & livestock | J17: Output net of tithe & seed & liveries to manorial servants | K17: in stock from last year | L17: Price | M17: Value of net output | N17: Value of sales (in "Sale of Corn")
B18: qrs | C18: qrs | D18: bus | E18: qrs | F18: qrs | G18: qrs | H18: bus | I18: qrs | J18: qrs | K18: qrs | L18: £ per qr | M18: £ | N18: £
A19: Net wheat | B19: =F5 -> 59.5 | C19: 16 | D19: 5 | E19: =C19+D19/8 -> 16.625 | G19: 2 | H19: 7 | I19: =G19+H19/8 -> 2.875 | J19: =B19-(E19+F19+I19) -> 40 | L19: =O5 -> 0.29770833 | M19: =L19*J19 -> 11.908333 | N19: =O5*I5 -> 11.908333
A20: Net curall | B20: =F6 -> 12.0625 | E20: =C20+D20/8 -> 0 | I20: =G20+H20/8 -> 0 | J20: =B20-(E20+F20+I20) -> 12.0625 | L20: =O6 -> 0.18877375 | M20: =L20*J20 -> 2.2770833 | N20: =O6*I6 -> 2.2770833
A21: Net Bere | B21: =F7 -> 4.25 | E21: =C21+D21/8 -> 0 | G21: 4 | H21: 2 | I21: =G21+H21/8 -> 4.25 | J21: =B21-(E21+F21+I21) -> 0 | L21: =O7 -> 0 | M21: =L21*J21 -> 0 | N21: =O7*I7 -> 0
A22: Net barley | B22: =F8 -> 95.375 | C22: 43 | D22: 2 | E22: =C22+D22/8 -> 43.25 | G22: =19.5+0.5+2+3+2+0.5 -> 27.5 | H22: =6.5+6+7 -> 19.5 | I22: =G22+H22/8 -> 29.9375 | J22: =B22-(E22+F22+I22) -> 22.1875 | L22: =O8 -> 0.20205993 | M22: =L22*J22 -> 4.4832046 | N22: =O8*I8 -> 4.4958333
A23: Net oats | B23: =F9 -> 170 | C23: 83 | D23: 3 | E23: =C23+D23/8 -> 83.375 | G23: =6+4+12+20 -> 42 | H23: =6+2+5 -> 13 | I23: =G23+H23/8 -> 43.625 | J23: =B23-(E23+F23+I23) -> 43 | L23: =O9 -> 0.10193798 | M23: =L23*J23 -> 4.3833333 | N23: =O9*I9 -> 4.3833333
A24: Net peas | B24: =F10 -> 6.5 | C24: 3 | E24: =C24+D24/8 -> 3 | H24: 3 | I24: =G24+H24/8 -> 0.375 | J24: =B24-(E24+F24+I24) -> 3.125 | L24: =O10 -> 0.15 | M24: =L24*J24 -> 0.46875 | N24: =O10*I10 -> 0.46875
A25: Net vetches | B25: =F11 -> 7.75 | C25: 3 | D25: 2 | E25: =C25+D25/8 -> 3.25 | I25: =G25+H25/8 -> 0 | J25: =B25-(E25+F25+I25) -> 4.5 | L25: =O11 -> 0.1 | M25: =L25*J25 -> 0.45 | N25: =O11*I11 -> 0.45
A26: Total | B26: =SUM(B19:B25) -> 355.4375 | E26: =SUM(E19:E25) -> 149.5 | J26: =SUM(J19:J25) -> 124.875 | M26: =SUM(M19:M25) -> 23.970705 | N26: =SUM(N19:N25) -> 23.983333

Sheet Stock
A1: EAST KNOYLE STOCK ACCOUNT
A3: Livestock | B3: Inherited stock | C3: Bought | D3: Produced | E3: strays | F3: herbage | G3: sold | H3: in murrain | I3: accounted for elsewhere | J3: End-period stock | K3: cross-check | L3: price 1 | M3: units 1 | N3: price 2 | O3: units 2 | P3: Weight (weys) | Q3: Unit price (£) | R3: Value of production (£) at sales prices | S3: Sales in (£) | T3: Details
A4: Cart-horses | B4: 2 | J4: 2 | K4: =B4+C4+D4+E4-F4-G4-H4-I4 -> 2 | Q4: =IFERROR((L4+N4)/(M4+O4),"") | R4: =IFERROR(D4*Q4,"") | S4: =IFERROR(Q4*G4,"")
A5: Mares | K5: =B5+C5+D5+E5-F5-G5-H5-I5 -> 0 | Q5: =IFERROR((L5+N5)/(M5+O5),"") | R5: =IFERROR(D5*Q5,"") | S5: =IFERROR(Q5*G5,"")
A6: Plough horses | B6: 5 | C6: 1 | D6: 1 | H6: 1 | J6: 6 | K6: =B6+C6+D6+E6-F6-G6-H6-I6 -> 6 | Q6: =IFERROR((L6+N6)/(M6+O6),"") | R6: =IFERROR(D6*Q6,"") | S6: =IFERROR(Q6*G6,"")
A7: Colts (2 years) | K7: =B7+C7+D7+E7-F7-G7-H7-I7 -> 0 | Q7: =IFERROR((L7+N7)/(M7+O7),"") | R7: =IFERROR(D7*Q7,"") | S7: =IFERROR(Q7*G7,"")
A8: Colts (2 years) | K8: =B8+C8+D8+E8-F8-G8-H8-I8 -> 0 | Q8: =IFERROR((L8+N8)/(M8+O8),"") | R8: =IFERROR(D8*Q8,"") | S8: =IFERROR(Q8*G8,"")
A9: Colts (1 year) | K9: =B9+C9+D9+E9-F9-G9-H9-I9 -> 0 | Q9: =IFERROR((L9+N9)/(M9+O9),"") | R9: =IFERROR(D9*Q9,"") | S9: =IFERROR(Q9*G9,"")
A10: Foals | K10: =B10+C10+D10+E10-F10-G10-H10-I10 -> 0 | Q10: =IFERROR((L10+N10)/(M10+O10),"") | R10: =IFERROR(D10*Q10,"") | S10: =IFERROR(Q10*G10,"")
A11: Oxen | B11: 30 | C11: 5 | D11: 1 | E11: 1 | H11: 2 | J11: 35 | K11: =B11+C11+D11+E11-F11-G11-H11-I11 -> 35 | Q11: =IFERROR((L11+N11)/(M11+O11),"") | R11: =IFERROR(D11*Q11,"") | S11: =IFERROR(Q11*G11,"")
A12: Bulls | B12: 1 | J12: 1 | K12: =B12+C12+D12+E12-F12-G12-H12-I12 -> 1 | Q12: =IFERROR((L12+N12)/(M12+O12),"") | R12: =IFERROR(D12*Q12,"") | S12: =IFERROR(Q12*G12,"")
A13: Cows | B13: 17 | D13: 2 | J13: 19 | K13: =B13+C13+D13+E13-F13-G13-H13-I13 -> 19 | Q13: =IFERROR((L13+N13)/(M13+O13),"") | R13: =IFERROR(D13*Q13,"") | S13: =IFERROR(Q13*G13,"")
A14: Steers | B14: 4 | H14: 1 | I14: 3 | J14: 0 | K14: =B14+C14+D14+E14-F14-G14-H14-I14 -> 0 | Q14: =IFERROR((L14+N14)/(M14+O14),"") | R14: =IFERROR(D14*Q14,"") | S14: =IFERROR(Q14*G14,"")
A15: Bullocks | B15: 5 | H15: 1 | J15: 4 | K15: =B15+C15+D15+E15-F15-G15-H15-I15 -> 4 | Q15: =IFERROR((L15+N15)/(M15+O15),"") | R15: =IFERROR(D15*Q15,"") | S15: =IFERROR(Q15*G15,"")
A16: Yearlings | B16: 6 | H16: 1 | J16: 5 | K16: =B16+C16+D16+E16-F16-G16-H16-I16 -> 5 | Q16: =IFERROR((L16+N16)/(M16+O16),"") | R16: =IFERROR(D16*Q16,"") | S16: =IFERROR(Q16*G16,"")
A17: Calves | D17: 13 | G17: 5 | H17: 1 | I17: 1 | J17: 6 | K17: =B17+C17+D17+E17-F17-G17-H17-I17 -> 6 | L17: ='Crawley Receipts'!F54 -> 0.25 | M17: 5 | Q17: =IFERROR((L17+N17)/(M17+O17),"") -> 0.05 | R17: =IFERROR(D17*Q17,"") -> 0.65 | S17: =IFERROR(Q17*G17,"") -> 0.25
A18: Wethers | B18: 383 | D18: 132 | G18: 47 | H18: 35 | J18: 433 | K18: =B18+C18+D18+E18-F18-G18-H18-I18 -> 433 | L18: ='Crawley Receipts'!F55 -> 2.7416667 | M18: 47 | Q18: =IFERROR((L18+N18)/(M18+O18),"") -> 0.058333333 | R18: =IFERROR(D18*Q18,"") -> 7.7 | S18: =IFERROR(Q18*G18,"") -> 2.7416667
A19: Rams | K19: =B19+C19+D19+E19-F19-G19-H19-I19 -> 0 | Q19: =IFERROR((L19+N19)/(M19+O19),"") | R19: =IFERROR(D19*Q19,"") | S19: =IFERROR(Q19*G19,"")
A20: Ewes | B20: 536 | D20: 131 | G20: 55 | H20: 37 | J20: 575 | K20: =B20+C20+D20+E20-F20-G20-H20-I20 -> 575 | L20: ='Crawley Receipts'!F56 -> 2.2916667 | M20: 55 | Q20: =IFERROR((L20+N20)/(M20+O20),"") -> 0.041666667 | R20: =IFERROR(D20*Q20,"") -> 5.4583333 | S20: =IFERROR(Q20*G20,"") -> 2.2916667
A21: Hoggs | B21: 286 | H21: 23 | I21: 263 | J21: 0 | K21: =B21+C21+D21+E21-F21-G21-H21-I21 -> 0 | Q21: =IFERROR((L21+N21)/(M21+O21),"") | R21: =IFERROR(D21*Q21,"") | S21: =IFERROR(Q21*G21,"")
A22: Lambs | D22: 392 | H22: 88 | I22: 36 | J22: 268 | K22: =B22+C22+D22+E22-F22-G22-H22-I22 -> 268 | Q22: =IFERROR((L22+N22)/(M22+O22),"") | R22: =IFERROR(D22*Q22,"") | S22: =IFERROR(Q22*G22,"") | T22: Accounted for elsewhere is tithe
A23: Boars | B23: 1 | J23: 1 | K23: =B23+C23+D23+E23-F23-G23-H23-I23 -> 1 | Q23: =IFERROR((L23+N23)/(M23+O23),"") | R23: =IFERROR(D23*Q23,"") | S23: =IFERROR(Q23*G23,"")
A24: Sows | K24: =B24+C24+D24+E24-F24-G24-H24-I24 -> 0 | Q24: =IFERROR((L24+N24)/(M24+O24),"") | R24: =IFERROR(D24*Q24,"") | S24: =IFERROR(Q24*G24,"")
A25: Pigs | B25: 27 | D25: 29 | G25: 26 | J25: 30 | K25: =B25+C25+D25+E25-F25-G25-H25-I25 -> 30 | L25: ='Crawley Receipts'!F57 -> 3.3666667 | M25: 26 | Q25: =IFERROR((L25+N25)/(M25+O25),"") -> 0.12948718 | R25: =IFERROR(D25*Q25,"") -> 3.7551282 | S25: =IFERROR(Q25*G25,"") -> 3.3666667
A26: Hoggets | B26: 29 | I26: 29 | J26: 0 | K26: =B26+C26+D26+E26-F26-G26-H26-I26 -> 0 | Q26: =IFERROR((L26+N26)/(M26+O26),"") | R26: =IFERROR(D26*Q26,"") | S26: =IFERROR(Q26*G26,"")
A27: Piglets | D27: 32 | E27: 2 | H27: 8 | I27: 3 | J27: 23 | K27: =B27+C27+D27+E27-F27-G27-H27-I27 -> 23 | Q27: =IFERROR((L27+N27)/(M27+O27),"") | R27: =IFERROR(D27*Q27,"") | S27: =IFERROR(Q27*G27,"") | T27: Accounted for elsewhere is tithe
A28: Swans | K28: =B28+C28+D28+E28-F28-G28-H28-I28 -> 0 | Q28: =IFERROR((L28+N28)/(M28+O28),"") | R28: =IFERROR(D28*Q28,"") | S28: =IFERROR(Q28*G28,"")
A29: Peacocks | K29: =B29+C29+D29+E29-F29-G29-H29-I29 -> 0 | Q29: =IFERROR((L29+N29)/(M29+O29),"") | R29: =IFERROR(D29*Q29,"") | S29: =IFERROR(Q29*G29,"")
A30: Total | S30: =SUM(S4:S29) -> 8.65
K31: =B31+C31+D31+E31-F31-G31-H31-I31 -> 0 | Q31: =IFERROR((L31+N31)/(M31+O31),"") | R31: =IFERROR(D31*Q31,"") | S31: =IFERROR(Q31*G31,"")
K32: =B32+C32+D32+E32-F32-G32-H32-I32 -> 0 | Q32: =IFERROR((L32+N32)/(M32+O32),"") | R32: =IFERROR(D32*Q32,"") | S32: =IFERROR(Q32*G32,"")
A33: Wool | K33: =B33+C33+D33+E33-F33-G33-H33-I33 -> 0 | Q33: =IFERROR((L33+N33)/(M33+O33),"") | R33: =IFERROR(D33*Q33,"") | S33: =IFERROR(Q33*G33,"")
A34: Fleeces | K34: =B34+C34+D34+E34-F34-G34-H34-I34 -> 0 | Q34: =IFERROR((L34+N34)/(M34+O34),"") | R34: =IFERROR(D34*Q34,"") | S34: =IFERROR(Q34*G34,"")
A35: Coarse wool | D35: 1035 | G35: 929 | I35: 106 | J35: 0 | K35: =B35+C35+D35+E35-F35-G35-H35-I35 -> 0 | L35: 0 | P35: =6.5+3*0.04 -> 6.62 | Q35: 0.02 | R35: =IFERROR(D35*Q35,"") -> 20.7 | S35: =IFERROR(Q35*G35,"") -> 18.58 | T35: unit price from overview sheet (UnitPricesStocks_averages)
A36: Lamb's wool | D36: 283 | G36: 283 | J36: 0 | K36: =B36+C36+D36+E36-F36-G36-H36-I36 -> 0 | L36: 0 | P36: =15*0.04 -> 0.6 | Q36: 0.01 | R36: =IFERROR(D36*Q36,"") -> 2.83 | S36: =IFERROR(Q36*G36,"") -> 2.83 | T36: unit price from overview sheet (UnitPricesStocks_averages)
A37: Wool locks | D37: =5*0.04 -> 0.2 | G37: =5*0.04 -> 0.2 | K37: =B37+C37+D37+E37-F37-G37-H37-I37 -> 0 | L37: ='Crawley Receipts'!F76 -> 0.21875 | M37: =5*0.04 -> 0.2 | P37: =5*0.04 -> 0.2 | Q37: =IFERROR((L37+N37)/(M37+O37),"") -> 1.09375 | R37: =IFERROR(D37*Q37,"") -> 0.21875 | S37: =IFERROR(Q37*G37,"") -> 0.21875
A38: Wool sold at shearing | K38: =B38+C38+D38+E38-F38-G38-H38-I38 -> 0 | Q38: =IFERROR((L38+N38)/(M38+O38),"") | R38: =IFERROR(D38*Q38,"") | S38: =IFERROR(Q38*G38,"")
A39: Total | K39: =B39+C39+D39+E39-F39-G39-H39-I39 -> 0 | Q39: =IFERROR((L39+N39)/(M39+O39),"") | R39: =IFERROR(D39*Q39,"") | S39: =SUM(S35:S38) -> 21.62875
K40: =B40+C40+D40+E40-F40-G40-H40-I40 -> 0 | Q40: =IFERROR((L40+N40)/(M40+O40),"") | R40: =IFERROR(D40*Q40,"") | S40: =IFERROR(Q40*G40,"")
K41: =B41+C41+D41+E41-F41-G41-H41-I41 -> 0 | Q41: =IFERROR((L41+N41)/(M41+O41),"") | R41: =IFERROR(D41*Q41,"") | S41: =IFERROR(Q41*G41,"")
A42: Hides | K42: =B42+C42+D42+E42-F42-G42-H42-I42 -> 0 | Q42: =IFERROR((L42+N42)/(M42+O42),"") | R42: =IFERROR(D42*Q42,"") | S42: =IFERROR(Q42*G42,"")
A43: Ox hides | D43: 2 | G43: 2 | J43: 0 | K43: =B43+C43+D43+E43-F43-G43-H43-I43 -> 0 | L43: ='Crawley Receipts'!F59 -> 0.22708333 | M43: 2 | Q43: =IFERROR((L43+N43)/(M43+O43),"") -> 0.11354167 | R43: =IFERROR(D43*Q43,"") -> 0.22708333 | S43: =IFERROR(Q43*G43,"") -> 0.22708333
A44: Cow hides | K44: =B44+C44+D44+E44-F44-G44-H44-I44 -> 0 | Q44: =IFERROR((L44+N44)/(M44+O44),"") | R44: =IFERROR(D44*Q44,"") | S44: =IFERROR(Q44*G44,"")
A45: Mare hides | D45: 1 | G45: 1 | J45: 0 | K45: =B45+C45+D45+E45-F45-G45-H45-I45 -> 0 | L45: ='Crawley Receipts'!F58 -> 0.045833333 | M45: 1 | Q45: =IFERROR((L45+N45)/(M45+O45),"") -> 0.045833333 | R45: =IFERROR(D45*Q45,"") -> 0.045833333 | S45: =IFERROR(Q45*G45,"") -> 0.045833333
A46: Steer hides | D46: 2 | G46: 2 | J46: 0 | K46: =B46+C46+D46+E46-F46-G46-H46-I46 -> 0 | L46: ='Crawley Receipts'!F61 -> 0.025 | M46: 1 | N46: ='Crawley Receipts'!F61 -> 0.025 | O46: 1 | Q46: =IFERROR((L46+N46)/(M46+O46),"") -> 0.025 | R46: =IFERROR(D46*Q46,"") -> 0.05 | S46: =IFERROR(Q46*G46,"") -> 0.05
A47: Yearling Calf hides | D47: 1 | G47: 1 | J47: 0 | K47: =B47+C47+D47+E47-F47-G47-H47-I47 -> 0 | L47: ='Crawley Receipts'!F62 -> 0.00625 | M47: 1 | Q47: =IFERROR((L47+N47)/(M47+O47),"") -> 0.00625 | R47: =IFERROR(D47*Q47,"") -> 0.00625 | S47: =IFERROR(Q47*G47,"") -> 0.00625
A48: Calf hides | D48: 1 | G48: 1 | J48: 0 | K48: =B48+C48+D48+E48-F48-G48-H48-I48 -> 0 | L48: ='Crawley Receipts'!F63 -> 0.0041666667 | M48: 1 | Q48: =IFERROR((L48+N48)/(M48+O48),"") -> 0.0041666667 | R48: =IFERROR(D48*Q48,"") -> 0.0041666667 | S48: =IFERROR(Q48*G48,"") -> 0.0041666667
A49: Pig hides | K49: =B49+C49+D49+E49-F49-G49-H49-I49 -> 0 | Q49: =IFERROR((L49+N49)/(M49+O49),"") | R49: =IFERROR(D49*Q49,"") | S49: =IFERROR(Q49*G49,"")
A50: Weather woolskins | D50: 21 | G50: 21 | J50: 0 | K50: =B50+C50+D50+E50-F50-G50-H50-I50 -> 0 | Q50: =IFERROR((L50+N50)/(M50+O50),"") | R50: =IFERROR(D50*Q50,"") | S50: =IFERROR(Q50*G50,"")
A51: Ram woolskins | K51: =B51+C51+D51+E51-F51-G51-H51-I51 -> 0 | Q51: =IFERROR((L51+N51)/(M51+O51),"") | R51: =IFERROR(D51*Q51,"") | S51: =IFERROR(Q51*G51,"")
A52: Ewe woolskins | D52: 24 | G52: 24 | J52: 0 | K52: =B52+C52+D52+E52-F52-G52-H52-I52 -> 0 | Q52: =IFERROR((L52+N52)/(M52+O52),"") | R52: =IFERROR(D52*Q52,"") | S52: =IFERROR(Q52*G52,"")
A53: Hogg woolskins | D53: 23 | G53: 23 | J53: 0 | K53: =B53+C53+D53+E53-F53-G53-H53-I53 -> 0 | Q53: =IFERROR((L53+N53)/(M53+O53),"") | R53: =IFERROR(D53*Q53,"") | S53: =IFERROR(Q53*G53,"")
A54: Woolskins (total) | D54: =SUM(D50:D53) -> 68 | G54: =SUM(G50:G53) -> 68 | J54: 0 | K54: =B54+C54+D54+E54-F54-G54-H54-I54 -> 0 | L54: ='Crawley Receipts'!F64 -> 0.94166667 | M54: 68 | Q54: =IFERROR((L54+N54)/(M54+O54),"") -> 0.013848039 | R54: =IFERROR(D54*Q54,"") -> 0.94166667 | S54: =IFERROR(Q54*G54,"") -> 0.94166667
A55: Wether bareskins | D55: 14 | G55: 14 | J55: 0 | K55: =B55+C55+D55+E55-F55-G55-H55-I55 -> 0 | Q55: =IFERROR((L55+N55)/(M55+O55),"") | R55: =IFERROR(D55*Q55,"") | S55: =IFERROR(Q55*G55,"")
A56: Ram bareskins | K56: =B56+C56+D56+E56-F56-G56-H56-I56 -> 0 | Q56: =IFERROR((L56+N56)/(M56+O56),"") | R56: =IFERROR(D56*Q56,"") | S56: =IFERROR(Q56*G56,"")
A57: Ewe bareskins | D57: 13 | G57: 13 | J57: 0 | K57: =B57+C57+D57+E57-F57-G57-H57-I57 -> 0 | Q57: =IFERROR((L57+N57)/(M57+O57),"") | R57: =IFERROR(D57*Q57,"") | S57: =IFERROR(Q57*G57,"")
A58: Hogg bareskins | K58: =B58+C58+D58+E58-F58-G58-H58-I58 -> 0 | Q58: =IFERROR((L58+N58)/(M58+O58),"") | R58: =IFERROR(D58*Q58,"") | S58: =IFERROR(Q58*G58,"")
A59: Bareskins (total) | D59: 27 | G59: 27 | J59: 0 | K59: =B59+C59+D59+E59-F59-G59-H59-I59 -> 0 | L59: ='Crawley Receipts'!$F$65 -> 0.225 | M59: 27 | Q59: =IFERROR((L59+N59)/(M59+O59),"") -> 0.0083333333 | R59: =IFERROR(D59*Q59,"") -> 0.225 | S59: =IFERROR(Q59*G59,"") -> 0.225
A60: Lambskins | D60: 88 | G60: 82 | I60: 6 | K60: =B60+C60+D60+E60-F60-G60-H60-I60 -> 0 | L60: ='Crawley Receipts'!F66 -> 0.25833333 | M60: 62 | N60: ='Crawley Receipts'!F67 -> 0.041666667 | O60: 20 | Q60: =IFERROR((L60+N60)/(M60+O60),"") -> 0.0036585366 | R60: =IFERROR(D60*Q60,"") -> 0.32195122 | S60: =IFERROR(Q60*G60,"") -> 0.3 | T60: Accounted for elsewhere is tithe
A61: Rotted skins | K61: =B61+C61+D61+E61-F61-G61-H61-I61 -> 0 | Q61: =IFERROR((L61+N61)/(M61+O61),"") | R61: =IFERROR(D61*Q61,"") | S61: =IFERROR(Q61*G61,"")
A62: Shorn skins | K62: =B62+C62+D62+E62-F62-G62-H62-I62 -> 0 | Q62: =IFERROR((L62+N62)/(M62+O62),"") | R62: =IFERROR(D62*Q62,"") | S62: =IFERROR(Q62*G62,"")
A63: Total | S63: =SUM(S43:S62) -> 1.8
K64: =B64+C64+D64+E64-F64-G64-H64-I64 -> 0 | Q64: =IFERROR((L64+N64)/(M64+O64),"") | R64: =IFERROR(D64*Q64,"") | S64: =IFERROR(Q64*G64,"")
K65: =B65+C65+D65+E65-F65-G65-H65-I65 -> 0 | Q65: =IFERROR((L65+N65)/(M65+O65),"") | R65: =IFERROR(D65*Q65,"") | S65: =IFERROR(Q65*G65,"")
A66: Poultry stock | K66: =B66+C66+D66+E66-F66-G66-H66-I66 -> 0 | Q66: =IFERROR((L66+N66)/(M66+O66),"") | R66: =IFERROR(D66*Q66,"") | S66: =IFERROR(Q66*G66,"")
A67: Hens | D67: 125 | G67: 95 | I67: 30 | K67: =B67+C67+D67+E67-F67-G67-H67-I67 -> 0 | L67: ='Crawley Receipts'!F71 -> 0.39583333 | M67: 95 | Q67: =IFERROR((L67+N67)/(M67+O67),"") -> 0.0041666667 | R67: =IFERROR(D67*Q67,"") -> 0.52083333 | S67: =IFERROR(Q67*G67,"") -> 0.39583333 | T67: Accounted for elsewhere is tithe
A68: Geese | K68: =B68+C68+D68+E68-F68-G68-H68-I68 -> 0 | Q68: =IFERROR((L68+N68)/(M68+O68),"") | R68: =IFERROR(D68*Q68,"") | S68: =IFERROR(Q68*G68,"")
A69: Capons (from chickens) | K69: =B69+C69+D69+E69-F69-G69-H69-I69 -> 0 | Q69: =IFERROR((L69+N69)/(M69+O69),"") | R69: =IFERROR(D69*Q69,"") | S69: =IFERROR(Q69*G69,"")
A70: Cocks & hens | K70: =B70+C70+D70+E70-F70-G70-H70-I70 -> 0 | Q70: =IFERROR((L70+N70)/(M70+O70),"") | R70: =IFERROR(D70*Q70,"") | S70: =IFERROR(Q70*G70,"")
A71: Total | K71: =B71+C71+D71+E71-F71-G71-H71-I71 -> 0 | Q71: =IFERROR((L71+N71)/(M71+O71),"") | R71: =IFERROR(D71*Q71,"") | S71: =SUM(S67:S70) -> 0.39583333
K72: =B72+C72+D72+E72-F72-G72-H72-I72 -> 0 | Q72: =IFERROR((L72+N72)/(M72+O72),"") | R72: =IFERROR(D72*Q72,"") | S72: =IFERROR(Q72*G72,"")
A73: Poultry production | K73: =B73+C73+D73+E73-F73-G73-H73-I73 -> 0 | Q73: =IFERROR((L73+N73)/(M73+O73),"") | R73: =IFERROR(D73*Q73,"") | S73: =IFERROR(Q73*G73,"")
A74: Eggs | K74: =B74+C74+D74+E74-F74-G74-H74-I74 -> 0 | Q74: =IFERROR((L74+N74)/(M74+O74),"") | R74: =IFERROR(D74*Q74,"") | S74: =IFERROR(Q74*G74,"")
A75: Cocks & hens from churchscot of customary tenants | K75: =B75+C75+D75+E75-F75-G75-H75-I75 -> 0 | Q75: =IFERROR((L75+N75)/(M75+O75),"") | R75: =IFERROR(D75*Q75,"") | S75: =IFERROR(Q75*G75,"")
K76: =B76+C76+D76+E76-F76-G76-H76-I76 -> 0 | Q76: =IFERROR((L76+N76)/(M76+O76),"") | R76: =IFERROR(D76*Q76,"") | S76: =IFERROR(Q76*G76,"")
K77: =B77+C77+D77+E77-F77-G77-H77-I77 -> 0 | Q77: =IFERROR((L77+N77)/(M77+O77),"") | R77: =IFERROR(D77*Q77,"") | S77: =IFERROR(Q77*G77,"")
A78: Meat | K78: =B78+C78+D78+E78-F78-G78-H78-I78 -> 0 | Q78: =IFERROR((L78+N78)/(M78+O78),"") | R78: =IFERROR(D78*Q78,"") | S78: =IFERROR(Q78*G78,"")
A79: Beef | K79: =B79+C79+D79+E79-F79-G79-H79-I79 -> 0 | Q79: =IFERROR((L79+N79)/(M79+O79),"") | R79: =IFERROR(D79*Q79,"") | S79: =IFERROR(Q79*G79,"")
A80: Mutton | K80: =B80+C80+D80+E80-F80-G80-H80-I80 -> 0 | Q80: =IFERROR((L80+N80)/(M80+O80),"") | R80: =IFERROR(D80*Q80,"") | S80: =IFERROR(Q80*G80,"")
A81: Pork | K81: =B81+C81+D81+E81-F81-G81-H81-I81 -> 0 | Q81: =IFERROR((L81+N81)/(M81+O81),"") | R81: =IFERROR(D81*Q81,"") | S81: =IFERROR(Q81*G81,"")
K82: =B82+C82+D82+E82-F82-G82-H82-I82 -> 0 | Q82: =IFERROR((L82+N82)/(M82+O82),"") | R82: =IFERROR(D82*Q82,"") | S82: =IFERROR(Q82*G82,"")
K83: =B83+C83+D83+E83-F83-G83-H83-I83 -> 0 | Q83: =IFERROR((L83+N83)/(M83+O83),"") | R83: =IFERROR(D83*Q83,"") | S83: =IFERROR(Q83*G83,"")
A84: Cheese | K84: =B84+C84+D84+E84-F84-G84-H84-I84 -> 0 | Q84: =IFERROR((L84+N84)/(M84+O84),"") | R84: =IFERROR(D84*Q84,"") | S84: =IFERROR(Q84*G84,"")
A85: Winter cheese | D85: =5*0.04+1*Assumptions!$E$4 -> 0.20571429 | G85: =5*0.04+1*Assumptions!$E$4 -> 0.20571429 | K85: =B85+C85+D85+E85-F85-G85-H85-I85 -> 0 | L85: ='Crawley Receipts'!F68 -> 0.075 | M85: =5*0.04+1*Assumptions!$E$4 -> 0.20571429 | P85: =5*0.04+1*Assumptions!$E$4 -> 0.20571429 | Q85: =IFERROR((L85+N85)/(M85+O85),"") -> 0.36458333 | R85: =IFERROR(D85*Q85,"") -> 0.075 | S85: =IFERROR(Q85*G85,"") -> 0.075
A86: Summer cheese | D86: 168 | G86: 148 | I86: 20 | K86: =B86+C86+D86+E86-F86-G86-H86-I86 -> 0 | L86: ='Crawley Receipts'!F69 -> 3.3041667 | M86: =P86 -> 7.98 | P86: =7.5+12*0.04 -> 7.98 | Q86: =IFERROR((L86+N86)/(M86+O86),"") -> 0.41405597 | R86: =IFERROR(D86*Q86,"") -> 69.561404 | S86: =IFERROR(Q86*G86,"") -> 61.280284
A87: Total | K87: =B87+C87+D87+E87-F87-G87-H87-I87 -> 0 | Q87: =IFERROR((L87+N87)/(M87+O87),"") | R87: =IFERROR(D87*Q87,"") | S87: =SUM(S85:S86) -> 61.355284
K88: =B88+C88+D88+E88-F88-G88-H88-I88 -> 0 | Q88: =IFERROR((L88+N88)/(M88+O88),"") | R88: =IFERROR(D88*Q88,"") | S88: =IFERROR(Q88*G88,"")
A89: Butter | D89: =15*0.04+5*Assumptions!$E$4 -> 0.62857143 | G89: =15*0.04+5*Assumptions!$E$4 -> 0.62857143 | K89: =B89+C89+D89+E89-F89-G89-H89-I89 -> 0 | M89: =15*0.04+5*Assumptions!$E$4 -> 0.62857143 | P89: =15*0.04+5*Assumptions!$E$4 -> 0.62857143 | Q89: =IFERROR((L89+N89)/(M89+O89),"") -> 0 | R89: =IFERROR(D89*Q89,"") -> 0 | S89: =IFERROR(Q89*G89,"") -> 0
A90: Total | K90: =B90+C90+D90+E90-F90-G90-H90-I90 -> 0 | Q90: =IFERROR((L90+N90)/(M90+O90),"") | R90: =IFERROR(D90*Q90,"") | S90: =SUM(S89) -> 0
K91: =B91+C91+D91+E91-F91-G91-H91-I91 -> 0 | Q91: =IFERROR((L91+N91)/(M91+O91),"") | R91: =IFERROR(D91*Q91,"") | S91: =IFERROR(Q91*G91,"")
A92: Cider | K92: =B92+C92+D92+E92-F92-G92-H92-I92 -> 0 | Q92: =IFERROR((L92+N92)/(M92+O92),"") | R92: =IFERROR(D92*Q92,"") | S92: =IFERROR(Q92*G92,"")
K93: =B93+C93+D93+E93-F93-G93-H93-I93 -> 0 | Q93: =IFERROR((L93+N93)/(M93+O93),"") | R93: =IFERROR(D93*Q93,"") | S93: =IFERROR(Q93*G93,"")
K94: =B94+C94+D94+E94-F94-G94-H94-I94 -> 0 | Q94: =IFERROR((L94+N94)/(M94+O94),"") | R94: =IFERROR(D94*Q94,"") | S94: =IFERROR(Q94*G94,"")
K95: =B95+C95+D95+E95-F95-G95-H95-I95 -> 0 | Q95: =IFERROR((L95+N95)/(M95+O95),"") | R95: =IFERROR(D95*Q95,"") | S95: =IFERROR(Q95*G95,"")
Q96: =IFERROR((L96+N96)/(M96+O96),"") | R96: =IFERROR(D96*Q96,"") | S96: =IFERROR(Q96*G96,"")
Q97: =IFERROR((L97+N97)/(M97+O97),"") | R97: =IFERROR(D97*Q97,"") | S97: =IFERROR(Q97*G97,"")

Sheet Assumptions
A1: ASSUMPTIONS
B3: Weights | C3: Value (in lbs) | D3: Value (in cloves) | E3: Value (in weys) | F3: Value (in stone)
B4: Lbs | C4: 1 | D4: =C4/C5 -> 0.14285714 | E4: =C4/C6 -> 0.0057142857 | F4: =C4/C7 -> 0.08
B5: Cloves | C5: 7 | D5: 1 | E5: =C5/C6 -> 0.04 | F5: =C7/C5 -> 1.7857143
B6: Wey | C6: 175 | D6: =C6/C5 -> 25 | E6: =C6/C6 -> 1 | F6: =C7/C6 -> 0.071428571
B7: Stone | C7: =175/14 -> 12.5 | D7: =C5/C7 -> 0.56 | E7: =C7/C6 -> 0.071428571 | F7: 1
