Workbook

Sheet Overview
A1: EAST MEON CHURCH | B1: Total in £ | C1: Error | D1: Note
A2: CASH ACCOUNT
A3: RECEIPTS
A4: Arrears total
A5: Rents of assize total
A6: Quittances total
A7: Defaults of rent total
A8: Defaults of rent through the pestilence total
A9: Cotlands defaults total
A10: Cotlands total
A11: Total of quittances and defaults of rent total
A12: Total of rents remaining clear total
A13: Farms total
... A22: Farm of the demesne land total
A23: Total of all receipts (calculated here) | B23: =Receipts!F103 -> 104.37333
A24: Total of all receipts (calculated here) incl arrears | B24: =Receipts!F104 -> 185.70333
A25: Total recorded in the accounts excl. arrears | B25: =Receipts!F102 -> 104.88 | C25: =B25-B23 -> 0.50666667
A26: Total recorded in the accounts incl. arrears
A29: EXPENSES
A30: Cost of ploughs total
A31: Purchase of corn total
A32: Cost of carts and wagons total
A33: Cost of dairy total
A34: Purchase of stock total
A35: Sheepcote total
A36: Cost of buildings total
A37: Threshing total
A38: Barley expenses
A39: Expenses of the harvest total
... A43: Annual fees
A44: Total of all expenses per account | B44: =Expenses!F94 -> 14.6
A45: Total of all expenses (calculated here) | B45: =Expenses!F95 -> 14.615833
A46: Total fixed investment | B46: =Expenses!F96 -> 4.9960417
A47: Total Demesne fixed investment | B47: =Expenses!F97 -> 4.9960417
A49: Owed by the reeve
A50: From accounts
A52: Allowances
A53: Cash deliveries
A54: Sum of the above
A55: Total of all allowances and cash deliveries in accounts
A57: Net amount owed
A58: Net amount owed in accounts
A60: GRANGE ACCOUNT | B60: Total Production
A61: Grange | B61: qrs | E61: Value of total gross production in £ | F61: Value of total net production in £
A62: wheat | B62: ='Issues of the Grange'!B2 -> 104.5 | E62: ='Issues of the Grange'!I2 -> 29.26 | F62: ='Issues of the Grange'!O15 -> 25.48
A63: bere | B63: ='Issues of the Grange'!B3 -> 41 | E63: ='Issues of the Grange'!I3 -> 6.8333333 | F63: ='Issues of the Grange'!O16 -> 5.625
A64: barley | B64: ='Issues of the Grange'!B4 -> 60.125 | E64: ='Issues of the Grange'!I4 -> 11.644296 | F64: ='Issues of the Grange'!O17 -> 7.9161845
A65: oats | B65: ='Issues of the Grange'!B5 -> 129.5 | E65: ='Issues of the Grange'!I5 -> 13.364913 | F65: ='Issues of the Grange'!O18 -> 6.6437552
A66: beans | B66: ='Issues of the Grange'!B6 -> 12.125 | E66: ='Issues of the Grange'!I6 -> 1.6166667 | F66: ='Issues of the Grange'!O19 -> 1.6166667
A67: peas | B67: ='Issues of the Grange'!B7 -> 2 | E67: ='Issues of the Grange'!I7 -> 0.3 | F67: ='Issues of the Grange'!O20 -> 0.3
A68: vetches | B68: ='Issues of the Grange'!B8 -> 7.25 | E68: ='Issues of the Grange'!I8 -> 0.725 | F68: ='Issues of the Grange'!O21 -> 0.725
A69: Total value of gross production (sum of the above) | E69: =SUM(E62:E68) -> 63.744209
A70: Total value of net production | E70: =SUM(F62:F68) -> 48.306606
A71: Value of sales | E71: =Receipts!F65 -> 10.36 | G71: not including sales from tithes
A73: MILL ACCOUNT
A74: Issues of the mill
A75: Wheat
A76: Oatmeal
A77: 1st grade malt
A78: 2nd grade malt
A79: Maslin
A80: Total value of production (sum of the above)
A81: Value of sales
A83: STOCK ACCOUNT
A84: Livestock | B84: Sales value in £
A85: Cart-horses | B85: =Stock!R5 -> 0
A86: Mares | B86: =Stock!R6 -> 0
A87: Plough horses | B87: =Stock!R7 -> 0.2
A88: Colts (2 years) | B88: =Stock!R8 -> 0
A89: Colts (2 years) | B89: =Stock!R9 -> 0
A90: Colts (1 year) | B90: =Stock!R10 -> 0
A91: Foals | B91: =Stock!R11 -> 0
A92: Oxen | B92: =Stock!R12 -> 0
A93: Bulls | B93: =Stock!R13 -> 0
A94: Cows | B94: =Stock!R14 -> 0
A95: Steers | B95: =Stock!R15 -> 0
A96: Bullocks | B96: =Stock!R16 -> 0
... A110: Peacocks | B110: =Stock!R30 -> 0
A111: Total value of stock (sum of the above)
A112: Total value of production
A113: Value of sales | B113: =Stock!R31 -> 2.34
A115: Wool | B115: Value of production at sales prices £
A116: Fleeces | B116: =Stock!T35 -> 3.6
A117: Coarse wool | B117: =Stock!T36 -> 0
A118: Lamb's wool | B118: =Stock!T37 -> 0
A119: Wool locks | B119: =Stock!T38 -> 0
A120: Wool sold at shearing | B120: =Stock!T39 -> 0
A121: Total value of production (sum of the above) | B121: =Stock!T40 -> 3.6
A122: Value of sales | B122: =Stock!R40 -> 0
A124: Hides | B124: Value of production at sales prices £
A125: Ox hides | B125: =Stock!T44 -> 0
A126: Cow hides | B126: =Stock!T45 -> 0
A127: Mare hides | B127: =Stock!T46 -> 0
A128: Steer hides | B128: =Stock!T47 -> 0
A129: Yearling Calf hides | B129: =Stock!T48 -> 0
A130: Calf hides | B130: =Stock!T49 -> 0
A131: Pig hides | B131: =Stock!T50 -> 0
A132: Wether woolskins | B132: =Stock!T51 -> 0
A133: Ram woolskins | B133: =Stock!T52 -> 0
A134: Ewe woolskins | B134: =Stock!T53 -> 0
...

Sheet Receipts
A1: EAST MEON CHURCH
A2: Heading | B2: £ | C2: s | D2: d | F2: Total in £ | G2: Error | H2: Notes
A3: Arrears | B3: 81 | C3: 6 | D3: 8.25 | F3: 81.33 | H3: Nicholas de Ychen', bailiff, and Robert Hugh', reeve, render account for £81 6 shilling 8.25pence of arrears from the previous year.
A4: Arrears | B4: 0 | C4: 0 | D4: 0 | F4: 0 | H4: All delivered to Sir Geoffrey, treasurer of Wolvesey.
A5: Arrears | B5: 0 | C5: 0 | D5: 0 | F5: 0 | H5: They are quit.
A6: Arrears | F6: 81.33 | G6: =F6-F3 -> 0 | H6: Total
A8: Rents of assize | B8: 1 | C8: 5 | D8: 0 | F8: 1.25 | H8: The same render account for £1 5 shilling for all rents of assize at Christmas.
A9: Rents of assize | B9: 1 | C9: 5 | D9: 0 | F9: 1.25 | H9: £1 5 shilling at Easter (22 April).
A10: Rents of assize | B10: 1 | C10: 5 | D10: 0 | F10: 1.25 | H10: £1 5 shilling at the feast of St John the Baptist (24 June).
A11: Rents of assize | B11: 1 | C11: 8 | D11: 0.5 | F11: 1.4 | H11: £1 8 shilling 0.5pence at Michaelmas (29 September).
A12: Rents of assize | B12: 5 | C12: 3 | D12: 0.5 | F12: 5.15 | H12: Total, £5 3 shilling 0.5pence
A13: Rents of assize | F13: 5.15 | G13: 0 | H13: Total
A15: Quittances | B15: 0 | C15: 3 | D15: 0 | F15: 0.15 | H15: In quittance of 1 reeve for the year 3 shilling.
A16: Quittances | B16: 0 | C16: 2 | D16: 6 | F16: 0.12 | H16: 1 ploughman for the year 2 shilling 6pence.
A17: Quittances | B17: 0 | C17: 2 | D17: 6 | F17: 0.12 | H17: one shepherd for the year 2 shilling 6pence
A18: Quittances | B18: 0 | C18: 8 | D18: 0 | F18: =B18+C18/20+D18/240 -> 0.4 | H18: Total, 8 shilling
A19: Quittances | F19: =SUM(F15:F17) -> 0.39 | G19: =F19-F18 -> -0.01 | H19: Total
A21: Total of rents remaining | B21: 4 | C21: 15 | D21: 0 | F21: 4.75 | H21: Total of rents remaining, £4 15 shilling .5pence
A22: Total of rents remaining | F22: 4.75 | G22: =F22-F21 -> 0 | H22: Total
A24: Cumin | B24: 0 | C24: 0 | D24: 0 | F24: 0 | H24: The same render account for 1 lb of cumin from Geoffrey Kynhow for annual recognizance.
A25: Cumin | B25: 0 | C25: 0 | D25: 0 | F25: 0 | H25: all delivered to Sir Geoffrey, treasurer of Wolvesey.
A26: Cumin | F26: 0 | G26: 0 | H26: Total
A28: Recognizance | B28: 0 | C28: 0 | D28: 3 | F28: 0.01 | H28: The same render account for 3pence from Henry Burrith' for annual recognizance.
A29: Recognizance | B29: 0 | C29: 0 | D29: 3 | F29: 0.01 | H29: Total, 3pence
A30: Recognizance | F30: 0.01 | G30: 0 | H30: Total
A32: Issues | B32: 0 | C32: 14 | D32: 5.25 | F32: 0.72 | H32: The same render account for 14 shilling 5.25pence from the small tithes of lambs this year.
A33: Issues | B33: 0 | C33: 14 | D33: 3.5 | F33: 0.71 | H33: 14 shilling 3.5pence from the small tithes of milk, wool, foals and calves this year.
A34: Issues | B34: 0 | C34: 0 | D34: 0 | F34: 0 | H34: nothing from coarse wool from the demesne or tithes here because it is sent to Wolvesey.
A35: Issues | B35: 0 | C35: 2 | D35: 3 | F35: 0.11 | H35: 2 shilling 3pence from 2 cloves 4 lb of wool locks sold, at 10.5pence a clove.
A36: Issues | B36: 0 | C36: 18 | D36: 7.5 | F36: 0.93 | H36: 18 shilling 7.5pence from 2 weys 2 cloves of cheese from tithes sold, at 9 shilling a wey.
A37: Issues | B37: 0 | C37: 2 | D37: 0 | F37: 0.1 | H37: 2 shilling from 2 branches of wood sold.
A38: Issues | B38: 0 | C38: 6 | D38: 8 | F38: 0.33 | H38: 6 shilling 8pence from pigeons sold.
A39: Issues | B39: 0 | C39: 6 | D39: 6 | F39: 0.33 | H39: 6 shilling 6pence from 26 geese from tithes sold.
A40: Issues | B40: 0 | C40: 1 | D40: 0 | F40: 0.05 | H40: 1 shilling from the pasturage on this side of the field of la Hyde sold, because it was all sown with wheat.
A41: Issues | B41: 0 | C41: 3 | D41: 0 | F41: 0.15 | H41: 3 shilling from .the pasturage of Otlond' sold this year.
A42: Issues | B42: 0 | C42: 0 | D42: 0 | F42: 0 | H42: nothing from the pasturage of Schortebond' because it was fallow.
A43: Issues | B43: 0 | C43: 1 | D43: 0 | F43: 0.05 | H43: 1 shilling from the pasturage of Wodebrech sold this year.
... A58: Issues | B58: 8 | C58: 19 | D58: 2.75 | F58: 8.96 | H58: Total, £8 19 shilling 2.75pence
A59: Issues | F59: =SUM(F32:F57) -> 8.96 | G59: =F59-F58 -> 0 | H59: Total
A61: Sale of corn from the demesne | B61: 7 | C61: 4 | D61: 5.5 | F61: 7.22 | H61: The same render account for £7 4 shilling 5.5pence from 25 quarters 1 bushels of wheat sold, at 5 shilling a qr for 8 quarters 5 bushels, 5 shilling 4pence a qr for 6.5 quarters, and 6 shilling 8pence a qr for 10 quarters.
A62: Sale of corn from the demesne | B62: 2 | C62: 12 | D62: 10.5 | F62: 2.64 | H62: £2 12 shilling 10.5pence from 18 quarters 7 bushels of bere sold, at 2 shilling 8pence a qr for 11 quarters 2 bushels, and 3 shilling a qr for 7 quarters 5 bushels.
A63: Sale of corn from the demesne | B63: 0 | C63: 10 | D63: 0 | F63: 0.5 | H63: 10 shilling from 2.5 quarters of barley sold, at 4 shilling a qr.
A64: Sale of corn from the demesne | B64: 10 | C64: 7 | D64: 4 | F64: 10.37 | H64: Total, £10 7 shilling 4pence
A65: Sale of corn from the demesne | F65: 10.36 | G65: -0.01 | H65: Total
A67: Sale of corn from tithes | B67: 20 | C67: 3 | D67: 7.5 | F67: 20.18 | H67: The same render account for £20 3 shilling 7.5pence from 65 quarters 7 bushels of wheat from tithes sold, at 5 shilling a qr for 9 quarters 1 bushels, 5 shilling 4pence a qr for 15 quarters 2 bushels, and 6 shilling 8pence a qr for 41.5 quarters.
A68: Sale of corn from tithes | B68: 1 | C68: 19 | D68: 7 | F68: 1.98 | H68: £1 19 shilling 7pence from 14 quarters 7 bushels of bere sold, at 2 shilling 8pence a qr.
A69: Sale of corn from tithes | B69: 7 | C69: 13 | D69: 6 | F69: 7.68 | H69: £7 13 shilling 6pence from 38 quarters 3 bushels of barley sold, at 4 shilling a qr.
A70: Sale of corn from tithes | B70: 5 | C70: 18 | D70: 1.5 | F70: 5.91 | H70: £5 18 shilling 1.5pence from 64 quarters of oats sold, at 1 shilling 8pence a qr for 44 quarters 7 bushels, 2 shilling 2pence a qr for 7 quarters 6 bushels, and 2 shilling 4pence a qr for 11 quarters 3 bushels.
A71: Sale of corn from tithes | B71: 1 | C71: 12 | D71: 4 | F71: 1.62 | H71: £1 12 shilling 4pence from 12 quarters 1 bushels of beans sold, at 2 shilling 8pence a qr.
A72: Sale of corn from tithes | B72: 0 | C72: 4 | D72: 0 | F72: 0.2 | H72: 4 shilling from 2 quarters of peas sold.
A73: Sale of corn from tithes | B73: 0 | C73: 12 | D73: 1 | F73: 0.6 | H73: 12 shilling 1pence from 7 quarters 2 bushels of vetches sold, at 1 shilling 8pence a qr.
A74: Sale of corn from tithes | B74: 38 | C74: 3 | D74: 4 | F74: 38.17 | H74: Total, £38 3 shilling 4pence
A75: Sale of corn from tithes | F75: 38.17 | G75: 0 | H75: Total
A77: Froxfield, Steep and Oxeschete | B77: 38 | C77: 0 | D77: 0 | F77: 38 | H77: The same render account for £38 from the tithes of corn from the chapels of Froxfield, Steep and Oxeshete sold wholesale.
A78: Froxfield, Steep and Oxeschete | B78: 38 | C78: 0 | D78: 0 | F78: 38 | H78: Total, £38.
A79: Froxfield, Steep and Oxeschete | F79: 38 | G79: 0 | H79: Total
A81: Bykeden' and Yteden' | B81: 0 | C81: 14 | D81: 0 | F81: 0.7 | H81: The same render account for 14 shilling from the tithes of corn from Bykeden' sold.
A82: Bykeden' and Yteden' | B82: 1 | C82: 0 | D82: 0 | F82: 1 | H82: £1 from the tithes of corn from Yteden' sold.
A83: Bykeden' and Yteden' | B83: 0 | C83: 7 | D83: 0 | F83: =B83+C83/20+D83/240 -> 0.35 | H83: 7 shilling from the tithes of corn from Gerard de Tygehale solpence
A84: Bykeden' and Yteden' | B84: 2 | C84: 1 | D84: 0 | F84: 2.05 | H84: Total, £2 1 shilling
A85: Bykeden' and Yteden' | F85: =SUM(F81:F83) -> 2.05 | G85: =F85-F84 -> 0 | H85: Total
A87: All corn | B87: 88 | C87: 1 | D87: 8 | F87: =B87+C87/20+D87/240 -> 88.083333 | H87: Total of all the corn from the demesne as well as from tithes sold wholesale, £88 1 shilling 8pence
A89: Entry and marriage fines | B89: 0 | C89: 4 | D89: 0 | F89: 0.2 | H89: The same render account for 4 shilling from the tithing for tithingpenny at the hundred-court of Martinmas.
A90: Entry and marriage fines | B90: 0 | C90: 4 | D90: 0 | F90: 0.2 | H90: 4 shilling from the tithing for tithingpenny at the hundred-court of Hockday.
A91: Entry and marriage fines | B91: 1 | C91: 0 | D91: 0 | F91: 1 | H91: £1 from Alice, relict of William Cocus de Pydeham, to retain 1 messuage and 1 virgate of land which belonged to her husbanpence
A92: Entry and marriage fines | B92: 1 | C92: 8 | D92: 0 | F92: =B92+C92/20+D92/240 -> 1.4 | H92: Total, £1 8 shilling
A93: Entry and marriage fines | F93: 1.4 | G93: =F93-F92 -> 0 | H93: Total
A95: Perquisites | B95: 1 | C95: 3 | D95: 6 | F95: 1.17 | H95: The same render account for £1 3 shilling 6pence from small perquisites from various men this year for various transgressions.
A96: Perquisites | B96: 1 | C96: 3 | D96: 6 | F96: 1.17 | H96: Total, £1 3 shilling 6pence
A98: Perquisites & entry and marriage fines | B98: 2 | C98: 11 | D98: 6 | F98: 2.57 | G98: =F98-(F96+F93) -> 0 | H98: Total of both, £2 11 shilling 6pence
A100: Total of all receipts | C100: 104 | D100: 17 | E100: 8.25 | F100: 104.88 | H100: Total of all receipts, £104 17 shilling 8.25pence
A102: Total of all receipts recorded in accounts | F102: =F100 -> 104.88
A103: Total cross-check without arrears | F103: =F96+F93+F87+F59+F30+F26+F22 -> 104.37333 | G103: =F103-F102 -> -0.50666667
A104: Total cross-check with arrears | F104: =F103+F6 -> 185.70333

Sheet Expenses
A1: EAST MEON CHURCH EXPENSES
A2: Heading | B2: £ | C2: s | D2: d | F2: Total in £ | G2: Error | H2: Notes | J2: Fixed investment | K2: Demesne fixed investment
A3: Cost of ploughs | B3: 0 | C3: 1 | D3: 8 | F3: 0.08 | H3: In ironwork of 1 horse-plough for the year 1 shilling 8pence. | J3: =F3 -> 0.08 | K3: =F3 -> 0.08
A4: Cost of ploughs | B4: 0 | C4: 1 | D4: 0 | F4: 0.05 | H4: stipend of the smith forging the ironwork 1 shilling. | J4: =F4 -> 0.05 | K4: =F4 -> 0.05
A5: Cost of ploughs | B5: 0 | C5: 0 | D5: 8.5 | F5: 0.04 | H5: 1 ploughshare bought 8.5pence. | J5: =F5 -> 0.04 | K5: =F5 -> 0.04
A6: Cost of ploughs | B6: 0 | C6: 0 | D6: 3.5 | F6: 0.01 | H6: 1 plough foot bought 3.5pence. | J6: =F6 -> 0.01 | K6: =F6 -> 0.01
A7: Cost of ploughs | B7: 0 | C7: 0 | D7: 8 | F7: 0.03 | H7: making and mending ploughs and harrows 8pence. | J7: =F7 -> 0.03 | K7: =F7 -> 0.03
A8: Cost of ploughs | B8: 0 | C8: 0 | D8: 4 | F8: 0.02 | H8: 1 pair of wheels bought for the same 4pence. | J8: =F8 -> 0.02 | K8: =F8 -> 0.02
A9: Cost of ploughs | B9: 0 | C9: 0 | D9: 10 | F9: 0.04 | H9: 1 coulter made anew with iron bought for the same 10pence. | J9: =F9 -> 0.04 | K9: =F9 -> 0.04
A10: Cost of ploughs | B10: 0 | C10: 0 | D10: 1.5 | F10: 0.01 | H10: 6 halters made from the horses' own hair 1.5pence. | J10: =F10 -> 0.01 | K10: =F10 -> 0.01
A11: Cost of ploughs | B11: 0 | C11: 0 | D11: 8 | F11: 0.03 | H11: stipend of 1 harrower at both sowings 8pence. | J11: =F11 -> 0.03 | K11: =F11 -> 0.03
A12: Cost of ploughs | B12: 0 | C12: 0 | D12: 9 | F12: 0.04 | H12: shoeing 6 plough-horses for the year 9pence. | J12: =F12 -> 0.04 | K12: =F12 -> 0.04
A13: Cost of ploughs | B13: 0 | C13: 0 | D13: 1 | F13: 0 | H13: fastening the same 1pence Delivered to 1 ploughman for 0.5 ewe at Martinmas according to custom 1.5pence. | J13: =F13 -> 0 | K13: =F13 -> 0
A14: Cost of ploughs | B14: 0 | C14: 3 | D14: 0 | F14: 0.15 | H14: stipend of 1 stot-keeper for the year 3 shilling.
A15: Cost of ploughs | B15: 0 | C15: 12 | D15: 6 | F15: =B15+C15/20+D15/240 -> 0.625 | H15: 1 plough-horse bought 12 shilling 6pence
A16: Cost of ploughs | B16: 1 | C16: 2 | D16: 9 | F16: 1.14 | H16: Total, £1 2 shilling 9pence
A17: Cost of ploughs | F17: =SUM(F3:F15) -> 1.125 | G17: =F17-F16 -> -0.015 | H17: Total
A19: Cost of carts | B19: 0 | C19: 0 | D19: 10 | F19: 0.04 | H19: In 1 pair of wheels made from the lord's timber 10pence. | J19: =F19 -> 0.04 | K19: =J19 -> 0.04
A20: Cost of carts | B20: 0 | C20: 12 | D20: 6 | F20: 0.62 | H20: 1 new binding, with clamps and large and small nails bought for the same, and with the stipend of the smith putting the said binding on the said wheels, 12 shilling 6pence. | J20: =F20 -> 0.62 | K20: =J20 -> 0.62
A21: Cost of carts | B21: 0 | C21: 0 | D21: 2 | F21: 0.01 | H21: hooping the hubs of the cart with iron 2pence. | J21: =F21 -> 0.01 | K21: =J21 -> 0.01
A22: Cost of carts | B22: 0 | C22: 0 | D22: 2 | F22: 0.01 | H22: fitting the cart with axles at various times 2pence. | J22: =F22 -> 0.01 | K22: =J22 -> 0.01
A23: Cost of carts | B23: 0 | C23: 1 | D23: 0 | F23: 0.05 | H23: white leather bought for mending harnesses 1 shilling. | J23: =F23 -> 0.05 | K23: =J23 -> 0.05
A24: Cost of carts | B24: 0 | C24: 0 | D24: 6 | F24: 0.03 | H24: grease bought 6pence. | J24: =F24 -> 0.03 | K24: =J24 -> 0.03
A25: Cost of carts | B25: 0 | C25: 2 | D25: 0 | F25: 0.1 | H25: shoeing 2 cart-horses for the year 2 shilling. | J25: =F25 -> 0.1 | K25: =J25 -> 0.1
A26: Cost of carts | B26: 0 | C26: 3 | D26: 4 | F26: 0.17 | H26: stipend of 1 carter for the year 3 shilling 4pence.
A27: Cost of carts | B27: 0 | C27: 16 | D27: 7 | F27: =B27+C27/20+D27/240 -> 0.82916667 | H27: 1 cart-horse bought 16 shilling 7pence
A28: Cost of carts | B28: 1 | C28: 17 | D28: 1 | F28: 1.85 | H28: Total, £1 17 shilling 1pence
A29: Cost of carts | F29: =SUM(F19:F27) -> 1.8591667 | G29: =F29-F28 -> 0.0091666667 | H29: Total
A31: Sheepfold and sheepcote | B31: 0 | C31: 0 | D31: 3 | F31: 0.01 | H31: In 9 hurdles made for the fold 3pence. | J31: =F31 -> 0.01 | K31: =J31 -> 0.01
A32: Sheepfold and sheepcote | B32: 0 | C32: 0 | D32: 7 | F32: 0.03 | H32: wattling 22 hurdles 7pence, at 1pence per 3 hurdles. | J32: =F32 -> 0.03 | K32: =J32 -> 0.03
A33: Sheepfold and sheepcote | B33: 0 | C33: 3 | D33: 2 | F33: 0.16 | H33: grease bought for greasing sheep 3 shilling 2pence. | J33: =F33 -> 0.16 | K33: =J33 -> 0.16
A34: Sheepfold and sheepcote | B34: 0 | C34: 3 | D34: 3 | F34: 0.16 | H34: 13 ells of canvas bought for putting wool in 3 shilling 3pence, at 3pence an ell. | J34: =F34 -> 0.16 | K34: =J34 -> 0.16
A35: Sheepfold and sheepcote | B35: 0 | C35: 0 | D35: 6 | F35: =B35+C35/20+D35/240 -> 0.025 | H35: making sacks for the wool with thread bought for the same 6pence | J35: =F35 -> 0.025 | K35: =J35 -> 0.025
A36: Sheepfold and sheepcote | B36: 0 | C36: 7 | D36: 9 | F36: =B36+C36/20+D36/240 -> 0.3875 | H36: Total, 7 shilling 9pence
A38: Cost of buildings | B38: 0 | C38: 2 | D38: 0 | F38: 0.1 | H38: In re-roofing the bailiff's stable and the cart-horses' stable in places 2 shilling. | J38: =F38 -> 0.1 | K38: =J38 -> 0.1
A39: Cost of buildings | B39: 0 | C39: 0 | D39: 8 | F39: 0.03 | H39: repairing and restoring the mangers of the said stables 8pence. | J39: =F39 -> 0.03 | K39: =J39 -> 0.03
A40: Cost of buildings | B40: 0 | C40: 2 | D40: 0 | F40: 0.1 | H40: re-roofing and mending in places the unroofed building of the press 2 shilling. | J40: =F40 -> 0.1 | K40: =J40 -> 0.1
A41: Cost of buildings | B41: 0 | C41: 1 | D41: 0 | F41: 0.05 | H41: re-roofing and mending the granary in places 1 shilling. | J41: =F41 -> 0.05 | K41: =J41 -> 0.05
A42: Cost of buildings | B42: 0 | C42: 0 | D42: 6 | F42: 0.03 | H42: 100 large nails and other small nails bought for the same 6pence. | J42: =F42 -> 0.03 | K42: =J42 -> 0.03
A43: Cost of buildings | B43: 1 | C43: 1 | D43: 5 | F43: 1.07 | H43: building anew 1 building for stabling the cart-horses and carts, £1 1 shilling 5pence for all costs. | J43: =F43 -> 1.07 | K43: =J43 -> 1.07
A44: Cost of buildings | B44: 0 | C44: 1 | D44: 0 | F44: 0.05 | H44: making and mending the bench in the great hall 1 shilling. | J44: =F44 -> 0.05 | K44: =J44 -> 0.05
A45: Cost of buildings | B45: 0 | C45: 0 | D45: 5 | F45: 0.02 | H45: mending the walls of the dairy and the door of the same building 5pence. | J45: =F45 -> 0.02 | K45: =J45 -> 0.02
A46: Cost of buildings | B46: 0 | C46: 0 | D46: 10.5 | F46: 0.04 | H46: mending the barn-door and likewise the gate of the curia with nails bought for the same 10.5pence. | J46: =F46 -> 0.04 | K46: =J46 -> 0.04
A47: Cost of buildings | B47: 1 | C47: 1 | D47: 0 | F47: 1.05 | H47: 9 empty casks bought £1 1 shilling, at 2 shilling 4pence each. | J47: =F47 -> 1.05 | K47: =J47 -> 1.05
A48: Cost of buildings | B48: 0 | C48: 1 | D48: 6 | F48: 0.08 | H48: hooping and mending these and others 1 shilling 6pence. | J48: =F48 -> 0.08 | K48: =J48 -> 0.08
A49: Cost of buildings | B49: 0 | C49: 0 | D49: 5 | F49: 0.02 | H49: hooping and mending tubs and barrows 5pence. | J49: =F49 -> 0.02 | K49: =J49 -> 0.02
... A51: Cost of buildings | B51: 0 | C51: 0 | D51: 4 | F51: 0.02 | H51: tallow and soap bought for the press 4pence. | J51: =F51 -> 0.02 | K51: =J51 -> 0.02
A52: Cost of buildings | B52: 0 | C52: 0 | D52: 0.25 | F52: =B52+C52/20+D52/240 -> 0.0010416667 | H52: 1 sieve bought for straining cider 0.25pence | J52: =F52 -> 0.0010416667 | K52: =J52 -> 0.0010416667
A53: Cost of buildings | B53: 2 | C53: 17 | D53: 2.25 | F53: 2.86 | H53: Total, £2 17 shilling 2.25pence
A54: Cost of buildings | F54: =SUM(F38:F52) -> 2.8810417 | G54: =F54-F53 -> 0.021041667 | H54: Total
A56: Threshing | B56: 0 | C56: 17 | D56: 5 | F56: 0.87 | H56: In threshing and winnowing 38 quarters 5 bushels of wheat from the demesne and 65 quarters 7 bushels of wheat from tithes by piece-work 17 shilling 5pence, at 2pence a struck quarter.
A57: Threshing | B57: 0 | C57: 11 | D57: 0.5 | F57: =B57+C57/20+D57/240 -> 0.55208333 | H57: threshing and winnowing 26 quarters 1 bushels of bere and 21 quarters' 6 bushels of barley from the demesne, and 14 quarters 7 bushels of bere, 38 quarters 3 bushels of barley and 9 quarters 2 bushels of peas and vetches from tithes, 11 shilling .5pence, at 1.5pence per 10 struck bushels.
A58: Threshing | B58: 0 | C58: 2 | D58: 0.25 | F58: =B58+C58/20+D58/240 -> 0.10104167 | H58: threshing and winnowing 12 quarters 1 bushels of beans by piece-work 2 shilling .25pence, at 2pence a struck quarter.
A59: Threshing | B59: 0 | C59: 8 | D59: 7.25 | F59: 0.43 | H59: threshing and winnowing, 65 quarters 2 bushels of oats from the demesne and 64 quarters of oats from tithes 8 shilling 7.25pence at 1pence per 10 struck bushels.
A60: Threshing | B60: 1 | C60: 19 | D60: 1 | F60: 1.95 | H60: Total, £1 19 shilling 1pence
A61: Threshing | F61: =SUM(F56:F59) -> 1.953125 | G61: =F61-F60 -> 0.003125 | H61: Total
A63: Harvest-time | B63: 1 | C63: 1 | D63: 5 | F63: 1.07 | H63: In bread and herrings, and cheese for a want of herrings, bought for 17 boon-works and 7 carrying-services of 615 men with the customary tenants who reaped, bound and carried all the corn, £1 1 shilling 5pence.
A64: Harvest-time | B64: 0 | C64: 2 | D64: 0 | F64: 0.1 | H64: stipend of 1 hayward at harvest-time 2 shilling
A65: Harvest-time | B65: 1 | C65: 3 | D65: 5 | F65: 1.17 | H65: Total, £1 3 shilling 5pence
A66: Harvest-time | F66: =SUM(F63:F64) -> 1.17 | G66: =F66-F65 -> 0 | H66: Total
A68: Also harvest-time | B68: 0 | C68: 15 | D68: 0 | F68: 0.75 | H68: In stipend of 3 riders this year, of whom 1 stayed for 36 days, 1 for 40 days, and 1 for 45 days, 15 shilling.
A69: Also harvest-time | B69: 0 | C69: 16 | D69: 0 | F69: 0.8 | H69: expenses of the same for the same time 16 shilling.
A70: Also harvest-time | B70: 0 | C70: 0 | D70: 9 | F70: 0.04 | H70: shoeing the horses of the same 9pence. | J70: =F70 -> 0.04 | K70: =J70 -> 0.04
A71: Also harvest-time | B71: 1 | C71: 15 | D71: 6 | F71: 1.77 | H71: expenses of 9 of the bishop's servants (pedon') and 2 stackers £1 15 shilling 6pence.
A72: Also harvest-time | B72: 0 | C72: 18 | D72: 4 | F72: 0.92 | H72: stipend of the same 18 shilling 4pence, or 1 shilling 8pence each.
A73: Also harvest-time | B73: 0 | C73: 0 | D73: 0 | F73: 0 | H73: And note that there is 1 servant fewer this year because the corn of Yteden' and Bykeden' was sold wholesale before the harvest.
A74: Also harvest-time | B74: 0 | C74: 1 | D74: 6 | F74: 0.08 | H74: 3 pairs of wheels made for carrying the corn from tithes 1 shilling 6pence. | J74: =F74 -> 0.08 | K74: =J74 -> 0.08
A75: Also harvest-time | B75: 0 | C75: 0 | D75: 6 | F75: 0.03 | H75: fitting the same with axles 6pence. | J75: =F75 -> 0.03 | K75: =J75 -> 0.03
A76: Also harvest-time | B76: 0 | C76: 2 | D76: 2 | F76: 0.11 | H76: 4 collars bought 2 shilling 2pence. | J76: =F76 -> 0.11 | K76: =J76 -> 0.11
A77: Also harvest-time | B77: 0 | C77: 1 | D77: 10 | F77: 0.09 | H77: clouts, nails and grease bought 1 shilling 10pence. | J77: =F77 -> 0.09 | K77: =J77 -> 0.09
A78: Also harvest-time | B78: 0 | C78: 2 | D78: 6 | F78: 0.12 | H78: shoeing the plough-horses hauling the carts 2 shilling 6pence. | J78: =F78 -> 0.12 | K78: =J78 -> 0.12
A79: Also harvest-time | B79: 0 | C79: 1 | D79: 0 | F79: 0.05 | H79: treating the carts before the harvest 1 shilling. | J79: =F79 -> 0.05 | K79: =J79 -> 0.05
A80: Also harvest-time | B80: 0 | C80: 2 | D80: 4 | F80: 0.12 | H80: hiring carters this year to help carry the corn at various times 2 shilling 4pence.
A81: Also harvest-time | B81: 0 | C81: 5 | D81: 4 | F81: 0.27 | H81: 4 quarters of oats bought for the fodder of the riders' horses 5 shilling 4pence, at 1 shilling 4pence a quarters.
A82: Also harvest-time | B82: 5 | C82: 4 | D82: 9 | F82: 5.24 | H82: Total, £5 4 shilling 9pence
A84: Total of all expenses | B84: 14 | C84: 12 | D84: 0.25 | F84: 14.6 | H84: Total of all expenses, £14 12 shilling 0.25pence
A85: Total of all expenses | F85: 14.6 | G85: =F85-F84 -> 0 | H85: Total
A87: And thus he owes | B87: 90 | C87: 5 | D87: 8 | F87: 90.28 | H87: And thus he owes, £90 5 shilling 8pence
A88: And thus he owes | B88: 43 | C88: 0 | D88: 0 | F88: 43 | H88: Delivered to Sir Geoffrey, treasurer of Wolvesey, by 1 tally, £43.
A91: And thus he owes clear | B91: 47 | C91: 5 | D91: 8 | F91: 47.28 | H91: And thus he owes clear, £47 5 shilling 8pence
A94: Total of all expenses per account | F94: =F85 -> 14.6
A95: Total of all expenses (calculated here) | F95: =F82+F66+F61+F54+F29+F36+F17 -> 14.615833 | G95: =F95-F94 -> 0.015833333
A96: Total fixed investment | F96: =SUM(J3:J82) -> 4.9960417
A97: Total Demesne fixed investment | F97: =SUM(K3:K81) -> 4.9960417

Sheet Issues of the Grange
A1: Gross Output | B1: Total Quantity | C1: Account Total Quarters | D1: Bought in Total Quarters | E1: Received from tithes | F1: Sold Total Quarters | G1: Difference Produced+Bought-Sold | H1: Weighted Average Price per Quarter | I1: Value of Total Production weighted
A2: wheat | B2: =C2+D2+E2 -> 104.5 | C2: =38+5/8 -> 38.625 | D2: 0 | E2: =65+7/8 -> 65.875 | F2: =25+1/8+E2 -> 91 | G2: =B2-F2 -> 13.5 | H2: 0.28 | I2: =H2*B2 -> 29.26 | J2: prices taken from East Meon
A3: bere | B3: =C3+D3+E3 -> 41 | C3: 26.125 | D3: 0 | E3: =14.5+3/8 -> 14.875 | F3: =18+7/8+E3 -> 33.75 | G3: =B3-F3 -> 7.25 | H3: 0.16666667 | I3: =H3*B3 -> 6.8333333 | J3: prices taken from Droxford
A4: barley | B4: =C4+D4+E4 -> 60.125 | C4: 21.75 | D4: 0 | E4: =38+3/8 -> 38.375 | F4: =2.5/8+E4 -> 38.6875 | G4: =B4-F4 -> 21.4375 | H4: 0.19366812 | I4: =H4*B4 -> 11.644296 | J4: prices taken from East Meon
A5: oats | B5: =C5+D5+E5 -> 129.5 | C5: 65.5 | D5: 0 | E5: =64 -> 64 | F5: =65+1/8+E5 -> 129.125 | G5: =B5-F5 -> 0.375 | H5: 0.10320396 | I5: =H5*B5 -> 13.364913 | J5: prices taken from East Meon
A6: beans | B6: =C6+D6+E6 -> 12.125 | C6: 0 | D6: 0 | E6: =12+1/8 -> 12.125 | F6: =E6 -> 12.125 | G6: =B6-F6 -> 0 | H6: =2/20+8/240 -> 0.13333333 | I6: =H6*B6 -> 1.6166667
A7: peas | B7: =C7+D7+E7 -> 2 | C7: 0 | D7: 0 | E7: =2 -> 2 | F7: =E7 -> 2 | G7: =B7-F7 -> 0 | H7: 0.15 | I7: =H7*B7 -> 0.3 | J7: prices from Bishops Sutton
A8: vetches | B8: =C8+D8+E8 -> 7.25 | C8: 0 | D8: 0 | E8: =7+2/8 -> 7.25 | F8: =E8 -> 7.25 | G8: =B8-F8 -> 0 | H8: 0.1 | I8: =H8*B8 -> 0.725 | J8: prices from Bishops Sutton
A10: Total Production | I10: =SUM(I2:I8) -> 63.744209
A11: Sales of corn (as recorded in accounts)
A14: Net output | B14: Gross output | C14: Seed quarters | D14: Seed bushels | E14: Seed total quarters | F14: tithe quarters | G14: tithe bushels | H14: tithe total | I14: manorial servants quarters | J14: manorial servants bushels | K14: manorial servants total quarters | L14: output net of tithe, seed, liveries | M14: in stock from last year | N14: Price in £ | O14: Value of net output in £ | P14: Value of sales (in "Sale of Corn") in £
A15: wheat | B15: =B2 -> 104.5 | C15: 9.5 | E15: =C15+D15/8 -> 9.5 | I15: 4 | K15: =I15+J15/8 -> 4 | L15: =B15-E15-K15 -> 91 | N15: =H2 -> 0.28 | O15: =N15*L15 -> 25.48
A16: bere | B16: =B3 -> 41 | C16: 7 | D16: 2 | E16: =C16+D16/8 -> 7.25 | K16: =I16+J16/8 -> 0 | L16: =B16-E16-K16 -> 33.75 | N16: =H3 -> 0.16666667 | O16: =N16*L16 -> 5.625
A17: barley | B17: =B4 -> 60.125 | C17: 6 | D17: 2 | E17: =C17+D17/8 -> 6.25 | I17: 13 | K17: =I17+J17/8 -> 13 | L17: =B17-E17-K17 -> 40.875 | N17: =H4 -> 0.19366812 | O17: =N17*L17 -> 7.9161845
A18: oats | B18: =B5 -> 129.5 | C18: 26.5 | E18: =C18+D18/8 -> 26.5 | I18: =19+17.5+0.5+1.5 -> 38.5 | J18: =1 -> 1 | K18: =I18+J18/8 -> 38.625 | L18: =B18-E18-K18 -> 64.375 | N18: =H5 -> 0.10320396 | O18: =N18*L18 -> 6.6437552
A19: beans | B19: =B6 -> 12.125 | E19: =C19+D19/8 -> 0 | K19: =I19+J19/8 -> 0 | L19: =B19-E19-K19 -> 12.125 | N19: =H6 -> 0.13333333 | O19: =N19*L19 -> 1.6166667
A20: peas | B20: =B7 -> 2 | E20: =C20+D20/8 -> 0 | K20: =I20+J20/8 -> 0 | L20: =B20-E20-K20 -> 2 | N20: =H7 -> 0.15 | O20: =N20*L20 -> 0.3
A21: vetches | B21: =B8 -> 7.25 | E21: =C21+D21/8 -> 0 | K21: =I21+J21/8 -> 0 | L21: =B21-E21-K21 -> 7.25 | N21: =H8 -> 0.1 | O21: =N21*L21 -> 0.725
A23: Total | O23: =SUM(O15:O21) -> 48.306606

Sheet Issues of the Mills

Sheet Stock
A1: EAST MEON CHURCH STOCK ACCOUNT
C3: added | G3: subtracted
A4: Livestock | B4: Inherited stock | C4: added | D4: strays | E4: herbage | F4: churchscot | G4: of which in default | H4: sold | I4: in murrain | J4: accounted for elsewhere | K4: End-period stock | L4: cross-check | M4: stock building | N4: raw production | O4: Unit price (£) | P4: Value of stock (£) at given value | Q4: Value of stock (£) at sales prices | R4: Sales in (£) | S4: Value of stock building (£) | T4: Value of production (£) at sales prices | U4: Details
A5: Cart-horses | B5: 3 | C5: 1 | J5: 1 | K5: 2
A6: Mares
A7: Plough horses | B7: 6 | C7: 1 | H7: 1 | K7: 7 | O7: =R7/H7 -> 0.2 | R7: =Receipts!F48 -> 0.2
A8: Colts (unspecified years)
A9: Colts (2 years)
A10: Colts (1 year)
A11: Foals
A12: Oxen | B12: 1 | K12: 1
A13: Bulls
A14: Cows
A15: Steers
A16: Bullocks
A17: Yearlings
A18: Calves
A19: Wethers | B19: 205 | C19: 50 | H19: 5 | I19: =20+21 -> 41 | K19: 209 | O19: =R19/H19 -> 0.05 | R19: =Receipts!F49 -> 0.25
A20: Rams
A21: Ewes
A22: Hoggs
A23: Lambs | B23: 150 | C23: 29 | H23: 121 | O23: =R23/H23 -> 0.015619835 | R23: =Receipts!F50 -> 1.89
A24: Boars
A25: Sows
A26: Pigs
A27: Hoggets
A28: Piglets | C28: 9 | I28: 1 | J28: 8 | K28: 0
A29: Swans
A30: Peacocks
A31: Total Value | R31: =SUM(R5:R30) -> 2.34
A34: Wool
A35: fleeces | C35: 180 | J35: 180 | O35: 0.02 | T35: =O35*J35 -> 3.6
A36: Coarse wool
A37: Lamb's wool
A38: Wool locks
A39: Wool sold at shearing
A40: Total wool | R40: 0 | T40: =SUM(T35:T39) -> 3.6
A43: Hides
A44: Ox hides
A45: Mare
A46: Steer
A47: calves
A48: pigs
A49: Woolskins (incl. 10 in tithe)
A50: wethers
A51: rams
A52: ewes
A53: hoggs
A54: Woolskins (excl. 10 in tithe)
... A67: Poultry stock
A68: Hens | F68: 38 | G68: =1+1+1 -> 3 | H68: 35 | J68: 0 | O68: =R68/H68 -> 0.0042857143 | R68: =Receipts!F56 -> 0.15 | T68: =O68*F68 -> 0.16285714
A69: Geese | C69: 26 | H69: 26 | J69: 0 | O69: =R69/H69 -> 0.012692308 | R69: =Receipts!F39 -> 0.33 | T69: =O69*C69 -> 0.33
A70: Capons (from chickens)
A71: Pigeons | C71: 10 | H71: 10 | O71: =R71/H71 -> 0.033 | R71: =Receipts!F38 -> 0.33 | T71: =O71*C71 -> 0.33
A72: Cocks & hens
A73: Total poultry stock | R73: =SUM(R68:R72) -> 0.81
A74: Total poultry excluding churchscot | T74: =SUM(T69:T71) -> 0.66
A76: Poultry production
A77: Eggs
A78: Cocks & hens from churchscot of customary tenants | F78: 38 | G78: 3 | H78: 35 | O78: =R78/H78 -> 0.0042857143 | R78: =Receipts!F56 -> 0.15 | T78: =O78*H78 -> 0.15
A79: Sum of above
A80: Total | R80: =SUM(R77:R79) -> 0.15 | T80: =T78 -> 0.15
A83: Meat
A84: Beef
A85: Mutton
A86: Pork
A87: Total
A89: Cheese
A90: Winter cheese
A91: Summer cheese | C91: 2 weys 2 cloves | H91: 2 weys 2 cloves | R91: =Receipts!F36 -> 0.93 | T91: =R91 -> 0.93
A92: Total | R92: =SUM(R90:R91) -> 0.93 | T92: =T91 -> 0.93
A94: Butter
A95: Butter
A96: Total
A98: Total Dairy Sales
A101: Cider
A102: CIder | B102: 3 | C102: 12 | H102: 3 | K102: 12 | O102: =R102/H102 -> 0.75 | R102: =Receipts!F55 -> 2.25 | T102: =R102 -> 2.25
A103: Cider | R103: =SUM(R102) -> 2.25 | T103: =T102 -> 2.25
A105: Additional Information (not necessarily useful)
A106: Utensils
A107: ploughs
A108: carts
A109: cart-ropes
A110: corn baskets
A111: seed-sacks
A112: seed basket
A113: locks for the doors
A114: lead vessel
A115: brass pots
A116: pans
... A131: brass posnets

Sheet raw data
A1: Heading | B1: Sentence | C1: Total in Pounds | D1: Pounds | E1: Shillings | F1: Pence | G1: Corn | H1: Total Quarters Except 1 | I1: Total Bushels Except 1 | J1: Total Corn Cross-Check | K1: Total Corn Manorial Account | L1: Corn Quantity Error | M1: Quarters 1 | N1: Bushels 1 | O1: Quarters 2 | P1: Bushels 2 | Q1: Quarters 3 | R1: Bushels 3 | S1: Quarters 4 | T1: Bushels 4 | U1: Quarters 5 | V1: Bushels 5 | W1: Quarters 6 | X1: Bushels 6 | Y1: shilling a quarter 1 | Z1: pence a quarter 1 | AA1: shilling a quarter 2 | AB1: pence a quarter 2 | AC1: shilling a quarter 3 | AD1: pence a quarter 3 | AE1: shilling a quarter 4 | AF1: pence a quarter 4 | AG1: shilling a bushel 1 | AH1: pence a bushel 1 | AI1: shilling a bushel 2 | AJ1: pence a bushel 2 | AK1: shilling a bushel 3 | AL1: pence a bushel 3 | AM1: shilling a bushel 4 | AN1: pence a bushel 4
A2: Arrears | B2: Nicholas de Ychen', bailiff, and Robert Hugh', reeve, render account for £81 6 shilling 8.25pence of arrears from the previous year. | C2: 81.33 | D2: 81 | E2: 6 | F2: 8.25 | H2: 0 | I2: 0 | J2: 0 | K2: 0 | L2: 0 | M2: 0 | N2: 0
A3: Arrears | B3: All delivered to Sir Geoffrey, treasurer of Wolvesey. | C3: 0 | D3: 0 | E3: 0 | F3: 0 | H3: 0 | I3: 0 | J3: 0 | K3: 0 | L3: 0 | M3: 0 | N3: 0
A4: Arrears | B4: They are quit. | C4: 0 | D4: 0 | E4: 0 | F4: 0 | H4: 0 | I4: 0 | J4: 0 | K4: 0 | L4: 0 | M4: 0 | N4: 0
A5: Rents of assize | B5: The same render account for £1 5 shilling for all rents of assize at Christmas. | C5: 1.25 | D5: 1 | E5: 5 | F5: 0 | H5: 0 | I5: 0 | J5: 0 | K5: 0 | L5: 0 | M5: 0 | N5: 0
A6: Rents of assize | B6: £1 5 shilling at Easter (22 April). | C6: 1.25 | D6: 1 | E6: 5 | F6: 0 | H6: 0 | I6: 0 | J6: 0 | K6: 0 | L6: 0 | M6: 0 | N6: 0
A7: Rents of assize | B7: £1 5 shilling at the feast of St John the Baptist (24 June). | C7: 1.25 | D7: 1 | E7: 5 | F7: 0 | H7: 0 | I7: 0 | J7: 0 | K7: 0 | L7: 0 | M7: 0 | N7: 0
A8: Rents of assize | B8: £1 8 shilling 0.5pence at Michaelmas (29 September). | C8: 1.4 | D8: 1 | E8: 8 | F8: 0.5 | H8: 0 | I8: 0 | J8: 0 | K8: 0 | L8: 0 | M8: 0 | N8: 0
A9: Rents of assize | B9: Total, £5 3 shilling 0.5pence | C9: 5.15 | D9: 5 | E9: 3 | F9: 0.5 | H9: 0 | I9: 0 | J9: 0 | K9: 0 | L9: 0 | M9: 0 | N9: 0
A10: Quittances | B10: In quittance of 1 reeve for the year 3 shilling. | C10: 0.15 | D10: 0 | E10: 3 | F10: 0 | H10: 0 | I10: 0 | J10: 0 | K10: 0 | L10: 0 | M10: 0 | N10: 0
A11: Quittances | B11: 1 ploughman for the year 2 shilling 6pence. | C11: 0.12 | D11: 0 | E11: 2 | F11: 6 | H11: 0 | I11: 0 | J11: 0 | K11: 0 | L11: 0 | M11: 0 | N11: 0
A12: Quittances | B12: one shepherd for the year 2 shilling 6pence Total, 8 shilling | C12: 0.12 | D12: 0 | E12: 2 | F12: 6 | H12: 0 | I12: 0 | J12: 0 | K12: 0 | L12: 0 | M12: 0 | N12: 0
A13: Total of rents remaining | B13: Total of rents remaining, £4 15 shilling .5pence | C13: 4.75 | D13: 4 | E13: 15 | F13: 0 | H13: 0 | I13: 0 | J13: 0 | K13: 0 | L13: 0 | M13: 0 | N13: 0
... A25: Issues | B25: 6 shilling 6pence from 26 geese from tithes sold. | C25: 0.33 | D25: 0 | E25: 6 | F25: 6 | H25: 0 | I25: 0 | J25: 0 | K25: 0 | L25: 0 | M25: 0 | N25: 0
A26: Issues | B26: 1 shilling from the pasturage on this side of the field of la Hyde sold, because it was all sown with wheat. | C26: 0.05 | D26: 0 | E26: 1 | F26: 0 | G26: wheat | H26: 0 | I26: 0 | J26: 0 | K26: 0 | L26: 0 | M26: 0 | N26: 0
A27: Issues | B27: 3 shilling from .the pasturage of Otlond' sold this year. | C27: 0.15 | D27: 0 | E27: 3 | F27: 0 | H27: 0 | I27: 0 | J27: 0 | K27: 0 | L27: 0 | M27: 0 | N27: 0
A28: Issues | B28: nothing from the pasturage of Schortebond' because it was fallow. | C28: 0 | D28: 0 | E28: 0 | F28: 0 | H28: 0 | I28: 0 | J28: 0 | K28: 0 | L28: 0 | M28: 0 | N28: 0
A29: Issues | B29: 1 shilling from the pasturage of Wodebrech sold this year. | C29: 0.05 | D29: 0 | E29: 1 | F29: 0 | H29: 0 | I29: 0 | J29: 0 | K29: 0 | L29: 0 | M29: 0 | N29: 0
A30: Issues | B30: 1 shilling from nettles (urtic') on this side of Bishop's field and the dovecote sold. | C30: 0.05 | D30: 0 | E30: 1 | F30: 0 | H30: 0 | I30: 0 | J30: 0 | K30: 0 | L30: 0 | M30: 0 | N30: 0
A31: Issues | B31: nothing from the herbage of the garden this year on account of the calves and other livestock of the lord. | C31: 0 | D31: 0 | E31: 0 | F31: 0 | H31: 0 | I31: 0 | J31: 0 | K31: 0 | L31: 0 | M31: 0 | N31: 0
A32: Issues | B32: 2 shilling from the pasturage of the meadow of Cherchemed sold after mowing. | C32: 0.1 | D32: 0 | E32: 2 | F32: 0 | H32: 0 | I32: 0 | J32: 0 | K32: 0 | L32: 0 | M32: 0 | N32: 0
A33: Issues | B33: 3 shilling 6pence from 1 pair of wheels with iron tyres sold. | C33: 0.17 | D33: 0 | E33: 3 | F33: 6 | H33: 0 | I33: 0 | J33: 0 | K33: 0 | L33: 0 | M33: 0 | N33: 0
A34: Issues | B34: 4 shilling from 1 old plough-horse sold. | C34: 0.2 | D34: 0 | E34: 4 | F34: 0 | H34: 0 | I34: 0 | J34: 0 | K34: 0 | L34: 0 | M34: 0 | N34: 0
A35: Issues | B35: 5 shilling from 5 wethers sold at Martinmas (11 November). | C35: 0.25 | D35: 0 | E35: 5 | F35: 0 | H35: 0 | I35: 0 | J35: 0 | K35: 0 | L35: 0 | M35: 0 | N35: 0
A36: Issues | B36: £1 17 shilling 9pence from 121 feeble lambs from tithes sold before shearing, at 4pence each for 30, 5pence each for 30, and 3pence each for 61. | C36: 1.89 | D36: 1 | E36: 17 | F36: 9 | H36: 0 | I36: 0 | J36: 0 | K36: 0 | L36: 0 | M36: 0 | N36: 0
A37: Issues | B37: nothing from piglets here because delivered to the reeve of the manor. | C37: 0 | D37: 0 | E37: 0 | F37: 0 | H37: 0 | I37: 0 | J37: 0 | K37: 0 | L37: 0 | M37: 0 | N37: 0
A38: Issues | B38: 5 shilling from the skins sold of 20 wethers in murrain before shearing, at 3pence a skin. | C38: 0.26 | D38: 0 | E38: 5 | F38: 3 | H38: 0 | I38: 0 | J38: 0 | K38: 0 | L38: 0 | M38: 0 | N38: 0
... A44: Issues | B44: Total, £8 19 shilling 2.75pence | C44: 8.96 | D44: 8 | E44: 19 | F44: 2.75 | H44: 0 | I44: 0 | J44: 0 | K44: 0 | L44: 0 | M44: 0 | N44: 0
A45: Sale of corn from the demesne | B45: The same render account for £7 4 shilling 5.5pence from 25 quarters 1 bushels of wheat sold, at 5 shilling a quarters for 8 quarters 5 bushels, 5 shilling 4pence a quarters for 6.5 quarters, and 6 shilling 8pence a quarters for 10 quarters. | C45: 7.22 | D45: 7 | E45: 4 | F45: 5.5 | G45: wheat | H45: 24.5 | I45: 5 | J45: 25.125 | K45: 25.125 | L45: 0 | M45: 25 | N45: 1 | O45: 8 | P45: 5 | Q45: 6.5 | R45: 0 | S45: 10 | T45: 0 | Y45: 5 | Z45: 0 | AA45: 5 | AB45: 4 | AC45: 6 | AD45: 8
A46: Sale of corn from the demesne | B46: £2 12 shilling 10.5pence from 18 quarters 7 bushels of bere sold, at 2 shilling 8pence a quarters for 11 quarters 2 bushels, and 3 shilling a quarters for 7 quarters 5 bushels. | C46: 2.64 | D46: 2 | E46: 12 | F46: 10.5 | H46: 18 | I46: 7 | J46: 18.875 | K46: 18.875 | L46: 0 | M46: 18 | N46: 7 | O46: 11 | P46: 2 | Q46: 7 | R46: 5 | Y46: 2 | Z46: 8 | AA46: 3 | AB46: 0
A47: Sale of corn from the demesne | B47: 10 shilling from 2.5 quarters of barley sold, at 4 shilling a quarters. | C47: 0.5 | D47: 0 | E47: 10 | F47: 0 | G47: barley | H47: 2.5 | I47: 0 | J47: 2.5 | K47: 2.5 | L47: 0 | M47: 2.5 | N47: 0 | Y47: 4 | Z47: 0
A48: Sale of corn from the demesne | B48: Total, £10 7 shilling 4pence | C48: 10.37 | D48: 10 | E48: 7 | F48: 4 | H48: 0 | I48: 0 | J48: 0 | K48: 0 | L48: 0 | M48: 0 | N48: 0
A49: Sale of corn from tithes | B49: The same render account for £20 3 shilling 7.5pence from 65 quarters 7 bushels of wheat from tithes sold, at 5 shilling a quarters for 9 quarters 1 bushels, 5 shilling 4pence a quarters for 15 quarters 2 bushels, and 6 shilling 8pence a quarters for 41.5 quarters. | C49: 20.18 | D49: 20 | E49: 3 | F49: 7.5 | G49: wheat | H49: 65.5 | I49: 3 | J49: 65.875 | K49: 65.875 | L49: 0 | M49: 65 | N49: 7 | O49: 9 | P49: 1 | Q49: 15 | R49: 2 | S49: 41.5 | T49: 0 | Y49: 5 | Z49: 0 | AA49: 5 | AB49: 4 | AC49: 6 | AD49: 8
A50: Sale of corn from tithes | B50: £1 19 shilling 7pence from 14 quarters 7 bushels of bere sold, at 2 shilling 8pence a quarters. | C50: 1.98 | D50: 1 | E50: 19 | F50: 7 | H50: 14 | I50: 7 | J50: 14.875 | K50: 14.875 | L50: 0 | M50: 14 | N50: 7 | Y50: 2 | Z50: 8
A51: Sale of corn from tithes | B51: £7 13 shilling 6pence from 38 quarters 3 bushels of barley sold, at 4 shilling a quarters. | C51: 7.68 | D51: 7 | E51: 13 | F51: 6 | G51: barley | H51: 38 | I51: 3 | J51: 38.375 | K51: 38.375 | L51: 0 | M51: 38 | N51: 3 | Y51: 4 | Z51: 0
A52: Sale of corn from tithes | B52: £5 18 shilling 1.5pence from 64 quarters of oats sold, at 1 shilling 8pence a quarters for 44 quarters 7 bushels, 2 shilling 2pence a quarters for 7 quarters 6 bushels, and 2 shilling 4pence a quarters for 11 quarters 3 bushels. | C52: 5.91 | D52: 5 | E52: 18 | F52: 1.5 | G52: oats | H52: 62 | I52: 16 | J52: 64 | K52: 64 | L52: 0 | M52: 64 | N52: 0 | O52: 44 | P52: 7 | Q52: 7 | R52: 6 | S52: 11 | T52: 3 | Y52: 1 | Z52: 8 | AA52: 2 | AB52: 2 | AC52: 2 | AD52: 4
A53: Sale of corn from tithes | B53: £1 12 shilling 4pence from 12 quarters 1 bushels of beans sold, at 2 shilling 8pence a quarters. | C53: 1.62 | D53: 1 | E53: 12 | F53: 4 | G53: beans | H53: 12 | I53: 1 | J53: 12.125 | K53: 12.125 | L53: 0 | M53: 12 | N53: 1 | Y53: 2 | Z53: 8
A54: Sale of corn from tithes | B54: 4 shilling from 2 quarters of peas sold. | C54: 0.2 | D54: 0 | E54: 4 | F54: 0 | G54: peas | H54: 2 | I54: 0 | J54: 2 | K54: 2 | L54: 0 | M54: 2 | N54: 0
A55: Sale of corn from tithes | B55: 12 shilling 1pence from 7 quarters 2 bushels of vetches sold, at 1 shilling 8pence a quarters. | C55: 0.6 | D55: 0 | E55: 12 | F55: 1 | G55: vetches | H55: 7 | I55: 2 | J55: 7.25 | K55: 7.25 | L55: 0 | M55: 7 | N55: 2 | Y55: 1 | Z55: 8
A56: Sale of corn from tithes | B56: Total, £38 3 shilling 4pence | C56: 38.17 | D56: 38 | E56: 3 | F56: 4 | H56: 0 | I56: 0 | J56: 0 | K56: 0 | L56: 0 | M56: 0 | N56: 0
A57: Froxfield, Steep and Oxeschete | B57: The same render account for £38 from the tithes of corn from the chapels of Froxfield, Steep and Oxeshete sold wholesale. | C57: 38 | D57: 38 | E57: 0 | F57: 0 | H57: 0 | I57: 0 | J57: 0 | K57: 0 | L57: 0 | M57: 0 | N57: 0
A58: Froxfield, Steep and Oxeschete | B58: Total, £38. | C58: 38 | D58: 38 | E58: 0 | F58: 0 | H58: 0 | I58: 0 | J58: 0 | K58: 0 | L58: 0 | M58: 0 | N58: 0
A59: Bykeden' and Yteden' | B59: The same render account for 14 shilling from the tithes of corn from Bykeden' sold. | C59: 0.7 | D59: 0 | E59: 14 | F59: 0 | H59: 0 | I59: 0 | J59: 0 | K59: 0 | L59: 0 | M59: 0 | N59: 0
A60: Bykeden' and Yteden' | B60: £1 from the tithes of corn from Yteden' sold. | C60: 1 | D60: 1 | E60: 0 | F60: 0 | H60: 0 | I60: 0 | J60: 0 | K60: 0 | L60: 0 | M60: 0 | N60: 0
A61: Bykeden' and Yteden' | B61: 7 shilling from the tithes of corn from Gerard de Tygehale solpence Total, £2 1 shilling Total of all the corn from the demesne as well as from tithes sold wholesale, £88 1 shilling 8pence | C61: 2.05 | D61: 2 | E61: 1 | F61: 0 | H61: 0 | I61: 0 | J61: 0 | K61: 0 | L61: 0 | M61: 0 | N61: 0
A62: Entry and marriage fines | B62: The same render account for 4 shilling from the tithing for tithingpenny at the hundred-court of Martinmas. | C62: 0.2 | D62: 0 | E62: 4 | F62: 0 | H62: 0 | I62: 0 | J62: 0 | K62: 0 | L62: 0 | M62: 0 | N62: 0
A63: Entry and marriage fines | B63: 4 shilling from the tithing for tithingpenny at the hundred-court of Hockday. | C63: 0.2 | D63: 0 | E63: 4 | F63: 0 | H63: 0 | I63: 0 | J63: 0 | K63: 0 | L63: 0 | M63: 0 | N63: 0
A64: Entry and marriage fines | B64: £1 from Alice, relict of William Cocus de Pydeham, to retain 1 messuage and 1 virgate of land which belonged to her husbanpence Total, £1 8 shilling | C64: 1 | D64: 1 | E64: 0 | F64: 0 | H64: 0 | I64: 0 | J64: 0 | K64: 0 | L64: 0 | M64: 0 | N64: 0
A65: Perquisites | B65: The same render account for £1 3 shilling 6pence from small perquisites from various men this year for various transgressions. | C65: 1.17 | D65: 1 | E65: 3 | F65: 6 | H65: 0 | I65: 0 | J65: 0 | K65: 0 | L65: 0 | M65: 0 | N65: 0
A66: Perquisites | B66: Total, £1 3 shilling 6pence | C66: 1.17 | D66: 1 | E66: 3 | F66: 6 | H66: 0 | I66: 0 | J66: 0 | K66: 0 | L66: 0 | M66: 0 | N66: 0
A67: Perquisites | B67: Total of both, £2 11 shilling 6pence | C67: 2.57 | D67: 2 | E67: 11 | F67: 6 | H67: 0 | I67: 0 | J67: 0 | K67: 0 | L67: 0 | M67: 0 | N67: 0
... A115: Cost of buildings | B115: 1 sieve bought for straining cider 0.25pence Total, £2 17 shilling 2.25pence | C115: 2.86 | D115: 2 | E115: 17 | F115: 2.25 | H115: 0 | I115: 0 | J115: 0 | K115: 0 | L115: 0 | M115: 0 | N115: 0
A116: Threshing | B116: In threshing and winnowing 38 quarters 5 bushels of wheat from the demesne and 65 quarters 7 bushels of wheat from tithes by piece-work 17 shilling 5pence, at 2pence a struck quarter. | C116: 0.87 | D116: 0 | E116: 17 | F116: 5 | G116: wheat | H116: 65 | I116: 7 | J116: 65.875 | K116: 38.625 | L116: 27.25 | M116: 38 | N116: 5 | O116: 65 | P116: 7
A117: Threshing | B117: . | C117: 0 | D117: 0 | E117: 0 | F117: 0 | H117: 0 | I117: 0 | J117: 0 | K117: 0 | L117: 0 | M117: 0 | N117: 0
A118: Threshing | B118: threshing and winnowing 26 quarters 1 bushels of bere and 21 quarters' 6 bushels of barley from the demesne, and 14 quarters 7 bushels of bere, 38 quarters 3 bushels of barley and 9 quarters 2 bushels of peas and vetches from tithes, 11 shilling .5pence, at 1.5pence per 10 struck bushels. | C118: 0.57 | D118: 0 | E118: 11 | F118: 5 | G118: barley, vetches, peas | H118: 82 | I118: 18 | J118: 84.25 | K118: 26.125 | L118: 58.125 | M118: 26 | N118: 1 | O118: 21 | P118: 0 | Q118: 0 | R118: 6 | S118: 14 | T118: 7 | U118: 38 | V118: 3 | W118: 9 | X118: 2
A119: Threshing | B119: . | C119: 0 | D119: 0 | E119: 0 | F119: 0 | H119: 0 | I119: 0 | J119: 0 | K119: 0 | L119: 0 | M119: 0 | N119: 0
A120: Threshing | B120: threshing and winnowing 12 quarters 1 bushels of beans by piece-work 2 shilling .25pence, at 2pence a struck quarter. | C120: 0.2 | D120: 0 | E120: 2 | F120: 25 | G120: beans | H120: 12 | I120: 1 | J120: 12.125 | K120: 12.125 | L120: 0 | M120: 12 | N120: 1
A121: Threshing | B121: . | C121: 0 | D121: 0 | E121: 0 | F121: 0 | H121: 0 | I121: 0 | J121: 0 | K121: 0 | L121: 0 | M121: 0 | N121: 0
A122: Threshing | B122: threshing and winnowing, 65 quarters 2 bushels of oats from the demesne and 64 quarters of oats from tithes 8 shilling 7.25pence at 1pence per 10 struck bushels. | C122: 0.43 | D122: 0 | E122: 8 | F122: 7.25 | G122: oats | H122: 64 | I122: 2 | J122: 64.25 | K122: 65.25 | L122: -1 | M122: 65 | N122: 2 | O122: 64 | P122: 0
A123: Threshing | B123: Total, £1 19 shilling 1pence | C123: 1.95 | D123: 1 | E123: 19 | F123: 1 | H123: 0 | I123: 0 | J123: 0 | K123: 0 | L123: 0 | M123: 0 | N123: 0
A124: Harvest-time | B124: In bread and herrings, and cheese for a want of herrings, bought for 17 boon-works and 7 carrying-services of 615 men with the customary tenants who reaped, bound and carried all the corn, £1 1 shilling 5pence. | C124: 1.07 | D124: 1 | E124: 1 | F124: 5 | H124: 0 | I124: 0 | J124: 0 | K124: 0 | L124: 0 | M124: 0 | N124: 0
A125: Harvest-time | B125: stipend of 1 hayward at harvest-time 2 shilling Total, | C125: 0.1 | D125: 0 | E125: 2 | F125: 0 | H125: 0 | I125: 0 | J125: 0 | K125: 0 | L125: 0 | M125: 0 | N125: 0
A126: Harvest-time | B126: £1 3 shilling 5pence | C126: 1.17 | D126: 1 | E126: 3 | F126: 5 | H126: 0 | I126: 0 | J126: 0 | K126: 0 | L126: 0 | M126: 0 | N126: 0
A127: Also harvest-time | B127: In stipend of 3 riders this year, of whom 1 stayed for 36 days, 1 for 40 days, and 1 for 45 days, 15 shilling. | C127: 0.75 | D127: 0 | E127: 15 | F127: 0 | H127: 0 | I127: 0 | J127: 0 | K127: 0 | L127: 0 | M127: 0 | N127: 0
A128: Also harvest-time | B128: expenses of the same for the same time 16 shilling. | C128: 0.8 | D128: 0 | E128: 16 | F128: 0 | H128: 0 | I128: 0 | J128: 0 | K128: 0 | L128: 0 | M128: 0 | N128: 0
A129: Also harvest-time | B129: shoeing the horses of the same 9pence. | C129: 0.04 | D129: 0 | E129: 0 | F129: 9 | H129: 0 | I129: 0 | J129: 0 | K129: 0 | L129: 0 | M129: 0 | N129: 0
A130: Also harvest-time | B130: expenses of 9 of the bishop's servants (pedon') and 2 stackers £1 15 shilling 6pence. | C130: 1.77 | D130: 1 | E130: 15 | F130: 6 | H130: 0 | I130: 0 | J130: 0 | K130: 0 | L130: 0 | M130: 0 | N130: 0
A131: Also harvest-time | B131: stipend of the same 18 shilling 4pence, or 1 shilling 8pence each. | C131: 0.92 | D131: 0 | E131: 18 | F131: 4 | H131: 0 | I131: 0 | J131: 0 | K131: 0 | L131: 0 | M131: 0 | N131: 0
A132: Also harvest-time | B132: And note that there is 1 servant fewer this year because the corn of Yteden' and Bykeden' was sold wholesale before the harvest. | C132: 0 | D132: 0 | E132: 0 | F132: 0 | H132: 0 | I132: 0 | J132: 0 | K132: 0 | L132: 0 | M132: 0 | N132: 0
A133: Also harvest-time | B133: . | C133: 0 | D133: 0 | E133: 0 | F133: 0 | H133: 0 | I133: 0 | J133: 0 | K133: 0 | L133: 0 | M133: 0 | N133: 0
A134: Also harvest-time | B134: 3 pairs of wheels made for carrying the corn from tithes 1 shilling 6pence. | C134: 0.08 | D134: 0 | E134: 1 | F134: 6 | H134: 0 | I134: 0 | J134: 0 | K134: 0 | L134: 0 | M134: 0 | N134: 0
... A140: Also harvest-time | B140: hiring carters this year to help carry the corn at various times 2 shilling 4pence. | C140: 0.12 | D140: 0 | E140: 2 | F140: 4 | H140: 0 | I140: 0 | J140: 0 | K140: 0 | L140: 0 | M140: 0 | N140: 0
A141: Also harvest-time | B141: 4 quarters of oats bought for the fodder of the riders' horses 5 shilling 4pence, at 1 shilling 4pence a quarters. | C141: 0.27 | D141: 0 | E141: 5 | F141: 4 | G141: oats | H141: 4 | I141: 0 | J141: 4 | K141: 4 | L141: 0 | M141: 4 | N141: 0 | Y141: 1 | Z141: 4
A142: Also harvest-time | B142: Total, £5 4 shilling 9pence | C142: 5.24 | D142: 5 | E142: 4 | F142: 9 | H142: 0 | I142: 0 | J142: 0 | K142: 0 | L142: 0 | M142: 0 | N142: 0
A143: Total of all expenses | B143: Total of all expenses, £14 12 shilling 0.25pence | C143: 14.6 | D143: 14 | E143: 12 | F143: 0.25 | H143: 0 | I143: 0 | J143: 0 | K143: 0 | L143: 0 | M143: 0 | N143: 0
A144: And thus he owes | B144: And thus he owes, £90 5 shilling 8pence | C144: 90.28 | D144: 90 | E144: 5 | F144: 8 | H144: 0 | I144: 0 | J144: 0 | K144: 0 | L144: 0 | M144: 0 | N144: 0
A145: And thus he owes | B145: Delivered to Sir Geoffrey, treasurer of Wolvesey, by 1 tally, £43. | C145: 43 | D145: 43 | E145: 0 | F145: 0 | H145: 0 | I145: 0 | J145: 0 | K145: 0 | L145: 0 | M145: 0 | N145: 0
A146: And thus he owes clear | B146: And thus he owes clear, £47 5 shilling 8pence | C146: 47.28 | D146: 47 | E146: 5 | F146: 8 | H146: 0 | I146: 0 | J146: 0 | K146: 0 | L146: 0 | M146: 0 | N146: 0
A147: Wheat from the demesne | B147: (yield: six-fold less 1 quarters 7 bushels) | C147: 0 | D147: 0 | E147: 0 | F147: 0 | H147: 1 | I147: 7 | J147: 1.875 | K147: 1.875 | L147: 0 | M147: 1 | N147: 7
A148: Wheat from the demesne | B148: The same render account for 38 quarters 5 bushels from the whole issue of wheat from the demesne by struck measure. | C148: 0 | D148: 0 | E148: 0 | F148: 0 | G148: wheat | H148: 38 | I148: 5 | J148: 38.625 | K148: 38.625 | L148: 0 | M148: 38 | N148: 5
A149: Wheat from the demesne | B149: Sown over 129 acres as they lie in Lahyd' and Wodebrok', 9.5 quarters. | C149: 0 | D149: 0 | E149: 0 | F149: 0 | H149: 9.5 | I149: 0 | J149: 9.5 | K149: 9.5 | L149: 0 | M149: 9.5 | N149: 0
A150: Wheat from the demesne | B150: that is, 1 bushels over 2 acres, plus 1 quarters 3.5 bushels in all. | C150: 0 | D150: 0 | E150: 0 | F150: 0 | H150: 1 | I150: 3.5 | J150: 1.4375 | K150: 0.125 | L150: 1.3125 | M150: 0 | N150: 1 | O150: 1 | P150: 3.5
A151: Wheat from the demesne | B151: . | C151: 0 | D151: 0 | E151: 0 | F151: 0 | H151: 0 | I151: 0 | J151: 0 | K151: 0 | L151: 0 | M151: 0 | N151: 0
A152: Wheat from the demesne | B152: provision of the bailiff, 4 quarters, because he takes the rest from the manor. | C152: 0 | D152: 0 | E152: 0 | F152: 0 | H152: 4 | I152: 0 | J152: 4 | K152: 4 | L152: 0 | M152: 4 | N152: 0
A153: Wheat from the demesne | B153: Sold, 25 quarters 1 bushels | C153: 0 | D153: 0 | E153: 0 | F153: 0 | H153: 25 | I153: 1 | J153: 25.125 | K153: 25.125 | L153: 0 | M153: 25 | N153: 1
A154: Bere | B154: (yield: three-fold plus 5 bushels} | C154: 0 | D154: 0 | E154: 0 | F154: 0 | H154: 0 | I154: 5 | J154: 0.625 | K154: 0.625 | L154: 0 | M154: 0 | N154: 5
A155: Bere | B155: The same render account for 26 quarters 1 bushels from the whole issue of bere by struck measure. | C155: 0 | D155: 0 | E155: 0 | F155: 0 | H155: 26 | I155: 1 | J155: 26.125 | K155: 26.125 | L155: 0 | M155: 26 | N155: 1
A156: Bere | B156: Sown over 41 acres as they lie in Watcombe, 7 quarters 2 bushels. | C156: 0 | D156: 0 | E156: 0 | F156: 0 | H156: 7 | I156: 2 | J156: 7.25 | K156: 7.25 | L156: 0 | M156: 7 | N156: 2
A157: Bere | B157: that is, 1.5 bushels an acre, less 3.5 bushels in all. | C157: 0 | D157: 0 | E157: 0 | F157: 0 | H157: 0 | I157: 3.5 | J157: 0.4375 | K157: 0.1875 | L157: 0.25 | M157: 0 | N157: 1.5 | O157: 0 | P157: 3.5
A158: Bere | B158: Sold, 18 quarters 7 bushels | C158: 0 | D158: 0 | E158: 0 | F158: 0 | H158: 18 | I158: 7 | J158: 18.875 | K158: 18.875 | L158: 0 | M158: 18 | N158: 7
A159: Barley | B159: (yield: three-and-a-half-fold plus 6 bushels) | C159: 0 | D159: 0 | E159: 0 | F159: 0 | H159: 0 | I159: 6 | J159: 0.75 | K159: 0.75 | L159: 0 | M159: 0 | N159: 6
A160: Barley | B160: The same render account for 21 quarters 6 bushels from the whole issue of barley from the demesne by struck measure. | C160: 0 | D160: 0 | E160: 0 | F160: 0 | G160: barley | H160: 21 | I160: 6 | J160: 21.75 | K160: 21.75 | L160: 0 | M160: 21 | N160: 6
A161: Barley | B161: Sown over 17 acres as they lie at Prusteslad', 6 quarters 2 bushels. | C161: 0 | D161: 0 | E161: 0 | F161: 0 | H161: 6 | I161: 2 | J161: 6.25 | K161: 6.25 | L161: 0 | M161: 6 | N161: 2
A162: Barley | B162: that is, 3 bushels an acre, less 1 bushels in all. | C162: 0 | D162: 0 | E162: 0 | F162: 0 | H162: 0 | I162: 1 | J162: 0.125 | K162: 0.375 | L162: -0.25 | M162: 0 | N162: 3 | O162: 0 | P162: 1
A163: Barley | B163: Delivered to 1 carter and 1 stot-keeper for the year, who take a quarter every 8 weeks, 13 quarters. | C163: 0 | D163: 0 | E163: 0 | F163: 0 | H163: 13 | I163: 0 | J163: 13 | K163: 13 | L163: 0 | M163: 13 | N163: 0
A164: Barley | B164: Sold, 2.5 quarters. | C164: 0 | D164: 0 | E164: 0 | F164: 0 | H164: 2.5 | I164: 0 | J164: 2.5 | K164: 2.5 | L164: 0 | M164: 2.5 | N164: 0
A165: Oats | B165: (fold less 5 quarters 3 bushels} | C165: 0 | D165: 0 | E165: 0 | F165: 0 | H165: 5 | I165: 3 | J165: 5.375 | K165: 5.375 | L165: 0 | M165: 5 | N165: 3
A166: Oats | B166: The same render account for 65 quarters. 1 bushels from the whole issue of oats by struck measure. | C166: 0 | D166: 0 | E166: 0 | F166: 0 | G166: oats | H166: 65 | I166: 1 | J166: 65.125 | K166: 65 | L166: 0.125 | M166: 65 | N166: 0 | O166: 0 | P166: 1
A167: Oats | B167: Sown over 105 acres as they lie at Prustehull', Stonyelond', and Watteconbe, 26.5 quarters. | C167: 0 | D167: 0 | E167: 0 | F167: 0 | H167: 26.5 | I167: 0 | J167: 26.5 | K167: 26.5 | L167: 0 | M167: 26.5 | N167: 0
A168: Oats | B168: that is, 2 bushels an acre, plus 2 bushels in all. | C168: 0 | D168: 0 | E168: 0 | F168: 0 | H168: 0 | I168: 2 | J168: 0.25 | K168: 0.25 | L168: 0 | M168: 0 | N168: 2 | O168: 0 | P168: 2
...

Sheet Issues of the Grange raw
A1: Heading | B1: Sentence | C1: Quarters 1_x | D1: Bushels 1_x | E1: Sown Quarters | F1: Sown Bushels | G1: Sown Total Quarters | H1: Bought in Quarters | I1: Bought in Bushels | J1: Bought in Total Quarters | K1: Tithe Quarters | L1: Tithe Bushels | M1: Tithe Total Quarters | N1: Manorial servants & livestock Quarters | O1: Manorial servants & livestock Bushels | P1: Manorial servants & livestock Total Quarters | Q1: Sold Quarters | R1: Sold Bushels | S1: Sold Total Quarters | T1: Account Quarters | U1: Account Bushels | V1: Account Total Quarters | W1: bought only | X1: Total Quarters Except 1 | Y1: Total Bushels Except 1 | Z1: Total Corn Cross-Check | AA1: Total Corn Manorial Account | AB1: Corn Quantity Error | AC1: Quarters 1_y | AD1: Bushels 1_y | AE1: Quarters 2 | AF1: Bushels 2 | AG1: Quarters 3 | AH1: Bushels 3 | AI1: Quarters 4 | AJ1: Bushels 4 | AK1: Quarters 5 | AL1: Bushels 5 | AM1: Quarters 6 | AN1: Bushels 6
A2: And thus he owes clear | B2: Total | C2: 0 | D2: 0 | E2: 0 | F2: 0 | G2: 0 | H2: 0 | I2: 0 | J2: 0 | K2: 0 | L2: 0 | M2: 0 | N2: 0 | O2: 0 | P2: 0 | Q2: 0 | R2: 0 | S2: 0 | T2: 0 | U2: 0 | V2: 0 | W2: 0
A3: Wheat from the demesne | B3: (yield: six-fold less 1 qr 7 bushels) | C3: 0 | D3: 0 | E3: 0 | F3: 0 | G3: 0 | H3: 0 | I3: 0 | J3: 0 | K3: 0 | L3: 0 | M3: 0 | N3: 0 | O3: 0 | P3: 0 | Q3: 0 | R3: 0 | S3: 0 | T3: 0 | U3: 0 | V3: 0 | W3: 0
A4: Wheat from the demesne | B4: The same render account for 38 quarters 5 bushels from the whole issue of wheat from the demesne by struck measure. | C4: 0 | D4: 0 | E4: 0 | F4: 0 | G4: 0 | H4: 0 | I4: 0 | J4: 0 | K4: 0 | L4: 0 | M4: 0 | N4: 0 | O4: 0 | P4: 0 | Q4: 0 | R4: 0 | S4: 0 | T4: 38 | U4: 5 | V4: 38.625 | W4: 0 | X4: 38 | Y4: 5 | Z4: 38.625 | AA4: 38.625 | AB4: 0 | AC4: 38 | AD4: 5
A5: Wheat from the demesne | B5: Sown over 129 acres as they lie in Lahyd' and Wodebrok', 9.5 quarters. | C5: 0 | D5: 0 | E5: 9.5 | F5: 0 | G5: 9.5 | H5: 0 | I5: 0 | J5: 0 | K5: 0 | L5: 0 | M5: 0 | N5: 0 | O5: 0 | P5: 0 | Q5: 0 | R5: 0 | S5: 0 | T5: 0 | U5: 0 | V5: 0 | W5: 0 | X5: 9.5 | Y5: 0 | Z5: 9.5 | AA5: 9.5 | AB5: 0 | AC5: 9.5 | AD5: 0
A6: Wheat from the demesne | B6: that is, 1 bushels over 2 acres, plus 1 qr 3.5 bushels in all. | C6: 0 | D6: 0 | E6: 0 | F6: 0 | G6: 0 | H6: 0 | I6: 0 | J6: 0 | K6: 0 | L6: 0 | M6: 0 | N6: 0 | O6: 0 | P6: 0 | Q6: 0 | R6: 0 | S6: 0 | T6: 0 | U6: 0 | V6: 0 | W6: 0
A7: Wheat from the demesne | B7: . | C7: 0 | D7: 0 | E7: 0 | F7: 0 | G7: 0 | H7: 0 | I7: 0 | J7: 0 | K7: 0 | L7: 0 | M7: 0 | N7: 0 | O7: 0 | P7: 0 | Q7: 0 | R7: 0 | S7: 0 | T7: 0 | U7: 0 | V7: 0 | W7: 0 | X7: 0 | Y7: 0 | Z7: 0 | AA7: 0 | AB7: 0 | AC7: 0 | AD7: 0
A8: Wheat from the demesne | B8: provision of the bailiff, 4 quarters, because he takes the rest from the manor. | C8: 0 | D8: 0 | E8: 0 | F8: 0 | G8: 0 | H8: 0 | I8: 0 | J8: 0 | K8: 0 | L8: 0 | M8: 0 | N8: 0 | O8: 0 | P8: 0 | Q8: 0 | R8: 0 | S8: 0 | T8: 0 | U8: 0 | V8: 0 | W8: 0 | X8: 4 | Y8: 0 | Z8: 4 | AA8: 4 | AB8: 0 | AC8: 4 | AD8: 0
A9: Wheat from the demesne | B9: Sold, 25 quarters 1 bushels | C9: 0 | D9: 0 | E9: 0 | F9: 0 | G9: 0 | H9: 0 | I9: 0 | J9: 0 | K9: 0 | L9: 0 | M9: 0 | N9: 0 | O9: 0 | P9: 0 | Q9: 25 | R9: 1 | S9: 25.125 | T9: 0 | U9: 0 | V9: 0 | W9: 0 | X9: 25 | Y9: 1 | Z9: 25.125 | AA9: 25.125 | AB9: 0 | AC9: 25 | AD9: 1
A10: Wheat from the demesne | B10: Total | C10: 0 | D10: 0 | E10: 0 | F10: 0 | G10: 0 | H10: 0 | I10: 0 | J10: 0 | K10: 0 | L10: 0 | M10: 0 | N10: 0 | O10: 0 | P10: 0 | Q10: 0 | R10: 0 | S10: 0 | T10: 0 | U10: 0 | V10: 0 | W10: 0
A11: Barley | B11: (yield: three-and-a-half-fold plus 6 bushels) | C11: 0 | D11: 0 | E11: 0 | F11: 0 | G11: 0 | H11: 0 | I11: 0 | J11: 0 | K11: 0 | L11: 0 | M11: 0 | N11: 0 | O11: 0 | P11: 0 | Q11: 0 | R11: 0 | S11: 0 | T11: 0 | U11: 0 | V11: 0 | W11: 0 | X11: 0 | Y11: 6 | Z11: 0.75 | AA11: 0.75 | AB11: 0 | AC11: 0 | AD11: 6
A12: Barley | B12: The same render account for 21 quarters 6 bushels from the whole issue of barley from the demesne by struck measure. | C12: 0 | D12: 0 | E12: 0 | F12: 0 | G12: 0 | H12: 0 | I12: 0 | J12: 0 | K12: 0 | L12: 0 | M12: 0 | N12: 0 | O12: 0 | P12: 0 | Q12: 0 | R12: 0 | S12: 0 | T12: 21 | U12: 6 | V12: 21.75 | W12: 0 | X12: 21 | Y12: 6 | Z12: 21.75 | AA12: 21.75 | AB12: 0 | AC12: 21 | AD12: 6
A13: Barley | B13: Sown over 17 acres as they lie at Prusteslad', 6 quarters 2 bushels. | C13: 0 | D13: 0 | E13: 6 | F13: 2 | G13: 6.25 | H13: 0 | I13: 0 | J13: 0 | K13: 0 | L13: 0 | M13: 0 | N13: 0 | O13: 0 | P13: 0 | Q13: 0 | R13: 0 | S13: 0 | T13: 0 | U13: 0 | V13: 0 | W13: 0 | X13: 6 | Y13: 2 | Z13: 6.25 | AA13: 6.25 | AB13: 0 | AC13: 6 | AD13: 2
A14: Barley | B14: that is, 3 bushels an acre, less 1 bushels in all. | C14: 0 | D14: 0 | E14: 0 | F14: 0 | G14: 0 | H14: 0 | I14: 0 | J14: 0 | K14: 0 | L14: 0 | M14: 0 | N14: 0 | O14: 0 | P14: 0 | Q14: 0 | R14: 0 | S14: 0 | T14: 0 | U14: 0 | V14: 0 | W14: 0 | X14: 0 | Y14: 1 | Z14: 0.125 | AA14: 0.375 | AB14: -0.25 | AC14: 0 | AD14: 3 | AE14: 0 | AF14: 1
A15: Barley | B15: Delivered to 1 carter and 1 stot-keeper for the year, who take a quarter every 8 weeks, 13 quarters. | C15: 0 | D15: 0 | E15: 0 | F15: 0 | G15: 0 | H15: 0 | I15: 0 | J15: 0 | K15: 0 | L15: 0 | M15: 0 | N15: 0 | O15: 0 | P15: 0 | Q15: 0 | R15: 0 | S15: 0 | T15: 0 | U15: 0 | V15: 0 | W15: 0 | X15: 13 | Y15: 0 | Z15: 13 | AA15: 13 | AB15: 0 | AC15: 13 | AD15: 0
A16: Barley | B16: Sold, 2.5 quarters. | C16: 0 | D16: 0 | E16: 0 | F16: 0 | G16: 0 | H16: 0 | I16: 0 | J16: 0 | K16: 0 | L16: 0 | M16: 0 | N16: 0 | O16: 0 | P16: 0 | Q16: 2.5 | R16: 0 | S16: 2.5 | T16: 0 | U16: 0 | V16: 0 | W16: 0 | X16: 2.5 | Y16: 0 | Z16: 2.5 | AA16: 2.5 | AB16: 0 | AC16: 2.5 | AD16: 0
A17: Barley | B17: Total | C17: 0 | D17: 0 | E17: 0 | F17: 0 | G17: 0 | H17: 0 | I17: 0 | J17: 0 | K17: 0 | L17: 0 | M17: 0 | N17: 0 | O17: 0 | P17: 0 | Q17: 0 | R17: 0 | S17: 0 | T17: 0 | U17: 0 | V17: 0 | W17: 0
A18: Oats | B18: (fold less 5 quarters 3 bushels} | C18: 0 | D18: 0 | E18: 0 | F18: 0 | G18: 0 | H18: 0 | I18: 0 | J18: 0 | K18: 0 | L18: 0 | M18: 0 | N18: 0 | O18: 0 | P18: 0 | Q18: 0 | R18: 0 | S18: 0 | T18: 0 | U18: 0 | V18: 0 | W18: 0 | X18: 5 | Y18: 3 | Z18: 5.375 | AA18: 5.375 | AB18: 0 | AC18: 5 | AD18: 3
A19: Oats | B19: The same render account for 65 quarters. 1 bushels from the whole issue of oats by struck measure. | C19: 0 | D19: 0 | E19: 0 | F19: 0 | G19: 0 | H19: 0 | I19: 0 | J19: 0 | K19: 0 | L19: 0 | M19: 0 | N19: 0 | O19: 0 | P19: 0 | Q19: 0 | R19: 0 | S19: 0 | T19: 65 | U19: 0 | V19: 65 | W19: 0 | X19: 65 | Y19: 1 | Z19: 65.125 | AA19: 65 | AB19: 0.125 | AC19: 65 | AD19: 0 | AE19: 0 | AF19: 1
A20: Oats | B20: Sown over 105 acres as they lie at Prustehull', Stonyelond', and Watteconbe, 26.5 qr. | C20: 0 | D20: 0 | E20: 0 | F20: 0 | G20: 0 | H20: 0 | I20: 0 | J20: 0 | K20: 0 | L20: 0 | M20: 0 | N20: 0 | O20: 0 | P20: 0 | Q20: 0 | R20: 0 | S20: 0 | T20: 0 | U20: 0 | V20: 0 | W20: 0
A21: Oats | B21: that is, 2 bushels an acre, plus 2 bushels in all. | C21: 0 | D21: 0 | E21: 0 | F21: 0 | G21: 0 | H21: 0 | I21: 0 | J21: 0 | K21: 0 | L21: 0 | M21: 0 | N21: 0 | O21: 0 | P21: 0 | Q21: 0 | R21: 0 | S21: 0 | T21: 0 | U21: 0 | V21: 0 | W21: 0 | X21: 0 | Y21: 2 | Z21: 0.25 | AA21: 0.25 | AB21: 0 | AC21: 0 | AD21: 2 | AE21: 0 | AF21: 2
A22: Oats | B22: . | C22: 0 | D22: 0 | E22: 0 | F22: 0 | G22: 0 | H22: 0 | I22: 0 | J22: 0 | K22: 0 | L22: 0 | M22: 0 | N22: 0 | O22: 0 | P22: 0 | Q22: 0 | R22: 0 | S22: 0 | T22: 0 | U22: 0 | V22: 0 | W22: 0 | X22: 0 | Y22: 0 | Z22: 0 | AA22: 0 | AB22: 0 | AC22: 0 | AD22: 0
A23: Oats | B23: . | C23: 0 | D23: 0 | E23: 0 | F23: 0 | G23: 0 | H23: 0 | I23: 0 | J23: 0 | K23: 0 | L23: 0 | M23: 0 | N23: 0 | O23: 0 | P23: 0 | Q23: 0 | R23: 0 | S23: 0 | T23: 0 | U23: 0 | V23: 0 | W23: 0 | X23: 0 | Y23: 0 | Z23: 0 | AA23: 0 | AB23: 0 | AC23: 0 | AD23: 0
A24: Oats | B24: . | C24: 0 | D24: 0 | E24: 0 | F24: 0 | G24: 0 | H24: 0 | I24: 0 | J24: 0 | K24: 0 | L24: 0 | M24: 0 | N24: 0 | O24: 0 | P24: 0 | Q24: 0 | R24: 0 | S24: 0 | T24: 0 | U24: 0 | V24: 0 | W24: 0 | X24: 0 | Y24: 0 | Z24: 0 | AA24: 0 | AB24: 0 | AC24: 0 | AD24: 0
A25: Oats | B25: . | C25: 0 | D25: 0 | E25: 0 | F25: 0 | G25: 0 | H25: 0 | I25: 0 | J25: 0 | K25: 0 | L25: 0 | M25: 0 | N25: 0 | O25: 0 | P25: 0 | Q25: 0 | R25: 0 | S25: 0 | T25: 0 | U25: 0 | V25: 0 | W25: 0 | X25: 0 | Y25: 0 | Z25: 0 | AA25: 0 | AB25: 0 | AC25: 0 | AD25: 0
A26: Oats | B26: fodder of 2 cart-horses from Michaelmas (29 September) until Lammas (1 August), for 306 nights, 19 quarters 1 bushels, at 0.5 bushels a night. | C26: 0 | D26: 0 | E26: 0 | F26: 0 | G26: 0 | H26: 0 | I26: 0 | J26: 0 | K26: 0 | L26: 0 | M26: 0 | N26: 19 | O26: 1 | P26: 19.125 | Q26: 0 | R26: 0 | S26: 0 | T26: 0 | U26: 0 | V26: 0 | W26: 0 | X26: 19 | Y26: 0.5 | Z26: 19.0625 | AA26: 19.125 | AB26: -0.0625 | AC26: 19 | AD26: 1 | AE26: 0 | AF26: 0.5
A27: Oats | B27: . | C27: 0 | D27: 0 | E27: 0 | F27: 0 | G27: 0 | H27: 0 | I27: 0 | J27: 0 | K27: 0 | L27: 0 | M27: 0 | N27: 0 | O27: 0 | P27: 0 | Q27: 0 | R27: 0 | S27: 0 | T27: 0 | U27: 0 | V27: 0 | W27: 0 | X27: 0 | Y27: 0 | Z27: 0 | AA27: 0 | AB27: 0 | AC27: 0 | AD27: 0
A28: Oats | B28: . | C28: 0 | D28: 0 | E28: 0 | F28: 0 | G28: 0 | H28: 0 | I28: 0 | J28: 0 | K28: 0 | L28: 0 | M28: 0 | N28: 0 | O28: 0 | P28: 0 | Q28: 0 | R28: 0 | S28: 0 | T28: 0 | U28: 0 | V28: 0 | W28: 0 | X28: 0 | Y28: 0 | Z28: 0 | AA28: 0 | AB28: 0 | AC28: 0 | AD28: 0
A29: Oats | B29: . | C29: 0 | D29: 0 | E29: 0 | F29: 0 | G29: 0 | H29: 0 | I29: 0 | J29: 0 | K29: 0 | L29: 0 | M29: 0 | N29: 0 | O29: 0 | P29: 0 | Q29: 0 | R29: 0 | S29: 0 | T29: 0 | U29: 0 | V29: 0 | W29: 0 | X29: 0 | Y29: 0 | Z29: 0 | AA29: 0 | AB29: 0 | AC29: 0 | AD29: 0
A30: Oats | B30: . | C30: 0 | D30: 0 | E30: 0 | F30: 0 | G30: 0 | H30: 0 | I30: 0 | J30: 0 | K30: 0 | L30: 0 | M30: 0 | N30: 0 | O30: 0 | P30: 0 | Q30: 0 | R30: 0 | S30: 0 | T30: 0 | U30: 0 | V30: 0 | W30: 0 | X30: 0 | Y30: 0 | Z30: 0 | AA30: 0 | AB30: 0 | AC30: 0 | AD30: 0
A31: Oats | B31: fodder of 6 plough-horses from the feast of the Circumcision (1 January) until Sunday before the feast of St Augustine (20 May), for 140 nights, 17.5 quarters, at 1 bushels a night. | C31: 0 | D31: 0 | E31: 0 | F31: 0 | G31: 0 | H31: 0 | I31: 0 | J31: 0 | K31: 0 | L31: 0 | M31: 0 | N31: 17.5 | O31: 0 | P31: 17.5 | Q31: 0 | R31: 0 | S31: 0 | T31: 0 | U31: 0 | V31: 0 | W31: 0 | X31: 17.5 | Y31: 1 | Z31: 17.625 | AA31: 17.5 | AB31: 0.125 | AC31: 17.5 | AD31: 0 | AE31: 0 | AF31: 1
A32: Oats | B32: . | C32: 0 | D32: 0 | E32: 0 | F32: 0 | G32: 0 | H32: 0 | I32: 0 | J32: 0 | K32: 0 | L32: 0 | M32: 0 | N32: 0 | O32: 0 | P32: 0 | Q32: 0 | R32: 0 | S32: 0 | T32: 0 | U32: 0 | V32: 0 | W32: 0 | X32: 0 | Y32: 0 | Z32: 0 | AA32: 0 | AB32: 0 | AC32: 0 | AD32: 0
A33: Oats | B33: . | C33: 0 | D33: 0 | E33: 0 | F33: 0 | G33: 0 | H33: 0 | I33: 0 | J33: 0 | K33: 0 | L33: 0 | M33: 0 | N33: 0 | O33: 0 | P33: 0 | Q33: 0 | R33: 0 | S33: 0 | T33: 0 | U33: 0 | V33: 0 | W33: 0 | X33: 0 | Y33: 0 | Z33: 0 | AA33: 0 | AB33: 0 | AC33: 0 | AD33: 0
A34: Oats | B34: . | C34: 0 | D34: 0 | E34: 0 | F34: 0 | G34: 0 | H34: 0 | I34: 0 | J34: 0 | K34: 0 | L34: 0 | M34: 0 | N34: 0 | O34: 0 | P34: 0 | Q34: 0 | R34: 0 | S34: 0 | T34: 0 | U34: 0 | V34: 0 | W34: 0 | X34: 0 | Y34: 0 | Z34: 0 | AA34: 0 | AB34: 0 | AC34: 0 | AD34: 0
A35: Oats | B35: . | C35: 0 | D35: 0 | E35: 0 | F35: 0 | G35: 0 | H35: 0 | I35: 0 | J35: 0 | K35: 0 | L35: 0 | M35: 0 | N35: 0 | O35: 0 | P35: 0 | Q35: 0 | R35: 0 | S35: 0 | T35: 0 | U35: 0 | V35: 0 | W35: 0 | X35: 0 | Y35: 0 | Z35: 0 | AA35: 0 | AB35: 0 | AC35: 0 | AD35: 0
A36: Oats | B36: fodder of the same when they ploughed after dinner, 0.5 qr. | C36: 0 | D36: 0 | E36: 0 | F36: 0 | G36: 0 | H36: 0 | I36: 0 | J36: 0 | K36: 0 | L36: 0 | M36: 0 | N36: 0 | O36: 0 | P36: 0 | Q36: 0 | R36: 0 | S36: 0 | T36: 0 | U36: 0 | V36: 0 | W36: 0
A37: Oats | B37: . | C37: 0 | D37: 0 | E37: 0 | F37: 0 | G37: 0 | H37: 0 | I37: 0 | J37: 0 | K37: 0 | L37: 0 | M37: 0 | N37: 0 | O37: 0 | P37: 0 | Q37: 0 | R37: 0 | S37: 0 | T37: 0 | U37: 0 | V37: 0 | W37: 0 | X37: 0 | Y37: 0 | Z37: 0 | AA37: 0 | AB37: 0 | AC37: 0 | AD37: 0
A38: Oats | B38: . | C38: 0 | D38: 0 | E38: 0 | F38: 0 | G38: 0 | H38: 0 | I38: 0 | J38: 0 | K38: 0 | L38: 0 | M38: 0 | N38: 0 | O38: 0 | P38: 0 | Q38: 0 | R38: 0 | S38: 0 | T38: 0 | U38: 0 | V38: 0 | W38: 0 | X38: 0 | Y38: 0 | Z38: 0 | AA38: 0 | AB38: 0 | AC38: 0 | AD38: 0
A39: Oats | B39: . | C39: 0 | D39: 0 | E39: 0 | F39: 0 | G39: 0 | H39: 0 | I39: 0 | J39: 0 | K39: 0 | L39: 0 | M39: 0 | N39: 0 | O39: 0 | P39: 0 | Q39: 0 | R39: 0 | S39: 0 | T39: 0 | U39: 0 | V39: 0 | W39: 0 | X39: 0 | Y39: 0 | Z39: 0 | AA39: 0 | AB39: 0 | AC39: 0 | AD39: 0
A40: Oats | B40: . | C40: 0 | D40: 0 | E40: 0 | F40: 0 | G40: 0 | H40: 0 | I40: 0 | J40: 0 | K40: 0 | L40: 0 | M40: 0 | N40: 0 | O40: 0 | P40: 0 | Q40: 0 | R40: 0 | S40: 0 | T40: 0 | U40: 0 | V40: 0 | W40: 0 | X40: 0 | Y40: 0 | Z40: 0 | AA40: 0 | AB40: 0 | AC40: 0 | AD40: 0
A41: Oats | B41: customary payment to 1 ploughman and 1 shepherd, 1.5 quarters. | C41: 0 | D41: 0 | E41: 0 | F41: 0 | G41: 0 | H41: 0 | I41: 0 | J41: 0 | K41: 0 | L41: 0 | M41: 0 | N41: 0 | O41: 0 | P41: 0 | Q41: 0 | R41: 0 | S41: 0 | T41: 0 | U41: 0 | V41: 0 | W41: 0 | X41: 1.5 | Y41: 0 | Z41: 1.5 | AA41: 1.5 | AB41: 0 | AC41: 1.5 | AD41: 0
A42: Oats | B42: Total, 65 quarters 1 bushels It balances. | C42: 0 | D42: 0 | E42: 0 | F42: 0 | G42: 0 | H42: 0 | I42: 0 | J42: 0 | K42: 0 | L42: 0 | M42: 0 | N42: 0 | O42: 0 | P42: 0 | Q42: 0 | R42: 0 | S42: 0 | T42: 0 | U42: 0 | V42: 0 | W42: 0 | X42: 65 | Y42: 1 | Z42: 65.125 | AA42: 65.125 | AB42: 0 | AC42: 65 | AD42: 1

Sheet Sale of Corn Prices
A1: Heading | B1: Sentence | C1: Total in Pounds | D1: Pounds | E1: Shillings | F1: Pence | G1: Corn | H1: Total Quarters Except 1 | I1: Total Bushels Except 1 | J1: Total Corn Cross-Check | K1: Total Corn Manorial Account | L1: Corn Quantity Error | M1: Quarters 0 | N1: Bushels 0 | O1: shilling a quarter 1 | P1: pence a quarter 1 | Q1: Quarters 1 | R1: Bushels 1 | S1: shilling a quarter 2 | T1: pence a quarter 2 | U1: Quarters 2 | V1: Bushels 2 | W1: shilling a quarter 3 | X1: pence a quarter 3 | Y1: Quarters 3 | Z1: Bushels 3 | AA1: shilling a quarter 4 | AB1: pence a quarter 4 | AC1: Quarters 4 | AD1: Bushels 4 | AE1: Quarters 5 | AF1: Bushels 5 | AG1: £ a quarter 1 | AH1: £ a quarter 2 | AI1: £ a quarter 3 | AJ1: £ a quarter 4 | AK1: Quarters Sold | AL1: Weighted Average Price per Quarter | AM1: Non-Weighted Average Price per Quarter | AN1: Corn lowercase
A2: Sale of corn from the demesne | B2: The same render account for £7 4 shilling 5.5pence from 25 quarters 1 bushels of wheat sold, at 5 shilling a quarters for 8 quarters 5 bushels, 5 shilling 4pence a quarters for 6.5 quarters, and 6 shilling 8pence a quarters for 10 quarters. | C2: 7.22 | D2: 7 | E2: 4 | F2: 5.5 | G2: wheat | H2: 24.5 | I2: 5 | J2: 25.125 | K2: 25.125 | L2: 0 | M2: 25 | N2: 1 | O2: 5 | P2: 0 | Q2: 8 | R2: 5 | S2: 5 | T2: 4 | U2: 6.5 | V2: 0 | W2: 6 | X2: 8 | Y2: 10 | Z2: 0 | AG2: 0.25 | AH2: 0.26666667 | AI2: 0.33333333 | AK2: 25.125 | AL2: 0.28747927 | AM2: 0.28333333 | AN2: wheat
A3: Sale of corn from the demesne | B3: £2 12 shilling 10.5pence from 18 quarters 7 bushels of bere sold, at 2 shilling 8pence a quarters for 11 quarters 2 bushels, and 3 shilling a quarters for 7 quarters 5 bushels. | C3: 2.64 | D3: 2 | E3: 12 | F3: 10.5 | H3: 18 | I3: 7 | J3: 18.875 | K3: 18.875 | L3: 0 | M3: 18 | N3: 7 | O3: 2 | P3: 8 | Q3: 11 | R3: 2 | S3: 3 | T3: 0 | U3: 7 | V3: 5 | AG3: 0.13333333 | AH3: 0.15 | AK3: 18.875 | AL3: 0.14006623 | AM3: 0.14166667
A4: Sale of corn from the demesne | B4: 10 shilling from 2.5 quarters of barley sold, at 4 shilling a quarters. | C4: 0.5 | D4: 0 | E4: 10 | F4: 0 | G4: barley | H4: 2.5 | I4: 0 | J4: 2.5 | K4: 2.5 | L4: 0 | M4: 2.5 | N4: 0 | O4: 4 | P4: 0 | AG4: 0.2 | AK4: 2.5 | AL4: 0.2 | AM4: 0.2 | AN4: barley
A5: Sale of corn from the demesne | B5: Total, £10 7 shilling 4pence | C5: 10.37 | D5: 10 | E5: 7 | F5: 4 | H5: 0 | I5: 0 | J5: 0 | K5: 0 | L5: 0 | M5: 0 | N5: 0 | AG5: inf | AK5: 0 | AL5: inf | AM5: inf
A6: Sale of corn from tithes | B6: The same render account for £20 3 shilling 7.5pence from 65 quarters 7 bushels of wheat from tithes sold, at 5 shilling a quarters for 9 quarters 1 bushels, 5 shilling 4pence a quarters for 15 quarters 2 bushels, and 6 shilling 8pence a quarters for 41.5 quarters. | C6: 20.18 | D6: 20 | E6: 3 | F6: 7.5 | G6: wheat | H6: 65.5 | I6: 3 | J6: 65.875 | K6: 65.875 | L6: 0 | M6: 65 | N6: 7 | O6: 5 | P6: 0 | Q6: 9 | R6: 1 | S6: 5 | T6: 4 | U6: 15 | V6: 2 | W6: 6 | X6: 8 | Y6: 41.5 | Z6: 0 | AG6: 0.25 | AH6: 0.26666667 | AI6: 0.33333333 | AK6: 65.875 | AL6: 0.30635674 | AM6: 0.28333333 | AN6: wheat
A7: Sale of corn from tithes | B7: £1 19 shilling 7pence from 14 quarters 7 bushels of bere sold, at 2 shilling 8pence a quarters. | C7: 1.98 | D7: 1 | E7: 19 | F7: 7 | H7: 14 | I7: 7 | J7: 14.875 | K7: 14.875 | L7: 0 | M7: 14 | N7: 7 | O7: 2 | P7: 8 | AG7: 0.13333333 | AK7: 14.875 | AL7: 0.13333333 | AM7: 0.13333333
A8: Sale of corn from tithes | B8: £7 13 shilling 6pence from 38 quarters 3 bushels of barley sold, at 4 shilling a quarters. | C8: 7.68 | D8: 7 | E8: 13 | F8: 6 | G8: barley | H8: 38 | I8: 3 | J8: 38.375 | K8: 38.375 | L8: 0 | M8: 38 | N8: 3 | O8: 4 | P8: 0 | AG8: 0.2 | AK8: 38.375 | AL8: 0.2 | AM8: 0.2 | AN8: barley
A9: Sale of corn from tithes | B9: £5 18 shilling 1.5pence from 64 quarters of oats sold, at 1 shilling 8pence a quarters for 44 quarters 7 bushels, 2 shilling 2pence a quarters for 7 quarters 6 bushels, and 2 shilling 4pence a quarters for 11 quarters 3 bushels. | C9: 5.91 | D9: 5 | E9: 18 | F9: 1.5 | G9: oats | H9: 62 | I9: 16 | J9: 64 | K9: 64 | L9: 0 | M9: 64 | N9: 0 | O9: 1 | P9: 8 | Q9: 44 | R9: 7 | S9: 2 | T9: 2 | U9: 7 | V9: 6 | W9: 2 | X9: 4 | Y9: 11 | Z9: 3 | AG9: 0.083333333 | AH9: 0.10833333 | AI9: 0.11666667 | AK9: 64 | AL9: 0.092285156 | AM9: 0.10277778 | AN9: oats
A10: Sale of corn from tithes | B10: £1 12 shilling 4pence from 12 quarters 1 bushels of beans sold, at 2 shilling 8pence a quarters. | C10: 1.62 | D10: 1 | E10: 12 | F10: 4 | G10: beans | H10: 12 | I10: 1 | J10: 12.125 | K10: 12.125 | L10: 0 | M10: 12 | N10: 1 | O10: 2 | P10: 8 | AG10: 0.13333333 | AK10: 12.125 | AL10: 0.13333333 | AM10: 0.13333333 | AN10: beans
A11: Sale of corn from tithes | B11: 4 shilling from 2 quarters of peas sold. | C11: 0.2 | D11: 0 | E11: 4 | F11: 0 | G11: peas | H11: 2 | I11: 0 | J11: 2 | K11: 2 | L11: 0 | M11: 2 | N11: 0 | AG11: 0.1 | AK11: 2 | AL11: 0.1 | AM11: 0.1 | AN11: peas
A12: Sale of corn from tithes | B12: 12 shilling 1pence from 7 quarters 2 bushels of vetches sold, at 1 shilling 8pence a quarters. | C12: 0.6 | D12: 0 | E12: 12 | F12: 1 | G12: vetches | H12: 7 | I12: 2 | J12: 7.25 | K12: 7.25 | L12: 0 | M12: 7 | N12: 2 | O12: 1 | P12: 8 | AG12: 0.083333333 | AK12: 7.25 | AL12: 0.083333333 | AM12: 0.083333333 | AN12: vetches
A13: Sale of corn from tithes | B13: Total, £38 3 shilling 4pence | C13: 38.17 | D13: 38 | E13: 3 | F13: 4 | H13: 0 | I13: 0 | J13: 0 | K13: 0 | L13: 0 | M13: 0 | N13: 0 | AG13: inf | AK13: 0 | AL13: inf | AM13: inf
