Workbook

Sheet Overview
A1: EAST MEON | B1: Total in £ | C1: Error | D1: Note
A2: CASH ACCOUNT
A3: RECEIPTS
A4: Arrears total
A5: Rents of assize total
A6: Quittances total
A7: Defaults of rent total
A8: Defaults of rent through the pestilence total
A9: Cotlands defaults total
A10: Cotlands total
A11: Total of quittances and defaults of rent total
A12: Total of rents remaining clear total
A13: Farms total
... A22: Farm of the demesne land total
A23: Total of all receipts (calculated here) | B23: =Receipts!F206 -> 264.22312
A24: Total of all receipts (calculated here) incl arrears | B24: =Receipts!F207 -> 358.46312
A25: Total recorded in the accounts excl. arrears | B25: =Receipts!F205 -> 270.1
A26: Total recorded in the accounts incl. arrears
A29: EXPENSES
A30: Cost of ploughs total
A31: Purchase of corn total
A32: Cost of carts and wagons total
A33: Cost of dairy total
A34: Purchase of stock total
A35: Sheepcote total
A36: Cost of buildings total
A37: Threshing total
A38: Barley expenses
A39: Expenses of the harvest total
... A43: Annual fees
A44: Total of all expenses per account | B44: =Expenses!F109 -> 39.28
A45: Total of all expenses (calculated here) | B45: =Expenses!F110 -> 39.312708
A46: Total fixed investment | B46: =Expenses!F111 -> 5.5833333
A47: Total Demesne fixed investment | B47: =Expenses!F112 -> 5.1283333
A49: Owed by the reeve
A50: From accounts
A52: Allowances
A53: Cash deliveries
A54: Sum of the above
A55: Total of all allowances and cash deliveries in accounts
A57: Net amount owed
A58: Net amount owed in accounts
A60: GRANGE ACCOUNT | B60: Total Production
A61: Grange | B61: qrs | E61: Value of total gross production in £ | F61: Value of total net production in £
A62: wheat | B62: ='Issues of the Grange'!B2 -> 357.875 | E62: ='Issues of the Grange'!I2 -> 98.548836 | F62: ='Issues of the Grange'!O13 -> 73.249012
A63: curall | B63: ='Issues of the Grange'!B3 -> 14 | E63: ='Issues of the Grange'!I3 -> 2.3333333 | F63: ='Issues of the Grange'!O14 -> 2.3333333
A64: barley | B64: ='Issues of the Grange'!B4 -> 115.6875 | E64: ='Issues of the Grange'!I4 -> 22.404981 | F64: ='Issues of the Grange'!O15 -> 5.54375
A65: oats | B65: ='Issues of the Grange'!B5 -> 616.5625 | E65: ='Issues of the Grange'!I5 -> 63.631694 | F65: ='Issues of the Grange'!O16 -> 28.593948
A66: Total value of gross production (sum of the above) | E66: =SUM(E62:E65) -> 186.91884
A67: Total value of net production | E67: =SUM(F62:F65) -> 109.72004
A68: Value of sales | E68: =Receipts!F150 -> 111.81
A70: MILL ACCOUNT
A71: Issues of the mill
A72: Wheat
A73: Oatmeal
A74: 1st grade malt
A75: 2nd grade malt
A76: Maslin
A77: Total value of production (sum of the above)
A78: Value of sales
A80: STOCK ACCOUNT
A81: Livestock | B81: Sales value in £
A82: Cart-horses | B82: =Stock!R5 -> 0
A83: Mares | B83: =Stock!R6 -> 0
A84: Plough horses | B84: =Stock!R7 -> 0.52
A85: Colts (2 years) | B85: =Stock!R8 -> 0
A86: Colts (2 years) | B86: =Stock!R9 -> 0
A87: Colts (1 year) | B87: =Stock!R10 -> 0
A88: Foals | B88: =Stock!R11 -> 0
A89: Oxen | B89: =Stock!R12 -> 4.1
A90: Bulls | B90: =Stock!R13 -> 0
A91: Cows | B91: =Stock!R14 -> 0.4
A92: Steers | B92: =Stock!R15 -> 0
A93: Bullocks | B93: =Stock!R16 -> 0
... A107: Peacocks | B107: =Stock!R30 -> 0
A108: Total value of stock (sum of the above)
A109: Total value of production
A110: Value of sales | B110: =Stock!R31 -> 15.19
A112: Wool | B112: Value of production at sales prices £
A113: Coarse wool | B113: =Stock!T35 -> 28.1
A114: Lamb's wool | B114: =Stock!T36 -> 4.33
A115: Wool locks | B115: =Stock!T37 -> 0.91
A116: Wool sold at shearing | B116: =Stock!T38 -> 0
A117: Total value of production (sum of the above) | B117: =SUM(B113:B116) -> 33.34
A118: Value of sales | B118: =Stock!R39 -> 0.91
A120: Hides | B120: Value of production at sales prices £
A121: Ox hides | B121: =Stock!T43 -> 0
A122: Cow hides | B122: =Stock!T44 -> 0
A123: Mare hides | B123: =Stock!T45 -> 0
A124: Steer hides | B124: =Stock!T46 -> 0
A125: Yearling Calf hides | B125: =Stock!T47 -> 0
A126: Calf hides | B126: =Stock!T48 -> 0
A127: Pig hides | B127: =Stock!T49 -> 0
A128: Wether woolskins | B128: =Stock!T50 -> 0
A129: Ram woolskins | B129: =Stock!T51 -> 0
A130: Ewe woolskins | B130: =Stock!T52 -> 0
A131: Hogg woolskins | B131: =Stock!T53 -> 0
A132: Woolskins (total) | B132: =Stock!T54 -> 0
... A140: Shorn skins | B140: =Stock!T62 -> 0.49
A141: Total value of production (sum of the above) | B141: =SUM(B121:B140) -> 1.76
...

Sheet Receipts
A1: EAST MEON RECEIPTS
A2: Heading | B2: £ | C2: s | D2: d | F2: Total in £ | G2: Error | H2: Notes
A3: Arrears | B3: 94 | C3: 4 | D3: 10.5 | F3: 94.24 | H3: Nicholas de Ychen', bailiff, and Richard Pokepole and Adam de Cumbe, reeves, render account for £94 4 shilling 10.5pence of arrears from the previous year.
A4: Arrears | B4: 0 | C4: 0 | D4: 0 | F4: 0 | H4: All delivered to Sir Geoffrey, treasurer of Wolvesey, by 1 tally.
A5: Arrears | B5: 0 | C5: 0 | D5: 0 | F5: 0 | H5: They are quit.
A6: Arrears | F6: 94.24 | G6: 94.24 | H6: Total
A8: Rents of assize | B8: 23 | C8: 2 | D8: 8.5 | F8: 23.14 | H8: The same render account for £23 2 shilling 8.5pence for all rents of assize at Christmas.
A9: Rents of assize | B9: 23 | C9: 2 | D9: 8.5 | F9: 23.14 | H9: £23 2 shilling 8.5pence at Easter (22 April).
A10: Rents of assize | B10: 23 | C10: 2 | D10: 8.5 | F10: 23.14 | H10: £23 2 shilling 8.5pence at the feast of St John the Baptist (24 June).
A11: Rents of assize | B11: 27 | C11: 18 | D11: 4 | F11: 27.92 | H11: £27 18 shilling 4pence at Michaelmas (29 September).
A12: Rents of assize | B12: 97 | C12: 6 | D12: 5.5 | F12: 97.32 | H12: Total, £97 6 shilling 5.5pence
A13: Rents of assize | F13: 97.34 | G13: 0.02 | H13: Total
A15: Increment | B15: 0 | C15: 0 | D15: 5 | F15: 0.02 | H15: The same render account for .5pence from John Miles for the increment of rent for a certain purpresture which before he encroached upon without licence of the lorpence
A16: Increment | B16: 0 | C16: 0 | D16: 0 | F16: 0 | H16: Total the same.
A17: Increment | F17: 0.02 | G17: 0 | H17: Total
A19: Quittances | B19: 0 | C19: 5 | D19: 0 | F19: 0.25 | H19: In quittance of 1 reeve for the year 5 shilling.
A20: Quittances | B20: 1 | C20: 10 | D20: 0 | F20: 1.5 | H20: 8 ploughmen, 3 shepherds and 1 swineherd for the year £1 10 shilling, or 2 shilling 6pence each.
A21: Quittances | B21: 0 | C21: 7 | D21: 6 | F21: =B21+C21/20+D21/240 -> 0.375 | H21: 3 ploughmen for the year who replaced 3 drovers who were at liberty 7 shilling 6pence
A22: Quittances | B22: 2 | C22: 2 | D22: 6 | F22: 2.12 | H22: Total, £2 2 shilling 6pence
A23: Quittances | F23: =SUM(F19:F21) -> 2.125 | G23: =F23-F22 -> 0.005 | H23: Total
A25: Defaults of rent | B25: 1 | C25: 1 | D25: 7.5 | F25: 1.08 | H25: In default of the land drawn into demesne, £1 1 shilling 7.5pence for the year.
A26: Defaults of rent | B26: 5 | C26: 0 | D26: 0 | F26: 5 | H26: the land of Rethecumbe given to the canons of Newark Priory by Bishop Godfrey, £5 for the year.
A27: Defaults of rent | B27: 2 | C27: 0 | D27: 0 | F27: 2 | H27: the pasture and wood of Balluns which belonged to Thomas de Cumbe drawn into demesne, £2 for the year.
A28: Defaults of rent | B28: 1 | C28: 0 | D28: 0 | F28: 1 | H28: the mill which Robert Molendinarius sometimes held drawn into demesne, £1 for the year.
A29: Defaults of rent | B29: 0 | C29: 3 | D29: 0 | F29: 0.15 | H29: 8 acres of land which Deodatus (Deudoenis) le Hayward sometimes held drawn into demesne, 3 shilling for the year.
A30: Defaults of rent | B30: 0 | C30: 3 | D30: 5 | F30: 0.17 | H30: the land which the Abbot of Durford held drawn into demesne, 3 shilling 5pence for the year.
A31: Defaults of rent | B31: 0 | C31: 3 | D31: 2 | F31: 0.16 | H31: the land of Barlych' drawn into the park, 3 shilling 2pence for the year.
A32: Defaults of rent | B32: 0 | C32: 0 | D32: 6 | F32: 0.03 | H32: 1 purpresture which belonged to William Gibbe drawn into demesne, 6pence for the year.
A33: Defaults of rent | B33: 0 | C33: 0 | D33: 4 | F33: =B33+C33/20+D33/240 -> 0.016666667 | H33: 1 plot beside the marl-pit of Wetham which H. de Borden' held, 4pence, because it was a nuisance to the neighbourhood.
A34: Defaults of rent | B34: 9 | C34: 12 | D34: 0.5 | F34: =B34+C34/20+D34/240 -> 9.6020833 | H34: Total, £9 12 shilling .5pence
A35: Defaults of rent | F35: =SUM(F25:F33) -> 9.6066667 | G35: =F35-F34 -> 0.0045833333 | H35: Total
A37: Total of quittances and defaults of rent | B37: 11 | C37: 14 | D37: 6.5 | F37: 11.73 | H37: Total of quittances and defaults of rent, £11 14 shilling 6.5pence
A38: Total of quittances and defaults of rent | F38: 11.73 | G38: =F38-F37 -> 0 | H38: Total
A40: Total of rents remaining | B40: 85 | C40: 11 | D40: 11.5 | F40: 85.6 | H40: Total of rents remaining, £85 11 shilling 11.5pence
A41: Total of rents remaining | F41: 85.6 | G41: =F41-F40 -> 0 | H41: Total
A43: Cumin | B43: 0 | C43: 0 | D43: 0 | F43: 0 | H43: The same render account for .5 lb of cumin from the rent of William ate Bere.
A44: Cumin | B44: 0 | C44: 0 | D44: 0 | F44: 0 | H44: 1 lb of cumin from Andrew de Holeweye for annual recognizance.
A45: Cumin | B45: 0 | C45: 0 | D45: 0 | F45: 0 | H45: Total, 1.5 lbs.
A46: Cumin | F46: 0 | G46: 0 | H46: Total
A48: Gloves | B48: 0 | C48: 0 | D48: 0 | F48: 0 | H48: The same render account for 1 pair of gloves from the rent of William Gilberd'.
A49: Gloves | B49: 0 | C49: 0 | D49: 0 | F49: 0 | H49: all delivered to Wolvesey.
A50: Gloves | F50: 0 | G50: 0 | H50: Total
A52: Wax | B52: 0 | C52: 0 | D52: 0 | F52: 0 | H52: The same render account for 1 lb of wax from Adam Osmund' for annual recognizance.
A53: Wax | B53: 0 | C53: 0 | D53: 0 | F53: 0 | H53: all delivered to Wolvesey.
A54: Wax | F54: 0 | G54: 0 | H54: Total
A56: Annual recognizance | B56: 0 | C56: 0 | D56: 3 | F56: 0.01 | H56: The same render account for 3pence from John le Espicir for annual recognizance.
A57: Annual recognizance | B57: 0 | C57: 0 | D57: 6 | F57: 0.03 | H57: 6pence from Henry de Afford' so that he may come and go within the hundred and pay suit of court for the tithing at the 2 hundred-courts.
A58: Annual recognizance | B58: 0 | C58: 0 | D58: 6 | F58: 0.03 | H58: 6pence from William de Stomore for the same.
A59: Annual recognizance | B59: 0 | C59: 0 | D59: 3 | F59: 0.01 | H59: 3pence from Robert Judde for annual recognizance so that he need not pay suit of court for the tithing.
A60: Annual recognizance | B60: 0 | C60: 0 | D60: 3 | F60: 0.01 | H60: 3pence from Robert Faber for annual recognizance.
A61: Annual recognizance | B61: 0 | C61: 0 | D61: 3 | F61: 0.01 | H61: 3pence from Henry ate Thorn' for the same, plus William ate Churche.
A62: Annual recognizance | B62: 0 | C62: 2 | D62: 0 | F62: 0.1 | H62: Total, 2 shilling
A63: Annual recognizance | F63: 0.1 | G63: -1.3877788e-17 | H63: Total
A65: Issues of the manor | B65: 2 | C65: 19 | D65: 10.5 | F65: 2.99 | H65: The same render account for £2 19 shilling 10.5pence from pannage of pigs within the hundred this year.
A66: Issues of the manor | B66: 0 | C66: 0 | D66: 0 | F66: 0 | H66: nothing from foreign pannage or in the park this year for a want of mast.
A67: Issues of the manor | B67: 0 | C67: 0 | D67: 0 | F67: 0 | H67: nothing from the pasturage in the stubble this year.
A68: Issues of the manor | B68: 0 | C68: 7 | D68: 4 | F68: 0.37 | H68: 7 shilling 4pence from winter pasturage in Hydon' which is called Blakedon on the west side of Astederod' which is the common land of East Meon, because the other part is enclosed for the lord's profit.
A69: Issues of the manor | B69: 0 | C69: 0 | D69: 0 | F69: 0 | H69: nothing from the pasturage in Smaldon' this year on account of the lord's stock.
A70: Issues of the manor | B70: 0 | C70: 3 | D70: 0 | F70: 0.15 | H70: 3 shilling from the pasturage of the meadow below Godeshull' sold in winter.
A71: Issues of the manor | B71: 0 | C71: 0 | D71: 0 | F71: 0 | H71: nothing from the pasturage of Innom' in winter or summer this year because it was mown.
A72: Issues of the manor | B72: 1 | C72: 2 | D72: 8 | F72: 1.13 | H72: £1 2 shilling 8pence from summer pasturage sold in Hydon' by agistment by the head.
A73: Issues of the manor | B73: 0 | C73: 7 | D73: 0 | F73: 0.35 | H73: 7 shilling from the pasturage beside the sheepcote of Holecumbe sold in summer.
A74: Issues of the manor | B74: 0 | C74: 4 | D74: 0 | F74: 0.2 | H74: 4 shilling from the pasturage in la Garston sold this year in summer.
A75: Issues of the manor | B75: 0 | C75: 0 | D75: 0 | F75: 0 | H75: nothing from the pasturage of Wodeueslynch' this year for the lord's lambs.
A76: Issues of the manor | B76: 0 | C76: 0 | D76: 0 | F76: 0 | H76: nothing from the pasturage of Bekes this year on account of the lord's sheep.
... A81: Issues of the manor | B81: 0 | C81: 5 | D81: 0 | F81: 0.25 | H81: 5 shilling from the pasturage of Oldefiswer' as far as Selecumbe and Sabwey sold this year.
A82: Issues of the manor | B82: 0 | C82: 2 | D82: 0 | F82: =B82+C82/20+D82/240 -> 0.1 | H82: 2 shilling from the pasturage of the heath beside Hydon sold.
A83: Issues of the manor | B83: 0 | C83: 0 | D83: 8 | F83: 0.03 | H83: 8pence from the pasturage beside the sheepcote of Westcrembe sold.
A84: Issues of the manor | B84: 0 | C84: 0 | D84: 0 | F84: 0 | H84: nothing from the pasturage of the garden this year because it was mown.
A85: Issues of the manor | B85: 0 | C85: 3 | D85: 6 | F85: 0.17 | H85: 3 shilling 6pence from the pasturage of 1 parcel of Selescumbe sold this year because the rest was sown.
A86: Issues of the manor | B86: 0 | C86: 0 | D86: 0 | F86: 0 | H86: nothing from the pasturage of Wodeslynch' this year on account of the lord's lambs.
A87: Issues of the manor | B87: 0 | C87: 0 | D87: 0 | F87: 0 | H87: nothing from the pasturage on this side (citra) of Northebrok' this year because it was fallow.
A88: Issues of the manor | B88: 0 | C88: 0 | D88: 0 | F88: 0 | H88: nothing from the pasturage of Litlecumbe this year on account of the lord's stock.
A89: Issues of the manor | B89: 0 | C89: 2 | D89: 0 | F89: 0.1 | H89: 2 shilling from the pasturage of la Ford' sold as far as the mill and this side of the chapel.
A90: Issues of the manor | B90: 0 | C90: 2 | D90: 0 | F90: 0.1 | H90: 2 shilling from the pasturage from the mill as far as Holewey and this side of the fishpond sold.
A91: Issues of the manor | B91: 0 | C91: 2 | D91: 0 | F91: 0.1 | H91: 2 shilling from the pasturage from the mill as far as Lymput' sold.
A92: Issues of the manor | B92: 0 | C92: 7 | D92: 0 | F92: 0.35 | H92: 7 shilling from the pasturage of Chalvecroft sold.
A93: Issues of the manor | B93: 0 | C93: 0 | D93: 0 | F93: 0 | H93: nothing from the pasturage of Wethull this year on account of the lord's stock.
A94: Issues of the manor | B94: 0 | C94: 0 | D94: 0 | F94: 0 | H94: nothing from the pasturage in ,Woasddon' on account of the lord's lambs.
... A117: Issues of the manor | B117: 1 | C117: 2 | D117: 5 | F117: 1.12 | H117: £1 2 shilling 5pence from the skins sold of 43 wethers, 28 ewes and 30 hoggs in murrain before shearing, at 3pence a skin of wethers, 2.5pence a skin of ewes, and 1.5pence a skin of hoggs.
A118: Issues of the manor | B118: 0 | C118: 3 | D118: 0 | F118: =B118+C118/20+D118/240 -> 0.15 | H118: 3 shilling from the skins sold of 26 wethers and 10 ewes in murrain after shearing, at 1pence a skin.
A119: Issues of the manor | B119: 0 | C119: 9 | D119: 9.75 | F119: 0.49 | H119: 9 shilling 9.75pence from the skins sold of 134 lambs in murrain before weaning, and 23 after weaning and before shearing, at .75pence a skin.
A120: Issues of the manor | B120: 0 | C120: 0 | D120: 3 | F120: 0.01 | H120: 3pence from the skins sold wholesale of 9 lambs in murrain after shearing.
A121: Issues of the manor | B121: 0 | C121: 4 | D121: 0.75 | F121: =B121+C121/20+D121/240 -> 0.203125 | H121: 4 shilling .75pence from 13 cloves of winter cheese sold, at 3.75pence a clove.
A122: Issues of the manor | B122: 6 | C122: 15 | D122: 0 | F122: 6.75 | H122: £6 15 shilling from 15 weys of summer cheese sold, at 9 shilling a wey.
A123: Issues of the manor | B123: 0 | C123: 9 | D123: 0 | F123: 0.45 | H123: 9 shilling from 1 wey of butter sold.
A124: Issues of the manor | B124: 0 | C124: 0 | D124: 0 | F124: 0 | H124: nothing from honey this year.
A125: Issues of the manor | B125: 2 | C125: 2 | D125: 8 | F125: 2.13 | H125: £2 2 shilling 8pence from 3 casks of cider sold, 1 of them with the wood for 16 shilling, and 2 without the wood at 13 shilling 4pence each.
A126: Issues of the manor | B126: 0 | C126: 1 | D126: 0 | F126: 0.05 | H126: 1 shilling from the heriot of Gilbert ate Brok' because he did not have 1 beast.
A127: Issues of the manor | B127: 0 | C127: 1 | D127: 0 | F127: 0.05 | H127: 1 shilling from the heriot of Christina Colevil'.
A128: Issues of the manor | B128: 0 | C128: 1 | D128: 0 | F128: 0.05 | H128: 1 shilling from the heriot of William Aylwyn' for the same.
A129: Issues of the manor | B129: 0 | C129: 0 | D129: 5 | F129: 0.02 | H129: 5pence from the tails and feathers of 2 peacocks sold.
A130: Issues of the manor | B130: 0 | C130: 2 | D130: 1.75 | F130: 0.11 | H130: 2 shilling 1.75pence from dairy produce sold at the audit.
A131: Issues of the manor | B131: 26 | C131: 6 | D131: 9.75 | F131: 26.34 | H131: Total, £26 6 shilling 9.75pence
A132: Issues of the manor | F132: =SUM(F65:F130) -> 26.363125 | G132: =F132-F131 -> 0.023125 | H132: Total
A134: Sale of stock | B134: 0 | C134: 10 | D134: 4 | F134: 0.52 | H134: 10 shilling from 3 old and feeble plough-horses sold, rat 3 shilling 4pence eachi because nearly dead.
A135: Sale of stock | B135: 4 | C135: 2 | D135: 0 | F135: 4.1 | H135: £4 2 shilling from 7 oxen sold, at 12 shilling each for 3, and 1 1 shilling 6pence each for 4.
A136: Sale of stock | B136: 0 | C136: 8 | D136: 0 | F136: 0.4 | H136: 8 shilling from 1 cow sold at Martinmas (11 November).
A137: Sale of stock | B137: 0 | C137: 8 | D137: 0 | F137: 0.4 | H137: 8 shilling from 8 late-born calves sold, at 1 shilling each.
A138: Sale of stock | B138: 1 | C138: 4 | D138: 6 | F138: 1.22 | H138: £1 4 shilling 6pence from 21 wethers sold at Martinmas, at 1 shilling 2pence each.
...

Sheet Expenses
A1: EAST MEON EXPENSES
A2: Heading | B2: £ | C2: s | D2: d | F2: Total in £ | G2: Error | H2: Notes | J2: Fixed investment | K2: Demesne fixed investment
A3: Cost of ploughs | B3: 0 | C3: 14 | D3: 3 | F3: 0.71 | H3: In ironwork of 5 ox-ploughs and 3 horse-ploughs (caruc' affr') for the year and 1 horse-plough (caruc' equin') at the Lenten sowing, 14 shilling 3pence this year, on account of the excessive drought. | J3: =F3 -> 0.71 | K3: =J3 -> 0.71
A4: Cost of ploughs | B4: 0 | C4: 8 | D4: 0 | F4: 0.4 | H4: stipend of the smith forging the ironwork of the said ploughs for the year, 8 shilling by fixed agreement. | J4: =F4 -> 0.4 | K4: =J4/2 -> 0.2
A5: Cost of ploughs | B5: 0 | C5: 3 | D5: 9 | F5: 0.19 | H5: 5 ploughshares bought 3 shilling 9pence. | J5: =F5 -> 0.19 | K5: =J5 -> 0.19
A6: Cost of ploughs | B6: 0 | C6: 0 | D6: 0 | F6: 0 | H6: 2 coulters mended 44.. | J6: =F6 -> 0 | K6: =J6/2 -> 0
A7: Cost of ploughs | B7: 0 | C7: 2 | D7: 11 | F7: 0.15 | H7: 7 plough feet bought 2 shilling 11pence, at 5pence each. | J7: =F7 -> 0.15 | K7: =J7 -> 0.15
A8: Cost of ploughs | B8: 0 | C8: 7 | D8: 4 | F8: 0.37 | H8: a new plough and harrow made and others mended for the year, 7 shilling 4pence by fixed agreement, and so much because the worker was not at the bailiff's table. | J8: =F8 -> 0.37 | K8: =J8/2 -> 0.185
A9: Cost of ploughs | B9: 0 | C9: 0 | D9: 6 | F9: 0.03 | H9: fitting the ploughs with iron tyres 6pence. | J9: =F9 -> 0.03 | K9: =J9 -> 0.03
A10: Cost of ploughs | B10: 0 | C10: 2 | D10: 0 | F10: 0.1 | H10: 6 pairs of wheels bought for the ploughs 2 shilling. | J10: =F10 -> 0.1 | K10: =J10/2 -> 0.05
A11: Cost of ploughs | B11: 0 | C11: 1 | D11: 6 | F11: 0.08 | H11: shoeing 18 plough-horses for the year 1 shilling 6pence. | J11: =F11 -> 0.08 | K11: =J11 -> 0.08
A12: Cost of ploughs | B12: 0 | C12: 0 | D12: 4 | F12: 0.02 | H12: fastening the same 4pence. | J12: =F12 -> 0.02 | K12: =J12/2 -> 0.01
A13: Cost of ploughs | B13: 0 | C13: 2 | D13: 2 | F13: 0.11 | H13: stipend of 1 harrower at both sowings 2 shilling 2pence. | J13: =F13 -> 0.11 | K13: =J13 -> 0.11
A14: Cost of ploughs | B14: 0 | C14: 0 | D14: 4 | F14: 0.02 | H14: 16 halters made from the horses' own hair 4pence. | J14: =F14 -> 0.02 | K14: =J14/2 -> 0.01
A15: Cost of ploughs | B15: 0 | C15: 0 | D15: 1.5 | F15: 0.01 | H15: 1 seed-basket bought 1.5pence. | J15: =F15 -> 0.01 | K15: =J15 -> 0.01
A16: Cost of ploughs | B16: 0 | C16: 9 | D16: 0 | F16: 0.45 | H16: stipend of 3 drovers for the year 9 shilling.
A17: Cost of ploughs | B17: 0 | C17: 10 | D17: 0 | F17: 0.5 | H17: stipend of 2 drovers for the year 10 shilling.
A18: Cost of ploughs | B18: 0 | C18: 3 | D18: 0 | F18: 0.15 | H18: stipend of 1 hayward for the year 3 shilling.
A19: Cost of ploughs | B19: 0 | C19: 3 | D19: 0 | F19: 0.15 | H19: stipend of 1 cowherd for the year 3 shilling.
A20: Cost of ploughs | B20: 0 | C20: 3 | D20: 0 | F20: 0.15 | H20: stipend of 1 keeper of lambs and hoggs for the year 3 shilling.
A21: Cost of ploughs | B21: 0 | C21: 0 | D21: 1 | F21: 0 | H21: ploughing boon-works in winter or Lent, nothing this year, that is, they are bound to plough 26 acres for landrihf in winter and 26 acres in Lent, because the land which William le Fissar' holds is commuted as made clear above, and those who plough for landrihe in winter are bound to thresh seed for 1 acre or give 1pence for the threshing at the lord's will.
A22: Cost of ploughs | B22: 0 | C22: 0 | D22: 3 | F22: 0.01 | H22: blood-letting of oxen 3pence.
A23: Cost of ploughs | B23: 0 | C23: 1 | D23: 0 | F23: 0.05 | H23: hiring men for the ploughs when they plough after dinner 1 shilling.
A24: Cost of ploughs | B24: 5 | C24: 6 | D24: 1.5 | F24: 5.31 | H24: 11 plough-horses bought for the ploughs £5 6 shilling 1.5pence, at 9 shilling each for 3, 9 shilling 6pence each for 2, and 10 shilling each for 6, plus 1.5pence in all.
A25: Cost of ploughs | B25: 6 | C25: 7 | D25: 0 | F25: 6.35 | H25: 10 oxen bought for ploughs £6 7 shilling .25pence, at 12 shilling .25pence for 1, 12 shilling 6pence each for 4, and 13 shilling each for 5..
A26: Cost of ploughs | B26: 0 | C26: 1 | D26: 0 | F26: =B26+C26/20+D26/240 -> 0.05 | H26: 2 sacks bought 1 shilling
A27: Cost of ploughs | B27: 15 | C27: 6 | D27: 11.25 | F27: 15.35 | H27: Total, £15 6 shilling 11.25pence
A28: Cost of ploughs | F28: =SUM(F3:F26) -> 15.36 | G28: =F28-F27 -> 0.01 | H28: Total
A30: Cost of carts | B30: 0 | C30: 0 | D30: 10 | F30: 0.04 | H30: In 1 pair of wheels made from the lord's timber 10pence. | J30: =F30 -> 0.04 | K30: =J30 -> 0.04
A31: Cost of carts | B31: 0 | C31: 4 | D31: 2.5 | F31: 0.21 | H31: an old binding fitted to the said wheels, with clamps and large and small nails bought for the same, and with the stipend of the smith, 4 shilling 2.5pence. | J31: =F31 -> 0.21 | K31: =J31 -> 0.21
A32: Cost of carts | B32: 0 | C32: 0 | D32: 2 | F32: 0.01 | H32: hooping the hubs of the cart with iron 2pence. | J32: =F32 -> 0.01 | K32: =J32 -> 0.01
A33: Cost of carts | B33: 0 | C33: 0 | D33: 6 | F33: 0.03 | H33: fitting the cart with axles for the year 6pence. | J33: =F33 -> 0.03 | K33: =J33 -> 0.03
A34: Cost of carts | B34: 0 | C34: 2 | D34: 10 | F34: 0.14 | H34: clouts, nails and grease bought for the same, 2 shilling 10pence this year, for carrying timber to the chapel. | J34: =F34 -> 0.14 | K34: =J34 -> 0.14
A35: Cost of carts | B35: 0 | C35: 0 | D35: 6 | F35: 0.03 | H35: white leather bought for mending harnesses 6pence. | J35: =F35 -> 0.03 | K35: =J35 -> 0.03
A36: Cost of carts | B36: 0 | C36: 0 | D36: 7 | F36: 0.03 | H36: 1 pair of traces bought 7pence. | J36: =F36 -> 0.03 | K36: =J36 -> 0.03
A37: Cost of carts | B37: 0 | C37: 0 | D37: 6.5 | F37: 0.03 | H37: 1 collar 6.5pence. | J37: =F37 -> 0.03 | K37: =J37 -> 0.03
A38: Cost of carts | B38: 0 | C38: 0 | D38: 2 | F38: 0.01 | H38: 2 halters bought 2pence. | J38: =F38 -> 0.01 | K38: =J38 -> 0.01
A39: Cost of carts | B39: 0 | C39: 0 | D39: 8 | F39: 0.03 | H39: 1 cart-body and 1 cart-rail made anew 8pence. | J39: =F39 -> 0.03 | K39: =J39 -> 0.03
A40: Cost of carts | B40: 0 | C40: 0 | D40: 8 | F40: 0.03 | H40: mending the old cart at various times 8pence in doctoring horses 4pence. | J40: =F40 -> 0.03 | K40: =J40 -> 0.03
A41: Cost of carts | B41: 0 | C41: 2 | D41: 0 | F41: 0.1 | H41: shoeing 2 cart-horses for the year 2 shilling. | J41: =F41 -> 0.1 | K41: =J41 -> 0.1
A42: Cost of carts | B42: 0 | C42: 3 | D42: 0 | F42: 0.15 | H42: stipend of 1 carter for the year 3 shilling
A43: Cost of carts | B43: 0 | C43: 17 | D43: 0 | F43: =B43+C43/20+D43/240 -> 0.85 | H43: Total, 17 shilling
A44: Cost of carts | F44: =SUM(F30:F42) -> 0.84 | G44: =F44-F43 -> -0.01 | H44: Total
A46: Cost of the dairy | B46: 0 | C46: 2 | D46: 3 | F46: 0.11 | H46: In 1 qr 1 bushels of salt bought for the dairy 2 shilling 3pence. | J46: =F46 -> 0.11 | K46: =J46 -> 0.11
A47: Cost of the dairy | B47: 0 | C47: 1 | D47: 3 | F47: 0.06 | H47: 5 bushels of salt bought for the pottage of the manorial servants 1 shilling 3pence. | J47: =F47 -> 0.06 | K47: =J47 -> 0.06
A48: Cost of the dairy | B48: 0 | C48: 0 | D48: 6 | F48: 0.03 | H48: a press bought 6pence. | J48: =F48 -> 0.03 | K48: =J48 -> 0.03
A49: Cost of the dairy | B49: 0 | C49: 1 | D49: 0 | F49: 0.05 | H49: linen and woollen cloth bought 1 shilling. | J49: =F49 -> 0.05 | K49: =J49 -> 0.05
A50: Cost of the dairy | B50: 0 | C50: 0 | D50: 6 | F50: 0.03 | H50: mending buckets and utensils of the dairy 6pence. | J50: =F50 -> 0.03 | K50: =J50 -> 0.03
A51: Cost of the dairy | B51: 0 | C51: 0 | D51: 6 | F51: 0.03 | H51: earthenware pots and pans bought 6pence. | J51: =F51 -> 0.03 | K51: =J51 -> 0.03
A52: Cost of the dairy | B52: 0 | C52: 18 | D52: 6 | F52: 0.93 | H52: grease, copperas and vinegar bought for greasing sheep 18 shilling 6pence. | J52: =F52 -> 0.93 | K52: =J52 -> 0.93
A53: Cost of the dairy | B53: 0 | C53: 7 | D53: 0 | F53: =B53+C53/20+D53/240 -> 0.35 | H53: 28 ells of canvas bought for packing wool 7 shilling, at 3pence an ell. | J53: =F53 -> 0.35 | K53: =J53 -> 0.35
A54: Cost of the dairy | B54: 0 | C54: 1 | D54: 2 | F54: 0.06 | H54: packing the wool and making sacks with thread bought for the same 1 shilling 2pence. | J54: =F54 -> 0.06 | K54: =J54 -> 0.06
A55: Cost of the dairy | B55: 0 | C55: 2 | D55: 2 | F55: 0.11 | H55: 60 hurdles made for the fold 2 shilling, at 2pence per 5 hurdles. | J55: =F55 -> 0.11 | K55: =J55 -> 0.11
A56: Cost of the dairy | B56: 0 | C56: 2 | D56: 8 | F56: 0.13 | H56: wattling 80 hurdles 2 shilling 8pence, at 2pence per 5 hurdles. | J56: =F56 -> 0.13 | K56: =J56 -> 0.13
A57: Cost of the dairy | B57: 0 | C57: 0 | D57: 10 | F57: 0.04 | H57: 30 hurdles made for pens 10pence, at 1pence per 3 hurdles. | J57: =F57 -> 0.04 | K57: =J57 -> 0.04
A58: Cost of the dairy | B58: 0 | C58: 1 | D58: 6 | F58: 0.08 | H58: mending the walls of the sheepcote of Holecumbe, putting in sills, and enclosing, 1 shilling 6pence. | J58: =F58 -> 0.08 | K58: =J58 -> 0.08
A59: Cost of the dairy | B59: 0 | C59: 0 | D59: 8 | F59: 0.03 | H59: cratches made for the hoggs 8pence. | J59: =F59 -> 0.03 | K59: =J59 -> 0.03
A60: Cost of the dairy | B60: 0 | C60: 0 | D60: 8 | F60: 0.03 | H60: roofing and mending the said sheepcote in places 8pence. | J60: =F60 -> 0.03 | K60: =J60 -> 0.03
A61: Cost of the dairy | B61: 0 | C61: 0 | D61: 4 | F61: =B61+C61/20+D61/240 -> 0.016666667 | H61: castrating and spaying pigs 4pence
A62: Cost of the dairy | B62: 2 | C62: 1 | D62: 4 | F62: 2.07 | H62: Total, £2 1 shilling 4pence
A63: Cost of the dairy | F63: =SUM(F46:F61) -> 2.0866667 | G63: =F63-F62 -> 0.016666667 | H63: Total
A65: Cost of buildings | B65: 0 | C65: 3 | D65: 10 | F65: 0.19 | H65: In roofing and mending the barn beside the pinfold and other buildings 3 shilling 10pence. | J65: =F65 -> 0.19 | K65: =J65 -> 0.19
A66: Cost of buildings | B66: 0 | C66: 2 | D66: 9 | F66: 0.14 | H66: rebuilding the walls of the plough-horses' shed which collapsed and making and mending the great fodder-rack with nails bought for the same 2 shilling 9pence. | J66: =F66 -> 0.14 | K66: =J66 -> 0.14
A67: Cost of buildings | B67: 0 | C67: 0 | D67: 4 | F67: 0.02 | H67: mending the gate of the byre with nails bought 4pence. | J67: =F67 -> 0.02 | K67: =J67 -> 0.02
A68: Cost of buildings | B68: 0 | C68: 1 | D68: 7.5 | F68: 0.08 | H68: building and mending the walls of the barley-barn which collapsed 1 shilling 7.5pence. | J68: =F68 -> 0.08 | K68: =J68 -> 0.08
A69: Cost of buildings | B69: 0 | C69: 0 | D69: 6 | F69: 0.03 | H69: mending and fitting with iron 3 shovels and 1 spade 6pence. | J69: =F69 -> 0.03 | K69: =J69 -> 0.03
A70: Cost of buildings | B70: 0 | C70: 2 | D70: 1.5 | F70: 0.11 | H70: enclosing 34 perches on this side of the pinfold and elsewhere in the curia with hedges 2 shilling 1.5pence, at 0.75pence a perch. | J70: =F70 -> 0.11 | K70: =J70 -> 0.11
A71: Cost of buildings | B71: 0 | C71: 0 | D71: 6 | F71: 0.03 | H71: hooping and mending 2 cider-casks and making and hooping 2 tubs 6pence. | J71: =F71 -> 0.03 | K71: =J71 -> 0.03
A72: Cost of buildings | B72: 0 | C72: 0 | D72: 8 | F72: =B72+C72/20+D72/240 -> 0.033333333 | H72: making 2 casks of cider 8pence | J72: =F72 -> 0.033333333 | K72: =J72 -> 0.033333333
A73: Cost of buildings | B73: 0 | C73: 12 | D73: 4 | F73: =B73+C73/20+D73/240 -> 0.61666667 | H73: Total, 12 shilling 4pence
A74: Cost of buildings | F74: =SUM(F65:F72) -> 0.63333333 | G74: =F74-F73 -> 0.016666667 | H74: Total
A76: Cost of the park | B76: 0 | C76: 10 | D76: 8 | F76: =B76+C76/20+D76/240 -> 0.53333333 | H76: In enclosing 4 furlongs 8 perches around the park with hedges 10 shilling 8pence.
A77: Cost of the park | B77: 0 | C77: 5 | D77: 0 | F77: =B77+C77/20+D77/240 -> 0.25 | H77: making and mending the palisade of the park 5 shilling
A78: Cost of the park | C78: 15 | D78: 8 | F78: =B78+C78/20+D78/240 -> 0.78333333 | H78: Total, 15 shilling 8pence
A79: Cost of the park | F79: =SUM(F76:F77) -> 0.78333333 | G79: =F79-F78 -> 0 | H79: Total
A81: Threshing | B81: 2 | C81: 19 | D81: 1.25 | F81: =B81+C81/20+D81/240 -> 2.9552083 | H81: In threshing and winnowing 354 quarters 7 bushels of wheat and curall by piece-work £2 19 shilling 1.25pence, at 2pence a struck quarter.
A82: Threshing | B82: 0 | C82: 10 | D82: 0 | F82: =B82+C82/20+D82/240 -> 0.5 | H82: threshing and winnowing 101 quarters 1 bushels of barley by piece-work 10 shilling 1.5pence, at 1.5pence per 10 struck bushe1 shilling.
A83: Threshing | B83: 1 | C83: 18 | D83: 2.25 | F83: =B83+C83/20+D83/240 -> 1.909375 | H83: threshing and winnowing 572 quarters 7 bushels of oats by piece-work £1 18 shilling 2.25pence, at 1pence per 10 struck bushe1 shilling
A84: Threshing | B84: 5 | C84: 7 | D84: 5.5 | F84: =B84+C84/20+D84/240 -> 5.3729167 | H84: Total, £5 7 shilling 5.5pence
A85: Threshing | F85: =SUM(F81:F83) -> 5.3645833 | G85: =F85-F84 -> -0.0083333333 | H85: Total
A87: Harvest-time | B87: 6 | C87: 12 | D87: 4.25 | F87: =B87+C87/20+D87/240 -> 6.6177083 | H87: In all costs for the great boon-work with 17 other boon-works of 1,807 men who reaped and bound all the corn, together with 1 boon-work of 160 men without food, £6 12 shilling 4.25pence, and each had .25pence of bread and 2 herrings or 1 cheese worth 'Apence, and for the great boon-work they had bread, meat and ale.
A88: Harvest-time | B88: 0 | C88: 1 | D88: 0 | F88: =B88+C88/20+D88/240 -> 0.05 | H88: mowing and tossing the meadow of Munnonce 1 shilling.
A89: Harvest-time | B89: 0 | C89: 1 | D89: 4 | F89: =B89+C89/20+D89/240 -> 0.066666667 | H89: mowing and tossing the garden 1 shilling 4pence
A90: Harvest-time | B90: 6 | C90: 14 | D90: 8.25 | F90: =B90+C90/20+D90/240 -> 6.734375 | H90: Total, £6 14 shilling 8.25pence
A91: Harvest-time | F91: =SUM(F87:F89) -> 6.734375 | G91: =F91-F90 -> 0 | H91: Total
A93: Expenses of the steward | B93: 0 | C93: 11 | D93: 8.5 | F93: =B93+C93/20+D93/240 -> 0.58541667 | H93: In expenses of the steward at the 2 hundred-courts by 1 tally 11 shilling 8.5pence.
A94: Expenses of the steward | B94: 6 | C94: 15 | D94: 6 | F94: =B94+C94/20+D94/240 -> 6.775 | H94: expenses of the bailiff for the year £6 15 shilling 6pence.
A95: Expenses of the steward | B95: 0 | C95: 3 | D95: 0 | F95: =B95+C95/20+D95/240 -> 0.15 | H95: fur for the summer livery of the same 3 shilling
A96: Expenses of the steward | B96: 7 | C96: 10 | D96: 2.5 | F96: =B96+C96/20+D96/240 -> 7.5104167 | H96: Total, £7 10 shilling 2.5pence
A97: Expenses of the steward | F97: =SUM(F93:F95) -> 7.5104167 | G97: =F97-F96 -> 0 | H97: Total
A99: Total of all expenses | B99: 39 | C99: 5 | D99: 7.5 | F99: 39.28 | H99: Total of all expenses, £39 5 shilling 7.5pence
A100: Total of all expenses | F100: =F99 -> 39.28 | G100: =F100-F99 -> 0 | H100: Total
A102: And he owes | B102: 230 | C102: 16 | D102: 4 | F102: 230.82 | H102: And he owes, £230 16 shilling 4pence
A103: And he owes | F103: 230.82 | G103: 0 | H103: Total
A105: Cash deliveries | B105: 139 | C105: 2 | D105: 0 | F105: 139.1 | H105: Delivered to Sir Geoffrey, treasurer of Wolvesey, by 2 tallies, £139 2 shilling
A107: And he owes clear | B107: 91 | C107: 14 | D107: 4 | F107: 91.72 | H107: And he owes clear, £91 14 shilling 4pence, of which £36 3.5pence against Richard de Poukepole, and £55 14 shilling 0.5pence against Adam de Cumbe.
A109: Total of all expenses per account | F109: =F100 -> 39.28
A110: Total of all expenses (calculated here) | F110: =F97+F91+F85+F79+F74+F63+F44+F28 -> 39.312708 | G110: =F110-F109 -> 0.032708333
A111: Total fixed investment | F111: =SUM(J3:J74) -> 5.5833333
A112: Total Demesne fixed investment | F112: =SUM(K3:K73) -> 5.1283333

Sheet Issues of the Grange
A1: Gross Output | B1: Total Quantity | C1: Account Total Quarters | D1: Bought in Total Quarters | E1: Received from churchscot | F1: Sold Total Quarters | G1: Difference Produced+Bought-Sold | H1: Weighted Average Price per Quarter | I1: Value of Total Production weighted
A2: wheat | B2: 357.875 | D2: 0 | F2: 274.25 | G2: =B2-F2 -> 83.625 | H2: 0.27537223 | I2: =H2*B2 -> 98.548836
A3: curall | B3: 14 | D3: 0 | F3: 14 | G3: =B3-F3 -> 0 | H3: 0.16666667 | I3: =H3*B3 -> 2.3333333
A4: barley | B4: 115.6875 | D4: 0 | F4: 28.625 | G4: =B4-F4 -> 87.0625 | H4: 0.19366812 | I4: =H4*B4 -> 22.404981
A5: oats | B5: 616.5625 | D5: 0 | F5: 275.375 | G5: =B5-F5 -> 341.1875 | H5: 0.10320396 | I5: =H5*B5 -> 63.631694
A8: Total Production
A9: Sales of corn (as recorded in accounts)
A12: Net output | B12: Gross output | C12: Seed quarters | D12: Seed bushels | E12: Seed total quarters | F12: tithe quarters | G12: tithe bushels | H12: tithe total | I12: manorial servants quarters | J12: manorial servants bushels | K12: manorial servants total quarters | L12: output net of tithe, seed, liveries | M12: in stock from last year | N12: Price in £ | O12: Value of net output in £ | P12: Value of sales (in "Sale of Corn") in £
A13: wheat | B13: =B2 -> 357.875 | C13: 67 | D13: 6 | E13: =C13+D13/8 -> 67.75 | I13: =8+10+5 -> 23 | J13: =2+7 -> 9 | K13: =I13+J13/8 -> 24.125 | L13: =B13-E13-H13-K13 -> 266 | N13: =H2 -> 0.27537223 | O13: =N13*L13 -> 73.249012
A14: curall | B14: =B3 -> 14 | E14: =C14+D14/8 -> 0 | K14: =I14+J14/8 -> 0 | L14: =B14-E14-H14-K14 -> 14 | N14: =H3 -> 0.16666667 | O14: =N14*L14 -> 2.3333333
A15: barley | B15: =B4 -> 115.6875 | C15: 26.5 | D15: 4.5 | E15: =C15+D15/8 -> 27.0625 | I15: =32.5+10+5+4+4+3 -> 58.5 | J15: =3+1.5+2.5+5 -> 12 | K15: =I15+J15/8 -> 60 | L15: =B15-E15-H15-K15 -> 28.625 | N15: =H4 -> 0.19366812 | O15: =N15*L15 -> 5.54375
A16: oats | B16: =B5 -> 616.5625 | C16: 190 | E16: =C16+D16/8 -> 190 | I16: =18+52.5+5+42+10.5+1.5+20 -> 149.5 | K16: =I16+J16/8 -> 149.5 | L16: =B16-E16-H16-K16 -> 277.0625 | N16: =H5 -> 0.10320396 | O16: =N16*L16 -> 28.593948
A18: Total

Sheet Issues of the Mills

Sheet Stock
A1: EAST MEON STOCK ACCOUNT
C3: added | G3: subtracted
A4: Livestock | B4: Inherited stock | C4: added | D4: strays | E4: herbage | F4: churchscot | G4: of which in default | H4: sold | I4: in murrain | J4: accounted for elsewhere | K4: End-period stock | L4: cross-check | M4: stock building | N4: raw production | O4: Unit price (£) | P4: Value of stock (£) at given value | Q4: Value of stock (£) at sales prices | R4: Sales in (£) | S4: Value of stock building (£) | T4: Value of production (£) at sales prices | U4: Details
A5: Cart-horses | B5: 2 | K5: 2
A6: Mares
A7: Plough horses | B7: 18 | C7: 11 | H7: 3 | I7: 9 | K7: 17 | R7: =Receipts!F134 -> 0.52
A8: Colts (unspecified years) | B8: 2 | I8: 2 | K8: 0
A9: Colts (2 years) | B9: 1 | K9: 1
A10: Colts (1 year)
A11: Foals | B11: 2 | I11: 1 | K11: 1
A12: Oxen | B12: 57 | C12: =8+3+10 -> 21 | H12: 7 | I12: 5 | K12: 66 | R12: =Receipts!F135 -> 4.1
A13: Bulls | B13: 1 | K13: 1
A14: Cows | B14: 18 | C14: =4+1 -> 5 | H14: 1 | K14: 22 | R14: =Receipts!F136 -> 0.4
A15: Steers | B15: 11 | C15: 1 | J15: =8+4 -> 12 | K15: 0
A16: Bullocks | B16: 9 | K16: 9
A17: Yearlings | B17: 6 | K17: 6
A18: Calves | B18: 22 | H18: 8 | I18: 1 | K18: 13 | R18: =Receipts!F137 -> 0.4
A19: Wethers | B19: 450 | C19: 129 | H19: 21 | I19: =43+26 -> 69 | J19: 3 | K19: 486 | R19: =Receipts!F138 -> 1.22
A20: Rams
A21: Ewes | B21: 797 | C21: =184+6 -> 190 | H21: =100 -> 100 | I21: =12+26+9 -> 47 | J21: =9 -> 9 | K21: 831 | R21: =Receipts!F139 -> 5
A22: Hoggs | B22: 402 | H22: 9 | I22: =30 -> 30 | J22: =129+184+50 -> 363 | K22: 0 | R22: =Receipts!F140 -> 0.23
A23: Lambs | B23: 555 | C23: =9+29 -> 38 | I23: =134+23+9+3 -> 169 | K23: 424
A24: Boars
A25: Sows | B25: 2 | C25: 2 | I25: 2 | K25: 2
A26: Pigs | B26: 35 | C26: 28 | H26: 19 | I26: 4 | K26: 50 | R26: =Receipts!F141 -> 3.32
A27: Hoggets | B27: 50 | I27: 10 | J27: =2+38 -> 40 | K27: 0
A28: Piglets | C28: =45+8 -> 53 | I28: 9 | K28: 44
A29: Swans | B29: 3 | C29: 2 | I29: 1 | K29: 4
A30: Peacocks | B30: 6 | I30: 1 | K30: 5
A31: Total Value | R31: =SUM(R5:R30) -> 15.19
A34: Wool
A35: Coarse wool | C35: 1405 | J35: 1405 | K35: 0 | O35: 0.02 | T35: =O35*J35 -> 28.1
A36: Lamb's wool | C36: 433 | J36: 433 | K36: 0 | O36: 0.01 | T36: =O36*J36 -> 4.33
A37: Wool locks | C37: 20 cloves 5 lb | H37: 20 cloves 5 lb | R37: =Receipts!F110 -> 0.91 | T37: =R37 -> 0.91
A38: Wool sold at shearing
A39: Total wool | R39: =R37 -> 0.91 | T39: =SUM(T35:T38) -> 33.34
A42: Hides
A43: Ox hides | C43: 5
A44: plough horses | C44: 9
A45: colts | C45: 2
A46: Mare
A47: Steer
A48: calves | C48: 1
A49: pigs
A50: Woolskins
A51: wethers | C51: 43 | H51: 43 | K51: 0
A52: rams
A53: ewes | C53: 38 | H53: 38 | K53: 0
A54: hoggs | C54: 30 | H54: 30 | K54: 0 | U54: issues only lists 28 whethers but stock lists 38
A55: Woolskins | C55: =SUM(C51:C54) -> 111 | H55: =SUM(H51:H54) -> 111 | O55: =R55/H55 -> 0.01009009 | R55: =Receipts!F117 -> 1.12 | T55: =O55*C55 -> 1.12
A56: Bareskins
A57: wethers | C57: 26 | H57: 26 | K57: 0 | O57: =R57/H57 -> 0 | T57: =O57*C57 -> 0
A58: rams
A59: ewes | C59: 10 | H59: 10 | K59: 0 | O59: =R59/H59 -> 0 | T59: =O59*C59 -> 0
A60: hoggs
A61: Bareskins (total) | C61: =SUM(C57:C60) -> 36 | H61: =SUM(H57:H60) -> 36 | O61: =R61/H61 -> 0.0041666667 | R61: =Receipts!F118 -> 0.15 | T61: =O61*C61 -> 0.15
A62: Lambskins | C62: 166 | H62: 166 | K62: 0 | O62: =R62/H62 -> 0.0029518072 | R62: =Receipts!F119 -> 0.49 | T62: =O62*C62 -> 0.49
A63: Rotted skins
A64: Shorn skins
A65: Total | R65: =SUM(R45:R64) -> 1.76 | T65: =SUM(T55:T62) -> 1.76
A68: Poultry stock
A69: Hens | F69: 325 | G69: =5+22+7+2+2+2 -> 40 | H69: 286 | K69: 0 | O69: =R69/H69 -> 0.0041608392 | R69: =Receipts!F111 -> 1.19 | T69: =O69*H69 -> 1.19
A70: Geese
A71: Capons (from chickens)
A72: Cocks & hens
A73: Total poultry stock | R73: =SUM(R67:R72) -> 1.19 | T73: =SUM(T69:T72) -> 1.19
A74: Total poultry excluding churchscot
A76: Poultry production
A77: Eggs
A78: Cocks & hens from churchscot of customary tenants
A79: Sum of above
A80: Total
A83: Meat
A84: Beef
A85: Mutton
A86: Pork
A87: Total
A89: Cheese
A90: Winter cheese | C90: 37 | H90: 37 | K90: 0 | O90: =R90/H90 -> 0.0054898649 | R90: =Receipts!F121 -> 0.203125 | T90: =O90*C90 -> 0.203125
A91: Summer cheese | C91: 176 | H91: 173 | J91: =2+1 -> 3 | K91: 0 | O91: =R91/H91 -> 0.039017341 | R91: =Receipts!F122 -> 6.75 | T91: =O91*C91 -> 6.867052
A92: Total | R92: =SUM(R90:R91) -> 6.953125 | T92: =SUM(T90:T91) -> 7.070177
A94: Butter
A95: Butter | C95: 1 | H95: 1 | K95: 0 | R95: =Receipts!F123 -> 0.45 | T95: =R95 -> 0.45
A96: Total | R96: =SUM(R95) -> 0.45 | T96: =T95 -> 0.45
A98: Total Dairy Sales
A101: Cider
A102: Cider | B102: 3 | C102: 2 | H102: 3 | K102: 2 | R102: =Receipts!F125 -> 2.13 | T102: =R102 -> 2.13
A103: Total | R103: =SUM(R102) -> 2.13 | T103: =T102 -> 2.13
A105: Additional Information (not necessarily useful)
A106: Utensils
A107: ploughs
A108: carts
A109: cart-ropes
A110: corn baskets
A111: seed-sacks
A112: seed basket
A113: locks for the doors
A114: lead vessel
A115: brass pots
A116: pans
...

Sheet raw data
A1: Heading | B1: Sentence | C1: Total in Pounds | D1: Pounds | E1: Shillings | F1: Pence | G1: Corn | H1: Total Quarters Except 1 | I1: Total Bushels Except 1 | J1: Total Corn Cross-Check | K1: Total Corn Manorial Account | L1: Corn Quantity Error | M1: Quarters 1 | N1: Bushels 1 | O1: Quarters 2 | P1: Bushels 2 | Q1: Quarters 3 | R1: Bushels 3 | S1: Quarters 4 | T1: Bushels 4 | U1: Quarters 5 | V1: Bushels 5 | W1: Quarters 6 | X1: Bushels 6 | Y1: shilling a quarter 1 | Z1: pence a quarter 1 | AA1: shilling a quarter 2 | AB1: pence a quarter 2 | AC1: shilling a quarter 3 | AD1: pence a quarter 3 | AE1: shilling a quarter 4 | AF1: pence a quarter 4 | AG1: shilling a quarter 5 | AH1: pence a quarter 5 | AI1: shilling a bushel 1 | AJ1: pence a bushel 1 | AK1: shilling a bushel 2 | AL1: pence a bushel 2 | AM1: shilling a bushel 3 | AN1: pence a bushel 3 | AO1: shilling a bushel 4 | AP1: pence a bushel 4
A2: Arrears | B2: Nicholas de Ychen', bailiff, and Richard Pokepole and Adam de Cumbe, reeves, render account for £94 4 shilling 10.5pence of arrears from the previous year. | C2: 94.24 | D2: 94 | E2: 4 | F2: 10.5 | H2: 0 | I2: 0 | J2: 0 | K2: 0 | L2: 0 | M2: 0 | N2: 0
A3: Arrears | B3: All delivered to Sir Geoffrey, treasurer of Wolvesey, by 1 tally. | C3: 0 | D3: 0 | E3: 0 | F3: 0 | H3: 0 | I3: 0 | J3: 0 | K3: 0 | L3: 0 | M3: 0 | N3: 0
A4: Arrears | B4: They are quit. | C4: 0 | D4: 0 | E4: 0 | F4: 0 | H4: 0 | I4: 0 | J4: 0 | K4: 0 | L4: 0 | M4: 0 | N4: 0
A5: Rents of assize | B5: The same render account for £23 2 shilling 8.5pence for all rents of assize at Christmas. | C5: 23.14 | D5: 23 | E5: 2 | F5: 8.5 | H5: 0 | I5: 0 | J5: 0 | K5: 0 | L5: 0 | M5: 0 | N5: 0
A6: Rents of assize | B6: £23 2 shilling 8.5pence at Easter (22 April). | C6: 23.14 | D6: 23 | E6: 2 | F6: 8.5 | H6: 0 | I6: 0 | J6: 0 | K6: 0 | L6: 0 | M6: 0 | N6: 0
A7: Rents of assize | B7: £23 2 shilling 8.5pence at the feast of St John the Baptist (24 June). | C7: 23.14 | D7: 23 | E7: 2 | F7: 8.5 | H7: 0 | I7: 0 | J7: 0 | K7: 0 | L7: 0 | M7: 0 | N7: 0
A8: Rents of assize | B8: £27 18 shilling 4pence at Michaelmas (29 September). | C8: 27.92 | D8: 27 | E8: 18 | F8: 4 | H8: 0 | I8: 0 | J8: 0 | K8: 0 | L8: 0 | M8: 0 | N8: 0
A9: Rents of assize | B9: Total, £97 6 shilling 5.5pence | C9: 97.32 | D9: 97 | E9: 6 | F9: 5.5 | H9: 0 | I9: 0 | J9: 0 | K9: 0 | L9: 0 | M9: 0 | N9: 0
A10: Increment | B10: The same render account for .5pence from John Miles for the increment of rent for a certain purpresture which before he encroached upon without licence of the lorpence Total the same. | C10: 0.02 | D10: 0 | E10: 0 | F10: 5 | H10: 0 | I10: 0 | J10: 0 | K10: 0 | L10: 0 | M10: 0 | N10: 0
A11: Total of all rents with increment | B11: Total of all rents with increment, £97 6 shilling 6pence | C11: 97.33 | D11: 97 | E11: 6 | F11: 6 | H11: 0 | I11: 0 | J11: 0 | K11: 0 | L11: 0 | M11: 0 | N11: 0
A12: Quittances | B12: In quittance of 1 reeve for the year 5 shilling. | C12: 0.25 | D12: 0 | E12: 5 | F12: 0 | H12: 0 | I12: 0 | J12: 0 | K12: 0 | L12: 0 | M12: 0 | N12: 0
A13: Quittances | B13: 8 ploughmen, 3 shepherds and 1 swineherd for the year £1 10 shilling, or 2 shilling 6pence each. | C13: 1.5 | D13: 1 | E13: 10 | F13: 0 | H13: 0 | I13: 0 | J13: 0 | K13: 0 | L13: 0 | M13: 0 | N13: 0
... A78: Issues of the manor | B78: 8 shilling 5pence from pinfolding sheep this year, at 1pence per 5 sheep, unless they have 20 sheep, because then they give the twentieth sheep. | C78: 0.42 | D78: 0 | E78: 8 | F78: 5 | H78: 0 | I78: 0 | J78: 0 | K78: 0 | L78: 0 | M78: 0 | N78: 0
A79: Issues of the manor | B79: 2 shilling 2pence from 26 customary tenants because the land of William le Fissar' is commuted, each of whom ploughs for landrihe and everyone is bound to thresh separately 3 bushels of wheat for sowing over 1 acre in winter or give 1pence at the lord's will for the threshing. | C79: 0.11 | D79: 0 | E79: 2 | F79: 2 | G79: wheat | H79: 0 | I79: 3 | J79: 0.375 | K79: 0.375 | L79: 0 | M79: 0 | N79: 3
A80: Issues of the manor | B80: £3 4 shilling 9pence from 448 labour services by the perch sold this year, at 2pence each for 329, and 1pence each for 119. | C80: 3.24 | D80: 3 | E80: 4 | F80: 9 | H80: 0 | I80: 0 | J80: 0 | K80: 0 | L80: 0 | M80: 0 | N80: 0
A81: Issues of the manor | B81: nothing from Avice de Quorteslod' separately because she worked with the others. | C81: 0 | D81: 0 | E81: 0 | F81: 0 | H81: 0 | I81: 0 | J81: 0 | K81: 0 | L81: 0 | M81: 0 | N81: 0
A82: Issues of the manor | B82: 1 shilling from William Ramwyle for release from labour service for the year. | C82: 0.05 | D82: 0 | E82: 1 | F82: 0 | H82: 0 | I82: 0 | J82: 0 | K82: 0 | L82: 0 | M82: 0 | N82: 0
A83: Issues of the manor | B83: nothing from John de Halewell' because he worked with the others. | C83: 0 | D83: 0 | E83: 0 | F83: 0 | H83: 0 | I83: 0 | J83: 0 | K83: 0 | L83: 0 | M83: 0 | N83: 0
A84: Issues of the manor | B84: nothing from coarse wool and lamb's-wool here because it is sent to Wolvesey. | C84: 0 | D84: 0 | E84: 0 | F84: 0 | H84: 0 | I84: 0 | J84: 0 | K84: 0 | L84: 0 | M84: 0 | N84: 0
A85: Issues of the manor | B85: 18 shilling 1.5pence from 20 cloves 5 lb of wool locks sold, at 10.5pence a clove. | C85: 0.91 | D85: 0 | E85: 18 | F85: 1.5 | H85: 0 | I85: 0 | J85: 0 | K85: 0 | L85: 0 | M85: 0 | N85: 0
A86: Issues of the manor | B86: £1 3 shilling 10pence from 286 hens from churchscot sold. | C86: 1.19 | D86: 1 | E86: 3 | F86: 10 | H86: 0 | I86: 0 | J86: 0 | K86: 0 | L86: 0 | M86: 0 | N86: 0
A87: Issues of the manor | B87: 6 shilling from the hides sold of 9 plough-horses in murrain, at 8pence each. | C87: 0.33 | D87: 0 | E87: 6 | F87: 8 | H87: 0 | I87: 0 | J87: 0 | K87: 0 | L87: 0 | M87: 0 | N87: 0
A88: Issues of the manor | B88: 1 shilling from the hides of 2 colts sold. | C88: 0.05 | D88: 0 | E88: 1 | F88: 0 | H88: 0 | I88: 0 | J88: 0 | K88: 0 | L88: 0 | M88: 0 | N88: 0
A89: Issues of the manor | B89: 5 shilling 6pence from the hides and flesh sold of 2 oxen in murrain. | C89: 0.28 | D89: 0 | E89: 5 | F89: 6 | H89: 0 | I89: 0 | J89: 0 | K89: 0 | L89: 0 | M89: 0 | N89: 0
A90: Issues of the manor | B90: 6 shilling from the hides sold of 3 oxen in murrain. | C90: 0.3 | D90: 0 | E90: 6 | F90: 0 | H90: 0 | I90: 0 | J90: 0 | K90: 0 | L90: 0 | M90: 0 | N90: 0
A91: Issues of the manor | B91: 1pence from the hide sold of 1 calf in murrain. | C91: 0 | D91: 0 | E91: 0 | F91: 1 | H91: 0 | I91: 0 | J91: 0 | K91: 0 | L91: 0 | M91: 0 | N91: 0
... A115: Sale of stock | B115: Total, £15 3 shilling 6pence | C115: 15.18 | D115: 15 | E115: 3 | F115: 6 | H115: 0 | I115: 0 | J115: 0 | K115: 0 | L115: 0 | M115: 0 | N115: 0
A116: Sale of corn | B116: The same render account for £75 10 shilling 5pence from 274 quarters 2 bushels of wheat sold, at 4 shilling a quarters for 29 quarters 2 bushels, 5 shilling a quarters for 70 quarters 6 bushels, 5 shilling 4pence a quarters for 82 quarters 3 bushels, 6 shilling a quarters for 18 quarters 2 bushels, and 6 shilling 8pence a quarters for 73 quarters 5 bushels. | C116: 75.52 | D116: 75 | E116: 10 | F116: 5 | G116: wheat | H116: 272 | I116: 18 | J116: 274.25 | K116: 274.25 | L116: 0 | M116: 274 | N116: 2 | O116: 29 | P116: 2 | Q116: 70 | R116: 6 | S116: 82 | T116: 3 | U116: 18 | V116: 2 | W116: 73 | X116: 5 | Y116: 4 | Z116: 0 | AA116: 5 | AB116: 0 | AC116: 5 | AD116: 4 | AE116: 6 | AF116: 0 | AG116: 6 | AH116: 8
A117: Sale of corn | B117: £2 6 shilling 8pence from 14 quarters of curall sold, at 3 shilling 4pence a quarters. | C117: 2.33 | D117: 2 | E117: 6 | F117: 8 | G117: curall | H117: 14 | I117: 0 | J117: 14 | K117: 14 | L117: 0 | M117: 14 | N117: 0 | Y117: 3 | Z117: 4
A118: Sale of corn | B118: £5 10 shilling 10.5pence from 28 quarters 5 bushels of barley sold, at 4 shilling a quarters for 25 quarters, and 3 shilling a quarters for 3 quarters 5 bushels. | C118: 5.54 | D118: 5 | E118: 10 | F118: 10.5 | G118: barley | H118: 28 | I118: 5 | J118: 28.625 | K118: 28.625 | L118: 0 | M118: 28 | N118: 5 | O118: 25 | P118: 0 | Q118: 3 | R118: 5 | Y118: 4 | Z118: 0 | AA118: 3 | AB118: 0
A119: Sale of corn | B119: £28 8 shilling 4.75pence from 275 quarters 3 bushels of oats sold, at 1 shilling 8pence a quarters for 55 quarters 3 bushels, 2 shilling a quarters for 86 quarters 3 bushels, 2 shilling 2pence a quarters for 50 quarters 5 bushels, and 2 shilling 4pence a quarters for 83 quarters. | C119: 28.42 | D119: 28 | E119: 8 | F119: 4.75 | G119: oats | H119: 274 | I119: 11 | J119: 275.375 | K119: 275.375 | L119: 0 | M119: 275 | N119: 3 | O119: 55 | P119: 3 | Q119: 86 | R119: 3 | S119: 50 | T119: 5 | U119: 83 | V119: 0 | Y119: 1 | Z119: 8 | AA119: 2 | AB119: 0 | AC119: 2 | AD119: 2 | AE119: 2 | AF119: 4
A120: Sale of corn | B120: Total of all corn sold, £111 16 shilling 4.25pence | C120: 111.82 | D120: 111 | E120: 16 | F120: 4.25 | H120: 0 | I120: 0 | J120: 0 | K120: 0 | L120: 0 | M120: 0 | N120: 0
A121: Farm of the mill | B121: The same render account for £1 15 shilling from the mill let at farm this year. | C121: 1.75 | D121: 1 | E121: 15 | F121: 0 | H121: 0 | I121: 0 | J121: 0 | K121: 0 | L121: 0 | M121: 0 | N121: 0
A122: Farm of the mill | B122: Total, £1 15 shilling | C122: 1.75 | D122: 1 | E122: 15 | F122: 0 | H122: 0 | I122: 0 | J122: 0 | K122: 0 | L122: 0 | M122: 0 | N122: 0
A123: Entry and marriage fines with tithingpenny | B123: The same render account for £3 6 shilling 8pence from all the tithings of the hundred for tithingpenny at the hundred-court of Martinmas. | C123: 3.33 | D123: 3 | E123: 6 | F123: 8 | H123: 0 | I123: 0 | J123: 0 | K123: 0 | L123: 0 | M123: 0 | N123: 0
A124: Entry and marriage fines with tithingpenny | B124: £3 6 shilling 8pence from the same tithings at the hundred-court of Hockday. | C124: 3.33 | D124: 3 | E124: 6 | F124: 8 | H124: 0 | I124: 0 | J124: 0 | K124: 0 | L124: 0 | M124: 0 | N124: 0
A125: Entry and marriage fines with tithingpenny | B125: £2 10 shilling from Nicholas, son and heir of Nicholas de Langriss', for fine to have all the lands and tenements which belonged to his father in the manor of East Meon. | C125: 2.5 | D125: 2 | E125: 10 | F125: 0 | H125: 0 | I125: 0 | J125: 0 | K125: 0 | L125: 0 | M125: 0 | N125: 0
A126: Entry and marriage fines with tithingpenny | B126: 13 shilling 4pence from Cecilia, relict of Gilbert ate Brok', to retain 1 messuage and 0.5 virgate of land which belonged to her husband. | C126: 0.67 | D126: 0 | E126: 13 | F126: 4 | H126: 0 | I126: 0 | J126: 0 | K126: 0 | L126: 0 | M126: 0 | N126: 0
A127: Entry and marriage fines with tithingpenny | B127: 4 shilling from William de Radesole to have 1.5 acres of land by surrender of Richard ate Burgh, and the aforesaid William will relieve the said Richard of 5.5pence annual rent. | C127: 0.22 | D127: 0 | E127: 4 | F127: 5.5 | H127: 0 | I127: 0 | J127: 0 | K127: 0 | L127: 0 | M127: 0 | N127: 0
A128: Entry and marriage fines with tithingpenny | B128: 1 shilling from Richard Clericus to have 1 plot which contains 2 day-works of land by surrender of William ate Church', and he will relieve the said William of 1 shilling annual rent. | C128: 0.05 | D128: 0 | E128: 1 | F128: 0 | H128: 0 | I128: 0 | J128: 0 | K128: 0 | L128: 0 | M128: 0 | N128: 0
A129: Entry and marriage fines with tithingpenny | B129: 3 shilling from Roginald Boll' to have 1 acre of land by surrender of John Tribald, and he will relieve the said John of 6pence annual rent. | C129: 0.17 | D129: 0 | E129: 3 | F129: 6 | H129: 0 | I129: 0 | J129: 0 | K129: 0 | L129: 0 | M129: 0 | N129: 0
A130: Entry and marriage fines with tithingpenny | B130: £1 13 shilling 4pence from Thomas, son of William de Schireve, to have 1 messuage and 1 virgate of land which belonged to his father. | C130: 1.67 | D130: 1 | E130: 13 | F130: 4 | H130: 0 | I130: 0 | J130: 0 | K130: 0 | L130: 0 | M130: 0 | N130: 0
A131: Entry and marriage fines with tithingpenny | B131: 6 shilling 8pence from Richard Corps to have 3.5 acres of land by surrender of William ate Wod'. | C131: 0.33 | D131: 0 | E131: 6 | F131: 8 | H131: 0 | I131: 0 | J131: 0 | K131: 0 | L131: 0 | M131: 0 | N131: 0
... A236: Cost of buildings | B236: mending the gate of the byre with nails bought 4pence. | C236: 0.02 | D236: 0 | E236: 0 | F236: 4 | H236: 0 | I236: 0 | J236: 0 | K236: 0 | L236: 0 | M236: 0 | N236: 0
A237: Cost of buildings | B237: building and mending the walls of the barley-barn which collapsed 1 shilling 7.5pence. | C237: 0.08 | D237: 0 | E237: 1 | F237: 7.5 | G237: barley | H237: 0 | I237: 0 | J237: 0 | K237: 0 | L237: 0 | M237: 0 | N237: 0
A238: Cost of buildings | B238: mending and fitting with iron 3 shovels and 1 spade 6pence. | C238: 0.03 | D238: 0 | E238: 0 | F238: 6 | H238: 0 | I238: 0 | J238: 0 | K238: 0 | L238: 0 | M238: 0 | N238: 0
A239: Cost of buildings | B239: enclosing 34 perches on this side of the pinfold and elsewhere in the curia with hedges 2 shilling 1.5pence, at 0.75pence a perch. | C239: 0.11 | D239: 0 | E239: 2 | F239: 1.5 | H239: 0 | I239: 0 | J239: 0 | K239: 0 | L239: 0 | M239: 0 | N239: 0
A240: Cost of buildings | B240: . | C240: 0 | D240: 0 | E240: 0 | F240: 0 | H240: 0 | I240: 0 | J240: 0 | K240: 0 | L240: 0 | M240: 0 | N240: 0
A241: Cost of buildings | B241: hooping and mending 2 cider-casks and making and hooping 2 tubs 6pence. | C241: 0.03 | D241: 0 | E241: 0 | F241: 6 | H241: 0 | I241: 0 | J241: 0 | K241: 0 | L241: 0 | M241: 0 | N241: 0
A242: Cost of buildings | B242: making 2 casks of cider 8pence Total, 12 shilling 4pence | C242: 0.63 | D242: 0 | E242: 12 | F242: 8 | H242: 0 | I242: 0 | J242: 0 | K242: 0 | L242: 0 | M242: 0 | N242: 0
A243: Cost of the park | B243: In enclosing 4 furlongs 8 perches around the park with hedges 10 shilling 8pence. | C243: 0.53 | D243: 0 | E243: 10 | F243: 8 | H243: 0 | I243: 0 | J243: 0 | K243: 0 | L243: 0 | M243: 0 | N243: 0
A244: Cost of the park | B244: making and mending the palisade of the park 5 shilling Total, 15 shilling 8pence | C244: 0.28 | D244: 0 | E244: 5 | F244: 8 | H244: 0 | I244: 0 | J244: 0 | K244: 0 | L244: 0 | M244: 0 | N244: 0
A245: Cost of the mill | B245: Nothing this year. | C245: 0 | D245: 0 | E245: 0 | F245: 0 | H245: 0 | I245: 0 | J245: 0 | K245: 0 | L245: 0 | M245: 0 | N245: 0
A246: Threshing | B246: In threshing and winnowing 354 quarters 7 bushels of wheat and curall by piece-work £219 shilling 1.25pence, at 2pence a struck quarter. | C246: 219 | D246: 219 | E246: 0 | F246: 0 | G246: curall, wheat | H246: 354 | I246: 7 | J246: 354.875 | K246: 354.875 | L246: 0 | M246: 354 | N246: 7
A247: Threshing | B247: . | C247: 0 | D247: 0 | E247: 0 | F247: 0 | H247: 0 | I247: 0 | J247: 0 | K247: 0 | L247: 0 | M247: 0 | N247: 0
A248: Threshing | B248: threshing and winnowing 101 quarters 1 bushels of barley by piece-work 10 shilling 1.5pence, at 1.5pence per 10 struck bushe1 shilling. | C248: 0.51 | D248: 0 | E248: 10 | F248: 1.5 | G248: barley | H248: 101 | I248: 1 | J248: 101.125 | K248: 101.125 | L248: 0 | M248: 101 | N248: 1
A249: Threshing | B249: threshing and winnowing 572 quarters 7 bushels of oats by piece-work £1 18 shilling 2.25pence, at 1pence per 10 struck bushe1 shilling Total, £57 shilling 5.5pence | C249: 1.91 | D249: 1 | E249: 18 | F249: 2.25 | G249: oats | H249: 572 | I249: 7 | J249: 572.875 | K249: 572.875 | L249: 0 | M249: 572 | N249: 7
A250: Harvest-time | B250: In all costs for the great boon-work with 17 other boon-works of 1,807 men who reaped and bound all the corn, together with 1 boon-work of 160 men without food, £612 shilling 4.25pence, and each had .25pence of bread and 2 herrings or 1 cheese worth 'Apence, and for the great boon-work they had bread, meat and ale. | C250: 612 | D250: 612 | E250: 0 | F250: 0 | H250: 0 | I250: 0 | J250: 0 | K250: 0 | L250: 0 | M250: 0 | N250: 0
A251: Harvest-time | B251: . | C251: 0 | D251: 0 | E251: 0 | F251: 0 | H251: 0 | I251: 0 | J251: 0 | K251: 0 | L251: 0 | M251: 0 | N251: 0
A252: Harvest-time | B252: mowing and tossing the meadow of Munnonce 1 shilling. | C252: 0.05 | D252: 0 | E252: 1 | F252: 0 | H252: 0 | I252: 0 | J252: 0 | K252: 0 | L252: 0 | M252: 0 | N252: 0
A253: Harvest-time | B253: mowing and tossing the garden 1 shilling 4pence Total, £6 14 shilling 8.25pence | C253: 6.73 | D253: 6 | E253: 14 | F253: 8.25 | H253: 0 | I253: 0 | J253: 0 | K253: 0 | L253: 0 | M253: 0 | N253: 0
A254: Expenses of the steward | B254: In expenses of the steward at the 2 hundred-courts by 1 tally l1 shilling 8.5pence. | C254: 0.09 | D254: 0 | E254: 1 | F254: 8.5 | H254: 0 | I254: 0 | J254: 0 | K254: 0 | L254: 0 | M254: 0 | N254: 0
A255: Expenses of the steward | B255: expenses of the bailiff for the year £6 15 shilling 6pence. | C255: 6.78 | D255: 6 | E255: 15 | F255: 6 | H255: 0 | I255: 0 | J255: 0 | K255: 0 | L255: 0 | M255: 0 | N255: 0
A256: Expenses of the steward | B256: fur for the summer livery of the same 3 shilling Total, £7 10 shilling 2.5pence | C256: 7.51 | D256: 7 | E256: 10 | F256: 2.5 | H256: 0 | I256: 0 | J256: 0 | K256: 0 | L256: 0 | M256: 0 | N256: 0
A257: Total of all expenses | B257: Total of all expenses, £39 5 shilling 7.5pence | C257: 39.28 | D257: 39 | E257: 5 | F257: 7.5 | H257: 0 | I257: 0 | J257: 0 | K257: 0 | L257: 0 | M257: 0 | N257: 0
A258: And he owes | B258: And he owes, £230 16 shilling 4pence | C258: 230.82 | D258: 230 | E258: 16 | F258: 4 | H258: 0 | I258: 0 | J258: 0 | K258: 0 | L258: 0 | M258: 0 | N258: 0
A259: Cash deliveries | B259: Delivered to Sir Geoffrey, treasurer of Wolvesey, by 2 tallies, £139 2 shilling | C259: 139.1 | D259: 139 | E259: 2 | F259: 0 | H259: 0 | I259: 0 | J259: 0 | K259: 0 | L259: 0 | M259: 0 | N259: 0
A260: And he owes clear | B260: And he owes clear, £91 14 shilling 4pence, of which £36 3.5pence against Richard de Poukepole, and £55 14 shilling 0.5pence against Adam de Cumbe. | C260: 91.72 | D260: 91 | E260: 14 | F260: 4 | H260: 0 | I260: 0 | J260: 0 | K260: 0 | L260: 0 | M260: 0 | N260: 0
A261: Wheat | B261: {yield: 6-fold plus 13 quarters 5 bushels} | C261: 0 | D261: 0 | E261: 0 | F261: 0 | H261: 13 | I261: 5 | J261: 13.625 | K261: 13.625 | L261: 0 | M261: 13 | N261: 5
A262: Wheat | B262: The same render account for 14 quarters of wheat remaining in the granary from the previous year. | C262: 0 | D262: 0 | E262: 0 | F262: 0 | G262: wheat | H262: 14 | I262: 0 | J262: 14 | K262: 14 | L262: 0 | M262: 14 | N262: 0
A263: Wheat | B263: 340 quarters 7 bushels from the whole issue of the grange by struck measure. | C263: 0 | D263: 0 | E263: 0 | F263: 0 | H263: 340 | I263: 7 | J263: 340.875 | K263: 340.875 | L263: 0 | M263: 340 | N263: 7
A264: Wheat | B264: 3 quarters from churchscot. | C264: 0 | D264: 0 | E264: 0 | F264: 0 | H264: 3 | I264: 0 | J264: 3 | K264: 3 | L264: 0 | M264: 3 | N264: 0
A265: Wheat | B265: Total, 357 quarters 7 bushels | C265: 0 | D265: 0 | E265: 0 | F265: 0 | H265: 357 | I265: 7 | J265: 357.875 | K265: 357.875 | L265: 0 | M265: 357 | N265: 7
A266: Wheat | B266: Sown over 608 acres as they lie in Selescumbe, Stonyelond', and Pykes, 67 quarters 6 bushels. | C266: 0 | D266: 0 | E266: 0 | F266: 0 | H266: 67 | I266: 6 | J266: 67.75 | K266: 67.75 | L266: 0 | M266: 67 | N266: 6
A267: Wheat | B267: that is, 1 bushels an acre, less 8 quarters 2 bushels in all. | C267: 0 | D267: 0 | E267: 0 | F267: 0 | H267: 8 | I267: 2 | J267: 8.25 | K267: 0.125 | L267: 8.125 | M267: 0 | N267: 1 | O267: 8 | P267: 2
A268: Wheat | B268: . | C268: 0 | D268: 0 | E268: 0 | F268: 0 | H268: 0 | I268: 0 | J268: 0 | K268: 0 | L268: 0 | M268: 0 | N268: 0
A269: Wheat | B269: provision of the steward for his visits by 1 tally, 7 bushels. | C269: 0 | D269: 0 | E269: 0 | F269: 0 | H269: 0 | I269: 7 | J269: 0.875 | K269: 0.875 | L269: 0 | M269: 0 | N269: 7
A270: Wheat | B270: provision of the bailiff for the year, 10 quarters, because he takes the rest from East Meon Church. | C270: 0 | D270: 0 | E270: 0 | F270: 0 | H270: 10 | I270: 0 | J270: 10 | K270: 10 | L270: 0 | M270: 10 | N270: 0
A271: Wheat | B271: Delivered to the vicar for his carrying-service, 5 quarters. | C271: 0 | D271: 0 | E271: 0 | F271: 0 | H271: 5 | I271: 0 | J271: 5 | K271: 5 | L271: 0 | M271: 5 | N271: 0
A272: Wheat | B272: Sold, 274 quarters 2 bushels | C272: 0 | D272: 0 | E272: 0 | F272: 0 | H272: 274 | I272: 2 | J272: 274.25 | K272: 274.25 | L272: 0 | M272: 274 | N272: 2
A273: Curall | B273: The same render account for 14 quarters from the whole issue of curall from the same wheat by struck measure. | C273: 0 | D273: 0 | E273: 0 | F273: 0 | G273: curall, wheat | H273: 14 | I273: 0 | J273: 14 | K273: 14 | L273: 0 | M273: 14 | N273: 0
A274: Curall | B274: Sold, 14 quarters. | C274: 0 | D274: 0 | E274: 0 | F274: 0 | H274: 14 | I274: 0 | J274: 14 | K274: 14 | L274: 0 | M274: 14 | N274: 0
A275: Barley | B275: {yield: three-and-a-half-fold less 3 quarters 7 bushels} | C275: 0 | D275: 0 | E275: 0 | F275: 0 | H275: 3 | I275: 7 | J275: 3.875 | K275: 3.875 | L275: 0 | M275: 3 | N275: 7
A276: Barley | B276: The same render account for 14 quarters of barley remaining from the previous year in the granary. | C276: 0 | D276: 0 | E276: 0 | F276: 0 | G276: barley | H276: 14 | I276: 0 | J276: 14 | K276: 14 | L276: 0 | M276: 14 | N276: 0
A277: Barley | B277: 101 quarters 1 bushels from the whole issue of barley this year by struck measure. | C277: 0 | D277: 0 | E277: 0 | F277: 0 | G277: barley | H277: 101 | I277: 1 | J277: 101.125 | K277: 101.125 | L277: 0 | M277: 101 | N277: 1
A278: Barley | B278: Total, 115 quarters 1 bushels | C278: 0 | D278: 0 | E278: 0 | F278: 0 | H278: 115 | I278: 1 | J278: 115.125 | K278: 115.125 | L278: 0 | M278: 115 | N278: 1
A279: Barley | B279: Sown over 95 acres as they lie in the field of la Chapele, 26.5 quarters. | C279: 0 | D279: 0 | E279: 0 | F279: 0 | H279: 26.5 | I279: 0 | J279: 26.5 | K279: 26.5 | L279: 0 | M279: 26.5 | N279: 0
A280: Barley | B280: that is, 4.5 bushels over 2 acres, less 1.5 bushels in all. | C280: 0 | D280: 0 | E280: 0 | F280: 0 | H280: 0 | I280: 1.5 | J280: 0.1875 | K280: 0.5625 | L280: -0.375 | M280: 0 | N280: 4.5 | O280: 0 | P280: 1.5
A281: Barley | B281: Delivered to 1 carter, 3 stot-keepers, and 1 keeper of hoggs and lambs for the year, 32.5 quarters, taking a quarter every 8 weeks. | C281: 0 | D281: 0 | E281: 0 | F281: 0 | H281: 32.5 | I281: 0 | J281: 32.5 | K281: 32.5 | L281: 0 | M281: 32.5 | N281: 0
A282: Barley | B282: Delivered to 2 oxherds for the year, because 3 customary tenants were drovers for the whole year to the advantage of the lord, 10 quarters 3 bushels, taking a quarter every 10 weeks. | C282: 0 | D282: 0 | E282: 0 | F282: 0 | H282: 10 | I282: 3 | J282: 10.375 | K282: 10.375 | L282: 0 | M282: 10 | N282: 3
A283: Barley | B283: Delivered to 1 dairymaid for the year, 5 quarters 1.5 bushels Delivered to 1 cowherd for the year, who takes a quarter every 12 weeks, 4 quarters 2.5 bushels Delivered to 3 keepers of lambs this year, 4 quarters 5 bushels. | C283: 0 | D283: 0 | E283: 0 | F283: 0 | H283: 8 | I283: 7.5 | J283: 8.9375 | K283: 5.1875 | L283: 3.75 | M283: 5 | N283: 1.5 | O283: 4 | P283: 2.5 | Q283: 4 | R283: 5
A284: Barley | B284: provision of the bailiff's attendant, 3 quarters. | C284: 0 | D284: 0 | E284: 0 | F284: 0 | H284: 3 | I284: 0 | J284: 3 | K284: 3 | L284: 0 | M284: 3 | N284: 0
A285: Barley | B285: Sold, 28 quarters 5 bushels | C285: 0 | D285: 0 | E285: 0 | F285: 0 | H285: 28 | I285: 5 | J285: 28.625 | K285: 28.625 | L285: 0 | M285: 28 | N285: 5
A286: Oats | B286: {yield: two-fold less 40 quarters 1 bushels) | C286: 0 | D286: 0 | E286: 0 | F286: 0 | H286: 40 | I286: 1 | J286: 40.125 | K286: 40.125 | L286: 0 | M286: 40 | N286: 1
A287: Oats | B287: The same render account for 572 quarters 7 bushels from the whole issue of oats by struck measure. | C287: 0 | D287: 0 | E287: 0 | F287: 0 | G287: oats | H287: 572 | I287: 7 | J287: 572.875 | K287: 572.875 | L287: 0 | M287: 572 | N287: 7
A288: Oats | B288: 42 quarters by estimation in sheaves. | C288: 0 | D288: 0 | E288: 0 | F288: 0 | H288: 42 | I288: 0 | J288: 42 | K288: 42 | L288: 0 | M288: 42 | N288: 0
A289: Oats | B289: Total, 614 quarters 7 bushels | C289: 0 | D289: 0 | E289: 0 | F289: 0 | H289: 614 | I289: 7 | J289: 614.875 | K289: 614.875 | L289: 0 | M289: 614 | N289: 7
A290: Oats | B290: Sown over 685 acres as they lie in the fields of la Chapele, Ponfaldesgore, and Crembe, 190 quarters. | C290: 0 | D290: 0 | E290: 0 | F290: 0 | H290: 190 | I290: 0 | J290: 190 | K290: 190 | L290: 0 | M290: 190 | N290: 0
A291: Oats | B291: that is, 4.5 bushels over 2 acres, less 2 quarters 5 bushels in all. | C291: 0 | D291: 0 | E291: 0 | F291: 0 | H291: 2 | I291: 5 | J291: 2.625 | K291: 0.5625 | L291: 2.0625 | M291: 0 | N291: 4.5 | O291: 2 | P291: 5
...

Sheet Issues of the Grange raw
A1: Heading | B1: Sentence | C1: Quarters 1_x | D1: Bushels 1_x | E1: Sown Quarters | F1: Sown Bushels | G1: Sown Total Quarters | H1: Bought in Quarters | I1: Bought in Bushels | J1: Bought in Total Quarters | K1: Tithe Quarters | L1: Tithe Bushels | M1: Tithe Total Quarters | N1: Manorial servants & livestock Quarters | O1: Manorial servants & livestock Bushels | P1: Manorial servants & livestock Total Quarters | Q1: Sold Quarters | R1: Sold Bushels | S1: Sold Total Quarters | T1: Account Quarters | U1: Account Bushels | V1: Account Total Quarters | W1: bought only | X1: Total Quarters Except 1 | Y1: Total Bushels Except 1 | Z1: Total Corn Cross-Check | AA1: Total Corn Manorial Account | AB1: Corn Quantity Error | AC1: Quarters 1_y | AD1: Bushels 1_y | AE1: Quarters 2 | AF1: Bushels 2 | AG1: Quarters 3 | AH1: Bushels 3 | AI1: Quarters 4 | AJ1: Bushels 4 | AK1: Quarters 5 | AL1: Bushels 5 | AM1: Quarters 6 | AN1: Bushels 6
A2: Cash deliveries | B2: Total | C2: 0 | D2: 0 | E2: 0 | F2: 0 | G2: 0 | H2: 0 | I2: 0 | J2: 0 | K2: 0 | L2: 0 | M2: 0 | N2: 0 | O2: 0 | P2: 0 | Q2: 0 | R2: 0 | S2: 0 | T2: 0 | U2: 0 | V2: 0 | W2: 0
A3: Wheat | B3: {yield: 6-fold plus 13 quarters 5 bushels} | C3: 0 | D3: 0 | E3: 0 | F3: 0 | G3: 0 | H3: 0 | I3: 0 | J3: 0 | K3: 0 | L3: 0 | M3: 0 | N3: 0 | O3: 0 | P3: 0 | Q3: 0 | R3: 0 | S3: 0 | T3: 0 | U3: 0 | V3: 0 | W3: 0 | X3: 13 | Y3: 5 | Z3: 13.625 | AA3: 13.625 | AB3: 0 | AC3: 13 | AD3: 5
A4: Wheat | B4: The same render account for 14 quarters of wheat remaining in the granary from the previous year. | C4: 0 | D4: 0 | E4: 0 | F4: 0 | G4: 0 | H4: 0 | I4: 0 | J4: 0 | K4: 0 | L4: 0 | M4: 0 | N4: 0 | O4: 0 | P4: 0 | Q4: 0 | R4: 0 | S4: 0 | T4: 14 | U4: 0 | V4: 14 | W4: 0 | X4: 14 | Y4: 0 | Z4: 14 | AA4: 14 | AB4: 0 | AC4: 14 | AD4: 0
A5: Wheat | B5: 340 quarters 7 bushels from the whole issue of the grange by struck measure. | C5: 0 | D5: 0 | E5: 0 | F5: 0 | G5: 0 | H5: 0 | I5: 0 | J5: 0 | K5: 0 | L5: 0 | M5: 0 | N5: 0 | O5: 0 | P5: 0 | Q5: 0 | R5: 0 | S5: 0 | T5: 340 | U5: 7 | V5: 340.875 | W5: 0 | X5: 340 | Y5: 7 | Z5: 340.875 | AA5: 340.875 | AB5: 0 | AC5: 340 | AD5: 7
A6: Wheat | B6: 3 quarters from churchscot. | C6: 0 | D6: 0 | E6: 0 | F6: 0 | G6: 0 | H6: 0 | I6: 0 | J6: 0 | K6: 0 | L6: 0 | M6: 0 | N6: 0 | O6: 0 | P6: 0 | Q6: 0 | R6: 0 | S6: 0 | T6: 0 | U6: 0 | V6: 0 | W6: 0 | X6: 3 | Y6: 0 | Z6: 3 | AA6: 3 | AB6: 0 | AC6: 3 | AD6: 0
A7: Wheat | B7: Total, 357 quarters 7 bushels | C7: 0 | D7: 0 | E7: 0 | F7: 0 | G7: 0 | H7: 0 | I7: 0 | J7: 0 | K7: 0 | L7: 0 | M7: 0 | N7: 0 | O7: 0 | P7: 0 | Q7: 0 | R7: 0 | S7: 0 | T7: 0 | U7: 0 | V7: 0 | W7: 0 | X7: 357 | Y7: 7 | Z7: 357.875 | AA7: 357.875 | AB7: 0 | AC7: 357 | AD7: 7
A8: Wheat | B8: Sown over 608 acres as they lie in Selescumbe, Stonyelond', and Pykes, 67 quarters 6 bushels. | C8: 0 | D8: 0 | E8: 67 | F8: 6 | G8: 67.75 | H8: 0 | I8: 0 | J8: 0 | K8: 0 | L8: 0 | M8: 0 | N8: 0 | O8: 0 | P8: 0 | Q8: 0 | R8: 0 | S8: 0 | T8: 0 | U8: 0 | V8: 0 | W8: 0 | X8: 67 | Y8: 6 | Z8: 67.75 | AA8: 67.75 | AB8: 0 | AC8: 67 | AD8: 6
A9: Wheat | B9: that is, 1 bushels an acre, less 8 quarters 2 bushels in all. | C9: 0 | D9: 0 | E9: 0 | F9: 0 | G9: 0 | H9: 0 | I9: 0 | J9: 0 | K9: 0 | L9: 0 | M9: 0 | N9: 0 | O9: 0 | P9: 0 | Q9: 0 | R9: 0 | S9: 0 | T9: 0 | U9: 0 | V9: 0 | W9: 0 | X9: 8 | Y9: 2 | Z9: 8.25 | AA9: 0.125 | AB9: 8.125 | AC9: 0 | AD9: 1 | AE9: 8 | AF9: 2
A10: Wheat | B10: . | C10: 0 | D10: 0 | E10: 0 | F10: 0 | G10: 0 | H10: 0 | I10: 0 | J10: 0 | K10: 0 | L10: 0 | M10: 0 | N10: 0 | O10: 0 | P10: 0 | Q10: 0 | R10: 0 | S10: 0 | T10: 0 | U10: 0 | V10: 0 | W10: 0 | X10: 0 | Y10: 0 | Z10: 0 | AA10: 0 | AB10: 0 | AC10: 0 | AD10: 0
A11: Wheat | B11: provision of the steward for his visits by 1 tally, 7 bushels. | C11: 0 | D11: 0 | E11: 0 | F11: 0 | G11: 0 | H11: 0 | I11: 0 | J11: 0 | K11: 0 | L11: 0 | M11: 0 | N11: 0 | O11: 0 | P11: 0 | Q11: 0 | R11: 0 | S11: 0 | T11: 0 | U11: 0 | V11: 0 | W11: 0 | X11: 0 | Y11: 7 | Z11: 0.875 | AA11: 0.875 | AB11: 0 | AC11: 0 | AD11: 7
A12: Wheat | B12: provision of the bailiff for the year, 10 quarters, because he takes the rest from East Meon Church. | C12: 0 | D12: 0 | E12: 0 | F12: 0 | G12: 0 | H12: 0 | I12: 0 | J12: 0 | K12: 0 | L12: 0 | M12: 0 | N12: 0 | O12: 0 | P12: 0 | Q12: 0 | R12: 0 | S12: 0 | T12: 0 | U12: 0 | V12: 0 | W12: 0 | X12: 10 | Y12: 0 | Z12: 10 | AA12: 10 | AB12: 0 | AC12: 10 | AD12: 0
A13: Wheat | B13: Delivered to the vicar for his carrying-service, 5 quarters. | C13: 0 | D13: 0 | E13: 0 | F13: 0 | G13: 0 | H13: 0 | I13: 0 | J13: 0 | K13: 0 | L13: 0 | M13: 0 | N13: 0 | O13: 0 | P13: 0 | Q13: 0 | R13: 0 | S13: 0 | T13: 0 | U13: 0 | V13: 0 | W13: 0 | X13: 5 | Y13: 0 | Z13: 5 | AA13: 5 | AB13: 0 | AC13: 5 | AD13: 0
A14: Wheat | B14: Sold, 274 quarters 2 bushels | C14: 0 | D14: 0 | E14: 0 | F14: 0 | G14: 0 | H14: 0 | I14: 0 | J14: 0 | K14: 0 | L14: 0 | M14: 0 | N14: 0 | O14: 0 | P14: 0 | Q14: 274 | R14: 2 | S14: 274.25 | T14: 0 | U14: 0 | V14: 0 | W14: 0 | X14: 274 | Y14: 2 | Z14: 274.25 | AA14: 274.25 | AB14: 0 | AC14: 274 | AD14: 2
A15: Wheat | B15: Total | C15: 0 | D15: 0 | E15: 0 | F15: 0 | G15: 0 | H15: 0 | I15: 0 | J15: 0 | K15: 0 | L15: 0 | M15: 0 | N15: 0 | O15: 0 | P15: 0 | Q15: 0 | R15: 0 | S15: 0 | T15: 0 | U15: 0 | V15: 0 | W15: 0
A16: Curall | B16: The same render account for 14 quarters from the whole issue of curall from the same wheat by struck measure. | C16: 0 | D16: 0 | E16: 0 | F16: 0 | G16: 0 | H16: 0 | I16: 0 | J16: 0 | K16: 0 | L16: 0 | M16: 0 | N16: 0 | O16: 0 | P16: 0 | Q16: 0 | R16: 0 | S16: 0 | T16: 14 | U16: 0 | V16: 14 | W16: 0 | X16: 14 | Y16: 0 | Z16: 14 | AA16: 14 | AB16: 0 | AC16: 14 | AD16: 0
A17: Curall | B17: Sold, 14 quarters. | C17: 0 | D17: 0 | E17: 0 | F17: 0 | G17: 0 | H17: 0 | I17: 0 | J17: 0 | K17: 0 | L17: 0 | M17: 0 | N17: 0 | O17: 0 | P17: 0 | Q17: 14 | R17: 0 | S17: 14 | T17: 0 | U17: 0 | V17: 0 | W17: 0 | X17: 14 | Y17: 0 | Z17: 14 | AA17: 14 | AB17: 0 | AC17: 14 | AD17: 0
A18: Curall | B18: Total | C18: 0 | D18: 0 | E18: 0 | F18: 0 | G18: 0 | H18: 0 | I18: 0 | J18: 0 | K18: 0 | L18: 0 | M18: 0 | N18: 0 | O18: 0 | P18: 0 | Q18: 0 | R18: 0 | S18: 0 | T18: 0 | U18: 0 | V18: 0 | W18: 0
A19: Barley | B19: {yield: three-and-a-half-fold less 3 quarters 7 bushels} | C19: 0 | D19: 0 | E19: 0 | F19: 0 | G19: 0 | H19: 0 | I19: 0 | J19: 0 | K19: 0 | L19: 0 | M19: 0 | N19: 0 | O19: 0 | P19: 0 | Q19: 0 | R19: 0 | S19: 0 | T19: 0 | U19: 0 | V19: 0 | W19: 0 | X19: 3 | Y19: 7 | Z19: 3.875 | AA19: 3.875 | AB19: 0 | AC19: 3 | AD19: 7
A20: Barley | B20: The same render account for 14 quarters of barley remaining from the previous year in the granary. | C20: 0 | D20: 0 | E20: 0 | F20: 0 | G20: 0 | H20: 0 | I20: 0 | J20: 0 | K20: 0 | L20: 0 | M20: 0 | N20: 0 | O20: 0 | P20: 0 | Q20: 0 | R20: 0 | S20: 0 | T20: 14 | U20: 0 | V20: 14 | W20: 0 | X20: 14 | Y20: 0 | Z20: 14 | AA20: 14 | AB20: 0 | AC20: 14 | AD20: 0
A21: Barley | B21: 101 quarters 1 bushels from the whole issue of barley this year by struck measure. | C21: 0 | D21: 0 | E21: 0 | F21: 0 | G21: 0 | H21: 0 | I21: 0 | J21: 0 | K21: 0 | L21: 0 | M21: 0 | N21: 0 | O21: 0 | P21: 0 | Q21: 0 | R21: 0 | S21: 0 | T21: 101 | U21: 1 | V21: 101.125 | W21: 0 | X21: 101 | Y21: 1 | Z21: 101.125 | AA21: 101.125 | AB21: 0 | AC21: 101 | AD21: 1
A22: Barley | B22: Total, 115 quarters 1 bushels | C22: 0 | D22: 0 | E22: 0 | F22: 0 | G22: 0 | H22: 0 | I22: 0 | J22: 0 | K22: 0 | L22: 0 | M22: 0 | N22: 0 | O22: 0 | P22: 0 | Q22: 0 | R22: 0 | S22: 0 | T22: 0 | U22: 0 | V22: 0 | W22: 0 | X22: 115 | Y22: 1 | Z22: 115.125 | AA22: 115.125 | AB22: 0 | AC22: 115 | AD22: 1
A23: Barley | B23: Sown over 95 acres as they lie in the field of la Chapele, 26.5 quarters. | C23: 0 | D23: 0 | E23: 26.5 | F23: 0 | G23: 26.5 | H23: 0 | I23: 0 | J23: 0 | K23: 0 | L23: 0 | M23: 0 | N23: 0 | O23: 0 | P23: 0 | Q23: 0 | R23: 0 | S23: 0 | T23: 0 | U23: 0 | V23: 0 | W23: 0 | X23: 26.5 | Y23: 0 | Z23: 26.5 | AA23: 26.5 | AB23: 0 | AC23: 26.5 | AD23: 0
A24: Barley | B24: that is, 4.5 bushels over 2 acres, less 1.5 bushels in all. | C24: 0 | D24: 0 | E24: 0 | F24: 0 | G24: 0 | H24: 0 | I24: 0 | J24: 0 | K24: 0 | L24: 0 | M24: 0 | N24: 0 | O24: 0 | P24: 0 | Q24: 0 | R24: 0 | S24: 0 | T24: 0 | U24: 0 | V24: 0 | W24: 0 | X24: 0 | Y24: 1.5 | Z24: 0.1875 | AA24: 0.5625 | AB24: -0.375 | AC24: 0 | AD24: 4.5 | AE24: 0 | AF24: 1.5
A25: Barley | B25: Delivered to 1 carter, 3 stot-keepers, and 1 keeper of hoggs and lambs for the year, 32.5 quarters, taking a quarter every 8 weeks. | C25: 0 | D25: 0 | E25: 0 | F25: 0 | G25: 0 | H25: 0 | I25: 0 | J25: 0 | K25: 0 | L25: 0 | M25: 0 | N25: 0 | O25: 0 | P25: 0 | Q25: 0 | R25: 0 | S25: 0 | T25: 0 | U25: 0 | V25: 0 | W25: 0 | X25: 32.5 | Y25: 0 | Z25: 32.5 | AA25: 32.5 | AB25: 0 | AC25: 32.5 | AD25: 0
A26: Barley | B26: Delivered to 2 oxherds for the year, because 3 customary tenants were drovers for the whole year to the advantage of the lord, 10 quarters 3 bushels, taking a quarter every 10 weeks. | C26: 0 | D26: 0 | E26: 0 | F26: 0 | G26: 0 | H26: 0 | I26: 0 | J26: 0 | K26: 0 | L26: 0 | M26: 0 | N26: 0 | O26: 0 | P26: 0 | Q26: 0 | R26: 0 | S26: 0 | T26: 0 | U26: 0 | V26: 0 | W26: 0 | X26: 10 | Y26: 3 | Z26: 10.375 | AA26: 10.375 | AB26: 0 | AC26: 10 | AD26: 3
A27: Barley | B27: Delivered to 1 dairymaid for the year, 5 quarters 1.5 bushels Delivered to 1 cowherd for the year, who takes a quarter every 12 weeks, 4 quarters 2.5 bushels Delivered to 3 keepers of lambs this year, 4 quarters 5 bushels. | C27: 0 | D27: 0 | E27: 0 | F27: 0 | G27: 0 | H27: 0 | I27: 0 | J27: 0 | K27: 0 | L27: 0 | M27: 0 | N27: 0 | O27: 0 | P27: 0 | Q27: 0 | R27: 0 | S27: 0 | T27: 0 | U27: 0 | V27: 0 | W27: 0 | X27: 8 | Y27: 7.5 | Z27: 8.9375 | AA27: 5.1875 | AB27: 3.75 | AC27: 5 | AD27: 1.5 | AE27: 4 | AF27: 2.5 | AG27: 4 | AH27: 5
A28: Barley | B28: provision of the bailiff's attendant, 3 quarters. | C28: 0 | D28: 0 | E28: 0 | F28: 0 | G28: 0 | H28: 0 | I28: 0 | J28: 0 | K28: 0 | L28: 0 | M28: 0 | N28: 0 | O28: 0 | P28: 0 | Q28: 0 | R28: 0 | S28: 0 | T28: 0 | U28: 0 | V28: 0 | W28: 0 | X28: 3 | Y28: 0 | Z28: 3 | AA28: 3 | AB28: 0 | AC28: 3 | AD28: 0
A29: Barley | B29: Sold, 28 quarters 5 bushels | C29: 0 | D29: 0 | E29: 0 | F29: 0 | G29: 0 | H29: 0 | I29: 0 | J29: 0 | K29: 0 | L29: 0 | M29: 0 | N29: 0 | O29: 0 | P29: 0 | Q29: 28 | R29: 5 | S29: 28.625 | T29: 0 | U29: 0 | V29: 0 | W29: 0 | X29: 28 | Y29: 5 | Z29: 28.625 | AA29: 28.625 | AB29: 0 | AC29: 28 | AD29: 5
A30: Barley | B30: Total | C30: 0 | D30: 0 | E30: 0 | F30: 0 | G30: 0 | H30: 0 | I30: 0 | J30: 0 | K30: 0 | L30: 0 | M30: 0 | N30: 0 | O30: 0 | P30: 0 | Q30: 0 | R30: 0 | S30: 0 | T30: 0 | U30: 0 | V30: 0 | W30: 0
A31: Oats | B31: {yield: two-fold less 40 quarters 1 bushels) | C31: 0 | D31: 0 | E31: 0 | F31: 0 | G31: 0 | H31: 0 | I31: 0 | J31: 0 | K31: 0 | L31: 0 | M31: 0 | N31: 0 | O31: 0 | P31: 0 | Q31: 0 | R31: 0 | S31: 0 | T31: 0 | U31: 0 | V31: 0 | W31: 0 | X31: 40 | Y31: 1 | Z31: 40.125 | AA31: 40.125 | AB31: 0 | AC31: 40 | AD31: 1
A32: Oats | B32: The same render account for 572 quarters 7 bushels from the whole issue of oats by struck measure. | C32: 0 | D32: 0 | E32: 0 | F32: 0 | G32: 0 | H32: 0 | I32: 0 | J32: 0 | K32: 0 | L32: 0 | M32: 0 | N32: 0 | O32: 0 | P32: 0 | Q32: 0 | R32: 0 | S32: 0 | T32: 572 | U32: 7 | V32: 572.875 | W32: 0 | X32: 572 | Y32: 7 | Z32: 572.875 | AA32: 572.875 | AB32: 0 | AC32: 572 | AD32: 7
A33: Oats | B33: 42 quarters by estimation in sheaves. | C33: 0 | D33: 0 | E33: 0 | F33: 0 | G33: 0 | H33: 0 | I33: 0 | J33: 0 | K33: 0 | L33: 0 | M33: 0 | N33: 0 | O33: 0 | P33: 0 | Q33: 0 | R33: 0 | S33: 0 | T33: 0 | U33: 0 | V33: 0 | W33: 0 | X33: 42 | Y33: 0 | Z33: 42 | AA33: 42 | AB33: 0 | AC33: 42 | AD33: 0
A34: Oats | B34: Total, 614 quarters 7 bushels | C34: 0 | D34: 0 | E34: 0 | F34: 0 | G34: 0 | H34: 0 | I34: 0 | J34: 0 | K34: 0 | L34: 0 | M34: 0 | N34: 0 | O34: 0 | P34: 0 | Q34: 0 | R34: 0 | S34: 0 | T34: 0 | U34: 0 | V34: 0 | W34: 0 | X34: 614 | Y34: 7 | Z34: 614.875 | AA34: 614.875 | AB34: 0 | AC34: 614 | AD34: 7
A35: Oats | B35: Sown over 685 acres as they lie in the fields of la Chapele, Ponfaldesgore, and Crembe, 190 quarters. | C35: 0 | D35: 0 | E35: 190 | F35: 0 | G35: 190 | H35: 0 | I35: 0 | J35: 0 | K35: 0 | L35: 0 | M35: 0 | N35: 0 | O35: 0 | P35: 0 | Q35: 0 | R35: 0 | S35: 0 | T35: 0 | U35: 0 | V35: 0 | W35: 0 | X35: 190 | Y35: 0 | Z35: 190 | AA35: 190 | AB35: 0 | AC35: 190 | AD35: 0
A36: Oats | B36: that is, 4.5 bushels over 2 acres, less 2 quarters 5 bushels in all. | C36: 0 | D36: 0 | E36: 0 | F36: 0 | G36: 0 | H36: 0 | I36: 0 | J36: 0 | K36: 0 | L36: 0 | M36: 0 | N36: 0 | O36: 0 | P36: 0 | Q36: 0 | R36: 0 | S36: 0 | T36: 0 | U36: 0 | V36: 0 | W36: 0 | X36: 2 | Y36: 5 | Z36: 2.625 | AA36: 0.5625 | AB36: 2.0625 | AC36: 0 | AD36: 4.5 | AE36: 2 | AF36: 5
A37: Oats | B37: . | C37: 0 | D37: 0 | E37: 0 | F37: 0 | G37: 0 | H37: 0 | I37: 0 | J37: 0 | K37: 0 | L37: 0 | M37: 0 | N37: 0 | O37: 0 | P37: 0 | Q37: 0 | R37: 0 | S37: 0 | T37: 0 | U37: 0 | V37: 0 | W37: 0 | X37: 0 | Y37: 0 | Z37: 0 | AA37: 0 | AB37: 0 | AC37: 0 | AD37: 0
A38: Oats | B38: . | C38: 0 | D38: 0 | E38: 0 | F38: 0 | G38: 0 | H38: 0 | I38: 0 | J38: 0 | K38: 0 | L38: 0 | M38: 0 | N38: 0 | O38: 0 | P38: 0 | Q38: 0 | R38: 0 | S38: 0 | T38: 0 | U38: 0 | V38: 0 | W38: 0 | X38: 0 | Y38: 0 | Z38: 0 | AA38: 0 | AB38: 0 | AC38: 0 | AD38: 0
A39: Oats | B39: . | C39: 0 | D39: 0 | E39: 0 | F39: 0 | G39: 0 | H39: 0 | I39: 0 | J39: 0 | K39: 0 | L39: 0 | M39: 0 | N39: 0 | O39: 0 | P39: 0 | Q39: 0 | R39: 0 | S39: 0 | T39: 0 | U39: 0 | V39: 0 | W39: 0 | X39: 0 | Y39: 0 | Z39: 0 | AA39: 0 | AB39: 0 | AC39: 0 | AD39: 0
A40: Oats | B40: . | C40: 0 | D40: 0 | E40: 0 | F40: 0 | G40: 0 | H40: 0 | I40: 0 | J40: 0 | K40: 0 | L40: 0 | M40: 0 | N40: 0 | O40: 0 | P40: 0 | Q40: 0 | R40: 0 | S40: 0 | T40: 0 | U40: 0 | V40: 0 | W40: 0 | X40: 0 | Y40: 0 | Z40: 0 | AA40: 0 | AB40: 0 | AC40: 0 | AD40: 0
A41: Oats | B41: . | C41: 0 | D41: 0 | E41: 0 | F41: 0 | G41: 0 | H41: 0 | I41: 0 | J41: 0 | K41: 0 | L41: 0 | M41: 0 | N41: 0 | O41: 0 | P41: 0 | Q41: 0 | R41: 0 | S41: 0 | T41: 0 | U41: 0 | V41: 0 | W41: 0 | X41: 0 | Y41: 0 | Z41: 0 | AA41: 0 | AB41: 0 | AC41: 0 | AD41: 0
A42: Oats | B42: . | C42: 0 | D42: 0 | E42: 0 | F42: 0 | G42: 0 | H42: 0 | I42: 0 | J42: 0 | K42: 0 | L42: 0 | M42: 0 | N42: 0 | O42: 0 | P42: 0 | Q42: 0 | R42: 0 | S42: 0 | T42: 0 | U42: 0 | V42: 0 | W42: 0 | X42: 0 | Y42: 0 | Z42: 0 | AA42: 0 | AB42: 0 | AC42: 0 | AD42: 0
A43: Oats | B43: . | C43: 0 | D43: 0 | E43: 0 | F43: 0 | G43: 0 | H43: 0 | I43: 0 | J43: 0 | K43: 0 | L43: 0 | M43: 0 | N43: 0 | O43: 0 | P43: 0 | Q43: 0 | R43: 0 | S43: 0 | T43: 0 | U43: 0 | V43: 0 | W43: 0 | X43: 0 | Y43: 0 | Z43: 0 | AA43: 0 | AB43: 0 | AC43: 0 | AD43: 0
A44: Oats | B44: fodder of 2 cart-horses for the year, 18 quarters. | C44: 0 | D44: 0 | E44: 0 | F44: 0 | G44: 0 | H44: 0 | I44: 0 | J44: 0 | K44: 0 | L44: 0 | M44: 0 | N44: 18 | O44: 0 | P44: 18 | Q44: 0 | R44: 0 | S44: 0 | T44: 0 | U44: 0 | V44: 0 | W44: 0 | X44: 18 | Y44: 0 | Z44: 18 | AA44: 18 | AB44: 0 | AC44: 18 | AD44: 0
A45: Oats | B45: . | C45: 0 | D45: 0 | E45: 0 | F45: 0 | G45: 0 | H45: 0 | I45: 0 | J45: 0 | K45: 0 | L45: 0 | M45: 0 | N45: 0 | O45: 0 | P45: 0 | Q45: 0 | R45: 0 | S45: 0 | T45: 0 | U45: 0 | V45: 0 | W45: 0 | X45: 0 | Y45: 0 | Z45: 0 | AA45: 0 | AB45: 0 | AC45: 0 | AD45: 0
A46: Oats | B46: . | C46: 0 | D46: 0 | E46: 0 | F46: 0 | G46: 0 | H46: 0 | I46: 0 | J46: 0 | K46: 0 | L46: 0 | M46: 0 | N46: 0 | O46: 0 | P46: 0 | Q46: 0 | R46: 0 | S46: 0 | T46: 0 | U46: 0 | V46: 0 | W46: 0 | X46: 0 | Y46: 0 | Z46: 0 | AA46: 0 | AB46: 0 | AC46: 0 | AD46: 0
A47: Oats | B47: . | C47: 0 | D47: 0 | E47: 0 | F47: 0 | G47: 0 | H47: 0 | I47: 0 | J47: 0 | K47: 0 | L47: 0 | M47: 0 | N47: 0 | O47: 0 | P47: 0 | Q47: 0 | R47: 0 | S47: 0 | T47: 0 | U47: 0 | V47: 0 | W47: 0 | X47: 0 | Y47: 0 | Z47: 0 | AA47: 0 | AB47: 0 | AC47: 0 | AD47: 0
A48: Oats | B48: . | C48: 0 | D48: 0 | E48: 0 | F48: 0 | G48: 0 | H48: 0 | I48: 0 | J48: 0 | K48: 0 | L48: 0 | M48: 0 | N48: 0 | O48: 0 | P48: 0 | Q48: 0 | R48: 0 | S48: 0 | T48: 0 | U48: 0 | V48: 0 | W48: 0 | X48: 0 | Y48: 0 | Z48: 0 | AA48: 0 | AB48: 0 | AC48: 0 | AD48: 0
... A51: Oats | B51: . | C51: 0 | D51: 0 | E51: 0 | F51: 0 | G51: 0 | H51: 0 | I51: 0 | J51: 0 | K51: 0 | L51: 0 | M51: 0 | N51: 0 | O51: 0 | P51: 0 | Q51: 0 | R51: 0 | S51: 0 | T51: 0 | U51: 0 | V51: 0 | W51: 0 | X51: 0 | Y51: 0 | Z51: 0 | AA51: 0 | AB51: 0 | AC51: 0 | AD51: 0
A52: Oats | B52: fodder of 18 plough-horses from the feast of the Circumcision (1 January) until Sunday before the feast of St Augustine (20 May), for 140 nights, 52.5 quarters, at 3 bushels a night. | C52: 0 | D52: 0 | E52: 0 | F52: 0 | G52: 0 | H52: 0 | I52: 0 | J52: 0 | K52: 0 | L52: 0 | M52: 0 | N52: 52.5 | O52: 0 | P52: 52.5 | Q52: 0 | R52: 0 | S52: 0 | T52: 0 | U52: 0 | V52: 0 | W52: 0 | X52: 52.5 | Y52: 3 | Z52: 52.875 | AA52: 52.5 | AB52: 0.375 | AC52: 52.5 | AD52: 0 | AE52: 0 | AF52: 3
A53: Oats | B53: . | C53: 0 | D53: 0 | E53: 0 | F53: 0 | G53: 0 | H53: 0 | I53: 0 | J53: 0 | K53: 0 | L53: 0 | M53: 0 | N53: 0 | O53: 0 | P53: 0 | Q53: 0 | R53: 0 | S53: 0 | T53: 0 | U53: 0 | V53: 0 | W53: 0 | X53: 0 | Y53: 0 | Z53: 0 | AA53: 0 | AB53: 0 | AC53: 0 | AD53: 0
A54: Oats | B54: . | C54: 0 | D54: 0 | E54: 0 | F54: 0 | G54: 0 | H54: 0 | I54: 0 | J54: 0 | K54: 0 | L54: 0 | M54: 0 | N54: 0 | O54: 0 | P54: 0 | Q54: 0 | R54: 0 | S54: 0 | T54: 0 | U54: 0 | V54: 0 | W54: 0 | X54: 0 | Y54: 0 | Z54: 0 | AA54: 0 | AB54: 0 | AC54: 0 | AD54: 0
A55: Oats | B55: . | C55: 0 | D55: 0 | E55: 0 | F55: 0 | G55: 0 | H55: 0 | I55: 0 | J55: 0 | K55: 0 | L55: 0 | M55: 0 | N55: 0 | O55: 0 | P55: 0 | Q55: 0 | R55: 0 | S55: 0 | T55: 0 | U55: 0 | V55: 0 | W55: 0 | X55: 0 | Y55: 0 | Z55: 0 | AA55: 0 | AB55: 0 | AC55: 0 | AD55: 0
A56: Oats | B56: . | C56: 0 | D56: 0 | E56: 0 | F56: 0 | G56: 0 | H56: 0 | I56: 0 | J56: 0 | K56: 0 | L56: 0 | M56: 0 | N56: 0 | O56: 0 | P56: 0 | Q56: 0 | R56: 0 | S56: 0 | T56: 0 | U56: 0 | V56: 0 | W56: 0 | X56: 0 | Y56: 0 | Z56: 0 | AA56: 0 | AB56: 0 | AC56: 0 | AD56: 0
A57: Oats | B57: . | C57: 0 | D57: 0 | E57: 0 | F57: 0 | G57: 0 | H57: 0 | I57: 0 | J57: 0 | K57: 0 | L57: 0 | M57: 0 | N57: 0 | O57: 0 | P57: 0 | Q57: 0 | R57: 0 | S57: 0 | T57: 0 | U57: 0 | V57: 0 | W57: 0 | X57: 0 | Y57: 0 | Z57: 0 | AA57: 0 | AB57: 0 | AC57: 0 | AD57: 0
A58: Oats | B58: . | C58: 0 | D58: 0 | E58: 0 | F58: 0 | G58: 0 | H58: 0 | I58: 0 | J58: 0 | K58: 0 | L58: 0 | M58: 0 | N58: 0 | O58: 0 | P58: 0 | Q58: 0 | R58: 0 | S58: 0 | T58: 0 | U58: 0 | V58: 0 | W58: 0 | X58: 0 | Y58: 0 | Z58: 0 | AA58: 0 | AB58: 0 | AC58: 0 | AD58: 0
A59: Oats | B59: . | C59: 0 | D59: 0 | E59: 0 | F59: 0 | G59: 0 | H59: 0 | I59: 0 | J59: 0 | K59: 0 | L59: 0 | M59: 0 | N59: 0 | O59: 0 | P59: 0 | Q59: 0 | R59: 0 | S59: 0 | T59: 0 | U59: 0 | V59: 0 | W59: 0 | X59: 0 | Y59: 0 | Z59: 0 | AA59: 0 | AB59: 0 | AC59: 0 | AD59: 0
A60: Oats | B60: fodder of the same when they ploughed after dinner, 5 quarters. | C60: 0 | D60: 0 | E60: 0 | F60: 0 | G60: 0 | H60: 0 | I60: 0 | J60: 0 | K60: 0 | L60: 0 | M60: 0 | N60: 5 | O60: 0 | P60: 5 | Q60: 0 | R60: 0 | S60: 0 | T60: 0 | U60: 0 | V60: 0 | W60: 0 | X60: 5 | Y60: 0 | Z60: 5 | AA60: 5 | AB60: 0 | AC60: 5 | AD60: 0
A61: Oats | B61: . | C61: 0 | D61: 0 | E61: 0 | F61: 0 | G61: 0 | H61: 0 | I61: 0 | J61: 0 | K61: 0 | L61: 0 | M61: 0 | N61: 0 | O61: 0 | P61: 0 | Q61: 0 | R61: 0 | S61: 0 | T61: 0 | U61: 0 | V61: 0 | W61: 0 | X61: 0 | Y61: 0 | Z61: 0 | AA61: 0 | AB61: 0 | AC61: 0 | AD61: 0
A62: Oats | B62: . | C62: 0 | D62: 0 | E62: 0 | F62: 0 | G62: 0 | H62: 0 | I62: 0 | J62: 0 | K62: 0 | L62: 0 | M62: 0 | N62: 0 | O62: 0 | P62: 0 | Q62: 0 | R62: 0 | S62: 0 | T62: 0 | U62: 0 | V62: 0 | W62: 0 | X62: 0 | Y62: 0 | Z62: 0 | AA62: 0 | AB62: 0 | AC62: 0 | AD62: 0
A63: Oats | B63: . | C63: 0 | D63: 0 | E63: 0 | F63: 0 | G63: 0 | H63: 0 | I63: 0 | J63: 0 | K63: 0 | L63: 0 | M63: 0 | N63: 0 | O63: 0 | P63: 0 | Q63: 0 | R63: 0 | S63: 0 | T63: 0 | U63: 0 | V63: 0 | W63: 0 | X63: 0 | Y63: 0 | Z63: 0 | AA63: 0 | AB63: 0 | AC63: 0 | AD63: 0
A64: Oats | B64: . | C64: 0 | D64: 0 | E64: 0 | F64: 0 | G64: 0 | H64: 0 | I64: 0 | J64: 0 | K64: 0 | L64: 0 | M64: 0 | N64: 0 | O64: 0 | P64: 0 | Q64: 0 | R64: 0 | S64: 0 | T64: 0 | U64: 0 | V64: 0 | W64: 0 | X64: 0 | Y64: 0 | Z64: 0 | AA64: 0 | AB64: 0 | AC64: 0 | AD64: 0
... A75: Oats | B75: . | C75: 0 | D75: 0 | E75: 0 | F75: 0 | G75: 0 | H75: 0 | I75: 0 | J75: 0 | K75: 0 | L75: 0 | M75: 0 | N75: 0 | O75: 0 | P75: 0 | Q75: 0 | R75: 0 | S75: 0 | T75: 0 | U75: 0 | V75: 0 | W75: 0 | X75: 0 | Y75: 0 | Z75: 0 | AA75: 0 | AB75: 0 | AC75: 0 | AD75: 0
A76: Oats | B76: customary payment to 8 ploughmen, 3 shepherds, and 3 customary tenants who replaced 3 drovers, who were accustomed to be at liberty, 10.5 quarters, or 6 bushels each. | C76: 0 | D76: 0 | E76: 0 | F76: 0 | G76: 0 | H76: 0 | I76: 0 | J76: 0 | K76: 0 | L76: 0 | M76: 0 | N76: 0 | O76: 0 | P76: 0 | Q76: 0 | R76: 0 | S76: 0 | T76: 0 | U76: 0 | V76: 0 | W76: 0 | X76: 10.5 | Y76: 6 | Z76: 11.25 | AA76: 10.5 | AB76: 0.75 | AC76: 10.5 | AD76: 0 | AE76: 0 | AF76: 6
A77: Oats | B77: . | C77: 0 | D77: 0 | E77: 0 | F77: 0 | G77: 0 | H77: 0 | I77: 0 | J77: 0 | K77: 0 | L77: 0 | M77: 0 | N77: 0 | O77: 0 | P77: 0 | Q77: 0 | R77: 0 | S77: 0 | T77: 0 | U77: 0 | V77: 0 | W77: 0 | X77: 0 | Y77: 0 | Z77: 0 | AA77: 0 | AB77: 0 | AC77: 0 | AD77: 0
A78: Oats | B78: . | C78: 0 | D78: 0 | E78: 0 | F78: 0 | G78: 0 | H78: 0 | I78: 0 | J78: 0 | K78: 0 | L78: 0 | M78: 0 | N78: 0 | O78: 0 | P78: 0 | Q78: 0 | R78: 0 | S78: 0 | T78: 0 | U78: 0 | V78: 0 | W78: 0 | X78: 0 | Y78: 0 | Z78: 0 | AA78: 0 | AB78: 0 | AC78: 0 | AD78: 0
A79: Oats | B79: . | C79: 0 | D79: 0 | E79: 0 | F79: 0 | G79: 0 | H79: 0 | I79: 0 | J79: 0 | K79: 0 | L79: 0 | M79: 0 | N79: 0 | O79: 0 | P79: 0 | Q79: 0 | R79: 0 | S79: 0 | T79: 0 | U79: 0 | V79: 0 | W79: 0 | X79: 0 | Y79: 0 | Z79: 0 | AA79: 0 | AB79: 0 | AC79: 0 | AD79: 0
A80: Oats | B80: . | C80: 0 | D80: 0 | E80: 0 | F80: 0 | G80: 0 | H80: 0 | I80: 0 | J80: 0 | K80: 0 | L80: 0 | M80: 0 | N80: 0 | O80: 0 | P80: 0 | Q80: 0 | R80: 0 | S80: 0 | T80: 0 | U80: 0 | V80: 0 | W80: 0 | X80: 0 | Y80: 0 | Z80: 0 | AA80: 0 | AB80: 0 | AC80: 0 | AD80: 0
A81: Oats | B81: . | C81: 0 | D81: 0 | E81: 0 | F81: 0 | G81: 0 | H81: 0 | I81: 0 | J81: 0 | K81: 0 | L81: 0 | M81: 0 | N81: 0 | O81: 0 | P81: 0 | Q81: 0 | R81: 0 | S81: 0 | T81: 0 | U81: 0 | V81: 0 | W81: 0 | X81: 0 | Y81: 0 | Z81: 0 | AA81: 0 | AB81: 0 | AC81: 0 | AD81: 0
A82: Oats | B82: . | C82: 0 | D82: 0 | E82: 0 | F82: 0 | G82: 0 | H82: 0 | I82: 0 | J82: 0 | K82: 0 | L82: 0 | M82: 0 | N82: 0 | O82: 0 | P82: 0 | Q82: 0 | R82: 0 | S82: 0 | T82: 0 | U82: 0 | V82: 0 | W82: 0 | X82: 0 | Y82: 0 | Z82: 0 | AA82: 0 | AB82: 0 | AC82: 0 | AD82: 0
A83: Oats | B83: . | C83: 0 | D83: 0 | E83: 0 | F83: 0 | G83: 0 | H83: 0 | I83: 0 | J83: 0 | K83: 0 | L83: 0 | M83: 0 | N83: 0 | O83: 0 | P83: 0 | Q83: 0 | R83: 0 | S83: 0 | T83: 0 | U83: 0 | V83: 0 | W83: 0 | X83: 0 | Y83: 0 | Z83: 0 | AA83: 0 | AB83: 0 | AC83: 0 | AD83: 0
A84: Oats | B84: fodder of the steward's horses for his visits by 1 tally, 1.5 quarters. | C84: 0 | D84: 0 | E84: 0 | F84: 0 | G84: 0 | H84: 0 | I84: 0 | J84: 0 | K84: 0 | L84: 0 | M84: 0 | N84: 1.5 | O84: 0 | P84: 1.5 | Q84: 0 | R84: 0 | S84: 0 | T84: 0 | U84: 0 | V84: 0 | W84: 0 | X84: 1.5 | Y84: 0 | Z84: 1.5 | AA84: 1.5 | AB84: 0 | AC84: 1.5 | AD84: 0
A85: Oats | B85: . | C85: 0 | D85: 0 | E85: 0 | F85: 0 | G85: 0 | H85: 0 | I85: 0 | J85: 0 | K85: 0 | L85: 0 | M85: 0 | N85: 0 | O85: 0 | P85: 0 | Q85: 0 | R85: 0 | S85: 0 | T85: 0 | U85: 0 | V85: 0 | W85: 0 | X85: 0 | Y85: 0 | Z85: 0 | AA85: 0 | AB85: 0 | AC85: 0 | AD85: 0
A86: Oats | B86: . | C86: 0 | D86: 0 | E86: 0 | F86: 0 | G86: 0 | H86: 0 | I86: 0 | J86: 0 | K86: 0 | L86: 0 | M86: 0 | N86: 0 | O86: 0 | P86: 0 | Q86: 0 | R86: 0 | S86: 0 | T86: 0 | U86: 0 | V86: 0 | W86: 0 | X86: 0 | Y86: 0 | Z86: 0 | AA86: 0 | AB86: 0 | AC86: 0 | AD86: 0
A87: Oats | B87: . | C87: 0 | D87: 0 | E87: 0 | F87: 0 | G87: 0 | H87: 0 | I87: 0 | J87: 0 | K87: 0 | L87: 0 | M87: 0 | N87: 0 | O87: 0 | P87: 0 | Q87: 0 | R87: 0 | S87: 0 | T87: 0 | U87: 0 | V87: 0 | W87: 0 | X87: 0 | Y87: 0 | Z87: 0 | AA87: 0 | AB87: 0 | AC87: 0 | AD87: 0
A88: Oats | B88: . | C88: 0 | D88: 0 | E88: 0 | F88: 0 | G88: 0 | H88: 0 | I88: 0 | J88: 0 | K88: 0 | L88: 0 | M88: 0 | N88: 0 | O88: 0 | P88: 0 | Q88: 0 | R88: 0 | S88: 0 | T88: 0 | U88: 0 | V88: 0 | W88: 0 | X88: 0 | Y88: 0 | Z88: 0 | AA88: 0 | AB88: 0 | AC88: 0 | AD88: 0
... A93: Oats | B93: Sold, 275 quarters 3 bushels | C93: 0 | D93: 0 | E93: 0 | F93: 0 | G93: 0 | H93: 0 | I93: 0 | J93: 0 | K93: 0 | L93: 0 | M93: 0 | N93: 0 | O93: 0 | P93: 0 | Q93: 275 | R93: 3 | S93: 275.375 | T93: 0 | U93: 0 | V93: 0 | W93: 0 | X93: 275 | Y93: 3 | Z93: 275.375 | AA93: 275.375 | AB93: 0 | AC93: 275 | AD93: 3
A94: Oats | B94: Total | C94: 0 | D94: 0 | E94: 0 | F94: 0 | G94: 0 | H94: 0 | I94: 0 | J94: 0 | K94: 0 | L94: 0 | M94: 0 | N94: 0 | O94: 0 | P94: 0 | Q94: 0 | R94: 0 | S94: 0 | T94: 0 | U94: 0 | V94: 0 | W94: 0

Sheet Sale of Corn Prices
A1: Heading | B1: Sentence | C1: Total in Pounds | D1: Pounds | E1: Shillings | F1: Pence | G1: Corn | H1: Total Quarters Except 1 | I1: Total Bushels Except 1 | J1: Total Corn Cross-Check | K1: Total Corn Manorial Account | L1: Corn Quantity Error | M1: Quarters 0 | N1: Bushels 0 | O1: shilling a quarter 1 | P1: pence a quarter 1 | Q1: Quarters 1 | R1: Bushels 1 | S1: shilling a quarter 2 | T1: pence a quarter 2 | U1: Quarters 2 | V1: Bushels 2 | W1: shilling a quarter 3 | X1: pence a quarter 3 | Y1: Quarters 3 | Z1: Bushels 3 | AA1: shilling a quarter 4 | AB1: pence a quarter 4 | AC1: Quarters 4 | AD1: Bushels 4 | AE1: shilling a quarter 5 | AF1: pence a quarter 5 | AG1: Quarters 5 | AH1: Bushels 5 | AI1: £ a quarter 1 | AJ1: £ a quarter 2 | AK1: £ a quarter 3 | AL1: £ a quarter 4 | AM1: £ a quarter 5 | AN1: Quarters Sold | AO1: Weighted Average Price per Quarter | AP1: Non-Weighted Average Price per Quarter | AQ1: Corn lowercase
A2: Sale of corn | B2: The same render account for £75 10 shilling 5pence from 274 quarters 2 bushels of wheat sold, at 4 shilling a quarters for 29 quarters 2 bushels, 5 shilling a quarters for 70 quarters 6 bushels, 5 shilling 4pence a quarters for 82 quarters 3 bushels, 6 shilling a quarters for 18 quarters 2 bushels, and 6 shilling 8pence a quarters for 73 quarters 5 bushels. | C2: 75.52 | D2: 75 | E2: 10 | F2: 5 | G2: wheat | H2: 272 | I2: 18 | J2: 274.25 | K2: 274.25 | L2: 0 | M2: 274 | N2: 2 | O2: 4 | P2: 0 | Q2: 29 | R2: 2 | S2: 5 | T2: 0 | U2: 70 | V2: 6 | W2: 5 | X2: 4 | Y2: 82 | Z2: 3 | AA2: 6 | AB2: 0 | AC2: 18 | AD2: 2 | AE2: 6 | AF2: 8 | AG2: 73 | AH2: 5 | AI2: 0.2 | AJ2: 0.25 | AK2: 0.26666667 | AL2: 0.3 | AM2: 0.33333333 | AN2: 274.25 | AO2: 0.27537223 | AP2: 0.27 | AQ2: wheat
A3: Sale of corn | B3: £2 6 shilling 8pence from 14 quarters of curall sold, at 3 shilling 4pence a quarters. | C3: 2.33 | D3: 2 | E3: 6 | F3: 8 | G3: curall | H3: 14 | I3: 0 | J3: 14 | K3: 14 | L3: 0 | M3: 14 | N3: 0 | O3: 3 | P3: 4 | AI3: 0.16666667 | AN3: 14 | AO3: 0.16666667 | AP3: 0.16666667 | AQ3: curall
A4: Sale of corn | B4: £5 10 shilling 10.5pence from 28 quarters 5 bushels of barley sold, at 4 shilling a quarters for 25 quarters, and 3 shilling a quarters for 3 quarters 5 bushels. | C4: 5.54 | D4: 5 | E4: 10 | F4: 10.5 | G4: barley | H4: 28 | I4: 5 | J4: 28.625 | K4: 28.625 | L4: 0 | M4: 28 | N4: 5 | O4: 4 | P4: 0 | Q4: 25 | R4: 0 | S4: 3 | T4: 0 | U4: 3 | V4: 5 | AI4: 0.2 | AJ4: 0.15 | AN4: 28.625 | AO4: 0.19366812 | AP4: 0.175 | AQ4: barley
A5: Sale of corn | B5: £28 8 shilling 4.75pence from 275 quarters 3 bushels of oats sold, at 1 shilling 8pence a quarters for 55 quarters 3 bushels, 2 shilling a quarters for 86 quarters 3 bushels, 2 shilling 2pence a quarters for 50 quarters 5 bushels, and 2 shilling 4pence a quarters for 83 quarters. | C5: 28.42 | D5: 28 | E5: 8 | F5: 4.75 | G5: oats | H5: 274 | I5: 11 | J5: 275.375 | K5: 275.375 | L5: 0 | M5: 275 | N5: 3 | O5: 1 | P5: 8 | Q5: 55 | R5: 3 | S5: 2 | T5: 0 | U5: 86 | V5: 3 | W5: 2 | X5: 2 | Y5: 50 | Z5: 5 | AA5: 2 | AB5: 4 | AC5: 83 | AD5: 0 | AI5: 0.083333333 | AJ5: 0.1 | AK5: 0.10833333 | AL5: 0.11666667 | AN5: 275.375 | AO5: 0.10320396 | AP5: 0.10208333 | AQ5: oats
A6: Sale of corn | B6: Total of all corn sold, £111 16 shilling 4.25pence | C6: 111.82 | D6: 111 | E6: 16 | F6: 4.25 | H6: 0 | I6: 0 | J6: 0 | K6: 0 | L6: 0 | M6: 0 | N6: 0 | AI6: inf | AN6: 0 | AO6: inf | AP6: inf
