Workbook

Sheet Overview
A1: ESHER | B1: Total in £ | C1: Error | D1: Note
A2: CASH ACCOUNT
A3: RECEIPTS
A4: Arrears total
A5: Rents of assize total
A6: Quittances total
A7: Defaults of rent total
A8: Defaults of rent through the pestilence total
A9: Cotlands defaults total
A10: Cotlands total
A11: Total of quittances and defaults of rent total
A12: Total of rents remaining clear total
A13: Farms total
... A183: % of capital expenses as calculated previously

Sheet Receipts
A1: ESHER RECEIPTS
A2: Heading | B2: £ | C2: s | D2: d | F2: Total in Pounds | G2: Error | H2: Sentence
A3: Arrears | B3: 0 | C3: 13 | D3: 1.75 | F3: 0.66 | H3: Richard atte Grove, reeve, renders account for 13 shilling 1.75pence of arrears from the previous year.
A4: Arrears | B4: 0 | C4: 0 | D4: 0 | F4: 0 | H4: All delivered to Geoffrey, treasurer, by 1 tally.
A5: Arrears | B5: 0 | C5: 0 | D5: 0 | F5: 0 | H5: He is quit.'
A6: Arrears | F6: 0.66 | G6: =F6-F3 -> 0 | H6: Total
A8: Rents of assize | B8: 0 | C8: 10 | D8: 0 | F8: 0.5 | H8: The same renders account for 10 shilling for rents of assize at the Invention of the Cross (3 May) by view of John de Hatfeud'.
A9: Rents of assize | B9: 5 | C9: 9 | D9: 10.5 | F9: 5.49 | H9: £5 9 shilling 10.5pence at Michaelmas (29 September).
A10: Rents of assize | B10: 5 | C10: 19 | D10: 10.5 | F10: 5.99 | H10: Total, £5 19 shilling 10.5pence
A11: Rents of assize | F11: 5.99 | G11: 0 | H11: Total
A13: Quittances | B13: 0 | C13: 1 | D13: 10 | F13: =B13+C13/20+D13/240 -> 0.091666667 | H13: In quittance of rent of the reeve for the year 1 shilling 10pence.
A14: Quittances | B14: 1 | C14: 0 | D14: 0 | F14: =B14+C14/20+D14/240 -> 1 | H14: default of a certain dwelling-house and land pertaining to the church drawn into demesne £1.
A15: Quittances | B15: 1 | C15: 1 | D15: 10 | F15: =B15+C15/20+D15/240 -> 1.0916667 | H15: Total of quittances and defaults of rent, £1 1 shilling 10pence
A16: Quittances | F16: =SUM(F13:F14) -> 1.0916667 | G16: =F16-F15 -> 0 | H16: Total
A18: Total of rents remaining | B18: 4 | C18: 18 | D18: 0.5 | F18: 4.9 | H18: Total of rents remaining, £4 18 shilling 0.5pence
A19: Total of rents remaining | F19: =F18 -> 4.9 | G19: =F19-F18 -> 0 | H19: Total
A21: Rent of the hall of Kingston hired for the year | B21: 0 | C21: 15 | D21: 0 | F21: 0.75 | H21: The same renders account for 15 shilling for the rent of the hall of Kingston at Christmas, Easter and Michaelmas.
A22: Rent of the hall of Kingston hired for the year | B22: 0 | C22: 15 | D22: 0 | F22: 0.75 | H22: Total, 15 shilling
A23: Rent of the hall of Kingston hired for the year | F23: 0.75 | G23: 0 | H23: Total
A25: Issues of the manor | B25: 0 | C25: 8 | D25: 3 | F25: 0.41 | H25: The same renders account for 8 shilling from pannage of 28 pigs and 6 piglets, at 3pence a pig and 2pence a piglet, and the said right of pannage (garsevese) for 6 pigs of Richard atte Barr' this year.
A26: Issues of the manor | B26: 0 | C26: 0 | D26: 0 | F26: 0 | H26: nothing from pannage of Esher and Northwod' this year.
A27: Issues of the manor | B27: 0 | C27: 4 | D27: 4 | F27: 0.22 | H27: 4 shilling from 12 animals going to the summer pasturage sold at Northwod this year, at 4pence a head.
A28: Issues of the manor | B28: 0 | C28: 3 | D28: 6 | F28: 0.17 | H28: 3 shilling 6pence from the pasturage in la More sold.
A29: Issues of the manor | B29: 0 | C29: 0 | D29: 6 | F29: 0.03 | H29: 6pence from the pasturage at la Crumbe sold.
A30: Issues of the manor | B30: 0 | C30: 0 | D30: 8 | F30: 0.03 | H30: 8pence from the herbage in the garden sold.
A31: Issues of the manor | B31: 0 | C31: 9 | D31: 0 | F31: 0.45 | H31: 9 shilling from fruit from the garden sold this year, the tithe deducted.
A32: Issues of the manor | B32: 0 | C32: 0 | D32: 8 | F32: 0.03 | H32: 8pence from the fishery at Northwod.
A33: Issues of the manor | B33: 0 | C33: 0 | D33: 10.5 | F33: 0.04 | H33: 10.5pence from 7 hens from churchscot sold.
A34: Issues of the manor | B34: 0 | C34: 0 | D34: 2.5 | F34: 0.01 | H34: 2.5pence from the hide sold of 1 yearling dead from murrain.
A35: Issues of the manor | B35: 0 | C35: 5 | D35: 6 | F35: 0.28 | H35: 5 shilling 6pence from the skins sold of 22 wethers dead from murrain before shearing.
A36: Issues of the manor | B36: 0 | C36: 1 | D36: 5 | F36: 0.07 | H36: 1 shilling .5pence from the skins sold of 5 ewes dead from murrain before shearing.
... A42: Issues of the manor | B42: 0 | C42: 7 | D42: 1.5 | F42: 0.36 | H42: 7 shilling from the milking of 56 ewes sold, at 1.5pence each.
A43: Issues of the manor | B43: 0 | C43: 0 | D43: 2 | F43: =B43+C43/20+D43/240 -> 0.0083333333 | H43: 2pence from rushes (ros') sold
A44: Issues of the manor | B44: 3 | C44: 4 | D44: 6 | F44: =B44+C44/20+D44/240 -> 3.225 | H44: Total, £3 4 shilling 6pence
A45: Issues of the manor | F45: =SUM(F25:F43) -> 3.2983333 | G45: =F45-F44 -> 0.073333333 | H45: Total
A47: Sale of stock | B47: 0 | C47: 9 | D47: 0 | F47: =B47+C47/20+D47/240 -> 0.45 | H47: The same renders account for 9 shilling from 9 wethers sold before shearing, at 1 shilling a head.
A48: Sale of stock | B48: 0 | C48: 11 | D48: 3 | F48: =B48+C48/20+D48/240 -> 0.5625 | H48: 11 shilling 3pence from 15 feeble ewes sold before shearing and lambing, at 9pence a head
A49: Sale of stock | B49: 1 | C49: 0 | D49: 3 | F49: =B49+C49/20+D49/240 -> 1.0125 | H49: Total, £1 3pence
A50: Sale of stock | F50: =SUM(F47:F48) -> 1.0125 | G50: =F50-F49 -> 0 | H50: Total
A52: Sale of rye and oats | B52: 3 | C52: 5 | D52: 9.75 | F52: 3.29 | H52: The same renders account for £3 5 shilling 9.75pence from 15 quarters 1.5 bushels of rye sold, at 4 shilling 4pence a qr.
A53: Sale of rye and oats | B53: 1 | C53: 4 | D53: 8 | F53: 1.23 | H53: £1 4 shilling 8pence from 18.5 quarters of oats sold, at 1 shilling 4pence a qr.
A54: Sale of rye and oats | B54: 0 | C54: 16 | D54: 5.5 | F54: 0.82 | H54: 16 shilling 5.5pence from 4 quarters 7.5 bushels of barley sold at the audit, at 3 shilling 4pence a qr.
A55: Sale of rye and oats | B55: 5 | C55: 6 | D55: 11.25 | F55: 5.35 | H55: Total, £5 6 shilling 11.25pence
A56: Sale of rye and oats | F56: 5.34 | G56: -0.01 | H56: Total
A58: Entry fines and perquisites of court | B58: 0 | C58: 2 | D58: 0 | F58: 0.1 | H58: The same renders account for 2 shilling from Matilda de Wexford' for damage done in the lord's wood by 2 cows.
A59: Entry fines and perquisites of court | B59: 0 | C59: 1 | D59: 0 | F59: 0.05 | H59: 1 shilling from Belotota le Fort for 1 cow in the lord's wood.
A60: Entry fines and perquisites of court | B60: 0 | C60: 3 | D60: 0 | F60: 0.15 | H60: 3 shilling from Richard ate Wod' for 3 bullocks in the lord's wood.
A61: Entry fines and perquisites of court | B61: 0 | C61: 3 | D61: 0 | F61: 0.15 | H61: 3 shilling from John Derlyng for 3 bullocks.
A62: Entry fines and perquisites of court | B62: 0 | C62: 3 | D62: 0 | F62: 0.15 | H62: 3 shilling from Richard ate Barre for 3 bullocks.
A63: Entry fines and perquisites of court | B63: 0 | C63: 1 | D63: 0 | F63: 0.05 | H63: 1 shilling from Alice Bronnemay for 1 bullock.
A64: Entry fines and perquisites of court | B64: 0 | C64: 2 | D64: 0 | F64: 0.1 | H64: 2 shilling from John ate Barre for 2 bullocks.
A65: Entry fines and perquisites of court | B65: 0 | C65: 1 | D65: 0 | F65: 0.05 | H65: 1 shilling from Richard Hamund for 3 pigs.
A66: Entry fines and perquisites of court | B66: 0 | C66: 0 | D66: 8 | F66: 0.03 | H66: 8pence from Alice Bronemay for 2 piglets.
A67: Entry fines and perquisites of court | B67: 0 | C67: 1 | D67: 4 | F67: 0.07 | H67: 1 shilling 4pence from John Selueyn for 4 pigs.
A68: Entry fines and perquisites of court | B68: 0 | C68: 0 | D68: 4 | F68: 0.02 | H68: 4pence from Richard ate Wod' for 1 pig.
A69: Entry fines and perquisites of court | B69: 0 | C69: 0 | D69: 4 | F69: 0.02 | H69: 4pence from the relict of Fort for 1 pig.
... A103: Entry fines and perquisites of court | B103: 2 | C103: 3 | D103: 1 | F103: 2.15 | H103: Total, £2 3 shilling 1pence
A104: Entry fines and perquisites of court | F104: 2.16 | G104: 0.01 | H104: Total
A106: Hall of Kingston | B106: 0 | C106: 1 | D106: 6 | F106: 0.08 | H106: The same renders account for 1 shilling 6pence from the brewers of Kingston because they sold ale against the assize.
A107: Hall of Kingston | B107: 0 | C107: 1 | D107: 6 | F107: 0.08 | H107: Total, 1 shilling 6pence
A108: Hall of Kingston | F108: 0.08 | G108: 0 | H108: Total
A110: Total of all receipts | B110: 17 | C110: 9 | D110: 3.75 | F110: 17.47 | H110: Total of all receipts, £17 9 shilling 3.75pence
F111: =F108+F104+F56+F50+F45+F23+F19 -> 17.540833 | H111: Total (without arrears)

Sheet Expenses
A1: ESHER EXPENSES
A2: Heading | B2: £ | C2: s | D2: d | F2: Total in £ | G2: Error | H2: Sentence
A3: Cost of ploughs | B3: 0 | C3: 0 | D3: 6 | F3: 0.03 | H3: In 2 plough feet bought and fitted to the ploughs 6pence.
A4: Cost of ploughs | B4: 0 | C4: 0 | D4: 4 | F4: 0.02 | H4: 1 pair of wheels bought for the ploughs 4pence.
A5: Cost of ploughs | B5: 0 | C5: 4 | D5: 0 | F5: 0.2 | H5: stipend of the smith repairing the ironwork of the ploughs for the year 4 shilling.
A6: Cost of ploughs | B6: 0 | C6: 0 | D6: 3 | F6: 0.01 | H6: 32 herrings bought for 16 harrowers at the sowing of the oats, 3pence this year, and each had 2 herrings.
A7: Cost of ploughs | B7: 0 | C7: 6 | D7: 0 | F7: 0.3 | H7: stipend of the ploughman for the year 6 shilling.
A8: Cost of ploughs | B8: 0 | C8: 5 | D8: 0 | F8: =B8+C8/20+D8/240 -> 0.25 | H8: stipend of the drover for the year 5 shilling
A9: Cost of ploughs | B9: 0 | C9: 16 | D9: 1 | F9: =B9+C9/20+D9/240 -> 0.80416667 | H9: Total, 16 shilling 1pence
A10: Cost of ploughs | F10: =SUM(F3:F8) -> 0.81 | G10: =F10-F9 -> 0.0058333333 | H10: Total
A13: Purchase of barley | B13: 0 | C13: 0 | D13: 0 | F13: 0 | H13: In 25 quarters 5 bushels of barley bought for the liveries of the manorial servants and the
A14: Purchase of barley | B14: 4 | C14: 5 | D14: 5 | F14: 4.27 | H14: provision of the harvest £4 5 shilling 5pence, at 3 shilling 4pence a qr.
A15: Purchase of barley | B15: 4 | C15: 5 | D15: 5 | F15: 4.27 | H15: Total, £4 5 shilling 5pence
A16: Purchase of barley | F16: 4.27 | G16: 0 | H16: Total
A19: Cost of carts | B19: 0 | C19: 1 | D19: 8 | F19: 0.08 | H19: In 1 pair of wheels bought for the cart 1 shilling 8pence.
A20: Cost of carts | B20: 0 | C20: 1 | D20: 0 | F20: 0.05 | H20: clouts and nails bought for the cart 1 shilling.
A21: Cost of carts | B21: 0 | C21: 0 | D21: 4 | F21: 0.02 | H21: grease bought for the same 4pence.
A22: Cost of carts | B22: 0 | C22: 0 | D22: 8 | F22: 0.03 | H22: 1 hemp rope bought to tie the cart 8pence.
A23: Cost of carts | B23: 0 | C23: 0 | D23: 6 | F23: 0.03 | H23: 1 saddle with saddle-pads bought for the cart 6pence.
A24: Cost of carts | B24: 0 | C24: 1 | D24: 2 | F24: 0.06 | H24: shoeing the horses, 1 shilling 2pence this year.
A25: Cost of carts | B25: 0 | C25: 7 | D25: 3.5 | F25: 0.36 | H25: 1 horse bought 7 shilling 3.5pence
A26: Cost of carts | C26: 12 | D26: 7.5 | F26: =B26+C26/20+D267247 -> 0.6 | H26: Total, 12 shilling 7.5pence
A27: Cost of carts | F27: =SUM(F19:F25) -> 0.63 | G27: =F27-F26 -> 0.03 | H27: Total
A30: Small necessaries | B30: 0 | C30: 0 | D30: 3.5 | F30: 0.01 | H30: In 1 bushels of salt bought 3.5pence.
A31: Small necessaries | B31: 0 | C31: 1 | D31: 3 | F31: 0.06 | H31: 5 ells of canvas bought for packing the wool of Esher 1 shilling 3pence, at 3pence an ell.
A32: Small necessaries | B32: 0 | C32: 0 | D32: 4 | F32: 0.02 | H32: expenses for carrying the wool of Esher to Wolvesey 4pence.
A33: Small necessaries | B33: 0 | C33: 0 | D33: 6 | F33: =B33+C33/20+D33/240 -> 0.025 | H33: 4 trestles made to support the lord's table 6pence
A34: Small necessaries | B34: 0 | C34: 2 | D34: 4.5 | F34: =B34+C34/20+D34/240 -> 0.11875 | H34: Total, 2 shilling 4.5pence
A35: Small necessaries | F35: =SUM(F30:F33) -> 0.115 | G35: =F35-F34 -> -0.00375 | H35: Total
A38: Repair of buildings | B38: 0 | C38: 0 | D38: 6 | F38: 0.03 | H38: In stipend of 2 carpenters mending the great gate for 1 day 6pence.
A39: Repair of buildings | B39: 0 | C39: 0 | D39: 2 | F39: 0.01 | H39: 50 board-nails bought for the same 2pence.
A40: Repair of buildings | B40: 0 | C40: 1 | D40: 3 | F40: 0.06 | H40: stipend of 2 carpenters mending the bridge at the kitchen-door for 2 days by piece-work 1 shilling, each of them taking 3pence a day.
A41: Repair of buildings | B41: 0 | C41: 1 | D41: 6 | F41: 0.08 | H41: 500 (di' miliar') tiles bought for tiling the hall, chapel and bishop's chamber where it was absolutely necessary 1 shilling 6pence.
A42: Repair of buildings | B42: 0 | C42: 1 | D42: 6 | F42: 0.08 | H42: stipend of 1 tiler on the hall, chapel and bishop's chamber for 3 days 1 shilling 6pence, taking 6pence a day.
A43: Repair of buildings | B43: 0 | C43: 0 | D43: 6 | F43: 0.03 | H43: stipend of 1 carpenter mending the walls of the byre and the walls of the squires' room for 2 days 6pence.
A44: Repair of buildings | B44: 0 | C44: 0 | D44: 8 | F44: 0.03 | H44: stipend of 1 roofer with an assistant roofing the gatehouse for 2 days 8pence, taking 4pence a day.
A45: Repair of buildings | B45: 0 | C45: 1 | D45: 3 | F45: 0.06 | H45: stipend of 1 carpenter at Nortwod' mending the sheepcote for 4 days 1 shilling, taking 3pence a day.
A46: Repair of buildings | B46: 0 | C46: 1 | D46: 8 | F46: 0.08 | H46: stipend of 1 roofer with 1 assistant on the said sheepcote for 5 days 1 shilling 8pence, taking 4pence a day.
A47: Repair of buildings | B47: 0 | C47: 9 | D47: 0 | F47: 0.45 | H47: Total, 9 shilling
A48: Repair of buildings | F48: 0.46 | G48: 0.01 | H48: Total
A51: Cost of the sheepfold (ovil') | B51: 0 | C51: 2 | D51: 3 | F51: 0.11 | H51: In 18 hurdles bought for the lord's sheepfold 2 shilling 3pence, at 1.5pence a hurdle.
A52: Cost of the sheepfold (ovil') | B52: 0 | C52: 1 | D52: 6 | F52: 0.08 | H52: 12 lb of grease bought to heal the sheep 1 shilling 6pence, at 1.5pence a lb.
A53: Cost of the sheepfold (ovil') | B53: 0 | C53: 0 | D53: 10 | F53: 0.04 | H53: verdigris and copperas bought to heal the sheep 10pence.
A54: Cost of the sheepfold (ovil') | B54: 0 | C54: 0 | D54: 5 | F54: 0.02 | H54: washing and shearing sheep besides those done by custom 5pence.
A55: Cost of the sheepfold (ovil') | B55: 0 | C55: 0 | D55: 3 | F55: 0.01 | H55: washing and shearing lambs, 3pence this year.
A56: Cost of the sheepfold (ovil') | B56: 0 | C56: 5 | D56: 0 | F56: 0.25 | H56: stipend of 1 shepherd for the year 5 shilling.
A57: Cost of the sheepfold (ovil') | B57: 0 | C57: 3 | D57: 6 | F57: 0.17 | H57: stipend of 1 man keeping the animals at Northwod' and mending fences for the year 3 shilling 6pence
A58: Cost of the sheepfold (ovil') | B58: 0 | C58: 13 | D58: 6 | F58: =B58+C58/20+D58/240 -> 0.675 | H58: Total, 13 shilling 6pence
A59: Cost of the sheepfold (ovil') | F59: 0.68 | G59: =F59-F58 -> 0.005 | H59: Total
A62: Threshing of corn | B62: 0 | C62: 4 | D62: 2 | F62: 0.21 | H62: In threshing 24 quarters of rye by piece-work 4 shilling, at 2pence a qr.
A63: Threshing of corn | B63: 0 | C63: 0 | D63: 6.75 | F63: 0.03 | H63: threshing 4 quarters 5 bushels of barley by piece-work 6.75pence, at 1 .5pence a qr.
A64: Threshing of corn | B64: 0 | C64: 3 | D64: 1 | F64: 0.15 | H64: threshing 36 quarters of oats by piece-work 3 shilling, at 1pence a qr.
A65: Threshing of corn | B65: 0 | C65: 1 | D65: 4 | F65: 0.07 | H65: winnowing the same corn 1 shilling 4pence, at 1pence per 4 quarters.
A66: Threshing of corn | B66: 0 | C66: 8 | D66: 10.5 | F66: 0.44 | H66: Total, 8 shilling 10.5pence
A67: Threshing of corn | F67: 0.46 | G67: 0.02 | H67: Total
A70: Mowing the meadows, weeding the corn | B70: 0 | C70: 0 | D70: 6 | F70: 0.03 | H70: In weeding the corn this year 6pence.
A71: Mowing the meadows, weeding the corn | B71: 0 | C71: 0 | D71: 1 | F71: 0 | H71: mowing the said meadow of Brodemed' by custom, bread from stock and 1 wether with its skin from the said sheepfo1pence.
A72: Mowing the meadows, weeding the corn | B72: 0 | C72: 0 | D72: 3 | F72: 0.01 | H72: cheese bought 3pence.
A73: Mowing the meadows, weeding the corn | B73: 0 | C73: 1 | D73: 2 | F73: 0.06 | H73: mowing the meadow of Esher by piece-work besides that done by custom 1 shilling 2pence.
A74: Mowing the meadows, weeding the corn | B74: 0 | C74: 0 | D74: 0 | F74: 0 | H74: carrying the hay of Brodemed' to the shed by custom, bread from stock.
A75: Mowing the meadows, weeding the corn | B75: 0 | C75: 0 | D75: 4 | F75: 0.02 | H75: herrings bought 4pence.
A76: Mowing the meadows, weeding the corn | B76: 0 | C76: 0 | D76: 8 | F76: 0.03 | H76: mowing the meadow of Northwod' by piece-work, 8pence this year.
A77: Mowing the meadows, weeding the corn | B77: 0 | C77: 2 | D77: 11 | F77: 0.15 | H77: Total, 2 shilling 11pence
A78: Mowing the meadows, weeding the corn | F78: 0.15 | G78: 0 | H78: Total
A81: Cost of the harvest | B81: 0 | C81: 0 | D81: 0 | F81: 0 | H81: In 1 boon-work without ale of 23 men who reaped and bound the lord's corn, bread from stock.
A82: Cost of the harvest | B82: 0 | C82: 0 | D82: 11 | F82: 0.05 | H82: 138 herrings bought, 11pence this year, at 8pence a 100, and each had 3 herrings at noon and 3 at supper.
A83: Cost of the harvest | B83: 0 | C83: 0 | D83: 0 | F83: 0 | H83: 1 boon-work with ale of 28 men who reaped and bound the lord's corn, bread from stock.
A84: Cost of the harvest | B84: 0 | C84: 2 | D84: 6 | F84: 0.12 | H84: ale bought 2 shilling 6pence.
A85: Cost of the harvest | B85: 0 | C85: 0 | D85: 8 | F85: 0.03 | H85: 100 herrings bought for noon 8pence.
A86: Cost of the harvest | B86: 0 | C86: 2 | D86: 2 | F86: 0.11 | H86: meat bought 2 shilling 2pence.
A87: Cost of the harvest | B87: 0 | C87: 0 | D87: 5 | F87: 0.02 | H87: wastel-bread bought for mortrel 1 .5pence.
A88: Cost of the harvest | B88: 0 | C88: 0 | D88: 2 | F88: 0.01 | H88: milk bought for the same 2pence.
A89: Cost of the harvest | B89: 0 | C89: 1 | D89: 0 | F89: 0.05 | H89: cheese bought for the whole harvest 1 shilling.
A90: Cost of the harvest | B90: 0 | C90: 0 | D90: 1 | F90: 0 | H90: candles bought 1pence.
A91: Cost of the harvest | B91: 0 | C91: 0 | D91: 0 | F91: 0 | H91: 27 men hired for 1 day for 2 meals a day at Northwod' who reaped and bound the lord's corn.
A92: Cost of the harvest | B92: 0 | C92: 0 | D92: 0 | F92: 0 | H92: Also in 26 men hired for 1 day for 2 meals a day at Northwod' who reaped and bound the lord's corn, bread from stock.
... A96: Cost of the harvest | B96: 0 | C96: 2 | D96: 9.5 | F96: 0.14 | H96: expenses of the reeve from Lammas until Michaelmas 2 shilling
A97: Cost of the harvest | B97: 0 | C97: 16 | D97: 9.5 | F97: =B97+C97/20+D97/240 -> 0.83958333 | H97: Total, 16 shilling 9.5pence
A98: Cost of the harvest | F98: =SUM(F81:F96) -> 0.89 | G98: =F98-F97 -> 0.050416667 | H98: Total
A101: Cost of the vineyard | B101: 1 | C101: 3 | D101: 0 | F101: 1.15 | H101: In expenses for digging around the vineyard of Esher this year £1 3 shilling.
A102: Cost of the vineyard | B102: 0 | C102: 3 | D102: 10 | F102: 0.19 | H102: collecting vines to make verjuice 3 shilling 10pence.
A103: Cost of the vineyard | B103: 0 | C103: 1 | D103: 2 | F103: 0.06 | H103: 4 bushels of salt bought to salt verjuice 1 shilling 2pence, at 3.5pence a bushels
A104: Cost of the vineyard | B104: 0 | C104: 3 | D104: 6 | F104: =B104+C104/20+D104/240 -> 0.175 | H104: Delivered to Peter, the lord's squire, whilst he remains at Esher in order to collect vines and make verjuice, by order of the bishop and by his letters, 3 shilling 6pence.
A105: Cost of the vineyard | B105: 0 | C105: 5 | D105: 0 | F105: 0.25 | H105: stipend of Alexander the vintner for the year 5 shilling.
A106: Cost of the vineyard | B106: 0 | C106: 2 | D106: 2 | F106: 0.11 | H106: 1 cask bought for putting the verjuice in 2 shilling 2pence.
A107: Cost of the vineyard | B107: 0 | C107: 1 | D107: 0 | F107: =B107+C107/20+D107/240 -> 0.05 | H107: 2 barrels bought for the same 1 shilling
A108: Cost of the vineyard | B108: 1 | C108: 19 | D108: 8 | F108: 1.98 | H108: Total, £1 19 shilling 8pence
A109: Cost of the vineyard | F109: =SUM(F101:F107) -> 1.985 | G109: =F109-F108 -> 0.005 | H109: Total
A112: Payment of outside rents | B112: 0 | C112: 6 | D112: 0 | F112: 0.3 | H112: In rent paid at Michaelmas to the Abbot of Chertsey for the land of Northwod' 6 shilling.
A113: Payment of outside rents | B113: 0 | C113: 1 | D113: 2 | F113: 0.06 | H113: 2 ploughshares bought for the same, paid to the same this year, 1 shilling 2pence
A114: Payment of outside rents | B114: 0 | C114: 7 | D114: 2 | F114: =B114+C114/20+D114/240 -> 0.35833333 | H114: Total, 7 shilling 2pence
A115: Payment of outside rents | F115: 0.36 | G115: =F115-F114 -> 0.0016666667 | H115: Total
A118: Foreign expenses | B118: 0 | C118: 1 | D118: 0 | F118: 0.05 | H118: Given for the keeping of a certain ox by the assessor of the fifteenth at Northwod' 1 shilling
A119: Foreign expenses | B119: 0 | C119: 0 | D119: 10 | F119: =B119+C119/20+D119/240 -> 0.041666667 | H119: 10pence
A120: Foreign expenses | B120: 0 | C120: 1 | D120: 10 | F120: 0.09 | H120: Total, 1 shilling 10pence
A121: Foreign expenses | F121: =SUM(F118:F119) -> 0.091666667 | G121: =F121-F120 -> 0.0016666667 | H121: Total
A124: And thus he owes | B124: 4 | C124: 17 | D124: 9.75 | F124: 4.89 | H124: And thus he owes, £4 17 shilling 9.75pence
A125: And thus he owes | F125: 4.89 | G125: 0 | H125: Total
A128: Cash deliveries | B128: 3 | C128: 0 | D128: 0 | F128: 3 | H128: Delivered to Sir Geoffrey, treasurer of Wolvesey, by 1 tally, £3.

Sheet Issues of the Grange
A1: ESHER STOCK ACCOUNT
A2: Gross Output | B2: Total Quantity | C2: Account Total Quarters | D2: Bought in Total Quarters | E2: Received from churchscot | F2: Sold Total Quarters | G2: Difference Produced+Bought-Sold | H2: Weighted Average Price per Quarter | I2: Value of Total Production weighted
A3: rye | B3: 30 | D3: 0 | F3: 15.1875 | G3: =B3-F3 -> 14.8125 | H3: 0.21666667 | I3: =H3*B3 -> 6.5
A4: barley | B4: =31+2.5/8 -> 31.3125 | D4: 25.625 | F4: 18.5 | G4: =B4-F4 -> 12.8125 | H4: 0.066666667 | I4: =H4*B4 -> 2.0875
A5: oats | B5: 48 | D5: 0 | F5: 4.9375 | G5: =B5-F5 -> 43.0625 | H5: 0.16666667 | I5: =H5*B5 -> 8
A7: Total Production
A8: Sales of corn (as recorded in accounts)
A10: Net output | B10: Gross output | C10: Seed quarters | D10: Seed bushels | E10: Seed total quarters | F10: tithe quarters | G10: tithe bushels | H10: tithe total | I10: manorial servants quarters | J10: manorial servants bushels | K10: manorial servants total quarters | L10: output net of tithe, seed, liveries | M10: in stock from last year | N10: Price in £ | O10: Value of net output in £ | P10: Value of sales (in "Sale of Corn") in £
A11: rye | B11: =B3 -> 30 | C11: 6 | D11: 3 | E11: =C11+D11/8 -> 6.375 | I11: =1+6.5 -> 7.5 | J11: =1+3+1+2 -> 7 | K11: =I11+J11/8 -> 8.375 | L11: =B11-E11-H11-K11 -> 15.25 | N11: =H3 -> 0.21666667 | O11: =N11*L11 -> 3.3041667
A12: barley | B12: =B4 -> 31.3125 | C12: 13 | E12: =C12+D12/8 -> 13 | I12: =1+5+4+1 -> 11 | J12: =5+1.5+2.5+2 -> 11 | K12: =I12+J12/8 -> 12.375 | L12: =B12-E12-H12-K12 -> 5.9375 | N12: =H4 -> 0.066666667 | O12: =N12*L12 -> 0.39583333
A13: oats | B13: =B5 -> 48 | C13: 21 | E13: =C13+D13/8 -> 21 | I13: =2.5+3+3 -> 8.5 | K13: =I13+J13/8 -> 8.5 | L13: =B13-E13-H13-K13 -> 18.5 | N13: =H5 -> 0.16666667 | O13: =N13*L13 -> 3.0833333
A15: Total | O15: =SUM(O11:O13) -> 6.7833333

Sheet Issues of the Mills

Sheet Stock
A1: ASHMANSWORTH STOCK ACCOUNT
C3: added | G3: subtracted
A4: Livestock | B4: Inherited stock | C4: added | D4: strays | E4: herbage | F4: churchscot | G4: of which in default | H4: sold | I4: in murrain | J4: accounted for elsewhere | K4: End-period stock | L4: cross-check | M4: stock building | N4: raw production | O4: Unit price (£) | P4: Value of stock (£) at given value | Q4: Value of stock (£) at sales prices | R4: Sales in (£) | S4: Value of stock building (£) | T4: Value of production (£) at sales prices | U4: Details
A5: Cart-horses | B5: 2 | C5: 1 | H5: 1 | K5: 2 | U5: sale not recorded here
A6: Mares
A7: Plough horses
A8: Colts (unspecified years)
A9: Colts (2 years)
A10: Colts (1 year)
A11: Foals
A12: Oxen | C12: 13 | D12: 1 | K12: 14
A13: Bulls
A14: Cows | B14: 8 | C14: 1 | K14: 9
A15: Steers
A16: Bullocks
A17: Yearlings | B17: 3 | I17: 1 | K17: 2
A18: Calves | C18: 7 | H18: 4 | K18: 3 | R18: =Receipts!F40 -> 0.72
A19: Wethers | B19: 124 | C19: 20 | I19: =22+5+9 -> 36 | J19: 1 | K19: 107
A20: Rams
A21: Ewes | B21: 80 | C21: 8 | H21: 15 | I21: 5 | K21: 68 | R21: =Receipts!F48 -> 0.5625
A22: Hoggs | B22: 33 | I22: 5 | J22: =20+8 -> 28 | K22: 0
A23: Lambs | B23: 56 | I23: 20 | J23: 3 | K23: 33
A24: Boars
A25: Sows
A26: Pigs
A27: Hoggets
A28: Piglets
A29: Swans
A30: Peacocks | B30: 8 | K30: 8
A31: Total Value | R31: =SUM(R5:R30) -> 1.2825
A34: Wool
A35: Fleeces (wethers)
A36: Coarse wool | B36: 186 | J36: =18+1+167 -> 186 | K36: 0 | O36: 0.02 | T36: =O36*J36 -> 3.72
A37: Lamb's wool | B37: 33 | J37: 33 | O37: 0.01 | T37: =O37*J37 -> 0.33
A38: Wool locks
A39: Wool sold at shearing
A40: Total wool | T40: =SUM(T36:T39) -> 4.05
A43: Hides
A44: Ox hides
A45: Yearling | C45: 1 | H45: 1 | R45: =Receipts!F34 -> 0.01
A46: Mare
A47: Steer
A48: calves
A49: pigs
A50: Woolskins
A51: wethers | C51: =22+5 -> 27 | H51: 27 | R51: =Receipts!F35 -> 0.28 | U51: Sale only records 22 ksins
A52: rams
A53: ewes
A54: hoggs | C54: 5 | H54: 5 | R54: =Receipts!F36 -> 0.07
A55: Woolskins
A56: Bareskins
A57: wethers
A58: rams
A59: ewes
A60: hoggs
A61: Bareskins (total)
A62: Lambskins | C62: 20 | H62: 20 | R62: =Receipts!F39 -> 0.06
A63: Rotted skins
A64: Shorn skins
A65: Total | R65: =SUM(R41:R64) -> 0.42
A68: Poultry stock
A69: Hens | F69: 10 | H69: 7 | J69: 3 | R69: =Receipts!F33 -> 0.04
A70: Geese
A71: Capons (from chickens)
A72: Cocks & hens
A73: Total poultry stock | R73: =SUM(R69:R72) -> 0.04
A74: Total poultry excluding churchscot
A76: Poultry production
A77: Eggs
A78: Cocks & hens from churchscot of customary tenants
A79: Sum of above
A80: Total
A83: Meat
A84: Beef
A85: Mutton
A86: Pork
A87: Total
A89: Cheese
... A94: Milk
A95: Milk | R95: =Receipts!F41+Receipts!F42 -> 0.74
A96: Total | R96: =R95 -> 0.74
A98: Total Dairy Sales
A101: Verjuice
A102: Verjuice | C102: 1 | J102: 1
A104: Additional Information (not necessarily useful)
A105: Utensils
A106: ploughs
A107: carts
A108: cart-ropes
A109: corn baskets
A110: seed-sacks
A111: seed basket
A112: locks for the doors
A113: lead vessel
A114: brass pots
A115: pans
... A130: brass posnets

Sheet raw data
A1: Heading | B1: Sentence | C1: Total in Pounds | D1: Pounds | E1: Shillings | F1: Pence | G1: Corn | H1: Total Quarters Except 1 | I1: Total Bushels Except 1 | J1: Total Corn Cross-Check | K1: Total Corn Manorial Account | L1: Corn Quantity Error | M1: Quarters 1 | N1: Bushels 1 | O1: Quarters 2 | P1: Bushels 2 | Q1: Quarters 3 | R1: Bushels 3 | S1: shilling a quarter 1 | T1: pence a quarter 1 | U1: shilling a quarter 2 | V1: pence a quarter 2 | W1: shilling a quarter 3 | X1: pence a quarter 3 | Y1: shilling a quarter 4 | Z1: pence a quarter 4 | AA1: shilling a bushel 1 | AB1: pence a bushel 1 | AC1: shilling a bushel 2 | AD1: pence a bushel 2 | AE1: shilling a bushel 3 | AF1: pence a bushel 3 | AG1: shilling a bushel 4 | AH1: pence a bushel 4
A2: Arrears | B2: Richard atte Grove, reeve, renders account for 13 shilling 1.75pence of arrears from the previous year. | C2: 0.66 | D2: 0 | E2: 13 | F2: 1.75 | H2: 0 | I2: 0 | J2: 0 | K2: 0 | L2: 0 | M2: 0 | N2: 0
A3: Arrears | B3: All delivered to Geoffrey, treasurer, by 1 tally. | C3: 0 | D3: 0 | E3: 0 | F3: 0 | H3: 0 | I3: 0 | J3: 0 | K3: 0 | L3: 0 | M3: 0 | N3: 0
A4: Arrears | B4: He is quit.' | C4: 0 | D4: 0 | E4: 0 | F4: 0 | H4: 0 | I4: 0 | J4: 0 | K4: 0 | L4: 0 | M4: 0 | N4: 0
A5: Rents of assize | B5: The same renders account for 10 shilling for rents of assize at the Invention of the Cross (3 May) by view of John de Hatfeud'. | C5: 0.5 | D5: 0 | E5: 10 | F5: 0 | H5: 0 | I5: 0 | J5: 0 | K5: 0 | L5: 0 | M5: 0 | N5: 0
A6: Rents of assize | B6: £5 9 shilling 10.5pence at Michaelmas (29 September). | C6: 5.49 | D6: 5 | E6: 9 | F6: 10.5 | H6: 0 | I6: 0 | J6: 0 | K6: 0 | L6: 0 | M6: 0 | N6: 0
A7: Rents of assize | B7: Total, £5 19 shilling 10.5pence | C7: 5.99 | D7: 5 | E7: 19 | F7: 10.5 | H7: 0 | I7: 0 | J7: 0 | K7: 0 | L7: 0 | M7: 0 | N7: 0
A8: Quittances | B8: In quittance of rent of the reeve for the year 1 shilling 10pence. | C8: 0.09 | D8: 0 | E8: 1 | F8: 10 | H8: 0 | I8: 0 | J8: 0 | K8: 0 | L8: 0 | M8: 0 | N8: 0
A9: Quittances | B9: default of a certain dwelling-house and land pertaining to the church drawn into demesne £1. Total of quittances and defaults of rent, £1 1 shilling 10pence | C9: 1 | D9: 1 | E9: 0 | F9: 0 | H9: 0 | I9: 0 | J9: 0 | K9: 0 | L9: 0 | M9: 0 | N9: 0
A10: Total of rents remaining | B10: Total of rents remaining, £4 18 shilling 0.5pence | C10: 4.9 | D10: 4 | E10: 18 | F10: 0.5 | H10: 0 | I10: 0 | J10: 0 | K10: 0 | L10: 0 | M10: 0 | N10: 0
A11: Rent of the hall of Kingston hired for the year | B11: The same renders account for 15 shilling for the rent of the hall of Kingston at Christmas, Easter and Michaelmas. | C11: 0.75 | D11: 0 | E11: 15 | F11: 0 | H11: 0 | I11: 0 | J11: 0 | K11: 0 | L11: 0 | M11: 0 | N11: 0
A12: Rent of the hall of Kingston hired for the year | B12: Total, 15 shilling | C12: 0.75 | D12: 0 | E12: 15 | F12: 0 | H12: 0 | I12: 0 | J12: 0 | K12: 0 | L12: 0 | M12: 0 | N12: 0
A13: Issues of the manor | B13: The same renders account for 8 shilling from pannage of 28 pigs and 6 piglets, at 3pence a pig and 2pence a piglet, and the said right of pannage (garsevese) for 6 pigs of Richard atte Barr' this year. | C13: 0.41 | D13: 0 | E13: 8 | F13: 3 | H13: 0 | I13: 0 | J13: 0 | K13: 0 | L13: 0 | M13: 0 | N13: 0
... A33: Sale of stock | B33: l1 shilling 3pence from 15 feeble ewes sold before shearing and lambing, at 9pence a heapence Total, £1 3pence | C33: 1.01 | D33: 1 | E33: 0 | F33: 3 | H33: 0 | I33: 0 | J33: 0 | K33: 0 | L33: 0 | M33: 0 | N33: 0
A34: Sale of rye and oats | B34: The same renders account for £3 5 shilling 9.75pence from 15 quarters 1.5 bushels of rye sold, at 4 shilling 4pence a quarters. | C34: 3.29 | D34: 3 | E34: 5 | F34: 9.75 | G34: rye | H34: 15 | I34: 1.5 | J34: 15.1875 | K34: 15.1875 | L34: 0 | M34: 15 | N34: 1.5 | S34: 4 | T34: 4
A35: Sale of rye and oats | B35: £1 4 shilling 8pence from 18.5 quarters of oats sold, at 1 shilling 4pence a quarters. | C35: 1.23 | D35: 1 | E35: 4 | F35: 8 | G35: oats | H35: 18.5 | I35: 0 | J35: 18.5 | K35: 18.5 | L35: 0 | M35: 18.5 | N35: 0 | S35: 1 | T35: 4
A36: Sale of rye and oats | B36: 16 shilling 5.5pence from 4 quarters 7.5 bushels of barley sold at the audit, at 3 shilling 4pence a quarters. | C36: 0.82 | D36: 0 | E36: 16 | F36: 5.5 | G36: barley | H36: 4 | I36: 7.5 | J36: 4.9375 | K36: 4.9375 | L36: 0 | M36: 4 | N36: 7.5 | S36: 3 | T36: 4
A37: Sale of rye and oats | B37: Total, £5 6 shilling 11.25pence | C37: 5.35 | D37: 5 | E37: 6 | F37: 11.25 | H37: 0 | I37: 0 | J37: 0 | K37: 0 | L37: 0 | M37: 0 | N37: 0
A38: Entry fines and perquisites of court | B38: The same renders account for 2 shilling from Matilda de Wexford' for damage done in the lord's wood by 2 cows. | C38: 0.1 | D38: 0 | E38: 2 | F38: 0 | H38: 0 | I38: 0 | J38: 0 | K38: 0 | L38: 0 | M38: 0 | N38: 0
A39: Entry fines and perquisites of court | B39: 1 shilling from Belotota le Fort for 1 cow in the lord's wood. | C39: 0.05 | D39: 0 | E39: 1 | F39: 0 | H39: 0 | I39: 0 | J39: 0 | K39: 0 | L39: 0 | M39: 0 | N39: 0
A40: Entry fines and perquisites of court | B40: 3 shilling from Richard ate Wod' for 3 bullocks in the lord's wood. | C40: 0.15 | D40: 0 | E40: 3 | F40: 0 | H40: 0 | I40: 0 | J40: 0 | K40: 0 | L40: 0 | M40: 0 | N40: 0
A41: Entry fines and perquisites of court | B41: 3 shilling from John Derlyng for 3 bullocks. | C41: 0.15 | D41: 0 | E41: 3 | F41: 0 | H41: 0 | I41: 0 | J41: 0 | K41: 0 | L41: 0 | M41: 0 | N41: 0
A42: Entry fines and perquisites of court | B42: 3 shilling from Richard ate Barre for 3 bullocks. | C42: 0.15 | D42: 0 | E42: 3 | F42: 0 | H42: 0 | I42: 0 | J42: 0 | K42: 0 | L42: 0 | M42: 0 | N42: 0
A43: Entry fines and perquisites of court | B43: 1 shilling from Alice Bronnemay for 1 bullock. | C43: 0.05 | D43: 0 | E43: 1 | F43: 0 | H43: 0 | I43: 0 | J43: 0 | K43: 0 | L43: 0 | M43: 0 | N43: 0
A44: Entry fines and perquisites of court | B44: 2 shilling from John ate Barre for 2 bullocks. | C44: 0.1 | D44: 0 | E44: 2 | F44: 0 | H44: 0 | I44: 0 | J44: 0 | K44: 0 | L44: 0 | M44: 0 | N44: 0
A45: Entry fines and perquisites of court | B45: 1 shilling from Richard Hamund for 3 pigs. | C45: 0.05 | D45: 0 | E45: 1 | F45: 0 | H45: 0 | I45: 0 | J45: 0 | K45: 0 | L45: 0 | M45: 0 | N45: 0
A46: Entry fines and perquisites of court | B46: 8pence from Alice Bronemay for 2 piglets. | C46: 0.03 | D46: 0 | E46: 0 | F46: 8 | H46: 0 | I46: 0 | J46: 0 | K46: 0 | L46: 0 | M46: 0 | N46: 0
A47: Entry fines and perquisites of court | B47: 1 shilling 4pence from John Selueyn for 4 pigs. | C47: 0.07 | D47: 0 | E47: 1 | F47: 4 | H47: 0 | I47: 0 | J47: 0 | K47: 0 | L47: 0 | M47: 0 | N47: 0
A48: Entry fines and perquisites of court | B48: 4pence from Richard ate Wod' for 1 pig. | C48: 0.02 | D48: 0 | E48: 0 | F48: 4 | H48: 0 | I48: 0 | J48: 0 | K48: 0 | L48: 0 | M48: 0 | N48: 0
... A89: Cost of ploughs | B89: stipend of the smith repairing the ironwork of the ploughs for the year 4 shilling. | C89: 0.2 | D89: 0 | E89: 4 | F89: 0 | H89: 0 | I89: 0 | J89: 0 | K89: 0 | L89: 0 | M89: 0 | N89: 0
A90: Cost of ploughs | B90: 32 herrings bought for 16 harrowers at the sowing of the oats, 3pence this year, and each had 2 herrings. | C90: 0.01 | D90: 0 | E90: 0 | F90: 3 | G90: oats | H90: 0 | I90: 0 | J90: 0 | K90: 0 | L90: 0 | M90: 0 | N90: 0
A91: Cost of ploughs | B91: . | C91: 0 | D91: 0 | E91: 0 | F91: 0 | H91: 0 | I91: 0 | J91: 0 | K91: 0 | L91: 0 | M91: 0 | N91: 0
A92: Cost of ploughs | B92: stipend of the ploughman for the year 6 shilling. | C92: 0.3 | D92: 0 | E92: 6 | F92: 0 | H92: 0 | I92: 0 | J92: 0 | K92: 0 | L92: 0 | M92: 0 | N92: 0
A93: Cost of ploughs | B93: stipend of the drover for the year 5 shilling Total, 16 shilling 1pence | C93: 0.25 | D93: 0 | E93: 5 | F93: 1 | H93: 0 | I93: 0 | J93: 0 | K93: 0 | L93: 0 | M93: 0 | N93: 0
A94: Purchase of barley | B94: In 25 quarters 5 bushels of barley bought for the liveries of the manorial servants and the | C94: 0 | D94: 0 | E94: 0 | F94: 0 | G94: barley | H94: 25 | I94: 5 | J94: 25.625 | K94: 25.625 | L94: 0 | M94: 25 | N94: 5
A95: Purchase of barley | B95: provision of the harvest £4 5 shilling 5pence, at 3 shilling 4pence a quarters. | C95: 4.27 | D95: 4 | E95: 5 | F95: 5 | H95: 0 | I95: 0 | J95: 0 | K95: 0 | L95: 0 | M95: 0 | N95: 0 | S95: 3 | T95: 4
A96: Purchase of barley | B96: Total, £4 5 shilling 5pence | C96: 4.27 | D96: 4 | E96: 5 | F96: 5 | H96: 0 | I96: 0 | J96: 0 | K96: 0 | L96: 0 | M96: 0 | N96: 0
A97: Cost of carts | B97: In 1 pair of wheels bought for the cart 1 shilling 8pence. | C97: 0.08 | D97: 0 | E97: 1 | F97: 8 | H97: 0 | I97: 0 | J97: 0 | K97: 0 | L97: 0 | M97: 0 | N97: 0
A98: Cost of carts | B98: clouts and nails bought for the cart 1 shilling. | C98: 0.05 | D98: 0 | E98: 1 | F98: 0 | H98: 0 | I98: 0 | J98: 0 | K98: 0 | L98: 0 | M98: 0 | N98: 0
A99: Cost of carts | B99: grease bought for the same 4pence. | C99: 0.02 | D99: 0 | E99: 0 | F99: 4 | H99: 0 | I99: 0 | J99: 0 | K99: 0 | L99: 0 | M99: 0 | N99: 0
A100: Cost of carts | B100: 1 hemp rope bought to tie the cart 8pence. | C100: 0.03 | D100: 0 | E100: 0 | F100: 8 | H100: 0 | I100: 0 | J100: 0 | K100: 0 | L100: 0 | M100: 0 | N100: 0
A101: Cost of carts | B101: 1 saddle with saddle-pads bought for the cart 6pence. | C101: 0.03 | D101: 0 | E101: 0 | F101: 6 | H101: 0 | I101: 0 | J101: 0 | K101: 0 | L101: 0 | M101: 0 | N101: 0
A102: Cost of carts | B102: shoeing the horses, 1 shilling 2pence this year. | C102: 0.06 | D102: 0 | E102: 1 | F102: 2 | H102: 0 | I102: 0 | J102: 0 | K102: 0 | L102: 0 | M102: 0 | N102: 0
A103: Cost of carts | B103: . | C103: 0 | D103: 0 | E103: 0 | F103: 0 | H103: 0 | I103: 0 | J103: 0 | K103: 0 | L103: 0 | M103: 0 | N103: 0
A104: Cost of carts | B104: 1 horse bought 7 shilling 3.5pence Total, 12 shilling 7.5pence | C104: 0.36 | D104: 0 | E104: 7 | F104: 3.5 | H104: 0 | I104: 0 | J104: 0 | K104: 0 | L104: 0 | M104: 0 | N104: 0
A105: Small necessaries | B105: In 1 bushels of salt bought 3.5pence. | C105: 0.01 | D105: 0 | E105: 0 | F105: 3.5 | H105: 0 | I105: 1 | J105: 0.125 | K105: 0.125 | L105: 0 | M105: 0 | N105: 1
A106: Small necessaries | B106: 5 ells of canvas bought for packing the wool of Esher 1 shilling 3pence, at 3pence an ell. | C106: 0.06 | D106: 0 | E106: 1 | F106: 3 | H106: 0 | I106: 0 | J106: 0 | K106: 0 | L106: 0 | M106: 0 | N106: 0
A107: Small necessaries | B107: . | C107: 0 | D107: 0 | E107: 0 | F107: 0 | H107: 0 | I107: 0 | J107: 0 | K107: 0 | L107: 0 | M107: 0 | N107: 0
... A151: Cost of the sheepfold (ovil') | B151: stipend of 1 man keeping the animals at Northwod' and mending fences for the year 3 shilling 6pence Total, 13 shilling 6pence | C151: 0.17 | D151: 0 | E151: 3 | F151: 6 | H151: 0 | I151: 0 | J151: 0 | K151: 0 | L151: 0 | M151: 0 | N151: 0
A152: Threshing of corn | B152: In threshing 24 quarters of rye by piece-work 4 shilling, at 2pence a quarters. | C152: 0.21 | D152: 0 | E152: 4 | F152: 2 | G152: rye | H152: 24 | I152: 0 | J152: 24 | K152: 24 | L152: 0 | M152: 24 | N152: 0
A153: Threshing of corn | B153: . | C153: 0 | D153: 0 | E153: 0 | F153: 0 | H153: 0 | I153: 0 | J153: 0 | K153: 0 | L153: 0 | M153: 0 | N153: 0
A154: Threshing of corn | B154: threshing 4 quarters 5 bushels of barley by piece-work 6.75pence, at 1 .5pence a quarters. | C154: 0.03 | D154: 0 | E154: 0 | F154: 6.75 | G154: barley | H154: 4 | I154: 5 | J154: 4.625 | K154: 4.625 | L154: 0 | M154: 4 | N154: 5
A155: Threshing of corn | B155: . | C155: 0 | D155: 0 | E155: 0 | F155: 0 | H155: 0 | I155: 0 | J155: 0 | K155: 0 | L155: 0 | M155: 0 | N155: 0
A156: Threshing of corn | B156: threshing 36 quarters of oats by piece-work 3 shilling, at 1pence a quarters. | C156: 0.15 | D156: 0 | E156: 3 | F156: 1 | G156: oats | H156: 36 | I156: 0 | J156: 36 | K156: 36 | L156: 0 | M156: 36 | N156: 0
A157: Threshing of corn | B157: . | C157: 0 | D157: 0 | E157: 0 | F157: 0 | H157: 0 | I157: 0 | J157: 0 | K157: 0 | L157: 0 | M157: 0 | N157: 0
A158: Threshing of corn | B158: winnowing the same corn 1 shilling 4pence, at 1pence per 4 quarters. | C158: 0.07 | D158: 0 | E158: 1 | F158: 4 | H158: 4 | I158: 0 | J158: 4 | K158: 4 | L158: 0 | M158: 4 | N158: 0
A159: Threshing of corn | B159: Total, 8 shilling 10.5pence | C159: 0.44 | D159: 0 | E159: 8 | F159: 10.5 | H159: 0 | I159: 0 | J159: 0 | K159: 0 | L159: 0 | M159: 0 | N159: 0
A160: Mowing the meadows, weeding the corn | B160: In weeding the corn this year 6pence. | C160: 0.03 | D160: 0 | E160: 0 | F160: 6 | H160: 0 | I160: 0 | J160: 0 | K160: 0 | L160: 0 | M160: 0 | N160: 0
A161: Mowing the meadows, weeding the corn | B161: mowing the said meadow of Brodemed' by custom, bread from stock and 1 wether with its skin from the said sheepfo1pence. | C161: 0 | D161: 0 | E161: 0 | F161: 1 | H161: 0 | I161: 0 | J161: 0 | K161: 0 | L161: 0 | M161: 0 | N161: 0
A162: Mowing the meadows, weeding the corn | B162: cheese bought 3pence. | C162: 0.01 | D162: 0 | E162: 0 | F162: 3 | H162: 0 | I162: 0 | J162: 0 | K162: 0 | L162: 0 | M162: 0 | N162: 0
A163: Mowing the meadows, weeding the corn | B163: mowing the meadow of Esher by piece-work besides that done by custom 1 shilling 2pence. | C163: 0.06 | D163: 0 | E163: 1 | F163: 2 | H163: 0 | I163: 0 | J163: 0 | K163: 0 | L163: 0 | M163: 0 | N163: 0
A164: Mowing the meadows, weeding the corn | B164: carrying the hay of Brodemed' to the shed by custom, bread from stock. | C164: 0 | D164: 0 | E164: 0 | F164: 0 | H164: 0 | I164: 0 | J164: 0 | K164: 0 | L164: 0 | M164: 0 | N164: 0
A165: Mowing the meadows, weeding the corn | B165: . | C165: 0 | D165: 0 | E165: 0 | F165: 0 | H165: 0 | I165: 0 | J165: 0 | K165: 0 | L165: 0 | M165: 0 | N165: 0
A166: Mowing the meadows, weeding the corn | B166: herrings bought 4pence. | C166: 0.02 | D166: 0 | E166: 0 | F166: 4 | H166: 0 | I166: 0 | J166: 0 | K166: 0 | L166: 0 | M166: 0 | N166: 0
A167: Mowing the meadows, weeding the corn | B167: mowing the meadow of Northwod' by piece-work, 8pence this year. | C167: 0.03 | D167: 0 | E167: 0 | F167: 8 | H167: 0 | I167: 0 | J167: 0 | K167: 0 | L167: 0 | M167: 0 | N167: 0
A168: Mowing the meadows, weeding the corn | B168: Total, 2 shilling 11pence | C168: 0.15 | D168: 0 | E168: 2 | F168: 11 | H168: 0 | I168: 0 | J168: 0 | K168: 0 | L168: 0 | M168: 0 | N168: 0
... A191: Cost of the vineyard | B191: collecting vines to make verjuice 3 shilling 10pence. | C191: 0.19 | D191: 0 | E191: 3 | F191: 10 | H191: 0 | I191: 0 | J191: 0 | K191: 0 | L191: 0 | M191: 0 | N191: 0
A192: Cost of the vineyard | B192: 4 bushels of salt bought to salt verjuice 1 shilling 2pence, at 3.5pence a bushels Delivered to Peter, the lord's squire, whilst he remains at Esher in order to collect vines and make verjuice, by order of the bishop and by his letters, 3pence 6pence. | C192: 0.06 | D192: 0 | E192: 1 | F192: 2 | H192: 0 | I192: 4 | J192: 0.5 | K192: 0.5 | L192: 0 | M192: 0 | N192: 4 | AA192: 0 | AB192: 3.5
A193: Cost of the vineyard | B193: stipend of Alexander the vintner for the year 5 shilling. | C193: 0.25 | D193: 0 | E193: 5 | F193: 0 | H193: 0 | I193: 0 | J193: 0 | K193: 0 | L193: 0 | M193: 0 | N193: 0
A194: Cost of the vineyard | B194: 1 cask bought for putting the verjuice in 2 shilling 2pence. | C194: 0.11 | D194: 0 | E194: 2 | F194: 2 | H194: 0 | I194: 0 | J194: 0 | K194: 0 | L194: 0 | M194: 0 | N194: 0
A195: Cost of the vineyard | B195: 2 barrels bought for the same 1 shilling Total, £1 19 shilling 8pence | C195: 1.98 | D195: 1 | E195: 19 | F195: 8 | H195: 0 | I195: 0 | J195: 0 | K195: 0 | L195: 0 | M195: 0 | N195: 0
A196: Payment of outside rents | B196: In rent paid at Michaelmas to the Abbot of Chertsey for the land of Northwod' 6 shilling. | C196: 0.3 | D196: 0 | E196: 6 | F196: 0 | H196: 0 | I196: 0 | J196: 0 | K196: 0 | L196: 0 | M196: 0 | N196: 0
A197: Payment of outside rents | B197: 2 ploughshares bought for the same, paid to the same this year, 1 shilling 2pence Total, 7 shilling 2pence | C197: 0.06 | D197: 0 | E197: 1 | F197: 2 | H197: 0 | I197: 0 | J197: 0 | K197: 0 | L197: 0 | M197: 0 | N197: 0
A198: Foreign expenses | B198: Given for the keeping of a certain ox by the assessor of the fifteenth at Northwod' 1 shilling | C198: 0.05 | D198: 0 | E198: 1 | F198: 0 | H198: 0 | I198: 0 | J198: 0 | K198: 0 | L198: 0 | M198: 0 | N198: 0
A199: Foreign expenses | B199: 10pence Total, 1 shilling 10pence | C199: 0.09 | D199: 0 | E199: 1 | F199: 10 | H199: 0 | I199: 0 | J199: 0 | K199: 0 | L199: 0 | M199: 0 | N199: 0
A200: Total of all expenses | B200: Total of all expenses, £12 11 shilling 6pence | C200: 12.58 | D200: 12 | E200: 11 | F200: 6 | H200: 0 | I200: 0 | J200: 0 | K200: 0 | L200: 0 | M200: 0 | N200: 0
A201: And thus he owes | B201: And thus he owes, £4 17 shilling 9.75pence | C201: 4.89 | D201: 4 | E201: 17 | F201: 9.75 | H201: 0 | I201: 0 | J201: 0 | K201: 0 | L201: 0 | M201: 0 | N201: 0
A202: Cash deliveries | B202: Delivered to Sir Geoffrey, treasurer of Wolvesey, by 1 tally, £3. | C202: 3 | D202: 3 | E202: 0 | F202: 0 | H202: 0 | I202: 0 | J202: 0 | K202: 0 | L202: 0 | M202: 0 | N202: 0
A203: And he owes clear, | B203: And he owes clear, £1 17 shilling 9.75pence | C203: 1.89 | D203: 1 | E203: 17 | F203: 9.75 | H203: 0 | I203: 0 | J203: 0 | K203: 0 | L203: 0 | M203: 0 | N203: 0
A204: Rye | B204: {yield: four-fold less 1 quarters} | C204: 0 | D204: 0 | E204: 0 | F204: 0 | H204: 1 | I204: 0 | J204: 1 | K204: 1 | L204: 0 | M204: 1 | N204: 0
A205: Rye | B205: The same renders account for 24 quarters of rye from the issue of the grange threshed by piece-work. | C205: 0 | D205: 0 | E205: 0 | F205: 0 | G205: rye | H205: 24 | I205: 0 | J205: 24 | K205: 24 | L205: 0 | M205: 24 | N205: 0
A206: Rye | B206: 6 quarters from the increment. | C206: 0 | D206: 0 | E206: 0 | F206: 0 | H206: 6 | I206: 0 | J206: 6 | K206: 6 | L206: 0 | M206: 6 | N206: 0
A207: Rye | B207: Total, 30 quarters. | C207: 0 | D207: 0 | E207: 0 | F207: 0 | H207: 30 | I207: 0 | J207: 30 | K207: 30 | L207: 0 | M207: 30 | N207: 0
A208: Rye | B208: Sown over 12 acres at Esher and 13.5 acres at Nortwod', 6 quarters 3 bushels. | C208: 0 | D208: 0 | E208: 0 | F208: 0 | H208: 6 | I208: 3 | J208: 6.375 | K208: 6.375 | L208: 0 | M208: 6 | N208: 3
A209: Rye | B209: that is, 2 bushels an acre. | C209: 0 | D209: 0 | E209: 0 | F209: 0 | H209: 0 | I209: 2 | J209: 0.25 | K209: 0.25 | L209: 0 | M209: 0 | N209: 2
A210: Rye | B210: . | C210: 0 | D210: 0 | E210: 0 | F210: 0 | H210: 0 | I210: 0 | J210: 0 | K210: 0 | L210: 0 | M210: 0 | N210: 0
A211: Rye | B211: bread baked for the harrowers at the sowing of the oats, 1 bushels. | C211: 0 | D211: 0 | E211: 0 | F211: 0 | G211: oats | H211: 0 | I211: 1 | J211: 0.125 | K211: 0.125 | L211: 0 | M211: 0 | N211: 1
A212: Rye | B212: bread baked for the mowing of the meadows, 3 bushels. | C212: 0 | D212: 0 | E212: 0 | F212: 0 | H212: 0 | I212: 3 | J212: 0.375 | K212: 0.375 | L212: 0 | M212: 0 | N212: 3
A213: Rye | B213: bread baked for the carrying of the hay from the meadows to the manor of Esher, 1 bushels. | C213: 0 | D213: 0 | E213: 0 | F213: 0 | H213: 0 | I213: 1 | J213: 0.125 | K213: 0.125 | L213: 0 | M213: 0 | N213: 1
A214: Rye | B214: bread baked for the shearing of the sheep, .5 bushels. | C214: 0 | D214: 0 | E214: 0 | F214: 0 | H214: 0 | I214: 5 | J214: 0.625 | K214: 0.625 | L214: 0 | M214: 0 | N214: 5
A215: Rye | B215: bread baked for the provision of the harvest, 1 quarters 2 bushels Delivered to 1 vintner for the year, 6.5 quarters, taking a quarter every 8 weeks. | C215: 0 | D215: 0 | E215: 0 | F215: 0 | H215: 6.5 | I215: 2 | J215: 6.75 | K215: 1.25 | L215: 5.5 | M215: 1 | N215: 2 | O215: 6.5 | P215: 0
A216: Rye | B216: Sold, 15 quarters 1.5 bushels Total, 30 quarters. | C216: 0 | D216: 0 | E216: 0 | F216: 0 | H216: 30 | I216: 1.5 | J216: 30.1875 | K216: 15.1875 | L216: 15 | M216: 15 | N216: 1.5 | O216: 30 | P216: 0
A217: Barley | B217: {yield: four-fold less 2.5 quarters} | C217: 0 | D217: 0 | E217: 0 | F217: 0 | H217: 2.5 | I217: 0 | J217: 2.5 | K217: 2.5 | L217: 0 | M217: 2.5 | N217: 0
A218: Barley | B218: The same render account for 4 quarters 5 bushels of barley from the issue of the grange threshed by piece-work. | C218: 0 | D218: 0 | E218: 0 | F218: 0 | G218: barley | H218: 4 | I218: 5 | J218: 4.625 | K218: 4.625 | L218: 0 | M218: 4 | N218: 5
A219: Barley | B219: 1 quarters from the increment. | C219: 0 | D219: 0 | E219: 0 | F219: 0 | H219: 1 | I219: 0 | J219: 1 | K219: 1 | L219: 0 | M219: 1 | N219: 0
A220: Barley | B220: 25 quarters 5 bushels bought. | C220: 0 | D220: 0 | E220: 0 | F220: 0 | H220: 25 | I220: 5 | J220: 25.625 | K220: 25.625 | L220: 0 | M220: 25 | N220: 5
A221: Barley | B221: Total, 31 quarters 2 .5 bushels | C221: 0 | D221: 0 | E221: 0 | F221: 0 | H221: 31 | I221: 5 | J221: 31.625 | K221: 31 | L221: 0.625 | M221: 31 | N221: 0 | O221: 0 | P221: 5
A222: Barley | B222: Sown over 2 acres, 1 quarters. | C222: 0 | D222: 0 | E222: 0 | F222: 0 | H222: 1 | I222: 0 | J222: 1 | K222: 1 | L222: 0 | M222: 1 | N222: 0
A223: Barley | B223: Delivered to 1 ploughman and 1 drover for the year, 13 quarters, each of them taking a quarter every 8 weeks. {Henceforth the ploughman and drover should take a quarter every 10 weeks and the keeper of animals every 12 weeks). | C223: 0 | D223: 0 | E223: 0 | F223: 0 | H223: 13 | I223: 0 | J223: 13 | K223: 13 | L223: 0 | M223: 13 | N223: 0
A224: Barley | B224: stipend of 1 vintner digging in the vineyard for 13 weeks, 1 quarters 5 bushels Delivered to 1 shepherd for the year, 5 quarters 1.5 bushels, taking a quarter every 10 weeks. | C224: 0 | D224: 0 | E224: 0 | F224: 0 | H224: 5 | I224: 1.5 | J224: 5.1875 | K224: 1.625 | L224: 3.5625 | M224: 1 | N224: 5 | O224: 5 | P224: 1.5
...

Sheet Issues of the Grange raw
A1: Heading | B1: Sentence | C1: Quarters 1_x | D1: Bushels 1_x | E1: Sown Quarters | F1: Sown Bushels | G1: Sown Total Quarters | H1: Bought in Quarters | I1: Bought in Bushels | J1: Bought in Total Quarters | K1: Tithe Quarters | L1: Tithe Bushels | M1: Tithe Total Quarters | N1: Manorial servants & livestock Quarters | O1: Manorial servants & livestock Bushels | P1: Manorial servants & livestock Total Quarters | Q1: Sold Quarters | R1: Sold Bushels | S1: Sold Total Quarters | T1: Account Quarters | U1: Account Bushels | V1: Account Total Quarters | W1: bought only | X1: Total Quarters Except 1 | Y1: Total Bushels Except 1 | Z1: Total Corn Cross-Check | AA1: Total Corn Manorial Account | AB1: Corn Quantity Error | AC1: Quarters 1_y | AD1: Bushels 1_y | AE1: Quarters 2 | AF1: Bushels 2 | AG1: Quarters 3 | AH1: Bushels 3
A2: Cash deliveries | B2: Total | C2: 0 | D2: 0 | E2: 0 | F2: 0 | G2: 0 | H2: 0 | I2: 0 | J2: 0 | K2: 0 | L2: 0 | M2: 0 | N2: 0 | O2: 0 | P2: 0 | Q2: 0 | R2: 0 | S2: 0 | T2: 0 | U2: 0 | V2: 0 | W2: 0
A3: Rye | B3: {yield: four-fold less 1 qr} | C3: 0 | D3: 0 | E3: 0 | F3: 0 | G3: 0 | H3: 0 | I3: 0 | J3: 0 | K3: 0 | L3: 0 | M3: 0 | N3: 0 | O3: 0 | P3: 0 | Q3: 0 | R3: 0 | S3: 0 | T3: 0 | U3: 0 | V3: 0 | W3: 0
A4: Rye | B4: The same renders account for 24 quarters of rye from the issue of the grange threshed by piece-work. | C4: 0 | D4: 0 | E4: 0 | F4: 0 | G4: 0 | H4: 0 | I4: 0 | J4: 0 | K4: 0 | L4: 0 | M4: 0 | N4: 0 | O4: 0 | P4: 0 | Q4: 0 | R4: 0 | S4: 0 | T4: 24 | U4: 0 | V4: 24 | W4: 0 | X4: 24 | Y4: 0 | Z4: 24 | AA4: 24 | AB4: 0 | AC4: 24 | AD4: 0
A5: Rye | B5: 6 quarters from the increment. | C5: 0 | D5: 0 | E5: 0 | F5: 0 | G5: 0 | H5: 0 | I5: 0 | J5: 0 | K5: 0 | L5: 0 | M5: 0 | N5: 0 | O5: 0 | P5: 0 | Q5: 0 | R5: 0 | S5: 0 | T5: 0 | U5: 0 | V5: 0 | W5: 0 | X5: 6 | Y5: 0 | Z5: 6 | AA5: 6 | AB5: 0 | AC5: 6 | AD5: 0
A6: Rye | B6: Total, 30 quarters. | C6: 0 | D6: 0 | E6: 0 | F6: 0 | G6: 0 | H6: 0 | I6: 0 | J6: 0 | K6: 0 | L6: 0 | M6: 0 | N6: 0 | O6: 0 | P6: 0 | Q6: 0 | R6: 0 | S6: 0 | T6: 0 | U6: 0 | V6: 0 | W6: 0 | X6: 30 | Y6: 0 | Z6: 30 | AA6: 30 | AB6: 0 | AC6: 30 | AD6: 0
A7: Rye | B7: Sown over 12 acres at Esher and 13.5 acres at Nortwod', 6 quarters 3 bushels. | C7: 0 | D7: 0 | E7: 6 | F7: 3 | G7: 6.375 | H7: 0 | I7: 0 | J7: 0 | K7: 0 | L7: 0 | M7: 0 | N7: 0 | O7: 0 | P7: 0 | Q7: 0 | R7: 0 | S7: 0 | T7: 0 | U7: 0 | V7: 0 | W7: 0 | X7: 6 | Y7: 3 | Z7: 6.375 | AA7: 6.375 | AB7: 0 | AC7: 6 | AD7: 3
A8: Rye | B8: that is, 2 bushels an acre. | C8: 0 | D8: 0 | E8: 0 | F8: 0 | G8: 0 | H8: 0 | I8: 0 | J8: 0 | K8: 0 | L8: 0 | M8: 0 | N8: 0 | O8: 0 | P8: 0 | Q8: 0 | R8: 0 | S8: 0 | T8: 0 | U8: 0 | V8: 0 | W8: 0 | X8: 0 | Y8: 2 | Z8: 0.25 | AA8: 0.25 | AB8: 0 | AC8: 0 | AD8: 2
A9: Rye | B9: . | C9: 0 | D9: 0 | E9: 0 | F9: 0 | G9: 0 | H9: 0 | I9: 0 | J9: 0 | K9: 0 | L9: 0 | M9: 0 | N9: 0 | O9: 0 | P9: 0 | Q9: 0 | R9: 0 | S9: 0 | T9: 0 | U9: 0 | V9: 0 | W9: 0 | X9: 0 | Y9: 0 | Z9: 0 | AA9: 0 | AB9: 0 | AC9: 0 | AD9: 0
A10: Rye | B10: bread baked for the harrowers at the sowing of the oats, 1 bushels. | C10: 0 | D10: 0 | E10: 0 | F10: 0 | G10: 0 | H10: 0 | I10: 0 | J10: 0 | K10: 0 | L10: 0 | M10: 0 | N10: 0 | O10: 0 | P10: 0 | Q10: 0 | R10: 0 | S10: 0 | T10: 0 | U10: 0 | V10: 0 | W10: 0 | X10: 0 | Y10: 1 | Z10: 0.125 | AA10: 0.125 | AB10: 0 | AC10: 0 | AD10: 1
A11: Rye | B11: bread baked for the mowing of the meadows, 3 bushels. | C11: 0 | D11: 0 | E11: 0 | F11: 0 | G11: 0 | H11: 0 | I11: 0 | J11: 0 | K11: 0 | L11: 0 | M11: 0 | N11: 0 | O11: 0 | P11: 0 | Q11: 0 | R11: 0 | S11: 0 | T11: 0 | U11: 0 | V11: 0 | W11: 0 | X11: 0 | Y11: 3 | Z11: 0.375 | AA11: 0.375 | AB11: 0 | AC11: 0 | AD11: 3
A12: Rye | B12: bread baked for the carrying of the hay from the meadows to the manor of Esher, 1 bushels. | C12: 0 | D12: 0 | E12: 0 | F12: 0 | G12: 0 | H12: 0 | I12: 0 | J12: 0 | K12: 0 | L12: 0 | M12: 0 | N12: 0 | O12: 0 | P12: 0 | Q12: 0 | R12: 0 | S12: 0 | T12: 0 | U12: 0 | V12: 0 | W12: 0 | X12: 0 | Y12: 1 | Z12: 0.125 | AA12: 0.125 | AB12: 0 | AC12: 0 | AD12: 1
A13: Rye | B13: bread baked for the shearing of the sheep, .5 bushels. | C13: 0 | D13: 0 | E13: 0 | F13: 0 | G13: 0 | H13: 0 | I13: 0 | J13: 0 | K13: 0 | L13: 0 | M13: 0 | N13: 0 | O13: 0 | P13: 0 | Q13: 0 | R13: 0 | S13: 0 | T13: 0 | U13: 0 | V13: 0 | W13: 0 | X13: 0 | Y13: 5 | Z13: 0.625 | AA13: 0.625 | AB13: 0 | AC13: 0 | AD13: 5
A14: Rye | B14: bread baked for the provision of the harvest, 1 qr 2 bushels Delivered to 1 vintner for the year, 6.5 quarters, taking a quarter every 8 weeks. | C14: 0 | D14: 0 | E14: 0 | F14: 0 | G14: 0 | H14: 0 | I14: 0 | J14: 0 | K14: 0 | L14: 0 | M14: 0 | N14: 0 | O14: 0 | P14: 0 | Q14: 0 | R14: 0 | S14: 0 | T14: 0 | U14: 0 | V14: 0 | W14: 0
A15: Rye | B15: Sold, 15 quarters 1.5 bushels Total, 30 quarters. | C15: 0 | D15: 0 | E15: 0 | F15: 0 | G15: 0 | H15: 0 | I15: 0 | J15: 0 | K15: 0 | L15: 0 | M15: 0 | N15: 0 | O15: 0 | P15: 0 | Q15: 45 | R15: 1.5 | S15: 45.1875 | T15: 0 | U15: 0 | V15: 0 | W15: 0 | X15: 30 | Y15: 1.5 | Z15: 30.1875 | AA15: 15.1875 | AB15: 15 | AC15: 15 | AD15: 1.5 | AE15: 30 | AF15: 0
A16: Rye | B16: Total | C16: 0 | D16: 0 | E16: 0 | F16: 0 | G16: 0 | H16: 0 | I16: 0 | J16: 0 | K16: 0 | L16: 0 | M16: 0 | N16: 0 | O16: 0 | P16: 0 | Q16: 0 | R16: 0 | S16: 0 | T16: 0 | U16: 0 | V16: 0 | W16: 0
A17: Barley | B17: {yield: four-fold less 2.5 quarters} | C17: 0 | D17: 0 | E17: 0 | F17: 0 | G17: 0 | H17: 0 | I17: 0 | J17: 0 | K17: 0 | L17: 0 | M17: 0 | N17: 0 | O17: 0 | P17: 0 | Q17: 0 | R17: 0 | S17: 0 | T17: 0 | U17: 0 | V17: 0 | W17: 0 | X17: 2.5 | Y17: 0 | Z17: 2.5 | AA17: 2.5 | AB17: 0 | AC17: 2.5 | AD17: 0
A18: Barley | B18: The same render account for 4 quarters 5 bushels of barley from the issue of the grange threshed by piece-work. | C18: 0 | D18: 0 | E18: 0 | F18: 0 | G18: 0 | H18: 0 | I18: 0 | J18: 0 | K18: 0 | L18: 0 | M18: 0 | N18: 0 | O18: 0 | P18: 0 | Q18: 0 | R18: 0 | S18: 0 | T18: 4 | U18: 5 | V18: 4.625 | W18: 0 | X18: 4 | Y18: 5 | Z18: 4.625 | AA18: 4.625 | AB18: 0 | AC18: 4 | AD18: 5
A19: Barley | B19: 1 qr from the increment. | C19: 0 | D19: 0 | E19: 0 | F19: 0 | G19: 0 | H19: 0 | I19: 0 | J19: 0 | K19: 0 | L19: 0 | M19: 0 | N19: 0 | O19: 0 | P19: 0 | Q19: 0 | R19: 0 | S19: 0 | T19: 0 | U19: 0 | V19: 0 | W19: 0
A20: Barley | B20: 25 quarters 5 bushels bought. | C20: 0 | D20: 0 | E20: 0 | F20: 0 | G20: 0 | H20: 25 | I20: 5 | J20: 25.625 | K20: 0 | L20: 0 | M20: 0 | N20: 0 | O20: 0 | P20: 0 | Q20: 0 | R20: 0 | S20: 0 | T20: 0 | U20: 0 | V20: 0 | W20: 0 | X20: 25 | Y20: 5 | Z20: 25.625 | AA20: 25.625 | AB20: 0 | AC20: 25 | AD20: 5
A21: Barley | B21: Total, 31 quarters 2 .5 bushels | C21: 0 | D21: 0 | E21: 0 | F21: 0 | G21: 0 | H21: 0 | I21: 0 | J21: 0 | K21: 0 | L21: 0 | M21: 0 | N21: 0 | O21: 0 | P21: 0 | Q21: 0 | R21: 0 | S21: 0 | T21: 0 | U21: 0 | V21: 0 | W21: 0 | X21: 31 | Y21: 5 | Z21: 31.625 | AA21: 31 | AB21: 0.625 | AC21: 31 | AD21: 0 | AE21: 0 | AF21: 5
A22: Barley | B22: Sown over 2 acres, 1 qr. | C22: 0 | D22: 0 | E22: 0 | F22: 0 | G22: 0 | H22: 0 | I22: 0 | J22: 0 | K22: 0 | L22: 0 | M22: 0 | N22: 0 | O22: 0 | P22: 0 | Q22: 0 | R22: 0 | S22: 0 | T22: 0 | U22: 0 | V22: 0 | W22: 0
A23: Barley | B23: Delivered to 1 ploughman and 1 drover for the year, 13 quarters, each of them taking a quarter every 8 weeks. {Henceforth the ploughman and drover should take a quarter every 10 weeks and the keeper of animals every 12 weeks). | C23: 0 | D23: 0 | E23: 0 | F23: 0 | G23: 0 | H23: 0 | I23: 0 | J23: 0 | K23: 0 | L23: 0 | M23: 0 | N23: 0 | O23: 0 | P23: 0 | Q23: 0 | R23: 0 | S23: 0 | T23: 0 | U23: 0 | V23: 0 | W23: 0 | X23: 13 | Y23: 0 | Z23: 13 | AA23: 13 | AB23: 0 | AC23: 13 | AD23: 0
A24: Barley | B24: stipend of 1 vintner digging in the vineyard for 13 weeks, 1 qr 5 bushels Delivered to 1 shepherd for the year, 5 quarters 1.5 bushels, taking a quarter every 10 weeks. | C24: 0 | D24: 0 | E24: 0 | F24: 0 | G24: 0 | H24: 0 | I24: 0 | J24: 0 | K24: 0 | L24: 0 | M24: 0 | N24: 0 | O24: 0 | P24: 0 | Q24: 0 | R24: 0 | S24: 0 | T24: 0 | U24: 0 | V24: 0 | W24: 0
A25: Barley | B25: Delivered to 1 man keeping the animals at Northwod and mending fences, 4 quarters 2.5 bushels, taking a quarter every 12 weeks. | C25: 0 | D25: 0 | E25: 0 | F25: 0 | G25: 0 | H25: 0 | I25: 0 | J25: 0 | K25: 0 | L25: 0 | M25: 0 | N25: 0 | O25: 0 | P25: 0 | Q25: 0 | R25: 0 | S25: 0 | T25: 0 | U25: 0 | V25: 0 | W25: 0 | X25: 4 | Y25: 2.5 | Z25: 4.3125 | AA25: 4.3125 | AB25: 0 | AC25: 4 | AD25: 2.5
A26: Barley | B26: . | C26: 0 | D26: 0 | E26: 0 | F26: 0 | G26: 0 | H26: 0 | I26: 0 | J26: 0 | K26: 0 | L26: 0 | M26: 0 | N26: 0 | O26: 0 | P26: 0 | Q26: 0 | R26: 0 | S26: 0 | T26: 0 | U26: 0 | V26: 0 | W26: 0 | X26: 0 | Y26: 0 | Z26: 0 | AA26: 0 | AB26: 0 | AC26: 0 | AD26: 0
A27: Barley | B27: bread baked for the provision of the harvest by mixing with rye, 1 qr 2 bushels Sold at the audit, 4 quarters 7.5 bushels Total, 31 quarters 2.5 bushels | C27: 0 | D27: 0 | E27: 0 | F27: 0 | G27: 0 | H27: 0 | I27: 0 | J27: 0 | K27: 0 | L27: 0 | M27: 0 | N27: 0 | O27: 0 | P27: 0 | Q27: 35 | R27: 10 | S27: 36.25 | T27: 0 | U27: 0 | V27: 0 | W27: 0
A28: Barley | B28: Total | C28: 0 | D28: 0 | E28: 0 | F28: 0 | G28: 0 | H28: 0 | I28: 0 | J28: 0 | K28: 0 | L28: 0 | M28: 0 | N28: 0 | O28: 0 | P28: 0 | Q28: 0 | R28: 0 | S28: 0 | T28: 0 | U28: 0 | V28: 0 | W28: 0
A29: Oats | B29: The same render account for 36 quarters of oats from the issue of the grange threshed by piece-work. | C29: 0 | D29: 0 | E29: 0 | F29: 0 | G29: 0 | H29: 0 | I29: 0 | J29: 0 | K29: 0 | L29: 0 | M29: 0 | N29: 0 | O29: 0 | P29: 0 | Q29: 0 | R29: 0 | S29: 0 | T29: 36 | U29: 0 | V29: 36 | W29: 0 | X29: 36 | Y29: 0 | Z29: 36 | AA29: 36 | AB29: 0 | AC29: 36 | AD29: 0
A30: Oats | B30: 9 quarters from the increment. | C30: 0 | D30: 0 | E30: 0 | F30: 0 | G30: 0 | H30: 0 | I30: 0 | J30: 0 | K30: 0 | L30: 0 | M30: 0 | N30: 0 | O30: 0 | P30: 0 | Q30: 0 | R30: 0 | S30: 0 | T30: 0 | U30: 0 | V30: 0 | W30: 0 | X30: 9 | Y30: 0 | Z30: 9 | AA30: 9 | AB30: 0 | AC30: 9 | AD30: 0
A31: Oats | B31: 3 quarters by estimation in sheaves for supporting oxen. | C31: 0 | D31: 0 | E31: 0 | F31: 0 | G31: 0 | H31: 0 | I31: 0 | J31: 0 | K31: 0 | L31: 0 | M31: 0 | N31: 0 | O31: 0 | P31: 0 | Q31: 0 | R31: 0 | S31: 0 | T31: 0 | U31: 0 | V31: 0 | W31: 0 | X31: 3 | Y31: 0 | Z31: 3 | AA31: 3 | AB31: 0 | AC31: 3 | AD31: 0
A32: Oats | B32: Total, 48 quarters. | C32: 0 | D32: 0 | E32: 0 | F32: 0 | G32: 0 | H32: 0 | I32: 0 | J32: 0 | K32: 0 | L32: 0 | M32: 0 | N32: 0 | O32: 0 | P32: 0 | Q32: 0 | R32: 0 | S32: 0 | T32: 0 | U32: 0 | V32: 0 | W32: 0 | X32: 48 | Y32: 0 | Z32: 48 | AA32: 48 | AB32: 0 | AC32: 48 | AD32: 0
A33: Oats | B33: Total, 48 quarters. | C33: 0 | D33: 0 | E33: 0 | F33: 0 | G33: 0 | H33: 0 | I33: 0 | J33: 0 | K33: 0 | L33: 0 | M33: 0 | N33: 0 | O33: 0 | P33: 0 | Q33: 0 | R33: 0 | S33: 0 | T33: 0 | U33: 0 | V33: 0 | W33: 0 | X33: 48 | Y33: 0 | Z33: 48 | AA33: 48 | AB33: 0 | AC33: 48 | AD33: 0
A34: Oats | B34: Sown over 20 acres at Esher and 22 acres at Northwod, 21 quarters. | C34: 0 | D34: 0 | E34: 21 | F34: 0 | G34: 21 | H34: 0 | I34: 0 | J34: 0 | K34: 0 | L34: 0 | M34: 0 | N34: 0 | O34: 0 | P34: 0 | Q34: 0 | R34: 0 | S34: 0 | T34: 0 | U34: 0 | V34: 0 | W34: 0 | X34: 21 | Y34: 0 | Z34: 21 | AA34: 21 | AB34: 0 | AC34: 21 | AD34: 0
A35: Oats | B35: that is, 4 bushels an acre. | C35: 0 | D35: 0 | E35: 0 | F35: 0 | G35: 0 | H35: 0 | I35: 0 | J35: 0 | K35: 0 | L35: 0 | M35: 0 | N35: 0 | O35: 0 | P35: 0 | Q35: 0 | R35: 0 | S35: 0 | T35: 0 | U35: 0 | V35: 0 | W35: 0 | X35: 0 | Y35: 4 | Z35: 0.5 | AA35: 0.5 | AB35: 0 | AC35: 0 | AD35: 4
A36: Oats | B36: . | C36: 0 | D36: 0 | E36: 0 | F36: 0 | G36: 0 | H36: 0 | I36: 0 | J36: 0 | K36: 0 | L36: 0 | M36: 0 | N36: 0 | O36: 0 | P36: 0 | Q36: 0 | R36: 0 | S36: 0 | T36: 0 | U36: 0 | V36: 0 | W36: 0 | X36: 0 | Y36: 0 | Z36: 0 | AA36: 0 | AB36: 0 | AC36: 0 | AD36: 0
A37: Oats | B37: . | C37: 0 | D37: 0 | E37: 0 | F37: 0 | G37: 0 | H37: 0 | I37: 0 | J37: 0 | K37: 0 | L37: 0 | M37: 0 | N37: 0 | O37: 0 | P37: 0 | Q37: 0 | R37: 0 | S37: 0 | T37: 0 | U37: 0 | V37: 0 | W37: 0 | X37: 0 | Y37: 0 | Z37: 0 | AA37: 0 | AB37: 0 | AC37: 0 | AD37: 0
A38: Oats | B38: . | C38: 0 | D38: 0 | E38: 0 | F38: 0 | G38: 0 | H38: 0 | I38: 0 | J38: 0 | K38: 0 | L38: 0 | M38: 0 | N38: 0 | O38: 0 | P38: 0 | Q38: 0 | R38: 0 | S38: 0 | T38: 0 | U38: 0 | V38: 0 | W38: 0 | X38: 0 | Y38: 0 | Z38: 0 | AA38: 0 | AB38: 0 | AC38: 0 | AD38: 0
A39: Oats | B39: meal for the pottage of the manorial servants, 2.5 quarters. | C39: 0 | D39: 0 | E39: 0 | F39: 0 | G39: 0 | H39: 0 | I39: 0 | J39: 0 | K39: 0 | L39: 0 | M39: 0 | N39: 0 | O39: 0 | P39: 0 | Q39: 0 | R39: 0 | S39: 0 | T39: 0 | U39: 0 | V39: 0 | W39: 0 | X39: 2.5 | Y39: 0 | Z39: 2.5 | AA39: 2.5 | AB39: 0 | AC39: 2.5 | AD39: 0
A40: Oats | B40: . | C40: 0 | D40: 0 | E40: 0 | F40: 0 | G40: 0 | H40: 0 | I40: 0 | J40: 0 | K40: 0 | L40: 0 | M40: 0 | N40: 0 | O40: 0 | P40: 0 | Q40: 0 | R40: 0 | S40: 0 | T40: 0 | U40: 0 | V40: 0 | W40: 0 | X40: 0 | Y40: 0 | Z40: 0 | AA40: 0 | AB40: 0 | AC40: 0 | AD40: 0
... A50: Oats | B50: Total, 48 quarters. | C50: 0 | D50: 0 | E50: 0 | F50: 0 | G50: 0 | H50: 0 | I50: 0 | J50: 0 | K50: 0 | L50: 0 | M50: 0 | N50: 0 | O50: 0 | P50: 0 | Q50: 0 | R50: 0 | S50: 0 | T50: 0 | U50: 0 | V50: 0 | W50: 0 | X50: 48 | Y50: 0 | Z50: 48 | AA50: 48 | AB50: 0 | AC50: 48 | AD50: 0

Sheet Sale of Corn Prices
A1: Heading | B1: Sentence | C1: Total in Pounds | D1: Pounds | E1: Shillings | F1: Pence | G1: Corn | H1: Total Quarters Except 1 | I1: Total Bushels Except 1 | J1: Total Corn Cross-Check | K1: Total Corn Manorial Account | L1: Corn Quantity Error | M1: Quarters 0 | N1: Bushels 0 | O1: shilling a quarter 1 | P1: pence a quarter 1 | Q1: Quarters 1 | R1: Bushels 1 | S1: shilling a quarter 2 | T1: pence a quarter 2 | U1: Quarters 2 | V1: Bushels 2 | W1: shilling a quarter 3 | X1: pence a quarter 3 | Y1: shilling a quarter 4 | Z1: pence a quarter 4 | AA1: £ a quarter 1 | AB1: £ a quarter 2 | AC1: £ a quarter 3 | AD1: £ a quarter 4 | AE1: Quarters Sold | AF1: Weighted Average Price per Quarter | AG1: Non-Weighted Average Price per Quarter | AH1: Corn lowercase
