Workbook

Sheet Overview
A1: HAMBLEDON | B1: Total in £ | C1: Error | D1: Note
A2: CASH ACCOUNT
A3: RECEIPTS
A4: Arrears total
A5: Rents of assize total
A6: Quittances total
A7: Defaults of rent total
A8: Defaults of rent through the pestilence total
A9: Cotlands defaults total
A10: Cotlands total
A11: Total of quittances and defaults of rent total
A12: Total of rents remaining clear total
A13: Farms total
... A22: Farm of the demesne land total
A23: Total of all receipts (calculated here) | B23: =Receipts!F168 -> 106.81333
A24: Total of all receipts (calculated here) incl arrears | B24: =Receipts!F169 -> 175.44333
A25: Total recorded in the accounts excl. arrears | B25: =Receipts!F167 -> 107.03 | C25: =B25-B23 -> 0.21666667
A26: Total recorded in the accounts incl. arrears
A29: EXPENSES
A30: Cost of ploughs total
A31: Purchase of corn total
A32: Cost of carts and wagons total
A33: Cost of dairy total
A34: Purchase of stock total
A35: Sheepcote total
A36: Cost of buildings total
A37: Threshing total
A38: Barley expenses
A39: Expenses of the harvest total
... A43: Annual fees
A44: Total of all expenses per account | B44: =Expenses!F122 -> 34.98
A45: Total of all expenses (calculated here) | B45: =Expenses!F123 -> 30.835
A46: Total fixed investment | B46: =Expenses!F124 -> 6.4491667
A47: Total Demesne fixed investment | B47: =Expenses!F125 -> 3.6575
A49: Owed by the reeve
A50: From accounts
A52: Allowances
A53: Cash deliveries
A54: Sum of the above
A55: Total of all allowances and cash deliveries in accounts
A57: Net amount owed
A58: Net amount owed in accounts
A60: GRANGE ACCOUNT | B60: Total Production
A61: Grange | B61: qrs | E61: Value of total gross production in £ | F61: Value of total net production in £
A62: wheat | B62: ='Issues of the Grange'!B2 -> 73.25 | E62: ='Issues of the Grange'!I2 -> 20.373583 | F62: ='Issues of the Grange'!O14 -> 13.437525
A63: curall | B63: ='Issues of the Grange'!B3 -> 13.125 | E63: ='Issues of the Grange'!I3 -> 1.75 | F63: ='Issues of the Grange'!O15 -> 1.75
A64: barley | B64: ='Issues of the Grange'!B4 -> 76.5 | E64: ='Issues of the Grange'!I4 -> 15.3 | F64: ='Issues of the Grange'!O16 -> 4.9125
A65: oats | B65: ='Issues of the Grange'!B5 -> 178.875 | E65: ='Issues of the Grange'!I5 -> 18.680134 | F65: ='Issues of the Grange'!O17 -> 3.3026372
A66: peas | B66: ='Issues of the Grange'!B6 -> 6.75 | E66: ='Issues of the Grange'!I6 -> 0.84375 | F66: ='Issues of the Grange'!O18 -> 0.625
A67: vetches | B67: ='Issues of the Grange'!B7 -> 8.25 | E67: ='Issues of the Grange'!I7 -> 0.825 | F67: ='Issues of the Grange'!O19 -> 0.825
A68: Total value of gross production (sum of the above) | E68: =SUM(E62:E67) -> 57.772467
A69: Total value of net production | E69: =SUM(F62:F67) -> 24.852663
A70: Value of sales | E70: =Receipts!F133 -> 24.16
A72: MILL ACCOUNT
A73: Issues of the mill
A74: Wheat
A75: Oatmeal
A76: 1st grade malt
A77: 2nd grade malt
A78: Maslin
A79: Total value of production (sum of the above)
A80: Value of sales
A82: STOCK ACCOUNT
A83: Livestock | B83: Sales value in £
A84: Cart-horses | B84: =Stock!T5 -> 0
A85: Mares | B85: =Stock!T6 -> 0
A86: Plough horses | B86: =Stock!T7 -> 0.04
A87: Colts (2 years) | B87: =Stock!T8 -> 0
A88: Colts (2 years) | B88: =Stock!T9 -> 0
A89: Colts (1 year) | B89: =Stock!T10 -> 0
A90: Foals | B90: =Stock!T11 -> 0
A91: Oxen | B91: =Stock!T12 -> 3.225
A92: Bulls | B92: =Stock!T13 -> 0
A93: Cows | B93: =Stock!T14 -> 0.37333333
A94: Steers | B94: =Stock!T15 -> 17.12
A95: Bullocks | B95: =Stock!T16 -> 0
... A109: Peacocks | B109: =Stock!T30 -> 0
A110: Total value of stock (sum of the above)
A111: Total value of production
A112: Value of sales | B112: =Stock!R31 -> 25.86
A114: Wool | B114: Value of production at sales prices £
A115: Coarse wool | B115: =Stock!T35 -> 16.24
A116: Lamb's wool | B116: =Stock!T36 -> 1.93
A117: Wool locks | B117: =Stock!T37 -> 0
A118: Wool sold at shearing | B118: =Stock!T38 -> 0
A119: Total value of production (sum of the above) | B119: =Stock!T39 -> 18.48
A120: Value of sales | B120: =Stock!R39 -> 0.31
A122: Hides | B122: Value of production at sales prices £
A123: Ox hides | B123: =Stock!T43 -> 0
A124: Cow hides | B124: =Stock!T44 -> 0.04
A125: Mare hides | B125: =Stock!T45 -> 0.01
A126: Steer hides | B126: =Stock!T46 -> 0
A127: Yearling Calf hides | B127: =Stock!T47 -> 0
A128: Calf hides | B128: =Stock!T48 -> 0.01
A129: Pig hides | B129: =Stock!T49 -> 0
A130: Wether woolskins | B130: =Stock!T50 -> 0
A131: Ram woolskins | B131: =Stock!T51 -> 0
A132: Ewe woolskins | B132: =Stock!T52 -> 0
A133: Hogg woolskins | B133: =Stock!T53 -> 0
A134: Woolskins (total) | B134: =Stock!T54 -> 0
...

Sheet Receipts
A1: HAMBLEDON RECEIPTS
A2: Heading | B2: £ | C2: s | D2: d | F2: Total in £ | G2: Error | H2: Notes | I2: Own notes
A3: Arrears | B3: 68 | C3: 12 | D3: 7.25 | F3: 68.63 | H3: Nicholas, bailiff, and William Bouelych', reeve, render account for £68 12 shilling 7.25pence of arrears from the previous year.
A4: Arrears | B4: 0 | C4: 0 | D4: 0 | F4: 0 | H4: All delivered to Sir Geoffrey, treasurer of Wolvesey.
A5: Arrears | B5: 0 | C5: 0 | D5: 0 | F5: 0 | H5: They are quit.
A6: Arrears | F6: 68.63 | G6: =F6-F3 -> 0 | H6: Total
A8: Rents of assize | B8: 6 | C8: 13 | D8: 11.25 | F8: 6.7 | H8: The same render account for £6 13 shilling 11.25pence for rents of assize at Christmas.
A9: Rents of assize | B9: 7 | C9: 9 | D9: 1 | F9: 7.45 | H9: £7 9 shilling 1pence at Easter (22 April).
A10: Rents of assize | B10: 6 | C10: 13 | D10: 11.25 | F10: 6.7 | H10: £6 13 shilling 11.25pence at St John the Baptist (24 June).
A11: Rents of assize | B11: 11 | C11: 10 | D11: 10.75 | F11: =B11+C11/20+D11/240 -> 11.544792 | H11: £11 10 shilling 10.75pence at Michaelmas (29 September).
A12: Rents of assize | B12: 32 | C12: 7 | D12: 10.25 | F12: 32.39 | H12: Total, £32 7 shilling 10.25pence
A13: Rents of assize | F13: =SUM(F8:F11) -> 32.394792 | G13: =F13-F12 -> 0.0047916667 | H13: Total
A15: Increment | B15: 0 | C15: 0 | D15: 1 | F15: =B15+C15/20+D15/240 -> 0.0041666667 | H15: The same render account for 1pence for the increment of rent from Robert Faber to have 1 plot of land, 12 feet long and 5 feet wide, in the vill of Hambledon.
A16: Increment | B16: 0 | C16: 0 | D16: 1 | F16: =B16+C16/20+D16/240 -> 0.0041666667 | H16: Total, 1pence
A17: Increment | F17: =B17+C17/20+D17/240 -> 0 | G17: =F17-F16 -> -0.0041666667 | H17: Total
A19: Total Rents | B19: 32 | C19: 7 | D19: 11.25 | F19: 32.4 | H19: Total of rents with increment, £32 7 shilling 11.25pence
A20: Total Rents | F20: =F13+F17 -> 32.394792 | G20: =F20-F19 -> -0.0052083333 | H20: Total
A22: Quittances | B22: 0 | C22: 2 | D22: 6 | F22: 0.12 | H22: In quittance of 1 reeve for the year 2 shilling 6pence.
A23: Quittances | B23: 0 | C23: 2 | D23: 6 | F23: 0.12 | H23: 1 bartoner for the year 2 shilling 6pence.
A24: Quittances | B24: 0 | C24: 5 | D24: 0 | F24: 0.25 | H24: 3 ploughmen for the year 5 shilling.
A25: Quittances | B25: 0 | C25: 5 | D25: 0 | F25: 0.25 | H25: 2 shepherds and 1 smith for the year 5 shilling.
A26: Quittances | B26: 0 | C26: 1 | D26: 8 | F26: 0.08 | H26: 1 cowherd for the year 1 shilling 8pence.
A27: Quittances | B27: 0 | C27: 1 | D27: 8 | F27: 0.08 | H27: 1 swineherd for the year 1 shilling 8pence
A28: Quittances | B28: 0 | C28: 18 | D28: 4 | F28: =B28+C28/20+D28/240 -> 0.91666667 | H28: Total, 18 shilling 4pence
A29: Quittances | F29: 0.9 | G29: =F29-F28 -> -0.016666667 | H29: Total
A31: Defaults of rent | B31: 0 | C31: 1 | D31: 6 | F31: 0.08 | H31: In default of the wood which Herbert' de Chidden' holds drawn into demesne, 1 shilling 6pence for the year.
A32: Defaults of rent | B32: 0 | C32: 0 | D32: 6 | F32: 0.03 | H32: the land of Shortelond', 6pence for the year.
A33: Defaults of rent | B33: 0 | C33: 0 | D33: 6 | F33: 0.03 | H33: 1 grove of Vineys drawn into demesne, 6pence for the year.
A34: Defaults of rent | B34: 0 | C34: 6 | D34: 0 | F34: =B34+C34/20+D34/240 -> 0.3 | H34: the wood of Mannely which is in demesne through the death of the holder 6 shilling
A35: Defaults of rent | B35: 0 | C35: 8 | D35: 6 | F35: =B35+C35/20+D35/240 -> 0.425 | H35: Total, 8 shilling 6pence
A36: Defaults of rent | F36: =SUM(F31:F34) -> 0.44 | G36: =F36-F35 -> 0.015 | H36: Total
A38: Total of rents remaining | B38: 31 | C38: 1 | D38: 1.25 | F38: 31.06 | H38: Total of rents remaining, £31 1 shilling 1.25pence
A39: Total of rents remaining | F39: 31.06 | G39: =F39-F38 -> 0 | H39: Total
A41: Annual recognizance | B41: 0 | C41: 0 | D41: 3 | F41: 0.01 | H41: The same render account for 3pence from Walter ate Greve for recognizance.
A42: Annual recognizance | B42: 0 | C42: 0 | D42: 3 | F42: 0.01 | H42: 3pence from Stephen Blaysut to be able to remain in the hundred of East Meon.
A43: Annual recognizance | B43: 0 | C43: 0 | D43: 3 | F43: 0.01 | H43: 3pence from William le Boys for annual recognizance.
A44: Annual recognizance | B44: 0 | C44: 0 | D44: 3 | F44: 0.01 | H44: 3pence from Henry Faber for the same.
A45: Annual recognizance | B45: 0 | C45: 0 | D45: 4 | F45: 0.02 | H45: 4pence from Adam le Cauz for the same.
A46: Annual recognizance | B46: 0 | C46: 0 | D46: 3 | F46: 0.01 | H46: 3pence from Robert Buly for the same.
A47: Annual recognizance | B47: 0 | C47: 0 | D47: 3 | F47: 0.01 | H47: 3pence from William Tassor' for the same and henceforth nothing from the same because he is dead.
A48: Annual recognizance | B48: 0 | C48: 0 | D48: 6 | F48: 0.03 | H48: 6pence from Adam Cattefan for the same.
A49: Annual recognizance | B49: 0 | C49: 0 | D49: 3 | F49: 0.01 | H49: 3pence from Thomas Sharpe for the same.
A50: Annual recognizance | B50: 0 | C50: 0 | D50: 6 | F50: 0.03 | H50: 6pence from Roger Boys for the same.
A51: Annual recognizance | B51: 0 | C51: 0 | D51: 3 | F51: 0.01 | H51: 3pence from Jordan Boys for the same.
A52: Annual recognizance | B52: 0 | C52: 3 | D52: 4 | F52: 0.17 | H52: Total, 3 shilling 4pence
A53: Annual recognizance | F53: 0.16 | G53: -0.01 | H53: Total
A55: Cumin | B55: 0 | C55: 0 | D55: 0 | F55: 0 | H55: The same render account for 1 lb of cumin from William Sicator' for the year.
A56: Cumin | B56: 0 | C56: 0 | D56: 0 | F56: 0 | H56: delivered to Wolvesey.
A57: Cumin | F57: 0 | G57: 0 | H57: Total
A59: Wax | B59: 0 | C59: 0 | D59: 0 | F59: 0 | H59: The same render account for .5 lb of wax from Philip Visard to have maintenance.
A60: Wax | B60: 0 | C60: 0 | D60: 0 | F60: 0 | H60: .5 lb from William le Ysmongar for the same.
A61: Wax | B61: 0 | C61: 0 | D61: 0 | F61: 0 | H61: .5 lb from Thomas Messor for the same.
A62: Wax | B62: 0 | C62: 0 | D62: 0 | F62: 0 | H62: Total, 1.5 lb.
A63: Wax | B63: 0 | C63: 0 | D63: 0 | F63: 0 | H63: Delivered to Wolvesey.
A64: Wax | F64: 0 | G64: 0 | H64: Total
A66: Talents | B66: 0 | C66: 0 | D66: 0 | F66: 0 | H66: The same render account for 1 talent received from the vicar of Hambledon.
A67: Talents | B67: 0 | C67: 0 | D67: 0 | F67: 0 | H67: delivered to Wolvesey.
A68: Talents | F68: 0 | G68: 0 | H68: Total
A70: Issues of the manor | B70: 1 | C70: 18 | D70: 4.5 | F70: 1.92 | H70: {henceforth mention should be made of the number of animals}The same render account for £1 18 shilling 4.5pence from pannage of pigs within this year.
A71: Issues of the manor | B71: 1 | C71: 1 | D71: 0 | F71: 1.05 | H71: £1 1 shilling from foreign pannage.
A72: Issues of the manor | B72: 1 | C72: 8 | D72: 6 | F72: 1.42 | H72: £1 8 shilling 6pence from pannage in the park.
A73: Issues of the manor | B73: 0 | C73: 0 | D73: 0 | F73: 0 | H73: nothing from William de Chidden from now on because he does the labour service for part of his land.
A74: Issues of the manor | B74: 0 | C74: 2 | D74: 6 | F74: 0.12 | H74: 2 shilling 6pence from Robert Cocus for release from the labour service for the land of Dimmyng'.
A75: Issues of the manor | B75: 0 | C75: 1 | D75: 8 | F75: 0.08 | H75: 1 shilling 8pence from the same Robert for the labour service of the land which belonged to Richard Luce.
A76: Issues of the manor | B76: 0 | C76: 0 | D76: 6 | F76: 0.03 | H76: 6pence from the relict of Philip de Furnaeaus for release from the labour service for the land which belonged to Walter Elyot.
A77: Issues of the manor | B77: 0 | C77: 2 | D77: 0 | F77: 0.1 | H77: 2 shilling from cablish sold in the great wood.
A78: Issues of the manor | B78: 0 | C78: 0 | D78: 0 | F78: 0 | H78: nothing from underwood in la Brok' this year.
A79: Issues of the manor | B79: 0 | C79: 3 | D79: 0 | F79: 0.15 | H79: 3 shilling from the men of Chidden for the pasturage in Eldecroft and answering elsewhere for 5 sheep for the same pasturage.
A80: Issues of the manor | B80: 0 | C80: 3 | D80: 3.5 | F80: 0.16 | H80: 3 shilling 3.5pence from pinfold this year.
A81: Issues of the manor | B81: 0 | C81: 3 | D81: 0 | F81: 0.15 | H81: 3 shilling from the men of Pantolf' for pasturage.
... A117: Issues of the manor | B117: 42 | C117: 3 | D117: 4 | F117: 42.17 | H117: Total, £42 3 shilling 4pence
F118: =SUM(F70:F116) -> 41.95 | G118: =F118-F117 -> -0.22 | H118: Total
A120: Farm of the mill | B120: 1 | C120: 16 | D120: 0 | F120: 1.8 | H120: The same render account for £1 16 shilling for the farm of the mill this year.
A121: Farm of the mill | B121: 1 | C121: 16 | D121: 0 | F121: 1.8 | H121: Total, £1 16 shilling
A122: Farm of the mill | F122: 1.8 | G122: 0 | H122: Total
A124: Sale of corn | B124: 12 | C124: 14 | D124: 3 | F124: 12.71 | H124: The same render account for £12 14 shilling 3pence from 45 quarters 6 bushels of wheat sold, at 5 shilling a qr for 20 quarters 2 bushels, and 6 shilling a qr for 25.5 quarters.
A125: Sale of corn | B125: 1 | C125: 15 | D125: 0 | F125: 1.75 | H125: £1 15 shilling from 13 quarters 1 bushels of curall sold, at 2 shilling 8pence a qr.
A126: Sale of corn | B126: 4 | C126: 13 | D126: 0 | F126: 4.65 | H126: £4 13 shilling from 23 quarters 2 bushels of barley sold, at 4 shilling a qr.
A127: Sale of corn | B127: 3 | C127: 5 | D127: 9.5 | F127: 3.29 | H127: £3 5 shilling 9.5pence from 31.5 quarters of oats sold, at 2 shilling a qr for 14 quarters 6 bushels, and 2 shilling 2pence a qr for 16 quarters 6 bushels.
A128: Sale of corn | B128: 0 | C128: 12 | D128: 6 | F128: 0.62 | H128: 12 shilling 6pence from 5 quarters of peas sold, at 2 shilling 6pence a qr.
A129: Sale of corn | B129: 0 | C129: 16 | D129: 6 | F129: 0.83 | H129: 16 shilling 6pence from 8 quarters of vetches sold, at 2 shilling a qr.
A130: Sale of corn | B130: 0 | C130: 3 | D130: 4.5 | F130: 0.17 | H130: 3 shilling 4.5pence from 4.5 bushels of wheat sold at the audit.
A131: Sale of corn | B131: 0 | C131: 2 | D131: 9 | F131: 0.14 | H131: 2 shilling 9pence from 5.5 bushels of barley sold at the audit.
A132: Sale of corn | B132: 24 | C132: 3 | D132: 2 | F132: 24.16 | H132: Total, £24 3 shilling 2pence
A133: Sale of corn | F133: 24.16 | G133: 0 | H133: Total
A135: Entry and marriage fines with tithingpenny | B135: 0 | C135: 5 | D135: 0 | F135: 0.25 | H135: The same render account for 5 shilling from the tithing of Chidden for tithingpenny at the hundred-court of Martinmas (11 November).
A136: Entry and marriage fines with tithingpenny | B136: 0 | C136: 5 | D136: 0 | F136: 0.25 | H136: 5 shilling from the tithing of Denmead for the same.
A137: Entry and marriage fines with tithingpenny | B137: 0 | C137: 5 | D137: 0 | F137: 0.25 | H137: 5 shilling from the tithing of la Lygh' for the same.
A138: Entry and marriage fines with tithingpenny | B138: 0 | C138: 5 | D138: 0 | F138: 0.25 | H138: 5 shilling from the tithing of Gludden for the same.
A139: Entry and marriage fines with tithingpenny | B139: 1 | C139: 0 | D139: 0 | F139: 1 | H139: £1 from the same tithings at the hundred-court of Hockday (1 May).
A140: Entry and marriage fines with tithingpenny | B140: 0 | C140: 5 | D140: 0 | F140: 0.25 | H140: 5 shilling from the relict of Thomas le Cog' to retain 1 cotland which belonged to her husband.
A141: Entry and marriage fines with tithingpenny | B141: 0 | C141: 10 | D141: 0 | F141: 0.5 | H141: 10 shilling from Adam Coker to have .5 virgate of land which belonged to Stephen his father.
A142: Entry and marriage fines with tithingpenny | B142: 0 | C142: 2 | D142: 0 | F142: 0.1 | H142: 2 shilling from William Bouelych' to have 2 acres of land by surrender of Adam Bythewod'.
A143: Entry and marriage fines with tithingpenny | B143: 0 | C143: 1 | D143: 0 | F143: 0.05 | H143: 1 shilling from John Pleyfot to have 1 plot of land in the vill of Hambledon by surrender of Walter le Grevere.
A144: Entry and marriage fines with tithingpenny | B144: 0 | C144: 1 | D144: 0 | F144: 0.05 | H144: 1 shilling from Robert Faber to have 1 plot of land, 12 feet long and 5 feet wide, in the same vill.
A145: Entry and marriage fines with tithingpenny | B145: 0 | C145: 4 | D145: 0 | F145: 0.2 | H145: 4 shilling from Robert le Bole to have 8 acres of land by surrender of William atte Oke.
A146: Entry and marriage fines with tithingpenny | B146: 0 | C146: 1 | D146: 0 | F146: 0.05 | H146: 1 shilling from Walter Rykeby for 1 plot of land, 12 feet long and 10 feet wide, for building in the market.
A147: Entry and marriage fines with tithingpenny | B147: 0 | C147: 10 | D147: 0 | F147: =B147+C147/20+D147/240 -> 0.5 | H147: 10 shilling from Peter ate Putte to have Juliana le Burgeys with her lanpence
A148: Entry and marriage fines with tithingpenny | B148: 3 | C148: 14 | D148: 0 | F148: =B148+C148/20+D148/240 -> 3.7 | H148: Total, £3 14 shilling
A149: Entry and marriage fines with tithingpenny | F149: =SUM(F135:F147) -> 3.7 | G149: =F149-F148 -> 0 | H149: Total
...

Sheet Expenses
A1: HAMBLEDON RECEIPTS
A2: Heading | B2: £ | C2: s | D2: d | F2: Total in £ | G2: Error | H2: Notes | I2: Own notes | K2: Fixed investment | L2: Demesne fixed investment
A3: Cost of ploughs | B3: 0 | C3: 0 | D3: 0 | F3: 0 | H3: (henceforth the ploughs of the customary tenants should not be taken if a profit is able to be made).
A4: Cost of ploughs | B4: 0 | C4: 11 | D4: 0 | F4: 0.55 | H4: iron and steel bought for 3 ploughs for the year 11 shilling. | K4: =F4 -> 0.55 | L4: =K4 -> 0.55
A5: Cost of ploughs | B5: 0 | C5: 1 | D5: 3 | F5: 0.06 | H5: 3 plough feet bought 1 shilling 3pence. | K5: =F5 -> 0.06 | L5: =K5 -> 0.06
A6: Cost of ploughs | B6: 0 | C6: 1 | D6: 6 | F6: 0.08 | H6: 2 ploughshares bought 1 shilling 6pence. | K6: =F6 -> 0.08 | L6: =K6 -> 0.08
A7: Cost of ploughs | B7: 0 | C7: 2 | D7: 3 | F7: 0.11 | H7: 5 ploughs made anew and others mended at various times, with timber felled and trimmed for the same, 2 shilling 3pence. | K7: =F7 -> 0.11 | L7: =K7 -> 0.11
A8: Cost of ploughs | B8: 0 | C8: 0 | D8: 6 | F8: 0.03 | H8: 2 pairs of wheels bought 6pence. | K8: =F8 -> 0.03 | L8: =K8 -> 0.03
A9: Cost of ploughs | B9: 0 | C9: 0 | D9: 6 | F9: 0.03 | H9: 3 harrows made anew 6pence. | K9: =F9 -> 0.03 | L9: =K9 -> 0.03
A10: Cost of ploughs | B10: 0 | C10: 0 | D10: 1.5 | F10: 0.01 | H10: fitting ploughs with iron tyres 1.5pence. | K10: =F10 -> 0.01 | L10: =K10 -> 0.01
A11: Cost of ploughs | B11: 0 | C11: 5 | D11: 6 | F11: 0.28 | H11: shoeing 6 plough-horses hauling ploughs at the time of both sowings and hauling dung when it was necessary until Lammas, because thereafter they were at the church, 5 shilling 6pence. | K11: =F11 -> 0.28 | L11: =K11 -> 0.28
A12: Cost of ploughs | B12: 1 | C12: 0 | D12: 0 | F12: 1 | H12: 32 ploughmen in winter and 32 in Lent, £1 according to custom, of whom each ploughman ploughed and harrowed 1 acre in winter and 1 acre in Lent.
A13: Cost of ploughs | B13: 0 | C13: 6 | D13: 9 | F13: 0.34 | H13: stipend of 3 ploughmen from Michaelmas until Lammas, because thereafter they were at the church, 6 shilling 9pence.
A14: Cost of ploughs | B14: 0 | C14: 12 | D14: 3 | F14: =B14+C14/20+D14/240 -> 0.6125 | H14: 1 plough-horse bought 12 shilling 3pence
A15: Cost of ploughs | B15: 3 | C15: 1 | D15: 7.5 | F15: 3.08 | H15: Total, £3 1 shilling 7.5pence
A16: Cost of ploughs | F16: =SUM(F3:F14) -> 3.1025 | G16: =F16-F15 -> 0.0225 | H16: Total
A18: Purchase of corn | B18: 0 | C18: 17 | D18: 4 | F18: 0.87 | H18: In 6.5 quarters of barley bought for the liveries of the manorial servants 17 shilling 4pence, at 2 shilling 8pence a qr.
A19: Purchase of corn | B19: 0 | C19: 17 | D19: 4 | F19: 0.87 | H19: Total, 17 shilling 4pence
A20: Purchase of corn | F20: 0.87 | G20: 0 | H20: Total
A22: Cost of carts | B22: 0 | C22: 0 | D22: 9 | F22: 0.04 | H22: in 1 pair of wheels made anew from the lord's timber 9pence. | K22: =F22 -> 0.04 | L22: =K22 -> 0.04
A23: Cost of carts | B23: 0 | C23: 2 | D23: 6 | F23: 0.12 | H23: mending 1 old binding and putting it on the said wheels with the stipend of the smith 2 shilling 6pence. | K23: =F23 -> 0.12 | L23: =K23 -> 0.12
A24: Cost of carts | B24: 0 | C24: 1 | D24: 9 | F24: 0.09 | H24: clouts, nails and grease bought 1 shilling 9pence. | K24: =F24 -> 0.09 | L24: =K24 -> 0.09
A25: Cost of carts | B25: 0 | C25: 0 | D25: 8 | F25: 0.03 | H25: mending the axles of the cart at various times 8pence, on account of the manor of Kilmeston. | K25: =F25 -> 0.03 | L25: =K25 -> 0.03
A26: Cost of carts | B26: 0 | C26: 3 | D26: 6 | F26: 0.17 | H26: shoeing 2 cart-horses 3 shilling 6pence. | K26: =F26 -> 0.17 | L26: =K26 -> 0.17
A27: Cost of carts | B27: 0 | C27: 0 | D27: 10 | F27: 0.04 | H27: 2 collars bought 10pence. | K27: =F27 -> 0.04 | L27: =K27 -> 0.04
A28: Cost of carts | B28: 0 | C28: 0 | D28: 9 | F28: 0.04 | H28: 2 pairs of traces bought 9pence. | K28: =F28 -> 0.04 | L28: =K28 -> 0.04
A29: Cost of carts | B29: 0 | C29: 1 | D29: 2 | F29: 0.06 | H29: 1 rope bought for the cart 1 shilling 2pence. | K29: =F29 -> 0.06 | L29: =K29 -> 0.06
A30: Cost of carts | B30: 0 | C30: 0 | D30: 1.5 | F30: 0.01 | H30: 2 halters bought 1.5pence. | K30: =F30 -> 0.01 | L30: =K30 -> 0.01
A31: Cost of carts | B31: 0 | C31: 2 | D31: 3 | F31: 0.11 | H31: stipend of 1 carter from Michaelmas until Lammas, because thereafter he was at the church, 2 shilling 3pence
A32: Cost of carts | B32: 0 | C32: 14 | D32: 3.5 | F32: =B32+C32/20+D32/240 -> 0.71458333 | H32: Total, 14 shilling 3.5pence
A33: Cost of carts | F33: 0.71 | G33: =F33-F32 -> -0.0045833333 | H33: Total
A35: Repair of buildings | B35: 0 | C35: 3 | D35: 4 | F35: 0.17 | H35: In 2,000 slates bought 3 shilling 4pence. | K35: =F35 -> 0.17
A36: Repair of buildings | B36: 0 | C36: 10 | D36: 6 | F36: 0.53 | H36: re-roofing the hall, lord's chamber, clerks' chamber and kitchen, which had been unroofed several times by the wind, 10 shilling 6pence. | K36: =F36 -> 0.53
A37: Repair of buildings | B37: 0 | C37: 0 | D37: 8 | F37: 0.03 | H37: nails and pegs bought for the same 8pence. | K37: =F37 -> 0.03
A38: Repair of buildings | B38: 0 | C38: 4 | D38: 4 | F38: 0.22 | H38: re-roofing the barn and other buildings in places 4 shilling 4pence. | K38: =F38 -> 0.22 | L38: =K38 -> 0.22
A39: Repair of buildings | B39: 0 | C39: 0 | D39: 5 | F39: 0.02 | H39: laying 100 shingles in places on the barn with nails bought for the same 5pence. | K39: =F39 -> 0.02 | L39: =K39 -> 0.02
A40: Repair of buildings | B40: 0 | C40: 2 | D40: 8 | F40: 0.13 | H40: building anew 1 palisade between the hall and kitchen 2 shilling 8pence. | K40: =F40 -> 0.13
A41: Repair of buildings | B41: 0 | C41: 2 | D41: 2 | F41: 0.11 | H41: building 1 palisade between the hall and dairy and 1 new garden-gate 2 shilling 2pence. | K41: =F41 -> 0.11 | L41: =K41 -> 0.11
A42: Repair of buildings | B42: 0 | C42: 0 | D42: 9 | F42: 0.04 | H42: felling and sawing timber for the same 9pence. | K42: =F42 -> 0.04 | L42: =K42 -> 0.04
A43: Repair of buildings | B43: 0 | C43: 3 | D43: 6 | F43: 0.17 | H43: mending the byre in part and making anew a fodder-rack for the byre 3 shilling 6pence. | K43: =F43 -> 0.17 | L43: =K43 -> 0.17
A44: Repair of buildings | B44: 0 | C44: 0 | D44: 6 | F44: 0.03 | H44: mending the fodder-rack and manger in the stable 6pence. | K44: =F44 -> 0.03 | L44: =K44 -> 0.03
A45: Repair of buildings | B45: 0 | C45: 0 | D45: 5 | F45: 0.02 | H45: making 1 window in the kitchen with hooks and hinges for the same 5pence. | K45: =F45 -> 0.02
A46: Repair of buildings | B46: 0 | C46: 0 | D46: 10 | F46: =B46+C46/20+D46/240 -> 0.041666667 | H46: plastering the walls of the bailiff's room and knights' chamber 10pence | K46: =F46 -> 0.041666667
A47: Repair of buildings | B47: 1 | C47: 10 | D47: 1 | F47: 1.5 | H47: Total, £1 10 shilling 1pence
A48: Repair of buildings | F48: =SUM(F35:F46) -> 1.5116667 | G48: =F48-F47 -> 0.011666667 | H48: Total
A50: Cost of the park | B50: 0 | C50: 0 | D50: 2 | F50: 0.01 | H50: In mending 2 gates in the park 2pence. | K50: =F50 -> 0.01
A51: Cost of the park | B51: 0 | C51: 10 | D51: 3 | F51: 0.51 | H51: making 2 furlongs 2 perches of ditch in the park for the pasture for the calves 10 shilling 3pence, at 1.5pence a perch. | K51: =F51 -> 0.51
A52: Cost of the park | B52: 0 | C52: 5 | D52: 1.5 | F52: 0.26 | H52: completing the hedge along the said ditch 5 shilling 1.5pence, at .75pence a perch. | K52: =F52 -> 0.26
A53: Cost of the park | B53: 1 | C53: 1 | D53: 10.5 | F53: 1.09 | H53: closing the gaps in the hedge along 8 furlongs 30 perches £1 1 shilling 10.5pence, at .75pence a perch. | K53: =F53 -> 1.09
A54: Cost of the park | B54: 1 | C54: 17 | D54: 5 | F54: 1.87 | H54: Total, £1 17 shilling 5pence
A55: Cost of the park | F55: 1.87 | G55: 0 | H55: Total
A57: Dairy | B57: 0 | C57: 2 | D57: 0 | F57: 0.1 | H57: In 1 qr of salt bought 2 shilling. | K57: =F57 -> 0.1 | L57: =K57 -> 0.1
A58: Dairy | B58: 0 | C58: 0 | D58: 4 | F58: 0.02 | H58: woollen and linen cloth bought 4pence. | K58: =F58 -> 0.02 | L58: =K58 -> 0.02
A59: Dairy | B59: 0 | C59: 0 | D59: 3 | F59: 0.01 | H59: a press bought 3pence. | K59: =F59 -> 0.01 | L59: =K59 -> 0.01
A60: Dairy | B60: 0 | C60: 0 | D60: 4.5 | F60: 0.02 | H60: earthenware pots and pans bought 4.5pence. | K60: =F60 -> 0.02 | L60: =K60 -> 0.02
A61: Dairy | B61: 0 | C61: 0 | D61: 6 | F61: 0.03 | H61: 2 cheese moulds bought 6pence. | K61: =F61 -> 0.03 | L61: =K61 -> 0.03
A62: Dairy | B62: 0 | C62: 0 | D62: 4 | F62: 0.02 | H62: mending the utensils of the dairy 4pence. | K62: =F62 -> 0.02 | L62: =K62 -> 0.02
A63: Dairy | B63: 0 | C63: 3 | D63: 1.5 | F63: 0.16 | H63: 15 ells of canvas bought 3 shilling 1.5pence. | K63: =F63 -> 0.16 | L63: =K63 -> 0.16
A64: Dairy | B64: 0 | C64: 0 | D64: 4 | F64: 0.02 | H64: making sacks with thread for the same and packing the said wool 4pence. | K64: =F64 -> 0.02 | L64: =K64 -> 0.02
A65: Dairy | B65: 0 | C65: 1 | D65: 6 | F65: =B65+C65/20+D65/240 -> 0.075 | H65: stipend of 1 dairymaid from the Purification (2 February) until Michaelmas (29 September) 1shilling 6pence.
A66: Dairy | B66: 2 | C66: 1 | D66: 0 | F66: =B66+C66/20+D66/240 -> 2.05 | H66: 80 lambs bought before shearing £2 1shilling 4pence, at 5pence each for 48, and 8pence each for 32..
A67: Dairy | B67: 0 | C67: 0 | D67: 4 | F67: 0.02 | H67: castrating piglets 4pence.
A68: Dairy | B68: 0 | C68: 16 | D68: 2 | F68: 0.81 | H68: grease and vinegar bought for greasing sheep 16 shilling 2pence. | K68: =F68 -> 0.81 | L68: =K68 -> 0.81
A69: Dairy | B69: 0 | C69: 2 | D69: 0 | F69: 0.1 | H69: stipend of 1 keeper of lambs for' year, 2 shilling this year.
A70: Dairy | B70: 3 | C70: 8 | D70: 7 | F70: 3.43 | H70: Total, £3 8 shilling 7pence
A71: Dairy | F71: =SUM(F57:F69) -> 3.435 | G71: =F71-F70 -> 0.005 | H71: Total
A73: Sheepcote | B73: 0 | C73: 1 | D73: 0 | F73: 0.05 | H73: In roofing part of the sheepcote 1 shilling. | K73: =F73 -> 0.05 | L73: =K73 -> 0.05
A74: Sheepcote | B74: 0 | C74: 0 | D74: 9.25 | F74: 0.04 | H74: making anew 1 door to the ewe-house with nooks and hinges for the same 9.25pence. | K74: =F74 -> 0.04 | L74: =K74 -> 0.04
A75: Sheepcote | B75: 0 | C75: 0 | D75: 9 | F75: =B75+C75/20+D75/240 -> 0.0375 | H75: a fodder-rack and cratch made for the ewe-house 9pence | K75: =F75 -> 0.0375 | L75: =K75 -> 0.0375
A76: Sheepcote | B76: 0 | C76: 2 | D76: 6.25 | F76: =B76+C76/20+D76/240 -> 0.12604167 | H76: Total, 2 shilling 6.25pence
A77: Sheepcote | F77: =SUM(F73:F75) -> 0.1275 | G77: =F77-F76 -> 0.0014583333 | H77: Total
A79: Cost of hay | B79: 0 | C79: 3 | D79: 1.5 | F79: 0.16 | H79: In fences for an enclosure and enclosing the meadow 3 shilling 1.5pence.
A80: Cost of hay | B80: 0 | C80: 10 | D80: 0 | F80: 0.5 | H80: mowing the whole of the meadow 10 shilling.
A81: Cost of hay | B81: 0 | C81: 2 | D81: 0 | F81: =B81+C81/20+D81/240 -> 0.1 | H81: tossing and spreading the hay and making haycocks therefrom 2 shilling
A82: Cost of hay | B82: 0 | C82: 15 | D82: 1.5 | F82: 0.76 | H82: Total, 15 shilling 1.5pence
A83: Cost of hay | F83: =SUM(F79:F81) -> 0.76 | G83: =F83-F82 -> 0 | H83: Total
A85: Threshing | B85: 0 | C85: 15 | D85: 7 | F85: 0.78 | H85: In threshing and winnowing 68 quarters of wheat and curall by piece-work 15 shilling 7pence, at 2.75pence a qr.
A86: Threshing | B86: 0 | C86: 9 | D86: 7.5 | F86: 0.48 | H86: threshing and winnowing 55 quarters 2 bushels of barley, 4 quarters of peas and 7 quarters of vetches by piece-work 9 shilling 7.5pence, at 1.75pence a qr.
A87: Threshing | B87: 0 | C87: 3 | D87: 2.5 | F87: 0.16 | H87: threshing and winnowing 44 quarters of oats by piece-work 3 shilling 2.5pence, at 1.75pence per 2 quarters.
A88: Threshing | B88: 0 | C88: 2 | D88: 6 | F88: =B88+C88/20+D88/240 -> 0.125 | H88: 5 sacks bought 2 shilling 6pence
A89: Threshing | B89: 1 | C89: 10 | D89: 11 | F89: 1.55 | H89: Total, £1 10 shilling 11pence
A90: Threshing | F90: =SUM(F85:F88) -> 1.545 | G90: =F90-F89 -> -0.005 | H90: Total
A92: Harvest-time | B92: 1 | C92: 19 | D92: 8 | F92: 1.98 | H92: In bread bought for 974 men at 15 boon-works with the carters and customary tenants who reaped and bound 222 acres of wheat, 107 acres of barley and 414 acres of oats as they lie £1 19 shilling 8pence.
A93: Harvest-time | B93: 0 | C93: 12 | D93: 0 | F93: 0.6 | H93: relish for the same 12 shilling.
A94: Harvest-time | B94: 0 | C94: 1 | D94: 8 | F94: =B94+C94/20+D94/240 -> 0.083333333 | H94: allowance of food for the reeve and bartoner at harvest-time 1 shilling 8pence
A95: Harvest-time | B95: 2 | C95: 13 | D95: 4 | F95: 2.67 | H95: Total, £2 13 shilling 4pence
A96: Harvest-time | F96: =SUM(F92:F94) -> 2.6633333 | G96: =F96-F95 -> -0.0066666667 | H96: Total
A98: Cost of the mill | B98: 0 | C98: 0 | D98: 8 | F98: 0.03 | H98: In iron bought for mending the spindle 8pence
A99: Cost of the mill | F99: 0.03 | H99: Total, 8pence
A100: Cost of the mill | F100: 0.03 | G100: =F100-F99 -> 0 | H100: Total
A102: Expenses of the steward | B102: 0 | C102: 9 | D102: 6 | F102: 0.48 | H102: In expenses of Simon, clerk, holding the place of the steward at the 2 tourns 9 shilling 6pence
A103: Expenses of the steward | B103: 0 | C103: 9 | D103: 6 | F103: 0.48 | H103: Total, 9 shilling 6pence
A104: Expenses of the steward | F104: 0.48 | G104: 0 | H104: Total
A106: Purchase of stock | B106: 13 | C106: 14 | D106: 7 | F106: 13.73 | H106: In 39 animals bought for pasturing £13 14 shilling 7pence
A107: Purchase of stock | B107: 13 | C107: 14 | D107: 7 | F107: 13.73 | H107: Total, £13 14 shilling 7pence
A108: Purchase of stock | F108: 13.73 | G108: 0 | H108: Total
A111: Total of all expenses | B111: 34 | C111: 19 | D111: 7.25 | F111: 34.98 | H111: Total of all expenses, £34 19 shilling 7.25pence
A112: Total of all expenses | F112: 34.98 | G112: =F112-F111 -> 0 | H112: Total
A114: And he owes | B114: 72 | C114: 0 | D114: 0 | F114: 72 | H114: And he owes, £72 l 1pence
A115: And he owes | F115: 72 | G115: 0 | H115: Total
...

Sheet Issues of the Grange
A1: Gross Output | B1: Total Quantity | C1: Account Total Quarters | D1: Bought in Total Quarters | E1: Received from churchscot | F1: Sold Total Quarters | G1: Difference Produced+Bought-Sold | H1: Weighted Average Price per Quarter | I1: Value of Total Production weighted
A2: wheat | B2: 73.25 | C2: 73.25 | D2: 0 | F2: 46.3125 | G2: =B2-F2 -> 26.9375 | H2: 0.27813765 | I2: =H2*B2 -> 20.373583
A3: curall | B3: 13.125 | C3: 13.125 | D3: 0 | F3: 13.125 | G3: =B3-F3 -> 0 | H3: 0.13333333 | I3: =H3*B3 -> 1.75
A4: barley | B4: 76.5 | C4: 69.25 | D4: 6.625 | F4: 23.9375 | G4: =B4-F4 -> 52.5625 | H4: 0.2 | I4: =H4*B4 -> 15.3
A5: oats | B5: 178.875 | C5: 178.875 | D5: 0 | F5: 31.5 | G5: =B5-F5 -> 147.375 | H5: 0.10443122 | I5: =H5*B5 -> 18.680134
A6: peas | B6: 6.75 | C6: 6.75 | D6: 0 | F6: 5 | G6: =B6-F6 -> 1.75 | H6: 0.125 | I6: =H6*B6 -> 0.84375
A7: vetches | B7: 8.25 | C7: 8.25 | D7: 0 | F7: 8 | G7: =B7-F7 -> 0.25 | H7: 0.1 | I7: =H7*B7 -> 0.825
A9: Total Production
A10: Sales of corn (as recorded in accounts)
A13: Net output | B13: Gross output | C13: Seed quarters | D13: Seed bushels | E13: Seed total quarters | F13: tithe quarters | G13: tithe bushels | H13: tithe total | I13: manorial servants quarters | J13: manorial servants bushels | K13: manorial servants total quarters | L13: output net of tithe, seed, liveries | M13: in stock from last year | N13: Price in £ | O13: Value of net output in £ | P13: Value of sales (in "Sale of Corn") in £
A14: wheat | B14: =B2 -> 73.25 | C14: 23 | D14: 3.5 | E14: =C14+D14/8 -> 23.4375 | J14: =6+6 -> 12 | K14: =I14+J14/8 -> 1.5 | L14: =B14-E14-K14 -> 48.3125 | N14: =H2 -> 0.27813765 | O14: =N14*L14 -> 13.437525
A15: curall | B15: =B3 -> 13.125 | E15: =C15+D15/8 -> 0 | K15: =I15+J15/8 -> 0 | L15: =B15-E15-K15 -> 13.125 | N15: =H3 -> 0.13333333 | O15: =N15*L15 -> 1.75
A16: barley | B16: =B4 -> 76.5 | C16: 20.5 | E16: =C16+D16/8 -> 20.5 | I16: =1+6.5+19.5+2+1 -> 30 | J16: =4+6.5+1 -> 11.5 | K16: =I16+J16/8 -> 31.4375 | L16: =B16-E16-K16 -> 24.5625 | N16: =H4 -> 0.2 | O16: =N16*L16 -> 4.9125
A17: oats | B17: =B5 -> 178.875 | C17: 82 | E17: =C17+D17/8 -> 82 | I17: =19.5+16+6+18+3+2 -> 64.5 | J17: =1+2+3 -> 6 | K17: =I17+J17/8 -> 65.25 | L17: =B17-E17-K17 -> 31.625 | N17: =H5 -> 0.10443122 | O17: =N17*L17 -> 3.3026372
A18: peas | B18: =B6 -> 6.75 | D18: 2 | E18: =C18+D18/8 -> 0.25 | I18: 1.5 | K18: =I18+J18/8 -> 1.5 | L18: =B18-E18-K18 -> 5 | N18: =H6 -> 0.125 | O18: =N18*L18 -> 0.625
A19: vetches | B19: =B7 -> 8.25 | E19: =C19+D19/8 -> 0 | K19: =I19+J19/8 -> 0 | L19: =B19-E19-K19 -> 8.25 | N19: =H7 -> 0.1 | O19: =N19*L19 -> 0.825
A21: Total

Sheet Issues of the Mills

Sheet Stock
A1: HAMBLEDON STOCK ACCOUNT
C3: added | G3: subtracted
A4: Livestock | B4: Inherited stock | C4: added | D4: strays | E4: herbage | F4: churchscot | G4: of which in default | H4: sold | I4: in murrain | J4: accounted for elsewhere | K4: End-period stock | L4: cross-check | M4: stock building | N4: raw production | O4: Unit price (£) | P4: Value of stock (£) at given value | Q4: Value of stock (£) at sales prices | R4: Sales in (£) | S4: Value of stock building (£) | T4: Value of production (£) at sales prices | U4: Details
A5: Cart-horses | B5: 2 | K5: 2
A6: Mares
A7: Plough horses | B7: 8 | C7: 1 | H7: 1 | I7: 1 | K7: 7 | O7: =R7/H7 -> 0.04 | R7: =Receipts!F98 -> 0.04 | T7: =O7*C7 -> 0.04
A8: Colts (unspecified years)
A9: Colts (2 years)
A10: Colts (1 year)
A11: Foals
A12: Oxen | B12: 26 | C12: =1+5 -> 6 | H12: 4 | K12: 28 | O12: =R12/H12 -> 0.5375 | R12: =Receipts!F85 -> 2.15 | T12: =O12*C12 -> 3.225
A13: Bulls | B13: 2 | K13: 2
A14: Cows | B14: 21 | C14: =1 -> 1 | H14: 3 | K14: 19 | O14: =R14/H14 -> 0.37333333 | R14: =Receipts!F86 -> 1.12 | T14: =O14*C14 -> 0.37333333
A15: Steers | B15: 5 | C15: 39 | H15: 39 | J15: =5 -> 5 | K15: 0 | O15: =R15/H15 -> 0.43897436 | R15: =Receipts!F116 -> 17.12 | T15: =O15*C15 -> 17.12
A16: Bullocks | B16: 5 | K16: 5
A17: Yearlings | B17: 7 | I17: 1 | K17: 6
A18: Calves | B18: 15 | H18: 6 | I18: 2 | J18: =1 -> 1 | K18: 6 | O18: =R18/H18 -> 0.05 | R18: =Receipts!F93 -> 0.3 | T18: =O18*C18 -> 0
A19: Wethers | B19: 354 | C19: =77+3 -> 80 | H19: 16 | I19: =24+12 -> 36 | K19: 382 | O19: =R19/H19 -> 0.0625 | R19: =Receipts!F94 -> 1 | T19: =O19*C19 -> 5
A20: Rams | B20: 13 | C20: 3 | I20: =1 -> 1 | K20: 15
A21: Ewes | B21: 339 | C21: =94+2 -> 96 | H21: 14 | I21: =24+8+7 -> 39 | K21: 381 | O21: =R21/H21 -> 0.046428571 | R21: =Receipts!F95 -> 0.65 | T21: =O21*C21 -> 4.4571429
A22: Hoggs | B22: 188 | I22: =14 -> 14 | J22: =77+3+94 -> 174 | K22: 0 | T22: =O22*C22 -> 0
A23: Lambs | C23: =255+80 -> 335 | H23: 38 | I23: =57+19 -> 76 | J23: =25+3 -> 28 | K23: 193 | O23: =R23/H23 -> 0.012631579 | R23: =Receipts!F96 -> 0.48 | T23: =O23*C23 -> 4.2315789
A24: Boars | B24: 1 | K24: 1 | T24: =O24*C24 -> 0
A25: Sows | B25: 2 | K25: 2 | T25: =O25*C25 -> 0
A26: Pigs | B26: 43 | C26: =24 -> 24 | H26: 19 | I26: 3 | K26: 45 | O26: =R26/H26 -> 0.15789474 | R26: =Receipts!F97 -> 3 | T26: =O26*C26 -> 3.7894737
A27: Hoggets | B27: 27 | H27: 19 | I27: 3 | J27: 24 | K27: 0 | O27: =R27/H27 -> 0 | U27: not found in issues
A28: Piglets | C28: 51 | J28: =5+3 -> 8 | K28: 43
A29: Swans
A30: Peacocks
A31: Total Value | R31: =SUM(R7:R29) -> 25.86 | T31: =SUM(T5:T26) -> 38.236529
A34: Wool
A35: Coarse wool | C35: 812 | J35: =81+2+729 -> 812 | K35: 0 | O35: 0.02 | T35: =O35*J35 -> 16.24 | U35: unit price from overview sheet (UnitPricesStocks_averages)
A36: Lamb's wool | C36: 193 | J36: 193 | O36: 0.01 | T36: =O36*J36 -> 1.93 | U36: unit price from overview sheet (UnitPricesStocks_averages)
A37: Wool locks | H37: 7 | R37: =Receipts!F105 -> 0.31 | U37: sales only recorded in issues; recorded in cloves
A38: Wool sold at shearing
A39: Total wool | R39: =SUM(R35:R38) -> 0.31 | T39: =SUM(T35:T36)+R37 -> 18.48
A42: Hides
A43: Ox hides
A44: plough horse | C44: 1 | H44: 1 | O44: =R44/H44 -> 0.04 | R44: =Receipts!F98 -> 0.04 | T44: =O44*C44 -> 0.04
A45: yearling | C45: 1 | H45: 1 | O45: =R45/H45 -> 0.01 | R45: =Receipts!F99 -> 0.01 | T45: =O45*C45 -> 0.01
A46: Mare | T46: =O46*C46 -> 0
A47: Steer | T47: =O47*C47 -> 0
A48: calves | C48: 3 | H48: 3 | O48: =R48/H48 -> 0.0033333333 | R48: =Receipts!F100 -> 0.01 | T48: =O48*C48 -> 0.01 | U48: only 2 calves recorded in issues
A49: pigs | T49: =O49*C49 -> 0
A50: Woolskins | T50: =O50*C50 -> 0
A51: wethers | C51: 24 | H51: 24 | O51: =R51/H51 -> 0 | T51: =O51*C51 -> 0
A52: rams | C52: 1 | H52: 1 | O52: =R52/H52 -> 0 | T52: =O52*C52 -> 0
A53: ewes | C53: 32 | H53: 32 | O53: =R53/H53 -> 0 | T53: =O53*C53 -> 0
A54: hoggs | T54: =O54*C54 -> 0
A55: Woolskins | C55: =SUM(C51:C54) -> 57 | H55: =SUM(H51:H54) -> 57 | O55: =R55/H55 -> 0.0049122807 | R55: =Receipts!F103 -> 0.28 | T55: =O55*C55 -> 0.28
A56: Bareskins | T56: =O56*C56 -> 0
A57: wethers | C57: 12 | H57: 12 | O57: =R57/H57 -> 0 | T57: =O57*C57 -> 0
A58: rams | T58: =O58*C58 -> 0
A59: ewes | C59: 7 | H59: 7 | O59: =R59/H59 -> 0 | T59: =O59*C59 -> 0
A60: hoggs | C60: 14 | H60: 14 | O60: =R60/H60 -> 0 | T60: =O60*C60 -> 0
A61: Bareskins (total) | C61: =SUM(C57:C60) -> 33 | H61: =SUM(H57:H60) -> 33 | O61: =R61/H61 -> 0.0024242424 | R61: =Receipts!F102 -> 0.08 | T61: =O61*C61 -> 0.08
A62: Lambskins | C62: 57 | H62: 57 | O62: =R62/H62 -> 0.0049122807 | R62: =Receipts!F103 -> 0.28 | T62: =O62*C62 -> 0.28
A63: Rotted skins | C63: 19 | H63: 19
A64: Shorn skins
A65: Total | R65: =SUM(R41:R63) -> 0.7 | T65: =SUM(T44:T62) -> 0.7
A68: Poultry stock
A69: Hens
A70: Geese
A71: Capons (from chickens)
A72: Cocks & hens
A73: Total poultry stock
A74: Total poultry excluding churchscot
A76: Poultry production
A77: Eggs
A78: Cocks & hens from churchscot of customary tenants | F78: 51 | G78: 16 | H78: 38 | O78: =R78/H78 -> 0.0042105263 | R78: =Receipts!F109 -> 0.16 | T78: =O78*H78 -> 0.16
A79: Sum of above
A80: Total | R80: =SUM(R76:R78) -> 0.16 | T80: =T78 -> 0.16
A83: Meat
A84: Beef
A85: Mutton
A86: Pork
A87: Total
A89: Cheese
A90: Winter cheese | C90: 30 | H90: 30 | O90: =R90/H90 -> 0.0083333333 | R90: =Receipts!F106 -> 0.25 | T90: =O90*C90 -> 0.25
A91: Summer cheese | C91: 167 | H91: 150 | O91: =R91/H91 -> 0.022666667 | R91: =Receipts!F107 -> 3.4 | T91: =O91*C91 -> 3.7853333
A92: Total | R92: =SUM(R90:R91) -> 3.65 | T92: =SUM(T90:T91) -> 4.0353333
A94: Butter
A95: Butter | C95: 1 wey 5 cloves | H95: 1 wey 5 cloves | R95: =Receipts!F108 -> 0.39 | T95: =R95 -> 0.39
A96: Total | R96: =SUM(R95) -> 0.39 | T96: =T95 -> 0.39
A98: Total Dairy Sales
A101: Cider
A104: Additional Information (not necessarily useful)
A105: Utensils
A106: ploughs
A107: carts
A108: cart-ropes
A109: corn baskets
A110: seed-sacks
A111: seed basket
A112: locks for the doors
A113: lead vessel
... A130: brass posnets

Sheet raw data
A1: Heading | B1: Sentence | C1: Total in Pounds | D1: Pounds | E1: Shillings | F1: Pence | G1: Corn | H1: Total Quarters Except 1 | I1: Total Bushels Except 1 | J1: Total Corn Cross-Check | K1: Total Corn Manorial Account | L1: Corn Quantity Error | M1: Quarters 1 | N1: Bushels 1 | O1: Quarters 2 | P1: Bushels 2 | Q1: Quarters 3 | R1: Bushels 3 | S1: shilling a quarter 1 | T1: pence a quarter 1 | U1: shilling a quarter 2 | V1: pence a quarter 2 | W1: shilling a quarter 3 | X1: pence a quarter 3 | Y1: shilling a quarter 4 | Z1: pence a quarter 4 | AA1: shilling a bushel 1 | AB1: pence a bushel 1 | AC1: shilling a bushel 2 | AD1: pence a bushel 2 | AE1: shilling a bushel 3 | AF1: pence a bushel 3 | AG1: shilling a bushel 4 | AH1: pence a bushel 4
A2: Arrears | B2: Nicholas, bailiff, and William Bouelych', reeve, render account for £68 12 shilling 7.25pence of arrears from the previous year. | C2: 68.63 | D2: 68 | E2: 12 | F2: 7.25 | H2: 0 | I2: 0 | J2: 0 | K2: 0 | L2: 0 | M2: 0 | N2: 0
A3: Arrears | B3: All delivered to Sir Geoffrey, treasurer of Wolvesey. | C3: 0 | D3: 0 | E3: 0 | F3: 0 | H3: 0 | I3: 0 | J3: 0 | K3: 0 | L3: 0 | M3: 0 | N3: 0
A4: Arrears | B4: They are quit. | C4: 0 | D4: 0 | E4: 0 | F4: 0 | H4: 0 | I4: 0 | J4: 0 | K4: 0 | L4: 0 | M4: 0 | N4: 0
A5: Rents of assize | B5: The same render account for £6 13 shilling 11.25pence for rents of assize at Christmas. | C5: 6.7 | D5: 6 | E5: 13 | F5: 11.25 | H5: 0 | I5: 0 | J5: 0 | K5: 0 | L5: 0 | M5: 0 | N5: 0
A6: Rents of assize | B6: £7 9 shilling 1pence at Easter (22 April). | C6: 7.45 | D6: 7 | E6: 9 | F6: 1 | H6: 0 | I6: 0 | J6: 0 | K6: 0 | L6: 0 | M6: 0 | N6: 0
A7: Rents of assize | B7: £6 13 shilling 11.25pence at St John the Baptist (24 June). | C7: 6.7 | D7: 6 | E7: 13 | F7: 11.25 | H7: 0 | I7: 0 | J7: 0 | K7: 0 | L7: 0 | M7: 0 | N7: 0
A8: Rents of assize | B8: £11 10 shilling 110.75pence1 at Michaelmas (29 September). | C8: 11.96 | D8: 11 | E8: 10 | F8: 110.75 | H8: 0 | I8: 0 | J8: 0 | K8: 0 | L8: 0 | M8: 0 | N8: 0
A9: Rents of assize | B9: Total, £32 7 shilling 10.25pence | C9: 32.39 | D9: 32 | E9: 7 | F9: 10.25 | H9: 0 | I9: 0 | J9: 0 | K9: 0 | L9: 0 | M9: 0 | N9: 0
A10: Increment | B10: The same render account for 1pence for the increment of rent from Robert Faber to have 1 plot of land, 12 feet long and 5 feet wide, in the vill of Hambledon. | C10: 0 | D10: 0 | E10: 0 | F10: 1 | H10: 0 | I10: 0 | J10: 0 | K10: 0 | L10: 0 | M10: 0 | N10: 0
A11: Increment | B11: Total, 1pence Total of rents with increment, £32 7 shilling 11.25pence | C11: 32.4 | D11: 32 | E11: 7 | F11: 11.25 | H11: 0 | I11: 0 | J11: 0 | K11: 0 | L11: 0 | M11: 0 | N11: 0
A12: Quittances | B12: In quittance of 1 reeve for the year 2 shilling 6pence. | C12: 0.12 | D12: 0 | E12: 2 | F12: 6 | H12: 0 | I12: 0 | J12: 0 | K12: 0 | L12: 0 | M12: 0 | N12: 0
A13: Quittances | B13: 1 bartoner for the year 2 shilling 6pence. | C13: 0.12 | D13: 0 | E13: 2 | F13: 6 | H13: 0 | I13: 0 | J13: 0 | K13: 0 | L13: 0 | M13: 0 | N13: 0
... A85: Issues of the manor | B85: 10 shilling from 5 quarters of salt sold. | C85: 0.5 | D85: 0 | E85: 10 | F85: 0 | H85: 5 | I85: 0 | J85: 5 | K85: 5 | L85: 0 | M85: 5 | N85: 0
A86: Issues of the manor | B86: 1 shilling 3pence from 15 workers who are bound to thresh 2 bushels of wheat and 4 bushels of oats. | C86: 0.06 | D86: 0 | E86: 1 | F86: 3 | G86: oats, wheat | H86: 0 | I86: 4 | J86: 0.5 | K86: 0.25 | L86: 0.25 | M86: 0 | N86: 2 | O86: 0 | P86: 4
A87: Issues of the manor | B87: nothing from labour services sold this year. | C87: 0 | D87: 0 | E87: 0 | F87: 0 | H87: 0 | I87: 0 | J87: 0 | K87: 0 | L87: 0 | M87: 0 | N87: 0
A88: Issues of the manor | B88: nothing from the turbary on la Crith this year. | C88: 0 | D88: 0 | E88: 0 | F88: 0 | H88: 0 | I88: 0 | J88: 0 | K88: 0 | L88: 0 | M88: 0 | N88: 0
A89: Issues of the manor | B89: nothing from the pasturage beside Parkgate this year for the lord's animals. | C89: 0 | D89: 0 | E89: 0 | F89: 0 | H89: 0 | I89: 0 | J89: 0 | K89: 0 | L89: 0 | M89: 0 | N89: 0
A90: Issues of the manor | B90: 3 shilling 9pence from dairy produce sold at the audit. | C90: 0.19 | D90: 0 | E90: 3 | F90: 9 | H90: 0 | I90: 0 | J90: 0 | K90: 0 | L90: 0 | M90: 0 | N90: 0
A91: Issues of the manor | B91: £17 2 shilling 6pence from 39 animals sold which were bought to agist in the pasture. | C91: 17.12 | D91: 17 | E91: 2 | F91: 6 | H91: 0 | I91: 0 | J91: 0 | K91: 0 | L91: 0 | M91: 0 | N91: 0
A92: Issues of the manor | B92: Total, £42 3 shilling 4pence | C92: 42.17 | D92: 42 | E92: 3 | F92: 4 | H92: 0 | I92: 0 | J92: 0 | K92: 0 | L92: 0 | M92: 0 | N92: 0
A93: Farm of the mill | B93: The same render account for £1 16 shilling for the farm of the mill this year. | C93: 1.8 | D93: 1 | E93: 16 | F93: 0 | H93: 0 | I93: 0 | J93: 0 | K93: 0 | L93: 0 | M93: 0 | N93: 0
A94: Farm of the mill | B94: Total, £1 16 shilling | C94: 1.8 | D94: 1 | E94: 16 | F94: 0 | H94: 0 | I94: 0 | J94: 0 | K94: 0 | L94: 0 | M94: 0 | N94: 0
A95: Sale of corn | B95: The same render account for £12 14 shilling 3pence from 45 quarters 6 bushels of wheat sold, at 5 shilling a quarters for 20 quarters 2 bushels, and 6 shilling a quarters for 25.5 quarters. | C95: 12.71 | D95: 12 | E95: 14 | F95: 3 | G95: wheat | H95: 45.5 | I95: 2 | J95: 45.75 | K95: 45.75 | L95: 0 | M95: 45 | N95: 6 | O95: 20 | P95: 2 | Q95: 25.5 | R95: 0 | S95: 5 | T95: 0 | U95: 6 | V95: 0
A96: Sale of corn | B96: £1 15 shilling from 13 quarters 1 bushels of curall sold, at 2 shilling 8pence a quarters. | C96: 1.75 | D96: 1 | E96: 15 | F96: 0 | G96: curall | H96: 13 | I96: 1 | J96: 13.125 | K96: 13.125 | L96: 0 | M96: 13 | N96: 1 | S96: 2 | T96: 8
A97: Sale of corn | B97: £4 13 shilling from 23 quarters 2 bushels of barley sold, at 4 shilling a quarters. | C97: 4.65 | D97: 4 | E97: 13 | F97: 0 | G97: barley | H97: 23 | I97: 2 | J97: 23.25 | K97: 23.25 | L97: 0 | M97: 23 | N97: 2 | S97: 4 | T97: 0
A98: Sale of corn | B98: £3 5 shilling 9.5pence from 31.5 quarters of oats sold, at 2 shilling a quarters for 14 quarters 6 bushels, and 2 shilling 2pence a quarters for 16 quarters 6 bushels. | C98: 3.29 | D98: 3 | E98: 5 | F98: 9.5 | G98: oats | H98: 30 | I98: 12 | J98: 31.5 | K98: 31.5 | L98: 0 | M98: 31.5 | N98: 0 | O98: 14 | P98: 6 | Q98: 16 | R98: 6 | S98: 2 | T98: 0 | U98: 2 | V98: 2
A99: Sale of corn | B99: 12 shilling 6pence from 5 quarters of peas sold, at 2 shilling 6pence a quarters. | C99: 0.62 | D99: 0 | E99: 12 | F99: 6 | G99: peas | H99: 5 | I99: 0 | J99: 5 | K99: 5 | L99: 0 | M99: 5 | N99: 0 | S99: 2 | T99: 6
A100: Sale of corn | B100: 16 shilling 6pence from 8 quarters of vetches sold, at 2 shilling a quarters. | C100: 0.83 | D100: 0 | E100: 16 | F100: 6 | G100: vetches | H100: 8 | I100: 0 | J100: 8 | K100: 8 | L100: 0 | M100: 8 | N100: 0 | S100: 2 | T100: 0
A101: Sale of corn | B101: 3 shilling 4.5pence from 4.5 bushels of wheat sold at the audit. | C101: 0.17 | D101: 0 | E101: 3 | F101: 4.5 | G101: wheat | H101: 0 | I101: 4.5 | J101: 0.5625 | K101: 0.5625 | L101: 0 | M101: 0 | N101: 4.5
A102: Sale of corn | B102: 2 shilling 9pence from 5.5 bushels of barley sold at the audit. | C102: 0.14 | D102: 0 | E102: 2 | F102: 9 | G102: barley | H102: 0 | I102: 5.5 | J102: 0.6875 | K102: 0.6875 | L102: 0 | M102: 0 | N102: 5.5
A103: Sale of corn | B103: Total, £24 3 shilling 2pence | C103: 24.16 | D103: 24 | E103: 3 | F103: 2 | H103: 0 | I103: 0 | J103: 0 | K103: 0 | L103: 0 | M103: 0 | N103: 0
A104: Entry and marriage fines with tithingpenny | B104: The same render account for 5 shilling from the tithing of Chidden for tithingpenny at the hundred-court of Martinmas (11 November). | C104: 0.25 | D104: 0 | E104: 5 | F104: 0 | H104: 0 | I104: 0 | J104: 0 | K104: 0 | L104: 0 | M104: 0 | N104: 0
A105: Entry and marriage fines with tithingpenny | B105: 5 shilling from the tithing of Denmead for the same. | C105: 0.25 | D105: 0 | E105: 5 | F105: 0 | H105: 0 | I105: 0 | J105: 0 | K105: 0 | L105: 0 | M105: 0 | N105: 0
A106: Entry and marriage fines with tithingpenny | B106: 5 shilling from the tithing of la Lygh' for the same. | C106: 0.25 | D106: 0 | E106: 5 | F106: 0 | H106: 0 | I106: 0 | J106: 0 | K106: 0 | L106: 0 | M106: 0 | N106: 0
A107: Entry and marriage fines with tithingpenny | B107: 5 shilling from the tithing of Gludden for the same. | C107: 0.25 | D107: 0 | E107: 5 | F107: 0 | H107: 0 | I107: 0 | J107: 0 | K107: 0 | L107: 0 | M107: 0 | N107: 0
A108: Entry and marriage fines with tithingpenny | B108: £1 from the same tithings at the hundred-court of Hockday (1 May). | C108: 1 | D108: 1 | E108: 0 | F108: 0 | H108: 0 | I108: 0 | J108: 0 | K108: 0 | L108: 0 | M108: 0 | N108: 0
A109: Entry and marriage fines with tithingpenny | B109: 5 shilling from the relict of Thomas le Cog' to retain 1 cotland which belonged to her husband. | C109: 0.25 | D109: 0 | E109: 5 | F109: 0 | H109: 0 | I109: 0 | J109: 0 | K109: 0 | L109: 0 | M109: 0 | N109: 0
A110: Entry and marriage fines with tithingpenny | B110: 10 shilling from Adam Coker to have .5 virgate of land which belonged to Stephen his father. | C110: 0.5 | D110: 0 | E110: 10 | F110: 0 | H110: 0 | I110: 0 | J110: 0 | K110: 0 | L110: 0 | M110: 0 | N110: 0
A111: Entry and marriage fines with tithingpenny | B111: 2 shilling from William Bouelych' to have 2 acres of land by surrender of Adam Bythewod'. | C111: 0.1 | D111: 0 | E111: 2 | F111: 0 | H111: 0 | I111: 0 | J111: 0 | K111: 0 | L111: 0 | M111: 0 | N111: 0
A112: Entry and marriage fines with tithingpenny | B112: 1 shilling from John Pleyfot to have 1 plot of land in the vill of Hambledon by surrender of Walter le Grevere. | C112: 0.05 | D112: 0 | E112: 1 | F112: 0 | H112: 0 | I112: 0 | J112: 0 | K112: 0 | L112: 0 | M112: 0 | N112: 0
A113: Entry and marriage fines with tithingpenny | B113: 1 shilling from Robert Faber to have 1 plot of land, 12 feet long and 5 feet wide, in the same vill. | C113: 0.05 | D113: 0 | E113: 1 | F113: 0 | H113: 0 | I113: 0 | J113: 0 | K113: 0 | L113: 0 | M113: 0 | N113: 0
A114: Entry and marriage fines with tithingpenny | B114: 4 shilling from Robert le Bole to have 8 acres of land by surrender of William atte Oke. | C114: 0.2 | D114: 0 | E114: 4 | F114: 0 | H114: 0 | I114: 0 | J114: 0 | K114: 0 | L114: 0 | M114: 0 | N114: 0
... A139: Cost of ploughs | B139: 1 plough-horse bought 12 shilling 3pence Total, £3 1 shilling 7.5pence | C139: 3.08 | D139: 3 | E139: 1 | F139: 7.5 | H139: 0 | I139: 0 | J139: 0 | K139: 0 | L139: 0 | M139: 0 | N139: 0
A140: Purchase of corn | B140: In 6.5 quarters of barley bought for the liveries of the manorial servants 17 shilling 4pence, at 2 shilling 8pence a quarters. | C140: 0.87 | D140: 0 | E140: 17 | F140: 4 | G140: barley | H140: 6.5 | I140: 0 | J140: 6.5 | K140: 6.5 | L140: 0 | M140: 6.5 | N140: 0 | S140: 2 | T140: 8
A141: Purchase of corn | B141: Total, 17 shilling 4pence | C141: 0.87 | D141: 0 | E141: 17 | F141: 4 | H141: 0 | I141: 0 | J141: 0 | K141: 0 | L141: 0 | M141: 0 | N141: 0
A142: Cost of carts | B142: in 1 pair of wheels made anew from the lord's timber 9pence. | C142: 0.04 | D142: 0 | E142: 0 | F142: 9 | H142: 0 | I142: 0 | J142: 0 | K142: 0 | L142: 0 | M142: 0 | N142: 0
A143: Cost of carts | B143: mending 1 old binding and putting it on the said wheels with the stipend of the smith 2 shilling 6pence. | C143: 0.12 | D143: 0 | E143: 2 | F143: 6 | H143: 0 | I143: 0 | J143: 0 | K143: 0 | L143: 0 | M143: 0 | N143: 0
A144: Cost of carts | B144: clouts, nails and grease bought 1 shilling 9pence. | C144: 0.09 | D144: 0 | E144: 1 | F144: 9 | H144: 0 | I144: 0 | J144: 0 | K144: 0 | L144: 0 | M144: 0 | N144: 0
A145: Cost of carts | B145: mending the axles of the cart at various times 8pence, on account of the manor of Kilmeston. | C145: 0.03 | D145: 0 | E145: 0 | F145: 8 | H145: 0 | I145: 0 | J145: 0 | K145: 0 | L145: 0 | M145: 0 | N145: 0
A146: Cost of carts | B146: . | C146: 0 | D146: 0 | E146: 0 | F146: 0 | H146: 0 | I146: 0 | J146: 0 | K146: 0 | L146: 0 | M146: 0 | N146: 0
A147: Cost of carts | B147: shoeing 2 cart-horses 3 shilling 6pence. | C147: 0.17 | D147: 0 | E147: 3 | F147: 6 | H147: 0 | I147: 0 | J147: 0 | K147: 0 | L147: 0 | M147: 0 | N147: 0
A148: Cost of carts | B148: 2 collars bought 10pence. | C148: 0.04 | D148: 0 | E148: 0 | F148: 10 | H148: 0 | I148: 0 | J148: 0 | K148: 0 | L148: 0 | M148: 0 | N148: 0
A149: Cost of carts | B149: 2 pairs of traces bought 9pence. | C149: 0.04 | D149: 0 | E149: 0 | F149: 9 | H149: 0 | I149: 0 | J149: 0 | K149: 0 | L149: 0 | M149: 0 | N149: 0
A150: Cost of carts | B150: 1 rope bought for the cart 1 shilling 2pence. | C150: 0.06 | D150: 0 | E150: 1 | F150: 2 | H150: 0 | I150: 0 | J150: 0 | K150: 0 | L150: 0 | M150: 0 | N150: 0
A151: Cost of carts | B151: 2 halters bought 1.5pence. | C151: 0.01 | D151: 0 | E151: 0 | F151: 1.5 | H151: 0 | I151: 0 | J151: 0 | K151: 0 | L151: 0 | M151: 0 | N151: 0
A152: Cost of carts | B152: stipend of 1 carter from Michaelmas until Lammas, because thereafter he was at the church, 2 shilling 3pence Total, 14 shilling 3.5pence | C152: 0.11 | D152: 0 | E152: 2 | F152: 3 | H152: 0 | I152: 0 | J152: 0 | K152: 0 | L152: 0 | M152: 0 | N152: 0
... A191: Cost of hay | B191: tossing and spreading the hay and making haycocks therefrom Total, 15 shilling 1.5pence | C191: 0.76 | D191: 0 | E191: 15 | F191: 1.5 | H191: 0 | I191: 0 | J191: 0 | K191: 0 | L191: 0 | M191: 0 | N191: 0
A192: Threshing | B192: In threshing and winnowing 68 quarters of wheat and curall by piece-work 15 shilling 7pence, at 2.75pence a quarters. | C192: 0.78 | D192: 0 | E192: 15 | F192: 7 | G192: curall, wheat | H192: 68 | I192: 0 | J192: 68 | K192: 68 | L192: 0 | M192: 68 | N192: 0
A193: Threshing | B193: . | C193: 0 | D193: 0 | E193: 0 | F193: 0 | H193: 0 | I193: 0 | J193: 0 | K193: 0 | L193: 0 | M193: 0 | N193: 0
A194: Threshing | B194: threshing and winnowing 55 quarters 2 bushels of barley, 4 quarters of peas and 7 quarters of vetches by piece-work 9 shilling 7.5pence, at 1.75pence a quarters. | C194: 0.48 | D194: 0 | E194: 9 | F194: 7.5 | G194: barley, vetches, peas | H194: 11 | I194: 2 | J194: 11.25 | K194: 55.25 | L194: -44 | M194: 55 | N194: 2 | O194: 4 | P194: 0 | Q194: 7 | R194: 0
A195: Threshing | B195: . | C195: 0 | D195: 0 | E195: 0 | F195: 0 | H195: 0 | I195: 0 | J195: 0 | K195: 0 | L195: 0 | M195: 0 | N195: 0
A196: Threshing | B196: threshing and winnowing 44 quarters of oats by piece-work 3 shilling 2.5pence, at 1.75pence per 2 quarters. | C196: 0.16 | D196: 0 | E196: 3 | F196: 2.5 | G196: oats | H196: 2 | I196: 0 | J196: 2 | K196: 44 | L196: -42 | M196: 44 | N196: 0 | O196: 2 | P196: 0
A197: Threshing | B197: . | C197: 0 | D197: 0 | E197: 0 | F197: 0 | H197: 0 | I197: 0 | J197: 0 | K197: 0 | L197: 0 | M197: 0 | N197: 0
A198: Threshing | B198: 5 sacks bought 2 shilling 6pence Total, £1 10 shilling 11pence | C198: 1.55 | D198: 1 | E198: 10 | F198: 11 | H198: 0 | I198: 0 | J198: 0 | K198: 0 | L198: 0 | M198: 0 | N198: 0
A199: Harvest-time | B199: In bread bought for 974 men at 15 boon-works with the carters and customary tenants who reaped and bound 222 acres of wheat, 107 acres of barley and 414 acres of oats as they lie £1 19 shilling 8pence. | C199: 1.98 | D199: 1 | E199: 19 | F199: 8 | G199: barley, oats, wheat | H199: 0 | I199: 0 | J199: 0 | K199: 0 | L199: 0 | M199: 0 | N199: 0
A200: Harvest-time | B200: relish for the same 12 shilling. | C200: 0.6 | D200: 0 | E200: 12 | F200: 0 | H200: 0 | I200: 0 | J200: 0 | K200: 0 | L200: 0 | M200: 0 | N200: 0
A201: Harvest-time | B201: allowance of food for the reeve and bartoner at harvest-time 1 shilling 8pence Total, £2 13 shilling 4pence | C201: 2.67 | D201: 2 | E201: 13 | F201: 4 | H201: 0 | I201: 0 | J201: 0 | K201: 0 | L201: 0 | M201: 0 | N201: 0
A202: Cost of the mill | B202: In iron bought for mending the spindle 8pence Total, 8pence | C202: 0.03 | D202: 0 | E202: 0 | F202: 8 | H202: 0 | I202: 0 | J202: 0 | K202: 0 | L202: 0 | M202: 0 | N202: 0
A203: Expenses of the steward | B203: In expenses of Simon, clerk, holding the place of the steward at the 2 tourns 9 shilling 6pence Total, 9 shilling 6pence | C203: 0.48 | D203: 0 | E203: 9 | F203: 6 | H203: 0 | I203: 0 | J203: 0 | K203: 0 | L203: 0 | M203: 0 | N203: 0
A204: Expenses of the bailiff | B204: In expenses of the bailiff for his visits £1 18 shilling. | C204: 1.9 | D204: 1 | E204: 18 | F204: 0 | H204: 0 | I204: 0 | J204: 0 | K204: 0 | L204: 0 | M204: 0 | N204: 0
A205: Expenses of the bailiff | B205: wages of 1 under-servant for the year £2 5 shilling 7.5pence, at 1.5pence a day, because the bailiff did not stay there. | C205: 2.28 | D205: 2 | E205: 5 | F205: 7.5 | H205: 0 | I205: 0 | J205: 0 | K205: 0 | L205: 0 | M205: 0 | N205: 0
A206: Expenses of the bailiff | B206: Total, £4 3 shilling 7.5pence | C206: 4.18 | D206: 4 | E206: 3 | F206: 7.5 | H206: 0 | I206: 0 | J206: 0 | K206: 0 | L206: 0 | M206: 0 | N206: 0
A207: Purchase of stock | B207: In 39 animals bought for pasturing £13 14 shilling 7pence Total, £13 14 shilling 7pence | C207: 13.73 | D207: 13 | E207: 14 | F207: 7 | H207: 0 | I207: 0 | J207: 0 | K207: 0 | L207: 0 | M207: 0 | N207: 0
A208: Total of all expenses | B208: Total of all expenses, £34 19 shilling 7.25pence | C208: 34.98 | D208: 34 | E208: 19 | F208: 7.25 | H208: 0 | I208: 0 | J208: 0 | K208: 0 | L208: 0 | M208: 0 | N208: 0
A209: And he owes | B209: And he owes, £72 l 1pence | C209: 72 | D209: 72 | E209: 0 | F209: 0 | H209: 0 | I209: 0 | J209: 0 | K209: 0 | L209: 0 | M209: 0 | N209: 0
A210: Cash deliveries | B210: Delivered to Sir Geoffrey, treasurer of Wolvesey, by 1 tally, £72. | C210: 72 | D210: 72 | E210: 0 | F210: 0 | H210: 0 | I210: 0 | J210: 0 | K210: 0 | L210: 0 | M210: 0 | N210: 0
A211: And thus he owes | B211: And thus he is quit. | C211: 0 | D211: 0 | E211: 0 | F211: 0 | H211: 0 | I211: 0 | J211: 0 | K211: 0 | L211: 0 | M211: 0 | N211: 0
A212: Wheat | B212: {yield: 4.5-fold less .5 quarters} | C212: 0 | D212: 0 | E212: 0 | F212: 0 | H212: 5 | I212: 0 | J212: 5 | K212: 5 | L212: 0 | M212: 5 | N212: 0
A213: Wheat | B213: The same render account for 71 quarters 6 bushels from the whole issue of wheat by struck measure. | C213: 0 | D213: 0 | E213: 0 | F213: 0 | G213: wheat | H213: 71 | I213: 6 | J213: 71.75 | K213: 71.75 | L213: 0 | M213: 71 | N213: 6
A214: Wheat | B214: 1.5 quarters from churchscot. | C214: 0 | D214: 0 | E214: 0 | F214: 0 | H214: 1.5 | I214: 0 | J214: 1.5 | K214: 1.5 | L214: 0 | M214: 1.5 | N214: 0
A215: Wheat | B215: Total, 73 quarters 2 bushels | C215: 0 | D215: 0 | E215: 0 | F215: 0 | H215: 73 | I215: 2 | J215: 73.25 | K215: 73.25 | L215: 0 | M215: 73 | N215: 2
A216: Wheat | B216: Sown over 75 acres which lie in la Garston', Slade and Vyneys, 23 quarters 3.5 bushels. | C216: 0 | D216: 0 | E216: 0 | F216: 0 | H216: 23 | I216: 3.5 | J216: 23.4375 | K216: 23.4375 | L216: 0 | M216: 23 | N216: 3.5
A217: Wheat | B217: that is, 2.5 bushels an acre. | C217: 0 | D217: 0 | E217: 0 | F217: 0 | H217: 0 | I217: 2.5 | J217: 0.3125 | K217: 0.3125 | L217: 0 | M217: 0 | N217: 2.5
A218: Wheat | B218: . | C218: 0 | D218: 0 | E218: 0 | F218: 0 | H218: 0 | I218: 0 | J218: 0 | K218: 0 | L218: 0 | M218: 0 | N218: 0
A219: Wheat | B219: provision of Simon, clerk, for 2 tourns, 6 bushels. | C219: 0 | D219: 0 | E219: 0 | F219: 0 | H219: 0 | I219: 6 | J219: 0.75 | K219: 0.75 | L219: 0 | M219: 0 | N219: 6
A220: Wheat | B220: provision of the bailiff for his visits, 2 quarters 6 bushels Sold, 45 quarters 6 bushels Sold at the audit, 4.5 bushels | C220: 0 | D220: 0 | E220: 0 | F220: 0 | H220: 45 | I220: 10.5 | J220: 46.3125 | K220: 2.75 | L220: 43.5625 | M220: 2 | N220: 6 | O220: 45 | P220: 6 | Q220: 0 | R220: 4.5
A221: Curall | B221: The same render account for 13 quarters 1 bushels from the issue of curall by struck measure. | C221: 0 | D221: 0 | E221: 0 | F221: 0 | G221: curall | H221: 13 | I221: 1 | J221: 13.125 | K221: 13.125 | L221: 0 | M221: 13 | N221: 1
A222: Curall | B222: all solpence | C222: 0 | D222: 0 | E222: 0 | F222: 0 | H222: 0 | I222: 0 | J222: 0 | K222: 0 | L222: 0 | M222: 0 | N222: 0
A223: Barley | B223: (yield: 4-fold less 3 quarters 2 bushels) | C223: 0 | D223: 0 | E223: 0 | F223: 0 | H223: 3 | I223: 2 | J223: 3.25 | K223: 3.25 | L223: 0 | M223: 3 | N223: 2
A224: Barley | B224: The same render account for 69 quarters 2 bushels from the whole issue of barley by struck measure. | C224: 0 | D224: 0 | E224: 0 | F224: 0 | G224: barley | H224: 69 | I224: 2 | J224: 69.25 | K224: 69.25 | L224: 0 | M224: 69 | N224: 2
A225: Barley | B225: 6 quarters 5 bushels bought. | C225: 0 | D225: 0 | E225: 0 | F225: 0 | H225: 6 | I225: 5 | J225: 6.625 | K225: 6.625 | L225: 0 | M225: 6 | N225: 5
A226: Barley | B226: Total, 75 quarters 7 bushels | C226: 0 | D226: 0 | E226: 0 | F226: 0 | H226: 75 | I226: 7 | J226: 75.875 | K226: 75.875 | L226: 0 | M226: 75 | N226: 7
A227: Barley | B227: Sown over 33 acres which lie at Parkgate and la Rugg', 20.5 quarters. | C227: 0 | D227: 0 | E227: 0 | F227: 0 | H227: 20.5 | I227: 0 | J227: 20.5 | K227: 20.5 | L227: 0 | M227: 20.5 | N227: 0
A228: Barley | B228: that is, 5 bushels an acre, less 2 bushels in all. | C228: 0 | D228: 0 | E228: 0 | F228: 0 | H228: 0 | I228: 2 | J228: 0.25 | K228: 0.625 | L228: -0.375 | M228: 0 | N228: 5 | O228: 0 | P228: 2
A229: Barley | B229: Delivered to 1 park-keeper for the year, 1 quarters according to custom. | C229: 0 | D229: 0 | E229: 0 | F229: 0 | H229: 1 | I229: 0 | J229: 1 | K229: 1 | L229: 0 | M229: 1 | N229: 0
A230: Barley | B230: . | C230: 0 | D230: 0 | E230: 0 | F230: 0 | H230: 0 | I230: 0 | J230: 0 | K230: 0 | L230: 0 | M230: 0 | N230: 0
A231: Barley | B231: customary payment to 1 keeper of lambs until the feast of St John the Baptist, 4 bushels Delivered to 1 carter, 6.5 quarters, taking a quarter every 8 weeks. | C231: 0 | D231: 0 | E231: 0 | F231: 0 | H231: 6.5 | I231: 4 | J231: 7 | K231: 0.5 | L231: 6.5 | M231: 0 | N231: 4 | O231: 6.5 | P231: 0
A232: Barley | B232: Delivered to 3 ploughmen for the year, 19.5 quarters. | C232: 0 | D232: 0 | E232: 0 | F232: 0 | H232: 19.5 | I232: 0 | J232: 19.5 | K232: 19.5 | L232: 0 | M232: 19.5 | N232: 0
A233: Barley | B233: Delivered to 1 dairymaid from the purification until Michaelmas, 2 quarters 6.5 bushels, taking a quarter every 12 weeks. | C233: 0 | D233: 0 | E233: 0 | F233: 0 | H233: 2 | I233: 6.5 | J233: 2.8125 | K233: 2.8125 | L233: 0 | M233: 2 | N233: 6.5
...

Sheet Issues of the Grange raw
A1: Heading | B1: Sentence | C1: Quarters 1_x | D1: Bushels 1_x | E1: Sown Quarters | F1: Sown Bushels | G1: Sown Total Quarters | H1: Bought in Quarters | I1: Bought in Bushels | J1: Bought in Total Quarters | K1: Tithe Quarters | L1: Tithe Bushels | M1: Tithe Total Quarters | N1: Manorial servants & livestock Quarters | O1: Manorial servants & livestock Bushels | P1: Manorial servants & livestock Total Quarters | Q1: Sold Quarters | R1: Sold Bushels | S1: Sold Total Quarters | T1: Account Quarters | U1: Account Bushels | V1: Account Total Quarters | W1: bought only | X1: Total Quarters Except 1 | Y1: Total Bushels Except 1 | Z1: Total Corn Cross-Check | AA1: Total Corn Manorial Account | AB1: Corn Quantity Error | AC1: Quarters 1_y | AD1: Bushels 1_y | AE1: Quarters 2 | AF1: Bushels 2 | AG1: Quarters 3 | AH1: Bushels 3
A2: And thus he owes | B2: Total | C2: 0 | D2: 0 | E2: 0 | F2: 0 | G2: 0 | H2: 0 | I2: 0 | J2: 0 | K2: 0 | L2: 0 | M2: 0 | N2: 0 | O2: 0 | P2: 0 | Q2: 0 | R2: 0 | S2: 0 | T2: 0 | U2: 0 | V2: 0 | W2: 0
A3: Wheat | B3: {yield: 4.5-fold less .5 qr} | C3: 0 | D3: 0 | E3: 0 | F3: 0 | G3: 0 | H3: 0 | I3: 0 | J3: 0 | K3: 0 | L3: 0 | M3: 0 | N3: 0 | O3: 0 | P3: 0 | Q3: 0 | R3: 0 | S3: 0 | T3: 0 | U3: 0 | V3: 0 | W3: 0
A4: Wheat | B4: The same render account for 71 quarters 6 bushels from the whole issue of wheat by struck measure. | C4: 0 | D4: 0 | E4: 0 | F4: 0 | G4: 0 | H4: 0 | I4: 0 | J4: 0 | K4: 0 | L4: 0 | M4: 0 | N4: 0 | O4: 0 | P4: 0 | Q4: 0 | R4: 0 | S4: 0 | T4: 71 | U4: 6 | V4: 71.75 | W4: 0 | X4: 71 | Y4: 6 | Z4: 71.75 | AA4: 71.75 | AB4: 0 | AC4: 71 | AD4: 6
A5: Wheat | B5: 1.5 quarters from churchscot. | C5: 0 | D5: 0 | E5: 0 | F5: 0 | G5: 0 | H5: 0 | I5: 0 | J5: 0 | K5: 0 | L5: 0 | M5: 0 | N5: 0 | O5: 0 | P5: 0 | Q5: 0 | R5: 0 | S5: 0 | T5: 0 | U5: 0 | V5: 0 | W5: 0 | X5: 1.5 | Y5: 0 | Z5: 1.5 | AA5: 1.5 | AB5: 0 | AC5: 1.5 | AD5: 0
A6: Wheat | B6: Total, 73 quarters 2 bushels | C6: 0 | D6: 0 | E6: 0 | F6: 0 | G6: 0 | H6: 0 | I6: 0 | J6: 0 | K6: 0 | L6: 0 | M6: 0 | N6: 0 | O6: 0 | P6: 0 | Q6: 0 | R6: 0 | S6: 0 | T6: 0 | U6: 0 | V6: 0 | W6: 0 | X6: 73 | Y6: 2 | Z6: 73.25 | AA6: 73.25 | AB6: 0 | AC6: 73 | AD6: 2
A7: Wheat | B7: Sown over 75 acres which lie in la Garston', Slade and Vyneys, 23 quarters 3.5 bushels. | C7: 0 | D7: 0 | E7: 23 | F7: 3.5 | G7: 23.4375 | H7: 0 | I7: 0 | J7: 0 | K7: 0 | L7: 0 | M7: 0 | N7: 0 | O7: 0 | P7: 0 | Q7: 0 | R7: 0 | S7: 0 | T7: 0 | U7: 0 | V7: 0 | W7: 0 | X7: 23 | Y7: 3.5 | Z7: 23.4375 | AA7: 23.4375 | AB7: 0 | AC7: 23 | AD7: 3.5
A8: Wheat | B8: that is, 2.5 bushels an acre. | C8: 0 | D8: 0 | E8: 0 | F8: 0 | G8: 0 | H8: 0 | I8: 0 | J8: 0 | K8: 0 | L8: 0 | M8: 0 | N8: 0 | O8: 0 | P8: 0 | Q8: 0 | R8: 0 | S8: 0 | T8: 0 | U8: 0 | V8: 0 | W8: 0 | X8: 0 | Y8: 2.5 | Z8: 0.3125 | AA8: 0.3125 | AB8: 0 | AC8: 0 | AD8: 2.5
A9: Wheat | B9: . | C9: 0 | D9: 0 | E9: 0 | F9: 0 | G9: 0 | H9: 0 | I9: 0 | J9: 0 | K9: 0 | L9: 0 | M9: 0 | N9: 0 | O9: 0 | P9: 0 | Q9: 0 | R9: 0 | S9: 0 | T9: 0 | U9: 0 | V9: 0 | W9: 0 | X9: 0 | Y9: 0 | Z9: 0 | AA9: 0 | AB9: 0 | AC9: 0 | AD9: 0
A10: Wheat | B10: provision of Simon, clerk, for 2 tourns, 6 bushels. | C10: 0 | D10: 0 | E10: 0 | F10: 0 | G10: 0 | H10: 0 | I10: 0 | J10: 0 | K10: 0 | L10: 0 | M10: 0 | N10: 0 | O10: 0 | P10: 0 | Q10: 0 | R10: 0 | S10: 0 | T10: 0 | U10: 0 | V10: 0 | W10: 0 | X10: 0 | Y10: 6 | Z10: 0.75 | AA10: 0.75 | AB10: 0 | AC10: 0 | AD10: 6
A11: Wheat | B11: provision of the bailiff for his visits, 2 quarters 6 bushels Sold, 45 quarters 6 bushels Sold at the audit, 4.5 bushels | C11: 0 | D11: 0 | E11: 0 | F11: 0 | G11: 0 | H11: 0 | I11: 0 | J11: 0 | K11: 0 | L11: 0 | M11: 0 | N11: 0 | O11: 0 | P11: 0 | Q11: 47 | R11: 12 | S11: 48.5 | T11: 0 | U11: 0 | V11: 0 | W11: 0 | X11: 45 | Y11: 10.5 | Z11: 46.3125 | AA11: 2.75 | AB11: 43.5625 | AC11: 2 | AD11: 6 | AE11: 45 | AF11: 6 | AG11: 0 | AH11: 4.5
A12: Wheat | B12: Total | C12: 0 | D12: 0 | E12: 0 | F12: 0 | G12: 0 | H12: 0 | I12: 0 | J12: 0 | K12: 0 | L12: 0 | M12: 0 | N12: 0 | O12: 0 | P12: 0 | Q12: 0 | R12: 0 | S12: 0 | T12: 0 | U12: 0 | V12: 0 | W12: 0
A13: Curall | B13: The same render account for 13 quarters 1 bushels from the issue of curall by struck measure. | C13: 0 | D13: 0 | E13: 0 | F13: 0 | G13: 0 | H13: 0 | I13: 0 | J13: 0 | K13: 0 | L13: 0 | M13: 0 | N13: 0 | O13: 0 | P13: 0 | Q13: 0 | R13: 0 | S13: 0 | T13: 13 | U13: 1 | V13: 13.125 | W13: 0 | X13: 13 | Y13: 1 | Z13: 13.125 | AA13: 13.125 | AB13: 0 | AC13: 13 | AD13: 1
A14: Curall | B14: all solpence | C14: 0 | D14: 0 | E14: 0 | F14: 0 | G14: 0 | H14: 0 | I14: 0 | J14: 0 | K14: 0 | L14: 0 | M14: 0 | N14: 0 | O14: 0 | P14: 0 | Q14: 0 | R14: 0 | S14: 0 | T14: 0 | U14: 0 | V14: 0 | W14: 0 | X14: 0 | Y14: 0 | Z14: 0 | AA14: 0 | AB14: 0 | AC14: 0 | AD14: 0
A15: Curall | B15: Total | C15: 0 | D15: 0 | E15: 0 | F15: 0 | G15: 0 | H15: 0 | I15: 0 | J15: 0 | K15: 0 | L15: 0 | M15: 0 | N15: 0 | O15: 0 | P15: 0 | Q15: 0 | R15: 0 | S15: 0 | T15: 0 | U15: 0 | V15: 0 | W15: 0
A16: Barley | B16: (yield: 4-fold less 3 quarters 2 bushels) | C16: 0 | D16: 0 | E16: 0 | F16: 0 | G16: 0 | H16: 0 | I16: 0 | J16: 0 | K16: 0 | L16: 0 | M16: 0 | N16: 0 | O16: 0 | P16: 0 | Q16: 0 | R16: 0 | S16: 0 | T16: 0 | U16: 0 | V16: 0 | W16: 0 | X16: 3 | Y16: 2 | Z16: 3.25 | AA16: 3.25 | AB16: 0 | AC16: 3 | AD16: 2
A17: Barley | B17: The same render account for 69 quarters 2 bushels from the whole issue of barley by struck measure. | C17: 0 | D17: 0 | E17: 0 | F17: 0 | G17: 0 | H17: 0 | I17: 0 | J17: 0 | K17: 0 | L17: 0 | M17: 0 | N17: 0 | O17: 0 | P17: 0 | Q17: 0 | R17: 0 | S17: 0 | T17: 69 | U17: 2 | V17: 69.25 | W17: 0 | X17: 69 | Y17: 2 | Z17: 69.25 | AA17: 69.25 | AB17: 0 | AC17: 69 | AD17: 2
A18: Barley | B18: 6 quarters 5 bushels bought. | C18: 0 | D18: 0 | E18: 0 | F18: 0 | G18: 0 | H18: 6 | I18: 5 | J18: 6.625 | K18: 0 | L18: 0 | M18: 0 | N18: 0 | O18: 0 | P18: 0 | Q18: 0 | R18: 0 | S18: 0 | T18: 0 | U18: 0 | V18: 0 | W18: 0 | X18: 6 | Y18: 5 | Z18: 6.625 | AA18: 6.625 | AB18: 0 | AC18: 6 | AD18: 5
A19: Barley | B19: Total, 75 quarters 7 bushels | C19: 0 | D19: 0 | E19: 0 | F19: 0 | G19: 0 | H19: 0 | I19: 0 | J19: 0 | K19: 0 | L19: 0 | M19: 0 | N19: 0 | O19: 0 | P19: 0 | Q19: 0 | R19: 0 | S19: 0 | T19: 0 | U19: 0 | V19: 0 | W19: 0 | X19: 75 | Y19: 7 | Z19: 75.875 | AA19: 75.875 | AB19: 0 | AC19: 75 | AD19: 7
A20: Barley | B20: Sown over 33 acres which lie at Parkgate and la Rugg', 20.5 quarters. | C20: 0 | D20: 0 | E20: 20.5 | F20: 0 | G20: 20.5 | H20: 0 | I20: 0 | J20: 0 | K20: 0 | L20: 0 | M20: 0 | N20: 0 | O20: 0 | P20: 0 | Q20: 0 | R20: 0 | S20: 0 | T20: 0 | U20: 0 | V20: 0 | W20: 0 | X20: 20.5 | Y20: 0 | Z20: 20.5 | AA20: 20.5 | AB20: 0 | AC20: 20.5 | AD20: 0
A21: Barley | B21: that is, 5 bushels an acre, less 2 bushels in all. | C21: 0 | D21: 0 | E21: 0 | F21: 0 | G21: 0 | H21: 0 | I21: 0 | J21: 0 | K21: 0 | L21: 0 | M21: 0 | N21: 0 | O21: 0 | P21: 0 | Q21: 0 | R21: 0 | S21: 0 | T21: 0 | U21: 0 | V21: 0 | W21: 0 | X21: 0 | Y21: 2 | Z21: 0.25 | AA21: 0.625 | AB21: -0.375 | AC21: 0 | AD21: 5 | AE21: 0 | AF21: 2
A22: Barley | B22: Delivered to 1 park-keeper for the year, 1 qr according to custom. | C22: 0 | D22: 0 | E22: 0 | F22: 0 | G22: 0 | H22: 0 | I22: 0 | J22: 0 | K22: 0 | L22: 0 | M22: 0 | N22: 0 | O22: 0 | P22: 0 | Q22: 0 | R22: 0 | S22: 0 | T22: 0 | U22: 0 | V22: 0 | W22: 0
A23: Barley | B23: . | C23: 0 | D23: 0 | E23: 0 | F23: 0 | G23: 0 | H23: 0 | I23: 0 | J23: 0 | K23: 0 | L23: 0 | M23: 0 | N23: 0 | O23: 0 | P23: 0 | Q23: 0 | R23: 0 | S23: 0 | T23: 0 | U23: 0 | V23: 0 | W23: 0 | X23: 0 | Y23: 0 | Z23: 0 | AA23: 0 | AB23: 0 | AC23: 0 | AD23: 0
A24: Barley | B24: customary payment to 1 keeper of lambs until the feast of St John the Baptist, 4 bushels Delivered to 1 carter, 6.5 quarters, taking a quarter every 8 weeks. | C24: 0 | D24: 0 | E24: 0 | F24: 0 | G24: 0 | H24: 0 | I24: 0 | J24: 0 | K24: 0 | L24: 0 | M24: 0 | N24: 0 | O24: 0 | P24: 0 | Q24: 0 | R24: 0 | S24: 0 | T24: 0 | U24: 0 | V24: 0 | W24: 0 | X24: 6.5 | Y24: 4 | Z24: 7 | AA24: 0.5 | AB24: 6.5 | AC24: 0 | AD24: 4 | AE24: 6.5 | AF24: 0
A25: Barley | B25: Delivered to 3 ploughmen for the year, 19.5 quarters. | C25: 0 | D25: 0 | E25: 0 | F25: 0 | G25: 0 | H25: 0 | I25: 0 | J25: 0 | K25: 0 | L25: 0 | M25: 0 | N25: 0 | O25: 0 | P25: 0 | Q25: 0 | R25: 0 | S25: 0 | T25: 0 | U25: 0 | V25: 0 | W25: 0 | X25: 19.5 | Y25: 0 | Z25: 19.5 | AA25: 19.5 | AB25: 0 | AC25: 19.5 | AD25: 0
A26: Barley | B26: Delivered to 1 dairymaid from the purification until Michaelmas, 2 quarters 6.5 bushels, taking a quarter every 12 weeks. | C26: 0 | D26: 0 | E26: 0 | F26: 0 | G26: 0 | H26: 0 | I26: 0 | J26: 0 | K26: 0 | L26: 0 | M26: 0 | N26: 0 | O26: 0 | P26: 0 | Q26: 0 | R26: 0 | S26: 0 | T26: 0 | U26: 0 | V26: 0 | W26: 0 | X26: 2 | Y26: 6.5 | Z26: 2.8125 | AA26: 2.8125 | AB26: 0 | AC26: 2 | AD26: 6.5
A27: Barley | B27: Delivered to 1 keeper of lambs from the feast of St John the Baptist until Michaelmas, for 13 weeks, 1 qr 1 bushels {Henceforth the keeper of lambs should take for 12 weeks} Sold, 23 quarters 2 bushels Sold at the audit, 5.5 bushels | C27: 0 | D27: 0 | E27: 0 | F27: 0 | G27: 0 | H27: 0 | I27: 0 | J27: 0 | K27: 0 | L27: 0 | M27: 0 | N27: 0 | O27: 0 | P27: 0 | Q27: 23 | R27: 2 | S27: 23.25 | T27: 0 | U27: 0 | V27: 0 | W27: 0
A28: Barley | B28: Total | C28: 0 | D28: 0 | E28: 0 | F28: 0 | G28: 0 | H28: 0 | I28: 0 | J28: 0 | K28: 0 | L28: 0 | M28: 0 | N28: 0 | O28: 0 | P28: 0 | Q28: 0 | R28: 0 | S28: 0 | T28: 0 | U28: 0 | V28: 0 | W28: 0
A29: Oats | B29: (yield: two-fold plus 7 bushels) | C29: 0 | D29: 0 | E29: 0 | F29: 0 | G29: 0 | H29: 0 | I29: 0 | J29: 0 | K29: 0 | L29: 0 | M29: 0 | N29: 0 | O29: 0 | P29: 0 | Q29: 0 | R29: 0 | S29: 0 | T29: 0 | U29: 0 | V29: 0 | W29: 0 | X29: 0 | Y29: 7 | Z29: 0.875 | AA29: 0.875 | AB29: 0 | AC29: 0 | AD29: 7
A30: Oats | B30: The same render account for 160 quarters 7 bushels from the whole issue of oats by struck measure. | C30: 0 | D30: 0 | E30: 0 | F30: 0 | G30: 0 | H30: 0 | I30: 0 | J30: 0 | K30: 0 | L30: 0 | M30: 0 | N30: 0 | O30: 0 | P30: 0 | Q30: 0 | R30: 0 | S30: 0 | T30: 160 | U30: 7 | V30: 160.875 | W30: 0 | X30: 160 | Y30: 7 | Z30: 160.875 | AA30: 160.875 | AB30: 0 | AC30: 160 | AD30: 7
A31: Oats | B31: 18 quarters by estimation in sheaves. | C31: 0 | D31: 0 | E31: 0 | F31: 0 | G31: 0 | H31: 0 | I31: 0 | J31: 0 | K31: 0 | L31: 0 | M31: 0 | N31: 0 | O31: 0 | P31: 0 | Q31: 0 | R31: 0 | S31: 0 | T31: 0 | U31: 0 | V31: 0 | W31: 0 | X31: 18 | Y31: 0 | Z31: 18 | AA31: 18 | AB31: 0 | AC31: 18 | AD31: 0
A32: Oats | B32: Total, 178 quarters 7 bushels | C32: 0 | D32: 0 | E32: 0 | F32: 0 | G32: 0 | H32: 0 | I32: 0 | J32: 0 | K32: 0 | L32: 0 | M32: 0 | N32: 0 | O32: 0 | P32: 0 | Q32: 0 | R32: 0 | S32: 0 | T32: 0 | U32: 0 | V32: 0 | W32: 0 | X32: 178 | Y32: 7 | Z32: 178.875 | AA32: 178.875 | AB32: 0 | AC32: 178 | AD32: 7
A33: Oats | B33: Sown over 131 acres and 1 rood which lie at la Worth', Brechlond' and la Vyneys, 82 quarters. | C33: 0 | D33: 0 | E33: 82 | F33: 0 | G33: 82 | H33: 0 | I33: 0 | J33: 0 | K33: 0 | L33: 0 | M33: 0 | N33: 0 | O33: 0 | P33: 0 | Q33: 0 | R33: 0 | S33: 0 | T33: 0 | U33: 0 | V33: 0 | W33: 0 | X33: 82 | Y33: 0 | Z33: 82 | AA33: 82 | AB33: 0 | AC33: 82 | AD33: 0
A34: Oats | B34: that is, 5 bushels an acre. | C34: 0 | D34: 0 | E34: 0 | F34: 0 | G34: 0 | H34: 0 | I34: 0 | J34: 0 | K34: 0 | L34: 0 | M34: 0 | N34: 0 | O34: 0 | P34: 0 | Q34: 0 | R34: 0 | S34: 0 | T34: 0 | U34: 0 | V34: 0 | W34: 0 | X34: 0 | Y34: 5 | Z34: 0.625 | AA34: 0.625 | AB34: 0 | AC34: 0 | AD34: 5
A35: Oats | B35: . | C35: 0 | D35: 0 | E35: 0 | F35: 0 | G35: 0 | H35: 0 | I35: 0 | J35: 0 | K35: 0 | L35: 0 | M35: 0 | N35: 0 | O35: 0 | P35: 0 | Q35: 0 | R35: 0 | S35: 0 | T35: 0 | U35: 0 | V35: 0 | W35: 0 | X35: 0 | Y35: 0 | Z35: 0 | AA35: 0 | AB35: 0 | AC35: 0 | AD35: 0
A36: Oats | B36: . | C36: 0 | D36: 0 | E36: 0 | F36: 0 | G36: 0 | H36: 0 | I36: 0 | J36: 0 | K36: 0 | L36: 0 | M36: 0 | N36: 0 | O36: 0 | P36: 0 | Q36: 0 | R36: 0 | S36: 0 | T36: 0 | U36: 0 | V36: 0 | W36: 0 | X36: 0 | Y36: 0 | Z36: 0 | AA36: 0 | AB36: 0 | AC36: 0 | AD36: 0
A37: Oats | B37: . | C37: 0 | D37: 0 | E37: 0 | F37: 0 | G37: 0 | H37: 0 | I37: 0 | J37: 0 | K37: 0 | L37: 0 | M37: 0 | N37: 0 | O37: 0 | P37: 0 | Q37: 0 | R37: 0 | S37: 0 | T37: 0 | U37: 0 | V37: 0 | W37: 0 | X37: 0 | Y37: 0 | Z37: 0 | AA37: 0 | AB37: 0 | AC37: 0 | AD37: 0
A38: Oats | B38: . | C38: 0 | D38: 0 | E38: 0 | F38: 0 | G38: 0 | H38: 0 | I38: 0 | J38: 0 | K38: 0 | L38: 0 | M38: 0 | N38: 0 | O38: 0 | P38: 0 | Q38: 0 | R38: 0 | S38: 0 | T38: 0 | U38: 0 | V38: 0 | W38: 0 | X38: 0 | Y38: 0 | Z38: 0 | AA38: 0 | AB38: 0 | AC38: 0 | AD38: 0
A39: Oats | B39: fodder of 2 cart-horses from Michaelmas until Lammas, because thereafter they were at the church, 19.5 quarters. | C39: 0 | D39: 0 | E39: 0 | F39: 0 | G39: 0 | H39: 0 | I39: 0 | J39: 0 | K39: 0 | L39: 0 | M39: 0 | N39: 19.5 | O39: 0 | P39: 19.5 | Q39: 0 | R39: 0 | S39: 0 | T39: 0 | U39: 0 | V39: 0 | W39: 0 | X39: 19.5 | Y39: 0 | Z39: 19.5 | AA39: 19.5 | AB39: 0 | AC39: 19.5 | AD39: 0
A40: Oats | B40: . | C40: 0 | D40: 0 | E40: 0 | F40: 0 | G40: 0 | H40: 0 | I40: 0 | J40: 0 | K40: 0 | L40: 0 | M40: 0 | N40: 0 | O40: 0 | P40: 0 | Q40: 0 | R40: 0 | S40: 0 | T40: 0 | U40: 0 | V40: 0 | W40: 0 | X40: 0 | Y40: 0 | Z40: 0 | AA40: 0 | AB40: 0 | AC40: 0 | AD40: 0
... A43: Oats | B43: . | C43: 0 | D43: 0 | E43: 0 | F43: 0 | G43: 0 | H43: 0 | I43: 0 | J43: 0 | K43: 0 | L43: 0 | M43: 0 | N43: 0 | O43: 0 | P43: 0 | Q43: 0 | R43: 0 | S43: 0 | T43: 0 | U43: 0 | V43: 0 | W43: 0 | X43: 0 | Y43: 0 | Z43: 0 | AA43: 0 | AB43: 0 | AC43: 0 | AD43: 0
A44: Oats | B44: fodder of 6 plough-horses from Christmas until the Invention of the Cross (3 May), 16 quarters, at 1 bushels a night. | C44: 0 | D44: 0 | E44: 0 | F44: 0 | G44: 0 | H44: 0 | I44: 0 | J44: 0 | K44: 0 | L44: 0 | M44: 0 | N44: 16 | O44: 0 | P44: 16 | Q44: 0 | R44: 0 | S44: 0 | T44: 0 | U44: 0 | V44: 0 | W44: 0 | X44: 16 | Y44: 1 | Z44: 16.125 | AA44: 16 | AB44: 0.125 | AC44: 16 | AD44: 0 | AE44: 0 | AF44: 1
A45: Oats | B45: . | C45: 0 | D45: 0 | E45: 0 | F45: 0 | G45: 0 | H45: 0 | I45: 0 | J45: 0 | K45: 0 | L45: 0 | M45: 0 | N45: 0 | O45: 0 | P45: 0 | Q45: 0 | R45: 0 | S45: 0 | T45: 0 | U45: 0 | V45: 0 | W45: 0 | X45: 0 | Y45: 0 | Z45: 0 | AA45: 0 | AB45: 0 | AC45: 0 | AD45: 0
A46: Oats | B46: . | C46: 0 | D46: 0 | E46: 0 | F46: 0 | G46: 0 | H46: 0 | I46: 0 | J46: 0 | K46: 0 | L46: 0 | M46: 0 | N46: 0 | O46: 0 | P46: 0 | Q46: 0 | R46: 0 | S46: 0 | T46: 0 | U46: 0 | V46: 0 | W46: 0 | X46: 0 | Y46: 0 | Z46: 0 | AA46: 0 | AB46: 0 | AC46: 0 | AD46: 0
A47: Oats | B47: . | C47: 0 | D47: 0 | E47: 0 | F47: 0 | G47: 0 | H47: 0 | I47: 0 | J47: 0 | K47: 0 | L47: 0 | M47: 0 | N47: 0 | O47: 0 | P47: 0 | Q47: 0 | R47: 0 | S47: 0 | T47: 0 | U47: 0 | V47: 0 | W47: 0 | X47: 0 | Y47: 0 | Z47: 0 | AA47: 0 | AB47: 0 | AC47: 0 | AD47: 0
A48: Oats | B48: . | C48: 0 | D48: 0 | E48: 0 | F48: 0 | G48: 0 | H48: 0 | I48: 0 | J48: 0 | K48: 0 | L48: 0 | M48: 0 | N48: 0 | O48: 0 | P48: 0 | Q48: 0 | R48: 0 | S48: 0 | T48: 0 | U48: 0 | V48: 0 | W48: 0 | X48: 0 | Y48: 0 | Z48: 0 | AA48: 0 | AB48: 0 | AC48: 0 | AD48: 0
A49: Oats | B49: fodder of the same when they ploughed after dinner, 6 quarters. | C49: 0 | D49: 0 | E49: 0 | F49: 0 | G49: 0 | H49: 0 | I49: 0 | J49: 0 | K49: 0 | L49: 0 | M49: 0 | N49: 6 | O49: 0 | P49: 6 | Q49: 0 | R49: 0 | S49: 0 | T49: 0 | U49: 0 | V49: 0 | W49: 0 | X49: 6 | Y49: 0 | Z49: 6 | AA49: 6 | AB49: 0 | AC49: 6 | AD49: 0
A50: Oats | B50: Given to oxen by estimation in sheaves, 18 quarters. | C50: 0 | D50: 0 | E50: 0 | F50: 0 | G50: 0 | H50: 0 | I50: 0 | J50: 0 | K50: 0 | L50: 0 | M50: 0 | N50: 0 | O50: 0 | P50: 0 | Q50: 0 | R50: 0 | S50: 0 | T50: 0 | U50: 0 | V50: 0 | W50: 0 | X50: 18 | Y50: 0 | Z50: 18 | AA50: 18 | AB50: 0 | AC50: 18 | AD50: 0
A51: Oats | B51: . | C51: 0 | D51: 0 | E51: 0 | F51: 0 | G51: 0 | H51: 0 | I51: 0 | J51: 0 | K51: 0 | L51: 0 | M51: 0 | N51: 0 | O51: 0 | P51: 0 | Q51: 0 | R51: 0 | S51: 0 | T51: 0 | U51: 0 | V51: 0 | W51: 0 | X51: 0 | Y51: 0 | Z51: 0 | AA51: 0 | AB51: 0 | AC51: 0 | AD51: 0
A52: Oats | B52: . | C52: 0 | D52: 0 | E52: 0 | F52: 0 | G52: 0 | H52: 0 | I52: 0 | J52: 0 | K52: 0 | L52: 0 | M52: 0 | N52: 0 | O52: 0 | P52: 0 | Q52: 0 | R52: 0 | S52: 0 | T52: 0 | U52: 0 | V52: 0 | W52: 0 | X52: 0 | Y52: 0 | Z52: 0 | AA52: 0 | AB52: 0 | AC52: 0 | AD52: 0
A53: Oats | B53: . | C53: 0 | D53: 0 | E53: 0 | F53: 0 | G53: 0 | H53: 0 | I53: 0 | J53: 0 | K53: 0 | L53: 0 | M53: 0 | N53: 0 | O53: 0 | P53: 0 | Q53: 0 | R53: 0 | S53: 0 | T53: 0 | U53: 0 | V53: 0 | W53: 0 | X53: 0 | Y53: 0 | Z53: 0 | AA53: 0 | AB53: 0 | AC53: 0 | AD53: 0
A54: Oats | B54: . | C54: 0 | D54: 0 | E54: 0 | F54: 0 | G54: 0 | H54: 0 | I54: 0 | J54: 0 | K54: 0 | L54: 0 | M54: 0 | N54: 0 | O54: 0 | P54: 0 | Q54: 0 | R54: 0 | S54: 0 | T54: 0 | U54: 0 | V54: 0 | W54: 0 | X54: 0 | Y54: 0 | Z54: 0 | AA54: 0 | AB54: 0 | AC54: 0 | AD54: 0
A55: Oats | B55: fodder of the horse of Simon, clerk, for 2 toums, 2 bushels. | C55: 0 | D55: 0 | E55: 0 | F55: 0 | G55: 0 | H55: 0 | I55: 0 | J55: 0 | K55: 0 | L55: 0 | M55: 0 | N55: 0 | O55: 0 | P55: 0 | Q55: 0 | R55: 0 | S55: 0 | T55: 0 | U55: 0 | V55: 0 | W55: 0 | X55: 0 | Y55: 2 | Z55: 0.25 | AA55: 0.25 | AB55: 0 | AC55: 0 | AD55: 2
A56: Oats | B56: fodder of the bailiff's horse for his visits, 3 quarters 2 bushels. | C56: 0 | D56: 0 | E56: 0 | F56: 0 | G56: 0 | H56: 0 | I56: 0 | J56: 0 | K56: 0 | L56: 0 | M56: 0 | N56: 3 | O56: 2 | P56: 3.25 | Q56: 0 | R56: 0 | S56: 0 | T56: 0 | U56: 0 | V56: 0 | W56: 0 | X56: 3 | Y56: 2 | Z56: 3.25 | AA56: 3.25 | AB56: 0 | AC56: 3 | AD56: 2
A57: Oats | B57: threshing and winnowing 129 quarters according to custom, 2 quarters 3 bushels, at 1 dish (discum) for 12 bushels, whereof 6 dishes make 1 bushel. | C57: 0 | D57: 0 | E57: 0 | F57: 0 | G57: 0 | H57: 0 | I57: 0 | J57: 0 | K57: 0 | L57: 0 | M57: 0 | N57: 0 | O57: 0 | P57: 0 | Q57: 0 | R57: 0 | S57: 0 | T57: 0 | U57: 0 | V57: 0 | W57: 0 | X57: 2 | Y57: 15 | Z57: 3.875 | AA57: 129 | AB57: -125.125 | AC57: 129 | AD57: 0 | AE57: 2 | AF57: 3 | AG57: 0 | AH57: 12
A58: Oats | B58: Sold, 31.5 quarters. | C58: 0 | D58: 0 | E58: 0 | F58: 0 | G58: 0 | H58: 0 | I58: 0 | J58: 0 | K58: 0 | L58: 0 | M58: 0 | N58: 0 | O58: 0 | P58: 0 | Q58: 31.5 | R58: 0 | S58: 31.5 | T58: 0 | U58: 0 | V58: 0 | W58: 0 | X58: 31.5 | Y58: 0 | Z58: 31.5 | AA58: 31.5 | AB58: 0 | AC58: 31.5 | AD58: 0
A59: Oats | B59: Total | C59: 0 | D59: 0 | E59: 0 | F59: 0 | G59: 0 | H59: 0 | I59: 0 | J59: 0 | K59: 0 | L59: 0 | M59: 0 | N59: 0 | O59: 0 | P59: 0 | Q59: 0 | R59: 0 | S59: 0 | T59: 0 | U59: 0 | V59: 0 | W59: 0
A60: Peas | B60: {yield: 4-fold plus 2 bushels) | C60: 0 | D60: 0 | E60: 0 | F60: 0 | G60: 0 | H60: 0 | I60: 0 | J60: 0 | K60: 0 | L60: 0 | M60: 0 | N60: 0 | O60: 0 | P60: 0 | Q60: 0 | R60: 0 | S60: 0 | T60: 0 | U60: 0 | V60: 0 | W60: 0 | X60: 0 | Y60: 2 | Z60: 0.25 | AA60: 0.25 | AB60: 0 | AC60: 0 | AD60: 2
A61: Peas | B61: The same render account for 4 quarters 2 bushels from the whole issue of peas by struck measure. | C61: 0 | D61: 0 | E61: 0 | F61: 0 | G61: 0 | H61: 0 | I61: 0 | J61: 0 | K61: 0 | L61: 0 | M61: 0 | N61: 0 | O61: 0 | P61: 0 | Q61: 0 | R61: 0 | S61: 0 | T61: 4 | U61: 2 | V61: 4.25 | W61: 0 | X61: 4 | Y61: 2 | Z61: 4.25 | AA61: 4.25 | AB61: 0 | AC61: 4 | AD61: 2
A62: Peas | B62: 1.5 quarters remaining from the previous year in the granary. | C62: 0 | D62: 0 | E62: 0 | F62: 0 | G62: 0 | H62: 0 | I62: 0 | J62: 0 | K62: 0 | L62: 0 | M62: 0 | N62: 0 | O62: 0 | P62: 0 | Q62: 0 | R62: 0 | S62: 0 | T62: 0 | U62: 0 | V62: 0 | W62: 0 | X62: 1.5 | Y62: 0 | Z62: 1.5 | AA62: 1.5 | AB62: 0 | AC62: 1.5 | AD62: 0
A63: Peas | B63: 1 qr remaining by estimation in the stack. | C63: 0 | D63: 0 | E63: 0 | F63: 0 | G63: 0 | H63: 0 | I63: 0 | J63: 0 | K63: 0 | L63: 0 | M63: 0 | N63: 0 | O63: 0 | P63: 0 | Q63: 0 | R63: 0 | S63: 0 | T63: 0 | U63: 0 | V63: 0 | W63: 0
A64: Peas | B64: Total, 6 quarters 6 bushels | C64: 0 | D64: 0 | E64: 0 | F64: 0 | G64: 0 | H64: 0 | I64: 0 | J64: 0 | K64: 0 | L64: 0 | M64: 0 | N64: 0 | O64: 0 | P64: 0 | Q64: 0 | R64: 0 | S64: 0 | T64: 0 | U64: 0 | V64: 0 | W64: 0 | X64: 6 | Y64: 6 | Z64: 6.75 | AA64: 6.75 | AB64: 0 | AC64: 6 | AD64: 6
A65: Peas | B65: Sown, 2 bushels Sold, 5 quarters. | C65: 0 | D65: 0 | E65: 5 | F65: 0 | G65: 5 | H65: 0 | I65: 0 | J65: 0 | K65: 0 | L65: 0 | M65: 0 | N65: 0 | O65: 0 | P65: 0 | Q65: 5 | R65: 0 | S65: 5 | T65: 0 | U65: 0 | V65: 0 | W65: 0 | X65: 5 | Y65: 2 | Z65: 5.25 | AA65: 0.25 | AB65: 5 | AC65: 0 | AD65: 2 | AE65: 5 | AF65: 0
A66: Peas | B66: . | C66: 0 | D66: 0 | E66: 0 | F66: 0 | G66: 0 | H66: 0 | I66: 0 | J66: 0 | K66: 0 | L66: 0 | M66: 0 | N66: 0 | O66: 0 | P66: 0 | Q66: 0 | R66: 0 | S66: 0 | T66: 0 | U66: 0 | V66: 0 | W66: 0 | X66: 0 | Y66: 0 | Z66: 0 | AA66: 0 | AB66: 0 | AC66: 0 | AD66: 0
A67: Peas | B67: fattening pigs for sale, 1.5 quarters. | C67: 0 | D67: 0 | E67: 0 | F67: 0 | G67: 0 | H67: 0 | I67: 0 | J67: 0 | K67: 0 | L67: 0 | M67: 0 | N67: 0 | O67: 0 | P67: 0 | Q67: 0 | R67: 0 | S67: 0 | T67: 0 | U67: 0 | V67: 0 | W67: 0 | X67: 1.5 | Y67: 0 | Z67: 1.5 | AA67: 1.5 | AB67: 0 | AC67: 1.5 | AD67: 0
A68: Peas | B68: Total | C68: 0 | D68: 0 | E68: 0 | F68: 0 | G68: 0 | H68: 0 | I68: 0 | J68: 0 | K68: 0 | L68: 0 | M68: 0 | N68: 0 | O68: 0 | P68: 0 | Q68: 0 | R68: 0 | S68: 0 | T68: 0 | U68: 0 | V68: 0 | W68: 0
A69: Vetches | B69: {yield: 4-fold} | C69: 0 | D69: 0 | E69: 0 | F69: 0 | G69: 0 | H69: 0 | I69: 0 | J69: 0 | K69: 0 | L69: 0 | M69: 0 | N69: 0 | O69: 0 | P69: 0 | Q69: 0 | R69: 0 | S69: 0 | T69: 0 | U69: 0 | V69: 0 | W69: 0 | X69: 0 | Y69: 0 | Z69: 0 | AA69: 0 | AB69: 0 | AC69: 0 | AD69: 0
A70: Vetches | B70: The same render account for 4 quarters 2 bushels from the issue of vetches remaining in the stack from the previous year. | C70: 0 | D70: 0 | E70: 0 | F70: 0 | G70: 0 | H70: 0 | I70: 0 | J70: 0 | K70: 0 | L70: 0 | M70: 0 | N70: 0 | O70: 0 | P70: 0 | Q70: 0 | R70: 0 | S70: 0 | T70: 4 | U70: 2 | V70: 4.25 | W70: 0 | X70: 4 | Y70: 2 | Z70: 4.25 | AA70: 4.25 | AB70: 0 | AC70: 4 | AD70: 2
A71: Vetches | B71: 4 quarters from this year's issue. | C71: 0 | D71: 0 | E71: 0 | F71: 0 | G71: 0 | H71: 0 | I71: 0 | J71: 0 | K71: 0 | L71: 0 | M71: 0 | N71: 0 | O71: 0 | P71: 0 | Q71: 0 | R71: 0 | S71: 0 | T71: 0 | U71: 0 | V71: 0 | W71: 0 | X71: 4 | Y71: 0 | Z71: 4 | AA71: 4 | AB71: 0 | AC71: 4 | AD71: 0
A72: Vetches | B72: Total, 8 quarters 2 bushels All solpence | C72: 0 | D72: 0 | E72: 0 | F72: 0 | G72: 0 | H72: 0 | I72: 0 | J72: 0 | K72: 0 | L72: 0 | M72: 0 | N72: 0 | O72: 0 | P72: 0 | Q72: 0 | R72: 0 | S72: 0 | T72: 0 | U72: 0 | V72: 0 | W72: 0 | X72: 8 | Y72: 2 | Z72: 8.25 | AA72: 8.25 | AB72: 0 | AC72: 8 | AD72: 2

Sheet Sale of Corn Prices
A1: Heading | B1: Sentence | C1: Total in Pounds | D1: Pounds | E1: Shillings | F1: Pence | G1: Corn | H1: Total Quarters Except 1 | I1: Total Bushels Except 1 | J1: Total Corn Cross-Check | K1: Total Corn Manorial Account | L1: Corn Quantity Error | M1: Quarters 0 | N1: Bushels 0 | O1: shilling a quarter 1 | P1: pence a quarter 1 | Q1: Quarters 1 | R1: Bushels 1 | S1: shilling a quarter 2 | T1: pence a quarter 2 | U1: Quarters 2 | V1: Bushels 2 | W1: shilling a quarter 3 | X1: pence a quarter 3 | Y1: shilling a quarter 4 | Z1: pence a quarter 4 | AA1: £ a quarter 1 | AB1: £ a quarter 2 | AC1: £ a quarter 3 | AD1: £ a quarter 4 | AE1: Quarters Sold | AF1: Weighted Average Price per Quarter | AG1: Non-Weighted Average Price per Quarter | AH1: Corn lowercase
A2: Sale of corn | B2: The same render account for £12 14 shilling 3pence from 45 quarters 6 bushels of wheat sold, at 5 shilling a quarters for 20 quarters 2 bushels, and 6 shilling a quarters for 25.5 quarters. | C2: 12.71 | D2: 12 | E2: 14 | F2: 3 | G2: wheat | H2: 45.5 | I2: 2 | J2: 45.75 | K2: 45.75 | L2: 0 | M2: 45 | N2: 6 | O2: 5 | P2: 0 | Q2: 20 | R2: 2 | S2: 6 | T2: 0 | U2: 25.5 | V2: 0 | AA2: 0.25 | AB2: 0.3 | AE2: 45.75 | AF2: 0.27786885 | AG2: 0.275 | AH2: wheat
A3: Sale of corn | B3: £1 15 shilling from 13 quarters 1 bushels of curall sold, at 2 shilling 8pence a quarters. | C3: 1.75 | D3: 1 | E3: 15 | F3: 0 | G3: curall | H3: 13 | I3: 1 | J3: 13.125 | K3: 13.125 | L3: 0 | M3: 13 | N3: 1 | O3: 2 | P3: 8 | AA3: 0.13333333 | AE3: 13.125 | AF3: 0.13333333 | AG3: 0.13333333 | AH3: curall
A4: Sale of corn | B4: £4 13 shilling from 23 quarters 2 bushels of barley sold, at 4 shilling a quarters. | C4: 4.65 | D4: 4 | E4: 13 | F4: 0 | G4: barley | H4: 23 | I4: 2 | J4: 23.25 | K4: 23.25 | L4: 0 | M4: 23 | N4: 2 | O4: 4 | P4: 0 | AA4: 0.2 | AE4: 23.25 | AF4: 0.2 | AG4: 0.2 | AH4: barley
A5: Sale of corn | B5: £3 5 shilling 9.5pence from 31.5 quarters of oats sold, at 2 shilling a quarters for 14 quarters 6 bushels, and 2 shilling 2pence a quarters for 16 quarters 6 bushels. | C5: 3.29 | D5: 3 | E5: 5 | F5: 9.5 | G5: oats | H5: 30 | I5: 12 | J5: 31.5 | K5: 31.5 | L5: 0 | M5: 31.5 | N5: 0 | O5: 2 | P5: 0 | Q5: 14 | R5: 6 | S5: 2 | T5: 2 | U5: 16 | V5: 6 | AA5: 0.1 | AB5: 0.10833333 | AE5: 31.5 | AF5: 0.10443122 | AG5: 0.10416667 | AH5: oats
A6: Sale of corn | B6: 12 shilling 6pence from 5 quarters of peas sold, at 2 shilling 6pence a quarters. | C6: 0.62 | D6: 0 | E6: 12 | F6: 6 | G6: peas | H6: 5 | I6: 0 | J6: 5 | K6: 5 | L6: 0 | M6: 5 | N6: 0 | O6: 2 | P6: 6 | AA6: 0.125 | AE6: 5 | AF6: 0.125 | AG6: 0.125 | AH6: peas
A7: Sale of corn | B7: 16 shilling 6pence from 8 quarters of vetches sold, at 2 shilling a quarters. | C7: 0.83 | D7: 0 | E7: 16 | F7: 6 | G7: vetches | H7: 8 | I7: 0 | J7: 8 | K7: 8 | L7: 0 | M7: 8 | N7: 0 | O7: 2 | P7: 0 | AA7: 0.1 | AE7: 8 | AF7: 0.1 | AG7: 0.1 | AH7: vetches
A8: Sale of corn | B8: 3 shilling 4.5pence from 4.5 bushels of wheat sold at the audit. | C8: 0.17 | D8: 0 | E8: 3 | F8: 4.5 | G8: wheat | H8: 0 | I8: 4.5 | J8: 0.5625 | K8: 0.5625 | L8: 0 | M8: 0 | N8: 4.5 | AA8: 0.30222222 | AE8: 0.5625 | AF8: 0.30222222 | AG8: 0.30222222 | AH8: wheat
A9: Sale of corn | B9: 2 shilling 9pence from 5.5 bushels of barley sold at the audit. | C9: 0.14 | D9: 0 | E9: 2 | F9: 9 | G9: barley | H9: 0 | I9: 5.5 | J9: 0.6875 | K9: 0.6875 | L9: 0 | M9: 0 | N9: 5.5 | AA9: 0.20363636 | AE9: 0.6875 | AF9: 0.20363636 | AG9: 0.20363636 | AH9: barley
A10: Sale of corn | B10: Total, £24 3 shilling 2pence | C10: 24.16 | D10: 24 | E10: 3 | F10: 2 | H10: 0 | I10: 0 | J10: 0 | K10: 0 | L10: 0 | M10: 0 | N10: 0 | AA10: inf | AE10: 0 | AF10: inf | AG10: inf
