Workbook

Sheet Overton Borough Overview
A1: OVERTON BOROUGH | B1: £ | C1: s | D1: d | G1: Total in £ | H1: Error
A3: CASH ACCOUNT
A4: RECEIPTS
A5: Arrears total | G5: =IF(INDEX('Overton Borough Receipts'!$A$4:$F$70,MATCH('Overton Borough Overview'!$A5,'Overton Borough Receipts'!$A$4:$A$70,0),6)=0,"",INDEX('Overton Borough Receipts'!$A$4:$F$70,MATCH('Overton Borough Overview'!$A5,'Overton Borough Receipts'!$A$4:$A$70,0),6)) -> 2.0604167
A6: Rents of assize total | G6: =IF(INDEX('Overton Borough Receipts'!$A$4:$F$70,MATCH('Overton Borough Overview'!$A6,'Overton Borough Receipts'!$A$4:$A$70,0),6)=0,"",INDEX('Overton Borough Receipts'!$A$4:$F$70,MATCH('Overton Borough Overview'!$A6,'Overton Borough Receipts'!$A$4:$A$70,0),6)) -> 8.2145833
A7: Quittances total | G7: =IF(INDEX('Overton Borough Receipts'!$A$4:$F$70,MATCH('Overton Borough Overview'!$A7,'Overton Borough Receipts'!$A$4:$A$70,0),6)=0,"",INDEX('Overton Borough Receipts'!$A$4:$F$70,MATCH('Overton Borough Overview'!$A7,'Overton Borough Receipts'!$A$4:$A$70,0),6)) -> 0.1
A8: Defaults of rent total | G8: =IF(INDEX('Overton Borough Receipts'!$A$4:$F$70,MATCH('Overton Borough Overview'!$A8,'Overton Borough Receipts'!$A$4:$A$70,0),6)=0,"",INDEX('Overton Borough Receipts'!$A$4:$F$70,MATCH('Overton Borough Overview'!$A8,'Overton Borough Receipts'!$A$4:$A$70,0),6)) -> 0.025
A9: Annual recognizances total | G9: =IF(INDEX('Overton Borough Receipts'!$A$4:$F$70,MATCH('Overton Borough Overview'!$A9,'Overton Borough Receipts'!$A$4:$A$70,0),6)=0,"",INDEX('Overton Borough Receipts'!$A$4:$F$70,MATCH('Overton Borough Overview'!$A9,'Overton Borough Receipts'!$A$4:$A$70,0),6)) -> 0.025
A10: Issues of the Manor total | G10: =IF(INDEX('Overton Borough Receipts'!$A$4:$F$70,MATCH('Overton Borough Overview'!$A10,'Overton Borough Receipts'!$A$4:$A$70,0),6)=0,"",INDEX('Overton Borough Receipts'!$A$4:$F$70,MATCH('Overton Borough Overview'!$A10,'Overton Borough Receipts'!$A$4:$A$70,0),6)) -> 0.8
A11: Sale of corn total | G11: ='Overton Borough Receipts'!F44 -> 0
A12: Entry and marriage fines total | G12: =IF(INDEX('Overton Borough Receipts'!$A$4:$F$70,MATCH('Overton Borough Overview'!$A12,'Overton Borough Receipts'!$A$4:$A$70,0),6)=0,"",INDEX('Overton Borough Receipts'!$A$4:$F$70,MATCH('Overton Borough Overview'!$A12,'Overton Borough Receipts'!$A$4:$A$70,0),6))
A13: Pleas & perquisites total | G13: =IF(INDEX('Overton Borough Receipts'!$A$4:$F$70,MATCH('Overton Borough Overview'!$A13,'Overton Borough Receipts'!$A$4:$A$70,0),6)=0,"",INDEX('Overton Borough Receipts'!$A$4:$F$70,MATCH('Overton Borough Overview'!$A13,'Overton Borough Receipts'!$A$4:$A$70,0),6)) -> 3.2625
A14: Sum of the above (incl. arrears) | G14: =SUM(G5:G13)-SUM(G7:G8) -> 14.3625
A15: Total recorded in the accounts excl. arrears | G15: ='Overton Borough Receipts'!F69 -> 12.675 | H15: =G14-G15 -> 1.6875
A16: Total recorded in the accounts incl. arrears | G16: ='Overton Borough Receipts'!F70 -> 0
A19: EXPENSES
A20: Cost of ploughs total | G20: =IF(INDEX('Overton Borough Expenses'!$A$2:$F$120,MATCH('Overton Borough Overview'!$A20,'Overton Borough Expenses'!$A$2:$A$120,0),6)=0,"",INDEX('Overton Borough Expenses'!$A$2:$F$120,MATCH('Overton Borough Overview'!$A20,'Overton Borough Expenses'!$A$2:$A$120,0),6))
A21: Purchase of corn total | G21: =IF(INDEX('Overton Borough Expenses'!$A$2:$F$120,MATCH('Overton Borough Overview'!$A21,'Overton Borough Expenses'!$A$2:$A$120,0),6)=0,"",INDEX('Overton Borough Expenses'!$A$2:$F$120,MATCH('Overton Borough Overview'!$A21,'Overton Borough Expenses'!$A$2:$A$120,0),6))
A22: Cost of carts and wagons total | G22: =IF(INDEX('Overton Borough Expenses'!$A$2:$F$120,MATCH('Overton Borough Overview'!$A22,'Overton Borough Expenses'!$A$2:$A$120,0),6)=0,"",INDEX('Overton Borough Expenses'!$A$2:$F$120,MATCH('Overton Borough Overview'!$A22,'Overton Borough Expenses'!$A$2:$A$120,0),6))
A23: Cost of dairy total | G23: =IF(INDEX('Overton Borough Expenses'!$A$2:$F$120,MATCH('Overton Borough Overview'!$A23,'Overton Borough Expenses'!$A$2:$A$120,0),6)=0,"",INDEX('Overton Borough Expenses'!$A$2:$F$120,MATCH('Overton Borough Overview'!$A23,'Overton Borough Expenses'!$A$2:$A$120,0),6))
A24: Purchase of stock total | G24: =IF(INDEX('Overton Borough Expenses'!$A$2:$F$120,MATCH('Overton Borough Overview'!$A24,'Overton Borough Expenses'!$A$2:$A$120,0),6)=0,"",INDEX('Overton Borough Expenses'!$A$2:$F$120,MATCH('Overton Borough Overview'!$A24,'Overton Borough Expenses'!$A$2:$A$120,0),6))
A25: Sheepcote total | G25: =IF(INDEX('Overton Borough Expenses'!$A$2:$F$120,MATCH('Overton Borough Overview'!$A25,'Overton Borough Expenses'!$A$2:$A$120,0),6)=0,"",INDEX('Overton Borough Expenses'!$A$2:$F$120,MATCH('Overton Borough Overview'!$A25,'Overton Borough Expenses'!$A$2:$A$120,0),6))
A26: Cost of buildings total | G26: =IF(INDEX('Overton Borough Expenses'!$A$2:$F$120,MATCH('Overton Borough Overview'!$A26,'Overton Borough Expenses'!$A$2:$A$120,0),6)=0,"",INDEX('Overton Borough Expenses'!$A$2:$F$120,MATCH('Overton Borough Overview'!$A26,'Overton Borough Expenses'!$A$2:$A$120,0),6)) -> 0.25833333
A27: Threshing total | G27: =IF(INDEX('Overton Borough Expenses'!$A$2:$F$120,MATCH('Overton Borough Overview'!$A27,'Overton Borough Expenses'!$A$2:$A$120,0),6)=0,"",INDEX('Overton Borough Expenses'!$A$2:$F$120,MATCH('Overton Borough Overview'!$A27,'Overton Borough Expenses'!$A$2:$A$120,0),6))
A28: Expenses of the harvest total | G28: =IF(INDEX('Overton Borough Expenses'!$A$2:$F$120,MATCH('Overton Borough Overview'!$A28,'Overton Borough Expenses'!$A$2:$A$120,0),6)=0,"",INDEX('Overton Borough Expenses'!$A$2:$F$120,MATCH('Overton Borough Overview'!$A28,'Overton Borough Expenses'!$A$2:$A$120,0),6))
A29: Steward's expenses total | G29: =IF(INDEX('Overton Borough Expenses'!$A$2:$F$120,MATCH('Overton Borough Overview'!$A29,'Overton Borough Expenses'!$A$2:$A$120,0),6)=0,"",INDEX('Overton Borough Expenses'!$A$2:$F$120,MATCH('Overton Borough Overview'!$A29,'Overton Borough Expenses'!$A$2:$A$120,0),6))
A30: Sum of the above | G30: =SUM(G20:G29) -> 0.25833333
A31: Total of all expenses | G31: ='Overton Borough Expenses'!F115 -> 0 | H31: =G30-G31 -> 0.25833333
A32: Capital Expenses | G32: ='Overton Borough Expenses'!F120 -> 0.10416667
A34: Owed by the reeve
A35: From accounts
A37: Cash deliveries
A38: Total of all allowances and cash deliveries in accounts | B38: n/a
A40: Net amount owed
A41: Net amount owed in accounts | H41: =G40-G41 -> 0
A43: GRANGE ACCOUNT | B43: Net Production
A44: Grange | B44: qrs | G44: £ | I44: Note: Columns indexed are hardcoded, do not alter number of columns in issues of grange
A45: Net wheat | B45: =IF(INDEX('Issues of the Grange'!$A$2:$P$24,MATCH('Overton Borough Overview'!$A45,'Issues of the Grange'!$A$2:$A$24,0),10)=0,"",INDEX('Issues of the Grange'!$A$2:$P$24,MATCH('Overton Borough Overview'!$A45,'Issues of the Grange'!$A$2:$A$24,0),10)) -> #N/A | G45: =IF(INDEX('Issues of the Grange'!$A$2:$P$24,MATCH('Overton Borough Overview'!$A45,'Issues of the Grange'!$A$2:$A$24,0),13)=0,"",INDEX('Issues of the Grange'!$A$2:$P$24,MATCH('Overton Borough Overview'!$A45,'Issues of the Grange'!$A$2:$A$24,0),13)) -> #N/A
A46: Net curall | B46: =IF(INDEX('Issues of the Grange'!$A$2:$P$24,MATCH('Overton Borough Overview'!$A46,'Issues of the Grange'!$A$2:$A$24,0),10)=0,"",INDEX('Issues of the Grange'!$A$2:$P$24,MATCH('Overton Borough Overview'!$A46,'Issues of the Grange'!$A$2:$A$24,0),10)) -> #N/A | G46: =IF(INDEX('Issues of the Grange'!$A$2:$P$24,MATCH('Overton Borough Overview'!$A46,'Issues of the Grange'!$A$2:$A$24,0),13)=0,"",INDEX('Issues of the Grange'!$A$2:$P$24,MATCH('Overton Borough Overview'!$A46,'Issues of the Grange'!$A$2:$A$24,0),13)) -> #N/A
A47: Net barley | B47: =IF(INDEX('Issues of the Grange'!$A$2:$P$24,MATCH('Overton Borough Overview'!$A47,'Issues of the Grange'!$A$2:$A$24,0),10)=0,"",INDEX('Issues of the Grange'!$A$2:$P$24,MATCH('Overton Borough Overview'!$A47,'Issues of the Grange'!$A$2:$A$24,0),10)) -> #N/A | G47: =IF(INDEX('Issues of the Grange'!$A$2:$P$24,MATCH('Overton Borough Overview'!$A47,'Issues of the Grange'!$A$2:$A$24,0),13)=0,"",INDEX('Issues of the Grange'!$A$2:$P$24,MATCH('Overton Borough Overview'!$A47,'Issues of the Grange'!$A$2:$A$24,0),13)) -> #N/A
A48: Net oats | B48: =IF(INDEX('Issues of the Grange'!$A$2:$P$24,MATCH('Overton Borough Overview'!$A48,'Issues of the Grange'!$A$2:$A$24,0),10)=0,"",INDEX('Issues of the Grange'!$A$2:$P$24,MATCH('Overton Borough Overview'!$A48,'Issues of the Grange'!$A$2:$A$24,0),10)) -> #N/A | G48: =IF(INDEX('Issues of the Grange'!$A$2:$P$24,MATCH('Overton Borough Overview'!$A48,'Issues of the Grange'!$A$2:$A$24,0),13)=0,"",INDEX('Issues of the Grange'!$A$2:$P$24,MATCH('Overton Borough Overview'!$A48,'Issues of the Grange'!$A$2:$A$24,0),13)) -> #N/A
A49: Net peas | B49: =IF(INDEX('Issues of the Grange'!$A$2:$P$24,MATCH('Overton Borough Overview'!$A49,'Issues of the Grange'!$A$2:$A$24,0),10)=0,"",INDEX('Issues of the Grange'!$A$2:$P$24,MATCH('Overton Borough Overview'!$A49,'Issues of the Grange'!$A$2:$A$24,0),10)) -> #N/A | G49: =IF(INDEX('Issues of the Grange'!$A$2:$P$24,MATCH('Overton Borough Overview'!$A49,'Issues of the Grange'!$A$2:$A$24,0),13)=0,"",INDEX('Issues of the Grange'!$A$2:$P$24,MATCH('Overton Borough Overview'!$A49,'Issues of the Grange'!$A$2:$A$24,0),13)) -> #N/A
A50: Net vetches | B50: =IF(INDEX('Issues of the Grange'!$A$2:$P$24,MATCH('Overton Borough Overview'!$A50,'Issues of the Grange'!$A$2:$A$24,0),10)=0,"",INDEX('Issues of the Grange'!$A$2:$P$24,MATCH('Overton Borough Overview'!$A50,'Issues of the Grange'!$A$2:$A$24,0),10)) -> #N/A | G50: =IF(INDEX('Issues of the Grange'!$A$2:$P$24,MATCH('Overton Borough Overview'!$A50,'Issues of the Grange'!$A$2:$A$24,0),13)=0,"",INDEX('Issues of the Grange'!$A$2:$P$24,MATCH('Overton Borough Overview'!$A50,'Issues of the Grange'!$A$2:$A$24,0),13)) -> #N/A
A51: Net value of production (sum of the above) | G51: =SUM(G45:G50) -> #N/A
A52: Value of sales | G52: ='Issues of the Grange'!N24 -> 0
A54: MILL ACCOUNT | B54: n/a
A55: Issues of the mill | B55: qrs | C55: bus | G55: £
A56: Wheat
A57: Oatmeal
A58: 1st grade malt
A59: 2nd grade malt
A60: Maslin
A61: Total value of production (sum of the above)
A62: Value of sales | G62: 0
A64: STOCK ACCOUNT
A65: Livestock | B65: Inherited stock | C65: End-period stock | D65: Stockbuilding | F65: Sales in (£) | G65: Value of production (£) at sales prices
A66: Cart-horses | B66: =IFERROR(INDEX(Stock!$A$3:$T$90,MATCH('Overton Borough Overview'!$A66,Stock!$A$3:$A$90,0),MATCH('Overton Borough Overview'!B$65,Stock!$A$3:$T$3,0)),0) -> 0 | C66: =IFERROR(INDEX(Stock!$A$3:$T$90,MATCH('Overton Borough Overview'!$A66,Stock!$A$3:$A$90,0),MATCH('Overton Borough Overview'!C$65,Stock!$A$3:$T$3,0)),0) -> 0 | D66: =C66-B66 -> 0 | F66: =IFERROR(INDEX(Stock!$A$3:$T$90,MATCH('Overton Borough Overview'!$A66,Stock!$A$3:$A$90,0),MATCH('Overton Borough Overview'!F$65,Stock!$A$3:$T$3,0)),0) -> 0 | G66: =IFERROR(INDEX(Stock!$A$3:$T$90,MATCH('Overton Borough Overview'!$A66,Stock!$A$3:$A$90,0),MATCH('Overton Borough Overview'!G$65,Stock!$A$3:$T$3,0)),0) -> 0
A67: Mares | B67: =IFERROR(INDEX(Stock!$A$3:$T$90,MATCH('Overton Borough Overview'!$A67,Stock!$A$3:$A$90,0),MATCH('Overton Borough Overview'!B$65,Stock!$A$3:$T$3,0)),0) -> 0 | C67: =IFERROR(INDEX(Stock!$A$3:$T$90,MATCH('Overton Borough Overview'!$A67,Stock!$A$3:$A$90,0),MATCH('Overton Borough Overview'!C$65,Stock!$A$3:$T$3,0)),0) -> 0 | D67: =C67-B67 -> 0 | F67: =IFERROR(INDEX(Stock!$A$3:$T$90,MATCH('Overton Borough Overview'!$A67,Stock!$A$3:$A$90,0),MATCH('Overton Borough Overview'!F$65,Stock!$A$3:$T$3,0)),0) -> 0 | G67: =IFERROR(INDEX(Stock!$A$3:$T$90,MATCH('Overton Borough Overview'!$A67,Stock!$A$3:$A$90,0),MATCH('Overton Borough Overview'!G$65,Stock!$A$3:$T$3,0)),0) -> 0
A68: Plough horses | B68: =IFERROR(INDEX(Stock!$A$3:$T$90,MATCH('Overton Borough Overview'!$A68,Stock!$A$3:$A$90,0),MATCH('Overton Borough Overview'!B$65,Stock!$A$3:$T$3,0)),0) -> 0 | C68: =IFERROR(INDEX(Stock!$A$3:$T$90,MATCH('Overton Borough Overview'!$A68,Stock!$A$3:$A$90,0),MATCH('Overton Borough Overview'!C$65,Stock!$A$3:$T$3,0)),0) -> 0 | D68: =C68-B68 -> 0 | F68: =IFERROR(INDEX(Stock!$A$3:$T$90,MATCH('Overton Borough Overview'!$A68,Stock!$A$3:$A$90,0),MATCH('Overton Borough Overview'!F$65,Stock!$A$3:$T$3,0)),0) -> 0 | G68: =IFERROR(INDEX(Stock!$A$3:$T$90,MATCH('Overton Borough Overview'!$A68,Stock!$A$3:$A$90,0),MATCH('Overton Borough Overview'!G$65,Stock!$A$3:$T$3,0)),0) -> 0
A69: Colts (2 years) | B69: =IFERROR(INDEX(Stock!$A$3:$T$90,MATCH('Overton Borough Overview'!$A69,Stock!$A$3:$A$90,0),MATCH('Overton Borough Overview'!B$65,Stock!$A$3:$T$3,0)),0) -> 0 | C69: =IFERROR(INDEX(Stock!$A$3:$T$90,MATCH('Overton Borough Overview'!$A69,Stock!$A$3:$A$90,0),MATCH('Overton Borough Overview'!C$65,Stock!$A$3:$T$3,0)),0) -> 0 | D69: =C69-B69 -> 0 | F69: =IFERROR(INDEX(Stock!$A$3:$T$90,MATCH('Overton Borough Overview'!$A69,Stock!$A$3:$A$90,0),MATCH('Overton Borough Overview'!F$65,Stock!$A$3:$T$3,0)),0) -> 0 | G69: =IFERROR(INDEX(Stock!$A$3:$T$90,MATCH('Overton Borough Overview'!$A69,Stock!$A$3:$A$90,0),MATCH('Overton Borough Overview'!G$65,Stock!$A$3:$T$3,0)),0) -> 0
A70: Colts (2 years) | B70: =IFERROR(INDEX(Stock!$A$3:$T$90,MATCH('Overton Borough Overview'!$A70,Stock!$A$3:$A$90,0),MATCH('Overton Borough Overview'!B$65,Stock!$A$3:$T$3,0)),0) -> 0 | C70: =IFERROR(INDEX(Stock!$A$3:$T$90,MATCH('Overton Borough Overview'!$A70,Stock!$A$3:$A$90,0),MATCH('Overton Borough Overview'!C$65,Stock!$A$3:$T$3,0)),0) -> 0 | D70: =C70-B70 -> 0 | F70: =IFERROR(INDEX(Stock!$A$3:$T$90,MATCH('Overton Borough Overview'!$A70,Stock!$A$3:$A$90,0),MATCH('Overton Borough Overview'!F$65,Stock!$A$3:$T$3,0)),0) -> 0 | G70: =IFERROR(INDEX(Stock!$A$3:$T$90,MATCH('Overton Borough Overview'!$A70,Stock!$A$3:$A$90,0),MATCH('Overton Borough Overview'!G$65,Stock!$A$3:$T$3,0)),0) -> 0
A71: Colts (1 year) | B71: =IFERROR(INDEX(Stock!$A$3:$T$90,MATCH('Overton Borough Overview'!$A71,Stock!$A$3:$A$90,0),MATCH('Overton Borough Overview'!B$65,Stock!$A$3:$T$3,0)),0) -> 0 | C71: =IFERROR(INDEX(Stock!$A$3:$T$90,MATCH('Overton Borough Overview'!$A71,Stock!$A$3:$A$90,0),MATCH('Overton Borough Overview'!C$65,Stock!$A$3:$T$3,0)),0) -> 0 | D71: =C71-B71 -> 0 | F71: =IFERROR(INDEX(Stock!$A$3:$T$90,MATCH('Overton Borough Overview'!$A71,Stock!$A$3:$A$90,0),MATCH('Overton Borough Overview'!F$65,Stock!$A$3:$T$3,0)),0) -> 0 | G71: =IFERROR(INDEX(Stock!$A$3:$T$90,MATCH('Overton Borough Overview'!$A71,Stock!$A$3:$A$90,0),MATCH('Overton Borough Overview'!G$65,Stock!$A$3:$T$3,0)),0) -> 0
A72: Foals | B72: =IFERROR(INDEX(Stock!$A$3:$T$90,MATCH('Overton Borough Overview'!$A72,Stock!$A$3:$A$90,0),MATCH('Overton Borough Overview'!B$65,Stock!$A$3:$T$3,0)),0) -> 0 | C72: =IFERROR(INDEX(Stock!$A$3:$T$90,MATCH('Overton Borough Overview'!$A72,Stock!$A$3:$A$90,0),MATCH('Overton Borough Overview'!C$65,Stock!$A$3:$T$3,0)),0) -> 0 | D72: =C72-B72 -> 0 | F72: =IFERROR(INDEX(Stock!$A$3:$T$90,MATCH('Overton Borough Overview'!$A72,Stock!$A$3:$A$90,0),MATCH('Overton Borough Overview'!F$65,Stock!$A$3:$T$3,0)),0) -> 0 | G72: =IFERROR(INDEX(Stock!$A$3:$T$90,MATCH('Overton Borough Overview'!$A72,Stock!$A$3:$A$90,0),MATCH('Overton Borough Overview'!G$65,Stock!$A$3:$T$3,0)),0) -> 0
A73: Oxen | B73: =IFERROR(INDEX(Stock!$A$3:$T$90,MATCH('Overton Borough Overview'!$A73,Stock!$A$3:$A$90,0),MATCH('Overton Borough Overview'!B$65,Stock!$A$3:$T$3,0)),0) -> 0 | C73: =IFERROR(INDEX(Stock!$A$3:$T$90,MATCH('Overton Borough Overview'!$A73,Stock!$A$3:$A$90,0),MATCH('Overton Borough Overview'!C$65,Stock!$A$3:$T$3,0)),0) -> 0 | D73: =C73-B73 -> 0 | F73: =IFERROR(INDEX(Stock!$A$3:$T$90,MATCH('Overton Borough Overview'!$A73,Stock!$A$3:$A$90,0),MATCH('Overton Borough Overview'!F$65,Stock!$A$3:$T$3,0)),0) -> 0 | G73: =IFERROR(INDEX(Stock!$A$3:$T$90,MATCH('Overton Borough Overview'!$A73,Stock!$A$3:$A$90,0),MATCH('Overton Borough Overview'!G$65,Stock!$A$3:$T$3,0)),0) -> 0
A74: Bulls | B74: =IFERROR(INDEX(Stock!$A$3:$T$90,MATCH('Overton Borough Overview'!$A74,Stock!$A$3:$A$90,0),MATCH('Overton Borough Overview'!B$65,Stock!$A$3:$T$3,0)),0) -> 0 | C74: =IFERROR(INDEX(Stock!$A$3:$T$90,MATCH('Overton Borough Overview'!$A74,Stock!$A$3:$A$90,0),MATCH('Overton Borough Overview'!C$65,Stock!$A$3:$T$3,0)),0) -> 0 | D74: =C74-B74 -> 0 | F74: =IFERROR(INDEX(Stock!$A$3:$T$90,MATCH('Overton Borough Overview'!$A74,Stock!$A$3:$A$90,0),MATCH('Overton Borough Overview'!F$65,Stock!$A$3:$T$3,0)),0) -> 0 | G74: =IFERROR(INDEX(Stock!$A$3:$T$90,MATCH('Overton Borough Overview'!$A74,Stock!$A$3:$A$90,0),MATCH('Overton Borough Overview'!G$65,Stock!$A$3:$T$3,0)),0) -> 0
A75: Cows | B75: =IFERROR(INDEX(Stock!$A$3:$T$90,MATCH('Overton Borough Overview'!$A75,Stock!$A$3:$A$90,0),MATCH('Overton Borough Overview'!B$65,Stock!$A$3:$T$3,0)),0) -> 0 | C75: =IFERROR(INDEX(Stock!$A$3:$T$90,MATCH('Overton Borough Overview'!$A75,Stock!$A$3:$A$90,0),MATCH('Overton Borough Overview'!C$65,Stock!$A$3:$T$3,0)),0) -> 0 | D75: =C75-B75 -> 0 | F75: =IFERROR(INDEX(Stock!$A$3:$T$90,MATCH('Overton Borough Overview'!$A75,Stock!$A$3:$A$90,0),MATCH('Overton Borough Overview'!F$65,Stock!$A$3:$T$3,0)),0) -> 0 | G75: =IFERROR(INDEX(Stock!$A$3:$T$90,MATCH('Overton Borough Overview'!$A75,Stock!$A$3:$A$90,0),MATCH('Overton Borough Overview'!G$65,Stock!$A$3:$T$3,0)),0) -> 0
A76: Steers | B76: =IFERROR(INDEX(Stock!$A$3:$T$90,MATCH('Overton Borough Overview'!$A76,Stock!$A$3:$A$90,0),MATCH('Overton Borough Overview'!B$65,Stock!$A$3:$T$3,0)),0) -> 0 | C76: =IFERROR(INDEX(Stock!$A$3:$T$90,MATCH('Overton Borough Overview'!$A76,Stock!$A$3:$A$90,0),MATCH('Overton Borough Overview'!C$65,Stock!$A$3:$T$3,0)),0) -> 0 | D76: =C76-B76 -> 0 | F76: =IFERROR(INDEX(Stock!$A$3:$T$90,MATCH('Overton Borough Overview'!$A76,Stock!$A$3:$A$90,0),MATCH('Overton Borough Overview'!F$65,Stock!$A$3:$T$3,0)),0) -> 0 | G76: =IFERROR(INDEX(Stock!$A$3:$T$90,MATCH('Overton Borough Overview'!$A76,Stock!$A$3:$A$90,0),MATCH('Overton Borough Overview'!G$65,Stock!$A$3:$T$3,0)),0) -> 0
A77: Bullocks | B77: =IFERROR(INDEX(Stock!$A$3:$T$90,MATCH('Overton Borough Overview'!$A77,Stock!$A$3:$A$90,0),MATCH('Overton Borough Overview'!B$65,Stock!$A$3:$T$3,0)),0) -> 0 | C77: =IFERROR(INDEX(Stock!$A$3:$T$90,MATCH('Overton Borough Overview'!$A77,Stock!$A$3:$A$90,0),MATCH('Overton Borough Overview'!C$65,Stock!$A$3:$T$3,0)),0) -> 0 | D77: =C77-B77 -> 0 | F77: =IFERROR(INDEX(Stock!$A$3:$T$90,MATCH('Overton Borough Overview'!$A77,Stock!$A$3:$A$90,0),MATCH('Overton Borough Overview'!F$65,Stock!$A$3:$T$3,0)),0) -> 0 | G77: =IFERROR(INDEX(Stock!$A$3:$T$90,MATCH('Overton Borough Overview'!$A77,Stock!$A$3:$A$90,0),MATCH('Overton Borough Overview'!G$65,Stock!$A$3:$T$3,0)),0) -> 0
... A91: Peacocks | B91: =IFERROR(INDEX(Stock!$A$3:$T$90,MATCH('Overton Borough Overview'!$A91,Stock!$A$3:$A$90,0),MATCH('Overton Borough Overview'!B$65,Stock!$A$3:$T$3,0)),0) -> 0 | C91: =IFERROR(INDEX(Stock!$A$3:$T$90,MATCH('Overton Borough Overview'!$A91,Stock!$A$3:$A$90,0),MATCH('Overton Borough Overview'!C$65,Stock!$A$3:$T$3,0)),0) -> 0 | D91: =C91-B91 -> 0 | F91: =IFERROR(INDEX(Stock!$A$3:$T$90,MATCH('Overton Borough Overview'!$A91,Stock!$A$3:$A$90,0),MATCH('Overton Borough Overview'!F$65,Stock!$A$3:$T$3,0)),0) -> 0 | G91: =IFERROR(INDEX(Stock!$A$3:$T$90,MATCH('Overton Borough Overview'!$A91,Stock!$A$3:$A$90,0),MATCH('Overton Borough Overview'!G$65,Stock!$A$3:$T$3,0)),0) -> 0
A92: Total | G92: =SUM(G66:G91) -> 0
A93: Value of sales | G93: =SUM(F66:F91) -> 0
A95: Wool | B95: Inherited stock | C95: End-period stock | D95: Stockbuilding | F95: Sales in (£) | G95: Value of production (£) at sales prices
A96: Fleeces | B96: =IFERROR(INDEX(Stock!$A$3:$T$90,MATCH('Overton Borough Overview'!$A96,Stock!$A$3:$A$90,0),MATCH('Overton Borough Overview'!B$65,Stock!$A$3:$T$3,0)),0) -> 0 | C96: =IFERROR(INDEX(Stock!$A$3:$T$90,MATCH('Overton Borough Overview'!$A96,Stock!$A$3:$A$90,0),MATCH('Overton Borough Overview'!C$65,Stock!$A$3:$T$3,0)),0) -> 0 | D96: =C96-B96 -> 0 | F96: =IFERROR(INDEX(Stock!$A$3:$T$90,MATCH('Overton Borough Overview'!$A96,Stock!$A$3:$A$90,0),MATCH('Overton Borough Overview'!F$65,Stock!$A$3:$T$3,0)),0) -> 0 | G96: =IFERROR(INDEX(Stock!$A$3:$T$90,MATCH('Overton Borough Overview'!$A96,Stock!$A$3:$A$90,0),MATCH('Overton Borough Overview'!G$65,Stock!$A$3:$T$3,0)),0) -> 0
A97: Coarse wool | B97: =IFERROR(INDEX(Stock!$A$3:$T$90,MATCH('Overton Borough Overview'!$A97,Stock!$A$3:$A$90,0),MATCH('Overton Borough Overview'!B$65,Stock!$A$3:$T$3,0)),0) -> 0 | C97: =IFERROR(INDEX(Stock!$A$3:$T$90,MATCH('Overton Borough Overview'!$A97,Stock!$A$3:$A$90,0),MATCH('Overton Borough Overview'!C$65,Stock!$A$3:$T$3,0)),0) -> 0 | D97: =C97-B97 -> 0 | F97: =IFERROR(INDEX(Stock!$A$3:$T$90,MATCH('Overton Borough Overview'!$A97,Stock!$A$3:$A$90,0),MATCH('Overton Borough Overview'!F$65,Stock!$A$3:$T$3,0)),0) -> 0 | G97: =IFERROR(INDEX(Stock!$A$3:$T$90,MATCH('Overton Borough Overview'!$A97,Stock!$A$3:$A$90,0),MATCH('Overton Borough Overview'!G$65,Stock!$A$3:$T$3,0)),0) -> 0
A98: Lamb's wool | B98: =IFERROR(INDEX(Stock!$A$3:$T$90,MATCH('Overton Borough Overview'!$A98,Stock!$A$3:$A$90,0),MATCH('Overton Borough Overview'!B$65,Stock!$A$3:$T$3,0)),0) -> 0 | C98: =IFERROR(INDEX(Stock!$A$3:$T$90,MATCH('Overton Borough Overview'!$A98,Stock!$A$3:$A$90,0),MATCH('Overton Borough Overview'!C$65,Stock!$A$3:$T$3,0)),0) -> 0 | D98: =C98-B98 -> 0 | F98: =IFERROR(INDEX(Stock!$A$3:$T$90,MATCH('Overton Borough Overview'!$A98,Stock!$A$3:$A$90,0),MATCH('Overton Borough Overview'!F$65,Stock!$A$3:$T$3,0)),0) -> 0 | G98: =IFERROR(INDEX(Stock!$A$3:$T$90,MATCH('Overton Borough Overview'!$A98,Stock!$A$3:$A$90,0),MATCH('Overton Borough Overview'!G$65,Stock!$A$3:$T$3,0)),0) -> 0
A99: Wool locks | B99: =IFERROR(INDEX(Stock!$A$3:$T$90,MATCH('Overton Borough Overview'!$A99,Stock!$A$3:$A$90,0),MATCH('Overton Borough Overview'!B$65,Stock!$A$3:$T$3,0)),0) -> 0 | C99: =IFERROR(INDEX(Stock!$A$3:$T$90,MATCH('Overton Borough Overview'!$A99,Stock!$A$3:$A$90,0),MATCH('Overton Borough Overview'!C$65,Stock!$A$3:$T$3,0)),0) -> 0 | D99: =C99-B99 -> 0 | F99: =IFERROR(INDEX(Stock!$A$3:$T$90,MATCH('Overton Borough Overview'!$A99,Stock!$A$3:$A$90,0),MATCH('Overton Borough Overview'!F$65,Stock!$A$3:$T$3,0)),0) -> 0 | G99: =IFERROR(INDEX(Stock!$A$3:$T$90,MATCH('Overton Borough Overview'!$A99,Stock!$A$3:$A$90,0),MATCH('Overton Borough Overview'!G$65,Stock!$A$3:$T$3,0)),0) -> 0
A100: Wool sold at shearing | B100: =IFERROR(INDEX(Stock!$A$3:$T$90,MATCH('Overton Borough Overview'!$A100,Stock!$A$3:$A$90,0),MATCH('Overton Borough Overview'!B$65,Stock!$A$3:$T$3,0)),0) -> 0 | C100: =IFERROR(INDEX(Stock!$A$3:$T$90,MATCH('Overton Borough Overview'!$A100,Stock!$A$3:$A$90,0),MATCH('Overton Borough Overview'!C$65,Stock!$A$3:$T$3,0)),0) -> 0 | D100: =C100-B100 -> 0 | F100: =IFERROR(INDEX(Stock!$A$3:$T$90,MATCH('Overton Borough Overview'!$A100,Stock!$A$3:$A$90,0),MATCH('Overton Borough Overview'!F$65,Stock!$A$3:$T$3,0)),0) -> 0 | G100: =IFERROR(INDEX(Stock!$A$3:$T$90,MATCH('Overton Borough Overview'!$A100,Stock!$A$3:$A$90,0),MATCH('Overton Borough Overview'!G$65,Stock!$A$3:$T$3,0)),0) -> 0
A101: Total value of production (sum of the above) | G101: =SUM(G96:G100) -> 0
A102: Value of sales | G102: =SUM(F96:F100) -> 0
A104: Hides | B104: Inherited stock | C104: End-period stock | D104: Stockbuilding | F104: Sales in (£) | G104: Value of production (£) at sales prices
A105: Ox hides | B105: =IFERROR(INDEX(Stock!$A$3:$T$90,MATCH('Overton Borough Overview'!$A105,Stock!$A$3:$A$90,0),MATCH('Overton Borough Overview'!B$65,Stock!$A$3:$T$3,0)),0) -> 0 | C105: =IFERROR(INDEX(Stock!$A$3:$T$90,MATCH('Overton Borough Overview'!$A105,Stock!$A$3:$A$90,0),MATCH('Overton Borough Overview'!C$65,Stock!$A$3:$T$3,0)),0) -> 0 | D105: =C105-B105 -> 0 | F105: =IFERROR(INDEX(Stock!$A$3:$T$90,MATCH('Overton Borough Overview'!$A105,Stock!$A$3:$A$90,0),MATCH('Overton Borough Overview'!F$65,Stock!$A$3:$T$3,0)),0) -> 0 | G105: =IFERROR(INDEX(Stock!$A$3:$T$90,MATCH('Overton Borough Overview'!$A105,Stock!$A$3:$A$90,0),MATCH('Overton Borough Overview'!G$65,Stock!$A$3:$T$3,0)),0) -> 0
A106: Cow hides | B106: =IFERROR(INDEX(Stock!$A$3:$T$90,MATCH('Overton Borough Overview'!$A106,Stock!$A$3:$A$90,0),MATCH('Overton Borough Overview'!B$65,Stock!$A$3:$T$3,0)),0) -> 0 | C106: =IFERROR(INDEX(Stock!$A$3:$T$90,MATCH('Overton Borough Overview'!$A106,Stock!$A$3:$A$90,0),MATCH('Overton Borough Overview'!C$65,Stock!$A$3:$T$3,0)),0) -> 0 | D106: =C106-B106 -> 0 | F106: =IFERROR(INDEX(Stock!$A$3:$T$90,MATCH('Overton Borough Overview'!$A106,Stock!$A$3:$A$90,0),MATCH('Overton Borough Overview'!F$65,Stock!$A$3:$T$3,0)),0) -> 0 | G106: =IFERROR(INDEX(Stock!$A$3:$T$90,MATCH('Overton Borough Overview'!$A106,Stock!$A$3:$A$90,0),MATCH('Overton Borough Overview'!G$65,Stock!$A$3:$T$3,0)),0) -> 0
A107: Mare hides | B107: =IFERROR(INDEX(Stock!$A$3:$T$90,MATCH('Overton Borough Overview'!$A107,Stock!$A$3:$A$90,0),MATCH('Overton Borough Overview'!B$65,Stock!$A$3:$T$3,0)),0) -> 0 | C107: =IFERROR(INDEX(Stock!$A$3:$T$90,MATCH('Overton Borough Overview'!$A107,Stock!$A$3:$A$90,0),MATCH('Overton Borough Overview'!C$65,Stock!$A$3:$T$3,0)),0) -> 0 | D107: =C107-B107 -> 0 | F107: =IFERROR(INDEX(Stock!$A$3:$T$90,MATCH('Overton Borough Overview'!$A107,Stock!$A$3:$A$90,0),MATCH('Overton Borough Overview'!F$65,Stock!$A$3:$T$3,0)),0) -> 0 | G107: =IFERROR(INDEX(Stock!$A$3:$T$90,MATCH('Overton Borough Overview'!$A107,Stock!$A$3:$A$90,0),MATCH('Overton Borough Overview'!G$65,Stock!$A$3:$T$3,0)),0) -> 0
A108: Steer hides | B108: =IFERROR(INDEX(Stock!$A$3:$T$90,MATCH('Overton Borough Overview'!$A108,Stock!$A$3:$A$90,0),MATCH('Overton Borough Overview'!B$65,Stock!$A$3:$T$3,0)),0) -> 0 | C108: =IFERROR(INDEX(Stock!$A$3:$T$90,MATCH('Overton Borough Overview'!$A108,Stock!$A$3:$A$90,0),MATCH('Overton Borough Overview'!C$65,Stock!$A$3:$T$3,0)),0) -> 0 | D108: =C108-B108 -> 0 | F108: =IFERROR(INDEX(Stock!$A$3:$T$90,MATCH('Overton Borough Overview'!$A108,Stock!$A$3:$A$90,0),MATCH('Overton Borough Overview'!F$65,Stock!$A$3:$T$3,0)),0) -> 0 | G108: =IFERROR(INDEX(Stock!$A$3:$T$90,MATCH('Overton Borough Overview'!$A108,Stock!$A$3:$A$90,0),MATCH('Overton Borough Overview'!G$65,Stock!$A$3:$T$3,0)),0) -> 0
A109: Yearling Calf hides | B109: =IFERROR(INDEX(Stock!$A$3:$T$90,MATCH('Overton Borough Overview'!$A109,Stock!$A$3:$A$90,0),MATCH('Overton Borough Overview'!B$65,Stock!$A$3:$T$3,0)),0) -> 0 | C109: =IFERROR(INDEX(Stock!$A$3:$T$90,MATCH('Overton Borough Overview'!$A109,Stock!$A$3:$A$90,0),MATCH('Overton Borough Overview'!C$65,Stock!$A$3:$T$3,0)),0) -> 0 | D109: =C109-B109 -> 0 | F109: =IFERROR(INDEX(Stock!$A$3:$T$90,MATCH('Overton Borough Overview'!$A109,Stock!$A$3:$A$90,0),MATCH('Overton Borough Overview'!F$65,Stock!$A$3:$T$3,0)),0) -> 0 | G109: =IFERROR(INDEX(Stock!$A$3:$T$90,MATCH('Overton Borough Overview'!$A109,Stock!$A$3:$A$90,0),MATCH('Overton Borough Overview'!G$65,Stock!$A$3:$T$3,0)),0) -> 0
A110: Calf hides | B110: =IFERROR(INDEX(Stock!$A$3:$T$90,MATCH('Overton Borough Overview'!$A110,Stock!$A$3:$A$90,0),MATCH('Overton Borough Overview'!B$65,Stock!$A$3:$T$3,0)),0) -> 0 | C110: =IFERROR(INDEX(Stock!$A$3:$T$90,MATCH('Overton Borough Overview'!$A110,Stock!$A$3:$A$90,0),MATCH('Overton Borough Overview'!C$65,Stock!$A$3:$T$3,0)),0) -> 0 | D110: =C110-B110 -> 0 | F110: =IFERROR(INDEX(Stock!$A$3:$T$90,MATCH('Overton Borough Overview'!$A110,Stock!$A$3:$A$90,0),MATCH('Overton Borough Overview'!F$65,Stock!$A$3:$T$3,0)),0) -> 0 | G110: =IFERROR(INDEX(Stock!$A$3:$T$90,MATCH('Overton Borough Overview'!$A110,Stock!$A$3:$A$90,0),MATCH('Overton Borough Overview'!G$65,Stock!$A$3:$T$3,0)),0) -> 0
A111: Pig hides | B111: =IFERROR(INDEX(Stock!$A$3:$T$90,MATCH('Overton Borough Overview'!$A111,Stock!$A$3:$A$90,0),MATCH('Overton Borough Overview'!B$65,Stock!$A$3:$T$3,0)),0) -> 0 | C111: =IFERROR(INDEX(Stock!$A$3:$T$90,MATCH('Overton Borough Overview'!$A111,Stock!$A$3:$A$90,0),MATCH('Overton Borough Overview'!C$65,Stock!$A$3:$T$3,0)),0) -> 0 | D111: =C111-B111 -> 0 | F111: =IFERROR(INDEX(Stock!$A$3:$T$90,MATCH('Overton Borough Overview'!$A111,Stock!$A$3:$A$90,0),MATCH('Overton Borough Overview'!F$65,Stock!$A$3:$T$3,0)),0) -> 0 | G111: =IFERROR(INDEX(Stock!$A$3:$T$90,MATCH('Overton Borough Overview'!$A111,Stock!$A$3:$A$90,0),MATCH('Overton Borough Overview'!G$65,Stock!$A$3:$T$3,0)),0) -> 0
A112: Weather woolskins | B112: =IFERROR(INDEX(Stock!$A$3:$T$90,MATCH('Overton Borough Overview'!$A112,Stock!$A$3:$A$90,0),MATCH('Overton Borough Overview'!B$65,Stock!$A$3:$T$3,0)),0) -> 0 | C112: =IFERROR(INDEX(Stock!$A$3:$T$90,MATCH('Overton Borough Overview'!$A112,Stock!$A$3:$A$90,0),MATCH('Overton Borough Overview'!C$65,Stock!$A$3:$T$3,0)),0) -> 0 | D112: =C112-B112 -> 0 | F112: =IFERROR(INDEX(Stock!$A$3:$T$90,MATCH('Overton Borough Overview'!$A112,Stock!$A$3:$A$90,0),MATCH('Overton Borough Overview'!F$65,Stock!$A$3:$T$3,0)),0) -> 0 | G112: =IFERROR(INDEX(Stock!$A$3:$T$90,MATCH('Overton Borough Overview'!$A112,Stock!$A$3:$A$90,0),MATCH('Overton Borough Overview'!G$65,Stock!$A$3:$T$3,0)),0) -> 0
A113: Ram woolskins | B113: =IFERROR(INDEX(Stock!$A$3:$T$90,MATCH('Overton Borough Overview'!$A113,Stock!$A$3:$A$90,0),MATCH('Overton Borough Overview'!B$65,Stock!$A$3:$T$3,0)),0) -> 0 | C113: =IFERROR(INDEX(Stock!$A$3:$T$90,MATCH('Overton Borough Overview'!$A113,Stock!$A$3:$A$90,0),MATCH('Overton Borough Overview'!C$65,Stock!$A$3:$T$3,0)),0) -> 0 | D113: =C113-B113 -> 0 | F113: =IFERROR(INDEX(Stock!$A$3:$T$90,MATCH('Overton Borough Overview'!$A113,Stock!$A$3:$A$90,0),MATCH('Overton Borough Overview'!F$65,Stock!$A$3:$T$3,0)),0) -> 0 | G113: =IFERROR(INDEX(Stock!$A$3:$T$90,MATCH('Overton Borough Overview'!$A113,Stock!$A$3:$A$90,0),MATCH('Overton Borough Overview'!G$65,Stock!$A$3:$T$3,0)),0) -> 0
A114: Ewe woolskins | B114: =IFERROR(INDEX(Stock!$A$3:$T$90,MATCH('Overton Borough Overview'!$A114,Stock!$A$3:$A$90,0),MATCH('Overton Borough Overview'!B$65,Stock!$A$3:$T$3,0)),0) -> 0 | C114: =IFERROR(INDEX(Stock!$A$3:$T$90,MATCH('Overton Borough Overview'!$A114,Stock!$A$3:$A$90,0),MATCH('Overton Borough Overview'!C$65,Stock!$A$3:$T$3,0)),0) -> 0 | D114: =C114-B114 -> 0 | F114: =IFERROR(INDEX(Stock!$A$3:$T$90,MATCH('Overton Borough Overview'!$A114,Stock!$A$3:$A$90,0),MATCH('Overton Borough Overview'!F$65,Stock!$A$3:$T$3,0)),0) -> 0 | G114: =IFERROR(INDEX(Stock!$A$3:$T$90,MATCH('Overton Borough Overview'!$A114,Stock!$A$3:$A$90,0),MATCH('Overton Borough Overview'!G$65,Stock!$A$3:$T$3,0)),0) -> 0
A115: Hogg woolskins | B115: =IFERROR(INDEX(Stock!$A$3:$T$90,MATCH('Overton Borough Overview'!$A115,Stock!$A$3:$A$90,0),MATCH('Overton Borough Overview'!B$65,Stock!$A$3:$T$3,0)),0) -> 0 | C115: =IFERROR(INDEX(Stock!$A$3:$T$90,MATCH('Overton Borough Overview'!$A115,Stock!$A$3:$A$90,0),MATCH('Overton Borough Overview'!C$65,Stock!$A$3:$T$3,0)),0) -> 0 | D115: =C115-B115 -> 0 | F115: =IFERROR(INDEX(Stock!$A$3:$T$90,MATCH('Overton Borough Overview'!$A115,Stock!$A$3:$A$90,0),MATCH('Overton Borough Overview'!F$65,Stock!$A$3:$T$3,0)),0) -> 0 | G115: =IFERROR(INDEX(Stock!$A$3:$T$90,MATCH('Overton Borough Overview'!$A115,Stock!$A$3:$A$90,0),MATCH('Overton Borough Overview'!G$65,Stock!$A$3:$T$3,0)),0) -> 0
A116: Woolskins (total) | B116: =IFERROR(INDEX(Stock!$A$3:$T$90,MATCH('Overton Borough Overview'!$A116,Stock!$A$3:$A$90,0),MATCH('Overton Borough Overview'!B$65,Stock!$A$3:$T$3,0)),0) -> 0 | C116: =IFERROR(INDEX(Stock!$A$3:$T$90,MATCH('Overton Borough Overview'!$A116,Stock!$A$3:$A$90,0),MATCH('Overton Borough Overview'!C$65,Stock!$A$3:$T$3,0)),0) -> 0 | D116: =C116-B116 -> 0 | F116: =IFERROR(INDEX(Stock!$A$3:$T$90,MATCH('Overton Borough Overview'!$A116,Stock!$A$3:$A$90,0),MATCH('Overton Borough Overview'!F$65,Stock!$A$3:$T$3,0)),0) -> 0 | G116: =IFERROR(INDEX(Stock!$A$3:$T$90,MATCH('Overton Borough Overview'!$A116,Stock!$A$3:$A$90,0),MATCH('Overton Borough Overview'!G$65,Stock!$A$3:$T$3,0)),0) -> 0
... A124: Shorn skins | B124: =IFERROR(INDEX(Stock!$A$3:$T$90,MATCH('Overton Borough Overview'!$A124,Stock!$A$3:$A$90,0),MATCH('Overton Borough Overview'!B$65,Stock!$A$3:$T$3,0)),0) -> 0 | C124: =IFERROR(INDEX(Stock!$A$3:$T$90,MATCH('Overton Borough Overview'!$A124,Stock!$A$3:$A$90,0),MATCH('Overton Borough Overview'!C$65,Stock!$A$3:$T$3,0)),0) -> 0 | D124: =C124-B124 -> 0 | F124: =IFERROR(INDEX(Stock!$A$3:$T$90,MATCH('Overton Borough Overview'!$A124,Stock!$A$3:$A$90,0),MATCH('Overton Borough Overview'!F$65,Stock!$A$3:$T$3,0)),0) -> 0 | G124: =IFERROR(INDEX(Stock!$A$3:$T$90,MATCH('Overton Borough Overview'!$A124,Stock!$A$3:$A$90,0),MATCH('Overton Borough Overview'!G$65,Stock!$A$3:$T$3,0)),0) -> 0
A125: Total value of production (sum of the above) | G125: =SUM(G105:G124) -> 0
A126: Value of sales | G126: =SUM(F105:F124) -> 0
A128: Poultry stock | B128: Inherited stock | C128: End-period stock | D128: Stockbuilding | F128: Sales in (£) | G128: Value of production (£) at sales prices
A129: Hens | B129: =IFERROR(INDEX(Stock!$A$3:$T$90,MATCH('Overton Borough Overview'!$A129,Stock!$A$3:$A$90,0),MATCH('Overton Borough Overview'!B$65,Stock!$A$3:$T$3,0)),0) -> 0 | C129: =IFERROR(INDEX(Stock!$A$3:$T$90,MATCH('Overton Borough Overview'!$A129,Stock!$A$3:$A$90,0),MATCH('Overton Borough Overview'!C$65,Stock!$A$3:$T$3,0)),0) -> 0 | D129: =C129-B129 -> 0 | F129: =IFERROR(INDEX(Stock!$A$3:$T$90,MATCH('Overton Borough Overview'!$A129,Stock!$A$3:$A$90,0),MATCH('Overton Borough Overview'!F$65,Stock!$A$3:$T$3,0)),0) -> 0 | G129: =IFERROR(INDEX(Stock!$A$3:$T$90,MATCH('Overton Borough Overview'!$A129,Stock!$A$3:$A$90,0),MATCH('Overton Borough Overview'!G$65,Stock!$A$3:$T$3,0)),0) -> 0
A130: Geese | B130: =IFERROR(INDEX(Stock!$A$3:$T$90,MATCH('Overton Borough Overview'!$A130,Stock!$A$3:$A$90,0),MATCH('Overton Borough Overview'!B$65,Stock!$A$3:$T$3,0)),0) -> 0 | C130: =IFERROR(INDEX(Stock!$A$3:$T$90,MATCH('Overton Borough Overview'!$A130,Stock!$A$3:$A$90,0),MATCH('Overton Borough Overview'!C$65,Stock!$A$3:$T$3,0)),0) -> 0 | D130: =C130-B130 -> 0 | F130: =IFERROR(INDEX(Stock!$A$3:$T$90,MATCH('Overton Borough Overview'!$A130,Stock!$A$3:$A$90,0),MATCH('Overton Borough Overview'!F$65,Stock!$A$3:$T$3,0)),0) -> 0 | G130: =IFERROR(INDEX(Stock!$A$3:$T$90,MATCH('Overton Borough Overview'!$A130,Stock!$A$3:$A$90,0),MATCH('Overton Borough Overview'!G$65,Stock!$A$3:$T$3,0)),0) -> 0
A131: Capons (from chickens) | B131: =IFERROR(INDEX(Stock!$A$3:$T$90,MATCH('Overton Borough Overview'!$A131,Stock!$A$3:$A$90,0),MATCH('Overton Borough Overview'!B$65,Stock!$A$3:$T$3,0)),0) -> 0 | C131: =IFERROR(INDEX(Stock!$A$3:$T$90,MATCH('Overton Borough Overview'!$A131,Stock!$A$3:$A$90,0),MATCH('Overton Borough Overview'!C$65,Stock!$A$3:$T$3,0)),0) -> 0 | D131: =C131-B131 -> 0 | F131: =IFERROR(INDEX(Stock!$A$3:$T$90,MATCH('Overton Borough Overview'!$A131,Stock!$A$3:$A$90,0),MATCH('Overton Borough Overview'!F$65,Stock!$A$3:$T$3,0)),0) -> 0 | G131: =IFERROR(INDEX(Stock!$A$3:$T$90,MATCH('Overton Borough Overview'!$A131,Stock!$A$3:$A$90,0),MATCH('Overton Borough Overview'!G$65,Stock!$A$3:$T$3,0)),0) -> 0
A132: Cocks & hens | B132: =IFERROR(INDEX(Stock!$A$3:$T$90,MATCH('Overton Borough Overview'!$A132,Stock!$A$3:$A$90,0),MATCH('Overton Borough Overview'!B$65,Stock!$A$3:$T$3,0)),0) -> 0 | C132: =IFERROR(INDEX(Stock!$A$3:$T$90,MATCH('Overton Borough Overview'!$A132,Stock!$A$3:$A$90,0),MATCH('Overton Borough Overview'!C$65,Stock!$A$3:$T$3,0)),0) -> 0 | D132: =C132-B132 -> 0 | F132: =IFERROR(INDEX(Stock!$A$3:$T$90,MATCH('Overton Borough Overview'!$A132,Stock!$A$3:$A$90,0),MATCH('Overton Borough Overview'!F$65,Stock!$A$3:$T$3,0)),0) -> 0 | G132: =IFERROR(INDEX(Stock!$A$3:$T$90,MATCH('Overton Borough Overview'!$A132,Stock!$A$3:$A$90,0),MATCH('Overton Borough Overview'!G$65,Stock!$A$3:$T$3,0)),0) -> 0
...

Sheet Overton Borough Receipts
A1: OVERTON BOROUGH RECEIPTS
B2: £ | C2: s | D2: d | F2: Total in £ | G2: Error | H2: Notes
A4: Arrears
A5: Arrears total | B5: 2 | C5: 1 | D5: 2.5 | F5: =B5+C5/20+D5/240 -> 2.0604167
A6: of which delivered to treasurer of Wolvesey | B6: 2 | C6: 1 | D6: 2.5 | F6: =B6+C6/20+D6/240 -> 2.0604167
A8: Rents of assize
A9: renst of assize for the year all paid at Michaelmas | B9: 8 | C9: 4 | D9: 3.5 | F9: =B9+C9/20+D9/240 -> 8.2145833
A10: Total recorded in accounts | B10: 8 | C10: 4 | D10: 3.5 | F10: =B10+C10/20+D10/240 -> 8.2145833
A11: Rents of assize total | B11: =SUM(B9:B9) -> 8 | C11: =SUM(C9:C9) -> 4 | D11: =SUM(D9:D9) -> 3.5 | F11: =B11+C11/20+D11/240 -> 8.2145833 | G11: =F11-F10 -> 0
A13: Quittances
A14: one reeve for the year | C14: 2 | F14: =B14+C14/20+D14/240 -> 0.1
A15: Total recorded in accounts | C15: 2 | F15: =B15+C15/20+D15/240 -> 0.1
A16: Quittances total | B16: =SUM(B14:B14) -> 0 | C16: =SUM(C14:C14) -> 2 | D16: =SUM(D14:D14) -> 0 | F16: =B16+C16/20+D16/240 -> 0.1 | G16: =F16-F15 -> 0
A18: Defaults of rent
A19: default of the house of Gilbert le Pynk | D19: 6 | F19: =B19+C19/20+D19/240 -> 0.025
A20: Total recorded in accounts | D20: 6 | F20: =B20+C20/20+D20/240 -> 0.025
A21: Defaults of rent total | B21: =SUM(B19:B19) -> 0 | C21: =SUM(C19:C19) -> 0 | D21: =SUM(D19:D19) -> 6 | F21: =B21+C21/20+D21/240 -> 0.025 | G21: =F21-F20 -> 0
A23: Total of rents remaining | B23: 8 | C23: 1 | D23: 9.5 | F23: =B23+C23/20+D23/240 -> 8.0895833 | H23: not included in receipts
A25: Wax
F26: =B26+C26/20+D26/240 -> 0
A27: Total recorded in accounts | F27: =B27+C27/20+D27/240 -> 0
A28: Wax total | B28: =SUM(B26) -> 0 | C28: =SUM(C26) -> 0 | D28: =SUM(D26) -> 0 | F28: =B28+C28/20+D28/240 -> 0 | G28: =F28-F27 -> 0
A30: Annual recognizances
A31: from Richard Hayward | D31: 6 | F31: =B31+C31/20+D31/240 -> 0.025
A32: Total recorded in accounts | D32: 6 | F32: =B32+C32/20+D32/240 -> 0.025
A33: Annual recognizances total | B33: =SUM(B31:B31) -> 0 | C33: =SUM(C31:C31) -> 0 | D33: =SUM(D31:D31) -> 6 | F33: =B33+C33/20+D33/240 -> 0.025 | G33: =F33-F32 -> 0
A35: Selds and stalls (no issue of the manor)
A36: 16 selds hired in the borough | C36: 10 | D36: 8 | F36: =B36+C36/20+D36/240 -> 0.53333333
A37: 32 stalls | C37: 5 | D37: 4 | F37: =B37+C37/20+D37/240 -> 0.26666667
A38: Total recorded in accounts | C38: 16 | F38: =B38+C38/20+D38/240 -> 0.8
A39: Issues of the manor total | B39: =SUM(B36:B37) -> 0 | C39: =SUM(C36:C37) -> 15 | D39: =SUM(D36:D37) -> 12 | F39: =B39+C39/20+D39/240 -> 0.8 | G39: =F39-F38 -> 0
A41: Sale of corn
A42: nothing | F42: =B42+C42/20+D42/240 -> 0
A43: Total recorded in accounts | F43: =B43+C43/20+D43/240 -> 0
A44: Sale of corn total | B44: =SUM(B42:B42) -> 0 | C44: =SUM(C42:C42) -> 0 | D44: =SUM(D42:D42) -> 0 | F44: =B44+C44/20+D44/240 -> 0 | G44: =F44-F43 -> 0
A46: Entry and marriage fines
A47: nothing | F47: =B47+C47/20+D47/240 -> 0
A48: Total recorded in accounts | F48: =B48+C48/20+D48/240 -> 0
A49: Entry and marriage fines total | B49: =SUM(B47:B47) -> 0 | C49: =SUM(C47:C47) -> 0 | D49: =SUM(D47:D47) -> 0 | F49: =B49+C49/20+D49/240 -> 0 | G49: =F49-F48 -> 0
A52: Farm of Freefolk
A53: for the farm of Freefolk at Michaelmas | C53: 10 | F53: =B53+C53/20+D53/240 -> 0.5
A54: Total recorded in accounts | C54: 10 | F54: =B54+C54/20+D54/240 -> 0.5
A55: Entry and marriage fines total | B55: =SUM(B53:B53) -> 0 | C55: =SUM(C53:C53) -> 10 | D55: =SUM(D53:D53) -> 0 | F55: =B55+C55/20+D55/240 -> 0.5 | G55: =F55-F54 -> 0
A58: Pleas and perquisites
A59: from William Sueyn | C59: 8 | D59: 9 | F59: =B59+C59/20+D59/240 -> 0.4375
A60: from John Wylly | C60: 2 | F60: =B60+C60/20+D60/240 -> 0.1
A61: from John Capellanus | C61: 7 | D61: 6 | F61: =B61+C61/20+D61/240 -> 0.375
A62: from John Blakeman | C62: 4 | D62: 6 | F62: =B62+C62/20+D62/240 -> 0.225
A63: from those who brewed ale breaking the assize | B63: 2 | C63: 2 | D63: 6 | F63: =B63+C63/20+D63/240 -> 2.125
A64: Total recorded in accounts | B64: 3 | C64: 5 | D64: 3 | F64: =B64+C64/20+D64/240 -> 3.2625
A65: Pleas & perquisites total | B65: =SUM(B59:B63) -> 2 | C65: =SUM(C59:C63) -> 23 | D65: =SUM(D59:D63) -> 27 | F65: =B65+C65/20+D65/240 -> 3.2625
A67: Total of all receipts (sum of above excl. arrears) | F67: =F65+F55+F49+F44+F39+F33+F28+F23 -> 12.677083
A68: Total of all receipts (sum of above incl. arrears) | F68: =F67+F6 -> 14.7375
A69: Total of all receipts in account excl. arrears | B69: 12 | C69: 13 | D69: 6 | F69: =B69+C69/20+D69/240 -> 12.675 | G69: =F69-F67 -> -0.0020833333
A70: Total of all receipts in account incl. arrears | F70: =B70+C70/20+D70/240 -> 0

Sheet Overton Borough Expenses
A1: OVERTON BOROUGH EXPENSES
B2: £ | C2: s | D2: d | F2: Total in £ | G2: Error | H2: Notes
A3: Cost of Ploughs
F4: =B4+C4/20+D4/240 -> 0
F5: =B5+C5/20+D5/240 -> 0
F6: =B6+C6/20+D6/240 -> 0
F7: =B7+C7/20+D7/240 -> 0
F8: =B8+C8/20+D8/240 -> 0
F9: =B9+C9/20+D9/240 -> 0
F10: =B10+C10/20+D10/240 -> 0
F11: =B11+C11/20+D11/240 -> 0
F12: =B12+C12/20+D12/240 -> 0
F13: =B13+C13/20+D13/240 -> 0
F14: =B14+C14/20+D14/240 -> 0
F15: =B15+C15/20+D15/240 -> 0
A16: Total recorded in accounts | F16: =B16+C16/20+D16/240 -> 0
A17: Cost of ploughs total | B17: =SUM(B3:B15) -> 0 | C17: =SUM(C3:C15) -> 0 | D17: =SUM(D3:D15) -> 0 | F17: =B17+C17/20+D17/240 -> 0 | G17: =F17-F16 -> 0
A18: Total capital expenses | B18: =SUM(B4:B7,B9,B10:B11,B13,B15) -> 0 | C18: =SUM(C4:C7,C9,C10:C11,C13,C15) -> 0 | D18: =SUM(D4:D7,D9,D10:D11,D13,D15) -> 0 | F18: =B18+C18/20+D18/240 -> 0
A20: Purchase of Corn
F21: =B21+C21/20+D21/240 -> 0
A22: Total recorded in accounts | F22: =B22+C22/20+D22/240 -> 0
A23: Purchase of corn total | B23: =SUM(B21) -> 0 | C23: =SUM(C21) -> 0 | D23: =SUM(D21) -> 0 | F23: =B23+C23/20+D23/240 -> 0 | G23: =F23-F22 -> 0
A25: Cost of Carts and Wagons
F26: =B26+C26/20+D26/240 -> 0
F27: =B27+C27/20+D27/240 -> 0
F28: =B28+C28/20+D28/240 -> 0
F29: =B29+C29/20+D29/240 -> 0
F30: =B30+C30/20+D30/240 -> 0
F31: =B31+C31/20+D31/240 -> 0
F32: =B32+C32/20+D32/240 -> 0
F33: =B33+C33/20+D33/240 -> 0
F34: =B34+C34/20+D34/240 -> 0
F35: =B35+C35/20+D35/240 -> 0
F36: =B36+C36/20+D36/240 -> 0
F37: =B37+C37/20+D37/240 -> 0
... F40: =B40+C40/20+D40/240 -> 0
A41: Total recorded in accounts | F41: =B41+C41/20+D41/240 -> 0
A42: Cost of carts and wagons total | B42: =SUM(B26:B40) -> 0 | C42: =SUM(C26:C40) -> 0 | D42: =SUM(D26:D40) -> 0 | F42: =B42+C42/20+D42/240 -> 0 | G42: =F42-F41 -> 0
A43: Total capital expenses | B43: =SUM(B26:B39) -> 0 | C43: =SUM(C26:C39) -> 0 | D43: =SUM(D26:D39) -> 0 | F43: =B43+C43/20+D43/240 -> 0
A45: Cost of Dairy
F46: =B46+C46/20+D46/240 -> 0
F47: =B47+C47/20+D47/240 -> 0
F48: =B48+C48/20+D48/240 -> 0
F49: =B49+C49/20+D49/240 -> 0
F50: =B50+C50/20+D50/240 -> 0
F51: =B51+C51/20+D51/240 -> 0
A52: Total recorded in accounts | F52: =B52+C52/20+D52/240 -> 0
A53: Cost of dairy total | B53: =SUM(B46:B51) -> 0 | C53: =SUM(C46:C51) -> 0 | D53: =SUM(D46:D51) -> 0 | F53: =B53+C53/20+D53/240 -> 0 | G53: =F53-F52 -> 0
A54: Total capital expenses | B54: =SUM(B46:B50) -> 0 | C54: =SUM(C46:C50) -> 0 | D54: =SUM(D46:D50) -> 0 | F54: =B54+C54/20+D54/240 -> 0
A56: Purchase of Stock
F57: =B57+C57/20+D57/240 -> 0
F58: =B58+C58/20+D58/240 -> 0
F59: =B59+C59/20+D59/240 -> 0
A60: Total recorded in accounts | F60: =B60+C60/20+D60/240 -> 0
A61: Purchase of stock total | B61: =SUM(B57:B59) -> 0 | C61: =SUM(C57:C59) -> 0 | D61: =SUM(D57:D59) -> 0 | F61: =B61+C61/20+D61/240 -> 0 | G61: =F61-F60 -> 0
A63: Sheepcote
F64: =B64+C64/20+D64/240 -> 0
F65: =B65+C65/20+D65/240 -> 0
F66: =B66+C66/20+D66/240 -> 0
F67: =B67+C67/20+D67/240 -> 0
F68: =B68+C68/20+D68/240 -> 0
F69: =B69+C69/20+D69/240 -> 0
A70: Total recorded in accounts | F70: =B70+C70/20+D70/240 -> 0
A71: Sheepcote total | B71: =SUM(B64:B69) -> 0 | C71: =SUM(C64:C69) -> 0 | D71: =SUM(D64:D69) -> 0 | F71: =B71+C71/20+D71/240 -> 0 | G71: =F71-F70 -> 0
A72: Total capital expenses | B72: =SUM(B64:B65,B66,B68:B69) -> 0 | C72: =SUM(C64:C65,C66,C68:C69) -> 0 | D72: =SUM(D64:D65,D66,D68:D69) -> 0 | F72: =B72+C72/20+D72/240 -> 0
A74: Cost of Buildings
A75: in roofing, pointing and mending selds in places | C75: 1 | D75: 8 | F75: =B75+C75/20+D75/240 -> 0.083333333
A76: collecting sands for the same and mending of the walls | D76: 5 | F76: =B76+C76/20+D76/240 -> 0.020833333
A77: in making 1 tumbrel anew and mending the pillory | C77: 3 | D77: 1 | F77: =B77+C77/20+D77/240 -> 0.15416667
F78: =B78+C78/20+D78/240 -> 0
F79: =B79+C79/20+D79/240 -> 0
F80: =B80+C80/20+D80/240 -> 0
F81: =B81+C81/20+D81/240 -> 0
F82: =B82+C82/20+D82/240 -> 0
F83: =B83+C83/20+D83/240 -> 0
F84: =B84+C84/20+D84/240 -> 0
F85: =B85+C85/20+D85/240 -> 0
A86: Total recorded in accounts | C86: 5 | D86: 2 | F86: =B86+C86/20+D86/240 -> 0.25833333
A87: Cost of buildings total | B87: =SUM(B75:B85) -> 0 | C87: =SUM(C75:C85) -> 4 | D87: =SUM(D75:D85) -> 14 | F87: =B87+C87/20+D87/240 -> 0.25833333 | G87: =F87-F86 -> 0
A88: Total capital expenses | B88: =SUM(B75:B76,B82:B85) -> 0 | C88: =SUM(C75:C76,C82:C85) -> 1 | D88: =SUM(D75:D76,D82:D85) -> 13 | F88: =B88+C88/20+D88/240 -> 0.10416667
A90: Threshing
F91: =B91+C91/20+D91/240 -> 0
F92: =B92+C92/20+D92/240 -> 0
F93: =B93+C93/20+D93/240 -> 0
F94: =B94+C94/20+D94/240 -> 0
F95: =B95+C95/20+D95/240 -> 0
A96: Total recorded in accounts | F96: =B96+C96/20+D96/240 -> 0
A97: Threshing total | B97: =SUM(B91:B95) -> 0 | C97: =SUM(C91:C95) -> 0 | D97: =SUM(D91:D95) -> 0 | F97: =B97+C97/20+D97/240 -> 0 | G97: =F97-F96 -> 0
A99: Expenses of the Harvest
F100: =B100+C100/20+D100/240 -> 0
F101: =B101+C101/20+D101/240 -> 0
F102: =B102+C102/20+D102/240 -> 0
F103: =B103+C103/20+D103/240 -> 0
F104: =B104+C104/20+D104/240 -> 0
A105: Total recorded in accounts | F105: =B105+C105/20+D105/240 -> 0
A106: Expenses of the harvest total | B106: =SUM(B100:B104) -> 0 | C106: =SUM(C100:C104) -> 0 | D106: =SUM(D100:D104) -> 0 | F106: =B106+C106/20+D106/240 -> 0 | G106: =F106-F105 -> 0
A108: Steward's Expenses
F109: =B109+C109/20+D109/240 -> 0
F110: =B110+C110/20+D110/240 -> 0
F111: =B111+C111/20+D111/240 -> 0
...

Sheet Issues of the Grange
A1: no grange

Sheet Stock
A2: no stock account

Sheet Assumptions
A1: ASSUMPTIONS
B3: Weights | C3: Value (in lbs) | D3: Value (in cloves) | E3: Value (in weys) | F3: Value (in stone)
B4: Lbs | C4: 1 | D4: =C4/C5 -> 0.14285714 | E4: =C4/C6 -> 0.0057142857 | F4: =C4/C7 -> 0.08
B5: Cloves | C5: 7 | D5: 1 | E5: =C5/C6 -> 0.04 | F5: =C7/C5 -> 1.7857143
B6: Wey | C6: 175 | D6: =C6/C5 -> 25 | E6: =C6/C6 -> 1 | F6: =C7/C6 -> 0.071428571
B7: Stone | C7: =175/14 -> 12.5 | D7: =C5/C7 -> 0.56 | E7: =C7/C6 -> 0.071428571 | F7: 1
