Workbook

Sheet Overview
A1: TAUNTON BOROUGH MANOR | B1: £ | C1: s | D1: d | F1: Total in £ | G1: Error | I1: Note
A3: CASH ACCOUNT
A4: RECEIPTS
A5: Rents | B5: =Receipts!B6 -> 22 | C5: =Receipts!C6 -> 16 | D5: =Receipts!D6 -> 2 | F5: =B5+C5/20+D5/240 -> 22.808333
A6: Quittances & Defaults | B6: =Receipts!B13 -> 0 | C6: =Receipts!C13 -> 4 | D6: =Receipts!D13 -> 12 | F6: =B6+C6/20+D6/240 -> 0.25
A7: Perquisites | B7: =Receipts!B65 -> 9 | C7: =Receipts!C65 -> 44 | D7: =Receipts!D65 -> 162 | F7: =B7+C7/20+D7/240 -> 11.875
A8: Sum of the above (incl. arrears if listed) | B8: =SUM(B5:B7) -> 31 | C8: =SUM(C5:C7) -> 64 | D8: =SUM(D5:D7) -> 176 | F8: =B8+C8/20+D8/240 -> 34.933333
A9: Total recorded in the accounts | B9: 34 | C9: 8 | D9: 8 | F9: =B9+C9/20+D9/240 -> 34.433333 | G9: =F9-F8 -> -0.5
A11: EXPENSES
A12: Cost of ploughs | B12: nothing
A13: Cost of ploughs - strictly capital expenses
A14: Cost of wagons
A15: Repair of buildings
A16: Cost of harvest
A17: Sum of the above
A18: Total of all expenses
A19: Capital Expenses
B20: nothing
A21: Owed by the reeve
A22: From accounts
A24: Allowances
A25: Cash Deliveries
A26: Sum of the above
A27: Total of all allowances and cash deliveries in accounts
A29: Net amount owed
A30: Net amount owed in accounts
A32: GRANGE ACCOUNT
A33: Grange | B33: nothing
A34: Wheat
A35: Curall
A36: Barley
A37: Oats
A38: Beans
A39: Peas
A40: Vetches
A41: Total value of production (sum of the above)
A42: Value of sales
A44: MILL ACCOUNT
A45: Issues of the mill | B45: nothing
A46: Wheat
A47: Barley
A48: 1st grade malt
A49: 2nd grade malt
A50: oatmeal
A51: fine bran
A52: eel
A53: Total value of production (sum of the above)
A54: Value of sales
A56: STOCK ACCOUNT
A57: Livestock | B57: nothing
A58: plough horses
A59: oxen
A60: cows
A61: yearlings
A62: Total (but incomplete)
A63: Value of sales
A65: Wool
A66: Coarse wool | B66: nothing
A67: Lamb's wool
A68: Wool locks
A69: Total value of production (sum of the above)
A70: Value of sales
A72: Hides
A73: Ox hides | B73: nothing
A74: Mare
A75: Steer
A76: calves
A77: pigs
A78: Woolskins (incl. 10 in tithe)
A79: Bareskins (total)
A80: Lambskins (excl. 8 in tithe)
A81: Rotted skins
A82: Shorn skins
A83: Total value of production (sum of the above)
A84: Value of sales
A86: Poultry stock
A87: Hens | B87: nothing
A88: Geese
A89: Capons (from chickens)
A90: Cocks & hens
A91: Total value of production (sum of the above)
A92: Value of sales
A94: Poultry production
A95: Eggs | B95: nothing
A96: Cocks & hens from churchscot of customary tenants
A97: Sum of above
A98: Total value of stock
A99: Value of sales
A101: Dairy Production
A102: Butter | B102: nothing
A103: Winter Cheese
A104: Summer Cheese
A105: Total value of production (sum of the above)
A106: Value of sales
B109: Total in £
A110: Total Production Value of all Output (Grange, Dairy, Livestock Sales, Wools, Skins - NO Mill) | B110: nothing
A111: Total Sales Value of all Output as defined above
A112: Total Sales of Corn + Issues of the Manor as recorded in account
A113: Production Value + Cash Receipts (excl. Arrears, Issues, Corn and Mill)
A115: % of capital expenses in terms of total production
...

Sheet Receipts
A1: TAUNTON BOROUGH MANOR RECEIPTS
B2: £ | C2: s | D2: d | F2: Total in £ | G2: Notes | I2: Error
A3: Rents
A4: rents of assize | B4: 22 | C4: 16 | D4: 2 | F4: =B4+C4/20+D4/240 -> 22.808333
A5: Total recorded in accounts | B5: 22 | C5: 16 | D5: 2 | F5: =B5+C5/20+D5/240 -> 22.808333
A6: Total | B6: =B4 -> 22 | C6: =C4 -> 16 | D6: =D4 -> 2 | F6: =B6+C6/20+D6/240 -> 22.808333 | I6: =F6-F5 -> 0
A8: Quittances & Defaults
A9: in quittances of two reeves for the year | C9: 4 | F9: =B9+C9/20+D9/240 -> 0.2
A10: in default of a certain tenement which belonged to Roginald le Dygher | D10: 6 | F10: =B10+C10/20+D10/240 -> 0.025
A11: one plot which belonged to Walter Pokoc | D11: 6 | F11: =B11+C11/20+D11/240 -> 0.025
A12: Total recorded in accounts | C12: 5 | F12: =B12+C12/20+D12/240 -> 0.25
A13: Total | B13: =SUM(B9:B11) -> 0 | C13: =SUM(C9:C11) -> 4 | D13: =SUM(D9:D11) -> 12 | F13: =B13+C13/20+D13/240 -> 0.25 | I13: =F13-F12 -> 0
A15: Perquisites
A16: from stallage this year | C16: 13 | F16: =B16+C16/20+D16/240 -> 0.65
A17: from those who brewed ale | B17: 3 | C17: 1 | F17: =B17+C17/20+D17/240 -> 3.05
A18: from those who brewed ale | B18: 3 | D18: 6 | F18: =B18+C18/20+D18/240 -> 3.025
A19: from toll corn sold this year | C19: 8 | F19: =B19+C19/20+D19/240 -> 0.4
A20: from tolls of the market | B20: 3 | C20: 10 | F20: =B20+C20/20+D20/240 -> 3.5
A21: from Thomas Segar | D21: 3 | F21: =B21+C21/20+D21/240 -> 0.0125
A22: from Thomas le Norays | D22: 6 | F22: =B22+C22/20+D22/240 -> 0.025
A23: from Robert le Ropere | D23: 6 | F23: =B23+C23/20+D23/240 -> 0.025
A24: from John Churihman | D24: 3 | F24: =B24+C24/20+D24/240 -> 0.0125
A25: from the bailiff | C25: 1 | F25: =B25+C25/20+D25/240 -> 0.05
A26: from Richard de la Lake | D26: 6 | F26: =B26+C26/20+D26/240 -> 0.025
A27: from Thomas le Lorm | D27: 3 | F27: =B27+C27/20+D27/240 -> 0.0125
A28: from John de Orchard | D28: 6 | F28: =B28+C28/20+D28/240 -> 0.025
A29: from John Balke | D29: 6 | F29: =B29+C29/20+D29/240 -> 0.025
A30: from John le Frye | D30: 3 | F30: =B30+C30/20+D30/240 -> 0.0125
A31: from Robert le Large | D31: 6 | F31: =B31+C31/20+D31/240 -> 0.025
A32: from a certain stranger | D32: 3 | F32: =B32+C32/20+D32/240 -> 0.0125
A33: from John Balke | D33: 6 | F33: =B33+C33/20+D33/240 -> 0.025
A34: from John Boveney | D34: 3 | F34: =B34+C34/20+D34/240 -> 0.0125
A35: from John Balke | D35: 6 | F35: =B35+C35/20+D35/240 -> 0.025
A36: from WIlliam Cridewey | D36: 3 | F36: =B36+C36/20+D36/240 -> 0.0125
A37: from Alice la Chalonere | D37: 3 | F37: =B37+C37/20+D37/240 -> 0.0125
... A39: from William le Flettere | D39: 3 | F39: =B39+C39/20+D39/240 -> 0.0125
A40: from Adam Akewombe | C40: 2 | D40: 6 | F40: =B40+C40/20+D40/240 -> 0.125
A41: from Adam Akewombe for transgression | D41: 3 | F41: =B41+C41/20+D41/240 -> 0.0125
A42: from John le Frye | D42: 3 | F42: =B42+C42/20+D42/240 -> 0.0125
A43: from William Galpyn | D43: 3 | F43: =B43+C43/20+D43/240 -> 0.0125
A44: from John Elys | D44: 6 | F44: =B44+C44/20+D44/240 -> 0.025
A45: from Nicholas le Whyte | C45: 1 | F45: =B45+C45/20+D45/240 -> 0.05
A46: from Walter de Buddelye | D46: 3 | F46: =B46+C46/20+D46/240 -> 0.0125
A47: from Gilber Dauwe | D47: 3 | F47: =B47+C47/20+D47/240 -> 0.0125
A48: from John Gulye | D48: 6 | F48: =B48+C48/20+D48/240 -> 0.025
A49: from Philip Leg | D49: 4 | F49: =B49+C49/20+D49/240 -> 0.016666667
A50: from Sevarus de Torre | D50: 2 | F50: =B50+C50/20+D50/240 -> 0.0083333333
A51: from Joan atte Mor | D51: 6 | F51: =B51+C51/20+D51/240 -> 0.025
A52: from Richard le Dygher | D52: 6 | F52: =B52+C52/20+D52/240 -> 0.025
A53: from John Balke | D53: 3 | F53: =B53+C53/20+D53/240 -> 0.0125
A54: frm Roginald Tatkelake | D54: 3 | F54: =B54+C54/20+D54/240 -> 0.0125
A55: from Matilda la Fatte | D55: 3 | F55: =B55+C55/20+D55/240 -> 0.0125
A56: from Roger Elyot of Tiverton | C56: 1 | F56: =B56+C56/20+D56/240 -> 0.05
A57: from Thomas Segar | D57: 3 | F57: =B57+C57/20+D57/240 -> 0.0125
A58: from William Byhsshop | D58: 3 | F58: =B58+C58/20+D58/240 -> 0.0125
A59: from Roger de Tyverton | C59: 1 | F59: =B59+C59/20+D59/240 -> 0.05
A60: from Richard Spyring | D60: 3 | F60: =B60+C60/20+D60/240 -> 0.0125
A61: from John Russel | D61: 3 | F61: =B61+C61/20+D61/240 -> 0.0125
A62: from a certain house beside the north gate | C62: 5 | F62: =B62+C62/20+D62/240 -> 0.25
A63: from a certain forge | C63: 1 | D63: 6 | F63: =B63+C63/20+D63/240 -> 0.075
A64: Total recorded in accounts | B64: 11 | C64: 17 | D64: 6 | F64: =B64+C64/20+D64/240 -> 11.875
A65: Total | B65: =SUM(B16:B63) -> 9 | C65: =SUM(C16:C63) -> 44 | D65: =SUM(D16:D63) -> 162 | F65: =B65+C65/20+D65/240 -> 11.875 | I65: =F65-F64 -> 0
A67: Total of all receipts recorded in accounts | B67: 34 | C67: 8 | D67: 8 | F67: =B67+C67/20+D67/240 -> 34.433333
A68: Total of all receipts (calculated here) | B68: =B65+B13+B6 -> 31 | C68: =C65+C13+C6 -> 64 | D68: =D65+D13+D6 -> 176 | F68: =B68+C68/20+D68/240 -> 34.933333 | I68: =F68-F67 -> 0.5
A69: Total of all receipts (calculated here) incl arrears

Sheet Expenses
A1: TAUNTON BOROUGH MANOR EXPENSES
B2: £ | C2: s | D2: d | F2: Total in £ | H2: Error | I2: Note
A3: nothing

Sheet Issues of the Grange
A1: TAUNTON BOROUGH GRANGE ACCOUNT
A3: nothing

Sheet Issues of the Mill
A1: TAUNTON BOROUGH MILL ACCOUNT
A3: nothing

Sheet Stock
A1: TAUNTON BOROUGH MANOR STOCK ACCOUNT
A3: nothing
