Workbook

Sheet Upton Overview
A1: UPTON OVERVIEW | B1: £ | C1: s | D1: d | G1: Total in £ | H1: Error
A3: CASH ACCOUNT
A4: RECEIPTS
A5: Arrears | G5: ='Upton Receipts'!F5 -> 5.9614583
A6: Rents of assize | G6: ='Upton Receipts'!F14 -> 1.1614583
A7: Quittances | G7: ='Upton Receipts'!F22 -> 0.7
A8: Defaults of rent | G8: ='Upton Receipts'!F27 -> 0.009375
A9: Annual reconizances
A10: Issues of the Manor | G10: ='Upton Receipts'!F39 -> 3.78125
A11: Sale of corn | G11: ='Upton Receipts'!F48 -> 7.0166667
A12: Entry and marriage fines
A13: Pleas & Perquisites | G13: ='Upton Receipts'!F51 -> 0.81666667
A14: Sum of the above (incl. arrears) | G14: =SUM(G5:G13) -> 19.446875
A15: Total recorded in the accounts excl. arrears? (p.10) | G15: ='Upton Receipts'!F55 -> 12.066667 | H15: =G14-G15 -> 7.3802083
A16: Total recorded in the accounts incl. arrears? (p.10) | G16: n/a
A18: EXPENSES
A19: Cost of ploughs | G19: ='Upton Expenses'!F14 -> 3.434375
A20: Purchase of corn
A21: Cost of carts and wagons | G21: ='Upton Expenses'!F25 -> 0.38125
A22: Cost of dairy
A23: Purchase of stock
A24: Sheepcote | G24: ='Upton Expenses'!F32 -> 0.225
A25: Cost of buildings | G25: ='Upton Expenses'!F44 -> 0.56458333
A26: Threshing | G26: ='Upton Expenses'!F53 -> 0.14270833
A27: Expenses of the harvest | G27: ='Upton Expenses'!F63 -> 0.40833333
A28: Stewards expenses
A29: Sum of the above | G29: =SUM(G19:G28) -> 5.15625
A30: Total of all expenses | G30: ='Upton Expenses'!F65 -> 5.1541667 | H30: =G29-G30 -> 0.0020833333
A31: Capital Expenses | G31: ='Upton Expenses'!F69 -> 1.4354167
A33: Owed by the reeve | G33: ='Upton Expenses'!F67 -> 6.9125
A34: From accounts
A36: Cash deliveries | G36: ='Upton Expenses'!F68 -> 0
A37: Cash delivers (Hindon Borough)
A38: Sum of the above | B38: =SUM(B36:B37) -> 0 | C38: =SUM(C36:C37) -> 0 | D38: =SUM(D36:D37) -> 0 | E38: =SUM(E36:E37) -> 0 | G38: =SUM(G36:G37) -> 0
A39: Total of all allowances and cash deliveries in accounts | B39: n/a
A41: Net amount owed | G41: ='Upton Expenses'!F67 -> 6.9125
A42: Net amount owed in accounts | H42: =G41-G42 -> 6.9125
A44: GRANGE ACCOUNT | B44: Total Production
A45: Grange | B45: qrs | C45: bus | G45: Value of total gross production in £ | H45: Value of total net production in £
A46: Wheat | B46: ='Issues of the Grange'!B5 -> 23 | C46: ='Issues of the Grange'!C5 -> 1 | G46: ='Issues of the Grange'!P5 -> 5.6599953 | H46: ='Issues of the Grange'!M18 -> 2.631133
A47: Curall | B47: ='Issues of the Grange'!B6 -> 6 | C47: ='Issues of the Grange'!C6 -> 0 | G47: ='Issues of the Grange'!P6 -> 0.6 | H47: ='Issues of the Grange'!M19 -> 0.6
A48: Barley | B48: ='Issues of the Grange'!B7 -> 34.5 | C48: ='Issues of the Grange'!C7 -> 0 | G48: ='Issues of the Grange'!P7 -> 5.175 | H48: ='Issues of the Grange'!M20 -> 1.575
A49: Oats | B49: ='Issues of the Grange'!B8 -> 32 | C49: ='Issues of the Grange'!C8 -> 6 | G49: ='Issues of the Grange'!P8 -> 3.8208333 | H49: ='Issues of the Grange'!M21 -> 1.6625
A50: Peas | B50: ='Issues of the Grange'!B9 -> 0 | C50: ='Issues of the Grange'!C9 -> 0 | G50: ='Issues of the Grange'!P9 -> 0 | H50: ='Issues of the Grange'!M22 -> 0
A51: Vetches | B51: ='Issues of the Grange'!B10 -> 7 | C51: ='Issues of the Grange'!C10 -> 6 | G51: ='Issues of the Grange'!P10 -> 0.75512821 | H51: ='Issues of the Grange'!M23 -> 0.475
A52: Total value of gross production (sum of the above) | B52: =SUM(B46:B51) -> 102.5 | C52: =SUM(C46:C51) -> 13 | G52: =SUM(G46:G51) -> 16.010957
A53: Total value of net production | G53: =SUM(H46:H51) -> 6.943633
A54: Value of sales | B54: ='Issues of the Grange'!N24 -> 7.0166667 | G54: ='Issues of the Grange'!N24 -> 7.0166667
A56: MILL ACCOUNT | B56: n/a
A57: Issues of the mill | B57: qrs | C57: bus | G57: £
A58: Wheat
A59: Oatmeal
A60: 1st grade malt
A61: 2nd grade malt
A62: Maslin
A63: Total value of production (sum of the above)
A64: Value of sales | G64: n/a
A66: STOCK ACCOUNT
A67: Livestock | B67: Inherited stock | C67: End-period stock | D67: Stockbuilding | F67: Sales in (£) | G67: Value of production (£) at sales prices
A68: Cart-horses | B68: =IFERROR(INDEX(Stock!$A$3:$S$91,MATCH('Upton Overview'!$A68,Stock!$A$3:$A$91,0),MATCH('Upton Overview'!B$67,Stock!$A$3:$S$3,0)),0) -> 0 | C68: =IFERROR(INDEX(Stock!$A$3:$S$91,MATCH('Upton Overview'!$A68,Stock!$A$3:$A$91,0),MATCH('Upton Overview'!C$67,Stock!$A$3:$S$3,0)),0) -> 0 | D68: =C68-B68 -> 0 | F68: =IFERROR(INDEX(Stock!$A$3:$S$91,MATCH('Upton Overview'!$A68,Stock!$A$3:$A$91,0),MATCH('Upton Overview'!F$67,Stock!$A$3:$S$3,0)),0) | G68: =IFERROR(INDEX(Stock!$A$3:$S$91,MATCH('Upton Overview'!$A68,Stock!$A$3:$A$91,0),MATCH('Upton Overview'!G$67,Stock!$A$3:$S$3,0)),0)
A69: Mares | B69: =IFERROR(INDEX(Stock!$A$3:$S$91,MATCH('Upton Overview'!$A69,Stock!$A$3:$A$91,0),MATCH('Upton Overview'!B$67,Stock!$A$3:$S$3,0)),0) -> 16 | C69: =IFERROR(INDEX(Stock!$A$3:$S$91,MATCH('Upton Overview'!$A69,Stock!$A$3:$A$91,0),MATCH('Upton Overview'!C$67,Stock!$A$3:$S$3,0)),0) -> 13 | D69: =C69-B69 -> -3 | F69: =IFERROR(INDEX(Stock!$A$3:$S$91,MATCH('Upton Overview'!$A69,Stock!$A$3:$A$91,0),MATCH('Upton Overview'!F$67,Stock!$A$3:$S$3,0)),0) -> 0.74166667 | G69: =IFERROR(INDEX(Stock!$A$3:$S$91,MATCH('Upton Overview'!$A69,Stock!$A$3:$A$91,0),MATCH('Upton Overview'!G$67,Stock!$A$3:$S$3,0)),0) -> 1.7305556
A70: Plough horses | B70: =IFERROR(INDEX(Stock!$A$3:$S$91,MATCH('Upton Overview'!$A70,Stock!$A$3:$A$91,0),MATCH('Upton Overview'!B$67,Stock!$A$3:$S$3,0)),0) -> 2 | C70: =IFERROR(INDEX(Stock!$A$3:$S$91,MATCH('Upton Overview'!$A70,Stock!$A$3:$A$91,0),MATCH('Upton Overview'!C$67,Stock!$A$3:$S$3,0)),0) -> 2 | D70: =C70-B70 -> 0 | F70: =IFERROR(INDEX(Stock!$A$3:$S$91,MATCH('Upton Overview'!$A70,Stock!$A$3:$A$91,0),MATCH('Upton Overview'!F$67,Stock!$A$3:$S$3,0)),0) | G70: =IFERROR(INDEX(Stock!$A$3:$S$91,MATCH('Upton Overview'!$A70,Stock!$A$3:$A$91,0),MATCH('Upton Overview'!G$67,Stock!$A$3:$S$3,0)),0)
A71: Colts (2 years) | B71: =IFERROR(INDEX(Stock!$A$3:$S$91,MATCH('Upton Overview'!$A71,Stock!$A$3:$A$91,0),MATCH('Upton Overview'!B$67,Stock!$A$3:$S$3,0)),0) -> 0 | C71: =IFERROR(INDEX(Stock!$A$3:$S$91,MATCH('Upton Overview'!$A71,Stock!$A$3:$A$91,0),MATCH('Upton Overview'!C$67,Stock!$A$3:$S$3,0)),0) -> 0 | D71: =C71-B71 -> 0 | F71: =IFERROR(INDEX(Stock!$A$3:$S$91,MATCH('Upton Overview'!$A71,Stock!$A$3:$A$91,0),MATCH('Upton Overview'!F$67,Stock!$A$3:$S$3,0)),0) | G71: =IFERROR(INDEX(Stock!$A$3:$S$91,MATCH('Upton Overview'!$A71,Stock!$A$3:$A$91,0),MATCH('Upton Overview'!G$67,Stock!$A$3:$S$3,0)),0)
A72: Colts (2 years) | B72: =IFERROR(INDEX(Stock!$A$3:$S$91,MATCH('Upton Overview'!$A72,Stock!$A$3:$A$91,0),MATCH('Upton Overview'!B$67,Stock!$A$3:$S$3,0)),0) -> 0 | C72: =IFERROR(INDEX(Stock!$A$3:$S$91,MATCH('Upton Overview'!$A72,Stock!$A$3:$A$91,0),MATCH('Upton Overview'!C$67,Stock!$A$3:$S$3,0)),0) -> 0 | D72: =C72-B72 -> 0 | F72: =IFERROR(INDEX(Stock!$A$3:$S$91,MATCH('Upton Overview'!$A72,Stock!$A$3:$A$91,0),MATCH('Upton Overview'!F$67,Stock!$A$3:$S$3,0)),0) | G72: =IFERROR(INDEX(Stock!$A$3:$S$91,MATCH('Upton Overview'!$A72,Stock!$A$3:$A$91,0),MATCH('Upton Overview'!G$67,Stock!$A$3:$S$3,0)),0)
A73: Colts (1 year) | B73: =IFERROR(INDEX(Stock!$A$3:$S$91,MATCH('Upton Overview'!$A73,Stock!$A$3:$A$91,0),MATCH('Upton Overview'!B$67,Stock!$A$3:$S$3,0)),0) -> 0 | C73: =IFERROR(INDEX(Stock!$A$3:$S$91,MATCH('Upton Overview'!$A73,Stock!$A$3:$A$91,0),MATCH('Upton Overview'!C$67,Stock!$A$3:$S$3,0)),0) -> 0 | D73: =C73-B73 -> 0 | F73: =IFERROR(INDEX(Stock!$A$3:$S$91,MATCH('Upton Overview'!$A73,Stock!$A$3:$A$91,0),MATCH('Upton Overview'!F$67,Stock!$A$3:$S$3,0)),0) | G73: =IFERROR(INDEX(Stock!$A$3:$S$91,MATCH('Upton Overview'!$A73,Stock!$A$3:$A$91,0),MATCH('Upton Overview'!G$67,Stock!$A$3:$S$3,0)),0)
A74: Foals | B74: =IFERROR(INDEX(Stock!$A$3:$S$91,MATCH('Upton Overview'!$A74,Stock!$A$3:$A$91,0),MATCH('Upton Overview'!B$67,Stock!$A$3:$S$3,0)),0) -> 0 | C74: =IFERROR(INDEX(Stock!$A$3:$S$91,MATCH('Upton Overview'!$A74,Stock!$A$3:$A$91,0),MATCH('Upton Overview'!C$67,Stock!$A$3:$S$3,0)),0) -> 0 | D74: =C74-B74 -> 0 | F74: =IFERROR(INDEX(Stock!$A$3:$S$91,MATCH('Upton Overview'!$A74,Stock!$A$3:$A$91,0),MATCH('Upton Overview'!F$67,Stock!$A$3:$S$3,0)),0) | G74: =IFERROR(INDEX(Stock!$A$3:$S$91,MATCH('Upton Overview'!$A74,Stock!$A$3:$A$91,0),MATCH('Upton Overview'!G$67,Stock!$A$3:$S$3,0)),0)
A75: Oxen | B75: =IFERROR(INDEX(Stock!$A$3:$S$91,MATCH('Upton Overview'!$A75,Stock!$A$3:$A$91,0),MATCH('Upton Overview'!B$67,Stock!$A$3:$S$3,0)),0) -> 0 | C75: =IFERROR(INDEX(Stock!$A$3:$S$91,MATCH('Upton Overview'!$A75,Stock!$A$3:$A$91,0),MATCH('Upton Overview'!C$67,Stock!$A$3:$S$3,0)),0) -> 0 | D75: =C75-B75 -> 0 | F75: =IFERROR(INDEX(Stock!$A$3:$S$91,MATCH('Upton Overview'!$A75,Stock!$A$3:$A$91,0),MATCH('Upton Overview'!F$67,Stock!$A$3:$S$3,0)),0) | G75: =IFERROR(INDEX(Stock!$A$3:$S$91,MATCH('Upton Overview'!$A75,Stock!$A$3:$A$91,0),MATCH('Upton Overview'!G$67,Stock!$A$3:$S$3,0)),0)
A76: Bulls | B76: =IFERROR(INDEX(Stock!$A$3:$S$91,MATCH('Upton Overview'!$A76,Stock!$A$3:$A$91,0),MATCH('Upton Overview'!B$67,Stock!$A$3:$S$3,0)),0) -> 0 | C76: =IFERROR(INDEX(Stock!$A$3:$S$91,MATCH('Upton Overview'!$A76,Stock!$A$3:$A$91,0),MATCH('Upton Overview'!C$67,Stock!$A$3:$S$3,0)),0) -> 0 | D76: =C76-B76 -> 0 | F76: =IFERROR(INDEX(Stock!$A$3:$S$91,MATCH('Upton Overview'!$A76,Stock!$A$3:$A$91,0),MATCH('Upton Overview'!F$67,Stock!$A$3:$S$3,0)),0) | G76: =IFERROR(INDEX(Stock!$A$3:$S$91,MATCH('Upton Overview'!$A76,Stock!$A$3:$A$91,0),MATCH('Upton Overview'!G$67,Stock!$A$3:$S$3,0)),0)
A77: Cows | B77: =IFERROR(INDEX(Stock!$A$3:$S$91,MATCH('Upton Overview'!$A77,Stock!$A$3:$A$91,0),MATCH('Upton Overview'!B$67,Stock!$A$3:$S$3,0)),0) -> 0 | C77: =IFERROR(INDEX(Stock!$A$3:$S$91,MATCH('Upton Overview'!$A77,Stock!$A$3:$A$91,0),MATCH('Upton Overview'!C$67,Stock!$A$3:$S$3,0)),0) -> 0 | D77: =C77-B77 -> 0 | F77: =IFERROR(INDEX(Stock!$A$3:$S$91,MATCH('Upton Overview'!$A77,Stock!$A$3:$A$91,0),MATCH('Upton Overview'!F$67,Stock!$A$3:$S$3,0)),0) | G77: =IFERROR(INDEX(Stock!$A$3:$S$91,MATCH('Upton Overview'!$A77,Stock!$A$3:$A$91,0),MATCH('Upton Overview'!G$67,Stock!$A$3:$S$3,0)),0)
A78: Steers | B78: =IFERROR(INDEX(Stock!$A$3:$S$91,MATCH('Upton Overview'!$A78,Stock!$A$3:$A$91,0),MATCH('Upton Overview'!B$67,Stock!$A$3:$S$3,0)),0) -> 0 | C78: =IFERROR(INDEX(Stock!$A$3:$S$91,MATCH('Upton Overview'!$A78,Stock!$A$3:$A$91,0),MATCH('Upton Overview'!C$67,Stock!$A$3:$S$3,0)),0) -> 0 | D78: =C78-B78 -> 0 | F78: =IFERROR(INDEX(Stock!$A$3:$S$91,MATCH('Upton Overview'!$A78,Stock!$A$3:$A$91,0),MATCH('Upton Overview'!F$67,Stock!$A$3:$S$3,0)),0) | G78: =IFERROR(INDEX(Stock!$A$3:$S$91,MATCH('Upton Overview'!$A78,Stock!$A$3:$A$91,0),MATCH('Upton Overview'!G$67,Stock!$A$3:$S$3,0)),0)
A79: Bullocks | B79: =IFERROR(INDEX(Stock!$A$3:$S$91,MATCH('Upton Overview'!$A79,Stock!$A$3:$A$91,0),MATCH('Upton Overview'!B$67,Stock!$A$3:$S$3,0)),0) -> 0 | C79: =IFERROR(INDEX(Stock!$A$3:$S$91,MATCH('Upton Overview'!$A79,Stock!$A$3:$A$91,0),MATCH('Upton Overview'!C$67,Stock!$A$3:$S$3,0)),0) -> 0 | D79: =C79-B79 -> 0 | F79: =IFERROR(INDEX(Stock!$A$3:$S$91,MATCH('Upton Overview'!$A79,Stock!$A$3:$A$91,0),MATCH('Upton Overview'!F$67,Stock!$A$3:$S$3,0)),0) | G79: =IFERROR(INDEX(Stock!$A$3:$S$91,MATCH('Upton Overview'!$A79,Stock!$A$3:$A$91,0),MATCH('Upton Overview'!G$67,Stock!$A$3:$S$3,0)),0)
... A93: Peacocks | B93: =IFERROR(INDEX(Stock!$A$3:$S$91,MATCH('Upton Overview'!$A93,Stock!$A$3:$A$91,0),MATCH('Upton Overview'!B$67,Stock!$A$3:$S$3,0)),0) -> 0 | C93: =IFERROR(INDEX(Stock!$A$3:$S$91,MATCH('Upton Overview'!$A93,Stock!$A$3:$A$91,0),MATCH('Upton Overview'!C$67,Stock!$A$3:$S$3,0)),0) -> 0 | D93: =C93-B93 -> 0 | F93: =IFERROR(INDEX(Stock!$A$3:$S$91,MATCH('Upton Overview'!$A93,Stock!$A$3:$A$91,0),MATCH('Upton Overview'!F$67,Stock!$A$3:$S$3,0)),0) | G93: =IFERROR(INDEX(Stock!$A$3:$S$91,MATCH('Upton Overview'!$A93,Stock!$A$3:$A$91,0),MATCH('Upton Overview'!G$67,Stock!$A$3:$S$3,0)),0)
A94: Total | G94: =SUM(G68:G93) -> 1.7305556
A95: Value of sales | G95: =SUM(F68:F93) -> 2.4854167
A97: Wool
A98: Fleeces | B98: =IFERROR(INDEX(Stock!$A$3:$S$91,MATCH('Upton Overview'!$A98,Stock!$A$3:$A$91,0),MATCH('Upton Overview'!B$67,Stock!$A$3:$S$3,0)),0) -> 0 | C98: =IFERROR(INDEX(Stock!$A$3:$S$91,MATCH('Upton Overview'!$A98,Stock!$A$3:$A$91,0),MATCH('Upton Overview'!C$67,Stock!$A$3:$S$3,0)),0) -> 0 | D98: =C98-B98 -> 0 | F98: =IFERROR(INDEX(Stock!$A$3:$S$91,MATCH('Upton Overview'!$A98,Stock!$A$3:$A$91,0),MATCH('Upton Overview'!F$67,Stock!$A$3:$S$3,0)),0) -> 0 | G98: =IFERROR(INDEX(Stock!$A$3:$S$91,MATCH('Upton Overview'!$A98,Stock!$A$3:$A$91,0),MATCH('Upton Overview'!G$67,Stock!$A$3:$S$3,0)),0) -> 5.74
A99: Coarse wool | B99: =IFERROR(INDEX(Stock!$A$3:$S$91,MATCH('Upton Overview'!$A99,Stock!$A$3:$A$91,0),MATCH('Upton Overview'!B$67,Stock!$A$3:$S$3,0)),0) -> 0 | C99: =IFERROR(INDEX(Stock!$A$3:$S$91,MATCH('Upton Overview'!$A99,Stock!$A$3:$A$91,0),MATCH('Upton Overview'!C$67,Stock!$A$3:$S$3,0)),0) -> 0 | D99: =C99-B99 -> 0 | F99: =IFERROR(INDEX(Stock!$A$3:$S$91,MATCH('Upton Overview'!$A99,Stock!$A$3:$A$91,0),MATCH('Upton Overview'!F$67,Stock!$A$3:$S$3,0)),0) | G99: =IFERROR(INDEX(Stock!$A$3:$S$91,MATCH('Upton Overview'!$A99,Stock!$A$3:$A$91,0),MATCH('Upton Overview'!G$67,Stock!$A$3:$S$3,0)),0)
A100: Lamb's wool | B100: =IFERROR(INDEX(Stock!$A$3:$S$91,MATCH('Upton Overview'!$A100,Stock!$A$3:$A$91,0),MATCH('Upton Overview'!B$67,Stock!$A$3:$S$3,0)),0) -> 0 | C100: =IFERROR(INDEX(Stock!$A$3:$S$91,MATCH('Upton Overview'!$A100,Stock!$A$3:$A$91,0),MATCH('Upton Overview'!C$67,Stock!$A$3:$S$3,0)),0) -> 0 | D100: =C100-B100 -> 0 | F100: =IFERROR(INDEX(Stock!$A$3:$S$91,MATCH('Upton Overview'!$A100,Stock!$A$3:$A$91,0),MATCH('Upton Overview'!F$67,Stock!$A$3:$S$3,0)),0) | G100: =IFERROR(INDEX(Stock!$A$3:$S$91,MATCH('Upton Overview'!$A100,Stock!$A$3:$A$91,0),MATCH('Upton Overview'!G$67,Stock!$A$3:$S$3,0)),0)
A101: Wool locks | B101: =IFERROR(INDEX(Stock!$A$3:$S$91,MATCH('Upton Overview'!$A101,Stock!$A$3:$A$91,0),MATCH('Upton Overview'!B$67,Stock!$A$3:$S$3,0)),0) -> 0 | C101: =IFERROR(INDEX(Stock!$A$3:$S$91,MATCH('Upton Overview'!$A101,Stock!$A$3:$A$91,0),MATCH('Upton Overview'!C$67,Stock!$A$3:$S$3,0)),0) -> 0 | D101: =C101-B101 -> 0 | F101: =IFERROR(INDEX(Stock!$A$3:$S$91,MATCH('Upton Overview'!$A101,Stock!$A$3:$A$91,0),MATCH('Upton Overview'!F$67,Stock!$A$3:$S$3,0)),0) -> 0 | G101: =IFERROR(INDEX(Stock!$A$3:$S$91,MATCH('Upton Overview'!$A101,Stock!$A$3:$A$91,0),MATCH('Upton Overview'!G$67,Stock!$A$3:$S$3,0)),0)
A102: Wool sold at shearing | B102: =IFERROR(INDEX(Stock!$A$3:$S$91,MATCH('Upton Overview'!$A102,Stock!$A$3:$A$91,0),MATCH('Upton Overview'!B$67,Stock!$A$3:$S$3,0)),0) -> 0 | C102: =IFERROR(INDEX(Stock!$A$3:$S$91,MATCH('Upton Overview'!$A102,Stock!$A$3:$A$91,0),MATCH('Upton Overview'!C$67,Stock!$A$3:$S$3,0)),0) -> 0 | D102: =C102-B102 -> 0 | F102: =IFERROR(INDEX(Stock!$A$3:$S$91,MATCH('Upton Overview'!$A102,Stock!$A$3:$A$91,0),MATCH('Upton Overview'!F$67,Stock!$A$3:$S$3,0)),0) | G102: =IFERROR(INDEX(Stock!$A$3:$S$91,MATCH('Upton Overview'!$A102,Stock!$A$3:$A$91,0),MATCH('Upton Overview'!G$67,Stock!$A$3:$S$3,0)),0)
A103: Total value of production (sum of the above) | G103: =SUM(G98:G102) -> 5.74
A104: Value of sales | G104: =SUM(F98:F102) -> 0
A106: Hides | G106: £
A107: Ox hides | B107: =IFERROR(INDEX(Stock!$A$3:$S$91,MATCH('Upton Overview'!$A107,Stock!$A$3:$A$91,0),MATCH('Upton Overview'!B$67,Stock!$A$3:$S$3,0)),0) -> 0 | C107: =IFERROR(INDEX(Stock!$A$3:$S$91,MATCH('Upton Overview'!$A107,Stock!$A$3:$A$91,0),MATCH('Upton Overview'!C$67,Stock!$A$3:$S$3,0)),0) -> 0 | D107: =C107-B107 -> 0 | F107: =IFERROR(INDEX(Stock!$A$3:$S$91,MATCH('Upton Overview'!$A107,Stock!$A$3:$A$91,0),MATCH('Upton Overview'!F$67,Stock!$A$3:$S$3,0)),0) | G107: =IFERROR(INDEX(Stock!$A$3:$S$91,MATCH('Upton Overview'!$A107,Stock!$A$3:$A$91,0),MATCH('Upton Overview'!G$67,Stock!$A$3:$S$3,0)),0)
A108: Cow hides | B108: =IFERROR(INDEX(Stock!$A$3:$S$91,MATCH('Upton Overview'!$A108,Stock!$A$3:$A$91,0),MATCH('Upton Overview'!B$67,Stock!$A$3:$S$3,0)),0) -> 0 | C108: =IFERROR(INDEX(Stock!$A$3:$S$91,MATCH('Upton Overview'!$A108,Stock!$A$3:$A$91,0),MATCH('Upton Overview'!C$67,Stock!$A$3:$S$3,0)),0) -> 0 | D108: =C108-B108 -> 0 | F108: =IFERROR(INDEX(Stock!$A$3:$S$91,MATCH('Upton Overview'!$A108,Stock!$A$3:$A$91,0),MATCH('Upton Overview'!F$67,Stock!$A$3:$S$3,0)),0) | G108: =IFERROR(INDEX(Stock!$A$3:$S$91,MATCH('Upton Overview'!$A108,Stock!$A$3:$A$91,0),MATCH('Upton Overview'!G$67,Stock!$A$3:$S$3,0)),0)
A109: Mare hides | B109: =IFERROR(INDEX(Stock!$A$3:$S$91,MATCH('Upton Overview'!$A109,Stock!$A$3:$A$91,0),MATCH('Upton Overview'!B$67,Stock!$A$3:$S$3,0)),0) -> 0 | C109: =IFERROR(INDEX(Stock!$A$3:$S$91,MATCH('Upton Overview'!$A109,Stock!$A$3:$A$91,0),MATCH('Upton Overview'!C$67,Stock!$A$3:$S$3,0)),0) -> 0 | D109: =C109-B109 -> 0 | F109: =IFERROR(INDEX(Stock!$A$3:$S$91,MATCH('Upton Overview'!$A109,Stock!$A$3:$A$91,0),MATCH('Upton Overview'!F$67,Stock!$A$3:$S$3,0)),0) | G109: =IFERROR(INDEX(Stock!$A$3:$S$91,MATCH('Upton Overview'!$A109,Stock!$A$3:$A$91,0),MATCH('Upton Overview'!G$67,Stock!$A$3:$S$3,0)),0)
A110: Steer hides | B110: =IFERROR(INDEX(Stock!$A$3:$S$91,MATCH('Upton Overview'!$A110,Stock!$A$3:$A$91,0),MATCH('Upton Overview'!B$67,Stock!$A$3:$S$3,0)),0) -> 0 | C110: =IFERROR(INDEX(Stock!$A$3:$S$91,MATCH('Upton Overview'!$A110,Stock!$A$3:$A$91,0),MATCH('Upton Overview'!C$67,Stock!$A$3:$S$3,0)),0) -> 0 | D110: =C110-B110 -> 0 | F110: =IFERROR(INDEX(Stock!$A$3:$S$91,MATCH('Upton Overview'!$A110,Stock!$A$3:$A$91,0),MATCH('Upton Overview'!F$67,Stock!$A$3:$S$3,0)),0) | G110: =IFERROR(INDEX(Stock!$A$3:$S$91,MATCH('Upton Overview'!$A110,Stock!$A$3:$A$91,0),MATCH('Upton Overview'!G$67,Stock!$A$3:$S$3,0)),0)
A111: Yearling Calf hides | B111: =IFERROR(INDEX(Stock!$A$3:$S$91,MATCH('Upton Overview'!$A111,Stock!$A$3:$A$91,0),MATCH('Upton Overview'!B$67,Stock!$A$3:$S$3,0)),0) -> 0 | C111: =IFERROR(INDEX(Stock!$A$3:$S$91,MATCH('Upton Overview'!$A111,Stock!$A$3:$A$91,0),MATCH('Upton Overview'!C$67,Stock!$A$3:$S$3,0)),0) -> 0 | D111: =C111-B111 -> 0 | F111: =IFERROR(INDEX(Stock!$A$3:$S$91,MATCH('Upton Overview'!$A111,Stock!$A$3:$A$91,0),MATCH('Upton Overview'!F$67,Stock!$A$3:$S$3,0)),0) | G111: =IFERROR(INDEX(Stock!$A$3:$S$91,MATCH('Upton Overview'!$A111,Stock!$A$3:$A$91,0),MATCH('Upton Overview'!G$67,Stock!$A$3:$S$3,0)),0)
A112: Calf hides | B112: =IFERROR(INDEX(Stock!$A$3:$S$91,MATCH('Upton Overview'!$A112,Stock!$A$3:$A$91,0),MATCH('Upton Overview'!B$67,Stock!$A$3:$S$3,0)),0) -> 0 | C112: =IFERROR(INDEX(Stock!$A$3:$S$91,MATCH('Upton Overview'!$A112,Stock!$A$3:$A$91,0),MATCH('Upton Overview'!C$67,Stock!$A$3:$S$3,0)),0) -> 0 | D112: =C112-B112 -> 0 | F112: =IFERROR(INDEX(Stock!$A$3:$S$91,MATCH('Upton Overview'!$A112,Stock!$A$3:$A$91,0),MATCH('Upton Overview'!F$67,Stock!$A$3:$S$3,0)),0) | G112: =IFERROR(INDEX(Stock!$A$3:$S$91,MATCH('Upton Overview'!$A112,Stock!$A$3:$A$91,0),MATCH('Upton Overview'!G$67,Stock!$A$3:$S$3,0)),0)
A113: Pig hides | B113: =IFERROR(INDEX(Stock!$A$3:$S$91,MATCH('Upton Overview'!$A113,Stock!$A$3:$A$91,0),MATCH('Upton Overview'!B$67,Stock!$A$3:$S$3,0)),0) -> 0 | C113: =IFERROR(INDEX(Stock!$A$3:$S$91,MATCH('Upton Overview'!$A113,Stock!$A$3:$A$91,0),MATCH('Upton Overview'!C$67,Stock!$A$3:$S$3,0)),0) -> 0 | D113: =C113-B113 -> 0 | F113: =IFERROR(INDEX(Stock!$A$3:$S$91,MATCH('Upton Overview'!$A113,Stock!$A$3:$A$91,0),MATCH('Upton Overview'!F$67,Stock!$A$3:$S$3,0)),0) | G113: =IFERROR(INDEX(Stock!$A$3:$S$91,MATCH('Upton Overview'!$A113,Stock!$A$3:$A$91,0),MATCH('Upton Overview'!G$67,Stock!$A$3:$S$3,0)),0)
A114: Weather woolskins | B114: =IFERROR(INDEX(Stock!$A$3:$S$91,MATCH('Upton Overview'!$A114,Stock!$A$3:$A$91,0),MATCH('Upton Overview'!B$67,Stock!$A$3:$S$3,0)),0) -> 0 | C114: =IFERROR(INDEX(Stock!$A$3:$S$91,MATCH('Upton Overview'!$A114,Stock!$A$3:$A$91,0),MATCH('Upton Overview'!C$67,Stock!$A$3:$S$3,0)),0) -> 0 | D114: =C114-B114 -> 0 | F114: =IFERROR(INDEX(Stock!$A$3:$S$91,MATCH('Upton Overview'!$A114,Stock!$A$3:$A$91,0),MATCH('Upton Overview'!F$67,Stock!$A$3:$S$3,0)),0) | G114: =IFERROR(INDEX(Stock!$A$3:$S$91,MATCH('Upton Overview'!$A114,Stock!$A$3:$A$91,0),MATCH('Upton Overview'!G$67,Stock!$A$3:$S$3,0)),0)
A115: Ram woolskins | B115: =IFERROR(INDEX(Stock!$A$3:$S$91,MATCH('Upton Overview'!$A115,Stock!$A$3:$A$91,0),MATCH('Upton Overview'!B$67,Stock!$A$3:$S$3,0)),0) -> 0 | C115: =IFERROR(INDEX(Stock!$A$3:$S$91,MATCH('Upton Overview'!$A115,Stock!$A$3:$A$91,0),MATCH('Upton Overview'!C$67,Stock!$A$3:$S$3,0)),0) -> 0 | D115: =C115-B115 -> 0 | F115: =IFERROR(INDEX(Stock!$A$3:$S$91,MATCH('Upton Overview'!$A115,Stock!$A$3:$A$91,0),MATCH('Upton Overview'!F$67,Stock!$A$3:$S$3,0)),0) | G115: =IFERROR(INDEX(Stock!$A$3:$S$91,MATCH('Upton Overview'!$A115,Stock!$A$3:$A$91,0),MATCH('Upton Overview'!G$67,Stock!$A$3:$S$3,0)),0)
A116: Ewe woolskins | B116: =IFERROR(INDEX(Stock!$A$3:$S$91,MATCH('Upton Overview'!$A116,Stock!$A$3:$A$91,0),MATCH('Upton Overview'!B$67,Stock!$A$3:$S$3,0)),0) -> 0 | C116: =IFERROR(INDEX(Stock!$A$3:$S$91,MATCH('Upton Overview'!$A116,Stock!$A$3:$A$91,0),MATCH('Upton Overview'!C$67,Stock!$A$3:$S$3,0)),0) -> 0 | D116: =C116-B116 -> 0 | F116: =IFERROR(INDEX(Stock!$A$3:$S$91,MATCH('Upton Overview'!$A116,Stock!$A$3:$A$91,0),MATCH('Upton Overview'!F$67,Stock!$A$3:$S$3,0)),0) | G116: =IFERROR(INDEX(Stock!$A$3:$S$91,MATCH('Upton Overview'!$A116,Stock!$A$3:$A$91,0),MATCH('Upton Overview'!G$67,Stock!$A$3:$S$3,0)),0)
A117: Hogg woolskins | B117: =IFERROR(INDEX(Stock!$A$3:$S$91,MATCH('Upton Overview'!$A117,Stock!$A$3:$A$91,0),MATCH('Upton Overview'!B$67,Stock!$A$3:$S$3,0)),0) -> 0 | C117: =IFERROR(INDEX(Stock!$A$3:$S$91,MATCH('Upton Overview'!$A117,Stock!$A$3:$A$91,0),MATCH('Upton Overview'!C$67,Stock!$A$3:$S$3,0)),0) -> 0 | D117: =C117-B117 -> 0 | F117: =IFERROR(INDEX(Stock!$A$3:$S$91,MATCH('Upton Overview'!$A117,Stock!$A$3:$A$91,0),MATCH('Upton Overview'!F$67,Stock!$A$3:$S$3,0)),0) | G117: =IFERROR(INDEX(Stock!$A$3:$S$91,MATCH('Upton Overview'!$A117,Stock!$A$3:$A$91,0),MATCH('Upton Overview'!G$67,Stock!$A$3:$S$3,0)),0)
A118: Woolskins (total) | B118: =IFERROR(INDEX(Stock!$A$3:$S$91,MATCH('Upton Overview'!$A118,Stock!$A$3:$A$91,0),MATCH('Upton Overview'!B$67,Stock!$A$3:$S$3,0)),0) -> 0 | C118: =IFERROR(INDEX(Stock!$A$3:$S$91,MATCH('Upton Overview'!$A118,Stock!$A$3:$A$91,0),MATCH('Upton Overview'!C$67,Stock!$A$3:$S$3,0)),0) -> 0 | D118: =C118-B118 -> 0 | F118: =IFERROR(INDEX(Stock!$A$3:$S$91,MATCH('Upton Overview'!$A118,Stock!$A$3:$A$91,0),MATCH('Upton Overview'!F$67,Stock!$A$3:$S$3,0)),0) -> 0.20416667 | G118: =IFERROR(INDEX(Stock!$A$3:$S$91,MATCH('Upton Overview'!$A118,Stock!$A$3:$A$91,0),MATCH('Upton Overview'!G$67,Stock!$A$3:$S$3,0)),0) -> 0.20416667
... A126: Shorn skins | B126: =IFERROR(INDEX(Stock!$A$3:$S$91,MATCH('Upton Overview'!$A126,Stock!$A$3:$A$91,0),MATCH('Upton Overview'!B$67,Stock!$A$3:$S$3,0)),0) -> 0 | C126: =IFERROR(INDEX(Stock!$A$3:$S$91,MATCH('Upton Overview'!$A126,Stock!$A$3:$A$91,0),MATCH('Upton Overview'!C$67,Stock!$A$3:$S$3,0)),0) -> 0 | D126: =C126-B126 -> 0 | F126: =IFERROR(INDEX(Stock!$A$3:$S$91,MATCH('Upton Overview'!$A126,Stock!$A$3:$A$91,0),MATCH('Upton Overview'!F$67,Stock!$A$3:$S$3,0)),0) | G126: =IFERROR(INDEX(Stock!$A$3:$S$91,MATCH('Upton Overview'!$A126,Stock!$A$3:$A$91,0),MATCH('Upton Overview'!G$67,Stock!$A$3:$S$3,0)),0)
A127: Total value of production (sum of the above) | G127: =SUM(G107:G126) -> 0.20416667
A128: Value of sales | G128: =SUM(F107:F126) -> 0.20416667
A130: Poultry stock | B130: nothing
A131: Hens | B131: =IFERROR(INDEX(Stock!$A$3:$S$91,MATCH('Upton Overview'!$A131,Stock!$A$3:$A$91,0),MATCH('Upton Overview'!B$67,Stock!$A$3:$S$3,0)),0) -> 0 | C131: =IFERROR(INDEX(Stock!$A$3:$S$91,MATCH('Upton Overview'!$A131,Stock!$A$3:$A$91,0),MATCH('Upton Overview'!C$67,Stock!$A$3:$S$3,0)),0) -> 0 | D131: =C131-B131 -> 0 | F131: =IFERROR(INDEX(Stock!$A$3:$S$91,MATCH('Upton Overview'!$A131,Stock!$A$3:$A$91,0),MATCH('Upton Overview'!F$67,Stock!$A$3:$S$3,0)),0) -> 0.18333333 | G131: =IFERROR(INDEX(Stock!$A$3:$S$91,MATCH('Upton Overview'!$A131,Stock!$A$3:$A$91,0),MATCH('Upton Overview'!G$67,Stock!$A$3:$S$3,0)),0) -> 0.18333333
...

Sheet Upton Receipts
A1: UPTON RECEIPTS
B2: £ | C2: s | D2: d | F2: Total in £ | G2: Error | H2: Notes
A4: Arrears
A5: arrears from previous year | B5: 5 | C5: 19 | D5: 2.75 | F5: =B5+C5/20+D5/240 -> 5.9614583
A6: of which delivered to treasurer of Wolvesey | B6: 1 | C6: 9 | F6: =B6+C6/20+D6/240 -> 1.45
A8: Rents of assize
A9: Feast of St. Andrew | C9: 7 | D9: 4 | F9: =B9+C9/20+D9/240 -> 0.36666667
A10: Palm Sunday | C10: 7 | D10: 4 | F10: =B10+C10/20+D10/240 -> 0.36666667
A11: Lammas | C11: 7 | D11: 4 | F11: =B11+C11/20+D11/240 -> 0.36666667
A12: Michaelmas | C12: 1 | D12: 2.75 | F12: =B12+C12/20+D12/240 -> 0.061458333
A13: Total recorded in accounts | B13: 1 | C13: 3 | D13: 2.75 | F13: =B13+C13/20+D13/240 -> 1.1614583
A14: Total | B14: =SUM(B9:B12) -> 0 | C14: =SUM(C9:C12) -> 22 | D14: =SUM(D9:D12) -> 14.75 | F14: =B14+C14/20+D14/240 -> 1.1614583 | G14: =F14-F13 -> 0
A16: Quittances
A17: in quittance of 1 reeve for the year | C17: 2 | F17: =B17+C17/20+D17/240 -> 0.1
A18: 3 ploughmen for the year | C18: 6 | F18: =B18+C18/20+D18/240 -> 0.3
A19: 1 shepherd for the year | C19: 2 | F19: =B19+C19/20+D19/240 -> 0.1
A20: 2 workers for the year | C20: 4 | F20: =B20+C20/20+D20/240 -> 0.2
A21: Total recorded in accounts | C21: 14 | F21: =B21+C21/20+D21/240 -> 0.7
A22: Total | B22: =SUM(B17:B20) -> 0 | C22: =SUM(C17:C20) -> 14 | D22: =SUM(D17:D20) -> 0 | F22: =B22+C22/20+D22/240 -> 0.7 | G22: =F22-F21 -> 0
A24: Defaults of rent
A25: 1 acre of land which John held dawn into demense | D25: 2.25 | F25: =B25+C25/20+D25/240 -> 0.009375
A26: Total recorded in accounts | D26: 2.25 | F26: =B26+C26/20+D26/240 -> 0.009375
A27: Total | B27: =SUM(B25:B25) -> 0 | C27: =SUM(C25:C25) -> 0 | D27: =SUM(D25:D25) -> 2.25 | F27: =B27+C27/20+D27/240 -> 0.009375 | G27: =F27-F26 -> 0
A29: Total of rents remaining | C29: 9 | D29: 0.5 | F29: =B29+C29/20+D29/240 -> 0.45208333
A31: Issues of the manor
A32: from 29 wethers sold | B32: 1 | C32: 14 | D32: 10.5 | F32: =B32+C32/20+D32/240 -> 1.74375
A33: from 3 feeble and sick oxen sold | C33: 14 | D33: 10 | F33: =B33+C33/20+D33/240 -> 0.74166667
A34: from hides of 7 oxen in murrain | C34: 18 | D34: 2 | F34: =B34+C34/20+D34/240 -> 0.90833333
A35: from skins of 13 wethers in murrain before shearing | C35: 3 | D35: 3 | F35: =B35+C35/20+D35/240 -> 0.1625
A36: from skins of 10 wethers after shearing | D36: 10 | F36: =B36+C36/20+D36/240 -> 0.041666667
A37: from 44 hens sold | C37: 3 | D37: 8 | F37: =B37+C37/20+D37/240 -> 0.18333333
A38: Total recorded in accounts | B38: 3 | C38: 15 | D38: 7.5 | F38: =B38+C38/20+D38/240 -> 3.78125
A39: Total | B39: =SUM(B32:B37) -> 1 | C39: =SUM(C32:C37) -> 52 | D39: =SUM(D32:D37) -> 43.5 | F39: =B39+C39/20+D39/240 -> 3.78125 | G39: =F39-F38 -> 0
A41: Sale of corn
A42: from 11qrs 1 bus of wheat sold | B42: 2 | C42: 14 | D42: 5.5 | F42: =B42+C42/20+D42/240 -> 2.7229167
A43: from 6 qrs of curall sold | C43: 12 | F43: =B43+C43/20+D43/240 -> 0.6
A44: from 10 qrs wrs 3 bus of barley sold | B44: 1 | C44: 11 | D44: 1.5 | F44: =B44+C44/20+D44/240 -> 1.55625
A45: from 14 qrs 2 bus of oats sold | B45: 1 | C45: 13 | D45: 3 | F45: =B45+C45/20+D45/240 -> 1.6625
A46: from 4 qrs and 7 bus of vetches sold | C46: 9 | D46: 6 | F46: =B46+C46/20+D46/240 -> 0.475
A47: Total recorded in accounts | B47: 7 | D47: 4 | F47: =B47+C47/20+D47/240 -> 7.0166667
A48: Total | B48: =SUM(B42:B46) -> 4 | C48: =SUM(C42:C46) -> 59 | D48: =SUM(D42:D46) -> 16 | F48: =B48+C48/20+D48/240 -> 7.0166667 | G48: =F48-F47 -> 0
A50: Pleas and perquisites
A51: from the amercements of the court this year | C51: 16 | D51: 4 | F51: =B51+C51/20+D51/240 -> 0.81666667
A53: Total of all receipts (sum of above excl. arrears) | B53: =SUM(B51,B48+B39+B27+B22+B14) -> 5 | C53: =SUM(C51,C48+C39+C27+C22+C14) -> 163 | D53: =SUM(D51,D48+D39+D27+D22+D14) -> 80.5 | F53: =B53+C53/20+D53/240 -> 13.485417
A54: Total of all receipts (sum of above incl. arrears) | B54: =B53+B5 -> 10 | C54: =C53+C5 -> 182 | D54: =D53+D5 -> 83.25 | F54: =B54+C54/20+D54/240 -> 19.446875
A55: Total of all receipts in account | B55: 12 | C55: 1 | D55: 4 | F55: =B55+C55/20+D55/240 -> 12.066667 | G55: =F55-F53 -> -1.41875

Sheet Upton Expenses
A1: UPTON EXPENSES
B2: £ | C2: s | D2: d | F2: Total in £ | G2: Error | H2: Notes
A3: Cost of Ploughs
A4: iron and steel bought for 2 ploughs | C4: 4 | D4: 9.5 | F4: =B4+C4/20+D4/240 -> 0.23958333
A5: 1 ploughshare | D5: 9 | F5: =B5+C5/20+D5/240 -> 0.0375
A6: 2 plough feet bought | D6: 6 | F6: =B6+C6/20+D6/240 -> 0.025
A7: 1 pair of wheels bought | D7: 2 | F7: =B7+C7/20+D7/240 -> 0.0083333333
A8: 2 yokes | D8: 2 | F8: =B8+C8/20+D8/240 -> 0.0083333333
A9: stipend of smith for ironwork of 2 ploughs | C9: 4 | F9: =B9+C9/20+D9/240 -> 0.2
A10: stipend of 1 oxherd | C10: 5 | F10: =B10+C10/20+D10/240 -> 0.25
A11: making 2 ploughs from lords timber | D11: 5 | F11: =B11+C11/20+D11/240 -> 0.020833333
A12: in 7 oxen bought due to others dying | B12: 2 | C12: 12 | D12: 10.75 | F12: =B12+C12/20+D12/240 -> 2.6447917
A13: Total recorded in accounts | B13: 3 | C13: 8 | D13: 8.25 | F13: =B13+C13/20+D13/240 -> 3.434375
A14: Total | B14: =SUM(B3:B12) -> 2 | C14: =SUM(C3:C12) -> 25 | D14: =SUM(D3:D12) -> 44.25 | F14: =B14+C14/20+D14/240 -> 3.434375 | G14: =F14-F13 -> 0
A15: Total capital expenses | B15: =SUM(B4:B9,B11) -> 0 | C15: =SUM(C4:C9,C11) -> 8 | D15: =SUM(D4:D9,D11) -> 33.5 | F15: =B15+C15/20+D15/240 -> 0.53958333
A17: Cost of Carts
A18: 4 tacks bought | D18: 3 | F18: =B18+C18/20+D18/240 -> 0.0125
A19: in 1 saddle pad | D19: 9 | F19: =B19+C19/20+D19/240 -> 0.0375
A20: in grease | D20: 1 | F20: =B20+C20/20+D20/240 -> 0.0041666667
A21: in shoeing 2 plough-horses | C21: 1 | D21: 5 | F21: =B21+C21/20+D21/240 -> 0.070833333
A22: in fitting cart with axels | D22: 1.5 | F22: =B22+C22/20+D22/240 -> 0.00625
A23: stipend of 1 carter | C23: 5 | F23: =B23+C23/20+D23/240 -> 0.25
A24: Total recorded in accounts | C24: 7 | D24: 7.5 | F24: =B24+C24/20+D24/240 -> 0.38125
A25: Total | B25: =SUM(B18:B23) -> 0 | C25: =SUM(C18:C23) -> 6 | D25: =SUM(D18:D23) -> 19.5 | F25: =B25+C25/20+D25/240 -> 0.38125 | G25: =F25-F24 -> 0
A26: Total capital expenses | B26: =SUM(B18:B22) -> 0 | C26: =SUM(C18:C22) -> 1 | D26: =SUM(D18:D22) -> 19.5 | F26: =B26+C26/20+D26/240 -> 0.13125
A28: Sheepcote
A29: washing and shearing sheep | D29: 6 | F29: =B29+C29/20+D29/240 -> 0.025
A30: grease bought | C30: 4 | F30: =B30+C30/20+D30/240 -> 0.2
A31: Total recorded in accounts | C31: 4 | D31: 6 | F31: =B31+C31/20+D31/240 -> 0.225
A32: Total | B32: =SUM(B29:B30) -> 0 | C32: =SUM(C29:C30) -> 4 | D32: =SUM(D29:D30) -> 6 | F32: =B32+C32/20+D32/240 -> 0.225 | G32: =F32-F31 -> 0
A33: Total capital expenses | B33: =SUM(B30) -> 0 | C33: =SUM(C30) -> 4 | D33: =SUM(D30) -> 0 | F33: =B33+C33/20+D33/240 -> 0.2
A35: Cost of Buildings
A36: roofing and mending hall and byre | D36: 7.5 | F36: =B36+C36/20+D36/240 -> 0.03125
A37: stipend of 1 man repairing wall around garden | C37: 2 | D37: 1 | F37: =B37+C37/20+D37/240 -> 0.10416667
A38: mending garden gate | D38: 2 | F38: =B38+C38/20+D38/240 -> 0.0083333333
A39: nails for same | D39: 1.5 | F39: =B39+C39/20+D39/240 -> 0.00625
A40: 1 lock bought | D40: 1.5 | F40: =B40+C40/20+D40/240 -> 0.00625
A41: stipend of 1 man re-roofing hay-barn and cart-house | C41: 1 | D41: 4 | F41: =B41+C41/20+D41/240 -> 0.066666667
A42: 2 casks bought for cider | C42: 6 | D42: 10 | F42: =B42+C42/20+D42/240 -> 0.34166667
A43: Total recorded in accounts | C43: 11 | D43: 3 | F43: =B43+C43/20+D43/240 -> 0.5625
A44: Total | B44: =SUM(B36:B42) -> 0 | C44: =SUM(C36:C42) -> 9 | D44: =SUM(D36:D42) -> 27.5 | F44: =B44+C44/20+D44/240 -> 0.56458333 | G44: =F44-F43 -> 0.0020833333
A45: Total capital expenses | B45: =B36+B37+B38+B39+B40+B41+B42 -> 0 | C45: =C36+C37+C38+C39+C40+C41+C42 -> 9 | D45: =D36+D37+D38+D39+D40+D41+D42 -> 27.5 | F45: =B45+C45/20+D45/240 -> 0.56458333
A47: Threshing
A48: threshing 7.5 qrs of wheat | C48: 1 | D48: 3 | F48: =B48+C48/20+D48/240 -> 0.0625
A49: winnowing the same | D49: 1.5 | F49: =B49+C49/20+D49/240 -> 0.00625
A50: in threshing 10.5 qrs of barley | C50: 1 | D50: 3.75 | F50: =B50+C50/20+D50/240 -> 0.065625
A51: in winnowing the same | D51: 2 | F51: =B51+C51/20+D51/240 -> 0.0083333333
A52: Total recorded in accounts | C52: 2 | D52: 10.25 | F52: =B52+C52/20+D52/240 -> 0.14270833
A53: Total | B53: =SUM(B48:B51) -> 0 | C53: =SUM(C48:C51) -> 2 | D53: =SUM(D48:D51) -> 10.25 | F53: =B53+C53/20+D53/240 -> 0.14270833 | G53: =F53-F52 -> 0
A55: Expenses of the Harvest
A56: weeding corn over and above labour service | C56: 1 | D56: 8 | F56: =B56+C56/20+D56/240 -> 0.083333333
A57: mowing and tossing meadow | D57: 4 | F57: =B57+C57/20+D57/240 -> 0.016666667
A58: cheese bought for the mowing and tossing | D58: 4 | F58: =B58+C58/20+D58/240 -> 0.016666667
A59: provision of household at harvest-time | C59: 1 | D59: 2 | F59: =B59+C59/20+D59/240 -> 0.058333333
A60: stipend of reep-reeve who is overseer of harvest | C60: 3 | F60: =B60+C60/20+D60/240 -> 0.15
A61: stipend of 1 stacker at harvest time | C61: 1 | D61: 8 | F61: =B61+C61/20+D61/240 -> 0.083333333
A62: Total recorded in accounts | C62: 8 | D62: 2 | F62: =B62+C62/20+D62/240 -> 0.40833333
A63: Total | B63: =SUM(B56:B61) -> 0 | C63: =SUM(C56:C61) -> 6 | D63: =SUM(D56:D61) -> 26 | F63: =B63+C63/20+D63/240 -> 0.40833333 | G63: =F63-F62 -> 0
A65: Total of all Expenses | B65: 5 | C65: 3 | D65: 1 | F65: =B65+C65/20+D65/240 -> 5.1541667
A66: Total of all Expenses (calculated) | B66: =SUM(B63,B53,B44,B32,B25,B14,) -> 2 | C66: =SUM(C63,C53,C44,C32,C25,C14,) -> 52 | D66: =SUM(D63,D53,D44,D32,D25,D14,) -> 133.5 | F66: =B66+C66/20+D66/240 -> 5.15625 | G66: =F66-F65 -> 0.0020833333
A67: And thus he owes | B67: 6 | C67: 18 | D67: 3 | F67: =B67+C67/20+D67/240 -> 6.9125
A68: Delivered to Sir Geoffrey, treasurer of Wolvesey | F68: =B68+C68/20+D68/240 -> 0
A69: Total capital expenses | B69: =SUM(B15,B26,B33,B45) -> 0 | C69: =SUM(C15,C26,C33,C45) -> 22 | D69: =SUM(D15,D26,D33,D45) -> 80.5 | F69: =B69+C69/20+D69/240 -> 1.4354167

Sheet Issues of the Grange
B1: The issue of the grange account gives the total "yield" at the top of each heading in curly brackets, measurements used: fold, qrs, bus
B2: In "Issues of the grange" (p.12-13) | G2: In "Sale of Corn" (p.7) | P2: Value of Total Production
A3: Gross output | B3: Quantity | D3: Additional bought-in | F3: Quantity | G3: Quantity noted as sold | J3: Difference Produced vs. Sold | K3: Price 1 | L3: Quantity 1 | M3: Price 2 | N3: Quantity 2 | O3: Unit price | P3: Value
B4: qrs | C4: bus | D4: qrs | E4: bus | F4: qrs | G4: qrs | H4: bus | I4: qrs | K4: £ | L4: qrs | M4: £ | N4: qrs | O4: £ per qr | P4: £
A5: Wheat | B5: 23 | C5: 1 | F5: =B5+D5+C5/8+E5/8 -> 23.125 | G5: 11 | H5: 1 | I5: =G5+H5/8 -> 11.125 | J5: =F5-I5 -> 12 | K5: =2+14/20+5.5/240 -> 2.7229167 | L5: =I5 -> 11.125 | O5: =IFERROR((K5+M5)/(L5+N5),0) -> 0.24475655 | P5: =O5*F5 -> 5.6599953
A6: Curall | B6: 6 | F6: =B6+D6+C6/8+E6/8 -> 6 | G6: 6 | I6: =G6+H6/8 -> 6 | J6: =F6-I6 -> 0 | K6: =12/20 -> 0.6 | L6: =I6 -> 6 | O6: =IFERROR((K6+M6)/(L6+N6),0) -> 0.1 | P6: =O6*F6 -> 0.6
A7: Barley | B7: 34.5 | F7: =B7+D7+C7/8+E7/8 -> 34.5 | G7: 10 | H7: 3 | I7: =G7+H7/8 -> 10.375 | J7: =F7-I7 -> 24.125 | K7: ='Upton Receipts'!F44 -> 1.55625 | L7: =I7 -> 10.375 | O7: =IFERROR((K7+M7)/(L7+N7),0) -> 0.15 | P7: =O7*F7 -> 5.175
A8: Oats | B8: 32 | C8: 6 | F8: =B8+D8+C8/8+E8/8 -> 32.75 | G8: 14 | H8: 2 | I8: =G8+H8/8 -> 14.25 | J8: =F8-I8 -> 18.5 | K8: ='Upton Receipts'!F45 -> 1.6625 | L8: =I8 -> 14.25 | O8: =IFERROR((K8+M8)/(L8+N8),0) -> 0.11666667 | P8: =O8*F8 -> 3.8208333
A9: Peas | F9: =B9+D9+C9/8+E9/8 -> 0 | I9: =G9+H9/8 -> 0 | J9: =F9-I9 -> 0 | L9: =I9 -> 0 | O9: =IFERROR((K9+M9)/(L9+N9),0) -> 0 | P9: =O9*F9 -> 0
A10: Vetches | B10: 7 | C10: 6 | F10: =B10+D10+C10/8+E10/8 -> 7.75 | G10: 4 | H10: 7 | I10: =G10+H10/8 -> 4.875 | J10: =F10-I10 -> 2.875 | K10: ='Upton Receipts'!F46 -> 0.475 | L10: =I10 -> 4.875 | O10: =IFERROR((K10+M10)/(L10+N10),0) -> 0.097435897 | P10: =O10*F10 -> 0.75512821
A12: Total Production | F12: =SUM(F5:F10) -> 104.125 | P12: =SUM(P5:P10) -> 16.010957 | Q12: Production value is significantly more, as much less was sold than what was produced
A13: Sales of corn (as recorded in accounts) | F13: =SUM(I5:I10) -> 46.625
A16: Net output | B16: Gross output | C16: Seed | F16: tithe | G16: to manorial servants & livestock | J16: Output net of tithe & seed & liveries to manorial servants | K16: in stock from last year | L16: Price | M16: Value of net output | N16: Value of sales (in "Sale of Corn")
B17: qrs | C17: qrs | D17: bus | E17: qrs | F17: qrs | G17: qrs | H17: bus | I17: qrs | J17: qrs | K17: qrs | L17: £ per qr | M17: £ | N17: £
A18: Wheat | B18: =F5 -> 23.125 | C18: 11 | E18: =C18+D18/8 -> 11 | G18: 1 | H18: 3 | I18: =G18+H18/8 -> 1.375 | J18: =B18-(E18+F18+I18) -> 10.75 | L18: =O5 -> 0.24475655 | M18: =L18*J18 -> 2.631133 | N18: ='Upton Receipts'!F42 -> 2.7229167
A19: Curall | B19: =F6 -> 6 | E19: =C19+D19/8 -> 0 | I19: =G19+H19/8 -> 0 | J19: =B19-(E19+F19+I19) -> 6 | L19: =O6 -> 0.1 | M19: =L19*J19 -> 0.6 | N19: ='Upton Receipts'!F43 -> 0.6
A20: Barley | B20: =F7 -> 34.5 | C20: 11 | D20: 6 | E20: =C20+D20/8 -> 11.75 | G20: 11.5 | H20: 6 | I20: =G20+H20/8 -> 12.25 | J20: =B20-(E20+F20+I20) -> 10.5 | L20: =O7 -> 0.15 | M20: =L20*J20 -> 1.575 | N20: ='Upton Receipts'!F44 -> 1.55625
A21: Oats | B21: =F8 -> 32.75 | C21: 15 | E21: =C21+D21/8 -> 15 | G21: 3.5 | I21: =G21+H21/8 -> 3.5 | J21: =B21-(E21+F21+I21) -> 14.25 | L21: =O8 -> 0.11666667 | M21: =L21*J21 -> 1.6625 | N21: ='Upton Receipts'!F45 -> 1.6625
A22: Peas | B22: =F9 -> 0 | E22: =C22+D22/8 -> 0 | I22: =G22+H22/8 -> 0 | J22: =B22-(E22+F22+I22) -> 0 | L22: =O9 -> 0 | M22: =L22*J22 -> 0
A23: Vetches | B23: =F10 -> 7.75 | C23: 1 | D23: 7 | E23: =C23+D23/8 -> 1.875 | G23: 1 | I23: =G23+H23/8 -> 1 | J23: =B23-(E23+F23+I23) -> 4.875 | L23: =O10 -> 0.097435897 | M23: =L23*J23 -> 0.475 | N23: ='Upton Receipts'!F46 -> 0.475
A24: Total | B24: =SUM(B18:B23) -> 104.125 | E24: =SUM(E18:E23) -> 39.625 | J24: =SUM(J18:J23) -> 46.375 | M24: =SUM(M18:M23) -> 6.943633 | N24: =SUM(N18:N23) -> 7.0166667

Sheet Stock
A1: EAST KNOYLE STOCK ACCOUNT
A3: Livestock | B3: Inherited stock | C3: added | D3: strays | E3: herbage | F3: sold | G3: in murrain | H3: accounted for elsewhere | I3: End-period stock | J3: cross-check | K3: price 1 | L3: units 1 | M3: price 2 | N3: units 2 | O3: Weight (weys) | P3: Unit price (£) | Q3: Value of production (£) at sales prices | R3: Sales in (£) | S3: Details
A4: Cart-horses | J4: =B4+C4-D4-E4-F4-G4-H4 -> 0 | P4: =IFERROR((K4+M4)/(L4+N4),"") | Q4: =IFERROR(C4*P4,"") | R4: =IFERROR(P4*F4,"")
A5: Mares | B5: 16 | C5: 7 | F5: 3 | G5: 7 | I5: 13 | J5: =B5+C5-D5-E5-F5-G5-H5 -> 13 | K5: ='Upton Receipts'!F33 -> 0.74166667 | L5: 3 | P5: =IFERROR((K5+M5)/(L5+N5),"") -> 0.24722222 | Q5: =IFERROR(C5*P5,"") -> 1.7305556 | R5: =IFERROR(P5*F5,"") -> 0.74166667
A6: Plough horses | B6: 2 | I6: 2 | J6: =B6+C6-D6-E6-F6-G6-H6 -> 2 | P6: =IFERROR((K6+M6)/(L6+N6),"") | Q6: =IFERROR(C6*P6,"") | R6: =IFERROR(P6*F6,"")
A7: Colts (2 years) | J7: =B7+C7-D7-E7-F7-G7-H7 -> 0 | P7: =IFERROR((K7+M7)/(L7+N7),"") | Q7: =IFERROR(C7*P7,"") | R7: =IFERROR(P7*F7,"")
A8: Colts (2 years) | J8: =B8+C8-D8-E8-F8-G8-H8 -> 0 | P8: =IFERROR((K8+M8)/(L8+N8),"") | Q8: =IFERROR(C8*P8,"") | R8: =IFERROR(P8*F8,"")
A9: Colts (1 year) | J9: =B9+C9-D9-E9-F9-G9-H9 -> 0 | P9: =IFERROR((K9+M9)/(L9+N9),"") | Q9: =IFERROR(C9*P9,"") | R9: =IFERROR(P9*F9,"")
A10: Foals | J10: =B10+C10-D10-E10-F10-G10-H10 -> 0 | P10: =IFERROR((K10+M10)/(L10+N10),"") | Q10: =IFERROR(C10*P10,"") | R10: =IFERROR(P10*F10,"")
A11: Oxen | J11: =B11+C11-D11-E11-F11-G11-H11 -> 0 | P11: =IFERROR((K11+M11)/(L11+N11),"") | Q11: =IFERROR(C11*P11,"") | R11: =IFERROR(P11*F11,"")
A12: Bulls | J12: =B12+C12-D12-E12-F12-G12-H12 -> 0 | P12: =IFERROR((K12+M12)/(L12+N12),"") | Q12: =IFERROR(C12*P12,"") | R12: =IFERROR(P12*F12,"")
A13: Cows | J13: =B13+C13-D13-E13-F13-G13-H13 -> 0 | P13: =IFERROR((K13+M13)/(L13+N13),"") | Q13: =IFERROR(C13*P13,"") | R13: =IFERROR(P13*F13,"")
A14: Steers | J14: =B14+C14-D14-E14-F14-G14-H14 -> 0 | P14: =IFERROR((K14+M14)/(L14+N14),"") | Q14: =IFERROR(C14*P14,"") | R14: =IFERROR(P14*F14,"")
A15: Bullocks | J15: =B15+C15-D15-E15-F15-G15-H15 -> 0 | P15: =IFERROR((K15+M15)/(L15+N15),"") | Q15: =IFERROR(C15*P15,"") | R15: =IFERROR(P15*F15,"")
A16: Yearlings | J16: =B16+C16-D16-E16-F16-G16-H16 -> 0 | P16: =IFERROR((K16+M16)/(L16+N16),"") | Q16: =IFERROR(C16*P16,"") | R16: =IFERROR(P16*F16,"")
A17: Calves | J17: =B17+C17-D17-E17-F17-G17-H17 -> 0 | P17: =IFERROR((K17+M17)/(L17+N17),"") | Q17: =IFERROR(C17*P17,"") | R17: =IFERROR(P17*F17,"")
A18: Wethers | B18: 313 | F18: 29 | G18: 26 | I18: 261 | J18: =B18+C18-D18-E18-F18-G18-H18 -> 258 | K18: ='Upton Receipts'!F32 -> 1.74375 | L18: 29 | P18: =IFERROR((K18+M18)/(L18+N18),"") -> 0.06012931 | Q18: =IFERROR(C18*P18,"") -> 0 | R18: =IFERROR(P18*F18,"") -> 1.74375
A19: Rams | J19: =B19+C19-D19-E19-F19-G19-H19 -> 0 | P19: =IFERROR((K19+M19)/(L19+N19),"") | Q19: =IFERROR(C19*P19,"") | R19: =IFERROR(P19*F19,"")
A20: Ewes | J20: =B20+C20-D20-E20-F20-G20-H20 -> 0 | P20: =IFERROR((K20+M20)/(L20+N20),"") | Q20: =IFERROR(C20*P20,"") | R20: =IFERROR(P20*F20,"")
A21: Hoggs | J21: =B21+C21-D21-E21-F21-G21-H21 -> 0 | P21: =IFERROR((K21+M21)/(L21+N21),"") | Q21: =IFERROR(C21*P21,"") | R21: =IFERROR(P21*F21,"")
A22: Lambs | J22: =B22+C22-D22-E22-F22-G22-H22 -> 0 | P22: =IFERROR((K22+M22)/(L22+N22),"") | Q22: =IFERROR(C22*P22,"") | R22: =IFERROR(P22*F22,"")
A23: Boars | J23: =B23+C23-D23-E23-F23-G23-H23 -> 0 | P23: =IFERROR((K23+M23)/(L23+N23),"") | Q23: =IFERROR(C23*P23,"") | R23: =IFERROR(P23*F23,"")
A24: Sows | J24: =B24+C24-D24-E24-F24-G24-H24 -> 0 | P24: =IFERROR((K24+M24)/(L24+N24),"") | Q24: =IFERROR(C24*P24,"") | R24: =IFERROR(P24*F24,"")
A25: Pigs | J25: =B25+C25-D25-E25-F25-G25-H25 -> 0 | P25: =IFERROR((K25+M25)/(L25+N25),"") | Q25: =IFERROR(C25*P25,"") | R25: =IFERROR(P25*F25,"")
A26: Hoggets | J26: =B26+C26-D26-E26-F26-G26-H26 -> 0 | P26: =IFERROR((K26+M26)/(L26+N26),"") | Q26: =IFERROR(C26*P26,"") | R26: =IFERROR(P26*F26,"")
A27: Piglets | J27: =B27+C27-D27-E27-F27-G27-H27 -> 0 | P27: =IFERROR((K27+M27)/(L27+N27),"") | Q27: =IFERROR(C27*P27,"") | R27: =IFERROR(P27*F27,"")
A28: Swans | J28: =B28+C28-D28-E28-F28-G28-H28 -> 0 | P28: =IFERROR((K28+M28)/(L28+N28),"") | Q28: =IFERROR(C28*P28,"") | R28: =IFERROR(P28*F28,"")
A29: Peacocks | J29: =B29+C29-D29-E29-F29-G29-H29 -> 0 | P29: =IFERROR((K29+M29)/(L29+N29),"") | Q29: =IFERROR(C29*P29,"") | R29: =IFERROR(P29*F29,"")
A30: Total | R30: =SUM(R4:R29) -> 2.4854167
P31: =IFERROR((K31+M31)/(L31+N31),"") | Q31: =IFERROR(C31*P31,"") | R31: =IFERROR(P31*F31,"")
P32: =IFERROR((K32+M32)/(L32+N32),"") | Q32: =IFERROR(C32*P32,"") | R32: =IFERROR(P32*F32,"")
A33: Wool | P33: =IFERROR((K33+M33)/(L33+N33),"") | Q33: =IFERROR(C33*P33,"") | R33: =IFERROR(P33*F33,"")
A34: Fleeces | C34: 287 | H34: 287 | I34: 0 | J34: =B34+C34-D34-E34-F34-G34-H34 -> 0 | P34: 0.02 | Q34: =IFERROR(C34*P34,"") -> 5.74 | R34: =IFERROR(P34*F34,"") -> 0 | S34: 286 Given to the Reeve of East Knoyle, one given to shepherd
A35: Coarse wool | J35: =B35+C37-D37-E37-F37-G37-H37 -> 0 | P35: =IFERROR((K35+M35)/(L35+N35),"") | Q35: =IFERROR(C35*P35,"") | R35: =IFERROR(P35*F35,"")
A36: Lamb's wool | J36: =B36+C36-D36-E36-F36-G36-H36 -> 0 | P36: =IFERROR((K36+M36)/(L36+N36),"") | Q36: =IFERROR(C36*P36,"") | R36: =IFERROR(P36*F36,"")
A37: Wool locks | C37: =O37 -> 0.14285714 | H37: =O37 -> 0.14285714 | I37: 0 | O37: =2*Assumptions!E7 -> 0.14285714 | P37: =IFERROR((K37+M37)/(L37+N37),"") | Q37: =IFERROR(C37*P37,"") | S37: given to East Knoyle
A38: Wool sold at shearing | J38: =B38+C38-D38-E38-F38-G38-H38 -> 0 | P38: =IFERROR((K38+M38)/(L38+N38),"") | Q38: =IFERROR(C38*P38,"") | R38: =IFERROR(P38*F38,"")
A39: Total | J39: =B39+C39-D39-E39-F39-G39-H39 -> 0 | P39: =IFERROR((K39+M39)/(L39+N39),"") | Q39: =SUM(Q34:Q38) -> 5.74 | R39: =IFERROR(P39*F39,"")
P40: =IFERROR((K40+M40)/(L40+N40),"") | Q40: =IFERROR(C40*P40,"") | R40: =IFERROR(P40*F40,"")
P41: =IFERROR((K41+M41)/(L41+N41),"") | Q41: =IFERROR(C41*P41,"") | R41: =IFERROR(P41*F41,"")
A42: Hides | P42: =IFERROR((K42+M42)/(L42+N42),"") | Q42: =IFERROR(C42*P42,"") | R42: =IFERROR(P42*F42,"")
A43: Ox hides | J43: =B43+C43-D43-E43-F43-G43-H43 -> 0 | P43: =IFERROR((K43+M43)/(L43+N43),"") | Q43: =IFERROR(C43*P43,"") | R43: =IFERROR(P43*F43,"")
A44: Cow hides | J44: =B44+C44-D44-E44-F44-G44-H44 -> 0 | P44: =IFERROR((K44+M44)/(L44+N44),"") | Q44: =IFERROR(C44*P44,"") | R44: =IFERROR(P44*F44,"")
A45: Mare hides | J45: =B45+C45-D45-E45-F45-G45-H45 -> 0 | P45: =IFERROR((K45+M45)/(L45+N45),"") | Q45: =IFERROR(C45*P45,"") | R45: =IFERROR(P45*F45,"")
A46: Steer hides | J46: =B46+C46-D46-E46-F46-G46-H46 -> 0 | P46: =IFERROR((K46+M46)/(L46+N46),"") | Q46: =IFERROR(C46*P46,"") | R46: =IFERROR(P46*F46,"")
A47: Yearling Calf hides | J47: =B47+C47-D47-E47-F47-G47-H47 -> 0 | P47: =IFERROR((K47+M47)/(L47+N47),"") | Q47: =IFERROR(C47*P47,"") | R47: =IFERROR(P47*F47,"")
A48: Calf hides | J48: =B48+C48-D48-E48-F48-G48-H48 -> 0 | P48: =IFERROR((K48+M48)/(L48+N48),"") | Q48: =IFERROR(C48*P48,"") | R48: =IFERROR(P48*F48,"")
A49: Pig hides | J49: =B49+C49-D49-E49-F49-G49-H49 -> 0 | P49: =IFERROR((K49+M49)/(L49+N49),"") | Q49: =IFERROR(C49*P49,"") | R49: =IFERROR(P49*F49,"")
A50: Weather woolskins | J50: =B50+C50-D50-E50-F50-G50-H50 -> 0 | P50: =IFERROR((K50+M50)/(L50+N50),"") | Q50: =IFERROR(C50*P50,"") | R50: =IFERROR(P50*F50,"")
A51: Ram woolskins | J51: =B51+C51-D51-E51-F51-G51-H51 -> 0 | P51: =IFERROR((K51+M51)/(L51+N51),"") | Q51: =IFERROR(C51*P51,"") | R51: =IFERROR(P51*F51,"")
A52: Ewe woolskins | J52: =B52+C52-D52-E52-F52-G52-H52 -> 0 | P52: =IFERROR((K52+M52)/(L52+N52),"") | Q52: =IFERROR(C52*P52,"") | R52: =IFERROR(P52*F52,"")
A53: Hogg woolskins | J53: =B53+C53-D53-E53-F53-G53-H53 -> 0 | P53: =IFERROR((K53+M53)/(L53+N53),"") | Q53: =IFERROR(C53*P53,"") | R53: =IFERROR(P53*F53,"")
A54: Woolskins (total) | C54: 23 | F54: 23 | I54: 0 | J54: =B54+C54-D54-E54-F54-G54-H54 -> 0 | K54: ='Upton Receipts'!F35 -> 0.1625 | L54: 13 | M54: ='Upton Receipts'!F36 -> 0.041666667 | N54: 10 | P54: =IFERROR((K54+M54)/(L54+N54),"") -> 0.0088768116 | Q54: =IFERROR(C54*P54,"") -> 0.20416667 | R54: =IFERROR(P54*F54,"") -> 0.20416667
A55: Wether bareskins | J55: =B55+C55-D55-E55-F55-G55-H55 -> 0 | P55: =IFERROR((K55+M55)/(L55+N55),"") | Q55: =IFERROR(C55*P55,"") | R55: =IFERROR(P55*F55,"")
A56: Ram bareskins | J56: =B56+C56-D56-E56-F56-G56-H56 -> 0 | P56: =IFERROR((K56+M56)/(L56+N56),"") | Q56: =IFERROR(C56*P56,"") | R56: =IFERROR(P56*F56,"")
A57: Ewe bareskins | J57: =B57+C57-D57-E57-F57-G57-H57 -> 0 | P57: =IFERROR((K57+M57)/(L57+N57),"") | Q57: =IFERROR(C57*P57,"") | R57: =IFERROR(P57*F57,"")
A58: Hogg bareskins | J58: =B58+C58-D58-E58-F58-G58-H58 -> 0 | P58: =IFERROR((K58+M58)/(L58+N58),"") | Q58: =IFERROR(C58*P58,"") | R58: =IFERROR(P58*F58,"")
A59: Bareskins (total) | J59: =B59+C59-D59-E59-F59-G59-H59 -> 0 | P59: =IFERROR((K59+M59)/(L59+N59),"") | Q59: =IFERROR(C59*P59,"") | R59: =IFERROR(P59*F59,"")
A60: Lambskins | J60: =B60+C60-D60-E60-F60-G60-H60 -> 0 | P60: =IFERROR((K60+M60)/(L60+N60),"") | Q60: =IFERROR(C60*P60,"") | R60: =IFERROR(P60*F60,"")
A61: Rotted skins | J61: =B61+C61-D61-E61-F61-G61-H61 -> 0 | P61: =IFERROR((K61+M61)/(L61+N61),"") | Q61: =IFERROR(C61*P61,"") | R61: =IFERROR(P61*F61,"")
A62: Shorn skins | J62: =B62+C62-D62-E62-F62-G62-H62 -> 0 | P62: =IFERROR((K62+M62)/(L62+N62),"") | Q62: =IFERROR(C62*P62,"") | R62: =IFERROR(P62*F62,"")
A63: Total | J63: =B63+C63-D63-E63-F63-G63-H63 -> 0 | P63: =IFERROR((K63+M63)/(L63+N63),"") | Q63: =IFERROR(C63*P63,"") | R63: =SUM(R43:R62) -> 0.20416667
P64: =IFERROR((K64+M64)/(L64+N64),"") | Q64: =IFERROR(C64*P64,"") | R64: =IFERROR(P64*F64,"")
A65: Poultry stock | P65: =IFERROR((K65+M65)/(L65+N65),"") | Q65: =IFERROR(C65*P65,"") | R65: =IFERROR(P65*F65,"")
A66: Hens | C66: 44 | F66: 44 | I66: 0 | J66: =B66+C66-D66-E66-F66-G66-H66 -> 0 | K66: ='Upton Receipts'!F37 -> 0.18333333 | L66: 44 | P66: =IFERROR((K66+M66)/(L66+N66),"") -> 0.0041666667 | Q66: =IFERROR(C66*P66,"") -> 0.18333333 | R66: =IFERROR(P66*F66,"") -> 0.18333333
A67: Geese | J67: =B67+C67-D67-E67-F67-G67-H67 -> 0 | P67: =IFERROR((K67+M67)/(L67+N67),"") | Q67: =IFERROR(C67*P67,"") | R67: =IFERROR(P67*F67,"")
A68: Capons (from chickens) | J68: =B68+C68-D68-E68-F68-G68-H68 -> 0 | P68: =IFERROR((K68+M68)/(L68+N68),"") | Q68: =IFERROR(C68*P68,"") | R68: =IFERROR(P68*F68,"")
A69: Cocks & hens | J69: =B69+C69-D69-E69-F69-G69-H69 -> 0 | P69: =IFERROR((K69+M69)/(L69+N69),"") | Q69: =IFERROR(C69*P69,"") | R69: =IFERROR(P69*F69,"")
A70: Total | J70: =B70+C70-D70-E70-F70-G70-H70 -> 0 | P70: =IFERROR((K70+M70)/(L70+N70),"") | Q70: =IFERROR(C70*P70,"") | R70: =SUM(R66:R69) -> 0.18333333
P71: =IFERROR((K71+M71)/(L71+N71),"") | Q71: =IFERROR(C71*P71,"") | R71: =IFERROR(P71*F71,"")
A72: Poultry production | P72: =IFERROR((K72+M72)/(L72+N72),"") | Q72: =IFERROR(C72*P72,"") | R72: =IFERROR(P72*F72,"")
A73: Eggs | J73: =B73+C73-D73-E73-F73-G73-H73 -> 0 | P73: =IFERROR((K73+M73)/(L73+N73),"") | Q73: =IFERROR(C73*P73,"") | R73: =IFERROR(P73*F73,"")
A74: Cocks & hens from churchscot of customary tenants | J74: =B74+C74-D74-E74-F74-G74-H74 -> 0 | P74: =IFERROR((K74+M74)/(L74+N74),"") | Q74: =IFERROR(C74*P74,"") | R74: =IFERROR(P74*F74,"")
J75: =B75+C75-D75-E75-F75-G75-H75 -> 0 | P75: =IFERROR((K75+M75)/(L75+N75),"") | Q75: =IFERROR(C75*P75,"") | R75: =IFERROR(P75*F75,"")
J76: =B76+C76-D76-E76-F76-G76-H76 -> 0 | P76: =IFERROR((K76+M76)/(L76+N76),"") | Q76: =IFERROR(C76*P76,"") | R76: =IFERROR(P76*F76,"")
A77: Meat | P77: =IFERROR((K77+M77)/(L77+N77),"") | Q77: =IFERROR(C77*P77,"") | R77: =IFERROR(P77*F77,"")
A78: Beef | J78: =B78+C78-D78-E78-F78-G78-H78 -> 0 | P78: =IFERROR((K78+M78)/(L78+N78),"") | Q78: =IFERROR(C78*P78,"") | R78: =IFERROR(P78*F78,"")
A79: Mutton | J79: =B79+C79-D79-E79-F79-G79-H79 -> 0 | P79: =IFERROR((K79+M79)/(L79+N79),"") | Q79: =IFERROR(C79*P79,"") | R79: =IFERROR(P79*F79,"")
A80: Pork | J80: =B80+C80-D80-E80-F80-G80-H80 -> 0 | P80: =IFERROR((K80+M80)/(L80+N80),"") | Q80: =IFERROR(C80*P80,"") | R80: =IFERROR(P80*F80,"")
J81: =B81+C81-D81-E81-F81-G81-H81 -> 0 | P81: =IFERROR((K81+M81)/(L81+N81),"") | Q81: =IFERROR(C81*P81,"") | R81: =IFERROR(P81*F81,"")
J82: =B82+C82-D82-E82-F82-G82-H82 -> 0 | P82: =IFERROR((K82+M82)/(L82+N82),"") | Q82: =IFERROR(C82*P82,"") | R82: =IFERROR(P82*F82,"")
A83: Cheese | J83: =B83+C83-D83-E83-F83-G83-H83 -> 0 | P83: =IFERROR((K83+M83)/(L83+N83),"") | Q83: =IFERROR(C83*P83,"") | R83: =IFERROR(P83*F83,"")
A84: Winter cheese | J84: =B84+C84-D84-E84-F84-G84-H84 -> 0 | P84: =IFERROR((K84+M84)/(L84+N84),"") | Q84: =IFERROR(C84*P84,"") | R84: =IFERROR(P84*F84,"")
A85: Summer cheese | J85: =B85+C85-D85-E85-F85-G85-H85 -> 0 | P85: =IFERROR((K85+M85)/(L85+N85),"") | Q85: =IFERROR(C85*P85,"") | R85: =IFERROR(P85*F85,"")
J86: =B86+C86-D86-E86-F86-G86-H86 -> 0 | P86: =IFERROR((K86+M86)/(L86+N86),"") | Q86: =IFERROR(C86*P86,"") | R86: =IFERROR(P86*F86,"")
J87: =B87+C87-D87-E87-F87-G87-H87 -> 0 | P87: =IFERROR((K87+M87)/(L87+N87),"") | Q87: =IFERROR(C87*P87,"") | R87: =IFERROR(P87*F87,"")
A88: Butter | J88: =B88+C88-D88-E88-F88-G88-H88 -> 0 | P88: =IFERROR((K88+M88)/(L88+N88),"") | Q88: =IFERROR(C88*P88,"") | R88: =IFERROR(P88*F88,"")
P89: =IFERROR((K89+M89)/(L89+N89),"") | Q89: =IFERROR(C89*P89,"") | R89: =IFERROR(P89*F89,"")
P90: =IFERROR((K90+M90)/(L90+N90),"") | Q90: =IFERROR(C90*P90,"") | R90: =IFERROR(P90*F90,"")
A91: Cider | C91: 2 | I91: 2 | J91: =B91+C91-D91-E91-F91-G91-H91 -> 2 | P91: =IFERROR((K91+M91)/(L91+N91),"") | Q91: =IFERROR(C91*P91,"") | R91: =IFERROR(P91*F91,"")
A92: Total | J92: =B92+C92-D92-E92-F92-G92-H92 -> 0 | P92: =IFERROR((K92+M92)/(L92+N92),"") | Q92: =IFERROR(C92*P92,"") | R92: =IFERROR(P92*F92,"")
P93: =IFERROR((K93+M93)/(L93+N93),"") | Q93: =IFERROR(C93*P93,"") | R93: =IFERROR(P93*F93,"")
P94: =IFERROR((K94+M94)/(L94+N94),"") | Q94: =IFERROR(C94*P94,"") | R94: =IFERROR(P94*F94,"")
P95: =IFERROR((K95+M95)/(L95+N95),"") | Q95: =IFERROR(C95*P95,"") | R95: =IFERROR(P95*F95,"")
P96: =IFERROR((K96+M96)/(L96+N96),"") | Q96: =IFERROR(C96*P96,"") | R96: =IFERROR(P96*F96,"")

Sheet Assumptions
A1: ASSUMPTIONS
B3: Weights | C3: Value (in lbs) | D3: Value (in cloves) | E3: Value (in weys) | F3: Value (in stone)
B4: Lbs | C4: 1 | D4: =C4/C5 -> 0.14285714 | E4: =C4/C6 -> 0.0057142857 | F4: =C4/C7 -> 0.08
B5: Cloves | C5: 7 | D5: 1 | E5: =C5/C6 -> 0.04 | F5: =C7/C5 -> 1.7857143
B6: Wey | C6: 175 | D6: =C6/C5 -> 25 | E6: =C6/C6 -> 1 | F6: =C7/C6 -> 0.071428571
B7: Stone | C7: =175/14 -> 12.5 | D7: =C5/C7 -> 0.56 | E7: =C7/C6 -> 0.071428571 | F7: 1
