Workbook

Sheet Overview
A1: DOWNTONBOROUGH OVERVIEW - COMPLETED | B1: Total in £ | C1: Error | D1: Note
A2: CASH ACCOUNT
A3: RECEIPTS
A4: Arrears total | B4: 0.78
A5: Rents of assize total | B5: 6.33
A6: Quittances total
A7: Defaults of rent total
A8: Defaults of rent through the pestilence total
A9: Cotlands defaults total
A10: Cotlands total
A11: Total of quittances and defaults of rent total
A12: Total of rents remaining clear total | B12: 6.5
A13: Farms total
A14: Annual recognizances total
A15: Issues of the Manor total
A16: Issues of the tenements in the lord's hands total
A17: Sale of labour services total
A18: Sale of corn total
A19: Entry and marriage fines total
A20: Pleas & perquisites total | B20: 2.67
A21: Forfeited chattels total
A22: Farm of the demesne land total
A23: Total of all receipts (calculated here) | B23: =SUM(B5:B11)
A24: Total of all receipts (calculated here) incl arrears | B24: =SUM(B4:B11)
A25: Total recorded in the accounts excl. arrears | B25: ='Receipts'!F20 | C25: =B23-B25
A26: Total recorded in the accounts incl. arrears | B26: ='Receipts'!F21
A29: EXPENSES
A30: Cost of ploughs total
A31: Purchase of corn total
A32: Cost of carts and wagons total
A33: Cost of dairy total
A34: Purchase of stock total
A35: Sheepcote total
A36: Cost of buildings total
A37: Threshing total
A38: Barley expenses
A39: Expenses of the harvest total
A40: Necessary expenses
... A43: Annual fees
A44: Total of all expenses per account | B44: 0
A45: Total of all expenses (calculated here) | B45: 0
A46: Total fixed investment
A47: Total Demesne fixed investment
A49: Owed by the reeve | B49: =B23-B45
A50: From accounts
A52: Allowances
A53: Cash deliveries | B53: 8.95
A54: Sum of the above | B54: =SUM(B52:B53)
A55: Total of all allowances and cash deliveries in accounts
A57: Net amount owed | B57: =B50-B54
A58: Net amount owed in accounts
A60: GRANGE ACCOUNT | B60: Total Production | D60: Value of total gross production in £ | E60: Value of total net production in £
A61: Grange | B61: qrs | C61: bus
A62: Wheat | B62: 0 | C62: 0 | D62: 0 | E62: 0
A63: Rye | B63: 0 | C63: 0 | D63: 0 | E63: 0
A64: Dredge | B64: 0 | C64: 0 | D64: 0 | E64: 0
A65: Curall | B65: 0 | C65: 0 | D65: 0 | E65: 0
A66: Barley | B66: 0 | C66: 0 | D66: 0 | E66: 0
A67: Oats | B67: 0 | C67: 0 | D67: 0 | E67: 0
A68: Beans | B68: 0 | C68: 0 | D68: 0 | E68: 0
A69: Peas | B69: 0 | C69: 0 | D69: 0 | E69: 0
A70: Vetches | B70: 0 | C70: 0 | D70: 0 | E70: 0
A71: Total value of gross production (sum of the above) | E71: =SUM(D62:D70)
A72: Total value of net production | E72: =SUM(E62:E70)
A73: Value of sales | E73: 0
A75: MILL ACCOUNT | B75: Total Production | D75: Total in £
A76: Issues of the mill | B76: qrs | C76: bus
A77: Wheat
A78: Oatmeal
A79: 1st grade malt
A80: 2nd grade malt
A81: Maslin
A82: Total value of production (sum of the above)
A83: Value of sales
A85: STOCK ACCOUNT
A86: Livestock | B86: Begin stock | C86: End stock | D86: Stockbuilding | F86: Value of stock in £ | G86: Value of stockbuilding
A87: Cart-horses | B87: 0 | C87: ='Stock'!L5 | D87: =C87-B87 | F87: ='Stock'!L5*'Stock'!O5 | G87: =D87*'Stock'!O5
A88: Mares | B88: 0 | C88: ='Stock'!L6 | D88: =C88-B88 | F88: ='Stock'!L6*'Stock'!O6 | G88: =D88*'Stock'!O6
A89: Plough horses | B89: 0 | C89: ='Stock'!L7 | D89: =C89-B89 | F89: ='Stock'!L7*'Stock'!O7 | G89: =D89*'Stock'!O7
A90: Colts (2 years) | B90: 0 | C90: ='Stock'!L9 | D90: =C90-B90 | F90: ='Stock'!L9*'Stock'!O9 | G90: =D90*'Stock'!O9
A91: Colts (2 years) | B91: 0 | C91: ='Stock'!L9 | D91: =C91-B91 | F91: ='Stock'!L9*'Stock'!O9 | G91: =D91*'Stock'!O9
A92: Colts (1 year) | B92: 0 | C92: ='Stock'!L10 | D92: =C92-B92 | F92: ='Stock'!L10*'Stock'!O10 | G92: =D92*'Stock'!O10
A93: Foals | B93: 0 | C93: ='Stock'!L11 | D93: =C93-B93 | F93: ='Stock'!L11*'Stock'!O11 | G93: =D93*'Stock'!O11
A94: Oxen | B94: 0 | C94: ='Stock'!L12 | D94: =C94-B94 | F94: ='Stock'!L12*'Stock'!O12 | G94: =D94*'Stock'!O12
A95: Bulls | B95: 0 | C95: ='Stock'!L13 | D95: =C95-B95 | F95: ='Stock'!L13*'Stock'!O13 | G95: =D95*'Stock'!O13
A96: Cows | B96: 0 | C96: ='Stock'!L14 | D96: =C96-B96 | F96: ='Stock'!L14*'Stock'!O14 | G96: =D96*'Stock'!O14
A97: Steers | B97: 0 | C97: ='Stock'!L15 | D97: =C97-B97 | F97: ='Stock'!L15*'Stock'!O15 | G97: =D97*'Stock'!O15
A98: Bullocks | B98: 0 | C98: ='Stock'!L16 | D98: =C98-B98 | F98: ='Stock'!L16*'Stock'!O16 | G98: =D98*'Stock'!O16
A99: Yearlings | B99: 0 | C99: ='Stock'!L17 | D99: =C99-B99 | F99: ='Stock'!L17*'Stock'!O17 | G99: =D99*'Stock'!O17
A100: Calves | B100: 0 | C100: ='Stock'!L18 | D100: =C100-B100 | F100: ='Stock'!L18*'Stock'!O18 | G100: =D100*'Stock'!O18
A101: Wethers | B101: 0 | C101: ='Stock'!L19 | D101: =C101-B101 | F101: ='Stock'!L19*'Stock'!O19 | G101: =D101*'Stock'!O19
A102: Rams | B102: 0 | C102: ='Stock'!L20 | D102: =C102-B102 | F102: ='Stock'!L20*'Stock'!O20 | G102: =D102*'Stock'!O20
... A112: Peacocks | B112: 0 | C112: ='Stock'!L30 | D112: =C112-B112 | F112: ='Stock'!L30*'Stock'!O30 | G112: =D112*'Stock'!O30
A113: Total value of stock (sum of the above) | F113: =SUM(F87:F112) | G113: =SUM(G87:G112)
A114: Total value of production | F114: =SUM('Stock'!T5:T30)
A115: Value of sales | F115: =SUM('Stock'!R5:R30)
A117: Wool | B117: Begin stock | C117: End stock | D117: Stockbuilding | F117: Value of stock in £
A118: Fleeces | B118: 0 | C118: 0 | D118: 0
A119: Coarse wool | B119: 0 | C119: 0 | D119: 0
A120: Lamb's wool | B120: 0 | C120: 0 | D120: 0
...

Sheet Receipts
A1: DOWNTONBOROUGH RECEIPTS
A2: Heading | B2: £ | C2: s | D2: d | F2: Total in £ | G2: Error | H2: Notes | I2: Own notes
A3: Arrears | B3: 0 | C3: 15 | D3: 7 | F3: 0.78 | H3: Ralph Fotere, reeve there, answers for 15 shilling 7pence of arrears from his last account of the preceding year.
A4: Arrears | B4: 0 | C4: 15 | D4: 7 | F4: 0.78 | H4: Total, 15 shilling 7pence.
A5: Arrears total | F5: 0.78 | G5: 0 | H5: Total
A7: Rents | B7: 6 | C7: 6 | D7: 2 | F7: 6.31 | H7: Geoffrey Fotere, reeve there, answers for £6 6 shilling 2pence for all rents of assize there for the year.
A8: Rents | B8: 0 | C8: 0 | D8: 4 | F8: 0.02 | H8: 4pence from John Seuyere for 1 plot of purpresture of the lord's ground, 20 feet long and 6 feet wide, at the eastern end of his house.
A9: Rents | B9: 6 | C9: 6 | D9: 6 | F9: 6.33 | H9: Total, £6 6 shilling 6pence.
A10: Rents total | F10: 6.33 | G10: 0 | H10: Total
A12: Total of rents remaining clear | B12: 6.5 | C12: 0 | D12: 0 | F12: 6.5 | H12: Total of rents remaining clear, £6.5 shilling 6pence.
A13: Total of rents remaining clear total | F13: 6.5 | G13: 0 | H13: Total
A15: Perquisites of court | B15: 1 | C15: 1 | D15: 5 | F15: 1.07 | H15: And for £1 1 shilling 5pence from the perquisites of the tourn of Martinmas (11 November).
A16: Perquisites of court | B16: 0 | C16: 3 | D16: 6 | F16: 0.17 | H16: 3 shilling 6pence from the perquisites of the courts held between Michaelmas and the tourn of Hockday.
A17: Perquisites of court | B17: 1 | C17: 5 | D17: 6 | F17: 1.27 | H17: £1 5 shilling 6pence from the perquisites of the tourn of Hockday (1 April).
A18: Perquisites of court | B18: 0 | C18: 3 | D18: 1 | F18: 0.15 | H18: 3 shilling 1pence from the perquisites of the courts held after the tourn of Hockday.
A19: Perquisites of court total | B19: 2 | C19: 13 | D19: 6 | F19: 2.67 | G19: 2.52 | H19: Total, £2 13 shilling 6pence.
A20: Total of all receipts recorded in accounts (calculated here) | F20: =SUMIF(A1:A19,"* total",F1:F19)-SUMIF(A1:A19,"Arrears total",F1:F19)
A21: Total of all receipts (calculated here) incl arrears | F21: =F20+SUMIF(A1:A19,"Arrears total",F1:F19)

Sheet Expenses
A1: DOWNTONBOROUGH EXPENSES
A2: Heading | B2: £ | C2: s | D2: d | F2: Total in £ | G2: Error | H2: Notes
A4: Cash deliveries | B4: 8 | C4: 19 | D4: 0 | F4: 8.95
A5: Cash deliveries | B5: 8 | C5: 19 | D5: 0 | F5: 8.95
A6: Cash deliveries total | F6: 8.95 | G6: 0

Sheet Stock
A1: DOWNTONBOROUGH STOCK ACCOUNT
C3: added | G3: subtracted
A4: Livestock | B4: Inherited stock | C4: added | D4: strays | E4: herbage | F4: churchscot | G4: of which in default | H4: sold | I4: in murrain | J4: accounted for elsewhere | K4: End-period stock | L4: cross-check | M4: stock building | N4: raw production | O4: Unit price (£) | P4: Value of stock (£) at given value | Q4: Value of stock (£) at sales prices | R4: Sales in (£) | S4: Value of stock building (£) | T4: Value of production (£) at sales prices | U4: Details
A5: Cart-horses | B5: 0 | C5: 0 | H5: 0 | I5: 0 | L5: =B5+C5-H5 | M5: =L5-B5 | N5: =C5 | O5: 0 | P5: =O5*K5 | R5: 0 | S5: =O5*M5 | T5: =O5*N5
A6: Mares | B6: 0 | C6: 0 | H6: 0 | I6: 0 | L6: =B6+C6-H6 | M6: =L6-B6 | N6: =C6 | O6: 0 | P6: =O6*K6 | R6: 0 | S6: =O6*M6 | T6: =O6*N6
A7: Plough horses | B7: 0 | C7: 0 | H7: 0 | I7: 0 | L7: =B7+C7-H7 | M7: =L7-B7 | N7: =C7 | O7: 0 | P7: =O7*K7 | R7: 0 | S7: =O7*M7 | T7: =O7*N7
A8: Colts (unspecified years) | B8: 0 | C8: 0 | H8: 0 | I8: 0 | L8: =B8+C8-H8 | M8: =L8-B8 | N8: =C8 | O8: 0 | P8: =O8*K8 | R8: 0 | S8: =O8*M8 | T8: =O8*N8
A9: Colts (2 years) | B9: 0 | C9: 0 | H9: 0 | I9: 0 | L9: =B9+C9-H9 | M9: =L9-B9 | N9: =C9 | O9: 0 | P9: =O9*K9 | R9: 0 | S9: =O9*M9 | T9: =O9*N9
A10: Colts (1 year) | B10: 0 | C10: 0 | H10: 0 | I10: 0 | L10: =B10+C10-H10 | M10: =L10-B10 | N10: =C10 | O10: 0 | P10: =O10*K10 | R10: 0 | S10: =O10*M10 | T10: =O10*N10
A11: Foals | B11: 0 | C11: 0 | H11: 0 | I11: 0 | L11: =B11+C11-H11 | M11: =L11-B11 | N11: =C11 | O11: 0 | P11: =O11*K11 | R11: 0 | S11: =O11*M11 | T11: =O11*N11
A12: Oxen | B12: 0 | C12: 0 | H12: 0 | I12: 0 | L12: =B12+C12-H12 | M12: =L12-B12 | N12: =C12 | O12: 0 | P12: =O12*K12 | R12: 0 | S12: =O12*M12 | T12: =O12*N12
A13: Bulls | B13: 0 | C13: 0 | H13: 0 | I13: 0 | L13: =B13+C13-H13 | M13: =L13-B13 | N13: =C13 | O13: 0 | P13: =O13*K13 | R13: 0 | S13: =O13*M13 | T13: =O13*N13
A14: Cows | B14: 0 | C14: 0 | H14: 0 | I14: 0 | L14: =B14+C14-H14 | M14: =L14-B14 | N14: =C14 | O14: 0 | P14: =O14*K14 | R14: 0 | S14: =O14*M14 | T14: =O14*N14
A15: Steers | B15: 0 | C15: 0 | H15: 0 | I15: 0 | L15: =B15+C15-H15 | M15: =L15-B15 | N15: =C15 | O15: 0 | P15: =O15*K15 | R15: 0 | S15: =O15*M15 | T15: =O15*N15
A16: Bullocks | B16: 0 | C16: 0 | H16: 0 | I16: 0 | L16: =B16+C16-H16 | M16: =L16-B16 | N16: =C16 | O16: 0 | P16: =O16*K16 | R16: 0 | S16: =O16*M16 | T16: =O16*N16
... A20: Rams | B20: 0 | C20: 0 | H20: 0 | I20: 0 | L20: =B20+C20-H20 | M20: =L20-B20 | N20: =C20 | O20: 0 | P20: =O20*K20 | R20: 0 | S20: =O20*M20 | T20: =O20*N20
A21: Ewes | B21: 0 | C21: 0 | H21: 0 | I21: 0 | L21: =B21+C21-H21 | M21: =L21-B21 | N21: =C21 | O21: 0 | P21: =O21*K21 | Q21: 0 | R21: 0 | S21: =O21*M21 | T21: =O21*N21
A22: Hoggs | B22: 0 | C22: 0 | H22: 0 | I22: 0 | L22: =B22+C22-H22 | M22: =L22-B22 | N22: =C22 | O22: 0 | P22: =O22*K22 | R22: 0 | S22: =O22*M22 | T22: =O22*N22
A23: Lambs | B23: 0 | C23: 0 | H23: 0 | I23: 0 | L23: =B23+C23-H23 | M23: =L23-B23 | N23: =C23 | O23: 0 | P23: =O23*K23 | R23: 0 | S23: =O23*M23 | T23: =O23*N23
A24: Boars | B24: 0 | C24: 0 | H24: 0 | I24: 0 | L24: =B24+C24-H24 | M24: =L24-B24 | N24: =C24 | O24: 0 | P24: =O24*K24 | R24: 0 | S24: =O24*M24 | T24: =O24*N24
A25: Sows | B25: 0 | C25: 0 | H25: 0 | I25: 0 | L25: =B25+C25-H25 | M25: =L25-B25 | N25: =C25 | O25: 0 | P25: =O25*K25 | R25: 0 | S25: =O25*M25 | T25: =O25*N25
A26: Pigs | B26: 0 | C26: 0 | H26: 0 | I26: 0 | L26: =B26+C26-H26 | M26: =L26-B26 | N26: =C26 | O26: 0 | P26: =O26*K26 | R26: 0 | S26: =O26*M26 | T26: =O26*N26
A27: Hoggets | B27: 0 | C27: 0 | H27: 0 | I27: 0 | L27: =B27+C27-H27 | M27: =L27-B27 | N27: =C27 | O27: 0 | P27: =O27*K27 | R27: 0 | S27: =O27*M27 | T27: =O27*N27
A28: Piglets | B28: 0 | C28: 0 | H28: 0 | I28: 0 | L28: =B28+C28-H28 | M28: =L28-B28 | N28: =C28 | O28: 0 | P28: =O28*K28 | R28: 0 | S28: =O28*M28 | T28: =O28*N28
A29: Swans | B29: 0 | C29: 0 | H29: 0 | I29: 0 | L29: =B29+C29-H29 | M29: =L29-B29 | N29: =C29 | O29: 0 | P29: =O29*K29 | R29: 0 | S29: =O29*M29 | T29: =O29*N29
A30: Peacocks | B30: 0 | C30: 0 | H30: 0 | I30: 0 | L30: =B30+C30-H30 | M30: =L30-B30 | N30: =C30 | O30: 0 | P30: =O30*K30 | R30: 0 | S30: =O30*M30 | T30: =O30*N30
A31: Total Value
A34: Wool | B34: 0 | C34: 0 | H34: 0 | I34: 0
A35: Coarse wool | B35: 0 | C35: 0 | H35: 0 | I35: 0
A36: Lamb's wool | B36: 0 | C36: 0 | H36: 0 | I36: 0
A37: Wool locks | B37: 0 | C37: 0 | H37: 0 | I37: 0
A38: Wool sold at shearing | B38: 0 | C38: 0 | H38: 0 | I38: 0
A39: Total wool | B39: 0 | C39: 0 | H39: 0 | I39: 0
B40: 0 | C40: 0 | H40: 0 | I40: 0
B41: 0 | C41: 0 | H41: 0 | I41: 0
A42: Hides | B42: 0 | C42: 0 | H42: 0 | I42: 0
A43: Ox hides | B43: 0 | C43: 0 | H43: 0 | I43: 0
A44: Mare | B44: 0 | C44: 0 | H44: 0 | I44: 0
A45: Steer | B45: 0 | C45: 0 | H45: 0 | I45: 0
A46: calves | B46: 0 | C46: 0 | H46: 0 | I46: 0
A47: pigs | B47: 0 | C47: 0 | H47: 0 | I47: 0
A48: Woolskins
A49: wethers
A50: rams
A51: ewes
A52: hoggs
A53: Woolskins total | B53: 0 | C53: 0 | H53: 0 | I53: 0
A54: Bareskins
A55: wethers
A56: rams
A57: ewes
A58: hoggs
A59: Bareskins total | B59: 0 | C59: 0 | H59: 0 | I59: 0
A60: Lambskins | B60: 0 | C60: 0 | H60: 0 | I60: 0
A61: Rotted skins | B61: 0 | C61: 0 | H61: 0 | I61: 0
A62: Shorn skins | B62: 0 | C62: 0 | H62: 0 | I62: 0
A63: Total
A66: Poultry stock
A67: Hens | L67: =B67+C67-H67 | M67: =L67-B67 | N67: =C67 | O67: 0 | Q67: =R67*K67 | R67: 0 | S67: =O67*M67 | T67: =O67*N67
A68: Geese | L68: =B68+C68-H68 | M68: =L68-B68 | N68: =C68 | O68: 0 | Q68: =R68*K68 | R68: 0 | S68: =O68*M68 | T68: =O68*N68
A69: Capons (from chickens) | B69: 0 | C69: 6 | H69: 6 | K69: 0 | L69: =B69+C69-H69 | M69: =L69-B69 | N69: =C69 | O69: 0 | Q69: =R69*K69 | R69: 0 | S69: =O69*M69 | T69: =O69*N69
A70: Cocks & hens | B70: 0 | F70: 28 | G70: 18 | H70: 10 | K70: 0 | L70: =B70+C70-H70 | M70: =L70-B70 | N70: =C70 | O70: 0 | Q70: =R70*K70 | R70: 0 | S70: =O70*M70 | T70: =O70*N70
A71: Total poultry stock
A72: Total poultry excluding churchscot
A74: Poultry production
A75: Eggs | B75: 0 | C75: 0 | H75: 0 | I75: 0 | S75: =O75*M75 | T75: =O75*N75
A76: Cocks & hens from churchscot of customary tenants | B76: 0 | C76: 0 | H76: 0 | I76: 0 | S76: =O76*M76 | T76: =O76*N76
A77: Sum of above | S77: =SUM(S75:S76) | T77: =SUM(T75:T76)
A78: Total
A81: Meat
A82: Beef | B82: 0 | C82: 0 | H82: 0 | I82: 0 | S82: =O82*M82 | T82: =O82*N82
A83: Mutton | B83: 0 | C83: 0 | H83: 0 | I83: 0 | S83: =O83*M83 | T83: =O83*N83
A84: Pork | B84: 0 | C84: 0 | H84: 0 | I84: 0 | S84: =O84*M84 | T84: =O84*N84
A85: Total
A87: Cheese
A88: Winter cheese | B88: 0 | C88: 0 | H88: 0 | I88: 0 | S88: =O88*M88 | T88: =O88*N88
A89: Summer cheese | B89: 0 | C89: 0 | H89: 0 | I89: 0 | S89: =O89*M89 | T89: =O89*N89
A90: Total
A92: Butter
A93: Butter | B93: 0 | C93: 0 | H93: 0 | I93: 0 | S93: =O93*M93 | T93: =O93*N93
A94: Total
A96: Total Dairy Sales
A99: Cider | B99: 0 | C99: 0 | H99: 0 | I99: 0
A102: Additional Information (not necessarily useful)
A103: Utensils
A104: ploughs
A105: carts
A106: cart-ropes
A107: corn baskets
A108: seed-sacks
A109: seed basket
A110: locks for the doors
A111: lead vessel
A112: brass pots
A113: pans
... A128: brass posnets

Sheet raw data
A1: Heading | B1: Sentence | C1: Total in Pounds | D1: Pounds | E1: Shillings | F1: Pence | G1: Corn | H1: Total Quarters Except 1 | I1: Total Bushels Except 1 | J1: Total Corn Cross-Check | K1: Total Corn Manorial Account | L1: Corn Quantity Error | M1: Quarters 1 | N1: Bushels 1 | O1: shilling a quarter 1 | P1: pence a quarter 1 | Q1: shilling a quarter 2 | R1: pence a quarter 2 | S1: shilling a quarter 3 | T1: pence a quarter 3 | U1: shilling a quarter 4 | V1: pence a quarter 4 | W1: shilling a bushel 1 | X1: pence a bushel 1 | Y1: shilling a bushel 2 | Z1: pence a bushel 2 | AA1: shilling a bushel 3 | AB1: pence a bushel 3 | AC1: shilling a bushel 4 | AD1: pence a bushel 4
A2: Downton Borough | B2: The account' of the same for the abovesaid year. | C2: 0 | D2: 0 | E2: 0 | F2: 0 | H2: 0 | I2: 0 | J2: 0 | K2: 0 | L2: 0 | M2: 0 | N2: 0
A3: Arrears | B3: Ralph Fotere, reeve there, answers for 15 shilling 7pence of arrears from his last account of the preceding year. | C3: 0.78 | D3: 0 | E3: 15 | F3: 7 | H3: 0 | I3: 0 | J3: 0 | K3: 0 | L3: 0 | M3: 0 | N3: 0
A4: Arrears | B4: Total, 15 shilling 7pence. | C4: 0.78 | D4: 0 | E4: 15 | F4: 7 | H4: 0 | I4: 0 | J4: 0 | K4: 0 | L4: 0 | M4: 0 | N4: 0
A5: Rents | B5: Geoffrey Fotere, reeve there, answers for £6 6 shilling 2pence for all rents of assize there for the year. | C5: 6.31 | D5: 6 | E5: 6 | F5: 2 | H5: 0 | I5: 0 | J5: 0 | K5: 0 | L5: 0 | M5: 0 | N5: 0
A6: Rents | B6: 4pence from John Seuyere for 1 plot of purpresture of the lord's ground, 20 feet long and 6 feet wide, at the eastern end of his house. | C6: 0.02 | D6: 0 | E6: 0 | F6: 4 | H6: 0 | I6: 0 | J6: 0 | K6: 0 | L6: 0 | M6: 0 | N6: 0
A7: Rents | B7: Total, £6 6 shilling 6pence. | C7: 6.33 | D7: 6 | E7: 6 | F7: 6 | H7: 0 | I7: 0 | J7: 0 | K7: 0 | L7: 0 | M7: 0 | N7: 0
A8: Quittances of rent | B8: In quittance of rent of 1 reeve of the borough for the year 1 shilling. | C8: 0.05 | D8: 0 | E8: 1 | F8: 0 | H8: 0 | I8: 0 | J8: 0 | K8: 0 | L8: 0 | M8: 0 | N8: 0
A9: Quittances of rent | B9: Total, 1 shilling. | C9: 0.05 | D9: 0 | E9: 1 | F9: 0 | H9: 0 | I9: 0 | J9: 0 | K9: 0 | L9: 0 | M9: 0 | N9: 0
A10: Total of rents remaining clear | B10: Total of rents remaining clear, £6.5 shilling 6pence. | C10: 6.5 | D10: 6.5 | E10: 0 | F10: 0 | H10: 0 | I10: 0 | J10: 0 | K10: 0 | L10: 0 | M10: 0 | N10: 0
A11: Perquisites of court | B11: And for £1 1 shilling 5pence from the perquisites of the tourn of Martinmas (11 November). | C11: 1.07 | D11: 1 | E11: 1 | F11: 5 | H11: 0 | I11: 0 | J11: 0 | K11: 0 | L11: 0 | M11: 0 | N11: 0
A12: Perquisites of court | B12: 3 shilling 6pence from the perquisites of the courts held between Michaelmas and the tourn of Hockday. | C12: 0.17 | D12: 0 | E12: 3 | F12: 6 | H12: 0 | I12: 0 | J12: 0 | K12: 0 | L12: 0 | M12: 0 | N12: 0
A13: Perquisites of court | B13: £1 5 shilling 6pence from the perquisites of the tourn of Hockday (1 April). | C13: 1.27 | D13: 1 | E13: 5 | F13: 6 | H13: 0 | I13: 0 | J13: 0 | K13: 0 | L13: 0 | M13: 0 | N13: 0
... A18: Cash deliveries | B18: Total, £8 19 shilling And he owes, 15 shilling 7pence, all of which is in the hands of the escheator, for which he is charged in the following account. | C18: 8.95 | D18: 8 | E18: 19 | F18: 0 | H18: 0 | I18: 0 | J18: 0 | K18: 0 | L18: 0 | M18: 0 | N18: 0

Sheet Issues of the Grange

Sheet Issues of the Mills

Sheet Stock_raw

Sheet Prices

Sheet Labour Rents

Sheet not needed
