Workbook

Sheet Adderbury Overview
A1: ADDERBURY | B1: Total in £ | C1: Error | D1: Note
A2: CASH ACCOUNT
A3: RECEIPTS
A4: Arrears total
A5: Rents of assize total | B5: ='Adderbury Receipts'!F9
A6: Quittances total | B6: ='Adderbury Receipts'!F22
A7: Defaults of rent total | B7: ='Adderbury Receipts'!F27
A8: Defaults of rent through the pestilence total | B8: ='Adderbury Receipts'!F36
A9: Cotlands defaults total | B9: ='Adderbury Receipts'!F45
A10: Cotlands total | B10: ='Adderbury Receipts'!F54
A11: Total of quittances and defaults of rent total | B11: ='Adderbury Receipts'!F56
A12: Total of rents remaining clear total | B12: ='Adderbury Receipts'!F58
A13: Farms total | B13: ='Adderbury Receipts'!F70
A14: Annual recognizances total | B14: ='Adderbury Receipts'!F90
A15: Issues of the Manor total | B15: ='Adderbury Receipts'!F117
A16: Issues of the tenements in the lord's hands total | B16: ='Adderbury Receipts'!F126
A17: Sale of labour services total | B17: ='Adderbury Receipts'!F135
A18: Sale of corn total | B18: ='Adderbury Receipts'!F138
A19: Entry and marriage fines total | B19: ='Adderbury Receipts'!F166
A20: Pleas & perquisites total | B20: ='Adderbury Receipts'!F173
A21: Forfeited chattels total | B21: ='Adderbury Receipts'!F177
A22: Farm of the demesne land total | B22: ='Adderbury Receipts'!F181
A23: Total of all receipts (calculated here) | B23: ='Adderbury Receipts'!F185
A24: Total of all receipts (calculated here) incl arrears
A25: Total recorded in the accounts excl. arrears | B25: ='Adderbury Receipts'!F184 | C25: =B23-B25
A26: Total recorded in the accounts incl. arrears
A29: EXPENSES
A30: Cost of ploughs total
A31: Purchase of corn total
A32: Cost of carts and wagons total
A33: Cost of dairy total
A34: Purchase of stock total
A35: Sheepcote total
A36: Cost of buildings total | B36: ='Adderbury Expenses'!F26
A37: Threshing total
A38: Barley expenses
A39: Expenses of the harvest total
A40: Necessary expenses
A41: Wages of the bailiff | B41: ='Adderbury Expenses'!F30
A42: Steward's expenses total | B42: ='Adderbury Expenses'!F33
A43: Annual fees | B43: ='Adderbury Expenses'!F37
A44: Total of all expenses per account
A45: Total of all expenses (calculated here)
A46: Total fixed investment
A47: Total Demesne fixed investment
A49: Owed by the reeve | B49: =B23-B45
A50: From accounts | B50: ='Adderbury Expenses'!F41
A52: Allowances | B52: ='Adderbury Expenses'!F45
A53: Cash deliveries | B53: ='Adderbury Expenses'!F48
A54: Sum of the above | B54: =SUM(B52:B53)
A55: Total of all allowances and cash deliveries in accounts
A57: Net amount owed | B57: =B50-B54
A58: Net amount owed in accounts
A60: GRANGE ACCOUNT | B60: Total Production | D60: Value of total gross production in £ | E60: Value of total net production in £
A61: Grange | B61: qrs | C61: bus
A62: Wheat
A63: Rye
A64: Dredge
A65: Curall
A66: Barley
A67: Oats
A68: Beans
A69: Peas
A70: Vetches
A71: Total value of gross production (sum of the above) | B71: =SUM(D62:D70)
A72: Total value of net production | B72: =SUM(E62:E70)
A73: Value of sales
A75: MILL ACCOUNT | B75: Total Production | D75: Total in £ | F75: Not yet implemented
A76: Issues of the mill | B76: qrs | C76: bus
A77: Wheat
A78: Oatmeal
A79: 1st grade malt
A80: 2nd grade malt
A81: Maslin
A82: Total value of production (sum of the above)
A83: Value of sales
A85: STOCK ACCOUNT
A86: Livestock | B86: Begin stock | C86: End stock | D86: Stockbuilding | F86: Value of stock in £ | G86: Value of stockbuilding
A87: Cart-horses | B87: ='Adderbury Stock'!B5 | C87: ='Adderbury Stock'!K5 | D87: ='Adderbury Overview'!C87-'Adderbury Overview'!B87 | F87: ='Adderbury Stock'!P5 | G87: ='Adderbury Stock'!S5
A88: Mares | B88: ='Adderbury Stock'!B6 | C88: ='Adderbury Stock'!K6 | D88: ='Adderbury Overview'!C88-'Adderbury Overview'!B88 | F88: ='Adderbury Stock'!P6 | G88: ='Adderbury Stock'!S6
A89: Plough horses | B89: ='Adderbury Stock'!B7 | C89: ='Adderbury Stock'!K7 | D89: ='Adderbury Overview'!C89-'Adderbury Overview'!B89 | F89: ='Adderbury Stock'!P7 | G89: ='Adderbury Stock'!S7
A90: Colts (2 years) | B90: ='Adderbury Stock'!B8 | C90: ='Adderbury Stock'!K8 | D90: ='Adderbury Overview'!C90-'Adderbury Overview'!B90 | F90: ='Adderbury Stock'!P8 | G90: ='Adderbury Stock'!S8
A91: Colts (2 years) | B91: ='Adderbury Stock'!B9 | C91: ='Adderbury Stock'!K9 | D91: ='Adderbury Overview'!C91-'Adderbury Overview'!B91 | F91: ='Adderbury Stock'!P9 | G91: ='Adderbury Stock'!S9
A92: Colts (1 year) | B92: ='Adderbury Stock'!B10 | C92: ='Adderbury Stock'!K10 | D92: ='Adderbury Overview'!C92-'Adderbury Overview'!B92 | F92: ='Adderbury Stock'!P10 | G92: ='Adderbury Stock'!S10
A93: Foals | B93: ='Adderbury Stock'!B11 | C93: ='Adderbury Stock'!K11 | D93: ='Adderbury Overview'!C93-'Adderbury Overview'!B93 | F93: ='Adderbury Stock'!P11 | G93: ='Adderbury Stock'!S11
A94: Oxen | B94: ='Adderbury Stock'!B12 | C94: ='Adderbury Stock'!K12 | D94: ='Adderbury Overview'!C94-'Adderbury Overview'!B94 | F94: ='Adderbury Stock'!P12 | G94: ='Adderbury Stock'!S12
A95: Bulls | B95: ='Adderbury Stock'!B13 | C95: ='Adderbury Stock'!K13 | D95: ='Adderbury Overview'!C95-'Adderbury Overview'!B95 | F95: ='Adderbury Stock'!P13 | G95: ='Adderbury Stock'!S13
A96: Cows | B96: ='Adderbury Stock'!B14 | C96: ='Adderbury Stock'!K14 | D96: ='Adderbury Overview'!C96-'Adderbury Overview'!B96 | F96: ='Adderbury Stock'!P14 | G96: ='Adderbury Stock'!S14
A97: Steers | B97: ='Adderbury Stock'!B15 | C97: ='Adderbury Stock'!K15 | D97: ='Adderbury Overview'!C97-'Adderbury Overview'!B97 | F97: ='Adderbury Stock'!P15 | G97: ='Adderbury Stock'!S15
A98: Bullocks | B98: ='Adderbury Stock'!B16 | C98: ='Adderbury Stock'!K16 | D98: ='Adderbury Overview'!C98-'Adderbury Overview'!B98 | F98: ='Adderbury Stock'!P16 | G98: ='Adderbury Stock'!S16
... A112: Peacocks | B112: ='Adderbury Stock'!B30 | C112: ='Adderbury Stock'!K30 | D112: ='Adderbury Overview'!C112-'Adderbury Overview'!B112 | F112: ='Adderbury Stock'!P30 | G112: ='Adderbury Stock'!S30
A113: Total value of stock (sum of the above) | F113: =SUM(F87:F112) | G113: ='Adderbury Stock'!S31
A114: Total value of production | F114: =SUM('Adderbury Stock'!T5:T29)
A115: Value of sales | F115: =SUM('Adderbury Stock'!R5:R23)
A117: Wool | B117: Begin stock | C117: End stock | D117: Stockbuilding | F117: Value of stock in £
A118: Fleeces
A119: Coarse wool
A120: Lamb's wool
A121: Wool locks
A122: Wool sold at shearing
...

Sheet Esher_1342 Stock
A1: ESHER_1342 STOCK ACCOUNT
C3: added | G3: subtracted
A4: Livestock | B4: Inherited stock | C4: added | D4: strays | E4: herbage | F4: churchscot | G4: of which in default | H4: sold | I4: in murrain | J4: accounted for elsewhere | K4: End-period stock | L4: cross-check | M4: stock building | N4: raw production | O4: Unit price (£) | P4: Value of stock (£) at given value | Q4: Value of stock (£) at sales prices | R4: Sales in (£) | S4: Value of stock building (£) | T4: Value of production (£) at sales prices | U4: Details
A5: Cart-horses | B5: 0 | C5: 0 | H5: 0 | I5: 0 | L5: =B5+C5-H5 | M5: =L5-B5 | N5: =C5 | O5: 0 | P5: =O5*K5 | R5: 0 | S5: =O5*M5 | T5: =O5*N5
A6: Mares | B6: 0 | C6: 0 | H6: 0 | I6: 0 | L6: =B6+C6-H6 | M6: =L6-B6 | N6: =C6 | O6: 0 | P6: =O6*K6 | R6: 0 | S6: =O6*M6 | T6: =O6*N6
A7: Plough horses | B7: 0 | C7: 0 | H7: 0 | I7: 0 | L7: =B7+C7-H7 | M7: =L7-B7 | N7: =C7 | O7: 0 | P7: =O7*K7 | R7: 0 | S7: =O7*M7 | T7: =O7*N7
A8: Colts (unspecified years) | B8: 0 | C8: 0 | H8: 0 | I8: 0 | L8: =B8+C8-H8 | M8: =L8-B8 | N8: =C8 | O8: 0 | P8: =O8*K8 | R8: 0 | S8: =O8*M8 | T8: =O8*N8
A9: Colts (2 years) | B9: 0 | C9: 0 | H9: 0 | I9: 0 | L9: =B9+C9-H9 | M9: =L9-B9 | N9: =C9 | O9: 0 | P9: =O9*K9 | R9: 0 | S9: =O9*M9 | T9: =O9*N9
A10: Colts (1 year) | B10: 0 | C10: 0 | H10: 0 | I10: 0 | L10: =B10+C10-H10 | M10: =L10-B10 | N10: =C10 | O10: 0 | P10: =O10*K10 | R10: 0 | S10: =O10*M10 | T10: =O10*N10
A11: Foals | B11: 0 | C11: 0 | H11: 0 | I11: 0 | L11: =B11+C11-H11 | M11: =L11-B11 | N11: =C11 | O11: 0 | P11: =O11*K11 | R11: 0 | S11: =O11*M11 | T11: =O11*N11
A12: Oxen | B12: 0 | C12: 0 | H12: 0 | I12: 0 | L12: =B12+C12-H12 | M12: =L12-B12 | N12: =C12 | O12: 0 | P12: =O12*K12 | R12: 2.73 | S12: =O12*M12 | T12: =O12*N12
A13: Bulls | B13: 0 | C13: 0 | H13: 0 | I13: 0 | L13: =B13+C13-H13 | M13: =L13-B13 | N13: =C13 | O13: 0 | P13: =O13*K13 | R13: 0 | S13: =O13*M13 | T13: =O13*N13
A14: Cows | B14: 0 | C14: 0 | H14: 0 | I14: 0 | L14: =B14+C14-H14 | M14: =L14-B14 | N14: =C14 | O14: 0 | P14: =O14*K14 | R14: 0 | S14: =O14*M14 | T14: =O14*N14
A15: Steers | B15: 0 | C15: 0 | H15: 0 | I15: 0 | L15: =B15+C15-H15 | M15: =L15-B15 | N15: =C15 | O15: 0 | P15: =O15*K15 | R15: 0 | S15: =O15*M15 | T15: =O15*N15
A16: Bullocks | B16: 0 | C16: 0 | H16: 0 | I16: 0 | L16: =B16+C16-H16 | M16: =L16-B16 | N16: =C16 | O16: 0 | P16: =O16*K16 | R16: 0 | S16: =O16*M16 | T16: =O16*N16
... A20: Rams | B20: 0 | C20: 0 | H20: 0 | I20: 0 | L20: =B20+C20-H20 | M20: =L20-B20 | N20: =C20 | O20: 0 | P20: =O20*K20 | R20: 0 | S20: =O20*M20 | T20: =O20*N20
A21: Ewes | B21: 0 | C21: 0 | H21: 0 | I21: 0 | L21: =B21+C21-H21 | M21: =L21-B21 | N21: =C21 | O21: 0 | P21: =O21*K21 | Q21: 0 | R21: 2.73 | S21: =O21*M21 | T21: =O21*N21
A22: Hoggs | B22: 0 | C22: 0 | H22: 0 | I22: 0 | L22: =B22+C22-H22 | M22: =L22-B22 | N22: =C22 | O22: 0 | P22: =O22*K22 | R22: 0 | S22: =O22*M22 | T22: =O22*N22
A23: Lambs | B23: 0 | C23: 0 | H23: 0 | I23: 0 | L23: =B23+C23-H23 | M23: =L23-B23 | N23: =C23 | O23: 0 | P23: =O23*K23 | R23: 0 | S23: =O23*M23 | T23: =O23*N23
A24: Boars | B24: 0 | C24: 0 | H24: 0 | I24: 0 | L24: =B24+C24-H24 | M24: =L24-B24 | N24: =C24 | O24: 0 | P24: =O24*K24 | R24: 0 | S24: =O24*M24 | T24: =O24*N24
A25: Sows | B25: 0 | C25: 0 | H25: 0 | I25: 0 | L25: =B25+C25-H25 | M25: =L25-B25 | N25: =C25 | O25: 0 | P25: =O25*K25 | R25: 0 | S25: =O25*M25 | T25: =O25*N25
A26: Pigs | B26: 0 | C26: 0 | H26: 0 | I26: 0 | L26: =B26+C26-H26 | M26: =L26-B26 | N26: =C26 | O26: 0 | P26: =O26*K26 | R26: 0 | S26: =O26*M26 | T26: =O26*N26
A27: Hoggets | B27: 0 | C27: 0 | H27: 0 | I27: 0 | L27: =B27+C27-H27 | M27: =L27-B27 | N27: =C27 | O27: 0 | P27: =O27*K27 | R27: 2.73 | S27: =O27*M27 | T27: =O27*N27
A28: Piglets | B28: 0 | C28: 0 | H28: 0 | I28: 0 | L28: =B28+C28-H28 | M28: =L28-B28 | N28: =C28 | O28: 0 | P28: =O28*K28 | R28: 0 | S28: =O28*M28 | T28: =O28*N28
A29: Swans | B29: 0 | C29: 0 | H29: 0 | I29: 0 | L29: =B29+C29-H29 | M29: =L29-B29 | N29: =C29 | O29: 0 | P29: =O29*K29 | R29: 0 | S29: =O29*M29 | T29: =O29*N29
A30: Peacocks | B30: 0 | C30: 0 | H30: 0 | I30: 0 | L30: =B30+C30-H30 | M30: =L30-B30 | N30: =C30 | O30: 0 | P30: =O30*K30 | R30: 0 | S30: =O30*M30 | T30: =O30*N30
A31: Total Value
A34: Wool | B34: 0 | C34: 0 | H34: 0 | I34: 0
A35: Coarse wool | B35: 0 | C35: 0 | H35: 0 | I35: 0
A36: Lamb's wool | B36: 0 | C36: 0 | H36: 0 | I36: 0
A37: Wool locks | B37: 0 | C37: 0 | H37: 0 | I37: 0
A38: Wool sold at shearing | B38: 0 | C38: 0 | H38: 0 | I38: 0
A39: Total wool | B39: 0 | C39: 0 | H39: 0 | I39: 0
B40: 0 | C40: 0 | H40: 0 | I40: 0
B41: 0 | C41: 0 | H41: 0 | I41: 0
A42: Hides | B42: 0 | C42: 0 | H42: 0 | I42: 0
A43: Ox hides | B43: 0 | C43: 0 | H43: 0 | I43: 0
A44: Mare | B44: 0 | C44: 0 | H44: 0 | I44: 0
A45: Steer | B45: 0 | C45: 0 | H45: 0 | I45: 0
A46: calves | B46: 0 | C46: 0 | H46: 0 | I46: 0
A47: pigs | B47: 0 | C47: 0 | H47: 0 | I47: 0
A48: Woolskins
A49: wethers
A50: rams
A51: ewes
A52: hoggs
A53: Woolskins total | B53: 0 | C53: 0 | H53: 0 | I53: 0
A54: Bareskins
A55: wethers
A56: rams
A57: ewes
A58: hoggs
A59: Bareskins total | B59: 0 | C59: 0 | H59: 0 | I59: 0
A60: Lambskins | B60: 0 | C60: 0 | H60: 0 | I60: 0
A61: Rotted skins | B61: 0 | C61: 0 | H61: 0 | I61: 0
A62: Shorn skins | B62: 0 | C62: 0 | H62: 0 | I62: 0
A63: Total
A66: Poultry stock
A67: Hens | L67: =B67+C67-H67 | M67: =L67-B67 | N67: =C67 | O67: 0 | Q67: =R67*K67 | R67: 0 | S67: =O67*M67 | T67: =O67*N67
A68: Geese | L68: =B68+C68-H68 | M68: =L68-B68 | N68: =C68 | O68: 0 | Q68: =R68*K68 | R68: 0 | S68: =O68*M68 | T68: =O68*N68
A69: Capons (from chickens) | B69: 0 | C69: 6 | H69: 6 | K69: 0 | L69: =B69+C69-H69 | M69: =L69-B69 | N69: =C69 | O69: 0 | Q69: =R69*K69 | R69: 0 | S69: =O69*M69 | T69: =O69*N69
A70: Cocks & hens | B70: 0 | F70: 28 | G70: 18 | H70: 10 | K70: 0 | L70: =B70+C70-H70 | M70: =L70-B70 | N70: =C70 | O70: 0 | Q70: =R70*K70 | R70: 0 | S70: =O70*M70 | T70: =O70*N70
A71: Total poultry stock
A72: Total poultry excluding churchscot
A74: Poultry production
A75: Eggs | B75: 0 | C75: 0 | H75: 0 | I75: 0 | S75: =O75*M75 | T75: =O75*N75
A76: Cocks & hens from churchscot of customary tenants | B76: 0 | C76: 0 | H76: 0 | I76: 0 | S76: =O76*M76 | T76: =O76*N76
A77: Sum of above | S77: =SUM(S75:S76) | T77: =SUM(T75:T76)
A78: Total
A81: Meat
A82: Beef | B82: 0 | C82: 0 | H82: 0 | I82: 0 | S82: =O82*M82 | T82: =O82*N82
A83: Mutton | B83: 0 | C83: 0 | H83: 0 | I83: 0 | S83: =O83*M83 | T83: =O83*N83
A84: Pork | B84: 0 | C84: 0 | H84: 0 | I84: 0 | S84: =O84*M84 | T84: =O84*N84
A85: Total
A87: Cheese
A88: Winter cheese | B88: 0 | C88: 0 | H88: 0 | I88: 0 | S88: =O88*M88 | T88: =O88*N88
A89: Summer cheese | B89: 0 | C89: 0 | H89: 0 | I89: 0 | S89: =O89*M89 | T89: =O89*N89
A90: Total
A92: Butter
A93: Butter | B93: 0 | C93: 0 | H93: 0 | I93: 0 | S93: =O93*M93 | T93: =O93*N93
A94: Total
A96: Total Dairy Sales
A99: Cider | B99: 0 | C99: 0 | H99: 0 | I99: 0
A102: Additional Information (not necessarily useful)
A103: Utensils
A104: ploughs
A105: carts
A106: cart-ropes
A107: corn baskets
A108: seed-sacks
A109: seed basket
A110: locks for the doors
A111: lead vessel
A112: brass pots
A113: pans
... A128: brass posnets

Sheet raw data
A1: Heading | B1: Sentence | C1: Total in Pounds | D1: Pounds | E1: Shillings | F1: Pence | G1: Corn | H1: Total Quarters Except 1 | I1: Total Bushels Except 1 | J1: Total Corn Cross-Check | K1: Total Corn Manorial Account | L1: Corn Quantity Error | M1: Quarters 1 | N1: Bushels 1 | O1: Quarters 2 | P1: Bushels 2 | Q1: Quarters 3 | R1: Bushels 3 | S1: shilling a quarter 1 | T1: pence a quarter 1 | U1: shilling a quarter 2 | V1: pence a quarter 2 | W1: shilling a quarter 3 | X1: pence a quarter 3 | Y1: shilling a quarter 4 | Z1: pence a quarter 4 | AA1: shilling a bushel 1 | AB1: pence a bushel 1 | AC1: shilling a bushel 2 | AD1: pence a bushel 2 | AE1: shilling a bushel 3 | AF1: pence a bushel 3 | AG1: shilling a bushel 4 | AH1: pence a bushel 4
A2: 33. 29 september 1342 to 29 september 1343 | B2: in 1342/3, five years after becoming the first duke of cornwall and in the year that he became the first prince of wales, the 12–13 year old edward de woodstock – later styled the black prince – stayed overnight at esher. | C2: 0 | D2: 0 | E2: 0 | F2: 0 | H2: 0 | I2: 0 | J2: 0 | K2: 0 | L2: 0 | M2: 0 | N2: 0
A3: 33. 29 september 1342 to 29 september 1343 | B3: he was not the only guest for, once again, the earl of surrey visited. | C3: 0 | D3: 0 | E3: 0 | F3: 0 | H3: 0 | I3: 0 | J3: 0 | K3: 0 | L3: 0 | M3: 0 | N3: 0
A4: 33. 29 september 1342 to 29 september 1343 | B4: the provisioning of visiting households such as these must have complicated the lives of manorial officials, and this account provides details about their differing needs and the arrangements put into place for meeting them. | C4: 0 | D4: 0 | E4: 0 | F4: 0 | H4: 0 | I4: 0 | J4: 0 | K4: 0 | L4: 0 | M4: 0 | N4: 0
A5: 33. 29 september 1342 to 29 september 1343 | B5: the account also situates esher in a number of other contexts, which together illustrate the diversity of forces to which managers of medieval manors and demesnes were expected to respond. | C5: 0 | D5: 0 | E5: 0 | F5: 0 | H5: 0 | I5: 0 | J5: 0 | K5: 0 | L5: 0 | M5: 0 | N5: 0
A6: 33. 29 september 1342 to 29 september 1343 | B6: locally, for instance, it highlights the power of custom in medieval society: although of low social standing, customary tenants were knowledgeable and assertive about their obligations, refusing on this occasion to shear demesne sheep on land that was not part of the ancient fee of esher. | C6: 0 | D6: 0 | E6: 0 | F6: 0 | H6: 0 | I6: 0 | J6: 0 | K6: 0 | L6: 0 | M6: 0 | N6: 0
A7: 33. 29 september 1342 to 29 september 1343 | B7: we also see the manor within a regional economic framework, especially with regard to sheep farming: wool was carried to farnham. | C7: 0 | D7: 0 | E7: 0 | F7: 0 | H7: 0 | I7: 0 | J7: 0 | K7: 0 | L7: 0 | M7: 0 | N7: 0
A8: 33. 29 september 1342 to 29 september 1343 | B8: hoggets were driven to bishop's sutton (hants.). | C8: 0 | D8: 0 | E8: 0 | F8: 0 | H8: 0 | I8: 0 | J8: 0 | K8: 0 | L8: 0 | M8: 0 | N8: 0
A9: 33. 29 september 1342 to 29 september 1343 | B9: while lambs were received from other manors in hampshire, alresford, cheriton, and yateley. | C9: 0 | D9: 0 | E9: 0 | F9: 0 | H9: 0 | I9: 0 | J9: 0 | K9: 0 | L9: 0 | M9: 0 | N9: 0
A10: 33. 29 september 1342 to 29 september 1343 | B10: these extensive transfers of sheep were plausibly connected to outbreaks of disease, for almost half of the lambs that had been born in the spring of 1342 died before they could be shorn in the summer of 1343, and several others are described as being 'exceedingly scabious'. | C10: 0 | D10: 0 | E10: 0 | F10: 0 | H10: 0 | I10: 0 | J10: 0 | K10: 0 | L10: 0 | M10: 0 | N10: 0
A11: 33. 29 september 1342 to 29 september 1343 | B11: environmental concerns for farm managers at esher were not restricted to this, for the summer of 1343 also brought a 'multitude of vermin in the [...] dovecot and breeding in the garden'. | C11: 0 | D11: 0 | E11: 0 | F11: 0 | H11: 0 | I11: 0 | J11: 0 | K11: 0 | L11: 0 | M11: 0 | N11: 0
A12: 33. 29 september 1342 to 29 september 1343 | B12: this is the first of three references to vermin in the esher accounts in the years 1342/3–135.5. the term vermin covers a range of animals, including polecats, foxes, mice, rats, and some birds. | C12: 0 | D12: 0 | E12: 0 | F12: 0 | H12: 0 | I12: 0 | J12: 0 | K12: 0 | L12: 0 | M12: 0 | N12: 0
A13: 33. 29 september 1342 to 29 september 1343 | B13: although it might be tempting, in the decade of the black death, to interpret this reference as an infestation of rats, medieval black rats do not seem to have behaved in such a predatory fashion (unlike brown rats, which arrived in england several centuries later). | C13: 0 | D13: 0 | E13: 0 | F13: 0 | H13: 0 | I13: 0 | J13: 0 | K13: 0 | L13: 0 | M13: 0 | N13: 0
... A58: issue of the manor | B58: sum 64 shilling 9½d. | C58: 3.2 | D58: 0 | E58: 64 | F58: 0 | H58: 0 | I58: 0 | J58: 0 | K58: 0 | L58: 0 | M58: 0 | N58: 0
A59: sale of corn | B59: the same answers for 21 pence received from 5 bushels of curallum of wheat sold, price of a bushel 3½d. | C59: 0.09 | D59: 0 | E59: 0 | F59: 21 | G59: wheat, curall | H59: 0 | I59: 5 | J59: 0.62 | K59: 0.62 | L59: 0 | M59: 0 | N59: 5 | AA59: 0 | AB59: 0
A60: sale of corn | B60: and for 12 shilling received from 3 quarters of rye sold in the month of september, price of a quarter 4 shilling and for 18 shilling 4½d received from 3 quarters 7½ bushels of rye, price of a quarter 4 shilling 8pence and for 4 shilling 1¼d received from 1 quarter 1 bushel 3 pecks of barley sold, price of a bushel 5pence and for 13 shilling 6¼d received from 10 quarters 6 bushels 3 pecks of oats sold to earl warenne, price of a quarter 15pence and for 4 shilling 11 pence from 3½ quarters of oats sold for expenses of the lord’s household. | C60: 0.63 | D60: 0 | E60: 12 | F60: 8 | G60: rye, barley, oats | H60: 13 | I60: 6 | J60: 13.75 | K60: 3 | L60: 10.75 | M60: 3 | N60: 0 | O60: 3 | P60: 0 | Q60: 10 | R60: 6 | AA60: 0 | AB60: 0
A61: sale of corn | B61: sum 54 shilling 8pence. | C61: 2.73 | D61: 0 | E61: 54 | F61: 8 | H61: 0 | I61: 0 | J61: 0 | K61: 0 | L61: 0 | M61: 0 | N61: 0
A62: sale of stock | B62: the same answers for 54 shilling received from 4 oxen because they were of no use to the stock, attested by the prior of sandon, price of which 13 shilling 6pence and for 10 shilling 6 pence received from 10 wethers and 4 ewes, old, sold, price of each of which 9pence and for 71 shilling from 71 hoggets sold. | C62: 2.73 | D62: 0 | E62: 54 | F62: 6 | H62: 0 | I62: 0 | J62: 0 | K62: 0 | L62: 0 | M62: 0 | N62: 0
A63: sale of stock | B63: sum £6 15 shilling 6pence. | C63: 6.78 | D63: 6 | E63: 15 | F63: 6 | H63: 0 | I63: 0 | J63: 0 | K63: 0 | L63: 0 | M63: 0 | N63: 0
A64: fines and marriage fines | B64: the same answers for 8 shilling from a fixed payment at the view of frankpledge for tithingpenny at the tourns of st martin and hockday. | C64: 0.4 | D64: 0 | E64: 8 | F64: 0 | H64: 0 | I64: 0 | J64: 0 | K64: 0 | L64: 0 | M64: 0 | N64: 0
A65: fines and marriage fines | B65: and for 2 shilling from peter derlyng and petronilla his wife [...]. | C65: 0.1 | D65: 0 | E65: 2 | F65: 0 | H65: 0 | I65: 0 | J65: 0 | K65: 0 | L65: 0 | M65: 0 | N65: 0
A66: fines and marriage fines | B66: and for 4 shilling from gilbert selevyn for [...]. | C66: 0.2 | D66: 0 | E66: 4 | F66: 0 | H66: 0 | I66: 0 | J66: 0 | K66: 0 | L66: 0 | M66: 0 | N66: 0
A67: perquisites of court | B67: the same answers for 15 pence received from the perquisites of a court held on the tuesday next after the feast of st luke [22 october]. | C67: 0.06 | D67: 0 | E67: 0 | F67: 15 | H67: 0 | I67: 0 | J67: 0 | K67: 0 | L67: 0 | M67: 0 | N67: 0
A68: perquisites of court | B68: and for 17 shilling received from the perquisites of the tourn of st martin with a court held on the saturday next after the feast of st mathias the apostle [1 march] together with ½ mark from the heriot. | C68: 0.85 | D68: 0 | E68: 17 | F68: 0 | H68: 0 | I68: 0 | J68: 0 | K68: 0 | L68: 0 | M68: 0 | N68: 0
A69: perquisites of court | B69: --- page 4 ---. | C69: 0 | D69: 0 | E69: 0 | F69: 0 | H69: 0 | I69: 0 | J69: 0 | K69: 0 | L69: 0 | M69: 0 | N69: 0
A70: foreign receipts | B70: the same answers for 3 shilling received from three-quarters of a hundredweight of firewood that was at the manor for the stock of the lord’s household sold to earl warenne. | C70: 0.15 | D70: 0 | E70: 3 | F70: 0 | H70: 0 | I70: 0 | J70: 0 | K70: 0 | L70: 0 | M70: 0 | N70: 0
A71: foreign receipts | B71: and for 2 shilling received from 5 quarters of charcoal from the aforesaid stock sold to the same earl. | C71: 0.1 | D71: 0 | E71: 2 | F71: 0 | H71: 5 | I71: 0 | J71: 5 | K71: 5 | L71: 0 | M71: 5 | N71: 0
A72: foreign receipts | B72: and nothing is answered for three-quarters of a hundredweight of firewood taken for the use of the duke of cornwall while he resided within the manor, because his treasurer and his other ministers refused to pay for this stock of provisions in other manors. | C72: 0 | D72: 0 | E72: 0 | F72: 0 | H72: 0 | I72: 0 | J72: 0 | K72: 0 | L72: 0 | M72: 0 | N72: 0
... A84: cost of ploughs | B84: stipend of one ploughdriver for the year 5 shilling sum 10 shilling 5pence. | C84: 0.27 | D84: 0 | E84: 5 | F84: 5 | H84: 0 | I84: 0 | J84: 0 | K84: 0 | L84: 0 | M84: 0 | N84: 0
A85: cost of customary tenants | B85: the same accounts for 28 herrings bought for the expenses of 14 customary tenants harrowing for one day at the sowing of oats 3½d, namely to each two herrings and bread from stock as elsewhere. | C85: 0 | D85: 0 | E85: 0 | F85: 0 | G85: oats | H85: 0 | I85: 0 | J85: 0 | K85: 0 | L85: 0 | M85: 0 | N85: 0
A86: cost of customary tenants | B86: likewise in expenses of 19 customary tenants carrying the lord’s manure out of the manor onto the lord’s land for two days this year 2 shilling 4 pence, each taking for a day by custom ¾d. | C86: 0.12 | D86: 0 | E86: 2 | F86: 4 | H86: 0 | I86: 0 | J86: 0 | K86: 0 | L86: 0 | M86: 0 | N86: 0
A87: cost of customary tenants | B87: sum 2 shilling 7½d. | C87: 0.1 | D87: 0 | E87: 2 | F87: 0 | H87: 0 | I87: 0 | J87: 0 | K87: 0 | L87: 0 | M87: 0 | N87: 0
A88: cost of carts | B88: the same accounts for three iron tyres bought for fitting to, and mending, broken wheels 5 pence, because the wheels were worn out. | C88: 0.02 | D88: 0 | E88: 0 | F88: 5 | H88: 0 | I88: 0 | J88: 0 | K88: 0 | L88: 0 | M88: 0 | N88: 0
A89: cost of carts | B89: eight clouts bought for the cart for the year 8pence. | C89: 0.03 | D89: 0 | E89: 0 | F89: 8 | H89: 0 | I89: 0 | J89: 0 | K89: 0 | L89: 0 | M89: 0 | N89: 0
A90: cost of carts | B90: nails for the same and for renewing 1pence. | C90: 0 | D90: 0 | E90: 0 | F90: 1 | H90: 0 | I90: 0 | J90: 0 | K90: 0 | L90: 0 | M90: 0 | N90: 0
A91: cost of carts | B91: grease bought for the. | C91: 0 | D91: 0 | E91: 0 | F91: 0 | H91: 0 | I91: 0 | J91: 0 | K91: 0 | L91: 0 | M91: 0 | N91: 0
A92: cost of carts | B92: --- page 5 ---. | C92: 0 | D92: 0 | E92: 0 | F92: 0 | H92: 0 | I92: 0 | J92: 0 | K92: 0 | L92: 0 | M92: 0 | N92: 0
A93: cost of carts | B93: same for the year 3pence. | C93: 0.01 | D93: 0 | E93: 0 | F93: 3 | H93: 0 | I93: 0 | J93: 0 | K93: 0 | L93: 0 | M93: 0 | N93: 0
A94: cost of carts | B94: one base bought for the saddle of the cart 4pence. | C94: 0.02 | D94: 0 | E94: 0 | F94: 4 | H94: 0 | I94: 0 | J94: 0 | K94: 0 | L94: 0 | M94: 0 | N94: 0
A95: cost of carts | B95: white-tawed leather bought for mending the harness of the cart for the year 3pence. | C95: 0.01 | D95: 0 | E95: 0 | F95: 3 | H95: 0 | I95: 0 | J95: 0 | K95: 0 | L95: 0 | M95: 0 | N95: 0
A96: cost of carts | B96: two halters bought 2pence. | C96: 0.01 | D96: 0 | E96: 0 | F96: 2 | H96: 0 | I96: 0 | J96: 0 | K96: 0 | L96: 0 | M96: 0 | N96: 0
A97: cost of carts | B97: one pair of traces bought 5pence. | C97: 0.02 | D97: 0 | E97: 0 | F97: 5 | H97: 0 | I97: 0 | J97: 0 | K97: 0 | L97: 0 | M97: 0 | N97: 0
... A117: cost of buildings | B117: sum 3 shilling 2½d. | C117: 0.15 | D117: 0 | E117: 3 | F117: 0 | H117: 0 | I117: 0 | J117: 0 | K117: 0 | L117: 0 | M117: 0 | N117: 0
A118: threshing corn | B118: the same accounts for threshing 9 quarters 1 bushel of wheat and curallum, 32 quarters 5 bushels of rye, and 4 bushels of peas by piecework 7 shilling ½d, for a quarter 2pence. | C118: 0.36 | D118: 0 | E118: 7 | F118: 2 | G118: wheat, rye, peas, curall | H118: 32 | I118: 9 | J118: 33.12 | K118: 9 | L118: 24.12 | M118: 9 | N118: 0 | O118: 32 | P118: 5 | Q118: 0 | R118: 4
A119: threshing corn | B119: 1 quarter 2 bushels of barley threshed by piecework 2pence. | C119: 0.01 | D119: 0 | E119: 0 | F119: 2 | G119: barley | H119: 0 | I119: 2 | J119: 0.25 | K119: 0.25 | L119: 0 | M119: 0 | N119: 2
A120: threshing corn | B120: 44 quarters 3 bushels of oats threshed by piecework 3 shilling 8½d, for a quarter 1pence. | C120: 0.15 | D120: 0 | E120: 3 | F120: 1 | G120: oats | H120: 44 | I120: 3 | J120: 44.38 | K120: 44.38 | L120: 0 | M120: 44 | N120: 3
A121: threshing corn | B121: winnowing all the aforesaid corn, which totalled 87 quarters 7 bushels, 2¼d, for a quarter ¼d. | C121: 0 | D121: 0 | E121: 0 | F121: 0 | H121: 87 | I121: 7 | J121: 87.88 | K121: 87.88 | L121: 0 | M121: 87 | N121: 7
A122: threshing corn | B122: sum 12 shilling 8¾d. | C122: 0.6 | D122: 0 | E122: 12 | F122: 0 | H122: 0 | I122: 0 | J122: 0 | K122: 0 | L122: 0 | M122: 0 | N122: 0
A123: purchase of corn | B123: the same accounts for 1 quarter of oats bought, as shown elsewhere, 15pence sum 15pence. | C123: 0.06 | D123: 0 | E123: 0 | F123: 15 | G123: oats | H123: 0 | I123: 0 | J123: 0 | K123: 0 | L123: 0 | M123: 0 | N123: 0
A124: purchase of corn | B124: --- page 6 ---. | C124: 0 | D124: 0 | E124: 0 | F124: 0 | H124: 0 | I124: 0 | J124: 0 | K124: 0 | L124: 0 | M124: 0 | N124: 0
A125: purchase of stock | B125: the same accounts as paid for 4 oxen bought for stock 50 shilling, attested by the same prior. | C125: 2.5 | D125: 0 | E125: 50 | F125: 0 | H125: 0 | I125: 0 | J125: 0 | K125: 0 | L125: 0 | M125: 0 | N125: 0
A126: purchase of stock | B126: 76 lambs bought before shearing 42 shilling 9pence. | C126: 2.14 | D126: 0 | E126: 42 | F126: 9 | H126: 0 | I126: 0 | J126: 0 | K126: 0 | L126: 0 | M126: 0 | N126: 0
A127: purchase of stock | B127: 34 lambs bought after shearing 22 shilling 8 pence, price of each 8pence sum 115 shilling 5pence. | C127: 1.13 | D127: 0 | E127: 22 | F127: 8 | H127: 0 | I127: 0 | J127: 0 | K127: 0 | L127: 0 | M127: 0 | N127: 0
A128: weeding and mowing | B128: the same accounts for weeding the lord’s corn at northwode this year 3 pence and at esher nothing because [by] the famuli. | C128: 0.01 | D128: 0 | E128: 0 | F128: 3 | H128: 0 | I128: 0 | J128: 0 | K128: 0 | L128: 0 | M128: 0 | N128: 0
A129: weeding and mowing | B129: expenses of customary tenants mowing the meadow of brodemed: bread and an accompaniment from stock, as elsewhere. | C129: 0 | D129: 0 | E129: 0 | F129: 0 | H129: 0 | I129: 0 | J129: 0 | K129: 0 | L129: 0 | M129: 0 | N129: 0
A130: weeding and mowing | B130: mowing and pitching the meadow of hullemed, the meadow of lake next to crumbe, and the meadow formerly of legarda atte mulle, containing in all 3 acres of meadow 22 pence, because [there was] much hay this year. | C130: 0.09 | D130: 0 | E130: 0 | F130: 22 | H130: 0 | I130: 0 | J130: 0 | K130: 0 | L130: 0 | M130: 0 | N130: 0
A131: weeding and mowing | B131: expenses of customary tenants carrying hay from brodemed to the manor: in an accompaniment 4 pence. | C131: 0.02 | D131: 0 | E131: 0 | F131: 4 | H131: 0 | I131: 0 | J131: 0 | K131: 0 | L131: 0 | M131: 0 | N131: 0
A132: weeding and mowing | B132: and bread from stock as elsewhere. | C132: 0 | D132: 0 | E132: 0 | F132: 0 | H132: 0 | I132: 0 | J132: 0 | K132: 0 | L132: 0 | M132: 0 | N132: 0
A133: weeding and mowing | B133: sum 2 shilling 5pence. | C133: 0.12 | D133: 0 | E133: 2 | F133: 5 | H133: 0 | I133: 0 | J133: 0 | K133: 0 | L133: 0 | M133: 0 | N133: 0
A134: cost of harvest | B134: the same accounts for an accompaniment bought for expenses of customary tenants at two boonworks called ‘waterbedrip’, each boonwork of 25 men reaping and binding all the lord’s corn at esher besides 1 acre of rye, 2 acres of peas, and 3 acres of oats, which were reaped by piecework, namely in 300 herrings 3 shilling 6 pence, price of a hundred 14 pence, to each by custom for a day six herrings. | C134: 0.17 | D134: 0 | E134: 3 | F134: 6 | G134: rye, oats, peas | H134: 0 | I134: 0 | J134: 0 | K134: 0 | L134: 0 | M134: 0 | N134: 0
A135: cost of harvest | B135: cheese bought for the same 6pence. | C135: 0.03 | D135: 0 | E135: 0 | F135: 6 | H135: 0 | I135: 0 | J135: 0 | K135: 0 | L135: 0 | M135: 0 | N135: 0
A136: cost of harvest | B136: reaping and binding 1 acre of rye, 2 acres of peas, and 3 acres of oats by piecework because they were not able to be done by the aforesaid two boonworks 2 shilling 6 pence, attested by the prior of sandon. | C136: 0.12 | D136: 0 | E136: 2 | F136: 6 | G136: rye, oats, peas | H136: 0 | I136: 0 | J136: 0 | K136: 0 | L136: 0 | M136: 0 | N136: 0
A137: cost of harvest | B137: likewise in reaping and binding 12 acres of rye, 20 acres 3 roods of oats at northwode by piecework 13 shilling 7¾d, for an acre 5 pence this year, by witness of the same prior. | C137: 0.67 | D137: 0 | E137: 13 | F137: 5 | G137: rye, oats | H137: 0 | I137: 0 | J137: 0 | K137: 0 | L137: 0 | M137: 0 | N137: 0
A138: cost of harvest | B138: sum 20 shilling 1¾d. | C138: 1 | D138: 0 | E138: 20 | F138: 0 | H138: 0 | I138: 0 | J138: 0 | K138: 0 | L138: 0 | M138: 0 | N138: 0
A139: foreign expenses | B139: the same accounts for driving 71 female hoggets to bishops sutton 6 pence, by order of the lord adam, stockman. | C139: 0.03 | D139: 0 | E139: 0 | F139: 6 | H139: 0 | I139: 0 | J139: 0 | K139: 0 | L139: 0 | M139: 0 | N139: 0
A140: foreign expenses | B140: bringing and carrying all the wool received at the shearing of the lord’s sheep, as shown elsewhere, to farnham 7pence sum 13pence. | C140: 0.03 | D140: 0 | E140: 0 | F140: 7 | H140: 0 | I140: 0 | J140: 0 | K140: 0 | L140: 0 | M140: 0 | N140: 0
A141: expenses of the steward | B141: the same accounts for the expenses of walter joce, steward, for his visit in the month of march 5 shilling 11 pence, by sealed bill. | C141: 0.3 | D141: 0 | E141: 5 | F141: 11 | H141: 0 | I141: 0 | J141: 0 | K141: 0 | L141: 0 | M141: 0 | N141: 0
A142: expenses of the steward | B142: sum 5 shilling 11pence. | C142: 0.3 | D142: 0 | E142: 5 | F142: 11 | H142: 0 | I142: 0 | J142: 0 | K142: 0 | L142: 0 | M142: 0 | N142: 0
A143: expenses of the steward | B143: <p>sum of all expenses £10 6 shilling 7¾d.<br>. | C143: 10.3 | D143: 10 | E143: 6 | F143: 0 | H143: 0 | I143: 0 | J143: 0 | K143: 0 | L143: 0 | M143: 0 | N143: 0
A144: expenses of the steward | B144: and he owes £12 11 shilling 11½d.</p>. | C144: 12.55 | D144: 12 | E144: 11 | F144: 0 | H144: 0 | I144: 0 | J144: 0 | K144: 0 | L144: 0 | M144: 0 | N144: 0
A145: expenses of the steward | B145: of which allowed to the same 10 shilling 7 pence paid to lord william de meone, treasurer of the lord’s household, in various provisions for the expenses of the said household, by one writ. | C145: 0.53 | D145: 0 | E145: 10 | F145: 7 | H145: 0 | I145: 0 | J145: 0 | K145: 0 | L145: 0 | M145: 0 | N145: 0
A146: expenses of the steward | B146: sum 10 shilling 7pence. | C146: 0.53 | D146: 0 | E146: 10 | F146: 7 | H146: 0 | I146: 0 | J146: 0 | K146: 0 | L146: 0 | M146: 0 | N146: 0
A147: expenses of the steward | B147: --- page 7 ---. | C147: 0 | D147: 0 | E147: 0 | F147: 0 | H147: 0 | I147: 0 | J147: 0 | K147: 0 | L147: 0 | M147: 0 | N147: 0
A148: expenses of the steward | B148: payment of money. | C148: 0 | D148: 0 | E148: 0 | F148: 0 | H148: 0 | I148: 0 | J148: 0 | K148: 0 | L148: 0 | M148: 0 | N148: 0
A149: expenses of the steward | B149: and paid to lord john de nubbelegh, treasurer of wolvesey, £9 5 shilling 7 pence, by one tally. | C149: 9.28 | D149: 9 | E149: 5 | F149: 7 | H149: 0 | I149: 0 | J149: 0 | K149: 0 | L149: 0 | M149: 0 | N149: 0
... A151: expenses of the steward | B151: and he owes net 55 shilling 9pence. | C151: 2.79 | D151: 0 | E151: 55 | F151: 9 | H151: 0 | I151: 0 | J151: 0 | K151: 0 | L151: 0 | M151: 0 | N151: 0
A152: wheat | B152: richard sewyne, reeve there, answers for 8 quarters 1 bushel of wheat received from issue of the granges of esher as well as northwode, threshed by piecework, razed measure, by one tally against the prior of sandon. | C152: 0 | D152: 0 | E152: 0 | F152: 0 | G152: wheat | H152: 8 | I152: 0 | J152: 8 | K152: 8 | L152: 0 | M152: 8 | N152: 0
A153: wheat | B153: and for 1 quarter of curallum received from issue of the said granges, threshed by the same, now by the same tally. | C153: 0 | D153: 0 | E153: 0 | F153: 0 | G153: curall | H153: 0 | I153: 0 | J153: 0 | K153: 0 | L153: 0 | M153: 0 | N153: 0
A154: wheat | B154: sum 9 quarters 1 bushel. | C154: 0 | D154: 0 | E154: 0 | F154: 0 | H154: 9 | I154: 0 | J154: 9 | K154: 9 | L154: 0 | M154: 9 | N154: 0
A155: wheat | B155: of which accounted for in seed over 6 acres 3 roods of land at esher in le buricheye and dyneslond 1 quarter 7 bushels, thus over an acre 2 bushels 1 peck. | C155: 0 | D155: 0 | E155: 0 | F155: 0 | H155: 0 | I155: 2 | J155: 0.25 | K155: 0.88 | L155: -0.62 | M155: 0 | N155: 7 | O155: 0 | P155: 2
A156: wheat | B156: and sold 6 bushels of curallum. | C156: 0 | D156: 0 | E156: 0 | F156: 0 | G156: curall | H156: 0 | I156: 6 | J156: 0.75 | K156: 0.75 | L156: 0 | M156: 0 | N156: 6
A157: wheat | B157: sold at the audit 6 quarters 4 bushels, for 32 shilling 6pence sum as above. | C157: 1.62 | D157: 0 | E157: 32 | F157: 6 | H157: 6 | I157: 4 | J157: 6.5 | K157: 6.5 | L157: 0 | M157: 6 | N157: 4
A158: wheat | B158: and it equals. | C158: 0 | D158: 0 | E158: 0 | F158: 0 | H158: 0 | I158: 0 | J158: 0 | K158: 0 | L158: 0 | M158: 0 | N158: 0
A159: rye | B159: the same answers for 32 quarters 5 bushels of rye received from issue of the said two granges, threshed by piecework, razed measure, by one tally against the aforesaid prior, of which from issue of northwode 13 quarters 1 bushel. | C159: 0 | D159: 0 | E159: 0 | F159: 0 | G159: rye | H159: 13 | I159: 5 | J159: 13.62 | K159: 32.62 | L159: -19 | M159: 32 | N159: 5 | O159: 13 | P159: 0
A160: rye | B160: sum 32 quarters 5 bushels. | C160: 0 | D160: 0 | E160: 0 | F160: 0 | H160: 32 | I160: 5 | J160: 32.62 | K160: 32.62 | L160: 0 | M160: 32 | N160: 5
A161: rye | B161: of which accounted for in seed over 28 acres by estimation, sown at esher as well as at northwode in parcels, 7 quarters 7 bushels, thus an acre takes 2 bushels 1 peck. | C161: 0 | D161: 0 | E161: 0 | F161: 0 | H161: 7 | I161: 2 | J161: 7.25 | K161: 7.88 | L161: -0.62 | M161: 7 | N161: 7 | O161: 0 | P161: 2
A162: rye | B162: to mixed corn for payment of the famuli, below, 16 quarters 2 bushels. | C162: 0 | D162: 0 | E162: 0 | F162: 0 | H162: 16 | I162: 2 | J162: 16.25 | K162: 16.25 | L162: 0 | M162: 16 | N162: 2
A163: rye | B163: customary payment to 14 customary tenants harrowing at the sowing of oats for one day 1 bushel. | C163: 0 | D163: 0 | E163: 0 | F163: 0 | G163: oats | H163: 0 | I163: 0 | J163: 0 | K163: 0 | L163: 0 | M163: 0 | N163: 0
A164: rye | B164: customary payment to customary tenants mowing the meadow of brodedmed and for the carriage of hay from the same meadow 3 bushels. | C164: 0 | D164: 0 | E164: 0 | F164: 0 | H164: 0 | I164: 3 | J164: 0.38 | K164: 0.38 | L164: 0 | M164: 0 | N164: 3
A165: rye | B165: expenses of the same reaping and binding the lord’s corn at esher for two wet boonworks, besides 1 acre of rye, 2 acres of peas, and 3 acres of oats that were reaped this year by piecework, 6 bushels by custom. | C165: 0 | D165: 0 | E165: 0 | F165: 0 | G165: rye, oats, peas | H165: 0 | I165: 6 | J165: 0.75 | K165: 0.75 | L165: 0 | M165: 0 | N165: 6
A166: rye | B166: and sold 6 quarters 7½ bushels, the eighth bushel heaped. | C166: 0 | D166: 0 | E166: 0 | F166: 0 | H166: 6 | I166: 0 | J166: 6 | K166: 6 | L166: 0 | M166: 6 | N166: 0
A167: rye | B167: a heap given for the same 1½ bushels. | C167: 0 | D167: 0 | E167: 0 | F167: 0 | H167: 0 | I167: 0 | J167: 0 | K167: 0 | L167: 0 | M167: 0 | N167: 0
A168: rye | B168: sum as above. | C168: 0 | D168: 0 | E168: 0 | F168: 0 | H168: 0 | I168: 0 | J168: 0 | K168: 0 | L168: 0 | M168: 0 | N168: 0
A169: rye | B169: and it equals. | C169: 0 | D169: 0 | E169: 0 | F169: 0 | H169: 0 | I169: 0 | J169: 0 | K169: 0 | L169: 0 | M169: 0 | N169: 0
A170: peas | B170: and for 4 bushels of peas received from issue of the grange of esher threshed by piecework by one tally against the said prior. | C170: 0 | D170: 0 | E170: 0 | F170: 0 | G170: peas | H170: 0 | I170: 4 | J170: 0.5 | K170: 0.5 | L170: 0 | M170: 0 | N170: 4
A171: peas | B171: sum 4 bushels. | C171: 0 | D171: 0 | E171: 0 | F171: 0 | H171: 0 | I171: 4 | J171: 0.5 | K171: 0.5 | L171: 0 | M171: 0 | N171: 4
A172: peas | B172: and it was sown over 2 acres at esher. | C172: 0 | D172: 0 | E172: 0 | F172: 0 | H172: 0 | I172: 0 | J172: 0 | K172: 0 | L172: 0 | M172: 0 | N172: 0
A173: peas | B173: and it equals. | C173: 0 | D173: 0 | E173: 0 | F173: 0 | H173: 0 | I173: 0 | J173: 0 | K173: 0 | L173: 0 | M173: 0 | N173: 0
A174: barley | B174: the same answers for 1 quarter 2 bushels of barley received from issue of the grange of esher, threshed by piecework, razed measure, by tally against the said prior. | C174: 0 | D174: 0 | E174: 0 | F174: 0 | G174: barley | H174: 0 | I174: 2 | J174: 0.25 | K174: 0.25 | L174: 0 | M174: 0 | N174: 2
A175: barley | B175: sum 1 quarter 2 bushels. | C175: 0 | D175: 0 | E175: 0 | F175: 0 | H175: 0 | I175: 2 | J175: 0.25 | K175: 0.25 | L175: 0 | M175: 0 | N175: 2
...

Sheet Receipts
A1: ESHER_1342 RECEIPTS
A2: Heading | B2: £ | C2: s | D2: d | F2: Total in £ | G2: Error | H2: Notes | I2: Own notes
A3: Arrears | B3: 0 | C3: 29 | D3: 0 | F3: 1.45 | H3: Richard Sewyne, reeve, answers for 29 shilling 6¼d received from arrears from the account for the preceding year.
A4: Arrears | B4: 0 | C4: 29 | D4: 0 | F4: 1.45 | H4: Sum 29 shilling 6¼d.
A5: Arrears total | F5: 2.9 | G5: 1.45 | H5: Total
A7: Sale of corn | B7: 0 | C7: 0 | D7: 21 | F7: 0.09 | H7: The same answers for 21 pence received from 5 bushels of curallum of wheat sold, price of a bushel 3½d.
A8: Sale of corn | B8: 0 | C8: 12 | D8: 8 | F8: 0.63 | H8: And for 12 shilling received from 3 quarters of rye sold in the month of September, price of a quarter 4 shilling And for 18 shilling 4½d received from 3 quarters 7½ bushels of rye, price of a quarter 4 shilling 8pence And for 4 shilling 1¼d received from 1 quarter 1 bushel 3 pecks of barley sold, price of a bushel 5pence And for 13 shilling 6¼d received from 10 quarters 6 bushels 3 pecks of oats sold to Earl Warenne, price of a quarter 15pence And for 4 shilling 11 pence from 3½ quarters of oats sold for expenses of the lord’s household.
A9: Sale of corn | B9: 0 | C9: 54 | D9: 8 | F9: 2.73 | H9: Sum 54 shilling 8pence.
A10: Sale of corn total | F10: 3.45 | G10: 0.72 | H10: Total
A12: Sale of stock | B12: 0 | C12: 54 | D12: 6 | F12: 2.73 | H12: The same answers for 54 shilling received from 4 oxen because they were of no use to the stock, attested by the prior of Sandon, price of which 13 shilling 6pence And for 10 shilling 6 pence received from 10 wethers and 4 ewes, old, sold, price of each of which 9pence And for 71 shilling from 71 hoggets sold.
A13: Sale of stock | B13: 6 | C13: 15 | D13: 6 | F13: 6.78 | H13: Sum £6 15 shilling 6pence.
A14: Sale of stock total | F14: 9.51 | G14: 2.73 | H14: Total
A16: Perquisites of court | B16: 0 | C16: 0 | D16: 15 | F16: 0.06 | H16: The same answers for 15 pence received from the perquisites of a court held on the Tuesday next after the feast of St Luke [22 October].
A17: Perquisites of court | B17: 0 | C17: 17 | D17: 0 | F17: 0.85 | H17: And for 17 shilling received from the perquisites of the tourn of St Martin with a court held on the Saturday next after the feast of St Mathias the Apostle [1 March] together with ½ mark from the heriot.
A18: Perquisites of court total | B18: 0 | C18: 0 | D18: 0 | F18: 0.91 | G18: 0 | H18: --- Page 4 ---.
A19: Total of all receipts recorded in accounts (calculated here) | F19: =SUMIF(A1:A18,"* total",F1:F18)-SUMIF(A1:A18,"Arrears total",F1:F18)
A20: Total of all receipts (calculated here) incl arrears | F20: =F19+SUMIF(A1:A18,"Arrears total",F1:F18)

Sheet Overview

Sheet Issues of the Mills

Sheet Stock

Sheet Prices

Sheet Labour Rents

Sheet not needed

Sheet Issues of the Grange raw
A1: Heading | B1: Sentence | C1: Quarters 1_x | D1: Bushels 1_x | E1: Sown Quarters | F1: Sown Bushels | G1: Sown Total Quarters | H1: Bought in Quarters | I1: Bought in Bushels | J1: Bought in Total Quarters | K1: Tithe Quarters | L1: Tithe Bushels | M1: Tithe Total Quarters | N1: Manorial servants & livestock Quarters | O1: Manorial servants & livestock Bushels | P1: Manorial servants & livestock Total Quarters | Q1: Sold Quarters | R1: Sold Bushels | S1: Sold Total Quarters | T1: Account Quarters | U1: Account Bushels | V1: Account Total Quarters | W1: bought only | X1: Total Quarters Except 1 | Y1: Total Bushels Except 1 | Z1: Total Corn Cross-Check | AA1: Total Corn Manorial Account | AB1: Corn Quantity Error | AC1: Quarters 1_y | AD1: Bushels 1_y | AE1: Quarters 2 | AF1: Bushels 2 | AG1: Quarters 3 | AH1: Bushels 3 | AI1: Total Bought Quarters
A2: expenses of the steward | B2: total | C2: 0 | D2: 0 | E2: 0 | F2: 0 | G2: 0 | H2: 0 | I2: 0 | J2: 0 | K2: 0 | L2: 0 | M2: 0 | N2: 0 | O2: 0 | P2: 0 | Q2: 0 | R2: 0 | S2: 0 | T2: 0 | U2: 0 | V2: 0 | W2: 0 | AI2: 0
A3: wheat | B3: richard sewyne, reeve there, answers for 8 quarters 1 bushel of wheat received from issue of the granges of esher as well as northwode, threshed by piecework, razed measure, by one tally against the prior of sandon. | C3: 0 | D3: 0 | E3: 0 | F3: 0 | G3: 0 | H3: 0 | I3: 0 | J3: 0 | K3: 0 | L3: 0 | M3: 0 | N3: 0 | O3: 0 | P3: 0 | Q3: 0 | R3: 0 | S3: 0 | T3: 0 | U3: 0 | V3: 0 | W3: 0 | X3: 8 | Y3: 0 | Z3: 8 | AA3: 8 | AB3: 0 | AC3: 8 | AD3: 0 | AI3: 0
A4: wheat | B4: and for 1 quarter of curallum received from issue of the said granges, threshed by the same, now by the same tally. | C4: 0 | D4: 0 | E4: 0 | F4: 0 | G4: 0 | H4: 0 | I4: 0 | J4: 0 | K4: 0 | L4: 0 | M4: 0 | N4: 0 | O4: 0 | P4: 0 | Q4: 0 | R4: 0 | S4: 0 | T4: 0 | U4: 0 | V4: 0 | W4: 0 | X4: 0 | Y4: 0 | Z4: 0 | AA4: 0 | AB4: 0 | AC4: 0 | AD4: 0 | AI4: 0
A5: wheat | B5: sum 9 quarters 1 bushel. | C5: 0 | D5: 0 | E5: 0 | F5: 0 | G5: 0 | H5: 0 | I5: 0 | J5: 0 | K5: 0 | L5: 0 | M5: 0 | N5: 0 | O5: 0 | P5: 0 | Q5: 0 | R5: 0 | S5: 0 | T5: 0 | U5: 0 | V5: 0 | W5: 0 | X5: 9 | Y5: 0 | Z5: 9 | AA5: 9 | AB5: 0 | AC5: 9 | AD5: 0 | AI5: 0
A6: wheat | B6: of which accounted for in seed over 6 acres 3 roods of land at esher in le buricheye and dyneslond 1 quarter 7 bushels, thus over an acre 2 bushels 1 peck. | C6: 0 | D6: 0 | E6: 0 | F6: 0 | G6: 0 | H6: 0 | I6: 0 | J6: 0 | K6: 0 | L6: 0 | M6: 0 | N6: 0 | O6: 0 | P6: 0 | Q6: 0 | R6: 0 | S6: 0 | T6: 0 | U6: 0 | V6: 0 | W6: 0 | X6: 0 | Y6: 2 | Z6: 0.25 | AA6: 0.88 | AB6: -0.62 | AC6: 0 | AD6: 7 | AE6: 0 | AF6: 2 | AI6: 0
A7: wheat | B7: and sold 6 bushels of curallum. | C7: 0 | D7: 0 | E7: 0 | F7: 0 | G7: 0 | H7: 0 | I7: 0 | J7: 0 | K7: 0 | L7: 0 | M7: 0 | N7: 0 | O7: 0 | P7: 0 | Q7: 0 | R7: 0 | S7: 0 | T7: 0 | U7: 0 | V7: 0 | W7: 0 | X7: 0 | Y7: 6 | Z7: 0.75 | AA7: 0.75 | AB7: 0 | AC7: 0 | AD7: 6 | AI7: 0
A8: wheat | B8: sold at the audit 6 quarters 4 bushels, for 32 shilling 6pence sum as above. | C8: 0 | D8: 0 | E8: 0 | F8: 0 | G8: 0 | H8: 0 | I8: 0 | J8: 0 | K8: 0 | L8: 0 | M8: 0 | N8: 0 | O8: 0 | P8: 0 | Q8: 6 | R8: 4 | S8: 6.5 | T8: 0 | U8: 0 | V8: 0 | W8: 0 | X8: 6 | Y8: 4 | Z8: 6.5 | AA8: 6.5 | AB8: 0 | AC8: 6 | AD8: 4 | AI8: 0
A9: wheat | B9: and it equals. | C9: 0 | D9: 0 | E9: 0 | F9: 0 | G9: 0 | H9: 0 | I9: 0 | J9: 0 | K9: 0 | L9: 0 | M9: 0 | N9: 0 | O9: 0 | P9: 0 | Q9: 0 | R9: 0 | S9: 0 | T9: 0 | U9: 0 | V9: 0 | W9: 0 | X9: 0 | Y9: 0 | Z9: 0 | AA9: 0 | AB9: 0 | AC9: 0 | AD9: 0 | AI9: 0
A10: wheat | B10: total | C10: 0 | D10: 0 | E10: 0 | F10: 0 | G10: 0 | H10: 0 | I10: 0 | J10: 0 | K10: 0 | L10: 0 | M10: 0 | N10: 0 | O10: 0 | P10: 0 | Q10: 0 | R10: 0 | S10: 0 | T10: 0 | U10: 0 | V10: 0 | W10: 0 | AI10: 0
A11: rye | B11: the same answers for 32 quarters 5 bushels of rye received from issue of the said two granges, threshed by piecework, razed measure, by one tally against the aforesaid prior, of which from issue of northwode 13 quarters 1 bushel. | C11: 0 | D11: 0 | E11: 0 | F11: 0 | G11: 0 | H11: 0 | I11: 0 | J11: 0 | K11: 0 | L11: 0 | M11: 0 | N11: 0 | O11: 0 | P11: 0 | Q11: 0 | R11: 0 | S11: 0 | T11: 0 | U11: 0 | V11: 0 | W11: 0 | X11: 13 | Y11: 5 | Z11: 13.62 | AA11: 32.62 | AB11: -19 | AC11: 32 | AD11: 5 | AE11: 13 | AF11: 0 | AI11: 0
A12: rye | B12: sum 32 quarters 5 bushels. | C12: 0 | D12: 0 | E12: 0 | F12: 0 | G12: 0 | H12: 0 | I12: 0 | J12: 0 | K12: 0 | L12: 0 | M12: 0 | N12: 0 | O12: 0 | P12: 0 | Q12: 0 | R12: 0 | S12: 0 | T12: 0 | U12: 0 | V12: 0 | W12: 0 | X12: 32 | Y12: 5 | Z12: 32.62 | AA12: 32.62 | AB12: 0 | AC12: 32 | AD12: 5 | AI12: 0
A13: rye | B13: of which accounted for in seed over 28 acres by estimation, sown at esher as well as at northwode in parcels, 7 quarters 7 bushels, thus an acre takes 2 bushels 1 peck. | C13: 0 | D13: 0 | E13: 7 | F13: 7 | G13: 7.88 | H13: 0 | I13: 0 | J13: 0 | K13: 0 | L13: 0 | M13: 0 | N13: 0 | O13: 0 | P13: 0 | Q13: 0 | R13: 0 | S13: 0 | T13: 0 | U13: 0 | V13: 0 | W13: 0 | X13: 7 | Y13: 2 | Z13: 7.25 | AA13: 7.88 | AB13: -0.62 | AC13: 7 | AD13: 7 | AE13: 0 | AF13: 2 | AI13: 0
A14: rye | B14: to mixed corn for payment of the famuli, below, 16 quarters 2 bushels. | C14: 0 | D14: 0 | E14: 0 | F14: 0 | G14: 0 | H14: 0 | I14: 0 | J14: 0 | K14: 0 | L14: 0 | M14: 0 | N14: 0 | O14: 0 | P14: 0 | Q14: 0 | R14: 0 | S14: 0 | T14: 0 | U14: 0 | V14: 0 | W14: 0 | X14: 16 | Y14: 2 | Z14: 16.25 | AA14: 16.25 | AB14: 0 | AC14: 16 | AD14: 2 | AI14: 0
A15: rye | B15: customary payment to 14 customary tenants harrowing at the sowing of oats for one day 1 bushel. | C15: 0 | D15: 0 | E15: 0 | F15: 0 | G15: 0 | H15: 0 | I15: 0 | J15: 0 | K15: 0 | L15: 0 | M15: 0 | N15: 0 | O15: 0 | P15: 0 | Q15: 0 | R15: 0 | S15: 0 | T15: 0 | U15: 0 | V15: 0 | W15: 0 | X15: 0 | Y15: 0 | Z15: 0 | AA15: 0 | AB15: 0 | AC15: 0 | AD15: 0 | AI15: 0
A16: rye | B16: customary payment to customary tenants mowing the meadow of brodedmed and for the carriage of hay from the same meadow 3 bushels. | C16: 0 | D16: 0 | E16: 0 | F16: 0 | G16: 0 | H16: 0 | I16: 0 | J16: 0 | K16: 0 | L16: 0 | M16: 0 | N16: 0 | O16: 0 | P16: 0 | Q16: 0 | R16: 0 | S16: 0 | T16: 0 | U16: 0 | V16: 0 | W16: 0 | X16: 0 | Y16: 3 | Z16: 0.38 | AA16: 0.38 | AB16: 0 | AC16: 0 | AD16: 3 | AI16: 0
A17: rye | B17: expenses of the same reaping and binding the lord’s corn at esher for two wet boonworks, besides 1 acre of rye, 2 acres of peas, and 3 acres of oats that were reaped this year by piecework, 6 bushels by custom. | C17: 0 | D17: 0 | E17: 0 | F17: 0 | G17: 0 | H17: 0 | I17: 0 | J17: 0 | K17: 0 | L17: 0 | M17: 0 | N17: 0 | O17: 0 | P17: 0 | Q17: 0 | R17: 0 | S17: 0 | T17: 0 | U17: 0 | V17: 0 | W17: 0 | X17: 0 | Y17: 6 | Z17: 0.75 | AA17: 0.75 | AB17: 0 | AC17: 0 | AD17: 6 | AI17: 0
A18: rye | B18: and sold 6 quarters 7½ bushels, the eighth bushel heaped. | C18: 0 | D18: 0 | E18: 0 | F18: 0 | G18: 0 | H18: 0 | I18: 0 | J18: 0 | K18: 0 | L18: 0 | M18: 0 | N18: 0 | O18: 0 | P18: 0 | Q18: 6 | R18: 0 | S18: 6 | T18: 0 | U18: 0 | V18: 0 | W18: 0 | X18: 6 | Y18: 0 | Z18: 6 | AA18: 6 | AB18: 0 | AC18: 6 | AD18: 0 | AI18: 0
A19: rye | B19: a heap given for the same 1½ bushels. | C19: 0 | D19: 0 | E19: 0 | F19: 0 | G19: 0 | H19: 0 | I19: 0 | J19: 0 | K19: 0 | L19: 0 | M19: 0 | N19: 0 | O19: 0 | P19: 0 | Q19: 0 | R19: 0 | S19: 0 | T19: 0 | U19: 0 | V19: 0 | W19: 0 | X19: 0 | Y19: 0 | Z19: 0 | AA19: 0 | AB19: 0 | AC19: 0 | AD19: 0 | AI19: 0
A20: rye | B20: sum as above. | C20: 0 | D20: 0 | E20: 0 | F20: 0 | G20: 0 | H20: 0 | I20: 0 | J20: 0 | K20: 0 | L20: 0 | M20: 0 | N20: 0 | O20: 0 | P20: 0 | Q20: 0 | R20: 0 | S20: 0 | T20: 0 | U20: 0 | V20: 0 | W20: 0 | X20: 0 | Y20: 0 | Z20: 0 | AA20: 0 | AB20: 0 | AC20: 0 | AD20: 0 | AI20: 0
A21: rye | B21: and it equals. | C21: 0 | D21: 0 | E21: 0 | F21: 0 | G21: 0 | H21: 0 | I21: 0 | J21: 0 | K21: 0 | L21: 0 | M21: 0 | N21: 0 | O21: 0 | P21: 0 | Q21: 0 | R21: 0 | S21: 0 | T21: 0 | U21: 0 | V21: 0 | W21: 0 | X21: 0 | Y21: 0 | Z21: 0 | AA21: 0 | AB21: 0 | AC21: 0 | AD21: 0 | AI21: 0
A22: rye | B22: total | C22: 0 | D22: 0 | E22: 0 | F22: 0 | G22: 0 | H22: 0 | I22: 0 | J22: 0 | K22: 0 | L22: 0 | M22: 0 | N22: 0 | O22: 0 | P22: 0 | Q22: 0 | R22: 0 | S22: 0 | T22: 0 | U22: 0 | V22: 0 | W22: 0 | AI22: 0
A23: peas | B23: and for 4 bushels of peas received from issue of the grange of esher threshed by piecework by one tally against the said prior. | C23: 0 | D23: 0 | E23: 0 | F23: 0 | G23: 0 | H23: 0 | I23: 0 | J23: 0 | K23: 0 | L23: 0 | M23: 0 | N23: 0 | O23: 0 | P23: 0 | Q23: 0 | R23: 0 | S23: 0 | T23: 0 | U23: 0 | V23: 0 | W23: 0 | X23: 0 | Y23: 4 | Z23: 0.5 | AA23: 0.5 | AB23: 0 | AC23: 0 | AD23: 4 | AI23: 0
A24: peas | B24: sum 4 bushels. | C24: 0 | D24: 0 | E24: 0 | F24: 0 | G24: 0 | H24: 0 | I24: 0 | J24: 0 | K24: 0 | L24: 0 | M24: 0 | N24: 0 | O24: 0 | P24: 0 | Q24: 0 | R24: 0 | S24: 0 | T24: 0 | U24: 0 | V24: 0 | W24: 0 | X24: 0 | Y24: 4 | Z24: 0.5 | AA24: 0.5 | AB24: 0 | AC24: 0 | AD24: 4 | AI24: 0
A25: peas | B25: and it was sown over 2 acres at esher. | C25: 0 | D25: 0 | E25: 0 | F25: 0 | G25: 0 | H25: 0 | I25: 0 | J25: 0 | K25: 0 | L25: 0 | M25: 0 | N25: 0 | O25: 0 | P25: 0 | Q25: 0 | R25: 0 | S25: 0 | T25: 0 | U25: 0 | V25: 0 | W25: 0 | X25: 0 | Y25: 0 | Z25: 0 | AA25: 0 | AB25: 0 | AC25: 0 | AD25: 0 | AI25: 0
A26: peas | B26: and it equals. | C26: 0 | D26: 0 | E26: 0 | F26: 0 | G26: 0 | H26: 0 | I26: 0 | J26: 0 | K26: 0 | L26: 0 | M26: 0 | N26: 0 | O26: 0 | P26: 0 | Q26: 0 | R26: 0 | S26: 0 | T26: 0 | U26: 0 | V26: 0 | W26: 0 | X26: 0 | Y26: 0 | Z26: 0 | AA26: 0 | AB26: 0 | AC26: 0 | AD26: 0 | AI26: 0
A27: peas | B27: total | C27: 0 | D27: 0 | E27: 0 | F27: 0 | G27: 0 | H27: 0 | I27: 0 | J27: 0 | K27: 0 | L27: 0 | M27: 0 | N27: 0 | O27: 0 | P27: 0 | Q27: 0 | R27: 0 | S27: 0 | T27: 0 | U27: 0 | V27: 0 | W27: 0 | AI27: 0
A28: barley | B28: the same answers for 1 quarter 2 bushels of barley received from issue of the grange of esher, threshed by piecework, razed measure, by tally against the said prior. | C28: 0 | D28: 0 | E28: 0 | F28: 0 | G28: 0 | H28: 0 | I28: 0 | J28: 0 | K28: 0 | L28: 0 | M28: 0 | N28: 0 | O28: 0 | P28: 0 | Q28: 0 | R28: 0 | S28: 0 | T28: 0 | U28: 0 | V28: 0 | W28: 0 | X28: 0 | Y28: 2 | Z28: 0.25 | AA28: 0.25 | AB28: 0 | AC28: 0 | AD28: 2 | AI28: 0
A29: barley | B29: sum 1 quarter 2 bushels. | C29: 0 | D29: 0 | E29: 0 | F29: 0 | G29: 0 | H29: 0 | I29: 0 | J29: 0 | K29: 0 | L29: 0 | M29: 0 | N29: 0 | O29: 0 | P29: 0 | Q29: 0 | R29: 0 | S29: 0 | T29: 0 | U29: 0 | V29: 0 | W29: 0 | X29: 0 | Y29: 2 | Z29: 0.25 | AA29: 0.25 | AB29: 0 | AC29: 0 | AD29: 2 | AI29: 0
A30: barley | B30: of which accounted for as sold 1 quarter 1 bushel 3 pecks, the eighth bushel heaped. | C30: 0 | D30: 0 | E30: 0 | F30: 0 | G30: 0 | H30: 0 | I30: 0 | J30: 0 | K30: 0 | L30: 0 | M30: 0 | N30: 0 | O30: 0 | P30: 0 | Q30: 0 | R30: 0 | S30: 0 | T30: 0 | U30: 0 | V30: 0 | W30: 0 | X30: 0 | Y30: 0 | Z30: 0 | AA30: 0 | AB30: 0 | AC30: 0 | AD30: 0 | AI30: 0
A31: barley | B31: a heap given for the same 1 peck. | C31: 0 | D31: 0 | E31: 0 | F31: 0 | G31: 0 | H31: 0 | I31: 0 | J31: 0 | K31: 0 | L31: 0 | M31: 0 | N31: 0 | O31: 0 | P31: 0 | Q31: 0 | R31: 0 | S31: 0 | T31: 0 | U31: 0 | V31: 0 | W31: 0 | X31: 0 | Y31: 0 | Z31: 0 | AA31: 0 | AB31: 0 | AC31: 0 | AD31: 0 | AI31: 0
A32: barley | B32: sum as above. | C32: 0 | D32: 0 | E32: 0 | F32: 0 | G32: 0 | H32: 0 | I32: 0 | J32: 0 | K32: 0 | L32: 0 | M32: 0 | N32: 0 | O32: 0 | P32: 0 | Q32: 0 | R32: 0 | S32: 0 | T32: 0 | U32: 0 | V32: 0 | W32: 0 | X32: 0 | Y32: 0 | Z32: 0 | AA32: 0 | AB32: 0 | AC32: 0 | AD32: 0 | AI32: 0
A33: barley | B33: and it equals. | C33: 0 | D33: 0 | E33: 0 | F33: 0 | G33: 0 | H33: 0 | I33: 0 | J33: 0 | K33: 0 | L33: 0 | M33: 0 | N33: 0 | O33: 0 | P33: 0 | Q33: 0 | R33: 0 | S33: 0 | T33: 0 | U33: 0 | V33: 0 | W33: 0 | X33: 0 | Y33: 0 | Z33: 0 | AA33: 0 | AB33: 0 | AC33: 0 | AD33: 0 | AI33: 0
A34: barley | B34: --- page 8 ---. | C34: 0 | D34: 0 | E34: 0 | F34: 0 | G34: 0 | H34: 0 | I34: 0 | J34: 0 | K34: 0 | L34: 0 | M34: 0 | N34: 0 | O34: 0 | P34: 0 | Q34: 0 | R34: 0 | S34: 0 | T34: 0 | U34: 0 | V34: 0 | W34: 0 | X34: 0 | Y34: 0 | Z34: 0 | AA34: 0 | AB34: 0 | AC34: 0 | AD34: 0 | AI34: 0
A35: barley | B35: total | C35: 0 | D35: 0 | E35: 0 | F35: 0 | G35: 0 | H35: 0 | I35: 0 | J35: 0 | K35: 0 | L35: 0 | M35: 0 | N35: 0 | O35: 0 | P35: 0 | Q35: 0 | R35: 0 | S35: 0 | T35: 0 | U35: 0 | V35: 0 | W35: 0 | AI35: 0
A36: oats | B36: the same answers for 9 quarters 2 bushels of large oats received from issue of the grange of esher threshed by piecework, razed measure, by one tally against the same prior. | C36: 0 | D36: 0 | E36: 0 | F36: 0 | G36: 0 | H36: 0 | I36: 0 | J36: 0 | K36: 0 | L36: 0 | M36: 0 | N36: 0 | O36: 0 | P36: 0 | Q36: 0 | R36: 0 | S36: 0 | T36: 0 | U36: 0 | V36: 0 | W36: 0 | X36: 9 | Y36: 2 | Z36: 9.25 | AA36: 9.25 | AB36: 0 | AC36: 9 | AD36: 2 | AI36: 0
A37: oats | B37: and for 35 quarters 1 bushel of oats received from issue of the granges of esher and northwode, threshed by piecework, razed measure, by the same tally, of which at northwode 16 quarters. | C37: 0 | D37: 0 | E37: 0 | F37: 0 | G37: 0 | H37: 0 | I37: 0 | J37: 0 | K37: 0 | L37: 0 | M37: 0 | N37: 0 | O37: 0 | P37: 0 | Q37: 0 | R37: 0 | S37: 0 | T37: 0 | U37: 0 | V37: 0 | W37: 0 | X37: 16 | Y37: 0 | Z37: 16 | AA37: 35 | AB37: -19 | AC37: 35 | AD37: 0 | AE37: 16 | AF37: 0 | AI37: 0
A38: oats | B38: and for 1 quarter of small oats received in three shocks of sheaves by estimation from the same issue for fodder for the oxen, a shock containing 15 sheaves. | C38: 0 | D38: 0 | E38: 0 | F38: 0 | G38: 0 | H38: 0 | I38: 0 | J38: 0 | K38: 0 | L38: 0 | M38: 0 | N38: 0 | O38: 0 | P38: 0 | Q38: 0 | R38: 0 | S38: 0 | T38: 0 | U38: 0 | V38: 0 | W38: 0 | X38: 0 | Y38: 0 | Z38: 0 | AA38: 0 | AB38: 0 | AC38: 0 | AD38: 0 | AI38: 0
A39: oats | B39: and for 1 quarter of oats bought, the eighth bushel heaped. | C39: 0 | D39: 0 | E39: 0 | F39: 0 | G39: 0 | H39: 0 | I39: 0 | J39: 0 | K39: 0 | L39: 0 | M39: 0 | N39: 0 | O39: 0 | P39: 0 | Q39: 0 | R39: 0 | S39: 0 | T39: 0 | U39: 0 | V39: 0 | W39: 0 | X39: 0 | Y39: 0 | Z39: 0 | AA39: 0 | AB39: 0 | AC39: 0 | AD39: 0 | AI39: 0
A40: oats | B40: and for 1 peck from increment for the heap. | C40: 0 | D40: 0 | E40: 0 | F40: 0 | G40: 0 | H40: 0 | I40: 0 | J40: 0 | K40: 0 | L40: 0 | M40: 0 | N40: 0 | O40: 0 | P40: 0 | Q40: 0 | R40: 0 | S40: 0 | T40: 0 | U40: 0 | V40: 0 | W40: 0 | X40: 0 | Y40: 0 | Z40: 0 | AA40: 0 | AB40: 0 | AC40: 0 | AD40: 0 | AI40: 0
A41: oats | B41: and for 1 quarter 1½ bushels from increment. | C41: 0 | D41: 0 | E41: 0 | F41: 0 | G41: 0 | H41: 0 | I41: 0 | J41: 0 | K41: 0 | L41: 0 | M41: 0 | N41: 0 | O41: 0 | P41: 0 | Q41: 0 | R41: 0 | S41: 0 | T41: 0 | U41: 0 | V41: 0 | W41: 0 | X41: 0 | Y41: 0 | Z41: 0 | AA41: 0 | AB41: 0 | AC41: 0 | AD41: 0 | AI41: 0
A42: oats | B42: sum 47 quarters 3 bushels 3 pecks. | C42: 0 | D42: 0 | E42: 0 | F42: 0 | G42: 0 | H42: 0 | I42: 0 | J42: 0 | K42: 0 | L42: 0 | M42: 0 | N42: 0 | O42: 0 | P42: 0 | Q42: 0 | R42: 0 | S42: 0 | T42: 0 | U42: 0 | V42: 0 | W42: 0 | X42: 47 | Y42: 3 | Z42: 47.38 | AA42: 47.38 | AB42: 0 | AC42: 47 | AD42: 3 | AI42: 0
A43: oats | B43: the same accounts in seed over 26 acres 3 roods of land at esher and over 20 acres 3 roods at northwode 25 quarters 6 bushels, of which 7 quarters was large oats, thus an acre takes 4½ bushels. | C43: 0 | D43: 0 | E43: 0 | F43: 0 | G43: 0 | H43: 0 | I43: 0 | J43: 0 | K43: 0 | L43: 0 | M43: 0 | N43: 0 | O43: 0 | P43: 0 | Q43: 0 | R43: 0 | S43: 0 | T43: 0 | U43: 0 | V43: 0 | W43: 0 | X43: 7 | Y43: 6 | Z43: 7.75 | AA43: 25.75 | AB43: -18 | AC43: 25 | AD43: 6 | AE43: 7 | AF43: 0 | AI43: 0
A44: oats | B44: flour made for pottage for the manorial famuli for the year 1 quarter 6 bushels. | C44: 0 | D44: 0 | E44: 0 | F44: 0 | G44: 0 | H44: 0 | I44: 0 | J44: 0 | K44: 0 | L44: 0 | M44: 0 | N44: 0 | O44: 0 | P44: 0 | Q44: 0 | R44: 0 | S44: 0 | T44: 0 | U44: 0 | V44: 0 | W44: 0 | X44: 0 | Y44: 6 | Z44: 0.75 | AA44: 0.75 | AB44: 0 | AC44: 0 | AD44: 6 | AI44: 0
A45: oats | B45: fodder for 2 cart horses of the manor in winter at sowing time 1½ quarters this year. | C45: 0 | D45: 0 | E45: 0 | F45: 0 | G45: 0 | H45: 0 | I45: 0 | J45: 0 | K45: 0 | L45: 0 | M45: 0 | N45: 0 | O45: 0 | P45: 0 | Q45: 0 | R45: 0 | S45: 0 | T45: 0 | U45: 0 | V45: 0 | W45: 0 | X45: 0 | Y45: 0 | Z45: 0 | AA45: 0 | AB45: 0 | AC45: 0 | AD45: 0 | AI45: 0
A46: oats | B46: fodder for 6 oxen ploughing at sowing time in sheaves as above, estimated at 1 quarter. | C46: 0 | D46: 0 | E46: 0 | F46: 0 | G46: 0 | H46: 0 | I46: 0 | J46: 0 | K46: 0 | L46: 0 | M46: 0 | N46: 0 | O46: 0 | P46: 0 | Q46: 0 | R46: 0 | S46: 0 | T46: 0 | U46: 0 | V46: 0 | W46: 0 | X46: 0 | Y46: 0 | Z46: 0 | AA46: 0 | AB46: 0 | AC46: 0 | AD46: 0 | AI46: 0
A47: oats | B47: fodder for the horses of the steward for his coming for holding court and supervising the manor 2 quarters 1½ bushels by tally and sealed bill. | C47: 0 | D47: 0 | E47: 0 | F47: 0 | G47: 0 | H47: 0 | I47: 0 | J47: 0 | K47: 0 | L47: 0 | M47: 0 | N47: 0 | O47: 0 | P47: 0 | Q47: 0 | R47: 0 | S47: 0 | T47: 0 | U47: 0 | V47: 0 | W47: 0 | X47: 2 | Y47: 0 | Z47: 2 | AA47: 2 | AB47: 0 | AC47: 2 | AD47: 0 | AI47: 0
A48: oats | B48: given to the purveyor of the household of the duke of cornwall for taking neither the lord’s oats nor hay within the manor 4 bushels. | C48: 0 | D48: 0 | E48: 0 | F48: 0 | G48: 0 | H48: 0 | I48: 0 | J48: 0 | K48: 0 | L48: 0 | M48: 0 | N48: 0 | O48: 0 | P48: 0 | Q48: 0 | R48: 0 | S48: 0 | T48: 0 | U48: 0 | V48: 0 | W48: 0 | X48: 0 | Y48: 4 | Z48: 0.5 | AA48: 0.5 | AB48: 0 | AC48: 0 | AD48: 4 | AI48: 0
A49: oats | B49: and sold 14 quarters 2½ bushels 1 peck, for the expenses of the lord’s household 3½ quarters, razed measure, and 10 quarters 6½ bushels for the use of earl warenne, residing within the manor for one night, the eighth bushel heaped. | C49: 0 | D49: 0 | E49: 0 | F49: 0 | G49: 0 | H49: 0 | I49: 0 | J49: 0 | K49: 0 | L49: 0 | M49: 0 | N49: 0 | O49: 0 | P49: 0 | Q49: 24 | R49: 0 | S49: 24 | T49: 0 | U49: 0 | V49: 0 | W49: 0 | X49: 10 | Y49: 0 | Z49: 10 | AA49: 14 | AB49: -4 | AC49: 14 | AD49: 0 | AE49: 10 | AF49: 0 | AI49: 0
A50: oats | B50: heaps given for the same 2½ bushels. | C50: 0 | D50: 0 | E50: 0 | F50: 0 | G50: 0 | H50: 0 | I50: 0 | J50: 0 | K50: 0 | L50: 0 | M50: 0 | N50: 0 | O50: 0 | P50: 0 | Q50: 0 | R50: 0 | S50: 0 | T50: 0 | U50: 0 | V50: 0 | W50: 0 | X50: 0 | Y50: 0 | Z50: 0 | AA50: 0 | AB50: 0 | AC50: 0 | AD50: 0 | AI50: 0
A51: oats | B51: and at the audit 2 bushels, for 6pence sum as above. | C51: 0 | D51: 0 | E51: 0 | F51: 0 | G51: 0 | H51: 0 | I51: 0 | J51: 0 | K51: 0 | L51: 0 | M51: 0 | N51: 0 | O51: 0 | P51: 0 | Q51: 0 | R51: 0 | S51: 0 | T51: 0 | U51: 0 | V51: 0 | W51: 0 | X51: 0 | Y51: 2 | Z51: 0.25 | AA51: 0.25 | AB51: 0 | AC51: 0 | AD51: 2 | AI51: 0
A52: oats | B52: and it equals. | C52: 0 | D52: 0 | E52: 0 | F52: 0 | G52: 0 | H52: 0 | I52: 0 | J52: 0 | K52: 0 | L52: 0 | M52: 0 | N52: 0 | O52: 0 | P52: 0 | Q52: 0 | R52: 0 | S52: 0 | T52: 0 | U52: 0 | V52: 0 | W52: 0 | X52: 0 | Y52: 0 | Z52: 0 | AA52: 0 | AB52: 0 | AC52: 0 | AD52: 0 | AI52: 0
A53: oats | B53: total | C53: 0 | D53: 0 | E53: 0 | F53: 0 | G53: 0 | H53: 0 | I53: 0 | J53: 0 | K53: 0 | L53: 0 | M53: 0 | N53: 0 | O53: 0 | P53: 0 | Q53: 0 | R53: 0 | S53: 0 | T53: 0 | U53: 0 | V53: 0 | W53: 0 | AI53: 0

Sheet Issues of the Grange
A1: Gross Output | B1: Bought Only Aggregated | C1: Account Quarters | D1: Account Bushels | E1: Account Total Quarters | F1: Bought in Quarters | G1: Bought in Bushels | H1: Total Bought Quarters | I1: Sold Quarters | J1: Sold Bushels | K1: Sold Total Quarters | L1: Total Corn Quantity | M1: Difference Produced+Bought-Sold | N1: Weighted Average Price per Quarter | O1: Non-Weighted Average Price per Quarter | P1: Value of Total Production weighted | Q1: Value of Total Production unweighted
A2: expenses of the steward | B2: 0 | C2: 0 | D2: 0 | E2: 0 | F2: 0 | G2: 0 | H2: 0 | I2: 0 | J2: 0 | K2: 0 | L2: 0 | M2: 0
A3: wheat | B3: 0 | C3: 0 | D3: 0 | E3: 0 | F3: 0 | G3: 0 | H3: 0 | I3: 6 | J3: 4 | K3: 6.5 | L3: 0 | M3: -6.5
A4: rye | B4: 0 | C4: 0 | D4: 0 | E4: 0 | F4: 0 | G4: 0 | H4: 0 | I4: 6 | J4: 0 | K4: 6 | L4: 0 | M4: -6
A5: peas | B5: 0 | C5: 0 | D5: 0 | E5: 0 | F5: 0 | G5: 0 | H5: 0 | I5: 0 | J5: 0 | K5: 0 | L5: 0 | M5: 0
A6: barley | B6: 0 | C6: 0 | D6: 0 | E6: 0 | F6: 0 | G6: 0 | H6: 0 | I6: 0 | J6: 0 | K6: 0 | L6: 0 | M6: 0
A7: oats | B7: 0 | C7: 0 | D7: 0 | E7: 0 | F7: 0 | G7: 0 | H7: 0 | I7: 24 | J7: 0 | K7: 24 | L7: 0 | M7: -24
A8: Mancorn | B8: 0 | C8: 0 | D8: 0 | E8: 0 | F8: 0 | G8: 0 | H8: 0 | I8: 0 | J8: 0 | K8: 0 | L8: 0 | M8: 0
A9: Maslin | B9: 0 | C9: 0 | D9: 0 | E9: 0 | F9: 0 | G9: 0 | H9: 0 | I9: 0 | J9: 0 | K9: 0 | L9: 0 | M9: 0
A10: First-grade malt | B10: 0 | C10: 0 | D10: 0 | E10: 0 | F10: 0 | G10: 0 | H10: 0 | I10: 0 | J10: 0 | K10: 0 | L10: 0 | M10: 0
A11: Second-grade malt | B11: 0 | C11: 0 | D11: 0 | E11: 0 | F11: 0 | G11: 0 | H11: 0 | I11: 0 | J11: 0 | K11: 0 | L11: 0 | M11: 0
A12: Oatmeal | B12: 0 | C12: 0 | D12: 0 | E12: 0 | F12: 0 | G12: 0 | H12: 0 | I12: 0 | J12: 0 | K12: 0 | L12: 0 | M12: 0
A13: Vetches | B13: 0 | C13: 0 | D13: 0 | E13: 0 | F13: 0 | G13: 0 | H13: 0 | I13: 0 | J13: 0 | K13: 0 | L13: 0 | M13: 0
... A17: Curall | B17: 0 | C17: 0 | D17: 0 | E17: 0 | F17: 0 | G17: 0 | H17: 0 | I17: 0 | J17: 0 | K17: 0 | L17: 0 | M17: 0

Sheet Sale of Corn Prices
A1: Heading | B1: Sentence | C1: Total in Pounds | D1: Pounds | E1: Shillings | F1: Pence | G1: Corn | H1: Total Quarters Except 1 | I1: Total Bushels Except 1 | J1: Total Corn Cross-Check | K1: Total Corn Manorial Account | L1: Corn Quantity Error | M1: Quarters 0 | N1: Bushels 0 | O1: shilling a quarter 1 | P1: pence a quarter 1 | Q1: Quarters 1 | R1: Bushels 1 | S1: shilling a quarter 2 | T1: pence a quarter 2 | U1: Quarters 2 | V1: Bushels 2 | W1: shilling a quarter 3 | X1: pence a quarter 3 | Y1: shilling a quarter 4 | Z1: pence a quarter 4 | AA1: £ a quarter 1 | AB1: £ a quarter 2 | AC1: £ a quarter 3 | AD1: £ a quarter 4 | AE1: Quarters Sold | AF1: Weighted Average Price per Quarter | AG1: Non-Weighted Average Price per Quarter | AH1: Corn lowercase
A2: sale of corn | B2: the same answers for 21 pence received from 5 bushels of curallum of wheat sold, price of a bushel 3½d. | C2: 0.09 | D2: 0 | E2: 0 | F2: 21 | G2: wheat, curall | H2: 0 | I2: 5 | J2: 0.62 | K2: 0.62 | L2: 0 | M2: 0 | N2: 5 | AA2: 0.14 | AE2: 0.62 | AF2: 0.14 | AG2: 0.14 | AH2: wheat, curall
A3: sale of corn | B3: and for 12 shilling received from 3 quarters of rye sold in the month of september, price of a quarter 4 shilling and for 18 shilling 4½d received from 3 quarters 7½ bushels of rye, price of a quarter 4 shilling 8pence and for 4 shilling 1¼d received from 1 quarter 1 bushel 3 pecks of barley sold, price of a bushel 5pence and for 13 shilling 6¼d received from 10 quarters 6 bushels 3 pecks of oats sold to earl warenne, price of a quarter 15pence and for 4 shilling 11 pence from 3½ quarters of oats sold for expenses of the lord’s household. | C3: 0.63 | D3: 0 | E3: 12 | F3: 8 | G3: rye, barley, oats | H3: 13 | I3: 6 | J3: 13.75 | K3: 3 | L3: 10.75 | M3: 3 | N3: 0 | Q3: 3 | R3: 0 | U3: 10 | V3: 6 | AA3: 0.21 | AE3: 3 | AF3: 0.21 | AG3: 0.21 | AH3: rye, barley, oats
A4: sale of corn | B4: sum 54 shilling 8pence. | C4: 2.73 | D4: 0 | E4: 54 | F4: 8 | H4: 0 | I4: 0 | J4: 0 | K4: 0 | L4: 0 | M4: 0 | N4: 0 | AA4: inf | AE4: 0 | AF4: inf | AG4: inf

Sheet Expenses
A1: ESHER_1342 EXPENSES
A2: Heading | B2: £ | C2: s | D2: d | F2: Total in £ | G2: Error | H2: Sentence | I2: Fixed Investments | J2: Demesne Fixed Investments
A4: Cost of ploughs | B4: 0 | C4: 3 | D4: 0 | F4: 0.15 | H4: The same accounts for iron and steel bought with the stipend of a smith for the year 3 shilling 6[d].
A5: Cost of ploughs | B5: 0 | C5: 0 | D5: 6 | F5: 0.03 | H5: two plough feet bought 6pence.
A6: Cost of ploughs | B6: 0 | C6: 0 | D6: 2 | F6: 0.01 | H6: two yokes bought 2pence.
A7: Cost of ploughs | B7: 0 | C7: 0 | D7: 6 | F7: 0.03 | H7: one plough covered with boards and fitted with a chip twice for the year 6 pence, so much because it was worn out.
A8: Cost of ploughs | B8: 0 | C8: 0 | D8: 2 | F8: 0.01 | H8: fitting the said plough with an axle on two occasions 2pence.
A9: Cost of ploughs | B9: 0 | C9: 0 | D9: 7 | F9: 0.03 | H9: one pair of wheels bought for the same 7pence.
A10: Cost of ploughs | B10: 0 | C10: 5 | D10: 5 | F10: 0.27 | H10: stipend of one ploughdriver for the year 5 shilling Sum 10 shilling 5pence.
A11: Cost of ploughs total | F11: 0.53 | G11: 0.26 | H11: Total
A13: Cost of carts | B13: 0 | C13: 0 | D13: 5 | F13: 0.02 | H13: The same accounts for three iron tyres bought for fitting to, and mending, broken wheels 5 pence, because the wheels were worn out.
A14: Cost of carts | B14: 0 | C14: 0 | D14: 8 | F14: 0.03 | H14: eight clouts bought for the cart for the year 8pence.
A15: Cost of carts | B15: 0 | C15: 0 | D15: 1 | F15: 0 | H15: nails for the same and for renewing 1pence.
A16: Cost of carts | B16: 0 | C16: 0 | D16: 0 | F16: 0 | H16: grease bought for the.
A17: Cost of carts | B17: 0 | C17: 0 | D17: 0 | F17: 0 | H17: --- Page 5 ---.
A18: Cost of carts | B18: 0 | C18: 0 | D18: 3 | F18: 0.01 | H18: same for the year 3pence.
A19: Cost of carts | B19: 0 | C19: 0 | D19: 4 | F19: 0.02 | H19: one base bought for the saddle of the cart 4pence.
A20: Cost of carts | B20: 0 | C20: 0 | D20: 3 | F20: 0.01 | H20: white-tawed leather bought for mending the harness of the cart for the year 3pence.
A21: Cost of carts | B21: 0 | C21: 0 | D21: 2 | F21: 0.01 | H21: two halters bought 2pence.
A22: Cost of carts | B22: 0 | C22: 0 | D22: 5 | F22: 0.02 | H22: one pair of traces bought 5pence.
A23: Cost of carts | B23: 0 | C23: 0 | D23: 1 | F23: 0 | H23: a carpenter for one axle for the cart 1pence.
A24: Cost of carts | B24: 0 | C24: 2 | D24: 6 | F24: 0.12 | H24: shoeing 2 horses of the manor for the year 2 shilling 6pence.
A25: Cost of carts | B25: 0 | C25: 5 | D25: 2 | F25: 0.26 | H25: stipend of one carter for the year 5 shilling Sum 10 shilling 2pence.
A26: Cost of carts total | F26: 0.5 | G26: 0.24 | H26: Total
A28: Small necessaries | B28: 0 | C28: 0 | D28: 4 | F28: 0.02 | H28: The same accounts for 1 bushel of salt bought for expenses of the manor for the year 4pence.
A29: Small necessaries | B29: 0 | C29: 0 | D29: 0 | F29: 0 | H29: one shovel and one spade with iron bought 5½d.
A30: Small necessaries | B30: 0 | C30: 0 | D30: 0 | F30: 0 | H30: one harrow made from the lord’s timber 2½d.
A31: Small necessaries | B31: 0 | C31: 0 | D31: 2 | F31: 0.01 | H31: castrating 16 male lambs 2pence.
A32: Small necessaries | B32: 0 | C32: 0 | D32: 1 | F32: 0 | H32: tithe paid for 2 lambs on the point of death not taken from the stock 1pence Sum 15pence.
A33: Small necessaries total | F33: 0.03 | G33: 0.03 | H33: Total
A35: Cost of buildings | B35: 0 | C35: 2 | D35: 8 | F35: 0.13 | H35: The same accounts for one roofer hired for roofing on the grange and oxshed of Northwode and on one piece of the wall next to the bridge of the manor of Esher together with his helper for eight days 2 shilling 8 pence, taking for a day 4pence.
A36: Cost of buildings | B36: 0 | C36: 0 | D36: 3 | F36: 0.01 | H36: 100 laths bought for the same 3pence.
A37: Cost of buildings | B37: 0 | C37: 0 | D37: 0 | F37: 0 | H37: 300 lath nails bought for the same 3½d.
A38: Cost of buildings | B38: 0 | C38: 3 | D38: 0 | F38: 0.15 | H38: Sum 3 shilling 2½d.
A39: Cost of buildings total | F39: 0.29 | G39: 0.14 | H39: Total
A41: Purchase of corn | B41: 0 | C41: 0 | D41: 15 | F41: 0.06 | H41: The same accounts for 1 quarter of oats bought, as shown elsewhere, 15pence Sum 15pence.
A42: Purchase of corn | B42: 0 | C42: 0 | D42: 0 | F42: 0 | H42: --- Page 6 ---.
A43: Purchase of corn total | F43: 0.06 | G43: 0.06 | H43: Total
A45: Purchase of stock | B45: 0 | C45: 50 | D45: 0 | F45: 2.5 | H45: The same accounts as paid for 4 oxen bought for stock 50 shilling, attested by the same prior.
A46: Purchase of stock | B46: 0 | C46: 42 | D46: 9 | F46: 2.14 | H46: 76 lambs bought before shearing 42 shilling 9pence.
A47: Purchase of stock | B47: 0 | C47: 22 | D47: 8 | F47: 1.13 | H47: 34 lambs bought after shearing 22 shilling 8 pence, price of each 8pence Sum 115 shilling 5pence.
A48: Purchase of stock total | F48: 5.77 | G48: 4.64 | H48: Total
A50: Foreign expenses | B50: 0 | C50: 0 | D50: 6 | F50: 0.03 | H50: The same accounts for driving 71 female hoggets to Bishops Sutton 6 pence, by order of the Lord Adam, stockman.
A51: Foreign expenses | B51: 0 | C51: 0 | D51: 7 | F51: 0.03 | H51: bringing and carrying all the wool received at the shearing of the lord’s sheep, as shown elsewhere, to Farnham 7pence Sum 13pence.
A52: Foreign expenses total | F52: 0.06 | G52: 0.03 | H52: Total
A54: Expenses of the steward | B54: 0 | C54: 5 | D54: 11 | F54: 0.3 | H54: The same accounts for the expenses of Walter Joce, steward, for his visit in the month of March 5 shilling 11 pence, by sealed bill.
A55: Expenses of the steward | B55: 0 | C55: 5 | D55: 11 | F55: 0.3 | H55: Sum 5 shilling 11pence.
A56: Expenses of the steward | B56: 10 | C56: 6 | D56: 0 | F56: 10.3 | H56: <P>Sum of all expenses £10 6 shilling 7¾d.<br>.
A57: Expenses of the steward | B57: 12 | C57: 11 | D57: 0 | F57: 12.55 | H57: And he owes £12 11 shilling 11½d.</P>.
A58: Expenses of the steward | B58: 0 | C58: 10 | D58: 7 | F58: 0.53 | H58: Of which allowed to the same 10 shilling 7 pence paid to Lord William de Meone, treasurer of the lord’s household, in various provisions for the expenses of the said household, by one writ.
A59: Expenses of the steward | B59: 0 | C59: 10 | D59: 7 | F59: 0.53 | H59: Sum 10 shilling 7pence.
A60: Expenses of the steward | B60: 0 | C60: 0 | D60: 0 | F60: 0 | H60: --- Page 7 ---.
A61: Expenses of the steward | B61: 0 | C61: 0 | D61: 0 | F61: 0 | H61: Payment of money.
A62: Expenses of the steward | B62: 9 | C62: 5 | D62: 7 | F62: 9.28 | H62: And paid to Lord John de Nubbelegh, treasurer of Wolvesey, £9 5 shilling 7 pence, by one tally.
A63: Expenses of the steward | B63: 9 | C63: 16 | D63: 0 | F63: 9.8 | H63: Sum of all allowances and payments £9 16 shilling 2½d.
A64: Expenses of the steward total | B64: 0 | C64: 55 | D64: 9 | F64: 2.79 | G64: -7.01 | H64: And he owes net 55 shilling 9pence.
