Workbook

Sheet Overview
A1: BISHOPSSUTTON OVERVIEW - COMPLETED | B1: Total in £ | C1: Error | D1: Note
A2: CASH ACCOUNT
A3: RECEIPTS
A4: Arrears total | B4: 8.88
A5: Rents of assize total | B5: 52.01
A6: Quittances total | B6: 0.8
A7: Defaults of rent total | B7: 4.77
A8: Defaults of rent through the pestilence total
A9: Cotlands defaults total
A10: Cotlands total
A11: Total of quittances and defaults of rent total | B11: 10.4
A12: Total of rents remaining clear total | B12: 41.61
A13: Farms total
A14: Annual recognizances total | B14: 0.21
A15: Issues of the Manor total | B15: 31.1
A16: Issues of the tenements in the lord's hands total
A17: Sale of labour services total
A18: Sale of corn total
A19: Entry and marriage fines total
A20: Pleas & perquisites total | B20: 3.98
A21: Forfeited chattels total
A22: Farm of the demesne land total
A23: Total of all receipts (calculated here) | B23: =SUM(B5:B11) -> 67.98
A24: Total of all receipts (calculated here) incl arrears | B24: =SUM(B4:B11) -> 76.86
A25: Total recorded in the accounts excl. arrears | B25: =Receipts!F108 -> 148.63 | C25: =B23-B25 -> -80.65
A26: Total recorded in the accounts incl. arrears | B26: =Receipts!F109 -> 157.51
A29: EXPENSES
A30: Cost of ploughs total | B30: 1.39
A31: Purchase of corn total
A32: Cost of carts and wagons total | B32: 1.37
A33: Cost of dairy total
A34: Purchase of stock total
A35: Sheepcote total
A36: Cost of buildings total
A37: Threshing total | B37: 1.16
A38: Barley expenses
A39: Expenses of the harvest total | B39: 1.41
A40: Necessary expenses
A41: Wages of the bailiff
A42: Steward's expenses total | B42: 0.87
A43: Costs of the park | B43: 4.79
A44: Annual fees
A45: Total of all expenses per account | B45: =Expenses!F77 -> 88.92
A46: Total of all expenses (calculated here) | B46: =Expenses!F78 -> 17.51
A47: Total fixed investment | B47: 1.83
A48: Total Demesne fixed investment | B48: 1.83
A50: Owed by the reeve | B50: =B23-B46 -> 50.47
A51: From accounts | B51: 99.24
A53: Allowances
A54: Cash deliveries | B54: 28
A55: Sum of the above | B55: =SUM(B53:B54) -> 28
A56: Total of all allowances and cash deliveries in accounts
A58: Net amount owed | B58: =B51-B55 -> 71.24
A59: Net amount owed in accounts
A61: GRANGE ACCOUNT | B61: Total Production | D61: Value of total gross production in £ | E61: Value of total net production in £
A62: Grange | B62: qrs | C62: bus
A63: Wheat | B63: 30 | C63: 4 | D63: 14.37 | E63: 14.37
A64: Rye | B64: 0 | C64: 0 | E64: 0
A65: Dredge | B65: 0 | C65: 0 | E65: 0
A66: Curall | B66: 0 | C66: 0 | E66: 0
A67: Barley | B67: 53 | C67: 4 | E67: 0
A68: Oats | B68: 39 | C68: 10 | E68: 0
A69: Beans | B69: 0 | C69: 0 | D69: 0 | E69: 0
A70: Peas | B70: 0 | C70: 0 | E70: 0
A71: Vetches | B71: 0 | C71: 0 | E71: 0
A72: Total value of gross production (sum of the above) | E72: =SUM(D63:D71) -> 14.37
A73: Total value of net production | E73: =SUM(E63:E71) -> 14.37
A74: Value of sales | E74: 17.625
A76: MILL ACCOUNT | B76: Total Production | D76: Total in £
A77: Issues of the mill | B77: qrs | C77: bus
A78: Wheat
A79: Oatmeal
A80: 1st grade malt
A81: 2nd grade malt
A82: Maslin
A83: Total value of production (sum of the above)
A84: Value of sales
A86: STOCK ACCOUNT
A87: Livestock | B87: Begin stock | C87: End stock | D87: Stockbuilding | F87: Value of stock in £ | G87: Value of stockbuilding
A88: Cart-horses | B88: 0 | C88: =Stock!L5 -> 0 | D88: =C88-B88 -> 0 | F88: =Stock!L5*Stock!O5 -> 0 | G88: =D88*Stock!O5 -> 0
A89: Mares | B89: 0 | C89: =Stock!L6 -> 0 | D89: =C89-B89 -> 0 | F89: =Stock!L6*Stock!O6 -> 0 | G89: =D89*Stock!O6 -> 0
A90: Plough horses | B90: 0 | C90: =Stock!L7 -> 0 | D90: =C90-B90 -> 0 | F90: =Stock!L7*Stock!O7 -> 0 | G90: =D90*Stock!O7 -> 0
A91: Colts (2 years) | B91: 0 | C91: =Stock!L9 -> 0 | D91: =C91-B91 -> 0 | F91: =Stock!L9*Stock!O9 -> 0 | G91: =D91*Stock!O9 -> 0
A92: Colts (2 years) | B92: 0 | C92: =Stock!L9 -> 0 | D92: =C92-B92 -> 0 | F92: =Stock!L9*Stock!O9 -> 0 | G92: =D92*Stock!O9 -> 0
A93: Colts (1 year) | B93: 0 | C93: =Stock!L10 -> 0 | D93: =C93-B93 -> 0 | F93: =Stock!L10*Stock!O10 -> 0 | G93: =D93*Stock!O10 -> 0
A94: Foals | B94: 0 | C94: =Stock!L11 -> 0 | D94: =C94-B94 -> 0 | F94: =Stock!L11*Stock!O11 -> 0 | G94: =D94*Stock!O11 -> 0
A95: Oxen | B95: 14 | C95: =Stock!L12 -> 14 | D95: =C95-B95 -> 0 | F95: =Stock!L12*Stock!O12 -> 0 | G95: =D95*Stock!O12 -> 0
A96: Bulls | B96: 0 | C96: =Stock!L13 -> -1 | D96: =C96-B96 -> -1 | F96: =Stock!L13*Stock!O13 -> 0 | G96: =D96*Stock!O13 -> 0
A97: Cows | B97: 22 | C97: =Stock!L14 -> 22 | D97: =C97-B97 -> 0 | F97: =Stock!L14*Stock!O14 -> 8.25 | G97: =D97*Stock!O14 -> 0
A98: Steers | B98: 7 | C98: =Stock!L15 -> 7 | D98: =C98-B98 -> 0 | F98: =Stock!L15*Stock!O15 -> 0 | G98: =D98*Stock!O15 -> 0
A99: Bullocks | B99: 0 | C99: =Stock!L16 -> 0 | D99: =C99-B99 -> 0 | F99: =Stock!L16*Stock!O16 -> 0 | G99: =D99*Stock!O16 -> 0
A100: Yearlings | B100: 0 | C100: =Stock!L17 -> 0 | D100: =C100-B100 -> 0 | F100: =Stock!L17*Stock!O17 -> 0 | G100: =D100*Stock!O17 -> 0
A101: Calves | B101: 8 | C101: =Stock!L18 -> -2 | D101: =C101-B101 -> -10 | F101: =Stock!L18*Stock!O18 -> -0.055333333 | G101: =D101*Stock!O18 -> -0.27666667
A102: Wethers | B102: 534 | C102: =Stock!L19 -> 522 | D102: =C102-B102 -> -12 | F102: =Stock!L19*Stock!O19 -> 26.1 | G102: =D102*Stock!O19 -> -0.6
A103: Rams | B103: 0 | C103: =Stock!L20 -> 0 | D103: =C103-B103 -> 0 | F103: =Stock!L20*Stock!O20 -> 0 | G103: =D103*Stock!O20 -> 0
... A113: Peacocks | B113: 0 | C113: =Stock!L30 -> 0 | D113: =C113-B113 -> 0 | F113: =Stock!L30*Stock!O30 -> 0 | G113: =D113*Stock!O30 -> 0
A114: Total value of stock (sum of the above) | F114: =SUM(F88:F113) -> 41.441631 | G114: =SUM(G88:G113) -> 4.8325
A115: Total value of production | F115: =SUM(Stock!T5:T30) -> 8.1875
A116: Value of sales | F116: =SUM(Stock!R5:R30) -> 2.73
A118: Wool | B118: Begin stock | C118: End stock | D118: Stockbuilding | F118: Value of stock in £
...

Sheet Receipts
A1: BISHOPSSUTTON RECEIPTS
A2: Heading | B2: £ | C2: s | D2: d | F2: Total in £ | G2: Error | H2: Notes | I2: Own notes
A3: Arrears | B3: 8 | C3: 17 | D3: 6 | F3: 8.88 | H3: The same answers for £8 17 shilling 6pence of arrears from his last account of the preceding year.
A4: Arrears | B4: 8 | C4: 17 | D4: 6 | F4: 8.88 | H4: Total, £8 17 shilling 6pence.
A5: Arrears total | F5: 8.88 | G5: 0 | H5: Total
A7: Rents of assize | B7: 9 | C7: 10 | D7: 10.25 | F7: 9.54 | H7: And for £9 10 shilling 10.25pence for all rents of assize at Christmas.
A8: Rents of assize | B8: 9 | C8: 10 | D8: 11 | F8: 9.55 | H8: £9 10 shilling 11pence at Easter (23 March).
A9: Rents of assize | B9: 9 | C9: 10 | D9: 10.25 | F9: 9.54 | H9: £9 10 shilling 10.25pence at the Nativity of St John the Baptist (24 June).
A10: Rents of assize | B10: 23 | C10: 7 | D10: 7 | F10: 23.38 | H10: £23 7 shilling 7pence at Michaelmas (29 September).
A11: Rents of assize | B11: 52 | C11: 0 | D11: 2.5 | F11: 52.01 | H11: Total, £52 2.5pence.
A12: Rents of assize total | F12: 52.01 | G12: 0 | H12: Total
A14: Quittances | B14: 0 | C14: 5 | D14: 0 | F14: 0.25 | H14: In quittance of rent of 1 reeve for the year 5 shilling.
A15: Quittances | B15: 0 | C15: 2 | D15: 0 | F15: 0.1 | H15: 1 smith for the year 2 shilling.
A16: Quittances | B16: 0 | C16: 0 | D16: 0 | F16: 0 | H16: 1 cowherd for the year, nothing, because there is none there from the customary tenants but he has the lord's livery as made clear elsewhere.
A17: Quittances | B17: 0 | C17: 3 | D17: 0 | F17: 0.15 | H17: 1 ploughman for the year 3 shilling.
A18: Quittances | B18: 0 | C18: 3 | D18: 0 | F18: 0.15 | H18: 1 keeper of wethers for the year 3 shilling.
A19: Quittances | B19: 0 | C19: 3 | D19: 0 | F19: 0.15 | H19: 1 swineherd for the year 3 shilling.
A20: Quittances | B20: 0 | C20: 16 | D20: 0 | F20: 0.8 | H20: Total, 16 shilling.
A21: Quittances total | F21: 0.8 | G21: 0 | H21: Total
A23: Defaults of rent | B23: 0 | C23: 2 | D23: 0 | F23: 0.1 | H23: In default of Philip Molendinarius, 2 shilling for the year.
A24: Defaults of rent | B24: 0 | C24: 1 | D24: 0 | F24: 0.05 | H24: the land of Geoffrey Hose given to the canons of Merton Priory 1 shilling.
A25: Defaults of rent | B25: 0 | C25: 0 | D25: 6 | F25: 0.03 | H25: 1 plot of land which belonged to John Pulent' 6pence.
A26: Defaults of rent | B26: 0 | C26: 10 | D26: 0 | F26: 0.5 | H26: I virgate of land of Adam Bedell' drawn into demesne, 10 shilling for the year.
A27: Defaults of rent | B27: 0 | C27: 3 | D27: 3 | F27: 0.16 | H27: 1 messuage pertaining to the mill and 1 plot pertaining to the bakehouse drawn into demesne, which William Carpunt' held, 3 shilling 3pence for the year.
A28: Defaults of rent | B28: 0 | C28: 1 | D28: 6 | F28: 0.08 | H28: 3 acres of land which Guy de Haywode held at la Gate drawn into demesne, 1 shilling 6pence for the year.
A29: Defaults of rent | B29: 0 | C29: 0 | D29: 8 | F29: 0.03 | H29: 1 plot of land which belonged to John Gilberd' drawn into demesne, 8pence for the year.
A30: Defaults of rent | B30: 2 | C30: 8 | D30: 4 | F30: 2.42 | H30: 1 messuage, 1 water-mill, 20.5 acres of land, 13 acres 1 kaild of purpresture, and 10 acres of wood, containing 40 acres of wood by estimation, formerly of John, son of John de Godisfeld', all of which was recently held unjustly by William de Overton', knight, by intrusion made into it in the time of William de Edyngdon', recently lord bishop of Winchester, and which the aforesaid bishop reseized, resumed and had drawn into demesne from the hands of the aforesaid William de Overton' as his right and that of his aforesaid church of Winchester, £2 8 shilling 4pence, and know that of the aforesaid 2 messuages 1 is at the mill beside the curia of Bishops Sutton and the other messuage is in fact that which the aforesaid John, son of John de Godisfeld', held and which Reginald Cornow held before, and that the third messuage is that which the aforesaid John, son of John de Godisfeld', held and which John atte Frithe held before, and nothing is in default because William Hokkele fined for the same, for this the fifty-first year.
A31: Defaults of rent | B31: 0 | C31: 0 | D31: 0 | F31: 0 | H31: all the land and tenements which belonged to John atte Fysshwer' and which William de Overton', knight, afterwards unjustly held and which the aforesaid bishop recovered and had drawn into demesne, as his right and that of his aforesaid church of.
A32: Defaults of rent | B32: 0 | C32: 7 | D32: 0 | F32: 0.35 | H32: Winchester, by a writ in the court of the lord king at Westminster in the thirty-second year of the reign of King Edward the Third after the Conquest (1358), under the description, 1 messuage 11h virgates of land, against the aforesaid William de Overton', by judgement tried (triat') in the same court against the accused, 7 shilling.
A33: Defaults of rent | B33: 0 | C33: 7 | D33: 0 | F33: 0.35 | H33: 1 messuage virgate of villein land formerly of Alice Clerk', who was wife of Roger Clerk' of Bishops Sutton, and which the aforesaid bishop recovered and had drawn into demense against the aforesaid William de Overton' in the aforesaid year in a similar way 7 shilling.
A34: Defaults of rent | B34: 0 | C34: 1 | D34: 6 | F34: 0.08 | H34: 3 acres of land lying in la Mullecroft, containing 5 acres by estimation, which the aforesaid bishop recovered and had drawn into demesne against the aforesaid wiiiiana de Overton' in the thirty-first and thirty-second years of the aforesaid king (1357-8), under the description, 5 acres of land, in a similar way, 1 shilling 6pence.
... A40: Defaults of rent | B40: 4 | C40: 14 | D40: 11 | F40: 4.75 | H40: Total, £4 14 shilling 11pence.
A41: Defaults of rent total | F41: 4.77 | G41: 0.02 | H41: Total
A43: Total of quittances and defaults of rent | B43: 10 | C43: 8 | D43: 0 | F43: 10.4 | H43: Total of quittances and defaults of rent, £10 8 shilling.
A44: Total of quittances and defaults of rent total | F44: 10.4 | G44: 0 | H44: Total
A46: Total of rents remaining clear | B46: 41 | C46: 12 | D46: 2.5 | F46: 41.61 | H46: Total of rents remaining clear, £41 12 shilling 2.5pence.
A47: Total of rents remaining clear total | F47: 41.61 | G47: 0 | H47: Total
A49: Annual recognizance | B49: 0 | C49: 1 | D49: 0 | F49: 0.05 | H49: Nothing of the 1 shilling for the annual recognizance of Robert Smyth' because he is dead as established by the court roll.
A50: Annual recognizance | B50: 0 | C50: 0 | D50: 2 | F50: 0.01 | H50: nothing of the 2pence for the annual recognizance of Thomas Tannere because he withdrew from the demesne as made clear as before.
A51: Annual recognizance | B51: 0 | C51: 1 | D51: 0 | F51: 0.05 | H51: 1 shilling from William Coupere so that he may dwell outside the lord's liberty as long as it pleases the lord and come to the tourn of Hockday for the year and remain the lord's villein as before.
A52: Annual recognizance | B52: 0 | C52: 0 | D52: 2 | F52: 0.01 | H52: nothing of the 2pence for the annual recognizance of William, son of Richard Cobbe, because he is amerced at each tourn and tithing (turnum & dec' & decena) for the same at the court.
A53: Annual recognizance | B53: 0 | C53: 0 | D53: 2 | F53: 0.01 | H53: nothing of the 2pence for the annual recognizance of John Todemond' because he withdrew from the demesne as made clear by the court roll.
A54: Annual recognizance | B54: 0 | C54: 1 | D54: 0 | F54: 0.05 | H54: 1 shilling from Roger Sourlond' so that he may dwell outside the lord's liberty as long as it pleases the lord and come to the tourn of Hockday for the year and remain the lord's villein as before, by pledge of William Sourlond'.
A55: Annual recognizance | B55: 0 | C55: 0 | D55: 8 | F55: 0.03 | H55: nothing of the 8pence for the annual recognizance of William, son of William' atte Lee, because he is dead as established by the court roll.
A56: Annual recognizance | B56: 0 | C56: 2 | D56: 0 | F56: 0.1 | H56: Total, 2 shilling.
A57: Annual recognizance total | F57: 0.21 | G57: 0.11 | H57: Total
A59: Issues of the manor | B59: 1 | C59: 8 | D59: 9.5 | F59: 1.44 | H59: And for £1 8 shilling 9.5pence from the pannage of the pigs of the customary tenants at Martinmas, at 2pence a pig over a year old, 1.5pence for one of 3 terms, 1pence for one of .5 year, and .5pence for a weaned piglet, whether or not there was mast.
A60: Issues of the manor | B60: 0 | C60: 0 | D60: 0 | F60: 0 | H60: nothing from the pannage of foreign pigs this year because there was no mast.
A61: Issues of the manor | B61: 0 | C61: 0 | D61: 6 | F61: 0.03 | H61: nothing of the 6pence for the pannage of the pigs of Roger Haywode this year for 1 virgate of land formerly of John Manycroft', because it is let at farm to the warden, fellows and scholars of the college of the blessed Mary near Winchester and their successors, by charter of William de Wykeham, recently lord bishop of Winchester, and by confirmation of the chapter of St Swithun's Priory, Winchester, as made clear below under the heading, issues through the pestilence.
A62: Issues of the manor | B62: 0 | C62: 2 | D62: 10.5 | F62: 0.14 | H62: 2 shilling 10.5pence from the pannage (ayes') of 11 cows of the cottars and 1 bullock this year, at 3pence a cow and 1.5pence a bullock.
A63: Issues of the manor | B63: 0 | C63: 1 | D63: 0 | F63: 0.05 | H63: 1 shilling from the churchscot of the customary tenants and not more because the land of Lucy2 Cartere and the land formerly of John Schephurc' and Thomas Mauncell' is commuted for a fixed cash sum and the lands of Roger Albard', John atte Puynde, William Hockele and John Hockele are in the lord's hands through the death of the same.
A64: Issues of the manor | B64: 0 | C64: 5 | D64: 0 | F64: 0.25 | H64: 5 shilling from the herbage of Faryngdon' sold.
A65: Issues of the manor | B65: 0 | C65: 1 | D65: 0 | F65: 0.05 | H65: 1 shilling from the pinfold of the ewes this year.
A66: Issues of the manor | B66: 0 | C66: 0 | D66: 0 | F66: 0 | H66: nothing from the sale of pasturage in the garden or in the meadow this year because it is grazed by the lord's cattle.
A67: Issues of the manor | B67: 0 | C67: 0 | D67: 0 | F67: 0 | H67: nothing from the pasturage of the garden behind the curia which William Overton' recently held for the same.
A68: Issues of the manor | B68: 0 | C68: 6 | D68: 8 | F68: 0.33 | H68: 6 shilling 8pence from the hides sold of 2 oxen, 2 cows and 4 yearlings in murrain as made clear elsewhere.
A69: Issues of the manor | B69: 0 | C69: 4 | D69: 3 | F69: 0.21 | H69: 4 shilling 3pence from the skins sold of 173 wethers in murrain before shearing, at 3pence a skin.
A70: Issues of the manor | B70: 0 | C70: 1 | D70: 0 | F70: 0.05 | H70: 1 shilling from the skins sold of 12 wethers in murrain after shearing.
... A88: Issues of the manor | B88: 31 | C88: 0 | D88: 9 | F88: 31.04 | H88: Total, £31 9pence.
A89: Issues of the manor total | F89: 31.1 | G89: 0.06 | H89: Total
A91: Sale of stock | B91: 0 | C91: 7 | D91: 10 | F91: 0.39 | H91: And for 7 shilling 10pence from 1 bull sold.
A92: Sale of stock | B92: 0 | C92: 7 | D92: 6 | F92: 0.38 | H92: 7 shilling 6pence from 1 cow useless for the stock sold.
A93: Sale of stock | B93: 0 | C93: 16 | D93: 8 | F93: 0.83 | H93: 16 shilling 8pence from 10 calves sold, at 1 shilling 8pence each.
A94: Sale of stock | B94: 0 | C94: 12 | D94: 0 | F94: 0.6 | H94: 12 shilling from 12 of the worse kebb wethers sold in the market after shearing, at 1 shilling each.
A95: Sale of stock | B95: 0 | C95: 2 | D95: 8 | F95: 0.13 | H95: 2 shilling 8pence from 2 kebb ewes from a heriot sold.
A96: Sale of stock | B96: 0 | C96: 4 | D96: 0 | F96: 0.2 | H96: 4 shilling from 4 lambs sold.
A97: Sale of stock | B97: 0 | C97: 5 | D97: 0 | F97: 0.25 | H97: 5 shilling from 1 boar sold to the lord's household.
A98: Sale of stock | B98: 0 | C98: 19 | D98: 6 | F98: 0.97 | H98: 19 shilling from 14 pigs sold to the lord's household, at 2 shilling 6pence each for 2, and 1 shilling 2pence each for 12..
A99: Sale of stock | B99: 3 | C99: 14 | D99: 8 | F99: 3.73 | H99: Total, £3 14 shilling 8pence.
A100: Sale of stock total | F100: 3.75 | G100: 0.02 | H100: Total
A102: Perquisites | B102: 0 | C102: 10 | D102: 1 | F102: 0.5 | H102: And for 10 shilling 1pence from the perquisites of the tourn of Martinmas (11 November).
A103: Perquisites | B103: 1 | C103: 2 | D103: 9 | F103: 1.14 | H103: £1 2 shilling 9pence from the perquisites of the courts held after the said tourn.
A104: Perquisites | B104: 0 | C104: 12 | D104: 8 | F104: 0.63 | H104: 12 shilling 8pence from the perquisites of the tourn of Hockday (1 April).
A105: Perquisites | B105: 0 | C105: 10 | D105: 8 | F105: 0.53 | H105: 10 shilling 8pence from the perquisites of the courts held by the bailiff after the said tourn of Hockday.
A106: Perquisites | B106: 1 | C106: 3 | D106: 6 | F106: 1.17 | H106: £1 3 shilling 6pence from the homage of Headley for release from their suit of court this year.
A107: Perquisites total | B107: 3 | C107: 19 | D107: 8 | F107: 3.98 | G107: 2.81 | H107: Total, £3 19 shilling 8pence.
A108: Total of all receipts recorded in accounts (calculated here) | F108: =SUMIF(A1:A107,"* total",F1:F107)-SUMIF(A1:A107,"Arrears total",F1:F107) -> 148.63
A109: Total of all receipts (calculated here) incl arrears | F109: =F108+SUMIF(A1:A107,"Arrears total",F1:F107) -> 157.51

Sheet Expenses
A1: BISHOPSSUTTON EXPENSES
A2: Heading | B2: £ | C2: s | D2: d | F2: Total in £ | G2: Error | H2: Sentence | I2: Fixed Investments | J2: Demesne Fixed Investments
A4: Cost of ploughs | B4: 0 | C4: 12 | D4: 10 | F4: 0.64 | H4: In iron and steel bought for the ironwork of 2 ploughs for the year 12 shilling 10pence. | I4: 0 | J4: 0
A5: Cost of ploughs | B5: 0 | C5: 1 | D5: 2 | F5: 0.06 | H5: 2 plough feet with nails bought for the same 1 shilling 2pence. | I5: 0 | J5: 0
A6: Cost of ploughs | B6: 0 | C6: 1 | D6: 4 | F6: 0.07 | H6: 2 pairs of wheels bought for the ploughs 1 shilling 4pence. | I6: 0 | J6: 0
A7: Cost of ploughs | B7: 0 | C7: 0 | D7: 6 | F7: 0.03 | H7: 1 plough made 6pence. | I7: 0 | J7: 0
A8: Cost of ploughs | B8: 0 | C8: 0 | D8: 4 | F8: 0.02 | H8: fitting the same with iron tyres 4pence. | I8: 0 | J8: 0
A9: Cost of ploughs | B9: 0 | C9: 0 | D9: 8 | F9: 0.03 | H9: fitting the ploughs with share-beams and mould-boards for the year 8pence.
A10: Cost of ploughs | B10: 0 | C10: 1 | D10: 6 | F10: 0.08 | H10: 1 ploughshare bought 1 shilling 6pence. | I10: 0.08 | J10: 0.08
A11: Cost of ploughs | B11: 0 | C11: 0 | D11: 6 | F11: 0.03 | H11: mending harrows 6pence. | I11: 0 | J11: 0
A12: Cost of ploughs | B12: 0 | C12: 2 | D12: 6 | F12: 0.12 | H12: shoeing 10 oxen and fastening them again 2 shilling 6pence. | I12: 0 | J12: 0
A13: Cost of ploughs | B13: 0 | C13: 2 | D13: 0 | F13: 0.1 | H13: customary payment to 12 customary tenants ploughing 24 acres as they lie at the winter and Lenten sowings 2 shilling. | I13: 0 | J13: 0
A14: Cost of ploughs | B14: 0 | C14: 0 | D14: 3 | F14: 0.01 | H14: 3 yokes made anew 3pence. | I14: 0 | J14: 0
A15: Cost of ploughs | B15: 0 | C15: 4 | D15: 0 | F15: 0.2 | H15: stipend of 1 drover for the year 4 shilling. | I15: 0 | J15: 0
A16: Cost of ploughs | B16: 1 | C16: 7 | D16: 8 | F16: 1.38 | H16: Total, £1 7 shilling 8pence. | I16: 0 | J16: 0
A17: Cost of ploughs total | F17: 1.39 | G17: 0.01 | H17: Total
A19: Cost of carts | B19: 0 | C19: 2 | D19: 0 | F19: 0.1 | H19: In clouts with nails bought for the carts 2 shilling.
A20: Cost of carts | B20: 0 | C20: 0 | D20: 8 | F20: 0.03 | H20: fitting the carts with axles 8pence.
A21: Cost of carts | B21: 0 | C21: 1 | D21: 0 | F21: 0.05 | H21: greasing the carts 1 shilling.
A22: Cost of carts | B22: 0 | C22: 1 | D22: 8 | F22: 0.08 | H22: white leather bought 1 shilling 8pence.
A23: Cost of carts | B23: 0 | C23: 0 | D23: 6 | F23: 0.03 | H23: 6 halters bought 6pence.
A24: Cost of carts | B24: 0 | C24: 2 | D24: 6 | F24: 0.12 | H24: 3 collars bought 2 shilling 6pence.
A25: Cost of carts | B25: 0 | C25: 1 | D25: 10 | F25: 0.09 | H25: 3 pairs of traces bought 1 shilling 10pence.
A26: Cost of carts | B26: 0 | C26: 1 | D26: 4 | F26: 0.07 | H26: 2 wood-ropes (woderop') bought 1 shilling 4pence.
A27: Cost of carts | B27: 0 | C27: 8 | D27: 0 | F27: 0.4 | H27: shoeing 4 horses for the year 8 shilling, and know that the smith will shoe 2 cart-horses at his own cost according to custom.
A28: Cost of carts | B28: 0 | C28: 8 | D28: 0 | F28: 0.4 | H28: stipend of 2 carters for the year 8 shilling.
A29: Cost of carts | B29: 1 | C29: 7 | D29: 6 | F29: 1.38 | H29: Total, £1 7 shilling 6pence.
A30: Cost of carts total | F30: 1.37 | G30: -0.01 | H30: Total
A32: Cost of the park | B32: 1 | C32: 15 | D32: 0 | F32: 1.75 | H32: In enclosing with new hedge 7 furlongs between Wyitonesrede and Clandon' £1 15 shilling, at 5 shilling a furlong. | I32: 1.75 | J32: 1.75
A33: Cost of the park | B33: 0 | C33: 0 | D33: 0 | F33: 0 | H33: enclosing with new hedge 2 furlongs at Brynkeworthes Rede lOs. | I33: 0 | J33: 0
A34: Cost of the park | B34: 3 | C34: 0 | D34: 10 | F34: 3.04 | H34: wages of the park-keeper for the year £3 10pence, taking 2pence a day. | I34: 0 | J34: 0
A35: Cost of the park | B35: 5 | C35: 5 | D35: 10 | F35: 5.29 | H35: Total, £5 5 shilling 10pence.
A36: Cost of the park total | F36: 4.79 | G36: -0.5 | H36: Total
A38: Cost of the mill | B38: 6 | C38: 0 | D38: 0 | F38: 6 | H38: In stipend of 4 carpenters making anew the mill-pond and sluice for 12 weeks £6 taking between them 10 shilling a week.
A39: Cost of the mill | B39: 0 | C39: 0 | D39: 0 | F39: 0 | H39: diverting the water from the mill, ramming i.
A40: Cost of the mill | B40: 0 | C40: 3 | D40: 4 | F40: 0.17 | H40: again, blocking it up and directing it into its right course by piece-work 3 shilling 4pence in expenses of the carters of the manor and other men helping to load the carts carrying timber to the aforesaid mill at various times 2 shilling.
A41: Cost of the mill | B41: 0 | C41: 6 | D41: 0 | F41: 0.3 | H41: 400 water-nails bought to fasten the flooring 6 shilling.
A42: Cost of the mill | B42: 0 | C42: 1 | D42: 0 | F42: 0.05 | H42: 200 floor-nails bought to fasten the boards of the water-wall with the same 1 shilling.
A43: Cost of the mill | B43: 6 | C43: 12 | D43: 4 | F43: 6.62 | H43: Total, £6 12 shilling 4pence.
A44: Cost of the mill total | F44: 6.52 | G44: -0.1 | H44: Total
A46: Threshing and winnowing | B46: 0 | C46: 8 | D46: 3 | F46: 0.41 | H46: In threshing 30 quarters 4 bushels of wheat and 1 qr 4 bushels of curall by piece-work 8 shilling, at 3pence a qr.
A47: Threshing and winnowing | B47: 0 | C47: 8 | D47: 11 | F47: 0.45 | H47: threshing 53 quarters 4 bushels of barley by piece-work 8 shilling 11pence, at 2pence a qr.
A48: Threshing and winnowing | B48: 0 | C48: 4 | D48: 3.75 | F48: 0.22 | H48: threshing 34 quartersl 3 bushels of oats by piece-work 4 shilling 3.75pence, at 1.5pence a qr.
A49: Threshing and winnowing | B49: 0 | C49: 1 | D49: 8 | F49: 0.08 | H49: winnowing a moiety of all the aforesaid corn by piece-work, that is, 59 quarters 7.5 bushels, 1 shilling 8pence, at 1pence per 3 quarters.
A50: Threshing and winnowing | B50: 1 | C50: 2 | D50: 10.75 | F50: 1.14 | H50: Total, £1 2 shilling 10.75pence.
A51: Threshing and winnowing total | F51: 1.16 | G51: 0.02 | H51: Total
A53: Cost of the harvest | B53: 0 | C53: 12 | D53: 4 | F53: 0.62 | H53: In bread bought for the harvest boon-works of 296 men with 6 officials of the curia at 3 boon-works, who reaped, bound and carried 54 acres of pulses and 7 acres of oats,2 which made 77 acres, 12 shilling 4pence, or .5pence of bread each.
A54: Cost of the harvest | B54: 0 | C54: 6 | D54: 2 | F54: 0.31 | H54: 592 herrings bought for the same 6 shilling 2pence, and each reaper has two herrings.
A55: Cost of the harvest | B55: 0 | C55: 6 | D55: 2 | F55: 0.31 | H55: cheese bought for the same 6 shilling 2pence, and each reaper has Vad. worth of cheese.
A56: Cost of the harvest | B56: 0 | C56: 0 | D56: 0 | F56: 0 | H56: Moreover, the customary tenants reaped for labour service 109 acres3 as they lie which made 54.5 acres by the perch for sheaves.
A57: Cost of the harvest | B57: 0 | C57: 3 | D57: 4 | F57: 0.17 | H57: stipend of 1 reap-reeve who supervised the reapers at harvest-time 3 shilling 4pence.
A58: Cost of the harvest | B58: 1 | C58: 8 | D58: 0 | F58: 1.4 | H58: Total, £1 8 shilling.
A59: Cost of the harvest total | F59: 1.41 | G59: 0.01 | H59: Total
A61: Expenses of the steward | B61: 0 | C61: 17 | D61: 4.5 | F61: 0.87 | H61: In expenses of Richard Wyot, steward, holding the tourns of Martinmas and Hockday 17 shilling 4.5pence.
A62: Expenses of the steward | B62: 0 | C62: 17 | D62: 4.5 | F62: 0.87 | H62: Total, 17 shilling 4.5pence.
A63: Expenses of the steward total | F63: 0.87 | G63: 0 | H63: Total
A65: Total of all expenses | B65: 88 | C65: 18 | D65: 4 | F65: 88.92 | H65: Total of all expenses, £88 18 shilling 4pence.
A66: Total of all expenses | F66: 0 | G66: -88.92 | H66: Total
A68: And he owes | B68: 99 | C68: 4 | D68: 10.75 | F68: 99.24 | H68: And he owes, £99 4 shilling 10.75pence.
A69: And he owes | F69: 99.24 | H69: Total
A70: And he owes total | B70: 4 | C70: 16 | D70: 6 | F70: 4.83 | G70: -94.41 | H70: And he owes, £4 16 shilling 6pence, of which £4 7 shilling 6pence is in the hands of the escheator, for which he is charged in the following account.
A72: Cash deliveries | B72: 28 | C72: 0 | D72: 0 | F72: 28 | H72: Delivered to John Arnold', receiver of Wolvesey, by 1 tally, £28..
A73: Cash deliveries | B73: 28 | C73: 0 | D73: 0 | F73: 28 | H73: Total, £28..
A74: Cash deliveries | B74: 94 | C74: 8 | D74: 4.75 | F74: 94.42 | H74: Total of all allowances and cash deliveries, £94 8 shilling 4.75pence.
A75: Cash deliveries total | F75: 28 | G75: -66.42 | H75: Total
A77: Total of all expenses per account | B77: 88 | C77: 18 | D77: 4 | F77: =F65 -> 88.92
A78: Total of all expenses (calculated here) | F78: =SUMIF(A1:A64,"* total",F1:F64) -> 17.51
A79: Total fixed investment | F79: =SUM(I4:I34) -> 1.83
A80: Total Demesne fixed investment | F80: =SUM(J4:J34) -> 1.83

Sheet Stock
A1: BISHOPSSUTTON STOCK ACCOUNT
C3: added | G3: subtracted
A4: Livestock | B4: Inherited stock | C4: added | D4: strays | E4: herbage | F4: churchscot | G4: of which in default | H4: sold | I4: in murrain | J4: accounted for elsewhere | K4: End-period stock | L4: cross-check | M4: stock building | N4: raw production | O4: Unit price (£) | P4: Value of stock (£) at given value | Q4: Value of stock (£) at sales prices | R4: Sales in (£) | S4: Value of stock building (£) | T4: Value of production (£) at sales prices | U4: Details
A5: Cart-horses | B5: 0 | C5: 0 | H5: 0 | I5: 0 | K5: =B5+C5-H5-I5 -> 0 | L5: =B5+C5-H5 -> 0 | M5: =L5-B5 -> 0 | N5: =C5 -> 0 | O5: 0 | P5: =O5*K5 -> 0 | R5: 0 | S5: =O5*M5 -> 0 | T5: =O5*N5 -> 0
A6: Mares | B6: 0 | C6: 0 | H6: 0 | I6: 0 | K6: =B6+C6-H6-I6 -> 0 | L6: =B6+C6-H6 -> 0 | M6: =L6-B6 -> 0 | N6: =C6 -> 0 | O6: 0 | P6: =O6*K6 -> 0 | R6: 0 | S6: =O6*M6 -> 0 | T6: =O6*N6 -> 0
A7: Plough horses | B7: 0 | C7: 0 | H7: 0 | I7: 0 | K7: =B7+C7-H7-I7 -> 0 | L7: =B7+C7-H7 -> 0 | M7: =L7-B7 -> 0 | N7: =C7 -> 0 | O7: 0 | P7: =O7*K7 -> 0 | R7: 0 | S7: =O7*M7 -> 0 | T7: =O7*N7 -> 0
A8: Colts (unspecified years) | B8: 0 | C8: 0 | H8: 0 | I8: 0 | K8: =B8+C8-H8-I8 -> 0 | L8: =B8+C8-H8 -> 0 | M8: =L8-B8 -> 0 | N8: =C8 -> 0 | O8: 0 | P8: =O8*K8 -> 0 | R8: 0 | S8: =O8*M8 -> 0 | T8: =O8*N8 -> 0
A9: Colts (2 years) | B9: 0 | C9: 0 | H9: 0 | I9: 0 | K9: =B9+C9-H9-I9 -> 0 | L9: =B9+C9-H9 -> 0 | M9: =L9-B9 -> 0 | N9: =C9 -> 0 | O9: 0 | P9: =O9*K9 -> 0 | R9: 0 | S9: =O9*M9 -> 0 | T9: =O9*N9 -> 0
A10: Colts (1 year) | B10: 0 | C10: 0 | H10: 0 | I10: 0 | K10: =B10+C10-H10-I10 -> 0 | L10: =B10+C10-H10 -> 0 | M10: =L10-B10 -> 0 | N10: =C10 -> 0 | O10: 0 | P10: =O10*K10 -> 0 | R10: 0 | S10: =O10*M10 -> 0 | T10: =O10*N10 -> 0
A11: Foals | B11: 0 | C11: 0 | H11: 0 | I11: 0 | K11: =B11+C11-H11-I11 -> 0 | L11: =B11+C11-H11 -> 0 | M11: =L11-B11 -> 0 | N11: =C11 -> 0 | O11: 0 | P11: =O11*K11 -> 0 | R11: 0 | S11: =O11*M11 -> 0 | T11: =O11*N11 -> 0
A12: Oxen | B12: 14 | C12: 0 | H12: 0 | I12: 2 | K12: =B12+C12-H12-I12 -> 12 | L12: =B12+C12-H12 -> 14 | M12: =L12-B12 -> 0 | N12: =C12 -> 0 | O12: 0 | P12: =O12*K12 -> 0 | R12: 0 | S12: =O12*M12 -> 0 | T12: =O12*N12 -> 0
A13: Bulls | B13: 0 | C13: 0 | H13: 1 | I13: 0 | K13: =B13+C13-H13-I13 -> -1 | L13: =B13+C13-H13 -> -1 | M13: =L13-B13 -> -1 | N13: =C13 -> 0 | O13: 0 | P13: =O13*K13 -> 0 | R13: 0 | S13: =O13*M13 -> 0 | T13: =O13*N13 -> 0
A14: Cows | B14: 22 | C14: 1 | H14: 1 | I14: 2 | K14: =B14+C14-H14-I14 -> 20 | L14: =B14+C14-H14 -> 22 | M14: =L14-B14 -> 0 | N14: =C14 -> 1 | O14: =90/240 -> 0.375 | P14: =O14*K14 -> 7.5 | R14: 0 | S14: =O14*M14 -> 0 | T14: =O14*N14 -> 0.375
A15: Steers | B15: 7 | C15: 0 | H15: 0 | I15: 0 | K15: =B15+C15-H15-I15 -> 7 | L15: =B15+C15-H15 -> 7 | M15: =L15-B15 -> 0 | N15: =C15 -> 0 | O15: 0 | P15: =O15*K15 -> 0 | R15: 0 | S15: =O15*M15 -> 0 | T15: =O15*N15 -> 0
A16: Bullocks | B16: 0 | C16: 0 | H16: 0 | I16: 0 | K16: =B16+C16-H16-I16 -> 0 | L16: =B16+C16-H16 -> 0 | M16: =L16-B16 -> 0 | N16: =C16 -> 0 | O16: 0 | P16: =O16*K16 -> 0 | R16: 0 | S16: =O16*M16 -> 0 | T16: =O16*N16 -> 0
A17: Yearlings | B17: 0 | C17: 0 | H17: 0 | I17: 0 | K17: =B17+C17-H17-I17 -> 0 | L17: =B17+C17-H17 -> 0 | M17: =L17-B17 -> 0 | N17: =C17 -> 0 | O17: 0 | P17: =O17*K17 -> 0 | R17: 0 | S17: =O17*M17 -> 0 | T17: =O17*N17 -> 0
A18: Calves | B18: 8 | C18: 20 | H18: 30 | I18: 0 | K18: =B18+C18-H18-I18 -> -2 | L18: =B18+C18-H18 -> -2 | M18: =L18-B18 -> -10 | N18: =C18 -> 20 | O18: 0.027666667 | P18: =O18*K18 -> -0.055333333 | R18: 0.83 | S18: =O18*M18 -> -0.27666667 | T18: =O18*N18 -> 0.55333333
A19: Wethers | B19: 534 | C19: 0 | H19: 12 | I19: 17 | K19: =B19+C19-H19-I19 -> 505 | L19: =B19+C19-H19 -> 522 | M19: =L19-B19 -> -12 | N19: =C19 -> 0 | O19: 0.05 | P19: =O19*K19 -> 25.25 | R19: 0.6 | S19: =O19*M19 -> -0.6 | T19: =O19*N19 -> 0
A20: Rams | B20: 0 | C20: 0 | H20: 0 | I20: 0 | K20: =B20+C20-H20-I20 -> 0 | L20: =B20+C20-H20 -> 0 | M20: =L20-B20 -> 0 | N20: =C20 -> 0 | O20: 0 | P20: =O20*K20 -> 0 | R20: 0 | S20: =O20*M20 -> 0 | T20: =O20*N20 -> 0
A21: Ewes | B21: 0 | C21: 2 | H21: 2 | I21: 0 | K21: =B21+C21-H21-I21 -> 0 | L21: =B21+C21-H21 -> 0 | M21: =L21-B21 -> 0 | N21: =C21 -> 2 | O21: 0.065 | P21: =O21*K21 -> 0 | Q21: 0 | R21: 0.13 | S21: =O21*M21 -> 0 | T21: =O21*N21 -> 0.13
A22: Hoggs | B22: 0 | C22: 80 | H22: 0 | I22: 0 | K22: =B22+C22-H22-I22 -> 80 | L22: =B22+C22-H22 -> 80 | M22: =L22-B22 -> 80 | N22: =C22 -> 80 | O22: =20/240 -> 0.083333333 | P22: =O22*K22 -> 6.6666667 | R22: 0 | S22: =O22*M22 -> 6.6666667 | T22: =O22*N22 -> 6.6666667
A23: Lambs | B23: 0 | C23: 8 | H23: 4 | I23: 1 | K23: =B23+C23-H23-I23 -> 3 | L23: =B23+C23-H23 -> 4 | M23: =L23-B23 -> 4 | N23: =C23 -> 8 | O23: 0.05 | P23: =O23*K23 -> 0.15 | R23: 0.2 | S23: =O23*M23 -> 0.2 | T23: =O23*N23 -> 0.4
A24: Boars | B24: 0 | C24: 0 | H24: 1 | I24: 0 | K24: =B24+C24-H24-I24 -> -1 | L24: =B24+C24-H24 -> -1 | M24: =L24-B24 -> -1 | N24: =C24 -> 0 | O24: =60/240 -> 0.25 | P24: =O24*K24 -> -0.25 | R24: 0 | S24: =O24*M24 -> -0.25 | T24: =O24*N24 -> 0
A25: Sows | B25: 2 | C25: 0 | H25: 0 | I25: 0 | K25: =B25+C25-H25-I25 -> 2 | L25: =B25+C25-H25 -> 2 | M25: =L25-B25 -> 0 | N25: =C25 -> 0 | O25: 0 | P25: =O25*K25 -> 0 | R25: 0 | S25: =O25*M25 -> 0 | T25: =O25*N25 -> 0
A26: Pigs | B26: 20 | C26: 0 | H26: 14 | I26: 0 | K26: =B26+C26-H26-I26 -> 6 | L26: =B26+C26-H26 -> 6 | M26: =L26-B26 -> -14 | N26: =C26 -> 0 | O26: 0.069285714 | P26: =O26*K26 -> 0.41571429 | R26: 0.97 | S26: =O26*M26 -> -0.97 | T26: =O26*N26 -> 0
A27: Hoggets | B27: 25 | C27: 0 | H27: 0 | I27: 3 | K27: =B27+C27-H27-I27 -> 22 | L27: =B27+C27-H27 -> 25 | M27: =L27-B27 -> 0 | N27: =C27 -> 0 | O27: 0 | P27: =O27*K27 -> 0 | R27: 0 | S27: =O27*M27 -> 0 | T27: =O27*N27 -> 0
A28: Piglets | B28: 25 | C28: 30 | H28: 0 | I28: 0 | K28: =B28+C28-H28-I28 -> 55 | L28: =B28+C28-H28 -> 55 | M28: =L28-B28 -> 30 | N28: =C28 -> 30 | O28: =0.5/240 -> 0.0020833333 | P28: =O28*K28 -> 0.11458333 | R28: 0 | S28: =O28*M28 -> 0.0625 | T28: =O28*N28 -> 0.0625
A29: Swans | B29: 0 | C29: 0 | H29: 0 | I29: 0 | K29: =B29+C29-H29-I29 -> 0 | L29: =B29+C29-H29 -> 0 | M29: =L29-B29 -> 0 | N29: =C29 -> 0 | O29: 0 | P29: =O29*K29 -> 0 | R29: 0 | S29: =O29*M29 -> 0 | T29: =O29*N29 -> 0
A30: Peacocks | B30: 0 | C30: 0 | H30: 0 | I30: 0 | K30: =B30+C30-H30-I30 -> 0 | L30: =B30+C30-H30 -> 0 | M30: =L30-B30 -> 0 | N30: =C30 -> 0 | O30: 0 | P30: =O30*K30 -> 0 | R30: 0 | S30: =O30*M30 -> 0 | T30: =O30*N30 -> 0
A31: Total Value
A34: Wool | B34: 0 | C34: 0 | H34: 0 | I34: 0
A35: Coarse wool | B35: 0 | C35: 0 | H35: 0 | I35: 2
A36: Lamb's wool | B36: 0 | C36: 0 | H36: 0 | I36: 0
A37: Wool locks | B37: 0 | C37: 0 | H37: 0 | I37: 0
A38: Wool sold at shearing | B38: 0 | C38: 0 | H38: 0 | I38: 0
A39: Total wool | B39: 0 | C39: 0 | H39: 0 | I39: 0
B40: 0 | C40: 0 | H40: 0 | I40: 0
B41: 0 | C41: 0 | H41: 0 | I41: 0
A42: Hides | B42: 0 | C42: 0 | H42: 0 | I42: 0
A43: Ox hides | B43: 0 | C43: 0 | H43: 0 | I43: 0
A44: Mare | B44: 0 | C44: 0 | H44: 0 | I44: 0
A45: Steer | B45: 0 | C45: 0 | H45: 0 | I45: 0
A46: calves | B46: 8 | C46: 20 | H46: 30 | I46: 0
A47: pigs | B47: 20 | C47: 0 | H47: 14 | I47: 0
A48: Woolskins
A49: wethers
A50: rams
A51: ewes
A52: hoggs
A53: Woolskins total | B53: 0 | C53: 0 | H53: 15 | I53: 17
A54: Bareskins
A55: wethers
A56: rams
A57: ewes
A58: hoggs
A59: Bareskins total | B59: 0 | C59: 0 | H59: 0 | I59: 12
A60: Lambskins | B60: 0 | C60: 0 | H60: 0 | I60: 1
A61: Rotted skins | B61: 0 | C61: 0 | H61: 0 | I61: 0
A62: Shorn skins | B62: 0 | C62: 0 | H62: 0 | I62: 0
A63: Total
A66: Poultry stock
A67: Hens | L67: =B67+C67-H67 -> 0 | M67: =L67-B67 -> 0 | N67: =C67 -> 0 | O67: 0 | Q67: =R67*K67 -> 0 | R67: 1.05 | S67: =O67*M67 -> 0 | T67: =O67*N67 -> 0
A68: Geese | L68: =B68+C68-H68 -> 0 | M68: =L68-B68 -> 0 | N68: =C68 -> 0 | O68: 0 | Q68: =R68*K68 -> 0 | R68: 0.27 | S68: =O68*M68 -> 0 | T68: =O68*N68 -> 0
A69: Capons (from chickens) | B69: 0 | C69: 6 | H69: 6 | K69: 0 | L69: =B69+C69-H69 -> 0 | M69: =L69-B69 -> 0 | N69: =C69 -> 6 | O69: 0 | Q69: =R69*K69 -> 0 | R69: 0 | S69: =O69*M69 -> 0 | T69: =O69*N69 -> 0
A70: Cocks & hens | B70: 0 | F70: 28 | G70: 18 | H70: 10 | K70: 0 | L70: =B70+C70-H70 -> -10 | M70: =L70-B70 -> -10 | N70: =C70 -> 0 | O70: 0 | Q70: =R70*K70 -> 0 | R70: 0 | S70: =O70*M70 -> 0 | T70: =O70*N70 -> 0
A71: Total poultry stock
A72: Total poultry excluding churchscot
A74: Poultry production
A75: Eggs | B75: 0 | C75: 0 | H75: 0 | I75: 0 | S75: =O75*M75 -> 0 | T75: =O75*N75 -> 0
A76: Cocks & hens from churchscot of customary tenants | B76: 0 | C76: 0 | H76: 0 | I76: 0 | S76: =O76*M76 -> 0 | T76: =O76*N76 -> 0
A77: Sum of above | S77: =SUM(S75:S76) -> 0 | T77: =SUM(T75:T76) -> 0
A78: Total
A81: Meat
A82: Beef | B82: 0 | C82: 0 | H82: 0 | I82: 0 | S82: =O82*M82 -> 0 | T82: =O82*N82 -> 0
A83: Mutton | B83: 0 | C83: 0 | H83: 0 | I83: 0 | S83: =O83*M83 -> 0 | T83: =O83*N83 -> 0
A84: Pork | B84: 0 | C84: 0 | H84: 0 | I84: 0 | S84: =O84*M84 -> 0 | T84: =O84*N84 -> 0
A85: Total
A87: Cheese
A88: Winter cheese | B88: 0 | C88: 0 | H88: 0 | I88: 0 | S88: =O88*M88 -> 0 | T88: =O88*N88 -> 0
A89: Summer cheese | B89: 0 | C89: 0 | H89: 0 | I89: 0 | S89: =O89*M89 -> 0 | T89: =O89*N89 -> 0
A90: Total
A92: Butter
A93: Butter | B93: 0 | C93: 0 | H93: 0 | I93: 0 | S93: =O93*M93 -> 0 | T93: =O93*N93 -> 0
A94: Total
A96: Total Dairy Sales
A99: Cider | B99: 0 | C99: 0 | H99: 0 | I99: 0
A102: Additional Information (not necessarily useful)
A103: Utensils
A104: ploughs
A105: carts
A106: cart-ropes
A107: corn baskets
A108: seed-sacks
A109: seed basket
A110: locks for the doors
A111: lead vessel
A112: brass pots
A113: pans
... A128: brass posnets

Sheet raw data
A1: Heading | B1: Sentence | C1: Total in Pounds | D1: Pounds | E1: Shillings | F1: Pence | G1: Corn | H1: Total Quarters Except 1 | I1: Total Bushels Except 1 | J1: Total Corn Cross-Check | K1: Total Corn Manorial Account | L1: Corn Quantity Error | M1: Quarters 1 | N1: Bushels 1 | O1: Quarters 2 | P1: Bushels 2 | Q1: Quarters 3 | R1: Bushels 3 | S1: Quarters 4 | T1: Bushels 4 | U1: Quarters 5 | V1: Bushels 5 | W1: Quarters 6 | X1: Bushels 6 | Y1: Quarters 7 | Z1: Bushels 7 | AA1: shilling a quarter 1 | AB1: pence a quarter 1 | AC1: shilling a quarter 2 | AD1: pence a quarter 2 | AE1: shilling a quarter 3 | AF1: pence a quarter 3 | AG1: shilling a quarter 4 | AH1: pence a quarter 4 | AI1: shilling a bushel 1 | AJ1: pence a bushel 1 | AK1: shilling a bushel 2 | AL1: pence a bushel 2 | AM1: shilling a bushel 3 | AN1: pence a bushel 3 | AO1: shilling a bushel 4 | AP1: pence a bushel 4
A2: bishops sutton | B2: the account of laurence sourlond', reeve there, from michaelmas of the fifth year of the translation of henry beaufort', lord bishop of winchester, until michaelmas of the sixth year, and the eleventh year of the reign of king henry the fourth. | C2: 0 | D2: 0 | E2: 0 | F2: 0 | H2: 0 | I2: 0 | J2: 0 | K2: 0 | L2: 0 | M2: 0 | N2: 0
A3: arrears | B3: the same answers for £8 17 shilling 6pence of arrears from his last account of the preceding year. | C3: 8.88 | D3: 8 | E3: 17 | F3: 6 | H3: 0 | I3: 0 | J3: 0 | K3: 0 | L3: 0 | M3: 0 | N3: 0
A4: arrears | B4: total, £8 17 shilling 6pence. | C4: 8.88 | D4: 8 | E4: 17 | F4: 6 | H4: 0 | I4: 0 | J4: 0 | K4: 0 | L4: 0 | M4: 0 | N4: 0
A5: rents of assize | B5: and for £9 10 shilling 10.25pence for all rents of assize at christmas. | C5: 9.54 | D5: 9 | E5: 10 | F5: 10.25 | H5: 0 | I5: 0 | J5: 0 | K5: 0 | L5: 0 | M5: 0 | N5: 0
A6: rents of assize | B6: £9 10 shilling 11pence at easter (23 march). | C6: 9.55 | D6: 9 | E6: 10 | F6: 11 | H6: 0 | I6: 0 | J6: 0 | K6: 0 | L6: 0 | M6: 0 | N6: 0
A7: rents of assize | B7: £9 10 shilling 10.25pence at the nativity of st john the baptist (24 june). | C7: 9.54 | D7: 9 | E7: 10 | F7: 10.25 | H7: 0 | I7: 0 | J7: 0 | K7: 0 | L7: 0 | M7: 0 | N7: 0
A8: rents of assize | B8: £23 7 shilling 7pence at michaelmas (29 september). | C8: 23.38 | D8: 23 | E8: 7 | F8: 7 | H8: 0 | I8: 0 | J8: 0 | K8: 0 | L8: 0 | M8: 0 | N8: 0
A9: rents of assize | B9: total, £52 2.5pence. | C9: 52.01 | D9: 52 | E9: 0 | F9: 2.5 | H9: 0 | I9: 0 | J9: 0 | K9: 0 | L9: 0 | M9: 0 | N9: 0
A10: quittances | B10: in quittance of rent of 1 reeve for the year 5 shilling. | C10: 0.25 | D10: 0 | E10: 5 | F10: 0 | H10: 0 | I10: 0 | J10: 0 | K10: 0 | L10: 0 | M10: 0 | N10: 0
A11: quittances | B11: 1 smith for the year 2 shilling. | C11: 0.1 | D11: 0 | E11: 2 | F11: 0 | H11: 0 | I11: 0 | J11: 0 | K11: 0 | L11: 0 | M11: 0 | N11: 0
A12: quittances | B12: 1 cowherd for the year, nothing, because there is none there from the customary tenants but he has the lord's livery as made clear elsewhere. | C12: 0 | D12: 0 | E12: 0 | F12: 0 | H12: 0 | I12: 0 | J12: 0 | K12: 0 | L12: 0 | M12: 0 | N12: 0
A13: quittances | B13: 1 ploughman for the year 3 shilling. | C13: 0.15 | D13: 0 | E13: 3 | F13: 0 | H13: 0 | I13: 0 | J13: 0 | K13: 0 | L13: 0 | M13: 0 | N13: 0
... A102: issues of the manor | B102: nothing from apples in the garden this year because there was no fruit. | C102: 0 | D102: 0 | E102: 0 | F102: 0 | H102: 0 | I102: 0 | J102: 0 | K102: 0 | L102: 0 | M102: 0 | N102: 0
A103: issues of the manor | B103: £1 from 15 quarters of limestone sold, at 1 shilling 4pence a quarters. | C103: 1 | D103: 1 | E103: 0 | F103: 0 | H103: 15 | I103: 0 | J103: 15 | K103: 15 | L103: 0 | M103: 15 | N103: 0 | AA103: 1 | AB103: 4
A104: issues of the manor | B104: total, £31 9pence. | C104: 31.04 | D104: 31 | E104: 0 | F104: 9 | H104: 0 | I104: 0 | J104: 0 | K104: 0 | L104: 0 | M104: 0 | N104: 0
A105: issues of the warren | B105: and for 8 shilling 4pence from 52 rabbits sold to the lord's household, at 4pence a pair. | C105: 0.42 | D105: 0 | E105: 8 | F105: 4 | H105: 0 | I105: 0 | J105: 0 | K105: 0 | L105: 0 | M105: 0 | N105: 0
A106: issues of the warren | B106: £3 1 shilling 9pence from 494 young rabbits sold to the lord's household, at 3pence a pair. | C106: 3.09 | D106: 3 | E106: 1 | F106: 9 | H106: 0 | I106: 0 | J106: 0 | K106: 0 | L106: 0 | M106: 0 | N106: 0
A107: issues of the warren | B107: total, £3 10 shilling 1pence. | C107: 3.5 | D107: 3 | E107: 10 | F107: 1 | H107: 0 | I107: 0 | J107: 0 | K107: 0 | L107: 0 | M107: 0 | N107: 0
A108: issues of the lands and tenements in the lord's hands which were recovered from william overtone | B108: nothing of the 10 shilling for the herbage of the meadow called vertdelay because of the lord's cattle. | C108: 0.5 | D108: 0 | E108: 10 | F108: 0 | H108: 0 | I108: 0 | J108: 0 | K108: 0 | L108: 0 | M108: 0 | N108: 0
A109: issues of the lands and tenements in the lord's hands which were recovered from william overtone | B109: nothing of the 4 shilling for the summer pasturage of 1 croft beside the south side of the said meadow because of the lord's cattle. | C109: 0.2 | D109: 0 | E109: 4 | F109: 0 | H109: 0 | I109: 0 | J109: 0 | K109: 0 | L109: 0 | M109: 0 | N109: 0
A110: issues of the lands and tenements in the lord's hands which were recovered from william overtone | B110: 16 shilling 6pence from william overton' for 1 toft with a curtilage and 1 croft containing 1 acre by estimation, 1 meadow formerly of john atte fysshewer', 1 croft containing 2 acres by estimation which lies on the west side of the tenement of the aforesaid william, 1 garden with a pond, 1 vennel called wranglane which lies on the east side of the tenement of the same william, and 2 acres called wodeacres which lie on the west side of 1 croft of the aforesaid william called swetele, demised to the aforesaid william by fine made with the lord therefor. | C110: 0.83 | D110: 0 | E110: 16 | F110: 6 | H110: 0 | I110: 0 | J110: 0 | K110: 0 | L110: 0 | M110: 0 | N110: 0
A111: issues of the lands and tenements in the lord's hands which were recovered from william overtone | B111: 1 shilling 6pence from 1 small garden beside the garden of la fysshewer', let to richard sourlond' this year. | C111: 0.08 | D111: 0 | E111: 1 | F111: 6 | H111: 0 | I111: 0 | J111: 0 | K111: 0 | L111: 0 | M111: 0 | N111: 0
A112: issues of the lands and tenements in the lord's hands which were recovered from william overtone | B112: nothing from the sale of beech saplings in la inhome this year. | C112: 0 | D112: 0 | E112: 0 | F112: 0 | H112: 0 | I112: 0 | J112: 0 | K112: 0 | L112: 0 | M112: 0 | N112: 0
A113: issues of the lands and tenements in the lord's hands which were recovered from william overtone | B113: 8 shilling from the issue of 6 acres of land which formerly belonged to thomas smyth' and 1 small wooded grove with 2 crofts at le3 brokes which belonged to john de godisfeld', let to roger maffey for the term of his life. | C113: 0.4 | D113: 0 | E113: 8 | F113: 0 | H113: 0 | I113: 0 | J113: 0 | K113: 0 | L113: 0 | M113: 0 | N113: 0
A114: issues of the lands and tenements in the lord's hands which were recovered from william overtone | B114: 5 shilling from the issue of 1 cottage which formerly belonged to john, son of john godisfeld', and before to reginald cornow and which was taken from william de overton' into the lord's hands and for which john schalden' fined, for this the twenty-fifth year. | C114: 0.25 | D114: 0 | E114: 5 | F114: 0 | H114: 0 | I114: 0 | J114: 0 | K114: 0 | L114: 0 | M114: 0 | N114: 0
A115: issues of the lands and tenements in the lord's hands which were recovered from william overtone | B115: nothing from apples in the garden beside the garden of william de overton' because william overton' fined for the same. | C115: 0 | D115: 0 | E115: 0 | F115: 0 | H115: 0 | I115: 0 | J115: 0 | K115: 0 | L115: 0 | M115: 0 | N115: 0
... A150: release of labour services | B150: total, £1 2 shilling 10pence. | C150: 1.14 | D150: 1 | E150: 2 | F150: 10 | H150: 0 | I150: 0 | J150: 0 | K150: 0 | L150: 0 | M150: 0 | N150: 0
A151: sale of corn and malt | B151: and for £14 7 shilling 11.75pence1 from 30 quarters of wheat sold, of which 7 quarters 4 bushels sold to the lord's household for £3 10 shilling, at 9 shilling 4pence a quarters, 1 quarters 1 bushels to the guardians of john coupere until he should come of age for 3 shilling 9pence, and 21 quarters 3 bushels per mutuum for £10 13 shilling 9pence, at 10 shilling a quarters. | C151: 14.4 | D151: 14 | E151: 7 | F151: 11.75 | G151: wheat | H151: 29 | I151: 8 | J151: 30 | K151: 30 | L151: 0 | M151: 30 | N151: 0 | O151: 7 | P151: 4 | Q151: 1 | R151: 1 | S151: 21 | T151: 3 | AA151: 9 | AB151: 4 | AC151: 10 | AD151: 0
A152: sale of corn and malt | B152: £50 14 shilling from 174 quarters of malt sold to the lord's household, at 6 shilling a quarters for 144 quarters, or £43 4 shilling, and 5 shilling a quarters for 30 quarters, or £7 10 shilling. | C152: 50.7 | D152: 50 | E152: 14 | F152: 0 | G152: malt | H152: 174 | I152: 0 | J152: 174 | K152: 174 | L152: 0 | M152: 174 | N152: 0 | O152: 144 | P152: 0 | Q152: 30 | R152: 0 | AA152: 6 | AB152: 0 | AC152: 5 | AD152: 0
A153: sale of corn and malt | B153: total, £65 1 shilling 11.75pence. | C153: 65.1 | D153: 65 | E153: 1 | F153: 11.75 | H153: 0 | I153: 0 | J153: 0 | K153: 0 | L153: 0 | M153: 0 | N153: 0
A154: sale of stock | B154: and for 7 shilling 10pence from 1 bull sold. | C154: 0.39 | D154: 0 | E154: 7 | F154: 10 | H154: 0 | I154: 0 | J154: 0 | K154: 0 | L154: 0 | M154: 0 | N154: 0
A155: sale of stock | B155: 7 shilling 6pence from 1 cow useless for the stock sold. | C155: 0.38 | D155: 0 | E155: 7 | F155: 6 | H155: 0 | I155: 0 | J155: 0 | K155: 0 | L155: 0 | M155: 0 | N155: 0
A156: sale of stock | B156: 16 shilling 8pence from 10 calves sold, at 1 shilling 8pence each. | C156: 0.83 | D156: 0 | E156: 16 | F156: 8 | H156: 0 | I156: 0 | J156: 0 | K156: 0 | L156: 0 | M156: 0 | N156: 0
A157: sale of stock | B157: 12 shilling from 12 of the worse kebb wethers sold in the market after shearing, at 1 shilling each. | C157: 0.6 | D157: 0 | E157: 12 | F157: 0 | H157: 0 | I157: 0 | J157: 0 | K157: 0 | L157: 0 | M157: 0 | N157: 0
A158: sale of stock | B158: 2 shilling 8pence from 2 kebb ewes from a heriot sold. | C158: 0.13 | D158: 0 | E158: 2 | F158: 8 | H158: 0 | I158: 0 | J158: 0 | K158: 0 | L158: 0 | M158: 0 | N158: 0
A159: sale of stock | B159: 4 shilling from 4 lambs sold. | C159: 0.2 | D159: 0 | E159: 4 | F159: 0 | H159: 0 | I159: 0 | J159: 0 | K159: 0 | L159: 0 | M159: 0 | N159: 0
A160: sale of stock | B160: 5 shilling from 1 boar sold to the lord's household. | C160: 0.25 | D160: 0 | E160: 5 | F160: 0 | H160: 0 | I160: 0 | J160: 0 | K160: 0 | L160: 0 | M160: 0 | N160: 0
A161: sale of stock | B161: 19 shilling from 14 pigs sold to the lord's household, at 2 shilling 6pence each for 2, and 1 shilling 2pence each for 12.. | C161: 0.97 | D161: 0 | E161: 19 | F161: 6 | H161: 0 | I161: 0 | J161: 0 | K161: 0 | L161: 0 | M161: 0 | N161: 0
A162: sale of stock | B162: total, £3 14 shilling 8pence. | C162: 3.73 | D162: 3 | E162: 14 | F162: 8 | H162: 0 | I162: 0 | J162: 0 | K162: 0 | L162: 0 | M162: 0 | N162: 0
A163: entry and marriage fines | B163: and for £3 4 shilling from tithingpenny at the tourns of martinmas and hockday. | C163: 3.2 | D163: 3 | E163: 4 | F163: 0 | H163: 0 | I163: 0 | J163: 0 | K163: 0 | L163: 0 | M163: 0 | N163: 0
A164: entry and marriage fines | B164: 13 shilling 4pence from john, son of walter gilberd', to have 1 messuage and 6 shillings and 8 pence of rents in staneford' in the tithing of headley which belonged to the aforesaid walter his father, by pledge of peter langeford'. | C164: 0.67 | D164: 0 | E164: 13 | F164: 4 | H164: 0 | I164: 0 | J164: 0 | K164: 0 | L164: 0 | M164: 0 | N164: 0
... A168: entry and marriage fines | B168: 1 shilling from john cartere the younger to have 1 croft and 1 cotland of villein land in bishops sutton, containing 10 acres, which belonged to james calue and afterwards to john smyth' and which came into the lord's hands as his escheat because the said john smyth abandoned it and refused to hold it any longer, rendering therefor to the lord 3 shilling a year for the ancient rent and 2 shilling for the labour services of the same commuted into cash, on condition that he builds 1 suitable building of 2 long bays and 2 yards within 3 years. | C168: 0.05 | D168: 0 | E168: 1 | F168: 0 | H168: 0 | I168: 0 | J168: 0 | K168: 0 | L168: 0 | M168: 0 | N168: 0
A169: entry and marriage fines | B169: 3 shilling 4pence from john, son of john doupere, to have 1 messuage .5 virgate of villein land in bishops sutton and 1 toft 0.5 virgate of villein land in ropley which belonged to the aforesaid john his father, and the wardship of this same john with his land is conunitted to john schalden' and john wydehay until the same john should come of age, rendering therefor to the lord 3 shilling 9pence a year for 9 bushels of wheat for churchscot, the ancient rent and all other customary labour services during the minority of the same john. | C169: 0.17 | D169: 0 | E169: 3 | F169: 4 | G169: wheat | H169: 0 | I169: 9 | J169: 1.12 | K169: 1.12 | L169: 0 | M169: 0 | N169: 9
A170: entry and marriage fines | B170: 3 shilling 4pence from hugh, son of john doupere, to have 1 toft 1 virgate of villein land in ropley called horneslond' and 2 acres of purpresture there which belonged to the aforesaid john his father, and the wardship of this same hugh with his land is committed to john schalden' and john wydehay until the same hugh should come of age. | C170: 0.17 | D170: 0 | E170: 3 | F170: 4 | H170: 0 | I170: 0 | J170: 0 | K170: 0 | L170: 0 | M170: 0 | N170: 0
A171: entry and marriage fines | B171: £1 from william mayhew and alice his wife to have 1 messuage 0.5 virgate of villein land, 3 acres of purpresture, 1 toft .5 virgate of villein land and 4 acres of purpresture in the tithing of ropley by surrender of john spede, on condition that the aforesaid william and alice will provide the aforesaid john and alice his wife with victuals and clothes for the term of their lives. | C171: 1 | D171: 1 | E171: 0 | F171: 0 | H171: 0 | I171: 0 | J171: 0 | K171: 0 | L171: 0 | M171: 0 | N171: 0
A172: entry and marriage fines | B172: 3 shilling 4pence from isabel atte feld' to have 1 messuage and 3 shillings of rents in headley which belonged to agnes atte feld' her kinswoman. | C172: 0.17 | D172: 0 | E172: 3 | F172: 4 | H172: 0 | I172: 0 | J172: 0 | K172: 0 | L172: 0 | M172: 0 | N172: 0
A173: entry and marriage fines | B173: 3 shilling 4pence from hugh letys to have isabel atte feld' with her land, that is, 1 messuage and 3 shillings of rents in headley. | C173: 0.17 | D173: 0 | E173: 3 | F173: 4 | H173: 0 | I173: 0 | J173: 0 | K173: 0 | L173: 0 | M173: 0 | N173: 0
A174: entry and marriage fines | B174: 3 shilling 4pence from emma, daughter of william som', for marrying herself outside. | C174: 0.17 | D174: 0 | E174: 3 | F174: 4 | H174: 0 | I174: 0 | J174: 0 | K174: 0 | L174: 0 | M174: 0 | N174: 0
A175: entry and marriage fines | B175: total, £7 5 shilling 4pence. | C175: 7.27 | D175: 7 | E175: 5 | F175: 4 | H175: 0 | I175: 0 | J175: 0 | K175: 0 | L175: 0 | M175: 0 | N175: 0
A176: perquisites | B176: and for 10 shilling 1pence from the perquisites of the tourn of martinmas (11 november). | C176: 0.5 | D176: 0 | E176: 10 | F176: 1 | H176: 0 | I176: 0 | J176: 0 | K176: 0 | L176: 0 | M176: 0 | N176: 0
A177: perquisites | B177: £1 2 shilling 9pence from the perquisites of the courts held after the said tourn. | C177: 1.14 | D177: 1 | E177: 2 | F177: 9 | H177: 0 | I177: 0 | J177: 0 | K177: 0 | L177: 0 | M177: 0 | N177: 0
A178: perquisites | B178: 12 shilling 8pence from the perquisites of the tourn of hockday (1 april). | C178: 0.63 | D178: 0 | E178: 12 | F178: 8 | H178: 0 | I178: 0 | J178: 0 | K178: 0 | L178: 0 | M178: 0 | N178: 0
A179: perquisites | B179: 10 shilling 8pence from the perquisites of the courts held by the bailiff after the said tourn of hockday. | C179: 0.53 | D179: 0 | E179: 10 | F179: 8 | H179: 0 | I179: 0 | J179: 0 | K179: 0 | L179: 0 | M179: 0 | N179: 0
A180: perquisites | B180: £1 3 shilling 6pence from the homage of headley for release from their suit of court this year. | C180: 1.17 | D180: 1 | E180: 3 | F180: 6 | H180: 0 | I180: 0 | J180: 0 | K180: 0 | L180: 0 | M180: 0 | N180: 0
A181: perquisites | B181: total, £3 19 shilling 8pence. | C181: 3.98 | D181: 3 | E181: 19 | F181: 8 | H181: 0 | I181: 0 | J181: 0 | K181: 0 | L181: 0 | M181: 0 | N181: 0
... A208: cost of carts | B208: total, £1 7 shilling 6pence. | C208: 1.38 | D208: 1 | E208: 7 | F208: 6 | H208: 0 | I208: 0 | J208: 0 | K208: 0 | L208: 0 | M208: 0 | N208: 0
A209: purchase of corn and stock | B209: in 167 quarters 2.5 bushels of barley bought for malting as made clear elsewhere £47 8 shilling 1.25pence, at 5 shilling 8pence a quarters. | C209: 47.41 | D209: 47 | E209: 8 | F209: 1.25 | G209: barley, malt | H209: 167 | I209: 2.5 | J209: 167.31 | K209: 167.31 | L209: 0 | M209: 167 | N209: 2.5 | AA209: 5 | AB209: 8
A210: purchase of corn and stock | B210: i quarters 4 bushels of pulses bought for sowing 6 shilling, at 6pence a bushels. | C210: 0.33 | D210: 0 | E210: 6 | F210: 6 | H210: 0 | I210: 4 | J210: 0.5 | K210: 0.5 | L210: 0 | M210: 0 | N210: 4 | AI210: 0 | AJ210: 6
A211: purchase of corn and stock | B211: 1 quarters 1 bushels of oats bought 3 shilling 4.5pence, at 4.5pence a bushels. | C211: 0.17 | D211: 0 | E211: 3 | F211: 4.5 | G211: oats | H211: 1 | I211: 1 | J211: 1.12 | K211: 1.12 | L211: 0 | M211: 1 | N211: 1 | AI211: 0 | AJ211: 4.5
A212: purchase of corn and stock | B212: i cow bought with calf 9 shilling. | C212: 0.45 | D212: 0 | E212: 9 | F212: 0 | H212: 0 | I212: 0 | J212: 0 | K212: 0 | L212: 0 | M212: 0 | N212: 0
A213: purchase of corn and stock | B213: 2 ewes bought before shearing 2 shilling. | C213: 0.1 | D213: 0 | E213: 2 | F213: 0 | H213: 0 | I213: 0 | J213: 0 | K213: 0 | L213: 0 | M213: 0 | N213: 0
A214: purchase of corn and stock | B214: 80 hoggs bought from the reeve of alresford before shearing £6 13 shilling 4pence, at 1 shilling 8pence each. | C214: 6.67 | D214: 6 | E214: 13 | F214: 4 | H214: 0 | I214: 0 | J214: 0 | K214: 0 | L214: 0 | M214: 0 | N214: 0
A215: purchase of corn and stock | B215: total, £55 1 shilling 9.75pence. | C215: 55.09 | D215: 55 | E215: 1 | F215: 9.75 | H215: 0 | I215: 0 | J215: 0 | K215: 0 | L215: 0 | M215: 0 | N215: 0
A216: cost of the fold and dairy | B216: in tar and grease bought for greasing the lord's sheep, 9 shilling this year, and so much this year on account of the scarcity of grease. | C216: 0.45 | D216: 0 | E216: 9 | F216: 0 | H216: 0 | I216: 0 | J216: 0 | K216: 0 | L216: 0 | M216: 0 | N216: 0
A217: cost of the fold and dairy | B217: 26 hurdles bought 4 shilling 4pence. | C217: 0.22 | D217: 0 | E217: 4 | F217: 4 | H217: 0 | I217: 0 | J217: 0 | K217: 0 | L217: 0 | M217: 0 | N217: 0
A218: cost of the fold and dairy | B218: collecting stubble for wattling the fold 1 shilling. | C218: 0.05 | D218: 0 | E218: 1 | F218: 0 | H218: 0 | I218: 0 | J218: 0 | K218: 0 | L218: 0 | M218: 0 | N218: 0
A219: cost of the fold and dairy | B219: carrying the fold from field to field 1 shilling. | C219: 0.05 | D219: 0 | E219: 1 | F219: 0 | H219: 0 | I219: 0 | J219: 0 | K219: 0 | L219: 0 | M219: 0 | N219: 0
A220: cost of the fold and dairy | B220: straw bought for supporting the wethers in winter 5 shilling 6pence. | C220: 0.28 | D220: 0 | E220: 5 | F220: 6 | H220: 0 | I220: 0 | J220: 0 | K220: 0 | L220: 0 | M220: 0 | N220: 0
A221: cost of the fold and dairy | B221: mending cratches and fodder-racks this year 10pence. | C221: 0.04 | D221: 0 | E221: 0 | F221: 10 | H221: 0 | I221: 0 | J221: 0 | K221: 0 | L221: 0 | M221: 0 | N221: 0
A222: cost of the fold and dairy | B222: 3 bushels of salt bought 2 shilling. | C222: 0.1 | D222: 0 | E222: 2 | F222: 0 | H222: 0 | I222: 3 | J222: 0.38 | K222: 0.38 | L222: 0 | M222: 0 | N222: 3
A223: cost of the fold and dairy | B223: clay pots and pans bought for the dairy 6pence. | C223: 0.03 | D223: 0 | E223: 0 | F223: 6 | H223: 0 | I223: 0 | J223: 0 | K223: 0 | L223: 0 | M223: 0 | N223: 0
... A246: cost of the buildings of the liberty | B246: total, £5 8 shilling 5.5pence. | C246: 5.42 | D246: 5 | E246: 8 | F246: 5.5 | H246: 0 | I246: 0 | J246: 0 | K246: 0 | L246: 0 | M246: 0 | N246: 0
A247: cost of buildings with necessaries | B247: in 4 sacks bought 4 shilling, both for the manor and for carrying malt for the lord's household. | C247: 0.2 | D247: 0 | E247: 4 | F247: 0 | G247: malt | H247: 0 | I247: 0 | J247: 0 | K247: 0 | L247: 0 | M247: 0 | N247: 0
A248: cost of buildings with necessaries | B248: making and drying 174 quarters of malt this year £1 16 shilling 3pence, at 2v2pence a quarters. | C248: 1.81 | D248: 1 | E248: 16 | F248: 3 | G248: malt | H248: 174 | I248: 0 | J248: 174 | K248: 174 | L248: 0 | M248: 174 | N248: 0
A249: cost of buildings with necessaries | B249: making 10 quarters of charcoal and taking it to the manor to dry the said malt 2 shilling 1pence, at 2.5pence for each quarter made. | C249: 0.1 | D249: 0 | E249: 2 | F249: 1 | G249: malt | H249: 10 | I249: 0 | J249: 10 | K249: 10 | L249: 0 | M249: 10 | N249: 0
A250: cost of buildings with necessaries | B250: hiring 1 thatcher to roof the barn for 2 days 8pence. | C250: 0.03 | D250: 0 | E250: 0 | F250: 8 | H250: 0 | I250: 0 | J250: 0 | K250: 0 | L250: 0 | M250: 0 | N250: 0
A251: cost of buildings with necessaries | B251: stipend of 1 of his mates for the same time 4pence. | C251: 0.02 | D251: 0 | E251: 0 | F251: 4 | H251: 0 | I251: 0 | J251: 0 | K251: 0 | L251: 0 | M251: 0 | N251: 0
A252: cost of buildings with necessaries | B252: hiring 1 roofer with his mate to roof the byre and the porches of the barns for 8 days 5 shilling 4pence, taking together 8pence a day. | C252: 0.27 | D252: 0 | E252: 5 | F252: 4 | H252: 0 | I252: 0 | J252: 0 | K252: 0 | L252: 0 | M252: 0 | N252: 0
A253: cost of buildings with necessaries | B253: hiring 1 carpenter to make anew 1 door in the north side of the barn and 1 door in the dairy building for 2 days 10pence. | C253: 0.04 | D253: 0 | E253: 0 | F253: 10 | H253: 0 | I253: 0 | J253: 0 | K253: 0 | L253: 0 | M253: 0 | N253: 0
A254: cost of buildings with necessaries | B254: 4 hooks and 4 hinges bought for the same 1 shilling 4pence. | C254: 0.07 | D254: 0 | E254: 1 | F254: 4 | H254: 0 | I254: 0 | J254: 0 | K254: 0 | L254: 0 | M254: 0 | N254: 0
A255: cost of buildings with necessaries | B255: 100 board-nails bought for the same 10pence. | C255: 0.04 | D255: 0 | E255: 0 | F255: 10 | H255: 0 | I255: 0 | J255: 0 | K255: 0 | L255: 0 | M255: 0 | N255: 0
A256: cost of buildings with necessaries | B256: hiring 1 carpenter to make anew 1 staircase and 1 door for the beadle's chamber for 1 day 5pence. | C256: 0.02 | D256: 0 | E256: 0 | F256: 5 | H256: 0 | I256: 0 | J256: 0 | K256: 0 | L256: 0 | M256: 0 | N256: 0
A257: cost of buildings with necessaries | B257: nails bought for the same 2pence. | C257: 0.01 | D257: 0 | E257: 0 | F257: 2 | H257: 0 | I257: 0 | J257: 0 | K257: 0 | L257: 0 | M257: 0 | N257: 0
A258: cost of buildings with necessaries | B258: hooks and hinges, nothing, because they were from the old door. | C258: 0 | D258: 0 | E258: 0 | F258: 0 | H258: 0 | I258: 0 | J258: 0 | K258: 0 | L258: 0 | M258: 0 | N258: 0
A259: cost of buildings with necessaries | B259: 1 seed-basket bought 5pence. | C259: 0.02 | D259: 0 | E259: 0 | F259: 5 | H259: 0 | I259: 0 | J259: 0 | K259: 0 | L259: 0 | M259: 0 | N259: 0
A260: cost of buildings with necessaries | B260: hooping the same with iron hoops 4pence. | C260: 0.02 | D260: 0 | E260: 0 | F260: 4 | H260: 0 | I260: 0 | J260: 0 | K260: 0 | L260: 0 | M260: 0 | N260: 0
A261: cost of buildings with necessaries | B261: hiring 1 cooper to mend 2 damaged vats and to hoop them with new wooden hoops 1 shilling 6pence. | C261: 0.08 | D261: 0 | E261: 1 | F261: 6 | H261: 0 | I261: 0 | J261: 0 | K261: 0 | L261: 0 | M261: 0 | N261: 0
... A287: weeding and mowing | B287: total, 14 shilling. | C287: 0.7 | D287: 0 | E287: 14 | F287: 0 | H287: 0 | I287: 0 | J287: 0 | K287: 0 | L287: 0 | M287: 0 | N287: 0
A288: threshing and winnowing | B288: in threshing 30 quarters 4 bushels of wheat and 1 quarters 4 bushels of curall by piece-work 8 shilling, at 3pence a quarters. | C288: 0.41 | D288: 0 | E288: 8 | F288: 3 | G288: wheat, curall | H288: 1 | I288: 4 | J288: 1.5 | K288: 30.5 | L288: -29 | M288: 30 | N288: 4 | O288: 1 | P288: 4
A289: threshing and winnowing | B289: threshing 53 quarters 4 bushels of barley by piece-work 8 shilling 11pence, at 2pence a quarters. | C289: 0.45 | D289: 0 | E289: 8 | F289: 11 | G289: barley | H289: 53 | I289: 4 | J289: 53.5 | K289: 53.5 | L289: 0 | M289: 53 | N289: 4
A290: threshing and winnowing | B290: threshing 34 quartersl 3 bushels of oats by piece-work 4 shilling 3.75pence, at 1.5pence a quarters. | C290: 0.22 | D290: 0 | E290: 4 | F290: 3.75 | G290: oats | H290: 34 | I290: 3 | J290: 34.38 | K290: 34 | L290: 0.38 | M290: 34 | N290: 0 | O290: 0 | P290: 3
A291: threshing and winnowing | B291: winnowing a moiety of all the aforesaid corn by piece-work, that is, 59 quarters 7.5 bushels, 1 shilling 8pence, at 1pence per 3 quarters. | C291: 0.08 | D291: 0 | E291: 1 | F291: 8 | H291: 3 | I291: 7.5 | J291: 3.94 | K291: 59.94 | L291: -56 | M291: 59 | N291: 7.5 | O291: 3 | P291: 0
A292: threshing and winnowing | B292: total, £1 2 shilling 10.75pence. | C292: 1.14 | D292: 1 | E292: 2 | F292: 10.75 | H292: 0 | I292: 0 | J292: 0 | K292: 0 | L292: 0 | M292: 0 | N292: 0
A293: cost of the harvest | B293: in bread bought for the harvest boon-works of 296 men with 6 officials of the curia at 3 boon-works, who reaped, bound and carried 54 acres of pulses and 7 acres of oats,2 which made 77 acres, 12 shilling 4pence, or .5pence of bread each. | C293: 0.62 | D293: 0 | E293: 12 | F293: 4 | G293: oats | H293: 0 | I293: 0 | J293: 0 | K293: 0 | L293: 0 | M293: 0 | N293: 0
A294: cost of the harvest | B294: 592 herrings bought for the same 6 shilling 2pence, and each reaper has two herrings. | C294: 0.31 | D294: 0 | E294: 6 | F294: 2 | H294: 0 | I294: 0 | J294: 0 | K294: 0 | L294: 0 | M294: 0 | N294: 0
A295: cost of the harvest | B295: cheese bought for the same 6 shilling 2pence, and each reaper has vad. worth of cheese. | C295: 0.31 | D295: 0 | E295: 6 | F295: 2 | H295: 0 | I295: 0 | J295: 0 | K295: 0 | L295: 0 | M295: 0 | N295: 0
A296: cost of the harvest | B296: moreover, the customary tenants reaped for labour service 109 acres3 as they lie which made 54.5 acres by the perch for sheaves. | C296: 0 | D296: 0 | E296: 0 | F296: 0 | H296: 0 | I296: 0 | J296: 0 | K296: 0 | L296: 0 | M296: 0 | N296: 0
A297: cost of the harvest | B297: stipend of 1 reap-reeve who supervised the reapers at harvest-time 3 shilling 4pence. | C297: 0.17 | D297: 0 | E297: 3 | F297: 4 | H297: 0 | I297: 0 | J297: 0 | K297: 0 | L297: 0 | M297: 0 | N297: 0
A298: cost of the harvest | B298: total, £1 8 shilling. | C298: 1.4 | D298: 1 | E298: 8 | F298: 0 | H298: 0 | I298: 0 | J298: 0 | K298: 0 | L298: 0 | M298: 0 | N298: 0
...

Sheet Stock_raw
A1: Heading | B1: Sentence | C1: Quarters 1 | D1: Bushels 1 | E1: stock | F1: inherited stock | G1: added | H1: murrain | I1: sold
A2: Oats | B2: Total | C2: 0 | D2: 0
A3: Stock | B3: Horses: 6 remain. | C3: 0 | D3: 0 | F3: 6
A4: Stock | B4: Oxen: 14 remain. | C4: 0 | D4: 0 | E4: Oxen | F4: 14
A5: Stock | B5: 1 from the heriot of John Reedere. | C5: 0 | D5: 0 | E5: Oxen
A6: Stock | B6: 1 from the heriot of Walter Gylberd'. | C6: 0 | D6: 0 | E6: Oxen
A7: Stock | B7: 3 added from steers below. | C7: 0 | D7: 0 | E7: Oxen
A8: Stock | B8: Total, 19. 2 in murrain. | C8: 0 | D8: 0 | E8: Oxen | H8: 2
A9: Stock | B9: Total, 2. 17 remain. | C9: 0 | D9: 0 | E9: Oxen
A10: Stock | B10: Bulls: 1 remains. | C10: 0 | D10: 0 | E10: Bulls
A11: Stock | B11: 1 added from steers below. | C11: 0 | D11: 0 | E11: Bulls
A12: Stock | B12: Total, 2. 1 sold. | C12: 0 | D12: 0 | E12: Bulls | I12: 1
A13: Stock | B13: 1 remains. | C13: 0 | D13: 0 | E13: Bulls
A14: Stock | B14: Cows: 22 remain, 1 bought. | C14: 0 | D14: 0 | E14: Cows | F14: 22 | G14: 1
A15: Stock | B15: 3 added from steers below. | C15: 0 | D15: 0 | E15: Cows
A16: Stock | B16: Total, 26. 2 in murrain, 1 sold because useless for the stock. | C16: 0 | D16: 0 | E16: Cows | H16: 2 | I16: 1
A17: Stock | B17: Total, 3. 23 remain, 1 of them a kebb. | C17: 0 | D17: 0 | E17: Cows
A18: Stock | B18: Steers: 7 use remain from the bullocks. | C18: 0 | D18: 0 | E18: Steers | F18: 7
A19: Stock | B19: Total, 7. 3 added above to oxen, 1 to bulls and 3. | C19: 0 | D19: 0 | E19: Steers
A20: Stock | B20: to cows. | C20: 0 | D20: 0 | E20: Steers
A21: Stock | B21: none remain. | C21: 0 | D21: 0 | E21: Steers
A22: Stock | B22: Calves: 20 offspring and not more because 1 cow died before calving and 1 was sold before calving. | C22: 0 | D22: 0 | E22: Calves | G22: 20 | I22: 20
A23: Stock | B23: Total, 20. 2 in tithe. | C23: 0 | D23: 0 | E23: Calves
A24: Stock | B24: 10 sold within. | C24: 0 | D24: 0 | E24: Calves | I24: 10
A25: Stock | B25: 8 remain. | C25: 0 | D25: 0 | E25: Calves | F25: 8
A26: Stock | B26: Wethers: 534 remain. | C26: 0 | D26: 0 | E26: Wethers | F26: 534
A27: Stock | B27: 80 added from hoggs below. | C27: 0 | D27: 0 | E27: Wethers
A28: Stock | B28: 1 from strays before shearing. | C28: 0 | D28: 0 | E28: Wethers
A29: Stock | B29: Total, 615. 17 in murrain before shearing and 12 after shearing. | C29: 0 | D29: 0 | E29: Wethers | H29: 17
A30: Stock | B30: 12 of the worse kebbs sold in the market after shearing. | C30: 0 | D30: 0 | E30: Wethers | I30: 12
A31: Stock | B31: Total, 79.1 574 remain, of which 38 delivered to the lord's household. | C31: 0 | D31: 0 | E31: Wethers
A32: Stock | B32: Ewes: 2 from the heriot of John Spede. | C32: 0 | D32: 0 | E32: Ewes
A33: Stock | B33: 2 bought. | C33: 0 | D33: 0 | E33: Ewes | G33: 2
A34: Stock | B34: Total, 4. 2 in liveries of the shepherd and smith according to custom at Martinmas. | C34: 0 | D34: 0 | E34: Ewes
A35: Stock | B35: 2 sold within. | C35: 0 | D35: 0 | E35: Ewes | I35: 2
A36: Stock | B36: none remain. | C36: 0 | D36: 0 | E36: Ewes
A37: Stock | B37: Hoggs: 80 bought before shearing from the reeve of Alresford. | C37: 0 | D37: 0 | E37: Hoggs | G37: 80
A38: Stock | B38: Total, 80. All added above to wethers. | C38: 0 | D38: 0 | E38: Hoggs
A39: Stock | B39: none remain. | C39: 0 | D39: 0 | E39: Hoggs
A40: Stock | B40: Lambs: 8 from the offspring of as many ewes going to mate (in mulo) with the wethers. | C40: 0 | D40: 0 | E40: Lambs | G40: 8
A41: Stock | B41: 1 from the heriot of Robert Northgate. | C41: 0 | D41: 0 | E41: Lambs
A42: Stock | B42: Total, 9. 1 in murrain. | C42: 0 | D42: 0 | E42: Lambs | H42: 1
A43: Stock | B43: 1 in tithe. | C43: 0 | D43: 0 | E43: Lambs
A44: Stock | B44: 3 in liveries of the reeve, shepherd and smith according to custom. | C44: 0 | D44: 0 | E44: Lambs
A45: Stock | B45: 4 sold within. | C45: 0 | D45: 0 | E45: Lambs | I45: 4
A46: Stock | B46: Boars: 1 remains. | C46: 0 | D46: 0 | E46: Boars
A47: Stock | B47: 1 added from hoggets below. | C47: 0 | D47: 0 | E47: Boars
A48: Stock | B48: Total, 2. 1 sold to the lord's household. | C48: 0 | D48: 0 | E48: Boars | I48: 1
A49: Stock | B49: 1 remains. | C49: 0 | D49: 0 | E49: Boars
A50: Stock | B50: Sows: 2 remain. | C50: 0 | D50: 0 | E50: Sows | F50: 2
A51: Stock | B51: Pigs: 20 remain. | C51: 0 | D51: 0 | E51: Pigs | F51: 20
A52: Stock | B52: 21 added from hoggets below. | C52: 0 | D52: 0 | E52: Pigs
A53: Stock | B53: Total, 41. 14 sold to the lord's household. | C53: 0 | D53: 0 | E53: Pigs | I53: 14
A54: Stock | B54: Total, 14. 27 remain. | C54: 0 | D54: 0 | E54: Pigs
A55: Stock | B55: Hoggets: 25 remain from the piglets. | C55: 0 | D55: 0 | E55: Hoggets | F55: 25
A56: Stock | B56: Total, 25. 3 in murrain. | C56: 0 | D56: 0 | E56: Hoggets | H56: 3
A57: Stock | B57: 1 added above to boars and 21 to pigs. | C57: 0 | D57: 0 | E57: Hoggets
A58: Stock | B58: none remain. | C58: 0 | D58: 0 | E58: Hoggets
A59: Stock | B59: Piglets: 30 from the offspring of the said sows. | C59: 0 | D59: 0 | E59: Piglets | G59: 30
A60: Stock | B60: Total, 30. 3 in tithe. | C60: 0 | D60: 0 | E60: Piglets
A61: Stock | B61: 2 in customary payment to the reeve and smith. | C61: 0 | D61: 0 | E61: Piglets
A62: Stock | B62: Total, 5. 25 remain. | C62: 0 | D62: 0 | E62: Piglets | F62: 25
A63: Stock | B63: Coarse wool: 518 fleeces from wethers and 80 from hoggs produced at the shearing this year. | C63: 0 | D63: 0 | E63: Coarse wool
A64: Stock | B64: Total, 598. 60 in tithe. | C64: 0 | D64: 0 | E64: Coarse wool
A65: Stock | B65: 1 in customary payment to the shepherd. | C65: 0 | D65: 0 | E65: Coarse wool
A66: Stock | B66: 537 delivered to the receiver of Wolvesey, weighing 1.5 sacks 21 cloves. | C66: 0 | D66: 0 | E66: Coarse wool
A67: Stock | B67: Hides: 2 from oxen, 2 from cows and 4 from yearlings in murrain as made clear above. | C67: 0 | D67: 0 | E67: Coarse wool | H67: 2
A68: Stock | B68: sold within. | C68: 0 | D68: 0 | E68: Coarse wool
A69: Stock | B69: none remain. | C69: 0 | D69: 0 | E69: Coarse wool
A70: Stock | B70: Woolskins: 17 from wethers in murrain before shearing as made clear above. | C70: 0 | D70: 0 | E70: Woolskins | H70: 17
A71: Stock | B71: 2 in tithe. | C71: 0 | D71: 0 | E71: Woolskins
A72: Stock | B72: 15 sold within. | C72: 0 | D72: 0 | E72: Woolskins | I72: 15
A73: Stock | B73: none remain. | C73: 0 | D73: 0 | E73: Woolskins
A74: Stock | B74: Bare skins: 12 from wethers in murrain after shearing as made clear above. | C74: 0 | D74: 0 | E74: Bareskins | H74: 12
A75: Stock | B75: sold within. | C75: 0 | D75: 0 | E75: Bareskins
A76: Stock | B76: none remain. | C76: 0 | D76: 0 | E76: Bareskins
A77: Stock | B77: Lambskins: 1 from a lamb in murrain as made clear above. | C77: 0 | D77: 0 | E77: Lambskins | H77: 1
A78: Stock | B78: sold within. | C78: 0 | D78: 0 | E78: Lambskins
A79: Stock | B79: none remain. | C79: 0 | D79: 0 | E79: Lambskins
A80: Stock | B80: Geese: 15 remain. | C80: 0 | D80: 0 | E80: Poultry stock | F80: 15
A81: Stock | B81: 24 offspring. | C81: 0 | D81: 0 | E81: Poultry stock | G81: 24
A82: Stock | B82: Total, 39. 2 in tithe. | C82: 0 | D82: 0 | E82: Poultry stock
A83: Stock | B83: 15 sold within, 10 of them to the lord's household. | C83: 0 | D83: 0 | E83: Poultry stock | I83: 15
A84: Stock | B84: 22 remain, 1 of them a gander and 4 breeding geese. | C84: 0 | D84: 0 | E84: Poultry stock
A85: Stock | B85: Capons: 24 remain. | C85: 0 | D85: 0 | E85: Poultry stock
A86: Stock | B86: 24 made from the chickens below. | C86: 0 | D86: 0 | E86: Poultry stock
A87: Stock | B87: Total, 48. 24 sold within, 21 of them to the lord's household. | C87: 0 | D87: 0 | E87: Poultry stock | I87: 24
A88: Stock | B88: 24 remain. | C88: 0 | D88: 0 | E88: Poultry stock
A89: Stock | B89: Cocks and hens: 1 cock and 5 hens remain. | C89: 0 | D89: 0 | E89: Poultry stock
A90: Stock | B90: 162 from the churchscot of the customary tenants at Martinmas. | C90: 0 | D90: 0 | E90: Poultry stock
A91: Stock | B91: Total, 168. 4 in default of the land of Hendyman because freely commuted. | C91: 0 | D91: 0 | E91: Poultry stock
A92: Stock | B92: 4 in default of the land of Alice Acreman because in the lord's hands through the death of the same in the first pestilence. | C92: 0 | D92: 0 | E92: Poultry stock
A93: Stock | B93: 4 in default of the land of John Tropenell' for the same. | C93: 0 | D93: 0 | E93: Poultry stock
A94: Stock | B94: 4 in default of the land of John Draft for the same, and 4 for the land of John Pycard' for the same. | C94: 0 | D94: 0 | E94: Poultry stock
A95: Stock | B95: 4 in default of the churchscot of the land of John Dauwe because in the lord's hands for this the fifty-first year, because the said John rendered nothing to the lord for rent or services. | C95: 0 | D95: 0 | E95: Poultry stock
A96: Stock | B96: 4 in default of the churchscot of the land of John Abbot for the same, 4 for the land of James Calwe for the same, 4 for the land of Thomas Pipere for the same, 4 for the land of John Goudman for the same, 4 for the land of John Spierke for the same. | C96: 0 | D96: 0 | E96: Poultry stock
A97: Stock | B97: 2 in default of the churchscot of the cotland of Roger Smyth and before of Emma Smyth because he has no wife, 2 for the land of Nicholas Gardyner for the same, and 2 for the land of John Puynder' for the same. | C97: 0 | D97: 0 | E97: Poultry stock
A98: Stock | B98: 112 sold within, 36 of them to the lord's household. | C98: 0 | D98: 0 | E98: Poultry stock | I98: 112
A99: Stock | B99: Total, 162. 1 cock and 5 hens remain. | C99: 0 | D99: 0 | E99: Poultry stock
A100: Stock | B100: Chickens: 24 from the offspring of the said hens. | C100: 0 | D100: 0 | E100: Poultry stock | G100: 24
...

Sheet Issues of the Mills

Sheet Prices

Sheet Labour Rents

Sheet not needed

Sheet Issues of the Grange raw
A1: Heading | B1: Sentence | C1: Quarters 1_x | D1: Bushels 1_x | E1: Sown Quarters | F1: Sown Bushels | G1: Sown Total Quarters | H1: Bought in Quarters | I1: Bought in Bushels | J1: Bought in Total Quarters | K1: Tithe Quarters | L1: Tithe Bushels | M1: Tithe Total Quarters | N1: Manorial servants & livestock Quarters | O1: Manorial servants & livestock Bushels | P1: Manorial servants & livestock Total Quarters | Q1: Sold Quarters | R1: Sold Bushels | S1: Sold Total Quarters | T1: Account Quarters | U1: Account Bushels | V1: Account Total Quarters | W1: bought only | X1: Total Quarters Except 1 | Y1: Total Bushels Except 1 | Z1: Total Corn Cross-Check | AA1: Total Corn Manorial Account | AB1: Corn Quantity Error | AC1: Quarters 1_y | AD1: Bushels 1_y | AE1: Quarters 2 | AF1: Bushels 2 | AG1: Quarters 3 | AH1: Bushels 3 | AI1: Quarters 4 | AJ1: Bushels 4 | AK1: Quarters 5 | AL1: Bushels 5 | AM1: Quarters 6 | AN1: Bushels 6 | AO1: Quarters 7 | AP1: Bushels 7 | AQ1: Total Bought Quarters
A2: and he owes | B2: total | C2: 0 | D2: 0 | E2: 0 | F2: 0 | G2: 0 | H2: 0 | I2: 0 | J2: 0 | K2: 0 | L2: 0 | M2: 0 | N2: 0 | O2: 0 | P2: 0 | Q2: 0 | R2: 0 | S2: 0 | T2: 0 | U2: 0 | V2: 0 | W2: 0 | AQ2: 0
A3: wheat | B3: laurence sourlond', reeve there, answers for 30 quarters 4 bushels from the whole issue, threshed by piece-work. | C3: 0 | D3: 0 | E3: 0 | F3: 0 | G3: 0 | H3: 0 | I3: 0 | J3: 0 | K3: 0 | L3: 0 | M3: 0 | N3: 0 | O3: 0 | P3: 0 | Q3: 0 | R3: 0 | S3: 0 | T3: 30 | U3: 4 | V3: 30.5 | W3: 0 | X3: 30 | Y3: 4 | Z3: 30.5 | AA3: 30.5 | AB3: 0 | AC3: 30 | AD3: 4 | AQ3: 0
A4: wheat | B4: 6 bushels from the same issue by estimation in sheaves. | C4: 0 | D4: 0 | E4: 0 | F4: 0 | G4: 0 | H4: 0 | I4: 0 | J4: 0 | K4: 0 | L4: 0 | M4: 0 | N4: 0 | O4: 0 | P4: 0 | Q4: 0 | R4: 0 | S4: 0 | T4: 0 | U4: 0 | V4: 0 | W4: 0 | X4: 0 | Y4: 6 | Z4: 0.75 | AA4: 0.75 | AB4: 0 | AC4: 0 | AD4: 6 | AQ4: 0
A5: wheat | B5: 22 quarters 4 bushels from the churchscot of the customary tenants at martinmas. | C5: 0 | D5: 0 | E5: 0 | F5: 0 | G5: 0 | H5: 0 | I5: 0 | J5: 0 | K5: 0 | L5: 0 | M5: 0 | N5: 0 | O5: 0 | P5: 0 | Q5: 0 | R5: 0 | S5: 0 | T5: 0 | U5: 0 | V5: 0 | W5: 0 | X5: 22 | Y5: 4 | Z5: 22.5 | AA5: 22.5 | AB5: 0 | AC5: 22 | AD5: 4 | AQ5: 0
A6: wheat | B6: 9 quarters 2 bushels surcharged so that he answers for a 3.5-fold yield. | C6: 0 | D6: 0 | E6: 0 | F6: 0 | G6: 0 | H6: 0 | I6: 0 | J6: 0 | K6: 0 | L6: 0 | M6: 0 | N6: 0 | O6: 0 | P6: 0 | Q6: 0 | R6: 0 | S6: 0 | T6: 0 | U6: 0 | V6: 0 | W6: 0 | X6: 9 | Y6: 2 | Z6: 9.25 | AA6: 9.25 | AB6: 0 | AC6: 9 | AD6: 2 | AQ6: 0
A7: wheat | B7: total, 63 quarters. | C7: 0 | D7: 0 | E7: 0 | F7: 0 | G7: 0 | H7: 0 | I7: 0 | J7: 0 | K7: 0 | L7: 0 | M7: 0 | N7: 0 | O7: 0 | P7: 0 | Q7: 0 | R7: 0 | S7: 0 | T7: 0 | U7: 0 | V7: 0 | W7: 0 | X7: 63 | Y7: 0 | Z7: 63 | AA7: 63 | AB7: 0 | AC7: 63 | AD7: 0 | AQ7: 0
A8: wheat | B8: sown over 54 acres of land by the perch in la reede, reghele and dellond', 13 quarters 4 bushels. | C8: 0 | D8: 0 | E8: 13 | F8: 4 | G8: 13.5 | H8: 0 | I8: 0 | J8: 0 | K8: 0 | L8: 0 | M8: 0 | N8: 0 | O8: 0 | P8: 0 | Q8: 0 | R8: 0 | S8: 0 | T8: 0 | U8: 0 | V8: 0 | W8: 0 | X8: 13 | Y8: 4 | Z8: 13.5 | AA8: 13.5 | AB8: 0 | AC8: 13 | AD8: 4 | AQ8: 0
A9: wheat | B9: that is, 2 bushels an acre. | C9: 0 | D9: 0 | E9: 0 | F9: 0 | G9: 0 | H9: 0 | I9: 0 | J9: 0 | K9: 0 | L9: 0 | M9: 0 | N9: 0 | O9: 0 | P9: 0 | Q9: 0 | R9: 0 | S9: 0 | T9: 0 | U9: 0 | V9: 0 | W9: 0 | X9: 0 | Y9: 2 | Z9: 0.25 | AA9: 0.25 | AB9: 0 | AC9: 0 | AD9: 2 | AQ9: 0
A10: wheat | B10: bread baked for the provision of richard wyot, steward, holding the tourns of martinmas and hockday, 4 bushels by bill. | C10: 0 | D10: 0 | E10: 0 | F10: 0 | G10: 0 | H10: 0 | I10: 0 | J10: 0 | K10: 0 | L10: 0 | M10: 0 | N10: 0 | O10: 0 | P10: 0 | Q10: 0 | R10: 0 | S10: 0 | T10: 0 | U10: 0 | V10: 0 | W10: 0 | X10: 0 | Y10: 4 | Z10: 0.5 | AA10: 0.5 | AB10: 0 | AC10: 0 | AD10: 4 | AQ10: 0
A11: wheat | B11: quittance of 3 half-virgates of land, of lucy cartere, john schephurde and thomas mauncell', which william wykeham, recently lord bishop of winchester, let at farm by his charter and the confirmation of the chapter to the warden and scholars of the blessed mary and their successors, just as is fully made clear within under the heading of issues through the pestilence, 3 quarters 3 bushels, of which each was accustomed to pay 1 qr 1 bushels for the year. | C11: 0 | D11: 0 | E11: 0 | F11: 0 | G11: 0 | H11: 0 | I11: 0 | J11: 0 | K11: 0 | L11: 0 | M11: 0 | N11: 0 | O11: 0 | P11: 0 | Q11: 0 | R11: 0 | S11: 0 | T11: 0 | U11: 0 | V11: 0 | W11: 0 | AQ11: 0
A12: wheat | B12: default of the churchscot of the land of alice clerk', formerly of john atte mere, now in the lord's hands through the death of the same in the first pestilence, 1 qr 1 bushels. | C12: 0 | D12: 0 | E12: 0 | F12: 0 | G12: 0 | H12: 0 | I12: 0 | J12: 0 | K12: 0 | L12: 0 | M12: 0 | N12: 0 | O12: 0 | P12: 0 | Q12: 0 | R12: 0 | S12: 0 | T12: 0 | U12: 0 | V12: 0 | W12: 0 | AQ12: 0
A13: wheat | B13: default of 4 half-virgates of land, of roger albard', john atte puynde, william hockele and john hockele, in the lord's hands because the said roger, john, william and john surrendered the said lands into the lord's hands and refused to hold them any longer, 4 quarters. | C13: 0 | D13: 0 | E13: 0 | F13: 0 | G13: 0 | H13: 0 | I13: 0 | J13: 0 | K13: 0 | L13: 0 | M13: 0 | N13: 0 | O13: 0 | P13: 0 | Q13: 0 | R13: 0 | S13: 0 | T13: 0 | U13: 0 | V13: 0 | W13: 0 | X13: 4 | Y13: 0 | Z13: 4 | AA13: 4 | AB13: 0 | AC13: 4 | AD13: 0 | AQ13: 0
A14: wheat | B14: liveries of the reeve and smith according to custom in 2 acres as they he, 6 bushels. | C14: 0 | D14: 0 | E14: 0 | F14: 0 | G14: 0 | H14: 0 | I14: 0 | J14: 0 | K14: 0 | L14: 0 | M14: 0 | N14: 0 | O14: 0 | P14: 0 | Q14: 0 | R14: 0 | S14: 0 | T14: 0 | U14: 0 | V14: 0 | W14: 0 | X14: 0 | Y14: 6 | Z14: 0.75 | AA14: 0.75 | AB14: 0 | AC14: 0 | AD14: 6 | AQ14: 0
A15: wheat | B15: sold within, 30 quarters, of which 7 quarters 4 bushels sold to the lord's household.. | C15: 0 | D15: 0 | E15: 0 | F15: 0 | G15: 0 | H15: 0 | I15: 0 | J15: 0 | K15: 0 | L15: 0 | M15: 0 | N15: 0 | O15: 0 | P15: 0 | Q15: 37 | R15: 4 | S15: 37.5 | T15: 0 | U15: 0 | V15: 0 | W15: 0 | X15: 7 | Y15: 4 | Z15: 7.5 | AA15: 30 | AB15: -22.5 | AC15: 30 | AD15: 0 | AE15: 7 | AF15: 4 | AQ15: 0
A16: wheat | B16: sold at the audit, 9 quarters 2 bushels for £3 14 shilling. | C16: 0 | D16: 0 | E16: 0 | F16: 0 | G16: 0 | H16: 0 | I16: 0 | J16: 0 | K16: 0 | L16: 0 | M16: 0 | N16: 0 | O16: 0 | P16: 0 | Q16: 9 | R16: 2 | S16: 9.25 | T16: 0 | U16: 0 | V16: 0 | W16: 0 | X16: 9 | Y16: 2 | Z16: 9.25 | AA16: 9.25 | AB16: 0 | AC16: 9 | AD16: 2 | AQ16: 0
A17: wheat | B17: total as before. | C17: 0 | D17: 0 | E17: 0 | F17: 0 | G17: 0 | H17: 0 | I17: 0 | J17: 0 | K17: 0 | L17: 0 | M17: 0 | N17: 0 | O17: 0 | P17: 0 | Q17: 0 | R17: 0 | S17: 0 | T17: 0 | U17: 0 | V17: 0 | W17: 0 | X17: 0 | Y17: 0 | Z17: 0 | AA17: 0 | AB17: 0 | AC17: 0 | AD17: 0 | AQ17: 0
A18: wheat | B18: it balances. | C18: 0 | D18: 0 | E18: 0 | F18: 0 | G18: 0 | H18: 0 | I18: 0 | J18: 0 | K18: 0 | L18: 0 | M18: 0 | N18: 0 | O18: 0 | P18: 0 | Q18: 0 | R18: 0 | S18: 0 | T18: 0 | U18: 0 | V18: 0 | W18: 0 | X18: 0 | Y18: 0 | Z18: 0 | AA18: 0 | AB18: 0 | AC18: 0 | AD18: 0 | AQ18: 0
A19: wheat | B19: total | C19: 0 | D19: 0 | E19: 0 | F19: 0 | G19: 0 | H19: 0 | I19: 0 | J19: 0 | K19: 0 | L19: 0 | M19: 0 | N19: 0 | O19: 0 | P19: 0 | Q19: 0 | R19: 0 | S19: 0 | T19: 0 | U19: 0 | V19: 0 | W19: 0 | AQ19: 0
A20: curall | B20: and for 1 qr 4 bushels of curall from the issue of the said wheat, threshed by piece-work. | C20: 0 | D20: 0 | E20: 0 | F20: 0 | G20: 0 | H20: 0 | I20: 0 | J20: 0 | K20: 0 | L20: 0 | M20: 0 | N20: 0 | O20: 0 | P20: 0 | Q20: 0 | R20: 0 | S20: 0 | T20: 0 | U20: 0 | V20: 0 | W20: 0 | AQ20: 0
A21: curall | B21: liveries of the manorial servants. | C21: 0 | D21: 0 | E21: 0 | F21: 0 | G21: 0 | H21: 0 | I21: 0 | J21: 0 | K21: 0 | L21: 0 | M21: 0 | N21: 0 | O21: 0 | P21: 0 | Q21: 0 | R21: 0 | S21: 0 | T21: 0 | U21: 0 | V21: 0 | W21: 0 | X21: 0 | Y21: 0 | Z21: 0 | AA21: 0 | AB21: 0 | AC21: 0 | AD21: 0 | AQ21: 0
A22: curall | B22: none remains. | C22: 0 | D22: 0 | E22: 0 | F22: 0 | G22: 0 | H22: 0 | I22: 0 | J22: 0 | K22: 0 | L22: 0 | M22: 0 | N22: 0 | O22: 0 | P22: 0 | Q22: 0 | R22: 0 | S22: 0 | T22: 0 | U22: 0 | V22: 0 | W22: 0 | X22: 0 | Y22: 0 | Z22: 0 | AA22: 0 | AB22: 0 | AC22: 0 | AD22: 0 | AQ22: 0
A23: curall | B23: total | C23: 0 | D23: 0 | E23: 0 | F23: 0 | G23: 0 | H23: 0 | I23: 0 | J23: 0 | K23: 0 | L23: 0 | M23: 0 | N23: 0 | O23: 0 | P23: 0 | Q23: 0 | R23: 0 | S23: 0 | T23: 0 | U23: 0 | V23: 0 | W23: 0 | AQ23: 0
A24: barley | B24: and for 53 quarters 4 bushels from the whole issue, threshed by piece-work. | C24: 0 | D24: 0 | E24: 0 | F24: 0 | G24: 0 | H24: 0 | I24: 0 | J24: 0 | K24: 0 | L24: 0 | M24: 0 | N24: 0 | O24: 0 | P24: 0 | Q24: 0 | R24: 0 | S24: 0 | T24: 53 | U24: 4 | V24: 53.5 | W24: 0 | X24: 53 | Y24: 4 | Z24: 53.5 | AA24: 53.5 | AB24: 0 | AC24: 53 | AD24: 4 | AQ24: 0
A25: barley | B25: 167 quarters 2.5 bushels bought, of which 115 quarters 3 bushels bought from the reeve of hambledon, 6 quarters 6 bushels from the reeve of north waltham, 12 quarters from the reeve of alresford, 12 quarters from the reeve of cheriton, 10 quarters from the reeve of overton, and 11 quarters 1.5 bushels in the market. | C25: 0 | D25: 0 | E25: 0 | F25: 0 | G25: 0 | H25: 333 | I25: 13 | J25: 334.62 | K25: 0 | L25: 0 | M25: 0 | N25: 0 | O25: 0 | P25: 0 | Q25: 0 | R25: 0 | S25: 0 | T25: 0 | U25: 0 | V25: 0 | W25: 0 | X25: 166 | Y25: 10.5 | Z25: 167.31 | AA25: 167.31 | AB25: 0 | AC25: 167 | AD25: 2.5 | AE25: 115 | AF25: 3 | AG25: 6 | AH25: 6 | AI25: 12 | AJ25: 0 | AK25: 12 | AL25: 0 | AM25: 10 | AN25: 0 | AO25: 11 | AP25: 1.5 | AQ25: 0
A26: barley | B26: 8 quarters 5 bushels surcharged so that he answers for a 3.5-fold yield. | C26: 0 | D26: 0 | E26: 0 | F26: 0 | G26: 0 | H26: 0 | I26: 0 | J26: 0 | K26: 0 | L26: 0 | M26: 0 | N26: 0 | O26: 0 | P26: 0 | Q26: 0 | R26: 0 | S26: 0 | T26: 0 | U26: 0 | V26: 0 | W26: 0 | X26: 8 | Y26: 5 | Z26: 8.62 | AA26: 8.62 | AB26: 0 | AC26: 8 | AD26: 5 | AQ26: 0
A27: barley | B27: total, 229 quarters 3.5 bushels sown over 36.5 acres below la northhull' and la bertones and swetecombe, 18 quarters 2 bushels. | C27: 0 | D27: 0 | E27: 247 | F27: 5.5 | G27: 247.69 | H27: 0 | I27: 0 | J27: 0 | K27: 0 | L27: 0 | M27: 0 | N27: 0 | O27: 0 | P27: 0 | Q27: 0 | R27: 0 | S27: 0 | T27: 0 | U27: 0 | V27: 0 | W27: 0 | X27: 18 | Y27: 2 | Z27: 18.25 | AA27: 229.44 | AB27: -211.19 | AC27: 229 | AD27: 3.5 | AE27: 18 | AF27: 2 | AQ27: 0
A28: barley | B28: that is, 4 bushels an acre. | C28: 0 | D28: 0 | E28: 0 | F28: 0 | G28: 0 | H28: 0 | I28: 0 | J28: 0 | K28: 0 | L28: 0 | M28: 0 | N28: 0 | O28: 0 | P28: 0 | Q28: 0 | R28: 0 | S28: 0 | T28: 0 | U28: 0 | V28: 0 | W28: 0 | X28: 0 | Y28: 4 | Z28: 0.5 | AA28: 0.5 | AB28: 0 | AC28: 0 | AD28: 4 | AQ28: 0
A29: barley | B29: liveries of the manorial servants below, 28 quarters 3.5 bushels. | C29: 0 | D29: 0 | E29: 0 | F29: 0 | G29: 0 | H29: 0 | I29: 0 | J29: 0 | K29: 0 | L29: 0 | M29: 0 | N29: 0 | O29: 0 | P29: 0 | Q29: 0 | R29: 0 | S29: 0 | T29: 0 | U29: 0 | V29: 0 | W29: 0 | X29: 28 | Y29: 3.5 | Z29: 28.44 | AA29: 28.44 | AB29: 0 | AC29: 28 | AD29: 3.5 | AQ29: 0
A30: barley | B30: malting below, 174 quarters 1 bushels. | C30: 0 | D30: 0 | E30: 0 | F30: 0 | G30: 0 | H30: 0 | I30: 0 | J30: 0 | K30: 0 | L30: 0 | M30: 0 | N30: 0 | O30: 0 | P30: 0 | Q30: 0 | R30: 0 | S30: 0 | T30: 0 | U30: 0 | V30: 0 | W30: 0 | X30: 174 | Y30: 1 | Z30: 174.12 | AA30: 174.12 | AB30: 0 | AC30: 174 | AD30: 1 | AQ30: 0
A31: barley | B31: sold at the audit, 8 quarters 5 bushels for £2 13 shilling. | C31: 0 | D31: 0 | E31: 0 | F31: 0 | G31: 0 | H31: 0 | I31: 0 | J31: 0 | K31: 0 | L31: 0 | M31: 0 | N31: 0 | O31: 0 | P31: 0 | Q31: 8 | R31: 5 | S31: 8.62 | T31: 0 | U31: 0 | V31: 0 | W31: 0 | X31: 8 | Y31: 5 | Z31: 8.62 | AA31: 8.62 | AB31: 0 | AC31: 8 | AD31: 5 | AQ31: 0
A32: barley | B32: total as before. | C32: 0 | D32: 0 | E32: 0 | F32: 0 | G32: 0 | H32: 0 | I32: 0 | J32: 0 | K32: 0 | L32: 0 | M32: 0 | N32: 0 | O32: 0 | P32: 0 | Q32: 0 | R32: 0 | S32: 0 | T32: 0 | U32: 0 | V32: 0 | W32: 0 | X32: 0 | Y32: 0 | Z32: 0 | AA32: 0 | AB32: 0 | AC32: 0 | AD32: 0 | AQ32: 0
A33: barley | B33: it balances. | C33: 0 | D33: 0 | E33: 0 | F33: 0 | G33: 0 | H33: 0 | I33: 0 | J33: 0 | K33: 0 | L33: 0 | M33: 0 | N33: 0 | O33: 0 | P33: 0 | Q33: 0 | R33: 0 | S33: 0 | T33: 0 | U33: 0 | V33: 0 | W33: 0 | X33: 0 | Y33: 0 | Z33: 0 | AA33: 0 | AB33: 0 | AC33: 0 | AD33: 0 | AQ33: 0
A34: barley | B34: total | C34: 0 | D34: 0 | E34: 0 | F34: 0 | G34: 0 | H34: 0 | I34: 0 | J34: 0 | K34: 0 | L34: 0 | M34: 0 | N34: 0 | O34: 0 | P34: 0 | Q34: 0 | R34: 0 | S34: 0 | T34: 0 | U34: 0 | V34: 0 | W34: 0 | AQ34: 0
A35: oats | B35: and for 33 quarters 3 bushels from the whole issue, threshed by piece-work, besides 6 quarters 7 bushels from the same issue, threshed the preceding year. | C35: 0 | D35: 0 | E35: 0 | F35: 0 | G35: 0 | H35: 0 | I35: 0 | J35: 0 | K35: 0 | L35: 0 | M35: 0 | N35: 0 | O35: 0 | P35: 0 | Q35: 0 | R35: 0 | S35: 0 | T35: 39 | U35: 10 | V35: 40.25 | W35: 0 | X35: 6 | Y35: 7 | Z35: 6.88 | AA35: 33.38 | AB35: -26.5 | AC35: 33 | AD35: 3 | AE35: 6 | AF35: 7 | AQ35: 0
A36: oats | B36: 6 quarters 6 bushels from the issue by estimation in sheaves. | C36: 0 | D36: 0 | E36: 0 | F36: 0 | G36: 0 | H36: 0 | I36: 0 | J36: 0 | K36: 0 | L36: 0 | M36: 0 | N36: 0 | O36: 0 | P36: 0 | Q36: 0 | R36: 0 | S36: 0 | T36: 0 | U36: 0 | V36: 0 | W36: 0 | X36: 6 | Y36: 6 | Z36: 6.75 | AA36: 6.75 | AB36: 0 | AC36: 6 | AD36: 6 | AQ36: 0
A37: oats | B37: 1 qr 1 bushels bought. | C37: 0 | D37: 0 | E37: 0 | F37: 0 | G37: 0 | H37: 0 | I37: 0 | J37: 0 | K37: 0 | L37: 0 | M37: 0 | N37: 0 | O37: 0 | P37: 0 | Q37: 0 | R37: 0 | S37: 0 | T37: 0 | U37: 0 | V37: 0 | W37: 0 | AQ37: 0
A38: oats | B38: 4 quarters 3 bushels surcharged so that he answers for a 3-fold yield.. | C38: 0 | D38: 0 | E38: 0 | F38: 0 | G38: 0 | H38: 0 | I38: 0 | J38: 0 | K38: 0 | L38: 0 | M38: 0 | N38: 0 | O38: 0 | P38: 0 | Q38: 0 | R38: 0 | S38: 0 | T38: 0 | U38: 0 | V38: 0 | W38: 0 | X38: 4 | Y38: 3 | Z38: 4.38 | AA38: 4.38 | AB38: 0 | AC38: 4 | AD38: 3 | AQ38: 0
A39: oats | B39: total, 45 quarters 5 bushels. | C39: 0 | D39: 0 | E39: 0 | F39: 0 | G39: 0 | H39: 0 | I39: 0 | J39: 0 | K39: 0 | L39: 0 | M39: 0 | N39: 0 | O39: 0 | P39: 0 | Q39: 0 | R39: 0 | S39: 0 | T39: 0 | U39: 0 | V39: 0 | W39: 0 | X39: 45 | Y39: 5 | Z39: 45.62 | AA39: 45.62 | AB39: 0 | AC39: 45 | AD39: 5 | AQ39: 0
A40: oats | B40: sown over 35 acres by the perch in tattescombe and reghele, 17 quarters 4 bushels. | C40: 0 | D40: 0 | E40: 17 | F40: 4 | G40: 17.5 | H40: 0 | I40: 0 | J40: 0 | K40: 0 | L40: 0 | M40: 0 | N40: 0 | O40: 0 | P40: 0 | Q40: 0 | R40: 0 | S40: 0 | T40: 0 | U40: 0 | V40: 0 | W40: 0 | X40: 17 | Y40: 4 | Z40: 17.5 | AA40: 17.5 | AB40: 0 | AC40: 17 | AD40: 4 | AQ40: 0
A41: oats | B41: that is, 4 bushels an acre. | C41: 0 | D41: 0 | E41: 0 | F41: 0 | G41: 0 | H41: 0 | I41: 0 | J41: 0 | K41: 0 | L41: 0 | M41: 0 | N41: 0 | O41: 0 | P41: 0 | Q41: 0 | R41: 0 | S41: 0 | T41: 0 | U41: 0 | V41: 0 | W41: 0 | X41: 0 | Y41: 4 | Z41: 0.5 | AA41: 0.5 | AB41: 0 | AC41: 0 | AD41: 4 | AQ41: 0
A42: oats | B42: fodder of the horses of richard wyot, steward, holding the tourns of martinmas and hockday, 4 quarters by bill. | C42: 0 | D42: 0 | E42: 0 | F42: 0 | G42: 0 | H42: 0 | I42: 0 | J42: 0 | K42: 0 | L42: 0 | M42: 0 | N42: 4 | O42: 0 | P42: 4 | Q42: 0 | R42: 0 | S42: 0 | T42: 0 | U42: 0 | V42: 0 | W42: 0 | X42: 4 | Y42: 0 | Z42: 4 | AA42: 4 | AB42: 0 | AC42: 4 | AD42: 0 | AQ42: 0
A43: oats | B43: meal made for the pottage of the manorial servants for the year, 3 quarters. | C43: 0 | D43: 0 | E43: 0 | F43: 0 | G43: 0 | H43: 0 | I43: 0 | J43: 0 | K43: 0 | L43: 0 | M43: 0 | N43: 0 | O43: 0 | P43: 0 | Q43: 0 | R43: 0 | S43: 0 | T43: 0 | U43: 0 | V43: 0 | W43: 0 | X43: 3 | Y43: 0 | Z43: 3 | AA43: 3 | AB43: 0 | AC43: 3 | AD43: 0 | AQ43: 0
A44: oats | B44: given to the oxen and calves, 6 quarters by estimation in sheaves. | C44: 0 | D44: 0 | E44: 0 | F44: 0 | G44: 0 | H44: 0 | I44: 0 | J44: 0 | K44: 0 | L44: 0 | M44: 0 | N44: 0 | O44: 0 | P44: 0 | Q44: 0 | R44: 0 | S44: 0 | T44: 0 | U44: 0 | V44: 0 | W44: 0 | X44: 6 | Y44: 0 | Z44: 6 | AA44: 6 | AB44: 0 | AC44: 6 | AD44: 0 | AQ44: 0
A45: oats | B45: liveries of the reeve and smith in 2 acres as they lie, 6 bushels according to custom. | C45: 0 | D45: 0 | E45: 0 | F45: 0 | G45: 0 | H45: 0 | I45: 0 | J45: 0 | K45: 0 | L45: 0 | M45: 0 | N45: 0 | O45: 0 | P45: 0 | Q45: 0 | R45: 0 | S45: 0 | T45: 0 | U45: 0 | V45: 0 | W45: 0 | X45: 0 | Y45: 6 | Z45: 0.75 | AA45: 0.75 | AB45: 0 | AC45: 0 | AD45: 6 | AQ45: 0
A46: oats | B46: fodder of the cart-horses at both sowings, 5 quarters.. | C46: 0 | D46: 0 | E46: 0 | F46: 0 | G46: 0 | H46: 0 | I46: 0 | J46: 0 | K46: 0 | L46: 0 | M46: 0 | N46: 5 | O46: 0 | P46: 5 | Q46: 0 | R46: 0 | S46: 0 | T46: 0 | U46: 0 | V46: 0 | W46: 0 | X46: 5 | Y46: 0 | Z46: 5 | AA46: 5 | AB46: 0 | AC46: 5 | AD46: 0 | AQ46: 0
A47: oats | B47: sold at the audit, 9 quarters 3 bushels for £1 7 shilling 9pence. | C47: 0 | D47: 0 | E47: 0 | F47: 0 | G47: 0 | H47: 0 | I47: 0 | J47: 0 | K47: 0 | L47: 0 | M47: 0 | N47: 0 | O47: 0 | P47: 0 | Q47: 9 | R47: 3 | S47: 9.38 | T47: 0 | U47: 0 | V47: 0 | W47: 0 | X47: 9 | Y47: 3 | Z47: 9.38 | AA47: 9.38 | AB47: 0 | AC47: 9 | AD47: 3 | AQ47: 0
A48: oats | B48: total as before. | C48: 0 | D48: 0 | E48: 0 | F48: 0 | G48: 0 | H48: 0 | I48: 0 | J48: 0 | K48: 0 | L48: 0 | M48: 0 | N48: 0 | O48: 0 | P48: 0 | Q48: 0 | R48: 0 | S48: 0 | T48: 0 | U48: 0 | V48: 0 | W48: 0 | X48: 0 | Y48: 0 | Z48: 0 | AA48: 0 | AB48: 0 | AC48: 0 | AD48: 0 | AQ48: 0
A49: oats | B49: it balances. | C49: 0 | D49: 0 | E49: 0 | F49: 0 | G49: 0 | H49: 0 | I49: 0 | J49: 0 | K49: 0 | L49: 0 | M49: 0 | N49: 0 | O49: 0 | P49: 0 | Q49: 0 | R49: 0 | S49: 0 | T49: 0 | U49: 0 | V49: 0 | W49: 0 | X49: 0 | Y49: 0 | Z49: 0 | AA49: 0 | AB49: 0 | AC49: 0 | AD49: 0 | AQ49: 0

Sheet Issues of the Grange
A1: Gross Output | B1: Bought Only Aggregated | C1: Account Quarters | D1: Account Bushels | E1: Account Total Quarters | F1: Bought in Quarters | G1: Bought in Bushels | H1: Total Bought Quarters | I1: Sold Quarters | J1: Sold Bushels | K1: Sold Total Quarters | L1: Total Corn Quantity | M1: Difference Produced+Bought-Sold | N1: Weighted Average Price per Quarter | O1: Non-Weighted Average Price per Quarter | P1: Value of Total Production weighted | Q1: Value of Total Production unweighted
A2: and he owes | B2: 0 | C2: 0 | D2: 0 | E2: 0 | F2: 0 | G2: 0 | H2: 0 | I2: 0 | J2: 0 | K2: 0 | L2: 0 | M2: 0
A3: wheat | B3: 0 | C3: 30 | D3: 4 | E3: 30.5 | F3: 0 | G3: 0 | H3: 0 | I3: 37 | J3: 4 | K3: 37.5 | L3: 30.5 | M3: -7 | N3: 0.47 | O3: 0.48 | P3: 14.37 | Q3: 14.74
A4: curall | B4: 0 | C4: 0 | D4: 0 | E4: 0 | F4: 0 | G4: 0 | H4: 0 | I4: 0 | J4: 0 | K4: 0 | L4: 0 | M4: 0
A5: barley | B5: 0 | C5: 53 | D5: 4 | E5: 53.5 | F5: 0 | G5: 13 | H5: 0 | I5: 8 | J5: 5 | K5: 8.62 | L5: 53.5 | M5: 44.88
A6: oats | B6: 0 | C6: 39 | D6: 10 | E6: 40.25 | F6: 0 | G6: 0 | H6: 0 | I6: 9 | J6: 3 | K6: 9.38 | L6: 40.25 | M6: 30.88
A7: Mancorn | B7: 0 | C7: 0 | D7: 0 | E7: 0 | F7: 0 | G7: 0 | H7: 0 | I7: 0 | J7: 0 | K7: 0 | L7: 0 | M7: 0
A8: Maslin | B8: 0 | C8: 0 | D8: 0 | E8: 0 | F8: 0 | G8: 0 | H8: 0 | I8: 0 | J8: 0 | K8: 0 | L8: 0 | M8: 0
A9: First-grade malt | B9: 0 | C9: 0 | D9: 0 | E9: 0 | F9: 0 | G9: 0 | H9: 0 | I9: 0 | J9: 0 | K9: 0 | L9: 0 | M9: 0
A10: Second-grade malt | B10: 0 | C10: 0 | D10: 0 | E10: 0 | F10: 0 | G10: 0 | H10: 0 | I10: 0 | J10: 0 | K10: 0 | L10: 0 | M10: 0
A11: Peas | B11: 0 | C11: 0 | D11: 0 | E11: 0 | F11: 0 | G11: 0 | H11: 0 | I11: 0 | J11: 0 | K11: 0 | L11: 0 | M11: 0
A12: Oatmeal | B12: 0 | C12: 0 | D12: 0 | E12: 0 | F12: 0 | G12: 0 | H12: 0 | I12: 0 | J12: 0 | K12: 0 | L12: 0 | M12: 0
A13: Vetches | B13: 0 | C13: 0 | D13: 0 | E13: 0 | F13: 0 | G13: 0 | H13: 0 | I13: 0 | J13: 0 | K13: 0 | L13: 0 | M13: 0
A14: Rye | B14: 0 | C14: 0 | D14: 0 | E14: 0 | F14: 0 | G14: 0 | H14: 0 | I14: 0 | J14: 0 | K14: 0 | L14: 0 | M14: 0
A15: Dredge | B15: 0 | C15: 0 | D15: 0 | E15: 0 | F15: 0 | G15: 0 | H15: 0 | I15: 0 | J15: 0 | K15: 0 | L15: 0 | M15: 0
A16: Malt | B16: 0 | C16: 0 | D16: 0 | E16: 0 | F16: 0 | G16: 0 | H16: 0 | I16: 0 | J16: 0 | K16: 0 | L16: 0 | M16: 0 | N16: 0.29 | O16: 0.28 | P16: 0 | Q16: 0
A17: Meal | B17: 0 | C17: 0 | D17: 0 | E17: 0 | F17: 0 | G17: 0 | H17: 0 | I17: 0 | J17: 0 | K17: 0 | L17: 0 | M17: 0

Sheet Sale of Corn Prices
A1: Heading | B1: Sentence | C1: Total in Pounds | D1: Pounds | E1: Shillings | F1: Pence | G1: Corn | H1: Total Quarters Except 1 | I1: Total Bushels Except 1 | J1: Total Corn Cross-Check | K1: Total Corn Manorial Account | L1: Corn Quantity Error | M1: Quarters 0 | N1: Bushels 0 | O1: shilling a quarter 1 | P1: pence a quarter 1 | Q1: Quarters 1 | R1: Bushels 1 | S1: shilling a quarter 2 | T1: pence a quarter 2 | U1: Quarters 2 | V1: Bushels 2 | W1: shilling a quarter 3 | X1: pence a quarter 3 | Y1: Quarters 3 | Z1: Bushels 3 | AA1: shilling a quarter 4 | AB1: pence a quarter 4 | AC1: Quarters 4 | AD1: Bushels 4 | AE1: Quarters 5 | AF1: Bushels 5 | AG1: Quarters 6 | AH1: Bushels 6 | AI1: £ a quarter 1 | AJ1: £ a quarter 2 | AK1: £ a quarter 3 | AL1: £ a quarter 4 | AM1: Quarters Sold | AN1: Weighted Average Price per Quarter | AO1: Non-Weighted Average Price per Quarter | AP1: Corn lowercase
A2: sale of corn and malt | B2: and for £14 7 shilling 11.75pence1 from 30 quarters of wheat sold, of which 7 quarters 4 bushels sold to the lord's household for £3 10 shilling, at 9 shilling 4pence a quarters, 1 quarters 1 bushels to the guardians of john coupere until he should come of age for 3 shilling 9pence, and 21 quarters 3 bushels per mutuum for £10 13 shilling 9pence, at 10 shilling a quarters. | C2: 14.4 | D2: 14 | E2: 7 | F2: 11.75 | G2: wheat | H2: 29 | I2: 8 | J2: 30 | K2: 30 | L2: 0 | M2: 30 | N2: 0 | O2: 9 | P2: 4 | Q2: 7 | R2: 4 | S2: 10 | T2: 0 | U2: 1 | V2: 1 | Y2: 21 | Z2: 3 | AI2: 0.47 | AJ2: 0.5 | AM2: 30 | AN2: 0.47 | AO2: 0.48 | AP2: wheat
A3: sale of corn and malt | B3: £50 14 shilling from 174 quarters of malt sold to the lord's household, at 6 shilling a quarters for 144 quarters, or £43 4 shilling, and 5 shilling a quarters for 30 quarters, or £7 10 shilling. | C3: 50.7 | D3: 50 | E3: 14 | F3: 0 | G3: malt | H3: 174 | I3: 0 | J3: 174 | K3: 174 | L3: 0 | M3: 174 | N3: 0 | O3: 6 | P3: 0 | Q3: 144 | R3: 0 | S3: 5 | T3: 0 | U3: 30 | V3: 0 | AI3: 0.3 | AJ3: 0.25 | AM3: 174 | AN3: 0.29 | AO3: 0.28 | AP3: malt
A4: sale of corn and malt | B4: total, £65 1 shilling 11.75pence. | C4: 65.1 | D4: 65 | E4: 1 | F4: 11.75 | H4: 0 | I4: 0 | J4: 0 | K4: 0 | L4: 0 | M4: 0 | N4: 0 | AI4: inf | AM4: 0 | AN4: inf | AO4: inf
