Workbook

Sheet Overview
A1: BISHOPSTONE OVERVIEW - COMPLETED | B1: Total in £ | C1: Error | D1: Note
A2: CASH ACCOUNT
A3: RECEIPTS
A4: Arrears total | B4: 0.51
A5: Rents of assize total | B5: 12.38
A6: Quittances total
A7: Defaults of rent total | B7: 1.61
A8: Defaults of rent through the pestilence total
A9: Cotlands defaults total
A10: Cotlands total
A11: Total of quittances and defaults of rent total | B11: 12.38
A12: Total of rents remaining clear total
A13: Farms total
A14: Annual recognizances total
A15: Issues of the Manor total | B15: 8.79
A16: Issues of the tenements in the lord's hands total
A17: Sale of labour services total
A18: Sale of corn total | B18: 32.83
A19: Entry and marriage fines total
A20: Pleas & perquisites total | B20: 1.15
A21: Forfeited chattels total
A22: Farm of the demesne land total
A23: Total of all receipts (calculated here) | B23: =SUM(B5:B11) -> 26.37
A24: Total of all receipts (calculated here) incl arrears | B24: =SUM(B4:B11) -> 26.88
A25: Total recorded in the accounts excl. arrears | B25: =Receipts!F73 -> 79.19 | C25: =B23-B25 -> -52.82
A26: Total recorded in the accounts incl. arrears | B26: =Receipts!F74 -> 79.7
A29: EXPENSES
A30: Cost of ploughs total | B30: 2.39
A31: Purchase of corn total
A32: Cost of carts and wagons total | B32: 0.58
A33: Cost of dairy total
A34: Purchase of stock total | B34: 2.74
A35: Sheepcote total
A36: Cost of buildings total | B36: 0.74
A37: Threshing total | B37: 1.87
A38: Barley expenses
A39: Expenses of the harvest total | B39: 5.08
A40: Necessary expenses
A41: Wages of the bailiff
A42: Steward's expenses total | B42: 0.45
A43: Annual fees
A44: Total of all expenses per account | B44: =Expenses!F82 -> 18.79
A45: Total of all expenses (calculated here) | B45: =Expenses!F83 -> 14.02
A46: Total fixed investment | B46: 3.33
A47: Total Demesne fixed investment | B47: 0.59
A49: Owed by the reeve | B49: =B23-B45 -> 12.35
A50: From accounts | B50: 62.78
A52: Allowances | B52: =Expenses!F80-Expenses!F78 -> 4.75
A53: Cash deliveries | B53: 57.51
A54: Sum of the above | B54: =SUM(B52:B53) -> 62.26
A55: Total of all allowances and cash deliveries in accounts | B55: =Expenses!F80 -> 62.26
A57: Net amount owed | B57: =B50-B54 -> 0.52
A58: Net amount owed in accounts
A60: GRANGE ACCOUNT | B60: Total Production | D60: Value of total gross production in £ | E60: Value of total net production in £
A61: Grange | B61: qrs | C61: bus
A62: Wheat | B62: 49 | C62: 1 | D62: 23.77 | E62: 23.77
A63: Rye | B63: 0 | C63: 0 | E63: 0
A64: Dredge | B64: 0 | C64: 0 | E64: 0
A65: Curall | B65: 0 | C65: 0 | D65: 0 | E65: 0
A66: Barley | B66: 106 | C66: 1 | D66: 31.84 | E66: 31.84
A67: Oats | B67: 20 | C67: 4 | D67: 3.42 | E67: 3.42
A68: Beans | B68: 0 | C68: 0 | D68: 0 | E68: 0
A69: Peas | B69: 0 | C69: 0 | D69: 0 | E69: 0
A70: Vetches | B70: 0 | C70: 0 | D70: 0 | E70: 0
A71: Total value of gross production (sum of the above) | E71: =SUM(D62:D70) -> 59.03
A72: Total value of net production | E72: =SUM(E62:E70) -> 59.03
A73: Value of sales | E73: 31.6647
A75: MILL ACCOUNT | B75: Total Production | D75: Total in £
A76: Issues of the mill | B76: qrs | C76: bus
A77: Wheat
A78: Oatmeal
A79: 1st grade malt
A80: 2nd grade malt
A81: Maslin
A82: Total value of production (sum of the above)
A83: Value of sales
A85: STOCK ACCOUNT
A86: Livestock | B86: Begin stock | C86: End stock | D86: Stockbuilding | F86: Value of stock in £ | G86: Value of stockbuilding
A87: Cart-horses | B87: 0 | C87: =Stock!L5 -> 0 | D87: =C87-B87 -> 0 | F87: =Stock!L5*Stock!O5 -> 0 | G87: =D87*Stock!O5 -> 0
A88: Mares | B88: 0 | C88: =Stock!L6 -> 0 | D88: =C88-B88 -> 0 | F88: =Stock!L6*Stock!O6 -> 0 | G88: =D88*Stock!O6 -> 0
A89: Plough horses | B89: 2 | C89: =Stock!L7 -> 2 | D89: =C89-B89 -> 0 | F89: =Stock!L7*Stock!O7 -> 0 | G89: =D89*Stock!O7 -> 0
A90: Colts (2 years) | B90: 0 | C90: =Stock!L9 -> 0 | D90: =C90-B90 -> 0 | F90: =Stock!L9*Stock!O9 -> 0 | G90: =D90*Stock!O9 -> 0
A91: Colts (2 years) | B91: 0 | C91: =Stock!L9 -> 0 | D91: =C91-B91 -> 0 | F91: =Stock!L9*Stock!O9 -> 0 | G91: =D91*Stock!O9 -> 0
A92: Colts (1 year) | B92: 0 | C92: =Stock!L10 -> 0 | D92: =C92-B92 -> 0 | F92: =Stock!L10*Stock!O10 -> 0 | G92: =D92*Stock!O10 -> 0
A93: Foals | B93: 0 | C93: =Stock!L11 -> 0 | D93: =C93-B93 -> 0 | F93: =Stock!L11*Stock!O11 -> 0 | G93: =D93*Stock!O11 -> 0
A94: Oxen | B94: 19 | C94: =Stock!L12 -> 18 | D94: =C94-B94 -> -1 | F94: =Stock!L12*Stock!O12 -> 7.98 | G94: =D94*Stock!O12 -> -0.44333333
A95: Bulls | B95: 0 | C95: =Stock!L13 -> 0 | D95: =C95-B95 -> 0 | F95: =Stock!L13*Stock!O13 -> 0 | G95: =D95*Stock!O13 -> 0
A96: Cows | B96: 2 | C96: =Stock!L14 -> 2 | D96: =C96-B96 -> 0 | F96: =Stock!L14*Stock!O14 -> 0 | G96: =D96*Stock!O14 -> 0
A97: Steers | B97: 2 | C97: =Stock!L15 -> 1 | D97: =C97-B97 -> -1 | F97: =Stock!L15*Stock!O15 -> 0.14583333 | G97: =D97*Stock!O15 -> -0.14583333
A98: Bullocks | B98: 2 | C98: =Stock!L16 -> 2 | D98: =C98-B98 -> 0 | F98: =Stock!L16*Stock!O16 -> 0 | G98: =D98*Stock!O16 -> 0
A99: Yearlings | B99: 2 | C99: =Stock!L17 -> 2 | D99: =C99-B99 -> 0 | F99: =Stock!L17*Stock!O17 -> 0 | G99: =D99*Stock!O17 -> 0
A100: Calves | B100: 2 | C100: =Stock!L18 -> 4 | D100: =C100-B100 -> 2 | F100: =Stock!L18*Stock!O18 -> 0 | G100: =D100*Stock!O18 -> 0
A101: Wethers | B101: 354 | C101: =Stock!L19 -> 319 | D101: =C101-B101 -> -35 | F101: =Stock!L19*Stock!O19 -> 26.613714 | G101: =D101*Stock!O19 -> -2.92
A102: Rams | B102: 9 | C102: =Stock!L20 -> 8 | D102: =C102-B102 -> -1 | F102: =Stock!L20*Stock!O20 -> 0.54254545 | G102: =D102*Stock!O20 -> -0.067818182
... A112: Peacocks | B112: 0 | C112: =Stock!L30 -> 0 | D112: =C112-B112 -> 0 | F112: =Stock!L30*Stock!O30 -> 0 | G112: =D112*Stock!O30 -> 0
A113: Total value of stock (sum of the above) | F113: =SUM(F87:F112) -> 68.052945 | G113: =SUM(G87:G112) -> 1.0736402
A114: Total value of production | F114: =SUM(Stock!T5:T30) -> 9.7972917
A115: Value of sales | F115: =SUM(Stock!R5:R30) -> 8.51
A117: Wool | B117: Begin stock | C117: End stock | D117: Stockbuilding | F117: Value of stock in £
A118: Fleeces | B118: 0 | C118: 0 | D118: 0
...

Sheet Receipts
A1: BISHOPSTONE RECEIPTS
A2: Heading | B2: £ | C2: s | D2: d | F2: Total in £ | G2: Error | H2: Notes | I2: Own notes
A3: Arrears | B3: 0 | C3: 10 | D3: 3 | F3: 0.51 | H3: John Algar', reeve there, answers for 10 shilling 3pence of arrears from his last account of the preceding year.
A4: Arrears | B4: 0 | C4: 10 | D4: 3 | F4: 0.51 | H4: Total, 10 shilling 3pence.
A5: Arrears total | F5: 0.51 | G5: 0 | H5: Total
A7: Rents | B7: 12 | C7: 7 | D7: 8 | F7: 12.38 | H7: And for £12 7 shilling 8pence for all rents of assize, or £3 1 shilling 11pence at each of the terms of Christmas, Easter (23 March), the Nativity of St John the Baptist (24 June) and Michaelmas (29 September).
A8: Rents | B8: 12 | C8: 7 | D8: 8 | F8: 12.38 | H8: Total, £12 7 shilling 8pence.
A9: Rents total | F9: 12.38 | G9: 0 | H9: Total
A11: Defaults of rent | B11: 0 | C11: 0 | D11: 6 | F11: 0.03 | H11: In default of 1 plot of land which formerly belonged to the vicar of Bishopstone 6pence.
A12: Defaults of rent | B12: 0 | C12: 4 | D12: 6 | F12: 0.23 | H12: 1 virgate of land formerly of John Salisbury in Netton because in the lord's hands, 4 shilling 6pence for the year.
A13: Defaults of rent | B13: 1 | C13: 2 | D13: 0 | F13: 1.1 | H13: 1 half-virgate of land formerly of Gunnora Burgeys, 1 half-virgate of land formerly of Adam Berewyke, 1 half-virgate of land formerly of Richard Dryvere, 1 half-virgate of land formerly of John Holm', 1 half-virgate of land formerly of John Salisbury, 1 half-virgate formerly of William Hardyng', 1 half-virgate of land formerly of Robert Cryor' and 1 half-virgate of land formerly of John Deyman' in Bishopstone because in the lord's hands, £1 2 shilling for the year, or 2 shilling 9pence for each half-virgate.
A14: Defaults of rent | B14: 0 | C14: 5 | D14: 0 | F14: 0.25 | H14: the holding formerly of Andrew Vicar' of Bishopstone there because in the lord's hands, 5 shilling for the year.
A15: Defaults of rent | B15: 1 | C15: 12 | D15: 0 | F15: 1.6 | H15: Total, £1 12 shilling.
A16: Defaults of rent total | F16: 1.61 | G16: 0.01 | H16: Total
A18: Total of quittances and defaults of rent | B18: 1 | C18: 16 | D18: 0 | F18: 1.8 | H18: Total of quittances and defaults of rent, £1 16 shilling.
A19: Total of quittances and defaults of rent | B19: 10 | C19: 11 | D19: 8 | F19: 10.58 | H19: Total of rents remaining clear, £10 11 shilling 8pence.
A20: Total of quittances and defaults of rent total | F20: 12.38 | G20: 0 | H20: Total
A22: Issues of the manor | B22: 0 | C22: 3 | D22: 1 | F22: 0.15 | H22: And for 3 shilling from the pannage of pigs at Martinmas, at 1pence a pig over a year old, and .5pence below.
A23: Issues of the manor | B23: 0 | C23: 1 | D23: 9.25 | F23: 0.09 | H23: 1 shilling 9.25pence from the agistment of oxen, cows and 2-year old bullocks, at 2.5pence an ox and 1.25pence a bullock.
A24: Issues of the manor | B24: 0 | C24: 1 | D24: 5.5 | F24: 0.07 | H24: 1 shilling 5.5pence from the herbage of sheep in the lord's fold this year.
A25: Issues of the manor | B25: 0 | C25: 1 | D25: 6.75 | F25: 0.08 | H25: 1 shilling 6.75pence from the herbage of oxen, cows and bullocks at Hockday this year.
A26: Issues of the manor | B26: 0 | C26: 0 | D26: 0 | F26: 0 | H26: nothing from the sale of old hay this year.
A27: Issues of the manor | B27: 4 | C27: 15 | D27: 0 | F27: 4.75 | H27: £4 15 shilling from new hay sold this year.
A28: Issues of the manor | B28: 0 | C28: 4 | D28: 8 | F28: 0.23 | H28: 4 shilling 8pence from the residue of Peter's pence.
A29: Issues of the manor | B29: 0 | C29: 0 | D29: 6 | F29: 0.03 | H29: 6pence from 3 lb of wool locks sold.
A30: Issues of the manor | B30: 0 | C30: 5 | D30: 0 | F30: 0.25 | H30: 5 shilling from the milking of 2 cows.
A31: Issues of the manor | B31: 0 | C31: 0 | D31: 0 | F31: 0 | H31: nothing from the milking of the ewes this year because they were not in milk.
A32: Issues of the manor | B32: 0 | C32: 4 | D32: 8 | F32: 0.23 | H32: 4 shilling 8pence from the woolskins sold of 10 wethers, 10 ewes and 4 hoggs in murrain before shearing, at 3pence a skin of wethers, 2pence of ewes and 1.5pence of hoggs.
A33: Issues of the manor | B33: 0 | C33: 1 | D33: 2 | F33: 0.06 | H33: 1 shilling 2pence from the bare skins sold of 7 wethers and 7 ewes in murrain after shearing, at 1pence a skin.
... A45: Issues of the manor | B45: 8 | C45: 16 | D45: 1 | F45: 8.8 | H45: Total, £8 16 shilling 1pence.
A46: Issues of the manor total | F46: 8.79 | G46: -0.01 | H46: Total
A48: Sale of corn | B48: 17 | C48: 16 | D48: 3.75 | F48: 17.82 | H48: And for £17 16 shilling 3.75pence from 36 quarters 6.5 bushels of wheat sold, at 10 shilling a qr for 25 quarters per mutuum, and 9 shilling a qr for 11 quarters 6.5 bushels in the market.
A49: Sale of corn | B49: 1 | C49: 4 | D49: 0 | F49: 1.2 | H49: £1 4 shilling from 4 quarters of curall sold.
A50: Sale of corn | B50: 11 | C50: 8 | D50: 9 | F50: 11.44 | H50: £11 8 shilling 9pence from 38 quarters 1 bushels of barley sold per mutuum, at 6 shilling a qr.
A51: Sale of corn | B51: 0 | C51: 15 | D51: 5 | F51: 0.77 | H51: 15 shilling 5pence from 4 quarters 5 bushels of oats sold per mutuum, at 3 shilling 4pence a qr.
A52: Sale of corn | B52: 0 | C52: 14 | D52: 4 | F52: 0.72 | H52: 14 shilling from 2 quarters 5 bushels of peas sold, at 5 shilling 4pence a qr.
A53: Sale of corn | B53: 0 | C53: 17 | D53: 6 | F53: 0.88 | H53: 17 shilling 6pence from 3 quarters 3 bushels' of vetches sold, at 5 shilling a qr.
A54: Sale of corn | B54: 32 | C54: 15 | D54: 11.75 | F54: 32.8 | H54: Total, £32 15 shilling 11.75pence.
A55: Sale of corn total | F55: 32.83 | G55: 0.03 | H55: Total
A57: Sale of stock | B57: 1 | C57: 6 | D57: 8 | F57: 1.33 | H57: And for £1 6 shilling 8pence from 2 kebb oxen sold.
A58: Sale of stock | B58: 0 | C58: 8 | D58: 0 | F58: 0.4 | H58: 8 shilling from 1 feeble ox sold.
A59: Sale of stock | B59: 0 | C59: 7 | D59: 0 | F59: 0.35 | H59: 7 shilling from 1 steer sold because feeble and useless for the lord's stock.
A60: Sale of stock | B60: 2 | C60: 18 | D60: 4 | F60: 2.92 | H60: £2 18 shilling 4pence from 35 kebb wethers sold before shearing, at 1 shilling 8pence each.
A61: Sale of stock | B61: 3 | C61: 14 | D61: 8 | F61: 3.73 | H61: £3 14 shilling 8pence from 1 ram and 55 kebb ewes sold before shearing, at 1 shilling 4pence each.
A62: Sale of stock | B62: 0 | C62: 10 | D62: 7.5 | F62: 0.53 | H62: 10 shilling from 16 lambs removed from stock and sold before shearing, at 7.5pence each.
A63: Sale of stock | B63: 0 | C63: 7 | D63: 4 | F63: 0.37 | H63: 7 shilling 4pence from 22 geese sold, at 4pence each.
A64: Sale of stock | B64: 0 | C64: 8 | D64: 4 | F64: 0.42 | H64: 8 shilling from 24 capons sold, at 4pence each.
A65: Sale of stock | B65: 10 | C65: 0 | D65: 0 | F65: 10 | H65: Total, £10..
A66: Sale of stock total | F66: 10.05 | G66: 0.05 | H66: Total
A68: Perquisites | B68: 0 | C68: 2 | D68: 10 | F68: 0.14 | H68: And for 2 shilling 10pence from the perquisites of the tourn of Martinmas (11 November).
A69: Perquisites | B69: 0 | C69: 0 | D69: 2 | F69: 0.01 | H69: 1 1 s. 2pence from the perquisites of the courts held by the bailiff between Michaelmas and the tourn of Hockday.
A70: Perquisites | B70: 0 | C70: 1 | D70: 10 | F70: 0.09 | H70: 1 shilling 10pence from the perquisites of the tourn of Hockday (1 April).
A71: Perquisites | B71: 0 | C71: 7 | D71: 1 | F71: 0.35 | H71: 7 shilling 1pence from the perquisites of the courts held by the bailiff after the tourn of Hockday.
A72: Perquisites total | B72: 1 | C72: 2 | D72: 11 | F72: 1.15 | G72: 0.8 | H72: Total, £1 2 shilling 11pence.
A73: Total of all receipts recorded in accounts (calculated here) | F73: =SUMIF(A1:A72,"* total",F1:F72)-SUMIF(A1:A72,"Arrears total",F1:F72) -> 79.19
A74: Total of all receipts (calculated here) incl arrears | F74: =F73+SUMIF(A1:A72,"Arrears total",F1:F72) -> 79.7

Sheet Expenses
A1: BISHOPSTONE EXPENSES
A2: Heading | B2: £ | C2: s | D2: d | F2: Total in £ | G2: Error | H2: Sentence | I2: Fixed Investments | J2: Demesne Fixed Investments
A4: Cost of ploughs | B4: 0 | C4: 16 | D4: 0 | F4: 0.8 | H4: In iron and steel bought for the ironwork of 2 ploughs for the year with the stipend of the smith 16 shilling.
A5: Cost of ploughs | B5: 0 | C5: 4 | D5: 0 | F5: 0.2 | H5: shoeing 18 oxen 4 shilling.
A6: Cost of ploughs | B6: 0 | C6: 0 | D6: 10 | F6: 0.04 | H6: 2 plough feet bought 10pence.
A7: Cost of ploughs | B7: 0 | C7: 0 | D7: 6 | F7: 0.03 | H7: mending iron rings, crooks and staples 6pence.
A8: Cost of ploughs | B8: 0 | C8: 0 | D8: 8 | F8: 0.03 | H8: 1 pair of wheels bought for the ploughs 8pence.
A9: Cost of ploughs | B9: 0 | C9: 1 | D9: 6 | F9: 0.08 | H9: 1 ploughshare bought 1 shilling 6pence.
A10: Cost of ploughs | B10: 0 | C10: 0 | D10: 6 | F10: 0.03 | H10: 3 yokes bought 6pence.
A11: Cost of ploughs | B11: 0 | C11: 1 | D11: 4 | F11: 0.07 | H11: reinforcing and lengthening the iron teeth of 2 harrows 1 shilling 4pence.
A12: Cost of ploughs | B12: 0 | C12: 6 | D12: 8 | F12: 0.33 | H12: stipend of 1 oxherd for the year 6 shilling 8pence.
A13: Cost of ploughs | B13: 0 | C13: 13 | D13: 4 | F13: 0.67 | H13: stipend of 2 drovers for the year 13 shilling 4pence.
A14: Cost of ploughs | B14: 0 | C14: 2 | D14: 2 | F14: 0.11 | H14: payment to the customary tenants for ploughing 14 acres according to custom 2 shilling 2pence, at 2pence an acre.
A15: Cost of ploughs | B15: 2 | C15: 7 | D15: 6 | F15: 2.38 | H15: Total, £2 7 shilling 6pence.
A16: Cost of ploughs total | F16: 2.39 | G16: 0.01 | H16: Total
A18: Cost of carts | B18: 0 | C18: 0 | D18: 10 | F18: 0.04 | H18: In 4 clouts with nails bought for the cart 10pence.
A19: Cost of carts | B19: 0 | C19: 0 | D19: 2 | F19: 0.01 | H19: 2 halters bought 2pence.
A20: Cost of carts | B20: 0 | C20: 0 | D20: 4 | F20: 0.02 | H20: grease bought for the cart 4pence.
A21: Cost of carts | B21: 0 | C21: 0 | D21: 4 | F21: 0.02 | H21: white leather bought 4pence.
A22: Cost of carts | B22: 0 | C22: 0 | D22: 2 | F22: 0.01 | H22: fitting the cart with axles 2pence.
A23: Cost of carts | B23: 0 | C23: 3 | D23: 0 | F23: 0.15 | H23: shoeing 2 plough-horses for the year 3 shilling.
A24: Cost of carts | B24: 0 | C24: 6 | D24: 8 | F24: 0.33 | H24: stipend of 1 carter for the year 6 shilling 8pence.
A25: Cost of carts | B25: 0 | C25: 11 | D25: 6 | F25: 0.58 | H25: Total, 11 shilling 6pence.
A26: Cost of carts total | F26: 0.58 | G26: 0 | H26: Total
A28: Purchase of stock | B28: 1 | C28: 6 | D28: 0 | F28: 1.3 | H28: In 2 oxen bought £1 6 shilling' 8pence. | I28: 1.3 | J28: 0
A29: Purchase of stock | B29: 1 | C29: 8 | D29: 9 | F29: 1.44 | H29: 23 lambs before shearing £1 8 shilling 9pence, at 1 shilling 3pence each. | I29: 1.44 | J29: 0
A30: Purchase of stock | B30: 2 | C30: 15 | D30: 5 | F30: 2.77 | H30: Total, £2 15 shilling 5pence.
A31: Purchase of stock total | F31: 2.74 | G31: -0.03 | H31: Total
A33: Cost of the dairy | B33: 0 | C33: 1 | D33: 0 | F33: 0.05 | H33: In 2 bushels of salt bought for the pottage of the manorial servants and the dairy for the year 1 shilling.
A34: Cost of the dairy | B34: 0 | C34: 0 | D34: 2 | F34: 0.01 | H34: rennet bought 2pence.
A35: Cost of the dairy | B35: 0 | C35: 0 | D35: 2 | F35: 0.01 | H35: linen cloth bought for wrapping cheese 2pence.
A36: Cost of the dairy | B36: 0 | C36: 2 | D36: 0 | F36: 0.1 | H36: stipend of 1 dairymaid for the year 2 shilling.
A37: Cost of the dairy | B37: 0 | C37: 3 | D37: 4 | F37: 0.17 | H37: Total, 3 shilling 4pence.
A38: Cost of the dairy total | F38: 0.17 | G38: 0 | H38: Total
A40: Cost of buildings | B40: 0 | C40: 1 | D40: 10 | F40: 0.09 | H40: In hiring 1 thatcher to roof the barn for 5.5 days 1 shilling 10pence, taking 4pence a day. | I40: 0 | J40: 0
A41: Cost of buildings | B41: 0 | C41: 6 | D41: 10 | F41: 0.34 | H41: underwood bought to make hedges in various places and hurdles for the lord's fold 6 shilling 10pence. | I41: 0.34 | J41: 0.34
A42: Cost of buildings | B42: 0 | C42: 1 | D42: 0 | F42: 0.05 | H42: 1 sack bought 1 shilling. | I42: 0 | J42: 0
A43: Cost of buildings | B43: 0 | C43: 2 | D43: 4 | F43: 0.12 | H43: hiring 1 man to dig 1 ditch at the eastern end of Estmede and plant seedlings there and to cut down other quickset hedge and enclose there for 7 days 2 shilling 4pence, taking 4pence a day. | I43: 0.12 | J43: 0.12
A44: Cost of buildings | B44: 0 | C44: 0 | D44: 5 | F44: 0.02 | H44: 1 sieve and 1 riddle bought 5pence. | I44: 0.02 | J44: 0
A45: Cost of buildings | B45: 0 | C45: 1 | D45: 8 | F45: 0.08 | H45: payment to the customary tenants for carrying 44 quarters of corn to market 1 shilling 8pence, at .5pence a qr. | I45: 0 | J45: 0
A46: Cost of buildings | B46: 0 | C46: 0 | D46: 4 | F46: 0.02 | H46: nails bought for mending the door of the pinfold and the doors of other buildings 4pence. | I46: 0 | J46: 0
A47: Cost of buildings | B47: 0 | C47: 0 | D47: 5 | F47: 0.02 | H47: 1 wheel bought for the barrow 5pence. | I47: 0.02 | J47: 0
A48: Cost of buildings | B48: 0 | C48: 15 | D48: 0 | F48: 0.75 | H48: Total, 15 shilling.
A49: Cost of buildings total | F49: 0.74 | G49: -0.01 | H49: Total
A51: Threshing and winnowing | B51: 0 | C51: 13 | D51: 3 | F51: 0.66 | H51: In threshing 49 quarters 1 bushels of wheat and 4 quarters of curall by piece-work 13 shilling 3pence, at 3pence a qr.
A52: Threshing and winnowing | B52: 0 | C52: 17 | D52: 8.25 | F52: 0.88 | H52: threshing 106 quarters 1 bushels of barley by piece-work 17 shilling 8.25pence, at 2pence a qr.
A53: Threshing and winnowing | B53: 0 | C53: 2 | D53: 6.75 | F53: 0.13 | H53: threshing 20 quarters 4 bushels of oats by piece-work 2 shilling 6.75pence, at 1.5pence a qr.
A54: Threshing and winnowing | B54: 0 | C54: 3 | D54: 11.75 | F54: 0.2 | H54: winnowing all the aforesaid corn by piece-work, both that threshed by piece-work and by the manorial servants, which made 191 quarters 3 bushels, 3 shilling 11.75pence, at 1pence per 4 quarters.
A55: Threshing and winnowing | B55: 1 | C55: 17 | D55: 5.5 | F55: 1.87 | H55: Total, £1 17 shilling 5.5pence.
A56: Threshing and winnowing total | F56: 1.87 | G56: 0 | H56: Total
A58: Cost of the harvest | B58: 0 | C58: 7 | D58: 0 | F58: 0.35 | H58: In expenses of the customary tenants at 3 harvest boon-works who reaped, bound and carried 32 acres 7 shilling.
A59: Cost of the harvest | B59: 4 | C59: 8 | D59: 0 | F59: 4.4 | H59: reaping, binding and gathering into shocks (huland') 96 acres of various kinds of corn, besides the 32 acres reaped by boon-works as made clear elsewhere, and the 4 acres given to the servants as made clear elsewhere, that is, in bread, ale, victuals and stipends, for 6 weeks this year, £4 8 shilling, and thus each acre was reaped for 11pence.
A60: Cost of the harvest | B60: 0 | C60: 6 | D60: 8 | F60: 0.33 | H60: stipend of 1 overseer of the harvest for the year 6 shilling 8pence.
A61: Cost of the harvest | B61: 5 | C61: 1 | D61: 8 | F61: 5.08 | H61: Total, £5 1 shilling 8pence.
A62: Cost of the harvest total | F62: 5.08 | G62: 0 | H62: Total
A64: Expenses of the steward | B64: 0 | C64: 0 | D64: 0 | F64: 0 | H64: In expenses of Richard Wyot', steward, at the tourns of Martinmas and Hockday, by 2.
A65: Expenses of the steward | B65: 0 | C65: 8 | D65: 11 | F65: 0.45 | H65: sealed bills, 8 shilling 11pence.
A66: Expenses of the steward | B66: 0 | C66: 8 | D66: 11 | F66: 0.45 | H66: Total, 8 shilling 11pence.
A67: Expenses of the steward total | F67: 0.45 | G67: 0 | H67: Total
A69: Total of all expenses | B69: 18 | C69: 15 | D69: 10.5 | F69: 18.79 | H69: Total of all expenses, £18 15 shilling 10.5pence.
A70: Total of all expenses | F70: 0 | G70: -18.79 | H70: Total
A72: And he owes | B72: 62 | C72: 15 | D72: 6.25 | F72: 62.78 | H72: And he owes, £62 15 shilling 6.25pence.
A73: And he owes total | F73: 62.78 | G73: 0 | H73: Total
A75: Cash deliveries | B75: 57 | C75: 9 | D75: 8 | F75: 57.48 | H75: Delivered to John Arnold', receiver of Wolvesey, by 1 tally, £57 9 shilling 8pence.
A76: Cash deliveries | B76: 57 | C76: 9 | D76: 0 | F76: 57.45 | H76: Total, £57 9 shilling.
A77: Cash deliveries | B77: 0 | C77: 0 | D77: 8 | F77: 0.03 | H77: 8pence.
A78: Cash deliveries total | F78: 57.51 | G78: 57.48 | H78: Total
A80: Total of all allowances and cash deliveries | B80: 62 | C80: 5 | D80: 3.25 | F80: 62.26 | H80: Total of all allowances and cash deliveries, £62 5 shilling 3.25pence.
A82: Total of all expenses per account | B82: 18 | C82: 15 | D82: 10.5 | F82: =F69 -> 18.79
A83: Total of all expenses (calculated here) | F83: =SUMIF(A1:A68,"* total",F1:F68) -> 14.02
A84: Total fixed investment | F84: =SUM(I:I) -> 3.24
A85: Total Demesne fixed investment | F85: =SUM(J:J) -> 0.46

Sheet Stock
A1: BISHOPSTONE STOCK ACCOUNT
C3: added | G3: subtracted
A4: Livestock | B4: Inherited stock | C4: added | D4: strays | E4: herbage | F4: churchscot | G4: of which in default | H4: sold | I4: in murrain | J4: accounted for elsewhere | K4: End-period stock | L4: cross-check | M4: stock building | N4: raw production | O4: Unit price (£) | P4: Value of stock (£) at given value | Q4: Value of stock (£) at sales prices | R4: Sales in (£) | S4: Value of stock building (£) | T4: Value of production (£) at sales prices | U4: Details
A5: Cart-horses | B5: 0 | C5: 0 | H5: 0 | I5: 0 | K5: =B5+C5-H5-I5 -> 0 | L5: =B5+C5-H5 -> 0 | M5: =L5-B5 -> 0 | N5: =C5 -> 0 | O5: 0 | P5: =O5*K5 -> 0 | R5: 0 | S5: =O5*M5 -> 0 | T5: =O5*N5 -> 0
A6: Mares | B6: 0 | C6: 0 | H6: 0 | I6: 0 | K6: =B6+C6-H6-I6 -> 0 | L6: =B6+C6-H6 -> 0 | M6: =L6-B6 -> 0 | N6: =C6 -> 0 | O6: 0 | P6: =O6*K6 -> 0 | R6: 0 | S6: =O6*M6 -> 0 | T6: =O6*N6 -> 0
A7: Plough horses | B7: 2 | C7: 0 | H7: 0 | I7: 0 | K7: =B7+C7-H7-I7 -> 2 | L7: =B7+C7-H7 -> 2 | M7: =L7-B7 -> 0 | N7: =C7 -> 0 | O7: 0 | P7: =O7*K7 -> 0 | R7: 0 | S7: =O7*M7 -> 0 | T7: =O7*N7 -> 0
A8: Colts (unspecified years) | B8: 0 | C8: 0 | H8: 0 | I8: 0 | K8: =B8+C8-H8-I8 -> 0 | L8: =B8+C8-H8 -> 0 | M8: =L8-B8 -> 0 | N8: =C8 -> 0 | O8: 0 | P8: =O8*K8 -> 0 | R8: 0 | S8: =O8*M8 -> 0 | T8: =O8*N8 -> 0
A9: Colts (2 years) | B9: 0 | C9: 0 | H9: 0 | I9: 0 | K9: =B9+C9-H9-I9 -> 0 | L9: =B9+C9-H9 -> 0 | M9: =L9-B9 -> 0 | N9: =C9 -> 0 | O9: 0 | P9: =O9*K9 -> 0 | R9: 0 | S9: =O9*M9 -> 0 | T9: =O9*N9 -> 0
A10: Colts (1 year) | B10: 0 | C10: 0 | H10: 0 | I10: 0 | K10: =B10+C10-H10-I10 -> 0 | L10: =B10+C10-H10 -> 0 | M10: =L10-B10 -> 0 | N10: =C10 -> 0 | O10: 0 | P10: =O10*K10 -> 0 | R10: 0 | S10: =O10*M10 -> 0 | T10: =O10*N10 -> 0
A11: Foals | B11: 0 | C11: 0 | H11: 0 | I11: 0 | K11: =B11+C11-H11-I11 -> 0 | L11: =B11+C11-H11 -> 0 | M11: =L11-B11 -> 0 | N11: =C11 -> 0 | O11: 0 | P11: =O11*K11 -> 0 | R11: 0 | S11: =O11*M11 -> 0 | T11: =O11*N11 -> 0
A12: Oxen | B12: 19 | C12: 2 | H12: 3 | I12: 0 | K12: =B12+C12-H12-I12 -> 18 | L12: =B12+C12-H12 -> 18 | M12: =L12-B12 -> -1 | N12: =C12 -> 2 | O12: 0.44333333 | P12: =O12*K12 -> 7.98 | R12: 1.33 | S12: =O12*M12 -> -0.44333333 | T12: =O12*N12 -> 0.88666667
A13: Bulls | B13: 0 | C13: 0 | H13: 0 | I13: 0 | K13: =B13+C13-H13-I13 -> 0 | L13: =B13+C13-H13 -> 0 | M13: =L13-B13 -> 0 | N13: =C13 -> 0 | O13: 0 | P13: =O13*K13 -> 0 | R13: 0 | S13: =O13*M13 -> 0 | T13: =O13*N13 -> 0
A14: Cows | B14: 2 | C14: 0 | H14: 0 | I14: 0 | K14: =B14+C14-H14-I14 -> 2 | L14: =B14+C14-H14 -> 2 | M14: =L14-B14 -> 0 | N14: =C14 -> 0 | O14: 0 | P14: =O14*K14 -> 0 | R14: 0 | S14: =O14*M14 -> 0 | T14: =O14*N14 -> 0
A15: Steers | B15: 2 | C15: 0 | H15: 1 | I15: 0 | K15: =B15+C15-H15-I15 -> 1 | L15: =B15+C15-H15 -> 1 | M15: =L15-B15 -> -1 | N15: =C15 -> 0 | O15: =35/240 -> 0.14583333 | P15: =O15*K15 -> 0.14583333 | R15: 0 | S15: =O15*M15 -> -0.14583333 | T15: =O15*N15 -> 0
A16: Bullocks | B16: 2 | C16: 0 | H16: 0 | I16: 0 | K16: =B16+C16-H16-I16 -> 2 | L16: =B16+C16-H16 -> 2 | M16: =L16-B16 -> 0 | N16: =C16 -> 0 | O16: 0 | P16: =O16*K16 -> 0 | R16: 0 | S16: =O16*M16 -> 0 | T16: =O16*N16 -> 0
A17: Yearlings | B17: 2 | C17: 0 | H17: 0 | I17: 0 | K17: =B17+C17-H17-I17 -> 2 | L17: =B17+C17-H17 -> 2 | M17: =L17-B17 -> 0 | N17: =C17 -> 0 | O17: 0 | P17: =O17*K17 -> 0 | R17: 0 | S17: =O17*M17 -> 0 | T17: =O17*N17 -> 0
A18: Calves | B18: 2 | C18: 2 | H18: 0 | I18: 0 | K18: =B18+C18-H18-I18 -> 4 | L18: =B18+C18-H18 -> 4 | M18: =L18-B18 -> 2 | N18: =C18 -> 2 | O18: 0 | P18: =O18*K18 -> 0 | R18: 0 | S18: =O18*M18 -> 0 | T18: =O18*N18 -> 0
A19: Wethers | B19: 354 | C19: 0 | H19: 35 | I19: 11 | K19: =B19+C19-H19-I19 -> 308 | L19: =B19+C19-H19 -> 319 | M19: =L19-B19 -> -35 | N19: =C19 -> 0 | O19: 0.083428571 | P19: =O19*K19 -> 25.696 | R19: 2.92 | S19: =O19*M19 -> -2.92 | T19: =O19*N19 -> 0
A20: Rams | B20: 9 | C20: 0 | H20: 1 | I20: 0 | K20: =B20+C20-H20-I20 -> 8 | L20: =B20+C20-H20 -> 8 | M20: =L20-B20 -> -1 | N20: =C20 -> 0 | O20: 0.067818182 | P20: =O20*K20 -> 0.54254545 | R20: 0 | S20: =O20*M20 -> -0.067818182 | T20: =O20*N20 -> 0
A21: Ewes | B21: 315 | C21: 0 | H21: 55 | I21: 18 | K21: =B21+C21-H21-I21 -> 242 | L21: =B21+C21-H21 -> 260 | M21: =L21-B21 -> -55 | N21: =C21 -> 0 | O21: 0.067818182 | P21: =O21*K21 -> 16.412 | Q21: 0 | R21: 3.73 | S21: =O21*M21 -> -3.73 | T21: =O21*N21 -> 0
A22: Hoggs | B22: 196 | C22: 0 | H22: 0 | I22: 5 | K22: =B22+C22-H22-I22 -> 191 | L22: =B22+C22-H22 -> 196 | M22: =L22-B22 -> 0 | N22: =C22 -> 0 | O22: 0 | P22: =O22*K22 -> 0 | R22: 0 | S22: =O22*M22 -> 0 | T22: =O22*N22 -> 0
A23: Lambs | B23: 204 | C23: 269 | H23: 16 | I23: 21 | K23: =B23+C23-H23-I23 -> 436 | L23: =B23+C23-H23 -> 457 | M23: =L23-B23 -> 253 | N23: =C23 -> 269 | O23: 0.033125 | P23: =O23*K23 -> 14.4425 | R23: 0.53 | S23: =O23*M23 -> 8.380625 | T23: =O23*N23 -> 8.910625
A24: Boars | B24: 0 | C24: 0 | H24: 0 | I24: 0 | K24: =B24+C24-H24-I24 -> 0 | L24: =B24+C24-H24 -> 0 | M24: =L24-B24 -> 0 | N24: =C24 -> 0 | O24: 0 | P24: =O24*K24 -> 0 | R24: 0 | S24: =O24*M24 -> 0 | T24: =O24*N24 -> 0
A25: Sows | B25: 0 | C25: 0 | H25: 0 | I25: 0 | K25: =B25+C25-H25-I25 -> 0 | L25: =B25+C25-H25 -> 0 | M25: =L25-B25 -> 0 | N25: =C25 -> 0 | O25: 0 | P25: =O25*K25 -> 0 | R25: 0 | S25: =O25*M25 -> 0 | T25: =O25*N25 -> 0
A26: Pigs | B26: 0 | C26: 0 | H26: 0 | I26: 0 | K26: =B26+C26-H26-I26 -> 0 | L26: =B26+C26-H26 -> 0 | M26: =L26-B26 -> 0 | N26: =C26 -> 0 | O26: 0 | P26: =O26*K26 -> 0 | R26: 0 | S26: =O26*M26 -> 0 | T26: =O26*N26 -> 0
A27: Hoggets | B27: 0 | C27: 0 | H27: 0 | I27: 0 | K27: =B27+C27-H27-I27 -> 0 | L27: =B27+C27-H27 -> 0 | M27: =L27-B27 -> 0 | N27: =C27 -> 0 | O27: 0 | P27: =O27*K27 -> 0 | R27: 0 | S27: =O27*M27 -> 0 | T27: =O27*N27 -> 0
A28: Piglets | B28: 0 | C28: 0 | H28: 0 | I28: 0 | K28: =B28+C28-H28-I28 -> 0 | L28: =B28+C28-H28 -> 0 | M28: =L28-B28 -> 0 | N28: =C28 -> 0 | O28: 0 | P28: =O28*K28 -> 0 | R28: 0 | S28: =O28*M28 -> 0 | T28: =O28*N28 -> 0
A29: Swans | B29: 0 | C29: 0 | H29: 0 | I29: 0 | K29: =B29+C29-H29-I29 -> 0 | L29: =B29+C29-H29 -> 0 | M29: =L29-B29 -> 0 | N29: =C29 -> 0 | O29: 0 | P29: =O29*K29 -> 0 | R29: 0 | S29: =O29*M29 -> 0 | T29: =O29*N29 -> 0
A30: Peacocks | B30: 0 | C30: 0 | H30: 0 | I30: 0 | K30: =B30+C30-H30-I30 -> 0 | L30: =B30+C30-H30 -> 0 | M30: =L30-B30 -> 0 | N30: =C30 -> 0 | O30: 0 | P30: =O30*K30 -> 0 | R30: 0 | S30: =O30*M30 -> 0 | T30: =O30*N30 -> 0
A31: Total Value
A34: Wool | B34: 0 | C34: 0 | H34: 0 | I34: 0
A35: Coarse wool | B35: 0 | C35: 0 | H35: 0 | I35: 0
A36: Lamb's wool | B36: 0 | C36: 0 | H36: 0 | I36: 0
A37: Wool locks | B37: 0 | C37: 0 | H37: 0 | I37: 0
A38: Wool sold at shearing | B38: 0 | C38: 0 | H38: 0 | I38: 0
A39: Total wool | B39: 0 | C39: 0 | H39: 0 | I39: 0
B40: 0 | C40: 0 | H40: 0 | I40: 0
B41: 0 | C41: 0 | H41: 0 | I41: 0
A42: Hides | B42: 0 | C42: 0 | H42: 0 | I42: 0
A43: Ox hides | B43: 0 | C43: 0 | H43: 0 | I43: 0
A44: Mare | B44: 0 | C44: 0 | H44: 0 | I44: 0
A45: Steer | B45: 0 | C45: 0 | H45: 0 | I45: 0
A46: calves | B46: 2 | C46: 2 | H46: 0 | I46: 0
A47: pigs | B47: 0 | C47: 0 | H47: 0 | I47: 0
A48: Woolskins
A49: wethers
A50: rams
A51: ewes
A52: hoggs
A53: Woolskins total | B53: 0 | C53: 0 | H53: 24 | I53: 0
A54: Bareskins
A55: wethers
A56: rams
A57: ewes
A58: hoggs
A59: Bareskins total | B59: 0 | C59: 0 | H59: 0 | I59: 7
A60: Lambskins | B60: 0 | C60: 0 | H60: 15 | I60: 17
A61: Rotted skins | B61: 0 | C61: 0 | H61: 0 | I61: 2
A62: Shorn skins | B62: 0 | C62: 0 | H62: 0 | I62: 4
A63: Total
A66: Poultry stock
A67: Hens | L67: =B67+C67-H67 -> 0 | M67: =L67-B67 -> 0 | N67: =C67 -> 0 | O67: 0 | Q67: =R67*K67 -> 0 | R67: 0.27 | S67: =O67*M67 -> 0 | T67: =O67*N67 -> 0
A68: Geese | L68: =B68+C68-H68 -> 0 | M68: =L68-B68 -> 0 | N68: =C68 -> 0 | O68: 0 | Q68: =R68*K68 -> 0 | R68: 0 | S68: =O68*M68 -> 0 | T68: =O68*N68 -> 0
A69: Capons (from chickens) | B69: 0 | C69: 6 | H69: 6 | K69: 0 | L69: =B69+C69-H69 -> 0 | M69: =L69-B69 -> 0 | N69: =C69 -> 6 | O69: 0 | Q69: =R69*K69 -> 0 | R69: 0 | S69: =O69*M69 -> 0 | T69: =O69*N69 -> 0
A70: Cocks & hens | B70: 0 | F70: 28 | G70: 18 | H70: 10 | K70: 0 | L70: =B70+C70-H70 -> -10 | M70: =L70-B70 -> -10 | N70: =C70 -> 0 | O70: 0 | Q70: =R70*K70 -> 0 | R70: 0 | S70: =O70*M70 -> 0 | T70: =O70*N70 -> 0
A71: Total poultry stock
A72: Total poultry excluding churchscot
A74: Poultry production
A75: Eggs | B75: 0 | C75: 0 | H75: 0 | I75: 0 | S75: =O75*M75 -> 0 | T75: =O75*N75 -> 0
A76: Cocks & hens from churchscot of customary tenants | B76: 0 | C76: 0 | H76: 0 | I76: 0 | S76: =O76*M76 -> 0 | T76: =O76*N76 -> 0
A77: Sum of above | S77: =SUM(S75:S76) -> 0 | T77: =SUM(T75:T76) -> 0
A78: Total
A81: Meat
A82: Beef | B82: 0 | C82: 0 | H82: 0 | I82: 0 | S82: =O82*M82 -> 0 | T82: =O82*N82 -> 0
A83: Mutton | B83: 0 | C83: 0 | H83: 0 | I83: 0 | S83: =O83*M83 -> 0 | T83: =O83*N83 -> 0
A84: Pork | B84: 0 | C84: 0 | H84: 0 | I84: 0 | S84: =O84*M84 -> 0 | T84: =O84*N84 -> 0
A85: Total
A87: Cheese
A88: Winter cheese | B88: 0 | C88: 0 | H88: 0 | I88: 0 | S88: =O88*M88 -> 0 | T88: =O88*N88 -> 0
A89: Summer cheese | B89: 0 | C89: 0 | H89: 0 | I89: 0 | S89: =O89*M89 -> 0 | T89: =O89*N89 -> 0
A90: Total
A92: Butter
A93: Butter | B93: 0 | C93: 0 | H93: 0 | I93: 0 | S93: =O93*M93 -> 0 | T93: =O93*N93 -> 0
A94: Total
A96: Total Dairy Sales
A99: Cider | B99: 0 | C99: 0 | H99: 0 | I99: 0
A102: Additional Information (not necessarily useful)
A103: Utensils
A104: ploughs
A105: carts
A106: cart-ropes
A107: corn baskets
A108: seed-sacks
A109: seed basket
A110: locks for the doors
A111: lead vessel
A112: brass pots
A113: pans
... A128: brass posnets

Sheet raw data
A1: Heading | B1: Sentence | C1: Total in Pounds | D1: Pounds | E1: Shillings | F1: Pence | G1: Corn | H1: Total Quarters Except 1 | I1: Total Bushels Except 1 | J1: Total Corn Cross-Check | K1: Total Corn Manorial Account | L1: Corn Quantity Error | M1: Quarters 1 | N1: Bushels 1 | O1: Quarters 2 | P1: Bushels 2 | Q1: Quarters 3 | R1: Bushels 3 | S1: shilling a quarter 1 | T1: pence a quarter 1 | U1: shilling a quarter 2 | V1: pence a quarter 2 | W1: shilling a quarter 3 | X1: pence a quarter 3 | Y1: shilling a quarter 4 | Z1: pence a quarter 4 | AA1: shilling a bushel 1 | AB1: pence a bushel 1 | AC1: shilling a bushel 2 | AD1: pence a bushel 2 | AE1: shilling a bushel 3 | AF1: pence a bushel 3 | AG1: shilling a bushel 4 | AH1: pence a bushel 4
A2: arrears | B2: john algar', reeve there, answers for 10 shilling 3pence of arrears from his last account of the preceding year. | C2: 0.51 | D2: 0 | E2: 10 | F2: 3 | H2: 0 | I2: 0 | J2: 0 | K2: 0 | L2: 0 | M2: 0 | N2: 0
A3: arrears | B3: total, 10 shilling 3pence. | C3: 0.51 | D3: 0 | E3: 10 | F3: 3 | H3: 0 | I3: 0 | J3: 0 | K3: 0 | L3: 0 | M3: 0 | N3: 0
A4: rents | B4: and for £12 7 shilling 8pence for all rents of assize, or £3 1 shilling 11pence at each of the terms of christmas, easter (23 march), the nativity of st john the baptist (24 june) and michaelmas (29 september). | C4: 12.38 | D4: 12 | E4: 7 | F4: 8 | H4: 0 | I4: 0 | J4: 0 | K4: 0 | L4: 0 | M4: 0 | N4: 0
A5: rents | B5: total, £12 7 shilling 8pence. | C5: 12.38 | D5: 12 | E5: 7 | F5: 8 | H5: 0 | I5: 0 | J5: 0 | K5: 0 | L5: 0 | M5: 0 | N5: 0
A6: quittances of rent | B6: in quittance of rent of 1 reeve for the year 4 shilling. | C6: 0.2 | D6: 0 | E6: 4 | F6: 0 | H6: 0 | I6: 0 | J6: 0 | K6: 0 | L6: 0 | M6: 0 | N6: 0
A7: quittances of rent | B7: 1 shepherd of ewes, nothing this year, because he has the lord's livery as made clear elsewhere. | C7: 0 | D7: 0 | E7: 0 | F7: 0 | H7: 0 | I7: 0 | J7: 0 | K7: 0 | L7: 0 | M7: 0 | N7: 0
A8: quittances of rent | B8: total, 4 shilling. | C8: 0.2 | D8: 0 | E8: 4 | F8: 0 | H8: 0 | I8: 0 | J8: 0 | K8: 0 | L8: 0 | M8: 0 | N8: 0
A9: defaults of rent | B9: in default of 1 plot of land which formerly belonged to the vicar of bishopstone 6pence. | C9: 0.03 | D9: 0 | E9: 0 | F9: 6 | H9: 0 | I9: 0 | J9: 0 | K9: 0 | L9: 0 | M9: 0 | N9: 0
A10: defaults of rent | B10: 1 virgate of land formerly of john salisbury in netton because in the lord's hands, 4 shilling 6pence for the year. | C10: 0.23 | D10: 0 | E10: 4 | F10: 6 | H10: 0 | I10: 0 | J10: 0 | K10: 0 | L10: 0 | M10: 0 | N10: 0
A11: defaults of rent | B11: 1 half-virgate of land formerly of gunnora burgeys, 1 half-virgate of land formerly of adam berewyke, 1 half-virgate of land formerly of richard dryvere, 1 half-virgate of land formerly of john holm', 1 half-virgate of land formerly of john salisbury, 1 half-virgate formerly of william hardyng', 1 half-virgate of land formerly of robert cryor' and 1 half-virgate of land formerly of john deyman' in bishopstone because in the lord's hands, £1 2 shilling for the year, or 2 shilling 9pence for each half-virgate. | C11: 1.1 | D11: 1 | E11: 2 | F11: 0 | H11: 0 | I11: 0 | J11: 0 | K11: 0 | L11: 0 | M11: 0 | N11: 0
A12: defaults of rent | B12: the holding formerly of andrew vicar' of bishopstone there because in the lord's hands, 5 shilling for the year. | C12: 0.25 | D12: 0 | E12: 5 | F12: 0 | H12: 0 | I12: 0 | J12: 0 | K12: 0 | L12: 0 | M12: 0 | N12: 0
A13: defaults of rent | B13: total, £1 12 shilling. | C13: 1.6 | D13: 1 | E13: 12 | F13: 0 | H13: 0 | I13: 0 | J13: 0 | K13: 0 | L13: 0 | M13: 0 | N13: 0
... A63: sale of pasture | B63: total, £1 14 shilling 6pence. | C63: 1.72 | D63: 1 | E63: 14 | F63: 6 | H63: 0 | I63: 0 | J63: 0 | K63: 0 | L63: 0 | M63: 0 | N63: 0
A64: sale of corn | B64: and for £17 16 shilling 3.75pence from 36 quarters 6.5 bushels of wheat sold, at 10 shilling a quarters for 25 quarters per mutuum, and 9 shilling a quarters for 11 quarters 6.5 bushels in the market. | C64: 17.82 | D64: 17 | E64: 16 | F64: 3.75 | G64: wheat | H64: 36 | I64: 6.5 | J64: 36.81 | K64: 36.81 | L64: 0 | M64: 36 | N64: 6.5 | O64: 25 | P64: 0 | Q64: 11 | R64: 6.5 | S64: 10 | T64: 0 | U64: 9 | V64: 0
A65: sale of corn | B65: £1 4 shilling from 4 quarters of curall sold. | C65: 1.2 | D65: 1 | E65: 4 | F65: 0 | G65: curall | H65: 4 | I65: 0 | J65: 4 | K65: 4 | L65: 0 | M65: 4 | N65: 0
A66: sale of corn | B66: £11 8 shilling 9pence from 38 quarters 1 bushels of barley sold per mutuum, at 6 shilling a quarters. | C66: 11.44 | D66: 11 | E66: 8 | F66: 9 | G66: barley | H66: 38 | I66: 1 | J66: 38.12 | K66: 38.12 | L66: 0 | M66: 38 | N66: 1 | S66: 6 | T66: 0
A67: sale of corn | B67: 15 shilling 5pence from 4 quarters 5 bushels of oats sold per mutuum, at 3 shilling 4pence a quarters. | C67: 0.77 | D67: 0 | E67: 15 | F67: 5 | G67: oats | H67: 4 | I67: 5 | J67: 4.62 | K67: 4.62 | L67: 0 | M67: 4 | N67: 5 | S67: 3 | T67: 4
A68: sale of corn | B68: 14 shilling from 2 quarters 5 bushels of peas sold, at 5 shilling 4pence a quarters. | C68: 0.72 | D68: 0 | E68: 14 | F68: 4 | G68: peas | H68: 2 | I68: 5 | J68: 2.62 | K68: 2.62 | L68: 0 | M68: 2 | N68: 5 | S68: 5 | T68: 4
A69: sale of corn | B69: 17 shilling 6pence from 3 quarters 3 bushels' of vetches sold, at 5 shilling a quarters. | C69: 0.88 | D69: 0 | E69: 17 | F69: 6 | G69: vetches | H69: 3 | I69: 3 | J69: 3.38 | K69: 3.38 | L69: 0 | M69: 3 | N69: 3 | S69: 5 | T69: 0
A70: sale of corn | B70: total, £32 15 shilling 11.75pence. | C70: 32.8 | D70: 32 | E70: 15 | F70: 11.75 | H70: 0 | I70: 0 | J70: 0 | K70: 0 | L70: 0 | M70: 0 | N70: 0
A71: sale of stock | B71: and for £1 6 shilling 8pence from 2 kebb oxen sold. | C71: 1.33 | D71: 1 | E71: 6 | F71: 8 | H71: 0 | I71: 0 | J71: 0 | K71: 0 | L71: 0 | M71: 0 | N71: 0
A72: sale of stock | B72: 8 shilling from 1 feeble ox sold. | C72: 0.4 | D72: 0 | E72: 8 | F72: 0 | H72: 0 | I72: 0 | J72: 0 | K72: 0 | L72: 0 | M72: 0 | N72: 0
A73: sale of stock | B73: 7 shilling from 1 steer sold because feeble and useless for the lord's stock. | C73: 0.35 | D73: 0 | E73: 7 | F73: 0 | H73: 0 | I73: 0 | J73: 0 | K73: 0 | L73: 0 | M73: 0 | N73: 0
A74: sale of stock | B74: £2 18 shilling 4pence from 35 kebb wethers sold before shearing, at 1 shilling 8pence each. | C74: 2.92 | D74: 2 | E74: 18 | F74: 4 | H74: 0 | I74: 0 | J74: 0 | K74: 0 | L74: 0 | M74: 0 | N74: 0
A75: sale of stock | B75: £3 14 shilling 8pence from 1 ram and 55 kebb ewes sold before shearing, at 1 shilling 4pence each. | C75: 3.73 | D75: 3 | E75: 14 | F75: 8 | H75: 0 | I75: 0 | J75: 0 | K75: 0 | L75: 0 | M75: 0 | N75: 0
A76: sale of stock | B76: 10 shilling from 16 lambs removed from stock and sold before shearing, at 7.5pence each. | C76: 0.53 | D76: 0 | E76: 10 | F76: 7.5 | H76: 0 | I76: 0 | J76: 0 | K76: 0 | L76: 0 | M76: 0 | N76: 0
A77: sale of stock | B77: 7 shilling 4pence from 22 geese sold, at 4pence each. | C77: 0.37 | D77: 0 | E77: 7 | F77: 4 | H77: 0 | I77: 0 | J77: 0 | K77: 0 | L77: 0 | M77: 0 | N77: 0
A78: sale of stock | B78: 8 shilling from 24 capons sold, at 4pence each. | C78: 0.42 | D78: 0 | E78: 8 | F78: 4 | H78: 0 | I78: 0 | J78: 0 | K78: 0 | L78: 0 | M78: 0 | N78: 0
A79: sale of stock | B79: total, £10.. | C79: 10 | D79: 10 | E79: 0 | F79: 0 | H79: 0 | I79: 0 | J79: 0 | K79: 0 | L79: 0 | M79: 0 | N79: 0
A80: entry fines | B80: and for 3 shilling from the tithing of bishopstone at the tourn of martinmas. | C80: 0.15 | D80: 0 | E80: 3 | F80: 0 | H80: 0 | I80: 0 | J80: 0 | K80: 0 | L80: 0 | M80: 0 | N80: 0
A81: entry fines | B81: 3 shilling from the tithing of flamston for similar. | C81: 0.15 | D81: 0 | E81: 3 | F81: 0 | H81: 0 | I81: 0 | J81: 0 | K81: 0 | L81: 0 | M81: 0 | N81: 0
... A145: cost of buildings | B145: total, 15 shilling. | C145: 0.75 | D145: 0 | E145: 15 | F145: 0 | H145: 0 | I145: 0 | J145: 0 | K145: 0 | L145: 0 | M145: 0 | N145: 0
A146: threshing and winnowing | B146: in threshing 49 quarters 1 bushels of wheat and 4 quarters of curall by piece-work 13 shilling 3pence, at 3pence a quarters. | C146: 0.66 | D146: 0 | E146: 13 | F146: 3 | G146: wheat, curall | H146: 4 | I146: 1 | J146: 4.12 | K146: 49.12 | L146: -45 | M146: 49 | N146: 1 | O146: 4 | P146: 0
A147: threshing and winnowing | B147: threshing 106 quarters 1 bushels of barley by piece-work 17 shilling 8.25pence, at 2pence a quarters. | C147: 0.88 | D147: 0 | E147: 17 | F147: 8.25 | G147: barley | H147: 106 | I147: 1 | J147: 106.12 | K147: 106.12 | L147: 0 | M147: 106 | N147: 1
A148: threshing and winnowing | B148: threshing 20 quarters 4 bushels of oats by piece-work 2 shilling 6.75pence, at 1.5pence a quarters. | C148: 0.13 | D148: 0 | E148: 2 | F148: 6.75 | G148: oats | H148: 20 | I148: 4 | J148: 20.5 | K148: 20.5 | L148: 0 | M148: 20 | N148: 4
A149: threshing and winnowing | B149: winnowing all the aforesaid corn by piece-work, both that threshed by piece-work and by the manorial servants, which made 191 quarters 3 bushels, 3 shilling 11.75pence, at 1pence per 4 quarters. | C149: 0.2 | D149: 0 | E149: 3 | F149: 11.75 | H149: 4 | I149: 3 | J149: 4.38 | K149: 191.38 | L149: -187 | M149: 191 | N149: 3 | O149: 4 | P149: 0
A150: threshing and winnowing | B150: total, £1 17 shilling 5.5pence. | C150: 1.87 | D150: 1 | E150: 17 | F150: 5.5 | H150: 0 | I150: 0 | J150: 0 | K150: 0 | L150: 0 | M150: 0 | N150: 0
A151: mowing the meadows | B151: in customary payment for the mowing of the lord's meadow 8pence. | C151: 0.03 | D151: 0 | E151: 0 | F151: 8 | H151: 0 | I151: 0 | J151: 0 | K151: 0 | L151: 0 | M151: 0 | N151: 0
A152: mowing the meadows | B152: customary payment. | C152: 0 | D152: 0 | E152: 0 | F152: 0 | H152: 0 | I152: 0 | J152: 0 | K152: 0 | L152: 0 | M152: 0 | N152: 0
A153: mowing the meadows | B153: for the same for 2 cheeses according to custom 1 shilling. | C153: 0.05 | D153: 0 | E153: 1 | F153: 0 | H153: 0 | I153: 0 | J153: 0 | K153: 0 | L153: 0 | M153: 0 | N153: 0
A154: mowing the meadows | B154: total, 1 shilling 8pence. | C154: 0.08 | D154: 0 | E154: 1 | F154: 8 | H154: 0 | I154: 0 | J154: 0 | K154: 0 | L154: 0 | M154: 0 | N154: 0
A155: cost of the harvest | B155: in expenses of the customary tenants at 3 harvest boon-works who reaped, bound and carried 32 acres 7 shilling. | C155: 0.35 | D155: 0 | E155: 7 | F155: 0 | H155: 0 | I155: 0 | J155: 0 | K155: 0 | L155: 0 | M155: 0 | N155: 0
A156: cost of the harvest | B156: reaping, binding and gathering into shocks (huland') 96 acres of various kinds of corn, besides the 32 acres reaped by boon-works as made clear elsewhere, and the 4 acres given to the servants as made clear elsewhere, that is, in bread, ale, victuals and stipends, for 6 weeks this year, £4 8 shilling, and thus each acre was reaped for 11pence. | C156: 4.4 | D156: 4 | E156: 8 | F156: 0 | H156: 0 | I156: 0 | J156: 0 | K156: 0 | L156: 0 | M156: 0 | N156: 0
A157: cost of the harvest | B157: stipend of 1 overseer of the harvest for the year 6 shilling 8pence. | C157: 0.33 | D157: 0 | E157: 6 | F157: 8 | H157: 0 | I157: 0 | J157: 0 | K157: 0 | L157: 0 | M157: 0 | N157: 0
A158: cost of the harvest | B158: total, £5 1 shilling 8pence. | C158: 5.08 | D158: 5 | E158: 1 | F158: 8 | H158: 0 | I158: 0 | J158: 0 | K158: 0 | L158: 0 | M158: 0 | N158: 0
A159: expenses of the steward | B159: in expenses of richard wyot', steward, at the tourns of martinmas and hockday, by 2. | C159: 0 | D159: 0 | E159: 0 | F159: 0 | H159: 0 | I159: 0 | J159: 0 | K159: 0 | L159: 0 | M159: 0 | N159: 0
A160: expenses of the steward | B160: sealed bills, 8 shilling 11pence. | C160: 0.45 | D160: 0 | E160: 8 | F160: 11 | H160: 0 | I160: 0 | J160: 0 | K160: 0 | L160: 0 | M160: 0 | N160: 0
A161: expenses of the steward | B161: total, 8 shilling 11pence. | C161: 0.45 | D161: 0 | E161: 8 | F161: 11 | H161: 0 | I161: 0 | J161: 0 | K161: 0 | L161: 0 | M161: 0 | N161: 0
... A172: and he owes clear | B172: and he owes clear, 10 shilling 3pence, all of which is in the hands of the escheator. | C172: 0.51 | D172: 0 | E172: 10 | F172: 3 | H172: 0 | I172: 0 | J172: 0 | K172: 0 | L172: 0 | M172: 0 | N172: 0
A173: wheat | B173: john algare, reeve there, answers for 49 quarters 1 bushels of wheat from the whole issue of the grange, threshed by piece-work. | C173: 0 | D173: 0 | E173: 0 | F173: 0 | G173: wheat | H173: 49 | I173: 1 | J173: 49.12 | K173: 49.12 | L173: 0 | M173: 49 | N173: 1
A174: wheat | B174: 4 quarters by estimation in sheaves in 4 acres, of which 1 is for the reeve, 1 for the men of croucheston and netton, 1 for the men of bishopstone, and 1 for all the manorial servants of the curia. | C174: 0 | D174: 0 | E174: 0 | F174: 0 | H174: 4 | I174: 0 | J174: 4 | K174: 4 | L174: 0 | M174: 4 | N174: 0
A175: wheat | B175: 5 quarters 3 bushels surcharged so that he answers for a 5-fold yield.. | C175: 0 | D175: 0 | E175: 0 | F175: 0 | H175: 5 | I175: 3 | J175: 5.38 | K175: 5.38 | L175: 0 | M175: 5 | N175: 3
A176: wheat | B176: total, 58 quarters 4 bushels. | C176: 0 | D176: 0 | E176: 0 | F176: 0 | H176: 58 | I176: 4 | J176: 58.5 | K176: 58.5 | L176: 0 | M176: 58 | N176: 4
A177: wheat | B177: sown over 48 acres, 12 quarters. | C177: 0 | D177: 0 | E177: 0 | F177: 0 | H177: 12 | I177: 0 | J177: 12 | K177: 12 | L177: 0 | M177: 12 | N177: 0
A178: wheat | B178: that is, 2 bushels an acre. | C178: 0 | D178: 0 | E178: 0 | F178: 0 | H178: 0 | I178: 2 | J178: 0.25 | K178: 0.25 | L178: 0 | M178: 0 | N178: 2
A179: wheat | B179: given to the customary tenants in 4 acres which they receive according to custom, 4 quarters. | C179: 0 | D179: 0 | E179: 0 | F179: 0 | H179: 4 | I179: 0 | J179: 4 | K179: 4 | L179: 0 | M179: 4 | N179: 0
A180: wheat | B180: provision of the steward at the tourns of martinmas and hockday, by 2 sealed bills, 2.5 bushels. | C180: 0 | D180: 0 | E180: 0 | F180: 0 | H180: 0 | I180: 2.5 | J180: 0.31 | K180: 0.31 | L180: 0 | M180: 0 | N180: 2.5
A181: wheat | B181: sold within, 36 quarters 6.5 bushels. | C181: 0 | D181: 0 | E181: 0 | F181: 0 | H181: 36 | I181: 6.5 | J181: 36.81 | K181: 36.81 | L181: 0 | M181: 36 | N181: 6.5
A182: wheat | B182: sold at the audit, 6 quarters' 3 bushels for £2 17 shilling 3pence. | C182: 2.86 | D182: 2 | E182: 17 | F182: 3 | H182: 6 | I182: 3 | J182: 6.38 | K182: 6 | L182: 0.38 | M182: 6 | N182: 0 | O182: 0 | P182: 3
A183: wheat | B183: total as before. | C183: 0 | D183: 0 | E183: 0 | F183: 0 | H183: 0 | I183: 0 | J183: 0 | K183: 0 | L183: 0 | M183: 0 | N183: 0
A184: wheat | B184: it balances. | C184: 0 | D184: 0 | E184: 0 | F184: 0 | H184: 0 | I184: 0 | J184: 0 | K184: 0 | L184: 0 | M184: 0 | N184: 0
A185: curall | B185: and for 4 quarters of curall from the issue of the said wheat, threshed by piece-work. | C185: 0 | D185: 0 | E185: 0 | F185: 0 | G185: wheat, curall | H185: 4 | I185: 0 | J185: 4 | K185: 4 | L185: 0 | M185: 4 | N185: 0
A186: curall | B186: sold within. | C186: 0 | D186: 0 | E186: 0 | F186: 0 | H186: 0 | I186: 0 | J186: 0 | K186: 0 | L186: 0 | M186: 0 | N186: 0
A187: curall | B187: none remains. | C187: 0 | D187: 0 | E187: 0 | F187: 0 | H187: 0 | I187: 0 | J187: 0 | K187: 0 | L187: 0 | M187: 0 | N187: 0
A188: barley | B188: and for 106 quarters 1 bushels of barley from the whole issue of the grange, threshed by piece¬work. | C188: 0 | D188: 0 | E188: 0 | F188: 0 | G188: barley | H188: 106 | I188: 1 | J188: 106.12 | K188: 106.12 | L188: 0 | M188: 106 | N188: 1
A189: barley | B189: 1 quarters 2 bushels by estimation in sheaves given for carrying the lord's corn at harvest-time. | C189: 0 | D189: 0 | E189: 0 | F189: 0 | H189: 1 | I189: 2 | J189: 1.25 | K189: 1.25 | L189: 0 | M189: 1 | N189: 2
A190: barley | B190: no corn given to the customary tenants for reaping this year because they were paid for their reaping service as made clear within. | C190: 0 | D190: 0 | E190: 0 | F190: 0 | H190: 0 | I190: 0 | J190: 0 | K190: 0 | L190: 0 | M190: 0 | N190: 0
A191: barley | B191: 11 quarters 3 bushels surcharged so that he answers for a 5.5-fold yield.. | C191: 0 | D191: 0 | E191: 0 | F191: 0 | H191: 11 | I191: 3 | J191: 11.38 | K191: 11.38 | L191: 0 | M191: 11 | N191: 3
A192: barley | B192: total, 118 quarters 6 bushels. | C192: 0 | D192: 0 | E192: 0 | F192: 0 | H192: 118 | I192: 6 | J192: 118.75 | K192: 118.75 | L192: 0 | M192: 118 | N192: 6
A193: barley | B193: sown over 42 acres, 21 quarters. | C193: 0 | D193: 0 | E193: 0 | F193: 0 | H193: 21 | I193: 0 | J193: 21 | K193: 21 | L193: 0 | M193: 21 | N193: 0
A194: barley | B194: that is, 4 bushels an acre. | C194: 0 | D194: 0 | E194: 0 | F194: 0 | H194: 0 | I194: 4 | J194: 0.5 | K194: 0.5 | L194: 0 | M194: 0 | N194: 4
A195: barley | B195: given for carrying the lord's corn at harvest-time, 1 quarters 2 bushels by estimation in sheaves. | C195: 0 | D195: 0 | E195: 0 | F195: 0 | H195: 1 | I195: 2 | J195: 1.25 | K195: 1.25 | L195: 0 | M195: 1 | N195: 2
A196: barley | B196: provision of 3 harvest boon-works, 2 quarters. | C196: 0 | D196: 0 | E196: 0 | F196: 0 | H196: 2 | I196: 0 | J196: 2 | K196: 2 | L196: 0 | M196: 2 | N196: 0
A197: barley | B197: liveries of the manorial servants below, 45 quarters.. | C197: 0 | D197: 0 | E197: 0 | F197: 0 | H197: 45 | I197: 0 | J197: 45 | K197: 45 | L197: 0 | M197: 45 | N197: 0
A198: barley | B198: sold within, 38 quarters 1 bushels. | C198: 0 | D198: 0 | E198: 0 | F198: 0 | H198: 38 | I198: 1 | J198: 38.12 | K198: 38.12 | L198: 0 | M198: 38 | N198: 1
A199: barley | B199: sold at the audit, 11 quarters 3 bushels for £3 8 shilling 3pence. | C199: 3.41 | D199: 3 | E199: 8 | F199: 3 | H199: 11 | I199: 3 | J199: 11.38 | K199: 11.38 | L199: 0 | M199: 11 | N199: 3
A200: barley | B200: total as before. | C200: 0 | D200: 0 | E200: 0 | F200: 0 | H200: 0 | I200: 0 | J200: 0 | K200: 0 | L200: 0 | M200: 0 | N200: 0
A201: barley | B201: it balances. | C201: 0 | D201: 0 | E201: 0 | F201: 0 | H201: 0 | I201: 0 | J201: 0 | K201: 0 | L201: 0 | M201: 0 | N201: 0
A202: oats | B202: and for 20 quarters 4 bushels of oats from the whole issue2 of the grange, threshed by piece¬work. | C202: 0 | D202: 0 | E202: 0 | F202: 0 | G202: oats | H202: 20 | I202: 4 | J202: 20.5 | K202: 20.5 | L202: 0 | M202: 20 | N202: 4
A203: oats | B203: 6 bushels by estimation in sheaves given for carrying the lord's corn at harvest-time. | C203: 0 | D203: 0 | E203: 0 | F203: 0 | H203: 0 | I203: 6 | J203: 0.75 | K203: 0.75 | L203: 0 | M203: 0 | N203: 6
A204: oats | B204: no sheaves given for reaping for the aforesaid reason. | C204: 0 | D204: 0 | E204: 0 | F204: 0 | H204: 0 | I204: 0 | J204: 0 | K204: 0 | L204: 0 | M204: 0 | N204: 0
A205: oats | B205: 5 quarters 6 bushels surcharged so that he answers for a 3-fold yield.. | C205: 0 | D205: 0 | E205: 0 | F205: 0 | H205: 5 | I205: 6 | J205: 5.75 | K205: 5.75 | L205: 0 | M205: 5 | N205: 6
A206: oats | B206: total, 27 quarters. | C206: 0 | D206: 0 | E206: 0 | F206: 0 | H206: 27 | I206: 0 | J206: 27 | K206: 27 | L206: 0 | M206: 27 | N206: 0
A207: oats | B207: sown over 20 acres, 10 quarters. | C207: 0 | D207: 0 | E207: 0 | F207: 0 | H207: 10 | I207: 0 | J207: 10 | K207: 10 | L207: 0 | M207: 10 | N207: 0
A208: oats | B208: that is, 4 bushels an acre. | C208: 0 | D208: 0 | E208: 0 | F208: 0 | H208: 0 | I208: 4 | J208: 0.5 | K208: 0.5 | L208: 0 | M208: 0 | N208: 4
A209: oats | B209: given for carrying the lord's corn at harvest-time, 6 bushels by estimation in sheaves. | C209: 0 | D209: 0 | E209: 0 | F209: 0 | H209: 0 | I209: 6 | J209: 0.75 | K209: 0.75 | L209: 0 | M209: 0 | N209: 6
A210: oats | B210: making meal for the pottage of the manorial servants for the year, 3 quarters. | C210: 0 | D210: 0 | E210: 0 | F210: 0 | G210: meal | H210: 3 | I210: 0 | J210: 3 | K210: 3 | L210: 0 | M210: 3 | N210: 0
A211: oats | B211: fodder of the horses of the steward at the tourns of martinmas and hockday, by 2 sealed bills, 2 quarters 7 bushels. | C211: 0 | D211: 0 | E211: 0 | F211: 0 | H211: 2 | I211: 7 | J211: 2.88 | K211: 2.88 | L211: 0 | M211: 2 | N211: 7
A212: oats | B212: sold within, 4 quarters 5 bushels. | C212: 0 | D212: 0 | E212: 0 | F212: 0 | H212: 4 | I212: 5 | J212: 4.62 | K212: 4.62 | L212: 0 | M212: 4 | N212: 5
A213: oats | B213: sold at the audit, 5 quarters 6 bushels for 17 shilling 3pence. | C213: 0.86 | D213: 0 | E213: 17 | F213: 3 | H213: 5 | I213: 6 | J213: 5.75 | K213: 5.75 | L213: 0 | M213: 5 | N213: 6
A214: oats | B214: total as before. | C214: 0 | D214: 0 | E214: 0 | F214: 0 | H214: 0 | I214: 0 | J214: 0 | K214: 0 | L214: 0 | M214: 0 | N214: 0
A215: oats | B215: it balances. | C215: 0 | D215: 0 | E215: 0 | F215: 0 | H215: 0 | I215: 0 | J215: 0 | K215: 0 | L215: 0 | M215: 0 | N215: 0
A216: peas | B216: and for 5 quarters 1 bushels of peas from the issue of the grange, threshed by the manorial servants. | C216: 0 | D216: 0 | E216: 0 | F216: 0 | G216: peas | H216: 5 | I216: 1 | J216: 5.12 | K216: 5.12 | L216: 0 | M216: 5 | N216: 1
A217: peas | B217: 2 quarters from the same issue by estimation in husks. | C217: 0 | D217: 0 | E217: 0 | F217: 0 | H217: 2 | I217: 0 | J217: 2 | K217: 2 | L217: 0 | M217: 2 | N217: 0
A218: peas | B218: 2 bushels by estimation in sheaves given for carrying the lord's corn at harvest-time. | C218: 0 | D218: 0 | E218: 0 | F218: 0 | H218: 0 | I218: 2 | J218: 0.25 | K218: 0.25 | L218: 0 | M218: 0 | N218: 2
A219: peas | B219: no sheaves given for reaping for the aforesaid reason.. | C219: 0 | D219: 0 | E219: 0 | F219: 0 | H219: 0 | I219: 0 | J219: 0 | K219: 0 | L219: 0 | M219: 0 | N219: 0
A220: peas | B220: total, 7 quarters 3 bushels. | C220: 0 | D220: 0 | E220: 0 | F220: 0 | H220: 7 | I220: 3 | J220: 7.38 | K220: 7.38 | L220: 0 | M220: 7 | N220: 3
A221: peas | B221: sown over 10 acres, 2 quarters 4 bushels. | C221: 0 | D221: 0 | E221: 0 | F221: 0 | H221: 2 | I221: 4 | J221: 2.5 | K221: 2.5 | L221: 0 | M221: 2 | N221: 4
A222: peas | B222: that is, 2 bushels an acre. | C222: 0 | D222: 0 | E222: 0 | F222: 0 | H222: 0 | I222: 2 | J222: 0.25 | K222: 0.25 | L222: 0 | M222: 0 | N222: 2
...

Sheet Stock_raw
A1: Heading | B1: Sentence | C1: Quarters 1 | D1: Bushels 1 | E1: stock | F1: inherited stock | G1: added | H1: murrain | I1: sold
A2: Vetches | B2: Total | C2: 0 | D2: 0
A3: Stock | B3: Plough-horses: 2 remain. | C3: 0 | D3: 0 | E3: Plough-horses | F3: 2
A4: Stock | B4: Oxen: 19 remain. | C4: 0 | D4: 0 | E4: Oxen | F4: 19
A5: Stock | B5: 1 added from steers below. | C5: 0 | D5: 0 | E5: Oxen
A6: Stock | B6: 2 bought within. | C6: 0 | D6: 0 | E6: Oxen | G6: 2
A7: Stock | B7: Total, 22. 3 sold within. | C7: 0 | D7: 0 | E7: Oxen | I7: 3
A8: Stock | B8: 19 remain. | C8: 0 | D8: 0 | E8: Oxen
A9: Stock | B9: Cows: 2 remain. | C9: 0 | D9: 0 | E9: Cows | F9: 2
A10: Stock | B10: Steers: 2 remain from the bullocks. | C10: 0 | D10: 0 | E10: Steers | F10: 2
A11: Stock | B11: Total, 2. 1 added above to oxen. | C11: 0 | D11: 0 | E11: Steers
A12: Stock | B12: 1 sold within because useless for the lord's stock. | C12: 0 | D12: 0 | E12: Steers | I12: 1
A13: Stock | B13: Total as before. | C13: 0 | D13: 0 | E13: Steers
A14: Stock | B14: None remain. | C14: 0 | D14: 0 | E14: Steers
A15: Stock | B15: Bullocks: 2 remain from the yearlings. | C15: 0 | D15: 0 | E15: Bullocks | F15: 2
A16: Stock | B16: 2 remain. | C16: 0 | D16: 0 | E16: Bullocks
A17: Stock | B17: Yearlings: 2 remain from the calves. | C17: 0 | D17: 0 | E17: Yearlings | F17: 2
A18: Stock | B18: 2 remain. | C18: 0 | D18: 0 | E18: Yearlings
A19: Stock | B19: Calves: 2 from the offspring of the said cows. | C19: 0 | D19: 0 | E19: Calves | G19: 2
A20: Stock | B20: 2 remain. | C20: 0 | D20: 0 | E20: Calves | F20: 2
A21: Stock | B21: Wethers: 354 remain. | C21: 0 | D21: 0 | E21: Wethers | F21: 354
A22: Stock | B22: 101 added from hoggs below after shearing. | C22: 0 | D22: 0 | E22: Wethers
A23: Stock | B23: Total, 455. 11 in murrain before shearing, 7 after shearing. | C23: 0 | D23: 0 | E23: Wethers | H23: 11
A24: Stock | B24: 2 in customary payment to the customary tenants after shearing for mowing the lord's meadow. | C24: 0 | D24: 0 | E24: Wethers
A25: Stock | B25: 35 kebbs sold within before shearing. | C25: 0 | D25: 0 | E25: Wethers | I25: 35
A26: Stock | B26: Total, 55. 400 remain. | C26: 0 | D26: 0 | E26: Wethers
A27: Stock | B27: Rams: 9 remain. | C27: 0 | D27: 0 | E27: Rams | F27: 9
A28: Stock | B28: Total, 9. 1 sold within before shearing. | C28: 0 | D28: 0 | E28: Rams | I28: 1
A29: Stock | B29: 8 remain. | C29: 0 | D29: 0 | E29: Rams
A30: Stock | B30: Ewes: 315 remain. | C30: 0 | D30: 0 | E30: Ewes | F30: 315
A31: Stock | B31: 90 added from hoggs below after shearing. | C31: 0 | D31: 0 | E31: Ewes
A32: Stock | B32: 1 from the heriot of Walter Pynnok' before shearing. | C32: 0 | D32: 0 | E32: Ewes
A33: Stock | B33: 1 from the heriot of John Godishalfe after shearing. | C33: 0 | D33: 0 | E33: Ewes
A34: Stock | B34: Total, 407. 11 in murrain before shearing and lambing. | C34: 0 | D34: 0 | E34: Ewes | H34: 11
A35: Stock | B35: 7 in murrain after shearing. | C35: 0 | D35: 0 | E35: Ewes | H35: 7
A36: Stock | B36: 55 kebbs sold within before shearing. | C36: 0 | D36: 0 | E36: Ewes | I36: 55
A37: Stock | B37: Total, 73. 334 remain. | C37: 0 | D37: 0 | E37: Ewes
A38: Stock | B38: Hoggs: 196 remain from the lambs. | C38: 0 | D38: 0 | E38: Hoggs | F38: 196
A39: Stock | B39: Total, 196. 5 in murrain before shearing. | C39: 0 | D39: 0 | E39: Hoggs | H39: 5
A40: Stock | B40: 101 added above to wethers and 90 to ewes after shearing. | C40: 0 | D40: 0 | E40: Hoggs
A41: Stock | B41: Total as before. | C41: 0 | D41: 0 | E41: Hoggs
A42: Stock | B42: None remain. | C42: 0 | D42: 0 | E42: Hoggs
A43: Stock | B43: Lambs: 246 from the offspring of the said ewes and not more because 11 ewes died before lambing and 58 were sterile this year. | C43: 0 | D43: 0 | E43: Lambs | G43: 246
A44: Stock | B44: 23 bought within before shearing. | C44: 0 | D44: 0 | E44: Lambs | G44: 23
A45: Stock | B45: Total, 269. 17 in murrain before weaning. | C45: 0 | D45: 0 | E45: Lambs | H45: 17
A46: Stock | B46: 23 in tithe. | C46: 0 | D46: 0 | E46: Lambs
A47: Stock | B47: 3 in customary payment to the reeve, smith and shepherd of ewes before shearing. | C47: 0 | D47: 0 | E47: Lambs
A48: Stock | B48: 4 in murrain after weaning and before shearing. | C48: 0 | D48: 0 | E48: Lambs | H48: 4
A49: Stock | B49: ' 16 removed from stock and sold within before shearing. | C49: 0 | D49: 0 | E49: Lambs | I49: 16
A50: Stock | B50: Total, 65. 204 remain. | C50: 0 | D50: 0 | E50: Lambs | F50: 204
A51: Stock | B51: Coarse wool: 318 fleeces from wethers, 8 from rams, 250 from ewes and 191 from hoggs produced at the shearing this year. | C51: 0 | D51: 0 | E51: Coarse wool
A52: Stock | B52: Total, 757.2 76 in tithe. | C52: 0 | D52: 0 | E52: Coarse wool
A53: Stock | B53: 2 given to the shepherd of wethers and shepherd of ewes. | C53: 0 | D53: 0 | E53: Coarse wool
A54: Stock | B54: 679 delivered to John Arnold', receiver of Wolvesey, weighing 2 sacks 29 cloves, answering for an average of 1.375 lb a fleece, plus 1 lb in all. | C54: 0 | D54: 0 | E54: Coarse wool
A55: Stock | B55: Total as before. | C55: 0 | D55: 0 | E55: Coarse wool
A56: Stock | B56: None remains. | C56: 0 | D56: 0 | E56: Coarse wool
A57: Stock | B57: Lamb's-wool: 208 fleeces from lambs produced at the shearing this year. | C57: 0 | D57: 0 | E57: Coarse wool
A58: Stock | B58: all sold within, weighing 10 cloves. | C58: 0 | D58: 0 | E58: Coarse wool
A59: Stock | B59: none remains. | C59: 0 | D59: 0 | E59: Coarse wool
A60: Stock | B60: Wool locks: 3 lb imposed on the shepherds at the shearing this year. | C60: 0 | D60: 0 | E60: Wool locks
A61: Stock | B61: sold within. | C61: 0 | D61: 0 | E61: Wool locks
A62: Stock | B62: none remain. | C62: 0 | D62: 0 | E62: Wool locks
... A64: Stock | B64: Total, 27. 3 in tithe. | C64: 0 | D64: 0 | E64: Woolskins
A65: Stock | B65: 24 sold within. | C65: 0 | D65: 0 | E65: Woolskins | I65: 24
A66: Stock | B66: Total as before. | C66: 0 | D66: 0 | E66: Woolskins
A67: Stock | B67: None remain. | C67: 0 | D67: 0 | E67: Woolskins
A68: Stock | B68: Bare skins: 7 from wethers and 7 from ewes in murrain as made clear above. | C68: 0 | D68: 0 | E68: Bareskins | H68: 7
A69: Stock | B69: sold within. | C69: 0 | D69: 0 | E69: Bareskins
A70: Stock | B70: none remain. | C70: 0 | D70: 0 | E70: Bareskins
A71: Stock | B71: Lambskins: 17 from lambs in murrain before weaning as made clear above. | C71: 0 | D71: 0 | E71: Lambskins | H71: 17
A72: Stock | B72: Total, 17. 2 in tithe. | C72: 0 | D72: 0 | E72: Lambskins
A73: Stock | B73: 15 sold within. | C73: 0 | D73: 0 | E73: Lambskins | I73: 15
A74: Stock | B74: Total as before. | C74: 0 | D74: 0 | E74: Lambskins
A75: Stock | B75: None remain. | C75: 0 | D75: 0 | E75: Lambskins
A76: Stock | B76: Rotted skins: 2 from lambs in murrain after weaning and before shearing as made clear above. | C76: 0 | D76: 0 | E76: Rotted skins | H76: 2
A77: Stock | B77: sold within. | C77: 0 | D77: 0 | E77: Rotted skins
A78: Stock | B78: none remain. | C78: 0 | D78: 0 | E78: Rotted skins
A79: Stock | B79: Shorn skins: 4 from lambs in murrain after shearing as made clear above. | C79: 0 | D79: 0 | E79: Shorn skins | H79: 4
A80: Stock | B80: sold within. | C80: 0 | D80: 0 | E80: Shorn skins
A81: Stock | B81: none remain. | C81: 0 | D81: 0 | E81: Shorn skins
A82: Stock | B82: Geese: 1 gander and 4 breeding geese remain. | C82: 0 | D82: 0 | E82: Poultry stock | F82: 1
A83: Stock | B83: 24 offspring. | C83: 0 | D83: 0 | E83: Poultry stock | G83: 24
A84: Stock | B84: Total, 29. 2 in tithe. | C84: 0 | D84: 0 | E84: Poultry stock
A85: Stock | B85: 22 sold within. | C85: 0 | D85: 0 | E85: Poultry stock | I85: 22
A86: Stock | B86: Total, 24. 1 gander and 4 breeding geese remain. | C86: 0 | D86: 0 | E86: Poultry stock
A87: Stock | B87: Capons: 24 remain. | C87: 0 | D87: 0 | E87: Poultry stock
A88: Stock | B88: 24 made from the chickens below. | C88: 0 | D88: 0 | E88: Poultry stock
A89: Stock | B89: Total, 48. 24 sold within. | C89: 0 | D89: 0 | E89: Poultry stock | I89: 24
A90: Stock | B90: Total, 24. 24 remain. | C90: 0 | D90: 0 | E90: Poultry stock
A91: Stock | B91: Cocks and hens: 1 cock and 5 hens remain. | C91: 0 | D91: 0 | E91: Poultry stock
A92: Stock | B92: Chickens: 24 from the offspring of the hens. | C92: 0 | D92: 0 | E92: Poultry stock | G92: 24
A93: Stock | B93: all turned into capons above. | C93: 0 | D93: 0 | E93: Poultry stock
A94: Stock | B94: none remain. | C94: 0 | D94: 0 | E94: Poultry stock
A95: Stock | B95: Eggs: 200 produced by the said hens. | C95: 0 | D95: 0 | E95: Poultry production
A96: Stock | B96: sold within. | C96: 0 | D96: 0 | E96: Poultry production
A97: Stock | B97: none remain. | C97: 0 | D97: 0 | E97: Poultry production
A98: Stock | B98: Cocks and hens: 88 from the churchscot of the customary tenants at Martinmas. | C98: 0 | D98: 0 | E98: Poultry stock
A99: Stock | B99: Total, 88. 8 in default of 1 half-virgate of land released to John Danyel. | C99: 0 | D99: 0 | E99: Poultry stock
A100: Stock | B100: 24 in default of 1 half-virgate of land formerly of Richard atte Style, 1 half-virgate of land formerly of John Salisbury, 1 half-virgate of land formerly of John atte Holme, 1 half-virgate of land formerly of John Dryvere, 1 half-virgate of land formerly of Adam Berewyke and 1 half-virgate of land formerly of Gunnora Burgeys because in the lord's hands. | C100: 0 | D100: 0 | E100: Poultry stock
A101: Stock | B101: 8 in default of 1 half-virgate of land formerly of Hugh Durant and 1 half-virgate of land formerly of John Apert because in the lord's hands. | C101: 0 | D101: 0 | E101: Poultry stock
...

Sheet Issues of the Mills

Sheet Prices

Sheet Labour Rents

Sheet not needed

Sheet Issues of the Grange raw
A1: Heading | B1: Sentence | C1: Quarters 1_x | D1: Bushels 1_x | E1: Sown Quarters | F1: Sown Bushels | G1: Sown Total Quarters | H1: Bought in Quarters | I1: Bought in Bushels | J1: Bought in Total Quarters | K1: Tithe Quarters | L1: Tithe Bushels | M1: Tithe Total Quarters | N1: Manorial servants & livestock Quarters | O1: Manorial servants & livestock Bushels | P1: Manorial servants & livestock Total Quarters | Q1: Sold Quarters | R1: Sold Bushels | S1: Sold Total Quarters | T1: Account Quarters | U1: Account Bushels | V1: Account Total Quarters | W1: bought only | X1: Total Quarters Except 1 | Y1: Total Bushels Except 1 | Z1: Total Corn Cross-Check | AA1: Total Corn Manorial Account | AB1: Corn Quantity Error | AC1: Quarters 1_y | AD1: Bushels 1_y | AE1: Quarters 2 | AF1: Bushels 2 | AG1: Quarters 3 | AH1: Bushels 3 | AI1: Total Bought Quarters
A2: total of all allowances and cash deliveries | B2: total | C2: 0 | D2: 0 | E2: 0 | F2: 0 | G2: 0 | H2: 0 | I2: 0 | J2: 0 | K2: 0 | L2: 0 | M2: 0 | N2: 0 | O2: 0 | P2: 0 | Q2: 0 | R2: 0 | S2: 0 | T2: 0 | U2: 0 | V2: 0 | W2: 0 | AI2: 0
A3: wheat | B3: john algare, reeve there, answers for 49 quarters 1 bushels of wheat from the whole issue of the grange, threshed by piece-work. | C3: 0 | D3: 0 | E3: 0 | F3: 0 | G3: 0 | H3: 0 | I3: 0 | J3: 0 | K3: 0 | L3: 0 | M3: 0 | N3: 0 | O3: 0 | P3: 0 | Q3: 0 | R3: 0 | S3: 0 | T3: 49 | U3: 1 | V3: 49.12 | W3: 0 | X3: 49 | Y3: 1 | Z3: 49.12 | AA3: 49.12 | AB3: 0 | AC3: 49 | AD3: 1 | AI3: 0
A4: wheat | B4: 4 quarters by estimation in sheaves in 4 acres, of which 1 is for the reeve, 1 for the men of croucheston and netton, 1 for the men of bishopstone, and 1 for all the manorial servants of the curia. | C4: 0 | D4: 0 | E4: 0 | F4: 0 | G4: 0 | H4: 0 | I4: 0 | J4: 0 | K4: 0 | L4: 0 | M4: 0 | N4: 0 | O4: 0 | P4: 0 | Q4: 0 | R4: 0 | S4: 0 | T4: 0 | U4: 0 | V4: 0 | W4: 0 | X4: 4 | Y4: 0 | Z4: 4 | AA4: 4 | AB4: 0 | AC4: 4 | AD4: 0 | AI4: 0
A5: wheat | B5: 5 quarters 3 bushels surcharged so that he answers for a 5-fold yield.. | C5: 0 | D5: 0 | E5: 0 | F5: 0 | G5: 0 | H5: 0 | I5: 0 | J5: 0 | K5: 0 | L5: 0 | M5: 0 | N5: 0 | O5: 0 | P5: 0 | Q5: 0 | R5: 0 | S5: 0 | T5: 0 | U5: 0 | V5: 0 | W5: 0 | X5: 5 | Y5: 3 | Z5: 5.38 | AA5: 5.38 | AB5: 0 | AC5: 5 | AD5: 3 | AI5: 0
A6: wheat | B6: total, 58 quarters 4 bushels. | C6: 0 | D6: 0 | E6: 0 | F6: 0 | G6: 0 | H6: 0 | I6: 0 | J6: 0 | K6: 0 | L6: 0 | M6: 0 | N6: 0 | O6: 0 | P6: 0 | Q6: 0 | R6: 0 | S6: 0 | T6: 0 | U6: 0 | V6: 0 | W6: 0 | X6: 58 | Y6: 4 | Z6: 58.5 | AA6: 58.5 | AB6: 0 | AC6: 58 | AD6: 4 | AI6: 0
A7: wheat | B7: sown over 48 acres, 12 quarters. | C7: 0 | D7: 0 | E7: 12 | F7: 0 | G7: 12 | H7: 0 | I7: 0 | J7: 0 | K7: 0 | L7: 0 | M7: 0 | N7: 0 | O7: 0 | P7: 0 | Q7: 0 | R7: 0 | S7: 0 | T7: 0 | U7: 0 | V7: 0 | W7: 0 | X7: 12 | Y7: 0 | Z7: 12 | AA7: 12 | AB7: 0 | AC7: 12 | AD7: 0 | AI7: 0
A8: wheat | B8: that is, 2 bushels an acre. | C8: 0 | D8: 0 | E8: 0 | F8: 0 | G8: 0 | H8: 0 | I8: 0 | J8: 0 | K8: 0 | L8: 0 | M8: 0 | N8: 0 | O8: 0 | P8: 0 | Q8: 0 | R8: 0 | S8: 0 | T8: 0 | U8: 0 | V8: 0 | W8: 0 | X8: 0 | Y8: 2 | Z8: 0.25 | AA8: 0.25 | AB8: 0 | AC8: 0 | AD8: 2 | AI8: 0
A9: wheat | B9: given to the customary tenants in 4 acres which they receive according to custom, 4 quarters. | C9: 0 | D9: 0 | E9: 0 | F9: 0 | G9: 0 | H9: 0 | I9: 0 | J9: 0 | K9: 0 | L9: 0 | M9: 0 | N9: 0 | O9: 0 | P9: 0 | Q9: 0 | R9: 0 | S9: 0 | T9: 0 | U9: 0 | V9: 0 | W9: 0 | X9: 4 | Y9: 0 | Z9: 4 | AA9: 4 | AB9: 0 | AC9: 4 | AD9: 0 | AI9: 0
A10: wheat | B10: provision of the steward at the tourns of martinmas and hockday, by 2 sealed bills, 2.5 bushels. | C10: 0 | D10: 0 | E10: 0 | F10: 0 | G10: 0 | H10: 0 | I10: 0 | J10: 0 | K10: 0 | L10: 0 | M10: 0 | N10: 0 | O10: 0 | P10: 0 | Q10: 0 | R10: 0 | S10: 0 | T10: 0 | U10: 0 | V10: 0 | W10: 0 | X10: 0 | Y10: 2.5 | Z10: 0.31 | AA10: 0.31 | AB10: 0 | AC10: 0 | AD10: 2.5 | AI10: 0
A11: wheat | B11: sold within, 36 quarters 6.5 bushels. | C11: 0 | D11: 0 | E11: 0 | F11: 0 | G11: 0 | H11: 0 | I11: 0 | J11: 0 | K11: 0 | L11: 0 | M11: 0 | N11: 0 | O11: 0 | P11: 0 | Q11: 36 | R11: 6.5 | S11: 36.81 | T11: 0 | U11: 0 | V11: 0 | W11: 0 | X11: 36 | Y11: 6.5 | Z11: 36.81 | AA11: 36.81 | AB11: 0 | AC11: 36 | AD11: 6.5 | AI11: 0
A12: wheat | B12: sold at the audit, 6 quarters' 3 bushels for £2 17 shilling 3pence. | C12: 0 | D12: 0 | E12: 0 | F12: 0 | G12: 0 | H12: 0 | I12: 0 | J12: 0 | K12: 0 | L12: 0 | M12: 0 | N12: 0 | O12: 0 | P12: 0 | Q12: 6 | R12: 0 | S12: 6 | T12: 0 | U12: 0 | V12: 0 | W12: 0 | X12: 6 | Y12: 3 | Z12: 6.38 | AA12: 6 | AB12: 0.38 | AC12: 6 | AD12: 0 | AE12: 0 | AF12: 3 | AI12: 0
A13: wheat | B13: total as before. | C13: 0 | D13: 0 | E13: 0 | F13: 0 | G13: 0 | H13: 0 | I13: 0 | J13: 0 | K13: 0 | L13: 0 | M13: 0 | N13: 0 | O13: 0 | P13: 0 | Q13: 0 | R13: 0 | S13: 0 | T13: 0 | U13: 0 | V13: 0 | W13: 0 | X13: 0 | Y13: 0 | Z13: 0 | AA13: 0 | AB13: 0 | AC13: 0 | AD13: 0 | AI13: 0
A14: wheat | B14: it balances. | C14: 0 | D14: 0 | E14: 0 | F14: 0 | G14: 0 | H14: 0 | I14: 0 | J14: 0 | K14: 0 | L14: 0 | M14: 0 | N14: 0 | O14: 0 | P14: 0 | Q14: 0 | R14: 0 | S14: 0 | T14: 0 | U14: 0 | V14: 0 | W14: 0 | X14: 0 | Y14: 0 | Z14: 0 | AA14: 0 | AB14: 0 | AC14: 0 | AD14: 0 | AI14: 0
A15: wheat | B15: total | C15: 0 | D15: 0 | E15: 0 | F15: 0 | G15: 0 | H15: 0 | I15: 0 | J15: 0 | K15: 0 | L15: 0 | M15: 0 | N15: 0 | O15: 0 | P15: 0 | Q15: 0 | R15: 0 | S15: 0 | T15: 0 | U15: 0 | V15: 0 | W15: 0 | AI15: 0
A16: curall | B16: and for 4 quarters of curall from the issue of the said wheat, threshed by piece-work. | C16: 0 | D16: 0 | E16: 0 | F16: 0 | G16: 0 | H16: 0 | I16: 0 | J16: 0 | K16: 0 | L16: 0 | M16: 0 | N16: 0 | O16: 0 | P16: 0 | Q16: 0 | R16: 0 | S16: 0 | T16: 0 | U16: 0 | V16: 0 | W16: 0 | X16: 4 | Y16: 0 | Z16: 4 | AA16: 4 | AB16: 0 | AC16: 4 | AD16: 0 | AI16: 0
A17: curall | B17: sold within. | C17: 0 | D17: 0 | E17: 0 | F17: 0 | G17: 0 | H17: 0 | I17: 0 | J17: 0 | K17: 0 | L17: 0 | M17: 0 | N17: 0 | O17: 0 | P17: 0 | Q17: 0 | R17: 0 | S17: 0 | T17: 0 | U17: 0 | V17: 0 | W17: 0 | X17: 0 | Y17: 0 | Z17: 0 | AA17: 0 | AB17: 0 | AC17: 0 | AD17: 0 | AI17: 0
A18: curall | B18: none remains. | C18: 0 | D18: 0 | E18: 0 | F18: 0 | G18: 0 | H18: 0 | I18: 0 | J18: 0 | K18: 0 | L18: 0 | M18: 0 | N18: 0 | O18: 0 | P18: 0 | Q18: 0 | R18: 0 | S18: 0 | T18: 0 | U18: 0 | V18: 0 | W18: 0 | X18: 0 | Y18: 0 | Z18: 0 | AA18: 0 | AB18: 0 | AC18: 0 | AD18: 0 | AI18: 0
A19: curall | B19: total | C19: 0 | D19: 0 | E19: 0 | F19: 0 | G19: 0 | H19: 0 | I19: 0 | J19: 0 | K19: 0 | L19: 0 | M19: 0 | N19: 0 | O19: 0 | P19: 0 | Q19: 0 | R19: 0 | S19: 0 | T19: 0 | U19: 0 | V19: 0 | W19: 0 | AI19: 0
A20: barley | B20: and for 106 quarters 1 bushels of barley from the whole issue of the grange, threshed by piece¬work. | C20: 0 | D20: 0 | E20: 0 | F20: 0 | G20: 0 | H20: 0 | I20: 0 | J20: 0 | K20: 0 | L20: 0 | M20: 0 | N20: 0 | O20: 0 | P20: 0 | Q20: 0 | R20: 0 | S20: 0 | T20: 106 | U20: 1 | V20: 106.12 | W20: 0 | X20: 106 | Y20: 1 | Z20: 106.12 | AA20: 106.12 | AB20: 0 | AC20: 106 | AD20: 1 | AI20: 0
A21: barley | B21: 1 qr 2 bushels by estimation in sheaves given for carrying the lord's corn at harvest-time. | C21: 0 | D21: 0 | E21: 0 | F21: 0 | G21: 0 | H21: 0 | I21: 0 | J21: 0 | K21: 0 | L21: 0 | M21: 0 | N21: 0 | O21: 0 | P21: 0 | Q21: 0 | R21: 0 | S21: 0 | T21: 0 | U21: 0 | V21: 0 | W21: 0 | AI21: 0
A22: barley | B22: no corn given to the customary tenants for reaping this year because they were paid for their reaping service as made clear within. | C22: 0 | D22: 0 | E22: 0 | F22: 0 | G22: 0 | H22: 0 | I22: 0 | J22: 0 | K22: 0 | L22: 0 | M22: 0 | N22: 0 | O22: 0 | P22: 0 | Q22: 0 | R22: 0 | S22: 0 | T22: 0 | U22: 0 | V22: 0 | W22: 0 | X22: 0 | Y22: 0 | Z22: 0 | AA22: 0 | AB22: 0 | AC22: 0 | AD22: 0 | AI22: 0
A23: barley | B23: 11 quarters 3 bushels surcharged so that he answers for a 5.5-fold yield.. | C23: 0 | D23: 0 | E23: 0 | F23: 0 | G23: 0 | H23: 0 | I23: 0 | J23: 0 | K23: 0 | L23: 0 | M23: 0 | N23: 0 | O23: 0 | P23: 0 | Q23: 0 | R23: 0 | S23: 0 | T23: 0 | U23: 0 | V23: 0 | W23: 0 | X23: 11 | Y23: 3 | Z23: 11.38 | AA23: 11.38 | AB23: 0 | AC23: 11 | AD23: 3 | AI23: 0
A24: barley | B24: total, 118 quarters 6 bushels. | C24: 0 | D24: 0 | E24: 0 | F24: 0 | G24: 0 | H24: 0 | I24: 0 | J24: 0 | K24: 0 | L24: 0 | M24: 0 | N24: 0 | O24: 0 | P24: 0 | Q24: 0 | R24: 0 | S24: 0 | T24: 0 | U24: 0 | V24: 0 | W24: 0 | X24: 118 | Y24: 6 | Z24: 118.75 | AA24: 118.75 | AB24: 0 | AC24: 118 | AD24: 6 | AI24: 0
A25: barley | B25: sown over 42 acres, 21 quarters. | C25: 0 | D25: 0 | E25: 21 | F25: 0 | G25: 21 | H25: 0 | I25: 0 | J25: 0 | K25: 0 | L25: 0 | M25: 0 | N25: 0 | O25: 0 | P25: 0 | Q25: 0 | R25: 0 | S25: 0 | T25: 0 | U25: 0 | V25: 0 | W25: 0 | X25: 21 | Y25: 0 | Z25: 21 | AA25: 21 | AB25: 0 | AC25: 21 | AD25: 0 | AI25: 0
A26: barley | B26: that is, 4 bushels an acre. | C26: 0 | D26: 0 | E26: 0 | F26: 0 | G26: 0 | H26: 0 | I26: 0 | J26: 0 | K26: 0 | L26: 0 | M26: 0 | N26: 0 | O26: 0 | P26: 0 | Q26: 0 | R26: 0 | S26: 0 | T26: 0 | U26: 0 | V26: 0 | W26: 0 | X26: 0 | Y26: 4 | Z26: 0.5 | AA26: 0.5 | AB26: 0 | AC26: 0 | AD26: 4 | AI26: 0
A27: barley | B27: given for carrying the lord's corn at harvest-time, 1 qr 2 bushels by estimation in sheaves. | C27: 0 | D27: 0 | E27: 0 | F27: 0 | G27: 0 | H27: 0 | I27: 0 | J27: 0 | K27: 0 | L27: 0 | M27: 0 | N27: 0 | O27: 0 | P27: 0 | Q27: 0 | R27: 0 | S27: 0 | T27: 0 | U27: 0 | V27: 0 | W27: 0 | AI27: 0
A28: barley | B28: provision of 3 harvest boon-works, 2 quarters. | C28: 0 | D28: 0 | E28: 0 | F28: 0 | G28: 0 | H28: 0 | I28: 0 | J28: 0 | K28: 0 | L28: 0 | M28: 0 | N28: 0 | O28: 0 | P28: 0 | Q28: 0 | R28: 0 | S28: 0 | T28: 0 | U28: 0 | V28: 0 | W28: 0 | X28: 2 | Y28: 0 | Z28: 2 | AA28: 2 | AB28: 0 | AC28: 2 | AD28: 0 | AI28: 0
A29: barley | B29: liveries of the manorial servants below, 45 quarters.. | C29: 0 | D29: 0 | E29: 0 | F29: 0 | G29: 0 | H29: 0 | I29: 0 | J29: 0 | K29: 0 | L29: 0 | M29: 0 | N29: 0 | O29: 0 | P29: 0 | Q29: 0 | R29: 0 | S29: 0 | T29: 0 | U29: 0 | V29: 0 | W29: 0 | X29: 45 | Y29: 0 | Z29: 45 | AA29: 45 | AB29: 0 | AC29: 45 | AD29: 0 | AI29: 0
A30: barley | B30: sold within, 38 quarters 1 bushels. | C30: 0 | D30: 0 | E30: 0 | F30: 0 | G30: 0 | H30: 0 | I30: 0 | J30: 0 | K30: 0 | L30: 0 | M30: 0 | N30: 0 | O30: 0 | P30: 0 | Q30: 38 | R30: 1 | S30: 38.12 | T30: 0 | U30: 0 | V30: 0 | W30: 0 | X30: 38 | Y30: 1 | Z30: 38.12 | AA30: 38.12 | AB30: 0 | AC30: 38 | AD30: 1 | AI30: 0
A31: barley | B31: sold at the audit, 11 quarters 3 bushels for £3 8 shilling 3pence. | C31: 0 | D31: 0 | E31: 0 | F31: 0 | G31: 0 | H31: 0 | I31: 0 | J31: 0 | K31: 0 | L31: 0 | M31: 0 | N31: 0 | O31: 0 | P31: 0 | Q31: 11 | R31: 3 | S31: 11.38 | T31: 0 | U31: 0 | V31: 0 | W31: 0 | X31: 11 | Y31: 3 | Z31: 11.38 | AA31: 11.38 | AB31: 0 | AC31: 11 | AD31: 3 | AI31: 0
A32: barley | B32: total as before. | C32: 0 | D32: 0 | E32: 0 | F32: 0 | G32: 0 | H32: 0 | I32: 0 | J32: 0 | K32: 0 | L32: 0 | M32: 0 | N32: 0 | O32: 0 | P32: 0 | Q32: 0 | R32: 0 | S32: 0 | T32: 0 | U32: 0 | V32: 0 | W32: 0 | X32: 0 | Y32: 0 | Z32: 0 | AA32: 0 | AB32: 0 | AC32: 0 | AD32: 0 | AI32: 0
A33: barley | B33: it balances. | C33: 0 | D33: 0 | E33: 0 | F33: 0 | G33: 0 | H33: 0 | I33: 0 | J33: 0 | K33: 0 | L33: 0 | M33: 0 | N33: 0 | O33: 0 | P33: 0 | Q33: 0 | R33: 0 | S33: 0 | T33: 0 | U33: 0 | V33: 0 | W33: 0 | X33: 0 | Y33: 0 | Z33: 0 | AA33: 0 | AB33: 0 | AC33: 0 | AD33: 0 | AI33: 0
A34: barley | B34: total | C34: 0 | D34: 0 | E34: 0 | F34: 0 | G34: 0 | H34: 0 | I34: 0 | J34: 0 | K34: 0 | L34: 0 | M34: 0 | N34: 0 | O34: 0 | P34: 0 | Q34: 0 | R34: 0 | S34: 0 | T34: 0 | U34: 0 | V34: 0 | W34: 0 | AI34: 0
A35: oats | B35: and for 20 quarters 4 bushels of oats from the whole issue2 of the grange, threshed by piece¬work. | C35: 0 | D35: 0 | E35: 0 | F35: 0 | G35: 0 | H35: 0 | I35: 0 | J35: 0 | K35: 0 | L35: 0 | M35: 0 | N35: 0 | O35: 0 | P35: 0 | Q35: 0 | R35: 0 | S35: 0 | T35: 20 | U35: 4 | V35: 20.5 | W35: 0 | X35: 20 | Y35: 4 | Z35: 20.5 | AA35: 20.5 | AB35: 0 | AC35: 20 | AD35: 4 | AI35: 0
A36: oats | B36: 6 bushels by estimation in sheaves given for carrying the lord's corn at harvest-time. | C36: 0 | D36: 0 | E36: 0 | F36: 0 | G36: 0 | H36: 0 | I36: 0 | J36: 0 | K36: 0 | L36: 0 | M36: 0 | N36: 0 | O36: 0 | P36: 0 | Q36: 0 | R36: 0 | S36: 0 | T36: 0 | U36: 0 | V36: 0 | W36: 0 | X36: 0 | Y36: 6 | Z36: 0.75 | AA36: 0.75 | AB36: 0 | AC36: 0 | AD36: 6 | AI36: 0
A37: oats | B37: no sheaves given for reaping for the aforesaid reason. | C37: 0 | D37: 0 | E37: 0 | F37: 0 | G37: 0 | H37: 0 | I37: 0 | J37: 0 | K37: 0 | L37: 0 | M37: 0 | N37: 0 | O37: 0 | P37: 0 | Q37: 0 | R37: 0 | S37: 0 | T37: 0 | U37: 0 | V37: 0 | W37: 0 | X37: 0 | Y37: 0 | Z37: 0 | AA37: 0 | AB37: 0 | AC37: 0 | AD37: 0 | AI37: 0
A38: oats | B38: 5 quarters 6 bushels surcharged so that he answers for a 3-fold yield.. | C38: 0 | D38: 0 | E38: 0 | F38: 0 | G38: 0 | H38: 0 | I38: 0 | J38: 0 | K38: 0 | L38: 0 | M38: 0 | N38: 0 | O38: 0 | P38: 0 | Q38: 0 | R38: 0 | S38: 0 | T38: 0 | U38: 0 | V38: 0 | W38: 0 | X38: 5 | Y38: 6 | Z38: 5.75 | AA38: 5.75 | AB38: 0 | AC38: 5 | AD38: 6 | AI38: 0
A39: oats | B39: total, 27 quarters. | C39: 0 | D39: 0 | E39: 0 | F39: 0 | G39: 0 | H39: 0 | I39: 0 | J39: 0 | K39: 0 | L39: 0 | M39: 0 | N39: 0 | O39: 0 | P39: 0 | Q39: 0 | R39: 0 | S39: 0 | T39: 0 | U39: 0 | V39: 0 | W39: 0 | X39: 27 | Y39: 0 | Z39: 27 | AA39: 27 | AB39: 0 | AC39: 27 | AD39: 0 | AI39: 0
A40: oats | B40: sown over 20 acres, 10 quarters. | C40: 0 | D40: 0 | E40: 10 | F40: 0 | G40: 10 | H40: 0 | I40: 0 | J40: 0 | K40: 0 | L40: 0 | M40: 0 | N40: 0 | O40: 0 | P40: 0 | Q40: 0 | R40: 0 | S40: 0 | T40: 0 | U40: 0 | V40: 0 | W40: 0 | X40: 10 | Y40: 0 | Z40: 10 | AA40: 10 | AB40: 0 | AC40: 10 | AD40: 0 | AI40: 0
A41: oats | B41: that is, 4 bushels an acre. | C41: 0 | D41: 0 | E41: 0 | F41: 0 | G41: 0 | H41: 0 | I41: 0 | J41: 0 | K41: 0 | L41: 0 | M41: 0 | N41: 0 | O41: 0 | P41: 0 | Q41: 0 | R41: 0 | S41: 0 | T41: 0 | U41: 0 | V41: 0 | W41: 0 | X41: 0 | Y41: 4 | Z41: 0.5 | AA41: 0.5 | AB41: 0 | AC41: 0 | AD41: 4 | AI41: 0
A42: oats | B42: given for carrying the lord's corn at harvest-time, 6 bushels by estimation in sheaves. | C42: 0 | D42: 0 | E42: 0 | F42: 0 | G42: 0 | H42: 0 | I42: 0 | J42: 0 | K42: 0 | L42: 0 | M42: 0 | N42: 0 | O42: 0 | P42: 0 | Q42: 0 | R42: 0 | S42: 0 | T42: 0 | U42: 0 | V42: 0 | W42: 0 | X42: 0 | Y42: 6 | Z42: 0.75 | AA42: 0.75 | AB42: 0 | AC42: 0 | AD42: 6 | AI42: 0
A43: oats | B43: making meal for the pottage of the manorial servants for the year, 3 quarters. | C43: 0 | D43: 0 | E43: 0 | F43: 0 | G43: 0 | H43: 0 | I43: 0 | J43: 0 | K43: 0 | L43: 0 | M43: 0 | N43: 0 | O43: 0 | P43: 0 | Q43: 0 | R43: 0 | S43: 0 | T43: 0 | U43: 0 | V43: 0 | W43: 0 | X43: 3 | Y43: 0 | Z43: 3 | AA43: 3 | AB43: 0 | AC43: 3 | AD43: 0 | AI43: 0
A44: oats | B44: fodder of the horses of the steward at the tourns of martinmas and hockday, by 2 sealed bills, 2 quarters 7 bushels. | C44: 0 | D44: 0 | E44: 0 | F44: 0 | G44: 0 | H44: 0 | I44: 0 | J44: 0 | K44: 0 | L44: 0 | M44: 0 | N44: 2 | O44: 7 | P44: 2.88 | Q44: 0 | R44: 0 | S44: 0 | T44: 0 | U44: 0 | V44: 0 | W44: 0 | X44: 2 | Y44: 7 | Z44: 2.88 | AA44: 2.88 | AB44: 0 | AC44: 2 | AD44: 7 | AI44: 0
A45: oats | B45: sold within, 4 quarters 5 bushels. | C45: 0 | D45: 0 | E45: 0 | F45: 0 | G45: 0 | H45: 0 | I45: 0 | J45: 0 | K45: 0 | L45: 0 | M45: 0 | N45: 0 | O45: 0 | P45: 0 | Q45: 4 | R45: 5 | S45: 4.62 | T45: 0 | U45: 0 | V45: 0 | W45: 0 | X45: 4 | Y45: 5 | Z45: 4.62 | AA45: 4.62 | AB45: 0 | AC45: 4 | AD45: 5 | AI45: 0
A46: oats | B46: sold at the audit, 5 quarters 6 bushels for 17 shilling 3pence. | C46: 0 | D46: 0 | E46: 0 | F46: 0 | G46: 0 | H46: 0 | I46: 0 | J46: 0 | K46: 0 | L46: 0 | M46: 0 | N46: 0 | O46: 0 | P46: 0 | Q46: 5 | R46: 6 | S46: 5.75 | T46: 0 | U46: 0 | V46: 0 | W46: 0 | X46: 5 | Y46: 6 | Z46: 5.75 | AA46: 5.75 | AB46: 0 | AC46: 5 | AD46: 6 | AI46: 0
... A48: oats | B48: it balances. | C48: 0 | D48: 0 | E48: 0 | F48: 0 | G48: 0 | H48: 0 | I48: 0 | J48: 0 | K48: 0 | L48: 0 | M48: 0 | N48: 0 | O48: 0 | P48: 0 | Q48: 0 | R48: 0 | S48: 0 | T48: 0 | U48: 0 | V48: 0 | W48: 0 | X48: 0 | Y48: 0 | Z48: 0 | AA48: 0 | AB48: 0 | AC48: 0 | AD48: 0 | AI48: 0
A49: oats | B49: total | C49: 0 | D49: 0 | E49: 0 | F49: 0 | G49: 0 | H49: 0 | I49: 0 | J49: 0 | K49: 0 | L49: 0 | M49: 0 | N49: 0 | O49: 0 | P49: 0 | Q49: 0 | R49: 0 | S49: 0 | T49: 0 | U49: 0 | V49: 0 | W49: 0 | AI49: 0
A50: peas | B50: and for 5 quarters 1 bushels of peas from the issue of the grange, threshed by the manorial servants. | C50: 0 | D50: 0 | E50: 0 | F50: 0 | G50: 0 | H50: 0 | I50: 0 | J50: 0 | K50: 0 | L50: 0 | M50: 0 | N50: 0 | O50: 0 | P50: 0 | Q50: 0 | R50: 0 | S50: 0 | T50: 0 | U50: 0 | V50: 0 | W50: 0 | X50: 5 | Y50: 1 | Z50: 5.12 | AA50: 5.12 | AB50: 0 | AC50: 5 | AD50: 1 | AI50: 0
A51: peas | B51: 2 quarters from the same issue by estimation in husks. | C51: 0 | D51: 0 | E51: 0 | F51: 0 | G51: 0 | H51: 0 | I51: 0 | J51: 0 | K51: 0 | L51: 0 | M51: 0 | N51: 0 | O51: 0 | P51: 0 | Q51: 0 | R51: 0 | S51: 0 | T51: 0 | U51: 0 | V51: 0 | W51: 0 | X51: 2 | Y51: 0 | Z51: 2 | AA51: 2 | AB51: 0 | AC51: 2 | AD51: 0 | AI51: 0
A52: peas | B52: 2 bushels by estimation in sheaves given for carrying the lord's corn at harvest-time. | C52: 0 | D52: 0 | E52: 0 | F52: 0 | G52: 0 | H52: 0 | I52: 0 | J52: 0 | K52: 0 | L52: 0 | M52: 0 | N52: 0 | O52: 0 | P52: 0 | Q52: 0 | R52: 0 | S52: 0 | T52: 0 | U52: 0 | V52: 0 | W52: 0 | X52: 0 | Y52: 2 | Z52: 0.25 | AA52: 0.25 | AB52: 0 | AC52: 0 | AD52: 2 | AI52: 0
A53: peas | B53: no sheaves given for reaping for the aforesaid reason.. | C53: 0 | D53: 0 | E53: 0 | F53: 0 | G53: 0 | H53: 0 | I53: 0 | J53: 0 | K53: 0 | L53: 0 | M53: 0 | N53: 0 | O53: 0 | P53: 0 | Q53: 0 | R53: 0 | S53: 0 | T53: 0 | U53: 0 | V53: 0 | W53: 0 | X53: 0 | Y53: 0 | Z53: 0 | AA53: 0 | AB53: 0 | AC53: 0 | AD53: 0 | AI53: 0
A54: peas | B54: total, 7 quarters 3 bushels. | C54: 0 | D54: 0 | E54: 0 | F54: 0 | G54: 0 | H54: 0 | I54: 0 | J54: 0 | K54: 0 | L54: 0 | M54: 0 | N54: 0 | O54: 0 | P54: 0 | Q54: 0 | R54: 0 | S54: 0 | T54: 0 | U54: 0 | V54: 0 | W54: 0 | X54: 7 | Y54: 3 | Z54: 7.38 | AA54: 7.38 | AB54: 0 | AC54: 7 | AD54: 3 | AI54: 0
A55: peas | B55: sown over 10 acres, 2 quarters 4 bushels. | C55: 0 | D55: 0 | E55: 2 | F55: 4 | G55: 2.5 | H55: 0 | I55: 0 | J55: 0 | K55: 0 | L55: 0 | M55: 0 | N55: 0 | O55: 0 | P55: 0 | Q55: 0 | R55: 0 | S55: 0 | T55: 0 | U55: 0 | V55: 0 | W55: 0 | X55: 2 | Y55: 4 | Z55: 2.5 | AA55: 2.5 | AB55: 0 | AC55: 2 | AD55: 4 | AI55: 0
A56: peas | B56: that is, 2 bushels an acre. | C56: 0 | D56: 0 | E56: 0 | F56: 0 | G56: 0 | H56: 0 | I56: 0 | J56: 0 | K56: 0 | L56: 0 | M56: 0 | N56: 0 | O56: 0 | P56: 0 | Q56: 0 | R56: 0 | S56: 0 | T56: 0 | U56: 0 | V56: 0 | W56: 0 | X56: 0 | Y56: 2 | Z56: 0.25 | AA56: 0.25 | AB56: 0 | AC56: 0 | AD56: 2 | AI56: 0
A57: peas | B57: supporting the ewes in winter, 2 quarters by estimation in husks. | C57: 0 | D57: 0 | E57: 0 | F57: 0 | G57: 0 | H57: 0 | I57: 0 | J57: 0 | K57: 0 | L57: 0 | M57: 0 | N57: 0 | O57: 0 | P57: 0 | Q57: 0 | R57: 0 | S57: 0 | T57: 0 | U57: 0 | V57: 0 | W57: 0 | X57: 2 | Y57: 0 | Z57: 2 | AA57: 2 | AB57: 0 | AC57: 2 | AD57: 0 | AI57: 0
A58: peas | B58: given for carrying the lord's corn at harvest-time, 2 bushels. | C58: 0 | D58: 0 | E58: 0 | F58: 0 | G58: 0 | H58: 0 | I58: 0 | J58: 0 | K58: 0 | L58: 0 | M58: 0 | N58: 0 | O58: 0 | P58: 0 | Q58: 0 | R58: 0 | S58: 0 | T58: 0 | U58: 0 | V58: 0 | W58: 0 | X58: 0 | Y58: 2 | Z58: 0.25 | AA58: 0.25 | AB58: 0 | AC58: 0 | AD58: 2 | AI58: 0
A59: peas | B59: sold within, 2 quarters 5 bushels. | C59: 0 | D59: 0 | E59: 0 | F59: 0 | G59: 0 | H59: 0 | I59: 0 | J59: 0 | K59: 0 | L59: 0 | M59: 0 | N59: 0 | O59: 0 | P59: 0 | Q59: 2 | R59: 5 | S59: 2.62 | T59: 0 | U59: 0 | V59: 0 | W59: 0 | X59: 2 | Y59: 5 | Z59: 2.62 | AA59: 2.62 | AB59: 0 | AC59: 2 | AD59: 5 | AI59: 0
A60: peas | B60: total as before. | C60: 0 | D60: 0 | E60: 0 | F60: 0 | G60: 0 | H60: 0 | I60: 0 | J60: 0 | K60: 0 | L60: 0 | M60: 0 | N60: 0 | O60: 0 | P60: 0 | Q60: 0 | R60: 0 | S60: 0 | T60: 0 | U60: 0 | V60: 0 | W60: 0 | X60: 0 | Y60: 0 | Z60: 0 | AA60: 0 | AB60: 0 | AC60: 0 | AD60: 0 | AI60: 0
A61: peas | B61: it balances. | C61: 0 | D61: 0 | E61: 0 | F61: 0 | G61: 0 | H61: 0 | I61: 0 | J61: 0 | K61: 0 | L61: 0 | M61: 0 | N61: 0 | O61: 0 | P61: 0 | Q61: 0 | R61: 0 | S61: 0 | T61: 0 | U61: 0 | V61: 0 | W61: 0 | X61: 0 | Y61: 0 | Z61: 0 | AA61: 0 | AB61: 0 | AC61: 0 | AD61: 0 | AI61: 0
A62: peas | B62: total | C62: 0 | D62: 0 | E62: 0 | F62: 0 | G62: 0 | H62: 0 | I62: 0 | J62: 0 | K62: 0 | L62: 0 | M62: 0 | N62: 0 | O62: 0 | P62: 0 | Q62: 0 | R62: 0 | S62: 0 | T62: 0 | U62: 0 | V62: 0 | W62: 0 | AI62: 0
A63: vetches | B63: and for 6 quarters 4 bushels of vetches from the issue of the grange, threshed by the manorial servants. | C63: 0 | D63: 0 | E63: 0 | F63: 0 | G63: 0 | H63: 0 | I63: 0 | J63: 0 | K63: 0 | L63: 0 | M63: 0 | N63: 0 | O63: 0 | P63: 0 | Q63: 0 | R63: 0 | S63: 0 | T63: 0 | U63: 0 | V63: 0 | W63: 0 | X63: 6 | Y63: 4 | Z63: 6.5 | AA63: 6.5 | AB63: 0 | AC63: 6 | AD63: 4 | AI63: 0
A64: vetches | B64: 2 quarters from the same issue by estimation in husks. | C64: 0 | D64: 0 | E64: 0 | F64: 0 | G64: 0 | H64: 0 | I64: 0 | J64: 0 | K64: 0 | L64: 0 | M64: 0 | N64: 0 | O64: 0 | P64: 0 | Q64: 0 | R64: 0 | S64: 0 | T64: 0 | U64: 0 | V64: 0 | W64: 0 | X64: 2 | Y64: 0 | Z64: 2 | AA64: 2 | AB64: 0 | AC64: 2 | AD64: 0 | AI64: 0
A65: vetches | B65: . 3 bushels by estimation in sheaves given for carrying the lord's corn at harvest-time. | C65: 0 | D65: 0 | E65: 0 | F65: 0 | G65: 0 | H65: 0 | I65: 0 | J65: 0 | K65: 0 | L65: 0 | M65: 0 | N65: 0 | O65: 0 | P65: 0 | Q65: 0 | R65: 0 | S65: 0 | T65: 0 | U65: 0 | V65: 0 | W65: 0 | X65: 0 | Y65: 3 | Z65: 0.38 | AA65: 0.38 | AB65: 0 | AC65: 0 | AD65: 3 | AI65: 0
A66: vetches | B66: no sheaves given for reaping for the aforesaid reason.. | C66: 0 | D66: 0 | E66: 0 | F66: 0 | G66: 0 | H66: 0 | I66: 0 | J66: 0 | K66: 0 | L66: 0 | M66: 0 | N66: 0 | O66: 0 | P66: 0 | Q66: 0 | R66: 0 | S66: 0 | T66: 0 | U66: 0 | V66: 0 | W66: 0 | X66: 0 | Y66: 0 | Z66: 0 | AA66: 0 | AB66: 0 | AC66: 0 | AD66: 0 | AI66: 0
A67: vetches | B67: total, 8 quarters 7 bushels. | C67: 0 | D67: 0 | E67: 0 | F67: 0 | G67: 0 | H67: 0 | I67: 0 | J67: 0 | K67: 0 | L67: 0 | M67: 0 | N67: 0 | O67: 0 | P67: 0 | Q67: 0 | R67: 0 | S67: 0 | T67: 0 | U67: 0 | V67: 0 | W67: 0 | X67: 8 | Y67: 7 | Z67: 8.88 | AA67: 8.88 | AB67: 0 | AC67: 8 | AD67: 7 | AI67: 0
A68: vetches | B68: sown over 12 acres, 3 quarters. | C68: 0 | D68: 0 | E68: 3 | F68: 0 | G68: 3 | H68: 0 | I68: 0 | J68: 0 | K68: 0 | L68: 0 | M68: 0 | N68: 0 | O68: 0 | P68: 0 | Q68: 0 | R68: 0 | S68: 0 | T68: 0 | U68: 0 | V68: 0 | W68: 0 | X68: 3 | Y68: 0 | Z68: 3 | AA68: 3 | AB68: 0 | AC68: 3 | AD68: 0 | AI68: 0
A69: vetches | B69: that is, 2 bushels an acre. | C69: 0 | D69: 0 | E69: 0 | F69: 0 | G69: 0 | H69: 0 | I69: 0 | J69: 0 | K69: 0 | L69: 0 | M69: 0 | N69: 0 | O69: 0 | P69: 0 | Q69: 0 | R69: 0 | S69: 0 | T69: 0 | U69: 0 | V69: 0 | W69: 0 | X69: 0 | Y69: 2 | Z69: 0.25 | AA69: 0.25 | AB69: 0 | AC69: 0 | AD69: 2 | AI69: 0
A70: vetches | B70: given to the lord's plough-horses and sheep, 2 quarters by estimation in husks. | C70: 0 | D70: 0 | E70: 0 | F70: 0 | G70: 0 | H70: 0 | I70: 0 | J70: 0 | K70: 0 | L70: 0 | M70: 0 | N70: 0 | O70: 0 | P70: 0 | Q70: 0 | R70: 0 | S70: 0 | T70: 0 | U70: 0 | V70: 0 | W70: 0 | X70: 2 | Y70: 0 | Z70: 2 | AA70: 2 | AB70: 0 | AC70: 2 | AD70: 0 | AI70: 0
A71: vetches | B71: given for carrying the lord's corn at harvest-time, 3 bushels. | C71: 0 | D71: 0 | E71: 0 | F71: 0 | G71: 0 | H71: 0 | I71: 0 | J71: 0 | K71: 0 | L71: 0 | M71: 0 | N71: 0 | O71: 0 | P71: 0 | Q71: 0 | R71: 0 | S71: 0 | T71: 0 | U71: 0 | V71: 0 | W71: 0 | X71: 0 | Y71: 3 | Z71: 0.38 | AA71: 0.38 | AB71: 0 | AC71: 0 | AD71: 3 | AI71: 0
A72: vetches | B72: sold within, 3 quarters 4 bushels. | C72: 0 | D72: 0 | E72: 0 | F72: 0 | G72: 0 | H72: 0 | I72: 0 | J72: 0 | K72: 0 | L72: 0 | M72: 0 | N72: 0 | O72: 0 | P72: 0 | Q72: 3 | R72: 4 | S72: 3.5 | T72: 0 | U72: 0 | V72: 0 | W72: 0 | X72: 3 | Y72: 4 | Z72: 3.5 | AA72: 3.5 | AB72: 0 | AC72: 3 | AD72: 4 | AI72: 0
A73: vetches | B73: total as before. | C73: 0 | D73: 0 | E73: 0 | F73: 0 | G73: 0 | H73: 0 | I73: 0 | J73: 0 | K73: 0 | L73: 0 | M73: 0 | N73: 0 | O73: 0 | P73: 0 | Q73: 0 | R73: 0 | S73: 0 | T73: 0 | U73: 0 | V73: 0 | W73: 0 | X73: 0 | Y73: 0 | Z73: 0 | AA73: 0 | AB73: 0 | AC73: 0 | AD73: 0 | AI73: 0
A74: vetches | B74: it balances. | C74: 0 | D74: 0 | E74: 0 | F74: 0 | G74: 0 | H74: 0 | I74: 0 | J74: 0 | K74: 0 | L74: 0 | M74: 0 | N74: 0 | O74: 0 | P74: 0 | Q74: 0 | R74: 0 | S74: 0 | T74: 0 | U74: 0 | V74: 0 | W74: 0 | X74: 0 | Y74: 0 | Z74: 0 | AA74: 0 | AB74: 0 | AC74: 0 | AD74: 0 | AI74: 0

Sheet Issues of the Grange
A1: Gross Output | B1: Bought Only Aggregated | C1: Account Quarters | D1: Account Bushels | E1: Account Total Quarters | F1: Bought in Quarters | G1: Bought in Bushels | H1: Total Bought Quarters | I1: Sold Quarters | J1: Sold Bushels | K1: Sold Total Quarters | L1: Total Corn Quantity | M1: Difference Produced+Bought-Sold | N1: Weighted Average Price per Quarter | O1: Non-Weighted Average Price per Quarter | P1: Value of Total Production weighted | Q1: Value of Total Production unweighted
A2: total of all allowances and cash deliveries | B2: 0 | C2: 0 | D2: 0 | E2: 0 | F2: 0 | G2: 0 | H2: 0 | I2: 0 | J2: 0 | K2: 0 | L2: 0 | M2: 0
A3: wheat | B3: 0 | C3: 49 | D3: 1 | E3: 49.12 | F3: 0 | G3: 0 | H3: 0 | I3: 36 | J3: 6.5 | K3: 36.81 | L3: 49.12 | M3: 12.31 | N3: 0.48 | O3: 0.47 | P3: 23.77 | Q3: 23.33
A4: curall | B4: 0 | C4: 0 | D4: 0 | E4: 0 | F4: 0 | G4: 0 | H4: 0 | I4: 0 | J4: 0 | K4: 0 | L4: 0 | M4: 0 | N4: 0.3 | O4: 0.3 | P4: 0 | Q4: 0
A5: barley | B5: 0 | C5: 106 | D5: 1 | E5: 106.12 | F5: 0 | G5: 0 | H5: 0 | I5: 38 | J5: 3 | K5: 38.12 | L5: 106.12 | M5: 68 | N5: 0.3 | O5: 0.3 | P5: 31.84 | Q5: 31.84
A6: oats | B6: 0 | C6: 20 | D6: 4 | E6: 20.5 | F6: 0 | G6: 0 | H6: 0 | I6: 5 | J6: 6 | K6: 5.75 | L6: 20.5 | M6: 14.75 | N6: 0.17 | O6: 0.17 | P6: 3.42 | Q6: 3.42
A7: peas | B7: 0 | C7: 0 | D7: 0 | E7: 0 | F7: 0 | G7: 0 | H7: 0 | I7: 2 | J7: 5 | K7: 2.62 | L7: 0 | M7: -2.62 | N7: 0.27 | O7: 0.27 | P7: 0 | Q7: 0
A8: vetches | B8: 0 | C8: 0 | D8: 0 | E8: 0 | F8: 0 | G8: 0 | H8: 0 | I8: 3 | J8: 4 | K8: 3.5 | L8: 0 | M8: -3.5 | N8: 0.25 | O8: 0.25 | P8: 0 | Q8: 0
A9: Mancorn | B9: 0 | C9: 0 | D9: 0 | E9: 0 | F9: 0 | G9: 0 | H9: 0 | I9: 0 | J9: 0 | K9: 0 | L9: 0 | M9: 0
A10: Maslin | B10: 0 | C10: 0 | D10: 0 | E10: 0 | F10: 0 | G10: 0 | H10: 0 | I10: 0 | J10: 0 | K10: 0 | L10: 0 | M10: 0
A11: First-grade malt | B11: 0 | C11: 0 | D11: 0 | E11: 0 | F11: 0 | G11: 0 | H11: 0 | I11: 0 | J11: 0 | K11: 0 | L11: 0 | M11: 0
A12: Second-grade malt | B12: 0 | C12: 0 | D12: 0 | E12: 0 | F12: 0 | G12: 0 | H12: 0 | I12: 0 | J12: 0 | K12: 0 | L12: 0 | M12: 0
A13: Oatmeal | B13: 0 | C13: 0 | D13: 0 | E13: 0 | F13: 0 | G13: 0 | H13: 0 | I13: 0 | J13: 0 | K13: 0 | L13: 0 | M13: 0
A14: Rye | B14: 0 | C14: 0 | D14: 0 | E14: 0 | F14: 0 | G14: 0 | H14: 0 | I14: 0 | J14: 0 | K14: 0 | L14: 0 | M14: 0
A15: Dredge | B15: 0 | C15: 0 | D15: 0 | E15: 0 | F15: 0 | G15: 0 | H15: 0 | I15: 0 | J15: 0 | K15: 0 | L15: 0 | M15: 0
A16: Malt | B16: 0 | C16: 0 | D16: 0 | E16: 0 | F16: 0 | G16: 0 | H16: 0 | I16: 0 | J16: 0 | K16: 0 | L16: 0 | M16: 0
A17: Meal | B17: 0 | C17: 0 | D17: 0 | E17: 0 | F17: 0 | G17: 0 | H17: 0 | I17: 0 | J17: 0 | K17: 0 | L17: 0 | M17: 0

Sheet Sale of Corn Prices
A1: Heading | B1: Sentence | C1: Total in Pounds | D1: Pounds | E1: Shillings | F1: Pence | G1: Corn | H1: Total Quarters Except 1 | I1: Total Bushels Except 1 | J1: Total Corn Cross-Check | K1: Total Corn Manorial Account | L1: Corn Quantity Error | M1: Quarters 0 | N1: Bushels 0 | O1: shilling a quarter 1 | P1: pence a quarter 1 | Q1: Quarters 1 | R1: Bushels 1 | S1: shilling a quarter 2 | T1: pence a quarter 2 | U1: Quarters 2 | V1: Bushels 2 | W1: shilling a quarter 3 | X1: pence a quarter 3 | Y1: shilling a quarter 4 | Z1: pence a quarter 4 | AA1: £ a quarter 1 | AB1: £ a quarter 2 | AC1: £ a quarter 3 | AD1: £ a quarter 4 | AE1: Quarters Sold | AF1: Weighted Average Price per Quarter | AG1: Non-Weighted Average Price per Quarter | AH1: Corn lowercase
A2: sale of corn | B2: and for £17 16 shilling 3.75pence from 36 quarters 6.5 bushels of wheat sold, at 10 shilling a quarters for 25 quarters per mutuum, and 9 shilling a quarters for 11 quarters 6.5 bushels in the market. | C2: 17.82 | D2: 17 | E2: 16 | F2: 3.75 | G2: wheat | H2: 36 | I2: 6.5 | J2: 36.81 | K2: 36.81 | L2: 0 | M2: 36 | N2: 6.5 | O2: 10 | P2: 0 | Q2: 25 | R2: 0 | S2: 9 | T2: 0 | U2: 11 | V2: 6.5 | AA2: 0.5 | AB2: 0.45 | AE2: 36.81 | AF2: 0.48 | AG2: 0.47 | AH2: wheat
A3: sale of corn | B3: £1 4 shilling from 4 quarters of curall sold. | C3: 1.2 | D3: 1 | E3: 4 | F3: 0 | G3: curall | H3: 4 | I3: 0 | J3: 4 | K3: 4 | L3: 0 | M3: 4 | N3: 0 | AA3: 0.3 | AE3: 4 | AF3: 0.3 | AG3: 0.3 | AH3: curall
A4: sale of corn | B4: £11 8 shilling 9pence from 38 quarters 1 bushels of barley sold per mutuum, at 6 shilling a quarters. | C4: 11.44 | D4: 11 | E4: 8 | F4: 9 | G4: barley | H4: 38 | I4: 1 | J4: 38.12 | K4: 38.12 | L4: 0 | M4: 38 | N4: 1 | O4: 6 | P4: 0 | AA4: 0.3 | AE4: 38.12 | AF4: 0.3 | AG4: 0.3 | AH4: barley
A5: sale of corn | B5: 15 shilling 5pence from 4 quarters 5 bushels of oats sold per mutuum, at 3 shilling 4pence a quarters. | C5: 0.77 | D5: 0 | E5: 15 | F5: 5 | G5: oats | H5: 4 | I5: 5 | J5: 4.62 | K5: 4.62 | L5: 0 | M5: 4 | N5: 5 | O5: 3 | P5: 4 | AA5: 0.17 | AE5: 4.62 | AF5: 0.17 | AG5: 0.17 | AH5: oats
A6: sale of corn | B6: 14 shilling from 2 quarters 5 bushels of peas sold, at 5 shilling 4pence a quarters. | C6: 0.72 | D6: 0 | E6: 14 | F6: 4 | G6: peas | H6: 2 | I6: 5 | J6: 2.62 | K6: 2.62 | L6: 0 | M6: 2 | N6: 5 | O6: 5 | P6: 4 | AA6: 0.27 | AE6: 2.62 | AF6: 0.27 | AG6: 0.27 | AH6: peas
A7: sale of corn | B7: 17 shilling 6pence from 3 quarters 3 bushels' of vetches sold, at 5 shilling a quarters. | C7: 0.88 | D7: 0 | E7: 17 | F7: 6 | G7: vetches | H7: 3 | I7: 3 | J7: 3.38 | K7: 3.38 | L7: 0 | M7: 3 | N7: 3 | O7: 5 | P7: 0 | AA7: 0.25 | AE7: 3.38 | AF7: 0.25 | AG7: 0.25 | AH7: vetches
A8: sale of corn | B8: total, £32 15 shilling 11.75pence. | C8: 32.8 | D8: 32 | E8: 15 | F8: 11.75 | H8: 0 | I8: 0 | J8: 0 | K8: 0 | L8: 0 | M8: 0 | N8: 0 | AA8: inf | AE8: 0 | AF8: inf | AG8: inf
