Workbook

Sheet Overview
A1: WESTWYCOMBE OVERVIEW - COMPLETED | B1: Total in £ | C1: Error | D1: Note
A2: CASH ACCOUNT
A3: RECEIPTS
A4: Arrears total | B4: 1.71
A5: Rents of assize total
A6: Quittances total
A7: Defaults of rent total
A8: Defaults of rent through the pestilence total
A9: Cotlands defaults total
A10: Cotlands total
A11: Total of quittances and defaults of rent total
A12: Total of rents remaining clear total
A13: Farms total
A14: Annual recognizances total
A15: Issues of the Manor total | B15: 0.68
A16: Issues of the tenements in the lord's hands total
A17: Sale of labour services total
A18: Sale of corn total
A19: Entry and marriage fines total | B19: 1.46
A20: Pleas & perquisites total | B20: 0.65
A21: Forfeited chattels total
A22: Farm of the demesne land total
A23: Total of all receipts (calculated here) | B23: =SUM(B5:B11)
A24: Total of all receipts (calculated here) incl arrears | B24: =SUM(B4:B11)
A25: Total recorded in the accounts excl. arrears | B25: ='Receipts'!F26 | C25: =B23-B25
A26: Total recorded in the accounts incl. arrears | B26: ='Receipts'!F27
A29: EXPENSES
A30: Cost of ploughs total
A31: Purchase of corn total
A32: Cost of carts and wagons total
A33: Cost of dairy total
A34: Purchase of stock total | B34: 3.67
A35: Sheepcote total
A36: Cost of buildings total | B36: 4.77
A37: Threshing total
A38: Barley expenses
A39: Expenses of the harvest total
A40: Necessary expenses
A41: Wages of the bailiff
A42: Steward's expenses total | B42: 1.41
A43: Annual fees
A44: Total of all expenses per account | B44: ='Expenses'!F57
A45: Total of all expenses (calculated here) | B45: ='Expenses'!F58
A46: Total fixed investment
A47: Total Demesne fixed investment
A49: Owed by the reeve | B49: =B23-B45
A50: From accounts | B50: 68.7
A52: Allowances
A53: Cash deliveries | B53: 66.17
A54: Sum of the above | B54: =SUM(B52:B53)
A55: Total of all allowances and cash deliveries in accounts
A57: Net amount owed | B57: =B50-B54
A58: Net amount owed in accounts
A60: GRANGE ACCOUNT | B60: Total Production | D60: Value of total gross production in £ | E60: Value of total net production in £
A61: Grange | B61: qrs | C61: bus
A62: Wheat | B62: 0 | C62: 0 | E62: 0
A63: Rye | B63: 0 | C63: 0 | E63: 0
A64: Dredge | B64: 0 | C64: 0 | E64: 0
A65: Curall | B65: 0 | C65: 0 | E65: 0
A66: Barley | B66: 0 | C66: 0 | E66: 0
A67: Oats | B67: 0 | C67: 0 | E67: 0
A68: Beans | B68: 0 | C68: 0 | D68: 0 | E68: 0
A69: Peas | B69: 0 | C69: 0 | E69: 0
A70: Vetches | B70: 0 | C70: 0 | E70: 0
A71: Total value of gross production (sum of the above) | E71: =SUM(D62:D70)
A72: Total value of net production | E72: =SUM(E62:E70)
A73: Value of sales | E73: 0
A75: MILL ACCOUNT | B75: Total Production | D75: Total in £
A76: Issues of the mill | B76: qrs | C76: bus
A77: Wheat
A78: Oatmeal
A79: 1st grade malt
A80: 2nd grade malt
A81: Maslin
A82: Total value of production (sum of the above)
A83: Value of sales
A85: STOCK ACCOUNT
A86: Livestock | B86: Begin stock | C86: End stock | D86: Stockbuilding | F86: Value of stock in £ | G86: Value of stockbuilding
A87: Cart-horses | B87: 0 | C87: ='Stock'!L5 | D87: =C87-B87 | F87: ='Stock'!L5*'Stock'!O5 | G87: =D87*'Stock'!O5
A88: Mares | B88: 0 | C88: ='Stock'!L6 | D88: =C88-B88 | F88: ='Stock'!L6*'Stock'!O6 | G88: =D88*'Stock'!O6
A89: Plough horses | B89: 12 | C89: ='Stock'!L7 | D89: =C89-B89 | F89: ='Stock'!L7*'Stock'!O7 | G89: =D89*'Stock'!O7
A90: Colts (2 years) | B90: 0 | C90: ='Stock'!L9 | D90: =C90-B90 | F90: ='Stock'!L9*'Stock'!O9 | G90: =D90*'Stock'!O9
A91: Colts (2 years) | B91: 0 | C91: ='Stock'!L9 | D91: =C91-B91 | F91: ='Stock'!L9*'Stock'!O9 | G91: =D91*'Stock'!O9
A92: Colts (1 year) | B92: 0 | C92: ='Stock'!L10 | D92: =C92-B92 | F92: ='Stock'!L10*'Stock'!O10 | G92: =D92*'Stock'!O10
A93: Foals | B93: 0 | C93: ='Stock'!L11 | D93: =C93-B93 | F93: ='Stock'!L11*'Stock'!O11 | G93: =D93*'Stock'!O11
A94: Oxen | B94: 0 | C94: ='Stock'!L12 | D94: =C94-B94 | F94: ='Stock'!L12*'Stock'!O12 | G94: =D94*'Stock'!O12
A95: Bulls | B95: 0 | C95: ='Stock'!L13 | D95: =C95-B95 | F95: ='Stock'!L13*'Stock'!O13 | G95: =D95*'Stock'!O13
A96: Cows | B96: 31 | C96: ='Stock'!L14 | D96: =C96-B96 | F96: ='Stock'!L14*'Stock'!O14 | G96: =D96*'Stock'!O14
A97: Steers | B97: 5 | C97: ='Stock'!L15 | D97: =C97-B97 | F97: ='Stock'!L15*'Stock'!O15 | G97: =D97*'Stock'!O15
A98: Bullocks | B98: 6 | C98: ='Stock'!L16 | D98: =C98-B98 | F98: ='Stock'!L16*'Stock'!O16 | G98: =D98*'Stock'!O16
A99: Yearlings | B99: 5 | C99: ='Stock'!L17 | D99: =C99-B99 | F99: ='Stock'!L17*'Stock'!O17 | G99: =D99*'Stock'!O17
A100: Calves | B100: 0 | C100: ='Stock'!L18 | D100: =C100-B100 | F100: ='Stock'!L18*'Stock'!O18 | G100: =D100*'Stock'!O18
A101: Wethers | B101: 0 | C101: ='Stock'!L19 | D101: =C101-B101 | F101: ='Stock'!L19*'Stock'!O19 | G101: =D101*'Stock'!O19
A102: Rams | B102: 8 | C102: ='Stock'!L20 | D102: =C102-B102 | F102: ='Stock'!L20*'Stock'!O20 | G102: =D102*'Stock'!O20
... A112: Peacocks | B112: 0 | C112: ='Stock'!L30 | D112: =C112-B112 | F112: ='Stock'!L30*'Stock'!O30 | G112: =D112*'Stock'!O30
A113: Total value of stock (sum of the above) | F113: =SUM(F87:F112) | G113: =SUM(G87:G112)
A114: Total value of production | F114: =SUM('Stock'!T5:T30)
A115: Value of sales | F115: =SUM('Stock'!R5:R30)
A117: Wool | B117: Begin stock | C117: End stock | D117: Stockbuilding | F117: Value of stock in £
A118: Fleeces | B118: 0 | C118: 0 | D118: 0
...

Sheet Receipts
A1: WESTWYCOMBE RECEIPTS
A2: Heading | B2: £ | C2: s | D2: d | F2: Total in £ | G2: Error | H2: Notes | I2: Own notes
A3: Arrears | B3: 1 | C3: 14 | D3: 2 | F3: 1.71 | H3: William Lythewey, farmer there, answers for £1 14 shilling 2pence of arrears from the last account of the preceding year.
A4: Arrears | B4: 1 | C4: 14 | D4: 2 | F4: 1.71 | H4: Total, £1 14 shilling 2pence.
A5: Arrears total | F5: 1.71 | G5: 0 | H5: Total
A7: Issues of the manor | B7: 0 | C7: 13 | D7: 6 | F7: 0.68 | H7: And for 13 shilling 6pence from the woolskins sold of 50 ewes in murrain before shearing as made clear elsewhere, at 3pence a skin.
A8: Issues of the manor | B8: 0 | C8: 13 | D8: 6 | F8: 0.68 | H8: Total, 13 shilling 6pence.
A9: Issues of the manor total | F9: 0.68 | G9: 0 | H9: Total
A11: Entry and marriage fines | B11: 0 | C11: 3 | D11: 4 | F11: 0.17 | H11: And for 3 shilling 4pence from John Lylye and Isabel his wife to have 1 messuage, 16.5 acres and the sixth part of 1 acre of land and 1 messuage, 11 acres and 1 rood of purpresture in the tithing of Booker, which belonged to John Lymmer' and which came into the lord's hands as his escheat because noone of the kin of the said John took steps to fine for the same although a proclamation was made according to the custom of the manor.
A12: Entry and marriage fines | B12: 0 | C12: 3 | D12: 4 | F12: 0.17 | H12: 3 shilling 4pence from John Lylye and Isabel his wife to have 1 toft and 1 ferling of villein land in the tithing of Towerage called Rammesmere and formerly Campeden' which belonged to John Kyng', a stranger, and which the same John forfeited as the penalty for a felony.
A13: Entry and marriage fines | B13: 0 | C13: 2 | D13: 0 | F13: 0.1 | H13: 2 shilling from John Flat to have 1 cottage with a curtilage of villein land called Flattes in the tithing of West Wycombe by surrender of Margery his mother.
A14: Entry and marriage fines | B14: 0 | C14: 5 | D14: 0 | F14: 0.25 | H14: 5 shilling from John Flat to have 1 toft and .5 virgate of villein land in the tithing of West Wycombe which belonged to Simon Flat and which came into the lord's hands as his escheat because noone of the kin of the said Simon took steps to fine for the same although a proclamation was made according to the custom of the manor.
A15: Entry and marriage fines | B15: 0 | C15: 5 | D15: 4 | F15: 0.27 | H15: 5 shilling from John Loot to have 1 messuage 1 virgate of villein land and .5 acre of purpresture in the tithing of Dounle which belonged to Thomas Gilberd', by surrender of Hugh Loot and Isabel his wife, who are examined about this in full court, and for which Agnes, daughter of John Gilbard', brother of the aforesaid Thomas, refused to fine in full court, and the aforesaid Agnes remised and released entirely all right and claim which she has or in any way will be able to have for herself and her heirs to the aforesaid John Loot, on condition that within three years he repairs the aforesaid tenement well and suitably. 1 shilling 4pence from Thomas Thresshere to have 1 loft with an adjacent garden of purpresture' in the tithing of Dounle by surrender of Stephen Berefeld'.
A16: Entry and marriage fines | B16: 0 | C16: 6 | D16: 8 | F16: 0.33 | H16: 6 shilling 8pence from Thomas Gardener Smyth' to have 1 cottage of purpresture in the tithing of Brokhende by surrender of William Lythewey.
A17: Entry and marriage fines | B17: 0 | C17: 3 | D17: 4 | F17: 0.17 | H17: 3 shilling 4pence from William Lythewey to have 1 cottage, 6.5 perches 7.5 feet long and 3.5 perches wide, of purpresture in the tithing of Brokhende by surrender of Thomas Garden' Smyth'.
A18: Entry and marriage fines | B18: 1 | C18: 15 | D18: 0 | F18: 1.75 | H18: Total, £1 15 shilling.
A19: Entry and marriage fines total | F19: 1.46 | G19: -0.29 | H19: Total
A21: Perquisites of court | B21: 0 | C21: 3 | D21: 6 | F21: 0.17 | H21: And for 3 shilling 6pence from the perquisites of the tourn of Martinmas (11 November).
A22: Perquisites of court | B22: 0 | C22: 8 | D22: 9 | F22: 0.44 | H22: 8 shilling 9pence from the perquisites of the courts held between the 2 tourns.
A23: Perquisites of court | B23: 0 | C23: 3 | D23: 9 | F23: 0.19 | H23: 3 shilling 9pence from the perquisites of the tourn of Hockday (1 April).
A24: Perquisites of court | B24: 0 | C24: 7 | D24: 8 | F24: 0.38 | H24: 7 shilling 8pence from the perquisites of the courts held after the tourn of Hockday.
A25: Perquisites of court total | B25: 0 | C25: 12 | D25: 11 | F25: 0.65 | G25: 0.27 | H25: Total, 12 shilling 11pence.
A26: Total of all receipts recorded in accounts (calculated here) | F26: =SUMIF(A1:A25,"* total",F1:F25)-SUMIF(A1:A25,"Arrears total",F1:F25)
A27: Total of all receipts (calculated here) incl arrears | F27: =F26+SUMIF(A1:A25,"Arrears total",F1:F25)

Sheet Expenses
A1: WESTWYCOMBE EXPENSES
A2: Heading | B2: £ | C2: s | D2: d | F2: Total in £ | G2: Error | H2: Sentence | I2: Fixed Investments | J2: Demesne Fixed Investments
A4: Purchase of stock | B4: 3 | C4: 13 | D4: 4 | F4: 3.67 | H4: In 55 ewes bought £3 13 shilling 4pence, at 1 shilling 4pence each.
A5: Purchase of stock | B5: 3 | C5: 13 | D5: 4 | F5: 3.67 | H5: Total, £3 13 shilling 4pence.
A6: Purchase of stock total | F6: 3.67 | G6: 0 | H6: Total
A8: Cost of buildings | B8: 1 | C8: 2 | D8: 0 | F8: 1.1 | H8: In hiring 1 carpenter to make 1 water-wheel from the lord's timber and to repair and restore (reparand' ac emend') all the defects of the waterworks (la waterwerk) of the lord's water-mill by piece-work £1 2 shilling.
A9: Cost of buildings | B9: 0 | C9: 9 | D9: 6 | F9: 0.48 | H9: hiring 2 sawyers to saw planks from the lord's timber for the said mill for 9.5 days 9 shilling 6pence, taking between them 1 shilling a day.
A10: Cost of buildings | B10: 0 | C10: 1 | D10: 8 | F10: 0.08 | H10: hiring 1 carpenter to make the head of the mill-dam from the lord's timber by piece-work 1 shilling 8pence.
A11: Cost of buildings | B11: 0 | C11: 3 | D11: 4 | F11: 0.17 | H11: 1 piece of millstone bought for the mill-dam 3 shilling 4pence.
A12: Cost of buildings | B12: 0 | C12: 1 | D12: 0 | F12: 0.05 | H12: hiring 1 mason to lay and attach the said millstone together by piece-work 1 shilling.
A13: Cost of buildings | B13: 0 | C13: 1 | D13: 6 | F13: 0.08 | H13: 200 spike-nails bought for the waterworks 1 shilling 6pence, at 9pence a 100..
A14: Cost of buildings | B14: 0 | C14: 1 | D14: 3 | F14: 0.06 | H14: hiring 1 man for 3 days to fell, lop and cut the lord's timber for the repair and restoration of the aforesaid mill 1 shilling 3pence, taking 5pence a day.
A15: Cost of buildings | B15: 0 | C15: 2 | D15: 8 | F15: 0.13 | H15: hiring 1 man for 31 days to carry the said timber for the repair and restoration of the aforesaid mill 2 shilling 8pence, taking 1 shilling 4pence a day.
A16: Cost of buildings | B16: 0 | C16: 1 | D16: 3 | F16: 0.06 | H16: hiring 1 carpenter for 3 days to underpin and fit with ground-sills and studs the aforesaid mill with the lord's timber for its repair and restoration 1 shilling 3pence, taking 5pence a day.
A17: Cost of buildings | B17: 0 | C17: 2 | D17: 8 | F17: 0.13 | H17: hiring 1 man to carry the said timber for the aforesaid mill for 2 days 2 shilling 8pence, taking 1 shilling 4pence a day as before.
A18: Cost of buildings | B18: 0 | C18: 5 | D18: 0 | F18: 0.25 | H18: hiring 1 carpenter to underpin and fit with ground-sills and studs 4 bays of the cow-shed by piece-work 5 shilling.
A19: Cost of buildings | B19: 0 | C19: 0 | D19: 3 | F19: 0.01 | H19: hiring 1 mason to pin and mend all the defects of the ground-wheel (le groundwhele) of the said mill for 6 days 3pence,2 taking 6pence a day.
... A36: Cost of buildings | B36: 5 | C36: 9 | D36: 2 | F36: 5.46 | H36: Total, £5 9 shilling 2pence.
A37: Cost of buildings total | F37: 4.77 | G37: -0.69 | H37: Total
A39: Expenses of the steward | B39: 0 | C39: 14 | D39: 5 | F39: 0.72 | H39: In expenses of Richard Wyot, steward, holding the tourns of Martinmas and Hockday, by 2 sealed bills in cash, 14 shilling 5pence.
A40: Expenses of the steward | B40: 0 | C40: 3 | D40: 6 | F40: 0.17 | H40: 3 bushels of wheat bought for baking bread 3 shilling 6pence, at 1 shilling 6pence for 1 bushels, and 1 shilling a bushels for 2 bushels.
A41: Expenses of the steward | B41: 0 | C41: 10 | D41: 4 | F41: 0.52 | H41: 3 quarters 2 bushels of oats bought 10 shilling 4pence, at 3 shilling a qr for 1 qr 4 bushels, and 3 shilling 4pence a qr for 1 qr 6 bushels.
A42: Expenses of the steward | B42: 1 | C42: 8 | D42: 3 | F42: 1.41 | H42: Total, £1 8 shilling 3pence.
A43: Expenses of the steward total | F43: 1.41 | G43: 0 | H43: Total
A45: Total of all expenses | B45: 15 | C45: 4 | D45: 1 | F45: 15.2 | H45: Total of all expenses, £15 4 shilling 1pence.
A46: Total of all expenses | F46: 0 | G46: -15.2 | H46: Total
A48: And he owes | B48: 68 | C48: 13 | D48: 11 | F48: 68.7 | H48: And he owes, £68 13 shilling 11pence.
A49: And he owes total | F49: 68.7 | G49: 0 | H49: Total
A51: Cash deliveries | B51: 66 | C51: 3 | D51: 4 | F51: 66.17 | H51: Delivered to John Arnald', receiver of Wolvesey, by 1 tally, £66 3 shilling 4pence.
A52: Cash deliveries | B52: 66 | C52: 3 | D52: 4 | F52: 66.17 | H52: Total, £66 3 shilling 4pence.
A53: Cash deliveries total | F53: 66.17 | G53: 0 | H53: Total
A55: Total of all allowances and cash deliveries | B55: 68 | C55: 13 | D55: 11 | F55: 68.7 | H55: Total of all allowances and cash deliveries, £68 13 shilling 11pence He is quit.
A57: Total of all expenses per account | B57: 15 | C57: 4 | D57: 1 | F57: =F45
A58: Total of all expenses (calculated here) | F58: =SUMIF(A1:A44,"* total",F1:F44)
A59: Total fixed investment
A60: Total Demesne fixed investment

Sheet Stock
A1: WESTWYCOMBE STOCK ACCOUNT
C3: added | G3: subtracted
A4: Livestock | B4: Inherited stock | C4: added | D4: strays | E4: herbage | F4: churchscot | G4: of which in default | H4: sold | I4: in murrain | J4: accounted for elsewhere | K4: End-period stock | L4: cross-check | M4: stock building | N4: raw production | O4: Unit price (£) | P4: Value of stock (£) at given value | Q4: Value of stock (£) at sales prices | R4: Sales in (£) | S4: Value of stock building (£) | T4: Value of production (£) at sales prices | U4: Details
A5: Cart-horses | B5: 0 | C5: 0 | H5: 0 | I5: 0 | K5: =B5+C5-H5-I5 | L5: =B5+C5-H5 | M5: =L5-B5 | N5: =C5 | O5: 0 | P5: =O5*K5 | R5: 0 | S5: =O5*M5 | T5: =O5*N5
A6: Mares | B6: 0 | C6: 0 | H6: 0 | I6: 0 | K6: =B6+C6-H6-I6 | L6: =B6+C6-H6 | M6: =L6-B6 | N6: =C6 | O6: 0 | P6: =O6*K6 | R6: 0 | S6: =O6*M6 | T6: =O6*N6
A7: Plough horses | B7: 12 | C7: 0 | H7: 0 | I7: 0 | K7: =B7+C7-H7-I7 | L7: =B7+C7-H7 | M7: =L7-B7 | N7: =C7 | O7: 0 | P7: =O7*K7 | R7: 0 | S7: =O7*M7 | T7: =O7*N7
A8: Colts (unspecified years) | B8: 0 | C8: 0 | H8: 0 | I8: 0 | K8: =B8+C8-H8-I8 | L8: =B8+C8-H8 | M8: =L8-B8 | N8: =C8 | O8: 0 | P8: =O8*K8 | R8: 0 | S8: =O8*M8 | T8: =O8*N8
A9: Colts (2 years) | B9: 0 | C9: 0 | H9: 0 | I9: 0 | K9: =B9+C9-H9-I9 | L9: =B9+C9-H9 | M9: =L9-B9 | N9: =C9 | O9: 0 | P9: =O9*K9 | R9: 0 | S9: =O9*M9 | T9: =O9*N9
A10: Colts (1 year) | B10: 0 | C10: 0 | H10: 0 | I10: 0 | K10: =B10+C10-H10-I10 | L10: =B10+C10-H10 | M10: =L10-B10 | N10: =C10 | O10: 0 | P10: =O10*K10 | R10: 0 | S10: =O10*M10 | T10: =O10*N10
A11: Foals | B11: 0 | C11: 0 | H11: 0 | I11: 0 | K11: =B11+C11-H11-I11 | L11: =B11+C11-H11 | M11: =L11-B11 | N11: =C11 | O11: 0 | P11: =O11*K11 | R11: 0 | S11: =O11*M11 | T11: =O11*N11
A12: Oxen | B12: 0 | C12: 0 | H12: 0 | I12: 0 | K12: =B12+C12-H12-I12 | L12: =B12+C12-H12 | M12: =L12-B12 | N12: =C12 | O12: 0 | P12: =O12*K12 | R12: 0 | S12: =O12*M12 | T12: =O12*N12
A13: Bulls | B13: 0 | C13: 0 | H13: 0 | I13: 0 | K13: =B13+C13-H13-I13 | L13: =B13+C13-H13 | M13: =L13-B13 | N13: =C13 | O13: 0 | P13: =O13*K13 | R13: 0 | S13: =O13*M13 | T13: =O13*N13
A14: Cows | B14: 31 | C14: 0 | H14: 0 | I14: 0 | K14: =B14+C14-H14-I14 | L14: =B14+C14-H14 | M14: =L14-B14 | N14: =C14 | O14: 0 | P14: =O14*K14 | R14: 0 | S14: =O14*M14 | T14: =O14*N14
A15: Steers | B15: 5 | C15: 0 | H15: 0 | I15: 0 | K15: =B15+C15-H15-I15 | L15: =B15+C15-H15 | M15: =L15-B15 | N15: =C15 | O15: 0 | P15: =O15*K15 | R15: 0 | S15: =O15*M15 | T15: =O15*N15
A16: Bullocks | B16: 6 | C16: 0 | H16: 0 | I16: 0 | K16: =B16+C16-H16-I16 | L16: =B16+C16-H16 | M16: =L16-B16 | N16: =C16 | O16: 0 | P16: =O16*K16 | R16: 0 | S16: =O16*M16 | T16: =O16*N16
... A20: Rams | B20: 8 | C20: 0 | H20: 0 | I20: 0 | K20: =B20+C20-H20-I20 | L20: =B20+C20-H20 | M20: =L20-B20 | N20: =C20 | O20: 0 | P20: =O20*K20 | R20: 0 | S20: =O20*M20 | T20: =O20*N20
A21: Ewes | B21: 313 | C21: 55 | H21: 0 | I21: 55 | K21: =B21+C21-H21-I21 | L21: =B21+C21-H21 | M21: =L21-B21 | N21: =C21 | O21: 0 | P21: =O21*K21 | Q21: 0 | R21: 0 | S21: =O21*M21 | T21: =O21*N21
A22: Hoggs | B22: 0 | C22: 0 | H22: 0 | I22: 0 | K22: =B22+C22-H22-I22 | L22: =B22+C22-H22 | M22: =L22-B22 | N22: =C22 | O22: 0 | P22: =O22*K22 | R22: 0 | S22: =O22*M22 | T22: =O22*N22
A23: Lambs | B23: 84 | C23: 0 | H23: 0 | I23: 0 | K23: =B23+C23-H23-I23 | L23: =B23+C23-H23 | M23: =L23-B23 | N23: =C23 | O23: 0 | P23: =O23*K23 | R23: 0 | S23: =O23*M23 | T23: =O23*N23
A24: Boars | B24: 0 | C24: 0 | H24: 0 | I24: 0 | K24: =B24+C24-H24-I24 | L24: =B24+C24-H24 | M24: =L24-B24 | N24: =C24 | O24: 0 | P24: =O24*K24 | R24: 0 | S24: =O24*M24 | T24: =O24*N24
A25: Sows | B25: 3 | C25: 0 | H25: 0 | I25: 0 | K25: =B25+C25-H25-I25 | L25: =B25+C25-H25 | M25: =L25-B25 | N25: =C25 | O25: 0 | P25: =O25*K25 | R25: 0 | S25: =O25*M25 | T25: =O25*N25
A26: Pigs | B26: 29 | C26: 0 | H26: 0 | I26: 0 | K26: =B26+C26-H26-I26 | L26: =B26+C26-H26 | M26: =L26-B26 | N26: =C26 | O26: 0 | P26: =O26*K26 | R26: 0 | S26: =O26*M26 | T26: =O26*N26
A27: Hoggets | B27: 32 | C27: 0 | H27: 0 | I27: 0 | K27: =B27+C27-H27-I27 | L27: =B27+C27-H27 | M27: =L27-B27 | N27: =C27 | O27: 0 | P27: =O27*K27 | R27: 0 | S27: =O27*M27 | T27: =O27*N27
A28: Piglets | B28: 13 | C28: 0 | H28: 0 | I28: 0 | K28: =B28+C28-H28-I28 | L28: =B28+C28-H28 | M28: =L28-B28 | N28: =C28 | O28: 0 | P28: =O28*K28 | R28: 0 | S28: =O28*M28 | T28: =O28*N28
A29: Swans | B29: 0 | C29: 0 | H29: 0 | I29: 0 | K29: =B29+C29-H29-I29 | L29: =B29+C29-H29 | M29: =L29-B29 | N29: =C29 | O29: 0 | P29: =O29*K29 | R29: 0 | S29: =O29*M29 | T29: =O29*N29
A30: Peacocks | B30: 0 | C30: 0 | H30: 0 | I30: 0 | K30: =B30+C30-H30-I30 | L30: =B30+C30-H30 | M30: =L30-B30 | N30: =C30 | O30: 0 | P30: =O30*K30 | R30: 0 | S30: =O30*M30 | T30: =O30*N30
A31: Total Value
A34: Wool | B34: 0 | C34: 0 | H34: 0 | I34: 0
A35: Coarse wool | B35: 0 | C35: 0 | H35: 0 | I35: 0
A36: Lamb's wool | B36: 0 | C36: 0 | H36: 0 | I36: 0
A37: Wool locks | B37: 0 | C37: 0 | H37: 0 | I37: 0
A38: Wool sold at shearing | B38: 0 | C38: 0 | H38: 0 | I38: 0
A39: Total wool | B39: 0 | C39: 0 | H39: 0 | I39: 0
B40: 0 | C40: 0 | H40: 0 | I40: 0
B41: 0 | C41: 0 | H41: 0 | I41: 0
A42: Hides | B42: 0 | C42: 0 | H42: 0 | I42: 0
A43: Ox hides | B43: 0 | C43: 0 | H43: 0 | I43: 0
A44: Mare | B44: 0 | C44: 0 | H44: 0 | I44: 0
A45: Steer | B45: 0 | C45: 0 | H45: 0 | I45: 0
A46: calves | B46: 0 | C46: 0 | H46: 0 | I46: 0
A47: pigs | B47: 29 | C47: 0 | H47: 0 | I47: 0
A48: Woolskins
A49: wethers
A50: rams
A51: ewes
A52: hoggs
A53: Woolskins total | B53: 0 | C53: 0 | H53: 50 | I53: 55
A54: Bareskins
A55: wethers
A56: rams
A57: ewes
A58: hoggs
A59: Bareskins total | B59: 0 | C59: 0 | H59: 0 | I59: 0
A60: Lambskins | B60: 0 | C60: 0 | H60: 0 | I60: 0
A61: Rotted skins | B61: 0 | C61: 0 | H61: 0 | I61: 0
A62: Shorn skins | B62: 0 | C62: 0 | H62: 0 | I62: 0
A63: Total
A66: Poultry stock
A67: Hens | L67: =B67+C67-H67 | M67: =L67-B67 | N67: =C67 | O67: 0 | Q67: =R67*K67 | R67: 0 | S67: =O67*M67 | T67: =O67*N67
A68: Geese | L68: =B68+C68-H68 | M68: =L68-B68 | N68: =C68 | O68: 0 | Q68: =R68*K68 | R68: 0 | S68: =O68*M68 | T68: =O68*N68
A69: Capons (from chickens) | B69: 0 | C69: 6 | H69: 6 | K69: 0 | L69: =B69+C69-H69 | M69: =L69-B69 | N69: =C69 | O69: 0 | Q69: =R69*K69 | R69: 0 | S69: =O69*M69 | T69: =O69*N69
A70: Cocks & hens | B70: 0 | F70: 28 | G70: 18 | H70: 10 | K70: 0 | L70: =B70+C70-H70 | M70: =L70-B70 | N70: =C70 | O70: 0 | Q70: =R70*K70 | R70: 0 | S70: =O70*M70 | T70: =O70*N70
A71: Total poultry stock
A72: Total poultry excluding churchscot
A74: Poultry production
A75: Eggs | B75: 0 | C75: 0 | H75: 0 | I75: 0 | S75: =O75*M75 | T75: =O75*N75
A76: Cocks & hens from churchscot of customary tenants | B76: 0 | C76: 0 | H76: 0 | I76: 0 | S76: =O76*M76 | T76: =O76*N76
A77: Sum of above | S77: =SUM(S75:S76) | T77: =SUM(T75:T76)
A78: Total
A81: Meat
A82: Beef | B82: 0 | C82: 0 | H82: 0 | I82: 0 | S82: =O82*M82 | T82: =O82*N82
A83: Mutton | B83: 0 | C83: 0 | H83: 0 | I83: 0 | S83: =O83*M83 | T83: =O83*N83
A84: Pork | B84: 0 | C84: 0 | H84: 0 | I84: 0 | S84: =O84*M84 | T84: =O84*N84
A85: Total
A87: Cheese
A88: Winter cheese | B88: 0 | C88: 0 | H88: 0 | I88: 0 | S88: =O88*M88 | T88: =O88*N88
A89: Summer cheese | B89: 0 | C89: 0 | H89: 0 | I89: 0 | S89: =O89*M89 | T89: =O89*N89
A90: Total
A92: Butter
A93: Butter | B93: 0 | C93: 0 | H93: 0 | I93: 0 | S93: =O93*M93 | T93: =O93*N93
A94: Total
A96: Total Dairy Sales
A99: Cider | B99: 0 | C99: 0 | H99: 0 | I99: 0
A102: Additional Information (not necessarily useful)
A103: Utensils
A104: ploughs
A105: carts
A106: cart-ropes
A107: corn baskets
A108: seed-sacks
A109: seed basket
A110: locks for the doors
A111: lead vessel
A112: brass pots
A113: pans
... A128: brass posnets

Sheet raw data
A1: Heading | B1: Sentence | C1: Total in Pounds | D1: Pounds | E1: Shillings | F1: Pence | G1: Corn | H1: Total Quarters Except 1 | I1: Total Bushels Except 1 | J1: Total Corn Cross-Check | K1: Total Corn Manorial Account | L1: Corn Quantity Error | M1: Quarters 1 | N1: Bushels 1 | O1: Quarters 2 | P1: Bushels 2 | Q1: Quarters 3 | R1: Bushels 3 | S1: shilling a quarter 1 | T1: pence a quarter 1 | U1: shilling a quarter 2 | V1: pence a quarter 2 | W1: shilling a quarter 3 | X1: pence a quarter 3 | Y1: shilling a quarter 4 | Z1: pence a quarter 4 | AA1: shilling a bushel 1 | AB1: pence a bushel 1 | AC1: shilling a bushel 2 | AD1: pence a bushel 2 | AE1: shilling a bushel 3 | AF1: pence a bushel 3 | AG1: shilling a bushel 4 | AH1: pence a bushel 4
A2: west wycombe | B2: the account there for the sixth year of the translation of henry beaufort', lord bishop of winchester, and the eleventh year of the reign of king henry the fourth after the conquest.. | C2: 0 | D2: 0 | E2: 0 | F2: 0 | H2: 0 | I2: 0 | J2: 0 | K2: 0 | L2: 0 | M2: 0 | N2: 0
A3: arrears | B3: william lythewey, farmer there, answers for £1 14 shilling 2pence of arrears from the last account of the preceding year. | C3: 1.71 | D3: 1 | E3: 14 | F3: 2 | H3: 0 | I3: 0 | J3: 0 | K3: 0 | L3: 0 | M3: 0 | N3: 0
A4: arrears | B4: total, £1 14 shilling 2pence. | C4: 1.71 | D4: 1 | E4: 14 | F4: 2 | H4: 0 | I4: 0 | J4: 0 | K4: 0 | L4: 0 | M4: 0 | N4: 0
A5: farm of the manor | B5: and for £73 6 shilling 8pence for the farm of the manor there for the year, excepting only the pleas of the court, wards, marriages, reliefs, entry fines, wood and all profits accruing from the steward's tourns, apart from tithingpenny. | C5: 73.33 | D5: 73 | E5: 6 | F5: 8 | H5: 0 | I5: 0 | J5: 0 | K5: 0 | L5: 0 | M5: 0 | N5: 0
A6: farm of the manor | B6: total, £73 6 shilling 8pence. | C6: 73.33 | D6: 73 | E6: 6 | F6: 8 | H6: 0 | I6: 0 | J6: 0 | K6: 0 | L6: 0 | M6: 0 | N6: 0
A7: issues of the manor | B7: and for 13 shilling 6pence from the woolskins sold of 50 ewes in murrain before shearing as made clear elsewhere, at 3pence a skin. | C7: 0.68 | D7: 0 | E7: 13 | F7: 6 | H7: 0 | I7: 0 | J7: 0 | K7: 0 | L7: 0 | M7: 0 | N7: 0
A8: issues of the manor | B8: total, 13 shilling 6pence. | C8: 0.68 | D8: 0 | E8: 13 | F8: 6 | H8: 0 | I8: 0 | J8: 0 | K8: 0 | L8: 0 | M8: 0 | N8: 0
A9: sale of wood | B9: and for £3 from wood sold in booker this year. | C9: 3 | D9: 3 | E9: 0 | F9: 0 | H9: 0 | I9: 0 | J9: 0 | K9: 0 | L9: 0 | M9: 0 | N9: 0
A10: sale of wood | B10: 9 shilling from wood sold in northewode. | C10: 0.45 | D10: 0 | E10: 9 | F10: 0 | H10: 0 | I10: 0 | J10: 0 | K10: 0 | L10: 0 | M10: 0 | N10: 0
A11: sale of wood | B11: £1 16 shilling 9pence from wood sold in haveryngdowne. | C11: 1.84 | D11: 1 | E11: 16 | F11: 9 | H11: 0 | I11: 0 | J11: 0 | K11: 0 | L11: 0 | M11: 0 | N11: 0
A12: sale of wood | B12: total, £5 5 shilling 9pence. | C12: 5.29 | D12: 5 | E12: 5 | F12: 9 | H12: 0 | I12: 0 | J12: 0 | K12: 0 | L12: 0 | M12: 0 | N12: 0
A13: entry and marriage fines | B13: and for 3 shilling 4pence from john lylye and isabel his wife to have 1 messuage, 16.5 acres and the sixth part of 1 acre of land and 1 messuage, 11 acres and 1 rood of purpresture in the tithing of booker, which belonged to john lymmer' and which came into the lord's hands as his escheat because noone of the kin of the said john took steps to fine for the same although a proclamation was made according to the custom of the manor. | C13: 0.17 | D13: 0 | E13: 3 | F13: 4 | H13: 0 | I13: 0 | J13: 0 | K13: 0 | L13: 0 | M13: 0 | N13: 0
... A45: cost of buildings | B45: 100 hollow tiles bought 4 shilling. | C45: 0.2 | D45: 0 | E45: 4 | F45: 0 | H45: 0 | I45: 0 | J45: 0 | K45: 0 | L45: 0 | M45: 0 | N45: 0
A46: cost of buildings | B46: 3 quarters of limestone bought 4 shilling, at 1 shilling 4pence a quarters. | C46: 0.22 | D46: 0 | E46: 4 | F46: 4 | H46: 3 | I46: 0 | J46: 3 | K46: 3 | L46: 0 | M46: 3 | N46: 0 | S46: 1 | T46: 4
A47: cost of buildings | B47: hiring 1 carter to carry the said 3,100 tiles and 3 quarters of lime 2 shilling 8pence. | C47: 0.13 | D47: 0 | E47: 2 | F47: 8 | H47: 3 | I47: 0 | J47: 3 | K47: 3 | L47: 0 | M47: 3 | N47: 0
A48: cost of buildings | B48: hiring 1 tiler to tile the said cow-shed by piece-work 11 s. 4pence. | C48: 0.02 | D48: 0 | E48: 0 | F48: 4 | H48: 0 | I48: 0 | J48: 0 | K48: 0 | L48: 0 | M48: 0 | N48: 0
A49: cost of buildings | B49: 300 laths bought 1 shilling 6pence, at 6pence a 100.. | C49: 0.08 | D49: 0 | E49: 1 | F49: 6 | H49: 0 | I49: 0 | J49: 0 | K49: 0 | L49: 0 | M49: 0 | N49: 0
A50: cost of buildings | B50: 1,000 lath-nails bought for the same 1 shilling 2pence. | C50: 0.06 | D50: 0 | E50: 1 | F50: 2 | H50: 0 | I50: 0 | J50: 0 | K50: 0 | L50: 0 | M50: 0 | N50: 0
A51: cost of buildings | B51: tile-pins bought 10pence. | C51: 0.04 | D51: 0 | E51: 0 | F51: 10 | H51: 0 | I51: 0 | J51: 0 | K51: 0 | L51: 0 | M51: 0 | N51: 0
A52: cost of buildings | B52: hiring 1 carpenter to fit the north end of the barley barn with ground-sills and studs by piece-work 2 shilling. | C52: 0.1 | D52: 0 | E52: 2 | F52: 0 | G52: barley | H52: 0 | I52: 0 | J52: 0 | K52: 0 | L52: 0 | M52: 0 | N52: 0
A53: cost of buildings | B53: hiring 1 man to cover with laths, daub and pin the said end of the barn by piece-work 2 shilling 2pence. | C53: 0.11 | D53: 0 | E53: 2 | F53: 2 | H53: 0 | I53: 0 | J53: 0 | K53: 0 | L53: 0 | M53: 0 | N53: 0
A54: cost of buildings | B54: hiring 1 carpenter to underpin and fit with ground-sills and studs the great chamber for 4 days 1 shilling 8pence, taking 5pence a day. | C54: 0.08 | D54: 0 | E54: 1 | F54: 8 | H54: 0 | I54: 0 | J54: 0 | K54: 0 | L54: 0 | M54: 0 | N54: 0
A55: cost of buildings | B55: hiring 1 man to wattle and daub the lower chamber under the great chamber for 3 days 1 shilling, taking 4pence a day. | C55: 0.07 | D55: 0 | E55: 1 | F55: 4 | H55: 0 | I55: 0 | J55: 0 | K55: 0 | L55: 0 | M55: 0 | N55: 0
A56: cost of buildings | B56: 100 stud-nails bought 4pence. | C56: 0.02 | D56: 0 | E56: 0 | F56: 4 | H56: 0 | I56: 0 | J56: 0 | K56: 0 | L56: 0 | M56: 0 | N56: 0
A57: cost of buildings | B57: hiring 1 man to dig earth and sand for the abovesaid repairs for 4 days 1 shilling 4pence, taking 4pence a day. | C57: 0.07 | D57: 0 | E57: 1 | F57: 4 | H57: 0 | I57: 0 | J57: 0 | K57: 0 | L57: 0 | M57: 0 | N57: 0
A58: cost of buildings | B58: hiring 1 carter to carry the said earth and sand for 4 days 4 shilling, taking ls, a day. | C58: 0.2 | D58: 0 | E58: 4 | F58: 0 | H58: 0 | I58: 0 | J58: 0 | K58: 0 | L58: 0 | M58: 0 | N58: 0
A59: cost of buildings | B59: total, £5 9 shilling 2pence. | C59: 5.46 | D59: 5 | E59: 9 | F59: 2 | H59: 0 | I59: 0 | J59: 0 | K59: 0 | L59: 0 | M59: 0 | N59: 0
A60: expenses of the steward | B60: in expenses of richard wyot, steward, holding the tourns of martinmas and hockday, by 2 sealed bills in cash, 14 shilling 5pence. | C60: 0.72 | D60: 0 | E60: 14 | F60: 5 | H60: 0 | I60: 0 | J60: 0 | K60: 0 | L60: 0 | M60: 0 | N60: 0
A61: expenses of the steward | B61: 3 bushels of wheat bought for baking bread 3 shilling 6pence, at 1 shilling 6pence for 1 bushels, and 1 shilling a bushels for 2 bushels. | C61: 0.17 | D61: 0 | E61: 3 | F61: 6 | G61: wheat | H61: 0 | I61: 3 | J61: 0.38 | K61: 0.38 | L61: 0 | M61: 0 | N61: 3 | O61: 0 | P61: 1 | Q61: 0 | R61: 2 | AA61: 1 | AB61: 0
A62: expenses of the steward | B62: 3 quarters 2 bushels of oats bought 10 shilling 4pence, at 3 shilling a quarters for 1 quarters 4 bushels, and 3 shilling 4pence a quarters for 1 quarters 6 bushels. | C62: 0.52 | D62: 0 | E62: 10 | F62: 4 | G62: oats | H62: 2 | I62: 10 | J62: 3.25 | K62: 3.25 | L62: 0 | M62: 3 | N62: 2 | O62: 1 | P62: 4 | Q62: 1 | R62: 6 | S62: 3 | T62: 0 | U62: 3 | V62: 4
A63: expenses of the steward | B63: total, £1 8 shilling 3pence. | C63: 1.41 | D63: 1 | E63: 8 | F63: 3 | H63: 0 | I63: 0 | J63: 0 | K63: 0 | L63: 0 | M63: 0 | N63: 0
A64: wages and stipends | B64: in wages of william beck', bailiff, for part of his wages, £3 6 shilling 8pence, and he takes the rest elsewhere. | C64: 3.33 | D64: 3 | E64: 6 | F64: 8 | H64: 0 | I64: 0 | J64: 0 | K64: 0 | L64: 0 | M64: 0 | N64: 0
A65: wages and stipends | B65: stipend of 1 warrener keeping the lord's woods and warrens, collecting amercements and summoning the courts for the year, by agreement made by the steward and bailiff, 13 shilling 4pence. | C65: 0.67 | D65: 0 | E65: 13 | F65: 4 | H65: 0 | I65: 0 | J65: 0 | K65: 0 | L65: 0 | M65: 0 | N65: 0
A66: wages and stipends | B66: total, £4.. | C66: 4 | D66: 4 | E66: 0 | F66: 0 | H66: 0 | I66: 0 | J66: 0 | K66: 0 | L66: 0 | M66: 0 | N66: 0
A67: total of all expenses | B67: total of all expenses, £15 4 shilling 1pence. | C67: 15.2 | D67: 15 | E67: 4 | F67: 1 | H67: 0 | I67: 0 | J67: 0 | K67: 0 | L67: 0 | M67: 0 | N67: 0
A68: and he owes | B68: and he owes, £68 13 shilling 11pence. | C68: 68.7 | D68: 68 | E68: 13 | F68: 11 | H68: 0 | I68: 0 | J68: 0 | K68: 0 | L68: 0 | M68: 0 | N68: 0
A69: allowances without writ | B69: in allowance to the farmer for £2 5 shilling 1pence for the murrain of livestock (averiorum) disallowed within and elsewhere because he attested at the audit that he should receive allowance of a moiety for common murrain when it occurs. | C69: 2.25 | D69: 2 | E69: 5 | F69: 1 | H69: 0 | I69: 0 | J69: 0 | K69: 0 | L69: 0 | M69: 0 | N69: 0
A70: allowances without writ | B70: 5 shilling 6pence for various disallowances made against him above. | C70: 0.28 | D70: 0 | E70: 5 | F70: 6 | H70: 0 | I70: 0 | J70: 0 | K70: 0 | L70: 0 | M70: 0 | N70: 0
A71: allowances without writ | B71: total, £2 10 shilling 7pence. | C71: 2.53 | D71: 2 | E71: 10 | F71: 7 | H71: 0 | I71: 0 | J71: 0 | K71: 0 | L71: 0 | M71: 0 | N71: 0
A72: cash deliveries | B72: delivered to john arnald', receiver of wolvesey, by 1 tally, £66 3 shilling 4pence. | C72: 66.17 | D72: 66 | E72: 3 | F72: 4 | H72: 0 | I72: 0 | J72: 0 | K72: 0 | L72: 0 | M72: 0 | N72: 0
A73: cash deliveries | B73: total, £66 3 shilling 4pence. | C73: 66.17 | D73: 66 | E73: 3 | F73: 4 | H73: 0 | I73: 0 | J73: 0 | K73: 0 | L73: 0 | M73: 0 | N73: 0
A74: total of all allowances and cash deliveries | B74: total of all allowances and cash deliveries, £68 13 shilling 11pence he is quit. | C74: 68.7 | D74: 68 | E74: 13 | F74: 11 | H74: 0 | I74: 0 | J74: 0 | K74: 0 | L74: 0 | M74: 0 | N74: 0
A75: wheat | B75: william lythewey, farmer there, answers for 12 quarters of wheat remaining.. | C75: 0 | D75: 0 | E75: 0 | F75: 0 | G75: wheat | H75: 12 | I75: 0 | J75: 12 | K75: 12 | L75: 0 | M75: 12 | N75: 0
A76: wheat | B76: total, 12 quarters.. | C76: 0 | D76: 0 | E76: 0 | F76: 0 | H76: 12 | I76: 0 | J76: 12 | K76: 12 | L76: 0 | M76: 12 | N76: 0
A77: wheat | B77: 12 quarters remain, sown over 38.5 acres of land by the perch lying on assherugg'. | C77: 0 | D77: 0 | E77: 0 | F77: 0 | H77: 12 | I77: 0 | J77: 12 | K77: 12 | L77: 0 | M77: 12 | N77: 0
A78: wheat | B78: that is, 2.5 bushels an acre, less 1 peck in all, in the hands of the said william lythewey, farmer there, to be restored and handed back at the end of 12 years, this year being the third.. | C78: 0 | D78: 0 | E78: 0 | F78: 0 | H78: 0 | I78: 2.5 | J78: 0.31 | K78: 0.31 | L78: 0 | M78: 0 | N78: 2.5
A79: barley | B79: and for 13 quarters of barley remaining.. | C79: 0 | D79: 0 | E79: 0 | F79: 0 | G79: barley | H79: 13 | I79: 0 | J79: 13 | K79: 13 | L79: 0 | M79: 13 | N79: 0
A80: barley | B80: total, 13 quarters.. | C80: 0 | D80: 0 | E80: 0 | F80: 0 | H80: 13 | I80: 0 | J80: 13 | K80: 13 | L80: 0 | M80: 13 | N80: 0
A81: barley | B81: 13 quarters remain, sown over 26 acres of land by the perch lying in le estfeld' and chetenor'. | C81: 0 | D81: 0 | E81: 0 | F81: 0 | H81: 13 | I81: 0 | J81: 13 | K81: 13 | L81: 0 | M81: 13 | N81: 0
A82: barley | B82: that is, 4 bushels an acre, in the hands of the said farmer, to be restored and handed back as before. | C82: 0 | D82: 0 | E82: 0 | F82: 0 | H82: 0 | I82: 4 | J82: 0.5 | K82: 0.5 | L82: 0 | M82: 0 | N82: 4
A83: dredge | B83: and for 7 quarters of dredge remaining.. | C83: 0 | D83: 0 | E83: 0 | F83: 0 | G83: dredge | H83: 7 | I83: 0 | J83: 7 | K83: 7 | L83: 0 | M83: 7 | N83: 0
A84: dredge | B84: total, 7 quarters.. | C84: 0 | D84: 0 | E84: 0 | F84: 0 | H84: 7 | I84: 0 | J84: 7 | K84: 7 | L84: 0 | M84: 7 | N84: 0
A85: dredge | B85: 7 quarters remain, sown over 14 acres of land by the perch lying in le estfeld. | C85: 0 | D85: 0 | E85: 0 | F85: 0 | H85: 7 | I85: 0 | J85: 7 | K85: 7 | L85: 0 | M85: 7 | N85: 0
A86: dredge | B86: that is, 4 bushels an acre, in the hands of the said fanner, to be restored and handed back as before. | C86: 0 | D86: 0 | E86: 0 | F86: 0 | H86: 0 | I86: 4 | J86: 0.5 | K86: 0.5 | L86: 0 | M86: 0 | N86: 4
A87: pulses | B87: and for 2 quarters of pulses remaining.. | C87: 0 | D87: 0 | E87: 0 | F87: 0 | H87: 2 | I87: 0 | J87: 2 | K87: 2 | L87: 0 | M87: 2 | N87: 0
A88: pulses | B88: total, 2 quarters.. | C88: 0 | D88: 0 | E88: 0 | F88: 0 | H88: 2 | I88: 0 | J88: 2 | K88: 2 | L88: 0 | M88: 2 | N88: 0
A89: pulses | B89: 2 quarters remain, sown over 5.5 acres of land by the perch lying in le estfeld'. | C89: 0 | D89: 0 | E89: 0 | F89: 0 | H89: 2 | I89: 0 | J89: 2 | K89: 2 | L89: 0 | M89: 2 | N89: 0
A90: pulses | B90: that is, 3 bushels an acre, less .5 bushels in all, in the hands of the said fanner, to be restored and handed back as before. | C90: 0 | D90: 0 | E90: 0 | F90: 0 | H90: 0 | I90: 5 | J90: 0.62 | K90: 0.38 | L90: 0.25 | M90: 0 | N90: 3 | O90: 0 | P90: 5
A91: oats | B91: and for 11 quarters of oats remaining.. | C91: 0 | D91: 0 | E91: 0 | F91: 0 | G91: oats | H91: 11 | I91: 0 | J91: 11 | K91: 11 | L91: 0 | M91: 11 | N91: 0
A92: oats | B92: total, 11 quarters.. | C92: 0 | D92: 0 | E92: 0 | F92: 0 | H92: 11 | I92: 0 | J92: 11 | K92: 11 | L92: 0 | M92: 11 | N92: 0
A93: oats | B93: 11 quarters remain, sown over 22 acres of land by the perch lying in sparburyfeld'. | C93: 0 | D93: 0 | E93: 0 | F93: 0 | H93: 11 | I93: 0 | J93: 11 | K93: 11 | L93: 0 | M93: 11 | N93: 0
A94: oats | B94: that is, 4 bushels an acre, in the hands of the said farmer, to be restored and handed back as before. | C94: 0 | D94: 0 | E94: 0 | F94: 0 | H94: 0 | I94: 4 | J94: 0.5 | K94: 0.5 | L94: 0 | M94: 0 | N94: 4
A95: acreage | B95: total acreage sown, 106 acres. | C95: 0 | D95: 0 | E95: 0 | F95: 0 | H95: 0 | I95: 0 | J95: 0 | K95: 0 | L95: 0 | M95: 0 | N95: 0
A96: stock | B96: horses: 4 remain. | C96: 0 | D96: 0 | E96: 0 | F96: 0 | H96: 0 | I96: 0 | J96: 0 | K96: 0 | L96: 0 | M96: 0 | N96: 0
A97: stock | B97: total, 4. 4 cart-horses remain, worth 14 shilling each, in the hands of the said farmer, to be restored at the end of his farm or the value of the same at the lord's will as before. | C97: 0.7 | D97: 0 | E97: 14 | F97: 0 | H97: 0 | I97: 0 | J97: 0 | K97: 0 | L97: 0 | M97: 0 | N97: 0
A98: stock | B98: plough-horses: 12 remain. | C98: 0 | D98: 0 | E98: 0 | F98: 0 | H98: 0 | I98: 0 | J98: 0 | K98: 0 | L98: 0 | M98: 0 | N98: 0
A99: stock | B99: total, 12. 12 remain, of which 6 are worth 8 shilling each and 6 worth 6 shilling each, in the hands of the said fanner, to be restored at the end of his farm or the value of the same at the lord's will. | C99: 0.4 | D99: 0 | E99: 8 | F99: 0 | H99: 0 | I99: 0 | J99: 0 | K99: 0 | L99: 0 | M99: 0 | N99: 0
A100: stock | B100: bulls: 1 remains, worth 9 shilling, in the hands of the said fanner, to be restored and handed back at the end of his farm or the value of the same at the lord's will. | C100: 0.45 | D100: 0 | E100: 9 | F100: 0 | H100: 0 | I100: 0 | J100: 0 | K100: 0 | L100: 0 | M100: 0 | N100: 0
A101: stock | B101: cows: 31 remain. | C101: 0 | D101: 0 | E101: 0 | F101: 0 | H101: 0 | I101: 0 | J101: 0 | K101: 0 | L101: 0 | M101: 0 | N101: 0
A102: stock | B102: total, 31, worth 9 shilling each, in the hands.of the said farmer, to be restored and handed back at the end of his farm as before. | C102: 0.45 | D102: 0 | E102: 9 | F102: 0 | H102: 0 | I102: 0 | J102: 0 | K102: 0 | L102: 0 | M102: 0 | N102: 0
A103: stock | B103: steers: 5 remain. | C103: 0 | D103: 0 | E103: 0 | F103: 0 | H103: 0 | I103: 0 | J103: 0 | K103: 0 | L103: 0 | M103: 0 | N103: 0
... A140: stock | B140: the aforesaid william lythewey, farmer there, is to hand back and restore that same stock, both live and dead, at the end of his term in as good condition as he received it. | C140: 0 | D140: 0 | E140: 0 | F140: 0 | H140: 0 | I140: 0 | J140: 0 | K140: 0 | L140: 0 | M140: 0 | N140: 0

Sheet Stock_raw
A1: Heading | B1: Sentence | C1: Quarters 1 | D1: Bushels 1 | E1: stock | F1: inherited stock | G1: added | H1: murrain | I1: sold
A2: Oats | B2: Total | C2: 0 | D2: 0
A3: Stock | B3: Horses: 4 remain. | C3: 0 | D3: 0 | F3: 4
A4: Stock | B4: Total, 4. 4 cart-horses remain, worth 14 shilling each, in the hands of the said farmer, to be restored at the end of his farm or the value of the same at the lord's will as before. | C4: 0 | D4: 0
A5: Stock | B5: Plough-horses: 12 remain. | C5: 0 | D5: 0 | E5: Plough-horses | F5: 12
A6: Stock | B6: Total, 12. 12 remain, of which 6 are worth 8 shilling each and 6 worth 6 shilling each, in the hands of the said fanner, to be restored at the end of his farm or the value of the same at the lord's will. | C6: 0 | D6: 0 | E6: Plough-horses
A7: Stock | B7: Bulls: 1 remains, worth 9 shilling, in the hands of the said fanner, to be restored and handed back at the end of his farm or the value of the same at the lord's will. | C7: 0 | D7: 0 | E7: Bulls
A8: Stock | B8: Cows: 31 remain. | C8: 0 | D8: 0 | E8: Cows | F8: 31
A9: Stock | B9: Total, 31, worth 9 shilling each, in the hands.of the said farmer, to be restored and handed back at the end of his farm as before. | C9: 0 | D9: 0 | E9: Cows
A10: Stock | B10: Steers: 5 remain. | C10: 0 | D10: 0 | E10: Steers | F10: 5
A11: Stock | B11: Total, 5. 5 remain, worth 5 shilling each, in the hands of the said farmer, to be restored and handed back at the end of his farm or the value of the same at the lord's will. | C11: 0 | D11: 0 | E11: Steers
A12: Stock | B12: Bullocks: 6 remain. | C12: 0 | D12: 0 | E12: Bullocks | F12: 6
A13: Stock | B13: Total, 6. 6 remain, worth 4 shilling each, in the hands of the said farmer, to be restored and handed back at the end of his farm or the value of the same at the lord's will. | C13: 0 | D13: 0 | E13: Bullocks
A14: Stock | B14: Yearlings: 5 remain. | C14: 0 | D14: 0 | E14: Yearlings | F14: 5
A15: Stock | B15: Total, 5. 5 remain, worth 3 shilling each, in the hands of the said farmer, to be restored and handed back at the end of his farm or the value of the same at the lord's will. | C15: 0 | D15: 0 | E15: Yearlings
A16: Stock | B16: Rams: 8 remain, worth 1 shilling 4pence each, in the hands of the said farmer, to be restored and handed back at the end of his farm or the value of the same at the lord's will. | C16: 0 | D16: 0 | E16: Rams | F16: 8
A17: Stock | B17: Ewes: 313 remain. | C17: 0 | D17: 0 | E17: Ewes | F17: 313
A18: Stock | B18: 55 bought. | C18: 0 | D18: 0 | E18: Ewes | G18: 55
A19: Stock | B19: Total, 368. 55 in murrain before lambing and shearing. | C19: 0 | D19: 0 | E19: Ewes | H19: 55
A20: Stock | B20: 313 remain, worth 1 shilling 4pence each, in the hands of the said farmer, to be restored and handed back at the end of his farm or the value of the same at the lord's will. | C20: 0 | D20: 0 | E20: Ewes
A21: Stock | B21: Lambs: 84 remain. | C21: 0 | D21: 0 | E21: Lambs | F21: 84
A22: Stock | B22: Total, 84. 84 remain, worth 10pence each, in the hands of the said farmer, to be restored and handed back at the end of his farm or the value of the same at the lord's will. | C22: 0 | D22: 0 | E22: Lambs
A23: Stock | B23: Boars: 1 remains, worth 4 shilling, in the hands of the said farmer, to be restored and handed back at the end of his farm or the value of the same at the lord's will. | C23: 0 | D23: 0 | E23: Boars
A24: Stock | B24: Sows: 3 remain. | C24: 0 | D24: 0 | E24: Sows | F24: 3
A25: Stock | B25: Total, 3. 3 remain, worth 2 shilling 6pence each, in the hands of the said farmer, to be restored and handed back at the end of his farm or the value of the same at the lord's will. | C25: 0 | D25: 0 | E25: Sows
A26: Stock | B26: Pigs: 29 remain. | C26: 0 | D26: 0 | E26: Pigs | F26: 29
A27: Stock | B27: Total, 29. 29 remain, worth 1 shilling 8pence each, in the hands of the said farmer, to be restored and handed back at the end of his farm or the value of the same at the lord's will. | C27: 0 | D27: 0 | E27: Pigs
A28: Stock | B28: Hoggets: 32 remain. | C28: 0 | D28: 0 | E28: Hoggets | F28: 32
A29: Stock | B29: Total, 32. 32 remain, worth 10pence each, in the hands of the said farmer, to be restored and handed back as before. | C29: 0 | D29: 0 | E29: Hoggets
A30: Stock | B30: Piglets: 13 remain. | C30: 0 | D30: 0 | E30: Piglets | F30: 13
A31: Stock | B31: Total, 13. 13 remain, worth 4pence each, in the hands of the said farmer, to be restored and handed back as before. | C31: 0 | D31: 0 | E31: Piglets
A32: Stock | B32: Woolskins: 55 from ewes in murrain before shearing as made clear aboVe. | C32: 0 | D32: 0 | E32: Woolskins | H32: 55
A33: Stock | B33: Total, 55. 5 in tithe. | C33: 0 | D33: 0 | E33: Woolskins
A34: Stock | B34: 50 sold within. | C34: 0 | D34: 0 | E34: Woolskins | I34: 50
A35: Stock | B35: Total as before. | C35: 0 | D35: 0 | E35: Woolskins
A36: Stock | B36: None remain. | C36: 0 | D36: 0 | E36: Woolskins
A37: Stock | B37: Geese: 1 gander, 4 breeding geese and 22 of their offspring remain, of which the gander and 4 geese are worth 6pence each and the 22 goslings 1.5pence each, in the hands of the said farmer, to be restored as before. | C37: 0 | D37: 0 | E37: Poultry stock | F37: 4 | G37: 4
A38: Stock | B38: Cocks and hens: 1 cock and 5 hens remain. | C38: 0 | D38: 0 | E38: Poultry stock
A39: Stock | B39: Total, 6. 1 cock and 5 hens remain, worth 2pence each, in the hands of the said farmer, to be restored as before. | C39: 0 | D39: 0 | E39: Poultry stock
A40: Stock | B40: Utensils: 3 ploughs with 3 coulters, 3 ploughshares, 3 iron plough shoes and all other equipment for 18 plough-horses, with 3 wooden harrows. | C40: 0 | D40: 0 | E40: Utensils
A41: Stock | B41: 2 carts, 1 of them with iron tyres, with 2 frames, 2 cart-rails, 4 linch-pins and 1 tumbrel remain. | C41: 0 | D41: 0 | E41: Utensils | F41: 4
A42: Stock | B42: 4 collars, 3 pairs of traces, 1 thill hame (thilhame), 2 cart-ropes and 2 cart-saddles with saddle-pads remain. | C42: 0 | D42: 0 | E42: Utensils
A43: Stock | B43: 2 brass pots, 1 posnet with 1 tripod, 2 brass pans and 1 basin with a ewer remain. | C43: 0 | D43: 0 | E43: Utensils
A44: Stock | B44: 1 canvas winnowing-fan, 2 sacks, 2 sieves, 2 riddles, 1 basket for carrying corn, 2 dung-forks and 1 fork for sheaves remain. | C44: 0 | D44: 0 | E44: Utensils
A45: Stock | B45: 2 pails, 2 fodder-racks for grazing cattle, 2 troughs and 4 locks with keys and chains for keeping the horses and plough-horses safe remain. | C45: 0 | D45: 0 | E45: Utensils
A46: Stock | B46: Total as made clear. | C46: 0 | D46: 0 | E46: Utensils
A47: Stock | B47: The aforesaid William Lythewey, farmer there, is to hand back and restore that same stock, both live and dead, at the end of his term in as good condition as he received it. | C47: 0 | D47: 0 | E47: Utensils
A48: Stock | B48: Total | C48: 0 | D48: 0 | E48: Utensils

Sheet Issues of the Mills

Sheet Prices

Sheet Labour Rents

Sheet not needed

Sheet Issues of the Grange raw
A1: Heading | B1: Sentence | C1: Quarters 1_x | D1: Bushels 1_x | E1: Sown Quarters | F1: Sown Bushels | G1: Sown Total Quarters | H1: Bought in Quarters | I1: Bought in Bushels | J1: Bought in Total Quarters | K1: Tithe Quarters | L1: Tithe Bushels | M1: Tithe Total Quarters | N1: Manorial servants & livestock Quarters | O1: Manorial servants & livestock Bushels | P1: Manorial servants & livestock Total Quarters | Q1: Sold Quarters | R1: Sold Bushels | S1: Sold Total Quarters | T1: Account Quarters | U1: Account Bushels | V1: Account Total Quarters | W1: bought only | X1: Total Quarters Except 1 | Y1: Total Bushels Except 1 | Z1: Total Corn Cross-Check | AA1: Total Corn Manorial Account | AB1: Corn Quantity Error | AC1: Quarters 1_y | AD1: Bushels 1_y | AE1: Quarters 2 | AF1: Bushels 2 | AG1: Quarters 3 | AH1: Bushels 3 | AI1: Total Bought Quarters
A2: total of all allowances and cash deliveries | B2: total | C2: 0 | D2: 0 | E2: 0 | F2: 0 | G2: 0 | H2: 0 | I2: 0 | J2: 0 | K2: 0 | L2: 0 | M2: 0 | N2: 0 | O2: 0 | P2: 0 | Q2: 0 | R2: 0 | S2: 0 | T2: 0 | U2: 0 | V2: 0 | W2: 0 | AI2: 0
A3: wheat | B3: william lythewey, farmer there, answers for 12 quarters of wheat remaining.. | C3: 0 | D3: 0 | E3: 0 | F3: 0 | G3: 0 | H3: 0 | I3: 0 | J3: 0 | K3: 0 | L3: 0 | M3: 0 | N3: 0 | O3: 0 | P3: 0 | Q3: 0 | R3: 0 | S3: 0 | T3: 0 | U3: 0 | V3: 0 | W3: 0 | X3: 12 | Y3: 0 | Z3: 12 | AA3: 12 | AB3: 0 | AC3: 12 | AD3: 0 | AI3: 0
A4: wheat | B4: total, 12 quarters.. | C4: 0 | D4: 0 | E4: 0 | F4: 0 | G4: 0 | H4: 0 | I4: 0 | J4: 0 | K4: 0 | L4: 0 | M4: 0 | N4: 0 | O4: 0 | P4: 0 | Q4: 0 | R4: 0 | S4: 0 | T4: 0 | U4: 0 | V4: 0 | W4: 0 | X4: 12 | Y4: 0 | Z4: 12 | AA4: 12 | AB4: 0 | AC4: 12 | AD4: 0 | AI4: 0
A5: wheat | B5: 12 quarters remain, sown over 38.5 acres of land by the perch lying on assherugg'. | C5: 0 | D5: 0 | E5: 12 | F5: 0 | G5: 12 | H5: 0 | I5: 0 | J5: 0 | K5: 0 | L5: 0 | M5: 0 | N5: 0 | O5: 0 | P5: 0 | Q5: 0 | R5: 0 | S5: 0 | T5: 0 | U5: 0 | V5: 0 | W5: 0 | X5: 12 | Y5: 0 | Z5: 12 | AA5: 12 | AB5: 0 | AC5: 12 | AD5: 0 | AI5: 0
A6: wheat | B6: that is, 2.5 bushels an acre, less 1 peck in all, in the hands of the said william lythewey, farmer there, to be restored and handed back at the end of 12 years, this year being the third.. | C6: 0 | D6: 0 | E6: 0 | F6: 0 | G6: 0 | H6: 0 | I6: 0 | J6: 0 | K6: 0 | L6: 0 | M6: 0 | N6: 0 | O6: 0 | P6: 0 | Q6: 0 | R6: 0 | S6: 0 | T6: 0 | U6: 0 | V6: 0 | W6: 0 | X6: 0 | Y6: 2.5 | Z6: 0.31 | AA6: 0.31 | AB6: 0 | AC6: 0 | AD6: 2.5 | AI6: 0
A7: wheat | B7: total | C7: 0 | D7: 0 | E7: 0 | F7: 0 | G7: 0 | H7: 0 | I7: 0 | J7: 0 | K7: 0 | L7: 0 | M7: 0 | N7: 0 | O7: 0 | P7: 0 | Q7: 0 | R7: 0 | S7: 0 | T7: 0 | U7: 0 | V7: 0 | W7: 0 | AI7: 0
A8: barley | B8: and for 13 quarters of barley remaining.. | C8: 0 | D8: 0 | E8: 0 | F8: 0 | G8: 0 | H8: 0 | I8: 0 | J8: 0 | K8: 0 | L8: 0 | M8: 0 | N8: 0 | O8: 0 | P8: 0 | Q8: 0 | R8: 0 | S8: 0 | T8: 0 | U8: 0 | V8: 0 | W8: 0 | X8: 13 | Y8: 0 | Z8: 13 | AA8: 13 | AB8: 0 | AC8: 13 | AD8: 0 | AI8: 0
A9: barley | B9: total, 13 quarters.. | C9: 0 | D9: 0 | E9: 0 | F9: 0 | G9: 0 | H9: 0 | I9: 0 | J9: 0 | K9: 0 | L9: 0 | M9: 0 | N9: 0 | O9: 0 | P9: 0 | Q9: 0 | R9: 0 | S9: 0 | T9: 0 | U9: 0 | V9: 0 | W9: 0 | X9: 13 | Y9: 0 | Z9: 13 | AA9: 13 | AB9: 0 | AC9: 13 | AD9: 0 | AI9: 0
A10: barley | B10: 13 quarters remain, sown over 26 acres of land by the perch lying in le estfeld' and chetenor'. | C10: 0 | D10: 0 | E10: 13 | F10: 0 | G10: 13 | H10: 0 | I10: 0 | J10: 0 | K10: 0 | L10: 0 | M10: 0 | N10: 0 | O10: 0 | P10: 0 | Q10: 0 | R10: 0 | S10: 0 | T10: 0 | U10: 0 | V10: 0 | W10: 0 | X10: 13 | Y10: 0 | Z10: 13 | AA10: 13 | AB10: 0 | AC10: 13 | AD10: 0 | AI10: 0
A11: barley | B11: that is, 4 bushels an acre, in the hands of the said farmer, to be restored and handed back as before. | C11: 0 | D11: 0 | E11: 0 | F11: 0 | G11: 0 | H11: 0 | I11: 0 | J11: 0 | K11: 0 | L11: 0 | M11: 0 | N11: 0 | O11: 0 | P11: 0 | Q11: 0 | R11: 0 | S11: 0 | T11: 0 | U11: 0 | V11: 0 | W11: 0 | X11: 0 | Y11: 4 | Z11: 0.5 | AA11: 0.5 | AB11: 0 | AC11: 0 | AD11: 4 | AI11: 0
A12: barley | B12: total | C12: 0 | D12: 0 | E12: 0 | F12: 0 | G12: 0 | H12: 0 | I12: 0 | J12: 0 | K12: 0 | L12: 0 | M12: 0 | N12: 0 | O12: 0 | P12: 0 | Q12: 0 | R12: 0 | S12: 0 | T12: 0 | U12: 0 | V12: 0 | W12: 0 | AI12: 0
A13: dredge | B13: and for 7 quarters of dredge remaining.. | C13: 0 | D13: 0 | E13: 0 | F13: 0 | G13: 0 | H13: 0 | I13: 0 | J13: 0 | K13: 0 | L13: 0 | M13: 0 | N13: 0 | O13: 0 | P13: 0 | Q13: 0 | R13: 0 | S13: 0 | T13: 0 | U13: 0 | V13: 0 | W13: 0 | X13: 7 | Y13: 0 | Z13: 7 | AA13: 7 | AB13: 0 | AC13: 7 | AD13: 0 | AI13: 0
A14: dredge | B14: total, 7 quarters.. | C14: 0 | D14: 0 | E14: 0 | F14: 0 | G14: 0 | H14: 0 | I14: 0 | J14: 0 | K14: 0 | L14: 0 | M14: 0 | N14: 0 | O14: 0 | P14: 0 | Q14: 0 | R14: 0 | S14: 0 | T14: 0 | U14: 0 | V14: 0 | W14: 0 | X14: 7 | Y14: 0 | Z14: 7 | AA14: 7 | AB14: 0 | AC14: 7 | AD14: 0 | AI14: 0
A15: dredge | B15: 7 quarters remain, sown over 14 acres of land by the perch lying in le estfeld. | C15: 0 | D15: 0 | E15: 7 | F15: 0 | G15: 7 | H15: 0 | I15: 0 | J15: 0 | K15: 0 | L15: 0 | M15: 0 | N15: 0 | O15: 0 | P15: 0 | Q15: 0 | R15: 0 | S15: 0 | T15: 0 | U15: 0 | V15: 0 | W15: 0 | X15: 7 | Y15: 0 | Z15: 7 | AA15: 7 | AB15: 0 | AC15: 7 | AD15: 0 | AI15: 0
A16: dredge | B16: that is, 4 bushels an acre, in the hands of the said fanner, to be restored and handed back as before. | C16: 0 | D16: 0 | E16: 0 | F16: 0 | G16: 0 | H16: 0 | I16: 0 | J16: 0 | K16: 0 | L16: 0 | M16: 0 | N16: 0 | O16: 0 | P16: 0 | Q16: 0 | R16: 0 | S16: 0 | T16: 0 | U16: 0 | V16: 0 | W16: 0 | X16: 0 | Y16: 4 | Z16: 0.5 | AA16: 0.5 | AB16: 0 | AC16: 0 | AD16: 4 | AI16: 0
A17: dredge | B17: total | C17: 0 | D17: 0 | E17: 0 | F17: 0 | G17: 0 | H17: 0 | I17: 0 | J17: 0 | K17: 0 | L17: 0 | M17: 0 | N17: 0 | O17: 0 | P17: 0 | Q17: 0 | R17: 0 | S17: 0 | T17: 0 | U17: 0 | V17: 0 | W17: 0 | AI17: 0
A18: oats | B18: and for 11 quarters of oats remaining.. | C18: 0 | D18: 0 | E18: 0 | F18: 0 | G18: 0 | H18: 0 | I18: 0 | J18: 0 | K18: 0 | L18: 0 | M18: 0 | N18: 0 | O18: 0 | P18: 0 | Q18: 0 | R18: 0 | S18: 0 | T18: 0 | U18: 0 | V18: 0 | W18: 0 | X18: 11 | Y18: 0 | Z18: 11 | AA18: 11 | AB18: 0 | AC18: 11 | AD18: 0 | AI18: 0
A19: oats | B19: total, 11 quarters.. | C19: 0 | D19: 0 | E19: 0 | F19: 0 | G19: 0 | H19: 0 | I19: 0 | J19: 0 | K19: 0 | L19: 0 | M19: 0 | N19: 0 | O19: 0 | P19: 0 | Q19: 0 | R19: 0 | S19: 0 | T19: 0 | U19: 0 | V19: 0 | W19: 0 | X19: 11 | Y19: 0 | Z19: 11 | AA19: 11 | AB19: 0 | AC19: 11 | AD19: 0 | AI19: 0
A20: oats | B20: 11 quarters remain, sown over 22 acres of land by the perch lying in sparburyfeld'. | C20: 0 | D20: 0 | E20: 11 | F20: 0 | G20: 11 | H20: 0 | I20: 0 | J20: 0 | K20: 0 | L20: 0 | M20: 0 | N20: 0 | O20: 0 | P20: 0 | Q20: 0 | R20: 0 | S20: 0 | T20: 0 | U20: 0 | V20: 0 | W20: 0 | X20: 11 | Y20: 0 | Z20: 11 | AA20: 11 | AB20: 0 | AC20: 11 | AD20: 0 | AI20: 0
A21: oats | B21: that is, 4 bushels an acre, in the hands of the said farmer, to be restored and handed back as before. | C21: 0 | D21: 0 | E21: 0 | F21: 0 | G21: 0 | H21: 0 | I21: 0 | J21: 0 | K21: 0 | L21: 0 | M21: 0 | N21: 0 | O21: 0 | P21: 0 | Q21: 0 | R21: 0 | S21: 0 | T21: 0 | U21: 0 | V21: 0 | W21: 0 | X21: 0 | Y21: 4 | Z21: 0.5 | AA21: 0.5 | AB21: 0 | AC21: 0 | AD21: 4 | AI21: 0

Sheet Issues of the Grange
A1: Gross Output | B1: Bought Only Aggregated | C1: Account Quarters | D1: Account Bushels | E1: Account Total Quarters | F1: Bought in Quarters | G1: Bought in Bushels | H1: Total Bought Quarters | I1: Sold Quarters | J1: Sold Bushels | K1: Sold Total Quarters | L1: Total Corn Quantity | M1: Difference Produced+Bought-Sold | N1: Weighted Average Price per Quarter | O1: Non-Weighted Average Price per Quarter | P1: Value of Total Production weighted | Q1: Value of Total Production unweighted
A2: total of all allowances and cash deliveries | B2: 0 | C2: 0 | D2: 0 | E2: 0 | F2: 0 | G2: 0 | H2: 0 | I2: 0 | J2: 0 | K2: 0 | L2: 0 | M2: 0
A3: wheat | B3: 0 | C3: 0 | D3: 0 | E3: 0 | F3: 0 | G3: 0 | H3: 0 | I3: 0 | J3: 0 | K3: 0 | L3: 0 | M3: 0
A4: barley | B4: 0 | C4: 0 | D4: 0 | E4: 0 | F4: 0 | G4: 0 | H4: 0 | I4: 0 | J4: 0 | K4: 0 | L4: 0 | M4: 0
A5: dredge | B5: 0 | C5: 0 | D5: 0 | E5: 0 | F5: 0 | G5: 0 | H5: 0 | I5: 0 | J5: 0 | K5: 0 | L5: 0 | M5: 0
A6: oats | B6: 0 | C6: 0 | D6: 0 | E6: 0 | F6: 0 | G6: 0 | H6: 0 | I6: 0 | J6: 0 | K6: 0 | L6: 0 | M6: 0
A7: Mancorn | B7: 0 | C7: 0 | D7: 0 | E7: 0 | F7: 0 | G7: 0 | H7: 0 | I7: 0 | J7: 0 | K7: 0 | L7: 0 | M7: 0
A8: Maslin | B8: 0 | C8: 0 | D8: 0 | E8: 0 | F8: 0 | G8: 0 | H8: 0 | I8: 0 | J8: 0 | K8: 0 | L8: 0 | M8: 0
A9: First-grade malt | B9: 0 | C9: 0 | D9: 0 | E9: 0 | F9: 0 | G9: 0 | H9: 0 | I9: 0 | J9: 0 | K9: 0 | L9: 0 | M9: 0
A10: Second-grade malt | B10: 0 | C10: 0 | D10: 0 | E10: 0 | F10: 0 | G10: 0 | H10: 0 | I10: 0 | J10: 0 | K10: 0 | L10: 0 | M10: 0
A11: Peas | B11: 0 | C11: 0 | D11: 0 | E11: 0 | F11: 0 | G11: 0 | H11: 0 | I11: 0 | J11: 0 | K11: 0 | L11: 0 | M11: 0
A12: Oatmeal | B12: 0 | C12: 0 | D12: 0 | E12: 0 | F12: 0 | G12: 0 | H12: 0 | I12: 0 | J12: 0 | K12: 0 | L12: 0 | M12: 0
A13: Vetches | B13: 0 | C13: 0 | D13: 0 | E13: 0 | F13: 0 | G13: 0 | H13: 0 | I13: 0 | J13: 0 | K13: 0 | L13: 0 | M13: 0
... A17: Curall | B17: 0 | C17: 0 | D17: 0 | E17: 0 | F17: 0 | G17: 0 | H17: 0 | I17: 0 | J17: 0 | K17: 0 | L17: 0 | M17: 0

Sheet Sale of Corn Prices
A1: Heading | B1: Sentence | C1: Total in Pounds | D1: Pounds | E1: Shillings | F1: Pence | G1: Corn | H1: Total Quarters Except 1 | I1: Total Bushels Except 1 | J1: Total Corn Cross-Check | K1: Total Corn Manorial Account | L1: Corn Quantity Error | M1: Quarters 0 | N1: Bushels 0 | O1: shilling a quarter 1 | P1: pence a quarter 1 | Q1: Quarters 1 | R1: Bushels 1 | S1: shilling a quarter 2 | T1: pence a quarter 2 | U1: Quarters 2 | V1: Bushels 2 | W1: shilling a quarter 3 | X1: pence a quarter 3 | Y1: shilling a quarter 4 | Z1: pence a quarter 4 | AA1: £ a quarter 1 | AB1: £ a quarter 2 | AC1: £ a quarter 3 | AD1: £ a quarter 4 | AE1: Quarters Sold | AF1: Weighted Average Price per Quarter | AG1: Non-Weighted Average Price per Quarter | AH1: Corn lowercase
