Workbook

Sheet Adderbury Overview
A1: ADDERBURY | B1: Total in £ | C1: Error | D1: Note
A2: CASH ACCOUNT
A3: RECEIPTS
A4: Arrears total
A5: Rents of assize total | B5: ='Adderbury Receipts'!F9
A6: Quittances total | B6: ='Adderbury Receipts'!F22
A7: Defaults of rent total | B7: ='Adderbury Receipts'!F27
A8: Defaults of rent through the pestilence total | B8: ='Adderbury Receipts'!F36
A9: Cotlands defaults total | B9: ='Adderbury Receipts'!F45
A10: Cotlands total | B10: ='Adderbury Receipts'!F54
A11: Total of quittances and defaults of rent total | B11: ='Adderbury Receipts'!F56
A12: Total of rents remaining clear total | B12: ='Adderbury Receipts'!F58
A13: Farms total | B13: ='Adderbury Receipts'!F70
A14: Annual recognizances total | B14: ='Adderbury Receipts'!F90
A15: Issues of the Manor total | B15: ='Adderbury Receipts'!F117
A16: Issues of the tenements in the lord's hands total | B16: ='Adderbury Receipts'!F126
A17: Sale of labour services total | B17: ='Adderbury Receipts'!F135
A18: Sale of corn total | B18: ='Adderbury Receipts'!F138
A19: Entry and marriage fines total | B19: ='Adderbury Receipts'!F166
A20: Pleas & perquisites total | B20: ='Adderbury Receipts'!F173
A21: Forfeited chattels total | B21: ='Adderbury Receipts'!F177
A22: Farm of the demesne land total | B22: ='Adderbury Receipts'!F181
A23: Total of all receipts (calculated here) | B23: ='Adderbury Receipts'!F185
A24: Total of all receipts (calculated here) incl arrears
A25: Total recorded in the accounts excl. arrears | B25: ='Adderbury Receipts'!F184 | C25: =B23-B25
A26: Total recorded in the accounts incl. arrears
A29: EXPENSES
A30: Cost of ploughs total
A31: Purchase of corn total
A32: Cost of carts and wagons total
A33: Cost of dairy total
A34: Purchase of stock total
A35: Sheepcote total
A36: Cost of buildings total | B36: ='Adderbury Expenses'!F26
A37: Threshing total
A38: Barley expenses
A39: Expenses of the harvest total
A40: Necessary expenses
A41: Wages of the bailiff | B41: ='Adderbury Expenses'!F30
A42: Steward's expenses total | B42: ='Adderbury Expenses'!F33
A43: Annual fees | B43: ='Adderbury Expenses'!F37
A44: Total of all expenses per account
A45: Total of all expenses (calculated here)
A46: Total fixed investment
A47: Total Demesne fixed investment
A49: Owed by the reeve | B49: =B23-B45
A50: From accounts | B50: ='Adderbury Expenses'!F41
A52: Allowances | B52: ='Adderbury Expenses'!F45
A53: Cash deliveries | B53: ='Adderbury Expenses'!F48
A54: Sum of the above | B54: =SUM(B52:B53)
A55: Total of all allowances and cash deliveries in accounts
A57: Net amount owed | B57: =B50-B54
A58: Net amount owed in accounts
A60: GRANGE ACCOUNT | B60: Total Production | D60: Value of total gross production in £ | E60: Value of total net production in £
A61: Grange | B61: qrs | C61: bus
A62: Wheat
A63: Rye
A64: Dredge
A65: Curall
A66: Barley
A67: Oats
A68: Beans
A69: Peas
A70: Vetches
A71: Total value of gross production (sum of the above) | B71: =SUM(D62:D70)
A72: Total value of net production | B72: =SUM(E62:E70)
A73: Value of sales
A75: MILL ACCOUNT | B75: Total Production | D75: Total in £ | F75: Not yet implemented
A76: Issues of the mill | B76: qrs | C76: bus
A77: Wheat
A78: Oatmeal
A79: 1st grade malt
A80: 2nd grade malt
A81: Maslin
A82: Total value of production (sum of the above)
A83: Value of sales
A85: STOCK ACCOUNT
A86: Livestock | B86: Begin stock | C86: End stock | D86: Stockbuilding | F86: Value of stock in £ | G86: Value of stockbuilding
A87: Cart-horses | B87: ='Adderbury Stock'!B5 | C87: ='Adderbury Stock'!K5 | D87: ='Adderbury Overview'!C87-'Adderbury Overview'!B87 | F87: ='Adderbury Stock'!P5 | G87: ='Adderbury Stock'!S5
A88: Mares | B88: ='Adderbury Stock'!B6 | C88: ='Adderbury Stock'!K6 | D88: ='Adderbury Overview'!C88-'Adderbury Overview'!B88 | F88: ='Adderbury Stock'!P6 | G88: ='Adderbury Stock'!S6
A89: Plough horses | B89: ='Adderbury Stock'!B7 | C89: ='Adderbury Stock'!K7 | D89: ='Adderbury Overview'!C89-'Adderbury Overview'!B89 | F89: ='Adderbury Stock'!P7 | G89: ='Adderbury Stock'!S7
A90: Colts (2 years) | B90: ='Adderbury Stock'!B8 | C90: ='Adderbury Stock'!K8 | D90: ='Adderbury Overview'!C90-'Adderbury Overview'!B90 | F90: ='Adderbury Stock'!P8 | G90: ='Adderbury Stock'!S8
A91: Colts (2 years) | B91: ='Adderbury Stock'!B9 | C91: ='Adderbury Stock'!K9 | D91: ='Adderbury Overview'!C91-'Adderbury Overview'!B91 | F91: ='Adderbury Stock'!P9 | G91: ='Adderbury Stock'!S9
A92: Colts (1 year) | B92: ='Adderbury Stock'!B10 | C92: ='Adderbury Stock'!K10 | D92: ='Adderbury Overview'!C92-'Adderbury Overview'!B92 | F92: ='Adderbury Stock'!P10 | G92: ='Adderbury Stock'!S10
A93: Foals | B93: ='Adderbury Stock'!B11 | C93: ='Adderbury Stock'!K11 | D93: ='Adderbury Overview'!C93-'Adderbury Overview'!B93 | F93: ='Adderbury Stock'!P11 | G93: ='Adderbury Stock'!S11
A94: Oxen | B94: ='Adderbury Stock'!B12 | C94: ='Adderbury Stock'!K12 | D94: ='Adderbury Overview'!C94-'Adderbury Overview'!B94 | F94: ='Adderbury Stock'!P12 | G94: ='Adderbury Stock'!S12
A95: Bulls | B95: ='Adderbury Stock'!B13 | C95: ='Adderbury Stock'!K13 | D95: ='Adderbury Overview'!C95-'Adderbury Overview'!B95 | F95: ='Adderbury Stock'!P13 | G95: ='Adderbury Stock'!S13
A96: Cows | B96: ='Adderbury Stock'!B14 | C96: ='Adderbury Stock'!K14 | D96: ='Adderbury Overview'!C96-'Adderbury Overview'!B96 | F96: ='Adderbury Stock'!P14 | G96: ='Adderbury Stock'!S14
A97: Steers | B97: ='Adderbury Stock'!B15 | C97: ='Adderbury Stock'!K15 | D97: ='Adderbury Overview'!C97-'Adderbury Overview'!B97 | F97: ='Adderbury Stock'!P15 | G97: ='Adderbury Stock'!S15
A98: Bullocks | B98: ='Adderbury Stock'!B16 | C98: ='Adderbury Stock'!K16 | D98: ='Adderbury Overview'!C98-'Adderbury Overview'!B98 | F98: ='Adderbury Stock'!P16 | G98: ='Adderbury Stock'!S16
... A112: Peacocks | B112: ='Adderbury Stock'!B30 | C112: ='Adderbury Stock'!K30 | D112: ='Adderbury Overview'!C112-'Adderbury Overview'!B112 | F112: ='Adderbury Stock'!P30 | G112: ='Adderbury Stock'!S30
A113: Total value of stock (sum of the above) | F113: =SUM(F87:F112) | G113: ='Adderbury Stock'!S31
A114: Total value of production | F114: =SUM('Adderbury Stock'!T5:T29)
A115: Value of sales | F115: =SUM('Adderbury Stock'!R5:R23)
A117: Wool | B117: Begin stock | C117: End stock | D117: Stockbuilding | F117: Value of stock in £
A118: Fleeces
A119: Coarse wool
A120: Lamb's wool
A121: Wool locks
A122: Wool sold at shearing
...

Sheet Ivinghoe Stock
A1: IVINGHOE STOCK ACCOUNT
C3: added | G3: subtracted
A4: Livestock | B4: Inherited stock | C4: added | D4: strays | E4: herbage | F4: churchscot | G4: of which in default | H4: sold | I4: in murrain | J4: accounted for elsewhere | K4: End-period stock | L4: cross-check | M4: stock building | N4: raw production | O4: Unit price (£) | P4: Value of stock (£) at given value | Q4: Value of stock (£) at sales prices | R4: Sales in (£) | S4: Value of stock building (£) | T4: Value of production (£) at sales prices | U4: Details
A5: Cart-horses | B5: 0 | C5: 0 | H5: 0 | I5: 0 | L5: =B5+C5-H5 | M5: =L5-B5 | N5: =C5 | O5: 0 | P5: =O5*K5 | R5: 0 | S5: =O5*M5 | T5: =O5*N5
A6: Mares | B6: 0 | C6: 0 | H6: 0 | I6: 0 | L6: =B6+C6-H6 | M6: =L6-B6 | N6: =C6 | O6: 0 | P6: =O6*K6 | R6: 0 | S6: =O6*M6 | T6: =O6*N6
A7: Plough horses | B7: 0 | C7: 0 | H7: 0 | I7: 0 | L7: =B7+C7-H7 | M7: =L7-B7 | N7: =C7 | O7: 0 | P7: =O7*K7 | R7: 0.75 | S7: =O7*M7 | T7: =O7*N7
A8: Colts (unspecified years) | B8: 0 | C8: 0 | H8: 0 | I8: 0 | L8: =B8+C8-H8 | M8: =L8-B8 | N8: =C8 | O8: 0 | P8: =O8*K8 | R8: 0 | S8: =O8*M8 | T8: =O8*N8
A9: Colts (2 years) | B9: 0 | C9: 0 | H9: 0 | I9: 0 | L9: =B9+C9-H9 | M9: =L9-B9 | N9: =C9 | O9: 0 | P9: =O9*K9 | R9: 0 | S9: =O9*M9 | T9: =O9*N9
A10: Colts (1 year) | B10: 0 | C10: 0 | H10: 0 | I10: 0 | L10: =B10+C10-H10 | M10: =L10-B10 | N10: =C10 | O10: 0 | P10: =O10*K10 | R10: 0 | S10: =O10*M10 | T10: =O10*N10
A11: Foals | B11: 0 | C11: 0 | H11: 0 | I11: 0 | L11: =B11+C11-H11 | M11: =L11-B11 | N11: =C11 | O11: 0 | P11: =O11*K11 | R11: 0 | S11: =O11*M11 | T11: =O11*N11
A12: Oxen | B12: 45 | C12: 8 | H12: 7 | I12: 5 | L12: =B12+C12-H12 | M12: =L12-B12 | N12: =C12 | O12: 0.37857143 | P12: =O12*K12 | R12: 2.65 | S12: =O12*M12 | T12: =O12*N12
A13: Bulls | B13: 2 | C13: 0 | H13: 0 | I13: 0 | L13: =B13+C13-H13 | M13: =L13-B13 | N13: =C13 | O13: 0 | P13: =O13*K13 | R13: 0 | S13: =O13*M13 | T13: =O13*N13
A14: Cows | B14: 30 | C14: 15 | H14: 10 | I14: 6 | L14: =B14+C14-H14 | M14: =L14-B14 | N14: =C14 | O14: 0.28 | P14: =O14*K14 | R14: 2.8 | S14: =O14*M14 | T14: =O14*N14
A15: Steers | B15: 5 | C15: 0 | H15: 0 | I15: 0 | L15: =B15+C15-H15 | M15: =L15-B15 | N15: =C15 | O15: 0 | P15: =O15*K15 | R15: 0 | S15: =O15*M15 | T15: =O15*N15
A16: Bullocks | B16: 5 | C16: 0 | H16: 0 | I16: 1 | L16: =B16+C16-H16 | M16: =L16-B16 | N16: =C16 | O16: 0 | P16: =O16*K16 | R16: 0 | S16: =O16*M16 | T16: =O16*N16
... A20: Rams | B20: 5 | C20: 0 | H20: 0 | I20: 1 | L20: =B20+C20-H20 | M20: =L20-B20 | N20: =C20 | O20: 0 | P20: =O20*K20 | R20: 0 | S20: =O20*M20 | T20: =O20*N20
A21: Ewes | B21: 208 | C21: 0 | H21: 20 | I21: 12 | L21: =B21+C21-H21 | M21: =L21-B21 | N21: =C21 | O21: 0.0665 | P21: =O21*K21 | Q21: 0 | R21: 1.33 | S21: =O21*M21 | T21: =O21*N21
A22: Hoggs | B22: 121 | C22: 0 | H22: 19 | I22: 8 | L22: =B22+C22-H22 | M22: =L22-B22 | N22: =C22 | O22: 0.041578947 | P22: =O22*K22 | R22: 0.79 | S22: =O22*M22 | T22: =O22*N22
A23: Lambs | B23: 110 | C23: 177 | H23: 20 | I23: 30 | L23: =B23+C23-H23 | M23: =L23-B23 | N23: =C23 | O23: 0.0265 | P23: =O23*K23 | R23: 0.53 | S23: =O23*M23 | T23: =O23*N23
A24: Boars | B24: 2 | C24: 0 | H24: 0 | I24: 1 | L24: =B24+C24-H24 | M24: =L24-B24 | N24: =C24 | O24: 0 | P24: =O24*K24 | R24: 0 | S24: =O24*M24 | T24: =O24*N24
A25: Sows | B25: 2 | C25: 0 | H25: 0 | I25: 4 | L25: =B25+C25-H25 | M25: =L25-B25 | N25: =C25 | O25: 0 | P25: =O25*K25 | R25: 0 | S25: =O25*M25 | T25: =O25*N25
A26: Pigs | B26: 112 | C26: 0 | H26: 8 | I26: 13 | L26: =B26+C26-H26 | M26: =L26-B26 | N26: =C26 | O26: 0.15 | P26: =O26*K26 | R26: 1.2 | S26: =O26*M26 | T26: =O26*N26
A27: Hoggets | B27: 40 | C27: 0 | H27: 0 | I27: 15 | L27: =B27+C27-H27 | M27: =L27-B27 | N27: =C27 | O27: 0 | P27: =O27*K27 | R27: 0 | S27: =O27*M27 | T27: =O27*N27
A28: Piglets | B28: 40 | C28: 45 | H28: 0 | I28: 1 | L28: =B28+C28-H28 | M28: =L28-B28 | N28: =C28 | O28: 0 | P28: =O28*K28 | R28: 0 | S28: =O28*M28 | T28: =O28*N28
A29: Swans | B29: 0 | C29: 0 | H29: 0 | I29: 0 | L29: =B29+C29-H29 | M29: =L29-B29 | N29: =C29 | O29: 0 | P29: =O29*K29 | R29: 0 | S29: =O29*M29 | T29: =O29*N29
A30: Peacocks | B30: 0 | C30: 0 | H30: 0 | I30: 0 | L30: =B30+C30-H30 | M30: =L30-B30 | N30: =C30 | O30: 0 | P30: =O30*K30 | R30: 0 | S30: =O30*M30 | T30: =O30*N30
A31: Total Value
A34: Wool | B34: 0 | C34: 0 | H34: 0 | I34: 0
A35: Coarse wool | B35: 0 | C35: 0 | H35: 0 | I35: 0
A36: Lamb's wool | B36: 0 | C36: 0 | H36: 0 | I36: 0
A37: Wool locks | B37: 0 | C37: 0 | H37: 0 | I37: 0
A38: Wool sold at shearing | B38: 0 | C38: 0 | H38: 0 | I38: 0
A39: Total wool | B39: 0 | C39: 0 | H39: 0 | I39: 0
B40: 0 | C40: 0 | H40: 0 | I40: 0
B41: 0 | C41: 0 | H41: 0 | I41: 0
A42: Hides | B42: 0 | C42: 0 | H42: 0 | I42: 0
A43: Ox hides | B43: 0 | C43: 0 | H43: 0 | I43: 0
A44: Mare | B44: 0 | C44: 0 | H44: 0 | I44: 0
A45: Steer | B45: 0 | C45: 0 | H45: 0 | I45: 0
A46: calves | B46: 8 | C46: 8 | H46: 0 | I46: 0
A47: pigs | B47: 112 | C47: 0 | H47: 8 | I47: 13
A48: Woolskins
A49: wethers
A50: rams
A51: ewes
A52: hoggs
A53: Woolskins total | B53: 0 | C53: 0 | H53: 38 | I53: 12
A54: Bareskins
A55: wethers
A56: rams
A57: ewes
A58: hoggs
A59: Bareskins total | B59: 0 | C59: 0 | H59: 0 | I59: 16
A60: Lambskins | B60: 5 | C60: 0 | H60: 0 | I60: 18
A61: Rotted skins | B61: 0 | C61: 0 | H61: 0 | I61: 0
A62: Shorn skins | B62: 0 | C62: 0 | H62: 0 | I62: 0
A63: Total
A66: Poultry stock
A67: Hens | L67: =B67+C67-H67 | M67: =L67-B67 | N67: =C67 | O67: 0 | Q67: =R67*K67 | R67: 0.1 | S67: =O67*M67 | T67: =O67*N67
A68: Geese | L68: =B68+C68-H68 | M68: =L68-B68 | N68: =C68 | O68: 0 | Q68: =R68*K68 | R68: 0.33 | S68: =O68*M68 | T68: =O68*N68
A69: Capons (from chickens) | B69: 0 | C69: 6 | H69: 6 | K69: 0 | L69: =B69+C69-H69 | M69: =L69-B69 | N69: =C69 | O69: 0 | Q69: =R69*K69 | R69: 0 | S69: =O69*M69 | T69: =O69*N69
A70: Cocks & hens | B70: 0 | F70: 28 | G70: 18 | H70: 10 | K70: 0 | L70: =B70+C70-H70 | M70: =L70-B70 | N70: =C70 | O70: 0 | Q70: =R70*K70 | R70: 0 | S70: =O70*M70 | T70: =O70*N70
A71: Total poultry stock
A72: Total poultry excluding churchscot
A74: Poultry production
A75: Eggs | B75: 0 | C75: 0 | H75: 0 | I75: 0 | S75: =O75*M75 | T75: =O75*N75
A76: Cocks & hens from churchscot of customary tenants | B76: 0 | C76: 0 | H76: 0 | I76: 0 | S76: =O76*M76 | T76: =O76*N76
A77: Sum of above | S77: =SUM(S75:S76) | T77: =SUM(T75:T76)
A78: Total
A81: Meat
A82: Beef | B82: 0 | C82: 0 | H82: 0 | I82: 0 | S82: =O82*M82 | T82: =O82*N82
A83: Mutton | B83: 0 | C83: 0 | H83: 0 | I83: 0 | S83: =O83*M83 | T83: =O83*N83
A84: Pork | B84: 0 | C84: 0 | H84: 0 | I84: 0 | S84: =O84*M84 | T84: =O84*N84
A85: Total
A87: Cheese
A88: Winter cheese | B88: 0 | C88: 0 | H88: 0 | I88: 0 | S88: =O88*M88 | T88: =O88*N88
A89: Summer cheese | B89: 0 | C89: 0 | H89: 0 | I89: 0 | S89: =O89*M89 | T89: =O89*N89
A90: Total
A92: Butter
A93: Butter | B93: 0 | C93: 0 | H93: 0 | I93: 0 | S93: =O93*M93 | T93: =O93*N93
A94: Total
A96: Total Dairy Sales
A99: Cider | B99: 0 | C99: 0 | H99: 0 | I99: 0
A102: Additional Information (not necessarily useful)
A103: Utensils
A104: ploughs
A105: carts
A106: cart-ropes
A107: corn baskets
A108: seed-sacks
A109: seed basket
A110: locks for the doors
A111: lead vessel
A112: brass pots
A113: pans
... A128: brass posnets

Sheet raw data
A1: Heading | B1: Sentence | C1: Total in Pounds | D1: Pounds | E1: Shillings | F1: Pence | G1: Corn | H1: Total Quarters Except 1 | I1: Total Bushels Except 1 | J1: Total Corn Cross-Check | K1: Total Corn Manorial Account | L1: Corn Quantity Error | M1: Quarters 1 | N1: Bushels 1 | O1: Quarters 2 | P1: Bushels 2 | Q1: Quarters 3 | R1: Bushels 3 | S1: Quarters 4 | T1: Bushels 4 | U1: Quarters 5 | V1: Bushels 5 | W1: Quarters 6 | X1: Bushels 6 | Y1: Quarters 7 | Z1: Bushels 7 | AA1: Quarters 8 | AB1: Bushels 8 | AC1: Quarters 9 | AD1: Bushels 9 | AE1: Quarters 10 | AF1: Bushels 10 | AG1: shilling a quarter 1 | AH1: pence a quarter 1 | AI1: shilling a quarter 2 | AJ1: pence a quarter 2 | AK1: shilling a quarter 3 | AL1: pence a quarter 3 | AM1: shilling a quarter 4 | AN1: pence a quarter 4 | AO1: shilling a bushel 1 | AP1: pence a bushel 1 | AQ1: shilling a bushel 2 | AR1: pence a bushel 2 | AS1: shilling a bushel 3 | AT1: pence a bushel 3 | AU1: shilling a bushel 4 | AV1: pence a bushel 4
A2: ivinghoe | B2: the account of the same for the sixth year of the translation of henry beaufort', lord bishop of winchester, and the eleventh year of the reign of king henry the fourth after the conquest. | C2: 0 | D2: 0 | E2: 0 | F2: 0 | H2: 0 | I2: 0 | J2: 0 | K2: 0 | L2: 0 | M2: 0 | N2: 0
A3: arrears | B3: richard baldewyn, reeve there, answers for £8 19 shilling 6pence of the arrears of john hoke from his last account of the preceding year. | C3: 8.97 | D3: 8 | E3: 19 | F3: 6 | H3: 0 | I3: 0 | J3: 0 | K3: 0 | L3: 0 | M3: 0 | N3: 0
A4: arrears | B4: total, £8 19 shilling 6pence. | C4: 8.97 | D4: 8 | E4: 19 | F4: 6 | H4: 0 | I4: 0 | J4: 0 | K4: 0 | L4: 0 | M4: 0 | N4: 0
A5: rents of assize | B5: and for £6 14 shilling 11.75pence for all rents of assize at christmas. | C5: 6.75 | D5: 6 | E5: 14 | F5: 11.75 | H5: 0 | I5: 0 | J5: 0 | K5: 0 | L5: 0 | M5: 0 | N5: 0
A6: rents of assize | B6: £6 15 shilling id. at the annunciation (25 march). | C6: 6.75 | D6: 6 | E6: 15 | F6: 0 | H6: 0 | I6: 0 | J6: 0 | K6: 0 | L6: 0 | M6: 0 | N6: 0
A7: rents of assize | B7: £6 14 shilling 113/id. at the nativity of st john the baptist (24 june). | C7: 6.7 | D7: 6 | E7: 14 | F7: 0 | H7: 0 | I7: 0 | J7: 0 | K7: 0 | L7: 0 | M7: 0 | N7: 0
A8: rents of assize | B8: £6 15 shilling 3.25pence at michaelmas (29 september). | C8: 6.76 | D8: 6 | E8: 15 | F8: 3.25 | H8: 0 | I8: 0 | J8: 0 | K8: 0 | L8: 0 | M8: 0 | N8: 0
A9: rents of assize | B9: 1pence for the increment of rent of simon edward' for 1 parcel of land of the lord's waste, 6 feet long and 3 feet wide, in the market of ivinghoe. | C9: 0 | D9: 0 | E9: 0 | F9: 1 | H9: 0 | I9: 0 | J9: 0 | K9: 0 | L9: 0 | M9: 0 | N9: 0
A10: rents of assize | B10: total, £27 3.75pence. | C10: 27.02 | D10: 27 | E10: 0 | F10: 3.75 | H10: 0 | I10: 0 | J10: 0 | K10: 0 | L10: 0 | M10: 0 | N10: 0
A11: quittances of rent | B11: in quittance of rent of 1 reeve for the year 5 shilling. | C11: 0.25 | D11: 0 | E11: 5 | F11: 0 | H11: 0 | I11: 0 | J11: 0 | K11: 0 | L11: 0 | M11: 0 | N11: 0
A12: quittances of rent | B12: 1 swineherd, nothing this year, because he has the lord's livery as made clear elsewhere. | C12: 0 | D12: 0 | E12: 0 | F12: 0 | H12: 0 | I12: 0 | J12: 0 | K12: 0 | L12: 0 | M12: 0 | N12: 0
A13: quittances of rent | B13: 5 customary ploughmen this year 15 shilling, or 3 shilling each. | C13: 0.75 | D13: 0 | E13: 15 | F13: 0 | H13: 0 | I13: 0 | J13: 0 | K13: 0 | L13: 0 | M13: 0 | N13: 0
... A68: issues of the manor | B68: total, £11 7 shilling 3.5pence. | C68: 11.36 | D68: 11 | E68: 7 | F68: 3.5 | H68: 0 | I68: 0 | J68: 0 | K68: 0 | L68: 0 | M68: 0 | N68: 0
A69: sale of corn and malt | B69: and for £8 18 shilling 6pence' from 22 quarters 2.5 bushels of wheat sold, at 8 shilling a quarters, as made clear elsewhere. | C69: 8.93 | D69: 8 | E69: 18 | F69: 6 | G69: wheat | H69: 22 | I69: 2.5 | J69: 22.31 | K69: 22.31 | L69: 0 | M69: 22 | N69: 2.5 | AG69: 8 | AH69: 0
A70: sale of corn and malt | B70: £4 12 shilling 4pence from 34 quarters 5 bushels of oats sold, at 2 shilling 8pence a quarters, as made clear elsewhere, of which 4 quarters 4 bushels sold to the lord's household. | C70: 4.62 | D70: 4 | E70: 12 | F70: 4 | G70: oats | H70: 4 | I70: 4 | J70: 4.5 | K70: 34.62 | L70: -30.12 | M70: 34 | N70: 5 | O70: 4 | P70: 4 | AG70: 2 | AH70: 8
A71: sale of corn and malt | B71: £24 7 shilling 4pence from 80 quarters 3 bushels 1 peck of malt sold, of which 71 quarters sold to the lord's household at esher, at 6. | C71: 24.37 | D71: 24 | E71: 7 | F71: 4 | G71: malt | H71: 71 | I71: 3 | J71: 71.38 | K71: 80.38 | L71: -9 | M71: 80 | N71: 3 | O71: 71 | P71: 0
A72: sale of corn and malt | B72: a quarters, and 9 quarters 3 bushels 1 peck, at 6 shilling 8pence a quarters. | C72: 0.33 | D72: 0 | E72: 6 | F72: 8 | H72: 9 | I72: 3 | J72: 9.38 | K72: 9.38 | L72: 0 | M72: 9 | N72: 3 | AG72: 6 | AH72: 8
A73: sale of corn and malt | B73: total, £37 18 shilling 2pence. | C73: 37.91 | D73: 37 | E73: 18 | F73: 2 | H73: 0 | I73: 0 | J73: 0 | K73: 0 | L73: 0 | M73: 0 | N73: 0
A74: sale of stock | B74: and for 15 shilling from 2 plough-horses sold as made clear elsewhere, at 10 shilling for 1, and 5 shilling for 1. | C74: 0.75 | D74: 0 | E74: 15 | F74: 0 | H74: 0 | I74: 0 | J74: 0 | K74: 0 | L74: 0 | M74: 0 | N74: 0
A75: sale of stock | B75: £2 13 shilling from 7 kebb oxen sold as made clear elsewhere, at 8 shilling each for 6, and 5s, for 1. | C75: 2.65 | D75: 2 | E75: 13 | F75: 0 | H75: 0 | I75: 0 | J75: 0 | K75: 0 | L75: 0 | M75: 0 | N75: 0
A76: sale of stock | B76: £2 16 shilling from 10 kebb cows sold before calving, at 6 shilling each for 6, and 5 shilling each for 4. | C76: 2.8 | D76: 2 | E76: 16 | F76: 0 | H76: 0 | I76: 0 | J76: 0 | K76: 0 | L76: 0 | M76: 0 | N76: 0
A77: sale of stock | B77: £2 5 shilling from 30 kebb wethers sold before shearing as made clear elsewhere, at 1 shilling 6pence each. | C77: 2.25 | D77: 2 | E77: 5 | F77: 0 | H77: 0 | I77: 0 | J77: 0 | K77: 0 | L77: 0 | M77: 0 | N77: 0
A78: sale of stock | B78: £2 from 30 kebb wethers sold after shearing as made clear elsewhere, 2 of them to the lord's household, at 1 shilling 4pence each. | C78: 2 | D78: 2 | E78: 0 | F78: 0 | H78: 0 | I78: 0 | J78: 0 | K78: 0 | L78: 0 | M78: 0 | N78: 0
A79: sale of stock | B79: £1 6 shilling 8pence from 20 kebb ewes sold as made clear elsewhere, at 1 shilling 4pence each. | C79: 1.33 | D79: 1 | E79: 6 | F79: 8 | H79: 0 | I79: 0 | J79: 0 | K79: 0 | L79: 0 | M79: 0 | N79: 0
A80: sale of stock | B80: 15 shilling 10pence from 19 hoggs, removed from stock and rejected for fear of murrain, sold after shearing as made clear elsewhere, at 10pence each. | C80: 0.79 | D80: 0 | E80: 15 | F80: 10 | H80: 0 | I80: 0 | J80: 0 | K80: 0 | L80: 0 | M80: 0 | N80: 0
A81: sale of stock | B81: 10 shilling from 20 lambs sold, removed from stock and rotted, at 6pence each. | C81: 0.53 | D81: 0 | E81: 10 | F81: 6 | H81: 0 | I81: 0 | J81: 0 | K81: 0 | L81: 0 | M81: 0 | N81: 0
A82: sale of stock | B82: £1 4 shilling from 8 pigs sold as made clear elsewhere, at 3 shilling each. | C82: 1.2 | D82: 1 | E82: 4 | F82: 0 | H82: 0 | I82: 0 | J82: 0 | K82: 0 | L82: 0 | M82: 0 | N82: 0
A83: sale of stock | B83: total, £14 5 shilling 6pence. | C83: 14.28 | D83: 14 | E83: 5 | F83: 6 | H83: 0 | I83: 0 | J83: 0 | K83: 0 | L83: 0 | M83: 0 | N83: 0
A84: sale of wood | B84: and for £6 1 shilling 6pence from wood from ivinghoe sold this year. | C84: 6.08 | D84: 6 | E84: 1 | F84: 6 | H84: 0 | I84: 0 | J84: 0 | K84: 0 | L84: 0 | M84: 0 | N84: 0
... A89: farm of the mill | B89: total, £1 4pence. | C89: 1.02 | D89: 1 | E89: 0 | F89: 4 | H89: 0 | I89: 0 | J89: 0 | K89: 0 | L89: 0 | M89: 0 | N89: 0
A90: sale of labour services | B90: and for 21 pence for the labour service of sowing wheat sold this year as made clear elsewhere. | C90: 0.09 | D90: 0 | E90: 0 | F90: 21 | G90: wheat | H90: 0 | I90: 0 | J90: 0 | K90: 0 | L90: 0 | M90: 0 | N90: 0
A91: sale of labour services | B91: £2 9 shilling 2pence for release of the labour services and service of robert palmere for 4 virgates of land at le fourhous, on top of the ancient rent of 17 shilling 6pence. | C91: 2.46 | D91: 2 | E91: 9 | F91: 2 | H91: 0 | I91: 0 | J91: 0 | K91: 0 | L91: 0 | M91: 0 | N91: 0
A92: sale of labour services | B92: total, £2 9 shilling 4.5pence. | C92: 2.47 | D92: 2 | E92: 9 | F92: 4.5 | H92: 0 | I92: 0 | J92: 0 | K92: 0 | L92: 0 | M92: 0 | N92: 0
A93: annual recognizance | B93: and for 2pence for the annual recognizance of robert taillour so that he may dwell within the liberty and come to the tourn of hockday. | C93: 0.01 | D93: 0 | E93: 0 | F93: 2 | H93: 0 | I93: 0 | J93: 0 | K93: 0 | L93: 0 | M93: 0 | N93: 0
A94: annual recognizance | B94: 2pence from hugh graston' for similar. | C94: 0.01 | D94: 0 | E94: 0 | F94: 2 | H94: 0 | I94: 0 | J94: 0 | K94: 0 | L94: 0 | M94: 0 | N94: 0
A95: annual recognizance | B95: 3pence from thomas hale for similar. | C95: 0.01 | D95: 0 | E95: 0 | F95: 3 | H95: 0 | I95: 0 | J95: 0 | K95: 0 | L95: 0 | M95: 0 | N95: 0
A96: annual recognizance | B96: 8pence from robert, son of john hook', the lord's villein, so that he may dwell outside the lord's liberty and come to the toum of hockday for the year and remain the lord's villein as before. | C96: 0.03 | D96: 0 | E96: 0 | F96: 8 | H96: 0 | I96: 0 | J96: 0 | K96: 0 | L96: 0 | M96: 0 | N96: 0
A97: annual recognizance | B97: 8pence from john, son of john sawell', the lord's villein, for the same. | C97: 0.03 | D97: 0 | E97: 0 | F97: 8 | H97: 0 | I97: 0 | J97: 0 | K97: 0 | L97: 0 | M97: 0 | N97: 0
A98: annual recognizance | B98: nothing of the 3pence from robert verdon' because he is dead as established by the court roll. | C98: 0.01 | D98: 0 | E98: 0 | F98: 3 | H98: 0 | I98: 0 | J98: 0 | K98: 0 | L98: 0 | M98: 0 | N98: 0
A99: entry and marriage fines | B99: and for 13 shilling 4pence from juliana, daughter of john clavle, to have 1 messuage and1 virgate of villein land in the tithing of aston bishop which belonged to the aforesaid john her father. | C99: 0.67 | D99: 0 | E99: 13 | F99: 4 | H99: 0 | I99: 0 | J99: 0 | K99: 0 | L99: 0 | M99: 0 | N99: 0
A100: entry and marriage fines | B100: 13 shilling 4pence from john stonhard' to have juliana, daughter of john claverle, with her land, that is, 1 messuage and 1 virgate of villein land in the tithing of aston bishop. | C100: 0.67 | D100: 0 | E100: 13 | F100: 4 | H100: 0 | I100: 0 | J100: 0 | K100: 0 | L100: 0 | M100: 0 | N100: 0
A101: entry and marriage fines | B101: 6 shilling 8pence from john, son of edward hastyng', to have 1 messuage and 1 virgate of villein land in ivinghoe which belonged to the aforesaid edward his father. | C101: 0.33 | D101: 0 | E101: 6 | F101: 8 | H101: 0 | I101: 0 | J101: 0 | K101: 0 | L101: 0 | M101: 0 | N101: 0
A102: entry and marriage fines | B102: 6 shilling 8pence from john lord' to have 1 cottage with a curtilage and .5 acre of assarted land in the tithing of nettleden which belonged to thomas lord his brother. | C102: 0.33 | D102: 0 | E102: 6 | F102: 8 | H102: 0 | I102: 0 | J102: 0 | K102: 0 | L102: 0 | M102: 0 | N102: 0
... A153: cost of carts | B153: total, £2 10 shilling 6pence. | C153: 2.52 | D153: 2 | E153: 10 | F153: 6 | H153: 0 | I153: 0 | J153: 0 | K153: 0 | L153: 0 | M153: 0 | N153: 0
A154: purchase of corn and stock | B154: in 17 quarters 1 bushels of mancorn bought £5 13 shilling 9pence, at 6 shilling 8pence a quarters. | C154: 5.69 | D154: 5 | E154: 13 | F154: 9 | G154: mancorn | H154: 17 | I154: 1 | J154: 17.12 | K154: 17.12 | L154: 0 | M154: 17 | N154: 1 | AG154: 6 | AH154: 8
A155: purchase of corn and stock | B155: 6 quarters of barley bought £1 16 shilling, at 6 shilling a quarters. | C155: 1.8 | D155: 1 | E155: 16 | F155: 0 | G155: barley | H155: 6 | I155: 0 | J155: 6 | K155: 6 | L155: 0 | M155: 6 | N155: 0 | AG155: 6 | AH155: 0
A156: purchase of corn and stock | B156: 8 quarters 4 bushels of pulses bought £1 14 shilling, at 4 shilling a quarters. | C156: 1.7 | D156: 1 | E156: 14 | F156: 0 | H156: 8 | I156: 4 | J156: 8.5 | K156: 8.5 | L156: 0 | M156: 8 | N156: 4 | AG156: 4 | AH156: 0
A157: purchase of corn and stock | B157: 1 horse bought £1 3 shilling 4pence. | C157: 1.17 | D157: 1 | E157: 3 | F157: 4 | H157: 0 | I157: 0 | J157: 0 | K157: 0 | L157: 0 | M157: 0 | N157: 0
A158: purchase of corn and stock | B158: 8 oxen bought £5 17 shilling, at 16 shilling each for 2, 15 shilling each for 3, and 13 shilling 4pence each for 3.. | C158: 5.85 | D158: 5 | E158: 17 | F158: 0 | H158: 0 | I158: 0 | J158: 0 | K158: 0 | L158: 0 | M158: 0 | N158: 0
A159: purchase of corn and stock | B159: 15 cows with calf bought £8 12 shilling, at 12 shilling each for 7, and 11 shilling each for 8.. | C159: 8.6 | D159: 8 | E159: 12 | F159: 0 | H159: 0 | I159: 0 | J159: 0 | K159: 0 | L159: 0 | M159: 0 | N159: 0
A160: purchase of corn and stock | B160: 8 calves bought from the farmer of the dairy 8 shilling. | C160: 0.4 | D160: 0 | E160: 8 | F160: 0 | H160: 0 | I160: 0 | J160: 0 | K160: 0 | L160: 0 | M160: 0 | N160: 0
A161: purchase of corn and stock | B161: 24 wethers bought before shearing as made clear elsewhere £2 16 shilling, at 2 shilling 4pence each. | C161: 2.8 | D161: 2 | E161: 16 | F161: 0 | H161: 0 | I161: 0 | J161: 0 | K161: 0 | L161: 0 | M161: 0 | N161: 0
A162: purchase of corn and stock | B162: total, £28 1pence. | C162: 28 | D162: 28 | E162: 0 | F162: 1 | H162: 0 | I162: 0 | J162: 0 | K162: 0 | L162: 0 | M162: 0 | N162: 0
A163: cost of buildings | B163: in 73 quarters 4 bushels of malt made 2 shilling 3pence, at 2pence a quarters. | C163: 0.11 | D163: 0 | E163: 2 | F163: 3 | G163: malt | H163: 73 | I163: 4 | J163: 73.5 | K163: 73.5 | L163: 0 | M163: 73 | N163: 4
A164: cost of buildings | B164: 10 yards of haircloth bought for the kiln 5 shilling, at 6pence a yard. | C164: 0.28 | D164: 0 | E164: 5 | F164: 6 | H164: 0 | I164: 0 | J164: 0 | K164: 0 | L164: 0 | M164: 0 | N164: 0
A165: cost of buildings | B165: mending and hooping the wooden vessels for malting 2 shilling. | C165: 0.1 | D165: 0 | E165: 2 | F165: 0 | G165: malt | H165: 0 | I165: 0 | J165: 0 | K165: 0 | L165: 0 | M165: 0 | N165: 0
A166: cost of buildings | B166: 1 vat containing 5 quarters bought for malting 10 shilling. | C166: 0.5 | D166: 0 | E166: 10 | F166: 0 | G166: malt | H166: 5 | I166: 0 | J166: 5 | K166: 5 | L166: 0 | M166: 5 | N166: 0
A167: cost of buildings | B167: 2 sacks of 6 bushels bought 2 shilling 8pence. | C167: 0.13 | D167: 0 | E167: 2 | F167: 8 | H167: 0 | I167: 6 | J167: 0.75 | K167: 0.75 | L167: 0 | M167: 0 | N167: 6
A168: cost of buildings | B168: 6 shovels bought, 4 of them fitted with iron, 1 shilling 8pence. | C168: 0.08 | D168: 0 | E168: 1 | F168: 8 | H168: 0 | I168: 0 | J168: 0 | K168: 0 | L168: 0 | M168: 0 | N168: 0
A169: cost of buildings | B169: hiring 1 carpenter to underpin, fit with ground-sills and studs and mend 10 bays of the wether-house 6 shilling 8pence. | C169: 0.33 | D169: 0 | E169: 6 | F169: 8 | H169: 0 | I169: 0 | J169: 0 | K169: 0 | L169: 0 | M169: 0 | N169: 0
A170: cost of buildings | B170: hiring 1 thatcher for 5 days to thatch the wether-house with straw 2 shilling 1pence, taking 5pence a day. | C170: 0.1 | D170: 0 | E170: 2 | F170: 1 | H170: 0 | I170: 0 | J170: 0 | K170: 0 | L170: 0 | M170: 0 | N170: 0
A171: cost of buildings | B171: hiring 2 mates for the same time 3 shilling 4pence, taking between them 8pence a day. | C171: 0.17 | D171: 0 | E171: 3 | F171: 4 | H171: 0 | I171: 0 | J171: 0 | K171: 0 | L171: 0 | M171: 0 | N171: 0
A172: cost of buildings | B172: hiring 1 carpenter to make the stalls of the byre and cowshed for 4 days 1 shilling 8pence, taking 5pence a day. | C172: 0.08 | D172: 0 | E172: 1 | F172: 8 | H172: 0 | I172: 0 | J172: 0 | K172: 0 | L172: 0 | M172: 0 | N172: 0
A173: cost of buildings | B173: 200 spike-nails for mending the kiln and various doors 1 shilling. | C173: 0.05 | D173: 0 | E173: 1 | F173: 0 | H173: 0 | I173: 0 | J173: 0 | K173: 0 | L173: 0 | M173: 0 | N173: 0
A174: cost of buildings | B174: hiring 1 carpenter to underpin, fit with ground-sills and studs and mend the defects of 1 bay of the small barn for 5 days 2 shilling ld , taking 5pence a day. | C174: 0.12 | D174: 0 | E174: 2 | F174: 5 | H174: 0 | I174: 0 | J174: 0 | K174: 0 | L174: 0 | M174: 0 | N174: 0
A175: cost of buildings | B175: hiring 1 mason to mend and pin the defects of the great barn and small barn for 6 days 2 shilling 6pence, taking 5pence a day. | C175: 0.12 | D175: 0 | E175: 2 | F175: 6 | H175: 0 | I175: 0 | J175: 0 | K175: 0 | L175: 0 | M175: 0 | N175: 0
A176: cost of buildings | B176: hiring 1 man to cover with laths and daub 1 bay of the small barn and mend the defects of the small barn and great barn for 6 days 2 shilling 6pence, taking 5pence a day. | C176: 0.12 | D176: 0 | E176: 2 | F176: 6 | H176: 0 | I176: 0 | J176: 0 | K176: 0 | L176: 0 | M176: 0 | N176: 0
A177: cost of buildings | B177: hiring 1 carpenter to make and mend the defects of the south porch of the great barn for 3 days 1 shilling 3pence, taking 5pence a day. | C177: 0.06 | D177: 0 | E177: 1 | F177: 3 | H177: 0 | I177: 0 | J177: 0 | K177: 0 | L177: 0 | M177: 0 | N177: 0
A178: cost of buildings | B178: hiring 1 tiler to tile and mend the defects of the great barn, small barn and granary for 8 days 3 shilling 4pence, taking 5pence a day. | C178: 0.17 | D178: 0 | E178: 3 | F178: 4 | H178: 0 | I178: 0 | J178: 0 | K178: 0 | L178: 0 | M178: 0 | N178: 0
... A180: cost of buildings | B180: 2,000 tiles bought for the same 11 shilling, at 5 shilling 6pence a 1,000.. | C180: 0.58 | D180: 0 | E180: 11 | F180: 6 | H180: 0 | I180: 0 | J180: 0 | K180: 0 | L180: 0 | M180: 0 | N180: 0
A181: cost of buildings | B181: 2 quarters of limestone bought 2 shilling 8pence, at 1 shilling 4pence a quarters. | C181: 0.13 | D181: 0 | E181: 2 | F181: 8 | H181: 2 | I181: 0 | J181: 2 | K181: 2 | L181: 0 | M181: 2 | N181: 0 | AG181: 1 | AH181: 4
A182: cost of buildings | B182: carrying the said tiles and 2 quarters of lime from chesham to ivinghoe on 3 occasions 1 shilling 6pence. | C182: 0.08 | D182: 0 | E182: 1 | F182: 6 | H182: 2 | I182: 0 | J182: 2 | K182: 2 | L182: 0 | M182: 2 | N182: 0
A183: cost of buildings | B183: 20 cart-loads of straw bought to support the oxen, cows, steers, bullocks and yearlings in winter 13 shilling 4pence. | C183: 0.67 | D183: 0 | E183: 13 | F183: 4 | H183: 0 | I183: 0 | J183: 0 | K183: 0 | L183: 0 | M183: 0 | N183: 0
A184: cost of buildings | B184: 2 cart-loads of hay 10 shilling. | C184: 0.5 | D184: 0 | E184: 10 | F184: 0 | H184: 0 | I184: 0 | J184: 0 | K184: 0 | L184: 0 | M184: 0 | N184: 0
A185: cost of buildings | B185: hiring 2 carpenters to fit with ground-sills, underpin, fit with studs and drive in piles (fug') for the small chamber annexed to the new chamber for 2 days 1 shilling 8pence, taking between them 10pence a day. | C185: 0.08 | D185: 0 | E185: 1 | F185: 8 | H185: 0 | I185: 0 | J185: 0 | K185: 0 | L185: 0 | M185: 0 | N185: 0
A186: cost of buildings | B186: hiring 1 man to pin, cover with laths and daub the said walls for 3 days 1 shilling 3pence, taking 5pence a day. | C186: 0.06 | D186: 0 | E186: 1 | F186: 3 | H186: 0 | I186: 0 | J186: 0 | K186: 0 | L186: 0 | M186: 0 | N186: 0
A187: cost of buildings | B187: hiring 1 tiler to tile and mend the defects of the small chamber annexed to the new chamber for 1 day 5pence. | C187: 0.02 | D187: 0 | E187: 0 | F187: 5 | H187: 0 | I187: 0 | J187: 0 | K187: 0 | L187: 0 | M187: 0 | N187: 0
A188: cost of buildings | B188: carrying 1 sack 37 cloves of coarse wool to wargrave 1 shilling 8pence. | C188: 0.08 | D188: 0 | E188: 1 | F188: 8 | H188: 0 | I188: 0 | J188: 0 | K188: 0 | L188: 0 | M188: 0 | N188: 0
A189: cost of buildings | B189: total, £5 9 shilling 7pence. | C189: 5.48 | D189: 5 | E189: 9 | F189: 7 | H189: 0 | I189: 0 | J189: 0 | K189: 0 | L189: 0 | M189: 0 | N189: 0
A190: new building of a hall and chamber | B190: in hiring 1 mason to build a wall of 7 perches for the hall and chamber, with doors and windows, of 18 feet in length and 10 feet high, £2 6 shilling 8pence,' taking 6 shilling 8pence a perch. | C190: 2.33 | D190: 2 | E190: 6 | F190: 8 | H190: 0 | I190: 0 | J190: 0 | K190: 0 | L190: 0 | M190: 0 | N190: 0
A191: new building of a hall and chamber | B191: 40 feet of egremond stone bought 5 shilling, at 1.5pence a foot. | C191: 0.26 | D191: 0 | E191: 5 | F191: 1.5 | H191: 0 | I191: 0 | J191: 0 | K191: 0 | L191: 0 | M191: 0 | N191: 0
A192: new building of a hall and chamber | B192: hiring 4 men to take down the tiles and old timber of the hall and chamber and to clear away the old walls of the aforesaid hall and chamber for 10 days 13 shilling 4pence, taking between them 1 shilling 4pence a day. | C192: 0.67 | D192: 0 | E192: 13 | F192: 4 | H192: 0 | I192: 0 | J192: 0 | K192: 0 | L192: 0 | M192: 0 | N192: 0
A193: new building of a hall and chamber | B193: hiring 2 men to dig stone, lime and earth for 10 days to build and fill the said walls 8 shilling 4pence, taking between them 10pence a day. | C193: 0.42 | D193: 0 | E193: 8 | F193: 4 | H193: 0 | I193: 0 | J193: 0 | K193: 0 | L193: 0 | M193: 0 | N193: 0
... A218: new building of a hall and chamber | B218: hiring 2 mates to assist them for the same 12 days 8 shilling, taking between them 8pence a day. | C218: 0.43 | D218: 0 | E218: 8 | F218: 8 | H218: 0 | I218: 0 | J218: 0 | K218: 0 | L218: 0 | M218: 0 | N218: 0
A219: new building of a hall and chamber | B219: 3 bushels of tile-pins bought 2 shilling 6pence, at 10pence a bushels. | C219: 0.12 | D219: 0 | E219: 2 | F219: 6 | H219: 0 | I219: 3 | J219: 0.38 | K219: 0.38 | L219: 0 | M219: 0 | N219: 3 | AO219: 0 | AP219: 10
A220: new building of a hall and chamber | B220: hiring 1 man to cover with laths and daub the walls of the chamber at the end of the hall and the ashlar of the hall for 12 days 5 shilling, taking 5pence a day. | C220: 0.27 | D220: 0 | E220: 5 | F220: 5 | H220: 0 | I220: 0 | J220: 0 | K220: 0 | L220: 0 | M220: 0 | N220: 0
A221: new building of a hall and chamber | B221: hiring his mate for the same 4 shilling, taking 4pence a day. | C221: 0.22 | D221: 0 | E221: 4 | F221: 4 | H221: 0 | I221: 0 | J221: 0 | K221: 0 | L221: 0 | M221: 0 | N221: 0
A222: new building of a hall and chamber | B222: total, £19 7 shilling 1pence. | C222: 19.35 | D222: 19 | E222: 7 | F222: 1 | H222: 0 | I222: 0 | J222: 0 | K222: 0 | L222: 0 | M222: 0 | N222: 0
A223: cost of the dairy and the fold | B223: in 4 bushels of salt bought for the pottage of the manorial servants 2 shilling 8pence. | C223: 0.13 | D223: 0 | E223: 2 | F223: 8 | H223: 0 | I223: 4 | J223: 0.5 | K223: 0.5 | L223: 0 | M223: 0 | N223: 4
A224: cost of the dairy and the fold | B224: 1 barrel of tar bought 4 shilling 8pence. | C224: 0.23 | D224: 0 | E224: 4 | F224: 8 | H224: 0 | I224: 0 | J224: 0 | K224: 0 | L224: 0 | M224: 0 | N224: 0
A225: cost of the dairy and the fold | B225: grease bought 5 shilling. | C225: 0.25 | D225: 0 | E225: 5 | F225: 0 | H225: 0 | I225: 0 | J225: 0 | K225: 0 | L225: 0 | M225: 0 | N225: 0
A226: cost of the dairy and the fold | B226: red ochre bought 1 shilling. | C226: 0.05 | D226: 0 | E226: 1 | F226: 0 | H226: 0 | I226: 0 | J226: 0 | K226: 0 | L226: 0 | M226: 0 | N226: 0
A227: cost of the dairy and the fold | B227: washing and shearing 586 wethers, rams, ewes and hoggs this year 12 shilling. | C227: 0.6 | D227: 0 | E227: 12 | F227: 0 | H227: 0 | I227: 0 | J227: 0 | K227: 0 | L227: 0 | M227: 0 | N227: 0
A228: cost of the dairy and the fold | B228: stipend of 1 dairymaid and 1 cowherd for the year 8 shilling. | C228: 0.4 | D228: 0 | E228: 8 | F228: 0 | H228: 0 | I228: 0 | J228: 0 | K228: 0 | L228: 0 | M228: 0 | N228: 0
A229: cost of the dairy and the fold | B229: stipend of 2 shepherds keeping the wethers, ewes and hoggs for the year £1 or 13 shilling 4pence for 1, and 6 shilling 8pence for the other. | C229: 1 | D229: 1 | E229: 0 | F229: 0 | H229: 0 | I229: 0 | J229: 0 | K229: 0 | L229: 0 | M229: 0 | N229: 0
A230: cost of the dairy and the fold | B230: stipend of 1 swineherd for the year 5 shilling 6pence. | C230: 0.28 | D230: 0 | E230: 5 | F230: 6 | H230: 0 | I230: 0 | J230: 0 | K230: 0 | L230: 0 | M230: 0 | N230: 0
A231: cost of the dairy and the fold | B231: stipend of 1 attendant helping the shepherd of wethers for 18 weeks in winter 1 shilling. | C231: 0.05 | D231: 0 | E231: 1 | F231: 0 | H231: 0 | I231: 0 | J231: 0 | K231: 0 | L231: 0 | M231: 0 | N231: 0
... A239: cost of meadows | B239: total, 4 shilling. | C239: 0.2 | D239: 0 | E239: 4 | F239: 0 | H239: 0 | I239: 0 | J239: 0 | K239: 0 | L239: 0 | M239: 0 | N239: 0
A240: threshing and winnowing | B240: in threshing 34 quarters of wheat and 70 quarters of berecorn by piece-work £1 6 shilling, at 3pence a quarters. | C240: 1.3 | D240: 1 | E240: 6 | F240: 0 | G240: wheat | H240: 70 | I240: 0 | J240: 70 | K240: 34 | L240: 36 | M240: 34 | N240: 0 | O240: 70 | P240: 0
...

Sheet Receipts
A1: IVINGHOE RECEIPTS
A2: Heading | B2: £ | C2: s | D2: d | F2: Total in £ | G2: Error | H2: Notes | I2: Own notes
A3: Arrears | B3: 8 | C3: 19 | D3: 6 | F3: 8.97 | H3: Richard Baldewyn, reeve there, answers for £8 19 shilling 6pence of the arrears of John Hoke from his last account of the preceding year.
A4: Arrears | B4: 8 | C4: 19 | D4: 6 | F4: 8.97 | H4: Total, £8 19 shilling 6pence.
A5: Arrears total | F5: 8.97 | G5: 0 | H5: Total
A7: Rents of assize | B7: 6 | C7: 14 | D7: 11.75 | F7: 6.75 | H7: And for £6 14 shilling 11.75pence for all rents of assize at Christmas.
A8: Rents of assize | B8: 6 | C8: 15 | D8: 0 | F8: 6.75 | H8: £6 15 shilling Id. at the Annunciation (25 March).
A9: Rents of assize | B9: 6 | C9: 14 | D9: 0 | F9: 6.7 | H9: £6 14 shilling 113/id. at the Nativity of St John the Baptist (24 June).
A10: Rents of assize | B10: 6 | C10: 15 | D10: 3.25 | F10: 6.76 | H10: £6 15 shilling 3.25pence at Michaelmas (29 September).
A11: Rents of assize | B11: 0 | C11: 0 | D11: 1 | F11: 0 | H11: 1pence for the increment of rent of Simon Edward' for 1 parcel of land of the lord's waste, 6 feet long and 3 feet wide, in the market of Ivinghoe.
A12: Rents of assize | B12: 27 | C12: 0 | D12: 3.75 | F12: 27.02 | H12: Total, £27 3.75pence.
A13: Rents of assize total | F13: 26.96 | G13: -0.06 | H13: Total
A15: Defaults of rent | B15: 0 | C15: 18 | D15: 0 | F15: 0.9 | H15: In default of the earl of Salisbury at Gaddesden, 18 shilling for the year, because Bishop Godfrey gave that land with the tenements to the said earl as made clear in the custumal of Ivinghoe.
A16: Defaults of rent | B16: 0 | C16: 18 | D16: 0 | F16: 0.9 | H16: Total, 18 shilling.
A17: Defaults of rent total | F17: 0.9 | G17: 0 | H17: Total
A19: Total of quittances and defaults of rent | B19: 5 | C19: 6 | D19: 11 | F19: 5.35 | H19: Total of quittances and defaults of rent, £5 6 shilling 11pence.
A20: Total of quittances and defaults of rent total | F20: 5.35 | G20: 0 | H20: Total
A22: Total of rents remaining clear | B22: 21 | C22: 13 | D22: 5.75 | F22: 21.67 | H22: Total of rents remaining clear, £21 13 shilling 5.75pence.
A23: Total of rents remaining clear total | F23: 21.67 | G23: 0 | H23: Total
A25: Issues of the manor | B25: 0 | C25: 6 | D25: 0 | F25: 0.3 | H25: And for 6 shilling 7.5d from the pannage of the pigs of the customary tenants at Martinmas.
A26: Issues of the manor | B26: 0 | C26: 0 | D26: 0 | F26: 0 | H26: nothing from the pannage of foreign pigs in the lord’s wood this year because there was no mast.
A27: Issues of the manor | B27: 0 | C27: 0 | D27: 0 | F27: 0 | H27: nothing from ploughing shared out (particat') this year for the reason made clear elsewhere.
A28: Issues of the manor | B28: 0 | C28: 4 | D28: 6 | F28: 0.23 | H28: 4 shilling 6pence from beasts agisted in the pasture and grove between Michaelmas and Martinmas.
A29: Issues of the manor | B29: 0 | C29: 0 | D29: 0 | F29: 0 | H29: nothing from the pasturage of cattle and sheep before theploughing at fallow-time nor from the agistment of cattle in the pasture and grove from Hockday until the Nativity of St John the Baptist because they are grazed with the lord's cattle this year.
A30: Issues of the manor | B30: 0 | C30: 0 | D30: 0 | F30: 0 | H30: nothing from the agistment of cattle there from then until Michaelmas this year.
A31: Issues of the manor | B31: 0 | C31: 2 | D31: 6 | F31: 0.12 | H31: 2 shilling from 4 oxen agisted with the lord's oxen from then until Michaelmas this year, giving 6pence a head.
A32: Issues of the manor | B32: 0 | C32: 2 | D32: 6 | F32: 0.12 | H32: 2 shilling from 4 cows agisted in the pasture and grove with the lord's cows from then until Michaelmas this year, giving 6pence a head.
A33: Issues of the manor | B33: 0 | C33: 0 | D33: 0 | F33: 0 | H33: nothing from the agistment of cows and calves in the barbican nor from cattle in the pasture of Carsewyk' nor from the agistment of lambs in the pasture this year because they are grazed with the lord's lambs and oxen.
A34: Issues of the manor | B34: 0 | C34: 0 | D34: 0 | F34: 0 | H34: nothing from the beadle's pasture this year because it is grazed with the lord's cattle.
A35: Issues of the manor | B35: 0 | C35: 0 | D35: 0 | F35: 0 | H35: nothing from nettles in the garden this year.
A36: Issues of the manor | B36: 0 | C36: 4 | D36: 0 | F36: 0.2 | H36: 4 shilling from hay sold to the lord's household.
... A54: Issues of the manor | B54: 11 | C54: 7 | D54: 3.5 | F54: 11.36 | H54: Total, £11 7 shilling 3.5pence.
A55: Issues of the manor total | F55: 10.98 | G55: -0.38 | H55: Total
A57: Sale of stock | B57: 0 | C57: 15 | D57: 0 | F57: 0.75 | H57: And for 15 shilling from 2 plough-horses sold as made clear elsewhere, at 10 shilling for 1, and 5 shilling for 1.
A58: Sale of stock | B58: 2 | C58: 13 | D58: 0 | F58: 2.65 | H58: £2 13 shilling from 7 kebb oxen sold as made clear elsewhere, at 8 shilling each for 6, and 5s, for 1.
A59: Sale of stock | B59: 2 | C59: 16 | D59: 0 | F59: 2.8 | H59: £2 16 shilling from 10 kebb cows sold before calving, at 6 shilling each for 6, and 5 shilling each for 4.
A60: Sale of stock | B60: 2 | C60: 5 | D60: 0 | F60: 2.25 | H60: £2 5 shilling from 30 kebb wethers sold before shearing as made clear elsewhere, at 1 shilling 6pence each.
A61: Sale of stock | B61: 2 | C61: 0 | D61: 0 | F61: 2 | H61: £2 from 30 kebb wethers sold after shearing as made clear elsewhere, 2 of them to the lord's household, at 1 shilling 4pence each.
A62: Sale of stock | B62: 1 | C62: 6 | D62: 8 | F62: 1.33 | H62: £1 6 shilling 8pence from 20 kebb ewes sold as made clear elsewhere, at 1 shilling 4pence each.
A63: Sale of stock | B63: 0 | C63: 15 | D63: 10 | F63: 0.79 | H63: 15 shilling 10pence from 19 hoggs, removed from stock and rejected for fear of murrain, sold after shearing as made clear elsewhere, at 10pence each.
A64: Sale of stock | B64: 0 | C64: 10 | D64: 6 | F64: 0.53 | H64: 10 shilling from 20 lambs sold, removed from stock and rotted, at 6pence each.
A65: Sale of stock | B65: 1 | C65: 4 | D65: 0 | F65: 1.2 | H65: £1 4 shilling from 8 pigs sold as made clear elsewhere, at 3 shilling each.
A66: Sale of stock | B66: 14 | C66: 5 | D66: 6 | F66: 14.28 | H66: Total, £14 5 shilling 6pence.
A67: Sale of stock total | F67: 14.3 | G67: 0.02 | H67: Total
A69: Farm of the mill | B69: 1 | C69: 0 | D69: 4 | F69: 1.02 | H69: And for £1 4pence from William Pleyer' for the farm of the mill, granted to the same from 18 April until Michaelmas, and not more here for the reason made clear elsewhere, and afterwards demised to the aforesaid William for the term of his life at £2 6 shilling 8pence a year, to be answered for in the following year.
A70: Farm of the mill | B70: 1 | C70: 0 | D70: 4 | F70: 1.02 | H70: Total, £1 4pence.
A71: Farm of the mill total | F71: 1.02 | G71: 0 | H71: Total
A73: Annual recognizance | B73: 0 | C73: 0 | D73: 2 | F73: 0.01 | H73: And for 2pence for the annual recognizance of Robert Taillour so that he may dwell within the liberty and come to the tourn of Hockday.
A74: Annual recognizance | B74: 0 | C74: 0 | D74: 2 | F74: 0.01 | H74: 2pence from Hugh Graston' for similar.
A75: Annual recognizance | B75: 0 | C75: 0 | D75: 3 | F75: 0.01 | H75: 3pence from Thomas Hale for similar.
A76: Annual recognizance | B76: 0 | C76: 0 | D76: 8 | F76: 0.03 | H76: 8pence from Robert, son of John Hook', the lord's villein, so that he may dwell outside the lord's liberty and come to the toum of Hockday for the year and remain the lord's villein as before.
A77: Annual recognizance | B77: 0 | C77: 0 | D77: 8 | F77: 0.03 | H77: 8pence from John, son of John Sawell', the lord's villein, for the same.
A78: Annual recognizance | B78: 0 | C78: 0 | D78: 3 | F78: 0.01 | H78: nothing of the 3pence from Robert Verdon' because he is dead as established by the court roll.
A79: Annual recognizance total | F79: 0.1 | G79: 0.09 | H79: Total
A81: Entry and marriage fines | B81: 0 | C81: 13 | D81: 4 | F81: 0.67 | H81: And for 13 shilling 4pence from Juliana, daughter of John Clavle, to have 1 messuage and1 virgate of villein land in the tithing of Aston Bishop which belonged to the aforesaid John her father.
A82: Entry and marriage fines | B82: 0 | C82: 13 | D82: 4 | F82: 0.67 | H82: 13 shilling 4pence from John Stonhard' to have Juliana, daughter of John Claverle, with her land, that is, 1 messuage and 1 virgate of villein land in the tithing of Aston Bishop.
A83: Entry and marriage fines | B83: 0 | C83: 6 | D83: 8 | F83: 0.33 | H83: 6 shilling 8pence from John, son of Edward Hastyng', to have 1 messuage and 1 virgate of villein land in Ivinghoe which belonged to the aforesaid Edward his father.
A84: Entry and marriage fines | B84: 0 | C84: 6 | D84: 8 | F84: 0.33 | H84: 6 shilling 8pence from John Lord' to have 1 cottage with a curtilage and .5 acre of assarted land in the tithing of Nettleden which belonged to Thomas Lord his brother.
A85: Entry and marriage fines | B85: 0 | C85: 10 | D85: 0 | F85: 0.5 | H85: 10 shilling from henry Venne to have Juliana, daughter of John Claverle, with her land, that is, 1 messuage and 1 virgate of villein land in the tithing of Aston Bishop.
A86: Entry and marriage fines | B86: 0 | C86: 10 | D86: 0 | F86: 0.5 | H86: 10 shilling from John Smyth' to have 1 cottage with a curtilage and 3.5 acres of assailed land in the tithing of Nettleden by surrender of Margery William.
A87: Entry and marriage fines | B87: 0 | C87: 6 | D87: 8 | F87: 0.33 | H87: 6 shilling 8pence from John Bacon to have 1 cottage with a curtilage and 3.5 acres of land held by labour service in the tithing of Ivinghoe by surrender of Simon Edward.
A88: Entry and marriage fines | B88: 0 | C88: 3 | D88: 4 | F88: 0.17 | H88: 3 shilling 4pence from William Hastyng' to have 1 cottage and 1 shop of purpresture in the tithing of Ivinghoe by surrender of William Sonnyng', which came into the lord's hands as his escheat because noone of the kin of the said William took steps to fine for the same although a proclamation was made according to the custom of the manor.
A89: Entry and marriage fines | B89: 0 | C89: 6 | D89: 8 | F89: 0.33 | H89: 6 shilling 8pence from Robert Hangueld' for marrying Lucy his daughter outside.
A90: Entry and marriage fines | B90: 0 | C90: 13 | D90: 4 | F90: 0.67 | H90: 13 shilling 4pence from Joan, daughter of Walter Palmere, to have 1 toft and 1 virgate of villein land in the tithing of Horton which belonged to John Palmer' her brother.
A91: Entry and marriage fines | B91: 0 | C91: 10 | D91: 0 | F91: 0.5 | H91: 10 shilling from Alexander Hood to have 1 messuage and 1 virgate of villein land in the tithing of Ivinghoe which belonged to Simon, son of William Hulot, and which came into the lord's hands as his escheat because noone of the kin of the said Simon took steps to fine for the same although a proclamation was made according to the custom of the manor.
A92: Entry and marriage fines | B92: 0 | C92: 18 | D92: 8 | F92: 0.93 | H92: 18 shilling 8pence from tithingpenny at the tours of Martinmas.
... A94: Entry and marriage fines | B94: 6 | C94: 17 | D94: 4 | F94: 6.87 | H94: Total, £6 17 shilling 4pence.
A95: Entry and marriage fines total | F95: 6.86 | G95: -0.01 | H95: Total
A97: Perquisites of court | B97: 0 | C97: 7 | D97: 4 | F97: 0.37 | H97: And for 7 shilling 4pence from the perquisites of the tourn of Martinmas (11 November).
A98: Perquisites of court | B98: 0 | C98: 14 | D98: 8 | F98: 0.73 | H98: 14 shilling 8pence from the perquisites of the tourn of Hockday (1 April).
A99: Perquisites of court | B99: 0 | C99: 9 | D99: 3 | F99: 0.46 | H99: 9 shilling 3pence from the perquisites of the courts held between the 2 tourns.
A100: Perquisites of court | B100: 0 | C100: 17 | D100: 6 | F100: 0.88 | H100: 17 shilling 6pence from the perquisites of the courts held after the tourn of Hockday.
A101: Perquisites of court total | B101: 2 | C101: 8 | D101: 9 | F101: 2.44 | G101: 1.56 | H101: Total, £2 8 shilling 9pence.
A102: Total of all receipts recorded in accounts (calculated here) | F102: =SUMIF(A1:A101,"* total",F1:F101)-SUMIF(A1:A101,"Arrears total",F1:F101)
A103: Total of all receipts (calculated here) incl arrears | F103: =F102+SUMIF(A1:A101,"Arrears total",F1:F101)

Sheet Stock
A1: Heading | B1: Sentence | C1: Quarters 1 | D1: Bushels 1 | E1: stock | F1: inherited stock | G1: added | H1: murrain | I1: sold
A2: Oats | B2: Total | C2: 0 | D2: 0
A3: Stock | B3: Horses: 8 remain. | C3: 0 | D3: 0 | F3: 8
A4: Stock | B4: 1 bought. | C4: 0 | D4: 0 | G4: 1
A5: Stock | B5: Total, 9. 2 in murrain. | C5: 0 | D5: 0 | H5: 2
A6: Stock | B6: Total, 2. 7 remain, of which 1 is for the horse-mill. | C6: 0 | D6: 0
A7: Stock | B7: Plough-horses: 1 from the heriot of Edward Hastyng'. | C7: 0 | D7: 0 | E7: Plough-horses
A8: Stock | B8: 1 from the heriot of Simon Edward'. | C8: 0 | D8: 0 | E8: Plough-horses
A9: Stock | B9: Total, 2. Sold within. | C9: 0 | D9: 0 | E9: Plough-horses
A10: Stock | B10: none remain. | C10: 0 | D10: 0 | E10: Plough-horses
A11: Stock | B11: Oxen: 45 remain. | C11: 0 | D11: 0 | E11: Oxen | F11: 45
A12: Stock | B12: 1 from the heriot of John Claverley. | C12: 0 | D12: 0 | E12: Oxen
A13: Stock | B13: 1 from the heriot of John Stoneherd'. | C13: 0 | D13: 0 | E13: Oxen
A14: Stock | B14: 8 bought. | C14: 0 | D14: 0 | E14: Oxen | G14: 8
A15: Stock | B15: 2 added from steers. | C15: 0 | D15: 0 | E15: Oxen
A16: Stock | B16: Total, 57. 5 in murrain. | C16: 0 | D16: 0 | E16: Oxen | H16: 5
A17: Stock | B17: 7 kebbs sold within. | C17: 0 | D17: 0 | E17: Oxen | I17: 7
A18: Stock | B18: Total, 12. 45 remain. | C18: 0 | D18: 0 | E18: Oxen
A19: Stock | B19: Bulls: 2 remain. | C19: 0 | D19: 0 | E19: Bulls | F19: 2
A20: Stock | B20: Total, 2. 2 remain. | C20: 0 | D20: 0 | E20: Bulls
A21: Stock | B21: Cows: 30 remain. | C21: 0 | D21: 0 | E21: Cows | F21: 30
A22: Stock | B22: 15 bought. | C22: 0 | D22: 0 | E22: Cows | G22: 15
A23: Stock | B23: nothing here of the 1 cow from the heriot of Thomas Lord because it is in the hands of John Brigford' and is unable to be seized because it is outside the liberty of the lord. | C23: 0 | D23: 0 | E23: Cows
A24: Stock | B24: 3 added from steers. | C24: 0 | D24: 0 | E24: Cows
A25: Stock | B25: Total, 48. 6 in murrain before calving. | C25: 0 | D25: 0 | E25: Cows | H25: 6
A26: Stock | B26: 10 kebbs with calf sold within. | C26: 0 | D26: 0 | E26: Cows | I26: 10
A27: Stock | B27: Total, 16. 221 remain. | C27: 0 | D27: 0 | E27: Cows
A28: Stock | B28: Steers: 5 remain from the bullocks. | C28: 0 | D28: 0 | E28: Steers | F28: 5
A29: Stock | B29: Total, 5. 2 added above to oxen and 3 to cows. | C29: 0 | D29: 0 | E29: Steers
A30: Stock | B30: Total as before. | C30: 0 | D30: 0 | E30: Steers
A31: Stock | B31: None remain. | C31: 0 | D31: 0 | E31: Steers
A32: Stock | B32: Bullocks: 5 remain from the yearlings. | C32: 0 | D32: 0 | E32: Bullocks | F32: 5
A33: Stock | B33: Total, 5. 1 in murrain. | C33: 0 | D33: 0 | E33: Bullocks | H33: 1
A34: Stock | B34: 4 remain. | C34: 0 | D34: 0 | E34: Bullocks
A35: Stock | B35: Yearlings: 8 remain from the calves. | C35: 0 | D35: 0 | E35: Yearlings | F35: 8
A36: Stock | B36: Total, 8. 1 in murrain. | C36: 0 | D36: 0 | E36: Yearlings | H36: 1
A37: Stock | B37: 7 remain. | C37: 0 | D37: 0 | E37: Yearlings
A38: Stock | B38: Calves: 8 bought from the farmer of the dairy. | C38: 0 | D38: 0 | E38: Calves | G38: 8
A39: Stock | B39: Total, 8. 8 remain. | C39: 0 | D39: 0 | E39: Calves | F39: 8
A40: Stock | B40: Wethers: 318 remain. | C40: 0 | D40: 0 | E40: Wethers | F40: 318
A41: Stock | B41: 43 added from hoggs. | C41: 0 | D41: 0 | E41: Wethers
A42: Stock | B42: 1 from the heriot of John Palmere before shearing. | C42: 0 | D42: 0 | E42: Wethers
A43: Stock | B43: 24 bought before shearing. | C43: 0 | D43: 0 | E43: Wethers | G43: 24
A44: Stock | B44: 1 from the heriot of Margery William. | C44: 0 | D44: 0 | E44: Wethers
A45: Stock | B45: Total, 387. 21 in murrain before shearing, 9 after shearing. | C45: 0 | D45: 0 | E45: Wethers | H45: 21
A46: Stock | B46: 2 sold within to the lord's household after shearing. | C46: 0 | D46: 0 | E46: Wethers | I46: 2
A47: Stock | B47: 60 kebbs sold for fear of murrain, 30 of them before shearing. | C47: 0 | D47: 0 | E47: Wethers | I47: 60
A48: Stock | B48: Total, 92. 295 remain. | C48: 0 | D48: 0 | E48: Wethers
A49: Stock | B49: Rams: 5 remain. | C49: 0 | D49: 0 | E49: Rams | F49: 5
A50: Stock | B50: 1 added from hoggs. | C50: 0 | D50: 0 | E50: Rams
A51: Stock | B51: Total, 6. 1 in murrain before shearing. | C51: 0 | D51: 0 | E51: Rams | H51: 1
A52: Stock | B52: 5 remain. | C52: 0 | D52: 0 | E52: Rams
A53: Stock | B53: Ewes: 208 remain. | C53: 0 | D53: 0 | E53: Ewes | F53: 208
A54: Stock | B54: 46 added from hoggs. | C54: 0 | D54: 0 | E54: Ewes
A55: Stock | B55: Total, 254. 12 in murrain before lambing and shearing, 16 after shearing. | C55: 0 | D55: 0 | E55: Ewes | H55: 12
A56: Stock | B56: 20 kebbs sold within after lambing and before shearing. | C56: 0 | D56: 0 | E56: Ewes | I56: 20
A57: Stock | B57: Total, 48. 206 remain. | C57: 0 | D57: 0 | E57: Ewes
A58: Stock | B58: Hoggs: 121 remain from the lambs. | C58: 0 | D58: 0 | E58: Hoggs | F58: 121
A59: Stock | B59: Total, 121. 8 in murrain before shearing and 4 after shearing. | C59: 0 | D59: 0 | E59: Hoggs | H59: 8
A60: Stock | B60: 43 added above to wethers, 1 to rams and 46 to ewes. | C60: 0 | D60: 0 | E60: Hoggs
A61: Stock | B61: 19 sold within after shearing. | C61: 0 | D61: 0 | E61: Hoggs | I61: 19
A62: Stock | B62: Total as before. | C62: 0 | D62: 0 | E62: Hoggs
A63: Stock | B63: None remain. | C63: 0 | D63: 0 | E63: Hoggs
A64: Stock | B64: Lambs: 177 from the offspring of as many ewes and not more because 12 died before lambing and 19 were sterile. 18 in murrain before weaning. | C64: 0 | D64: 0 | E64: Lambs | G64: 177 | H64: 18
A65: Stock | B65: 16 given in tithe. | C65: 0 | D65: 0 | E65: Lambs
A66: Stock | B66: 1 in agreement with the shepherd. | C66: 0 | D66: 0 | E66: Lambs
A67: Stock | B67: 12 in murrain after weaning. | C67: 0 | D67: 0 | E67: Lambs | H67: 12
A68: Stock | B68: 20 removed from stock and sold within. | C68: 0 | D68: 0 | E68: Lambs | I68: 20
A69: Stock | B69: Total, 67. 110 remain. | C69: 0 | D69: 0 | E69: Lambs | F69: 110
A70: Stock | B70: Boars: 2 remain. | C70: 0 | D70: 0 | E70: Boars | F70: 2
A71: Stock | B71: Total, 2. 1 in murrain. | C71: 0 | D71: 0 | E71: Boars | H71: 1
A72: Stock | B72: 1 remains. | C72: 0 | D72: 0 | E72: Boars
A73: Stock | B73: Sows: 2 remain. | C73: 0 | D73: 0 | E73: Sows | F73: 2
A74: Stock | B74: 4 additions. | C74: 0 | D74: 0 | E74: Sows
A75: Stock | B75: Total, 7. 4 in murrain. | C75: 0 | D75: 0 | E75: Sows | H75: 4
A76: Stock | B76: Total, 4. 3 remain. | C76: 0 | D76: 0 | E76: Sows
A77: Stock | B77: Pigs: 112 remain. | C77: 0 | D77: 0 | E77: Pigs | F77: 112
A78: Stock | B78: 21 added from hoggets. | C78: 0 | D78: 0 | E78: Pigs
A79: Stock | B79: Total, 42. 13 in murrain. | C79: 0 | D79: 0 | E79: Pigs | H79: 13
A80: Stock | B80: 8 sold within. | C80: 0 | D80: 0 | E80: Pigs | I80: 8
A81: Stock | B81: Total, 21. 21 remain. | C81: 0 | D81: 0 | E81: Pigs
A82: Stock | B82: Hoggets: 40 remain from the piglets. | C82: 0 | D82: 0 | E82: Hoggets | F82: 40
A83: Stock | B83: Total, 40. 15 in murrain. | C83: 0 | D83: 0 | E83: Hoggets | H83: 15
A84: Stock | B84: 4 added above to sows and 21 to pigs. | C84: 0 | D84: 0 | E84: Hoggets
A85: Stock | B85: Total as before. | C85: 0 | D85: 0 | E85: Hoggets
A86: Stock | B86: None remain. | C86: 0 | D86: 0 | E86: Hoggets
A87: Stock | B87: Piglets: 45 from the offspring of the said 3 sows. | C87: 0 | D87: 0 | E87: Piglets | G87: 45
A88: Stock | B88: Total, 45. 4 in tithe. | C88: 0 | D88: 0 | E88: Piglets
A89: Stock | B89: 1 in agreement with the swineherd. | C89: 0 | D89: 0 | E89: Piglets
A90: Stock | B90: Total, 5. 40 remain. | C90: 0 | D90: 0 | E90: Piglets | F90: 40
A91: Stock | B91: Hides: 2 from horses, 5 from oxen, 6 from cows, 1 from a bullock and 1 from a yearling in murrain as made clear above. | C91: 0 | D91: 0 | E91: Piglets | H91: 1
A92: Stock | B92: Total, 15. Sold within. | C92: 0 | D92: 0 | E92: Piglets
A93: Stock | B93: none remain. | C93: 0 | D93: 0 | E93: Piglets
A94: Stock | B94: Coarse wool: 293 fleeces from wethers, 4 from rams, 176 from ewes and 113 from hoggs produced at the shearing this year. | C94: 0 | D94: 0 | E94: Coarse wool
A95: Stock | B95: Total, 586. 56 in tithe. | C95: 0 | D95: 0 | E95: Coarse wool
A96: Stock | B96: 1 in agreement with the shepherd of wethers. | C96: 0 | D96: 0 | E96: Coarse wool
A97: Stock | B97: 1 in agreement with the shepherd of ewes. | C97: 0 | D97: 0 | E97: Coarse wool
A98: Stock | B98: 527 delivered to Wargrave, weighing 1 sack 37 cloves. | C98: 0 | D98: 0 | E98: Coarse wool
A99: Stock | B99: Total as before. | C99: 0 | D99: 0 | E99: Coarse wool
A100: Stock | B100: None remains. | C100: 0 | D100: 0 | E100: Coarse wool
...

Sheet Overview

Sheet Issues of the Mills

Sheet Prices

Sheet Labour Rents

Sheet not needed

Sheet Issues of the Grange raw
A1: Heading | B1: Sentence | C1: Quarters 1_x | D1: Bushels 1_x | E1: Sown Quarters | F1: Sown Bushels | G1: Sown Total Quarters | H1: Bought in Quarters | I1: Bought in Bushels | J1: Bought in Total Quarters | K1: Tithe Quarters | L1: Tithe Bushels | M1: Tithe Total Quarters | N1: Manorial servants & livestock Quarters | O1: Manorial servants & livestock Bushels | P1: Manorial servants & livestock Total Quarters | Q1: Sold Quarters | R1: Sold Bushels | S1: Sold Total Quarters | T1: Account Quarters | U1: Account Bushels | V1: Account Total Quarters | W1: bought only | X1: Total Quarters Except 1 | Y1: Total Bushels Except 1 | Z1: Total Corn Cross-Check | AA1: Total Corn Manorial Account | AB1: Corn Quantity Error | AC1: Quarters 1_y | AD1: Bushels 1_y | AE1: Quarters 2 | AF1: Bushels 2 | AG1: Quarters 3 | AH1: Bushels 3 | AI1: Quarters 4 | AJ1: Bushels 4 | AK1: Quarters 5 | AL1: Bushels 5 | AM1: Quarters 6 | AN1: Bushels 6 | AO1: Quarters 7 | AP1: Bushels 7 | AQ1: Quarters 8 | AR1: Bushels 8 | AS1: Quarters 9 | AT1: Bushels 9 | AU1: Quarters 10 | AV1: Bushels 10 | AW1: Total Bought Quarters
A2: and he owes | B2: total | C2: 0 | D2: 0 | E2: 0 | F2: 0 | G2: 0 | H2: 0 | I2: 0 | J2: 0 | K2: 0 | L2: 0 | M2: 0 | N2: 0 | O2: 0 | P2: 0 | Q2: 0 | R2: 0 | S2: 0 | T2: 0 | U2: 0 | V2: 0 | W2: 0 | AW2: 0
A3: wheat | B3: richard baldewyn, reeve there, answers for 34 quarters of wheat from the whole issue of the grange, threshed by piece-work. | C3: 0 | D3: 0 | E3: 0 | F3: 0 | G3: 0 | H3: 0 | I3: 0 | J3: 0 | K3: 0 | L3: 0 | M3: 0 | N3: 0 | O3: 0 | P3: 0 | Q3: 0 | R3: 0 | S3: 0 | T3: 34 | U3: 0 | V3: 34 | W3: 0 | X3: 34 | Y3: 0 | Z3: 34 | AA3: 34 | AB3: 0 | AC3: 34 | AD3: 0 | AW3: 0
A4: wheat | B4: 13 quarters surcharged so that he answers for a 4-fold yield.. | C4: 0 | D4: 0 | E4: 0 | F4: 0 | G4: 0 | H4: 0 | I4: 0 | J4: 0 | K4: 0 | L4: 0 | M4: 0 | N4: 0 | O4: 0 | P4: 0 | Q4: 0 | R4: 0 | S4: 0 | T4: 0 | U4: 0 | V4: 0 | W4: 0 | X4: 13 | Y4: 0 | Z4: 13 | AA4: 13 | AB4: 0 | AC4: 13 | AD4: 0 | AW4: 0
A5: wheat | B5: total, 47 quarters. | C5: 0 | D5: 0 | E5: 0 | F5: 0 | G5: 0 | H5: 0 | I5: 0 | J5: 0 | K5: 0 | L5: 0 | M5: 0 | N5: 0 | O5: 0 | P5: 0 | Q5: 0 | R5: 0 | S5: 0 | T5: 0 | U5: 0 | V5: 0 | W5: 0 | X5: 47 | Y5: 0 | Z5: 47 | AA5: 47 | AB5: 0 | AC5: 47 | AD5: 0 | AW5: 0
A6: wheat | B6: sown over 36.5 acres of land by the perch which lie above le middelfeld', 10 quarters 2 bushels. | C6: 0 | D6: 0 | E6: 10 | F6: 2 | G6: 10.25 | H6: 0 | I6: 0 | J6: 0 | K6: 0 | L6: 0 | M6: 0 | N6: 0 | O6: 0 | P6: 0 | Q6: 0 | R6: 0 | S6: 0 | T6: 0 | U6: 0 | V6: 0 | W6: 0 | X6: 10 | Y6: 2 | Z6: 10.25 | AA6: 10.25 | AB6: 0 | AC6: 10 | AD6: 2 | AW6: 0
A7: wheat | B7: that is, 2 bushels 1 peck an acre, less .5 peck in all. | C7: 0 | D7: 0 | E7: 0 | F7: 0 | G7: 0 | H7: 0 | I7: 0 | J7: 0 | K7: 0 | L7: 0 | M7: 0 | N7: 0 | O7: 0 | P7: 0 | Q7: 0 | R7: 0 | S7: 0 | T7: 0 | U7: 0 | V7: 0 | W7: 0 | X7: 0 | Y7: 2 | Z7: 0.25 | AA7: 0.25 | AB7: 0 | AC7: 0 | AD7: 2 | AW7: 0
A8: wheat | B8: provision of the steward holding the tourns of martinmas and hockday, by 2 sealed bills, 3.5 bushels. | C8: 0 | D8: 0 | E8: 0 | F8: 0 | G8: 0 | H8: 0 | I8: 0 | J8: 0 | K8: 0 | L8: 0 | M8: 0 | N8: 0 | O8: 0 | P8: 0 | Q8: 0 | R8: 0 | S8: 0 | T8: 0 | U8: 0 | V8: 0 | W8: 0 | X8: 0 | Y8: 3.5 | Z8: 0.44 | AA8: 0.44 | AB8: 0 | AC8: 0 | AD8: 3.5 | AW8: 0
A9: wheat | B9: customary payment to the customary tenants mowing the lord's meadow, 1 qr. | C9: 0 | D9: 0 | E9: 0 | F9: 0 | G9: 0 | H9: 0 | I9: 0 | J9: 0 | K9: 0 | L9: 0 | M9: 0 | N9: 0 | O9: 0 | P9: 0 | Q9: 0 | R9: 0 | S9: 0 | T9: 0 | U9: 0 | V9: 0 | W9: 0 | AW9: 0
A10: wheat | B10: sold within, 22 quarters 2.5 bushels. | C10: 0 | D10: 0 | E10: 0 | F10: 0 | G10: 0 | H10: 0 | I10: 0 | J10: 0 | K10: 0 | L10: 0 | M10: 0 | N10: 0 | O10: 0 | P10: 0 | Q10: 22 | R10: 2.5 | S10: 22.31 | T10: 0 | U10: 0 | V10: 0 | W10: 0 | X10: 22 | Y10: 2.5 | Z10: 22.31 | AA10: 22.31 | AB10: 0 | AC10: 22 | AD10: 2.5 | AW10: 0
A11: wheat | B11: sold at the audit, 13 quarters for £4 6 shilling 8pence. | C11: 0 | D11: 0 | E11: 0 | F11: 0 | G11: 0 | H11: 0 | I11: 0 | J11: 0 | K11: 0 | L11: 0 | M11: 0 | N11: 0 | O11: 0 | P11: 0 | Q11: 13 | R11: 0 | S11: 13 | T11: 0 | U11: 0 | V11: 0 | W11: 0 | X11: 13 | Y11: 0 | Z11: 13 | AA11: 13 | AB11: 0 | AC11: 13 | AD11: 0 | AW11: 0
A12: wheat | B12: total as before. | C12: 0 | D12: 0 | E12: 0 | F12: 0 | G12: 0 | H12: 0 | I12: 0 | J12: 0 | K12: 0 | L12: 0 | M12: 0 | N12: 0 | O12: 0 | P12: 0 | Q12: 0 | R12: 0 | S12: 0 | T12: 0 | U12: 0 | V12: 0 | W12: 0 | X12: 0 | Y12: 0 | Z12: 0 | AA12: 0 | AB12: 0 | AC12: 0 | AD12: 0 | AW12: 0
A13: wheat | B13: it balances. | C13: 0 | D13: 0 | E13: 0 | F13: 0 | G13: 0 | H13: 0 | I13: 0 | J13: 0 | K13: 0 | L13: 0 | M13: 0 | N13: 0 | O13: 0 | P13: 0 | Q13: 0 | R13: 0 | S13: 0 | T13: 0 | U13: 0 | V13: 0 | W13: 0 | X13: 0 | Y13: 0 | Z13: 0 | AA13: 0 | AB13: 0 | AC13: 0 | AD13: 0 | AW13: 0
A14: wheat | B14: total | C14: 0 | D14: 0 | E14: 0 | F14: 0 | G14: 0 | H14: 0 | I14: 0 | J14: 0 | K14: 0 | L14: 0 | M14: 0 | N14: 0 | O14: 0 | P14: 0 | Q14: 0 | R14: 0 | S14: 0 | T14: 0 | U14: 0 | V14: 0 | W14: 0 | AW14: 0
A15: barley | B15: and for 68 quarters 2 bushels of barley from the whole issue of the grange, threshed by piece¬work. | C15: 0 | D15: 0 | E15: 0 | F15: 0 | G15: 0 | H15: 0 | I15: 0 | J15: 0 | K15: 0 | L15: 0 | M15: 0 | N15: 0 | O15: 0 | P15: 0 | Q15: 0 | R15: 0 | S15: 0 | T15: 68 | U15: 2 | V15: 68.25 | W15: 0 | X15: 68 | Y15: 2 | Z15: 68.25 | AA15: 68.25 | AB15: 0 | AC15: 68 | AD15: 2 | AW15: 0
A16: barley | B16: 6 quarters bought in the market for sowing. | C16: 0 | D16: 0 | E16: 0 | F16: 0 | G16: 0 | H16: 6 | I16: 0 | J16: 6 | K16: 0 | L16: 0 | M16: 0 | N16: 0 | O16: 0 | P16: 0 | Q16: 0 | R16: 0 | S16: 0 | T16: 0 | U16: 0 | V16: 0 | W16: 0 | X16: 6 | Y16: 0 | Z16: 6 | AA16: 6 | AB16: 0 | AC16: 6 | AD16: 0 | AW16: 0
A17: barley | B17: 12 quarters 6 bushels surcharged so that he answers for a 3-fold yield.. | C17: 0 | D17: 0 | E17: 0 | F17: 0 | G17: 0 | H17: 0 | I17: 0 | J17: 0 | K17: 0 | L17: 0 | M17: 0 | N17: 0 | O17: 0 | P17: 0 | Q17: 0 | R17: 0 | S17: 0 | T17: 0 | U17: 0 | V17: 0 | W17: 0 | X17: 12 | Y17: 6 | Z17: 12.75 | AA17: 12.75 | AB17: 0 | AC17: 12 | AD17: 6 | AW17: 0
A18: barley | B18: total, 87 quarters. | C18: 0 | D18: 0 | E18: 0 | F18: 0 | G18: 0 | H18: 0 | I18: 0 | J18: 0 | K18: 0 | L18: 0 | M18: 0 | N18: 0 | O18: 0 | P18: 0 | Q18: 0 | R18: 0 | S18: 0 | T18: 0 | U18: 0 | V18: 0 | W18: 0 | X18: 87 | Y18: 0 | Z18: 87 | AA18: 87 | AB18: 0 | AC18: 87 | AD18: 0 | AW18: 0
A19: barley | B19: sown over 40 acres of land by the perch which lie in le middelfeld', 20 quarters. | C19: 0 | D19: 0 | E19: 20 | F19: 0 | G19: 20 | H19: 0 | I19: 0 | J19: 0 | K19: 0 | L19: 0 | M19: 0 | N19: 0 | O19: 0 | P19: 0 | Q19: 0 | R19: 0 | S19: 0 | T19: 0 | U19: 0 | V19: 0 | W19: 0 | X19: 20 | Y19: 0 | Z19: 20 | AA19: 20 | AB19: 0 | AC19: 20 | AD19: 0 | AW19: 0
A20: barley | B20: that is, 4 bushels an acre. | C20: 0 | D20: 0 | E20: 0 | F20: 0 | G20: 0 | H20: 0 | I20: 0 | J20: 0 | K20: 0 | L20: 0 | M20: 0 | N20: 0 | O20: 0 | P20: 0 | Q20: 0 | R20: 0 | S20: 0 | T20: 0 | U20: 0 | V20: 0 | W20: 0 | X20: 0 | Y20: 4 | Z20: 0.5 | AA20: 0.5 | AB20: 0 | AC20: 0 | AD20: 4 | AW20: 0
A21: barley | B21: malting, 54 quarters 2 bushels. | C21: 0 | D21: 0 | E21: 0 | F21: 0 | G21: 0 | H21: 0 | I21: 0 | J21: 0 | K21: 0 | L21: 0 | M21: 0 | N21: 0 | O21: 0 | P21: 0 | Q21: 0 | R21: 0 | S21: 0 | T21: 0 | U21: 0 | V21: 0 | W21: 0 | X21: 54 | Y21: 2 | Z21: 54.25 | AA21: 54.25 | AB21: 0 | AC21: 54 | AD21: 2 | AW21: 0
A22: barley | B22: sold at the audit, 12 quarters 6 bushels for £2 18 shilling 9pence. | C22: 0 | D22: 0 | E22: 0 | F22: 0 | G22: 0 | H22: 0 | I22: 0 | J22: 0 | K22: 0 | L22: 0 | M22: 0 | N22: 0 | O22: 0 | P22: 0 | Q22: 12 | R22: 6 | S22: 12.75 | T22: 0 | U22: 0 | V22: 0 | W22: 0 | X22: 12 | Y22: 6 | Z22: 12.75 | AA22: 12.75 | AB22: 0 | AC22: 12 | AD22: 6 | AW22: 0
A23: barley | B23: total as before. | C23: 0 | D23: 0 | E23: 0 | F23: 0 | G23: 0 | H23: 0 | I23: 0 | J23: 0 | K23: 0 | L23: 0 | M23: 0 | N23: 0 | O23: 0 | P23: 0 | Q23: 0 | R23: 0 | S23: 0 | T23: 0 | U23: 0 | V23: 0 | W23: 0 | X23: 0 | Y23: 0 | Z23: 0 | AA23: 0 | AB23: 0 | AC23: 0 | AD23: 0 | AW23: 0
A24: barley | B24: it balances. | C24: 0 | D24: 0 | E24: 0 | F24: 0 | G24: 0 | H24: 0 | I24: 0 | J24: 0 | K24: 0 | L24: 0 | M24: 0 | N24: 0 | O24: 0 | P24: 0 | Q24: 0 | R24: 0 | S24: 0 | T24: 0 | U24: 0 | V24: 0 | W24: 0 | X24: 0 | Y24: 0 | Z24: 0 | AA24: 0 | AB24: 0 | AC24: 0 | AD24: 0 | AW24: 0
A25: barley | B25: total | C25: 0 | D25: 0 | E25: 0 | F25: 0 | G25: 0 | H25: 0 | I25: 0 | J25: 0 | K25: 0 | L25: 0 | M25: 0 | N25: 0 | O25: 0 | P25: 0 | Q25: 0 | R25: 0 | S25: 0 | T25: 0 | U25: 0 | V25: 0 | W25: 0 | AW25: 0
A26: dredge | B26: and for 29 quarters 4 bushels of dredge from the whole issue of the grange, threshed by piece-work. | C26: 0 | D26: 0 | E26: 0 | F26: 0 | G26: 0 | H26: 0 | I26: 0 | J26: 0 | K26: 0 | L26: 0 | M26: 0 | N26: 0 | O26: 0 | P26: 0 | Q26: 0 | R26: 0 | S26: 0 | T26: 29 | U26: 4 | V26: 29.5 | W26: 0 | X26: 29 | Y26: 4 | Z26: 29.5 | AA26: 29.5 | AB26: 0 | AC26: 29 | AD26: 4 | AW26: 0
A27: dredge | B27: 12 quarters 4 bushels surcharged so that he answers for a 4-fold yield. | C27: 0 | D27: 0 | E27: 0 | F27: 0 | G27: 0 | H27: 0 | I27: 0 | J27: 0 | K27: 0 | L27: 0 | M27: 0 | N27: 0 | O27: 0 | P27: 0 | Q27: 0 | R27: 0 | S27: 0 | T27: 0 | U27: 0 | V27: 0 | W27: 0 | X27: 12 | Y27: 4 | Z27: 12.5 | AA27: 12.5 | AB27: 0 | AC27: 12 | AD27: 4 | AW27: 0
A28: dredge | B28: total, 42 quarters. | C28: 0 | D28: 0 | E28: 0 | F28: 0 | G28: 0 | H28: 0 | I28: 0 | J28: 0 | K28: 0 | L28: 0 | M28: 0 | N28: 0 | O28: 0 | P28: 0 | Q28: 0 | R28: 0 | S28: 0 | T28: 0 | U28: 0 | V28: 0 | W28: 0 | X28: 42 | Y28: 0 | Z28: 42 | AA28: 42 | AB28: 0 | AC28: 42 | AD28: 0 | AW28: 0
A29: dredge | B29: sown over 20.5 acres of land by the perch which lie in le malme, 10 quarters 2 bushels. | C29: 0 | D29: 0 | E29: 10 | F29: 2 | G29: 10.25 | H29: 0 | I29: 0 | J29: 0 | K29: 0 | L29: 0 | M29: 0 | N29: 0 | O29: 0 | P29: 0 | Q29: 0 | R29: 0 | S29: 0 | T29: 0 | U29: 0 | V29: 0 | W29: 0 | X29: 10 | Y29: 2 | Z29: 10.25 | AA29: 10.25 | AB29: 0 | AC29: 10 | AD29: 2 | AW29: 0
A30: dredge | B30: that is, 4 bushels an acre. | C30: 0 | D30: 0 | E30: 0 | F30: 0 | G30: 0 | H30: 0 | I30: 0 | J30: 0 | K30: 0 | L30: 0 | M30: 0 | N30: 0 | O30: 0 | P30: 0 | Q30: 0 | R30: 0 | S30: 0 | T30: 0 | U30: 0 | V30: 0 | W30: 0 | X30: 0 | Y30: 4 | Z30: 0.5 | AA30: 0.5 | AB30: 0 | AC30: 0 | AD30: 4 | AW30: 0
A31: dredge | B31: malting, 19 quarters 2 bushels. | C31: 0 | D31: 0 | E31: 0 | F31: 0 | G31: 0 | H31: 0 | I31: 0 | J31: 0 | K31: 0 | L31: 0 | M31: 0 | N31: 0 | O31: 0 | P31: 0 | Q31: 0 | R31: 0 | S31: 0 | T31: 0 | U31: 0 | V31: 0 | W31: 0 | X31: 19 | Y31: 2 | Z31: 19.25 | AA31: 19.25 | AB31: 0 | AC31: 19 | AD31: 2 | AW31: 0
A32: dredge | B32: sold at the audit, 12 quarters 4 bushels for £2 10 shilling. | C32: 0 | D32: 0 | E32: 0 | F32: 0 | G32: 0 | H32: 0 | I32: 0 | J32: 0 | K32: 0 | L32: 0 | M32: 0 | N32: 0 | O32: 0 | P32: 0 | Q32: 12 | R32: 4 | S32: 12.5 | T32: 0 | U32: 0 | V32: 0 | W32: 0 | X32: 12 | Y32: 4 | Z32: 12.5 | AA32: 12.5 | AB32: 0 | AC32: 12 | AD32: 4 | AW32: 0
A33: dredge | B33: total as before. | C33: 0 | D33: 0 | E33: 0 | F33: 0 | G33: 0 | H33: 0 | I33: 0 | J33: 0 | K33: 0 | L33: 0 | M33: 0 | N33: 0 | O33: 0 | P33: 0 | Q33: 0 | R33: 0 | S33: 0 | T33: 0 | U33: 0 | V33: 0 | W33: 0 | X33: 0 | Y33: 0 | Z33: 0 | AA33: 0 | AB33: 0 | AC33: 0 | AD33: 0 | AW33: 0
A34: dredge | B34: it balances. | C34: 0 | D34: 0 | E34: 0 | F34: 0 | G34: 0 | H34: 0 | I34: 0 | J34: 0 | K34: 0 | L34: 0 | M34: 0 | N34: 0 | O34: 0 | P34: 0 | Q34: 0 | R34: 0 | S34: 0 | T34: 0 | U34: 0 | V34: 0 | W34: 0 | X34: 0 | Y34: 0 | Z34: 0 | AA34: 0 | AB34: 0 | AC34: 0 | AD34: 0 | AW34: 0
A35: dredge | B35: total | C35: 0 | D35: 0 | E35: 0 | F35: 0 | G35: 0 | H35: 0 | I35: 0 | J35: 0 | K35: 0 | L35: 0 | M35: 0 | N35: 0 | O35: 0 | P35: 0 | Q35: 0 | R35: 0 | S35: 0 | T35: 0 | U35: 0 | V35: 0 | W35: 0 | AW35: 0
A36: oats | B36: and for 36 quarters of oats from the whole issue of the grange, threshed by piece-work. | C36: 0 | D36: 0 | E36: 0 | F36: 0 | G36: 0 | H36: 0 | I36: 0 | J36: 0 | K36: 0 | L36: 0 | M36: 0 | N36: 0 | O36: 0 | P36: 0 | Q36: 0 | R36: 0 | S36: 0 | T36: 36 | U36: 0 | V36: 36 | W36: 0 | X36: 36 | Y36: 0 | Z36: 36 | AA36: 36 | AB36: 0 | AC36: 36 | AD36: 0 | AW36: 0
A37: oats | B37: 12 quarters from the same issue by estimation in sheaves. | C37: 0 | D37: 0 | E37: 0 | F37: 0 | G37: 0 | H37: 0 | I37: 0 | J37: 0 | K37: 0 | L37: 0 | M37: 0 | N37: 0 | O37: 0 | P37: 0 | Q37: 0 | R37: 0 | S37: 0 | T37: 0 | U37: 0 | V37: 0 | W37: 0 | X37: 12 | Y37: 0 | Z37: 12 | AA37: 12 | AB37: 0 | AC37: 12 | AD37: 0 | AW37: 0
A38: oats | B38: 39 quarters 3 bushels from the vill according to custom at the purification (2 february). | C38: 0 | D38: 0 | E38: 0 | F38: 0 | G38: 0 | H38: 0 | I38: 0 | J38: 0 | K38: 0 | L38: 0 | M38: 0 | N38: 0 | O38: 0 | P38: 0 | Q38: 0 | R38: 0 | S38: 0 | T38: 0 | U38: 0 | V38: 0 | W38: 0 | X38: 39 | Y38: 3 | Z38: 39.38 | AA38: 39.38 | AB38: 0 | AC38: 39 | AD38: 3 | AW38: 0
A39: oats | B39: 6 quarters surcharged so that he answers for a 3-fold yield. | C39: 0 | D39: 0 | E39: 0 | F39: 0 | G39: 0 | H39: 0 | I39: 0 | J39: 0 | K39: 0 | L39: 0 | M39: 0 | N39: 0 | O39: 0 | P39: 0 | Q39: 0 | R39: 0 | S39: 0 | T39: 0 | U39: 0 | V39: 0 | W39: 0 | X39: 6 | Y39: 0 | Z39: 6 | AA39: 6 | AB39: 0 | AC39: 6 | AD39: 0 | AW39: 0
A40: oats | B40: total, 93 quarters 3 bushels. | C40: 0 | D40: 0 | E40: 0 | F40: 0 | G40: 0 | H40: 0 | I40: 0 | J40: 0 | K40: 0 | L40: 0 | M40: 0 | N40: 0 | O40: 0 | P40: 0 | Q40: 0 | R40: 0 | S40: 0 | T40: 0 | U40: 0 | V40: 0 | W40: 0 | X40: 93 | Y40: 3 | Z40: 93.38 | AA40: 93.38 | AB40: 0 | AC40: 93 | AD40: 3 | AW40: 0
A41: oats | B41: sown over 34.5 acres of land by the perch which lie in le malme, 17 quarters 2 bushels. | C41: 0 | D41: 0 | E41: 17 | F41: 2 | G41: 17.25 | H41: 0 | I41: 0 | J41: 0 | K41: 0 | L41: 0 | M41: 0 | N41: 0 | O41: 0 | P41: 0 | Q41: 0 | R41: 0 | S41: 0 | T41: 0 | U41: 0 | V41: 0 | W41: 0 | X41: 17 | Y41: 2 | Z41: 17.25 | AA41: 17.25 | AB41: 0 | AC41: 17 | AD41: 2 | AW41: 0
A42: oats | B42: that is, 4 bushels an acre. | C42: 0 | D42: 0 | E42: 0 | F42: 0 | G42: 0 | H42: 0 | I42: 0 | J42: 0 | K42: 0 | L42: 0 | M42: 0 | N42: 0 | O42: 0 | P42: 0 | Q42: 0 | R42: 0 | S42: 0 | T42: 0 | U42: 0 | V42: 0 | W42: 0 | X42: 0 | Y42: 4 | Z42: 0.5 | AA42: 0.5 | AB42: 0 | AC42: 0 | AD42: 4 | AW42: 0
A43: oats | B43: default of various tenements in the lord's hands through the death of customary tenants by the pestilence, 11 quarters 2 bushels. | C43: 0 | D43: 0 | E43: 0 | F43: 0 | G43: 0 | H43: 0 | I43: 0 | J43: 0 | K43: 0 | L43: 0 | M43: 0 | N43: 0 | O43: 0 | P43: 0 | Q43: 0 | R43: 0 | S43: 0 | T43: 0 | U43: 0 | V43: 0 | W43: 0 | X43: 11 | Y43: 2 | Z43: 11.25 | AA43: 11.25 | AB43: 0 | AC43: 11 | AD43: 2 | AW43: 0
A44: oats | B44: that is, 6 bushels for the tenement of james fourhous, 1 qr 4 bushels for that of john wodefoghell', 1 qr 4 bushels for that of henry havecombe, 6 bushels for that of john peke, 1 qr 4 bushels for that of john havecombe, 6 bushels for that of william vage, 2 quarters 2 bushels for that of john atte wode, 6 bushels for that of william elyot, 6 bushels for that of james gybon, and 6 bushels for that of john herry. | C44: 0 | D44: 0 | E44: 0 | F44: 0 | G44: 0 | H44: 0 | I44: 0 | J44: 0 | K44: 0 | L44: 0 | M44: 0 | N44: 0 | O44: 0 | P44: 0 | Q44: 0 | R44: 0 | S44: 0 | T44: 0 | U44: 0 | V44: 0 | W44: 0 | AW44: 0
A45: oats | B45: meal made for the pottage of the manorial servants for the year, 4 quarters. | C45: 0 | D45: 0 | E45: 0 | F45: 0 | G45: 0 | H45: 0 | I45: 0 | J45: 0 | K45: 0 | L45: 0 | M45: 0 | N45: 0 | O45: 0 | P45: 0 | Q45: 0 | R45: 0 | S45: 0 | T45: 0 | U45: 0 | V45: 0 | W45: 0 | X45: 4 | Y45: 0 | Z45: 4 | AA45: 4 | AB45: 0 | AC45: 4 | AD45: 0 | AW45: 0
A46: oats | B46: fodder of the cart-horses at both sowings, 2 quarters. | C46: 0 | D46: 0 | E46: 0 | F46: 0 | G46: 0 | H46: 0 | I46: 0 | J46: 0 | K46: 0 | L46: 0 | M46: 0 | N46: 2 | O46: 0 | P46: 2 | Q46: 0 | R46: 0 | S46: 0 | T46: 0 | U46: 0 | V46: 0 | W46: 0 | X46: 2 | Y46: 0 | Z46: 2 | AA46: 2 | AB46: 0 | AC46: 2 | AD46: 0 | AW46: 0
A47: oats | B47: given to support the oxen, cows, calves and other cattle, ewes and hoggs in winter by reason of their feebleness, 10 quarters by estimation in sheaves. | C47: 0 | D47: 0 | E47: 0 | F47: 0 | G47: 0 | H47: 0 | I47: 0 | J47: 0 | K47: 0 | L47: 0 | M47: 0 | N47: 0 | O47: 0 | P47: 0 | Q47: 0 | R47: 0 | S47: 0 | T47: 0 | U47: 0 | V47: 0 | W47: 0 | X47: 10 | Y47: 0 | Z47: 10 | AA47: 10 | AB47: 0 | AC47: 10 | AD47: 0 | AW47: 0
A48: oats | B48: fodder of the horses of the steward holding the tourns of martinmas and hockday, by 2 sealed bills, 2 quarters 2 bushels. | C48: 0 | D48: 0 | E48: 0 | F48: 0 | G48: 0 | H48: 0 | I48: 0 | J48: 0 | K48: 0 | L48: 0 | M48: 0 | N48: 2 | O48: 2 | P48: 2.25 | Q48: 0 | R48: 0 | S48: 0 | T48: 0 | U48: 0 | V48: 0 | W48: 0 | X48: 2 | Y48: 2 | Z48: 2.25 | AA48: 2.25 | AB48: 0 | AC48: 2 | AD48: 2 | AW48: 0
A49: oats | B49: sold within, 34 quarters 5 bushels, of which 4 quarters 4 bushels sold to the lord's household.. | C49: 0 | D49: 0 | E49: 0 | F49: 0 | G49: 0 | H49: 0 | I49: 0 | J49: 0 | K49: 0 | L49: 0 | M49: 0 | N49: 0 | O49: 0 | P49: 0 | Q49: 38 | R49: 9 | S49: 39.12 | T49: 0 | U49: 0 | V49: 0 | W49: 0 | X49: 4 | Y49: 4 | Z49: 4.5 | AA49: 34.62 | AB49: -30.12 | AC49: 34 | AD49: 5 | AE49: 4 | AF49: 4 | AW49: 0
A50: oats | B50: sold at the audit,, 12 quarters for £1 4 shilling. | C50: 0 | D50: 0 | E50: 0 | F50: 0 | G50: 0 | H50: 0 | I50: 0 | J50: 0 | K50: 0 | L50: 0 | M50: 0 | N50: 0 | O50: 0 | P50: 0 | Q50: 12 | R50: 0 | S50: 12 | T50: 0 | U50: 0 | V50: 0 | W50: 0 | X50: 12 | Y50: 0 | Z50: 12 | AA50: 12 | AB50: 0 | AC50: 12 | AD50: 0 | AW50: 0
A51: oats | B51: total as before. | C51: 0 | D51: 0 | E51: 0 | F51: 0 | G51: 0 | H51: 0 | I51: 0 | J51: 0 | K51: 0 | L51: 0 | M51: 0 | N51: 0 | O51: 0 | P51: 0 | Q51: 0 | R51: 0 | S51: 0 | T51: 0 | U51: 0 | V51: 0 | W51: 0 | X51: 0 | Y51: 0 | Z51: 0 | AA51: 0 | AB51: 0 | AC51: 0 | AD51: 0 | AW51: 0
A52: oats | B52: it balances. | C52: 0 | D52: 0 | E52: 0 | F52: 0 | G52: 0 | H52: 0 | I52: 0 | J52: 0 | K52: 0 | L52: 0 | M52: 0 | N52: 0 | O52: 0 | P52: 0 | Q52: 0 | R52: 0 | S52: 0 | T52: 0 | U52: 0 | V52: 0 | W52: 0 | X52: 0 | Y52: 0 | Z52: 0 | AA52: 0 | AB52: 0 | AC52: 0 | AD52: 0 | AW52: 0

Sheet Issues of the Grange
A1: Gross Output | B1: Bought Only Aggregated | C1: Account Quarters | D1: Account Bushels | E1: Account Total Quarters | F1: Bought in Quarters | G1: Bought in Bushels | H1: Total Bought Quarters | I1: Sold Quarters | J1: Sold Bushels | K1: Sold Total Quarters | L1: Total Corn Quantity | M1: Difference Produced+Bought-Sold | N1: Weighted Average Price per Quarter | O1: Non-Weighted Average Price per Quarter | P1: Value of Total Production weighted | Q1: Value of Total Production unweighted
A2: and he owes | B2: 0 | C2: 0 | D2: 0 | E2: 0 | F2: 0 | G2: 0 | H2: 0 | I2: 0 | J2: 0 | K2: 0 | L2: 0 | M2: 0
A3: wheat | B3: 0 | C3: 34 | D3: 0 | E3: 34 | F3: 0 | G3: 0 | H3: 0 | I3: 22 | J3: 2.5 | K3: 22.31 | L3: 34 | M3: 11.69 | N3: 0.4 | O3: 0.4 | P3: 13.6 | Q3: 13.6
A4: barley | B4: 0 | C4: 68 | D4: 2 | E4: 68.25 | F4: 0 | G4: 0 | H4: 0 | I4: 12 | J4: 6 | K4: 12.75 | L4: 68.25 | M4: 55.5
A5: dredge | B5: 0 | C5: 29 | D5: 4 | E5: 29.5 | F5: 0 | G5: 0 | H5: 0 | I5: 12 | J5: 4 | K5: 12.5 | L5: 29.5 | M5: 17
A6: oats | B6: 0 | C6: 36 | D6: 0 | E6: 36 | F6: 0 | G6: 0 | H6: 0 | I6: 38 | J6: 9 | K6: 39.12 | L6: 36 | M6: -3.12 | N6: 0.13 | O6: 0.13 | P6: 4.8 | Q6: 4.8
A7: Mancorn | B7: 0 | C7: 0 | D7: 0 | E7: 0 | F7: 0 | G7: 0 | H7: 0 | I7: 0 | J7: 0 | K7: 0 | L7: 0 | M7: 0
A8: Maslin | B8: 0 | C8: 0 | D8: 0 | E8: 0 | F8: 0 | G8: 0 | H8: 0 | I8: 0 | J8: 0 | K8: 0 | L8: 0 | M8: 0
A9: First-grade malt | B9: 0 | C9: 0 | D9: 0 | E9: 0 | F9: 0 | G9: 0 | H9: 0 | I9: 0 | J9: 0 | K9: 0 | L9: 0 | M9: 0
A10: Second-grade malt | B10: 0 | C10: 0 | D10: 0 | E10: 0 | F10: 0 | G10: 0 | H10: 0 | I10: 0 | J10: 0 | K10: 0 | L10: 0 | M10: 0
A11: Peas | B11: 0 | C11: 0 | D11: 0 | E11: 0 | F11: 0 | G11: 0 | H11: 0 | I11: 0 | J11: 0 | K11: 0 | L11: 0 | M11: 0
A12: Oatmeal | B12: 0 | C12: 0 | D12: 0 | E12: 0 | F12: 0 | G12: 0 | H12: 0 | I12: 0 | J12: 0 | K12: 0 | L12: 0 | M12: 0
A13: Vetches | B13: 0 | C13: 0 | D13: 0 | E13: 0 | F13: 0 | G13: 0 | H13: 0 | I13: 0 | J13: 0 | K13: 0 | L13: 0 | M13: 0
A14: Rye | B14: 0 | C14: 0 | D14: 0 | E14: 0 | F14: 0 | G14: 0 | H14: 0 | I14: 0 | J14: 0 | K14: 0 | L14: 0 | M14: 0
A15: Malt | B15: 0 | C15: 0 | D15: 0 | E15: 0 | F15: 0 | G15: 0 | H15: 0 | I15: 0 | J15: 0 | K15: 0 | L15: 0 | M15: 0 | N15: 0.3 | O15: 0.3 | P15: 0 | Q15: 0
A16: Meal | B16: 0 | C16: 0 | D16: 0 | E16: 0 | F16: 0 | G16: 0 | H16: 0 | I16: 0 | J16: 0 | K16: 0 | L16: 0 | M16: 0
A17: Curall | B17: 0 | C17: 0 | D17: 0 | E17: 0 | F17: 0 | G17: 0 | H17: 0 | I17: 0 | J17: 0 | K17: 0 | L17: 0 | M17: 0

Sheet Sale of Corn Prices
A1: Heading | B1: Sentence | C1: Total in Pounds | D1: Pounds | E1: Shillings | F1: Pence | G1: Corn | H1: Total Quarters Except 1 | I1: Total Bushels Except 1 | J1: Total Corn Cross-Check | K1: Total Corn Manorial Account | L1: Corn Quantity Error | M1: Quarters 0 | N1: Bushels 0 | O1: shilling a quarter 1 | P1: pence a quarter 1 | Q1: Quarters 1 | R1: Bushels 1 | S1: shilling a quarter 2 | T1: pence a quarter 2 | U1: Quarters 2 | V1: Bushels 2 | W1: shilling a quarter 3 | X1: pence a quarter 3 | Y1: Quarters 3 | Z1: Bushels 3 | AA1: shilling a quarter 4 | AB1: pence a quarter 4 | AC1: Quarters 4 | AD1: Bushels 4 | AE1: Quarters 5 | AF1: Bushels 5 | AG1: Quarters 6 | AH1: Bushels 6 | AI1: Quarters 7 | AJ1: Bushels 7 | AK1: Quarters 8 | AL1: Bushels 8 | AM1: Quarters 9 | AN1: Bushels 9 | AO1: £ a quarter 1 | AP1: £ a quarter 2 | AQ1: £ a quarter 3 | AR1: £ a quarter 4 | AS1: Quarters Sold | AT1: Weighted Average Price per Quarter | AU1: Non-Weighted Average Price per Quarter | AV1: Corn lowercase
A2: sale of corn and malt | B2: and for £8 18 shilling 6pence' from 22 quarters 2.5 bushels of wheat sold, at 8 shilling a quarters, as made clear elsewhere. | C2: 8.93 | D2: 8 | E2: 18 | F2: 6 | G2: wheat | H2: 22 | I2: 2.5 | J2: 22.31 | K2: 22.31 | L2: 0 | M2: 22 | N2: 2.5 | O2: 8 | P2: 0 | AO2: 0.4 | AS2: 22.31 | AT2: 0.4 | AU2: 0.4 | AV2: wheat
A3: sale of corn and malt | B3: £4 12 shilling 4pence from 34 quarters 5 bushels of oats sold, at 2 shilling 8pence a quarters, as made clear elsewhere, of which 4 quarters 4 bushels sold to the lord's household. | C3: 4.62 | D3: 4 | E3: 12 | F3: 4 | G3: oats | H3: 4 | I3: 4 | J3: 4.5 | K3: 34.62 | L3: -30.12 | M3: 34 | N3: 5 | O3: 2 | P3: 8 | Q3: 4 | R3: 4 | AO3: 0.13 | AS3: 34.62 | AT3: 0.13 | AU3: 0.13 | AV3: oats
A4: sale of corn and malt | B4: £24 7 shilling 4pence from 80 quarters 3 bushels 1 peck of malt sold, of which 71 quarters sold to the lord's household at esher, at 6. | C4: 24.37 | D4: 24 | E4: 7 | F4: 4 | G4: malt | H4: 71 | I4: 3 | J4: 71.38 | K4: 80.38 | L4: -9 | M4: 80 | N4: 3 | Q4: 71 | R4: 0 | AO4: 0.3 | AS4: 80.38 | AT4: 0.3 | AU4: 0.3 | AV4: malt
A5: sale of corn and malt | B5: a quarters, and 9 quarters 3 bushels 1 peck, at 6 shilling 8pence a quarters. | C5: 0.33 | D5: 0 | E5: 6 | F5: 8 | H5: 9 | I5: 3 | J5: 9.38 | K5: 9.38 | L5: 0 | M5: 9 | N5: 3 | O5: 6 | P5: 8 | AO5: 0.33 | AS5: 9.38 | AT5: 0.33 | AU5: 0.33
A6: sale of corn and malt | B6: total, £37 18 shilling 2pence. | C6: 37.91 | D6: 37 | E6: 18 | F6: 2 | H6: 0 | I6: 0 | J6: 0 | K6: 0 | L6: 0 | M6: 0 | N6: 0 | AO6: inf | AS6: 0 | AT6: inf | AU6: inf

Sheet Expenses
A1: IVINGHOE EXPENSES
A2: Heading | B2: £ | C2: s | D2: d | F2: Total in £ | G2: Error | H2: Notes
A4: Cost of ploughs | B4: 1 | C4: 0 | D4: 0 | F4: 1
A5: Cost of ploughs | B5: 0 | C5: 12 | D5: 0 | F5: 0.6
A6: Cost of ploughs | B6: 0 | C6: 2 | D6: 0 | F6: 0.1
A7: Cost of ploughs | B7: 0 | C7: 1 | D7: 0 | F7: 0.05
A8: Cost of ploughs | B8: 0 | C8: 2 | D8: 1 | F8: 0.1
A9: Cost of ploughs | B9: 0 | C9: 5 | D9: 0 | F9: 0.25
A10: Cost of ploughs | B10: 0 | C10: 2 | D10: 8 | F10: 0.13
A11: Cost of ploughs | B11: 0 | C11: 1 | D11: 0 | F11: 0.05
A12: Cost of ploughs | B12: 0 | C12: 1 | D12: 0 | F12: 0.05
A13: Cost of ploughs | B13: 0 | C13: 2 | D13: 6 | F13: 0.12
A14: Cost of ploughs | B14: 0 | C14: 7 | D14: 6 | F14: 0.38
A15: Cost of ploughs | B15: 1 | C15: 0 | D15: 0 | F15: 1
A16: Cost of ploughs | B16: 3 | C16: 16 | D16: 9 | F16: 3.84
A17: Cost of ploughs total | F17: 3.83 | G17: -0.01
A19: Cost of carts | B19: 0 | C19: 2 | D19: 8 | F19: 0.13
A20: Cost of carts | B20: 0 | C20: 8 | D20: 0 | F20: 0.4
A21: Cost of carts | B21: 0 | C21: 4 | D21: 0 | F21: 0.2
A22: Cost of carts | B22: 0 | C22: 2 | D22: 8 | F22: 0.13
A23: Cost of carts | B23: 0 | C23: 1 | D23: 0 | F23: 0.05
A24: Cost of carts | B24: 0 | C24: 1 | D24: 0 | F24: 0.05
A25: Cost of carts | B25: 0 | C25: 2 | D25: 0 | F25: 0.1
A26: Cost of carts | B26: 0 | C26: 1 | D26: 0 | F26: 0.05
A27: Cost of carts | B27: 0 | C27: 1 | D27: 0 | F27: 0.05
A28: Cost of carts | B28: 0 | C28: 2 | D28: 0 | F28: 0.1
A29: Cost of carts | B29: 0 | C29: 0 | D29: 0 | F29: 0
A30: Cost of carts | B30: 0 | C30: 2 | D30: 4 | F30: 0.12
... A38: Cost of carts | B38: 2 | C38: 10 | D38: 6 | F38: 2.52
A39: Cost of carts total | F39: 2.53 | G39: 0.01
A41: Threshing and winnowing | B41: 1 | C41: 6 | D41: 0 | F41: 1.3
A42: Threshing and winnowing | B42: 0 | C42: 16 | D42: 3.5 | F42: 0.81
A43: Threshing and winnowing | B43: 0 | C43: 4 | D43: 6 | F43: 0.23
A44: Threshing and winnowing | B44: 0 | C44: 6 | D44: 7.5 | F44: 0.33
A45: Threshing and winnowing | B45: 2 | C45: 13 | D45: 5 | F45: 2.67
A46: Threshing and winnowing total | F46: 2.67 | G46: 0
A48: Expenses of the steward | B48: 0 | C48: 12 | D48: 11.5 | F48: 0.65
A49: Expenses of the steward | B49: 0 | C49: 12 | D49: 11.5 | F49: 0.65
A50: Expenses of the steward total | F50: 0.65 | G50: 0
A52: Total of all expenses | B52: 70 | C52: 7 | D52: 2.5 | F52: 70.36
A53: Total of all expenses | F53: 0 | G53: -70.36
A55: And he owes | B55: 64 | C55: 7 | D55: 8.25 | F55: 64.38
A56: And he owes | F56: 64.38
A57: And he owes total | B57: 1 | C57: 14 | D57: 0 | F57: 1.7 | G57: -62.68
A59: Cash deliveries | B59: 23 | C59: 6 | D59: 0 | F59: 23.3
A60: Cash deliveries | B60: 23 | C60: 6 | D60: 0 | F60: 23.3
A61: Cash deliveries total | F61: 23.3 | G61: 0
A63: Total of all allowances and cash deliveries | B63: 67 | C63: 13 | D63: 8.25 | F63: 67.68
A64: Total of all allowances and cash deliveries total | F64: 0 | G64: -67.68
A66: Total of all expenses per account | B66: 70 | C66: 7 | D66: 2.5 | F66: =F52
A67: Total of all expenses (calculated here) | F67: =SUMIF(A1:A51,"* total",F1:F51)
A68: Total fixed investment
A69: Total Demesne fixed investment
