Workbook

Sheet Adderbury Overview
A1: ADDERBURY | B1: Total in £ | C1: Error | D1: Note
A2: CASH ACCOUNT
A3: RECEIPTS
A4: Arrears total
A5: Rents of assize total | B5: ='Adderbury Receipts'!F9
A6: Quittances total | B6: ='Adderbury Receipts'!F22
A7: Defaults of rent total | B7: ='Adderbury Receipts'!F27
A8: Defaults of rent through the pestilence total | B8: ='Adderbury Receipts'!F36
A9: Cotlands defaults total | B9: ='Adderbury Receipts'!F45
A10: Cotlands total | B10: ='Adderbury Receipts'!F54
A11: Total of quittances and defaults of rent total | B11: ='Adderbury Receipts'!F56
A12: Total of rents remaining clear total | B12: ='Adderbury Receipts'!F58
A13: Farms total | B13: ='Adderbury Receipts'!F70
A14: Annual recognizances total | B14: ='Adderbury Receipts'!F90
A15: Issues of the Manor total | B15: ='Adderbury Receipts'!F117
A16: Issues of the tenements in the lord's hands total | B16: ='Adderbury Receipts'!F126
A17: Sale of labour services total | B17: ='Adderbury Receipts'!F135
A18: Sale of corn total | B18: ='Adderbury Receipts'!F138
A19: Entry and marriage fines total | B19: ='Adderbury Receipts'!F166
A20: Pleas & perquisites total | B20: ='Adderbury Receipts'!F173
A21: Forfeited chattels total | B21: ='Adderbury Receipts'!F177
A22: Farm of the demesne land total | B22: ='Adderbury Receipts'!F181
A23: Total of all receipts (calculated here) | B23: ='Adderbury Receipts'!F185
A24: Total of all receipts (calculated here) incl arrears
A25: Total recorded in the accounts excl. arrears | B25: ='Adderbury Receipts'!F184 | C25: =B23-B25
A26: Total recorded in the accounts incl. arrears
A29: EXPENSES
A30: Cost of ploughs total
A31: Purchase of corn total
A32: Cost of carts and wagons total
A33: Cost of dairy total
A34: Purchase of stock total
A35: Sheepcote total
A36: Cost of buildings total | B36: ='Adderbury Expenses'!F26
A37: Threshing total
A38: Barley expenses
A39: Expenses of the harvest total
A40: Necessary expenses
A41: Wages of the bailiff | B41: ='Adderbury Expenses'!F30
A42: Steward's expenses total | B42: ='Adderbury Expenses'!F33
A43: Annual fees | B43: ='Adderbury Expenses'!F37
A44: Total of all expenses per account
A45: Total of all expenses (calculated here)
A46: Total fixed investment
A47: Total Demesne fixed investment
A49: Owed by the reeve | B49: =B23-B45
A50: From accounts | B50: ='Adderbury Expenses'!F41
A52: Allowances | B52: ='Adderbury Expenses'!F45
A53: Cash deliveries | B53: ='Adderbury Expenses'!F48
A54: Sum of the above | B54: =SUM(B52:B53)
A55: Total of all allowances and cash deliveries in accounts
A57: Net amount owed | B57: =B50-B54
A58: Net amount owed in accounts
A60: GRANGE ACCOUNT | B60: Total Production | D60: Value of total gross production in £ | E60: Value of total net production in £
A61: Grange | B61: qrs | C61: bus
A62: Wheat
A63: Rye
A64: Dredge
A65: Curall
A66: Barley
A67: Oats
A68: Beans
A69: Peas
A70: Vetches
A71: Total value of gross production (sum of the above) | B71: =SUM(D62:D70)
A72: Total value of net production | B72: =SUM(E62:E70)
A73: Value of sales
A75: MILL ACCOUNT | B75: Total Production | D75: Total in £ | F75: Not yet implemented
A76: Issues of the mill | B76: qrs | C76: bus
A77: Wheat
A78: Oatmeal
A79: 1st grade malt
A80: 2nd grade malt
A81: Maslin
A82: Total value of production (sum of the above)
A83: Value of sales
A85: STOCK ACCOUNT
A86: Livestock | B86: Begin stock | C86: End stock | D86: Stockbuilding | F86: Value of stock in £ | G86: Value of stockbuilding
A87: Cart-horses | B87: ='Adderbury Stock'!B5 | C87: ='Adderbury Stock'!K5 | D87: ='Adderbury Overview'!C87-'Adderbury Overview'!B87 | F87: ='Adderbury Stock'!P5 | G87: ='Adderbury Stock'!S5
A88: Mares | B88: ='Adderbury Stock'!B6 | C88: ='Adderbury Stock'!K6 | D88: ='Adderbury Overview'!C88-'Adderbury Overview'!B88 | F88: ='Adderbury Stock'!P6 | G88: ='Adderbury Stock'!S6
A89: Plough horses | B89: ='Adderbury Stock'!B7 | C89: ='Adderbury Stock'!K7 | D89: ='Adderbury Overview'!C89-'Adderbury Overview'!B89 | F89: ='Adderbury Stock'!P7 | G89: ='Adderbury Stock'!S7
A90: Colts (2 years) | B90: ='Adderbury Stock'!B8 | C90: ='Adderbury Stock'!K8 | D90: ='Adderbury Overview'!C90-'Adderbury Overview'!B90 | F90: ='Adderbury Stock'!P8 | G90: ='Adderbury Stock'!S8
A91: Colts (2 years) | B91: ='Adderbury Stock'!B9 | C91: ='Adderbury Stock'!K9 | D91: ='Adderbury Overview'!C91-'Adderbury Overview'!B91 | F91: ='Adderbury Stock'!P9 | G91: ='Adderbury Stock'!S9
A92: Colts (1 year) | B92: ='Adderbury Stock'!B10 | C92: ='Adderbury Stock'!K10 | D92: ='Adderbury Overview'!C92-'Adderbury Overview'!B92 | F92: ='Adderbury Stock'!P10 | G92: ='Adderbury Stock'!S10
A93: Foals | B93: ='Adderbury Stock'!B11 | C93: ='Adderbury Stock'!K11 | D93: ='Adderbury Overview'!C93-'Adderbury Overview'!B93 | F93: ='Adderbury Stock'!P11 | G93: ='Adderbury Stock'!S11
A94: Oxen | B94: ='Adderbury Stock'!B12 | C94: ='Adderbury Stock'!K12 | D94: ='Adderbury Overview'!C94-'Adderbury Overview'!B94 | F94: ='Adderbury Stock'!P12 | G94: ='Adderbury Stock'!S12
A95: Bulls | B95: ='Adderbury Stock'!B13 | C95: ='Adderbury Stock'!K13 | D95: ='Adderbury Overview'!C95-'Adderbury Overview'!B95 | F95: ='Adderbury Stock'!P13 | G95: ='Adderbury Stock'!S13
A96: Cows | B96: ='Adderbury Stock'!B14 | C96: ='Adderbury Stock'!K14 | D96: ='Adderbury Overview'!C96-'Adderbury Overview'!B96 | F96: ='Adderbury Stock'!P14 | G96: ='Adderbury Stock'!S14
A97: Steers | B97: ='Adderbury Stock'!B15 | C97: ='Adderbury Stock'!K15 | D97: ='Adderbury Overview'!C97-'Adderbury Overview'!B97 | F97: ='Adderbury Stock'!P15 | G97: ='Adderbury Stock'!S15
A98: Bullocks | B98: ='Adderbury Stock'!B16 | C98: ='Adderbury Stock'!K16 | D98: ='Adderbury Overview'!C98-'Adderbury Overview'!B98 | F98: ='Adderbury Stock'!P16 | G98: ='Adderbury Stock'!S16
... A112: Peacocks | B112: ='Adderbury Stock'!B30 | C112: ='Adderbury Stock'!K30 | D112: ='Adderbury Overview'!C112-'Adderbury Overview'!B112 | F112: ='Adderbury Stock'!P30 | G112: ='Adderbury Stock'!S30
A113: Total value of stock (sum of the above) | F113: =SUM(F87:F112) | G113: ='Adderbury Stock'!S31
A114: Total value of production | F114: =SUM('Adderbury Stock'!T5:T29)
A115: Value of sales | F115: =SUM('Adderbury Stock'!R5:R23)
A117: Wool | B117: Begin stock | C117: End stock | D117: Stockbuilding | F117: Value of stock in £
A118: Fleeces
A119: Coarse wool
A120: Lamb's wool
A121: Wool locks
A122: Wool sold at shearing
...

Sheet Newtown Stock
A1: NEWTOWN STOCK ACCOUNT
C3: added | G3: subtracted
A4: Livestock | B4: Inherited stock | C4: added | D4: strays | E4: herbage | F4: churchscot | G4: of which in default | H4: sold | I4: in murrain | J4: accounted for elsewhere | K4: End-period stock | L4: cross-check | M4: stock building | N4: raw production | O4: Unit price (£) | P4: Value of stock (£) at given value | Q4: Value of stock (£) at sales prices | R4: Sales in (£) | S4: Value of stock building (£) | T4: Value of production (£) at sales prices | U4: Details
A5: Cart-horses | B5: 0 | C5: 0 | H5: 0 | I5: 0 | L5: =B5+C5-H5 | M5: =L5-B5 | N5: =C5 | O5: 0 | P5: =O5*K5 | R5: 0 | S5: =O5*M5 | T5: =O5*N5
A6: Mares | B6: 0 | C6: 0 | H6: 0 | I6: 0 | L6: =B6+C6-H6 | M6: =L6-B6 | N6: =C6 | O6: 0 | P6: =O6*K6 | R6: 0 | S6: =O6*M6 | T6: =O6*N6
A7: Plough horses | B7: 0 | C7: 0 | H7: 0 | I7: 0 | L7: =B7+C7-H7 | M7: =L7-B7 | N7: =C7 | O7: 0 | P7: =O7*K7 | R7: 0 | S7: =O7*M7 | T7: =O7*N7
A8: Colts (unspecified years) | B8: 0 | C8: 0 | H8: 0 | I8: 0 | L8: =B8+C8-H8 | M8: =L8-B8 | N8: =C8 | O8: 0 | P8: =O8*K8 | R8: 0 | S8: =O8*M8 | T8: =O8*N8
A9: Colts (2 years) | B9: 0 | C9: 0 | H9: 0 | I9: 0 | L9: =B9+C9-H9 | M9: =L9-B9 | N9: =C9 | O9: 0 | P9: =O9*K9 | R9: 0 | S9: =O9*M9 | T9: =O9*N9
A10: Colts (1 year) | B10: 0 | C10: 0 | H10: 0 | I10: 0 | L10: =B10+C10-H10 | M10: =L10-B10 | N10: =C10 | O10: 0 | P10: =O10*K10 | R10: 0 | S10: =O10*M10 | T10: =O10*N10
A11: Foals | B11: 0 | C11: 0 | H11: 0 | I11: 0 | L11: =B11+C11-H11 | M11: =L11-B11 | N11: =C11 | O11: 0 | P11: =O11*K11 | R11: 0 | S11: =O11*M11 | T11: =O11*N11
A12: Oxen | B12: 0 | C12: 0 | H12: 0 | I12: 0 | L12: =B12+C12-H12 | M12: =L12-B12 | N12: =C12 | O12: 0 | P12: =O12*K12 | R12: 0 | S12: =O12*M12 | T12: =O12*N12
A13: Bulls | B13: 0 | C13: 0 | H13: 0 | I13: 0 | L13: =B13+C13-H13 | M13: =L13-B13 | N13: =C13 | O13: 0 | P13: =O13*K13 | R13: 0 | S13: =O13*M13 | T13: =O13*N13
A14: Cows | B14: 0 | C14: 0 | H14: 0 | I14: 0 | L14: =B14+C14-H14 | M14: =L14-B14 | N14: =C14 | O14: 0 | P14: =O14*K14 | R14: 0 | S14: =O14*M14 | T14: =O14*N14
A15: Steers | B15: 0 | C15: 0 | H15: 0 | I15: 0 | L15: =B15+C15-H15 | M15: =L15-B15 | N15: =C15 | O15: 0 | P15: =O15*K15 | R15: 0 | S15: =O15*M15 | T15: =O15*N15
A16: Bullocks | B16: 0 | C16: 0 | H16: 0 | I16: 0 | L16: =B16+C16-H16 | M16: =L16-B16 | N16: =C16 | O16: 0 | P16: =O16*K16 | R16: 0 | S16: =O16*M16 | T16: =O16*N16
... A20: Rams | B20: 0 | C20: 0 | H20: 0 | I20: 0 | L20: =B20+C20-H20 | M20: =L20-B20 | N20: =C20 | O20: 0 | P20: =O20*K20 | R20: 0 | S20: =O20*M20 | T20: =O20*N20
A21: Ewes | B21: 0 | C21: 0 | H21: 0 | I21: 0 | L21: =B21+C21-H21 | M21: =L21-B21 | N21: =C21 | O21: 0 | P21: =O21*K21 | Q21: 0 | R21: 0 | S21: =O21*M21 | T21: =O21*N21
A22: Hoggs | B22: 0 | C22: 0 | H22: 0 | I22: 0 | L22: =B22+C22-H22 | M22: =L22-B22 | N22: =C22 | O22: 0 | P22: =O22*K22 | R22: 0 | S22: =O22*M22 | T22: =O22*N22
A23: Lambs | B23: 0 | C23: 0 | H23: 0 | I23: 0 | L23: =B23+C23-H23 | M23: =L23-B23 | N23: =C23 | O23: 0 | P23: =O23*K23 | R23: 0 | S23: =O23*M23 | T23: =O23*N23
A24: Boars | B24: 0 | C24: 0 | H24: 0 | I24: 0 | L24: =B24+C24-H24 | M24: =L24-B24 | N24: =C24 | O24: 0 | P24: =O24*K24 | R24: 0 | S24: =O24*M24 | T24: =O24*N24
A25: Sows | B25: 0 | C25: 0 | H25: 0 | I25: 0 | L25: =B25+C25-H25 | M25: =L25-B25 | N25: =C25 | O25: 0 | P25: =O25*K25 | R25: 0 | S25: =O25*M25 | T25: =O25*N25
A26: Pigs | B26: 0 | C26: 0 | H26: 0 | I26: 0 | L26: =B26+C26-H26 | M26: =L26-B26 | N26: =C26 | O26: 0 | P26: =O26*K26 | R26: 0 | S26: =O26*M26 | T26: =O26*N26
A27: Hoggets | B27: 0 | C27: 0 | H27: 0 | I27: 0 | L27: =B27+C27-H27 | M27: =L27-B27 | N27: =C27 | O27: 0 | P27: =O27*K27 | R27: 0 | S27: =O27*M27 | T27: =O27*N27
A28: Piglets | B28: 0 | C28: 0 | H28: 0 | I28: 0 | L28: =B28+C28-H28 | M28: =L28-B28 | N28: =C28 | O28: 0 | P28: =O28*K28 | R28: 0 | S28: =O28*M28 | T28: =O28*N28
A29: Swans | B29: 0 | C29: 0 | H29: 0 | I29: 0 | L29: =B29+C29-H29 | M29: =L29-B29 | N29: =C29 | O29: 0 | P29: =O29*K29 | R29: 0 | S29: =O29*M29 | T29: =O29*N29
A30: Peacocks | B30: 0 | C30: 0 | H30: 0 | I30: 0 | L30: =B30+C30-H30 | M30: =L30-B30 | N30: =C30 | O30: 0 | P30: =O30*K30 | R30: 0 | S30: =O30*M30 | T30: =O30*N30
A31: Total Value
A34: Wool | B34: 0 | C34: 0 | H34: 0 | I34: 0
A35: Coarse wool | B35: 0 | C35: 0 | H35: 0 | I35: 0
A36: Lamb's wool | B36: 0 | C36: 0 | H36: 0 | I36: 0
A37: Wool locks | B37: 0 | C37: 0 | H37: 0 | I37: 0
A38: Wool sold at shearing | B38: 0 | C38: 0 | H38: 0 | I38: 0
A39: Total wool | B39: 0 | C39: 0 | H39: 0 | I39: 0
B40: 0 | C40: 0 | H40: 0 | I40: 0
B41: 0 | C41: 0 | H41: 0 | I41: 0
A42: Hides | B42: 0 | C42: 0 | H42: 0 | I42: 0
A43: Ox hides | B43: 0 | C43: 0 | H43: 0 | I43: 0
A44: Mare | B44: 0 | C44: 0 | H44: 0 | I44: 0
A45: Steer | B45: 0 | C45: 0 | H45: 0 | I45: 0
A46: calves | B46: 0 | C46: 0 | H46: 0 | I46: 0
A47: pigs | B47: 0 | C47: 0 | H47: 0 | I47: 0
A48: Woolskins
A49: wethers
A50: rams
A51: ewes
A52: hoggs
A53: Woolskins total | B53: 0 | C53: 0 | H53: 0 | I53: 0
A54: Bareskins
A55: wethers
A56: rams
A57: ewes
A58: hoggs
A59: Bareskins total | B59: 0 | C59: 0 | H59: 0 | I59: 0
A60: Lambskins | B60: 0 | C60: 0 | H60: 0 | I60: 0
A61: Rotted skins | B61: 0 | C61: 0 | H61: 0 | I61: 0
A62: Shorn skins | B62: 0 | C62: 0 | H62: 0 | I62: 0
A63: Total
A66: Poultry stock
A67: Hens | L67: =B67+C67-H67 | M67: =L67-B67 | N67: =C67 | O67: 0 | Q67: =R67*K67 | R67: 0 | S67: =O67*M67 | T67: =O67*N67
A68: Geese | L68: =B68+C68-H68 | M68: =L68-B68 | N68: =C68 | O68: 0 | Q68: =R68*K68 | R68: 0 | S68: =O68*M68 | T68: =O68*N68
A69: Capons (from chickens) | B69: 0 | C69: 6 | H69: 6 | K69: 0 | L69: =B69+C69-H69 | M69: =L69-B69 | N69: =C69 | O69: 0 | Q69: =R69*K69 | R69: 0 | S69: =O69*M69 | T69: =O69*N69
A70: Cocks & hens | B70: 0 | F70: 28 | G70: 18 | H70: 10 | K70: 0 | L70: =B70+C70-H70 | M70: =L70-B70 | N70: =C70 | O70: 0 | Q70: =R70*K70 | R70: 0 | S70: =O70*M70 | T70: =O70*N70
A71: Total poultry stock
A72: Total poultry excluding churchscot
A74: Poultry production
A75: Eggs | B75: 0 | C75: 0 | H75: 0 | I75: 0 | S75: =O75*M75 | T75: =O75*N75
A76: Cocks & hens from churchscot of customary tenants | B76: 0 | C76: 0 | H76: 0 | I76: 0 | S76: =O76*M76 | T76: =O76*N76
A77: Sum of above | S77: =SUM(S75:S76) | T77: =SUM(T75:T76)
A78: Total
A81: Meat
A82: Beef | B82: 0 | C82: 0 | H82: 0 | I82: 0 | S82: =O82*M82 | T82: =O82*N82
A83: Mutton | B83: 0 | C83: 0 | H83: 0 | I83: 0 | S83: =O83*M83 | T83: =O83*N83
A84: Pork | B84: 0 | C84: 0 | H84: 0 | I84: 0 | S84: =O84*M84 | T84: =O84*N84
A85: Total
A87: Cheese
A88: Winter cheese | B88: 0 | C88: 0 | H88: 0 | I88: 0 | S88: =O88*M88 | T88: =O88*N88
A89: Summer cheese | B89: 0 | C89: 0 | H89: 0 | I89: 0 | S89: =O89*M89 | T89: =O89*N89
A90: Total
A92: Butter
A93: Butter | B93: 0 | C93: 0 | H93: 0 | I93: 0 | S93: =O93*M93 | T93: =O93*N93
A94: Total
A96: Total Dairy Sales
A99: Cider | B99: 0 | C99: 0 | H99: 0 | I99: 0
A102: Additional Information (not necessarily useful)
A103: Utensils
A104: ploughs
A105: carts
A106: cart-ropes
A107: corn baskets
A108: seed-sacks
A109: seed basket
A110: locks for the doors
A111: lead vessel
A112: brass pots
A113: pans
... A128: brass posnets

Sheet raw data
A1: Heading | B1: Sentence | C1: Total in Pounds | D1: Pounds | E1: Shillings | F1: Pence | G1: Corn | H1: Total Quarters Except 1 | I1: Total Bushels Except 1 | J1: Total Corn Cross-Check | K1: Total Corn Manorial Account | L1: Corn Quantity Error | M1: Quarters 1 | N1: Bushels 1 | O1: shilling a quarter 1 | P1: pence a quarter 1 | Q1: shilling a quarter 2 | R1: pence a quarter 2 | S1: shilling a quarter 3 | T1: pence a quarter 3 | U1: shilling a quarter 4 | V1: pence a quarter 4 | W1: shilling a bushel 1 | X1: pence a bushel 1 | Y1: shilling a bushel 2 | Z1: pence a bushel 2 | AA1: shilling a bushel 3 | AB1: pence a bushel 3 | AC1: shilling a bushel 4 | AD1: pence a bushel 4
A2: Newtown | B2: The account of Walter Haukyn, reeve there, for the same year of the translation of the lord as before. | C2: 0 | D2: 0 | E2: 0 | F2: 0 | H2: 0 | I2: 0 | J2: 0 | K2: 0 | L2: 0 | M2: 0 | N2: 0
A3: Arrears | B3: The same answers for 2 shilling 5pence of arrears from the last account of the preceding year. | C3: 0.12 | D3: 0 | E3: 2 | F3: 5 | H3: 0 | I3: 0 | J3: 0 | K3: 0 | L3: 0 | M3: 0 | N3: 0
A4: Arrears | B4: Total, 2 shilling 5pence. | C4: 0.12 | D4: 0 | E4: 2 | F4: 5 | H4: 0 | I4: 0 | J4: 0 | K4: 0 | L4: 0 | M4: 0 | N4: 0
A5: Rents of assize | B5: And for £7 11 shilling for all the rents of assize there for the year and all paid at Michaelmas (29 September). | C5: 7.55 | D5: 7 | E5: 11 | F5: 0 | H5: 0 | I5: 0 | J5: 0 | K5: 0 | L5: 0 | M5: 0 | N5: 0
A6: Rents of assize | B6: Total, £7 11 shilling. | C6: 7.55 | D6: 7 | E6: 11 | F6: 0 | H6: 0 | I6: 0 | J6: 0 | K6: 0 | L6: 0 | M6: 0 | N6: 0
A7: Quittances and defaults of rent | B7: In quittance of rent of 1 reeve of the borough for the year 1 shilling. | C7: 0.05 | D7: 0 | E7: 1 | F7: 0 | H7: 0 | I7: 0 | J7: 0 | K7: 0 | L7: 0 | M7: 0 | N7: 0
A8: Quittances and defaults of rent | B8: quittance of 1 plot of land which Alice Basele held and which has now been pulled down by statute 2pence. | C8: 0.01 | D8: 0 | E8: 0 | F8: 2 | H8: 0 | I8: 0 | J8: 0 | K8: 0 | L8: 0 | M8: 0 | N8: 0
A9: Quittances and defaults of rent | B9: default of the land of Newman, 1 shilling for the year. | C9: 0.05 | D9: 0 | E9: 1 | F9: 0 | H9: 0 | I9: 0 | J9: 0 | K9: 0 | L9: 0 | M9: 0 | N9: 0
A10: Quittances and defaults of rent | B10: Total, 2 shilling 2pence. | C10: 0.11 | D10: 0 | E10: 2 | F10: 2 | H10: 0 | I10: 0 | J10: 0 | K10: 0 | L10: 0 | M10: 0 | N10: 0
A11: Total of rents remaining clear | B11: Total of rents remaining clear, £7 8 shilling 10pence. | C11: 7.44 | D11: 7 | E11: 8 | F11: 10 | H11: 0 | I11: 0 | J11: 0 | K11: 0 | L11: 0 | M11: 0 | N11: 0
A12: Perquisites of court | B12: And for 2 shilling from tithingpenny at the tourns of Martinmas and Hockday. | C12: 0.1 | D12: 0 | E12: 2 | F12: 0 | H12: 0 | I12: 0 | J12: 0 | K12: 0 | L12: 0 | M12: 0 | N12: 0
A13: Perquisites of court | B13: 6 shilling from the perquisites of the said toums. | C13: 0.3 | D13: 0 | E13: 6 | F13: 0 | H13: 0 | I13: 0 | J13: 0 | K13: 0 | L13: 0 | M13: 0 | N13: 0
... A19: And he owes | B19: And he owes, 2 shilling 5pence, and all is in the hands of the escheator.. | C19: 0.12 | D19: 0 | E19: 2 | F19: 5 | H19: 0 | I19: 0 | J19: 0 | K19: 0 | L19: 0 | M19: 0 | N19: 0

Sheet Receipts
A1: NEWTOWN RECEIPTS
A2: Heading | B2: £ | C2: s | D2: d | F2: Total in £ | G2: Error | H2: Notes | I2: Own notes
A3: Arrears | B3: 0 | C3: 2 | D3: 5 | F3: 0.12 | H3: The same answers for 2 shilling 5pence of arrears from the last account of the preceding year.
A4: Arrears | B4: 0 | C4: 2 | D4: 5 | F4: 0.12 | H4: Total, 2 shilling 5pence.
A5: Arrears total | F5: 0.12 | G5: 0 | H5: Total
A7: Rents of assize | B7: 7 | C7: 11 | D7: 0 | F7: 7.55 | H7: And for £7 11 shilling for all the rents of assize there for the year and all paid at Michaelmas (29 September).
A8: Rents of assize | B8: 7 | C8: 11 | D8: 0 | F8: 7.55 | H8: Total, £7 11 shilling.
A9: Rents of assize total | F9: 7.55 | G9: 0 | H9: Total
A11: Total of rents remaining clear | B11: 7 | C11: 8 | D11: 10 | F11: 7.44 | H11: Total of rents remaining clear, £7 8 shilling 10pence.
A12: Total of rents remaining clear total | F12: 7.44 | G12: 0 | H12: Total
A14: Perquisites of court | B14: 0 | C14: 2 | D14: 0 | F14: 0.1 | H14: And for 2 shilling from tithingpenny at the tourns of Martinmas and Hockday.
A15: Perquisites of court | B15: 0 | C15: 6 | D15: 0 | F15: 0.3 | H15: 6 shilling from the perquisites of the said toums.
A16: Perquisites of court | B16: 0 | C16: 3 | D16: 6 | F16: 0.17 | H16: 3 shilling 6pence from the chattels of a fugitive felon.
A17: Perquisites of court total | B17: 0 | C17: 11 | D17: 6 | F17: 0.58 | G17: 0.41 | H17: Total, 11 shilling 6pence.
A18: Total of all receipts recorded in accounts (calculated here) | F18: =SUMIF(A1:A17,"* total",F1:F17)-SUMIF(A1:A17,"Arrears total",F1:F17)
A19: Total of all receipts (calculated here) incl arrears | F19: =F18+SUMIF(A1:A17,"Arrears total",F1:F17)

Sheet Overview

Sheet Issues of the Grange

Sheet Issues of the Mills

Sheet Stock

Sheet Prices

Sheet Labour Rents

Sheet not needed

Sheet Expenses
A1: NEWTOWN EXPENSES
A2: Heading | B2: £ | C2: s | D2: d | F2: Total in £ | G2: Error | H2: Notes
A4: Cash deliveries | B4: 8 | C4: 0 | D4: 4 | F4: 8.02
A5: Cash deliveries | B5: 8 | C5: 0 | D5: 4 | F5: 8.02
A6: Cash deliveries total | F6: 8.02 | G6: 0
A8: And he owes | B8: 0 | C8: 2 | D8: 5 | F8: 0.12
A9: And he owes total | F9: 0.12 | G9: 0
