Workbook

Sheet Alverstoke Overview - Completed
A1: ALVERSTOKE OVERVIEW - COMPLETED | B1: Total in £ | C1: Error | D1: Note
A2: CASH ACCOUNT
A3: RECEIPTS
A4: Arrears total | B4: 2.13
A5: Rents of assize total | B5: 53.564583
A6: Quittances total
A7: Defaults of rent total
A8: Defaults of rent through the pestilence total
A9: Cotlands defaults total
A10: Cotlands total
A11: Total of quittances and defaults of rent total
A12: Total of rents remaining clear total
A13: Farms total
A14: Annual recognizances total
A15: Issues of the Manor total
A16: Issues of the tenements in the lord's hands total
A17: Sale of labour services total
... A22: Farm of the demesne land total
A23: Total of all receipts (calculated here) | B23: =SUM(B5:B22)
A24: Total of all receipts (calculated here) incl arrears | B24: =SUM(B4:B22)
A25: Total recorded in the accounts excl. arrears | B25: 59.65 | C25: =B23-B25
A26: Total recorded in the accounts incl. arrears | B26: =B25+B4
A29: EXPENSES
A30: Cost of ploughs total
A31: Purchase of corn total
A32: Cost of carts and wagons total
A33: Cost of dairy total
A34: Purchase of stock total
A35: Sheepcote total
A36: Cost of buildings total
A37: Threshing total
A38: Barley expenses
A39: Expenses of the harvest total
A40: Necessary expenses
A41: Wages of the bailiff
A42: Steward's expenses total | B42: 0.46
A43: Annual fees
A44: Total of all expenses per account
A45: Total of all expenses (calculated here) | B45: 0.46
A46: Total fixed investment | B46: 0
A47: Total Demesne fixed investment | B47: 0
A49: Owed by the reeve | B49: =B23-B45
A50: From accounts
A52: Allowances
A53: Cash deliveries | B53: 52.75
A54: Sum of the above | B54: =SUM(B52:B53)
A55: Total of all allowances and cash deliveries in accounts
A57: Net amount owed | B57: =B50-B54
A58: Net amount owed in accounts
A60: GRANGE ACCOUNT | B60: Total Production | D60: Value of total gross production in £ | E60: Value of total net production in £
A61: Grange | B61: qrs | C61: bus
A62: Wheat
A63: Rye
A64: Dredge
A65: Curall
A66: Barley
A67: Oats
A68: Beans
A69: Peas
A70: Vetches
A71: Total value of gross production (sum of the above)
A72: Total value of net production
A73: Value of sales
A75: MILL ACCOUNT | B75: Total Production | D75: Total in £
A76: Issues of the mill | B76: qrs | C76: bus
A77: Wheat
A78: Oatmeal
A79: 1st grade malt
A80: 2nd grade malt
A81: Maslin
A82: Total value of production (sum of the above)
A83: Value of sales
A85: STOCK ACCOUNT
A86: Livestock | B86: Begin stock | C86: End stock | D86: Stockbuilding | F86: Value of stock in £ | G86: Value of stockbuilding
A87: Cart-horses | D87: =C87-B87 | F87: ='Stock'!K5*'Stock'!O5 | G87: =D87*'Stock'!O5
A88: Mares | D88: =C88-B88 | F88: ='Stock'!K6*'Stock'!O6 | G88: =D88*'Stock'!O6
A89: Plough horses | D89: =C89-B89 | F89: ='Stock'!K7*'Stock'!O7 | G89: =D89*'Stock'!O7
A90: Colts (2 years) | D90: =C90-B90 | F90: ='Stock'!K8*'Stock'!O8 | G90: =D90*'Stock'!O8
A91: Colts (2 years) | D91: =C91-B91 | F91: ='Stock'!K9*'Stock'!O9 | G91: =D91*'Stock'!O9
A92: Colts (1 year) | D92: =C92-B92 | F92: ='Stock'!K10*'Stock'!O10 | G92: =D92*'Stock'!O10
A93: Foals | D93: =C93-B93 | F93: ='Stock'!K11*'Stock'!O11 | G93: =D93*'Stock'!O11
A94: Oxen | D94: =C94-B94 | F94: ='Stock'!K12*'Stock'!O12 | G94: =D94*'Stock'!O12
A95: Bulls | D95: =C95-B95 | F95: ='Stock'!K13*'Stock'!O13 | G95: =D95*'Stock'!O13
A96: Cows | D96: =C96-B96 | F96: ='Stock'!K14*'Stock'!O14 | G96: =D96*'Stock'!O14
A97: Steers | D97: =C97-B97 | F97: ='Stock'!K15*'Stock'!O15 | G97: =D97*'Stock'!O15
A98: Bullocks | D98: =C98-B98 | F98: ='Stock'!K16*'Stock'!O16 | G98: =D98*'Stock'!O16
... A112: Peacocks | D112: =C112-B112 | F112: ='Stock'!K30*'Stock'!O30 | G112: =D112*'Stock'!O30
A113: Total value of stock (sum of the above) | F113: =SUM(F87:F112) | G113: =SUM(G87:G112)
A114: Total value of production | F114: =SUM('Stock'!T5:T30)
A115: Value of sales | F115: =SUM('Stock'!R5:R30)
A117: Wool | B117: Begin stock | C117: End stock | D117: Stockbuilding | F117: Value of stock in £
A118: Fleeces
A119: Coarse wool
A120: Lamb's wool
A121: Wool locks
A122: Wool sold at shearing
A123: Total value of production (sum of the above)
A124: Value of sales
A126: Hides | B126: Begin stock | C126: End stock | D126: Stockbuilding | F126: Value of stock in £
A127: Ox hides
...

Sheet Prices
A1: Meat & Dairy Prices
C2: 1301 | D2: 1302 | E2: Average
A3: Beef | B3: £ per lb | C3: 0.0033351854 | D3: 0.0032608538 | E3: =AVERAGE(C3:D3)
A4: Mutton | B4: £ per lb | C4: 0.0036593977 | D4: 0.0037125513 | E4: =AVERAGE(C4:D4)
A5: Pork | B5: £ per lb | C5: 0.0038431326 | D5: 0.0037574803 | E5: =AVERAGE(C5:D5)
A6: Cheese | B6: £ per lb | C6: 0.0055768754 | D6: 0.0056654898 | E6: =AVERAGE(C6:D6)
A7: Butter | B7: £ per lb | C7: 0.0036626221 | D7: 0.0035935077 | E7: =AVERAGE(C7:D7)
A8: Milk | B8: £ per gallon | C8: 0.0055768754 | D8: 0.0056654898 | E8: =AVERAGE(C8:D8)

Sheet Labour Rents

Sheet Overview
A1: ALVERSTOKE | B1: Total in £ | C1: Error | D1: Note
A2: CASH ACCOUNT
A3: RECEIPTS
A4: Arrears total | B4: =Receipts!F5
A5: Rents of assize total | B5: =Receipts!F14
A6: Recognizance total | B6: =Receipts!F22
A7: Reliefs total | B7: =Receipts!F33
A8: Quittances total
A9: Defaults of rent total
A10: Defaults of rent through the pestilence total
A11: Cotlands defaults total
A12: Cotlands total
A13: Total of quittances and defaults of rent total
A14: Total of rents remaining clear total
A15: Farms total | B15: =Receipts!F18
A16: Annual recognizances total
A17: Issues of the Manor total
A18: Issues of the tenements in the lord's hands total
A19: Sale of labour services total
A20: Sale of corn total
A21: Entry and marriage fines total
A22: Pleas & perquisites total | B22: =Receipts!F117
A23: Forfeited chattels total
A24: Farm of the demesne land total
A25: Total of all receipts (calculated here) | B25: =Receipts!F120
A26: Total of all receipts (calculated here) incl arrears
A27: Total recorded in the accounts excl. arrears | B27: =Receipts!F119 | C27: =B27-B25
A28: Total recorded in the accounts incl. arrears | B28: =Receipts!F121
A31: EXPENSES
A32: Cost of ploughs total
A33: Purchase of corn total
A34: Cost of carts and wagons total
A35: Cost of dairy total
A36: Purchase of stock total
A37: Sheepcote total
A38: Cost of buildings total
A39: Threshing total
A40: Barley expenses
A41: Expenses of the harvest total
A42: Necessary expenses
A43: Wages of the bailiff
A44: Steward's expenses total | B44: =Expenses!F4
A45: Annual fees
A46: Total of all expenses per account
A47: Total of all expenses (calculated here) | B47: =Expenses!F15
A48: Total fixed investment | B48: 0
A49: Total Demesne fixed investment | B49: 0
A51: Owed by the reeve
A52: From accounts
A54: Allowances
A55: Cash deliveries
A56: Sum of the above
A57: Total of all allowances and cash deliveries in accounts
A59: Net amount owed
A60: Net amount owed in accounts
A62: GRANGE ACCOUNT | B62: Total Production
A63: Grange | B63: qrs | E63: Value of total gross production in £ | F63: Value of total net production in £
A64: Wheat | G64: nothing
A65: Rye
A66: Dredge
A67: Curall
A68: Barley
A69: Oats
A70: Beans
A71: Peas
A72: Vetches
A73: Total value of gross production (sum of the above)
A74: Total value of net production
A75: Value of sales
A77: MILL ACCOUNT
A78: Issues of the mill | G78: nothing
A79: Wheat
A80: Oatmeal
A81: 1st grade malt
A82: 2nd grade malt
A83: Maslin
A84: Total value of production (sum of the above)
A85: Value of sales
A87: STOCK ACCOUNT
A88: Livestock | B88: Sales value in £
A89: Cart-horses | G89: nothing
A90: Mares
A91: Plough horses
A92: Colts (2 years)
A93: Colts (2 years)
A94: Colts (1 year)
A95: Foals
A96: Oxen
A97: Bulls
A98: Cows
A99: Steers
A100: Bullocks
A101: Yearlings
... A117: Value of sales
A119: Wool | B119: Value of production at sales prices £
A120: Fleeces
A121: Coarse wool
A122: Lamb's wool
A123: Wool locks
A124: Wool sold at shearing
...

Sheet Receipts
A1: ALVERSTOKE RECEIPTS
A2: Heading | B2: £ | C2: s | D2: d | F2: Total in £ | G2: Error | H2: Sentence
A3: Arrears | B3: 2 | C3: 2 | D3: 7 | F3: 2.13 | H3: John de Forton', bailiff, renders account for £2 2 shilling 7pence of arrears from the previous year.
A4: Arrears | B4: 0 | C4: 0 | D4: 0 | F4: 0 | H4: All delivered to Geoffrey, treasurer of Wolvesey, by 1 tally, and he is quit.
A5: Arrears | F5: 2.13 | G5: =F5-F3 | H5: Total
A7: Rents | B7: 13 | C7: 0 | D7: 0 | F7: 13 | H7: The same renders account for £13 for rents of assize at All Saints (1 November).
A8: Rents | B8: 13 | C8: 0 | D8: 0 | F8: 13 | H8: £13 at the Purification (2 February).
A9: Rents | B9: 13 | C9: 0 | D9: 0 | F9: 13 | H9: £13 at the Invention of the Cross (3 May).
A10: Rents | B10: 14 | C10: 0 | D10: 7.5 | F10: =B10+C10/20+D10/240 | H10: £14 7.5d at Michaelmas (29 September).
A11: Rents | B11: 0 | C11: 10 | D11: 0 | F11: =B11+C11/20+D11/240 | H11: 10 shilling from the rent of Robert de Chark at the same feast.
A12: Rents | B12: 0 | C12: 0 | D12: 8 | F12: =B12+C12/20+D12/240 | H12: 8pence from John Aze and Alexander Cred' for 1 marsh and 2 water-channels at the same feast.
A13: Rents | B13: 53 | C13: 11 | D13: 3.5 | F13: =B13+C13/20+D13/240 | H13: Total, £53 11 shilling 3.5pence
A14: Rents | F14: =SUM(F7:F12) | G14: =F14-F13 | H14: Total
A16: Farm of the mill | B16: 2 | C16: 10 | D16: 0 | F16: 2.5 | H16: The same renders account for £2 10 shilling for the farm of the mill of Forton'.
A17: Farm of the mill | B17: 2 | C17: 10 | D17: 0 | F17: 2.5 | H17: Total, £2 10 shilling
A18: Farm of the mill | F18: 2.5 | G18: 0 | H18: Total
A20: Recognizance | B20: 0 | C20: 0 | D20: 1 | F20: 0 | H20: The same renders account for 1pence for the annual recognizance of Adam Guldebrigg'.
A21: Recognizance | B21: 0 | C21: 0 | D21: 1 | F21: 0 | H21: Total, 1pence
A22: Recognizance | F22: 0 | G22: 0 | H22: Total
A24: Reliefs | B24: 0 | C24: 13 | D24: 3 | F24: 0.66 | H24: The same renders account for 13 shilling 3pence from John le Pope for relief for the lands and tenements which belonged to William Pope his father.
A25: Reliefs | B25: 0 | C25: 1 | D25: 0 | F25: 0.05 | H25: 1 shilling from Joan le Pope for relief for the lands which belonged to Joan her mother.
A26: Reliefs | B26: 0 | C26: 13 | D26: 6 | F26: 0.68 | H26: 13 shilling 6pence from Bartholomew Hendel for relief for the lands and tenements which belonged to William Hendel his father.
A27: Reliefs | B27: 0 | C27: 0 | D27: 8 | F27: 0.03 | H27: 8pence from William Molendinarius for relief for the lands and tenements which belonged to John Molendinarius his brother.
A28: Reliefs | B28: 0 | C28: 0 | D28: 2 | F28: 0.01 | H28: 2pence from William Arnold for relief for 1 half-acre (aulve) of land by surrender of John le Bege.
A29: Reliefs | B29: 0 | C29: 0 | D29: 2 | F29: 0.01 | H29: 2pence from Richard Arnold for relief for 1 half-acre of land by surrender of Thomas Bild'.
A30: Reliefs | B30: 0 | C30: 0 | D30: 1 | F30: 0 | H30: 1pence from Richard Piris for relief for the land which belonged to Peter Randoldf his father.
A31: Reliefs | B31: 0 | C31: 0 | D31: 4 | F31: 0.02 | H31: 4pence from Agnes and Alice Bild' for relief for the land which belonged to Adam Bild' their father.
A32: Reliefs | B32: 1 | C32: 9 | D32: 2 | F32: 1.46 | H32: Total, £1 9 shilling 2pence
A33: Reliefs | F33: 1.46 | G33: 0 | H33: Total
A35: Perquisites | B35: 0 | C35: 0 | D35: 6 | F35: 0.03 | H35: The same renders account for 6pence from Sarah de Forton' for breaking the assize of ale.
A36: Perquisites | B36: 0 | C36: 0 | D36: 6 | F36: 0.03 | H36: 6pence from William Page for the same.
A37: Perquisites | B37: 0 | C37: 0 | D37: 3 | F37: 0.01 | H37: 3pence from John Spark' for the same.
A38: Perquisites | B38: 0 | C38: 0 | D38: 6 | F38: 0.03 | H38: 6pence from John Aubr' for the same.
A39: Perquisites | B39: 0 | C39: 0 | D39: 3 | F39: 0.01 | H39: 3pence from Robert Clericus for the same.
A40: Perquisites | B40: 0 | C40: 0 | D40: 3 | F40: 0.01 | H40: 3pence from John Walt' for the same.
A41: Perquisites | B41: 0 | C41: 0 | D41: 6 | F41: 0.03 | H41: 6pence from the relict of Edward for the same.
A42: Perquisites | B42: 0 | C42: 0 | D42: 6 | F42: 0.03 | H42: 6pence from John Fontayn for the same.
A43: Perquisites | B43: 0 | C43: 0 | D43: 6 | F43: 0.03 | H43: 6pence from Henry Bissop for the same.
A44: Perquisites | B44: 0 | C44: 1 | D44: 0 | F44: 0.05 | H44: 1 shilling from William Lote for the same.
A45: Perquisites | B45: 0 | C45: 0 | D45: 6 | F45: 0.03 | H45: 6pence from William Unwyn' for the same.
A46: Perquisites | B46: 0 | C46: 0 | D46: 6 | F46: 0.03 | H46: 6pence from John Bege for the same.
... A116: Perquisites | B116: 2 | C116: 2 | D116: 6 | F116: 2.12 | H116: Total, £2 2 shilling 6pence
A117: Perquisites | F117: 2.13 | G117: 0.01 | H117: Total
A119: Total of all receipts recorded in accounts | B119: 59 | C119: 13 | D119: 0.5 | F119: 59.65 | H119: Total of all receipts, £59 13 shilling 0.5pence
A120: Total cross-check without arrears | F120: =F117+F33+F18+F14 | G120: =F120-F119
A121: Total cross-check with arrears | F121: =F120+F5

Sheet Expenses
A1: ALVERSTOKE EXPENSES
A2: Heading | B2: Pounds | C2: Shillings | D2: Pence | F2: Total in Pounds | G2: Error | H2: Sentence
A3: Expenses of the steward | B3: 0 | C3: 9 | D3: 1.25 | F3: 0.46 | H3: In expenses of the steward for the tourns of Martinmas and Hockday by 2 tallies, 9 shilling 1.25pence
A4: Expenses of the steward | F4: 0.46 | G4: 0 | H4: Total
A6: and he owes | B6: 59 | C6: 3 | D6: 5.25 | F6: 59.17 | H6: And he owes, £59 3 shilling 5.25pence
A8: cash deliveries | B8: 52 | C8: 15 | D8: 0 | F8: 52.75 | H8: Delivered to Sir Geoffrey, treasurer of Wolvesey, by 1 tally, £52 15 shilling
A10: And thus he owes clear | B10: 6 | C10: 8 | D10: 5.25 | F10: 6.42 | H10: And thus he owes clear, £6 8 shilling 5.25pence
A11: And thus he owes clear | F11: 6.42 | G11: 0 | H11: Total
A14: Total of all expenses per account
A15: Total of all expenses (calculated here) | F15: =F4
A16: Total fixed investment | F16: 0
A17: Total Demesne fixed investment | F17: 0

Sheet Issues of the Grange
A1: no grange

Sheet Issues of the Mills
A1: no mills

Sheet Stock
A1: no stock

Sheet raw data
A1: Heading | B1: Sentence | C1: Total in Pounds | D1: Pounds | E1: Shillings | F1: Pence | G1: Corn | H1: Total Quarters Except 1 | I1: Total Bushels Except 1 | J1: Total Corn Cross-Check | K1: Total Corn Manorial Account | L1: Corn Quantity Error | M1: Quarters 1 | N1: Bushels 1 | O1: shilling a quarter 1 | P1: pence a quarter 1 | Q1: shilling a quarter 2 | R1: pence a quarter 2 | S1: shilling a quarter 3 | T1: pence a quarter 3 | U1: shilling a quarter 4 | V1: pence a quarter 4 | W1: shilling a bushel 1 | X1: pence a bushel 1 | Y1: shilling a bushel 2 | Z1: pence a bushel 2 | AA1: shilling a bushel 3 | AB1: pence a bushel 3 | AC1: shilling a bushel 4 | AD1: pence a bushel 4
A2: Arrears | B2: John de Forton', bailiff, renders account for £2 2 shilling 7pence of arrears from the previous year. | C2: 2.13 | D2: 2 | E2: 2 | F2: 7 | H2: 0 | I2: 0 | J2: 0 | K2: 0 | L2: 0 | M2: 0 | N2: 0
A3: Arrears | B3: All delivered to Geoffrey, treasurer of Wolvesey, by 1 tally, and he is quit. | C3: 0 | D3: 0 | E3: 0 | F3: 0 | H3: 0 | I3: 0 | J3: 0 | K3: 0 | L3: 0 | M3: 0 | N3: 0
A4: Rents | B4: The same renders account for £13 for rents of assize at All Saints (1 November). | C4: 13 | D4: 13 | E4: 0 | F4: 0 | H4: 0 | I4: 0 | J4: 0 | K4: 0 | L4: 0 | M4: 0 | N4: 0
A5: Rents | B5: £13 at the Purification (2 February). | C5: 13 | D5: 13 | E5: 0 | F5: 0 | H5: 0 | I5: 0 | J5: 0 | K5: 0 | L5: 0 | M5: 0 | N5: 0
A6: Rents | B6: £13 at the Invention of the Cross (3 May). | C6: 13 | D6: 13 | E6: 0 | F6: 0 | H6: 0 | I6: 0 | J6: 0 | K6: 0 | L6: 0 | M6: 0 | N6: 0
A7: Rents | B7: £14 7.5d at Michaelmas (29 September). | C7: 14 | D7: 14 | E7: 0 | F7: 0 | H7: 0 | I7: 0 | J7: 0 | K7: 0 | L7: 0 | M7: 0 | N7: 0
A8: Rents | B8: 10 shilling from the rent of Robert de Chark at the same feast. | C8: 0.5 | D8: 0 | E8: 10 | F8: 0 | H8: 0 | I8: 0 | J8: 0 | K8: 0 | L8: 0 | M8: 0 | N8: 0
A9: Rents | B9: 8pence from John Aze and Alexander Cred' for 1 marsh and 2 water-channels at the same feast. | C9: 0.03 | D9: 0 | E9: 0 | F9: 8 | H9: 0 | I9: 0 | J9: 0 | K9: 0 | L9: 0 | M9: 0 | N9: 0
A10: Rents | B10: Total, £53 11 shilling 3.5pence | C10: 53.56 | D10: 53 | E10: 11 | F10: 3.5 | H10: 0 | I10: 0 | J10: 0 | K10: 0 | L10: 0 | M10: 0 | N10: 0
A11: Farm of the mill | B11: The same renders account for £2 10 shilling for the farm of the mill of Forton'. | C11: 2.5 | D11: 2 | E11: 10 | F11: 0 | H11: 0 | I11: 0 | J11: 0 | K11: 0 | L11: 0 | M11: 0 | N11: 0
A12: Farm of the mill | B12: Total, £2 10 shilling | C12: 2.5 | D12: 2 | E12: 10 | F12: 0 | H12: 0 | I12: 0 | J12: 0 | K12: 0 | L12: 0 | M12: 0 | N12: 0
A13: Recognizance | B13: The same renders account for 1pence for the annual recognizance of Adam Guldebrigg'. | C13: 0 | D13: 0 | E13: 0 | F13: 1 | H13: 0 | I13: 0 | J13: 0 | K13: 0 | L13: 0 | M13: 0 | N13: 0
... A111: And thus he owes clear | B111: And thus he owes clear, £6 8 shilling 5.25pence | C111: 6.42 | D111: 6 | E111: 8 | F111: 5.25 | H111: 0 | I111: 0 | J111: 0 | K111: 0 | L111: 0 | M111: 0 | N111: 0
