Workbook

Sheet BishopsFonthill 1301 Overview -
A1: BISHOPSFONTHILL 1301 OVERVIEW - COMPLETED | B1: Total in £ | C1: Error | D1: Note
A2: CASH ACCOUNT
A3: RECEIPTS
A4: Arrears total
A5: Rents of assize total
A6: Quittances total
A7: Defaults of rent total
A8: Defaults of rent through the pestilence total
A9: Cotlands defaults total
A10: Cotlands total
A11: Total of quittances and defaults of rent total
A12: Total of rents remaining clear total
A13: Farms total
... A22: Farm of the demesne land total
A23: Total of all receipts (calculated here) | B23: =SUM(B5:B22) -> 0
A24: Total of all receipts (calculated here) incl arrears | B24: =SUM(B4:B22) -> 0
A25: Total recorded in the accounts excl. arrears | C25: =B23-B25 -> 0
A26: Total recorded in the accounts incl. arrears | B26: =B25+B4 -> 0
A29: EXPENSES
A30: Cost of ploughs total
A31: Purchase of corn total
A32: Cost of carts and wagons total
A33: Cost of dairy total
A34: Purchase of stock total
A35: Sheepcote total
A36: Cost of buildings total
A37: Threshing total
A38: Barley expenses
A39: Expenses of the harvest total
A40: Necessary expenses
... A47: Total Demesne fixed investment
A49: Owed by the reeve | B49: =B23-B45 -> 0
A50: From accounts | B50: 6.8208333
A52: Allowances
A53: Cash deliveries
A54: Sum of the above | B54: =SUM(B52:B53) -> 0
A55: Total of all allowances and cash deliveries in accounts
A57: Net amount owed | B57: =B50-B54 -> 6.8208333
A58: Net amount owed in accounts
A60: GRANGE ACCOUNT | B60: Total Production | D60: Value of total gross production in £ | E60: Value of total net production in £
A61: Grange | B61: qrs | C61: bus
A62: Wheat | B62: 81
A63: Rye
A64: Dredge
A65: Curall | B65: 1
A66: Barley | B66: 64
A67: Oats | B67: 59
A68: Beans
A69: Peas
A70: Vetches
A71: Total value of gross production (sum of the above)
A72: Total value of net production
A73: Value of sales
A75: MILL ACCOUNT | B75: Total Production | D75: Total in £
A76: Issues of the mill | B76: qrs | C76: bus
A77: Wheat
A78: Oatmeal
A79: 1st grade malt
A80: 2nd grade malt
A81: Maslin
A82: Total value of production (sum of the above)
A83: Value of sales
A85: STOCK ACCOUNT
A86: Livestock | B86: Begin stock | C86: End stock | D86: Stockbuilding | F86: Value of stock in £ | G86: Value of stockbuilding
A87: Cart-horses | D87: =C87-B87 -> 0 | F87: =Stock!K5*Stock!O5 -> 0 | G87: =D87*Stock!O5 -> 0
A88: Mares | C88: 0 | D88: =C88-B88 -> 0 | F88: =Stock!K5*Stock!O5 -> 0 | G88: =D88*Stock!O5 -> 0
A89: Plough horses | B89: 2 | C89: 2 | D89: 0 | F89: =Stock!K6*Stock!O6 -> 0 | G89: =D89*Stock!O6 -> 0
A90: Colts (2 years) | C90: 0 | D90: =C90-B90 -> 0 | F90: =Stock!K8*Stock!O8 -> 0 | G90: =D90*Stock!O8 -> 0
A91: Colts (2 years) | C91: 0 | D91: =C91-B91 -> 0 | F91: =Stock!K8*Stock!O8 -> 0 | G91: =D91*Stock!O8 -> 0
A92: Colts (1 year) | C92: 0 | D92: =C92-B92 -> 0 | F92: =Stock!K9*Stock!O9 -> 0 | G92: =D92*Stock!O9 -> 0
A93: Foals | C93: 0 | D93: =C93-B93 -> 0 | F93: =Stock!K10*Stock!O10 -> 0 | G93: =D93*Stock!O10 -> 0
A94: Oxen | B94: 24 | C94: 28 | D94: 4 | F94: =Stock!K11*Stock!O11 -> 0 | G94: =D94*Stock!O11 -> 0
A95: Bulls | C95: 0 | D95: =C95-B95 -> 0 | F95: =Stock!K12*Stock!O12 -> 0 | G95: =D95*Stock!O12 -> 0
A96: Cows | C96: 0 | D96: =C96-B96 -> 0 | F96: =Stock!K13*Stock!O13 -> 0 | G96: =D96*Stock!O13 -> 0
A97: Steers | C97: 0 | D97: =C97-B97 -> 0 | F97: =Stock!K14*Stock!O14 -> 0 | G97: =D97*Stock!O14 -> 0
A98: Bullocks | C98: 0 | D98: =C98-B98 -> 0 | F98: =Stock!K15*Stock!O15 -> 0 | G98: =D98*Stock!O15 -> 0
A99: Yearlings | C99: 0 | D99: =C99-B99 -> 0 | F99: =Stock!K16*Stock!O16 -> 0 | G99: =D99*Stock!O16 -> 0
A100: Calves | C100: 0 | D100: =C100-B100 -> 0 | F100: =Stock!K17*Stock!O17 -> 0 | G100: =D100*Stock!O17 -> 0
A101: Wethers | B101: 323 | C101: 285 | D101: -38 | F101: =Stock!K18*Stock!O18 -> 0 | G101: =D101*Stock!O18 -> 0
A102: Rams | C102: 0 | D102: =C102-B102 -> 0 | F102: =Stock!K19*Stock!O19 -> 0 | G102: =D102*Stock!O19 -> 0
A103: Ewes | C103: 0 | D103: =C103-B103 -> 0 | F103: =Stock!K20*Stock!O20 -> 0 | G103: =D103*Stock!O20 -> 0
A104: Hoggs | C104: 0 | D104: =C104-B104 -> 0 | F104: =Stock!K21*Stock!O21 -> 0 | G104: =D104*Stock!O21 -> 0
A105: Lambs | C105: 10 | D105: =C105-B105 -> 10 | F105: =Stock!K22*Stock!O22 -> 0 | G105: =D105*Stock!O22 -> 0
A106: Boars | C106: 0 | D106: =C106-B106 -> 0 | F106: =Stock!K23*Stock!O23 -> 0 | G106: =D106*Stock!O23 -> 0
A107: Sows | C107: 0 | D107: =C107-B107 -> 0 | F107: =Stock!K24*Stock!O24 -> 0 | G107: =D107*Stock!O24 -> 0
A108: Pigs | B108: 40 | C108: 26 | D108: -14 | F108: =Stock!K25*Stock!O25 -> 0 | G108: =D108*Stock!O25 -> 0
A109: Hoggets | B109: 28 | C109: 0 | D109: -28 | F109: =Stock!K26*Stock!O26 -> 0 | G109: =D109*Stock!O26 -> 0
A110: Piglets | C110: 13 | D110: =C110-B110 -> 13 | F110: =Stock!K27*Stock!O27 -> 0 | G110: =D110*Stock!O27 -> 0
A111: Swans | C111: 0 | D111: =C111-B111 -> 0 | F111: =Stock!K28*Stock!O28 -> 0 | G111: =D111*Stock!O28 -> 0
A112: Peacocks | C112: 0 | D112: =C112-B112 -> 0 | F112: =Stock!K29*Stock!O29 -> 0 | G112: =D112*Stock!O29 -> 0
A113: Total value of stock (sum of the above) | F113: =SUM(F87:F112) -> 0 | G113: =SUM(G87:G112) -> 0
A114: Total value of production | F114: =SUM(Stock!T5:T30) -> 0
A115: Value of sales | F115: =SUM(Stock!R5:R30) -> 7.5787879
A117: Wool | B117: Begin stock | C117: End stock | D117: Stockbuilding | F117: Value of stock in £
A118: Fleeces
A119: Coarse wool | C119: 0 | F119: =C119*Stock!O35 -> 0
A120: Lamb's wool | C120: 0 | F120: =C120*Stock!O36 -> 0
A121: Wool locks | C121: 0 | F121: =C121*Stock!O37 -> 0
A122: Wool sold at shearing | C122: 0 | F122: =C122*Stock!O38 -> 0
A123: Total value of production (sum of the above)
...

Sheet Issues of the Mills
A1: No mill account for Adderbury

Sheet raw data
A1: Heading | B1: Sentence | C1: Total in Pounds | D1: Pounds | E1: Shillings | F1: Pence | G1: Corn | H1: Total Quarters Except 1 | I1: Total Bushels Except 1 | J1: Total Corn Cross-Check | K1: Total Corn Manorial Account | L1: Corn Quantity Error | M1: Quarters 1 | N1: Bushels 1 | O1: shilling a quarter 1 | P1: pence a quarter 1 | Q1: shilling a quarter 2 | R1: pence a quarter 2 | S1: shilling a quarter 3 | T1: pence a quarter 3 | U1: shilling a quarter 4 | V1: pence a quarter 4 | W1: shilling a bushel 1 | X1: pence a bushel 1 | Y1: shilling a bushel 2 | Z1: pence a bushel 2 | AA1: shilling a bushel 3 | AB1: pence a bushel 3 | AC1: shilling a bushel 4 | AD1: pence a bushel 4
A2: Adderbury | B2: The account2 of William Jakeman, reeve there, for the sixth year of the translation of Henry Beaufort', lord bishop of Winchester, and the eleventh year of the reign of King Henry the Fourth. | C2: 0 | D2: 0 | E2: 0 | F2: 0 | H2: 0 | I2: 0 | J2: 0 | K2: 0 | L2: 0 | M2: 0 | N2: 0
A3: Arrears | B3: None. | C3: 0 | D3: 0 | E3: 0 | F3: 0 | H3: 0 | I3: 0 | J3: 0 | K3: 0 | L3: 0 | M3: 0 | N3: 0
A4: Rents of assize | B4: And for £6 9 shilling 6.25pence for all rents of assize at St Thomas the Apostle (21 December). | C4: 6.48 | D4: 6 | E4: 9 | F4: 6.25 | H4: 0 | I4: 0 | J4: 0 | K4: 0 | L4: 0 | M4: 0 | N4: 0
A5: Rents of assize | B5: £6 9 shilling 8.5pence at Easter (23 March). | C5: 6.49 | D5: 6 | E5: 9 | F5: 8.5 | H5: 0 | I5: 0 | J5: 0 | K5: 0 | L5: 0 | M5: 0 | N5: 0
A6: Rents of assize | B6: £6 9 shilling 6.25pence at the Nativity of St John the Baptist (24 June). | C6: 6.48 | D6: 6 | E6: 9 | F6: 6.25 | H6: 0 | I6: 0 | J6: 0 | K6: 0 | L6: 0 | M6: 0 | N6: 0
A7: Rents of assize | B7: £6 10 shilling 1.5pence at Michaelmas (29 September). | C7: 6.51 | D7: 6 | E7: 10 | F7: 1.5 | H7: 0 | I7: 0 | J7: 0 | K7: 0 | L7: 0 | M7: 0 | N7: 0
A8: Rents of assize | B8: Total, £25 18 shilling 10.5pence. | C8: 25.94 | D8: 25 | E8: 18 | F8: 10.5 | H8: 0 | I8: 0 | J8: 0 | K8: 0 | L8: 0 | M8: 0 | N8: 0
A9: Quittances of rent | B9: In quittance of rent of 1 reeve for the year 5 shilling. | C9: 0.25 | D9: 0 | E9: 5 | F9: 0 | H9: 0 | I9: 0 | J9: 0 | K9: 0 | L9: 0 | M9: 0 | N9: 0
A10: Quittances of rent | B10: nothing this year of the 4 shilling for 1 smith forging the ironwork of 2 ploughs for the year. | C10: 0.2 | D10: 0 | E10: 4 | F10: 0 | H10: 0 | I10: 0 | J10: 0 | K10: 0 | L10: 0 | M10: 0 | N10: 0
A11: Quittances of rent | B11: nothing this year of the 4 shilling for 1 shepherd keeping the lord's wethers for the year. | C11: 0.2 | D11: 0 | E11: 4 | F11: 0 | H11: 0 | I11: 0 | J11: 0 | K11: 0 | L11: 0 | M11: 0 | N11: 0
A12: Quittances of rent | B12: nothing this year of the 4 shilling for 1 swineherd for the year. | C12: 0.2 | D12: 0 | E12: 4 | F12: 0 | H12: 0 | I12: 0 | J12: 0 | K12: 0 | L12: 0 | M12: 0 | N12: 0
A13: Quittances of rent | B13: nothing this year of the 4 shilling for 1 cowherd for the year. | C13: 0.2 | D13: 0 | E13: 4 | F13: 0 | H13: 0 | I13: 0 | J13: 0 | K13: 0 | L13: 0 | M13: 0 | N13: 0
... A149: Cost of buildings | B149: board-nails and clout-nails bought for the same 1 shilling 4pence. | C149: 0.07 | D149: 0 | E149: 1 | F149: 4 | H149: 0 | I149: 0 | J149: 0 | K149: 0 | L149: 0 | M149: 0 | N149: 0
A150: Cost of buildings | B150: 4 quarters 4 bushels of limestone bought at Walton' 5 shilling 3pence, at 1 shilling 2pence a quarters. | C150: 0.26 | D150: 0 | E150: 5 | F150: 3 | H150: 4 | I150: 4 | J150: 4.5 | K150: 4.5 | L150: 0 | M150: 4 | N150: 4 | O150: 1 | P150: 2
A151: Cost of buildings | B151: carrying the same 4pence. | C151: 0.02 | D151: 0 | E151: 0 | F151: 4 | H151: 0 | I151: 0 | J151: 0 | K151: 0 | L151: 0 | M151: 0 | N151: 0
A152: Cost of buildings | B152: 8 quarters of limestone bought at Witney 10 shilling 4pence, at 1 shilling 31 pence a quarters. | C152: 0.52 | D152: 0 | E152: 10 | F152: 4 | H152: 8 | I152: 0 | J152: 8 | K152: 8 | L152: 0 | M152: 8 | N152: 0 | O152: 1 | P152: 31
A153: Cost of buildings | B153: carrying the same from Witney to Adderbury 3 shilling 8pence. | C153: 0.18 | D153: 0 | E153: 3 | F153: 8 | H153: 0 | I153: 0 | J153: 0 | K153: 0 | L153: 0 | M153: 0 | N153: 0
A154: Cost of buildings | B154: 1,500 stone slates bought 6 shilling, at 4 shilling a 1,000.. | C154: 0.3 | D154: 0 | E154: 6 | F154: 0 | H154: 0 | I154: 0 | J154: 0 | K154: 0 | L154: 0 | M154: 0 | N154: 0
A155: Cost of buildings | B155: 500 eaves-stones bought 2 shilling 6pence, at 6pence a 100.. | C155: 0.12 | D155: 0 | E155: 2 | F155: 6 | H155: 0 | I155: 0 | J155: 0 | K155: 0 | L155: 0 | M155: 0 | N155: 0
A156: Cost of buildings | B156: 6,000 pins bought 2 shilling, at 4pence a 1,000.. | C156: 0.12 | D156: 0 | E156: 2 | F156: 4 | H156: 0 | I156: 0 | J156: 0 | K156: 0 | L156: 0 | M156: 0 | N156: 0
A157: Cost of buildings | B157: 50 ridge-tiles bought 6 shilling 3pence, at 1.5pence each. | C157: 0.31 | D157: 0 | E157: 6 | F157: 3 | H157: 0 | I157: 0 | J157: 0 | K157: 0 | L157: 0 | M157: 0 | N157: 0
A158: Cost of buildings | B158: sand bought and dug and quarried at Tadmarton 10pence. | C158: 0.04 | D158: 0 | E158: 0 | F158: 10 | H158: 0 | I158: 0 | J158: 0 | K158: 0 | L158: 0 | M158: 0 | N158: 0
A159: Cost of buildings | B159: stipend of 1 man going to Walton' to quarry lime there 2pence. | C159: 0.01 | D159: 0 | E159: 0 | F159: 2 | H159: 0 | I159: 0 | J159: 0 | K159: 0 | L159: 0 | M159: 0 | N159: 0
A160: Cost of buildings | B160: expenses of 12 men coming for a boon-work with 6 carts to quarry sand at Newotele and carry it to Adderbury, with the digging, 2 shilling 3pence. | C160: 0.11 | D160: 0 | E160: 2 | F160: 3 | H160: 0 | I160: 0 | J160: 0 | K160: 0 | L160: 0 | M160: 0 | N160: 0
A161: Cost of buildings | B161: hiring 1 man to carry sand and lime from the warrener's chamber to the barn by piece-work 4pence. | C161: 0.02 | D161: 0 | E161: 0 | F161: 4 | H161: 0 | I161: 0 | J161: 0 | K161: 0 | L161: 0 | M161: 0 | N161: 0
A162: Cost of buildings | B162: carrying the ridge-tiles bought above 8pence. | C162: 0.03 | D162: 0 | E162: 0 | F162: 8 | H162: 0 | I162: 0 | J162: 0 | K162: 0 | L162: 0 | M162: 0 | N162: 0
A163: Cost of buildings | B163: expenses of various men coming for a boon-work to buy slates at Aynho and carry them to Adderbury with the expenses of 1 man there mending the said slates 2d 1 shilling 9.5pence. | C163: 0.09 | D163: 0 | E163: 1 | F163: 9.5 | H163: 0 | I163: 0 | J163: 0 | K163: 0 | L163: 0 | M163: 0 | N163: 0
A164: Cost of buildings | B164: 1 tine bought 8pence. | C164: 0.03 | D164: 0 | E164: 0 | F164: 8 | H164: 0 | I164: 0 | J164: 0 | K164: 0 | L164: 0 | M164: 0 | N164: 0
... A181: Total of all allowances | B181: Total of all allowances and cash deliveries, £64 19 shilling 11.5pence He is quit. | C181: 65 | D181: 64 | E181: 19 | F181: 11.5 | H181: 0 | I181: 0 | J181: 0 | K181: 0 | L181: 0 | M181: 0 | N181: 0
A182: Wheat | B182: William Jakeman, reeve there, answers for 3 quarters of wheat remaining.. | C182: 0 | D182: 0 | E182: 0 | F182: 0 | G182: wheat | H182: 3 | I182: 0 | J182: 3 | K182: 3 | L182: 0 | M182: 3 | N182: 0
A183: Wheat | B183: Total, 3 quarters.. | C183: 0 | D183: 0 | E183: 0 | F183: 0 | H183: 3 | I183: 0 | J183: 3 | K183: 3 | L183: 0 | M183: 3 | N183: 0
A184: Wheat | B184: 3 quarters remain in the keeping of John Eadburbury, farmer there, to be handed back and restored at the end of his farm of 12 years, this year being the fifth. | C184: 0 | D184: 0 | E184: 0 | F184: 0 | H184: 3 | I184: 0 | J184: 3 | K184: 3 | L184: 0 | M184: 3 | N184: 0
A185: Rye | B185: And for 34 quarters of rye remaining.. | C185: 0 | D185: 0 | E185: 0 | F185: 0 | G185: rye | H185: 34 | I185: 0 | J185: 34 | K185: 34 | L185: 0 | M185: 34 | N185: 0
A186: Rye | B186: Total, 34 quarters.. | C186: 0 | D186: 0 | E186: 0 | F186: 0 | H186: 34 | I186: 0 | J186: 34 | K186: 34 | L186: 0 | M186: 34 | N186: 0
A187: Rye | B187: 34 quarters remain in the keeping of the said John Eadburbury, farmer there, to be handed back and restored at the end of his farm as before. | C187: 0 | D187: 0 | E187: 0 | F187: 0 | H187: 34 | I187: 0 | J187: 34 | K187: 34 | L187: 0 | M187: 34 | N187: 0
A188: Dredge | B188: And for 30 quarters of dredge remaining.. | C188: 0 | D188: 0 | E188: 0 | F188: 0 | G188: dredge | H188: 30 | I188: 0 | J188: 30 | K188: 30 | L188: 0 | M188: 30 | N188: 0
A189: Dredge | B189: Total, 30 quarters.. | C189: 0 | D189: 0 | E189: 0 | F189: 0 | H189: 30 | I189: 0 | J189: 30 | K189: 30 | L189: 0 | M189: 30 | N189: 0
A190: Dredge | B190: 30 quarters remain in the keeping of the said John Eadburbury, farmer there, to be handed back and restored as before. | C190: 0 | D190: 0 | E190: 0 | F190: 0 | H190: 30 | I190: 0 | J190: 30 | K190: 30 | L190: 0 | M190: 30 | N190: 0
A191: Pulses | B191: None remain. | C191: 0 | D191: 0 | E191: 0 | F191: 0 | H191: 0 | I191: 0 | J191: 0 | K191: 0 | L191: 0 | M191: 0 | N191: 0
A192: Oats | B192: And for 10 quarters of oats.. | C192: 0 | D192: 0 | E192: 0 | F192: 0 | G192: oats | H192: 10 | I192: 0 | J192: 10 | K192: 10 | L192: 0 | M192: 10 | N192: 0
A193: Oats | B193: Total, 10 quarters.. | C193: 0 | D193: 0 | E193: 0 | F193: 0 | H193: 10 | I193: 0 | J193: 10 | K193: 10 | L193: 0 | M193: 10 | N193: 0
A194: Oats | B194: 10 quarters remain in the keeping of the said John Eadburbury, farmer there, to be handed back and restored as before. | C194: 0 | D194: 0 | E194: 0 | F194: 0 | H194: 10 | I194: 0 | J194: 10 | K194: 10 | L194: 0 | M194: 10 | N194: 0
A195: Oats | B195: Eadburbury, farmer, to be handed back and restored at the end of his farm or the value of the same as before. | C195: 0 | D195: 0 | E195: 0 | F195: 0 | H195: 0 | I195: 0 | J195: 0 | K195: 0 | L195: 0 | M195: 0 | N195: 0
A196: Stock | B196: Horses: 4 remain. | C196: 0 | D196: 0 | E196: 0 | F196: 0 | H196: 0 | I196: 0 | J196: 0 | K196: 0 | L196: 0 | M196: 0 | N196: 0
A197: Stock | B197: 1 from the heriot of William Rundell'. | C197: 0 | D197: 0 | E197: 0 | F197: 0 | H197: 0 | I197: 0 | J197: 0 | K197: 0 | L197: 0 | M197: 0 | N197: 0
A198: Stock | B198: Total 5. 1 sold within. | C198: 0 | D198: 0 | E198: 0 | F198: 0 | H198: 0 | I198: 0 | J198: 0 | K198: 0 | L198: 0 | M198: 0 | N198: 0
A199: Stock | B199: 4 cart-horses remain, of which 2 are worth £1 6s 8pence, 1 is worth £1, and 1 feeble one is worth 2 shilling, in the keeping of the said John Eadburbury, farmer there, to be handed back and restored at the end of his farm or the value of the same at the choice of the lord bishop or his attorney. | C199: 1 | D199: 1 | E199: 0 | F199: 0 | H199: 0 | I199: 0 | J199: 0 | K199: 0 | L199: 0 | M199: 0 | N199: 0
A200: Stock | B200: Plough-horses: 6 remain. | C200: 0 | D200: 0 | E200: 0 | F200: 0 | H200: 0 | I200: 0 | J200: 0 | K200: 0 | L200: 0 | M200: 0 | N200: 0
A201: Stock | B201: Total, 6. 6 remain, worth £2, in the keeping of John. | C201: 2 | D201: 2 | E201: 0 | F201: 0 | H201: 0 | I201: 0 | J201: 0 | K201: 0 | L201: 0 | M201: 0 | N201: 0
A202: Stock | B202: Colts: 1 from the heriot of John Diconurn. | C202: 0 | D202: 0 | E202: 0 | F202: 0 | H202: 0 | I202: 0 | J202: 0 | K202: 0 | L202: 0 | M202: 0 | N202: 0
A203: Stock | B203: sold within. | C203: 0 | D203: 0 | E203: 0 | F203: 0 | H203: 0 | I203: 0 | J203: 0 | K203: 0 | L203: 0 | M203: 0 | N203: 0
A204: Stock | B204: none remain. | C204: 0 | D204: 0 | E204: 0 | F204: 0 | H204: 0 | I204: 0 | J204: 0 | K204: 0 | L204: 0 | M204: 0 | N204: 0
... A268: Stock | B268: none remain. mid. | C268: 0 | D268: 0 | E268: 0 | F268: 0 | H268: 0 | I268: 0 | J268: 0 | K268: 0 | L268: 0 | M268: 0 | N268: 0

Sheet Prices
A1: Meat & Dairy Prices
C2: 1301 | D2: 1302 | E2: Average
A3: Beef | B3: £ per lb | C3: 0.0033351854 | D3: 0.0032608538 | E3: =AVERAGE(C3:D3) -> 0.0032980196
A4: Mutton | B4: £ per lb | C4: 0.0036593977 | D4: 0.0037125513 | E4: =AVERAGE(C4:D4) -> 0.0036859745
A5: Pork | B5: £ per lb | C5: 0.0038431326 | D5: 0.0037574803 | E5: =AVERAGE(C5:D5) -> 0.0038003065
A6: Cheese | B6: £ per lb | C6: 0.0055768754 | D6: 0.0056654898 | E6: =AVERAGE(C6:D6) -> 0.0056211826
A7: Butter | B7: £ per lb | C7: 0.0036626221 | D7: 0.0035935077 | E7: =AVERAGE(C7:D7) -> 0.0036280649
A8: Milk | B8: £ per gallon | C8: 0.0055768754 | D8: 0.0056654898 | E8: =AVERAGE(C8:D8) -> 0.0056211826

Sheet Labour Rents

Sheet Bishops Fonthill Overview
A1: BISHOPS FONTHILL | B1: £ | C1: s | D1: d | G1: Total in £ | H1: Error
A3: CASH ACCOUNT
A4: RECEIPTS
A5: Arrears | G5: ='Bishops Fonthill Receipts'!F5 -> 11.3875
A6: Rents of assize | G6: ='Bishops Fonthill Receipts'!F14 -> 5.0125
A7: Quittances | G7: ='Bishops Fonthill Receipts'!F24 -> 1.075
A8: Defaults of rent | I8: none
A9: Total of rents remaining | G9: ='Bishops Fonthill Receipts'!F26 -> 3.9375
A10: Annual reconizances | G10: ='Bishops Fonthill Receipts'!F38 -> 0.0375
A11: Issues of the Manor | G11: ='Bishops Fonthill Receipts'!F55 -> 7.7145833
A12: Sale of corn | G12: ='Bishops Fonthill Receipts'!F64 -> 22.63125
A13: Entry and marriage fines | G13: ='Bishops Fonthill Receipts'!F71 -> 0.55
A14: Pleas & Perquisites | G14: ='Bishops Fonthill Receipts'!F76 -> 2.0416667
A15: Sum of the above (incl. arrears) | G15: =G5+G9+G10+G11+G12+G13+G14 -> 48.3
A16: Total recorded in the accounts excl. arrears | G16: ='Bishops Fonthill Receipts'!F80 -> 36.952083
A17: Total recorded in the accounts incl. arrears | I17: not feasible
A20: EXPENSES
A21: Cost of ploughs | G21: ='Bishops Fonthill Expenses'!F14 -> 3.6208333
A22: Purchase of corn
A23: Cost of carts and wagons | G23: ='Bishops Fonthill Expenses'!F29 -> 0.4
A24: Cost of dairy
A25: Purchase of stock
A26: Sheepcote | G26: ='Bishops Fonthill Expenses'!F49 -> 0.39583333
A27: Cost of buildings | G27: ='Bishops Fonthill Expenses'!F40 -> 0.4375
A28: Threshing | G28: ='Bishops Fonthill Expenses'!F58 -> 1.2583333
A29: Expenses of the harvest | G29: ='Bishops Fonthill Expenses'!F66 -> 0.58333333
A30: Stewards expenses | G30: ='Bishops Fonthill Expenses'!F71 -> 0.125
A31: Sum of the above | G31: =SUM(G21:G30) -> 6.8208333
A32: Total of all expenses | G32: ='Bishops Fonthill Expenses'!F73 -> 6.8208333 | H32: =G31-G32 -> 0
A33: Total Demesne fixed investment | G33: ='Bishops Fonthill Expenses'!F78 -> 1.8208333
A35: Owed by the reeve | G35: ='Bishops Fonthill Expenses'!F75 -> 30.13125
A36: From accounts
A38: Cash deliveries | G38: ='Bishops Fonthill Expenses'!F76 -> 21.6
A39: Cash delivers (Hindon Borough)
A40: Sum of the above | B40: =SUM(B38:B39) -> 0 | C40: =SUM(C38:C39) -> 0 | D40: =SUM(D38:D39) -> 0 | E40: =SUM(E38:E39) -> 0 | G40: =SUM(G38:G39) -> 21.6
A41: Total of all allowances and cash deliveries in accounts | B41: n/a
A43: Net amount owed | G43: ='Bishops Fonthill Expenses'!F77 -> 8.53125
A44: Net amount owed in accounts | H44: =G43-G44 -> 8.53125
A46: GRANGE ACCOUNT | B46: Net Production | F46: Value of total gross production in £ | G46: Value of total net production in £
A47: Grange | B47: qrs | C47: bus | F47: £ | G47: £
A48: Wheat | B48: ='Issues of the Grange'!J18 -> 59.375 | F48: ='Issues of the Grange'!P5 -> 20.46875 | G48: ='Issues of the Grange'!M18 -> 14.84375
A49: Curall | B49: ='Issues of the Grange'!J19 -> 1.125 | F49: ='Issues of the Grange'!P6 -> 0.1125 | G49: ='Issues of the Grange'!M19 -> 0.1125
A50: Barley | B50: ='Issues of the Grange'!J20 -> 29.75 | F50: ='Issues of the Grange'!P7 -> 10.666667 | G50: ='Issues of the Grange'!M20 -> 4.9583333
A51: Oats | B51: ='Issues of the Grange'!J21 -> 25 | F51: ='Issues of the Grange'!P8 -> 5.7758333 | G51: ='Issues of the Grange'!M21 -> 2.4166667
A52: Bere | B52: ='Issues of the Grange'!J22 -> 0 | F52: ='Issues of the Grange'!P9 -> 0 | G52: ='Issues of the Grange'!M22 -> 0
A53: Vetches | B53: ='Issues of the Grange'!J23 -> 3 | F53: ='Issues of the Grange'!P10 -> 0.625 | G53: ='Issues of the Grange'!M23 -> 0
A54: Total value of gross production (sum of the above) | F54: =SUM(F48:F53) -> 37.64875
A55: Total value of net production | F55: =SUM(G48:G53) -> 22.33125
A56: Value of sales | F56: ='Issues of the Grange'!N25 -> 22.33125
A58: MILL ACCOUNT | B58: n/a
A59: Issues of the mill | B59: qrs | C59: bus | G59: £
A60: Wheat
A61: Oatmeal
A62: 1st grade malt
A63: 2nd grade malt
A64: Maslin
A65: Total value of production (sum of the above)
A66: Value of sales | G66: n/a
A68: STOCK ACCOUNT
A69: Livestock | B69: Inherited stock | C69: End-period stock | D69: Stockbuilding | F69: Sales in (£) | G69: Value of production (£) at sales prices
A70: Cart-horses | B70: =IFERROR(INDEX(Stock!$A$3:$T$92,MATCH('Bishops Fonthill Overview'!$A70,Stock!$A$3:$A$92,0),MATCH('Bishops Fonthill Overview'!B$69,Stock!$A$3:$T$3,0)),0) -> 0 | C70: =IFERROR(INDEX(Stock!$A$3:$T$92,MATCH('Bishops Fonthill Overview'!$A70,Stock!$A$3:$A$92,0),MATCH('Bishops Fonthill Overview'!C$69,Stock!$A$3:$T$3,0)),0) -> 0 | D70: =C70-B70 -> 0 | F70: =IFERROR(INDEX(Stock!$A$3:$T$92,MATCH('Bishops Fonthill Overview'!$A70,Stock!$A$3:$A$92,0),MATCH('Bishops Fonthill Overview'!F$69,Stock!$A$3:$T$3,0)),0) | G70: =IFERROR(INDEX(Stock!$A$3:$T$92,MATCH('Bishops Fonthill Overview'!$A70,Stock!$A$3:$A$92,0),MATCH('Bishops Fonthill Overview'!G$69,Stock!$A$3:$T$3,0)),0)
A71: Mares | B71: =IFERROR(INDEX(Stock!$A$3:$T$92,MATCH('Bishops Fonthill Overview'!$A71,Stock!$A$3:$A$92,0),MATCH('Bishops Fonthill Overview'!B$69,Stock!$A$3:$T$3,0)),0) -> 0 | C71: =IFERROR(INDEX(Stock!$A$3:$T$92,MATCH('Bishops Fonthill Overview'!$A71,Stock!$A$3:$A$92,0),MATCH('Bishops Fonthill Overview'!C$69,Stock!$A$3:$T$3,0)),0) -> 0 | D71: =C71-B71 -> 0 | F71: =IFERROR(INDEX(Stock!$A$3:$T$92,MATCH('Bishops Fonthill Overview'!$A71,Stock!$A$3:$A$92,0),MATCH('Bishops Fonthill Overview'!F$69,Stock!$A$3:$T$3,0)),0) | G71: =IFERROR(INDEX(Stock!$A$3:$T$92,MATCH('Bishops Fonthill Overview'!$A71,Stock!$A$3:$A$92,0),MATCH('Bishops Fonthill Overview'!G$69,Stock!$A$3:$T$3,0)),0)
A72: Plough horses | B72: =IFERROR(INDEX(Stock!$A$3:$T$92,MATCH('Bishops Fonthill Overview'!$A72,Stock!$A$3:$A$92,0),MATCH('Bishops Fonthill Overview'!B$69,Stock!$A$3:$T$3,0)),0) -> 2 | C72: =IFERROR(INDEX(Stock!$A$3:$T$92,MATCH('Bishops Fonthill Overview'!$A72,Stock!$A$3:$A$92,0),MATCH('Bishops Fonthill Overview'!C$69,Stock!$A$3:$T$3,0)),0) -> 2 | D72: =C72-B72 -> 0 | F72: =IFERROR(INDEX(Stock!$A$3:$T$92,MATCH('Bishops Fonthill Overview'!$A72,Stock!$A$3:$A$92,0),MATCH('Bishops Fonthill Overview'!F$69,Stock!$A$3:$T$3,0)),0) | G72: =IFERROR(INDEX(Stock!$A$3:$T$92,MATCH('Bishops Fonthill Overview'!$A72,Stock!$A$3:$A$92,0),MATCH('Bishops Fonthill Overview'!G$69,Stock!$A$3:$T$3,0)),0)
A73: Colts (2 years) | B73: =IFERROR(INDEX(Stock!$A$3:$T$92,MATCH('Bishops Fonthill Overview'!$A73,Stock!$A$3:$A$92,0),MATCH('Bishops Fonthill Overview'!B$69,Stock!$A$3:$T$3,0)),0) -> 0 | C73: =IFERROR(INDEX(Stock!$A$3:$T$92,MATCH('Bishops Fonthill Overview'!$A73,Stock!$A$3:$A$92,0),MATCH('Bishops Fonthill Overview'!C$69,Stock!$A$3:$T$3,0)),0) -> 0 | D73: =C73-B73 -> 0 | F73: =IFERROR(INDEX(Stock!$A$3:$T$92,MATCH('Bishops Fonthill Overview'!$A73,Stock!$A$3:$A$92,0),MATCH('Bishops Fonthill Overview'!F$69,Stock!$A$3:$T$3,0)),0) | G73: =IFERROR(INDEX(Stock!$A$3:$T$92,MATCH('Bishops Fonthill Overview'!$A73,Stock!$A$3:$A$92,0),MATCH('Bishops Fonthill Overview'!G$69,Stock!$A$3:$T$3,0)),0)
A74: Colts (2 years) | B74: =IFERROR(INDEX(Stock!$A$3:$T$92,MATCH('Bishops Fonthill Overview'!$A74,Stock!$A$3:$A$92,0),MATCH('Bishops Fonthill Overview'!B$69,Stock!$A$3:$T$3,0)),0) -> 0 | C74: =IFERROR(INDEX(Stock!$A$3:$T$92,MATCH('Bishops Fonthill Overview'!$A74,Stock!$A$3:$A$92,0),MATCH('Bishops Fonthill Overview'!C$69,Stock!$A$3:$T$3,0)),0) -> 0 | D74: =C74-B74 -> 0 | F74: =IFERROR(INDEX(Stock!$A$3:$T$92,MATCH('Bishops Fonthill Overview'!$A74,Stock!$A$3:$A$92,0),MATCH('Bishops Fonthill Overview'!F$69,Stock!$A$3:$T$3,0)),0) | G74: =IFERROR(INDEX(Stock!$A$3:$T$92,MATCH('Bishops Fonthill Overview'!$A74,Stock!$A$3:$A$92,0),MATCH('Bishops Fonthill Overview'!G$69,Stock!$A$3:$T$3,0)),0)
A75: Colts (1 year) | B75: =IFERROR(INDEX(Stock!$A$3:$T$92,MATCH('Bishops Fonthill Overview'!$A75,Stock!$A$3:$A$92,0),MATCH('Bishops Fonthill Overview'!B$69,Stock!$A$3:$T$3,0)),0) -> 0 | C75: =IFERROR(INDEX(Stock!$A$3:$T$92,MATCH('Bishops Fonthill Overview'!$A75,Stock!$A$3:$A$92,0),MATCH('Bishops Fonthill Overview'!C$69,Stock!$A$3:$T$3,0)),0) -> 0 | D75: =C75-B75 -> 0 | F75: =IFERROR(INDEX(Stock!$A$3:$T$92,MATCH('Bishops Fonthill Overview'!$A75,Stock!$A$3:$A$92,0),MATCH('Bishops Fonthill Overview'!F$69,Stock!$A$3:$T$3,0)),0) | G75: =IFERROR(INDEX(Stock!$A$3:$T$92,MATCH('Bishops Fonthill Overview'!$A75,Stock!$A$3:$A$92,0),MATCH('Bishops Fonthill Overview'!G$69,Stock!$A$3:$T$3,0)),0)
A76: Foals | B76: =IFERROR(INDEX(Stock!$A$3:$T$92,MATCH('Bishops Fonthill Overview'!$A76,Stock!$A$3:$A$92,0),MATCH('Bishops Fonthill Overview'!B$69,Stock!$A$3:$T$3,0)),0) -> 0 | C76: =IFERROR(INDEX(Stock!$A$3:$T$92,MATCH('Bishops Fonthill Overview'!$A76,Stock!$A$3:$A$92,0),MATCH('Bishops Fonthill Overview'!C$69,Stock!$A$3:$T$3,0)),0) -> 0 | D76: =C76-B76 -> 0 | F76: =IFERROR(INDEX(Stock!$A$3:$T$92,MATCH('Bishops Fonthill Overview'!$A76,Stock!$A$3:$A$92,0),MATCH('Bishops Fonthill Overview'!F$69,Stock!$A$3:$T$3,0)),0) | G76: =IFERROR(INDEX(Stock!$A$3:$T$92,MATCH('Bishops Fonthill Overview'!$A76,Stock!$A$3:$A$92,0),MATCH('Bishops Fonthill Overview'!G$69,Stock!$A$3:$T$3,0)),0)
A77: Oxen | B77: =IFERROR(INDEX(Stock!$A$3:$T$92,MATCH('Bishops Fonthill Overview'!$A77,Stock!$A$3:$A$92,0),MATCH('Bishops Fonthill Overview'!B$69,Stock!$A$3:$T$3,0)),0) -> 24 | C77: =IFERROR(INDEX(Stock!$A$3:$T$92,MATCH('Bishops Fonthill Overview'!$A77,Stock!$A$3:$A$92,0),MATCH('Bishops Fonthill Overview'!C$69,Stock!$A$3:$T$3,0)),0) -> 0 | D77: =C77-B77 -> -24 | F77: =IFERROR(INDEX(Stock!$A$3:$T$92,MATCH('Bishops Fonthill Overview'!$A77,Stock!$A$3:$A$92,0),MATCH('Bishops Fonthill Overview'!F$69,Stock!$A$3:$T$3,0)),0) -> 0.8 | G77: =IFERROR(INDEX(Stock!$A$3:$T$92,MATCH('Bishops Fonthill Overview'!$A77,Stock!$A$3:$A$92,0),MATCH('Bishops Fonthill Overview'!G$69,Stock!$A$3:$T$3,0)),0) -> 2.4
A78: Bulls | B78: =IFERROR(INDEX(Stock!$A$3:$T$92,MATCH('Bishops Fonthill Overview'!$A78,Stock!$A$3:$A$92,0),MATCH('Bishops Fonthill Overview'!B$69,Stock!$A$3:$T$3,0)),0) -> 0 | C78: =IFERROR(INDEX(Stock!$A$3:$T$92,MATCH('Bishops Fonthill Overview'!$A78,Stock!$A$3:$A$92,0),MATCH('Bishops Fonthill Overview'!C$69,Stock!$A$3:$T$3,0)),0) -> 0 | D78: =C78-B78 -> 0 | F78: =IFERROR(INDEX(Stock!$A$3:$T$92,MATCH('Bishops Fonthill Overview'!$A78,Stock!$A$3:$A$92,0),MATCH('Bishops Fonthill Overview'!F$69,Stock!$A$3:$T$3,0)),0) | G78: =IFERROR(INDEX(Stock!$A$3:$T$92,MATCH('Bishops Fonthill Overview'!$A78,Stock!$A$3:$A$92,0),MATCH('Bishops Fonthill Overview'!G$69,Stock!$A$3:$T$3,0)),0)
A79: Cows | B79: =IFERROR(INDEX(Stock!$A$3:$T$92,MATCH('Bishops Fonthill Overview'!$A79,Stock!$A$3:$A$92,0),MATCH('Bishops Fonthill Overview'!B$69,Stock!$A$3:$T$3,0)),0) -> 0 | C79: =IFERROR(INDEX(Stock!$A$3:$T$92,MATCH('Bishops Fonthill Overview'!$A79,Stock!$A$3:$A$92,0),MATCH('Bishops Fonthill Overview'!C$69,Stock!$A$3:$T$3,0)),0) -> 0 | D79: =C79-B79 -> 0 | F79: =IFERROR(INDEX(Stock!$A$3:$T$92,MATCH('Bishops Fonthill Overview'!$A79,Stock!$A$3:$A$92,0),MATCH('Bishops Fonthill Overview'!F$69,Stock!$A$3:$T$3,0)),0) | G79: =IFERROR(INDEX(Stock!$A$3:$T$92,MATCH('Bishops Fonthill Overview'!$A79,Stock!$A$3:$A$92,0),MATCH('Bishops Fonthill Overview'!G$69,Stock!$A$3:$T$3,0)),0)
A80: Steers | B80: =IFERROR(INDEX(Stock!$A$3:$T$92,MATCH('Bishops Fonthill Overview'!$A80,Stock!$A$3:$A$92,0),MATCH('Bishops Fonthill Overview'!B$69,Stock!$A$3:$T$3,0)),0) -> 0 | C80: =IFERROR(INDEX(Stock!$A$3:$T$92,MATCH('Bishops Fonthill Overview'!$A80,Stock!$A$3:$A$92,0),MATCH('Bishops Fonthill Overview'!C$69,Stock!$A$3:$T$3,0)),0) -> 0 | D80: =C80-B80 -> 0 | F80: =IFERROR(INDEX(Stock!$A$3:$T$92,MATCH('Bishops Fonthill Overview'!$A80,Stock!$A$3:$A$92,0),MATCH('Bishops Fonthill Overview'!F$69,Stock!$A$3:$T$3,0)),0) | G80: =IFERROR(INDEX(Stock!$A$3:$T$92,MATCH('Bishops Fonthill Overview'!$A80,Stock!$A$3:$A$92,0),MATCH('Bishops Fonthill Overview'!G$69,Stock!$A$3:$T$3,0)),0)
A81: Bullocks | B81: =IFERROR(INDEX(Stock!$A$3:$T$92,MATCH('Bishops Fonthill Overview'!$A81,Stock!$A$3:$A$92,0),MATCH('Bishops Fonthill Overview'!B$69,Stock!$A$3:$T$3,0)),0) -> 0 | C81: =IFERROR(INDEX(Stock!$A$3:$T$92,MATCH('Bishops Fonthill Overview'!$A81,Stock!$A$3:$A$92,0),MATCH('Bishops Fonthill Overview'!C$69,Stock!$A$3:$T$3,0)),0) -> 0 | D81: =C81-B81 -> 0 | F81: =IFERROR(INDEX(Stock!$A$3:$T$92,MATCH('Bishops Fonthill Overview'!$A81,Stock!$A$3:$A$92,0),MATCH('Bishops Fonthill Overview'!F$69,Stock!$A$3:$T$3,0)),0) | G81: =IFERROR(INDEX(Stock!$A$3:$T$92,MATCH('Bishops Fonthill Overview'!$A81,Stock!$A$3:$A$92,0),MATCH('Bishops Fonthill Overview'!G$69,Stock!$A$3:$T$3,0)),0)
... A95: Peacocks | B95: =IFERROR(INDEX(Stock!$A$3:$T$92,MATCH('Bishops Fonthill Overview'!$A95,Stock!$A$3:$A$92,0),MATCH('Bishops Fonthill Overview'!B$69,Stock!$A$3:$T$3,0)),0) -> 0 | C95: =IFERROR(INDEX(Stock!$A$3:$T$92,MATCH('Bishops Fonthill Overview'!$A95,Stock!$A$3:$A$92,0),MATCH('Bishops Fonthill Overview'!C$69,Stock!$A$3:$T$3,0)),0) -> 0 | D95: =C95-B95 -> 0 | F95: =IFERROR(INDEX(Stock!$A$3:$T$92,MATCH('Bishops Fonthill Overview'!$A95,Stock!$A$3:$A$92,0),MATCH('Bishops Fonthill Overview'!F$69,Stock!$A$3:$T$3,0)),0) | G95: =IFERROR(INDEX(Stock!$A$3:$T$92,MATCH('Bishops Fonthill Overview'!$A95,Stock!$A$3:$A$92,0),MATCH('Bishops Fonthill Overview'!G$69,Stock!$A$3:$T$3,0)),0)
A96: Total | G96: =SUM(G70:G95) -> 7.5787879
A97: Value of sales | G97: =SUM(F70:F95) -> 7.2367424
A99: Wool | B99: Inherited stock | C99: End-period stock | D99: Stockbuilding | F99: Sales in (£) | G99: Value of production (£) at sales prices
A100: Fleeces | B100: =IFERROR(INDEX(Stock!$A$3:$T$92,MATCH('Bishops Fonthill Overview'!$A100,Stock!$A$3:$A$92,0),MATCH('Bishops Fonthill Overview'!B$69,Stock!$A$3:$T$3,0)),0) -> 0 | C100: =IFERROR(INDEX(Stock!$A$3:$T$92,MATCH('Bishops Fonthill Overview'!$A100,Stock!$A$3:$A$92,0),MATCH('Bishops Fonthill Overview'!C$69,Stock!$A$3:$T$3,0)),0) -> 0 | D100: =C100-B100 -> 0 | F100: =IFERROR(INDEX(Stock!$A$3:$T$92,MATCH('Bishops Fonthill Overview'!$A100,Stock!$A$3:$A$92,0),MATCH('Bishops Fonthill Overview'!F$69,Stock!$A$3:$T$3,0)),0) -> 6.24 | G100: =IFERROR(INDEX(Stock!$A$3:$T$92,MATCH('Bishops Fonthill Overview'!$A100,Stock!$A$3:$A$92,0),MATCH('Bishops Fonthill Overview'!G$69,Stock!$A$3:$T$3,0)),0) -> 6.32
A101: Coarse wool | B101: =IFERROR(INDEX(Stock!$A$3:$T$92,MATCH('Bishops Fonthill Overview'!$A101,Stock!$A$3:$A$92,0),MATCH('Bishops Fonthill Overview'!B$69,Stock!$A$3:$T$3,0)),0) -> 0 | C101: =IFERROR(INDEX(Stock!$A$3:$T$92,MATCH('Bishops Fonthill Overview'!$A101,Stock!$A$3:$A$92,0),MATCH('Bishops Fonthill Overview'!C$69,Stock!$A$3:$T$3,0)),0) -> 0 | D101: =C101-B101 -> 0 | F101: =IFERROR(INDEX(Stock!$A$3:$T$92,MATCH('Bishops Fonthill Overview'!$A101,Stock!$A$3:$A$92,0),MATCH('Bishops Fonthill Overview'!F$69,Stock!$A$3:$T$3,0)),0) | G101: =IFERROR(INDEX(Stock!$A$3:$T$92,MATCH('Bishops Fonthill Overview'!$A101,Stock!$A$3:$A$92,0),MATCH('Bishops Fonthill Overview'!G$69,Stock!$A$3:$T$3,0)),0)
A102: Lamb's wool | B102: =IFERROR(INDEX(Stock!$A$3:$T$92,MATCH('Bishops Fonthill Overview'!$A102,Stock!$A$3:$A$92,0),MATCH('Bishops Fonthill Overview'!B$69,Stock!$A$3:$T$3,0)),0) -> 0 | C102: =IFERROR(INDEX(Stock!$A$3:$T$92,MATCH('Bishops Fonthill Overview'!$A102,Stock!$A$3:$A$92,0),MATCH('Bishops Fonthill Overview'!C$69,Stock!$A$3:$T$3,0)),0) -> 0 | D102: =C102-B102 -> 0 | F102: =IFERROR(INDEX(Stock!$A$3:$T$92,MATCH('Bishops Fonthill Overview'!$A102,Stock!$A$3:$A$92,0),MATCH('Bishops Fonthill Overview'!F$69,Stock!$A$3:$T$3,0)),0) -> 0.041666667 | G102: =IFERROR(INDEX(Stock!$A$3:$T$92,MATCH('Bishops Fonthill Overview'!$A102,Stock!$A$3:$A$92,0),MATCH('Bishops Fonthill Overview'!G$69,Stock!$A$3:$T$3,0)),0) -> 0.041666667
A103: Wool locks | B103: =IFERROR(INDEX(Stock!$A$3:$T$92,MATCH('Bishops Fonthill Overview'!$A103,Stock!$A$3:$A$92,0),MATCH('Bishops Fonthill Overview'!B$69,Stock!$A$3:$T$3,0)),0) -> 0 | C103: =IFERROR(INDEX(Stock!$A$3:$T$92,MATCH('Bishops Fonthill Overview'!$A103,Stock!$A$3:$A$92,0),MATCH('Bishops Fonthill Overview'!C$69,Stock!$A$3:$T$3,0)),0) -> 0 | D103: =C103-B103 -> 0 | F103: =IFERROR(INDEX(Stock!$A$3:$T$92,MATCH('Bishops Fonthill Overview'!$A103,Stock!$A$3:$A$92,0),MATCH('Bishops Fonthill Overview'!F$69,Stock!$A$3:$T$3,0)),0) -> 0.18333333 | G103: =IFERROR(INDEX(Stock!$A$3:$T$92,MATCH('Bishops Fonthill Overview'!$A103,Stock!$A$3:$A$92,0),MATCH('Bishops Fonthill Overview'!G$69,Stock!$A$3:$T$3,0)),0) -> 0.18333333
A104: Wool sold at shearing | B104: =IFERROR(INDEX(Stock!$A$3:$T$92,MATCH('Bishops Fonthill Overview'!$A104,Stock!$A$3:$A$92,0),MATCH('Bishops Fonthill Overview'!B$69,Stock!$A$3:$T$3,0)),0) -> 0 | C104: =IFERROR(INDEX(Stock!$A$3:$T$92,MATCH('Bishops Fonthill Overview'!$A104,Stock!$A$3:$A$92,0),MATCH('Bishops Fonthill Overview'!C$69,Stock!$A$3:$T$3,0)),0) -> 0 | D104: =C104-B104 -> 0 | F104: =IFERROR(INDEX(Stock!$A$3:$T$92,MATCH('Bishops Fonthill Overview'!$A104,Stock!$A$3:$A$92,0),MATCH('Bishops Fonthill Overview'!F$69,Stock!$A$3:$T$3,0)),0) | G104: =IFERROR(INDEX(Stock!$A$3:$T$92,MATCH('Bishops Fonthill Overview'!$A104,Stock!$A$3:$A$92,0),MATCH('Bishops Fonthill Overview'!G$69,Stock!$A$3:$T$3,0)),0)
A105: Total value of production (sum of the above) | G105: =SUM(G100:G104) -> 6.545
A106: Value of sales | G106: =SUM(F100:F104) -> 6.465
A108: Hides | B108: Inherited stock | C108: End-period stock | D108: Stockbuilding | F108: Sales in (£) | G108: Value of production (£) at sales prices
A109: Ox hides | B109: =IFERROR(INDEX(Stock!$A$3:$T$92,MATCH('Bishops Fonthill Overview'!$A109,Stock!$A$3:$A$92,0),MATCH('Bishops Fonthill Overview'!B$69,Stock!$A$3:$T$3,0)),0) -> 0 | C109: =IFERROR(INDEX(Stock!$A$3:$T$92,MATCH('Bishops Fonthill Overview'!$A109,Stock!$A$3:$A$92,0),MATCH('Bishops Fonthill Overview'!C$69,Stock!$A$3:$T$3,0)),0) -> 0 | D109: =C109-B109 -> 0 | F109: =IFERROR(INDEX(Stock!$A$3:$T$92,MATCH('Bishops Fonthill Overview'!$A109,Stock!$A$3:$A$92,0),MATCH('Bishops Fonthill Overview'!F$69,Stock!$A$3:$T$3,0)),0) | G109: =IFERROR(INDEX(Stock!$A$3:$T$92,MATCH('Bishops Fonthill Overview'!$A109,Stock!$A$3:$A$92,0),MATCH('Bishops Fonthill Overview'!G$69,Stock!$A$3:$T$3,0)),0)
A110: Cow hides | B110: =IFERROR(INDEX(Stock!$A$3:$T$92,MATCH('Bishops Fonthill Overview'!$A110,Stock!$A$3:$A$92,0),MATCH('Bishops Fonthill Overview'!B$69,Stock!$A$3:$T$3,0)),0) -> 0 | C110: =IFERROR(INDEX(Stock!$A$3:$T$92,MATCH('Bishops Fonthill Overview'!$A110,Stock!$A$3:$A$92,0),MATCH('Bishops Fonthill Overview'!C$69,Stock!$A$3:$T$3,0)),0) -> 0 | D110: =C110-B110 -> 0 | F110: =IFERROR(INDEX(Stock!$A$3:$T$92,MATCH('Bishops Fonthill Overview'!$A110,Stock!$A$3:$A$92,0),MATCH('Bishops Fonthill Overview'!F$69,Stock!$A$3:$T$3,0)),0) | G110: =IFERROR(INDEX(Stock!$A$3:$T$92,MATCH('Bishops Fonthill Overview'!$A110,Stock!$A$3:$A$92,0),MATCH('Bishops Fonthill Overview'!G$69,Stock!$A$3:$T$3,0)),0)
A111: Mare hides | B111: =IFERROR(INDEX(Stock!$A$3:$T$92,MATCH('Bishops Fonthill Overview'!$A111,Stock!$A$3:$A$92,0),MATCH('Bishops Fonthill Overview'!B$69,Stock!$A$3:$T$3,0)),0) -> 0 | C111: =IFERROR(INDEX(Stock!$A$3:$T$92,MATCH('Bishops Fonthill Overview'!$A111,Stock!$A$3:$A$92,0),MATCH('Bishops Fonthill Overview'!C$69,Stock!$A$3:$T$3,0)),0) -> 0 | D111: =C111-B111 -> 0 | F111: =IFERROR(INDEX(Stock!$A$3:$T$92,MATCH('Bishops Fonthill Overview'!$A111,Stock!$A$3:$A$92,0),MATCH('Bishops Fonthill Overview'!F$69,Stock!$A$3:$T$3,0)),0) | G111: =IFERROR(INDEX(Stock!$A$3:$T$92,MATCH('Bishops Fonthill Overview'!$A111,Stock!$A$3:$A$92,0),MATCH('Bishops Fonthill Overview'!G$69,Stock!$A$3:$T$3,0)),0)
A112: Steer hides | B112: =IFERROR(INDEX(Stock!$A$3:$T$92,MATCH('Bishops Fonthill Overview'!$A112,Stock!$A$3:$A$92,0),MATCH('Bishops Fonthill Overview'!B$69,Stock!$A$3:$T$3,0)),0) -> 0 | C112: =IFERROR(INDEX(Stock!$A$3:$T$92,MATCH('Bishops Fonthill Overview'!$A112,Stock!$A$3:$A$92,0),MATCH('Bishops Fonthill Overview'!C$69,Stock!$A$3:$T$3,0)),0) -> 0 | D112: =C112-B112 -> 0 | F112: =IFERROR(INDEX(Stock!$A$3:$T$92,MATCH('Bishops Fonthill Overview'!$A112,Stock!$A$3:$A$92,0),MATCH('Bishops Fonthill Overview'!F$69,Stock!$A$3:$T$3,0)),0) | G112: =IFERROR(INDEX(Stock!$A$3:$T$92,MATCH('Bishops Fonthill Overview'!$A112,Stock!$A$3:$A$92,0),MATCH('Bishops Fonthill Overview'!G$69,Stock!$A$3:$T$3,0)),0)
A113: Yearling Calf hides | B113: =IFERROR(INDEX(Stock!$A$3:$T$92,MATCH('Bishops Fonthill Overview'!$A113,Stock!$A$3:$A$92,0),MATCH('Bishops Fonthill Overview'!B$69,Stock!$A$3:$T$3,0)),0) -> 0 | C113: =IFERROR(INDEX(Stock!$A$3:$T$92,MATCH('Bishops Fonthill Overview'!$A113,Stock!$A$3:$A$92,0),MATCH('Bishops Fonthill Overview'!C$69,Stock!$A$3:$T$3,0)),0) -> 0 | D113: =C113-B113 -> 0 | F113: =IFERROR(INDEX(Stock!$A$3:$T$92,MATCH('Bishops Fonthill Overview'!$A113,Stock!$A$3:$A$92,0),MATCH('Bishops Fonthill Overview'!F$69,Stock!$A$3:$T$3,0)),0) | G113: =IFERROR(INDEX(Stock!$A$3:$T$92,MATCH('Bishops Fonthill Overview'!$A113,Stock!$A$3:$A$92,0),MATCH('Bishops Fonthill Overview'!G$69,Stock!$A$3:$T$3,0)),0)
A114: Calf hides | B114: =IFERROR(INDEX(Stock!$A$3:$T$92,MATCH('Bishops Fonthill Overview'!$A114,Stock!$A$3:$A$92,0),MATCH('Bishops Fonthill Overview'!B$69,Stock!$A$3:$T$3,0)),0) -> 0 | C114: =IFERROR(INDEX(Stock!$A$3:$T$92,MATCH('Bishops Fonthill Overview'!$A114,Stock!$A$3:$A$92,0),MATCH('Bishops Fonthill Overview'!C$69,Stock!$A$3:$T$3,0)),0) -> 0 | D114: =C114-B114 -> 0 | F114: =IFERROR(INDEX(Stock!$A$3:$T$92,MATCH('Bishops Fonthill Overview'!$A114,Stock!$A$3:$A$92,0),MATCH('Bishops Fonthill Overview'!F$69,Stock!$A$3:$T$3,0)),0) | G114: =IFERROR(INDEX(Stock!$A$3:$T$92,MATCH('Bishops Fonthill Overview'!$A114,Stock!$A$3:$A$92,0),MATCH('Bishops Fonthill Overview'!G$69,Stock!$A$3:$T$3,0)),0)
A115: Pig hides | B115: =IFERROR(INDEX(Stock!$A$3:$T$92,MATCH('Bishops Fonthill Overview'!$A115,Stock!$A$3:$A$92,0),MATCH('Bishops Fonthill Overview'!B$69,Stock!$A$3:$T$3,0)),0) -> 0 | C115: =IFERROR(INDEX(Stock!$A$3:$T$92,MATCH('Bishops Fonthill Overview'!$A115,Stock!$A$3:$A$92,0),MATCH('Bishops Fonthill Overview'!C$69,Stock!$A$3:$T$3,0)),0) -> 0 | D115: =C115-B115 -> 0 | F115: =IFERROR(INDEX(Stock!$A$3:$T$92,MATCH('Bishops Fonthill Overview'!$A115,Stock!$A$3:$A$92,0),MATCH('Bishops Fonthill Overview'!F$69,Stock!$A$3:$T$3,0)),0) | G115: =IFERROR(INDEX(Stock!$A$3:$T$92,MATCH('Bishops Fonthill Overview'!$A115,Stock!$A$3:$A$92,0),MATCH('Bishops Fonthill Overview'!G$69,Stock!$A$3:$T$3,0)),0)
A116: Weather woolskins | B116: =IFERROR(INDEX(Stock!$A$3:$T$92,MATCH('Bishops Fonthill Overview'!$A116,Stock!$A$3:$A$92,0),MATCH('Bishops Fonthill Overview'!B$69,Stock!$A$3:$T$3,0)),0) -> 0 | C116: =IFERROR(INDEX(Stock!$A$3:$T$92,MATCH('Bishops Fonthill Overview'!$A116,Stock!$A$3:$A$92,0),MATCH('Bishops Fonthill Overview'!C$69,Stock!$A$3:$T$3,0)),0) -> 0 | D116: =C116-B116 -> 0 | F116: =IFERROR(INDEX(Stock!$A$3:$T$92,MATCH('Bishops Fonthill Overview'!$A116,Stock!$A$3:$A$92,0),MATCH('Bishops Fonthill Overview'!F$69,Stock!$A$3:$T$3,0)),0) | G116: =IFERROR(INDEX(Stock!$A$3:$T$92,MATCH('Bishops Fonthill Overview'!$A116,Stock!$A$3:$A$92,0),MATCH('Bishops Fonthill Overview'!G$69,Stock!$A$3:$T$3,0)),0)
A117: Ram woolskins | B117: =IFERROR(INDEX(Stock!$A$3:$T$92,MATCH('Bishops Fonthill Overview'!$A117,Stock!$A$3:$A$92,0),MATCH('Bishops Fonthill Overview'!B$69,Stock!$A$3:$T$3,0)),0) -> 0 | C117: =IFERROR(INDEX(Stock!$A$3:$T$92,MATCH('Bishops Fonthill Overview'!$A117,Stock!$A$3:$A$92,0),MATCH('Bishops Fonthill Overview'!C$69,Stock!$A$3:$T$3,0)),0) -> 0 | D117: =C117-B117 -> 0 | F117: =IFERROR(INDEX(Stock!$A$3:$T$92,MATCH('Bishops Fonthill Overview'!$A117,Stock!$A$3:$A$92,0),MATCH('Bishops Fonthill Overview'!F$69,Stock!$A$3:$T$3,0)),0) | G117: =IFERROR(INDEX(Stock!$A$3:$T$92,MATCH('Bishops Fonthill Overview'!$A117,Stock!$A$3:$A$92,0),MATCH('Bishops Fonthill Overview'!G$69,Stock!$A$3:$T$3,0)),0)
A118: Ewe woolskins | B118: =IFERROR(INDEX(Stock!$A$3:$T$92,MATCH('Bishops Fonthill Overview'!$A118,Stock!$A$3:$A$92,0),MATCH('Bishops Fonthill Overview'!B$69,Stock!$A$3:$T$3,0)),0) -> 0 | C118: =IFERROR(INDEX(Stock!$A$3:$T$92,MATCH('Bishops Fonthill Overview'!$A118,Stock!$A$3:$A$92,0),MATCH('Bishops Fonthill Overview'!C$69,Stock!$A$3:$T$3,0)),0) -> 0 | D118: =C118-B118 -> 0 | F118: =IFERROR(INDEX(Stock!$A$3:$T$92,MATCH('Bishops Fonthill Overview'!$A118,Stock!$A$3:$A$92,0),MATCH('Bishops Fonthill Overview'!F$69,Stock!$A$3:$T$3,0)),0) | G118: =IFERROR(INDEX(Stock!$A$3:$T$92,MATCH('Bishops Fonthill Overview'!$A118,Stock!$A$3:$A$92,0),MATCH('Bishops Fonthill Overview'!G$69,Stock!$A$3:$T$3,0)),0)
A119: Hogg woolskins | B119: =IFERROR(INDEX(Stock!$A$3:$T$92,MATCH('Bishops Fonthill Overview'!$A119,Stock!$A$3:$A$92,0),MATCH('Bishops Fonthill Overview'!B$69,Stock!$A$3:$T$3,0)),0) -> 0 | C119: =IFERROR(INDEX(Stock!$A$3:$T$92,MATCH('Bishops Fonthill Overview'!$A119,Stock!$A$3:$A$92,0),MATCH('Bishops Fonthill Overview'!C$69,Stock!$A$3:$T$3,0)),0) -> 0 | D119: =C119-B119 -> 0 | F119: =IFERROR(INDEX(Stock!$A$3:$T$92,MATCH('Bishops Fonthill Overview'!$A119,Stock!$A$3:$A$92,0),MATCH('Bishops Fonthill Overview'!F$69,Stock!$A$3:$T$3,0)),0) | G119: =IFERROR(INDEX(Stock!$A$3:$T$92,MATCH('Bishops Fonthill Overview'!$A119,Stock!$A$3:$A$92,0),MATCH('Bishops Fonthill Overview'!G$69,Stock!$A$3:$T$3,0)),0)
A120: Woolskins (total) | B120: =IFERROR(INDEX(Stock!$A$3:$T$92,MATCH('Bishops Fonthill Overview'!$A120,Stock!$A$3:$A$92,0),MATCH('Bishops Fonthill Overview'!B$69,Stock!$A$3:$T$3,0)),0) -> 0 | C120: =IFERROR(INDEX(Stock!$A$3:$T$92,MATCH('Bishops Fonthill Overview'!$A120,Stock!$A$3:$A$92,0),MATCH('Bishops Fonthill Overview'!C$69,Stock!$A$3:$T$3,0)),0) -> 0 | D120: =C120-B120 -> 0 | F120: =IFERROR(INDEX(Stock!$A$3:$T$92,MATCH('Bishops Fonthill Overview'!$A120,Stock!$A$3:$A$92,0),MATCH('Bishops Fonthill Overview'!F$69,Stock!$A$3:$T$3,0)),0) -> 0.11979167 | G120: =IFERROR(INDEX(Stock!$A$3:$T$92,MATCH('Bishops Fonthill Overview'!$A120,Stock!$A$3:$A$92,0),MATCH('Bishops Fonthill Overview'!G$69,Stock!$A$3:$T$3,0)),0) -> 0.11979167
... A128: Shorn skins | B128: =IFERROR(INDEX(Stock!$A$3:$T$92,MATCH('Bishops Fonthill Overview'!$A128,Stock!$A$3:$A$92,0),MATCH('Bishops Fonthill Overview'!B$69,Stock!$A$3:$T$3,0)),0) -> 0 | C128: =IFERROR(INDEX(Stock!$A$3:$T$92,MATCH('Bishops Fonthill Overview'!$A128,Stock!$A$3:$A$92,0),MATCH('Bishops Fonthill Overview'!C$69,Stock!$A$3:$T$3,0)),0) -> 0 | D128: =C128-B128 -> 0 | F128: =IFERROR(INDEX(Stock!$A$3:$T$92,MATCH('Bishops Fonthill Overview'!$A128,Stock!$A$3:$A$92,0),MATCH('Bishops Fonthill Overview'!F$69,Stock!$A$3:$T$3,0)),0) | G128: =IFERROR(INDEX(Stock!$A$3:$T$92,MATCH('Bishops Fonthill Overview'!$A128,Stock!$A$3:$A$92,0),MATCH('Bishops Fonthill Overview'!G$69,Stock!$A$3:$T$3,0)),0)
A129: Total value of production (sum of the above) | G129: =SUM(G109:G128) -> 0.11979167
A130: Value of sales | G130: =SUM(F109:F128) -> 0.11979167
A132: Poultry stock | B132: Inherited stock | C132: End-period stock | D132: Stockbuilding | F132: Sales in (£) | G132: Value of production (£) at sales prices
...

Sheet Bishops Fonthill Receipts
A1: BISHOPS FONTHILL RECEIPTS
B2: £ | C2: s | D2: d | F2: Total in £ | G2: Error | H2: Notes
A4: Arrears
A5: arrears from previous year | B5: 11 | C5: 7 | D5: 9 | F5: =B5+C5/20+D5/240 -> 11.3875
A6: of which delivered to treasurer of Wolvesey | B6: 11 | C6: 7 | D6: 9 | F6: =B6+C6/20+D6/240 -> 11.3875
A8: Rents of assize
A9: Christmas | B9: 1 | C9: 5 | D9: 0.75 | F9: =B9+C9/20+D9/240 -> 1.253125
A10: Easter | B10: 1 | C10: 5 | D10: 0.75 | F10: =B10+C10/20+D10/240 -> 1.253125
A11: Feast of John Baptist | B11: 1 | C11: 5 | D11: 0.75 | F11: =B11+C11/20+D11/240 -> 1.253125
A12: Michaelmas | B12: 1 | C12: 5 | D12: 0.75 | F12: =B12+C12/20+D12/240 -> 1.253125
A13: Total recorded in accounts | B13: 5 | D13: 3 | F13: =B13+C13/20+D13/240 -> 5.0125
A14: Total | B14: =SUM(B9:B12) -> 4 | C14: =SUM(C9:C12) -> 20 | D14: =SUM(D9:D12) -> 3 | F14: =B14+C14/20+D14/240 -> 5.0125 | G14: =F14-F13 -> 0
A16: Quittances
A17: 1 reeve for the year | C17: 2 | F17: =B17+C17/20+D17/240 -> 0.1
A18: 1 bartoner for the year | C18: 2 | F18: =B18+C18/20+D18/240 -> 0.1
A19: 1 smith for the year for ironwork of 3 ploughs | C19: 2 | F19: =B19+C19/20+D19/240 -> 0.1
A20: 1 swineherd for the year who oversees harvest | C20: 2 | F20: =B20+C20/20+D20/240 -> 0.1
A21: 2 shepherds, one keeps sheep in pinfold | C21: 3 | D21: 6 | F21: =B21+C21/20+D21/240 -> 0.175
A22: 5 ploughmen for the year | C22: 10 | F22: =B22+C22/20+D22/240 -> 0.5
A23: Total recorded in accounts | B23: 1 | C23: 1 | D23: 6 | F23: =B23+C23/20+D23/240 -> 1.075
A24: Total | B24: =SUM(B17:B22) -> 0 | C24: =SUM(C17:C22) -> 21 | D24: =SUM(D17:D22) -> 6 | F24: =B24+C24/20+D24/240 -> 1.075 | G24: =F24-F23 -> 0
A26: Total of rents remaining | B26: 3 | C26: 18 | D26: 9 | F26: =B26+C26/20+D26/240 -> 3.9375 | H26: not included in receipts
A28: Wax
F29: =B29+C29/20+D29/240 -> 0
A30: Total recorded in accounts | F30: =B30+C30/20+D30/240 -> 0
A31: Total | B31: =SUM(B29) -> 0 | C31: =SUM(C29) -> 0 | D31: =SUM(D29) -> 0 | F31: =B31+C31/20+D31/240 -> 0 | G31: =F31-F30 -> 0
A33: Annual recognizances
A34: from Thomas Tritur | D34: 3 | F34: =B34+C34/20+D34/240 -> 0.0125
A35: from John le Charectyr | D35: 3 | F35: =B35+C35/20+D35/240 -> 0.0125
A36: from John of Fontel | D36: 3 | F36: =B36+C36/20+D36/240 -> 0.0125
A37: Total recorded in accounts | D37: 9 | F37: =B37+C37/20+D37/240 -> 0.0375
A38: Total | B38: =SUM(B34:B36) -> 0 | C38: =SUM(C34:C36) -> 0 | D38: =SUM(D34:D36) -> 9 | F38: =B38+C38/20+D38/240 -> 0.0375 | G38: =F38-F37 -> 0
A40: Issues of the manor
A41: from pannage of pigs | C41: 2 | D41: 2 | F41: =B41+C41/20+D41/240 -> 0.10833333
A42: from residue of Peter's pence | C42: 1 | D42: 11 | F42: =B42+C42/20+D42/240 -> 0.095833333
A43: from 22 pigs sold | B43: 2 | C43: 18 | D43: 7 | F43: =B43+C43/20+D43/240 -> 2.9291667
A44: from 2 oxen sold | C44: 16 | F44: =B44+C44/20+D44/240 -> 0.8
A45: from 51 wethers sold | B45: 2 | C45: 19 | D45: 6 | F45: =B45+C45/20+D45/240 -> 2.975
A46: from skins of 11 wethers and 1 hogg | C46: 2 | D46: 3.5 | F46: =B46+C46/20+D46/240 -> 0.11458333
A47: from skins of 9 wethers and 1 hogg after shearing | E47: 9.5 | F47: =B47+C47/20+D47/240 -> 0
A48: from 34 hens from churchshot sold | C48: 2 | D48: 10 | F48: =B48+C48/20+D48/240 -> 0.14166667
A49: from reeve for release from labour service | C49: 2 | D49: 6 | F49: =B49+C49/20+D49/240 -> 0.125
A50: from the labour service and churchscot of the lands of William son of John (reeve) | C50: 2 | F50: =B50+C50/20+D50/240 -> 0.1
A51: for release of labour at harvest time | C51: 2 | F51: =B51+C51/20+D51/240 -> 0.1
A52: from2 stone of wool locks sold | C52: 3 | D52: 8 | F52: =B52+C52/20+D52/240 -> 0.18333333
A53: from the fleeces of 10 lambs sold | D53: 10 | F53: =B53+C53/20+D53/240 -> 0.041666667
A54: Total recorded in accounts | B54: 7 | C54: 15 | D54: 1 | F54: =B54+C54/20+D54/240 -> 7.7541667
A55: Total | B55: =SUM(B41:B53) -> 4 | C55: =SUM(C41:C53) -> 69 | D55: =SUM(D41:D53) -> 63.5 | F55: =B55+C55/20+D55/240 -> 7.7145833 | G55: =F55-F54 -> -0.039583333
A57: Sale of corn
A58: from 59 qrs 3 bus of wheat | B58: 14 | C58: 16 | D58: 10.5 | F58: =B58+C58/20+D58/240 -> 14.84375
A59: from 1 qr 1 bus of curall sold | C59: 2 | D59: 3 | F59: =B59+C59/20+D59/240 -> 0.1125
A60: from 29 qrs 6 bus of barley sold | B60: 4 | C60: 19 | D60: 2 | F60: =B60+C60/20+D60/240 -> 4.9583333
A61: from 25 qrs of oats sold | B61: 2 | C61: 8 | D61: 4 | F61: =B61+C61/20+D61/240 -> 2.4166667
A62: from 3 qrs of vetches sold | C62: 6 | F62: =B62+C62/20+D62/240 -> 0.3
A63: Total recorded in accounts | B63: 22 | C63: 12 | D63: 7.5 | F63: =B63+C63/20+D63/240 -> 22.63125
A64: Total | B64: =SUM(B58:B62) -> 20 | C64: =SUM(C58:C62) -> 51 | D64: =SUM(D58:D62) -> 19.5 | F64: =B64+C64/20+D64/240 -> 22.63125 | G64: =F64-F63 -> 0
A66: Entry and marriage fines
A67: from tithingpenny at martinmas | C67: 3 | F67: =B67+C67/20+D67/240 -> 0.15
A68: from same tithing at Hockday | C68: 3 | F68: =B68+C68/20+D68/240 -> 0.15
A69: from Alice Stevenes for marrying herself to a certain Thomas, son of Robert de Burton' | C69: 5 | F69: =B69+C69/20+D69/240 -> 0.25
A70: Total recorded in accounts | C70: 11 | F70: =B70+C70/20+D70/240 -> 0.55
A71: Total | B71: =SUM(B67:B69) -> 0 | C71: =SUM(C67:C69) -> 11 | D71: =SUM(D67:D69) -> 0 | F71: =B71+C71/20+D71/240 -> 0.55 | G71: =F71-F70 -> 0
A73: Pleas and perquisites
A74: from details in court rolls | B74: 2 | D74: 10 | F74: =B74+C74/20+D74/240 -> 2.0416667
A75: Total recorded in accounts | B75: 2 | D75: 10 | F75: =B75+C75/20+D75/240 -> 2.0416667
A76: Total | B76: =SUM(B74) -> 2 | C76: =SUM(C74) -> 0 | D76: =SUM(D74) -> 10 | F76: =B76+C76/20+D76/240 -> 2.0416667 | G76: =F76-F75 -> 0
A78: Total of all receipts (sum of above excl. arrears) | B78: =B79-B5 -> 30 | C78: =C79-C5 -> 172 | D78: =D79-D5 -> 111 | F78: =B78+C78/20+D78/240 -> 39.0625
A79: Total of all receipts (sum of above incl. arrears) | B79: =SUM(B5,B14,B24,B31,B38,B55,B64,B71,B76) -> 41 | C79: =SUM(C5,C14,C24,C31,C38,C55,C64,C71,C76) -> 179 | D79: =SUM(D5,D14,D24,D31,D38,D55,D64,D71,D76) -> 120 | F79: =B79+C79/20+D79/240 -> 50.45
A80: Total of all receipts in account excl. arrears | B80: 36 | C80: 19 | D80: 0.5 | F80: =B80+C80/20+D80/240 -> 36.952083 | G80: =F80-F78 -> -2.1104167
A81: Total of all receipts in account incl. arrears

Sheet Bishops Fonthill Expenses
A1: BISHOPS FONTHILL EXPENSES
B2: £ | C2: s | D2: d | F2: Total in £ | G2: Error | H2: Notes
A3: Cost of Ploughs
A4: in iron and steel for 3 ploughs | C4: 10 | D4: 6 | F4: =B4+C4/20+D4/240 -> 0.525
A5: in 3 pairs of wheels bought | C5: 1 | F5: =B5+C5/20+D5/240 -> 0.05
A6: in 9 yokes bought | C6: 1 | F6: =B6+C6/20+D6/240 -> 0.05
A7: in 3 plough feet bought | D7: 9 | F7: =B7+C7/20+D7/240 -> 0.0375
A8: in 2 ploughshares bought | C8: 1 | D8: 8 | F8: =B8+C8/20+D8/240 -> 0.083333333
A9: in stipend of 1 carpenter making 3 ploughs | D9: 6 | F9: =B9+C9/20+D9/240 -> 0.025
A10: given to the smith in place of 2 trunks | C10: 2 | F10: =B10+C10/20+D10/240 -> 0.1
A11: in stipend of 1 oxherd for the year | C11: 3 | F11: =B11+C11/20+D11/240 -> 0.15
A12: in 6 oxen bought for ploughs | B12: 2 | C12: 12 | F12: =B12+C12/20+D12/240 -> 2.6
A13: Total recorded in accounts | B13: 3 | C13: 12 | D13: 5 | F13: =B13+C13/20+D13/240 -> 3.6208333
A14: Total | B14: =SUM(B3:B12) -> 2 | C14: =SUM(C3:C12) -> 30 | D14: =SUM(D3:D12) -> 29 | F14: =B14+C14/20+D14/240 -> 3.6208333 | G14: =F14-F13 -> 0
A15: Total capital expenses | B15: =SUM(B4:B10) -> 0 | C15: =SUM(C4:C10) -> 15 | D15: =SUM(D4:D10) -> 29 | F15: =B15+C15/20+D15/240 -> 0.87083333
A17: Cost of Carts and Wagons
A18: in clouts and nails bought for the cart | D18: 4 | F18: =B18+C18/20+D18/240 -> 0.016666667
A19: in 2 axles bought | D19: 4 | F19: =B19+C19/20+D19/240 -> 0.016666667
A20: in grease | D20: 2 | F20: =B20+C20/20+D20/240 -> 0.0083333333
A21: in stipend of 1 making 2 collars | D21: 3 | F21: =B21+C21/20+D21/240 -> 0.0125
A22: in 2 halters | D22: 2 | F22: =B22+C22/20+D22/240 -> 0.0083333333
A23: in shoeing 2 plough-horses | C23: 3 | F23: =B23+C23/20+D23/240 -> 0.15
A24: in 2 ropes bought for tethering plough horses | D24: 2 | F24: =B24+C24/20+D24/240 -> 0.0083333333
A25: in stipend of 1 carter | C25: 3 | F25: =B25+C25/20+D25/240 -> 0.15
A26: in 1 pair of traces | D26: 6 | F26: =B26+C26/20+D26/240 -> 0.025
A27: in re-covering 1 saddle | D27: 1 | F27: =B27+C27/20+D27/240 -> 0.0041666667
A28: Total recorded in accounts | C28: 8 | F28: =B28+C28/20+D28/240 -> 0.4
A29: Total | B29: =SUM(B18:B27) -> 0 | C29: =SUM(C18:C27) -> 6 | D29: =SUM(D18:D27) -> 24 | F29: =B29+C29/20+D29/240 -> 0.4 | G29: =F29-F28 -> 0
A30: Total capital expenses | B30: =SUM(B18:B24,B26:B27) -> 0 | C30: =SUM(C18:C24,C26:C27) -> 3 | D30: =SUM(D18:D24,D26:D27) -> 24 | F30: =B30+C30/20+D30/240 -> 0.25
A32: Cost of Buildings
A33: in stipend of 1 man re-roofing | C33: 1 | F33: =B33+C33/20+D33/240 -> 0.05
A34: in 1 cask bought and others repaired | C34: 3 | D34: 4.5 | F34: =B34+C34/20+D34/240 -> 0.16875
A35: in stipend of 1 man repairing the press | C35: 2 | F35: =B35+C35/20+D35/240 -> 0.1
A36: in grease bought for the same | D36: 3 | F36: =B36+C36/20+D36/240 -> 0.0125
A37: in stipend of 1 man making anew gate | C37: 2 | F37: =B37+C37/20+D37/240 -> 0.1
A38: in 1 shovel bought | D38: 1.5 | F38: =B38+C38/20+D38/240 -> 0.00625
A39: Total recorded in accounts | C39: 8 | D39: 9 | F39: =B39+C39/20+D39/240 -> 0.4375
A40: Total | B40: =SUM(B33:B38) -> 0 | C40: =SUM(C33:C38) -> 8 | D40: =SUM(D33:D38) -> 9 | F40: =B40+C40/20+D40/240 -> 0.4375 | G40: =F40-F39 -> 0
A41: Total capital expenses | B41: =SUM(B33:B38) -> 0 | C41: =SUM(C33:C38) -> 8 | D41: =SUM(D33:D38) -> 9
A43: Sheepcote
A44: in grease bought | C44: 5 | F44: =B44+C44/20+D44/240 -> 0.25
A45: in making anew 9 hurdles | D45: 3 | F45: =B45+C45/20+D45/240 -> 0.0125
A46: in 8 ells of canvas bought for packing wool | C46: 2 | F46: =B46+C46/20+D46/240 -> 0.1
A47: in packing the said wool | D47: 8 | F47: =B47+C47/20+D47/240 -> 0.033333333
A48: Total recorded in accounts | C48: 7 | D48: 11 | F48: =B48+C48/20+D48/240 -> 0.39583333
A49: Total | B49: =SUM(B44:B47) -> 0 | C49: =SUM(C44:C47) -> 7 | D49: =SUM(D44:D47) -> 11 | F49: =B49+C49/20+D49/240 -> 0.39583333 | G49: =F49-F48 -> 0
A50: Total capital expenses | B50: =SUM(B44:B45) -> 0 | C50: =SUM(C44:C45) -> 5 | D50: =SUM(D44:D45) -> 3 | F50: =B50+C50/20+D50/240 -> 0.2625
A52: Threshing
A53: in threshing and winnowing 72 qrs 2 bus of wheat, 1 qr 1 bus of curall and 7 qrs of bere by piecework | C53: 15 | D53: 0.75 | F53: =B53+C53/20+D53/240 -> 0.753125
A54: in threshing and winnowing 58 qrs 7 bus of barley and 5 qrs 2 bus of vetches | C54: 6 | D54: 7.75 | F54: =B54+C54/20+D54/240 -> 0.33229167
A55: in threshing and winnowing 55 qrs 6 bus of oats | C55: 2 | D55: 9.5 | F55: =B55+C55/20+D55/240 -> 0.13958333
A56: in 1 sack bought | D56: 8 | F56: =B56+C56/20+D56/240 -> 0.033333333
A57: Total recorded in accounts | B57: 1 | C57: 5 | D57: 2 | F57: =B57+C57/20+D57/240 -> 1.2583333
A58: Total | B58: =SUM(B53:B56) -> 0 | C58: =SUM(C53:C56) -> 23 | D58: =SUM(D53:D56) -> 26 | F58: =B58+C58/20+D58/240 -> 1.2583333 | G58: =F58-F57 -> 0
A60: Expenses of the Harvest
A61: in weeding the corn (wheat barley and oats) | C61: 2 | D61: 8 | F61: =B61+C61/20+D61/240 -> 0.13333333
A62: in customary payment to 1 overseer of the harvest | D62: 4 | F62: =B62+C62/20+D62/240 -> 0.016666667
A63: in mowing and tossing the meadow | C63: 2 | F63: =B63+C63/20+D63/240 -> 0.1
A64: in stipend of 1 overseer of the harvest for the year | C64: 6 | D64: 8 | F64: =B64+C64/20+D64/240 -> 0.33333333
A65: Total recorded in accounts | C65: 11 | D65: 8 | F65: =B65+C65/20+D65/240 -> 0.58333333
A66: Total | B66: =SUM(B61:B64) -> 0 | C66: =SUM(C61:C64) -> 10 | D66: =SUM(D61:D64) -> 20 | F66: =B66+C66/20+D66/240 -> 0.58333333 | G66: =F66-F65 -> 0
A68: Bailiff's Expenses
A69: in expense for his visits | C69: 2 | D69: 6 | F69: =B69+C69/20+D69/240 -> 0.125
A70: Total recorded in accounts | C70: 2 | D70: 6 | F70: =B70+C70/20+D70/240 -> 0.125
A71: Total | B71: =SUM(B69:B69) -> 0 | C71: =SUM(C69:C69) -> 2 | D71: =SUM(D69:D69) -> 6 | F71: =B71+C71/20+D71/240 -> 0.125 | G71: =F71-F70 -> 0
A73: Total of all Expenses | B73: 6 | C73: 16 | D73: 5 | F73: =B73+C73/20+D73/240 -> 6.8208333
A74: Total of all Expenses (calculated) | B74: =SUM(B14,B29,B40,B49,B58,B71+B66) -> 2 | C74: =SUM(C14,C29,C40,C49,C58,C71+C66) -> 86 | D74: =SUM(D14,D29,D40,D49,D58,D71+D66) -> 125 | F74: =B74+C74/20+D74/240 -> 6.8208333 | G74: =F74-F73 -> 0
A75: And thus he owes | B75: 30 | C75: 2 | D75: 7.5 | F75: =B75+C75/20+D75/240 -> 30.13125
A76: Delivered to Sir Geoffrey, treasurer of Wolvesey | B76: 21 | C76: 12 | F76: =B76+C76/20+D76/240 -> 21.6
A77: and thus he owes clear | B77: 8 | C77: 10 | D77: 7.5 | F77: =B77+C77/20+D77/240 -> 8.53125
A78: Total capital expenses | B78: =SUM(B15,B30,B41,B50) -> 0 | C78: =SUM(C15,C30,C41,C50) -> 31 | D78: =SUM(D15,D30,D41,D50) -> 65 | F78: =B78+C78/20+D78/240 -> 1.8208333

Sheet Issues of the Grange
B1: The issue of the grange account gives the total "yield" at the top of each heading in curly brackets, measurements used: fold, qrs, bus
B2: In "Issues of the grange" (p.xx) | G2: In "Sale of Corn" (p.x) | P2: Value of Total Production
A3: Gross output | B3: Quantity | D3: Additional bought-in | F3: Quantity | G3: Quantity noted as sold | J3: Difference Produced vs. Sold | K3: Price 1 | L3: Quantity 1 | M3: Price 2 | N3: Quantity 2 | O3: Unit price | P3: Value
B4: qrs | C4: bus | D4: qrs | E4: bus | F4: qrs | G4: qrs | H4: bus | I4: qrs | K4: £ | L4: qrs | M4: £ | N4: qrs | O4: £ per qr | P4: £
A5: Wheat | B5: 81 | C5: 7 | F5: =B5+D5+C5/8+E5/8 -> 81.875 | G5: 59 | H5: 3 | I5: =G5+H5/8 -> 59.375 | J5: =F5-I5 -> 22.5 | K5: ='Bishops Fonthill Receipts'!F58 -> 14.84375 | L5: =I5 -> 59.375 | O5: =IFERROR((K5+M5)/(L5+N5),0) -> 0.25 | P5: =O5*F5 -> 20.46875
A6: Curall | B6: 1 | C6: 1 | F6: =B6+D6+C6/8+E6/8 -> 1.125 | G6: 1 | H6: 1 | I6: =G6+H6/8 -> 1.125 | J6: =F6-I6 -> 0 | K6: ='Bishops Fonthill Receipts'!F59 -> 0.1125 | L6: =I6 -> 1.125 | O6: =IFERROR((K6+M6)/(L6+N6),0) -> 0.1 | P6: =O6*F6 -> 0.1125
A7: Barley | B7: 64 | F7: =B7+D7+C7/8+E7/8 -> 64 | G7: 29 | H7: 6 | I7: =G7+H7/8 -> 29.75 | J7: =F7-I7 -> 34.25 | K7: ='Bishops Fonthill Receipts'!F60 -> 4.9583333 | L7: =I7 -> 29.75 | O7: =IFERROR((K7+M7)/(L7+N7),0) -> 0.16666667 | P7: =O7*F7 -> 10.666667
A8: Oats | B8: 59 | C8: 6 | F8: =B8+D8+C8/8+E8/8 -> 59.75 | G8: 25 | I8: =G8+H8/8 -> 25 | J8: =F8-I8 -> 34.75 | K8: ='Bishops Fonthill Receipts'!F61 -> 2.4166667 | L8: =I8 -> 25 | O8: =IFERROR((K8+M8)/(L8+N8),0) -> 0.096666667 | P8: =O8*F8 -> 5.7758333
A9: Bere | B9: 10 | F9: =B9+D9+C9/8+E9/8 -> 10 | G9: 0 | H9: 0 | I9: =G9+H9/8 -> 0 | J9: =F9-I9 -> 10 | K9: 0 | L9: =I9 -> 0 | O9: =IFERROR((K9+M9)/(L9+N9),0) -> 0 | P9: =O9*F9 -> 0
A10: Vetches | B10: 6 | C10: 2 | F10: =B10+D10+C10/8+E10/8 -> 6.25 | G10: 3 | I10: =G10+H10/8 -> 3 | J10: =F10-I10 -> 3.25 | K10: ='Bishops Fonthill Receipts'!F62 -> 0.3 | L10: =I10 -> 3 | O10: =IFERROR((K10+M10)/(L10+N10),0) -> 0.1 | P10: =O10*F10 -> 0.625
A12: Total Production | F12: =SUM(F5:F10) -> 223 | I12: =SUM(I5:I10) -> 118.25 | J12: =SUM(J5:J10) -> 104.75 | P12: =SUM(P5:P10) -> 37.64875 | Q12: Production value is significantly more, as much less was sold than what was produced
A13: Sales of corn (as recorded in accounts) | F13: =SUM(K5:K10,M5:M10) -> 22.63125
A16: Net output | B16: Gross output | C16: Seed | F16: tithe | G16: to manorial servants & livestock | J16: Output net of tithe & seed & liveries to manorial servants | K16: in stock from last year | L16: Price | M16: Value of net output | N16: Value of sales (in "Sale of Corn")
B17: qrs | C17: qrs | D17: bus | E17: qrs | F17: qrs | G17: qrs | H17: bus | I17: qrs | J17: qrs | K17: qrs | L17: £ per qr | M17: £ | N17: £
A18: Wheat | B18: =F5 -> 81.875 | C18: 13.5 | E18: =C18+D18/8 -> 13.5 | G18: 8 | H18: 8 | I18: =G18+H18/8 -> 9 | J18: =B18-(E18+F18+I18) -> 59.375 | L18: =O5 -> 0.25 | M18: =L18*J18 -> 14.84375 | N18: =K5 -> 14.84375
A19: Curall | B19: =F6 -> 1.125 | E19: =C19+D19/8 -> 0 | I19: =G19+H19/8 -> 0 | J19: =B19-(E19+F19+I19) -> 1.125 | L19: =O6 -> 0.1 | M19: =L19*J19 -> 0.1125 | N19: =K6 -> 0.1125
A20: Barley | B20: =F7 -> 64 | C20: 13 | E20: =C20+D20/8 -> 13 | G20: 21 | H20: 2 | I20: =G20+H20/8 -> 21.25 | J20: =B20-(E20+F20+I20) -> 29.75 | L20: =O7 -> 0.16666667 | M20: =L20*J20 -> 4.9583333 | N20: =K7 -> 4.9583333
A21: Oats | B21: =F8 -> 59.75 | C21: 26 | D21: 5 | E21: =C21+D21/8 -> 26.625 | G21: 8 | H21: 1 | I21: =G21+H21/8 -> 8.125 | J21: =B21-(E21+F21+I21) -> 25 | L21: =O8 -> 0.096666667 | M21: =L21*J21 -> 2.4166667 | N21: =K8 -> 2.4166667
A22: Bere | B22: =F9 -> 10 | C22: 7 | E22: =C22+D22/8 -> 7 | G22: 3 | I22: =G22+H22/8 -> 3 | J22: =B22-(E22+F22+I22) -> 0 | L22: =O9 -> 0 | M22: =L22*J22 -> 0 | N22: =K9 -> 0
A23: Vetches | B23: =F10 -> 6.25 | C23: 1 | D23: 7 | E23: =C23+D23/8 -> 1.875 | G23: 1 | H23: 3 | I23: =G23+H23/8 -> 1.375 | J23: =B23-(E23+F23+I23) -> 3
A24: Liveries of manorial servants
A25: Total | B25: =SUM(B18:B23) -> 223 | E25: =SUM(E18:E23) -> 62 | J25: =SUM(J18:J23) -> 118.25 | M25: =SUM(M18:M23) -> 22.33125 | N25: =SUM(N18:N22) -> 22.33125

Sheet Stock
A1: EAST KNOYLE STOCK ACCOUNT
A3: Livestock | B3: Inherited stock | C3: bought | D3: produced | E3: strays | F3: herbage | G3: sold | H3: in murrain | I3: accounted for elsewhere | J3: End-period stock | K3: cross-check | L3: price 1 | M3: units 1 | N3: price 2 | O3: units 2 | P3: Weight (weys) | Q3: Unit price (£) | R3: Value of production (£) at sales prices | S3: Sales in (£) | T3: Details
A4: Cart-horses | K4: =B4+C4+D4-E4-F4-G4-H4-I4 -> 0 | Q4: =IFERROR((L4+N4)/(M4+O4),"") | R4: =IFERROR(D4*Q4,"") | S4: =IFERROR(Q4*G4,"")
A5: Mares | K5: =B5+C5+D5-E5-F5-G5-H5-I5 -> 0 | Q5: =IFERROR((L5+N5)/(M5+O5),"") | R5: =IFERROR(D5*Q5,"") | S5: =IFERROR(Q5*G5,"")
A6: Plough horses | B6: 2 | J6: 2 | K6: =B6+C6+D6-E6-F6-G6-H6-I6 -> 2 | Q6: =IFERROR((L6+N6)/(M6+O6),"") | R6: =IFERROR(D6*Q6,"") | S6: =IFERROR(Q6*G6,"")
A7: Colts (2 years) | K7: =B7+C7+D7-E7-F7-G7-H7-I7 -> 0 | Q7: =IFERROR((L7+N7)/(M7+O7),"") | R7: =IFERROR(D7*Q7,"") | S7: =IFERROR(Q7*G7,"")
A8: Colts (2 years) | K8: =B8+C8+D8-E8-F8-G8-H8-I8 -> 0 | Q8: =IFERROR((L8+N8)/(M8+O8),"") | R8: =IFERROR(D8*Q8,"") | S8: =IFERROR(Q8*G8,"")
A9: Colts (1 year) | K9: =B9+C9+D9-E9-F9-G9-H9-I9 -> 0 | Q9: =IFERROR((L9+N9)/(M9+O9),"") | R9: =IFERROR(D9*Q9,"") | S9: =IFERROR(Q9*G9,"")
A10: Foals | K10: =B10+C10+D10-E10-F10-G10-H10-I10 -> 0 | Q10: =IFERROR((L10+N10)/(M10+O10),"") | R10: =IFERROR(D10*Q10,"") | S10: =IFERROR(Q10*G10,"")
A11: Oxen | B11: 24 | C11: 6 | G11: 2 | K11: =B11+C11+D11-E11-F11-G11-H11-I11 -> 28 | L11: ='Bishops Fonthill Receipts'!F44 -> 0.8 | M11: 2 | Q11: =IFERROR((L11+N11)/(M11+O11),"") -> 0.4 | R11: =IFERROR(C11*Q11,"") -> 2.4 | S11: =IFERROR(Q11*G11,"") -> 0.8
A12: Bulls | K12: =B12+C12+D12-E12-F12-G12-H12-I12 -> 0 | Q12: =IFERROR((L12+N12)/(M12+O12),"") | R12: =IFERROR(D12*Q12,"") | S12: =IFERROR(Q12*G12,"")
A13: Cows | K13: =B13+C13+D13-E13-F13-G13-H13-I13 -> 0 | Q13: =IFERROR((L13+N13)/(M13+O13),"") | R13: =IFERROR(D13*Q13,"") | S13: =IFERROR(Q13*G13,"")
A14: Steers | K14: =B14+C14+D14-E14-F14-G14-H14-I14 -> 0 | Q14: =IFERROR((L14+N14)/(M14+O14),"") | R14: =IFERROR(D14*Q14,"") | S14: =IFERROR(Q14*G14,"")
A15: Bullocks | K15: =B15+C15+D15-E15-F15-G15-H15-I15 -> 0 | Q15: =IFERROR((L15+N15)/(M15+O15),"") | R15: =IFERROR(D15*Q15,"") | S15: =IFERROR(Q15*G15,"")
A16: Yearlings | K16: =B16+C16+D16-E16-F16-G16-H16-I16 -> 0 | Q16: =IFERROR((L16+N16)/(M16+O16),"") | R16: =IFERROR(D16*Q16,"") | S16: =IFERROR(Q16*G16,"")
A17: Calves | K17: =B17+C17+D17-E17-F17-G17-H17-I17 -> 0 | Q17: =IFERROR((L17+N17)/(M17+O17),"") | R17: =IFERROR(D17*Q17,"") | S17: =IFERROR(Q17*G17,"")
A18: Wethers | B18: 323 | D18: 34 | G18: 51 | H18: 21 | J18: 285 | K18: =B18+C18+D18-E18-F18-G18-H18-I18 -> 285 | L18: ='Bishops Fonthill Receipts'!F45 -> 2.975 | M18: 51 | Q18: =IFERROR((L18+N18)/(M18+O18),"") -> 0.058333333 | R18: =IFERROR(D18*Q18,"") -> 1.9833333 | S18: =IFERROR(Q18*G18,"") -> 2.975
A19: Rams | K19: =B19+C19+D19-E19-F19-G19-H19-I19 -> 0 | Q19: =IFERROR((L19+N19)/(M19+O19),"") | R19: =IFERROR(D19*Q19,"") | S19: =IFERROR(Q19*G19,"")
A20: Ewes | K20: =B20+C20+D20-E20-F20-G20-H20-I20 -> 0 | Q20: =IFERROR((L20+N20)/(M20+O20),"") | R20: =IFERROR(D20*Q20,"") | S20: =IFERROR(Q20*G20,"")
A21: Hoggs | K21: =B21+C21+D21-E21-F21-G21-H21-I21 -> 0 | Q21: =IFERROR((L21+N21)/(M21+O21),"") | R21: =IFERROR(D21*Q21,"") | S21: =IFERROR(Q21*G21,"")
A22: Lambs | D22: 10 | J22: 10 | K22: =B22+C22+D22-E22-F22-G22-H22-I22 -> 10 | Q22: =IFERROR((L22+N22)/(M22+O22),"") | R22: =IFERROR(D22*Q22,"") | S22: =IFERROR(Q22*G22,"")
A23: Boars | K23: =B23+C23+D23-E23-F23-G23-H23-I23 -> 0 | Q23: =IFERROR((L23+N23)/(M23+O23),"") | R23: =IFERROR(D23*Q23,"") | S23: =IFERROR(Q23*G23,"")
A24: Sows | K24: =B24+C24+D24-E24-F24-G24-H24-I24 -> 0 | Q24: =IFERROR((L24+N24)/(M24+O24),"") | R24: =IFERROR(D24*Q24,"") | S24: =IFERROR(Q24*G24,"")
A25: Pigs | B25: 40 | D25: 24 | G25: 26 | H25: 12 | J25: 26 | K25: =B25+C25+D25-E25-F25-G25-H25-I25 -> 26 | L25: ='Bishops Fonthill Receipts'!F43 -> 2.9291667 | M25: 22 | Q25: =IFERROR((L25+N25)/(M25+O25),"") -> 0.13314394 | R25: =IFERROR(D25*Q25,"") -> 3.1954545 | S25: =IFERROR(Q25*G25,"") -> 3.4617424 | T25: Sold doesn’t match receipts
A26: Hoggets | B26: 28 | H26: 4 | I26: 24 | J26: 0 | K26: =B26+C26+D26-E26-F26-G26-H26-I26 -> 0 | Q26: =IFERROR((L26+N26)/(M26+O26),"") | R26: =IFERROR(D26*Q26,"") | S26: =IFERROR(Q26*G26,"")
A27: Piglets | D27: 33 | H27: 17 | I27: 3 | J27: 13 | K27: =B27+C27+D27-E27-F27-G27-H27-I27 -> 13 | Q27: =IFERROR((L27+N27)/(M27+O27),"") | R27: =IFERROR(D27*Q27,"") | S27: =IFERROR(Q27*G27,"")
A28: Swans | K28: =B28+C28+D28-E28-F28-G28-H28-I28 -> 0 | Q28: =IFERROR((L28+N28)/(M28+O28),"") | R28: =IFERROR(D28*Q28,"") | S28: =IFERROR(Q28*G28,"")
A29: Peacocks | K29: =B29+C29+D29-E29-F29-G29-H29-I29 -> 0 | Q29: =IFERROR((L29+N29)/(M29+O29),"") | R29: =IFERROR(D29*Q29,"") | S29: =IFERROR(Q29*G29,"")
A30: Total | S30: =SUM(S4:S29) -> 7.2367424
K31: =B31+C31+D31-E31-F31-G31-H31-I31 -> 0 | Q31: =IFERROR((L31+N31)/(M31+O31),"") | R31: =IFERROR(D31*Q31,"") | S31: =IFERROR(Q31*G31,"")
K32: =B32+C32+D32-E32-F32-G32-H32-I32 -> 0 | Q32: =IFERROR((L32+N32)/(M32+O32),"") | R32: =IFERROR(D32*Q32,"") | S32: =IFERROR(Q32*G32,"")
A33: Wool | K33: =B33+C33+D33-E33-F33-G33-H33-I33 -> 0 | Q33: =IFERROR((L33+N33)/(M33+O33),"") | R33: =IFERROR(D33*Q33,"") | S33: =IFERROR(Q33*G33,"")
A34: Fleeces | D34: 316 | G34: 312 | I34: 4 | K34: =B34+C34+D34-E34-F34-G34-H34-I34 -> 0 | P34: =2+12*Assumptions!E5 -> 2.48 | Q34: 0.02 | R34: =IFERROR(D34*Q34,"") -> 6.32 | S34: =IFERROR(Q34*G34,"") -> 6.24 | T34: unit price from overview sheet (UnitPricesStocks_averages)
A35: Coarse wool | K35: =B35+C35+D35-E35-F35-G35-H35-I35 -> 0 | Q35: =IFERROR((L35+N35)/(M35+O35),"") | R35: =IFERROR(D35*Q35,"") | S35: =IFERROR(Q35*G35,"")
A36: Lamb's wool | D36: 10 | G36: 10 | K36: =B36+C36+D36-E36-F36-G36-H36-I36 -> 0 | L36: ='Bishops Fonthill Receipts'!F53 -> 0.041666667 | M36: 10 | Q36: =IFERROR((L36+N36)/(M36+O36),"") -> 0.0041666667 | R36: =IFERROR(D36*Q36,"") -> 0.041666667 | S36: =IFERROR(Q36*G36,"") -> 0.041666667
A37: Wool locks | D37: =P37 -> 0.14285714 | G37: =P37 -> 0.14285714 | K37: =B37+C37+D37-E37-F37-G37-H37-I37 -> 0 | L37: ='Bishops Fonthill Receipts'!F52 -> 0.18333333 | M37: =P37 -> 0.14285714 | P37: =2*Assumptions!E7 -> 0.14285714 | Q37: =IFERROR((L37+N37)/(M37+O37),"") -> 1.2833333 | R37: =IFERROR(D37*Q37,"") -> 0.18333333 | S37: =IFERROR(Q37*G37,"") -> 0.18333333
A38: Wool sold at shearing | K38: =B38+C38+D38-E38-F38-G38-H38-I38 -> 0 | Q38: =IFERROR((L38+N38)/(M38+O38),"") | R38: =IFERROR(D38*Q38,"") | S38: =IFERROR(Q38*G38,"")
A39: Total | K39: =B39+C39+D39-E39-F39-G39-H39-I39 -> 0 | Q39: =IFERROR((L39+N39)/(M39+O39),"") | R39: =IFERROR(D39*Q39,"") | S39: =SUM(S34:S38) -> 6.465
K40: =B40+C40+D40-E40-F40-G40-H40-I40 -> 0 | Q40: =IFERROR((L40+N40)/(M40+O40),"") | R40: =IFERROR(D40*Q40,"") | S40: =IFERROR(Q40*G40,"")
K41: =B41+C41+D41-E41-F41-G41-H41-I41 -> 0 | Q41: =IFERROR((L41+N41)/(M41+O41),"") | R41: =IFERROR(D41*Q41,"") | S41: =IFERROR(Q41*G41,"")
A42: Hides | K42: =B42+C42+D42-E42-F42-G42-H42-I42 -> 0 | Q42: =IFERROR((L42+N42)/(M42+O42),"") | R42: =IFERROR(D42*Q42,"") | S42: =IFERROR(Q42*G42,"")
A43: Ox hides | K43: =B43+C43+D43-E43-F43-G43-H43-I43 -> 0 | Q43: =IFERROR((L43+N43)/(M43+O43),"") | R43: =IFERROR(D43*Q43,"") | S43: =IFERROR(Q43*G43,"")
A44: Cow hides | K44: =B44+C44+D44-E44-F44-G44-H44-I44 -> 0 | Q44: =IFERROR((L44+N44)/(M44+O44),"") | R44: =IFERROR(D44*Q44,"") | S44: =IFERROR(Q44*G44,"")
A45: Mare hides | K45: =B45+C45+D45-E45-F45-G45-H45-I45 -> 0 | Q45: =IFERROR((L45+N45)/(M45+O45),"") | R45: =IFERROR(D45*Q45,"") | S45: =IFERROR(Q45*G45,"")
A46: Steer hides | K46: =B46+C46+D46-E46-F46-G46-H46-I46 -> 0 | Q46: =IFERROR((L46+N46)/(M46+O46),"") | R46: =IFERROR(D46*Q46,"") | S46: =IFERROR(Q46*G46,"")
A47: Yearling Calf hides | K47: =B47+C47+D47-E47-F47-G47-H47-I47 -> 0 | Q47: =IFERROR((L47+N47)/(M47+O47),"") | R47: =IFERROR(D47*Q47,"") | S47: =IFERROR(Q47*G47,"")
A48: Calf hides | K48: =B48+C48+D48-E48-F48-G48-H48-I48 -> 0 | Q48: =IFERROR((L48+N48)/(M48+O48),"") | R48: =IFERROR(D48*Q48,"") | S48: =IFERROR(Q48*G48,"")
A49: Pig hides | K49: =B49+C49+D49-E49-F49-G49-H49-I49 -> 0 | Q49: =IFERROR((L49+N49)/(M49+O49),"") | R49: =IFERROR(D49*Q49,"") | S49: =IFERROR(Q49*G49,"")
A50: Weather woolskins | K50: =B50+C50+D50-E50-F50-G50-H50-I50 -> 0 | Q50: =IFERROR((L50+N50)/(M50+O50),"") | R50: =IFERROR(D50*Q50,"") | S50: =IFERROR(Q50*G50,"")
A51: Ram woolskins | K51: =B51+C51+D51-E51-F51-G51-H51-I51 -> 0 | Q51: =IFERROR((L51+N51)/(M51+O51),"") | R51: =IFERROR(D51*Q51,"") | S51: =IFERROR(Q51*G51,"")
A52: Ewe woolskins | K52: =B52+C52+D52-E52-F52-G52-H52-I52 -> 0 | Q52: =IFERROR((L52+N52)/(M52+O52),"") | R52: =IFERROR(D52*Q52,"") | S52: =IFERROR(Q52*G52,"")
A53: Hogg woolskins | K53: =B53+C53+D53-E53-F53-G53-H53-I53 -> 0 | Q53: =IFERROR((L53+N53)/(M53+O53),"") | R53: =IFERROR(D53*Q53,"") | S53: =IFERROR(Q53*G53,"")
A54: Woolskins (total) | D54: 23 | G54: 23 | K54: =B54+C54+D54-E54-F54-G54-H54-I54 -> 0 | L54: ='Bishops Fonthill Receipts'!F46 -> 0.11458333 | M54: 12 | N54: ='Bishops Fonthill Receipts'!F47 -> 0 | O54: 10 | Q54: =IFERROR((L54+N54)/(M54+O54),"") -> 0.0052083333 | R54: =IFERROR(D54*Q54,"") -> 0.11979167 | S54: =IFERROR(Q54*G54,"") -> 0.11979167 | T54: Sold doesn’t match receipts
A55: Wether bareskins | K55: =B55+C55+D55-E55-F55-G55-H55-I55 -> 0 | Q55: =IFERROR((L55+N55)/(M55+O55),"") | R55: =IFERROR(D55*Q55,"") | S55: =IFERROR(Q55*G55,"")
A56: Ram bareskins | K56: =B56+C56+D56-E56-F56-G56-H56-I56 -> 0 | Q56: =IFERROR((L56+N56)/(M56+O56),"") | R56: =IFERROR(D56*Q56,"") | S56: =IFERROR(Q56*G56,"")
A57: Ewe bareskins | K57: =B57+C57+D57-E57-F57-G57-H57-I57 -> 0 | Q57: =IFERROR((L57+N57)/(M57+O57),"") | R57: =IFERROR(D57*Q57,"") | S57: =IFERROR(Q57*G57,"")
A58: Hogg bareskins | K58: =B58+C58+D58-E58-F58-G58-H58-I58 -> 0 | Q58: =IFERROR((L58+N58)/(M58+O58),"") | R58: =IFERROR(D58*Q58,"") | S58: =IFERROR(Q58*G58,"")
A59: Bareskins (total) | K59: =B59+C59+D59-E59-F59-G59-H59-I59 -> 0 | Q59: =IFERROR((L59+N59)/(M59+O59),"") | R59: =IFERROR(D59*Q59,"") | S59: =IFERROR(Q59*G59,"")
A60: Lambskins | K60: =B60+C60+D60-E60-F60-G60-H60-I60 -> 0 | Q60: =IFERROR((L60+N60)/(M60+O60),"") | R60: =IFERROR(D60*Q60,"") | S60: =IFERROR(Q60*G60,"")
A61: Rotted skins | K61: =B61+C61+D61-E61-F61-G61-H61-I61 -> 0 | Q61: =IFERROR((L61+N61)/(M61+O61),"") | R61: =IFERROR(D61*Q61,"") | S61: =IFERROR(Q61*G61,"")
A62: Shorn skins | K62: =B62+C62+D62-E62-F62-G62-H62-I62 -> 0 | Q62: =IFERROR((L62+N62)/(M62+O62),"") | R62: =IFERROR(D62*Q62,"") | S62: =IFERROR(Q62*G62,"")
A63: Total | S63: =SUM(S42:S62) -> 0.11979167
K64: =B64+C64+D64-E64-F64-G64-H64-I64 -> 0 | Q64: =IFERROR((L64+N64)/(M64+O64),"") | R64: =IFERROR(D64*Q64,"") | S64: =IFERROR(Q64*G64,"")
K65: =B65+C65+D65-E65-F65-G65-H65-I65 -> 0 | Q65: =IFERROR((L65+N65)/(M65+O65),"") | R65: =IFERROR(D65*Q65,"") | S65: =IFERROR(Q65*G65,"")
A66: Poultry stock | K66: =B66+C66+D66-E66-F66-G66-H66-I66 -> 0 | Q66: =IFERROR((L66+N66)/(M66+O66),"") | R66: =IFERROR(D66*Q66,"") | S66: =IFERROR(Q66*G66,"")
A67: Hens | D67: 48 | G67: 34 | I67: 14 | K67: =B67+C67+D67-E67-F67-G67-H67-I67 -> 0 | L67: ='Bishops Fonthill Receipts'!F48 -> 0.14166667 | M67: 34 | Q67: =IFERROR((L67+N67)/(M67+O67),"") -> 0.0041666667 | R67: =IFERROR(D67*Q67,"") -> 0.2 | S67: =IFERROR(Q67*G67,"") -> 0.14166667
A68: Geese | K68: =B68+C68+D68-E68-F68-G68-H68-I68 -> 0 | Q68: =IFERROR((L68+N68)/(M68+O68),"") | R68: =IFERROR(D68*Q68,"") | S68: =IFERROR(Q68*G68,"")
A69: Capons (from chickens) | K69: =B69+C69+D69-E69-F69-G69-H69-I69 -> 0 | Q69: =IFERROR((L69+N69)/(M69+O69),"") | R69: =IFERROR(D69*Q69,"") | S69: =IFERROR(Q69*G69,"")
A70: Cocks & hens | K70: =B70+C70+D70-E70-F70-G70-H70-I70 -> 0 | Q70: =IFERROR((L70+N70)/(M70+O70),"") | R70: =IFERROR(D70*Q70,"") | S70: =IFERROR(Q70*G70,"")
A71: Total | K71: =B71+C71+D71-E71-F71-G71-H71-I71 -> 0 | Q71: =IFERROR((L71+N71)/(M71+O71),"") | R71: =IFERROR(D71*Q71,"") | S71: =SUM(S67:S70) -> 0.14166667
K72: =B72+C72+D72-E72-F72-G72-H72-I72 -> 0 | Q72: =IFERROR((L72+N72)/(M72+O72),"") | R72: =IFERROR(D72*Q72,"") | S72: =IFERROR(Q72*G72,"")
A73: Poultry production | K73: =B73+C73+D73-E73-F73-G73-H73-I73 -> 0 | Q73: =IFERROR((L73+N73)/(M73+O73),"") | R73: =IFERROR(D73*Q73,"") | S73: =IFERROR(Q73*G73,"")
A74: Eggs | K74: =B74+C74+D74-E74-F74-G74-H74-I74 -> 0 | Q74: =IFERROR((L74+N74)/(M74+O74),"") | R74: =IFERROR(D74*Q74,"") | S74: =IFERROR(Q74*G74,"")
A75: Cocks & hens from churchscot of customary tenants | K75: =B75+C75+D75-E75-F75-G75-H75-I75 -> 0 | Q75: =IFERROR((L75+N75)/(M75+O75),"") | R75: =IFERROR(D75*Q75,"") | S75: =IFERROR(Q75*G75,"")
K76: =B76+C76+D76-E76-F76-G76-H76-I76 -> 0 | Q76: =IFERROR((L76+N76)/(M76+O76),"") | R76: =IFERROR(D76*Q76,"") | S76: =IFERROR(Q76*G76,"")
K77: =B77+C77+D77-E77-F77-G77-H77-I77 -> 0 | Q77: =IFERROR((L77+N77)/(M77+O77),"") | R77: =IFERROR(D77*Q77,"") | S77: =IFERROR(Q77*G77,"")
A78: Meat | K78: =B78+C78+D78-E78-F78-G78-H78-I78 -> 0 | Q78: =IFERROR((L78+N78)/(M78+O78),"") | R78: =IFERROR(D78*Q78,"") | S78: =IFERROR(Q78*G78,"")
A79: Beef | K79: =B79+C79+D79-E79-F79-G79-H79-I79 -> 0 | Q79: =IFERROR((L79+N79)/(M79+O79),"") | R79: =IFERROR(D79*Q79,"") | S79: =IFERROR(Q79*G79,"")
A80: Mutton | K80: =B80+C80+D80-E80-F80-G80-H80-I80 -> 0 | Q80: =IFERROR((L80+N80)/(M80+O80),"") | R80: =IFERROR(D80*Q80,"") | S80: =IFERROR(Q80*G80,"")
A81: Pork | K81: =B81+C81+D81-E81-F81-G81-H81-I81 -> 0 | Q81: =IFERROR((L81+N81)/(M81+O81),"") | R81: =IFERROR(D81*Q81,"") | S81: =IFERROR(Q81*G81,"")
K82: =B82+C82+D82-E82-F82-G82-H82-I82 -> 0 | Q82: =IFERROR((L82+N82)/(M82+O82),"") | R82: =IFERROR(D82*Q82,"") | S82: =IFERROR(Q82*G82,"")
K83: =B83+C83+D83-E83-F83-G83-H83-I83 -> 0 | Q83: =IFERROR((L83+N83)/(M83+O83),"") | R83: =IFERROR(D83*Q83,"") | S83: =IFERROR(Q83*G83,"")
A84: Cheese | K84: =B84+C84+D84-E84-F84-G84-H84-I84 -> 0 | Q84: =IFERROR((L84+N84)/(M84+O84),"") | R84: =IFERROR(D84*Q84,"") | S84: =IFERROR(Q84*G84,"")
A85: Winter cheese | K85: =B85+C85+D85-E85-F85-G85-H85-I85 -> 0 | Q85: =IFERROR((L85+N85)/(M85+O85),"") | R85: =IFERROR(D85*Q85,"") | S85: =IFERROR(Q85*G85,"")
A86: Summer cheese | K86: =B86+C86+D86-E86-F86-G86-H86-I86 -> 0 | Q86: =IFERROR((L86+N86)/(M86+O86),"") | R86: =IFERROR(D86*Q86,"") | S86: =IFERROR(Q86*G86,"")
K87: =B87+C87+D87-E87-F87-G87-H87-I87 -> 0 | Q87: =IFERROR((L87+N87)/(M87+O87),"") | R87: =IFERROR(D87*Q87,"") | S87: =IFERROR(Q87*G87,"")
K88: =B88+C88+D88-E88-F88-G88-H88-I88 -> 0 | Q88: =IFERROR((L88+N88)/(M88+O88),"") | R88: =IFERROR(D88*Q88,"") | S88: =IFERROR(Q88*G88,"")
A89: Butter | K89: =B89+C89+D89-E89-F89-G89-H89-I89 -> 0 | Q89: =IFERROR((L89+N89)/(M89+O89),"") | R89: =IFERROR(D89*Q89,"") | S89: =IFERROR(Q89*G89,"")
K90: =B90+C90+D90-E90-F90-G90-H90-I90 -> 0 | Q90: =IFERROR((L90+N90)/(M90+O90),"") | R90: =IFERROR(D90*Q90,"") | S90: =IFERROR(Q90*G90,"")
K91: =B91+C91+D91-E91-F91-G91-H91-I91 -> 0 | Q91: =IFERROR((L91+N91)/(M91+O91),"") | R91: =IFERROR(D91*Q91,"") | S91: =IFERROR(Q91*G91,"")
A92: Cider | D92: 2 | J92: 2 | K92: =B92+C92+D92-E92-F92-G92-H92-I92 -> 2 | Q92: =IFERROR((L92+N92)/(M92+O92),"") | R92: =IFERROR(D92*Q92,"") | S92: =IFERROR(Q92*G92,"")
K93: =B93+C93+D93-E93-F93-G93-H93-I93 -> 0 | Q93: =IFERROR((L93+N93)/(M93+O93),"") | R93: =IFERROR(D93*Q93,"") | S93: =IFERROR(Q93*G93,"")
K94: =B94+C94+D94-E94-F94-G94-H94-I94 -> 0 | Q94: =IFERROR((L94+N94)/(M94+O94),"") | R94: =IFERROR(D94*Q94,"") | S94: =IFERROR(Q94*G94,"")
K95: =B95+C95+D95-E95-F95-G95-H95-I95 -> 0 | Q95: =IFERROR((L95+N95)/(M95+O95),"") | R95: =IFERROR(D95*Q95,"") | S95: =IFERROR(Q95*G95,"")
Q96: =IFERROR((L96+N96)/(M96+O96),"") | R96: =IFERROR(D96*Q96,"") | S96: =IFERROR(Q96*G96,"")
Q97: =IFERROR((L97+N97)/(M97+O97),"") | R97: =IFERROR(D97*Q97,"") | S97: =IFERROR(Q97*G97,"")

Sheet Assumptions
A1: ASSUMPTIONS
B3: Weights | C3: Value (in lbs) | D3: Value (in cloves) | E3: Value (in weys) | F3: Value (in stone)
B4: Lbs | C4: 1 | D4: =C4/C5 -> 0.14285714 | E4: =C4/C6 -> 0.0057142857 | F4: =C4/C7 -> 0.08
B5: Cloves | C5: 7 | D5: 1 | E5: =C5/C6 -> 0.04 | F5: =C7/C5 -> 1.7857143
B6: Wey | C6: 175 | D6: =C6/C5 -> 25 | E6: =C6/C6 -> 1 | F6: =C7/C6 -> 0.071428571
B7: Stone | C7: =175/14 -> 12.5 | D7: =C5/C7 -> 0.56 | E7: =C7/C6 -> 0.071428571 | F7: 1
