Workbook

Sheet BishopsSutton Overview - Completed
A1: BISHOPSSUTTON OVERVIEW - COMPLETED | B1: Total in £ | C1: Error | D1: Note
A2: CASH ACCOUNT
A3: RECEIPTS
A4: Arrears total | B4: 48.38
A5: Rents of assize total | B5: 49
A6: Quittances total | B6: 2.93
A7: Defaults of rent total | B7: 0.92
A8: Defaults of rent through the pestilence total
A9: Cotlands defaults total
A10: Cotlands total
A11: Total of quittances and defaults of rent total | B11: 3.84
A12: Total of rents remaining clear total | B12: 46.1
A13: Farms total
A14: Annual recognizances total | B14: 0.04
A15: Issues of the Manor total | B15: 34.16
A16: Issues of the tenements in the lord's hands total
A17: Sale of labour services total
A18: Sale of corn total
A19: Entry and marriage fines total | B19: 10.09
A20: Pleas & perquisites total
A21: Forfeited chattels total
A22: Farm of the demesne land total
A23: Total of all receipts (calculated here) | B23: =SUM(B5:B22)
A24: Total of all receipts (calculated here) incl arrears | B24: =SUM(B4:B22)
A25: Total recorded in the accounts excl. arrears | B25: 114.64 | C25: =B23-B25
A26: Total recorded in the accounts incl. arrears | B26: =B25+B4
A29: EXPENSES
A30: Cost of ploughs total
A31: Purchase of corn total
A32: Cost of carts and wagons total
A33: Cost of dairy total
A34: Purchase of stock total | B34: 7.89
A35: Sheepcote total
A36: Cost of buildings total
A37: Threshing total
A38: Barley expenses
A39: Expenses of the harvest total
A40: Necessary expenses | B40: 1.95
A41: Wages of the bailiff
A42: Steward's expenses total | B42: 6.7266667
A43: Annual fees
A44: Total of all expenses per account | B44: 26.3
A45: Total of all expenses (calculated here) | B45: 26.340833
A46: Total fixed investment | B46: 5.3475
A47: Total Demesne fixed investment | B47: 3.6575
A49: Owed by the reeve | B49: =B23-B45
A50: From accounts | B50: 26.3
A52: Allowances
A53: Cash deliveries | B53: 52.87
A54: Sum of the above | B54: =SUM(B52:B53)
A55: Total of all allowances and cash deliveries in accounts
A57: Net amount owed | B57: =B50-B54
A58: Net amount owed in accounts
A60: GRANGE ACCOUNT | B60: Total Production | D60: Value of total gross production in £ | E60: Value of total net production in £
A61: Grange | B61: qrs | C61: bus
A62: Wheat | B62: 88.375 | E62: 18.15
A63: Rye
A64: Dredge
A65: Curall | B65: 1.25 | E65: 0.14583333
A66: Barley | B66: 36 | E66: 3.2229167
A67: Oats | B67: 90 | E67: 0
A68: Beans
A69: Peas | B69: 1.5 | E69: 0.075
A70: Vetches | B70: 2.625 | E70: 0.05
A71: Total value of gross production (sum of the above)
A72: Total value of net production
A73: Value of sales
A75: MILL ACCOUNT | B75: Total Production | D75: Total in £
A76: Issues of the mill | B76: qrs | C76: bus
A77: Wheat
A78: Oatmeal
A79: 1st grade malt
A80: 2nd grade malt
A81: Maslin
A82: Total value of production (sum of the above)
A83: Value of sales
A85: STOCK ACCOUNT
A86: Livestock | B86: Begin stock | C86: End stock | D86: Stockbuilding | F86: Value of stock in £ | G86: Value of stockbuilding
A87: Cart-horses | B87: 3 | C87: 3 | D87: 0 | F87: ='Stock'!K5*'Stock'!O5 | G87: =D87*'Stock'!O5
A88: Mares | D88: =C88-B88 | F88: ='Stock'!K6*'Stock'!O6 | G88: =D88*'Stock'!O6
A89: Plough horses | B89: 7 | C89: 5 | D89: -2 | F89: ='Stock'!K7*'Stock'!O7 | G89: =D89*'Stock'!O7
A90: Colts (2 years) | B90: 2 | C90: 0 | D90: -2 | F90: ='Stock'!K9*'Stock'!O9 | G90: =D90*'Stock'!O9
A91: Colts (2 years) | B91: 2 | C91: 0 | D91: -2 | F91: ='Stock'!K9*'Stock'!O9 | G91: =D91*'Stock'!O9
A92: Colts (1 year) | B92: 3 | C92: 2 | D92: -1 | F92: ='Stock'!K10*'Stock'!O10 | G92: =D92*'Stock'!O10
A93: Foals | B93: 2 | C93: 2 | D93: 0 | F93: ='Stock'!K11*'Stock'!O11 | G93: =D93*'Stock'!O11
A94: Oxen | B94: 28 | C94: 25 | D94: -3 | F94: ='Stock'!K12*'Stock'!O12 | G94: =D94*'Stock'!O12
A95: Bulls | B95: 2 | C95: 1 | D95: -1 | F95: ='Stock'!K13*'Stock'!O13 | G95: =D95*'Stock'!O13
A96: Cows | B96: 16 | C96: 16 | D96: 0 | F96: ='Stock'!K14*'Stock'!O14 | G96: =D96*'Stock'!O14
A97: Steers | B97: 6 | C97: 0 | D97: -6 | F97: ='Stock'!K15*'Stock'!O15 | G97: =D97*'Stock'!O15
A98: Bullocks | B98: 5 | C98: 4 | D98: -1 | F98: ='Stock'!K16*'Stock'!O16 | G98: =D98*'Stock'!O16
A99: Yearlings | B99: 4 | C99: 4 | D99: 0 | F99: ='Stock'!K17*'Stock'!O17 | G99: =D99*'Stock'!O17
A100: Calves | C100: 8 | D100: =C100-B100 | F100: ='Stock'!K18*'Stock'!O18 | G100: =D100*'Stock'!O18
A101: Wethers | B101: 186 | C101: 188 | D101: 2 | F101: ='Stock'!K19*'Stock'!O19 | G101: =D101*'Stock'!O19
A102: Rams | B102: 6 | C102: 8 | D102: 2 | F102: ='Stock'!K20*'Stock'!O20 | G102: =D102*'Stock'!O20
A103: Ewes | B103: 176 | C103: 177 | D103: 1 | F103: ='Stock'!K21*'Stock'!O21 | G103: =D103*'Stock'!O21
A104: Hoggs | B104: 64 | C104: 0 | D104: -64 | F104: ='Stock'!K22*'Stock'!O22 | G104: =D104*'Stock'!O22
A105: Lambs | C105: 90 | D105: =C105-B105 | F105: ='Stock'!K23*'Stock'!O23 | G105: =D105*'Stock'!O23
A106: Boars | D106: =C106-B106 | F106: ='Stock'!K24*'Stock'!O24 | G106: =D106*'Stock'!O24
A107: Sows | B107: 1 | C107: 2 | D107: 1 | F107: ='Stock'!K25*'Stock'!O25 | G107: =D107*'Stock'!O25
A108: Pigs | B108: 11 | C108: 35 | D108: 24 | F108: ='Stock'!K26*'Stock'!O26 | G108: =D108*'Stock'!O26
...

Sheet Prices
A1: Meat & Dairy Prices
C2: 1301 | D2: 1302 | E2: Average
A3: Beef | B3: £ per lb | C3: 0.0033351854 | D3: 0.0032608538 | E3: =AVERAGE(C3:D3)
A4: Mutton | B4: £ per lb | C4: 0.0036593977 | D4: 0.0037125513 | E4: =AVERAGE(C4:D4)
A5: Pork | B5: £ per lb | C5: 0.0038431326 | D5: 0.0037574803 | E5: =AVERAGE(C5:D5)
A6: Cheese | B6: £ per lb | C6: 0.0055768754 | D6: 0.0056654898 | E6: =AVERAGE(C6:D6)
A7: Butter | B7: £ per lb | C7: 0.0036626221 | D7: 0.0035935077 | E7: =AVERAGE(C7:D7)
A8: Milk | B8: £ per gallon | C8: 0.0055768754 | D8: 0.0056654898 | E8: =AVERAGE(C8:D8)

Sheet Labour Rents

Sheet Overview
A1: BISHOPS SUTTON | B1: Total in £ | C1: Error | D1: Note
A2: CASH ACCOUNT
A3: RECEIPTS
A4: Arrears total
A5: Rents of assize total
A6: Quittances total
A7: Defaults of rent total
A8: Defaults of rent through the pestilence total
A9: Cotlands defaults total
A10: Cotlands total
A11: Total of quittances and defaults of rent total
A12: Total of rents remaining clear total
A13: Farms total
... A22: Farm of the demesne land total
A23: Total of all receipts (calculated here) | B23: =Receipts!F124
A24: Total of all receipts (calculated here) incl arrears | B24: =Receipts!F125
A25: Total recorded in the accounts excl. arrears | B25: =Receipts!F123 | C25: =B25-B23
A26: Total recorded in the accounts incl. arrears
A29: EXPENSES
A30: Cost of ploughs total
A31: Purchase of corn total
A32: Cost of carts and wagons total
A33: Cost of dairy total
A34: Purchase of stock total
A35: Sheepcote total
A36: Cost of buildings total
A37: Threshing total
A38: Barley expenses
A39: Expenses of the harvest total
... A43: Annual fees
A44: Total of all expenses per account | B44: =Expenses!F115
A45: Total of all expenses (calculated here) | B45: =Expenses!F116
A46: Total fixed investment | B46: =Expenses!F117
A47: Total Demesne fixed investment | B47: =Expenses!F118
A49: Owed by the reeve | B49: =B23-B45
A50: From accounts | B50: =Expenses!F109 | C50: =B50-B49
A52: Allowances
A53: Cash deliveries | B53: =Expenses!F113
A54: Sum of the above | B54: =SUM(B52:B53)
A55: Total of all allowances and cash deliveries in accounts
A57: Net amount owed | B57: =B49-B54
A58: Net amount owed in accounts | B58: =Expenses!F111 | C58: =B58-B57
A60: GRANGE ACCOUNT | B60: Total Production
A61: Grange | B61: qrs | E61: Value of total gross production in £ | F61: Value of total net production in £
A62: wheat | B62: ='Issues of the Grange'!B2 | E62: ='Issues of the Grange'!I2 | F62: ='Issues of the Grange'!O14
A63: curall | B63: ='Issues of the Grange'!B3 | E63: ='Issues of the Grange'!I3 | F63: ='Issues of the Grange'!O15
A64: barley | B64: ='Issues of the Grange'!B4 | E64: ='Issues of the Grange'!I4 | F64: ='Issues of the Grange'!O16
A65: oats | B65: ='Issues of the Grange'!B5 | E65: ='Issues of the Grange'!I5 | F65: ='Issues of the Grange'!O17
A66: peas | B66: ='Issues of the Grange'!B6 | E66: ='Issues of the Grange'!I6 | F66: ='Issues of the Grange'!O18
A67: vetches | B67: ='Issues of the Grange'!B7 | E67: ='Issues of the Grange'!I7 | F67: ='Issues of the Grange'!O19
A68: Total value of gross production (sum of the above) | E68: =SUM(E62:E67)
A69: Total value of net production | E69: =SUM(F62:F67)
A70: Value of sales | E70: =Receipts!F93
A72: MILL ACCOUNT
A73: Issues of the mill
A74: Wheat
A75: Oatmeal
A76: 1st grade malt
A77: 2nd grade malt
A78: Maslin
A79: Total value of production (sum of the above)
A80: Value of sales
A82: STOCK ACCOUNT
A83: Livestock | B83: Sales value in £
A84: Cart-horses | B84: =Stock!R5
A85: Mares | B85: =Stock!R6
A86: Plough horses | B86: =Stock!R7
A87: Colts (2 years) | B87: =Stock!R8
A88: Colts (2 years) | B88: =Stock!R9
A89: Colts (1 year) | B89: =Stock!R10
A90: Foals | B90: =Stock!R11
A91: Oxen | B91: =Stock!R12
A92: Bulls | B92: =Stock!R13
A93: Cows | B93: =Stock!R14
A94: Steers | B94: =Stock!R15
A95: Bullocks | B95: =Stock!R16
... A109: Peacocks | B109: =Stock!R30
A110: Total value of stock (sum of the above)
A111: Total value of production
A112: Value of sales | B112: =Stock!R31
A114: Wool | B114: Value of production at sales prices £
A115: Coarse wool | B115: =Stock!T35
A116: from wethers | B116: =Stock!T36
A117: from rams | B117: =Stock!T37
A118: from ewes | B118: =Stock!T38
A119: from hoggs | B119: =Stock!T39
A120: Lamb's wool | B120: =Stock!T40
A121: Wool locks | B121: =Stock!T41
A122: Wool sold at shearing | B122: =Stock!T42
A123: Total value of production (sum of the above) | B123: =Stock!T43
A124: Value of sales | B124: =Stock!R43
A126: Hides | B126: Value of production at sales prices £
A127: Ox hides | B127: =Stock!T47
A128: Cow hides | B128: =Stock!T48
A129: Mare hides | B129: =Stock!T49
A130: Steer hides | B130: =Stock!T50
A131: Yearling Calf hides | B131: =Stock!T51
A132: Calf hides | B132: =Stock!T52
A133: Pig hides | B133: =Stock!T53
A134: Wether woolskins | B134: =Stock!T54
...

Sheet Receipts
A1: BISHOPS SUTTON RECEIPTS
A2: Heading | B2: £ | C2: s | D2: d | F2: Total in £ | G2: Error | H2: Notes | I2: Own notes
A3: Arrears | B3: 48 | C3: 7 | D3: 7.5 | F3: 48.38 | H3: Nicholas, bailiff, and Walter de Manestrott', reeve, render account for £48 7 shilling 7.5pence of arrears from the previous year.
A4: Arrears | B4: 0 | C4: 0 | D4: 0 | F4: 0 | H4: All delivered to Sir Geoffrey de Farham, treasurer of Wolvesey, and they are quit.
A5: Arrears | F5: 48.38 | G5: =F5-F3 | H5: Total
A7: Rents of assize | B7: 49 | C7: 0 | D7: 0 | F7: 49 | H7: The same render account for £49 for all rents of assize in the manor of Bishops Sutton for the year: £9 7 shilling 3pence at Christmas, £9 7 shilling 2.5pence at Easter (22 April), £9 7 shilling 3.25pence at the feast of St John the Baptist (24 June), £21 17 shilling 1.25pence at Michaelmas (29 September).
A8: Rents of assize | B8: 49 | C8: 18 | D8: 10 | F8: 49.94 | H8: Total, £49 18 shilling 10pence
A9: Rents of assize | F9: =SUM(F7:F7) | G9: =F9-F8 | H9: Total
A11: Quittances | B11: 0 | C11: 5 | D11: 0 | F11: 0.25 | H11: In quittance of 1 reeve for the year 5 shilling.
A12: Quittances | B12: 0 | C12: 3 | D12: 0 | F12: 0.15 | H12: 1 beadle who is hayward for the year 3 shilling.
A13: Quittances | B13: 0 | C13: 2 | D13: 0 | F13: 0.1 | H13: 1 smith for the year 2 shilling.
A14: Quittances | B14: 0 | C14: 2 | D14: 3 | F14: 0.11 | H14: 1 shepherd for three terms because there was no threshing in the fourth term 2 shilling 3pence.
A15: Quittances | B15: 0 | C15: 3 | D15: 0 | F15: 0.15 | H15: 1 shepherd for the year 3 shilling.
A16: Quittances | B16: 0 | C16: 18 | D16: 0 | F16: 0.9 | H16: 6 ploughmen for the year 18 shilling, or 3 shilling each.
A17: Quittances | B17: 0 | C17: 19 | D17: 4.5 | F17: 0.97 | H17: 6 workers working 2 days a week from Michaelmas until Lammas and everyday at harvest-time 19 shilling 4.5pence.
A18: Quittances | B18: 0 | C18: 3 | D18: 0 | F18: 0.15 | H18: 1 cowherd for the year 3 shilling.
A19: Quittances | B19: 0 | C19: 3 | D19: 0 | F19: =B19+C19/20+D19/240 | H19: 1 swineherd 3 shilling
A20: Quittances | B20: 2 | C20: 18 | D20: 7.5 | F20: 2.93 | H20: Total, £2 18 shilling 7.5pence
A21: Quittances | F21: =SUM(F11:F19) | G21: =F21-F20 | H21: Total
A23: Defaults of rent | B23: 0 | C23: 2 | D23: 0 | F23: 0.1 | H23: In default of thel land of Philip [Molendinariusi] drawn into demesne, 2 shilling for the year.
A24: Defaults of rent | B24: 0 | C24: 1 | D24: 0 | F24: 0.05 | H24: the land of Geoffrey Hose given to the canons of Merton Priory for a fishpond 1 shilling.
A25: Defaults of rent | B25: 0 | C25: 0 | D25: 6 | F25: 0.03 | H25: 1 plot which belonged to John le Poleter, 6pence for the year.
A26: Defaults of rent | B26: 0 | C26: 10 | D26: 0 | F26: 0.5 | H26: 1 virgate of land which rbe' iongedl to Adam Bedell' drawn into demesne 10 shilling.
A27: Defaults of rent | B27: 0 | C27: 3 | D27: 3 | F27: 0.16 | H27: 1 messuage pertaining to the mill and 1 plot at the bakehouse pertaining to the same which William Carpenter held 3 shilling 3pence.
A28: Defaults of rent | B28: 0 | C28: 1 | D28: 6 | F28: 0.08 | H28: 3 acres of land which Guy de Hayden' held at la Leygate 1 shilling 6pence
A29: Defaults of rent | B29: 0 | C29: 18 | D29: 3 | F29: =B29+C29/20+D29/240 | H29: Total, 18 shilling 3pence
A30: Defaults of rent | F30: 0.92 | G30: =F30-F29 | H30: Total
A32: Total of quittances and defaults of rent | B32: 3 | C32: 16 | D32: 10.5 | F32: 3.84 | H32: Total of quittances and defaults of rent, £3 16 shilling 10.5pence
A33: Total of quittances and defaults of rent | F33: =F32 | G33: =F33-F32 | H33: Total
A36: Total of rents remaining clear | B36: 46 | C36: 1 | D36: 11.5 | F36: 46.1 | H36: Total of rents remaining clear, £46 1 shilling 11.5pence
A37: Total of rents remaining clear | F37: 46.1 | G37: =F37-F36 | H37: Total
A40: Annual recognizance | B40: 0 | C40: 0 | D40: 3 | F40: 0.01 | H40: The same render account for 3pence from William Syniar' for annual recognizance whilst he wishes to remain on the land of St Swithun's.
A41: Annual recognizance | B41: 0 | C41: 0 | D41: 3 | F41: 0.01 | H41: 3pence from John le Fode so that he may serve and make his profit outside the liberty of the lord and not be challenged for this by the lord, and that he may come to the law-day and remain a villein as before.
A42: Annual recognizance | B42: 0 | C42: 0 | D42: 3 | F42: 0.01 | H42: 3pence from John le Ma3on of Headley not to be prosecuted by the tithing for default at the law-day if he be not present and to be quit of tithingpenny, by the pledge of John ate Brigg'.
A43: Annual recognizance | B43: 0 | C43: 0 | D43: 3 | F43: 0.01 | H43: 3pence from Henry Faber for annual recognizance, by the pledge of Richard ate Putte.
A44: Annual recognizance | B44: 0 | C44: 1 | D44: 0 | F44: 0.05 | H44: Total, 1 shilling
A45: Annual recognizance | F45: 0.04 | G45: -0.01 | H45: Total
A48: Issues of the manor | B48: 1 | C48: 5 | D48: 1 | F48: 1.25 | H48: The same render account for £1 5 shilling 1pence from pannage of pigs of the vill this year.
A49: Issues of the manor | B49: 0 | C49: 18 | D49: 11 | F49: =B49+C49/12+D49/20 | H49: 18 shilling 11pence from foreign pannage.
A50: Issues of the manor | B50: 0 | C50: 10 | D50: 4 | F50: 0.52 | H50: 10 shilling from pannage of the cottars, at 4pence for each working ox, and 3pence for a cow of full age.
A51: Issues of the manor | B51: 0 | C51: 5 | D51: 0 | F51: 0.25 | H51: 5 shilling from the herbage of Farndon.
A52: Issues of the manor | B52: 0 | C52: 4 | D52: 0 | F52: 0.2 | H52: 4 shilling from pinfold.
A53: Issues of the manor | B53: 0 | C53: 2 | D53: 1 | F53: 0.1 | H53: 2 shilling 1pence from churchscot.
A54: Issues of the manor | B54: 0 | C54: 2 | D54: 0 | F54: 0.1 | H54: 2 shilling from the herbage behind the curia sold.
A55: Issues of the manor | B55: 1 | C55: 10 | D55: 0 | F55: 1.5 | H55: £1 10 shilling from 3 old plough-horses sold.
A56: Issues of the manor | B56: 3 | C56: 16 | D56: 10 | F56: 3.84 | H56: £3 16 shilling 10pence from 8 old oxen sold at various prices, that is, 10 shilling each for 7, and 6 shilling 10pence for 1.
A57: Issues of the manor | B57: 0 | C57: 10 | D57: 0 | F57: 0.5 | H57: 10 shilling from 1 bull sold.
A58: Issues of the manor | B58: 1 | C58: 12 | D58: 0 | F58: 1.6 | H58: £1 12 shilling from 4 old cows sold, at 8 shilling each.
A59: Issues of the manor | B59: 0 | C59: 2 | D59: 6 | F59: 0.12 | H59: 2 shilling 6pence from 3 late-born calves sold.
A60: Issues of the manor | B60: 10 | C60: 12 | D60: 6.5 | F60: 10.63 | H60: £10 12 shilling 6.5pence from 29 animals bought for pasturing and sold at various prices.
A61: Issues of the manor | B61: 0 | C61: 16 | D61: 4 | F61: 0.82 | H61: 16 shilling 4pence from 14 wethers sold at Martinmas, at 1 shilling 2pence each.
... A82: Issues of the manor | B82: 33 | C82: 1 | D82: 2.25 | F82: 33.06 | H82: Total, £33 1 shilling 2.25pence
A83: Issues of the manor | F83: =SUM(F48:F81) | G83: =F83-F82 | H83: Total
A86: Sale of wheat | B86: 18 | C86: 3 | D86: 0 | F86: 18.15 | H86: The same render account for £18 3 shilling from 60.5 quarters of wheat sold, at 6 shilling a qr.
A87: Sale of wheat | B87: 0 | C87: 2 | D87: 11 | F87: 0.15 | H87: 2 shilling 11pence from 5 bushels of curall sold.
A88: Sale of wheat | B88: 1 | C88: 10 | D88: 4 | F88: 1.52 | H88: £1 10 shilling 4pence from 6.5 quarters of barley sold, at 4 shilling 8pence a qr.
A89: Sale of wheat | B89: 0 | C89: 1 | D89: 6 | F89: 0.08 | H89: 1 shilling 6pence from 4 bushels of peas sold.
A90: Sale of wheat | B90: 0 | C90: 1 | D90: 0 | F90: 0.05 | H90: 1 shilling from 4 bushels of vetches sold.
A91: Sale of wheat | B91: 0 | C91: 3 | D91: 9.5 | F91: 0.19 | H91: 3 shilling 9.5pence from 6.5 bushels of barley sold at the audit.
A92: Sale of wheat | B92: 20 | C92: 2 | D92: 6.5 | F92: 20.13 | H92: Total, £20 2 shilling 6.5pence
A93: Sale of wheat | F93: 20.14 | G93: 0.01 | H93: Total
A96: Entry and marriage fines with tithingpenny | B96: 0 | C96: 5 | D96: 0 | F96: 0.25 | H96: The same render account for 5 shilling from the tithing of Bishops Sutton for tithingpenny at the hundred-court of Martinmas.
A97: Entry and marriage fines with tithingpenny | B97: 0 | C97: 10 | D97: 0 | F97: 0.5 | H97: 10 shilling from the tithing of Ropley for the same.
A98: Entry and marriage fines with tithingpenny | B98: 0 | C98: 4 | D98: 0 | F98: 0.2 | H98: 4 shilling from the tithing of Bighton for the same.
A99: Entry and marriage fines with tithingpenny | B99: 0 | C99: 3 | D99: 0 | F99: 0.15 | H99: 3 shilling from the tithing of Bramdean for the same.
A100: Entry and marriage fines with tithingpenny | B100: 0 | C100: 2 | D100: 0 | F100: 0.1 | H100: 2 shilling from the tithing of West Tisted for the same.
A101: Entry and marriage fines with tithingpenny | B101: 0 | C101: 8 | D101: 0 | F101: 0.4 | H101: 8 shilling from the tithing of Headley for the same.
A102: Entry and marriage fines with tithingpenny | B102: 1 | C102: 12 | D102: 0 | F102: 1.6 | H102: £1 12 shilling from the same for the same at the hundred-court of Hockday.
A103: Entry and marriage fines with tithingpenny | B103: 0 | C103: 4 | D103: 0 | F103: 0.2 | H103: 4 shilling from Richard Sutore for 1 plot which came into the lord's hands by the death of William le Dudeler'.
A104: Entry and marriage fines with tithingpenny | B104: 0 | C104: 13 | D104: 4 | F104: 0.67 | H104: 13 shilling 4pence from Richard de Graveschate to have the land of his father by surrender of Juliana his mother.
A105: Entry and marriage fines with tithingpenny | B105: 0 | C105: 2 | D105: 0 | F105: 0.1 | H105: 2 shilling from John Gileberd for marrying Agnes his daughter.
A106: Entry and marriage fines with tithingpenny | B106: 1 | C106: 0 | D106: 0 | F106: 1 | H106: £1 from Walter Parmehoud to have 1 virgate of land of his inheritance after the death of Seyld his mother.
A107: Entry and marriage fines with tithingpenny | B107: 0 | C107: 13 | D107: 4 | F107: 0.67 | H107: 13 shilling 4pence from William le Monek to have Alice de Merton' with her land.
... A111: Entry and marriage fines with tithingpenny | B111: 10 | C111: 1 | D111: 8 | F111: 10.08 | H111: Total, £10 1 shilling 8pence
A112: Entry and marriage fines with tithingpenny | F112: 10.09 | G112: 0.01 | H112: Total
A115: Perquisites | B115: 0 | C115: 4 | D115: 0 | F115: 0.2 | H115: The same render account for 4 shilling from Thomas ate Hok' for trespass of the lord's charcoal.
A116: Perquisites | B116: 5 | C116: 0 | D116: 6 | F116: 5.03 | H116: £5 6pence from other small perquisites.
A117: Perquisites | B117: 5 | C117: 4 | D117: 6 | F117: 5.23 | H117: Total, £5 4 shilling 6pence
A119: Total of all receipts | B119: 15 | C119: 6 | D119: 2 | F119: 15.31 | H119: Total of both, £15 6 shilling 2pence
A120: Total of all receipts | F120: =F117+F111 | G120: =F120-F119 | H120: Total
A123: Total of all receipts recorded in accounts | B123: 114 | C123: 12 | D123: 10.25 | F123: 114.64 | H123: Total of all receipts, £114 12 shilling 10.25pence
A124: Total cross-check without arrears | F124: =F117+F112+F93+F83+F45+F37 | G124: =F124-F123
A125: Total cross-check with arrears | F125: =F124+F5

Sheet Expenses
A1: BISHOPS SUTTON EXPENSES
A2: Heading | B2: £ | C2: s | D2: d | F2: Total in £ | G2: Error | H2: Notes | J2: Fixed investment | K2: Demesne fixed investment
A3: Necessary expenses of ploughs | B3: 0 | C3: 5 | D3: 0 | F3: 0.25 | H3: In ironwork of 3 ploughs this year 5 shilling. | J3: =F3 | K3: =F3
A4: Necessary expenses of ploughs | B4: 0 | C4: 0 | D4: 9 | F4: 0.04 | H4: 2 plough feet bought 9pence Nothing accounted this year for the shoeing of 2 cart-horses because the smith is bound to shoe 2 cart-horses of Bishops Sutton at his own cost, and he will have 1 acre of wheat as it lies for making the iron of the shoes and 3 trunks for charcoal this year, because there were there three ploughs, and other customs are contained on the dorse of the roll. | J4: =F4 | K4: =F4
A5: Necessary expenses of ploughs | B5: 0 | C5: 0 | D5: 6 | F5: 0.03 | H5: 3 ploughs made anew 6pence. | J5: =F5 | K5: =F5
A6: Necessary expenses of ploughs | B6: 0 | C6: 0 | D6: 2 | F6: 0.01 | H6: mending other ploughs 2pence. | J6: =F6 | K6: =F6
A7: Necessary expenses of ploughs | B7: 0 | C7: 0 | D7: 2 | F7: 0.01 | H7: fitting ploughs with iron tyres 2pence. | J7: =F7 | K7: =F7
A8: Necessary expenses of ploughs | B8: 0 | C8: 0 | D8: 6 | F8: 0.03 | H8: 3 pairs of wheels bought 6pence Richard de Manicroft' and John de Puteo ploughed 12 acres in winter and 12 acres in Lent, and they will take nothing. | J8: =F8 | K8: =F8
A9: Necessary expenses of ploughs | B9: 0 | C9: 0 | D9: 3 | F9: 0.01 | H9: 1 harrow made anew and others mended 3pence. | J9: =F9 | K9: =F9
A10: Necessary expenses of ploughs | B10: 0 | C10: 0 | D10: 2.5 | F10: 0.01 | H10: 5 yokes made 2.5pence. | J10: =F10 | K10: =F10
A11: Necessary expenses of ploughs | B11: 1 | C11: 1 | D11: 6 | F11: 1.07 | H11: 2 oxen bought £1 1 shilling 6pence. | J11: =F11 | K11: =F11
A12: Necessary expenses of ploughs | B12: 0 | C12: 10 | D12: 0 | F12: =B12+C12/20+D12/240 | H12: forage bought to support plough-horses, oxen and cows 10 shilling
A13: Necessary expenses of ploughs | B13: 1 | C13: 19 | D13: 0.5 | F13: 1.95 | H13: Total, £1 19 shilling 0.5pence
F14: =SUM(F3:F12) | G14: =F14-F13 | H14: Total
A16: Sowing and fodder | B16: 1 | C16: 11 | D16: 8 | F16: 1.58 | H16: In 15 quarters of oats bought for sowing and fodder £1 11 shilling 8pence, at 1 shilling 8pence a qr for 5 quarters, and 2 shilling 4pence a qr for 10 quarters.
A17: Sowing and fodder | B17: 1 | C17: 11 | D17: 8 | F17: 1.58 | H17: Total, £1 11 shilling 8pence
A18: Sowing and fodder | F18: 1.58 | G18: 0 | H18: Total
A20: Carts | B20: 0 | C20: 0 | D20: 9 | F20: 0.04 | H20: In 1 pair of wheels made from the lord's timber 9pence. | J20: =F20 | K20: =J20
A21: Carts | B21: 0 | C21: 1 | D21: 4 | F21: 0.07 | H21: clouts, nails and grease bought 1 shilling 4pence. | J21: =F21 | K21: =J21
A22: Carts | B22: 0 | C22: 0 | D22: 6 | F22: 0.03 | H22: fitting the cart with axles 6pence. | J22: =F22 | K22: =J22
A23: Carts | B23: 0 | C23: 0 | D23: 6 | F23: 0.03 | H23: 1 collar bought 6pence. | J23: =F23 | K23: =J23
A24: Carts | B24: 0 | C24: 0 | D24: 6 | F24: 0.03 | H24: 1 pair of traces bought 6pence. | J24: =F24 | K24: =J24
A25: Carts | B25: 0 | C25: 1 | D25: 1 | F25: 0.05 | H25: 1 cart-rope bought 1 shilling 1pence. | J25: =F25 | K25: =J25
A26: Carts | B26: 0 | C26: 0 | D26: 10 | F26: 0.04 | H26: white leather bought for harnesses 10pence. | J26: =F26 | K26: =J26
A27: Carts | B27: 0 | C27: 1 | D27: 4 | F27: 0.07 | H27: shoeing 4 plough-horses 1 shilling 4pence. | J27: =F27 | K27: =J27
A28: Carts | B28: 0 | C28: 0 | D28: 1 | F28: 0 | H28: a halter bought 1pence. | J28: =F28 | K28: =J28
A29: Carts | B29: 0 | C29: 3 | D29: 0 | F29: 0.15 | H29: stipend of 1 carter for the year 3 shilling.
A30: Carts | B30: 0 | C30: 0 | D30: 9 | F30: =B30+C30/20+D30/240 | H30: pair of wheels made for dung 9pence | J30: =F30 | K30: =J30
A31: Carts | B31: 0 | C31: 10 | D31: 3 | F31: =B31+C31/20+D31/240 | H31: Total, 10 shilling 3pence
A32: Carts | F32: =SUM(F20:F30) | G32: =F32-F31 | H32: Total
A34: Dairy | B34: 0 | C34: 1 | D34: 3 | F34: 0.06 | H34: bushels 5 of salt bought 1 shilling 3pence. | J34: =F34 | K34: =J34
A35: Dairy | B35: 0 | C35: 0 | D35: 6 | F35: 0.03 | H35: linen and woollen cloth 6pence. | J35: =F35 | K35: =J35
A36: Dairy | B36: 0 | C36: 0 | D36: 2.5 | F36: 0.01 | H36: earthenware pots and pans bought 2.5pence. | J36: =F36 | K36: =J36
A37: Dairy | B37: 0 | C37: 0 | D37: 4 | F37: 0.02 | H37: a press bought 4pence. | J37: =F37 | K37: =J37
A38: Dairy | B38: 0 | C38: 0 | D38: 3 | F38: 0.01 | H38: mending the utensils of the dairy 3pence. | J38: =F38 | K38: =J38
A39: Dairy | B39: 0 | C39: 2 | D39: 3 | F39: 0.11 | H39: 9 ells of canvas bought for packing the coarse wool and lamb's-wool 2 shilling 3pence. | J39: =F39 | K39: =J39
A40: Dairy | B40: 0 | C40: 0 | D40: 2 | F40: 0.01 | H40: packing the same and making sacks 2pence. | J40: =F40 | K40: =J40
A41: Dairy | B41: 0 | C41: 10 | D41: 0 | F41: 0.5 | H41: grease, vinegar and copperas to make well diseased sheep 10 shilling. | J41: =F41 | K41: =J41
A42: Dairy | B42: 0 | C42: 1 | D42: 3 | F42: 0.06 | H42: 30 hurdles made 1 shilling 3pence. | J42: =F42 | K42: =J42
A43: Dairy | B43: 0 | C43: 3 | D43: 9.5 | F43: 0.19 | H43: cratches made anew around the walls in the sheepcote 3 shilling 9.5pence. | J43: =F43 | K43: =J43
A44: Dairy | B44: 0 | C44: 0 | D44: 2 | F44: 0.01 | H44: tithe of 2 foals 2pence. | J44: =F44 | K44: =J44
A45: Dairy | B45: 0 | C45: 0 | D45: 3.5 | F45: 0.01 | H45: gelding piglets 3.5pence. | J45: =F45 | K45: =J45
A46: Dairy | B46: 0 | C46: 3 | D46: 0 | F46: 0.15 | H46: stipend of the dairy-keeper who is male 3 shilling.
A47: Dairy | B47: 0 | C47: 13 | D47: 4 | F47: 0.67 | H47: 20 lambs bought 13 shilling 4pence, at 8pence each.
A48: Dairy | B48: 0 | C48: 10 | D48: 10 | F48: 0.54 | H48: 1 sow and 11 pigs bought 10 shilling 10pence, at various prices.
A49: Dairy | B49: 2 | C49: 7 | D49: 7.5 | F49: 2.38 | H49: Total, £2 7 shilling 7.5pence
A50: Dairy | F50: 2.38 | G50: 0 | H50: Total
A53: Repair of buildings | B53: 0 | C53: 2 | D53: 0 | F53: 0.1 | H53: In thatch bought for roofing the bakehouse and covering the stone walls 2 shilling. | J53: =F53 | K53: =J53
A54: Repair of buildings | B54: 0 | C54: 6 | D54: 0 | F54: 0.3 | H54: thatch bought and roofing the barn in part and the byre nearly anew 6 shilling. | J54: =F54 | K54: =J54
A55: Repair of buildings | B55: 0 | C55: 5 | D55: 6 | F55: 0.28 | H55: hedging to enclose around the curia anew and repairing it where necessary with fencing felled for the same 5 shilling 6pence. | J55: =F55
A56: Repair of buildings | B56: 0 | C56: 6 | D56: 5 | F56: 0.32 | H56: 3,500 shingles made 6 shilling 5pence. | J56: =F56
A57: Repair of buildings | B57: 0 | C57: 5 | D57: 10 | F57: 0.29 | H57: laying the same on the hall, room of the steward's clerks, and chapel 5 shilling 10pence. | J57: =F57
A58: Repair of buildings | B58: 0 | C58: 2 | D58: 0 | F58: 0.1 | H58: roofing and mending the said buildings with old shingles in places where it was necessary 2 shilling. | J58: =F58
A59: Repair of buildings | B59: 0 | C59: 2 | D59: 6 | F59: 0.12 | H59: large and small nails bought for the same 2 shilling 6pence. | J59: =F59
A60: Repair of buildings | B60: 0 | C60: 2 | D60: 8 | F60: 0.13 | H60: sawing boards and felling timber for the walls of the granary 2 shilling 8pence. | J60: =F60 | K60: =J60
A61: Repair of buildings | B61: 0 | C61: 4 | D61: 0 | F61: 0.2 | H61: a carpenter making the said walls nearly anew 4 shilling. | J61: =F61 | K61: =J61
A62: Repair of buildings | B62: 0 | C62: 0 | D62: 11.5 | F62: 0.05 | H62: large nails bought for the same 11.5pence. | J62: =F62 | K62: =J62
A63: Repair of buildings | B63: 0 | C63: 1 | D63: 8 | F63: 0.08 | H63: roofing the bailiff's room in places 1 shilling 8pence. | J63: =F63
A64: Repair of buildings | B64: 0 | C64: 10 | D64: 0 | F64: =B64+C64/20+D64/240 | H64: charcoal made 10 shilling | J64: =F64
A65: Repair of buildings | B65: 2 | C65: 9 | D65: 6.5 | F65: 2.48 | H65: Total, £2 9 shilling 6.5pence
A66: Repair of buildings | F66: =SUM(F53:F64) | G66: =F66-F65 | H66: Total
A69: Harvest-time | B69: 0 | C69: 19 | D69: 0 | F69: 0.95 | H69: In 5 quarters of barley bought for the bread of 500 men with the officials of the curia at 3 harvest boon-works 19 shilling, and each had 1 loaf a day, of which 100 were made from a quarter.
A70: Harvest-time | B70: 0 | C70: 6 | D70: 9 | F70: 0.34 | H70: 1,000 herrings bought to eat with the bread (companag' eorundem) 6 shilling 9pence, and each had 2 herrings a day.
A71: Harvest-time | B71: 0 | C71: 0 | D71: 4 | F71: 0.02 | H71: meal bought for the pottage of the same 4pence They reaped 288 acres of wheat, barley and oats as they lie.
A72: Harvest-time | B72: 0 | C72: 0 | D72: 0 | F72: 0 | H72: moreover, they are to reap 161 acres which are called gavel-acres (gavelacr') each year according to custom, and this year they reaped all the acres of wheat, barley and oats, and 22 acres are in quittance for the officials of the curia whilst they are in the lord's service.
A73: Harvest-time | B73: 0 | C73: 2 | D73: 11.5 | F73: 0.15 | H73: mending a press 2 shilling 11.5pence.
A74: Harvest-time | B74: 0 | C74: 10 | D74: 0 | F74: 0.5 | H74: 5 empty casks bought 10 shilling.
A75: Harvest-time | B75: 0 | C75: 1 | D75: 11.5 | F75: 0.1 | H75: timber bought to hoop the said casks 1 shilling 11.5pence.
A76: Harvest-time | B76: 0 | C76: 1 | D76: 10 | F76: 0.09 | H76: hooping the said casks 1 shilling 10pence.
A77: Harvest-time | B77: 0 | C77: 1 | D77: 6 | F77: =B77+C77/20+D77/240 | H77: making cider 1 shilling 6pence
A78: Harvest-time | B78: 2 | C78: 4 | D78: 4 | F78: 2.22 | H78: Total, £2 4 shilling 4pence
A79: Harvest-time | F79: =SUM(F69:F77) | G79: =F79-F78 | H79: Total
A81: Cost of the park | B81: 0 | C81: 6 | D81: 8 | F81: =B81+C81/20+D81/240 | H81: In stipend of 1 park-keeper for the year according to custom 6 shilling 8pence.
A82: Cost of the park | B82: 0 | C82: 1 | D82: 4 | F82: =B82+C82/20+D82/240 | H82: mending the hedges in the enclosure 1 shilling 4pence
A83: Cost of the park | B83: 0 | C83: 8 | D83: 0 | F83: =B83+C83/20+D83/240 | H83: Total, 8 shilling
A84: Cost of the park | F84: =SUM(F81:F82) | G84: =F84-F83 | H84: Total
A86: Cost of the meadow | B86: 0 | C86: 2 | D86: 2 | F86: 0.11 | H86: In a second mowing of the meadow of Bishops Sutton in parcels 2 shilling 2pence.
A87: Cost of the meadow | B87: 0 | C87: 0 | D87: 3 | F87: 0.01 | H87: spreading the said hay 3pence.
A88: Cost of the meadow | B88: 0 | C88: 0 | D88: 10 | F88: =B88+C88/20+D88/240 | H88: tossing the said hay and making haycocks therefrom 10pence
A89: Cost of the meadow | B89: 0 | C89: 3 | D89: 3 | F89: =B89+C89/20+D89/240 | H89: Total, 3 shilling 3pence
A90: Cost of the meadow | F90: =SUM(F86:F88) | G90: =F90-F89 | H90: Total
A93: Expenses of the steward and bailiff | B93: 0 | C93: 10 | D93: 2 | F93: 0.51 | H93: In expenses of Simon, clerk, for 2 tourns 10 shilling 2pence.
A94: Expenses of the steward and bailiff | B94: 5 | C94: 17 | D94: 0 | F94: 5.85 | H94: expenses of the bailiff for the year £5 17 shilling.
A95: Expenses of the steward and bailiff | B95: 0 | C95: 3 | D95: 0 | F95: 0.15 | H95: 1 fur bought for the summer livery of the bailiff 3 shilling.
A96: Expenses of the steward and bailiff | B96: 0 | C96: 4 | D96: 4 | F96: =B96+C96/20+D96/240 | H96: expenses of the sheriff for 1 visit 4 shilling 4pence
A97: Expenses of the steward and bailiff | B97: 6 | C97: 14 | D97: 6 | F97: 6.73 | H97: Total, £6 14 shilling 6pence
A98: Expenses of the steward and bailiff | F98: =SUM(F93:F96) | G98: =F98-F97 | H98: Total
A100: Purchase of stock | B100: 7 | C100: 17 | D100: 9 | F100: 7.89 | H100: In 29 animals bought for pasturing £7 17 shilling 9pence
A101: Purchase of stock | B101: 7 | C101: 17 | D101: 9 | F101: 7.89 | H101: Total, £7 17 shilling 9pence
A102: Purchase of stock | F102: 7.89 | G102: =F102-F101 | H102: Total
A104: Total of all expenses | B104: 26 | C104: 5 | D104: 11.5 | F104: 26.3 | H104: Total of all expenses, £26 5 shilling 11.5pence
A105: Total of all expenses | F105: 26.3 | G105: =F105-F104 | H105: Total
A108: And he owes | B108: 88 | C108: 6 | D108: 10.25 | F108: 88.34 | H108: And he owes, £88 6 shilling 10.25pence
A109: And he owes | F109: 88.34 | G109: 0 | H109: Total
A111: And he owes clear | B111: 35 | C111: 9 | D111: 6.25 | F111: 35.48 | H111: And thus he owes clear
A113: Cash deliveries | B113: 52 | C113: 17 | D113: 4.5 | F113: 52.87 | H113: Delivered to Sir Geoffrey, treasurer, by 1 tally, £52 17 shilling 4.5pence
A115: Total of all expenses per account | F115: =F105
A116: Total of all expenses (calculated here) | F116: =F98+F90+F84+F79+F66+F50+F32+F18+F14+F102 | G116: =F116-F115
A117: Total fixed investment | F117: =SUM(J3:J66)
A118: Total Demesne fixed investment | F118: =SUM(K2:K64)

Sheet Issues of the Grange
A1: Gross Output | B1: Total Quantity | C1: Account Total Quarters | D1: Bought in Total Quarters | E1: Received from churchscot | F1: Sold Total Quarters | G1: Difference Produced+Bought-Sold | H1: Weighted Average Price per Quarter | I1: Value of Total Production weighted
A2: wheat | B2: 88.375 | D2: 0 | F2: 60.5 | G2: =B2-F2 | H2: 0.3 | I2: =H2*B2
A3: curall | B3: 1.25 | D3: 0 | F3: 0.625 | G3: =B3-F3 | H3: 0.23333333 | I3: =H3*B3
A4: barley | B4: 36 | D4: 0 | F4: 7.3125 | G4: =B4-F4 | H4: 0.23333333 | I4: =H4*B4
A5: oats | B5: =C5+D5 | C5: 75 | D5: 15 | F5: 0 | G5: =B5-F5 | H5: 0 | I5: =H5*B5
A6: peas | B6: 1.5 | D6: 0 | F6: 0.5 | G6: =B6-F6 | H6: 0.15 | I6: =H6*B6
A7: vetches | B7: 2.625 | D7: 0 | F7: 0.5 | G7: =B7-F7 | H7: 0.1 | I7: =H7*B7
A9: Total Production
A10: Sales of corn (as recorded in accounts)
A13: Net output | B13: Gross output | C13: Seed quarters | D13: Seed bushels | E13: Seed total quarters | F13: tithe quarters | G13: tithe bushels | H13: tithe total | I13: manorial servants quarters | J13: manorial servants bushels | K13: manorial servants total quarters | L13: output net of tithe, seed, liveries | M13: in stock from last year | N13: Price in £ | O13: Value of net output in £ | P13: Value of sales (in "Sale of Corn") in £
A14: wheat | B14: =B2 | C14: 16 | D14: 1 | E14: =C14+D14/8 | I14: 11 | J14: =4+2 | K14: =I14+J14/8 | L14: =B14-E14-H14-K14 | N14: =H2 | O14: =L14*N14
A15: curall | B15: =B3 | E15: =C15+D15/8 | J15: 5 | K15: =I15+J15/8 | L15: =B15-E15-H15-K15 | N15: =H3 | O15: =L15*N15
A16: barley | B16: =B4 | C16: 11.5 | E16: =C16+D16/8 | I16: =5+2+2 | J16: =1.5+4+2+6 | K16: =I16+J16/8 | L16: =B16-E16-H16-K16 | N16: =H4 | O16: =L16*N16
A17: oats | B17: =B5 | C17: 36 | E17: =C17+D17/8 | I17: =18.5+15+18+2 | J17: =4 | K17: =I17+J17/8 | L17: =B17-E17-H17-K17 | N17: =H5 | O17: =L17*N17
A18: peas | B18: =B6 | C18: 1 | E18: =C18+D18/8 | K18: =I18+J18/8 | L18: =B18-E18-H18-K18 | N18: =H6 | O18: =L18*N18
A19: vetches | B19: =B7 | D19: 5 | E19: =C19+D19/8 | I19: 1 | J19: =1+3 | K19: =I19+J19/8 | L19: =B19-E19-H19-K19 | N19: =H7 | O19: =L19*N19
A21: Total

Sheet Issues of the Mills

Sheet Stock
A1: BISHOPS SUTTON ACCOUNT
C3: added | G3: subtracted
A4: Livestock | B4: Inherited stock | C4: added | D4: strays | E4: herbage | F4: churchscot | G4: of which in default | H4: sold | I4: in murrain | J4: accounted for elsewhere | K4: End-period stock | L4: cross-check | M4: stock building | N4: raw production | O4: Unit price (£) | P4: Value of stock (£) at given value | Q4: Value of stock (£) at sales prices | R4: Sales in (£) | S4: Value of stock building (£) | T4: Value of production (£) at sales prices | U4: Details
A5: Cart-horses | B5: 3 | K5: 3 | L5: =B5+C5+D5+E5+F5-G5-H5-I5-J5 | M5: =K5-B5
A6: Mares | L6: =B6+C6+D6+E6+F6-G6-H6-I6-J6 | M6: =K6-B6
A7: Plough horses | B7: 7 | C7: =2 | H7: 3 | I7: 1 | K7: 5 | L7: =B7+C7+D7+E7+F7-G7-H7-I7-J7 | M7: =K7-B7 | R7: =Receipts!F55
A8: Colts (unspecified years) | L8: =B8+C8+D8+E8+F8-G8-H8-I8-J8 | M8: =K8-B8
A9: Colts (2 years) | B9: 2 | I9: 1 | J9: 1 | K9: 0 | L9: =B9+C9+D9+E9+F9-G9-H9-I9-J9 | M9: =K9-B9
A10: Colts (1 year) | B10: 3 | I10: 1 | K10: 2 | L10: =B10+C10+D10+E10+F10-G10-H10-I10-J10 | M10: =K10-B10
A11: Foals | B11: 2 | K11: 2 | L11: =B11+C11+D11+E11+F11-G11-H11-I11-J11 | M11: =K11-B11
A12: Oxen | B12: 28 | C12: =1+2+2 | H12: 8 | K12: 25 | L12: =B12+C12+D12+E12+F12-G12-H12-I12-J12 | M12: =K12-B12 | R12: =Receipts!F56
A13: Bulls | B13: 2 | H13: 1 | K13: 1 | L13: =B13+C13+D13+E13+F13-G13-H13-I13-J13 | M13: =K13-B13 | R13: =Receipts!F57
A14: Cows | B14: 16 | C14: 4 | H14: 4 | K14: 16 | L14: =B14+C14+D14+E14+F14-G14-H14-I14-J14 | M14: =K14-B14 | R14: =Receipts!F58
A15: Steers | B15: 6 | C15: 29 | H15: 29 | J15: =2+4 | K15: 0 | L15: =B15+C15+D15+E15+F15-G15-H15-I15-J15 | M15: =K15-B15 | R15: =Receipts!F60
A16: Bullocks | B16: 5 | I16: 1 | K16: 4 | L16: =B16+C16+D16+E16+F16-G16-H16-I16-J16 | M16: =K16-B16
A17: Yearlings | B17: 4 | K17: 4 | L17: =B17+C17+D17+E17+F17-G17-H17-I17-J17 | M17: =K17-B17
A18: Calves | C18: 12 | H18: 3 | J18: 1 | K18: 8 | L18: =B18+C18+D18+E18+F18-G18-H18-I18-J18 | M18: =K18-B18 | R18: =Receipts!F59
A19: Wethers | B19: 186 | C19: 24 | H19: 14 | I19: =7+1 | K19: 188 | L19: =B19+C19+D19+E19+F19-G19-H19-I19-J19 | M19: =K19-B19 | R19: =Receipts!F61
A20: Rams | B20: 6 | C20: 2 | K20: 8 | L20: =B20+C20+D20+E20+F20-G20-H20-I20-J20 | M20: =K20-B20
A21: Ewes | B21: 176 | C21: 30 | H21: 14 | I21: =11+2 | J21: =2 | K21: 177 | L21: =B21+C21+D21+E21+F21-G21-H21-I21-J21 | M21: =K21-B21 | R21: =Receipts!F62
A22: Hoggs | B22: 64 | I22: =8 | J22: =24+2+30 | K22: 0 | L22: =B22+C22+D22+E22+F22-G22-H22-I22-J22 | M22: =K22-B22
A23: Lambs | C23: =126+7+20 | H23: 13 | I23: =21+10+4 | J23: =12+3 | K23: 90 | L23: =B23+C23+D23+E23+F23-G23-H23-I23-J23 | M23: =K23-B23 | R23: =Receipts!F64
A24: Boars | L24: =B24+C24+D24+E24+F24-G24-H24-I24-J24 | M24: =K24-B24
A25: Sows | B25: 1 | C25: 1 | K25: 2 | L25: =B25+C25+D25+E25+F25-G25-H25-I25-J25 | M25: =K25-B25
A26: Pigs | B26: 11 | C26: =16+11 | D26: 1 | H26: 4 | K26: 35 | L26: =B26+C26+D26+E26+F26-G26-H26-I26-J26 | M26: =K26-B26 | R26: =Receipts!F63
A27: Hoggets | B27: 16 | J27: 16 | K27: 0 | L27: =B27+C27+D27+E27+F27-G27-H27-I27-J27 | M27: =K27-B27
A28: Piglets | C28: 26 | I28: 5 | J28: =2+3 | K28: 16 | L28: =B28+C28+D28+E28+F28-G28-H28-I28-J28 | M28: =K28-B28
A29: Swans | L29: =B29+C29+D29+E29+F29-G29-H29-I29-J29 | M29: =K29-B29
A30: Peacocks | B30: 12 | C30: 2 | K30: 14 | L30: =B30+C30+D30+E30+F30-G30-H30-I30-J30 | M30: =K30-B30
A31: Total Value | L31: =B31+C31+D31+E31+F31-G31-H31-I31-J31 | M31: =K31-B31 | R31: =SUM(R5:R30)
A34: Wool | L34: =B34+C34+D34+E34+F34-G34-H34-I34-J34 | M34: =K34-B34
A35: Coarse wool | C35: =SUM(C36:C39) | J35: =37+1+338 | K35: 0 | L35: =B35+C35+D35+E35+F35-G35-H35-I35-J35 | M35: =K35-B35 | O35: 0.02 | T35: =O35*J35
A36: from wethers | C36: 165 | L36: =B36+C36+D36+E36+F36-G36-H36-I36-J36 | M36: =K36-B36
A37: from rams | C37: 6 | L37: =B37+C37+D37+E37+F37-G37-H37-I37-J37 | M37: =K37-B37
A38: from ewes | C38: 149 | L38: =B38+C38+D38+E38+F38-G38-H38-I38-J38 | M38: =K38-B38
A39: from hoggs | C39: 56 | L39: =B39+C39+D39+E39+F39-G39-H39-I39-J39 | M39: =K39-B39
A40: Lamb's wool | C40: 94 | J40: 94 | K40: 0 | L40: =B40+C40+D40+E40+F40-G40-H40-I40-J40 | M40: =K40-B40 | O40: 0.01 | T40: =O40*J40
A41: Wool locks | L41: =B41+C41+D41+E41+F41-G41-H41-I41-J41 | M41: =K41-B41
A42: Wool sold at shearing | L42: =B42+C42+D42+E42+F42-G42-H42-I42-J42 | M42: =K42-B42
A43: Total wool | L43: =B43+C43+D43+E43+F43-G43-H43-I43-J43 | M43: =K43-B43 | T43: =SUM(T35:T42)
A46: Hides | L46: =B46+C46+D46+E46+F46-G46-H46-I46-J46 | M46: =K46-B46
A47: plough horse | C47: 1 | H47: 1 | L47: =B47+C47+D47+E47+F47-G47-H47-I47-J47 | M47: =K47-B47 | O47: =R47/(H47+H48) | R47: =Receipts!F65 | T47: =O47*C47
A48: colt | C48: 3 | H48: 3 | L48: =B48+C48+D48+E48+F48-G48-H48-I48-J48 | M48: =K48-B48 | O48: =R47/(H47+H48) | R48: =R47 | T48: =O48*C48
A49: yearling | C49: 1 | H49: 1 | L49: =B49+C49+D49+E49+F49-G49-H49-I49-J49 | M49: =K49-B49 | T49: =O49*C49 | U49: sale not recorded in issues of the manor
A50: Ox hides | L50: =B50+C50+D50+E50+F50-G50-H50-I50-J50 | M50: =K50-B50
A51: Mare | L51: =B51+C51+D51+E51+F51-G51-H51-I51-J51 | M51: =K51-B51
A52: Steer | L52: =B52+C52+D52+E52+F52-G52-H52-I52-J52 | M52: =K52-B52
A53: calves | L53: =B53+C53+D53+E53+F53-G53-H53-I53-J53 | M53: =K53-B53
A54: pigs | L54: =B54+C54+D54+E54+F54-G54-H54-I54-J54 | M54: =K54-B54
A55: Woolskins | L55: =B55+C55+D55+E55+F55-G55-H55-I55-J55 | M55: =K55-B55
A56: wethers | C56: 7 | H56: 7 | L56: =B56+C56+D56+E56+F56-G56-H56-I56-J56 | M56: =K56-B56
A57: rams | L57: =B57+C57+D57+E57+F57-G57-H57-I57-J57 | M57: =K57-B57
A58: ewes | C58: 11 | H58: 11 | L58: =B58+C58+D58+E58+F58-G58-H58-I58-J58 | M58: =K58-B58
A59: hoggs | C59: 8 | H59: 8 | L59: =B59+C59+D59+E59+F59-G59-H59-I59-J59 | M59: =K59-B59
A60: Woolskins | C60: =SUM(C56:C59) | H60: =SUM(H56:H59) | O60: =R60/(H60+H62+H64) | R60: =Receipts!F67 | T60: =O60*C60
A61: Bareskins | L61: =B61+C61+D61+E61+F61-G61-H61-I61-J61 | M61: =K61-B61 | T61: =O61*C61
A62: wethers | C62: 1 | H62: 1 | L62: =B62+C62+D62+E62+F62-G62-H62-I62-J62 | M62: =K62-B62 | O62: =R60/(H60+H62+H64) | R62: =Receipts!F67 | T62: =O62*C62
A63: rams | L63: =B63+C63+D63+E63+F63-G63-H63-I63-J63 | M63: =K63-B63 | T63: =O63*C63
A64: ewes | C64: 2 | H64: 2 | L64: =B64+C64+D64+E64+F64-G64-H64-I64-J64 | M64: =K64-B64 | O64: =R60/(H60+H62+H64) | R64: =Receipts!F67 | T64: =O64*C64
A65: hoggs | L65: =B65+C65+D65+E65+F65-G65-H65-I65-J65 | M65: =K65-B65 | T65: =O65*C65
A66: Bareskins (total) | L66: =B66+C66+D66+E66+F66-G66-H66-I66-J66 | M66: =K66-B66 | T66: =O66*C66
A67: Lambskins | C67: =21+14 | H67: =21+14 | L67: =B67+C67+D67+E67+F67-G67-H67-I67-J67 | M67: =K67-B67 | O67: =R67/H67 | R67: =Receipts!F68 | T67: =O67*C67
A68: Rotted skins | L68: =B68+C68+D68+E68+F68-G68-H68-I68-J68 | M68: =K68-B68
A69: Shorn skins | L69: =B69+C69+D69+E69+F69-G69-H69-I69-J69 | M69: =K69-B69
A70: Total | L70: =B70+C70+D70+E70+F70-G70-H70-I70-J70 | M70: =K70-B70 | R70: =R47+R60+R67 | T70: =SUM(T47:T69)
A73: Poultry stock | L73: =B73+C73+D73+E73+F73-G73-H73-I73-J73 | M73: =K73-B73
A74: Hens | L74: =B74+C74+D74+E74+F74-G74-H74-I74-J74 | M74: =K74-B74
A75: Geese | L75: =B75+C75+D75+E75+F75-G75-H75-I75-J75 | M75: =K75-B75
A76: Capons (from chickens) | L76: =B76+C76+D76+E76+F76-G76-H76-I76-J76 | M76: =K76-B76
A77: Cocks & hens | L77: =B77+C77+D77+E77+F77-G77-H77-I77-J77 | M77: =K77-B77
A78: Total poultry stock | L78: =B78+C78+D78+E78+F78-G78-H78-I78-J78 | M78: =K78-B78
A79: Total poultry excluding churchscot | L79: =B79+C79+D79+E79+F79-G79-H79-I79-J79 | M79: =K79-B79
A81: Poultry production | L81: =B81+C81+D81+E81+F81-G81-H81-I81-J81 | M81: =K81-B81
A82: Eggs | F82: 600 | H82: 600 | L82: =B82+C82+D82+E82+F82-G82-H82-I82-J82 | M82: =K82-B82 | O82: =R82/H82 | R82: =Receipts!F75 | T82: =O82*F82
A83: Cocks & hens from churchscot of customary tenants | F83: 162 | G83: =38 | H83: 124 | L83: =B83+C83+D83+E83+F83-G83-H83-I83-J83 | M83: =K83-B83 | O83: =R83/H83 | R83: =Receipts!F74 | T83: =O83*H83
A84: Sum of above | L84: =B84+C84+D84+E84+F84-G84-H84-I84-J84 | M84: =K84-B84
A85: Total | L85: =B85+C85+D85+E85+F85-G85-H85-I85-J85 | M85: =K85-B85 | R85: =SUM(R81:R84) | T85: =SUM(T82:T83)
M86: =K86-B86
M87: =K87-B87
M88: =K88-B88
A89: Beef | L89: =B89+C89+D89+E89+F89-G89-H89-I89-J89 | M89: =K89-B89
A90: Mutton | L90: =B90+C90+D90+E90+F90-G90-H90-I90-J90 | M90: =K90-B90
A91: Pork | L91: =B91+C91+D91+E91+F91-G91-H91-I91-J91 | M91: =K91-B91
A92: Total | L92: =B92+C92+D92+E92+F92-G92-H92-I92-J92 | M92: =K92-B92
M93: =K93-B93
A94: Cheese | L94: =B94+C94+D94+E94+F94-G94-H94-I94-J94 | M94: =K94-B94
A95: Winter cheese | B95: 28 | L95: =B95+C95+D95+E95+F95-G95-H95-I95-J95 | M95: =K95-B95 | O95: =R95/B95 | R95: =Receipts!F71 | T95: =O95*B95
A96: Summer cheese | B96: 162 | H96: 120 | J96: =16+2 | L96: =B96+C96+D96+E96+F96-G96-H96-I96-J96 | M96: =K96-B96 | O96: =R96/H96 | R96: =Receipts!F72 | T96: =O96*B96
A97: Total | L97: =B97+C97+D97+E97+F97-G97-H97-I97-J97 | M97: =K97-B97 | R97: =SUM(R94:R96) | T97: =SUM(T95:T96)
M98: =K98-B98
A99: Butter | L99: =B99+C99+D99+E99+F99-G99-H99-I99-J99 | M99: =K99-B99
A100: Butter | B100: 8 | H100: 8 | K100: 0 | L100: =B100+C100+D100+E100+F100-G100-H100-I100-J100 | M100: =K100-B100 | O100: =R100/H100 | R100: =Receipts!F73 | T100: =R100 | U100: measured in cloves
A101: Total | R101: =SUM(R99:R100) | T101: =R101
A103: Total Dairy Sales
A106: Cider
A109: Additional Information (not necessarily useful)
A110: Utensils
A111: ploughs
A112: carts
A113: cart-ropes
...

Sheet Issues of the Grange raw
A1: Heading | B1: Sentence | C1: Quarters 1_x | D1: Bushels 1_x | E1: Sown Quarters | F1: Sown Bushels | G1: Sown Total Quarters | H1: Bought in Quarters | I1: Bought in Bushels | J1: Bought in Total Quarters | K1: Tithe Quarters | L1: Tithe Bushels | M1: Tithe Total Quarters | N1: Manorial servants & livestock Quarters | O1: Manorial servants & livestock Bushels | P1: Manorial servants & livestock Total Quarters | Q1: Sold Quarters | R1: Sold Bushels | S1: Sold Total Quarters | T1: Account Quarters | U1: Account Bushels | V1: Account Total Quarters | W1: bought only | X1: Total Quarters Except 1 | Y1: Total Bushels Except 1 | Z1: Total Corn Cross-Check | AA1: Total Corn Manorial Account | AB1: Corn Quantity Error | AC1: Quarters 1_y | AD1: Bushels 1_y | AE1: Quarters 2 | AF1: Bushels 2 | AG1: Quarters 3 | AH1: Bushels 3
A2: Cash deliveries | B2: Total | C2: 0 | D2: 0 | E2: 0 | F2: 0 | G2: 0 | H2: 0 | I2: 0 | J2: 0 | K2: 0 | L2: 0 | M2: 0 | N2: 0 | O2: 0 | P2: 0 | Q2: 0 | R2: 0 | S2: 0 | T2: 0 | U2: 0 | V2: 0 | W2: 0
A3: Wheat | B3: {yield: three-and-a-half-fold less 4 quarters 7 bushels} | C3: 0 | D3: 0 | E3: 0 | F3: 0 | G3: 0 | H3: 0 | I3: 0 | J3: 0 | K3: 0 | L3: 0 | M3: 0 | N3: 0 | O3: 0 | P3: 0 | Q3: 0 | R3: 0 | S3: 0 | T3: 0 | U3: 0 | V3: 0 | W3: 0 | X3: 4 | Y3: 7 | Z3: 4.875 | AA3: 4.875 | AB3: 0 | AC3: 4 | AD3: 7
A4: Wheat | B4: The same render account for 64 quarters 6 bushels from the whole issue of wheat from the grange in the granary without heaped measure. | C4: 0 | D4: 0 | E4: 0 | F4: 0 | G4: 0 | H4: 0 | I4: 0 | J4: 0 | K4: 0 | L4: 0 | M4: 0 | N4: 0 | O4: 0 | P4: 0 | Q4: 0 | R4: 0 | S4: 0 | T4: 64 | U4: 6 | V4: 64.75 | W4: 0 | X4: 64 | Y4: 6 | Z4: 64.75 | AA4: 64.75 | AB4: 0 | AC4: 64 | AD4: 6
A5: Wheat | B5: 23 quarters 5 bushels from churchscot. | C5: 0 | D5: 0 | E5: 0 | F5: 0 | G5: 0 | H5: 0 | I5: 0 | J5: 0 | K5: 0 | L5: 0 | M5: 0 | N5: 0 | O5: 0 | P5: 0 | Q5: 0 | R5: 0 | S5: 0 | T5: 0 | U5: 0 | V5: 0 | W5: 0 | X5: 23 | Y5: 5 | Z5: 23.625 | AA5: 23.625 | AB5: 0 | AC5: 23 | AD5: 5
A6: Wheat | B6: Total, 88 quarters 3 bushels | C6: 0 | D6: 0 | E6: 0 | F6: 0 | G6: 0 | H6: 0 | I6: 0 | J6: 0 | K6: 0 | L6: 0 | M6: 0 | N6: 0 | O6: 0 | P6: 0 | Q6: 0 | R6: 0 | S6: 0 | T6: 0 | U6: 0 | V6: 0 | W6: 0 | X6: 88 | Y6: 3 | Z6: 88.375 | AA6: 88.375 | AB6: 0 | AC6: 88 | AD6: 3
A7: Wheat | B7: Sown over 43 acres in the fields of Rowele, Mol' I and la Rude, 16 quarters 1 bushels. | C7: 0 | D7: 0 | E7: 16 | F7: 1 | G7: 16.125 | H7: 0 | I7: 0 | J7: 0 | K7: 0 | L7: 0 | M7: 0 | N7: 0 | O7: 0 | P7: 0 | Q7: 0 | R7: 0 | S7: 0 | T7: 0 | U7: 0 | V7: 0 | W7: 0 | X7: 16 | Y7: 1 | Z7: 16.125 | AA7: 16.125 | AB7: 0 | AC7: 16 | AD7: 1
A8: Wheat | B8: that is, 3 bushels an acre. | C8: 0 | D8: 0 | E8: 0 | F8: 0 | G8: 0 | H8: 0 | I8: 0 | J8: 0 | K8: 0 | L8: 0 | M8: 0 | N8: 0 | O8: 0 | P8: 0 | Q8: 0 | R8: 0 | S8: 0 | T8: 0 | U8: 0 | V8: 0 | W8: 0 | X8: 0 | Y8: 3 | Z8: 0.375 | AA8: 0.375 | AB8: 0 | AC8: 0 | AD8: 3
A9: Wheat | B9: . | C9: 0 | D9: 0 | E9: 0 | F9: 0 | G9: 0 | H9: 0 | I9: 0 | J9: 0 | K9: 0 | L9: 0 | M9: 0 | N9: 0 | O9: 0 | P9: 0 | Q9: 0 | R9: 0 | S9: 0 | T9: 0 | U9: 0 | V9: 0 | W9: 0 | X9: 0 | Y9: 0 | Z9: 0 | AA9: 0 | AB9: 0 | AC9: 0 | AD9: 0
A10: Wheat | B10: provision of Simon, clerk, for 2 tourns, 4 bushels. | C10: 0 | D10: 0 | E10: 0 | F10: 0 | G10: 0 | H10: 0 | I10: 0 | J10: 0 | K10: 0 | L10: 0 | M10: 0 | N10: 0 | O10: 0 | P10: 0 | Q10: 0 | R10: 0 | S10: 0 | T10: 0 | U10: 0 | V10: 0 | W10: 0 | X10: 0 | Y10: 4 | Z10: 0.5 | AA10: 0.5 | AB10: 0 | AC10: 0 | AD10: 4
A11: Wheat | B11: provision of the bailiff for the year, 11 quarters 2 bushels Sold, 60.5 quarters. | C11: 0 | D11: 0 | E11: 0 | F11: 0 | G11: 0 | H11: 0 | I11: 0 | J11: 0 | K11: 0 | L11: 0 | M11: 0 | N11: 0 | O11: 0 | P11: 0 | Q11: 71.5 | R11: 2 | S11: 71.75 | T11: 0 | U11: 0 | V11: 0 | W11: 0 | X11: 60.5 | Y11: 2 | Z11: 60.75 | AA11: 11.25 | AB11: 49.5 | AC11: 11 | AD11: 2 | AE11: 60.5 | AF11: 0
A12: Wheat | B12: Total | C12: 0 | D12: 0 | E12: 0 | F12: 0 | G12: 0 | H12: 0 | I12: 0 | J12: 0 | K12: 0 | L12: 0 | M12: 0 | N12: 0 | O12: 0 | P12: 0 | Q12: 0 | R12: 0 | S12: 0 | T12: 0 | U12: 0 | V12: 0 | W12: 0
A13: Curall | B13: The same render account for 1 qr 2 bushels from the whole issue of curall from the grange in the granary without heaped measure. | C13: 0 | D13: 0 | E13: 0 | F13: 0 | G13: 0 | H13: 0 | I13: 0 | J13: 0 | K13: 0 | L13: 0 | M13: 0 | N13: 0 | O13: 0 | P13: 0 | Q13: 0 | R13: 0 | S13: 0 | T13: 0 | U13: 0 | V13: 0 | W13: 0
A14: Curall | B14: Mixed with barley for the liveries of the manorial servants, 5 bushels Sold, 5 bushels | C14: 0 | D14: 0 | E14: 0 | F14: 0 | G14: 0 | H14: 0 | I14: 0 | J14: 0 | K14: 0 | L14: 0 | M14: 0 | N14: 0 | O14: 0 | P14: 0 | Q14: 0 | R14: 0 | S14: 0 | T14: 0 | U14: 0 | V14: 0 | W14: 0 | X14: 0 | Y14: 5 | Z14: 0.625 | AA14: 0.625 | AB14: 0 | AC14: 0 | AD14: 5 | AE14: 0 | AF14: 5
A15: Curall | B15: Total | C15: 0 | D15: 0 | E15: 0 | F15: 0 | G15: 0 | H15: 0 | I15: 0 | J15: 0 | K15: 0 | L15: 0 | M15: 0 | N15: 0 | O15: 0 | P15: 0 | Q15: 0 | R15: 0 | S15: 0 | T15: 0 | U15: 0 | V15: 0 | W15: 0
A16: Barley | B16: {yield: three-fold less 5 quarters 2 bushels} | C16: 0 | D16: 0 | E16: 0 | F16: 0 | G16: 0 | H16: 0 | I16: 0 | J16: 0 | K16: 0 | L16: 0 | M16: 0 | N16: 0 | O16: 0 | P16: 0 | Q16: 0 | R16: 0 | S16: 0 | T16: 0 | U16: 0 | V16: 0 | W16: 0 | X16: 5 | Y16: 2 | Z16: 5.25 | AA16: 5.25 | AB16: 0 | AC16: 5 | AD16: 2
A17: Barley | B17: The same render account for 35 quarters 2 bushels from the whole issue of barley from the grange in the granary without heaped measure. | C17: 0 | D17: 0 | E17: 0 | F17: 0 | G17: 0 | H17: 0 | I17: 0 | J17: 0 | K17: 0 | L17: 0 | M17: 0 | N17: 0 | O17: 0 | P17: 0 | Q17: 0 | R17: 0 | S17: 0 | T17: 35 | U17: 2 | V17: 35.25 | W17: 0 | X17: 35 | Y17: 2 | Z17: 35.25 | AA17: 35.25 | AB17: 0 | AC17: 35 | AD17: 2
A18: Barley | B18: 5 bushels of curall received for the liveries of the manorial servants. | C18: 0 | D18: 0 | E18: 0 | F18: 0 | G18: 0 | H18: 0 | I18: 0 | J18: 0 | K18: 0 | L18: 0 | M18: 0 | N18: 0 | O18: 0 | P18: 0 | Q18: 0 | R18: 0 | S18: 0 | T18: 0 | U18: 0 | V18: 0 | W18: 0 | X18: 0 | Y18: 5 | Z18: 0.625 | AA18: 0.625 | AB18: 0 | AC18: 0 | AD18: 5
A19: Barley | B19: 1 bushels of vetches received for the same. | C19: 0 | D19: 0 | E19: 0 | F19: 0 | G19: 0 | H19: 0 | I19: 0 | J19: 0 | K19: 0 | L19: 0 | M19: 0 | N19: 0 | O19: 0 | P19: 0 | Q19: 0 | R19: 0 | S19: 0 | T19: 0 | U19: 0 | V19: 0 | W19: 0 | X19: 0 | Y19: 1 | Z19: 0.125 | AA19: 0.125 | AB19: 0 | AC19: 0 | AD19: 1
A20: Barley | B20: Total, 36 quarters. | C20: 0 | D20: 0 | E20: 0 | F20: 0 | G20: 0 | H20: 0 | I20: 0 | J20: 0 | K20: 0 | L20: 0 | M20: 0 | N20: 0 | O20: 0 | P20: 0 | Q20: 0 | R20: 0 | S20: 0 | T20: 0 | U20: 0 | V20: 0 | W20: 0 | X20: 36 | Y20: 0 | Z20: 36 | AA20: 36 | AB20: 0 | AC20: 36 | AD20: 0
A21: Barley | B21: Sown over 23 acres in the field of Bradewey and beside the sheepcote, 11.5 quarters. | C21: 0 | D21: 0 | E21: 11.5 | F21: 0 | G21: 11.5 | H21: 0 | I21: 0 | J21: 0 | K21: 0 | L21: 0 | M21: 0 | N21: 0 | O21: 0 | P21: 0 | Q21: 0 | R21: 0 | S21: 0 | T21: 0 | U21: 0 | V21: 0 | W21: 0 | X21: 11.5 | Y21: 0 | Z21: 11.5 | AA21: 11.5 | AB21: 0 | AC21: 11.5 | AD21: 0
A22: Barley | B22: that is, .5 qr an acre. | C22: 0 | D22: 0 | E22: 0 | F22: 0 | G22: 0 | H22: 0 | I22: 0 | J22: 0 | K22: 0 | L22: 0 | M22: 0 | N22: 0 | O22: 0 | P22: 0 | Q22: 0 | R22: 0 | S22: 0 | T22: 0 | U22: 0 | V22: 0 | W22: 0
A23: Barley | B23: Delivered to 1 carter for the year, 6.5 quarters, taking a quarter every 8 weeks. | C23: 0 | D23: 0 | E23: 0 | F23: 0 | G23: 0 | H23: 0 | I23: 0 | J23: 0 | K23: 0 | L23: 0 | M23: 0 | N23: 0 | O23: 0 | P23: 0 | Q23: 0 | R23: 0 | S23: 0 | T23: 0 | U23: 0 | V23: 0 | W23: 0 | X23: 6.5 | Y23: 0 | Z23: 6.5 | AA23: 6.5 | AB23: 0 | AC23: 6.5 | AD23: 0
A24: Barley | B24: Delivered to 1 man who is in place of the dairymaid and who makes the cheese and keeps the garden and does other work in the curia, 5 quarters 1.5 bushels, taking a quarter every 10 weeks. | C24: 0 | D24: 0 | E24: 0 | F24: 0 | G24: 0 | H24: 0 | I24: 0 | J24: 0 | K24: 0 | L24: 0 | M24: 0 | N24: 0 | O24: 0 | P24: 0 | Q24: 0 | R24: 0 | S24: 0 | T24: 0 | U24: 0 | V24: 0 | W24: 0 | X24: 5 | Y24: 1.5 | Z24: 5.1875 | AA24: 5.1875 | AB24: 0 | AC24: 5 | AD24: 1.5
A25: Barley | B25: Delivered to 1 harrower, 4 bushels. | C25: 0 | D25: 0 | E25: 0 | F25: 0 | G25: 0 | H25: 0 | I25: 0 | J25: 0 | K25: 0 | L25: 0 | M25: 0 | N25: 0 | O25: 0 | P25: 0 | Q25: 0 | R25: 0 | S25: 0 | T25: 0 | U25: 0 | V25: 0 | W25: 0 | X25: 0 | Y25: 4 | Z25: 0.5 | AA25: 0.5 | AB25: 0 | AC25: 0 | AD25: 4
A26: Barley | B26: provision of the bailiff's attendant, 2 quarters. | C26: 0 | D26: 0 | E26: 0 | F26: 0 | G26: 0 | H26: 0 | I26: 0 | J26: 0 | K26: 0 | L26: 0 | M26: 0 | N26: 0 | O26: 0 | P26: 0 | Q26: 0 | R26: 0 | S26: 0 | T26: 0 | U26: 0 | V26: 0 | W26: 0 | X26: 2 | Y26: 0 | Z26: 2 | AA26: 2 | AB26: 0 | AC26: 2 | AD26: 0
A27: Barley | B27: Delivered to 1 keeper of lambs on Fobedon' with the lambs of Wield for 23 weeks, 2 quarters 2 bushels. | C27: 0 | D27: 0 | E27: 0 | F27: 0 | G27: 0 | H27: 0 | I27: 0 | J27: 0 | K27: 0 | L27: 0 | M27: 0 | N27: 0 | O27: 0 | P27: 0 | Q27: 0 | R27: 0 | S27: 0 | T27: 0 | U27: 0 | V27: 0 | W27: 0 | X27: 2 | Y27: 2 | Z27: 2.25 | AA27: 2.25 | AB27: 0 | AC27: 2 | AD27: 2
A28: Barley | B28: customary payment to the swineherd this year, 6 bushels Sold, 6.5 quarters. | C28: 0 | D28: 0 | E28: 0 | F28: 0 | G28: 0 | H28: 0 | I28: 0 | J28: 0 | K28: 0 | L28: 0 | M28: 0 | N28: 0 | O28: 0 | P28: 0 | Q28: 6.5 | R28: 0 | S28: 6.5 | T28: 0 | U28: 0 | V28: 0 | W28: 0 | X28: 6.5 | Y28: 6 | Z28: 7.25 | AA28: 0.75 | AB28: 6.5 | AC28: 0 | AD28: 6 | AE28: 6.5 | AF28: 0
A29: Barley | B29: Sold at the audit, 6.5 bushels | C29: 0 | D29: 0 | E29: 0 | F29: 0 | G29: 0 | H29: 0 | I29: 0 | J29: 0 | K29: 0 | L29: 0 | M29: 0 | N29: 0 | O29: 0 | P29: 0 | Q29: 0 | R29: 0 | S29: 0 | T29: 0 | U29: 0 | V29: 0 | W29: 0 | X29: 0 | Y29: 6.5 | Z29: 0.8125 | AA29: 0.8125 | AB29: 0 | AC29: 0 | AD29: 6.5
A30: Barley | B30: Total | C30: 0 | D30: 0 | E30: 0 | F30: 0 | G30: 0 | H30: 0 | I30: 0 | J30: 0 | K30: 0 | L30: 0 | M30: 0 | N30: 0 | O30: 0 | P30: 0 | Q30: 0 | R30: 0 | S30: 0 | T30: 0 | U30: 0 | V30: 0 | W30: 0
A31: Oats | B31: {yield: two-fold less 7.5 quarters} | C31: 0 | D31: 0 | E31: 0 | F31: 0 | G31: 0 | H31: 0 | I31: 0 | J31: 0 | K31: 0 | L31: 0 | M31: 0 | N31: 0 | O31: 0 | P31: 0 | Q31: 0 | R31: 0 | S31: 0 | T31: 0 | U31: 0 | V31: 0 | W31: 0 | X31: 7.5 | Y31: 0 | Z31: 7.5 | AA31: 7.5 | AB31: 0 | AC31: 7.5 | AD31: 0
A32: Oats | B32: The same render account for 60 quarters from the whole issue of oats from the grange in the granary without heaped measure. | C32: 0 | D32: 0 | E32: 0 | F32: 0 | G32: 0 | H32: 0 | I32: 0 | J32: 0 | K32: 0 | L32: 0 | M32: 0 | N32: 0 | O32: 0 | P32: 0 | Q32: 0 | R32: 0 | S32: 0 | T32: 60 | U32: 0 | V32: 60 | W32: 0 | X32: 60 | Y32: 0 | Z32: 60 | AA32: 60 | AB32: 0 | AC32: 60 | AD32: 0
A33: Oats | B33: 15 quarters by estimation in sheaves given to oxen. | C33: 0 | D33: 0 | E33: 0 | F33: 0 | G33: 0 | H33: 0 | I33: 0 | J33: 0 | K33: 0 | L33: 0 | M33: 0 | N33: 0 | O33: 0 | P33: 0 | Q33: 0 | R33: 0 | S33: 0 | T33: 0 | U33: 0 | V33: 0 | W33: 0 | X33: 15 | Y33: 0 | Z33: 15 | AA33: 15 | AB33: 0 | AC33: 15 | AD33: 0
A34: Oats | B34: 15 quarters bought. | C34: 0 | D34: 0 | E34: 0 | F34: 0 | G34: 0 | H34: 15 | I34: 0 | J34: 15 | K34: 0 | L34: 0 | M34: 0 | N34: 0 | O34: 0 | P34: 0 | Q34: 0 | R34: 0 | S34: 0 | T34: 0 | U34: 0 | V34: 0 | W34: 0 | X34: 15 | Y34: 0 | Z34: 15 | AA34: 15 | AB34: 0 | AC34: 15 | AD34: 0
A35: Oats | B35: Total, 90 quarters. | C35: 0 | D35: 0 | E35: 0 | F35: 0 | G35: 0 | H35: 0 | I35: 0 | J35: 0 | K35: 0 | L35: 0 | M35: 0 | N35: 0 | O35: 0 | P35: 0 | Q35: 0 | R35: 0 | S35: 0 | T35: 0 | U35: 0 | V35: 0 | W35: 0 | X35: 90 | Y35: 0 | Z35: 90 | AA35: 90 | AB35: 0 | AC35: 90 | AD35: 0
A36: Oats | B36: Sown over 72 acres in the fields of Rowele, Holecumbe and la Rude, 36 quarters. | C36: 0 | D36: 0 | E36: 36 | F36: 0 | G36: 36 | H36: 0 | I36: 0 | J36: 0 | K36: 0 | L36: 0 | M36: 0 | N36: 0 | O36: 0 | P36: 0 | Q36: 0 | R36: 0 | S36: 0 | T36: 0 | U36: 0 | V36: 0 | W36: 0 | X36: 36 | Y36: 0 | Z36: 36 | AA36: 36 | AB36: 0 | AC36: 36 | AD36: 0
A37: Oats | B37: that is, .5 qr an acre. | C37: 0 | D37: 0 | E37: 0 | F37: 0 | G37: 0 | H37: 0 | I37: 0 | J37: 0 | K37: 0 | L37: 0 | M37: 0 | N37: 0 | O37: 0 | P37: 0 | Q37: 0 | R37: 0 | S37: 0 | T37: 0 | U37: 0 | V37: 0 | W37: 0
A38: Oats | B38: . | C38: 0 | D38: 0 | E38: 0 | F38: 0 | G38: 0 | H38: 0 | I38: 0 | J38: 0 | K38: 0 | L38: 0 | M38: 0 | N38: 0 | O38: 0 | P38: 0 | Q38: 0 | R38: 0 | S38: 0 | T38: 0 | U38: 0 | V38: 0 | W38: 0 | X38: 0 | Y38: 0 | Z38: 0 | AA38: 0 | AB38: 0 | AC38: 0 | AD38: 0
A39: Oats | B39: . | C39: 0 | D39: 0 | E39: 0 | F39: 0 | G39: 0 | H39: 0 | I39: 0 | J39: 0 | K39: 0 | L39: 0 | M39: 0 | N39: 0 | O39: 0 | P39: 0 | Q39: 0 | R39: 0 | S39: 0 | T39: 0 | U39: 0 | V39: 0 | W39: 0 | X39: 0 | Y39: 0 | Z39: 0 | AA39: 0 | AB39: 0 | AC39: 0 | AD39: 0
A40: Oats | B40: . | C40: 0 | D40: 0 | E40: 0 | F40: 0 | G40: 0 | H40: 0 | I40: 0 | J40: 0 | K40: 0 | L40: 0 | M40: 0 | N40: 0 | O40: 0 | P40: 0 | Q40: 0 | R40: 0 | S40: 0 | T40: 0 | U40: 0 | V40: 0 | W40: 0 | X40: 0 | Y40: 0 | Z40: 0 | AA40: 0 | AB40: 0 | AC40: 0 | AD40: 0
A41: Oats | B41: . | C41: 0 | D41: 0 | E41: 0 | F41: 0 | G41: 0 | H41: 0 | I41: 0 | J41: 0 | K41: 0 | L41: 0 | M41: 0 | N41: 0 | O41: 0 | P41: 0 | Q41: 0 | R41: 0 | S41: 0 | T41: 0 | U41: 0 | V41: 0 | W41: 0 | X41: 0 | Y41: 0 | Z41: 0 | AA41: 0 | AB41: 0 | AC41: 0 | AD41: 0
A42: Oats | B42: fodder of 3 cart-horses harrowing at both sowings, 18.5 quarters. | C42: 0 | D42: 0 | E42: 0 | F42: 0 | G42: 0 | H42: 0 | I42: 0 | J42: 0 | K42: 0 | L42: 0 | M42: 0 | N42: 18.5 | O42: 0 | P42: 18.5 | Q42: 0 | R42: 0 | S42: 0 | T42: 0 | U42: 0 | V42: 0 | W42: 0 | X42: 18.5 | Y42: 0 | Z42: 18.5 | AA42: 18.5 | AB42: 0 | AC42: 18.5 | AD42: 0
A43: Oats | B43: . | C43: 0 | D43: 0 | E43: 0 | F43: 0 | G43: 0 | H43: 0 | I43: 0 | J43: 0 | K43: 0 | L43: 0 | M43: 0 | N43: 0 | O43: 0 | P43: 0 | Q43: 0 | R43: 0 | S43: 0 | T43: 0 | U43: 0 | V43: 0 | W43: 0 | X43: 0 | Y43: 0 | Z43: 0 | AA43: 0 | AB43: 0 | AC43: 0 | AD43: 0
A44: Oats | B44: . | C44: 0 | D44: 0 | E44: 0 | F44: 0 | G44: 0 | H44: 0 | I44: 0 | J44: 0 | K44: 0 | L44: 0 | M44: 0 | N44: 0 | O44: 0 | P44: 0 | Q44: 0 | R44: 0 | S44: 0 | T44: 0 | U44: 0 | V44: 0 | W44: 0 | X44: 0 | Y44: 0 | Z44: 0 | AA44: 0 | AB44: 0 | AC44: 0 | AD44: 0
A45: Oats | B45: . | C45: 0 | D45: 0 | E45: 0 | F45: 0 | G45: 0 | H45: 0 | I45: 0 | J45: 0 | K45: 0 | L45: 0 | M45: 0 | N45: 0 | O45: 0 | P45: 0 | Q45: 0 | R45: 0 | S45: 0 | T45: 0 | U45: 0 | V45: 0 | W45: 0 | X45: 0 | Y45: 0 | Z45: 0 | AA45: 0 | AB45: 0 | AC45: 0 | AD45: 0
A46: Oats | B46: . | C46: 0 | D46: 0 | E46: 0 | F46: 0 | G46: 0 | H46: 0 | I46: 0 | J46: 0 | K46: 0 | L46: 0 | M46: 0 | N46: 0 | O46: 0 | P46: 0 | Q46: 0 | R46: 0 | S46: 0 | T46: 0 | U46: 0 | V46: 0 | W46: 0 | X46: 0 | Y46: 0 | Z46: 0 | AA46: 0 | AB46: 0 | AC46: 0 | AD46: 0
A47: Oats | B47: fodder of oxen by estimation in sheaves, 15 quarters. | C47: 0 | D47: 0 | E47: 0 | F47: 0 | G47: 0 | H47: 0 | I47: 0 | J47: 0 | K47: 0 | L47: 0 | M47: 0 | N47: 15 | O47: 0 | P47: 15 | Q47: 0 | R47: 0 | S47: 0 | T47: 0 | U47: 0 | V47: 0 | W47: 0 | X47: 15 | Y47: 0 | Z47: 15 | AA47: 15 | AB47: 0 | AC47: 15 | AD47: 0
A48: Oats | B48: . | C48: 0 | D48: 0 | E48: 0 | F48: 0 | G48: 0 | H48: 0 | I48: 0 | J48: 0 | K48: 0 | L48: 0 | M48: 0 | N48: 0 | O48: 0 | P48: 0 | Q48: 0 | R48: 0 | S48: 0 | T48: 0 | U48: 0 | V48: 0 | W48: 0 | X48: 0 | Y48: 0 | Z48: 0 | AA48: 0 | AB48: 0 | AC48: 0 | AD48: 0
A49: Oats | B49: . | C49: 0 | D49: 0 | E49: 0 | F49: 0 | G49: 0 | H49: 0 | I49: 0 | J49: 0 | K49: 0 | L49: 0 | M49: 0 | N49: 0 | O49: 0 | P49: 0 | Q49: 0 | R49: 0 | S49: 0 | T49: 0 | U49: 0 | V49: 0 | W49: 0 | X49: 0 | Y49: 0 | Z49: 0 | AA49: 0 | AB49: 0 | AC49: 0 | AD49: 0
... A58: Oats | B58: fodder of the clerk's horse, 2 quarters until Christmas. | C58: 0 | D58: 0 | E58: 0 | F58: 0 | G58: 0 | H58: 0 | I58: 0 | J58: 0 | K58: 0 | L58: 0 | M58: 0 | N58: 2 | O58: 0 | P58: 2 | Q58: 0 | R58: 0 | S58: 0 | T58: 0 | U58: 0 | V58: 0 | W58: 0 | X58: 2 | Y58: 0 | Z58: 2 | AA58: 2 | AB58: 0 | AC58: 2 | AD58: 0
A59: Oats | B59: Total | C59: 0 | D59: 0 | E59: 0 | F59: 0 | G59: 0 | H59: 0 | I59: 0 | J59: 0 | K59: 0 | L59: 0 | M59: 0 | N59: 0 | O59: 0 | P59: 0 | Q59: 0 | R59: 0 | S59: 0 | T59: 0 | U59: 0 | V59: 0 | W59: 0
A60: Peas | B60: {yield: 3-fold} | C60: 0 | D60: 0 | E60: 0 | F60: 0 | G60: 0 | H60: 0 | I60: 0 | J60: 0 | K60: 0 | L60: 0 | M60: 0 | N60: 0 | O60: 0 | P60: 0 | Q60: 0 | R60: 0 | S60: 0 | T60: 0 | U60: 0 | V60: 0 | W60: 0 | X60: 0 | Y60: 0 | Z60: 0 | AA60: 0 | AB60: 0 | AC60: 0 | AD60: 0
A61: Peas | B61: The same render account for 1.5 quarters from the whole issue of peas from the grange in the granary without heaped measure. | C61: 0 | D61: 0 | E61: 0 | F61: 0 | G61: 0 | H61: 0 | I61: 0 | J61: 0 | K61: 0 | L61: 0 | M61: 0 | N61: 0 | O61: 0 | P61: 0 | Q61: 0 | R61: 0 | S61: 0 | T61: 1.5 | U61: 0 | V61: 1.5 | W61: 0 | X61: 1.5 | Y61: 0 | Z61: 1.5 | AA61: 1.5 | AB61: 0 | AC61: 1.5 | AD61: 0
A62: Peas | B62: Sown, 1 qr. | C62: 0 | D62: 0 | E62: 0 | F62: 0 | G62: 0 | H62: 0 | I62: 0 | J62: 0 | K62: 0 | L62: 0 | M62: 0 | N62: 0 | O62: 0 | P62: 0 | Q62: 0 | R62: 0 | S62: 0 | T62: 0 | U62: 0 | V62: 0 | W62: 0
A63: Peas | B63: Sold, 4 bushels | C63: 0 | D63: 0 | E63: 0 | F63: 0 | G63: 0 | H63: 0 | I63: 0 | J63: 0 | K63: 0 | L63: 0 | M63: 0 | N63: 0 | O63: 0 | P63: 0 | Q63: 0 | R63: 0 | S63: 0 | T63: 0 | U63: 0 | V63: 0 | W63: 0 | X63: 0 | Y63: 4 | Z63: 0.5 | AA63: 0.5 | AB63: 0 | AC63: 0 | AD63: 4
A64: Peas | B64: Total | C64: 0 | D64: 0 | E64: 0 | F64: 0 | G64: 0 | H64: 0 | I64: 0 | J64: 0 | K64: 0 | L64: 0 | M64: 0 | N64: 0 | O64: 0 | P64: 0 | Q64: 0 | R64: 0 | S64: 0 | T64: 0 | U64: 0 | V64: 0 | W64: 0
A65: Vetches | B65: (yield: two-fold plus 3 bushels) | C65: 0 | D65: 0 | E65: 0 | F65: 0 | G65: 0 | H65: 0 | I65: 0 | J65: 0 | K65: 0 | L65: 0 | M65: 0 | N65: 0 | O65: 0 | P65: 0 | Q65: 0 | R65: 0 | S65: 0 | T65: 0 | U65: 0 | V65: 0 | W65: 0 | X65: 0 | Y65: 3 | Z65: 0.375 | AA65: 0.375 | AB65: 0 | AC65: 0 | AD65: 3
A66: Vetches | B66: The same render account for 2 quarters 5 bushels from the whole issue of vetches. | C66: 0 | D66: 0 | E66: 0 | F66: 0 | G66: 0 | H66: 0 | I66: 0 | J66: 0 | K66: 0 | L66: 0 | M66: 0 | N66: 0 | O66: 0 | P66: 0 | Q66: 0 | R66: 0 | S66: 0 | T66: 2 | U66: 5 | V66: 2.625 | W66: 0 | X66: 2 | Y66: 5 | Z66: 2.625 | AA66: 2.625 | AB66: 0 | AC66: 2 | AD66: 5
A67: Vetches | B67: Sown, 5 bushels Mixed with barley for the liveries of the manorial servants, 1 bushels. | C67: 0 | D67: 0 | E67: 0 | F67: 0 | G67: 0 | H67: 0 | I67: 0 | J67: 0 | K67: 0 | L67: 0 | M67: 0 | N67: 0 | O67: 0 | P67: 0 | Q67: 0 | R67: 0 | S67: 0 | T67: 0 | U67: 0 | V67: 0 | W67: 0 | X67: 0 | Y67: 1 | Z67: 0.125 | AA67: 0.625 | AB67: -0.5 | AC67: 0 | AD67: 5 | AE67: 0 | AF67: 1
A68: Vetches | B68: supporting pigs and piglets, 1 qr 3 bushels Sold, 3 bushels | C68: 0 | D68: 0 | E68: 0 | F68: 0 | G68: 0 | H68: 0 | I68: 0 | J68: 0 | K68: 0 | L68: 0 | M68: 0 | N68: 0 | O68: 0 | P68: 0 | Q68: 0 | R68: 0 | S68: 0 | T68: 0 | U68: 0 | V68: 0 | W68: 0

Sheet Sale of Corn Prices
A1: Heading | B1: Sentence | C1: Total in Pounds | D1: Pounds | E1: Shillings | F1: Pence | G1: Corn | H1: Total Quarters Except 1 | I1: Total Bushels Except 1 | J1: Total Corn Cross-Check | K1: Total Corn Manorial Account | L1: Corn Quantity Error | M1: Quarters 0 | N1: Bushels 0 | O1: shilling a quarter 1 | P1: pence a quarter 1 | Q1: Quarters 1 | R1: Bushels 1 | S1: shilling a quarter 2 | T1: pence a quarter 2 | U1: Quarters 2 | V1: Bushels 2 | W1: shilling a quarter 3 | X1: pence a quarter 3 | Y1: shilling a quarter 4 | Z1: pence a quarter 4 | AA1: £ a quarter 1 | AB1: £ a quarter 2 | AC1: £ a quarter 3 | AD1: £ a quarter 4 | AE1: Quarters Sold | AF1: Weighted Average Price per Quarter | AG1: Non-Weighted Average Price per Quarter | AH1: Corn lowercase

Sheet raw data
A1: Heading | B1: Sentence | C1: Total in Pounds | D1: Pounds | E1: Shillings | F1: Pence | G1: Corn | H1: Total Quarters Except 1 | I1: Total Bushels Except 1 | J1: Total Corn Cross-Check | K1: Total Corn Manorial Account | L1: Corn Quantity Error | M1: Quarters 1 | N1: Bushels 1 | O1: Quarters 2 | P1: Bushels 2 | Q1: Quarters 3 | R1: Bushels 3 | S1: shilling a quarter 1 | T1: pence a quarter 1 | U1: shilling a quarter 2 | V1: pence a quarter 2 | W1: shilling a quarter 3 | X1: pence a quarter 3 | Y1: shilling a quarter 4 | Z1: pence a quarter 4 | AA1: shilling a bushel 1 | AB1: pence a bushel 1 | AC1: shilling a bushel 2 | AD1: pence a bushel 2 | AE1: shilling a bushel 3 | AF1: pence a bushel 3 | AG1: shilling a bushel 4 | AH1: pence a bushel 4
A2: Arrears | B2: Nicholas, bailiff, and Walter de Manestrott', reeve, render account for £48 7 shilling 7.5pence of arrears from the previous year. | C2: 48.38 | D2: 48 | E2: 7 | F2: 7.5 | H2: 0 | I2: 0 | J2: 0 | K2: 0 | L2: 0 | M2: 0 | N2: 0
A3: Arrears | B3: All delivered to Sir Geoffrey de Farham, treasurer of Wolvesey, and they are quit. | C3: 0 | D3: 0 | E3: 0 | F3: 0 | H3: 0 | I3: 0 | J3: 0 | K3: 0 | L3: 0 | M3: 0 | N3: 0
A4: Rents of assize | B4: The same render account for £49 for all rents of assize in the manor of Bishops Sutton for the year: £9 7 shilling 3pence at Christmas. | C4: 49 | D4: 49 | E4: 0 | F4: 0 | H4: 0 | I4: 0 | J4: 0 | K4: 0 | L4: 0 | M4: 0 | N4: 0
A5: Rents of assize | B5: £9 7 shilling 2.5pence at Easter (22 April). | C5: 9.36 | D5: 9 | E5: 7 | F5: 2.5 | H5: 0 | I5: 0 | J5: 0 | K5: 0 | L5: 0 | M5: 0 | N5: 0
A6: Rents of assize | B6: £9 7 shilling 3.25pence at the feast of St John the Baptist (24 June). | C6: 9.36 | D6: 9 | E6: 7 | F6: 3.25 | H6: 0 | I6: 0 | J6: 0 | K6: 0 | L6: 0 | M6: 0 | N6: 0
A7: Rents of assize | B7: £21 17 shilling 1.25pence at Michaelmas (29 September). | C7: 21.86 | D7: 21 | E7: 17 | F7: 1.25 | H7: 0 | I7: 0 | J7: 0 | K7: 0 | L7: 0 | M7: 0 | N7: 0
A8: Rents of assize | B8: Total, £49 18 shilling 10pence | C8: 49.94 | D8: 49 | E8: 18 | F8: 10 | H8: 0 | I8: 0 | J8: 0 | K8: 0 | L8: 0 | M8: 0 | N8: 0
A9: Quittances | B9: In quittance of 1 reeve for the year 5 shilling. | C9: 0.25 | D9: 0 | E9: 5 | F9: 0 | H9: 0 | I9: 0 | J9: 0 | K9: 0 | L9: 0 | M9: 0 | N9: 0
A10: Quittances | B10: 1 beadle who is hayward for the year 3 shilling. | C10: 0.15 | D10: 0 | E10: 3 | F10: 0 | H10: 0 | I10: 0 | J10: 0 | K10: 0 | L10: 0 | M10: 0 | N10: 0
A11: Quittances | B11: 1 smith for the year 2 shilling. | C11: 0.1 | D11: 0 | E11: 2 | F11: 0 | H11: 0 | I11: 0 | J11: 0 | K11: 0 | L11: 0 | M11: 0 | N11: 0
A12: Quittances | B12: 1 shepherd for three terms because there was no threshing in the fourth term 2 shilling 3pence. | C12: 0.11 | D12: 0 | E12: 2 | F12: 3 | H12: 0 | I12: 0 | J12: 0 | K12: 0 | L12: 0 | M12: 0 | N12: 0
A13: Quittances | B13: 1 shepherd for the year 3 shilling. | C13: 0.15 | D13: 0 | E13: 3 | F13: 0 | H13: 0 | I13: 0 | J13: 0 | K13: 0 | L13: 0 | M13: 0 | N13: 0
... A65: Issues of the manor | B65: Total, £33 1 shilling 2.25pence | C65: 33.06 | D65: 33 | E65: 1 | F65: 2.25 | H65: 0 | I65: 0 | J65: 0 | K65: 0 | L65: 0 | M65: 0 | N65: 0
A66: Sale of wheat | B66: The same render account for £18 3 shilling from 60.5 quarters of wheat sold, at 6 shilling a quarters. | C66: 18.15 | D66: 18 | E66: 3 | F66: 0 | G66: wheat | H66: 60.5 | I66: 0 | J66: 60.5 | K66: 60.5 | L66: 0 | M66: 60.5 | N66: 0 | S66: 6 | T66: 0
A67: Sale of wheat | B67: 2 shilling 11pence from 5 bushels of curall sold. | C67: 0.15 | D67: 0 | E67: 2 | F67: 11 | G67: curall | H67: 0 | I67: 5 | J67: 0.625 | K67: 0.625 | L67: 0 | M67: 0 | N67: 5
A68: Sale of wheat | B68: £1 10 shilling 4pence from 6.5 quarters of barley sold, at 4 shilling 8pence a quarters. | C68: 1.52 | D68: 1 | E68: 10 | F68: 4 | G68: barley | H68: 6.5 | I68: 0 | J68: 6.5 | K68: 6.5 | L68: 0 | M68: 6.5 | N68: 0 | S68: 4 | T68: 8
A69: Sale of wheat | B69: 1 shilling 6pence from 4 bushels of peas sold. | C69: 0.08 | D69: 0 | E69: 1 | F69: 6 | G69: peas | H69: 0 | I69: 4 | J69: 0.5 | K69: 0.5 | L69: 0 | M69: 0 | N69: 4
A70: Sale of wheat | B70: 1 shilling from 4 bushels of vetches sold. | C70: 0.05 | D70: 0 | E70: 1 | F70: 0 | G70: vetches | H70: 0 | I70: 4 | J70: 0.5 | K70: 0.5 | L70: 0 | M70: 0 | N70: 4
A71: Sale of wheat | B71: 3 shilling 9.5pence from 6.5 bushels of barley sold at the audit. | C71: 0.19 | D71: 0 | E71: 3 | F71: 9.5 | G71: barley | H71: 0 | I71: 6.5 | J71: 0.8125 | K71: 0.8125 | L71: 0 | M71: 0 | N71: 6.5
A72: Sale of wheat | B72: Total, £20 2 shilling 6.5pence | C72: 20.13 | D72: 20 | E72: 2 | F72: 6.5 | H72: 0 | I72: 0 | J72: 0 | K72: 0 | L72: 0 | M72: 0 | N72: 0
A73: Entry and marriage fines with tithingpenny | B73: The same render account for 5 shilling from the tithing of Bishops Sutton for tithingpenny at the hundred-court of Martinmas. | C73: 0.25 | D73: 0 | E73: 5 | F73: 0 | H73: 0 | I73: 0 | J73: 0 | K73: 0 | L73: 0 | M73: 0 | N73: 0
A74: Entry and marriage fines with tithingpenny | B74: 10 shilling from the tithing of Ropley for the same. | C74: 0.5 | D74: 0 | E74: 10 | F74: 0 | H74: 0 | I74: 0 | J74: 0 | K74: 0 | L74: 0 | M74: 0 | N74: 0
A75: Entry and marriage fines with tithingpenny | B75: 4 shilling from the tithing of Bighton for the same. | C75: 0.2 | D75: 0 | E75: 4 | F75: 0 | H75: 0 | I75: 0 | J75: 0 | K75: 0 | L75: 0 | M75: 0 | N75: 0
A76: Entry and marriage fines with tithingpenny | B76: 3 shilling from the tithing of Bramdean for the same. | C76: 0.15 | D76: 0 | E76: 3 | F76: 0 | H76: 0 | I76: 0 | J76: 0 | K76: 0 | L76: 0 | M76: 0 | N76: 0
A77: Entry and marriage fines with tithingpenny | B77: 2 shilling from the tithing of West Tisted for the same. | C77: 0.1 | D77: 0 | E77: 2 | F77: 0 | H77: 0 | I77: 0 | J77: 0 | K77: 0 | L77: 0 | M77: 0 | N77: 0
A78: Entry and marriage fines with tithingpenny | B78: 8 shilling from the tithing of Headley for the same. | C78: 0.4 | D78: 0 | E78: 8 | F78: 0 | H78: 0 | I78: 0 | J78: 0 | K78: 0 | L78: 0 | M78: 0 | N78: 0
A79: Entry and marriage fines with tithingpenny | B79: £1 12 shilling from the same for the same at the hundred-court of Hockday. | C79: 1.6 | D79: 1 | E79: 12 | F79: 0 | H79: 0 | I79: 0 | J79: 0 | K79: 0 | L79: 0 | M79: 0 | N79: 0
A80: Entry and marriage fines with tithingpenny | B80: 4 shilling from Richard Sutore for 1 plot which came into the lord's hands by the death of William le Dudeler'. | C80: 0.2 | D80: 0 | E80: 4 | F80: 0 | H80: 0 | I80: 0 | J80: 0 | K80: 0 | L80: 0 | M80: 0 | N80: 0
A81: Entry and marriage fines with tithingpenny | B81: 13 shilling 4pence from Richard de Graveschate to have the land of his father by surrender of Juliana his mother. | C81: 0.67 | D81: 0 | E81: 13 | F81: 4 | H81: 0 | I81: 0 | J81: 0 | K81: 0 | L81: 0 | M81: 0 | N81: 0
A82: Entry and marriage fines with tithingpenny | B82: 2 shilling from John Gileberd for marrying Agnes his daughter. | C82: 0.1 | D82: 0 | E82: 2 | F82: 0 | H82: 0 | I82: 0 | J82: 0 | K82: 0 | L82: 0 | M82: 0 | N82: 0
A83: Entry and marriage fines with tithingpenny | B83: £1 from Walter Parmehoud to have 1 virgate of land of his inheritance after the death of Seyld his mother. | C83: 1 | D83: 1 | E83: 0 | F83: 0 | H83: 0 | I83: 0 | J83: 0 | K83: 0 | L83: 0 | M83: 0 | N83: 0
... A95: Necessary expenses of ploughs | B95: In ironwork of 3 ploughs this year 5 shilling. | C95: 0.25 | D95: 0 | E95: 5 | F95: 0 | H95: 0 | I95: 0 | J95: 0 | K95: 0 | L95: 0 | M95: 0 | N95: 0
A96: Necessary expenses of ploughs | B96: 2 plough feet bought 9pence Nothing accounted this year for the shoeing of 2 cart-horses because the smith is bound to shoe 2 cart-horses of Bishops Sutton at his own cost, and he will have 1 acre of wheat as it lies for making the iron of the shoes and 3 trunks for charcoal this year, because there were there three ploughs, and other customs are contained on the dorse of the roll. | C96: 0.04 | D96: 0 | E96: 0 | F96: 9 | G96: wheat | H96: 0 | I96: 0 | J96: 0 | K96: 0 | L96: 0 | M96: 0 | N96: 0
A97: Necessary expenses of ploughs | B97: . | C97: 0 | D97: 0 | E97: 0 | F97: 0 | H97: 0 | I97: 0 | J97: 0 | K97: 0 | L97: 0 | M97: 0 | N97: 0
A98: Necessary expenses of ploughs | B98: 3 ploughs made anew 6pence. | C98: 0.03 | D98: 0 | E98: 0 | F98: 6 | H98: 0 | I98: 0 | J98: 0 | K98: 0 | L98: 0 | M98: 0 | N98: 0
A99: Necessary expenses of ploughs | B99: mending other ploughs 2pence. | C99: 0.01 | D99: 0 | E99: 0 | F99: 2 | H99: 0 | I99: 0 | J99: 0 | K99: 0 | L99: 0 | M99: 0 | N99: 0
A100: Necessary expenses of ploughs | B100: fitting ploughs with iron tyres 2pence. | C100: 0.01 | D100: 0 | E100: 0 | F100: 2 | H100: 0 | I100: 0 | J100: 0 | K100: 0 | L100: 0 | M100: 0 | N100: 0
A101: Necessary expenses of ploughs | B101: 3 pairs of wheels bought 6pence Richard de Manicroft' and John de Puteo ploughed 12 acres in winter and 12 acres in Lent, and they will take nothing. | C101: 0.03 | D101: 0 | E101: 0 | F101: 6 | H101: 0 | I101: 0 | J101: 0 | K101: 0 | L101: 0 | M101: 0 | N101: 0
A102: Necessary expenses of ploughs | B102: . | C102: 0 | D102: 0 | E102: 0 | F102: 0 | H102: 0 | I102: 0 | J102: 0 | K102: 0 | L102: 0 | M102: 0 | N102: 0
A103: Necessary expenses of ploughs | B103: 1 harrow made anew and others mended 3pence. | C103: 0.01 | D103: 0 | E103: 0 | F103: 3 | H103: 0 | I103: 0 | J103: 0 | K103: 0 | L103: 0 | M103: 0 | N103: 0
A104: Necessary expenses of ploughs | B104: 5 yokes made 2.5pence. | C104: 0.01 | D104: 0 | E104: 0 | F104: 2.5 | H104: 0 | I104: 0 | J104: 0 | K104: 0 | L104: 0 | M104: 0 | N104: 0
A105: Necessary expenses of ploughs | B105: 2 oxen bought £1 1 shilling 6pence. | C105: 1.07 | D105: 1 | E105: 1 | F105: 6 | H105: 0 | I105: 0 | J105: 0 | K105: 0 | L105: 0 | M105: 0 | N105: 0
A106: Necessary expenses of ploughs | B106: forage bought to support plough-horses, oxen and cows 10 shilling Total, £1 19 shilling 0.5pence | C106: 1.95 | D106: 1 | E106: 19 | F106: 0.5 | H106: 0 | I106: 0 | J106: 0 | K106: 0 | L106: 0 | M106: 0 | N106: 0
A107: Sowing and fodder | B107: In 15 quarters of oats bought for sowing and fodder £1 11 shilling 8pence, at 1 shilling 8pence a quarters for 5 quarters, and 2 shilling 4pence a quarters for 10 quarters. | C107: 1.58 | D107: 1 | E107: 11 | F107: 8 | G107: oats | H107: 15 | I107: 0 | J107: 15 | K107: 15 | L107: 0 | M107: 15 | N107: 0 | O107: 5 | P107: 0 | Q107: 10 | R107: 0 | S107: 1 | T107: 8 | U107: 2 | V107: 4
A108: Sowing and fodder | B108: Total, £1 11 shilling 8pence | C108: 1.58 | D108: 1 | E108: 11 | F108: 8 | H108: 0 | I108: 0 | J108: 0 | K108: 0 | L108: 0 | M108: 0 | N108: 0
A109: Carts | B109: In 1 pair of wheels made from the lord's timber 9pence. | C109: 0.04 | D109: 0 | E109: 0 | F109: 9 | H109: 0 | I109: 0 | J109: 0 | K109: 0 | L109: 0 | M109: 0 | N109: 0
A110: Carts | B110: clouts, nails and grease bought 1 shilling 4pence. | C110: 0.07 | D110: 0 | E110: 1 | F110: 4 | H110: 0 | I110: 0 | J110: 0 | K110: 0 | L110: 0 | M110: 0 | N110: 0
A111: Carts | B111: fitting the cart with axles 6pence. | C111: 0.03 | D111: 0 | E111: 0 | F111: 6 | H111: 0 | I111: 0 | J111: 0 | K111: 0 | L111: 0 | M111: 0 | N111: 0
A112: Carts | B112: 1 collar bought 6pence. | C112: 0.03 | D112: 0 | E112: 0 | F112: 6 | H112: 0 | I112: 0 | J112: 0 | K112: 0 | L112: 0 | M112: 0 | N112: 0
A113: Carts | B113: 1 pair of traces bought 6pence. | C113: 0.03 | D113: 0 | E113: 0 | F113: 6 | H113: 0 | I113: 0 | J113: 0 | K113: 0 | L113: 0 | M113: 0 | N113: 0
A114: Carts | B114: 1 cart-rope bought 1 shilling 1pence. | C114: 0.05 | D114: 0 | E114: 1 | F114: 1 | H114: 0 | I114: 0 | J114: 0 | K114: 0 | L114: 0 | M114: 0 | N114: 0
A115: Carts | B115: white leather bought for harnesses 10pence. | C115: 0.04 | D115: 0 | E115: 0 | F115: 10 | H115: 0 | I115: 0 | J115: 0 | K115: 0 | L115: 0 | M115: 0 | N115: 0
A116: Carts | B116: shoeing 4 plough-horses 1 shilling 4pence. | C116: 0.07 | D116: 0 | E116: 1 | F116: 4 | H116: 0 | I116: 0 | J116: 0 | K116: 0 | L116: 0 | M116: 0 | N116: 0
A117: Carts | B117: a halter bought 1pence. | C117: 0 | D117: 0 | E117: 0 | F117: 1 | H117: 0 | I117: 0 | J117: 0 | K117: 0 | L117: 0 | M117: 0 | N117: 0
A118: Carts | B118: stipend of 1 carter for the year 3 shilling. | C118: 0.15 | D118: 0 | E118: 3 | F118: 0 | H118: 0 | I118: 0 | J118: 0 | K118: 0 | L118: 0 | M118: 0 | N118: 0
A119: Carts | B119: pair of wheels made for dung 9pence Total, 10 shilling 3pence | C119: 0.54 | D119: 0 | E119: 10 | F119: 9 | H119: 0 | I119: 0 | J119: 0 | K119: 0 | L119: 0 | M119: 0 | N119: 0
... A148: Repair of buildings | B148: charcoal made 10 shilling Total, £2 9 shilling 6.5pence | C148: 2.48 | D148: 2 | E148: 9 | F148: 6.5 | H148: 0 | I148: 0 | J148: 0 | K148: 0 | L148: 0 | M148: 0 | N148: 0
A149: Harvest-time | B149: In 5 quarters of barley bought for the bread of 500 men with the officials of the curia at 3 harvest boon-works 19 shilling, and each had 1 loaf a day, of which 100 were made from a quarter. | C149: 0.95 | D149: 0 | E149: 19 | F149: 0 | G149: barley | H149: 5 | I149: 0 | J149: 5 | K149: 5 | L149: 0 | M149: 5 | N149: 0
A150: Harvest-time | B150: . | C150: 0 | D150: 0 | E150: 0 | F150: 0 | H150: 0 | I150: 0 | J150: 0 | K150: 0 | L150: 0 | M150: 0 | N150: 0
A151: Harvest-time | B151: 1,000 herrings bought to eat with the bread (companag' eorundem) 6 shilling 9pence, and each had 2 herrings a day. | C151: 0.34 | D151: 0 | E151: 6 | F151: 9 | H151: 0 | I151: 0 | J151: 0 | K151: 0 | L151: 0 | M151: 0 | N151: 0
A152: Harvest-time | B152: . | C152: 0 | D152: 0 | E152: 0 | F152: 0 | H152: 0 | I152: 0 | J152: 0 | K152: 0 | L152: 0 | M152: 0 | N152: 0
A153: Harvest-time | B153: meal bought for the pottage of the same 4pence They reaped 288 acres of wheat, barley and oats as they lie. | C153: 0.02 | D153: 0 | E153: 0 | F153: 4 | G153: barley, oats, wheat | H153: 0 | I153: 0 | J153: 0 | K153: 0 | L153: 0 | M153: 0 | N153: 0
A154: Harvest-time | B154: moreover, they are to reap 161 acres which are called gavel-acres (gavelacr') each year according to custom, and this year they reaped all the acres of wheat, barley and oats, and 22 acres are in quittance for the officials of the curia whilst they are in the lord's service. | C154: 0 | D154: 0 | E154: 0 | F154: 0 | G154: barley, oats, wheat | H154: 0 | I154: 0 | J154: 0 | K154: 0 | L154: 0 | M154: 0 | N154: 0
A155: Harvest-time | B155: . | C155: 0 | D155: 0 | E155: 0 | F155: 0 | H155: 0 | I155: 0 | J155: 0 | K155: 0 | L155: 0 | M155: 0 | N155: 0
A156: Harvest-time | B156: mending a press 2 shilling 11.5pence. | C156: 0.15 | D156: 0 | E156: 2 | F156: 11.5 | H156: 0 | I156: 0 | J156: 0 | K156: 0 | L156: 0 | M156: 0 | N156: 0
A157: Harvest-time | B157: 5 empty casks bought 10 shilling. | C157: 0.5 | D157: 0 | E157: 10 | F157: 0 | H157: 0 | I157: 0 | J157: 0 | K157: 0 | L157: 0 | M157: 0 | N157: 0
A158: Harvest-time | B158: timber bought to hoop the said casks 1 shilling 11.5pence. | C158: 0.1 | D158: 0 | E158: 1 | F158: 11.5 | H158: 0 | I158: 0 | J158: 0 | K158: 0 | L158: 0 | M158: 0 | N158: 0
A159: Harvest-time | B159: hooping the said casks 1 shilling 10pence. | C159: 0.09 | D159: 0 | E159: 1 | F159: 10 | H159: 0 | I159: 0 | J159: 0 | K159: 0 | L159: 0 | M159: 0 | N159: 0
A160: Harvest-time | B160: making cider 1 shilling 6pence Total, £2 4 shilling 4pence | C160: 2.22 | D160: 2 | E160: 4 | F160: 4 | H160: 0 | I160: 0 | J160: 0 | K160: 0 | L160: 0 | M160: 0 | N160: 0
A161: Cost of the park | B161: In stipend of 1 park-keeper for the year according to custom 6 shilling 8pence. | C161: 0.33 | D161: 0 | E161: 6 | F161: 8 | H161: 0 | I161: 0 | J161: 0 | K161: 0 | L161: 0 | M161: 0 | N161: 0
A162: Cost of the park | B162: mending the hedges in the enclosure 1 shilling 4pence Total, 8 shilling | C162: 0.07 | D162: 0 | E162: 1 | F162: 4 | H162: 0 | I162: 0 | J162: 0 | K162: 0 | L162: 0 | M162: 0 | N162: 0
A163: Cost of the meadow | B163: In a second mowing of the meadow of Bishops Sutton in parcels 2 shilling 2pence. | C163: 0.11 | D163: 0 | E163: 2 | F163: 2 | H163: 0 | I163: 0 | J163: 0 | K163: 0 | L163: 0 | M163: 0 | N163: 0
A164: Cost of the meadow | B164: spreading the said hay 3pence. | C164: 0.01 | D164: 0 | E164: 0 | F164: 3 | H164: 0 | I164: 0 | J164: 0 | K164: 0 | L164: 0 | M164: 0 | N164: 0
A165: Cost of the meadow | B165: tossing the said hay and making haycocks therefrom 10pence Total, 3 shilling 3pence | C165: 0.19 | D165: 0 | E165: 3 | F165: 10 | H165: 0 | I165: 0 | J165: 0 | K165: 0 | L165: 0 | M165: 0 | N165: 0
A166: Expenses of the steward and bailiff | B166: In expenses of Simon, clerk, for 2 tourns 10 shilling 2pence. | C166: 0.51 | D166: 0 | E166: 10 | F166: 2 | H166: 0 | I166: 0 | J166: 0 | K166: 0 | L166: 0 | M166: 0 | N166: 0
... A175: Wheat | B175: {yield: three-and-a-half-fold less 4 quarters 7 bushels} | C175: 0 | D175: 0 | E175: 0 | F175: 0 | H175: 4 | I175: 7 | J175: 4.875 | K175: 4.875 | L175: 0 | M175: 4 | N175: 7
A176: Wheat | B176: The same render account for 64 quarters 6 bushels from the whole issue of wheat from the grange in the granary without heaped measure. | C176: 0 | D176: 0 | E176: 0 | F176: 0 | G176: wheat | H176: 64 | I176: 6 | J176: 64.75 | K176: 64.75 | L176: 0 | M176: 64 | N176: 6
A177: Wheat | B177: 23 quarters 5 bushels from churchscot. | C177: 0 | D177: 0 | E177: 0 | F177: 0 | H177: 23 | I177: 5 | J177: 23.625 | K177: 23.625 | L177: 0 | M177: 23 | N177: 5
A178: Wheat | B178: Total, 88 quarters 3 bushels | C178: 0 | D178: 0 | E178: 0 | F178: 0 | H178: 88 | I178: 3 | J178: 88.375 | K178: 88.375 | L178: 0 | M178: 88 | N178: 3
A179: Wheat | B179: Sown over 43 acres in the fields of Rowele, Mol' I and la Rude, 16 quarters 1 bushels. | C179: 0 | D179: 0 | E179: 0 | F179: 0 | H179: 16 | I179: 1 | J179: 16.125 | K179: 16.125 | L179: 0 | M179: 16 | N179: 1
A180: Wheat | B180: that is, 3 bushels an acre. | C180: 0 | D180: 0 | E180: 0 | F180: 0 | H180: 0 | I180: 3 | J180: 0.375 | K180: 0.375 | L180: 0 | M180: 0 | N180: 3
A181: Wheat | B181: . | C181: 0 | D181: 0 | E181: 0 | F181: 0 | H181: 0 | I181: 0 | J181: 0 | K181: 0 | L181: 0 | M181: 0 | N181: 0
A182: Wheat | B182: provision of Simon, clerk, for 2 tourns, 4 bushels. | C182: 0 | D182: 0 | E182: 0 | F182: 0 | H182: 0 | I182: 4 | J182: 0.5 | K182: 0.5 | L182: 0 | M182: 0 | N182: 4
A183: Wheat | B183: provision of the bailiff for the year, 11 quarters 2 bushels Sold, 60.5 quarters. | C183: 0 | D183: 0 | E183: 0 | F183: 0 | H183: 60.5 | I183: 2 | J183: 60.75 | K183: 11.25 | L183: 49.5 | M183: 11 | N183: 2 | O183: 60.5 | P183: 0
A184: Curall | B184: The same render account for 1 quarters 2 bushels from the whole issue of curall from the grange in the granary without heaped measure. | C184: 0 | D184: 0 | E184: 0 | F184: 0 | G184: curall | H184: 1 | I184: 2 | J184: 1.25 | K184: 1.25 | L184: 0 | M184: 1 | N184: 2
A185: Curall | B185: Mixed with barley for the liveries of the manorial servants, 5 bushels Sold, 5 bushels | C185: 0 | D185: 0 | E185: 0 | F185: 0 | G185: barley | H185: 0 | I185: 5 | J185: 0.625 | K185: 0.625 | L185: 0 | M185: 0 | N185: 5 | O185: 0 | P185: 5
A186: Barley | B186: {yield: three-fold less 5 quarters 2 bushels} | C186: 0 | D186: 0 | E186: 0 | F186: 0 | H186: 5 | I186: 2 | J186: 5.25 | K186: 5.25 | L186: 0 | M186: 5 | N186: 2
A187: Barley | B187: The same render account for 35 quarters 2 bushels from the whole issue of barley from the grange in the granary without heaped measure. | C187: 0 | D187: 0 | E187: 0 | F187: 0 | G187: barley | H187: 35 | I187: 2 | J187: 35.25 | K187: 35.25 | L187: 0 | M187: 35 | N187: 2
A188: Barley | B188: 5 bushels of curall received for the liveries of the manorial servants. | C188: 0 | D188: 0 | E188: 0 | F188: 0 | G188: curall | H188: 0 | I188: 5 | J188: 0.625 | K188: 0.625 | L188: 0 | M188: 0 | N188: 5
A189: Barley | B189: 1 bushels of vetches received for the same. | C189: 0 | D189: 0 | E189: 0 | F189: 0 | G189: vetches | H189: 0 | I189: 1 | J189: 0.125 | K189: 0.125 | L189: 0 | M189: 0 | N189: 1
A190: Barley | B190: Total, 36 quarters. | C190: 0 | D190: 0 | E190: 0 | F190: 0 | H190: 36 | I190: 0 | J190: 36 | K190: 36 | L190: 0 | M190: 36 | N190: 0
A191: Barley | B191: Sown over 23 acres in the field of Bradewey and beside the sheepcote, 11.5 quarters. | C191: 0 | D191: 0 | E191: 0 | F191: 0 | H191: 11.5 | I191: 0 | J191: 11.5 | K191: 11.5 | L191: 0 | M191: 11.5 | N191: 0
A192: Barley | B192: that is, .5 quarters an acre. | C192: 0 | D192: 0 | E192: 0 | F192: 0 | H192: 5 | I192: 0 | J192: 5 | K192: 5 | L192: 0 | M192: 5 | N192: 0
A193: Barley | B193: Delivered to 1 carter for the year, 6.5 quarters, taking a quarter every 8 weeks. | C193: 0 | D193: 0 | E193: 0 | F193: 0 | H193: 6.5 | I193: 0 | J193: 6.5 | K193: 6.5 | L193: 0 | M193: 6.5 | N193: 0
A194: Barley | B194: Delivered to 1 man who is in place of the dairymaid and who makes the cheese and keeps the garden and does other work in the curia, 5 quarters 1.5 bushels, taking a quarter every 10 weeks. | C194: 0 | D194: 0 | E194: 0 | F194: 0 | H194: 5 | I194: 1.5 | J194: 5.1875 | K194: 5.1875 | L194: 0 | M194: 5 | N194: 1.5
A195: Barley | B195: Delivered to 1 harrower, 4 bushels. | C195: 0 | D195: 0 | E195: 0 | F195: 0 | H195: 0 | I195: 4 | J195: 0.5 | K195: 0.5 | L195: 0 | M195: 0 | N195: 4
A196: Barley | B196: provision of the bailiff's attendant, 2 quarters. | C196: 0 | D196: 0 | E196: 0 | F196: 0 | H196: 2 | I196: 0 | J196: 2 | K196: 2 | L196: 0 | M196: 2 | N196: 0
A197: Barley | B197: Delivered to 1 keeper of lambs on Fobedon' with the lambs of Wield for 23 weeks, 2 quarters 2 bushels. | C197: 0 | D197: 0 | E197: 0 | F197: 0 | H197: 2 | I197: 2 | J197: 2.25 | K197: 2.25 | L197: 0 | M197: 2 | N197: 2
A198: Barley | B198: customary payment to the swineherd this year, 6 bushels Sold, 6.5 quarters. | C198: 0 | D198: 0 | E198: 0 | F198: 0 | H198: 6.5 | I198: 6 | J198: 7.25 | K198: 0.75 | L198: 6.5 | M198: 0 | N198: 6 | O198: 6.5 | P198: 0
...
