Workbook

Sheet Bitterne Overview - Completed
A1: BITTERNE OVERVIEW - COMPLETED | B1: Total in £ | C1: Error | D1: Note
A2: CASH ACCOUNT
A3: RECEIPTS
A4: Arrears total | B4: 7.72
A5: Rents of assize total | B5: 9.18
A6: Quittances total | B6: 0.55
A7: Defaults of rent total | B7: 0.1
A8: Defaults of rent through the pestilence total
A9: Cotlands defaults total
A10: Cotlands total
A11: Total of quittances and defaults of rent total | B11: 0.65
A12: Total of rents remaining clear total
A13: Farms total
A14: Annual recognizances total | B14: 0.1
A15: Issues of the Manor total | B15: 8.32
A16: Issues of the tenements in the lord's hands total
A17: Sale of labour services total
A18: Sale of corn total | B18: 4.48
A19: Entry and marriage fines total | B19: 3.51
A20: Pleas & perquisites total
A21: Forfeited chattels total
A22: Farm of the demesne land total
A23: Total of all receipts (calculated here) | B23: =SUM(B5:B22)
A24: Total of all receipts (calculated here) incl arrears | B24: =SUM(B4:B22)
A25: Total recorded in the accounts excl. arrears | B25: 38.31 | C25: =B23-B25
A26: Total recorded in the accounts incl. arrears | B26: =B25+B4
A29: EXPENSES
A30: Cost of ploughs total | B30: 2.0033333
A31: Purchase of corn total
A32: Cost of carts and wagons total
A33: Cost of dairy total
A34: Purchase of stock total
A35: Sheepcote total
A36: Cost of buildings total | B36: 1.46375
A37: Threshing total | B37: 0.68
A38: Barley expenses
A39: Expenses of the harvest total
A40: Necessary expenses
A41: Wages of the bailiff
A42: Steward's expenses total | B42: 3.59
A43: Annual fees
A44: Total of all expenses per account | B44: 17.26
A45: Total of all expenses (calculated here) | B45: 17.35875
A46: Total fixed investment | B46: 6.0704167
A47: Total Demesne fixed investment | B47: 1.7154167
A49: Owed by the reeve | B49: =B23-B45
A50: From accounts | B50: 17.26
A52: Allowances
A53: Cash deliveries
A54: Sum of the above | B54: =SUM(B52:B53)
A55: Total of all allowances and cash deliveries in accounts
A57: Net amount owed | B57: =B50-B54
A58: Net amount owed in accounts
A60: GRANGE ACCOUNT | B60: Total Production | D60: Value of total gross production in £ | E60: Value of total net production in £
A61: Grange | B61: qrs | C61: bus
A62: Wheat | B62: 18.5 | E62: 2.625
A63: Rye | B63: 3.5
A64: Dredge | B64: 14.5
A65: Curall | B65: 8.625 | E65: 0.94791667
A66: Barley | B66: 49.375 | E66: 0
A67: Oats | B67: 24.625 | E67: 0
A68: Beans | B68: 0
A69: Peas | B69: 7.5 | E69: 0.52
A70: Vetches | E70: 0
A71: Total value of gross production (sum of the above)
A72: Total value of net production
A73: Value of sales
A75: MILL ACCOUNT | B75: Total Production | D75: Total in £
A76: Issues of the mill | B76: qrs | C76: bus
A77: Wheat
A78: Oatmeal
A79: 1st grade malt
A80: 2nd grade malt
A81: Maslin
A82: Total value of production (sum of the above)
A83: Value of sales
A85: STOCK ACCOUNT
A86: Livestock | B86: Begin stock | C86: End stock | D86: Stockbuilding | F86: Value of stock in £ | G86: Value of stockbuilding
A87: Cart-horses | B87: 5 | C87: 2 | D87: -3 | F87: 0.75 | G87: -1.125
A88: Mares | B88: 3 | C88: 2 | D88: -1 | F88: 0.8 | G88: -0.4
A89: Plough horses | B89: 1 | C89: 0 | D89: -1 | F89: ='Stock'!K8*'Stock'!O8 | G89: =D89*'Stock'!O8
A90: Colts (2 years) | D90: =C90-B90 | F90: ='Stock'!K10*'Stock'!O10 | G90: =D90*'Stock'!O10
A91: Colts (2 years) | D91: =C91-B91 | F91: ='Stock'!K10*'Stock'!O10 | G91: =D91*'Stock'!O10
A92: Colts (1 year) | B92: 1 | C92: 1 | D92: 0 | F92: ='Stock'!K11*'Stock'!O11 | G92: =D92*'Stock'!O11
A93: Foals | B93: 1 | C93: 3 | D93: 2 | F93: ='Stock'!K12*'Stock'!O12 | G93: =D93*'Stock'!O12
A94: Oxen | B94: 22 | C94: 22 | D94: 0 | F94: ='Stock'!K13*'Stock'!O13 | G94: =D94*'Stock'!O13
A95: Bulls | B95: 1 | C95: 1 | D95: 0 | F95: ='Stock'!K14*'Stock'!O14 | G95: =D95*'Stock'!O14
A96: Cows | B96: 10 | C96: 18 | D96: 8 | F96: ='Stock'!K15*'Stock'!O15 | G96: =D96*'Stock'!O15
A97: Steers | B97: 1 | C97: 0 | D97: -1 | F97: ='Stock'!K16*'Stock'!O16 | G97: =D97*'Stock'!O16
A98: Bullocks | B98: 5 | C98: 5 | D98: 0 | F98: ='Stock'!K17*'Stock'!O17 | G98: =D98*'Stock'!O17
A99: Yearlings | B99: 5 | C99: 3 | D99: -2 | F99: ='Stock'!K18*'Stock'!O18 | G99: =D99*'Stock'!O18
A100: Calves | C100: 7 | D100: =C100-B100 | F100: 0.35 | G100: =D100*'Stock'!O19
A101: Wethers | B101: 277 | C101: 240 | D101: -37 | F101: 12 | G101: -1.85
A102: Rams | D102: =C102-B102 | F102: ='Stock'!K21*'Stock'!O21 | G102: =D102*'Stock'!O21
A103: Ewes | D103: =C103-B103 | F103: ='Stock'!K22*'Stock'!O22 | G103: =D103*'Stock'!O22
A104: Hoggs | D104: =C104-B104 | F104: ='Stock'!K23*'Stock'!O23 | G104: =D104*'Stock'!O23
A105: Lambs | D105: =C105-B105 | F105: ='Stock'!K24*'Stock'!O24 | G105: =D105*'Stock'!O24
A106: Boars | D106: =C106-B106 | F106: ='Stock'!K25*'Stock'!O25 | G106: =D106*'Stock'!O25
A107: Sows | B107: 1 | C107: 1 | D107: 0 | F107: ='Stock'!K26*'Stock'!O26 | G107: =D107*'Stock'!O26
A108: Pigs | B108: 6 | C108: 2 | D108: -4 | F108: 0.275 | G108: -0.55
...

Sheet Prices
A1: Meat & Dairy Prices
C2: 1301 | D2: 1302 | E2: Average
A3: Beef | B3: £ per lb | C3: 0.0033351854 | D3: 0.0032608538 | E3: =AVERAGE(C3:D3)
A4: Mutton | B4: £ per lb | C4: 0.0036593977 | D4: 0.0037125513 | E4: =AVERAGE(C4:D4)
A5: Pork | B5: £ per lb | C5: 0.0038431326 | D5: 0.0037574803 | E5: =AVERAGE(C5:D5)
A6: Cheese | B6: £ per lb | C6: 0.0055768754 | D6: 0.0056654898 | E6: =AVERAGE(C6:D6)
A7: Butter | B7: £ per lb | C7: 0.0036626221 | D7: 0.0035935077 | E7: =AVERAGE(C7:D7)
A8: Milk | B8: £ per gallon | C8: 0.0055768754 | D8: 0.0056654898 | E8: =AVERAGE(C8:D8)

Sheet Labour Rents

Sheet Overview
A1: BITTERNE | B1: Total in £ | C1: Error | D1: Note
A2: CASH ACCOUNT
A3: RECEIPTS
A4: Arrears total
A5: Rents of assize total
A6: Quittances total
A7: Defaults of rent total
A8: Defaults of rent through the pestilence total
A9: Cotlands defaults total
A10: Cotlands total
A11: Total of quittances and defaults of rent total
A12: Total of rents remaining clear total
A13: Farms total
... A22: Farm of the demesne land total
A23: Total of all receipts (calculated here) | B23: =Receipts!F120
A24: Total of all receipts (calculated here) incl arrears | B24: =Receipts!F121
A25: Total recorded in the accounts excl. arrears | B25: =Receipts!F119 | C25: =B25-B23
A26: Total recorded in the accounts incl. arrears
A29: EXPENSES
A30: Cost of ploughs total
A31: Purchase of corn total
A32: Cost of carts and wagons total
A33: Cost of dairy total
A34: Purchase of stock total
A35: Sheepcote total
A36: Cost of buildings total
A37: Threshing total
A38: Barley expenses
A39: Expenses of the harvest total
... A43: Annual fees
A44: Total of all expenses per account | B44: =Expenses!F135
A45: Total of all expenses (calculated here) | B45: =Expenses!F136
A46: Total fixed investment | B46: =Expenses!F137
A47: Total Demesne fixed investment | B47: =Expenses!F138
A49: Owed by the reeve
A50: From accounts
A52: Allowances
A53: Cash deliveries
A54: Sum of the above
A55: Total of all allowances and cash deliveries in accounts
A57: Net amount owed
A58: Net amount owed in accounts
A60: GRANGE ACCOUNT | B60: Total Production
A61: Grange | B61: qrs | E61: Value of total gross production in £ | F61: Value of total net production in £
A62: wheat | B62: ='Issues of the Grange'!B2 | E62: ='Issues of the Grange'!I2 | F62: ='Issues of the Grange'!O18
A63: curall | B63: ='Issues of the Grange'!B3 | E63: ='Issues of the Grange'!I3 | F63: ='Issues of the Grange'!O19
A64: rye | B64: ='Issues of the Grange'!B4 | E64: ='Issues of the Grange'!I4 | F64: ='Issues of the Grange'!O20
A65: barley | B65: ='Issues of the Grange'!B5 | E65: ='Issues of the Grange'!I5 | F65: ='Issues of the Grange'!O21
A66: dredge | B66: ='Issues of the Grange'!B6 | E66: ='Issues of the Grange'!I6 | F66: ='Issues of the Grange'!O22
A67: oats | B67: ='Issues of the Grange'!B7 | E67: ='Issues of the Grange'!I7 | F67: ='Issues of the Grange'!O23
A68: beans | B68: ='Issues of the Grange'!B8 | E68: ='Issues of the Grange'!I8 | F68: ='Issues of the Grange'!O24
A69: peas | B69: ='Issues of the Grange'!B9 | E69: ='Issues of the Grange'!I9 | F69: ='Issues of the Grange'!O25
A70: vetches | B70: ='Issues of the Grange'!B10 | E70: ='Issues of the Grange'!I10 | F70: ='Issues of the Grange'!O26
A71: Total value of gross production (sum of the above) | E71: =SUM(E62:E70)
A72: Total value of net production | E72: =SUM(F62:F70)
A73: Value of sales | E73: =Receipts!F87+Receipts!F95
A75: MILL ACCOUNT
A76: Issues of the mill
A77: Wheat
A78: Oatmeal
A79: 1st grade malt
A80: 2nd grade malt
A81: Maslin
A82: Total value of production (sum of the above)
A83: Value of sales
A85: STOCK ACCOUNT
A86: Livestock | B86: Sales value in £
A87: Cart-horses | B87: =Stock!R6
A88: Mares | B88: =Stock!R7
A89: Plough horses | B89: =Stock!R8
A90: Colts (2 years) | B90: =Stock!R9
A91: Colts (2 years) | B91: =Stock!R10
A92: Colts (1 year) | B92: =Stock!R11
A93: Foals | B93: =Stock!R12
A94: Oxen | B94: =Stock!R13
A95: Bulls | B95: =Stock!R14
A96: Cows | B96: =Stock!R15
A97: Steers | B97: =Stock!R16
A98: Bullocks | B98: =Stock!R17
... A112: Peacocks | B112: =Stock!R31
A113: Total value of stock (sum of the above)
A114: Total value of production
A115: Value of sales | B115: =Stock!R32
A117: Wool | B117: Value of production at sales prices £
A118: Coarse wool | B118: =Stock!T36
A119: Lamb's wool | B119: =Stock!T37
A120: Wool locks | B120: =Stock!T38
A121: Wool sold at shearing | B121: =Stock!T39
A122: Total value of production (sum of the above) | B122: =SUM(B118:B121)
A123: Value of sales | B123: =Stock!R38
A125: Hides | B125: Value of production at sales prices £
A126: Ox hides | B126: =Stock!T44
A127: Cow hides | B127: =Stock!T45
A128: Mare hides | B128: =Stock!T46
A129: Steer hides | B129: =Stock!T47
A130: Yearling Calf hides | B130: =Stock!T48
A131: Calf hides | B131: =Stock!T49
A132: Pig hides | B132: =Stock!T50
A133: Wether woolskins | B133: =Stock!T51
A134: Ram woolskins | B134: =Stock!T52
...

Sheet Receipts
A1: BITTERNE RECEIPTS
A2: Heading | B2: Pounds | C2: Shillings | D2: Pence | F2: Total in Pounds | G2: Error | H2: Sentence
A3: Arrears | B3: 7 | C3: 14 | D3: 4.5 | F3: 7.72 | H3: William de Worsted', sergeant, and Walter le Parker, reeve, render account for £7 14 shilling 4.5pence of arrears from the previous year.
A4: Arrears | B4: 0 | C4: 0 | D4: 0 | F4: 0 | H4: All delivered to Sir Geoffrey, treasurer of Wolvesey.
A5: Arrears | F5: 7.72 | G5: =F5-F3 | H5: Total
A7: Rents of assize | B7: 2 | C7: 0 | D7: 3 | F7: 2.01 | H7: The same render account for £2 3pence for all rents of assize at Christmas.
A8: Rents of assize | B8: 2 | C8: 0 | D8: 3 | F8: 2.01 | H8: £2 3pence at Easter (22 April).
A9: Rents of assize | B9: 2 | C9: 0 | D9: 3 | F9: 2.01 | H9: £2 3pence at the Nativity of St John the Baptist (24 June).
A10: Rents of assize | B10: 3 | C10: 2 | D10: 11.5 | F10: 3.15 | H10: £3 2 shilling 11.5pence at Michaelmas (29 September).
A11: Rents of assize | B11: 9 | C11: 3 | D11: 8.5 | F11: 9.19 | H11: Total, £9 3 shilling 8.5pence
A12: Rents of assize | F12: 9.18 | G12: -0.01 | H12: Total
A14: Quittances | B14: 0 | C14: 4 | D14: 0 | F14: 0.2 | H14: In quittance of 1 reeve for the year 4 shilling.
A15: Quittances | B15: 0 | C15: 3 | D15: 0 | F15: 0.15 | H15: 2 ploughmen for the year 3 shilling.
A16: Quittances | B16: 0 | C16: 4 | D16: 0 | F16: 0.2 | H16: 1 park-keeper for the year 4 shilling
A17: Quittances | B17: 0 | C17: 11 | D17: 0 | F17: 0.55 | H17: Total, 11 shilling
A18: Quittances | F18: 0.55 | G18: 0 | H18: Total
A20: Defaults of rent | B20: 0 | C20: 2 | D20: 1 | F20: 0.1 | H20: In default of the land of Vyel drawn into demesne, 2 shilling 1pence for the year.
A21: Defaults of rent | B21: 0 | C21: 2 | D21: 1 | F21: 0.1 | H21: Total, 2 shilling 1pence
A22: Defaults of rent | F22: 0.1 | G22: 0 | H22: Total
A24: Total of quittances and defaults of rent | B24: 0 | C24: 13 | D24: 1 | F24: 0.65 | H24: Total of quittances and defaults of rent, 13 shilling 1pence
A25: Total of quittances and defaults of rent | F25: 0.65 | G25: =F25-F24 | H25: Total
A27: Total of rents remaining | B27: 8 | C27: 10 | D27: 7.5 | F27: 8.53 | H27: Total of rents remaining, £8 10 shilling 7.5pence
A28: Total of rents remaining | F28: 8.53 | G28: =F28-F27 | H28: Total
A30: Annual recognizance | B30: 0 | C30: 0 | D30: 6 | F30: 0.03 | H30: The same render account for 6pence from Roger le Saltere for annual recognizance.
A31: Annual recognizance | B31: 0 | C31: 0 | D31: 3 | F31: 0.01 | H31: 3pence from Richard Seuar' for the same.
A32: Annual recognizance | B32: 0 | C32: 0 | D32: 6 | F32: 0.03 | H32: 6pence from William Austyn for the same.
A33: Annual recognizance | B33: 0 | C33: 0 | D33: 6 | F33: 0.03 | H33: 6pence from Robert Clericus of Fawley for the same.
A34: Annual recognizance | B34: 0 | C34: 1 | D34: 9 | F34: 0.09 | H34: Total, 1 shilling 9pence
A35: Annual recognizance | F35: 0.1 | G35: 0.01 | H35: Total
A37: Issues of the manor | B37: 0 | C37: 10 | D37: 0 | F37: 0.5 | H37: The same render account for 10 shilling from pannage of pigs this year.
A38: Issues of the manor | B38: 0 | C38: 9 | D38: 4 | F38: 0.47 | H38: 9 shilling 4pence from the agistment of pigs in the park.
A39: Issues of the manor | B39: 0 | C39: 17 | D39: 6 | F39: 0.88 | H39: 17 shilling 6pence from the agistment of livestock in the park in summer.
A40: Issues of the manor | B40: 0 | C40: 0 | D40: 0 | F40: 0 | H40: nothing from winter pasturage on account of the lord's stock.
A41: Issues of the manor | B41: 0 | C41: 1 | D41: 0 | F41: 0.05 | H41: 1 shilling from the pasturage in Prestemed' sold after mowing.
A42: Issues of the manor | B42: 0 | C42: 0 | D42: 0 | F42: 0 | H42: nothing from winter pasturage for, the lord's stock.
A43: Issues of the manor | B43: 0 | C43: 0 | D43: 0 | F43: 0 | H43: nothing from the pasturage on the land of Bathard and in Pistok this year because it was sown.
A44: Issues of the manor | B44: 0 | C44: 0 | D44: 6 | F44: 0.03 | H44: 6pence from the pasturage in various places sold this year.
A45: Issues of the manor | B45: 0 | C45: 15 | D45: 0 | F45: 0.75 | H45: 15 shilling from 2 cart-horses sold, at 3 shilling for 1 because feeble, and 12 shilling for 1.
A46: Issues of the manor | B46: 0 | C46: 8 | D46: 0 | F46: 0.4 | H46: 8 shilling from 1 old mare sold.
A47: Issues of the manor | B47: 0 | C47: 6 | D47: 0 | F47: 0.3 | H47: 6 shilling from 6 late-born calves sold, at 1 shilling each.
A48: Issues of the manor | B48: 0 | C48: 17 | D48: 0 | F48: 0.85 | H48: 17 shilling from 17 wethers sold at Martinmas (11 November), at 1 shilling each.
A49: Issues of the manor | B49: 0 | C49: 11 | D49: 0 | F49: =B49+C49/20+D49/240 | H49: 11 shilling from 4 pigs sold, at 2 shilling 9pence each.
A50: Issues of the manor | B50: 0 | C50: 12 | D50: 11 | F50: 0.65 | H50: 12 shilling 11pence from 151 hens from churchscot sold.
A51: Issues of the manor | B51: 0 | C51: 0 | D51: 0 | F51: 0 | H51: nothing from nuts collected in the park this year.
A52: Issues of the manor | B52: 0 | C52: 0 | D52: 0 | F52: 0 | H52: nothing from rushes in the park this year.
A53: Issues of the manor | B53: 0 | C53: 2 | D53: 0 | F53: 0.1 | H53: 2 shilling from heath sold this year.
A54: Issues of the manor | B54: 0 | C54: 3 | D54: 1.5 | F54: 0.16 | H54: 3 shilling 1.5pence from rowen cheese sold.
A55: Issues of the manor | B55: 1 | C55: 14 | D55: 0 | F55: 1.7 | H55: £1 14 shilling from 4 weys 7 cloves of summer cheese sold, at 8 shilling a wey.
A56: Issues of the manor | B56: 0 | C56: 2 | D56: 3 | F56: 0.11 | H56: 2 shilling 3pence from 6 cloves of butter sold, at 4.5pence a clove.
A57: Issues of the manor | B57: 0 | C57: 5 | D57: 0 | F57: 0.25 | H57: 5 shilling from hay sold this year.
A58: Issues of the manor | B58: 0 | C58: 0 | D58: 0 | F58: 0 | H58: nothing from heath in the quagmire (quabbemer') this year because none was obtained to sell.
A59: Issues of the manor | B59: 0 | C59: 0 | D59: 0 | F59: 0 | H59: nothing from underwood in the park this year for the same reason.
A60: Issues of the manor | B60: 0 | C60: 0 | D60: 10 | F60: 0.04 | H60: 10pence from the hide sold of 1 cart-horse in murrain.
A61: Issues of the manor | B61: 0 | C61: 0 | D61: 8 | F61: 0.03 | H61: 8pence from the hide sold of 1 plough-horse in murrain.
... A73: Issues of the manor | B73: 8 | C73: 7 | D73: 3 | F73: 8.36 | H73: Total, £8 7 shilling 3pence
A74: Issues of the manor | F74: =SUM(F37:F72) | G74: =F74-F73 | H74: Total
A76: Fishery | B76: 7 | C76: 4 | D76: 0 | F76: 7.2 | H76: The same render account for £7 4 shilling from 53 salmon sold, at 4 shilling each for 19, and 2 shilling each for 34.
A77: Fishery | F77: 7.2 | H77: Total, £7 4 shilling
A78: Fishery | F78: 7.2 | G78: 0 | H78: Total
A80: Sale of corn | B80: 2 | C80: 12 | D80: 6 | F80: 2.62 | H80: The same render account for £2 12 shilling 6pence from 8 quarters 6 bushels of wheat sold, at 6 shilling a qr.
A81: Sale of corn | B81: 0 | C81: 5 | D81: 5 | F81: 0.27 | H81: 5 shilling 5pence from 1 qr 2 bushels of curall sold, at 4 shilling 4pence a qr.
A82: Sale of corn | B82: 1 | C82: 6 | D82: 5 | F82: 1.32 | H82: £1 6 shilling 5pence from 11 quarters 3 bushels of dredge sold, at 2 shilling a qr for 3 quarters 7 bushels, 2 shilling 4pence a qr for 4 quarters, and 2 shilling 8pence a qr for 3.5 quarters.
A83: Sale of corn | B83: 0 | C83: 1 | D83: 0 | F83: 0.05 | H83: 1 shilling from .5 qr of dredge sold at the audit.
A84: Sale of corn | B84: 0 | C84: 2 | D84: 6 | F84: 0.12 | H84: 2 shilling from 4 bushels of peas sold, at 6pence a bushels.
A85: Sale of corn | B85: 0 | C85: 2 | D85: 0 | F85: 0.1 | H85: 2 shilling from 6 bushels of peas sold at the audit.
A86: Sale of corn | B86: 4 | C86: 9 | D86: 4 | F86: 4.47 | H86: Total, £4 9 shilling 4pence
A87: Sale of corn | F87: 4.48 | G87: 0.01 | H87: Total
A89: Sale of the mill's corn | B89: 0 | C89: 10 | D89: 3 | F89: 0.51 | H89: The same render account for 10 shilling 3pence from 1 qr 7 bushels of wheat sold, at 7.5pence a bushels for 2 bushels, 5 shilling 4pence a qr for 1 qr 1 bushels, and 9pence a bushels for 4 bushels.
A90: Sale of the mill's corn | B90: 1 | C90: 15 | D90: 10 | F90: 1.79 | H90: £1 15 shilling 10pence from 11 quarters 6 bushels of barley sold, at 2 shilling 8pence a qr for 3 quarters, 3 shilling a qr for 4 quarters, and 3 shilling 4pence a qr for 4 quarters 6 bushels.
A91: Sale of the mill's corn | B91: 0 | C91: 11 | D91: 4 | F91: =B91+C91/20+D91/240 | H91: 11 shilling from 2 quarters 1 bushels of coarse-ground corn sold, at 5 shilling for 1 qr, and 5 shilling 4pence a qr for 1 qr 1 bushels.
A92: Sale of the mill's corn | B92: 0 | C92: 10 | D92: 9 | F92: =B92+C92/20+D92/240 | H92: 10 shilling 9pence from 4 quarters 7 bushels of malt sold, at 2 shilling a qr for 1 qr 7 bushels, and 2 shilling 4pence a qr for 3 quarters.
A93: Sale of the mill's corn | B93: 0 | C93: 0 | D93: 8 | F93: =B93+C93/20+D93/240 | H93: 8pence from 1 bushels of oatmeal sold
A94: Sale of the mill's corn | B94: 3 | C94: 8 | D94: 6 | F94: 3.42 | H94: Total, £3 8 shilling 6pence
A95: Sale of the mill's corn | F95: =SUM(F89:F93) | G95: =F95-F94 | H95: Total
A97: Entry and marriage fines | B97: 0 | C97: 6 | D97: 8 | F97: 0.33 | H97: The same render account for 6 shilling 8pence from the tithing of Bitterne at the hundred-court of Martinmas for tithingpenny.
A98: Entry and marriage fines | B98: 0 | C98: 6 | D98: 8 | F98: 0.33 | H98: 6 shilling 8pence from the tithing of Fawley at the said hundred-court for the same.
A99: Entry and marriage fines | B99: 0 | C99: 13 | D99: 4 | F99: 0.67 | H99: 13 shilling 4pence from the same at the hundred-court of Hockday for the same.
A100: Entry and marriage fines | B100: 0 | C100: 1 | D100: 0 | F100: 0.05 | H100: 1 shilling from John le Careter for marrying Joan his stepdaughter outside.
A101: Entry and marriage fines | B101: 0 | C101: 3 | D101: 0 | F101: 0.15 | H101: 3 shilling from .Havvise, daughter of Austin Mich', to have 1 house and 2 acres of land which belonged to Edith her mother.
A102: Entry and marriage fines | B102: 0 | C102: 6 | D102: 8 | F102: 0.33 | H102: 6 shilling 8pence from Matilda, daughter of Mabel Ace, to have 1 messuage and 1 ferling of land by surrender of Mabel her mother, so that the said Mabel be supported by holding the same land equally with her.
A103: Entry and marriage fines | B103: 0 | C103: 6 | D103: 8 | F103: 0.33 | H103: 6 shilling 8pence from Nicholas le Pyn to have the said Matilda with her land.
A104: Entry and marriage fines | B104: 0 | C104: 6 | D104: 8 | F104: 0.33 | H104: 6 shilling 8pence from Walter le Schepphurd' to have the land which belonged to his mother.
A105: Entry and marriage fines | B105: 0 | C105: 13 | D105: 4 | F105: 0.67 | H105: 13 shilling 4pence from Roger ate Clive to have the land which belonged to Gunilda Gardenir.
A106: Entry and marriage fines | B106: 0 | C106: 3 | D106: 4 | F106: 0.17 | H106: 3 shilling 4pence from Roger Westsyd' to have 1 house and 1 curtilage by surrender of Walter le Schiphurd', and he will relieve the said Walter of 6pence annual rent.
A107: Entry and marriage fines | B107: 0 | C107: 1 | D107: 0 | F107: 0.05 | H107: 1 shilling from Joan Alayn for marrying herself.
A108: Entry and marriage fines | B108: 0 | C108: 1 | D108: 0 | F108: 0.05 | H108: 1 shilling from Margery, daughter of Walter le Schiphurd', for marrying herself.
... A110: Entry and marriage fines | B110: 3 | C110: 10 | D110: 4 | F110: 3.52 | H110: Total, £3 10 shilling 4pence
A111: Entry and marriage fines | F111: 3.51 | G111: -0.01 | H111: Total
A113: Perquisites | B113: 0 | C113: 2 | D113: 0 | F113: 0.1 | H113: The same render account for 2 shilling from the tithing of Fawley because it did not present the default of John Baron at the tourn of Martinmas.
A114: Perquisites | B114: 0 | C114: 2 | D114: 0 | F114: 0.1 | H114: 2 shilling from the same tithing because it did not produce in court the individual whom it had bailed.
A115: Perquisites | B115: 2 | C115: 10 | D115: 4 | F115: 2.52 | H115: £2 10 shilling 4pence from small amercements from various men for various transgressions.
A116: Perquisites | B116: 2 | C116: 14 | D116: 4 | F116: 2.72 | H116: Total, £2 14 shilling 4pence
A117: Perquisites | F117: 2.72 | G117: 0 | H117: Total
A119: Total of all receipts recorded in accounts | B119: 38 | C119: 6 | D119: 1.5 | F119: 38.31 | H119: Total of all receipts, £38 6 shilling 1.5pence
A120: Total cross-check without arrears | F120: =F117+F111+F95+F87+F78+F74+F35+F28 | G120: =F120-F119
A121: Total cross-check with arrears | F121: =F120+F5

Sheet Expenses
A1: BITTERNE EXPENSES
A2: Heading | B2: £ | C2: s | D2: d | F2: Total in £ | G2: Error | H2: Notes | J2: Fixed investment | K2: Demesne fixed investment
A3: Cost of ploughs | B3: 0 | C3: 3 | D3: 1 | F3: 0.15 | H3: In iron and steel bought for 2 ploughs for the year 3 shilling 1pence. | J3: =F3 | K3: =J3
A4: Cost of ploughs | B4: 0 | C4: 0 | D4: 5 | F4: 0.02 | H4: 1 plough foot bought 5pence. | J4: =F4 | K4: =J4
A5: Cost of ploughs | B5: 0 | C5: 0 | D5: 4.5 | F5: 0.02 | H5: 3 wheels bought for ploughs 4.5pence. | J5: =F5 | K5: =J5
A6: Cost of ploughs | B6: 0 | C6: 0 | D6: 9.5 | F6: 0.04 | H6: making a new plough and mending others and harrows 9.5pence. | J6: =F6 | K6: =J6
A7: Cost of ploughs | B7: 0 | C7: 0 | D7: 9 | F7: 0.04 | H7: 1 ploughshare bought 9pence. | J7: =F7 | K7: =J7
A8: Cost of ploughs | B8: 0 | C8: 2 | D8: 4 | F8: 0.12 | H8: stipend of the smith making the ironwork of the ploughs 2 shilling 4pence. | J8: =F8 | K8: =J8/2 | L8: halfed to account for stipend part
A9: Cost of ploughs | B9: 0 | C9: 0 | D9: 3 | F9: 0.01 | H9: fitting the wain with axles 3pence. | J9: =F9 | K9: =J9
A10: Cost of ploughs | B10: 0 | C10: 1 | D10: 5.5 | F10: 0.07 | H10: clouts, nails and grease bought for the same 1 shilling 5.5pence, and so much because it went to the marling for the whole summer. | J10: =F10 | K10: =J10
A11: Cost of ploughs | B11: 0 | C11: 0 | D11: 1.5 | F11: 0.01 | H11: cleaning iron tyres 1.5pence. | J11: =F11 | K11: =J11
A12: Cost of ploughs | B12: 0 | C12: 0 | D12: 5 | F12: 0.02 | H12: 1 rope, 6 halters and 1 pair of traces made from their own canvas 5pence. | J12: =F12 | K12: =J12
A13: Cost of ploughs | B13: 0 | C13: 10 | D13: 0 | F13: 0.5 | H13: 1 ox bought 10 shilling.
A14: Cost of ploughs | B14: 0 | C14: 6 | D14: 0 | F14: 0.3 | H14: stipend of 2 ploughmen for the year 6 shilling.
A15: Cost of ploughs | B15: 0 | C15: 1 | D15: 4 | F15: 0.07 | H15: 4 bushels of beans bought for sowing 1 shilling 4pence.
A16: Cost of ploughs | B16: 0 | C16: 12 | D16: 8 | F16: =B16+C16/20+D16/240 | H16: forage bought for supporting oxen 12 shilling 8pence
A17: Cost of ploughs | B17: 2 | C17: 0 | D17: 0 | F17: 2 | H17: Total, £2.
A18: Cost of ploughs | F18: =SUM(F3:F16) | G18: =F18-F17 | H18: Total
A20: Cost of carts | B20: 0 | C20: 0 | D20: 5.5 | F20: 0.02 | H20: In fitting the cart with axles at various times with axles bought for the same 5.5pence. | J20: =F20 | K20: =J20
A21: Cost of carts | B21: 0 | C21: 0 | D21: 6.5 | F21: 0.03 | H21: clouts, nails, grease bought for the same 6.5pence. | J21: =F21 | K21: =J21
A22: Cost of carts | B22: 0 | C22: 0 | D22: 8 | F22: 0.03 | H22: 1 collar bought 8pence. | J22: =F22 | K22: =J22
A23: Cost of carts | B23: 0 | C23: 0 | D23: 6 | F23: 0.03 | H23: white leather bought for mending harnesses 6pence. | J23: =F23 | K23: =J23
A24: Cost of carts | B24: 0 | C24: 0 | D24: 7 | F24: 0.03 | H24: a broad-axe bought for mending the cart 7pence. | J24: =F24 | K24: =J24
A25: Cost of carts | B25: 0 | C25: 0 | D25: 3 | F25: 0.01 | H25: hooping the hubs of wheels with bands of wood 3pence. | J25: =F25 | K25: =J25
A26: Cost of carts | B26: 0 | C26: 2 | D26: 6 | F26: 0.12 | H26: shoeing 2 cart-horses for the year 2 shilling 6pence. | J26: =F26 | K26: =J26
A27: Cost of carts | B27: 0 | C27: 0 | D27: 8 | F27: 0.03 | H27: shoeing 2 plough-horses going to harrow at both sowings 8pence. | J27: =F27 | K27: =J27
A28: Cost of carts | B28: 0 | C28: 3 | D28: 0 | F28: 0.15 | H28: stipend of 1 carter for the year 3 shilling.
A29: Cost of carts | B29: 0 | C29: 8 | D29: 8 | F29: 0.43 | H29: 4 quarters 2 bushels of oats bought for the fodder of horses 8 shilling 8pence
A30: Cost of carts | B30: 0 | C30: 17 | D30: 8 | F30: =B30+C30/20+D30/240 | H30: Total, 17 shilling 8pence
A31: Cost of carts | F31: 0.88 | G31: =F31-F30 | H31: Total
A33: Cost of the dairy | B33: 0 | C33: 0 | D33: 5 | F33: 0.02 | H33: In woollen and linen cloth bought for the dairy 5pence. | J33: =F33 | K33: =J33
A34: Cost of the dairy | B34: 0 | C34: 1 | D34: 5 | F34: 0.07 | H34: 5 bushels of salt bought 1 shilling .5pence. | J34: =F34 | K34: =J34
A35: Cost of the dairy | B35: 0 | C35: 0 | D35: 2 | F35: 0.01 | H35: earthenware pots and pans bought for the same 2pence. | J35: =F35 | K35: =J35
A36: Cost of the dairy | B36: 0 | C36: 0 | D36: 5 | F36: 0.02 | H36: 1 new bucket bought and another mended 5pence. | J36: =F36 | K36: =J36
A37: Cost of the dairy | B37: 0 | C37: 0 | D37: 3 | F37: 0.01 | H37: a press bought for the same 3pence. | J37: =F37 | K37: =J37
A38: Cost of the dairy | B38: 0 | C38: 1 | D38: 7.5 | F38: 0.08 | H38: 6 ells of canvas bought for putting the wool in 1 shilling7.5pence, at 3.25pence an ell. | J38: =F38 | K38: =J38
A39: Cost of the dairy | B39: 0 | C39: 0 | D39: 2 | F39: 0.01 | H39: packing the wool 2pence. | J39: =F39 | K39: =J39
A40: Cost of the dairy | B40: 0 | C40: 3 | D40: 0 | F40: 0.15 | H40: grease bought for greasing sheep 3 shilling. | J40: =F40 | K40: =J40
A41: Cost of the dairy | B41: 0 | C41: 0 | D41: 4 | F41: 0.02 | H41: 1 mould bought for making cheese 4pence. | J41: =F41 | K41: =J41
A42: Cost of the dairy | B42: 0 | C42: 1 | D42: 6 | F42: 0.08 | H42: stipend of 1 dairymaid for the year 1 shilling 6pence.
A43: Cost of the dairy | B43: 0 | C43: 3 | D43: 0 | F43: 0.15 | H43: stipend of 1 shepherd for the year 3 shilling.
A44: Cost of the dairy | B44: 2 | C44: 19 | D44: 1 | F44: 2.95 | H44: 7 cows bought for the lord's stock £2 19 shilling 1pence, at 7 shilling 9.5pence each for 2, 8 shilling 6pence each for 3, and 9 shilling each for 2..
A45: Cost of the dairy | B45: 0 | C45: 1 | D45: 6 | F45: =B45+C45/20+D45/240 | H45: 1 wether bought before shearing 1 shilling 6pence
A46: Cost of the dairy | B46: 3 | C46: 12 | D46: 6 | F46: 3.62 | H46: Total, £3 12 shilling 6pence
A47: Cost of the dairy | F47: =SUM(F33:F45) | G47: =F47-F46 | H47: Total
A49: Threshing | B49: 0 | C49: 5 | D49: 2.5 | F49: 0.26 | H49: In threshing 30 quarters of wheat, curall and rye by piece-work 5 shilling, at 2.5pence per 10 struck bushe1 shilling.
A50: Threshing | B50: 0 | C50: 6 | D50: 0 | F50: 0.3 | H50: threshing 64 quarters 1 bushels of barley, dredge, peas and vetches by piece-work 6 shilling per 10 struck bushe1 shilling.
A51: Threshing | B51: 0 | C51: 1 | D51: 0 | F51: 0.05 | H51: threshing 20 quarters 3 bushels of oats by piece-workper 20 struck bushe1 shilling.
A52: Threshing | B52: 0 | C52: 1 | D52: 4.5 | F52: 0.07 | H52: winnowing all the corn beyond that 4.5pence, at 1.5pence 1 shilling, at 1.5pence winnowed by the dairymaid 9pence
A53: Threshing | B53: 0 | C53: 13 | D53: 1.5 | F53: =B53+C53/20+D53/240 | H53: Total, 13 shilling 1.5pence
A54: Threshing | F54: 0.68 | G54: =F54-F53 | H54: Total
A56: Cost of buildings | B56: 0 | C56: 6 | D56: 11 | F56: 0.35 | H56: in 6 lb of tin and 2 fotmals of lead bought for mending the lord's tower and various gutters in the curia 6 shilling 11pence. | J56: =F56
A57: Cost of buildings | B57: 0 | C57: 1 | D57: 6 | F57: 0.08 | H57: 1 plumber with 1 mate cutting the said tin and lead and mending the tower and various gutters in the curia for 3 days 1 shilling 6pence, at 6pence a day.'. | J57: =F57
A58: Cost of buildings | B58: 0 | C58: 0 | D58: 2 | F58: 0.01 | H58: nails for the same 2pence. | J58: =F58
A59: Cost of buildings | B59: 0 | C59: 13 | D59: 6 | F59: 0.68 | H59: re-roofing in places the hall and lord's chamber, the archdeacon's chamber, knights' chamber, bailiff's room and granary, which had been partly unroofed, 13 shilling 6pence. | J59: =F59
A60: Cost of buildings | B60: 0 | C60: 2 | D60: 0 | F60: =B60+C60/20+D60/240 | H60: 3 quarters of lime bought for the same 2 shilling, at 8pence a qr. | J60: =F60
A61: Cost of buildings | B61: 0 | C61: 0 | D61: 2 | F61: =B61+C61/20+D61/240 | H61: 200 nails bought for fastening the laths 2pence. | J61: =F61
A62: Cost of buildings | B62: 0 | C62: 2 | D62: 6 | F62: =B62+C62/20+D62/240 | H62: re-roofing in places the great barn, byre, cow-shed and building of the press which had been unroofed 2 shilling 6pence. | J62: =F62 | K62: =J62
A63: Cost of buildings | B63: 0 | C63: 0 | D63: 6 | F63: =B63+C63/20+D63/240 | H63: re-roofing the sheepcote in places 6pence. | J63: =F63 | K63: =J63
A64: Cost of buildings | B64: 0 | C64: 0 | D64: 7 | F64: =B64+C64/20+D64/240 | H64: 2 locks bought for the building of the press and the door to the chamber of the chapel 7pence. | J64: =F64 | K64: =J64
A65: Cost of buildings | B65: 0 | C65: 0 | D65: 10 | F65: =B65+C65/20+D65/240 | H65: 1 band of iron for hooping the beam of the press 10pence. | J65: =F65 | K65: =J65
A66: Cost of buildings | B66: 0 | C66: 0 | D66: 3.5 | F66: =B66+C66/20+D66/240 | H66: 1 iron shovel bought 3.5pence | J66: =F66 | K66: =J66
A67: Cost of buildings | B67: 1 | C67: 8 | D67: 11.5 | F67: 1.45 | H67: Total, £1 8 shilling 11.5pence
A68: Cost of buildings | F68: =SUM(F56:F66) | G68: =F68-F67 | H68: Total
A70: Cost of the park | B70: 0 | C70: 3 | D70: 0 | F70: 0.15 | H70: In mending the palisade of the park in places 3 shilling. | J70: =F70
A71: Cost of the park | B71: 0 | C71: 4 | D71: 5 | F71: 0.22 | H71: enclosing 54 perches in the said park 4 shilling 5pence, at 1pence a perch. | J71: =F71
A72: Cost of the park | B72: 0 | C72: 0 | D72: 11 | F72: =B72+C72/20+D72/240 | H72: mending the old fences of the said park in places 11pence | J72: =F72
A73: Cost of the park | B73: 0 | C73: 8 | D73: 4 | F73: =B73+C73/20+D73/240 | H73: Total, 8 shilling 4pence
A74: Cost of the park | F74: =SUM(F70:F72) | G74: =F74-F73 | H74: Total
A76: Cost of the harvest | B76: 0 | C76: 2 | D76: 0 | F76: 0.1 | H76: In mowing the meadow of Botley and Hove which contains 6 acres measured by the perch by piece-work 2 shilling.
A77: Cost of the harvest | B77: 0 | C77: 2 | D77: 0 | F77: 0.1 | H77: mowing le Longemor' 2 shilling.
A78: Cost of the harvest | B78: 0 | C78: 2 | D78: 0 | F78: 0.1 | H78: mowing Bathardesmed' 2 shilling.
A79: Cost of the harvest | B79: 0 | C79: 0 | D79: 7.5 | F79: 0.03 | H79: mowing the meadow which belonged to the Abbot of Netley 7.5pence.
A80: Cost of the harvest | B80: 0 | C80: 1 | D80: 3 | F80: 0.06 | H80: tossing and tedding all the hay 1 shilling 3pence.
A81: Cost of the harvest | B81: 0 | C81: 5 | D81: 9 | F81: 0.29 | H81: 864 herrings bought for 1.5 boon-works of 108 men who reaped and bound 68 acres of wheat, 12 acres of rye and 40 acres of barley 5 shilling 9pence.
A82: Cost of the harvest | B82: 0 | C82: 0 | D82: 0 | F82: 0 | H82: and know that each of them has 5 herrings a day, 3 at lunch and 2 at supper.
A83: Cost of the harvest | B83: 0 | C83: 0 | D83: 0 | F83: 0 | H83: and know that the rest of the corn is reaped by labour service.
A84: Cost of the harvest | B84: 0 | C84: 16 | D84: 8 | F84: 0.83 | H84: 6 casks bought for cider 16 shilling, at 2 shilling 8pence a cask.
A85: Cost of the harvest | B85: 0 | C85: 2 | D85: 4 | F85: 0.12 | H85: hooping and binding the same 2 shilling 4pence.
A86: Cost of the harvest | B86: 0 | C86: 1 | D86: 0 | F86: =B86+C86/20+D86/240 | H86: hooping and mending 3 tubs, 1 small tub and 1 tine 1 shilling
A87: Cost of the harvest | B87: 1 | C87: 12 | D87: 11.5 | F87: =B87+C87/20+D87/240 | H87: Total, £1 12 shilling 11.5pence
A88: Cost of the harvest | F88: =SUM(F76:F86) | G88: =F88-F87 | H88: Total
A90: Cost of the mill | B90: 0 | C90: 2 | D90: 10 | F90: 0.14 | H90: In lengthening 2 spindles with iron bought and with the stipend of the smith 2 shilling 10pence. | J90: =F90
A91: Cost of the mill | B91: 0 | C91: 1 | D91: 4 | F91: 0.07 | H91: mending 1 mill-rind with iron for the same and with the stipend of the smith for the same 1 shilling 4pence. | J91: =F91
A92: Cost of the mill | B92: 0 | C92: 2 | D92: 0 | F92: 0.1 | H92: steeling, mending and sharpening bills for the year 2 shilling. | J92: =F92
A93: Cost of the mill | B93: 1 | C93: 18 | D93: 0 | F93: 1.9 | H93: 1 millstone bought for the said mill £1 18 shilling. | J93: =F93
A94: Cost of the mill | B94: 0 | C94: 1 | D94: 0 | F94: 0.05 | H94: carrying the same from Southampton to the mill 1 shilling. | J94: =F94
A95: Cost of the mill | B95: 0 | C95: 0 | D95: 8 | F95: 0.03 | H95: 2 iron bands made with iron bought for the same for hooping the head of the beam 8pence. | J95: =F95
A96: Cost of the mill | B96: 0 | C96: 4 | D96: 7 | F96: 0.23 | H96: casting 1 pole with brass bought for the same 4 shilling 7pence. | J96: =F96
A97: Cost of the mill | B97: 0 | C97: 1 | D97: 5 | F97: =B97+C97/20+D97/240 | H97: 2 iron bands made with iron bought for the same and with the stipend of the smith for hooping the inner wheel 1 shilling 5pence | J97: =F97
A98: Cost of the mill | B98: 2 | C98: 11 | D98: 10 | F98: 2.59 | H98: Total, £2 11 shilling 10pence
A99: Cost of the mill | F99: =SUM(F90:F97) | G99: =F99-F98 | H99: Total
A101: Fish-trap (hiltra) | B101: 0 | C101: 0 | D101: 10 | F101: 0.04 | H101: In 1 lock bought for the same 10pence. | J101: =F101 | K101: =J101
A102: Fish-trap (hiltra) | B102: 0 | C102: 1 | D102: 8 | F102: 0.08 | H102: 3 salmon caught by nets in the sea 1 shilling 8pence | J102: =F102 | K102: =J102
A103: Fish-trap (hiltra) | B103: 0 | C103: 2 | D103: 4 | F103: =B103+C103/20+D103/240 | H103: Total, 2 shilling 4pence
A104: Fish-trap (hiltra) | F104: 0.12 | G104: =F104-F103 | H104: Total
A106: Water-pipe (wymond') | B106: 0 | C106: 1 | D106: 1.5 | F106: 0.06 | H106: In 5 lb of tin bought 1 shilling 1.5pence. | J106: =F106 | K106: =J106
A107: Water-pipe (wymond') | B107: 0 | C107: 2 | D107: 2 | F107: 0.11 | H107: pitch, canvas and grease bought for the same 2 shilling 2pence. | J107: =F107 | K107: =J107
A108: Water-pipe (wymond') | B108: 0 | C108: 2 | D108: 4 | F108: 0.12 | H108: stipend of 1 man for 7 days mending the said water-pipe 2 shilling 4pence, or 4pence a day. | J108: =F108 | K108: =J108/2
A109: Water-pipe (wymond') | B109: 0 | C109: 5 | D109: 7.5 | F109: 0.28 | H109: Total, 5 shilling 7.5pence
...

Sheet Issues of the Grange
A1: Gross Output | B1: Total Quantity | C1: Account Total Quarters | D1: Bought in Total Quarters | E1: Received from churchscot | F1: Sold Total Quarters | G1: Difference Produced+Bought-Sold | H1: Weighted Average Price per Quarter | I1: Value of Total Production weighted
A2: wheat | B2: 18.5 | D2: 0 | F2: 8.75 | G2: =B2-F2 | H2: 0.3 | I2: =H2*B2
A3: curall | B3: 8.625 | D3: 0 | F3: 1.25 | G3: =B3-F3 | H3: 0.21666667 | I3: =H3*B3
A4: rye | B4: 3.5 | D4: 0 | G4: =B4-F4 | I4: =H4*B4
A5: barley | B5: 49.375 | D5: 0 | G5: =B5-F5 | H5: 0.19 | I5: =H5*B5 | J5: price from East Meon
A6: dredge | B6: 14.5 | D6: 0 | F6: =11+7/8 | G6: =B6-F6 | H6: 0.083715013 | I6: =H6*B6
A7: oats | B7: 24.625 | D7: 4.25 | G7: =B7-F7 | H7: 0.10320396 | I7: =H7*B7 | J7: price from East Meon
A8: beans | B8: 0 | D8: 0.5 | G8: =B8-F8 | H8: 0.13 | I8: =H8*B8 | J8: price from East Meon Church
A9: peas | B9: 7.5 | D9: 0 | F9: 1.25 | G9: =B9-F9 | H9: 0.16 | I9: =H9*B9
A10: vetches | B10: 3 | D10: 0 | G10: =B10-F10 | H10: 0.1 | I10: =H10*B10 | J10: price from Bishops Sutton
A13: Total Production
A14: Sales of corn (as recorded in accounts)
A17: Net output | B17: Gross output | C17: Seed quarters | D17: Seed bushels | E17: Seed total quarters | F17: tithe quarters | G17: tithe bushels | H17: tithe total | I17: manorial servants quarters | J17: manorial servants bushels | K17: manorial servants total quarters | L17: output net of tithe, seed, liveries | M17: in stock from last year | N17: Price in £ | O17: Value of net output in £ | P17: Value of sales (in "Sale of Corn") in £
A18: wheat | B18: =B2 | C18: 9.5 | D18: 1 | E18: =C18+D18/8 | J18: 1 | K18: =I18+J18/8 | L18: =B18-E18-H18-K18 | N18: =H2 | O18: =N18*L18
A19: curall | B19: =B3 | E19: =C19+D19/8 | I19: =3+1 | J19: =1+1 | K19: =I19+J19/8 | L19: =B19-E19-H19-K19 | N19: =H3 | O19: =N19*L19
A20: rye | B20: =B4 | C20: 1 | D20: 6 | E20: =C20+D20/8 | I20: 1 | J20: 6 | K20: =I20+J20/8 | L20: =B20-E20-H20-K20 | N20: =H4 | O20: =N20*L20
A21: barley | B21: =B5 | C21: 14 | D21: 2 | E21: =C21+D21/8 | I21: =19.5+4+3+6.5+1 | J21: =2+1+6 | K21: =I21+J21/8 | L21: =B21-E21-H21-K21 | N21: =H5 | O21: =N21*L21
A22: dredge | B22: =B6 | C22: 2 | D22: 5 | E22: =C22+D22/8 | K22: =I22+J22/8 | L22: =B22-E22-H22-K22 | N22: =H6 | O22: =N22*L22
A23: oats | B23: =B7 | C23: 14 | D23: 2 | E23: =C23+D23/8 | I23: =7+2 | J23: =4.5+1.5+5 | K23: =I23+J23/8 | L23: =B23-E23-H23-K23 | N23: =H7 | O23: =N23*L23
A24: beans | B24: =B8 | E24: =C24+D24/8 | K24: =I24+J24/8 | L24: =B24-E24-H24-K24 | N24: =H8 | O24: =N24*L24
A25: peas | B25: =B9 | E25: =C25+D25/8 | I25: 4 | J25: 2 | K25: =I25+J25/8 | L25: =B25-E25-H25-K25 | N25: =H9 | O25: =N25*L25
A26: vetches | B26: =B10 | C26: 1 | D26: 7 | E26: =C26+D26/8 | I26: 1 | J26: 1 | K26: =I26+J26/8 | L26: =B26-E26-H26-K26 | N26: =H10 | O26: =N26*L26

Sheet Issues of the Mills

Sheet Stock
A1: BITTERNE STOCK ACCOUNT
C4: added | G4: subtracted
A5: Livestock | B5: Inherited stock | C5: added | D5: strays | E5: herbage | F5: churchscot | G5: of which in default | H5: sold | I5: in murrain | J5: accounted for elsewhere | K5: End-period stock | L5: cross-check | M5: stock building | N5: raw production | O5: Unit price (£) | P5: Value of stock (£) at given value | Q5: Value of stock (£) at sales prices | R5: Sales in (£) | S5: Value of stock building (£) | T5: Value of production (£) at sales prices | U5: Details
A6: Cart-horses | B6: 5 | H6: 2 | I6: 1 | K6: 2 | L6: =B6+C6+D6+E6+F6-G6-H6-I6-J6 | M6: =K6-B6 | O6: =R6/H6 | R6: =Receipts!F45
A7: Mares | B7: 3 | H7: 1 | K7: 2 | L7: =B7+C7+D7+E7+F7-G7-H7-I7-J7 | M7: =K7-B7 | O7: =R7/H7 | R7: =Receipts!F46
A8: Plough horses | B8: 1 | I8: 1 | K8: 0 | L8: =B8+C8+D8+E8+F8-G8-H8-I8-J8 | M8: =K8-B8
A9: Colts (unspecified years) | L9: =B9+C9+D9+E9+F9-G9-H9-I9-J9 | M9: =K9-B9
A10: Colts (2 years) | L10: =B10+C10+D10+E10+F10-G10-H10-I10-J10 | M10: =K10-B10
A11: Colts (1 year) | B11: 1 | K11: 1 | L11: =B11+C11+D11+E11+F11-G11-H11-I11-J11 | M11: =K11-B11
A12: Foals | B12: 1 | C12: 2 | K12: =1+2 | L12: =B12+C12+D12+E12+F12-G12-H12-I12-J12 | M12: =K12-B12
A13: Oxen | B13: 22 | C13: 1 | I13: 1 | K13: 22 | L13: =B13+C13+D13+E13+F13-G13-H13-I13-J13 | M13: =K13-B13
A14: Bulls | B14: 1 | K14: 1 | L14: =B14+C14+D14+E14+F14-G14-H14-I14-J14 | M14: =K14-B14
A15: Cows | B15: 10 | C15: =1+7 | K15: 18 | L15: =B15+C15+D15+E15+F15-G15-H15-I15-J15 | M15: =K15-B15
A16: Steers | B16: 1 | J16: 1 | K16: 0 | L16: =B16+C16+D16+E16+F16-G16-H16-I16-J16 | M16: =K16-B16
A17: Bullocks | B17: 5 | K17: 5 | L17: =B17+C17+D17+E17+F17-G17-H17-I17-J17 | M17: =K17-B17
A18: Yearlings | B18: 5 | I18: 2 | K18: 3 | L18: =B18+C18+D18+E18+F18-G18-H18-I18-J18 | M18: =K18-B18
A19: Calves | C19: 15 | H19: 6 | I19: 1 | K19: 7 | L19: =B19+C19+D19+E19+F19-G19-H19-I19-J19 | M19: =K19-B19 | O19: =R19/H19 | R19: =Receipts!F47
A20: Wethers | B20: 277 | C20: 1 | H20: 17 | I20: =4+17 | K20: 240 | L20: =B20+C20+D20+E20+F20-G20-H20-I20-J20 | M20: =K20-B20 | O20: =R20/H20 | R20: =Receipts!F48
A21: Rams | L21: =B21+C21+D21+E21+F21-G21-H21-I21-J21 | M21: =K21-B21
A22: Ewes | L22: =B22+C22+D22+E22+F22-G22-H22-I22-J22 | M22: =K22-B22
A23: Hoggs | L23: =B23+C23+D23+E23+F23-G23-H23-I23-J23 | M23: =K23-B23
A24: Lambs | L24: =B24+C24+D24+E24+F24-G24-H24-I24-J24 | M24: =K24-B24
A25: Boars | L25: =B25+C25+D25+E25+F25-G25-H25-I25-J25 | M25: =K25-B25
A26: Sows | B26: 1 | K26: 1 | L26: =B26+C26+D26+E26+F26-G26-H26-I26-J26 | M26: =K26-B26
A27: Pigs | B27: 6 | H27: 4 | K27: 2 | L27: =B27+C27+D27+E27+F27-G27-H27-I27-J27 | M27: =K27-B27 | O27: =R27/H27 | R27: =Receipts!F49
A28: Hoggets | B28: 1 | I28: 1 | K28: 0 | L28: =B28+C28+D28+E28+F28-G28-H28-I28-J28 | M28: =K28-B28
A29: Piglets | C29: 8 | K29: 8 | L29: =B29+C29+D29+E29+F29-G29-H29-I29-J29 | M29: =K29-B29
A30: Swans | M30: =K30-B30
A31: Peacocks | M31: =K31-B31
A32: Total Value | R32: =SUM(R6:R31)
A35: Wool | M35: =K35-B35
A36: Coarse wool | B36: 257 | J36: =26+231 | M36: =K36-B36 | O36: 0.02 | T36: =O36*J36
A37: Lamb's wool | M37: =K37-B37 | O37: 0.01
A38: Wool locks | C38: 3 | M38: =K38-B38 | R38: =Receipts!F70 | T38: =R38 | U38: 3lb of wool locks recorded as sold in issues (not in stock)
A39: Wool sold at shearing | M39: =K39-B39
A40: Total wool | T40: =SUM(T36:T39)
A43: Hides | M43: =K43-B43
A44: Ox hides | C44: 1 | H44: 1 | K44: 0 | L44: =B44+C44+D44+E44+F44-G44-H44-I44-J44 | M44: =K44-B44 | O44: =R44/H44 | R44: =Receipts!F62 | T44: =O44*C44 | U44: no ox hide found in sales, only bullock - potentially a mistake by clerk
A45: cart horse | C45: 1 | H45: 1 | K45: 0 | L45: =B45+C45+D45+E45+F45-G45-H45-I45-J45 | M45: =K45-B45 | O45: =R45/H45 | R45: =Receipts!F60 | T45: =O45*C45
A46: plough horse | C46: 1 | H46: 1 | K46: 0 | L46: =B46+C46+D46+E46+F46-G46-H46-I46-J46 | M46: =K46-B46 | O46: =R46/H46 | R46: =Receipts!F61 | T46: =O46*C46
A47: yearlings | C47: 2 | H47: 2 | K47: 0 | L47: =B47+C47+D47+E47+F47-G47-H47-I47-J47 | M47: =K47-B47 | O47: =R47/H47 | R47: =Receipts!F63 | T47: =O47*C47
A48: Mare | L48: =B48+C48+D48+E48+F48-G48-H48-I48-J48 | M48: =K48-B48 | T48: =O48*C48
A49: Steer | L49: =B49+C49+D49+E49+F49-G49-H49-I49-J49 | M49: =K49-B49 | T49: =O49*C49
A50: calves | H50: 1 | L50: =B50+C50+D50+E50+F50-G50-H50-I50-J50 | M50: =K50-B50 | O50: =R50/H50 | R50: =Receipts!F64 | T50: =O50*H50 | U50: only noted in issues not in stock
A51: pigs | L51: =B51+C51+D51+E51+F51-G51-H51-I51-J51 | M51: =K51-B51 | T51: =O51*C51
A52: Woolskins | L52: =B52+C52+D52+E52+F52-G52-H52-I52-J52 | M52: =K52-B52 | T52: =O52*C52
A53: wethers | C53: 4 | H53: 4 | K53: 0 | L53: =B53+C53+D53+E53+F53-G53-H53-I53-J53 | M53: =K53-B53 | O53: =R53/H53 | R53: =Receipts!F65 | T53: =O53*C53
A54: rams | L54: =B54+C54+D54+E54+F54-G54-H54-I54-J54 | M54: =K54-B54 | T54: =O54*C54
A55: ewes | L55: =B55+C55+D55+E55+F55-G55-H55-I55-J55 | M55: =K55-B55 | T55: =O55*C55
A56: hoggs | L56: =B56+C56+D56+E56+F56-G56-H56-I56-J56 | M56: =K56-B56 | T56: =O56*C56
A57: Woolskins | L57: =B57+C57+D57+E57+F57-G57-H57-I57-J57 | M57: =K57-B57 | T57: =O57*C57
A58: Bareskins | L58: =B58+C58+D58+E58+F58-G58-H58-I58-J58 | M58: =K58-B58 | T58: =O58*C58
A59: wethers | C59: 17 | H59: 17 | K59: 0 | L59: =B59+C59+D59+E59+F59-G59-H59-I59-J59 | M59: =K59-B59 | O59: =R59/H59 | R59: =Receipts!F66 | T59: =O59*C59
A60: rams
A61: ewes
A62: hoggs
A63: Bareskins (total)
A64: Lambskins (excl. 8 in tithe)
A65: Rotted skins
A66: Shorn skins
A67: Total | R67: =SUM(R42:R66) | T67: =SUM(T44:T64)
A70: Poultry stock
A71: Hens
A72: Geese
A73: Capons (from chickens)
A74: Cocks & hens
A75: Total poultry stock
A76: Total poultry excluding churchscot
A78: Poultry production
A79: Eggs
A80: Cocks & hens from churchscot of customary tenants | F80: 195 | G80: 40 | H80: 155 | K80: 0 | M80: =K80-B80 | O80: =R80/H80 | R80: =Receipts!F50 | T80: =O80*H80 | U80: issues only records the sale of 151 hens
A81: Sum of above
A82: Total | R82: =SUM(R74:R81) | T82: =T80
A85: Meat
A86: Beef | M86: =K86-B86
A87: Mutton | M87: =K87-B87
A88: Pork | M88: =K88-B88
A89: Total | M89: =K89-B89
M90: =K90-B90
A91: Cheese | M91: =K91-B91
A92: Winter cheese | C92: 33 | M92: =K92-B92 | R92: =Receipts!F54 | T92: =R92
A93: Summer cheese | C93: 137 | H93: 124 | J93: 13 | M93: =K93-B93 | O93: =R93/H93 | R93: =Receipts!F55 | T93: =O93*C93
A94: Total | R94: =SUM(R86:R93) | T94: =SUM(T92:T93)
A96: Butter
A97: Butter | C97: 6 | H97: 6 | M97: =K97-B97 | O97: =R97/H97 | R97: =Receipts!F56 | T97: =O97*H97 | U97: measured in cloves
A98: Total | R98: =R97 | T98: =T97
A100: Total Dairy Sales
A103: Fish
A104: Salmon | C104: 55 | H104: 53 | J104: 2 | O104: =R104/H104 | R104: =Receipts!F76
A105: Total | R105: =SUM(R104)
A107: Additional Information (not necessarily useful)
A108: Utensils
A109: ploughs
A110: carts
A111: cart-ropes
A112: corn baskets
A113: seed-sacks
A114: seed basket
A115: locks for the doors
A116: lead vessel
...

Sheet raw data
A1: Heading | B1: Sentence | C1: Total in Pounds | D1: Pounds | E1: Shillings | F1: Pence | G1: Corn | H1: Total Quarters Except 1 | I1: Total Bushels Except 1 | J1: Total Corn Cross-Check | K1: Total Corn Manorial Account | L1: Corn Quantity Error | M1: Quarters 1 | N1: Bushels 1 | O1: Quarters 2 | P1: Bushels 2 | Q1: Quarters 3 | R1: Bushels 3 | S1: Quarters 4 | T1: Bushels 4 | U1: shilling a quarter 1 | V1: pence a quarter 1 | W1: shilling a quarter 2 | X1: pence a quarter 2 | Y1: shilling a quarter 3 | Z1: pence a quarter 3 | AA1: shilling a quarter 4 | AB1: pence a quarter 4 | AC1: shilling a bushel 1 | AD1: pence a bushel 1 | AE1: shilling a bushel 2 | AF1: pence a bushel 2 | AG1: shilling a bushel 3 | AH1: pence a bushel 3 | AI1: shilling a bushel 4 | AJ1: pence a bushel 4
A2: Arrears | B2: William de Worsted', sergeant, and Walter le Parker, reeve, render account for £7 14 shilling 4.5pence of arrears from the previous year. | C2: 7.72 | D2: 7 | E2: 14 | F2: 4.5 | H2: 0 | I2: 0 | J2: 0 | K2: 0 | L2: 0 | M2: 0 | N2: 0
A3: Arrears | B3: All delivered to Sir Geoffrey, treasurer of Wolvesey. | C3: 0 | D3: 0 | E3: 0 | F3: 0 | H3: 0 | I3: 0 | J3: 0 | K3: 0 | L3: 0 | M3: 0 | N3: 0
A4: Rents of assize | B4: The same render account for £2 3pence for all rents of assize at Christmas. | C4: 2.01 | D4: 2 | E4: 0 | F4: 3 | H4: 0 | I4: 0 | J4: 0 | K4: 0 | L4: 0 | M4: 0 | N4: 0
A5: Rents of assize | B5: £2 3pence at Easter (22 April). | C5: 2.01 | D5: 2 | E5: 0 | F5: 3 | H5: 0 | I5: 0 | J5: 0 | K5: 0 | L5: 0 | M5: 0 | N5: 0
A6: Rents of assize | B6: £2 3pence at the Nativity of St John the Baptist (24 June). | C6: 2.01 | D6: 2 | E6: 0 | F6: 3 | H6: 0 | I6: 0 | J6: 0 | K6: 0 | L6: 0 | M6: 0 | N6: 0
A7: Rents of assize | B7: £3 2 shilling 11.5pence at Michaelmas (29 September). | C7: 3.15 | D7: 3 | E7: 2 | F7: 11.5 | H7: 0 | I7: 0 | J7: 0 | K7: 0 | L7: 0 | M7: 0 | N7: 0
A8: Rents of assize | B8: Total, £9 3 shilling 8.5pence | C8: 9.19 | D8: 9 | E8: 3 | F8: 8.5 | H8: 0 | I8: 0 | J8: 0 | K8: 0 | L8: 0 | M8: 0 | N8: 0
A9: Quittances | B9: In quittance of 1 reeve for the year 4 shilling. | C9: 0.2 | D9: 0 | E9: 4 | F9: 0 | H9: 0 | I9: 0 | J9: 0 | K9: 0 | L9: 0 | M9: 0 | N9: 0
A10: Quittances | B10: 2 ploughmen for the year 3 shilling. | C10: 0.15 | D10: 0 | E10: 3 | F10: 0 | H10: 0 | I10: 0 | J10: 0 | K10: 0 | L10: 0 | M10: 0 | N10: 0
A11: Quittances | B11: 1 park-keeper for the year 4 shilling | C11: 0.2 | D11: 0 | E11: 4 | F11: 0 | H11: 0 | I11: 0 | J11: 0 | K11: 0 | L11: 0 | M11: 0 | N11: 0
A12: Quittances | B12: Total, 11 shilling | C12: 0.55 | D12: 0 | E12: 11 | F12: 0 | H12: 0 | I12: 0 | J12: 0 | K12: 0 | L12: 0 | M12: 0 | N12: 0
A13: Defaults of rent | B13: In default of the land of Vyel drawn into demesne, 2 shilling 1pence for the year. | C13: 0.1 | D13: 0 | E13: 2 | F13: 1 | H13: 0 | I13: 0 | J13: 0 | K13: 0 | L13: 0 | M13: 0 | N13: 0
... A59: Fishery | B59: The same render account for £7 4 shilling from 53 salmon sold, at 4 shilling each for 19, and 2 shilling each for 34. Total, £7 4 shilling | C59: 7.2 | D59: 7 | E59: 4 | F59: 0 | H59: 0 | I59: 0 | J59: 0 | K59: 0 | L59: 0 | M59: 0 | N59: 0
A60: Sale of corn | B60: The same render account for £2 12 shilling 6pence from 8 quarters 6 bushels of wheat sold, at 6 shilling a quarters. | C60: 2.62 | D60: 2 | E60: 12 | F60: 6 | G60: wheat | H60: 8 | I60: 6 | J60: 8.75 | K60: 8.75 | L60: 0 | M60: 8 | N60: 6 | U60: 6 | V60: 0
A61: Sale of corn | B61: 5 shilling 5pence from 1 quarters 2 bushels of curall sold, at 4 shilling 4pence a quarters. | C61: 0.27 | D61: 0 | E61: 5 | F61: 5 | G61: curall | H61: 1 | I61: 2 | J61: 1.25 | K61: 1.25 | L61: 0 | M61: 1 | N61: 2 | U61: 4 | V61: 4
A62: Sale of corn | B62: £1 6 shilling 5pence from 11 quarters 3 bushels of dredge sold, at 2 shilling a quarters for 3 quarters 7 bushels, 2 shilling 4pence a quarters for 4 quarters, and 2 shilling 8pence a quarters for 3.5 quarters. | C62: 1.32 | D62: 1 | E62: 6 | F62: 5 | H62: 10.5 | I62: 7 | J62: 11.375 | K62: 11.375 | L62: 0 | M62: 11 | N62: 3 | O62: 3 | P62: 7 | Q62: 4 | R62: 0 | S62: 3.5 | T62: 0 | U62: 2 | V62: 0 | W62: 2 | X62: 4 | Y62: 2 | Z62: 8
A63: Sale of corn | B63: 1 shilling from .5 quarters of dredge sold at the audit. | C63: 0.05 | D63: 0 | E63: 1 | F63: 0 | H63: 5 | I63: 0 | J63: 5 | K63: 5 | L63: 0 | M63: 5 | N63: 0
A64: Sale of corn | B64: 2 shilling from 4 bushels of peas sold, at 6pence a bushels. | C64: 0.12 | D64: 0 | E64: 2 | F64: 6 | G64: peas | H64: 0 | I64: 4 | J64: 0.5 | K64: 0.5 | L64: 0 | M64: 0 | N64: 4 | AC64: 0 | AD64: 6
A65: Sale of corn | B65: 2 shilling from 6 bushels of peas sold at the audit. | C65: 0.1 | D65: 0 | E65: 2 | F65: 0 | G65: peas | H65: 0 | I65: 6 | J65: 0.75 | K65: 0.75 | L65: 0 | M65: 0 | N65: 6
A66: Sale of corn | B66: Total, £4 9 shilling 4pence | C66: 4.47 | D66: 4 | E66: 9 | F66: 4 | H66: 0 | I66: 0 | J66: 0 | K66: 0 | L66: 0 | M66: 0 | N66: 0
A67: Sale of the mill's corn | B67: The same render account for 10 shilling 3pence from 1 quarters 7 bushels of wheat sold, at 7.5pence a bushels for 2 bushels, 5 shilling 4pence a quarters for 1 quarters 1 bushels, and 9pence a bushels for 4 bushels. | C67: 0.51 | D67: 0 | E67: 10 | F67: 3 | G67: wheat | H67: 1 | I67: 7 | J67: 1.875 | K67: 1.875 | L67: 0 | M67: 1 | N67: 7 | O67: 0 | P67: 2 | Q67: 1 | R67: 1 | S67: 0 | T67: 4 | U67: 5 | V67: 4 | AC67: 0 | AD67: 7.5 | AE67: 0 | AF67: 9
A68: Sale of the mill's corn | B68: £1 15 shilling 10pence from 11 quarters 6 bushels of barley sold, at 2 shilling 8pence a quarters for 3 quarters, 3 shilling a quarters for 4 quarters, and 3 shilling 4pence a quarters for 4 quarters 6 bushels. | C68: 1.79 | D68: 1 | E68: 15 | F68: 10 | G68: barley | H68: 11 | I68: 6 | J68: 11.75 | K68: 11.75 | L68: 0 | M68: 11 | N68: 6 | O68: 3 | P68: 0 | Q68: 4 | R68: 0 | S68: 4 | T68: 6 | U68: 2 | V68: 8 | W68: 3 | X68: 0 | Y68: 3 | Z68: 4
A69: Sale of the mill's corn | B69: 1 1 shilling from 2 quarters 1 bushels of coarse-ground corn sold, at 5 shilling for 1 quarters, and 5 shilling 4pence a quarters for 1 quarters 1 bushels. | C69: 0.07 | D69: 0 | E69: 1 | F69: 4 | H69: 2 | I69: 1 | J69: 2.125 | K69: 2.125 | L69: 0 | M69: 2 | N69: 1 | O69: 1 | P69: 0 | Q69: 1 | R69: 1 | U69: 5 | V69: 4
A70: Sale of the mill's corn | B70: 10 shilling 9pence from 4 quarters 7 bushels of malt sold, at 2 shilling a quarters for 1 quarters 7 bushels, and 2 shilling 4pence a quarters for 3 quarters. | C70: 0.54 | D70: 0 | E70: 10 | F70: 9 | H70: 4 | I70: 7 | J70: 4.875 | K70: 4.875 | L70: 0 | M70: 4 | N70: 7 | O70: 1 | P70: 7 | Q70: 3 | R70: 0 | U70: 2 | V70: 0 | W70: 2 | X70: 4
A71: Sale of the mill's corn | B71: 8pence from 1 bushels of oatmeal sold Total, £3 8 shilling 6pence | C71: 3.42 | D71: 3 | E71: 8 | F71: 6 | G71: oatmeal | H71: 0 | I71: 1 | J71: 0.125 | K71: 0.125 | L71: 0 | M71: 0 | N71: 1
A72: Entry and marriage fines | B72: The same render account for 6 shilling 8pence from the tithing of Bitterne at the hundred-court of Martinmas for tithingpenny. | C72: 0.33 | D72: 0 | E72: 6 | F72: 8 | H72: 0 | I72: 0 | J72: 0 | K72: 0 | L72: 0 | M72: 0 | N72: 0
A73: Entry and marriage fines | B73: 6 shilling 8pence from the tithing of Fawley at the said hundred-court for the same. | C73: 0.33 | D73: 0 | E73: 6 | F73: 8 | H73: 0 | I73: 0 | J73: 0 | K73: 0 | L73: 0 | M73: 0 | N73: 0
A74: Entry and marriage fines | B74: 13 shilling 4pence from the same at the hundred-court of Hockday for the same. | C74: 0.67 | D74: 0 | E74: 13 | F74: 4 | H74: 0 | I74: 0 | J74: 0 | K74: 0 | L74: 0 | M74: 0 | N74: 0
A75: Entry and marriage fines | B75: 1 shilling from John le Careter for marrying Joan his stepdaughter outside. | C75: 0.05 | D75: 0 | E75: 1 | F75: 0 | H75: 0 | I75: 0 | J75: 0 | K75: 0 | L75: 0 | M75: 0 | N75: 0
A76: Entry and marriage fines | B76: 3 shilling from .Havvise, daughter of Austin Mich', to have 1 house and 2 acres of land which belonged to Edith her mother. | C76: 0.15 | D76: 0 | E76: 3 | F76: 0 | H76: 0 | I76: 0 | J76: 0 | K76: 0 | L76: 0 | M76: 0 | N76: 0
A77: Entry and marriage fines | B77: 6 shilling 8pence from Matilda, daughter of Mabel Ace, to have 1 messuage and 1 ferling of land by surrender of Mabel her mother, so that the said Mabel be supported by holding the same land equally with her. | C77: 0.33 | D77: 0 | E77: 6 | F77: 8 | H77: 0 | I77: 0 | J77: 0 | K77: 0 | L77: 0 | M77: 0 | N77: 0
A78: Entry and marriage fines | B78: 6 shilling 8pence from Nicholas le Pyn to have the said Matilda with her land. | C78: 0.33 | D78: 0 | E78: 6 | F78: 8 | H78: 0 | I78: 0 | J78: 0 | K78: 0 | L78: 0 | M78: 0 | N78: 0
A79: Entry and marriage fines | B79: 6 shilling 8pence from Walter le Schepphurd' to have the land which belonged to his mother. | C79: 0.33 | D79: 0 | E79: 6 | F79: 8 | H79: 0 | I79: 0 | J79: 0 | K79: 0 | L79: 0 | M79: 0 | N79: 0
A80: Entry and marriage fines | B80: 13 shilling 4pence from Roger ate Clive to have the land which belonged to Gunilda Gardenir. | C80: 0.67 | D80: 0 | E80: 13 | F80: 4 | H80: 0 | I80: 0 | J80: 0 | K80: 0 | L80: 0 | M80: 0 | N80: 0
A81: Entry and marriage fines | B81: 3 shilling 4pence from Roger Westsyd' to have 1 house and 1 curtilage by surrender of Walter le Schiphurd', and he will relieve the said Walter of 6pence annual rent. | C81: 0.17 | D81: 0 | E81: 3 | F81: 4 | H81: 0 | I81: 0 | J81: 0 | K81: 0 | L81: 0 | M81: 0 | N81: 0
A82: Entry and marriage fines | B82: 1 shilling from Joan Alayn for marrying herself. | C82: 0.05 | D82: 0 | E82: 1 | F82: 0 | H82: 0 | I82: 0 | J82: 0 | K82: 0 | L82: 0 | M82: 0 | N82: 0
A83: Entry and marriage fines | B83: 1 shilling from Margery, daughter of Walter le Schiphurd', for marrying herself. | C83: 0.05 | D83: 0 | E83: 1 | F83: 0 | H83: 0 | I83: 0 | J83: 0 | K83: 0 | L83: 0 | M83: 0 | N83: 0
... A104: Cost of ploughs | B104: stipend of 2 ploughmen for the year 6 shilling. | C104: 0.3 | D104: 0 | E104: 6 | F104: 0 | H104: 0 | I104: 0 | J104: 0 | K104: 0 | L104: 0 | M104: 0 | N104: 0
A105: Cost of ploughs | B105: 4 bushels of beans bought for sowing 1 shilling 4pence. | C105: 0.07 | D105: 0 | E105: 1 | F105: 4 | G105: beans | H105: 0 | I105: 4 | J105: 0.5 | K105: 0.5 | L105: 0 | M105: 0 | N105: 4
A106: Cost of ploughs | B106: forage bought for supporting oxen 12 shilling 8pence Total, £2. | C106: 2 | D106: 2 | E106: 0 | F106: 0 | H106: 0 | I106: 0 | J106: 0 | K106: 0 | L106: 0 | M106: 0 | N106: 0
A107: Cost of carts | B107: In fitting the cart with axles at various times with axles bought for the same 5.5pence. | C107: 0.02 | D107: 0 | E107: 0 | F107: 5.5 | H107: 0 | I107: 0 | J107: 0 | K107: 0 | L107: 0 | M107: 0 | N107: 0
A108: Cost of carts | B108: clouts, nails, grease bought for the same 6.5pence. | C108: 0.03 | D108: 0 | E108: 0 | F108: 6.5 | H108: 0 | I108: 0 | J108: 0 | K108: 0 | L108: 0 | M108: 0 | N108: 0
A109: Cost of carts | B109: 1 collar bought 8pence. | C109: 0.03 | D109: 0 | E109: 0 | F109: 8 | H109: 0 | I109: 0 | J109: 0 | K109: 0 | L109: 0 | M109: 0 | N109: 0
A110: Cost of carts | B110: white leather bought for mending harnesses 6pence. | C110: 0.03 | D110: 0 | E110: 0 | F110: 6 | H110: 0 | I110: 0 | J110: 0 | K110: 0 | L110: 0 | M110: 0 | N110: 0
A111: Cost of carts | B111: a broad-axe bought for mending the cart 7pence. | C111: 0.03 | D111: 0 | E111: 0 | F111: 7 | H111: 0 | I111: 0 | J111: 0 | K111: 0 | L111: 0 | M111: 0 | N111: 0
A112: Cost of carts | B112: hooping the hubs of wheels with bands of wood 3pence. | C112: 0.01 | D112: 0 | E112: 0 | F112: 3 | H112: 0 | I112: 0 | J112: 0 | K112: 0 | L112: 0 | M112: 0 | N112: 0
A113: Cost of carts | B113: shoeing 2 cart-horses for the year 2 shilling 6pence. | C113: 0.12 | D113: 0 | E113: 2 | F113: 6 | H113: 0 | I113: 0 | J113: 0 | K113: 0 | L113: 0 | M113: 0 | N113: 0
A114: Cost of carts | B114: shoeing 2 plough-horses going to harrow at both sowings 8pence. | C114: 0.03 | D114: 0 | E114: 0 | F114: 8 | H114: 0 | I114: 0 | J114: 0 | K114: 0 | L114: 0 | M114: 0 | N114: 0
A115: Cost of carts | B115: stipend of 1 carter for the year 3 shilling. | C115: 0.15 | D115: 0 | E115: 3 | F115: 0 | H115: 0 | I115: 0 | J115: 0 | K115: 0 | L115: 0 | M115: 0 | N115: 0
A116: Cost of carts | B116: 4 quarters 2 bushels of oats bought for the fodder of horses 8 shilling 8pence Total, 17 shilling 8pence | C116: 0.43 | D116: 0 | E116: 8 | F116: 8 | G116: oats | H116: 4 | I116: 2 | J116: 4.25 | K116: 4.25 | L116: 0 | M116: 4 | N116: 2
A117: Cost of the dairy | B117: In woollen and linen cloth bought for the dairy 5pence. | C117: 0.02 | D117: 0 | E117: 0 | F117: 5 | H117: 0 | I117: 0 | J117: 0 | K117: 0 | L117: 0 | M117: 0 | N117: 0
A118: Cost of the dairy | B118: 5 bushels of salt bought 1 shilling .5pence. | C118: 0.07 | D118: 0 | E118: 1 | F118: 5 | H118: 0 | I118: 5 | J118: 0.625 | K118: 0.625 | L118: 0 | M118: 0 | N118: 5
A119: Cost of the dairy | B119: earthenware pots and pans bought for the same 2pence. | C119: 0.01 | D119: 0 | E119: 0 | F119: 2 | H119: 0 | I119: 0 | J119: 0 | K119: 0 | L119: 0 | M119: 0 | N119: 0
A120: Cost of the dairy | B120: 1 new bucket bought and another mended 5pence. | C120: 0.02 | D120: 0 | E120: 0 | F120: 5 | H120: 0 | I120: 0 | J120: 0 | K120: 0 | L120: 0 | M120: 0 | N120: 0
A121: Cost of the dairy | B121: a press bought for the same 3pence. | C121: 0.01 | D121: 0 | E121: 0 | F121: 3 | H121: 0 | I121: 0 | J121: 0 | K121: 0 | L121: 0 | M121: 0 | N121: 0
A122: Cost of the dairy | B122: 6 ells of canvas bought for putting the wool in 1 shilling7.5pence, at 3.25pence an ell. | C122: 0.08 | D122: 0 | E122: 1 | F122: 7.5 | H122: 0 | I122: 0 | J122: 0 | K122: 0 | L122: 0 | M122: 0 | N122: 0
A123: Cost of the dairy | B123: . | C123: 0 | D123: 0 | E123: 0 | F123: 0 | H123: 0 | I123: 0 | J123: 0 | K123: 0 | L123: 0 | M123: 0 | N123: 0
A124: Cost of the dairy | B124: packing the wool 2pence. | C124: 0.01 | D124: 0 | E124: 0 | F124: 2 | H124: 0 | I124: 0 | J124: 0 | K124: 0 | L124: 0 | M124: 0 | N124: 0
A125: Cost of the dairy | B125: grease bought for greasing sheep 3 shilling. | C125: 0.15 | D125: 0 | E125: 3 | F125: 0 | H125: 0 | I125: 0 | J125: 0 | K125: 0 | L125: 0 | M125: 0 | N125: 0
A126: Cost of the dairy | B126: 1 mould bought for making cheese 4pence. | C126: 0.02 | D126: 0 | E126: 0 | F126: 4 | H126: 0 | I126: 0 | J126: 0 | K126: 0 | L126: 0 | M126: 0 | N126: 0
A127: Cost of the dairy | B127: stipend of 1 dairymaid for the year 1 shilling 6pence. | C127: 0.08 | D127: 0 | E127: 1 | F127: 6 | H127: 0 | I127: 0 | J127: 0 | K127: 0 | L127: 0 | M127: 0 | N127: 0
A128: Cost of the dairy | B128: stipend of 1 shepherd for the year 3 shilling. | C128: 0.15 | D128: 0 | E128: 3 | F128: 0 | H128: 0 | I128: 0 | J128: 0 | K128: 0 | L128: 0 | M128: 0 | N128: 0
... A130: Cost of the dairy | B130: 1 wether bought before shearing 1 shilling 6pence Total, £3 12 shilling 6pence | C130: 3.62 | D130: 3 | E130: 12 | F130: 6 | H130: 0 | I130: 0 | J130: 0 | K130: 0 | L130: 0 | M130: 0 | N130: 0
A131: Threshing | B131: In threshing 30 quarters of wheat, curall and rye by piece-work 5 shilling, at 2.5pence per 10 struck bushe1 shilling. | C131: 0.26 | D131: 0 | E131: 5 | F131: 2.5 | G131: curall, rye, wheat | H131: 30 | I131: 0 | J131: 30 | K131: 30 | L131: 0 | M131: 30 | N131: 0
A132: Threshing | B132: threshing 64 quarters 1 bushels of barley, dredge, peas and vetches by piece-work 6 shilling per 10 struck bushe1 shilling. | C132: 0.3 | D132: 0 | E132: 6 | F132: 0 | G132: barley, vetches, peas | H132: 64 | I132: 1 | J132: 64.125 | K132: 64.125 | L132: 0 | M132: 64 | N132: 1
A133: Threshing | B133: threshing 20 quarters 3 bushels of oats by piece-workper 20 struck bushe1 shilling. | C133: 0.05 | D133: 0 | E133: 1 | F133: 0 | G133: oats | H133: 20 | I133: 3 | J133: 20.375 | K133: 20.375 | L133: 0 | M133: 20 | N133: 3
A134: Threshing | B134: winnowing all the corn beyond that 4.5pence, at 1.5pence 1 shilling, at 1.5pence winnowed by the dairymaid 9pence Total, 13 shilling 1.5pence | C134: 0.07 | D134: 0 | E134: 1 | F134: 4.5 | H134: 0 | I134: 0 | J134: 0 | K134: 0 | L134: 0 | M134: 0 | N134: 0
A135: Cost of buildings | B135: in 6 lb of tin and 2 fotmals of lead bought for mending the lord's tower and various gutters in the curia 6 shilling 11pence. | C135: 0.35 | D135: 0 | E135: 6 | F135: 11 | H135: 0 | I135: 0 | J135: 0 | K135: 0 | L135: 0 | M135: 0 | N135: 0
A136: Cost of buildings | B136: 1 plumber with 1 mate cutting the said tin and lead and mending the tower and various gutters in the curia for 3 days 1 shilling 6pence, at 6pence a day.'. | C136: 0.08 | D136: 0 | E136: 1 | F136: 6 | H136: 0 | I136: 0 | J136: 0 | K136: 0 | L136: 0 | M136: 0 | N136: 0
A137: Cost of buildings | B137: nails for the same 2pence. | C137: 0.01 | D137: 0 | E137: 0 | F137: 2 | H137: 0 | I137: 0 | J137: 0 | K137: 0 | L137: 0 | M137: 0 | N137: 0
A138: Cost of buildings | B138: re-roofing in places the hall and lord's chamber, the archdeacon's chamber, knights' chamber, bailiff's room and granary, which had been partly unroofed, 13 shilling 6pence. | C138: 0.68 | D138: 0 | E138: 13 | F138: 6 | H138: 0 | I138: 0 | J138: 0 | K138: 0 | L138: 0 | M138: 0 | N138: 0
A139: Cost of buildings | B139: 3 quarters of lime bought for the same 2 shilling, at 8pence a quarters. | C139: 0.13 | D139: 0 | E139: 2 | F139: 8 | H139: 3 | I139: 0 | J139: 3 | K139: 3 | L139: 0 | M139: 3 | N139: 0
A140: Cost of buildings | B140: . | C140: 0 | D140: 0 | E140: 0 | F140: 0 | H140: 0 | I140: 0 | J140: 0 | K140: 0 | L140: 0 | M140: 0 | N140: 0
A141: Cost of buildings | B141: 200 nails bought for fastening the laths 2pence. | C141: 0.01 | D141: 0 | E141: 0 | F141: 2 | H141: 0 | I141: 0 | J141: 0 | K141: 0 | L141: 0 | M141: 0 | N141: 0
A142: Cost of buildings | B142: re-roofing in places the great barn, byre, cow-shed and building of the press which had been unroofed 2 shilling 6pence. | C142: 0.12 | D142: 0 | E142: 2 | F142: 6 | H142: 0 | I142: 0 | J142: 0 | K142: 0 | L142: 0 | M142: 0 | N142: 0
A143: Cost of buildings | B143: re-roofing the sheepcote in places 6pence. | C143: 0.03 | D143: 0 | E143: 0 | F143: 6 | H143: 0 | I143: 0 | J143: 0 | K143: 0 | L143: 0 | M143: 0 | N143: 0
A144: Cost of buildings | B144: 2 locks bought for the building of the press and the2 door to the chamber of the chapel 7pence. | C144: 0.03 | D144: 0 | E144: 0 | F144: 7 | H144: 0 | I144: 0 | J144: 0 | K144: 0 | L144: 0 | M144: 0 | N144: 0
A145: Cost of buildings | B145: 1 band of iron for hooping the beam of the press 10pence. | C145: 0.04 | D145: 0 | E145: 0 | F145: 10 | H145: 0 | I145: 0 | J145: 0 | K145: 0 | L145: 0 | M145: 0 | N145: 0
... A155: Cost of the harvest | B155: tossing and tedding all the hay 1 shilling 3pence. | C155: 0.06 | D155: 0 | E155: 1 | F155: 3 | H155: 0 | I155: 0 | J155: 0 | K155: 0 | L155: 0 | M155: 0 | N155: 0
A156: Cost of the harvest | B156: 864 herrings bought for 1.5 boon-works of 108 men who reaped and bound 68 acres of wheat, 12 acres of rye and 40 acres of barley 5 shilling 9pence. | C156: 0.29 | D156: 0 | E156: 5 | F156: 9 | G156: barley, rye, wheat | H156: 0 | I156: 0 | J156: 0 | K156: 0 | L156: 0 | M156: 0 | N156: 0
A157: Cost of the harvest | B157: and know that each of them has 5 herrings a day, 3 at lunch and 2 at supper. | C157: 0 | D157: 0 | E157: 0 | F157: 0 | H157: 0 | I157: 0 | J157: 0 | K157: 0 | L157: 0 | M157: 0 | N157: 0
A158: Cost of the harvest | B158: and know that the rest of the corn is reaped by labour service. | C158: 0 | D158: 0 | E158: 0 | F158: 0 | H158: 0 | I158: 0 | J158: 0 | K158: 0 | L158: 0 | M158: 0 | N158: 0
A159: Cost of the harvest | B159: . | C159: 0 | D159: 0 | E159: 0 | F159: 0 | H159: 0 | I159: 0 | J159: 0 | K159: 0 | L159: 0 | M159: 0 | N159: 0
A160: Cost of the harvest | B160: 6 casks bought for cider 16 shilling, at 2 shilling 8pence a cask. | C160: 0.83 | D160: 0 | E160: 16 | F160: 8 | H160: 0 | I160: 0 | J160: 0 | K160: 0 | L160: 0 | M160: 0 | N160: 0
A161: Cost of the harvest | B161: . | C161: 0 | D161: 0 | E161: 0 | F161: 0 | H161: 0 | I161: 0 | J161: 0 | K161: 0 | L161: 0 | M161: 0 | N161: 0
A162: Cost of the harvest | B162: hooping and binding the same 2 shilling 4pence. | C162: 0.12 | D162: 0 | E162: 2 | F162: 4 | H162: 0 | I162: 0 | J162: 0 | K162: 0 | L162: 0 | M162: 0 | N162: 0
A163: Cost of the harvest | B163: hooping and mending 3 tubs, 1 small tub and 1 tine 1 shilling Total, £l 12 shilling 11.5pence | C163: 0.1 | D163: 0 | E163: 1 | F163: 11.5 | H163: 0 | I163: 0 | J163: 0 | K163: 0 | L163: 0 | M163: 0 | N163: 0
A164: Cost of the mill | B164: In lengthening 2 spindles with iron bought and with the stipend of the smith 2 shilling 10pence. | C164: 0.14 | D164: 0 | E164: 2 | F164: 10 | H164: 0 | I164: 0 | J164: 0 | K164: 0 | L164: 0 | M164: 0 | N164: 0
A165: Cost of the mill | B165: mending 1 mill-rind with iron for the same and with the stipend of the smith for the same 1 shilling 4pence. | C165: 0.07 | D165: 0 | E165: 1 | F165: 4 | H165: 0 | I165: 0 | J165: 0 | K165: 0 | L165: 0 | M165: 0 | N165: 0
A166: Cost of the mill | B166: steeling, mending and sharpening bills for the year 2 shilling. | C166: 0.1 | D166: 0 | E166: 2 | F166: 0 | H166: 0 | I166: 0 | J166: 0 | K166: 0 | L166: 0 | M166: 0 | N166: 0
A167: Cost of the mill | B167: 1 millstone bought for the said mill £1 18 shilling. | C167: 1.9 | D167: 1 | E167: 18 | F167: 0 | H167: 0 | I167: 0 | J167: 0 | K167: 0 | L167: 0 | M167: 0 | N167: 0
A168: Cost of the mill | B168: carrying the same from Southampton to the mill 1 shilling. | C168: 0.05 | D168: 0 | E168: 1 | F168: 0 | H168: 0 | I168: 0 | J168: 0 | K168: 0 | L168: 0 | M168: 0 | N168: 0
... A188: Wheat | B188: {yield: two-fold plus 1 quarters 4 bushels) | C188: 0 | D188: 0 | E188: 0 | F188: 0 | H188: 1 | I188: 4 | J188: 1.5 | K188: 1.5 | L188: 0 | M188: 1 | N188: 4
A189: Wheat | B189: The same render account for 18.5 quarters from the whole issue of wheat by struck measure. | C189: 0 | D189: 0 | E189: 0 | F189: 0 | G189: wheat | H189: 18.5 | I189: 0 | J189: 18.5 | K189: 18.5 | L189: 0 | M189: 18.5 | N189: 0
A190: Wheat | B190: Sown over 68 acres as they lie in Gildewyneslond', 9.5 quarters 1 bushels. | C190: 0 | D190: 0 | E190: 0 | F190: 0 | H190: 9.5 | I190: 1 | J190: 9.625 | K190: 9.625 | L190: 0 | M190: 9.5 | N190: 1
A191: Wheat | B191: that is, 1 bushels an acre, plus 1 quarters 1 bushels in all. | C191: 0 | D191: 0 | E191: 0 | F191: 0 | H191: 1 | I191: 1 | J191: 1.125 | K191: 0.125 | L191: 1 | M191: 0 | N191: 1 | O191: 1 | P191: 1
A192: Wheat | B192: . | C192: 0 | D192: 0 | E192: 0 | F192: 0 | H192: 0 | I192: 0 | J192: 0 | K192: 0 | L192: 0 | M192: 0 | N192: 0
A193: Wheat | B193: provision of the steward for his visits, 1 bushels Sold, 8 quarters 6 bushels | C193: 0 | D193: 0 | E193: 0 | F193: 0 | H193: 8 | I193: 6 | J193: 8.75 | K193: 0.125 | L193: 8.625 | M193: 0 | N193: 1 | O193: 8 | P193: 6
A194: Curall | B194: The same render account for 8 quarters .5 bushels from the whole issue of curall from the same wheat by struck measure. | C194: 0 | D194: 0 | E194: 0 | F194: 0 | G194: curall, wheat | H194: 8 | I194: 5 | J194: 8.625 | K194: 8 | L194: 0.625 | M194: 8 | N194: 0 | O194: 0 | P194: 5
...

Sheet Issues of the Grange raw
A1: Heading | B1: Sentence | C1: Quarters 1_x | D1: Bushels 1_x | E1: Sown Quarters | F1: Sown Bushels | G1: Sown Total Quarters | H1: Bought in Quarters | I1: Bought in Bushels | J1: Bought in Total Quarters | K1: Tithe Quarters | L1: Tithe Bushels | M1: Tithe Total Quarters | N1: Manorial servants & livestock Quarters | O1: Manorial servants & livestock Bushels | P1: Manorial servants & livestock Total Quarters | Q1: Sold Quarters | R1: Sold Bushels | S1: Sold Total Quarters | T1: Account Quarters | U1: Account Bushels | V1: Account Total Quarters | W1: bought only | X1: Total Quarters Except 1 | Y1: Total Bushels Except 1 | Z1: Total Corn Cross-Check | AA1: Total Corn Manorial Account | AB1: Corn Quantity Error | AC1: Quarters 1_y | AD1: Bushels 1_y | AE1: Quarters 2 | AF1: Bushels 2 | AG1: Quarters 3 | AH1: Bushels 3 | AI1: Quarters 4 | AJ1: Bushels 4
A2: And thus he owes clear | B2: Total | C2: 0 | D2: 0 | E2: 0 | F2: 0 | G2: 0 | H2: 0 | I2: 0 | J2: 0 | K2: 0 | L2: 0 | M2: 0 | N2: 0 | O2: 0 | P2: 0 | Q2: 0 | R2: 0 | S2: 0 | T2: 0 | U2: 0 | V2: 0 | W2: 0
A3: Wheat | B3: {yield: two-fold plus 1 qr 4 bushels) | C3: 0 | D3: 0 | E3: 0 | F3: 0 | G3: 0 | H3: 0 | I3: 0 | J3: 0 | K3: 0 | L3: 0 | M3: 0 | N3: 0 | O3: 0 | P3: 0 | Q3: 0 | R3: 0 | S3: 0 | T3: 0 | U3: 0 | V3: 0 | W3: 0
A4: Wheat | B4: The same render account for 18.5 quarters from the whole issue of wheat by struck measure. | C4: 0 | D4: 0 | E4: 0 | F4: 0 | G4: 0 | H4: 0 | I4: 0 | J4: 0 | K4: 0 | L4: 0 | M4: 0 | N4: 0 | O4: 0 | P4: 0 | Q4: 0 | R4: 0 | S4: 0 | T4: 18.5 | U4: 0 | V4: 18.5 | W4: 0 | X4: 18.5 | Y4: 0 | Z4: 18.5 | AA4: 18.5 | AB4: 0 | AC4: 18.5 | AD4: 0
A5: Wheat | B5: Sown over 68 acres as they lie in Gildewyneslond', 9.5 quarters 1 bushels. | C5: 0 | D5: 0 | E5: 9.5 | F5: 1 | G5: 9.625 | H5: 0 | I5: 0 | J5: 0 | K5: 0 | L5: 0 | M5: 0 | N5: 0 | O5: 0 | P5: 0 | Q5: 0 | R5: 0 | S5: 0 | T5: 0 | U5: 0 | V5: 0 | W5: 0 | X5: 9.5 | Y5: 1 | Z5: 9.625 | AA5: 9.625 | AB5: 0 | AC5: 9.5 | AD5: 1
A6: Wheat | B6: that is, 1 bushels an acre, plus 1 qr 1 bushels in all. | C6: 0 | D6: 0 | E6: 0 | F6: 0 | G6: 0 | H6: 0 | I6: 0 | J6: 0 | K6: 0 | L6: 0 | M6: 0 | N6: 0 | O6: 0 | P6: 0 | Q6: 0 | R6: 0 | S6: 0 | T6: 0 | U6: 0 | V6: 0 | W6: 0
A7: Wheat | B7: . | C7: 0 | D7: 0 | E7: 0 | F7: 0 | G7: 0 | H7: 0 | I7: 0 | J7: 0 | K7: 0 | L7: 0 | M7: 0 | N7: 0 | O7: 0 | P7: 0 | Q7: 0 | R7: 0 | S7: 0 | T7: 0 | U7: 0 | V7: 0 | W7: 0 | X7: 0 | Y7: 0 | Z7: 0 | AA7: 0 | AB7: 0 | AC7: 0 | AD7: 0
A8: Wheat | B8: provision of the steward for his visits, 1 bushels Sold, 8 quarters 6 bushels | C8: 0 | D8: 0 | E8: 0 | F8: 0 | G8: 0 | H8: 0 | I8: 0 | J8: 0 | K8: 0 | L8: 0 | M8: 0 | N8: 8 | O8: 6 | P8: 8.75 | Q8: 8 | R8: 6 | S8: 8.75 | T8: 0 | U8: 0 | V8: 0 | W8: 0 | X8: 8 | Y8: 6 | Z8: 8.75 | AA8: 0.125 | AB8: 8.625 | AC8: 0 | AD8: 1 | AE8: 8 | AF8: 6
A9: Wheat | B9: Total | C9: 0 | D9: 0 | E9: 0 | F9: 0 | G9: 0 | H9: 0 | I9: 0 | J9: 0 | K9: 0 | L9: 0 | M9: 0 | N9: 0 | O9: 0 | P9: 0 | Q9: 0 | R9: 0 | S9: 0 | T9: 0 | U9: 0 | V9: 0 | W9: 0
A10: Curall | B10: The same render account for 8 quarters .5 bushels from the whole issue of curall from the same wheat by struck measure. | C10: 0 | D10: 0 | E10: 0 | F10: 0 | G10: 0 | H10: 0 | I10: 0 | J10: 0 | K10: 0 | L10: 0 | M10: 0 | N10: 0 | O10: 0 | P10: 0 | Q10: 0 | R10: 0 | S10: 0 | T10: 8 | U10: 0 | V10: 8 | W10: 0 | X10: 8 | Y10: 5 | Z10: 8.625 | AA10: 8 | AB10: 0.625 | AC10: 8 | AD10: 0 | AE10: 0 | AF10: 5
A11: Curall | B11: Mixed with barley for the liveries of the manorial servants, 3 quarters 1 bushels. | C11: 0 | D11: 0 | E11: 0 | F11: 0 | G11: 0 | H11: 0 | I11: 0 | J11: 0 | K11: 0 | L11: 0 | M11: 0 | N11: 3 | O11: 1 | P11: 3.125 | Q11: 0 | R11: 0 | S11: 0 | T11: 0 | U11: 0 | V11: 0 | W11: 0 | X11: 3 | Y11: 1 | Z11: 3.125 | AA11: 3.125 | AB11: 0 | AC11: 3 | AD11: 1
A12: Curall | B12: supporting pigs, 1 qr 1 bushels Sold, 1 qr 2 bushels Total, 5.5 quarters. | C12: 0 | D12: 0 | E12: 0 | F12: 0 | G12: 0 | H12: 0 | I12: 0 | J12: 0 | K12: 0 | L12: 0 | M12: 0 | N12: 0 | O12: 0 | P12: 0 | Q12: 5.5 | R12: 0 | S12: 5.5 | T12: 0 | U12: 0 | V12: 0 | W12: 0
A13: Curall | B13: And 2.5 quarters .5 bushels remain in the granary. | C13: 0 | D13: 0 | E13: 0 | F13: 0 | G13: 0 | H13: 0 | I13: 0 | J13: 0 | K13: 0 | L13: 0 | M13: 0 | N13: 0 | O13: 0 | P13: 0 | Q13: 0 | R13: 0 | S13: 0 | T13: 0 | U13: 0 | V13: 0 | W13: 0 | X13: 2.5 | Y13: 5 | Z13: 3.125 | AA13: 2.5 | AB13: 0.625 | AC13: 2.5 | AD13: 0 | AE13: 0 | AF13: 5
A14: Curall | B14: Total | C14: 0 | D14: 0 | E14: 0 | F14: 0 | G14: 0 | H14: 0 | I14: 0 | J14: 0 | K14: 0 | L14: 0 | M14: 0 | N14: 0 | O14: 0 | P14: 0 | Q14: 0 | R14: 0 | S14: 0 | T14: 0 | U14: 0 | V14: 0 | W14: 0
A15: Rye | B15: {yield: two-and-a-half-fold plus .51} | C15: 0 | D15: 0 | E15: 0 | F15: 0 | G15: 0 | H15: 0 | I15: 0 | J15: 0 | K15: 0 | L15: 0 | M15: 0 | N15: 0 | O15: 0 | P15: 0 | Q15: 0 | R15: 0 | S15: 0 | T15: 0 | U15: 0 | V15: 0 | W15: 0 | X15: 0 | Y15: 0 | Z15: 0 | AA15: 0 | AB15: 0 | AC15: 0 | AD15: 0
A16: Rye | B16: The same render account for 3.5 quarters from the whole issue of rye by struck measure. | C16: 0 | D16: 0 | E16: 0 | F16: 0 | G16: 0 | H16: 0 | I16: 0 | J16: 0 | K16: 0 | L16: 0 | M16: 0 | N16: 0 | O16: 0 | P16: 0 | Q16: 0 | R16: 0 | S16: 0 | T16: 3.5 | U16: 0 | V16: 3.5 | W16: 0 | X16: 3.5 | Y16: 0 | Z16: 3.5 | AA16: 3.5 | AB16: 0 | AC16: 3.5 | AD16: 0
A17: Rye | B17: Sown over 12 acres as they lie in Westbynne, 1 qr 6 bushels. | C17: 0 | D17: 0 | E17: 0 | F17: 0 | G17: 0 | H17: 0 | I17: 0 | J17: 0 | K17: 0 | L17: 0 | M17: 0 | N17: 0 | O17: 0 | P17: 0 | Q17: 0 | R17: 0 | S17: 0 | T17: 0 | U17: 0 | V17: 0 | W17: 0
A18: Rye | B18: that is, 1 bushels an acre, plus 2 bushels in all. | C18: 0 | D18: 0 | E18: 0 | F18: 0 | G18: 0 | H18: 0 | I18: 0 | J18: 0 | K18: 0 | L18: 0 | M18: 0 | N18: 0 | O18: 0 | P18: 0 | Q18: 0 | R18: 0 | S18: 0 | T18: 0 | U18: 0 | V18: 0 | W18: 0 | X18: 0 | Y18: 2 | Z18: 0.25 | AA18: 0.125 | AB18: 0.125 | AC18: 0 | AD18: 1 | AE18: 0 | AF18: 2
A19: Rye | B19: Mixed with barley for the liveries of the manorial servants, 1 qr 6 bushels It balances. | C19: 0 | D19: 0 | E19: 0 | F19: 0 | G19: 0 | H19: 0 | I19: 0 | J19: 0 | K19: 0 | L19: 0 | M19: 0 | N19: 0 | O19: 0 | P19: 0 | Q19: 0 | R19: 0 | S19: 0 | T19: 0 | U19: 0 | V19: 0 | W19: 0
A20: Rye | B20: Total | C20: 0 | D20: 0 | E20: 0 | F20: 0 | G20: 0 | H20: 0 | I20: 0 | J20: 0 | K20: 0 | L20: 0 | M20: 0 | N20: 0 | O20: 0 | P20: 0 | Q20: 0 | R20: 0 | S20: 0 | T20: 0 | U20: 0 | V20: 0 | W20: 0
A21: Barley | B21: {yield: two-and-a-half-fold plus 2 quarters} | C21: 0 | D21: 0 | E21: 0 | F21: 0 | G21: 0 | H21: 0 | I21: 0 | J21: 0 | K21: 0 | L21: 0 | M21: 0 | N21: 0 | O21: 0 | P21: 0 | Q21: 0 | R21: 0 | S21: 0 | T21: 0 | U21: 0 | V21: 0 | W21: 0 | X21: 2 | Y21: 0 | Z21: 2 | AA21: 2 | AB21: 0 | AC21: 2 | AD21: 0
A22: Barley | B22: The same render account for 39 quarters 1 bushels from the whole issue of barley by struck measure. | C22: 0 | D22: 0 | E22: 0 | F22: 0 | G22: 0 | H22: 0 | I22: 0 | J22: 0 | K22: 0 | L22: 0 | M22: 0 | N22: 0 | O22: 0 | P22: 0 | Q22: 0 | R22: 0 | S22: 0 | T22: 39 | U22: 1 | V22: 39.125 | W22: 0 | X22: 39 | Y22: 1 | Z22: 39.125 | AA22: 39.125 | AB22: 0 | AC22: 39 | AD22: 1
A23: Barley | B23: 3 quarters 1 bushels received from curall and mixed with barley for the liveries of the manorial servants. | C23: 0 | D23: 0 | E23: 0 | F23: 0 | G23: 0 | H23: 0 | I23: 0 | J23: 0 | K23: 0 | L23: 0 | M23: 0 | N23: 3 | O23: 1 | P23: 3.125 | Q23: 0 | R23: 0 | S23: 0 | T23: 0 | U23: 0 | V23: 0 | W23: 0 | X23: 3 | Y23: 1 | Z23: 3.125 | AA23: 3.125 | AB23: 0 | AC23: 3 | AD23: 1
A24: Barley | B24: 1 qr 6 bushels received from rye. | C24: 0 | D24: 0 | E24: 0 | F24: 0 | G24: 0 | H24: 0 | I24: 0 | J24: 0 | K24: 0 | L24: 0 | M24: 0 | N24: 0 | O24: 0 | P24: 0 | Q24: 0 | R24: 0 | S24: 0 | T24: 0 | U24: 0 | V24: 0 | W24: 0
A25: Barley | B25: 4 quarters 2 bushels received from peas. | C25: 0 | D25: 0 | E25: 0 | F25: 0 | G25: 0 | H25: 0 | I25: 0 | J25: 0 | K25: 0 | L25: 0 | M25: 0 | N25: 0 | O25: 0 | P25: 0 | Q25: 0 | R25: 0 | S25: 0 | T25: 0 | U25: 0 | V25: 0 | W25: 0 | X25: 4 | Y25: 2 | Z25: 4.25 | AA25: 4.25 | AB25: 0 | AC25: 4 | AD25: 2
A26: Barley | B26: 1 qr 1 bushels received from vetches and mixed for the same. | C26: 0 | D26: 0 | E26: 0 | F26: 0 | G26: 0 | H26: 0 | I26: 0 | J26: 0 | K26: 0 | L26: 0 | M26: 0 | N26: 0 | O26: 0 | P26: 0 | Q26: 0 | R26: 0 | S26: 0 | T26: 0 | U26: 0 | V26: 0 | W26: 0
A27: Barley | B27: Total, 49 quarters 3 bushels Sown over 75 acres as they lie in Bathardefeld', 14 quarters 2 bushels. | C27: 0 | D27: 0 | E27: 63 | F27: 5 | G27: 63.625 | H27: 0 | I27: 0 | J27: 0 | K27: 0 | L27: 0 | M27: 0 | N27: 0 | O27: 0 | P27: 0 | Q27: 0 | R27: 0 | S27: 0 | T27: 0 | U27: 0 | V27: 0 | W27: 0 | X27: 14 | Y27: 2 | Z27: 14.25 | AA27: 49.375 | AB27: -35.125 | AC27: 49 | AD27: 3 | AE27: 14 | AF27: 2
A28: Barley | B28: that is, 1.5 bushels an acre, less 1.5 bushels in all. | C28: 0 | D28: 0 | E28: 0 | F28: 0 | G28: 0 | H28: 0 | I28: 0 | J28: 0 | K28: 0 | L28: 0 | M28: 0 | N28: 0 | O28: 0 | P28: 0 | Q28: 0 | R28: 0 | S28: 0 | T28: 0 | U28: 0 | V28: 0 | W28: 0 | X28: 0 | Y28: 1.5 | Z28: 0.1875 | AA28: 0.1875 | AB28: 0 | AC28: 0 | AD28: 1.5 | AE28: 0 | AF28: 1.5
A29: Barley | B29: Delivered to 1 carter and 2 drovers for the year, 19.5 quarters, taking a quarter every 8 weeks. | C29: 0 | D29: 0 | E29: 0 | F29: 0 | G29: 0 | H29: 0 | I29: 0 | J29: 0 | K29: 0 | L29: 0 | M29: 0 | N29: 0 | O29: 0 | P29: 0 | Q29: 0 | R29: 0 | S29: 0 | T29: 0 | U29: 0 | V29: 0 | W29: 0 | X29: 19.5 | Y29: 0 | Z29: 19.5 | AA29: 19.5 | AB29: 0 | AC29: 19.5 | AD29: 0
A30: Barley | B30: Delivered to 1 cowherd for the year, 4 quarters 2 bushels, taking a quarter every 12 weeks. | C30: 0 | D30: 0 | E30: 0 | F30: 0 | G30: 0 | H30: 0 | I30: 0 | J30: 0 | K30: 0 | L30: 0 | M30: 0 | N30: 0 | O30: 0 | P30: 0 | Q30: 0 | R30: 0 | S30: 0 | T30: 0 | U30: 0 | V30: 0 | W30: 0 | X30: 4 | Y30: 2 | Z30: 4.25 | AA30: 4.25 | AB30: 0 | AC30: 4 | AD30: 2
A31: Barley | B31: Delivered to 1 dairymaid for the year, 3 quarters 1 bushels, taking a quarter every 16 weeks. | C31: 0 | D31: 0 | E31: 0 | F31: 0 | G31: 0 | H31: 0 | I31: 0 | J31: 0 | K31: 0 | L31: 0 | M31: 0 | N31: 0 | O31: 0 | P31: 0 | Q31: 0 | R31: 0 | S31: 0 | T31: 0 | U31: 0 | V31: 0 | W31: 0 | X31: 3 | Y31: 1 | Z31: 3.125 | AA31: 3.125 | AB31: 0 | AC31: 3 | AD31: 1
A32: Barley | B32: Delivered to 1 shepherd for the year, 6.5 quarters, taking a quarter every 8 weeks. | C32: 0 | D32: 0 | E32: 0 | F32: 0 | G32: 0 | H32: 0 | I32: 0 | J32: 0 | K32: 0 | L32: 0 | M32: 0 | N32: 0 | O32: 0 | P32: 0 | Q32: 0 | R32: 0 | S32: 0 | T32: 0 | U32: 0 | V32: 0 | W32: 0 | X32: 6.5 | Y32: 0 | Z32: 6.5 | AA32: 6.5 | AB32: 0 | AC32: 6.5 | AD32: 0
A33: Barley | B33: . | C33: 0 | D33: 0 | E33: 0 | F33: 0 | G33: 0 | H33: 0 | I33: 0 | J33: 0 | K33: 0 | L33: 0 | M33: 0 | N33: 0 | O33: 0 | P33: 0 | Q33: 0 | R33: 0 | S33: 0 | T33: 0 | U33: 0 | V33: 0 | W33: 0 | X33: 0 | Y33: 0 | Z33: 0 | AA33: 0 | AB33: 0 | AC33: 0 | AD33: 0
A34: Barley | B34: customary payment to 1 park-keeper, 1 qr. | C34: 0 | D34: 0 | E34: 0 | F34: 0 | G34: 0 | H34: 0 | I34: 0 | J34: 0 | K34: 0 | L34: 0 | M34: 0 | N34: 0 | O34: 0 | P34: 0 | Q34: 0 | R34: 0 | S34: 0 | T34: 0 | U34: 0 | V34: 0 | W34: 0
A35: Barley | B35: Delivered to 1 harrower at various times at both sowings, 6 bushels It balances. | C35: 0 | D35: 0 | E35: 0 | F35: 0 | G35: 0 | H35: 0 | I35: 0 | J35: 0 | K35: 0 | L35: 0 | M35: 0 | N35: 0 | O35: 0 | P35: 0 | Q35: 0 | R35: 0 | S35: 0 | T35: 0 | U35: 0 | V35: 0 | W35: 0 | X35: 0 | Y35: 6 | Z35: 0.75 | AA35: 0.75 | AB35: 0 | AC35: 0 | AD35: 6
A36: Barley | B36: Total | C36: 0 | D36: 0 | E36: 0 | F36: 0 | G36: 0 | H36: 0 | I36: 0 | J36: 0 | K36: 0 | L36: 0 | M36: 0 | N36: 0 | O36: 0 | P36: 0 | Q36: 0 | R36: 0 | S36: 0 | T36: 0 | U36: 0 | V36: 0 | W36: 0
A37: Dredge | B37: {yield: four-fold less .5 qr} | C37: 0 | D37: 0 | E37: 0 | F37: 0 | G37: 0 | H37: 0 | I37: 0 | J37: 0 | K37: 0 | L37: 0 | M37: 0 | N37: 0 | O37: 0 | P37: 0 | Q37: 0 | R37: 0 | S37: 0 | T37: 0 | U37: 0 | V37: 0 | W37: 0
A38: Dredge | B38: The same render account for 14.5 quarters from the whole issue of dredge by struck measure. | C38: 0 | D38: 0 | E38: 0 | F38: 0 | G38: 0 | H38: 0 | I38: 0 | J38: 0 | K38: 0 | L38: 0 | M38: 0 | N38: 0 | O38: 0 | P38: 0 | Q38: 0 | R38: 0 | S38: 0 | T38: 14.5 | U38: 0 | V38: 14.5 | W38: 0 | X38: 14.5 | Y38: 0 | Z38: 14.5 | AA38: 14.5 | AB38: 0 | AC38: 14.5 | AD38: 0
A39: Dredge | B39: Sown over 18 acres as they lie in Westbune, 2 quarters 5 bushels. | C39: 0 | D39: 0 | E39: 2 | F39: 5 | G39: 2.625 | H39: 0 | I39: 0 | J39: 0 | K39: 0 | L39: 0 | M39: 0 | N39: 0 | O39: 0 | P39: 0 | Q39: 0 | R39: 0 | S39: 0 | T39: 0 | U39: 0 | V39: 0 | W39: 0 | X39: 2 | Y39: 5 | Z39: 2.625 | AA39: 2.625 | AB39: 0 | AC39: 2 | AD39: 5
A40: Dredge | B40: that is, 1 bushels an acre, plus 3 bushels in all. | C40: 0 | D40: 0 | E40: 0 | F40: 0 | G40: 0 | H40: 0 | I40: 0 | J40: 0 | K40: 0 | L40: 0 | M40: 0 | N40: 0 | O40: 0 | P40: 0 | Q40: 0 | R40: 0 | S40: 0 | T40: 0 | U40: 0 | V40: 0 | W40: 0 | X40: 0 | Y40: 3 | Z40: 0.375 | AA40: 0.125 | AB40: 0.25 | AC40: 0 | AD40: 1 | AE40: 0 | AF40: 3
A41: Dredge | B41: Sold, 11 quarters 7 bushels | C41: 0 | D41: 0 | E41: 0 | F41: 0 | G41: 0 | H41: 0 | I41: 0 | J41: 0 | K41: 0 | L41: 0 | M41: 0 | N41: 0 | O41: 0 | P41: 0 | Q41: 11 | R41: 7 | S41: 11.875 | T41: 0 | U41: 0 | V41: 0 | W41: 0 | X41: 11 | Y41: 7 | Z41: 11.875 | AA41: 11.875 | AB41: 0 | AC41: 11 | AD41: 7
A42: Dredge | B42: Total | C42: 0 | D42: 0 | E42: 0 | F42: 0 | G42: 0 | H42: 0 | I42: 0 | J42: 0 | K42: 0 | L42: 0 | M42: 0 | N42: 0 | O42: 0 | P42: 0 | Q42: 0 | R42: 0 | S42: 0 | T42: 0 | U42: 0 | V42: 0 | W42: 0
A43: Oats | B43: {yield: two-fold less 3 quarters 5 bushels} | C43: 0 | D43: 0 | E43: 0 | F43: 0 | G43: 0 | H43: 0 | I43: 0 | J43: 0 | K43: 0 | L43: 0 | M43: 0 | N43: 0 | O43: 0 | P43: 0 | Q43: 0 | R43: 0 | S43: 0 | T43: 0 | U43: 0 | V43: 0 | W43: 0 | X43: 3 | Y43: 5 | Z43: 3.625 | AA43: 3.625 | AB43: 0 | AC43: 3 | AD43: 5
A44: Oats | B44: The same render account for 20 quarters 3 bushels from the whole issue of oats by struck measure. | C44: 0 | D44: 0 | E44: 0 | F44: 0 | G44: 0 | H44: 0 | I44: 0 | J44: 0 | K44: 0 | L44: 0 | M44: 0 | N44: 0 | O44: 0 | P44: 0 | Q44: 0 | R44: 0 | S44: 0 | T44: 20 | U44: 3 | V44: 20.375 | W44: 0 | X44: 20 | Y44: 3 | Z44: 20.375 | AA44: 20.375 | AB44: 0 | AC44: 20 | AD44: 3
A45: Oats | B45: 4 quarters 2 bushels bought. | C45: 0 | D45: 0 | E45: 0 | F45: 0 | G45: 0 | H45: 4 | I45: 2 | J45: 4.25 | K45: 0 | L45: 0 | M45: 0 | N45: 0 | O45: 0 | P45: 0 | Q45: 0 | R45: 0 | S45: 0 | T45: 0 | U45: 0 | V45: 0 | W45: 0 | X45: 4 | Y45: 2 | Z45: 4.25 | AA45: 4.25 | AB45: 0 | AC45: 4 | AD45: 2
A46: Oats | B46: Total, 24 quarters 5 bushels | C46: 0 | D46: 0 | E46: 0 | F46: 0 | G46: 0 | H46: 0 | I46: 0 | J46: 0 | K46: 0 | L46: 0 | M46: 0 | N46: 0 | O46: 0 | P46: 0 | Q46: 0 | R46: 0 | S46: 0 | T46: 0 | U46: 0 | V46: 0 | W46: 0 | X46: 24 | Y46: 5 | Z46: 24.625 | AA46: 24.625 | AB46: 0 | AC46: 24 | AD46: 5
A47: Oats | B47: Sown over 57 acres as they lie in Pustukes and Bathardeslond', 14 quarters 2 bushels. | C47: 0 | D47: 0 | E47: 14 | F47: 2 | G47: 14.25 | H47: 0 | I47: 0 | J47: 0 | K47: 0 | L47: 0 | M47: 0 | N47: 0 | O47: 0 | P47: 0 | Q47: 0 | R47: 0 | S47: 0 | T47: 0 | U47: 0 | V47: 0 | W47: 0 | X47: 14 | Y47: 2 | Z47: 14.25 | AA47: 14.25 | AB47: 0 | AC47: 14 | AD47: 2
A48: Oats | B48: that is, 2 bushels an acre. | C48: 0 | D48: 0 | E48: 0 | F48: 0 | G48: 0 | H48: 0 | I48: 0 | J48: 0 | K48: 0 | L48: 0 | M48: 0 | N48: 0 | O48: 0 | P48: 0 | Q48: 0 | R48: 0 | S48: 0 | T48: 0 | U48: 0 | V48: 0 | W48: 0 | X48: 0 | Y48: 2 | Z48: 0.25 | AA48: 0.25 | AB48: 0 | AC48: 0 | AD48: 2
A49: Oats | B49: . | C49: 0 | D49: 0 | E49: 0 | F49: 0 | G49: 0 | H49: 0 | I49: 0 | J49: 0 | K49: 0 | L49: 0 | M49: 0 | N49: 0 | O49: 0 | P49: 0 | Q49: 0 | R49: 0 | S49: 0 | T49: 0 | U49: 0 | V49: 0 | W49: 0 | X49: 0 | Y49: 0 | Z49: 0 | AA49: 0 | AB49: 0 | AC49: 0 | AD49: 0
A50: Oats | B50: . | C50: 0 | D50: 0 | E50: 0 | F50: 0 | G50: 0 | H50: 0 | I50: 0 | J50: 0 | K50: 0 | L50: 0 | M50: 0 | N50: 0 | O50: 0 | P50: 0 | Q50: 0 | R50: 0 | S50: 0 | T50: 0 | U50: 0 | V50: 0 | W50: 0 | X50: 0 | Y50: 0 | Z50: 0 | AA50: 0 | AB50: 0 | AC50: 0 | AD50: 0
A51: Oats | B51: provision of the steward for his visits, 4.5 bushels. | C51: 0 | D51: 0 | E51: 0 | F51: 0 | G51: 0 | H51: 0 | I51: 0 | J51: 0 | K51: 0 | L51: 0 | M51: 0 | N51: 0 | O51: 0 | P51: 0 | Q51: 0 | R51: 0 | S51: 0 | T51: 0 | U51: 0 | V51: 0 | W51: 0 | X51: 0 | Y51: 4.5 | Z51: 0.5625 | AA51: 0.5625 | AB51: 0 | AC51: 0 | AD51: 4.5
A52: Oats | B52: fodder of the clerk's horse for his visits, 1.5 bushels. | C52: 0 | D52: 0 | E52: 0 | F52: 0 | G52: 0 | H52: 0 | I52: 0 | J52: 0 | K52: 0 | L52: 0 | M52: 0 | N52: 0 | O52: 0 | P52: 0 | Q52: 0 | R52: 0 | S52: 0 | T52: 0 | U52: 0 | V52: 0 | W52: 0 | X52: 0 | Y52: 1.5 | Z52: 0.1875 | AA52: 0.1875 | AB52: 0 | AC52: 0 | AD52: 1.5
A53: Oats | B53: fodder of 2 cart-horses for the year, 7 quarters this year. | C53: 0 | D53: 0 | E53: 0 | F53: 0 | G53: 0 | H53: 0 | I53: 0 | J53: 0 | K53: 0 | L53: 0 | M53: 0 | N53: 7 | O53: 0 | P53: 7 | Q53: 0 | R53: 0 | S53: 0 | T53: 0 | U53: 0 | V53: 0 | W53: 0 | X53: 7 | Y53: 0 | Z53: 7 | AA53: 7 | AB53: 0 | AC53: 7 | AD53: 0
A54: Oats | B54: . | C54: 0 | D54: 0 | E54: 0 | F54: 0 | G54: 0 | H54: 0 | I54: 0 | J54: 0 | K54: 0 | L54: 0 | M54: 0 | N54: 0 | O54: 0 | P54: 0 | Q54: 0 | R54: 0 | S54: 0 | T54: 0 | U54: 0 | V54: 0 | W54: 0 | X54: 0 | Y54: 0 | Z54: 0 | AA54: 0 | AB54: 0 | AC54: 0 | AD54: 0
... A56: Oats | B56: fodder of 2 plough-horses going to harrow at both sowings, 2 quarters 5 bushels this year, and this because the carts carried wood for fencing (claustr') from the park to the curia for the enclosure by order of the lorpence It balances. | C56: 0 | D56: 0 | E56: 0 | F56: 0 | G56: 0 | H56: 0 | I56: 0 | J56: 0 | K56: 0 | L56: 0 | M56: 0 | N56: 2 | O56: 5 | P56: 2.625 | Q56: 0 | R56: 0 | S56: 0 | T56: 0 | U56: 0 | V56: 0 | W56: 0 | X56: 2 | Y56: 5 | Z56: 2.625 | AA56: 2.625 | AB56: 0 | AC56: 2 | AD56: 5
A57: Oats | B57: Total | C57: 0 | D57: 0 | E57: 0 | F57: 0 | G57: 0 | H57: 0 | I57: 0 | J57: 0 | K57: 0 | L57: 0 | M57: 0 | N57: 0 | O57: 0 | P57: 0 | Q57: 0 | R57: 0 | S57: 0 | T57: 0 | U57: 0 | V57: 0 | W57: 0
A58: Vetches | B58: {yield: two-fold plus .5 qr} | C58: 0 | D58: 0 | E58: 0 | F58: 0 | G58: 0 | H58: 0 | I58: 0 | J58: 0 | K58: 0 | L58: 0 | M58: 0 | N58: 0 | O58: 0 | P58: 0 | Q58: 0 | R58: 0 | S58: 0 | T58: 0 | U58: 0 | V58: 0 | W58: 0
A59: Vetches | B59: The same render account for 3 quarters from the whole issue of vetches by struck measure. | C59: 0 | D59: 0 | E59: 0 | F59: 0 | G59: 0 | H59: 0 | I59: 0 | J59: 0 | K59: 0 | L59: 0 | M59: 0 | N59: 0 | O59: 0 | P59: 0 | Q59: 0 | R59: 0 | S59: 0 | T59: 3 | U59: 0 | V59: 3 | W59: 0 | X59: 3 | Y59: 0 | Z59: 3 | AA59: 3 | AB59: 0 | AC59: 3 | AD59: 0
A60: Vetches | B60: Sown over 15 acres as they lie in Charelliscroft and Pollescroft, 1 qr 7 bushels. | C60: 0 | D60: 0 | E60: 0 | F60: 0 | G60: 0 | H60: 0 | I60: 0 | J60: 0 | K60: 0 | L60: 0 | M60: 0 | N60: 0 | O60: 0 | P60: 0 | Q60: 0 | R60: 0 | S60: 0 | T60: 0 | U60: 0 | V60: 0 | W60: 0
A61: Vetches | B61: that is, 1 bushels an acre. | C61: 0 | D61: 0 | E61: 0 | F61: 0 | G61: 0 | H61: 0 | I61: 0 | J61: 0 | K61: 0 | L61: 0 | M61: 0 | N61: 0 | O61: 0 | P61: 0 | Q61: 0 | R61: 0 | S61: 0 | T61: 0 | U61: 0 | V61: 0 | W61: 0 | X61: 0 | Y61: 0 | Z61: 0 | AA61: 0 | AB61: 0 | AC61: 0 | AD61: 0
A62: Vetches | B62: Mixed with barley for the liveries of the manorial servants, 1 qr 1 bushels | C62: 0 | D62: 0 | E62: 0 | F62: 0 | G62: 0 | H62: 0 | I62: 0 | J62: 0 | K62: 0 | L62: 0 | M62: 0 | N62: 0 | O62: 0 | P62: 0 | Q62: 0 | R62: 0 | S62: 0 | T62: 0 | U62: 0 | V62: 0 | W62: 0

Sheet Sale of Corn Prices
A1: Heading | B1: Sentence | C1: Total in Pounds | D1: Pounds | E1: Shillings | F1: Pence | G1: Corn | H1: Total Quarters Except 1 | I1: Total Bushels Except 1 | J1: Total Corn Cross-Check | K1: Total Corn Manorial Account | L1: Corn Quantity Error | M1: Quarters 0 | N1: Bushels 0 | O1: shilling a quarter 1 | P1: pence a quarter 1 | Q1: Quarters 1 | R1: Bushels 1 | S1: shilling a quarter 2 | T1: pence a quarter 2 | U1: Quarters 2 | V1: Bushels 2 | W1: shilling a quarter 3 | X1: pence a quarter 3 | Y1: Quarters 3 | Z1: Bushels 3 | AA1: shilling a quarter 4 | AB1: pence a quarter 4 | AC1: £ a quarter 1 | AD1: £ a quarter 2 | AE1: £ a quarter 3 | AF1: £ a quarter 4 | AG1: Quarters Sold | AH1: Weighted Average Price per Quarter | AI1: Non-Weighted Average Price per Quarter | AJ1: Corn lowercase
A2: Sale of corn | B2: The same render account for £2 12 shilling 6pence from 8 quarters 6 bushels of wheat sold, at 6 shilling a quarters. | C2: 2.62 | D2: 2 | E2: 12 | F2: 6 | G2: wheat | H2: 8 | I2: 6 | J2: 8.75 | K2: 8.75 | L2: 0 | M2: 8 | N2: 6 | O2: 6 | P2: 0 | AC2: 0.3 | AG2: 8.75 | AH2: 0.3 | AI2: 0.3 | AJ2: wheat
A3: Sale of corn | B3: 5 shilling 5pence from 1 quarters 2 bushels of curall sold, at 4 shilling 4pence a quarters. | C3: 0.27 | D3: 0 | E3: 5 | F3: 5 | G3: curall | H3: 1 | I3: 2 | J3: 1.25 | K3: 1.25 | L3: 0 | M3: 1 | N3: 2 | O3: 4 | P3: 4 | AC3: 0.21666667 | AG3: 1.25 | AH3: 0.21666667 | AI3: 0.21666667 | AJ3: curall
A4: Sale of corn | B4: £1 6 shilling 5pence from 11 quarters 3 bushels of dredge sold, at 2 shilling a quarters for 3 quarters 7 bushels, 2 shilling 4pence a quarters for 4 quarters, and 2 shilling 8pence a quarters for 3.5 quarters. | C4: 1.32 | D4: 1 | E4: 6 | F4: 5 | H4: 10.5 | I4: 7 | J4: 11.375 | K4: 11.375 | L4: 0 | M4: 11 | N4: 3 | O4: 2 | P4: 0 | Q4: 3 | R4: 7 | S4: 2 | T4: 4 | U4: 4 | V4: 0 | W4: 2 | X4: 8 | Y4: 3.5 | Z4: 0 | AC4: 0.1 | AD4: 0.11666667 | AE4: 0.13333333 | AG4: 11.375 | AH4: 0.11611722 | AI4: 0.11666667
A5: Sale of corn | B5: 1 shilling from .5 quarters of dredge sold at the audit. | C5: 0.05 | D5: 0 | E5: 1 | F5: 0 | H5: 5 | I5: 0 | J5: 5 | K5: 5 | L5: 0 | M5: 5 | N5: 0 | AC5: 0.01 | AG5: 5 | AH5: 0.01 | AI5: 0.01
A6: Sale of corn | B6: 2 shilling from 4 bushels of peas sold, at 6pence a bushels. | C6: 0.12 | D6: 0 | E6: 2 | F6: 6 | G6: peas | H6: 0 | I6: 4 | J6: 0.5 | K6: 0.5 | L6: 0 | M6: 0 | N6: 4 | AC6: 0.24 | AG6: 0.5 | AH6: 0.24 | AI6: 0.24 | AJ6: peas
A7: Sale of corn | B7: 2 shilling from 6 bushels of peas sold at the audit. | C7: 0.1 | D7: 0 | E7: 2 | F7: 0 | G7: peas | H7: 0 | I7: 6 | J7: 0.75 | K7: 0.75 | L7: 0 | M7: 0 | N7: 6 | AC7: 0.13333333 | AG7: 0.75 | AH7: 0.13333333 | AI7: 0.13333333 | AJ7: peas
A8: Sale of corn | B8: Total, £4 9 shilling 4pence | C8: 4.47 | D8: 4 | E8: 9 | F8: 4 | H8: 0 | I8: 0 | J8: 0 | K8: 0 | L8: 0 | M8: 0 | N8: 0 | AC8: inf | AG8: 0 | AH8: inf | AI8: inf
