Workbook

Sheet Brightwell Overview - Completed
A1: BRIGHTWELL OVERVIEW - COMPLETED | B1: Total in £ | C1: Error | D1: Note
A2: CASH ACCOUNT
A3: RECEIPTS
A4: Arrears total | B4: 25.6
A5: Rents of assize total | B5: 14.45
A6: Quittances total | B6: 3.7129167
A7: Defaults of rent total | B7: 3.7285417
A8: Defaults of rent through the pestilence total
A9: Cotlands defaults total
A10: Cotlands total
A11: Total of quittances and defaults of rent total
A12: Total of rents remaining clear total
A13: Farms total
A14: Annual recognizances total | B14: 0.09
A15: Issues of the Manor total | B15: 6.1333333
A16: Issues of the tenements in the lord's hands total
A17: Sale of labour services total
A18: Sale of corn total | B18: 57.695833
A19: Entry and marriage fines total
A20: Pleas & perquisites total
A21: Forfeited chattels total
A22: Farm of the demesne land total
A23: Total of all receipts (calculated here) | B23: =SUM(B5:B22)
A24: Total of all receipts (calculated here) incl arrears | B24: =SUM(B4:B22)
A25: Total recorded in the accounts excl. arrears | B25: 99.76 | C25: =B23-B25
A26: Total recorded in the accounts incl. arrears | B26: =B25+B4
A29: EXPENSES
A30: Cost of ploughs total | B30: 1.44
A31: Purchase of corn total | B31: 2.6920833
A32: Cost of carts and wagons total
A33: Cost of dairy total
A34: Purchase of stock total | B34: 8.2170833
A35: Sheepcote total
A36: Cost of buildings total
A37: Threshing total | B37: 0.65
A38: Barley expenses
A39: Expenses of the harvest total
A40: Necessary expenses
A41: Wages of the bailiff
A42: Steward's expenses total | B42: 5.8791667
A43: Annual fees
A44: Total of all expenses per account | B44: 26.89
A45: Total of all expenses (calculated here) | B45: 27.553958
A46: Total fixed investment | B46: 6.7989583
A47: Total Demesne fixed investment | B47: 1.3758333
A49: Owed by the reeve | B49: =B23-B45
A50: From accounts | B50: 26.89
A52: Allowances
A53: Cash deliveries | B53: 53.15
A54: Sum of the above | B54: =SUM(B52:B53)
A55: Total of all allowances and cash deliveries in accounts
A57: Net amount owed | B57: =B50-B54
A58: Net amount owed in accounts
A60: GRANGE ACCOUNT | B60: Total Production | D60: Value of total gross production in £ | E60: Value of total net production in £
A61: Grange | B61: qrs | C61: bus
A62: Wheat | B62: 154.4375 | E62: 29.838542
A63: Rye | B63: 73
A64: Dredge | B64: 33.125
A65: Curall
A66: Barley | B66: 150.9375 | E66: 20.200095
A67: Oats | B67: 19.5 | E67: 0
A68: Beans
A69: Peas
A70: Vetches
A71: Total value of gross production (sum of the above)
A72: Total value of net production
A73: Value of sales
A75: MILL ACCOUNT | B75: Total Production | D75: Total in £
A76: Issues of the mill | B76: qrs | C76: bus
A77: Wheat
A78: Oatmeal
A79: 1st grade malt
A80: 2nd grade malt
A81: Maslin
A82: Total value of production (sum of the above)
A83: Value of sales
A85: STOCK ACCOUNT
A86: Livestock | B86: Begin stock | C86: End stock | D86: Stockbuilding | F86: Value of stock in £ | G86: Value of stockbuilding
A87: Cart-horses | B87: 2 | C87: 3 | D87: 1 | F87: ='Stock'!K5*'Stock'!O5 | G87: =D87*'Stock'!O5
A88: Mares | B88: 1 | C88: 1 | D88: 0 | F88: ='Stock'!K6*'Stock'!O6 | G88: =D88*'Stock'!O6
A89: Plough horses | B89: 11 | C89: 0 | D89: -11 | F89: 0 | G89: -2.81
A90: Colts (2 years) | B90: 1 | C90: 0 | D90: -1 | F90: ='Stock'!K9*'Stock'!O9 | G90: =D90*'Stock'!O9
A91: Colts (2 years) | B91: 1 | C91: 0 | D91: -1 | F91: ='Stock'!K9*'Stock'!O9 | G91: =D91*'Stock'!O9
A92: Colts (1 year) | B92: 3 | C92: 3 | D92: 0 | F92: ='Stock'!K10*'Stock'!O10 | G92: =D92*'Stock'!O10
A93: Foals | D93: =C93-B93 | F93: ='Stock'!K11*'Stock'!O11 | G93: =D93*'Stock'!O11
A94: Oxen | B94: 31 | C94: 45 | D94: 14 | F94: ='Stock'!K12*'Stock'!O12 | G94: =D94*'Stock'!O12
A95: Bulls | B95: 1 | C95: 0 | D95: -1 | F95: 0 | G95: -0.67
A96: Cows | B96: 13 | C96: 16 | D96: 3 | F96: ='Stock'!K14*'Stock'!O14 | G96: =D96*'Stock'!O14
A97: Steers | B97: 6 | C97: 0 | D97: -6 | F97: ='Stock'!K15*'Stock'!O15 | G97: =D97*'Stock'!O15
A98: Bullocks | B98: 6 | C98: 6 | D98: 0 | F98: ='Stock'!K16*'Stock'!O16 | G98: =D98*'Stock'!O16
A99: Yearlings | B99: 6 | C99: 6 | D99: 0 | F99: ='Stock'!K17*'Stock'!O17 | G99: =D99*'Stock'!O17
A100: Calves | C100: 7 | D100: =C100-B100 | F100: 0.35 | G100: =D100*'Stock'!O18
A101: Wethers | D101: =C101-B101 | F101: ='Stock'!K19*'Stock'!O19 | G101: =D101*'Stock'!O19
A102: Rams | D102: =C102-B102 | F102: ='Stock'!K20*'Stock'!O20 | G102: =D102*'Stock'!O20
A103: Ewes | D103: =C103-B103 | F103: ='Stock'!K21*'Stock'!O21 | G103: =D103*'Stock'!O21
A104: Hoggs | D104: =C104-B104 | F104: ='Stock'!K22*'Stock'!O22 | G104: =D104*'Stock'!O22
A105: Lambs | D105: =C105-B105 | F105: ='Stock'!K23*'Stock'!O23 | G105: =D105*'Stock'!O23
A106: Boars | D106: =C106-B106 | F106: ='Stock'!K24*'Stock'!O24 | G106: =D106*'Stock'!O24
A107: Sows | B107: 3 | C107: 3 | D107: 0 | F107: ='Stock'!K25*'Stock'!O25 | G107: =D107*'Stock'!O25
A108: Pigs | B108: 36 | C108: 43 | D108: 7 | F108: 8.1686218 | G108: 1.3297756
...

Sheet Prices
A1: Meat & Dairy Prices
C2: 1301 | D2: 1302 | E2: Average
A3: Beef | B3: £ per lb | C3: 0.0033351854 | D3: 0.0032608538 | E3: =AVERAGE(C3:D3)
A4: Mutton | B4: £ per lb | C4: 0.0036593977 | D4: 0.0037125513 | E4: =AVERAGE(C4:D4)
A5: Pork | B5: £ per lb | C5: 0.0038431326 | D5: 0.0037574803 | E5: =AVERAGE(C5:D5)
A6: Cheese | B6: £ per lb | C6: 0.0055768754 | D6: 0.0056654898 | E6: =AVERAGE(C6:D6)
A7: Butter | B7: £ per lb | C7: 0.0036626221 | D7: 0.0035935077 | E7: =AVERAGE(C7:D7)
A8: Milk | B8: £ per gallon | C8: 0.0055768754 | D8: 0.0056654898 | E8: =AVERAGE(C8:D8)

Sheet Labour Rents

Sheet Overview
A1: BRIGHTWELL | B1: Total in £ | C1: Error | D1: Note
A2: CASH ACCOUNT
A3: RECEIPTS
A4: Arrears total
A5: Rents of assize total
A6: Quittances total
A7: Defaults of rent total
A8: Defaults of rent through the pestilence total
A9: Cotlands defaults total
A10: Cotlands total
A11: Total of quittances and defaults of rent total
A12: Total of rents remaining clear total
A13: Farms total
... A22: Farm of the demesne land total
A23: Total of all receipts (calculated here) | B23: =Receipts!F176
A24: Total of all receipts (calculated here) incl arrears | B24: =Receipts!F177
A25: Total recorded in the accounts excl. arrears | B25: =Receipts!F175 | C25: =B25-B23
A26: Total recorded in the accounts incl. arrears
A29: EXPENSES
A30: Cost of ploughs total
A31: Purchase of corn total
A32: Cost of carts and wagons total
A33: Cost of dairy total
A34: Purchase of stock total
A35: Sheepcote total
A36: Cost of buildings total
A37: Threshing total
A38: Barley expenses
A39: Expenses of the harvest total
... A43: Annual fees
A44: Total of all expenses per account | B44: =Expenses!F124
A45: Total of all expenses (calculated here) | B45: =Expenses!F125
A46: Total fixed investment | B46: =Expenses!F126
A47: Total Demesne fixed investment | B47: =Expenses!F127
A49: Owed by the reeve
A50: From accounts
A52: Allowances
A53: Cash deliveries
A54: Sum of the above
A55: Total of all allowances and cash deliveries in accounts
A57: Net amount owed
A58: Net amount owed in accounts
A60: GRANGE ACCOUNT | B60: Total Production
A61: Grange | B61: qrs | E61: Value of total gross production in £ | F61: Value of total net production in £
A62: wheat | B62: ='Issues of the Grange'!B2 | E62: ='Issues of the Grange'!I2 | F62: ='Issues of the Grange'!O13
A63: rye | B63: ='Issues of the Grange'!B3 | E63: ='Issues of the Grange'!I3 | F63: ='Issues of the Grange'!O14
A64: barley | B64: ='Issues of the Grange'!B4 | E64: ='Issues of the Grange'!I4 | F64: ='Issues of the Grange'!O15
A65: dredge | B65: ='Issues of the Grange'!B5 | E65: ='Issues of the Grange'!I5 | F65: ='Issues of the Grange'!O16
A66: oats | B66: ='Issues of the Grange'!B6 | E66: ='Issues of the Grange'!I6 | F66: ='Issues of the Grange'!O17
A67: Total value of gross production (sum of the above) | E67: =SUM(E62:E66)
A68: Total value of net production | E68: =SUM(F62:F66)
A69: Value of sales | E69: =Receipts!F112+Receipts!F102
A71: MILL ACCOUNT
A72: Issues of the mill
A73: Wheat
A74: Oatmeal
A75: 1st grade malt
A76: 2nd grade malt
A77: Maslin
A78: Total value of production (sum of the above)
A79: Value of sales
A81: STOCK ACCOUNT
A82: Livestock | B82: Sales value in £
A83: Cart-horses | B83: =Stock!R5
A84: Mares | B84: =Stock!R6
A85: Plough horses | B85: =Stock!R7
A86: Colts (2 years) | B86: =Stock!R8
A87: Colts (2 years) | B87: =Stock!R9
A88: Colts (1 year) | B88: =Stock!R10
A89: Foals | B89: =Stock!R11
A90: Oxen | B90: =Stock!R12
A91: Bulls | B91: =Stock!R13
A92: Cows | B92: =Stock!R14
A93: Steers | B93: =Stock!R15
A94: Bullocks | B94: =Stock!R16
... A109: Total value of stock (sum of the above) | B109: =Stock!R31
A110: Total value of production
A111: Value of sales
A113: Wool | B113: Value of production at sales prices £
A114: Fleeces | B114: =Stock!T34
A115: Coarse wool | B115: =Stock!T35
A116: Lamb's wool | B116: =Stock!T36
A117: Wool locks | B117: =Stock!T37
A118: Wool sold at shearing | B118: =Stock!T38
A119: Total value of production (sum of the above) | B119: =Stock!T39
A120: Value of sales | B120: =Stock!T40
A122: Hides | B122: Value of production at sales prices £
A123: Ox hides | B123: =Stock!T43
A124: Cow hides | B124: =Stock!T44
A125: Mare hides | B125: =Stock!T45
A126: Steer hides | B126: =Stock!T46
A127: Yearling Calf hides | B127: =Stock!T47
A128: Calf hides | B128: =Stock!T48
A129: Pig hides | B129: =Stock!T49
A130: Wether woolskins | B130: =Stock!T50
A131: Ram woolskins | B131: =Stock!T51
A132: Ewe woolskins | B132: =Stock!T52
A133: Hogg woolskins | B133: =Stock!T53
A134: Woolskins (total) | B134: =Stock!T54
... A142: Shorn skins | B142: =Stock!T62
...

Sheet Receipts
A1: BRIGHTWELL
A2: Heading | B2: £ | C2: s | D2: d | F2: Total in £ | G2: Error | H2: Notes
A3: Arrears | B3: 25 | C3: 11 | D3: 11 | F3: 25.6 | H3: Roginald de Lynham, bailiff, and Richard E1y3, reeve, render account for £25 11 shilling 11pence of arrears from the last account.
A4: Arrears | B4: 0 | C4: 0 | D4: 0 | F4: 0 | H4: All delivered to Sir Geoffrey, treasurer of Wolvesey, and they are quit.
A5: Arrears | F5: 25.6 | G5: =F5-F3 | H5: Total
A7: Rents | B7: 3 | C7: 0 | D7: 2 | F7: 3.01 | H7: The same render account for £3 2pence for all rents of assize at Christmas.
A8: Rents | B8: 3 | C8: 0 | D8: 2 | F8: 3.01 | H8: £3 2pence at Easter (22 April).
A9: Rents | B9: 3 | C9: 0 | D9: 2 | F9: 3.01 | H9: £3 2pence at the Nativity of the blessed John (24 June).
A10: Rents | B10: 5 | C10: 8 | D10: 4.5 | F10: 5.42 | H10: £5 8 shilling 4.5pence at Michaelmas (29 September).
A11: Rents | B11: 14 | C11: 8 | D11: 10.5 | F11: 14.44 | H11: Total, £14 8 shilling 10.5pence
A12: Rents | F12: 14.45 | G12: 0.01 | H12: Total
A14: Quittances | B14: 0 | C14: 5 | D14: 0 | F14: 0.25 | H14: In quittance of 1 reeve for the year 5 shilling.
A15: Quittances | B15: 0 | C15: 2 | D15: 6 | F15: 0.12 | H15: 1 smith working the iron of 3 ploughs for the year 2 shilling 6pence.
A16: Quittances | B16: 0 | C16: 2 | D16: 0 | F16: 0.1 | H16: 1 overseer of the harvest sowing the land, and keeping the meadow, pasture and corn for the year 2 shilling 24..
A17: Quittances | B17: 0 | C17: 2 | D17: 2 | F17: 0.11 | H17: 1 swineherd for the year 2 shilling 2pence.
A18: Quittances | B18: 0 | C18: 15 | D18: 2 | F18: 0.76 | H18: 7 ploughmen for the year 15 shilling 2pence, or 2 shilling 2pence each.
A19: Quittances | B19: 0 | C19: 15 | D19: 10.5 | F19: 0.79 | H19: 8 virgaters in Brightwell working every other day each week, apart from Saturdays and celebrated feasts, from Michaelmas until the feast of the Apostles Peter and Paul (29 June), that is, for 3 terms, 15 shilling, or 1 shilling 10.5pence each.
A20: Quittances | B20: 0 | C20: 2 | D20: 4 | F20: 0.12 | H20: the same working every day except Saturdays from the said feast of the Apostles Peter and Paul until Michaelmas 2 shilling 4pence, or 3'/ 4. each, and know that there are appointed here 8 half-virgaters where before there were appointed 10, because 2 half-virgates of land were made into 1 whole virgate of land which John Herberd holds by fine made in the steward's court which he answers for from now on and works with the other virgaters of land and is the fifth virgater of land in Brightwell.
A21: Quittances | B21: 0 | C21: 14 | D21: 1 | F21: 0.7 | H21: 13 virgaters of land in Sotwell working every other day each week, except feast-days and Saturdays, for the aforesaid time, 14 shilling 1pence, or 1 shilling Ipence each.
A22: Quittances | B22: 0 | C22: 9 | D22: 4 | F22: 0.47 | H22: 7 virgaters in Mackney working every day apart from Saturdays for the aforesaid time 9 shilling 4pence, or 1 shilling 4pence each.
A23: Quittances | B23: 0 | C23: 5 | D23: 5 | F23: 0.27 | H23: 5 virgaters in Brightwell, to whom the fifth should be added here, working in the same way for the same time 5 shilling 5pence, or 1 shilling1pence each.
A24: Quittances | B24: 0 | C24: 0 | D24: 5.5 | F24: =B24+C24/20+D24/240 | H24: 1 tenant working 2 days a week, that is, Monday and Friday, for the same time, 5.5pence
A25: Quittances | B25: 3 | C25: 13 | D25: 7.5 | F25: 3.68 | H25: Total, £3 13 shilling 7.5pence
A26: Quittances | F26: =SUM(F14:F24) | G26: =F26-F25 | H26: Total
A28: Defaults of rent | B28: 0 | C28: 0 | D28: 3.25 | F28: 0.01 | H28: In default of the land of Andrew de Walingeford' from the old land to the castle ditch 3.25pence
A29: Defaults of rent | D29: 3.75 | F29: =B29+C29/20+D29/240 | H29: Total, 3.75pence
A31: Defaults of rent | B31: 3 | C31: 13 | D31: 11.25 | F31: 3.7 | H31: Total of both, £3 13 shilling 11.25pence
A32: Defaults of rent | F32: =F29+F26 | G32: =F32-F31 | H32: Total
A34: Total of rents remaining | B34: 10 | C34: 14 | D34: 11.25 | F34: 10.75 | H34: Total of rents remaining, £10 14 shilling 11.25pence
A35: Total of rents remaining | F35: 10.75 | G35: =F35-F34 | H35: Total
A37: Annual recognizance | B37: 0 | C37: 0 | D37: 4 | F37: 0.02 | H37: The same render account for 4pence from Thomas Clericus for annual recognizance whilst he wishes to reside within the lord's liberty.
A38: Annual recognizance | B38: 0 | C38: 0 | D38: 6 | F38: 0.03 | H38: 6pence from John Bordel' for the same.
A39: Annual recognizance | B39: 0 | C39: 0 | D39: 10 | F39: 0.04 | H39: nothing from John Longus because he is sold outside the tithing by William de Mackeney his lorpence Total, 10pence
A40: Annual recognizance | F40: 0.09 | G40: 0.05 | H40: Total
A43: Issues of the manor | B43: 0 | C43: 13 | D43: 4 | F43: 0.67 | H43: The same render account for 13 shilling 4pence from the pasturage in the east field sold.
A44: Issues of the manor | B44: 0 | C44: 7 | D44: 1.5 | F44: 0.36 | H44: 7 shilling 1.5pence from pannage of pigs at Martinmas (11 November).
A45: Issues of the manor | B45: 0 | C45: 2 | D45: 0 | F45: 0.1 | H45: 2 shilling from the pasturage in the croft sold, which formerly belonged to William le Fisscher', because it is in the lord's hands through the death of Thomas de Mack' who held that tenement of the lord after the decease of the said William.
A46: Issues of the manor | B46: 0 | C46: 2 | D46: 6.5 | F46: 0.13 | H46: 2 shilling 6.5pence from 29 rowen (relucro) cheeses sold by warrant (per man').
A47: Issues of the manor | B47: 0 | C47: 3 | D47: 5 | F47: 0.17 | H47: 3 shilling .5pence from 36.5 gallons of milk sold for the lambs, at the price made clear.
A48: Issues of the manor | B48: 1 | C48: 18 | D48: 9 | F48: 1.94 | H48: £1 18 shilling 9pence from 117 cheeses, weighing 3.5 weys 41b, sold at 11 shilling a wey.
A49: Issues of the manor | B49: 0 | C49: 5 | D49: 4 | F49: 0.27 | H49: 5 shilling 4pence from 16 cloves of butter sold, at 4pence a clove.
A50: Issues of the manor | B50: 0 | C50: 0 | D50: 4 | F50: 0.02 | H50: 4pence from 2 capons from the rent of William le Fisscher' sold.
A51: Issues of the manor | B51: 0 | C51: 8 | D51: 7 | F51: 0.43 | H51: 8 shilling 7pence from 103 cocks and hens from churchscot at Martinmas sold.
A52: Issues of the manor | B52: 0 | C52: 1 | D52: 2 | F52: 0.06 | H52: 1 shilling 2pence from 350 eggs sold, received according to custom at Easter.
A53: Issues of the manor | B53: 0 | C53: 1 | D53: 2 | F53: 0.06 | H53: 1 shilling 2pence from the hide sold of 1 mare from the mill dead from murrain.
A54: Issues of the manor | B54: 0 | C54: 4 | D54: 10 | F54: 0.24 | H54: 4 shilling 10pence from the carcass of 1 cow dead from murrain about the feast of St Nicholas (6 December) sold together with the hide.
... A62: Issues of the manor | B62: 0 | C62: 3 | D62: 4 | F62: 0.17 | H62: 3 shilling 4pence from 10 acres of stubble sold.
A63: Issues of the manor | B63: 0 | C63: 1 | D63: 1 | F63: =B63+C63/12+D63/20 | H63: 1 shilling 1 pence from dairy produce sold at the audit.
A64: Issues of the manor | B64: 6 | C64: 0 | D64: 4.5 | F64: 6.02 | H64: Total, £6 4.5pence
A65: Issues of the manor | F65: =SUM(F43:F63) | G65: =F65-F64 | H65: Total
A67: Sale of plough-horses | B67: 0 | C67: 9 | D67: 0 | F67: 0.45 | H67: The same render account for 9 shilling from 2 mares sold to Henry Horlok by warrant.
A68: Sale of plough-horses | B68: 0 | C68: 6 | D68: 0 | F68: 0.3 | H68: 6 shilling from 1 mare sold to William le Frensch' by warrant.
A69: Sale of plough-horses | B69: 0 | C69: 4 | D69: 6 | F69: 0.23 | H69: 4 shilling 6pence from 1 mare sold to William ad Aqua by warrant.
A70: Sale of plough-horses | B70: 0 | C70: 6 | D70: 0 | F70: 0.3 | H70: 6 shilling from 1 mare sold to Thomas de Mack' by loan (per acommod').
A71: Sale of plough-horses | B71: 0 | C71: 4 | D71: 6 | F71: 0.23 | H71: 4 shilling 6pence from 1 mare sold to William atte Lan' by loan.
A72: Sale of plough-horses | B72: 0 | C72: 3 | D72: 6 | F72: 0.17 | H72: 3 shilling 6pence from 1 mare sold to Richard Cullebol' by loan.
A73: Sale of plough-horses | B73: 0 | C73: 8 | D73: 0 | F73: 0.4 | H73: 8 shilling from 1 mare to Stephen Godefray by loan.
A74: Sale of plough-horses | B74: 0 | C74: 3 | D74: 0 | F74: 0.15 | H74: 3 shilling from 1 mare sold to Thomas le Venour by loan.
A75: Sale of plough-horses | B75: 0 | C75: 5 | D75: 0 | F75: 0.25 | H75: 5 shilling from 1 mare sold to Robert le Mere by loan.
A76: Sale of plough-horses | B76: 0 | C76: 6 | D76: 8 | F76: 0.33 | H76: 6 shilling 8pence from 1 mare sold to Henry Deme de Hakeborne.
A77: Sale of plough-horses | B77: 2 | C77: 16 | D77: 2 | F77: 2.81 | H77: Total, £2 16 shilling 2pence
A78: Sale of plough-horses | F78: 2.81 | G78: 0 | H78: Total
A80: Sale of pigs | B80: 1 | C80: 3 | D80: 4 | F80: 1.17 | H80: The same render account for £1 3 shilling 4pence from 8 pigs over a year old sold to Jordan le Carpenter, at 4 shilling 2pence each.
A81: Sale of pigs | B81: 0 | C81: 16 | D81: 0 | F81: 0.8 | H81: 16 shilling from 4 pigs over a year old sold to Richard Beye and John Herbcrd, at the price made clear.
A82: Sale of pigs | B82: 0 | C82: 8 | D82: 0 | F82: 0.4 | H82: 8 shilling from 2 pigs over a year old sold to Walter le Gol.
A83: Sale of pigs | B83: 0 | C83: 7 | D83: 0 | F83: 0.35 | H83: 7 shilling from 2 pigs over a year old sold to Robert Sangar.
A84: Sale of pigs | B84: 0 | C84: 7 | D84: 0 | F84: 0.35 | H84: 7 shilling from 2 pigs over a year old sold to Robert atte Nywerewe.
A85: Sale of pigs | B85: 0 | C85: 3 | D85: 6 | F85: 0.17 | H85: 3 shilling 6pence from 1 pig over a year old sold to Thomas de Fonte.
A86: Sale of pigs | B86: 0 | C86: 3 | D86: 8 | F86: 0.18 | H86: 3 shilling 8pence from 1 pig over a year old sold to Thomas Kepe.
A87: Sale of pigs | B87: 0 | C87: 7 | D87: 4 | F87: 0.37 | H87: 7 shilling 4pence from 2 pigs over a year old sold to William Beye.
A88: Sale of pigs | B88: 0 | C88: 3 | D88: 0 | F88: 0.15 | H88: 3 shilling from 1 pig over a year old sold to Simon Faber.
A89: Sale of pigs | B89: 0 | C89: 10 | D89: 0 | F89: 0.5 | H89: 10 shilling from 3 pigs over a year old sold to Richard Beneyt of Wallingford.
A90: Sale of pigs | B90: 0 | C90: 0 | D90: 5 | F90: =B90+C90/20+D90/240 | H90: 5pence from 1 sick hogget sold
A91: Sale of pigs | B91: 4 | C91: 19 | D91: 3 | F91: 4.96 | H91: Total, £4 19 shilling 3pence
A92: Sale of pigs | F92: =SUM(F80:F90) | G92: =F92-F91 | H92: Total
A95: Sale of corn | B95: 29 | C95: 16 | D95: 9.25 | F95: 29.84 | H95: The same render account for £29 16 shilling 9.25pence from 105 quarters 2.5 bushels of wheat sold, at 5 shilling 8pence a qr.
A96: Sale of corn | B96: 4 | C96: 9 | D96: 10.25 | F96: =B96+C96/20+D96/240 | H96: £4 9 shilling 10.25pence from 28 quarters 3 bushels of rye sold, at 3 shilling 2pence a qr.
A97: Sale of corn | B97: 20 | C97: 16 | D97: 0.75 | F97: =B97+C97/20+D97/240 | H97: £20 16 shilling .75pence from 118 quarters of barley sold, at 3 shilling 6pence a qr.
A98: Sale of corn | B98: 2 | C98: 8 | D98: 9 | F98: 2.44 | H98: £2 8 shilling 9pence from 16 quarters 2 bushels of dredge sold, at 3 shilling a qr, 2 shilling 4.5pence from 6 bushels of rye sold at the audit.
A99: Sale of corn | B99: 0 | C99: 1 | D99: 9 | F99: 0.09 | H99: 1 shilling 9pence from .5 qr of barley sold at the audit.
A100: Sale of corn | B100: 0 | C100: 0 | D100: 8 | F100: 0.03 | H100: 8pence from .5 qr of vetches sold at the audit.
A101: Sale of corn | B101: 57 | C101: 16 | D101: 2.75 | F101: 57.81 | H101: Total, £57 16 shilling 2.75pence
A102: Sale of corn | F102: =SUM(F95:F100) | G102: =F102-F101 | H102: Total
A104: Sale of the mill's corn | B104: 2 | C104: 17 | D104: 4 | F104: 2.87 | H104: The same render account for £2 17 shilling 4pence from 13 quarters .5 bushels of wheat from the mill sold, at 4 shilling a qr for 4 quarters, 4 shilling 4pence a qr for 3 quarters, and 4 shilling 8pence a qr for 6 quarters .5 bushels.
A105: Sale of the mill's corn | B105: 2 | C105: 2 | D105: 11 | F105: 2.15 | H105: £2 2 shilling 11pence from 17.5 quarters of maslin sold, at 2 shilling a qr for 5 quarters 5 bushels, and 2 shilling 8pence a qr for 11 quarters 7 bushels.
A106: Sale of the mill's corn | B106: 1 | C106: 3 | D106: 2 | F106: 1.16 | H106: £1 3 shilling 2pence from 5 quarters 2 bushels of coarse-ground corn from the mill sold, at 4 shilling a qr for 2 quarters, and 4 shilling 8pence a qr for 3 quarters 2 bushels.
A107: Sale of the mill's corn | B107: 3 | C107: 9 | D107: 3 | F107: 3.46 | H107: £3 9 shilling 3pence from 22.5 quarters of second-grade malt sold, at 3 shilling a qr for 12 quarters, and 3 shilling 2pence a qr for 10.5 quarters.
A108: Sale of the mill's corn | B108: 0 | C108: 5 | D108: 4 | F108: 0.27 | H108: 5 shilling 4pence from eels sold at various times.
A109: Sale of the mill's corn | B109: 0 | C109: 0 | D109: 0 | F109: 0 | H109: Note that there was no more from the issue of the mill this year because for 4 weeks after Christmas and for 2 weeks in Lent it was idle due to torrents.
A110: Sale of the mill's corn | B110: 0 | C110: 0 | D110: 3 | F110: 0.01 | H110: And for 3pence from 1 bushels of maslin sold at the audit.
A111: Sale of the mill's corn | B111: 9 | C111: 18 | D111: 3 | F111: 9.91 | H111: Total, £9 18 shilling 3pence
A112: Sale of the mill's corn | F112: 9.92 | G112: 0.01 | H112: Total
A114: Fixed payments, entry and marriage fines | B114: 1 | C114: 6 | D114: 8 | F114: 1.33 | H114: The same render account for £1 6 shilling 8pence from fixed payments at the 2 hundred-courts for tithingpenny.
A115: Fixed payments, entry and marriage fines | B115: 2 | C115: 13 | D115: 4 | F115: 2.67 | H115: £2 13 shilling 4pence from the fine of Roger ate Grove to have Agnes, relict of Henry Wys, with .5 virgate of customary land.
A116: Fixed payments, entry and marriage fines | B116: 0 | C116: 13 | D116: 4 | F116: 0.67 | H116: 13 shilling 4pence from the fine of John G 'third to recover a certain cottage which he sold to John Cocus without licence.
A117: Fixed payments, entry and marriage fines | B117: 4 | C117: 13 | D117: 4 | F117: 4.67 | H117: Total, £4 13 shilling 4pence
A118: Fixed payments, entry and marriage fines | F118: 4.67 | G118: 0 | H118: Total
A120: Perquisites | B120: 0 | C120: 1 | D120: 0 | F120: 0.05 | H120: The same render account for 1 shilling, from Geoffrey de Brighwalton for release from his suit at 2 views.
A121: Perquisites | B121: 0 | C121: 1 | D121: 6 | F121: 0.08 | H121: 1 shilling from Osbert de Nutle fort he same, 6pence from Emma ate Strem’ for trespass of pasture, 6pence from John atte Strem’ for trespass in the curia.
A122: Perquisites | B122: 0 | C122: 0 | D122: 6 | F122: 0.03 | H122: 6pence from John ate Street' William le King3 for trespass with his sheep in the pasture.
...

Sheet Expenses
A1: BRIGHTWELL RECEIPTS
A2: Heading | B2: £ | C2: s | D2: d | F2: Total in £ | G2: Error | H2: Notes | J2: Fixed investment | K2: Demesne fixed investment
A3: Cost of ploughs | B3: 0 | C3: 1 | D3: 2 | F3: 0.06 | H3: In 3 pieces of iron bought for the ploughs 1 shilling 2pence. | J3: =F3 | K3: =J3
A4: Cost of ploughs | B4: 0 | C4: 4 | D4: 10 | F4: 0.24 | H4: 6 pieces of steel bought for the same 4 shilling 10pence. | J4: =F4 | K4: =J4
A5: Cost of ploughs | B5: 0 | C5: 1 | D5: 6 | F5: 0.08 | H5: 2 new ploughshares bought for the ploughs with the repair of the same 1 shilling 6pence. | J5: =F5 | K5: =J5
A6: Cost of ploughs | B6: 0 | C6: 1 | D6: 9 | F6: 0.09 | H6: 9 wheels bought for ploughs 1 shilling 9pence. | J6: =F6 | K6: =J6
A7: Cost of ploughs | B7: 0 | C7: 0 | D7: 10.5 | F7: 0.04 | H7: withies bought for the draught-chains (hart') of the ploughs 10.5pence. | J7: =F7 | K7: =J7
A8: Cost of ploughs | B8: 0 | C8: 4 | D8: 0 | F8: 0.2 | H8: stipend of the smith working the iron of 2 ploughs for the year 4 shilling, because 1 acre of wheat was removed from his stipend, and he quits .5 virgate of land through the iron for 2 ploughs. | J8: =F8 | K8: =J8/2
A9: Cost of ploughs | B9: 0 | C9: 0 | D9: 8 | F9: =B9+C9/20+D9/240 | H9: 1 new wheelbarrow bought 8pence | J9: =F9 | K9: =J9
A10: Cost of ploughs | B10: 0 | C10: 14 | D10: 9.5 | F10: =B10+C10/20+D10/240 | H10: Total, 14 shilling 9.5pence
A11: Cost of ploughs | F11: 1.44 | G11: 0.71 | H11: Total
A13: Carts and ironwork | B13: 0 | C13: 1 | D13: 4 | F13: 0.07 | H13: In 2 new horse-collars bought 1 shilling 4pence. | J13: =F13 | K13: =J13
A14: Carts and ironwork | B14: 0 | C14: 1 | D14: 4 | F14: 0.07 | H14: 1 hemp rope bought for tethering the cart at Reading 1 shilling 4pence. | J14: =F14 | K14: =J14
A15: Carts and ironwork | B15: 0 | C15: 0 | D15: 5 | F15: 0.02 | H15: 1 pair of traces bought there 5pence. | J15: =F15 | K15: =J15
A16: Carts and ironwork | B16: 0 | C16: 1 | D16: 8.75 | F16: 0.09 | H16: fitting 1 cart with axles, with axles, white leather, clouts and nails bought for the year, 1 shilling 8.75pence. | J16: =F16 | K16: =J16
A17: Carts and ironwork | B17: 0 | C17: 0 | D17: 2 | F17: 0.01 | H17: frets bought for the cart 2pence. | J17: =F17 | K17: =J17
A18: Carts and ironwork | B18: 0 | C18: 0 | D18: 1 | F18: 0 | H18: 1 metal plate bought for the cart 1pence. | J18: =F18 | K18: =J18
A19: Carts and ironwork | B19: 0 | C19: 0 | D19: 3 | F19: 0.01 | H19: 1 leather halter bought for I cart-horse 3pence. | J19: =F19 | K19: =J19
A20: Carts and ironwork | B20: 0 | C20: 3 | D20: 0 | F20: =B20+C20/20+D20/240 | H20: shoeing 2 cart-horses for the year, for all necessaries which pertain to their provision, together with their removal and fastening, 3 shilling | J20: =F20 | K20: =J20
A21: Carts and ironwork | B21: 0 | C21: 8 | D21: 3.75 | F21: =B21+C21/20+D21/240 | H21: Total, 8 shilling 3.75pence
A22: Carts and ironwork | F22: =SUM(F13:F20) | G22: 0.27 | H22: Total
A24: Small necessaries | B24: 0 | C24: 0 | D24: 0 | F24: 0 | H24: In 12 dishes, 8 pans, 12 saucers. [price ommitted] | J24: =F24 | K24: =J24
A25: Small necessaries | B25: 0 | C25: 1 | D25: 0 | F25: 0.05 | H25: 12 cart-loads of wood felled in the wood of Wargrave 1 shilling. | K25: =J25
A26: Small necessaries | B26: 0 | C26: 0 | D26: 11 | F26: 0.05 | H26: 2.5 bushels of salt bought for the pease pottage of the manorial servants 11pence. | K26: =J26
A27: Small necessaries | B27: 0 | C27: 2 | D27: 6.5 | F27: 0.13 | H27: 4 new sacks bought for corn 2 shilling 6.5pence. | J27: =F27 | K27: =J27
A28: Small necessaries | B28: 0 | C28: 0 | D28: 4 | F28: 0.02 | H28: 1 basket (sporta) bought 4pence. | J28: =F28 | K28: =J28
A29: Small necessaries | B29: 0 | C29: 0 | D29: 7 | F29: 0.03 | H29: castrating 12 male and spaying 9 female piglets 7pence. | K29: =J29
A30: Small necessaries | B30: 0 | C30: 1 | D30: 1.5 | F30: 0.06 | H30: 1.5 bushels of oatmeal bought for pease pottage for the year, 1 shilling 1.5pence this year. | K30: =J30
A31: Small necessaries | B31: 0 | C31: 0 | D31: 2.5 | F31: 0.01 | H31: withies bought for penning oxen in the byre in winter 2.5pence. | J31: =F31 | K31: =J31
A32: Small necessaries | B32: 0 | C32: 0 | D32: 1 | F32: 0 | H32: 1 piece of iron made for a certain shovel out of the demesne iron 1pence. | J32: =F32 | K32: =J32
A33: Small necessaries | B33: 0 | C33: 2 | D33: 6 | F33: 0.12 | H33: hiring a certain man to clean the inside of 2 tuns for putting cider in and moreover hooping them anew and hooping anew 5 tubs by piece-work for 10 days 2 shilling 6pence. | K33: =J33
A34: Small necessaries | B34: 0 | C34: 0 | D34: 7.5 | F34: 0.03 | H34: hiring a certain roofer for 2.5 days to roof over the enclosure between the bishop's chamber and chapel 7.5pence. | K34: =J34
A35: Small necessaries | B35: 0 | C35: 0 | D35: 1 | F35: =B35+C35/20+D35/240 | H35: small nails for fastening laths to the walls of the byre 1pence | J35: =F35 | K35: =J35
A36: Small necessaries | B36: 0 | C36: 11 | D36: 0 | F36: =B36+C36/20+D36/240 | H36: Total, 11 shilling
A37: Small necessaries | F37: =SUM(F24:F35) | G37: =F37-F36 | H37: Total
A39: Threshing and winnowing | B39: 0 | C39: 3 | D39: 2 | F39: 0.16 | H39: In threshing 26 quarters of barley 3 shilling 2pence, at 1.5pence a qr.
A40: Threshing and winnowing | B40: 0 | C40: 0 | D40: 5 | F40: 0.02 | H40: winnowing the said corn 5pence, at 1pence per 5 quarters.
A41: Threshing and winnowing | B41: 0 | C41: 7 | D41: 5.5 | F41: 0.37 | H41: wages of John Touresmere overseeing the threshing and winnowing of corn at various times 7 shilling 5.5pence, taking 1.5pence a day.
A42: Threshing and winnowing | B42: 0 | C42: 2 | D42: 0 | F42: =B42+C42/20+D42/240 | H42: stipend of the same here 2 shilling, because he takes the rest elsewhere up to 10 shilling
A43: Threshing and winnowing | B43: 0 | C43: 13 | D43: 1.5 | F43: =B43+C43/20+D43/240 | H43: Total, 13 shilling 1.5pence
A44: Threshing and winnowing | F44: =SUM(F39:F42) | G44: =F44-F43 | H44: Total
A46: Purchase of corn | B46: 1 | C46: 15 | D46: 1 | F46: 1.75 | H46: In 7 quarters 6 bushels of wheat bought for sowing £1 15 shilling 1pence, at 4 shilling 8pence a qr for 4.5 quarters, and 4 shilling 4pence a qr for 3 quarters 2 bushels.
A47: Purchase of corn | B47: 0 | C47: 17 | D47: 8.5 | F47: 0.89 | H47: 10 quarters 5 bushels of oats bought for fodder for the year 17 shilling 8.5pence, at 1 shilling 8pence a qr.
A48: Purchase of corn | B48: 0 | C48: 1 | D48: 0.5 | F48: =B48+C48/20+D48/240 | H48: 5 bushels of beans bought for pigs 1 shilling .5pence
A49: Purchase of corn | B49: 2 | C49: 13 | D49: 10 | F49: 2.69 | H49: Total, £2 13 shilling 10pence
A50: Purchase of corn | F50: =SUM(F46:F48) | G50: =F50-F49 | H50: Total
A52: Purchase of stock | B52: 0 | C52: 14 | D52: 0 | F52: 0.7 | H52: In 1 ox bought for the ploughs at Warbewey 14 shilling.
A53: Purchase of stock | B53: 0 | C53: 14 | D53: 6 | F53: 0.72 | H53: 1 ox bought for the same at Abingdon 14 shilling 6pence.
A54: Purchase of stock | B54: 0 | C54: 16 | D54: 0 | F54: 0.8 | H54: 1 ox bought there for the same 16 shilling.
A55: Purchase of stock | B55: 0 | C55: 12 | D55: 6 | F55: 0.62 | H55: 1 ox bought there for the same 12 shilling 6pence.
A56: Purchase of stock | B56: 1 | C56: 4 | D56: 0.5 | F56: =B56+C56/20+D56/240 | H56: 2 oxen bought there for the same £1 4 shilling .5pence.
A57: Purchase of stock | B57: 0 | C57: 15 | D57: 0 | F57: =B57+C57/20+D57/240 | H57: 1 ox bought there for the same 15 shilling.
A58: Purchase of stock | B58: 0 | C58: 14 | D58: 6 | F58: =B58+C58/20+D58/240 | H58: 1 ox bought there for the same 14 shilling 6pence.
A59: Purchase of stock | B59: 0 | C59: 15 | D59: 0 | F59: =B59+C59/20+D59/240 | H59: 1 ox bought there for the same 15 shilling.
A60: Purchase of stock | B60: 0 | C60: 11 | D60: 6 | F60: =B60+C60/20+D60/240 | H60: 1 ox bought there for the same 11 shilling 6pence.
A61: Purchase of stock | B61: 0 | C61: 12 | D61: 0 | F61: =B61+C61/20+D61/240 | H61: 1 ox bought there for the same 12 shilling.
A62: Purchase of stock | B62: 0 | C62: 15 | D62: 6 | F62: =B62+C62/20+D62/240 | H62: 1 ox bought there for the same 15 shilling 6pence
A63: Purchase of stock | B63: 8 | C63: 4 | D63: 6.5 | F63: 8.23 | H63: Total, £8 4 shilling 6.5pence
A64: Purchase of stock | F64: =SUM(F52:F62) | G64: =F64-F63 | H64: Total
A66: Cost of the dairy | B66: 0 | C66: 1 | D66: 4 | F66: 0.07 | H66: In 4 bushels of salt bought for the dairy 1 shilling 4pence. | J66: =F66 | K66: =J66
A67: Cost of the dairy | B67: 0 | C67: 0 | D67: 6 | F67: 0.03 | H67: 2 buckets bought for the dairy 6pence. | J67: =F67 | K67: =J67
A68: Cost of the dairy | B68: 0 | C68: 0 | D68: 6 | F68: 0.03 | H68: 2 ells of canvas bought for making cheese cloth therefrom 6pence. | J68: =F68 | K68: =J68
A69: Cost of the dairy | B69: 0 | C69: 0 | D69: 2 | F69: 0.01 | H69: earthenware pans bought for the same 2pence. | J69: =F69 | K69: =J69
A70: Cost of the dairy | B70: 0 | C70: 0 | D70: 2 | F70: =B70+C70/20+D70/240 | H70: 1 cheese mould bought 2pence | J70: =F70 | K70: =J70
A71: Cost of the dairy | B71: 0 | C71: 2 | D71: 8 | F71: =B71+C71/20+D71/240 | H71: Total, 2 shilling 8pence
A72: Cost of the dairy | F72: =SUM(F66:F70) | G72: =F72-F71 | H72: Total
A74: Cost of the mill | B74: 0 | C74: 16 | D74: 0.75 | F74: =B74+C74/20++D74/240 | H74: In 1 mare bought for the mill 16 shilling .75pence. | J74: =F74
A75: Cost of the mill | B75: 2 | C75: 13 | D75: 9 | F75: 2.69 | H75: 1 millstone lying at the said mill bought £2 13 shilling 9pence. | J75: =F75
A76: Cost of the mill | B76: 0 | C76: 0 | D76: 8 | F76: 0.03 | H76: customary payment to the vill of Wallingford for buying the said stone within the vill 8pence. | J76: =F76
A77: Cost of the mill | B77: 0 | C77: 0 | D77: 7 | F77: 0.03 | H77: 7 oaks felled at la Wassch' for the bridge of the mill of Wallingford 7pence. | J77: =F77
A78: Cost of the mill | B78: 0 | C78: 0 | D78: 6.5 | F78: 0.03 | H78: sawing the said oaks crosswise for carrying (ducend') 6.5pence. | J78: =F78
A79: Cost of the mill | B79: 0 | C79: 2 | D79: 6 | F79: 0.12 | H79: sawing the timber for the bridge of Wallingford lengthwise 2 shilling 6pence. | J79: =F79
A80: Cost of the mill | B80: 0 | C80: 0 | D80: 10 | F80: 0.04 | H80: 100 nails bought for the bays of the mill 10pence. | J80: =F80
A81: Cost of the mill | B81: 0 | C81: 0 | D81: 2 | F81: 0.01 | H81: hiring 1 water-axe (waterax) to level the foundations of the bridge where the timber was being placed 2pence. | J81: =F81
A82: Cost of the mill | B82: 0 | C82: 0 | D82: 4 | F82: 0.02 | H82: ironwork of 1 pier to enlarge the holes in the foundations where the other piers were being placed 4pence. | J82: =F82
A83: Cost of the mill | B83: 1 | C83: 6 | D83: 8 | F83: 1.33 | H83: carpentry done for the said bridge by piece-work by fixed agreement £1 6 shilling 8pence, and .5 qr of wheat from the granary. | J83: =F83
A84: Cost of the mill | B84: 0 | C84: 1 | D84: 4 | F84: 0.07 | H84: 8 cart-loads of stones bought for the bays of the said bridge and for the bays of the lake (la Lak') 1 shilling 4pence. | J84: =F84
A85: Cost of the mill | B85: 0 | C85: 3 | D85: 0 | F85: =B85+C85/20+D85/240 | H85: piers bought for the said bridge and other necessaries of the said mill 3 shilling | J85: =F85
A86: Cost of the mill | B86: 5 | C86: 6 | D86: 4.75 | F86: 5.32 | H86: Total, £5 6 shilling 4.75pence
A87: Cost of the mill | F87: =SUM(F74:F85) | G87: =F87-F86 | H87: Total
A89: Customary payments | B89: 0 | C89: 1 | D89: 10 | F89: 0.09 | H89: In customary payments to 1 reeve, 1 overseer of the harvest, 1 smith, 1 swineherd and 7 ploughmen for their corrodies (corred') at Christmas 1 shilling 10pence, or 2pence each.
A90: Customary payments | B90: 0 | C90: 4 | D90: 4 | F90: 0.22 | H90: customary payment to 28 men mowing the northern meadow and 3 men spreading hay in the same, 4 shilling 4pence and 1 summer cheese.
A91: Customary payments | B91: 0 | C91: 2 | D91: 0 | F91: =B91+C91/20+D91/240 | H91: customary payment for the mowing of the meadows in place of 2 wethers owed to them 2 shilling
A92: Customary payments | B92: 0 | C92: 8 | D92: 2 | F92: =B92+C92/20+D92/240 | H92: Total, 8 shilling 2pence
A93: Customary payments | F93: =SUM(F89:F91) | G93: =F93-F92 | H93: Total
A95: Cost of the harvest | B95: 1 | C95: 17 | D95: 4 | F95: 1.87 | H95: In expenses of 5 harvest boon-works of 375 men reaping as if for 1 day £1 17 shilling 4pence, because they have a meal twice a day.
A96: Cost of the harvest | B96: 1 | C96: 17 | D96: 4 | F96: 1.87 | H96: Total, £1 17 shilling 4pence
A97: Cost of the harvest | F97: 1.87 | G97: 0 | H97: Total
A99: Expenses of the steward | B99: 1 | C99: 3 | D99: 11.5 | F99: 1.2 | H99: In expenses of Sir Robert, steward, and Simon, clerk, for their visits for the year to hold the hundred-courts, £1 3 shilling 11.5pence by 3 tallies.
A100: Expenses of the steward | B100: 3 | C100: 9 | D100: 3 | F100: =B100+C100/20+D100/240 | H100: expenses of Walter de Poulton', bailiff from Michaelmas (29 September) until the feast of St Lucy the Virgin (13 December), 9 shilling 3pence by 1 tally, paid to Roginald de Lynham, bailiff, as part of his wages of £3 by 1 tally.
A101: Expenses of the steward | B101: 1 | C101: 4 | D101: 0 | F101: =B101+C101/20+D101/240 | H101: a certain robe with fur bought for the said Roginald at Christmas £1 4 shilling.
A102: Expenses of the steward | B102: 0 | C102: 0 | D102: 4 | F102: =B102+C102/20+D102/240 | H102: expenses of a certain attendant pleading for the steward and Simon, clerk, for the aforesaid distraint taken against the lord bishop 4pence
A103: Expenses of the steward | B103: 5 | C103: 17 | D103: 6.5 | F103: 5.88 | H103: Total, £5 17 shilling 6.5pence
A104: Expenses of the steward | F104: =SUM(F99:F102) | G104: =F104-F103 | H104: Total
A106: Total of all expenses | B106: 26 | C106: 17 | D106: 8.5 | F106: 26.89 | H106: Total of all expenses, £26 17 shilling 8.5pence
A107: Total of all expenses | F107: 26.89 | G107: =F107-F106 | H107: Total
A110: And he owes | B110: 72 | C110: 17 | D110: 6 | F110: 72.88 | H110: And he owes, £72 17 shilling 6pence
A111: And he owes | F111: 72.88 | G111: 0 | H111: Total
A114: Allowances | B114: 1 | C114: 0 | D114: 0 | F114: 1 | H114: In allowance of the reeve for contributions made to certain amercements by the vill of Wallingford to the court of the lord king's marshal, because the bishop has a mill in the vill which was taken into the hands of the lord king by the lord king's marshal, £1. Given to a certain man for release from a certain distraint taken against the lord bishop 1 shilling Total of all allowances, £1 1 shilling
A115: Allowances | F115: 1 | G115: 0 | H115: Total
...

Sheet Issues of the Grange
A1: Gross Output | B1: Total Quantity | C1: Account Total Quarters | D1: Bought in Total Quarters | E1: Received from churchscot | F1: Sold Total Quarters | G1: Difference Produced+Bought-Sold | H1: Weighted Average Price per Quarter | I1: Value of Total Production weighted
A2: wheat | B2: 154.4375 | C2: 139.9375 | D2: 7.75 | F2: 105.3125 | G2: =B2-F2 | H2: 0.28333333 | I2: =H2*B2
A3: rye | B3: 73 | C3: 73 | D3: 0 | F3: 29.125 | G3: =B3-F3 | H3: 0.15833333 | I3: =H3*B3
A4: barley | B4: 150.9375 | C4: 0.5 | D4: 0 | F4: 123 | G4: =B4-F4 | H4: 0.16859756 | I4: =H4*B4
A5: dredge | B5: 33.125 | C5: 33.125 | D5: 0 | F5: 16.25 | G5: =B5-F5 | H5: 0.15 | I5: =H5*B5
A6: oats | B6: 19.5 | C6: 8.875 | D6: 10.625 | F6: 5 | G6: =B6-F6 | H6: 0.0066666667 | I6: =H6*B6
A8: Total Production
A9: Sales of corn (as recorded in accounts)
A12: Net output | B12: Gross output | C12: Seed quarters | D12: Seed bushels | E12: Seed total quarters | F12: tithe quarters | G12: tithe bushels | H12: tithe total | I12: manorial servants quarters | J12: manorial servants bushels | K12: manorial servants total quarters | L12: output net of tithe, seed, liveries | M12: in stock from last year | N12: Price in £ | O12: Value of net output in £ | P12: Value of sales (in "Sale of Corn") in £
A13: wheat | B13: =B2 | C13: 38 | D13: 3 | E13: =C13+D13/8 | I13: =1+1+1+0.5+6 | J13: =1+2+1+6 | K13: =I13+J13/8 | L13: =B13-E13-K13 | N13: =H2 | O13: =N13*L13
A14: rye | B14: =B3 | C14: 16 | D14: 3 | E14: =C14+D14/8 | I14: =20+3+3 | J14: =6+6 | K14: =I14+J14/8 | L14: =B14-E14-K14 | N14: =H3 | O14: =N14*L14
A15: barley | B15: =B4 | C15: 31 | E15: =C15+D15/8 | J15: =1 | K15: =I15+J15/8 | L15: =B15-E15-K15 | N15: =H4 | O15: =N15*L15
A16: dredge | B16: =B5 | C16: 15.5 | E16: =C16+D16/8 | I16: 1 | J16: 3 | K16: =I16+J16/8 | L16: =B16-E16-K16 | N16: =H5 | O16: =N16*L16
A17: oats | B17: =B6 | C17: 8 | D17: 1 | E17: =C17+D17/8 | I17: =2+2+7 | J17: =2+1 | K17: =I17+J17/8 | L17: =B17-E17-K17 | N17: =H6 | O17: =N17*L17
A19: Total

Sheet Issues of the Mills

Sheet Stock
A1: BRIGHTWELL STOCK ACCOUNT
C3: added | G3: subtracted
A4: Livestock | B4: Inherited stock | C4: added | D4: strays | E4: herbage | F4: churchscot | G4: of which in default | H4: sold | I4: in murrain | J4: accounted for elsewhere | K4: End-period stock | L4: cross-check | M4: stock building | N4: raw production | O4: Unit price (£) | P4: Value of stock (£) at given value | Q4: Value of stock (£) at sales prices | R4: Sales in (£) | S4: Value of stock building (£) | T4: Value of production (£) at sales prices | U4: Details
A5: Cart-horses | B5: 2 | C5: 1 | K5: 3 | L5: =B5+C5+D5+E5+F5-G5-H5-I5-J5 | M5: =K5-B5
A6: Mares | B6: 1 | C6: 1 | I6: 1 | K6: 1 | L6: =B6+C6+D6+E6+F6-G6-H6-I6-J6 | M6: =K6-B6
A7: Plough horses | B7: 11 | H7: 11 | K7: 0 | L7: =B7+C7+D7+E7+F7-G7-H7-I7-J7 | M7: =K7-B7 | O7: =R7/H7 | R7: =Receipts!F77
A8: Colts (unspecified years) | L8: =B8+C8+D8+E8+F8-G8-H8-I8-J8 | M8: =K8-B8
A9: Colts (2 years) | B9: 1 | J9: 1 | K9: 0 | L9: =B9+C9+D9+E9+F9-G9-H9-I9-J9 | M9: =K9-B9
A10: Colts (1 year) | B10: 3 | K10: 3 | L10: =B10+C10+D10+E10+F10-G10-H10-I10-J10 | M10: =K10-B10
A11: Foals | L11: =B11+C11+D11+E11+F11-G11-H11-I11-J11 | M11: =K11-B11
A12: Oxen | B12: 31 | C12: =2+12 | K12: 45 | L12: =B12+C12+D12+E12+F12-G12-H12-I12-J12 | M12: =K12-B12
A13: Bulls | B13: 1 | H13: 1 | K13: 0 | L13: =B13+C13+D13+E13+F13-G13-H13-I13-J13 | M13: =K13-B13 | O13: =R13/H13 | R13: =Receipts!F60
A14: Cows | B14: 13 | C14: 4 | I14: 1 | K14: 16 | L14: =B14+C14+D14+E14+F14-G14-H14-I14-J14 | M14: =K14-B14
A15: Steers | B15: 6 | J15: 6 | K15: 0 | L15: =B15+C15+D15+E15+F15-G15-H15-I15-J15 | M15: =K15-B15
A16: Bullocks | B16: 6 | K16: 6 | L16: =B16+C16+D16+E16+F16-G16-H16-I16-J16 | M16: =K16-B16
A17: Yearlings | B17: 6 | K17: 6 | L17: =B17+C17+D17+E17+F17-G17-H17-I17-J17 | M17: =K17-B17
A18: Calves | C18: 13 | H18: 5 | J18: 1 | K18: 7 | L18: =B18+C18+D18+E18+F18-G18-H18-I18-J18 | M18: =K18-B18 | O18: =R18/H18 | R18: =Receipts!F57+Receipts!F58+Receipts!F59
A19: Wethers | L19: =B19+C19+D19+E19+F19-G19-H19-I19-J19 | M19: =K19-B19
A20: Rams | L20: =B20+C20+D20+E20+F20-G20-H20-I20-J20 | M20: =K20-B20
A21: Ewes | L21: =B21+C21+D21+E21+F21-G21-H21-I21-J21 | M21: =K21-B21
A22: Hoggs | L22: =B22+C22+D22+E22+F22-G22-H22-I22-J22 | M22: =K22-B22
A23: Lambs | L23: =B23+C23+D23+E23+F23-G23-H23-I23-J23 | M23: =K23-B23
A24: Boars | L24: =B24+C24+D24+E24+F24-G24-H24-I24-J24 | M24: =K24-B24
A25: Sows | B25: 3 | K25: 3 | L25: =B25+C25+D25+E25+F25-G25-H25-I25-J25 | M25: =K25-B25
A26: Pigs | B26: 36 | C26: 33 | H26: 26 | K26: 43 | L26: =B26+C26+D26+E26+F26-G26-H26-I26-J26 | M26: =K26-B26 | O26: =R26/H26 | R26: =Receipts!F91-R27
A27: Hoggets | B27: 34 | H27: 1 | J27: 33 | K27: 0 | L27: =B27+C27+D27+E27+F27-G27-H27-I27-J27 | M27: =K27-B27 | O27: =R27/H27 | R27: =Receipts!F90
A28: Piglets | C28: 43 | J28: =4+1 | K28: 38 | L28: =B28+C28+D28+E28+F28-G28-H28-I28-J28 | M28: =K28-B28
A29: Swans
A30: Peacocks
A31: Total Value | R31: =SUM(R5:R29)
A34: Wool
A35: Coarse wool
A36: Lamb's wool
A37: Wool locks
A38: Wool sold at shearing
A39: Total wool
A42: Hides
A43: Ox hides
A44: Mare | B44: 1 | H44: 1 | O44: =R44/H44 | R44: =Receipts!F53 | T44: =O44*H44
A45: cow | B45: 1 | H45: 1 | O45: =R45/H45 | R45: =Receipts!F54 | T45: =O45*H45
A46: Steer | T46: =O46*H46
A47: calves | H47: 1 | O47: =R47/H47 | R47: =Receipts!F55 | T47: =O47*H47 | U47: onyl recorded in issues not stock
A48: pigs
A49: Woolskins (incl. 10 in tithe)
A50: wethers
A51: rams
A52: ewes
A53: hoggs
A54: Woolskins (excl. 10 in tithe)
A55: Bareskins
A56: wethers
A57: rams
A58: ewes
A59: hoggs
... A63: Shorn skins
A64: Total | R64: =SUM(R44:R62) | T64: =SUM(T44:T61)
A67: Poultry stock
A68: Hens
A69: Geese
A70: Capons (from chickens)
A71: Cocks & hens
A72: Total poultry stock
A73: Total poultry excluding churchscot
A75: Poultry production
A76: Eggs | F76: 350 | H76: 350 | P76: =R76/H76 | R76: =Receipts!F52 | T76: =P76*H76
A77: Cocks & hens from churchscot of customary tenants | F77: 138 | G77: =2+8+4+2+2+2+8+2+2+1+2 | H77: 103 | P77: =R77/H77 | R77: =Receipts!F51 | T77: =P77*H77
A78: Sum of above
A79: Total | R79: =SUM(R75:R78) | T79: =SUM(T76:T77)
A82: Meat
A83: Beef
A84: Mutton
A85: Pork
A86: Total
A88: Cheese
A89: Winter cheese
A90: Summer cheese
A91: Total
A93: Butter
A94: Butter
A95: Total
... A100: Cider
A101: Cider | B101: 1 | C101: 2 | H101: 1 | K101: 2 | R101: =Receipts!F61 | T101: =R101
A102: Total | R102: =SUM(R101) | T102: =T101
A104: Additional Information (not necessarily useful)
A105: Utensils
A106: ploughs
A107: carts
A108: cart-ropes
A109: corn baskets
A110: seed-sacks
A111: seed basket
A112: locks for the doors
A113: lead vessel
A114: brass pots
A115: pans
... A130: brass posnets

Sheet raw data
A1: Heading | B1: Sentence | C1: Total in Pounds | D1: Pounds | E1: Shillings | F1: Pence | G1: Corn | H1: Total Quarters Except 1 | I1: Total Bushels Except 1 | J1: Total Corn Cross-Check | K1: Total Corn Manorial Account | L1: Corn Quantity Error | M1: Quarters 1 | N1: Bushels 1 | O1: Quarters 2 | P1: Bushels 2 | Q1: Quarters 3 | R1: Bushels 3 | S1: Quarters 4 | T1: Bushels 4 | U1: Quarters 5 | V1: Bushels 5 | W1: Quarters 6 | X1: Bushels 6 | Y1: shilling a quarter 1 | Z1: pence a quarter 1 | AA1: shilling a quarter 2 | AB1: pence a quarter 2 | AC1: shilling a quarter 3 | AD1: pence a quarter 3 | AE1: shilling a quarter 4 | AF1: pence a quarter 4 | AG1: shilling a bushel 1 | AH1: pence a bushel 1 | AI1: shilling a bushel 2 | AJ1: pence a bushel 2 | AK1: shilling a bushel 3 | AL1: pence a bushel 3 | AM1: shilling a bushel 4 | AN1: pence a bushel 4
A2: Arrears | B2: Roginald de Lynham, bailiff, and Richard E1y3, reeve, render account for £25 11 shilling 11pence of arrears from the last account. | C2: 25.6 | D2: 25 | E2: 11 | F2: 11 | H2: 0 | I2: 0 | J2: 0 | K2: 0 | L2: 0 | M2: 0 | N2: 0
A3: Arrears | B3: All delivered to Sir Geoffrey, treasurer of Wolvesey, and they are quit. | C3: 0 | D3: 0 | E3: 0 | F3: 0 | H3: 0 | I3: 0 | J3: 0 | K3: 0 | L3: 0 | M3: 0 | N3: 0
A4: Rents | B4: The same render account for £3 2pence for all rents of assize at Christmas. | C4: 3.01 | D4: 3 | E4: 0 | F4: 2 | H4: 0 | I4: 0 | J4: 0 | K4: 0 | L4: 0 | M4: 0 | N4: 0
A5: Rents | B5: £3 2pence at Easter (22 April). | C5: 3.01 | D5: 3 | E5: 0 | F5: 2 | H5: 0 | I5: 0 | J5: 0 | K5: 0 | L5: 0 | M5: 0 | N5: 0
A6: Rents | B6: £3 2pence at the Nativity of the blessed John (24 June). | C6: 3.01 | D6: 3 | E6: 0 | F6: 2 | H6: 0 | I6: 0 | J6: 0 | K6: 0 | L6: 0 | M6: 0 | N6: 0
A7: Rents | B7: £5 8 shilling 4.5pence at Michaelmas (29 September). | C7: 5.42 | D7: 5 | E7: 8 | F7: 4.5 | H7: 0 | I7: 0 | J7: 0 | K7: 0 | L7: 0 | M7: 0 | N7: 0
A8: Rents | B8: Total, £14 8 shilling 10.5pence | C8: 14.44 | D8: 14 | E8: 8 | F8: 10.5 | H8: 0 | I8: 0 | J8: 0 | K8: 0 | L8: 0 | M8: 0 | N8: 0
A9: Quittances | B9: In quittance of 1 reeve for the year 5 shilling. | C9: 0.25 | D9: 0 | E9: 5 | F9: 0 | H9: 0 | I9: 0 | J9: 0 | K9: 0 | L9: 0 | M9: 0 | N9: 0
A10: Quittances | B10: 1 smith working the iron of 3 ploughs for the year 2 shilling 6pence. | C10: 0.12 | D10: 0 | E10: 2 | F10: 6 | H10: 0 | I10: 0 | J10: 0 | K10: 0 | L10: 0 | M10: 0 | N10: 0
A11: Quittances | B11: 1 overseer of the harvest sowing the land, and keeping the meadow, pasture and corn for the year 2 shilling 24.. | C11: 0.1 | D11: 0 | E11: 2 | F11: 0 | H11: 0 | I11: 0 | J11: 0 | K11: 0 | L11: 0 | M11: 0 | N11: 0
A12: Quittances | B12: 1 swineherd for the year 2 shilling 2pence. | C12: 0.11 | D12: 0 | E12: 2 | F12: 2 | H12: 0 | I12: 0 | J12: 0 | K12: 0 | L12: 0 | M12: 0 | N12: 0
A13: Quittances | B13: 7 ploughmen for the year 15 shilling 2pence, or 2 shilling 2pence each. | C13: 0.76 | D13: 0 | E13: 15 | F13: 2 | H13: 0 | I13: 0 | J13: 0 | K13: 0 | L13: 0 | M13: 0 | N13: 0
... A69: Sale of pigs | B69: 5pence from 1 sick hogget sold Total, £4 19 shilling 3pence | C69: 4.96 | D69: 4 | E69: 19 | F69: 3 | H69: 0 | I69: 0 | J69: 0 | K69: 0 | L69: 0 | M69: 0 | N69: 0
A70: Sale of corn | B70: The same render account for £29 16 shilling 9.25pence from 105 quarters 2.5 bushels of wheat sold, at 5 shilling 8pence a quarters, £4 9 shilling 10.25pence from 28 quarters 3 bushels of rye sold, at 3 shilling 2pence a quarters. | C70: 29.84 | D70: 29 | E70: 16 | F70: 9.25 | G70: rye, wheat | H70: 28 | I70: 3 | J70: 28.375 | K70: 105.3125 | L70: -76.9375 | M70: 105 | N70: 2.5 | O70: 28 | P70: 3 | Y70: 5 | Z70: 8 | AA70: 3 | AB70: 2
A71: Sale of corn | B71: £20 16 shilling .75pence from 118 quarters of barley sold, at 3 shilling 6pence a quarters. | C71: 20.8 | D71: 20 | E71: 16 | F71: 0 | G71: barley | H71: 118 | I71: 0 | J71: 118 | K71: 118 | L71: 0 | M71: 118 | N71: 0 | Y71: 3 | Z71: 6
A72: Sale of corn | B72: £2 8 shilling 9pence from 16 quarters 2 bushels of dredge sold, at 3 shilling a quarters, 2 shilling 4.5pence from 6 bushels of rye sold at the audit. | C72: 2.44 | D72: 2 | E72: 8 | F72: 9 | G72: rye | H72: 16 | I72: 6 | J72: 16.75 | K72: 16.25 | L72: 0.5 | M72: 16 | N72: 2 | O72: 0 | P72: 6 | Y72: 3 | Z72: 0
A73: Sale of corn | B73: 1 shilling 9pence from .5 quarters of barley sold at the audit. | C73: 0.09 | D73: 0 | E73: 1 | F73: 9 | G73: barley | H73: 5 | I73: 0 | J73: 5 | K73: 5 | L73: 0 | M73: 5 | N73: 0
A74: Sale of corn | B74: 8pence from .5 quarters of vetches sold at the audit. | C74: 0.03 | D74: 0 | E74: 0 | F74: 8 | G74: vetches | H74: 5 | I74: 0 | J74: 5 | K74: 5 | L74: 0 | M74: 5 | N74: 0
A75: Sale of corn | B75: Total, £57 16 shilling 2.75pence | C75: 57.81 | D75: 57 | E75: 16 | F75: 2.75 | H75: 0 | I75: 0 | J75: 0 | K75: 0 | L75: 0 | M75: 0 | N75: 0
A76: Sale of the mill's corn | B76: The same render account for £2 17 shilling 4pence from 13 quarters .5 bushels of wheat from the mill sold, at 4 shilling a quarters for 4 quarters, 4 shilling 4pence a quarters for 3 quarters, and 4 shilling 8pence a quarters for 6 quarters .5 bushels. | C76: 2.87 | D76: 2 | E76: 17 | F76: 4 | G76: wheat | H76: 13 | I76: 10 | J76: 14.25 | K76: 13 | L76: 1.25 | M76: 13 | N76: 0 | O76: 0 | P76: 5 | Q76: 4 | R76: 0 | S76: 3 | T76: 0 | U76: 6 | V76: 0 | W76: 0 | X76: 5 | Y76: 4 | Z76: 0 | AA76: 4 | AB76: 4 | AC76: 4 | AD76: 8
A77: Sale of the mill's corn | B77: £2 2 shilling 11pence from 17.5 quarters of maslin sold, at 2 shilling a quarters for 5 quarters 5 bushels, and 2 shilling 8pence a quarters for 11 quarters 7 bushels. | C77: 2.15 | D77: 2 | E77: 2 | F77: 11 | G77: maslin | H77: 16 | I77: 12 | J77: 17.5 | K77: 17.5 | L77: 0 | M77: 17.5 | N77: 0 | O77: 5 | P77: 5 | Q77: 11 | R77: 7 | Y77: 2 | Z77: 0 | AA77: 2 | AB77: 8
A78: Sale of the mill's corn | B78: £1 3 shilling 2pence from 5 quarters 2 bushels of coarse-ground corn from the mill sold, at 4 shilling a quarters for 2 quarters, and 4 shilling 8pence a quarters for 3 quarters 2 bushels. | C78: 1.16 | D78: 1 | E78: 3 | F78: 2 | H78: 5 | I78: 2 | J78: 5.25 | K78: 5.25 | L78: 0 | M78: 5 | N78: 2 | O78: 2 | P78: 0 | Q78: 3 | R78: 2 | Y78: 4 | Z78: 0 | AA78: 4 | AB78: 8
A79: Sale of the mill's corn | B79: £3 9 shilling 3pence from 22.5 quarters of second-grade malt sold, at 3 shilling a quarters for 12 quarters, and 3 shilling 2pence a quarters for 10.5 quarters. | C79: 3.46 | D79: 3 | E79: 9 | F79: 3 | G79: second-grade malt | H79: 22.5 | I79: 0 | J79: 22.5 | K79: 22.5 | L79: 0 | M79: 22.5 | N79: 0 | O79: 12 | P79: 0 | Q79: 10.5 | R79: 0 | Y79: 3 | Z79: 0 | AA79: 3 | AB79: 2
A80: Sale of the mill's corn | B80: 5 shilling 4pence from eels sold at various times. | C80: 0.27 | D80: 0 | E80: 5 | F80: 4 | H80: 0 | I80: 0 | J80: 0 | K80: 0 | L80: 0 | M80: 0 | N80: 0
A81: Sale of the mill's corn | B81: Note that there was no more from the issue of the mill this year because for 4 weeks after Christmas and for 2 weeks in Lent it was idle due to torrents. | C81: 0 | D81: 0 | E81: 0 | F81: 0 | H81: 0 | I81: 0 | J81: 0 | K81: 0 | L81: 0 | M81: 0 | N81: 0
A82: Sale of the mill's corn | B82: And for 3pence from 1 bushels of maslin sold at the audit. | C82: 0.01 | D82: 0 | E82: 0 | F82: 3 | G82: maslin | H82: 0 | I82: 1 | J82: 0.125 | K82: 0.125 | L82: 0 | M82: 0 | N82: 1
A83: Sale of the mill's corn | B83: Total, £9 18 shilling 3pence | C83: 9.91 | D83: 9 | E83: 18 | F83: 3 | H83: 0 | I83: 0 | J83: 0 | K83: 0 | L83: 0 | M83: 0 | N83: 0
A84: Fixed payments, entry and marriage fines | B84: The same render account for £1 6 shilling 8pence from fixed payments at the 2 hundred-courts for tithingpenny. | C84: 1.33 | D84: 1 | E84: 6 | F84: 8 | H84: 0 | I84: 0 | J84: 0 | K84: 0 | L84: 0 | M84: 0 | N84: 0
A85: Fixed payments, entry and marriage fines | B85: £2 13 shilling 4pence from the fine of Roger ate Grove to have Agnes, relict of Henry Wys, with .5 virgate of customary land. | C85: 2.67 | D85: 2 | E85: 13 | F85: 4 | H85: 0 | I85: 0 | J85: 0 | K85: 0 | L85: 0 | M85: 0 | N85: 0
A86: Fixed payments, entry and marriage fines | B86: 13 shilling 4pence from the fine of John G 'third to recover a certain cottage which he sold to John Cocus without licence. | C86: 0.67 | D86: 0 | E86: 13 | F86: 4 | H86: 0 | I86: 0 | J86: 0 | K86: 0 | L86: 0 | M86: 0 | N86: 0
A87: Fixed payments, entry and marriage fines | B87: Total, £4 13 shilling 4pence | C87: 4.67 | D87: 4 | E87: 13 | F87: 4 | H87: 0 | I87: 0 | J87: 0 | K87: 0 | L87: 0 | M87: 0 | N87: 0
A88: Perquisites | B88: The same render account for 1 shilling, from Geoffrey de Brighwalton for release from his suit at 2 views. | C88: 0.05 | D88: 0 | E88: 1 | F88: 0 | H88: 0 | I88: 0 | J88: 0 | K88: 0 | L88: 0 | M88: 0 | N88: 0
A89: Perquisites | B89: 1 shilling from Osbert de Nutle fort he same, 6pence from Emma ate Strem’ for trespass of pasture, 6pence from John atte Strem’ for trespass in the curia. | C89: 0.08 | D89: 0 | E89: 1 | F89: 6 | H89: 0 | I89: 0 | J89: 0 | K89: 0 | L89: 0 | M89: 0 | N89: 0
A90: Perquisites | B90: 6pence from John ate Street' William le King3 for trespass with his sheep in the pasture. | C90: 0.03 | D90: 0 | E90: 0 | F90: 6 | H90: 0 | I90: 0 | J90: 0 | K90: 0 | L90: 0 | M90: 0 | N90: 0
A91: Perquisites | B91: 3pence from Juliana de Wodek for the assize of ale. | C91: 0.01 | D91: 0 | E91: 0 | F91: 3 | H91: 0 | I91: 0 | J91: 0 | K91: 0 | L91: 0 | M91: 0 | N91: 0
A92: Perquisites | B92: 3d, from Christina relict of Thomas Amys for the stone. | C92: 0 | D92: 0 | E92: 0 | F92: 0 | H92: 0 | I92: 0 | J92: 0 | K92: 0 | L92: 0 | M92: 0 | N92: 0
A93: Perquisites | B93: 3d, from Alice Poukeput for the same. | C93: 0 | D93: 0 | E93: 0 | F93: 0 | H93: 0 | I93: 0 | J93: 0 | K93: 0 | L93: 0 | M93: 0 | N93: 0
A94: Perquisites | B94: 3pence from Richard the reeve for the same. | C94: 0.01 | D94: 0 | E94: 0 | F94: 3 | H94: 0 | I94: 0 | J94: 0 | K94: 0 | L94: 0 | M94: 0 | N94: 0
... A143: Cost of ploughs | B143: withies bought for the draught-chains (hart') of the ploughs 10.5pence. | C143: 0.04 | D143: 0 | E143: 0 | F143: 10.5 | H143: 0 | I143: 0 | J143: 0 | K143: 0 | L143: 0 | M143: 0 | N143: 0
A144: Cost of ploughs | B144: stipend of the smith working the iron of 2 ploughs for the year 4 shilling, because 1 acre of wheat was removed from his stipend, and he quits .5 virgate of land through the iron for 2 ploughs. | C144: 0.2 | D144: 0 | E144: 4 | F144: 0 | G144: wheat | H144: 0 | I144: 0 | J144: 0 | K144: 0 | L144: 0 | M144: 0 | N144: 0
A145: Cost of ploughs | B145: . | C145: 0 | D145: 0 | E145: 0 | F145: 0 | H145: 0 | I145: 0 | J145: 0 | K145: 0 | L145: 0 | M145: 0 | N145: 0
A146: Cost of ploughs | B146: 1 new wheelbarrow bought 8pence Total, 14 shilling 9.5pence | C146: 0.73 | D146: 0 | E146: 14 | F146: 8 | H146: 0 | I146: 0 | J146: 0 | K146: 0 | L146: 0 | M146: 0 | N146: 0
A147: Carts and ironwork | B147: In 2 new horse-collars bought 1 shilling 4pence. | C147: 0.07 | D147: 0 | E147: 1 | F147: 4 | H147: 0 | I147: 0 | J147: 0 | K147: 0 | L147: 0 | M147: 0 | N147: 0
A148: Carts and ironwork | B148: 1 hemp rope bought for tethering the cart at Reading 1 shilling 4pence. | C148: 0.07 | D148: 0 | E148: 1 | F148: 4 | H148: 0 | I148: 0 | J148: 0 | K148: 0 | L148: 0 | M148: 0 | N148: 0
A149: Carts and ironwork | B149: 1 pair of traces bought there 5pence. | C149: 0.02 | D149: 0 | E149: 0 | F149: 5 | H149: 0 | I149: 0 | J149: 0 | K149: 0 | L149: 0 | M149: 0 | N149: 0
A150: Carts and ironwork | B150: fitting 1 cart with axles, with axles, white leather, clouts and nails bought for the year, 1 shilling 8.75pence. | C150: 0.09 | D150: 0 | E150: 1 | F150: 8.75 | H150: 0 | I150: 0 | J150: 0 | K150: 0 | L150: 0 | M150: 0 | N150: 0
A151: Carts and ironwork | B151: frets bought for the cart 2pence. | C151: 0.01 | D151: 0 | E151: 0 | F151: 2 | H151: 0 | I151: 0 | J151: 0 | K151: 0 | L151: 0 | M151: 0 | N151: 0
A152: Carts and ironwork | B152: 1 metal plate bought for the cart 1pence. | C152: 0 | D152: 0 | E152: 0 | F152: 1 | H152: 0 | I152: 0 | J152: 0 | K152: 0 | L152: 0 | M152: 0 | N152: 0
A153: Carts and ironwork | B153: 1 leather halter bought for I cart-horse 3pence. | C153: 0.01 | D153: 0 | E153: 0 | F153: 3 | H153: 0 | I153: 0 | J153: 0 | K153: 0 | L153: 0 | M153: 0 | N153: 0
A154: Carts and ironwork | B154: shoeing 2 cart-horses for the year, for all necessaries which pertain to their provision, together with their removal and fastening, 3 shilling Total, 8 shilling 3.75pence | C154: 0.17 | D154: 0 | E154: 3 | F154: 3.75 | H154: 0 | I154: 0 | J154: 0 | K154: 0 | L154: 0 | M154: 0 | N154: 0
A155: Small necessaries | B155: In 12 dishes, 8 pans, 12 saucers. | C155: 0 | D155: 0 | E155: 0 | F155: 0 | H155: 0 | I155: 0 | J155: 0 | K155: 0 | L155: 0 | M155: 0 | N155: 0
A156: Small necessaries | B156: . | C156: 0 | D156: 0 | E156: 0 | F156: 0 | H156: 0 | I156: 0 | J156: 0 | K156: 0 | L156: 0 | M156: 0 | N156: 0
A157: Small necessaries | B157: 12 cart-loads of wood felled in the wood of Wargrave 1 shilling. | C157: 0.05 | D157: 0 | E157: 1 | F157: 0 | H157: 0 | I157: 0 | J157: 0 | K157: 0 | L157: 0 | M157: 0 | N157: 0
A158: Small necessaries | B158: 2.5 bushels of salt bought for the pease pottage of the manorial servants 11pence. | C158: 0.05 | D158: 0 | E158: 0 | F158: 11 | G158: peas | H158: 0 | I158: 2.5 | J158: 0.3125 | K158: 0.3125 | L158: 0 | M158: 0 | N158: 2.5
A159: Small necessaries | B159: 4 new sacks bought for corn 2 shilling 6.5pence. | C159: 0.13 | D159: 0 | E159: 2 | F159: 6.5 | H159: 0 | I159: 0 | J159: 0 | K159: 0 | L159: 0 | M159: 0 | N159: 0
A160: Small necessaries | B160: 1 basket (sporta) bought 4pence. | C160: 0.02 | D160: 0 | E160: 0 | F160: 4 | H160: 0 | I160: 0 | J160: 0 | K160: 0 | L160: 0 | M160: 0 | N160: 0
A161: Small necessaries | B161: castrating 12 male and spaying 9 female piglets 7pence. | C161: 0.03 | D161: 0 | E161: 0 | F161: 7 | H161: 0 | I161: 0 | J161: 0 | K161: 0 | L161: 0 | M161: 0 | N161: 0
A162: Small necessaries | B162: 1.5 bushels of oatmeal bought for pease pottage for the year, 1 shilling 1.5pence this year. | C162: 0.06 | D162: 0 | E162: 1 | F162: 1.5 | G162: peas, oatmeal | H162: 0 | I162: 1.5 | J162: 0.1875 | K162: 0.1875 | L162: 0 | M162: 0 | N162: 1.5
A163: Small necessaries | B163: . | C163: 0 | D163: 0 | E163: 0 | F163: 0 | H163: 0 | I163: 0 | J163: 0 | K163: 0 | L163: 0 | M163: 0 | N163: 0
A164: Small necessaries | B164: withies bought for penning oxen in the byre in winter 2.5pence. | C164: 0.01 | D164: 0 | E164: 0 | F164: 2.5 | H164: 0 | I164: 0 | J164: 0 | K164: 0 | L164: 0 | M164: 0 | N164: 0
A165: Small necessaries | B165: 1 piece of iron made for a certain shovel out of the demesne iron 1pence. | C165: 0 | D165: 0 | E165: 0 | F165: 1 | H165: 0 | I165: 0 | J165: 0 | K165: 0 | L165: 0 | M165: 0 | N165: 0
A166: Small necessaries | B166: hiring a certain man to clean the inside of 2 tuns for putting cider in and moreover hooping them anew and hooping anew 5 tubs by piece-work for 10 days 2 shilling 6pence. | C166: 0.12 | D166: 0 | E166: 2 | F166: 6 | H166: 0 | I166: 0 | J166: 0 | K166: 0 | L166: 0 | M166: 0 | N166: 0
A167: Small necessaries | B167: hiring a certain roofer for 2.5 days to roof over the enclosure between the bishop's chamber and chapel 7.5pence. | C167: 0.03 | D167: 0 | E167: 0 | F167: 7.5 | H167: 0 | I167: 0 | J167: 0 | K167: 0 | L167: 0 | M167: 0 | N167: 0
A168: Small necessaries | B168: small nails for fastening laths to the walls of the byre 1pence Total, 11 shilling | C168: 0.55 | D168: 0 | E168: 11 | F168: 1 | H168: 0 | I168: 0 | J168: 0 | K168: 0 | L168: 0 | M168: 0 | N168: 0
A169: Threshing and winnowing | B169: In threshing 26 quarters of barley 3 shilling 2pence, at 1.5pence a quarters. | C169: 0.16 | D169: 0 | E169: 3 | F169: 2 | G169: barley | H169: 26 | I169: 0 | J169: 26 | K169: 26 | L169: 0 | M169: 26 | N169: 0
A170: Threshing and winnowing | B170: . | C170: 0 | D170: 0 | E170: 0 | F170: 0 | H170: 0 | I170: 0 | J170: 0 | K170: 0 | L170: 0 | M170: 0 | N170: 0
A171: Threshing and winnowing | B171: winnowing the said corn 5pence, at 1pence per 5 quarters. | C171: 0.02 | D171: 0 | E171: 0 | F171: 5 | H171: 5 | I171: 0 | J171: 5 | K171: 5 | L171: 0 | M171: 5 | N171: 0
A172: Threshing and winnowing | B172: . | C172: 0 | D172: 0 | E172: 0 | F172: 0 | H172: 0 | I172: 0 | J172: 0 | K172: 0 | L172: 0 | M172: 0 | N172: 0
A173: Threshing and winnowing | B173: wages of John Touresmere overseeing the threshing and winnowing of corn at various times 7 shilling 5.5pence, taking 1.5pence a day. | C173: 0.37 | D173: 0 | E173: 7 | F173: 5.5 | H173: 0 | I173: 0 | J173: 0 | K173: 0 | L173: 0 | M173: 0 | N173: 0
A174: Threshing and winnowing | B174: . | C174: 0 | D174: 0 | E174: 0 | F174: 0 | H174: 0 | I174: 0 | J174: 0 | K174: 0 | L174: 0 | M174: 0 | N174: 0
A175: Threshing and winnowing | B175: stipend of the same here 2 shilling, because he takes the rest elsewhere up to 10 shilling Total, 13 shilling 1.5pence | C175: 0.11 | D175: 0 | E175: 2 | F175: 1.5 | H175: 0 | I175: 0 | J175: 0 | K175: 0 | L175: 0 | M175: 0 | N175: 0
A176: Purchase of corn | B176: In 7 quarters 6 bushels of wheat bought for sowing £1 15 shilling 1pence, at 4 shilling 8pence a quarters for 4.5 quarters, and 4 shilling 4pence a quarters for 3 quarters 2 bushels. | C176: 1.75 | D176: 1 | E176: 15 | F176: 1 | G176: wheat | H176: 7.5 | I176: 2 | J176: 7.75 | K176: 7.75 | L176: 0 | M176: 7 | N176: 6 | O176: 4.5 | P176: 0 | Q176: 3 | R176: 2 | Y176: 4 | Z176: 8 | AA176: 4 | AB176: 4
A177: Purchase of corn | B177: 10 quarters 5 bushels of oats bought for fodder for the year 17 shilling 8.5pence, at 1 shilling 8pence a quarters. | C177: 0.89 | D177: 0 | E177: 17 | F177: 8.5 | G177: oats | H177: 10 | I177: 5 | J177: 10.625 | K177: 10.625 | L177: 0 | M177: 10 | N177: 5 | Y177: 1 | Z177: 8
A178: Purchase of corn | B178: . | C178: 0 | D178: 0 | E178: 0 | F178: 0 | H178: 0 | I178: 0 | J178: 0 | K178: 0 | L178: 0 | M178: 0 | N178: 0
A179: Purchase of corn | B179: 5 bushels of beans bought for pigs 1 shilling .5pence Total, £2 13 shilling 10pence | C179: 2.69 | D179: 2 | E179: 13 | F179: 10 | G179: beans | H179: 0 | I179: 5 | J179: 0.625 | K179: 0.625 | L179: 0 | M179: 0 | N179: 5
A180: Purchase of stock | B180: In 1 ox bought for the ploughs at Warbewey 14 shilling. | C180: 0.7 | D180: 0 | E180: 14 | F180: 0 | H180: 0 | I180: 0 | J180: 0 | K180: 0 | L180: 0 | M180: 0 | N180: 0
A181: Purchase of stock | B181: 1 ox bought for the same at Abingdon 14 shilling 6pence. | C181: 0.72 | D181: 0 | E181: 14 | F181: 6 | H181: 0 | I181: 0 | J181: 0 | K181: 0 | L181: 0 | M181: 0 | N181: 0
A182: Purchase of stock | B182: 1 ox bought there for the same 16 shilling. | C182: 0.8 | D182: 0 | E182: 16 | F182: 0 | H182: 0 | I182: 0 | J182: 0 | K182: 0 | L182: 0 | M182: 0 | N182: 0
A183: Purchase of stock | B183: 1 ox bought there for the same 12 shilling 6pence. | C183: 0.62 | D183: 0 | E183: 12 | F183: 6 | H183: 0 | I183: 0 | J183: 0 | K183: 0 | L183: 0 | M183: 0 | N183: 0
A184: Purchase of stock | B184: 2 oxen bought there for the same £1 4 shilling .5pence. | C184: 1.2 | D184: 1 | E184: 4 | F184: 0 | H184: 0 | I184: 0 | J184: 0 | K184: 0 | L184: 0 | M184: 0 | N184: 0
A185: Purchase of stock | B185: 1 ox bought there for the same 15 shilling. | C185: 0.75 | D185: 0 | E185: 15 | F185: 0 | H185: 0 | I185: 0 | J185: 0 | K185: 0 | L185: 0 | M185: 0 | N185: 0
A186: Purchase of stock | B186: 1 ox bought there for the same 14 shilling 6pence. | C186: 0.72 | D186: 0 | E186: 14 | F186: 6 | H186: 0 | I186: 0 | J186: 0 | K186: 0 | L186: 0 | M186: 0 | N186: 0
A187: Purchase of stock | B187: 1 ox bought there for the same 15 shilling. | C187: 0.75 | D187: 0 | E187: 15 | F187: 0 | H187: 0 | I187: 0 | J187: 0 | K187: 0 | L187: 0 | M187: 0 | N187: 0
A188: Purchase of stock | B188: 1 ox bought there for the same 1 1 shilling 6pence. | C188: 0.08 | D188: 0 | E188: 1 | F188: 6 | H188: 0 | I188: 0 | J188: 0 | K188: 0 | L188: 0 | M188: 0 | N188: 0
A189: Purchase of stock | B189: 1 ox bought there for the same 12 shilling. | C189: 0.6 | D189: 0 | E189: 12 | F189: 0 | H189: 0 | I189: 0 | J189: 0 | K189: 0 | L189: 0 | M189: 0 | N189: 0
A190: Purchase of stock | B190: 1 ox bought there for the same 15 shilling 6pence Total, £8 4 shilling 6.5pence | C190: 8.23 | D190: 8 | E190: 4 | F190: 6.5 | H190: 0 | I190: 0 | J190: 0 | K190: 0 | L190: 0 | M190: 0 | N190: 0
A191: Cost of the dairy | B191: In 4 bushels of salt bought for the dairy 1 shilling 4pence. | C191: 0.07 | D191: 0 | E191: 1 | F191: 4 | H191: 0 | I191: 4 | J191: 0.5 | K191: 0.5 | L191: 0 | M191: 0 | N191: 4
... A204: Cost of the mill | B204: ironwork of 1 pier to enlarge the holes in the foundations where the other piers were being placed 4pence. | C204: 0.02 | D204: 0 | E204: 0 | F204: 4 | H204: 0 | I204: 0 | J204: 0 | K204: 0 | L204: 0 | M204: 0 | N204: 0
A205: Cost of the mill | B205: carpentry done for the said bridge by piece-work by fixed agreement £1 6 shilling 8pence, and .5 quarters of wheat from the granary. | C205: 1.33 | D205: 1 | E205: 6 | F205: 8 | G205: wheat | H205: 5 | I205: 0 | J205: 5 | K205: 5 | L205: 0 | M205: 5 | N205: 0
A206: Cost of the mill | B206: . | C206: 0 | D206: 0 | E206: 0 | F206: 0 | H206: 0 | I206: 0 | J206: 0 | K206: 0 | L206: 0 | M206: 0 | N206: 0
A207: Cost of the mill | B207: 8 cart-loads of stones bought for the bays of the said bridge and for the bays of the lake (la Lak') 1 shilling 4pence. | C207: 0.07 | D207: 0 | E207: 1 | F207: 4 | H207: 0 | I207: 0 | J207: 0 | K207: 0 | L207: 0 | M207: 0 | N207: 0
A208: Cost of the mill | B208: piers bought for the said bridge and other necessaries of the said mill 3 shilling Total, £5 6 shilling 4.75pence | C208: 5.32 | D208: 5 | E208: 6 | F208: 4.75 | H208: 0 | I208: 0 | J208: 0 | K208: 0 | L208: 0 | M208: 0 | N208: 0
A209: Customary payments | B209: In customary payments to 1 reeve, 1 overseer of the harvest, 1 smith, 1 swineherd and 7 ploughmen for their corrodies (corred') at Christmas 1 shilling 10pence, or 2pence each. | C209: 0.09 | D209: 0 | E209: 1 | F209: 10 | H209: 0 | I209: 0 | J209: 0 | K209: 0 | L209: 0 | M209: 0 | N209: 0
A210: Customary payments | B210: . | C210: 0 | D210: 0 | E210: 0 | F210: 0 | H210: 0 | I210: 0 | J210: 0 | K210: 0 | L210: 0 | M210: 0 | N210: 0
A211: Customary payments | B211: customary payment to 28 men mowing the northern meadow and 3 men spreading hay in the same, 4 shilling 4pence and 1 summer cheese. | C211: 0.22 | D211: 0 | E211: 4 | F211: 4 | H211: 0 | I211: 0 | J211: 0 | K211: 0 | L211: 0 | M211: 0 | N211: 0
A212: Customary payments | B212: . | C212: 0 | D212: 0 | E212: 0 | F212: 0 | H212: 0 | I212: 0 | J212: 0 | K212: 0 | L212: 0 | M212: 0 | N212: 0
A213: Customary payments | B213: customary payment for the mowing of the meadows in place of 2 wethers owed to them 2 shilling Total, 8 shilling 2pence | C213: 0.11 | D213: 0 | E213: 2 | F213: 2 | H213: 0 | I213: 0 | J213: 0 | K213: 0 | L213: 0 | M213: 0 | N213: 0
A214: Cost of the harvest | B214: In expenses of 5 harvest boon-works of 375 men reaping as if for 1 day £1 17 shilling 4pence, because they have a meal twice a day. | C214: 1.87 | D214: 1 | E214: 17 | F214: 4 | H214: 0 | I214: 0 | J214: 0 | K214: 0 | L214: 0 | M214: 0 | N214: 0
A215: Cost of the harvest | B215: Total, £1 17 shilling 4pence | C215: 1.87 | D215: 1 | E215: 17 | F215: 4 | H215: 0 | I215: 0 | J215: 0 | K215: 0 | L215: 0 | M215: 0 | N215: 0
...

Sheet Issues of the Grange raw
A1: Heading | B1: Sentence | C1: Quarters 1_x | D1: Bushels 1_x | E1: Sown Quarters | F1: Sown Bushels | G1: Sown Total Quarters | H1: Bought in Quarters | I1: Bought in Bushels | J1: Bought in Total Quarters | K1: Tithe Quarters | L1: Tithe Bushels | M1: Tithe Total Quarters | N1: Manorial servants & livestock Quarters | O1: Manorial servants & livestock Bushels | P1: Manorial servants & livestock Total Quarters | Q1: Sold Quarters | R1: Sold Bushels | S1: Sold Total Quarters | T1: Account Quarters | U1: Account Bushels | V1: Account Total Quarters | W1: bought only | X1: Total Quarters Except 1 | Y1: Total Bushels Except 1 | Z1: Total Corn Cross-Check | AA1: Total Corn Manorial Account | AB1: Corn Quantity Error | AC1: Quarters 1_y | AD1: Bushels 1_y | AE1: Quarters 2 | AF1: Bushels 2 | AG1: Quarters 3 | AH1: Bushels 3 | AI1: Quarters 4 | AJ1: Bushels 4 | AK1: Quarters 5 | AL1: Bushels 5 | AM1: Quarters 6 | AN1: Bushels 6
A2: Total of all allowances and cash deliveries | B2: Total | C2: 0 | D2: 0 | E2: 0 | F2: 0 | G2: 0 | H2: 0 | I2: 0 | J2: 0 | K2: 0 | L2: 0 | M2: 0 | N2: 0 | O2: 0 | P2: 0 | Q2: 0 | R2: 0 | S2: 0 | T2: 0 | U2: 0 | V2: 0 | W2: 0
A3: Wheat | B3: (yield: 4.5-fold less 1 qrl 6.5 bushels in all) | C3: 0 | D3: 0 | E3: 0 | F3: 0 | G3: 0 | H3: 0 | I3: 0 | J3: 0 | K3: 0 | L3: 0 | M3: 0 | N3: 0 | O3: 0 | P3: 0 | Q3: 0 | R3: 0 | S3: 0 | T3: 0 | U3: 0 | V3: 0 | W3: 0 | X3: 0 | Y3: 6.5 | Z3: 0.8125 | AA3: 0.8125 | AB3: 0 | AC3: 0 | AD3: 6.5
A4: Wheat | B4: The same render account for 139 quarters 7.5 bushels of wheat from the whole issue of the grange, threshed by labour service by 2 tallies of struck measure. | C4: 0 | D4: 0 | E4: 0 | F4: 0 | G4: 0 | H4: 0 | I4: 0 | J4: 0 | K4: 0 | L4: 0 | M4: 0 | N4: 0 | O4: 0 | P4: 0 | Q4: 0 | R4: 0 | S4: 0 | T4: 139 | U4: 7.5 | V4: 139.9375 | W4: 0 | X4: 139 | Y4: 7.5 | Z4: 139.9375 | AA4: 139.9375 | AB4: 0 | AC4: 139 | AD4: 7.5
A5: Wheat | B5: 6 quarters 6 bushels of wheat by estimation in 5.5 acres given to the manorial servants for their stipends in summer. | C5: 0 | D5: 0 | E5: 0 | F5: 0 | G5: 0 | H5: 0 | I5: 0 | J5: 0 | K5: 0 | L5: 0 | M5: 0 | N5: 0 | O5: 0 | P5: 0 | Q5: 0 | R5: 0 | S5: 0 | T5: 0 | U5: 0 | V5: 0 | W5: 0 | X5: 6 | Y5: 6 | Z5: 6.75 | AA5: 6.75 | AB5: 0 | AC5: 6 | AD5: 6
A6: Wheat | B6: 7 quarters 6 bushels of wheat bought as noted above. | C6: 0 | D6: 0 | E6: 0 | F6: 0 | G6: 0 | H6: 7 | I6: 6 | J6: 7.75 | K6: 0 | L6: 0 | M6: 0 | N6: 0 | O6: 0 | P6: 0 | Q6: 0 | R6: 0 | S6: 0 | T6: 0 | U6: 0 | V6: 0 | W6: 0 | X6: 7 | Y6: 6 | Z6: 7.75 | AA6: 7.75 | AB6: 0 | AC6: 7 | AD6: 6
A7: Wheat | B7: Total, 154 quarters 3.5 bus, clerk. | C7: 0 | D7: 0 | E7: 0 | F7: 0 | G7: 0 | H7: 0 | I7: 0 | J7: 0 | K7: 0 | L7: 0 | M7: 0 | N7: 0 | O7: 0 | P7: 0 | Q7: 0 | R7: 0 | S7: 0 | T7: 0 | U7: 0 | V7: 0 | W7: 0
A8: Wheat | B8: Sown over 103 acres of land as they lie as they lie in the field, 38 quarters 3 bushels by 1. | C8: 0 | D8: 0 | E8: 38 | F8: 3 | G8: 38.375 | H8: 0 | I8: 0 | J8: 0 | K8: 0 | L8: 0 | M8: 0 | N8: 0 | O8: 0 | P8: 0 | Q8: 0 | R8: 0 | S8: 0 | T8: 0 | U8: 0 | V8: 0 | W8: 0 | X8: 38 | Y8: 3 | Z8: 38.375 | AA8: 38.375 | AB8: 0 | AC8: 38 | AD8: 3
A9: Wheat | B9: that is 3 bushels an acre, less 2 bushels in all. | C9: 0 | D9: 0 | E9: 0 | F9: 0 | G9: 0 | H9: 0 | I9: 0 | J9: 0 | K9: 0 | L9: 0 | M9: 0 | N9: 0 | O9: 0 | P9: 0 | Q9: 0 | R9: 0 | S9: 0 | T9: 0 | U9: 0 | V9: 0 | W9: 0 | X9: 0 | Y9: 2 | Z9: 0.25 | AA9: 0.375 | AB9: -0.125 | AC9: 0 | AD9: 3 | AE9: 0 | AF9: 2
A10: Wheat | B10: . | C10: 0 | D10: 0 | E10: 0 | F10: 0 | G10: 0 | H10: 0 | I10: 0 | J10: 0 | K10: 0 | L10: 0 | M10: 0 | N10: 0 | O10: 0 | P10: 0 | Q10: 0 | R10: 0 | S10: 0 | T10: 0 | U10: 0 | V10: 0 | W10: 0 | X10: 0 | Y10: 0 | Z10: 0 | AA10: 0 | AB10: 0 | AC10: 0 | AD10: 0
A11: Wheat | B11: . | C11: 0 | D11: 0 | E11: 0 | F11: 0 | G11: 0 | H11: 0 | I11: 0 | J11: 0 | K11: 0 | L11: 0 | M11: 0 | N11: 0 | O11: 0 | P11: 0 | Q11: 0 | R11: 0 | S11: 0 | T11: 0 | U11: 0 | V11: 0 | W11: 0 | X11: 0 | Y11: 0 | Z11: 0 | AA11: 0 | AB11: 0 | AC11: 0 | AD11: 0
A12: Wheat | B12: . | C12: 0 | D12: 0 | E12: 0 | F12: 0 | G12: 0 | H12: 0 | I12: 0 | J12: 0 | K12: 0 | L12: 0 | M12: 0 | N12: 0 | O12: 0 | P12: 0 | Q12: 0 | R12: 0 | S12: 0 | T12: 0 | U12: 0 | V12: 0 | W12: 0 | X12: 0 | Y12: 0 | Z12: 0 | AA12: 0 | AB12: 0 | AC12: 0 | AD12: 0
A13: Wheat | B13: . | C13: 0 | D13: 0 | E13: 0 | F13: 0 | G13: 0 | H13: 0 | I13: 0 | J13: 0 | K13: 0 | L13: 0 | M13: 0 | N13: 0 | O13: 0 | P13: 0 | Q13: 0 | R13: 0 | S13: 0 | T13: 0 | U13: 0 | V13: 0 | W13: 0 | X13: 0 | Y13: 0 | Z13: 0 | AA13: 0 | AB13: 0 | AC13: 0 | AD13: 0
A14: Wheat | B14: provision of Sir Robert, steward, and Simon, clerk for their visits, that is, in bread baked for their use, 1 qr 1 bushels by 3 tallies with their expenses. | C14: 0 | D14: 0 | E14: 0 | F14: 0 | G14: 0 | H14: 0 | I14: 0 | J14: 0 | K14: 0 | L14: 0 | M14: 0 | N14: 0 | O14: 0 | P14: 0 | Q14: 0 | R14: 0 | S14: 0 | T14: 0 | U14: 0 | V14: 0 | W14: 0
A15: Wheat | B15: . | C15: 0 | D15: 0 | E15: 0 | F15: 0 | G15: 0 | H15: 0 | I15: 0 | J15: 0 | K15: 0 | L15: 0 | M15: 0 | N15: 0 | O15: 0 | P15: 0 | Q15: 0 | R15: 0 | S15: 0 | T15: 0 | U15: 0 | V15: 0 | W15: 0 | X15: 0 | Y15: 0 | Z15: 0 | AA15: 0 | AB15: 0 | AC15: 0 | AD15: 0
A16: Wheat | B16: . | C16: 0 | D16: 0 | E16: 0 | F16: 0 | G16: 0 | H16: 0 | I16: 0 | J16: 0 | K16: 0 | L16: 0 | M16: 0 | N16: 0 | O16: 0 | P16: 0 | Q16: 0 | R16: 0 | S16: 0 | T16: 0 | U16: 0 | V16: 0 | W16: 0 | X16: 0 | Y16: 0 | Z16: 0 | AA16: 0 | AB16: 0 | AC16: 0 | AD16: 0
A17: Wheat | B17: . | C17: 0 | D17: 0 | E17: 0 | F17: 0 | G17: 0 | H17: 0 | I17: 0 | J17: 0 | K17: 0 | L17: 0 | M17: 0 | N17: 0 | O17: 0 | P17: 0 | Q17: 0 | R17: 0 | S17: 0 | T17: 0 | U17: 0 | V17: 0 | W17: 0 | X17: 0 | Y17: 0 | Z17: 0 | AA17: 0 | AB17: 0 | AC17: 0 | AD17: 0
A18: Wheat | B18: . | C18: 0 | D18: 0 | E18: 0 | F18: 0 | G18: 0 | H18: 0 | I18: 0 | J18: 0 | K18: 0 | L18: 0 | M18: 0 | N18: 0 | O18: 0 | P18: 0 | Q18: 0 | R18: 0 | S18: 0 | T18: 0 | U18: 0 | V18: 0 | W18: 0 | X18: 0 | Y18: 0 | Z18: 0 | AA18: 0 | AB18: 0 | AC18: 0 | AD18: 0
A19: Wheat | B19: provision of Walter de Polton after Michaelmas, 1 qr, that is, in bread by 1 tally with his expenses. | C19: 0 | D19: 0 | E19: 0 | F19: 0 | G19: 0 | H19: 0 | I19: 0 | J19: 0 | K19: 0 | L19: 0 | M19: 0 | N19: 0 | O19: 0 | P19: 0 | Q19: 0 | R19: 0 | S19: 0 | T19: 0 | U19: 0 | V19: 0 | W19: 0
A20: Wheat | B20: Given to the steward and constable of Wallingford Castle, 1 qr. | C20: 0 | D20: 0 | E20: 0 | F20: 0 | G20: 0 | H20: 0 | I20: 0 | J20: 0 | K20: 0 | L20: 0 | M20: 0 | N20: 0 | O20: 0 | P20: 0 | Q20: 0 | R20: 0 | S20: 0 | T20: 0 | U20: 0 | V20: 0 | W20: 0
A21: Wheat | B21: . | C21: 0 | D21: 0 | E21: 0 | F21: 0 | G21: 0 | H21: 0 | I21: 0 | J21: 0 | K21: 0 | L21: 0 | M21: 0 | N21: 0 | O21: 0 | P21: 0 | Q21: 0 | R21: 0 | S21: 0 | T21: 0 | U21: 0 | V21: 0 | W21: 0 | X21: 0 | Y21: 0 | Z21: 0 | AA21: 0 | AB21: 0 | AC21: 0 | AD21: 0
A22: Wheat | B22: . | C22: 0 | D22: 0 | E22: 0 | F22: 0 | G22: 0 | H22: 0 | I22: 0 | J22: 0 | K22: 0 | L22: 0 | M22: 0 | N22: 0 | O22: 0 | P22: 0 | Q22: 0 | R22: 0 | S22: 0 | T22: 0 | U22: 0 | V22: 0 | W22: 0 | X22: 0 | Y22: 0 | Z22: 0 | AA22: 0 | AB22: 0 | AC22: 0 | AD22: 0
A23: Wheat | B23: . | C23: 0 | D23: 0 | E23: 0 | F23: 0 | G23: 0 | H23: 0 | I23: 0 | J23: 0 | K23: 0 | L23: 0 | M23: 0 | N23: 0 | O23: 0 | P23: 0 | Q23: 0 | R23: 0 | S23: 0 | T23: 0 | U23: 0 | V23: 0 | W23: 0 | X23: 0 | Y23: 0 | Z23: 0 | AA23: 0 | AB23: 0 | AC23: 0 | AD23: 0
A24: Wheat | B24: . | C24: 0 | D24: 0 | E24: 0 | F24: 0 | G24: 0 | H24: 0 | I24: 0 | J24: 0 | K24: 0 | L24: 0 | M24: 0 | N24: 0 | O24: 0 | P24: 0 | Q24: 0 | R24: 0 | S24: 0 | T24: 0 | U24: 0 | V24: 0 | W24: 0 | X24: 0 | Y24: 0 | Z24: 0 | AA24: 0 | AB24: 0 | AC24: 0 | AD24: 0
A25: Wheat | B25: agreement with Jordan (Joriad') le Carpenter for making the bridge of the mill, 0.5 qr. | C25: 0 | D25: 0 | E25: 0 | F25: 0 | G25: 0 | H25: 0 | I25: 0 | J25: 0 | K25: 0 | L25: 0 | M25: 0 | N25: 0 | O25: 0 | P25: 0 | Q25: 0 | R25: 0 | S25: 0 | T25: 0 | U25: 0 | V25: 0 | W25: 0
A26: Wheat | B26: Given to Sibyl de Morton', 2 bushels. | C26: 0 | D26: 0 | E26: 0 | F26: 0 | G26: 0 | H26: 0 | I26: 0 | J26: 0 | K26: 0 | L26: 0 | M26: 0 | N26: 0 | O26: 0 | P26: 0 | Q26: 0 | R26: 0 | S26: 0 | T26: 0 | U26: 0 | V26: 0 | W26: 0 | X26: 0 | Y26: 2 | Z26: 0.25 | AA26: 0.25 | AB26: 0 | AC26: 0 | AD26: 2
A27: Wheat | B27: customary payment to the overseer of the harvest for his fee, 1 bushels, because it is found to be the custom. | C27: 0 | D27: 0 | E27: 0 | F27: 0 | G27: 0 | H27: 0 | I27: 0 | J27: 0 | K27: 0 | L27: 0 | M27: 0 | N27: 0 | O27: 0 | P27: 0 | Q27: 0 | R27: 0 | S27: 0 | T27: 0 | U27: 0 | V27: 0 | W27: 0 | X27: 0 | Y27: 1 | Z27: 0.125 | AA27: 0.125 | AB27: 0 | AC27: 0 | AD27: 1
A28: Wheat | B28: . | C28: 0 | D28: 0 | E28: 0 | F28: 0 | G28: 0 | H28: 0 | I28: 0 | J28: 0 | K28: 0 | L28: 0 | M28: 0 | N28: 0 | O28: 0 | P28: 0 | Q28: 0 | R28: 0 | S28: 0 | T28: 0 | U28: 0 | V28: 0 | W28: 0 | X28: 0 | Y28: 0 | Z28: 0 | AA28: 0 | AB28: 0 | AC28: 0 | AD28: 0
A29: Wheat | B29: . | C29: 0 | D29: 0 | E29: 0 | F29: 0 | G29: 0 | H29: 0 | I29: 0 | J29: 0 | K29: 0 | L29: 0 | M29: 0 | N29: 0 | O29: 0 | P29: 0 | Q29: 0 | R29: 0 | S29: 0 | T29: 0 | U29: 0 | V29: 0 | W29: 0 | X29: 0 | Y29: 0 | Z29: 0 | AA29: 0 | AB29: 0 | AC29: 0 | AD29: 0
A30: Wheat | B30: . | C30: 0 | D30: 0 | E30: 0 | F30: 0 | G30: 0 | H30: 0 | I30: 0 | J30: 0 | K30: 0 | L30: 0 | M30: 0 | N30: 0 | O30: 0 | P30: 0 | Q30: 0 | R30: 0 | S30: 0 | T30: 0 | U30: 0 | V30: 0 | W30: 0 | X30: 0 | Y30: 0 | Z30: 0 | AA30: 0 | AB30: 0 | AC30: 0 | AD30: 0
A31: Wheat | B31: . | C31: 0 | D31: 0 | E31: 0 | F31: 0 | G31: 0 | H31: 0 | I31: 0 | J31: 0 | K31: 0 | L31: 0 | M31: 0 | N31: 0 | O31: 0 | P31: 0 | Q31: 0 | R31: 0 | S31: 0 | T31: 0 | U31: 0 | V31: 0 | W31: 0 | X31: 0 | Y31: 0 | Z31: 0 | AA31: 0 | AB31: 0 | AC31: 0 | AD31: 0
A32: Wheat | B32: stipend of 1 reeve, 1 overseer of the harvest, 1 carter and 3 ploughmen for their stipends in summer, 6 quarters 6 bushels, that is, in 5.5 acres of wheat delivered to them. | C32: 0 | D32: 0 | E32: 0 | F32: 0 | G32: 0 | H32: 0 | I32: 0 | J32: 0 | K32: 0 | L32: 0 | M32: 0 | N32: 0 | O32: 0 | P32: 0 | Q32: 0 | R32: 0 | S32: 0 | T32: 0 | U32: 0 | V32: 0 | W32: 0 | X32: 6 | Y32: 6 | Z32: 6.75 | AA32: 6.75 | AB32: 0 | AC32: 6 | AD32: 6
A33: Wheat | B33: Sold, 105 quarters 2.5 bushels Total, 154 quarters 3.5 bushels None remains. | C33: 0 | D33: 0 | E33: 0 | F33: 0 | G33: 0 | H33: 0 | I33: 0 | J33: 0 | K33: 0 | L33: 0 | M33: 0 | N33: 0 | O33: 0 | P33: 0 | Q33: 259 | R33: 6 | S33: 259.75 | T33: 0 | U33: 0 | V33: 0 | W33: 0 | X33: 154 | Y33: 3.5 | Z33: 154.4375 | AA33: 105.3125 | AB33: 49.125 | AC33: 105 | AD33: 2.5 | AE33: 154 | AF33: 3.5
A34: Wheat | B34: Total | C34: 0 | D34: 0 | E34: 0 | F34: 0 | G34: 0 | H34: 0 | I34: 0 | J34: 0 | K34: 0 | L34: 0 | M34: 0 | N34: 0 | O34: 0 | P34: 0 | Q34: 0 | R34: 0 | S34: 0 | T34: 0 | U34: 0 | V34: 0 | W34: 0
A35: Rye | B35: {yield: 3.5-fold plus 4 quarters 6 bushels) | C35: 0 | D35: 0 | E35: 0 | F35: 0 | G35: 0 | H35: 0 | I35: 0 | J35: 0 | K35: 0 | L35: 0 | M35: 0 | N35: 0 | O35: 0 | P35: 0 | Q35: 0 | R35: 0 | S35: 0 | T35: 0 | U35: 0 | V35: 0 | W35: 0 | X35: 4 | Y35: 6 | Z35: 4.75 | AA35: 4.75 | AB35: 0 | AC35: 4 | AD35: 6
A36: Rye | B36: The same render account for 73 quarters from the issue of the grange, threshed by labour service by 2 tallies of struck measure. | C36: 0 | D36: 0 | E36: 0 | F36: 0 | G36: 0 | H36: 0 | I36: 0 | J36: 0 | K36: 0 | L36: 0 | M36: 0 | N36: 0 | O36: 0 | P36: 0 | Q36: 0 | R36: 0 | S36: 0 | T36: 73 | U36: 0 | V36: 73 | W36: 0 | X36: 73 | Y36: 0 | Z36: 73 | AA36: 73 | AB36: 0 | AC36: 73 | AD36: 0
A37: Rye | B37: Total, 73 quarters. | C37: 0 | D37: 0 | E37: 0 | F37: 0 | G37: 0 | H37: 0 | I37: 0 | J37: 0 | K37: 0 | L37: 0 | M37: 0 | N37: 0 | O37: 0 | P37: 0 | Q37: 0 | R37: 0 | S37: 0 | T37: 0 | U37: 0 | V37: 0 | W37: 0 | X37: 73 | Y37: 0 | Z37: 73 | AA37: 73 | AB37: 0 | AC37: 73 | AD37: 0
A38: Rye | B38: Sown over 52 acres of land as they lie in the field, 16 quarters 3 bushels by 1 tally. | C38: 0 | D38: 0 | E38: 16 | F38: 3 | G38: 16.375 | H38: 0 | I38: 0 | J38: 0 | K38: 0 | L38: 0 | M38: 0 | N38: 0 | O38: 0 | P38: 0 | Q38: 0 | R38: 0 | S38: 0 | T38: 0 | U38: 0 | V38: 0 | W38: 0 | X38: 16 | Y38: 3 | Z38: 16.375 | AA38: 16.375 | AB38: 0 | AC38: 16 | AD38: 3
A39: Rye | B39: that is, 2.5 bushels an acre, plus 1 bushels in all. | C39: 0 | D39: 0 | E39: 0 | F39: 0 | G39: 0 | H39: 0 | I39: 0 | J39: 0 | K39: 0 | L39: 0 | M39: 0 | N39: 0 | O39: 0 | P39: 0 | Q39: 0 | R39: 0 | S39: 0 | T39: 0 | U39: 0 | V39: 0 | W39: 0 | X39: 0 | Y39: 1 | Z39: 0.125 | AA39: 0.3125 | AB39: -0.1875 | AC39: 0 | AD39: 2.5 | AE39: 0 | AF39: 1
A40: Rye | B40: Delivered to 1 carter and 3 ploughmen for the year, 20 quarters 6 bushels, or 5 quarters 1.5 bushels each, taking a quarter every 10 weeks. | C40: 0 | D40: 0 | E40: 0 | F40: 0 | G40: 0 | H40: 0 | I40: 0 | J40: 0 | K40: 0 | L40: 0 | M40: 0 | N40: 0 | O40: 0 | P40: 0 | Q40: 0 | R40: 0 | S40: 0 | T40: 0 | U40: 0 | V40: 0 | W40: 0 | X40: 5 | Y40: 1.5 | Z40: 5.1875 | AA40: 20.75 | AB40: -15.5625 | AC40: 20 | AD40: 6 | AE40: 5 | AF40: 1.5
A41: Rye | B41: Delivered to 1 cowherd for the year, 3 quarters of rye, taking a quarter every 14 weeks and not more because he takes the rest from the men whose cows have rights of common with the lord's cows. | C41: 0 | D41: 0 | E41: 0 | F41: 0 | G41: 0 | H41: 0 | I41: 0 | J41: 0 | K41: 0 | L41: 0 | M41: 0 | N41: 0 | O41: 0 | P41: 0 | Q41: 0 | R41: 0 | S41: 0 | T41: 0 | U41: 0 | V41: 0 | W41: 0 | X41: 3 | Y41: 0 | Z41: 3 | AA41: 3 | AB41: 0 | AC41: 3 | AD41: 0
A42: Rye | B42: Delivered to 1 dairymaid for the year, 3 quarters 6 bushels, taking a quarter every 14 weeks. | C42: 0 | D42: 0 | E42: 0 | F42: 0 | G42: 0 | H42: 0 | I42: 0 | J42: 0 | K42: 0 | L42: 0 | M42: 0 | N42: 0 | O42: 0 | P42: 0 | Q42: 0 | R42: 0 | S42: 0 | T42: 0 | U42: 0 | V42: 0 | W42: 0 | X42: 3 | Y42: 6 | Z42: 3.75 | AA42: 3.75 | AB42: 0 | AC42: 3 | AD42: 6
A43: Rye | B43: Sold, 28 quarters 3 bushels Sold at the audit, 6 bushels Total, 73 quarters. | C43: 0 | D43: 0 | E43: 0 | F43: 0 | G43: 0 | H43: 0 | I43: 0 | J43: 0 | K43: 0 | L43: 0 | M43: 0 | N43: 0 | O43: 0 | P43: 0 | Q43: 101 | R43: 3 | S43: 101.375 | T43: 0 | U43: 0 | V43: 0 | W43: 0 | X43: 73 | Y43: 6 | Z43: 73.75 | AA43: 28.375 | AB43: 45.375 | AC43: 28 | AD43: 3 | AE43: 0 | AF43: 6 | AG43: 73 | AH43: 0
A44: Rye | B44: None remains. | C44: 0 | D44: 0 | E44: 0 | F44: 0 | G44: 0 | H44: 0 | I44: 0 | J44: 0 | K44: 0 | L44: 0 | M44: 0 | N44: 0 | O44: 0 | P44: 0 | Q44: 0 | R44: 0 | S44: 0 | T44: 0 | U44: 0 | V44: 0 | W44: 0 | X44: 0 | Y44: 0 | Z44: 0 | AA44: 0 | AB44: 0 | AC44: 0 | AD44: 0
A45: Rye | B45: Total | C45: 0 | D45: 0 | E45: 0 | F45: 0 | G45: 0 | H45: 0 | I45: 0 | J45: 0 | K45: 0 | L45: 0 | M45: 0 | N45: 0 | O45: 0 | P45: 0 | Q45: 0 | R45: 0 | S45: 0 | T45: 0 | U45: 0 | V45: 0 | W45: 0
A46: Barley | B46: {yield: 5.5-fold less 4 quarters 7 bushels} | C46: 0 | D46: 0 | E46: 0 | F46: 0 | G46: 0 | H46: 0 | I46: 0 | J46: 0 | K46: 0 | L46: 0 | M46: 0 | N46: 0 | O46: 0 | P46: 0 | Q46: 0 | R46: 0 | S46: 0 | T46: 0 | U46: 0 | V46: 0 | W46: 0 | X46: 4 | Y46: 7 | Z46: 4.875 | AA46: 4.875 | AB46: 0 | AC46: 4 | AD46: 7
A47: Barley | B47: The same render account for 150.5 quarters of barley from the whole issue of the grange by 1 tally of struck measure, 26 quarters by piece-work, and 124 quarters by labour service. | C47: 0 | D47: 0 | E47: 0 | F47: 0 | G47: 0 | H47: 0 | I47: 0 | J47: 0 | K47: 0 | L47: 0 | M47: 0 | N47: 0 | O47: 0 | P47: 0 | Q47: 0 | R47: 0 | S47: 0 | T47: 300.5 | U47: 0 | V47: 300.5 | W47: 0 | X47: 150 | Y47: 0 | Z47: 150 | AA47: 150.5 | AB47: -0.5 | AC47: 150.5 | AD47: 0 | AE47: 26 | AF47: 0 | AG47: 124 | AH47: 0
A48: Barley | B48: Total, 150.5 quarters. | C48: 0 | D48: 0 | E48: 0 | F48: 0 | G48: 0 | H48: 0 | I48: 0 | J48: 0 | K48: 0 | L48: 0 | M48: 0 | N48: 0 | O48: 0 | P48: 0 | Q48: 0 | R48: 0 | S48: 0 | T48: 0 | U48: 0 | V48: 0 | W48: 0 | X48: 150.5 | Y48: 0 | Z48: 150.5 | AA48: 150.5 | AB48: 0 | AC48: 150.5 | AD48: 0
A49: Barley | B49: Sown over 65 acres of land as they lie in the field, 31 quarters by 1 tally. | C49: 0 | D49: 0 | E49: 31 | F49: 0 | G49: 31 | H49: 0 | I49: 0 | J49: 0 | K49: 0 | L49: 0 | M49: 0 | N49: 0 | O49: 0 | P49: 0 | Q49: 0 | R49: 0 | S49: 0 | T49: 0 | U49: 0 | V49: 0 | W49: 0 | X49: 31 | Y49: 0 | Z49: 31 | AA49: 31 | AB49: 0 | AC49: 31 | AD49: 0
A50: Barley | B50: that is, 3.5 bushels 1 peck an acre, plus .5 qr 1 peck. | C50: 0 | D50: 0 | E50: 0 | F50: 0 | G50: 0 | H50: 0 | I50: 0 | J50: 0 | K50: 0 | L50: 0 | M50: 0 | N50: 0 | O50: 0 | P50: 0 | Q50: 0 | R50: 0 | S50: 0 | T50: 0 | U50: 0 | V50: 0 | W50: 0
A51: Barley | B51: . | C51: 0 | D51: 0 | E51: 0 | F51: 0 | G51: 0 | H51: 0 | I51: 0 | J51: 0 | K51: 0 | L51: 0 | M51: 0 | N51: 0 | O51: 0 | P51: 0 | Q51: 0 | R51: 0 | S51: 0 | T51: 0 | U51: 0 | V51: 0 | W51: 0 | X51: 0 | Y51: 0 | Z51: 0 | AA51: 0 | AB51: 0 | AC51: 0 | AD51: 0
A52: Barley | B52: customary payment to 1 overseer of the harvest for sowing (sedcod), 1 bushels, because it is found to be the custom and always receivepence Sold, 118 quarters 7 bushels Sold at the audit, 0.5 qr. | C52: 0 | D52: 0 | E52: 0 | F52: 0 | G52: 0 | H52: 0 | I52: 0 | J52: 0 | K52: 0 | L52: 0 | M52: 0 | N52: 0 | O52: 0 | P52: 0 | Q52: 118 | R52: 7 | S52: 118.875 | T52: 0 | U52: 0 | V52: 0 | W52: 0
A53: Barley | B53: Total, 150 quarters.2 None remains. | C53: 0 | D53: 0 | E53: 0 | F53: 0 | G53: 0 | H53: 0 | I53: 0 | J53: 0 | K53: 0 | L53: 0 | M53: 0 | N53: 0 | O53: 0 | P53: 0 | Q53: 0 | R53: 0 | S53: 0 | T53: 0 | U53: 0 | V53: 0 | W53: 0 | X53: 150 | Y53: 0 | Z53: 150 | AA53: 150 | AB53: 0 | AC53: 150 | AD53: 0
A54: Barley | B54: Total | C54: 0 | D54: 0 | E54: 0 | F54: 0 | G54: 0 | H54: 0 | I54: 0 | J54: 0 | K54: 0 | L54: 0 | M54: 0 | N54: 0 | O54: 0 | P54: 0 | Q54: 0 | R54: 0 | S54: 0 | T54: 0 | U54: 0 | V54: 0 | W54: 0
A55: Dredge | B55: {yield: three-fold plus 1 bushels) | C55: 0 | D55: 0 | E55: 0 | F55: 0 | G55: 0 | H55: 0 | I55: 0 | J55: 0 | K55: 0 | L55: 0 | M55: 0 | N55: 0 | O55: 0 | P55: 0 | Q55: 0 | R55: 0 | S55: 0 | T55: 0 | U55: 0 | V55: 0 | W55: 0 | X55: 0 | Y55: 1 | Z55: 0.125 | AA55: 0.125 | AB55: 0 | AC55: 0 | AD55: 1
A56: Dredge | B56: The same render account for 33 quarters 1 bushels of dredge from the whole issue of the grange, threshed by labour service by 1 tally of struck measure. | C56: 0 | D56: 0 | E56: 0 | F56: 0 | G56: 0 | H56: 0 | I56: 0 | J56: 0 | K56: 0 | L56: 0 | M56: 0 | N56: 0 | O56: 0 | P56: 0 | Q56: 0 | R56: 0 | S56: 0 | T56: 33 | U56: 1 | V56: 33.125 | W56: 0 | X56: 33 | Y56: 1 | Z56: 33.125 | AA56: 33.125 | AB56: 0 | AC56: 33 | AD56: 1
A57: Dredge | B57: Total, 33 quarters 1 bushels Sown over 55 acres of land as they lie in the field, 15.5 quarters by 1 tally. | C57: 0 | D57: 0 | E57: 48.5 | F57: 1 | G57: 48.625 | H57: 0 | I57: 0 | J57: 0 | K57: 0 | L57: 0 | M57: 0 | N57: 0 | O57: 0 | P57: 0 | Q57: 0 | R57: 0 | S57: 0 | T57: 0 | U57: 0 | V57: 0 | W57: 0 | X57: 15.5 | Y57: 1 | Z57: 15.625 | AA57: 33.125 | AB57: -17.5 | AC57: 33 | AD57: 1 | AE57: 15.5 | AF57: 0
A58: Dredge | B58: . | C58: 0 | D58: 0 | E58: 0 | F58: 0 | G58: 0 | H58: 0 | I58: 0 | J58: 0 | K58: 0 | L58: 0 | M58: 0 | N58: 0 | O58: 0 | P58: 0 | Q58: 0 | R58: 0 | S58: 0 | T58: 0 | U58: 0 | V58: 0 | W58: 0 | X58: 0 | Y58: 0 | Z58: 0 | AA58: 0 | AB58: 0 | AC58: 0 | AD58: 0
A59: Dredge | B59: supporting pigs for the year, 1 qr 3 bushels Sold, 16 quarters 2 bushels Total, 33 quarters 1 bushels None remains. | C59: 0 | D59: 0 | E59: 0 | F59: 0 | G59: 0 | H59: 0 | I59: 0 | J59: 0 | K59: 0 | L59: 0 | M59: 0 | N59: 0 | O59: 0 | P59: 0 | Q59: 49 | R59: 3 | S59: 49.375 | T59: 0 | U59: 0 | V59: 0 | W59: 0
A60: Dredge | B60: Total | C60: 0 | D60: 0 | E60: 0 | F60: 0 | G60: 0 | H60: 0 | I60: 0 | J60: 0 | K60: 0 | L60: 0 | M60: 0 | N60: 0 | O60: 0 | P60: 0 | Q60: 0 | R60: 0 | S60: 0 | T60: 0 | U60: 0 | V60: 0 | W60: 0
A61: Oats | B61: {yield: 6 bushels less than sown) The same render account for 8 quarters 7 bushels of oats from the whole issue of the grange, threshed by labour service by 2 tallies of struck measure. | C61: 0 | D61: 0 | E61: 8 | F61: 7 | G61: 8.875 | H61: 0 | I61: 0 | J61: 0 | K61: 0 | L61: 0 | M61: 0 | N61: 0 | O61: 0 | P61: 0 | Q61: 0 | R61: 0 | S61: 0 | T61: 8 | U61: 7 | V61: 8.875 | W61: 0 | X61: 8 | Y61: 7 | Z61: 8.875 | AA61: 0.75 | AB61: 8.125 | AC61: 0 | AD61: 6 | AE61: 8 | AF61: 7
A62: Oats | B62: 10 quarters 5 bushels of oats bought. | C62: 0 | D62: 0 | E62: 0 | F62: 0 | G62: 0 | H62: 10 | I62: 5 | J62: 10.625 | K62: 0 | L62: 0 | M62: 0 | N62: 0 | O62: 0 | P62: 0 | Q62: 0 | R62: 0 | S62: 0 | T62: 0 | U62: 0 | V62: 0 | W62: 0 | X62: 10 | Y62: 5 | Z62: 10.625 | AA62: 10.625 | AB62: 0 | AC62: 10 | AD62: 5
A63: Oats | B63: Total, 19.5 quarters. | C63: 0 | D63: 0 | E63: 0 | F63: 0 | G63: 0 | H63: 0 | I63: 0 | J63: 0 | K63: 0 | L63: 0 | M63: 0 | N63: 0 | O63: 0 | P63: 0 | Q63: 0 | R63: 0 | S63: 0 | T63: 0 | U63: 0 | V63: 0 | W63: 0 | X63: 19.5 | Y63: 0 | Z63: 19.5 | AA63: 19.5 | AB63: 0 | AC63: 19.5 | AD63: 0
A64: Oats | B64: Sown over 23 acres of land as they lie in the field, 8 quarters 1 bushels by 1 tally. | C64: 0 | D64: 0 | E64: 8 | F64: 1 | G64: 8.125 | H64: 0 | I64: 0 | J64: 0 | K64: 0 | L64: 0 | M64: 0 | N64: 0 | O64: 0 | P64: 0 | Q64: 0 | R64: 0 | S64: 0 | T64: 0 | U64: 0 | V64: 0 | W64: 0 | X64: 8 | Y64: 1 | Z64: 8.125 | AA64: 8.125 | AB64: 0 | AC64: 8 | AD64: 1
A65: Oats | B65: that is, 2 bushels | C65: 0 | D65: 0 | E65: 0 | F65: 0 | G65: 0 | H65: 0 | I65: 0 | J65: 0 | K65: 0 | L65: 0 | M65: 0 | N65: 0 | O65: 0 | P65: 0 | Q65: 0 | R65: 0 | S65: 0 | T65: 0 | U65: 0 | V65: 0 | W65: 0 | X65: 0 | Y65: 2 | Z65: 0.25 | AA65: 0.25 | AB65: 0 | AC65: 0 | AD65: 2
A66: Oats | B66: 3 pecks an acre, [plus] 1 bushels 3 pecks. | C66: 0 | D66: 0 | E66: 0 | F66: 0 | G66: 0 | H66: 0 | I66: 0 | J66: 0 | K66: 0 | L66: 0 | M66: 0 | N66: 0 | O66: 0 | P66: 0 | Q66: 0 | R66: 0 | S66: 0 | T66: 0 | U66: 0 | V66: 0 | W66: 0 | X66: 0 | Y66: 1 | Z66: 0.125 | AA66: 0.125 | AB66: 0 | AC66: 0 | AD66: 1
A67: Oats | B67: . | C67: 0 | D67: 0 | E67: 0 | F67: 0 | G67: 0 | H67: 0 | I67: 0 | J67: 0 | K67: 0 | L67: 0 | M67: 0 | N67: 0 | O67: 0 | P67: 0 | Q67: 0 | R67: 0 | S67: 0 | T67: 0 | U67: 0 | V67: 0 | W67: 0 | X67: 0 | Y67: 0 | Z67: 0 | AA67: 0 | AB67: 0 | AC67: 0 | AD67: 0
A68: Oats | B68: . | C68: 0 | D68: 0 | E68: 0 | F68: 0 | G68: 0 | H68: 0 | I68: 0 | J68: 0 | K68: 0 | L68: 0 | M68: 0 | N68: 0 | O68: 0 | P68: 0 | Q68: 0 | R68: 0 | S68: 0 | T68: 0 | U68: 0 | V68: 0 | W68: 0 | X68: 0 | Y68: 0 | Z68: 0 | AA68: 0 | AB68: 0 | AC68: 0 | AD68: 0
A69: Oats | B69: . | C69: 0 | D69: 0 | E69: 0 | F69: 0 | G69: 0 | H69: 0 | I69: 0 | J69: 0 | K69: 0 | L69: 0 | M69: 0 | N69: 0 | O69: 0 | P69: 0 | Q69: 0 | R69: 0 | S69: 0 | T69: 0 | U69: 0 | V69: 0 | W69: 0 | X69: 0 | Y69: 0 | Z69: 0 | AA69: 0 | AB69: 0 | AC69: 0 | AD69: 0
A70: Oats | B70: fodder of the horses of the steward and Simon for their visits for the year, 2 quarters by 2 tallies with their expenses. | C70: 0 | D70: 0 | E70: 0 | F70: 0 | G70: 0 | H70: 0 | I70: 0 | J70: 0 | K70: 0 | L70: 0 | M70: 0 | N70: 2 | O70: 0 | P70: 2 | Q70: 0 | R70: 0 | S70: 0 | T70: 0 | U70: 0 | V70: 0 | W70: 0 | X70: 2 | Y70: 0 | Z70: 2 | AA70: 2 | AB70: 0 | AC70: 2 | AD70: 0
A71: Oats | B71: . | C71: 0 | D71: 0 | E71: 0 | F71: 0 | G71: 0 | H71: 0 | I71: 0 | J71: 0 | K71: 0 | L71: 0 | M71: 0 | N71: 0 | O71: 0 | P71: 0 | Q71: 0 | R71: 0 | S71: 0 | T71: 0 | U71: 0 | V71: 0 | W71: 0 | X71: 0 | Y71: 0 | Z71: 0 | AA71: 0 | AB71: 0 | AC71: 0 | AD71: 0
A72: Oats | B72: . | C72: 0 | D72: 0 | E72: 0 | F72: 0 | G72: 0 | H72: 0 | I72: 0 | J72: 0 | K72: 0 | L72: 0 | M72: 0 | N72: 0 | O72: 0 | P72: 0 | Q72: 0 | R72: 0 | S72: 0 | T72: 0 | U72: 0 | V72: 0 | W72: 0 | X72: 0 | Y72: 0 | Z72: 0 | AA72: 0 | AB72: 0 | AC72: 0 | AD72: 0
A73: Oats | B73: . | C73: 0 | D73: 0 | E73: 0 | F73: 0 | G73: 0 | H73: 0 | I73: 0 | J73: 0 | K73: 0 | L73: 0 | M73: 0 | N73: 0 | O73: 0 | P73: 0 | Q73: 0 | R73: 0 | S73: 0 | T73: 0 | U73: 0 | V73: 0 | W73: 0 | X73: 0 | Y73: 0 | Z73: 0 | AA73: 0 | AB73: 0 | AC73: 0 | AD73: 0
... A78: Oats | B78: fodder of 2 cart-horses for the year, 7 quarters 2 bushels, sometimes more, sometimes less, as they labourepence. | C78: 0 | D78: 0 | E78: 0 | F78: 0 | G78: 0 | H78: 0 | I78: 0 | J78: 0 | K78: 0 | L78: 0 | M78: 0 | N78: 7 | O78: 2 | P78: 7.25 | Q78: 0 | R78: 0 | S78: 0 | T78: 0 | U78: 0 | V78: 0 | W78: 0 | X78: 7 | Y78: 2 | Z78: 7.25 | AA78: 7.25 | AB78: 0 | AC78: 7 | AD78: 2
A79: Oats | B79: customary payment to the overseer of the harvest for sowing (sedcod), 1 bushels, because it is found to be the custom and always hapence Total, 19.5 quarters. | C79: 0 | D79: 0 | E79: 0 | F79: 0 | G79: 0 | H79: 0 | I79: 0 | J79: 0 | K79: 0 | L79: 0 | M79: 0 | N79: 0 | O79: 0 | P79: 0 | Q79: 0 | R79: 0 | S79: 0 | T79: 0 | U79: 0 | V79: 0 | W79: 0 | X79: 19.5 | Y79: 1 | Z79: 19.625 | AA79: 0.125 | AB79: 19.5 | AC79: 0 | AD79: 1 | AE79: 19.5 | AF79: 0
A80: Oats | B80: None remains. | C80: 0 | D80: 0 | E80: 0 | F80: 0 | G80: 0 | H80: 0 | I80: 0 | J80: 0 | K80: 0 | L80: 0 | M80: 0 | N80: 0 | O80: 0 | P80: 0 | Q80: 0 | R80: 0 | S80: 0 | T80: 0 | U80: 0 | V80: 0 | W80: 0 | X80: 0 | Y80: 0 | Z80: 0 | AA80: 0 | AB80: 0 | AC80: 0 | AD80: 0
A81: Oats | B81: Total | C81: 0 | D81: 0 | E81: 0 | F81: 0 | G81: 0 | H81: 0 | I81: 0 | J81: 0 | K81: 0 | L81: 0 | M81: 0 | N81: 0 | O81: 0 | P81: 0 | Q81: 0 | R81: 0 | S81: 0 | T81: 0 | U81: 0 | V81: 0 | W81: 0
A82: Beans, peas, vetches | B82: (henceforth each kind of corn should have its own title) | C82: 0 | D82: 0 | E82: 0 | F82: 0 | G82: 0 | H82: 0 | I82: 0 | J82: 0 | K82: 0 | L82: 0 | M82: 0 | N82: 0 | O82: 0 | P82: 0 | Q82: 0 | R82: 0 | S82: 0 | T82: 0 | U82: 0 | V82: 0 | W82: 0 | X82: 0 | Y82: 0 | Z82: 0 | AA82: 0 | AB82: 0 | AC82: 0 | AD82: 0
A83: Beans, peas, vetches | B83: The same render account for 5.5 quarters of peas (yield: five-and-a-half-fold). | C83: 0 | D83: 0 | E83: 0 | F83: 0 | G83: 0 | H83: 0 | I83: 0 | J83: 0 | K83: 0 | L83: 0 | M83: 0 | N83: 0 | O83: 0 | P83: 0 | Q83: 0 | R83: 0 | S83: 0 | T83: 5.5 | U83: 0 | V83: 5.5 | W83: 0 | X83: 5.5 | Y83: 0 | Z83: 5.5 | AA83: 5.5 | AB83: 0 | AC83: 5.5 | AD83: 0
A84: Beans, peas, vetches | B84: 5 quarters 1 bushels of vetches from the issue of the grange, threshed by labour service by 2 tallies of struck measure (yield: 5-fold less 0.5qr). | C84: 0 | D84: 0 | E84: 0 | F84: 0 | G84: 0 | H84: 0 | I84: 0 | J84: 0 | K84: 0 | L84: 0 | M84: 0 | N84: 0 | O84: 0 | P84: 0 | Q84: 0 | R84: 0 | S84: 0 | T84: 0 | U84: 0 | V84: 0 | W84: 0 | X84: 5 | Y84: 1 | Z84: 5.125 | AA84: 5.125 | AB84: 0 | AC84: 5 | AD84: 1
A85: Beans, peas, vetches | B85: 5 bushels of beans bought. | C85: 0 | D85: 0 | E85: 0 | F85: 0 | G85: 0 | H85: 0 | I85: 0 | J85: 0 | K85: 0 | L85: 0 | M85: 0 | N85: 0 | O85: 0 | P85: 0 | Q85: 0 | R85: 0 | S85: 0 | T85: 0 | U85: 0 | V85: 0 | W85: 0 | X85: 0 | Y85: 5 | Z85: 0.625 | AA85: 0.625 | AB85: 0 | AC85: 0 | AD85: 5
A86: Beans, peas, vetches | B86: Total, 111 quarters 2 bushels Sown over 8 acres of land, 1.5 quarters of peas. | C86: 0 | D86: 0 | E86: 112.5 | F86: 2 | G86: 112.75 | H86: 0 | I86: 0 | J86: 0 | K86: 0 | L86: 0 | M86: 0 | N86: 0 | O86: 0 | P86: 0 | Q86: 0 | R86: 0 | S86: 0 | T86: 0 | U86: 0 | V86: 0 | W86: 0 | X86: 1.5 | Y86: 2 | Z86: 1.75 | AA86: 111.25 | AB86: -109.5 | AC86: 111 | AD86: 2 | AE86: 1.5 | AF86: 0
A87: Beans, peas, vetches | B87: over 2 acres of land, 3 bushels of vetches by 1 tally. | C87: 0 | D87: 0 | E87: 0 | F87: 0 | G87: 0 | H87: 0 | I87: 0 | J87: 0 | K87: 0 | L87: 0 | M87: 0 | N87: 0 | O87: 0 | P87: 0 | Q87: 0 | R87: 0 | S87: 0 | T87: 0 | U87: 0 | V87: 0 | W87: 0 | X87: 0 | Y87: 3 | Z87: 0.375 | AA87: 0.375 | AB87: 0 | AC87: 0 | AD87: 3
A88: Beans, peas, vetches | B88: . | C88: 0 | D88: 0 | E88: 0 | F88: 0 | G88: 0 | H88: 0 | I88: 0 | J88: 0 | K88: 0 | L88: 0 | M88: 0 | N88: 0 | O88: 0 | P88: 0 | Q88: 0 | R88: 0 | S88: 0 | T88: 0 | U88: 0 | V88: 0 | W88: 0 | X88: 0 | Y88: 0 | Z88: 0 | AA88: 0 | AB88: 0 | AC88: 0 | AD88: 0
A89: Beans, peas, vetches | B89: . | C89: 0 | D89: 0 | E89: 0 | F89: 0 | G89: 0 | H89: 0 | I89: 0 | J89: 0 | K89: 0 | L89: 0 | M89: 0 | N89: 0 | O89: 0 | P89: 0 | Q89: 0 | R89: 0 | S89: 0 | T89: 0 | U89: 0 | V89: 0 | W89: 0 | X89: 0 | Y89: 0 | Z89: 0 | AA89: 0 | AB89: 0 | AC89: 0 | AD89: 0
A90: Beans, peas, vetches | B90: . | C90: 0 | D90: 0 | E90: 0 | F90: 0 | G90: 0 | H90: 0 | I90: 0 | J90: 0 | K90: 0 | L90: 0 | M90: 0 | N90: 0 | O90: 0 | P90: 0 | Q90: 0 | R90: 0 | S90: 0 | T90: 0 | U90: 0 | V90: 0 | W90: 0 | X90: 0 | Y90: 0 | Z90: 0 | AA90: 0 | AB90: 0 | AC90: 0 | AD90: 0
A91: Beans, peas, vetches | B91: fattening pigs for sale, 3 quarters 4.5 bushels of peas. | C91: 0 | D91: 0 | E91: 0 | F91: 0 | G91: 0 | H91: 0 | I91: 0 | J91: 0 | K91: 0 | L91: 0 | M91: 0 | N91: 0 | O91: 0 | P91: 0 | Q91: 0 | R91: 0 | S91: 0 | T91: 0 | U91: 0 | V91: 0 | W91: 0 | X91: 3 | Y91: 4.5 | Z91: 3.5625 | AA91: 3.5625 | AB91: 0 | AC91: 3 | AD91: 4.5
A92: Beans, peas, vetches | B92: . | C92: 0 | D92: 0 | E92: 0 | F92: 0 | G92: 0 | H92: 0 | I92: 0 | J92: 0 | K92: 0 | L92: 0 | M92: 0 | N92: 0 | O92: 0 | P92: 0 | Q92: 0 | R92: 0 | S92: 0 | T92: 0 | U92: 0 | V92: 0 | W92: 0 | X92: 0 | Y92: 0 | Z92: 0 | AA92: 0 | AB92: 0 | AC92: 0 | AD92: 0
A93: Beans, peas, vetches | B93: . | C93: 0 | D93: 0 | E93: 0 | F93: 0 | G93: 0 | H93: 0 | I93: 0 | J93: 0 | K93: 0 | L93: 0 | M93: 0 | N93: 0 | O93: 0 | P93: 0 | Q93: 0 | R93: 0 | S93: 0 | T93: 0 | U93: 0 | V93: 0 | W93: 0 | X93: 0 | Y93: 0 | Z93: 0 | AA93: 0 | AB93: 0 | AC93: 0 | AD93: 0
A94: Beans, peas, vetches | B94: . | C94: 0 | D94: 0 | E94: 0 | F94: 0 | G94: 0 | H94: 0 | I94: 0 | J94: 0 | K94: 0 | L94: 0 | M94: 0 | N94: 0 | O94: 0 | P94: 0 | Q94: 0 | R94: 0 | S94: 0 | T94: 0 | U94: 0 | V94: 0 | W94: 0 | X94: 0 | Y94: 0 | Z94: 0 | AA94: 0 | AB94: 0 | AC94: 0 | AD94: 0
A95: Beans, peas, vetches | B95: pease pottage for the manorial servants for the year, 3.5 bushels of peas. | C95: 0 | D95: 0 | E95: 0 | F95: 0 | G95: 0 | H95: 0 | I95: 0 | J95: 0 | K95: 0 | L95: 0 | M95: 0 | N95: 0 | O95: 0 | P95: 0 | Q95: 0 | R95: 0 | S95: 0 | T95: 0 | U95: 0 | V95: 0 | W95: 0 | X95: 0 | Y95: 3.5 | Z95: 0.4375 | AA95: 0.4375 | AB95: 0 | AC95: 0 | AD95: 3.5
A96: Beans, peas, vetches | B96: . | C96: 0 | D96: 0 | E96: 0 | F96: 0 | G96: 0 | H96: 0 | I96: 0 | J96: 0 | K96: 0 | L96: 0 | M96: 0 | N96: 0 | O96: 0 | P96: 0 | Q96: 0 | R96: 0 | S96: 0 | T96: 0 | U96: 0 | V96: 0 | W96: 0 | X96: 0 | Y96: 0 | Z96: 0 | AA96: 0 | AB96: 0 | AC96: 0 | AD96: 0
A97: Beans, peas, vetches | B97: . | C97: 0 | D97: 0 | E97: 0 | F97: 0 | G97: 0 | H97: 0 | I97: 0 | J97: 0 | K97: 0 | L97: 0 | M97: 0 | N97: 0 | O97: 0 | P97: 0 | Q97: 0 | R97: 0 | S97: 0 | T97: 0 | U97: 0 | V97: 0 | W97: 0 | X97: 0 | Y97: 0 | Z97: 0 | AA97: 0 | AB97: 0 | AC97: 0 | AD97: 0
A98: Beans, peas, vetches | B98: . | C98: 0 | D98: 0 | E98: 0 | F98: 0 | G98: 0 | H98: 0 | I98: 0 | J98: 0 | K98: 0 | L98: 0 | M98: 0 | N98: 0 | O98: 0 | P98: 0 | Q98: 0 | R98: 0 | S98: 0 | T98: 0 | U98: 0 | V98: 0 | W98: 0 | X98: 0 | Y98: 0 | Z98: 0 | AA98: 0 | AB98: 0 | AC98: 0 | AD98: 0
A99: Beans, peas, vetches | B99: supporting pigs in the manor in winter and summer when it was necessary, 4 quarters 2 bushels of vetches and 5 bushels of beans. | C99: 0 | D99: 0 | E99: 0 | F99: 0 | G99: 0 | H99: 0 | I99: 0 | J99: 0 | K99: 0 | L99: 0 | M99: 0 | N99: 0 | O99: 0 | P99: 0 | Q99: 0 | R99: 0 | S99: 0 | T99: 0 | U99: 0 | V99: 0 | W99: 0 | X99: 4 | Y99: 5 | Z99: 4.625 | AA99: 4.25 | AB99: 0.375 | AC99: 4 | AD99: 2 | AE99: 0 | AF99: 5
A100: Beans, peas, vetches | B100: Sold at the audit, 0.5 qr of vetches. | C100: 0 | D100: 0 | E100: 0 | F100: 0 | G100: 0 | H100: 0 | I100: 0 | J100: 0 | K100: 0 | L100: 0 | M100: 0 | N100: 0 | O100: 0 | P100: 0 | Q100: 0 | R100: 0 | S100: 0 | T100: 0 | U100: 0 | V100: 0 | W100: 0
A101: Beans, peas, vetches | B101: Total, 10 quarters 6 bushels2 None remains. | C101: 0 | D101: 0 | E101: 0 | F101: 0 | G101: 0 | H101: 0 | I101: 0 | J101: 0 | K101: 0 | L101: 0 | M101: 0 | N101: 0 | O101: 0 | P101: 0 | Q101: 0 | R101: 0 | S101: 0 | T101: 0 | U101: 0 | V101: 0 | W101: 0 | X101: 10 | Y101: 6 | Z101: 10.75 | AA101: 10.75 | AB101: 0 | AC101: 10 | AD101: 6

Sheet Sale of Corn Prices
A1: Heading | B1: Sentence | C1: Total in Pounds | D1: Pounds | E1: Shillings | F1: Pence | G1: Corn | H1: Total Quarters Except 1 | I1: Total Bushels Except 1 | J1: Total Corn Cross-Check | K1: Total Corn Manorial Account | L1: Corn Quantity Error | M1: Quarters 0 | N1: Bushels 0 | O1: shilling a quarter 1 | P1: pence a quarter 1 | Q1: Quarters 1 | R1: Bushels 1 | S1: shilling a quarter 2 | T1: pence a quarter 2 | U1: Quarters 2 | V1: Bushels 2 | W1: shilling a quarter 3 | X1: pence a quarter 3 | Y1: Quarters 3 | Z1: Bushels 3 | AA1: shilling a quarter 4 | AB1: pence a quarter 4 | AC1: Quarters 4 | AD1: Bushels 4 | AE1: Quarters 5 | AF1: Bushels 5 | AG1: £ a quarter 1 | AH1: £ a quarter 2 | AI1: £ a quarter 3 | AJ1: £ a quarter 4 | AK1: Quarters Sold | AL1: Weighted Average Price per Quarter | AM1: Non-Weighted Average Price per Quarter | AN1: Corn lowercase
A2: Sale of corn | B2: The same render account for £29 16 shilling 9.25pence from 105 quarters 2.5 bushels of wheat sold, at 5 shilling 8pence a quarters, £4 9 shilling 10.25pence from 28 quarters 3 bushels of rye sold, at 3 shilling 2pence a quarters. | C2: 29.84 | D2: 29 | E2: 16 | F2: 9.25 | G2: rye, wheat | H2: 28 | I2: 3 | J2: 28.375 | K2: 105.3125 | L2: -76.9375 | M2: 105 | N2: 2.5 | O2: 5 | P2: 8 | Q2: 28 | R2: 3 | S2: 3 | T2: 2 | AG2: 0.28333333 | AH2: 0.15833333 | AK2: 105.3125 | AM2: 0.22083333 | AN2: rye, wheat
A3: Sale of corn | B3: £20 16 shilling .75pence from 118 quarters of barley sold, at 3 shilling 6pence a quarters. | C3: 20.8 | D3: 20 | E3: 16 | F3: 0 | G3: barley | H3: 118 | I3: 0 | J3: 118 | K3: 118 | L3: 0 | M3: 118 | N3: 0 | O3: 3 | P3: 6 | AG3: 0.175 | AK3: 118 | AL3: 0.175 | AM3: 0.175 | AN3: barley
A4: Sale of corn | B4: £2 8 shilling 9pence from 16 quarters 2 bushels of dredge sold, at 3 shilling a quarters, 2 shilling 4.5pence from 6 bushels of rye sold at the audit. | C4: 2.44 | D4: 2 | E4: 8 | F4: 9 | G4: rye | H4: 16 | I4: 6 | J4: 16.75 | K4: 16.25 | L4: 0.5 | M4: 16 | N4: 2 | O4: 3 | P4: 0 | Q4: 0 | R4: 6 | AG4: 0.15 | AK4: 16.25 | AL4: 0.15 | AM4: 0.15 | AN4: rye
A5: Sale of corn | B5: 1 shilling 9pence from .5 quarters of barley sold at the audit. | C5: 0.09 | D5: 0 | E5: 1 | F5: 9 | G5: barley | H5: 5 | I5: 0 | J5: 5 | K5: 5 | L5: 0 | M5: 5 | N5: 0 | AG5: 0.018 | AK5: 5 | AL5: 0.018 | AM5: 0.018 | AN5: barley
A6: Sale of corn | B6: 8pence from .5 quarters of vetches sold at the audit. | C6: 0.03 | D6: 0 | E6: 0 | F6: 8 | G6: vetches | H6: 5 | I6: 0 | J6: 5 | K6: 5 | L6: 0 | M6: 5 | N6: 0 | AG6: 0.006 | AK6: 5 | AL6: 0.006 | AM6: 0.006 | AN6: vetches
A7: Sale of corn | B7: Total, £57 16 shilling 2.75pence | C7: 57.81 | D7: 57 | E7: 16 | F7: 2.75 | H7: 0 | I7: 0 | J7: 0 | K7: 0 | L7: 0 | M7: 0 | N7: 0 | AG7: inf | AK7: 0 | AL7: inf | AM7: inf
