Workbook

Sheet Cheriton Overview - Completed
A1: CHERITON OVERVIEW - COMPLETED | B1: Total in £ | C1: Error | D1: Note
A2: CASH ACCOUNT
A3: RECEIPTS
A4: Arrears total | B4: 57.61
A5: Rents of assize total | B5: 31.6
A6: Quittances total | B6: 2.1
A7: Defaults of rent total | B7: 4.7266667
A8: Defaults of rent through the pestilence total
A9: Cotlands defaults total
A10: Cotlands total
A11: Total of quittances and defaults of rent total | B11: 6.83
A12: Total of rents remaining clear total | B12: 24.76
A13: Farms total
A14: Annual recognizances total | B14: 0.03
A15: Issues of the Manor total | B15: 23.85
A16: Issues of the tenements in the lord's hands total
A17: Sale of labour services total
A18: Sale of corn total
A19: Entry and marriage fines total | B19: 4.31
A20: Pleas & perquisites total
A21: Forfeited chattels total
A22: Farm of the demesne land total
A23: Total of all receipts (calculated here) | B23: =SUM(B5:B22)
A24: Total of all receipts (calculated here) incl arrears | B24: =SUM(B4:B22)
A25: Total recorded in the accounts excl. arrears | B25: 91.591667 | C25: =B23-B25
A26: Total recorded in the accounts incl. arrears | B26: =B25+B4
A29: EXPENSES
A30: Cost of ploughs total | B30: 4.13
A31: Purchase of corn total | B31: 3.01
A32: Cost of carts and wagons total
A33: Cost of dairy total
A34: Purchase of stock total | B34: 3.97
A35: Sheepcote total
A36: Cost of buildings total
A37: Threshing total | B37: 1.8941667
A38: Barley expenses
A39: Expenses of the harvest total
A40: Necessary expenses
A41: Wages of the bailiff
A42: Steward's expenses total | B42: 0.34
A43: Annual fees
A44: Total of all expenses per account | B44: 21
A45: Total of all expenses (calculated here) | B45: 21.542708
A46: Total fixed investment | B46: 2.84
A47: Total Demesne fixed investment | B47: 2.84
A49: Owed by the reeve | B49: =B23-B45
A50: From accounts | B50: 21
A52: Allowances
A53: Cash deliveries | B53: 40.53
A54: Sum of the above | B54: =SUM(B52:B53)
A55: Total of all allowances and cash deliveries in accounts
A57: Net amount owed | B57: =B50-B54
A58: Net amount owed in accounts
A60: GRANGE ACCOUNT | B60: Total Production | D60: Value of total gross production in £ | E60: Value of total net production in £
A61: Grange | B61: qrs | C61: bus
A62: Wheat | B62: 94 | E62: 20.041667
A63: Rye
A64: Dredge
A65: Curall | B65: 3.25 | E65: 0.4375
A66: Barley | B66: 55.5 | E66: 3.5512821
A67: Oats | B67: 135 | E67: 4.4437908
A68: Beans
A69: Peas | B69: 2.5 | E69: 0.064583333
A70: Vetches | B70: 2.125 | E70: 0.0625
A71: Total value of gross production (sum of the above)
A72: Total value of net production
A73: Value of sales
A75: MILL ACCOUNT | B75: Total Production | D75: Total in £
A76: Issues of the mill | B76: qrs | C76: bus
A77: Wheat
A78: Oatmeal
A79: 1st grade malt
A80: 2nd grade malt
A81: Maslin
A82: Total value of production (sum of the above)
A83: Value of sales
A85: STOCK ACCOUNT
A86: Livestock | B86: Begin stock | C86: End stock | D86: Stockbuilding | F86: Value of stock in £ | G86: Value of stockbuilding
A87: Cart-horses | B87: 2 | C87: 2 | D87: 0 | F87: ='Stock'!K5*'Stock'!O5 | G87: =D87*'Stock'!O5
A88: Mares | D88: =C88-B88 | F88: ='Stock'!K6*'Stock'!O6 | G88: =D88*'Stock'!O6
A89: Plough horses | B89: 13 | C89: 8 | D89: -5 | F89: ='Stock'!K7*'Stock'!O7 | G89: =D89*'Stock'!O7
A90: Colts (2 years) | B90: 2 | C90: 1 | D90: -1 | F90: ='Stock'!K9*'Stock'!O9 | G90: =D90*'Stock'!O9
A91: Colts (2 years) | B91: 2 | C91: 1 | D91: -1 | F91: ='Stock'!K9*'Stock'!O9 | G91: =D91*'Stock'!O9
A92: Colts (1 year) | D92: =C92-B92 | F92: ='Stock'!K10*'Stock'!O10 | G92: =D92*'Stock'!O10
A93: Foals | D93: =C93-B93 | F93: ='Stock'!K11*'Stock'!O11 | G93: =D93*'Stock'!O11
A94: Oxen | B94: 39 | C94: 40 | D94: 1 | F94: ='Stock'!K12*'Stock'!O12 | G94: =D94*'Stock'!O12
A95: Bulls | D95: =C95-B95 | F95: ='Stock'!K13*'Stock'!O13 | G95: =D95*'Stock'!O13
A96: Cows | B96: 10 | C96: 22 | D96: 12 | F96: ='Stock'!K14*'Stock'!O14 | G96: =D96*'Stock'!O14
A97: Steers | B97: 4 | C97: 0 | D97: -4 | F97: ='Stock'!K15*'Stock'!O15 | G97: =D97*'Stock'!O15
A98: Bullocks | B98: 4 | C98: 4 | D98: 0 | F98: ='Stock'!K16*'Stock'!O16 | G98: =D98*'Stock'!O16
A99: Yearlings | B99: 4 | C99: 4 | D99: 0 | F99: ='Stock'!K17*'Stock'!O17 | G99: =D99*'Stock'!O17
A100: Calves | B100: 14 | C100: 8 | D100: -6 | F100: ='Stock'!K18*'Stock'!O18 | G100: =D100*'Stock'!O18
A101: Wethers | B101: 324 | C101: 339 | D101: 15 | F101: ='Stock'!K19*'Stock'!O19 | G101: =D101*'Stock'!O19
A102: Rams | B102: 8 | C102: 10 | D102: 2 | F102: ='Stock'!K20*'Stock'!O20 | G102: =D102*'Stock'!O20
A103: Ewes | B103: 288 | C103: 301 | D103: 13 | F103: ='Stock'!K21*'Stock'!O21 | G103: =D103*'Stock'!O21
A104: Hoggs | B104: 150 | C104: 0 | D104: -150 | F104: ='Stock'!K22*'Stock'!O22 | G104: =D104*'Stock'!O22
A105: Lambs | B105: 236 | C105: 176 | D105: -60 | F105: ='Stock'!K23*'Stock'!O23 | G105: =D105*'Stock'!O23
A106: Boars | D106: =C106-B106 | F106: ='Stock'!K24*'Stock'!O24 | G106: =D106*'Stock'!O24
A107: Sows | B107: 2 | C107: 2 | D107: 0 | F107: ='Stock'!K25*'Stock'!O25 | G107: =D107*'Stock'!O25
A108: Pigs | B108: 17 | C108: 36 | D108: 19 | F108: ='Stock'!K26*'Stock'!O26 | G108: =D108*'Stock'!O26
...

Sheet Prices
A1: Meat & Dairy Prices
C2: 1301 | D2: 1302 | E2: Average
A3: Beef | B3: £ per lb | C3: 0.0033351854 | D3: 0.0032608538 | E3: =AVERAGE(C3:D3)
A4: Mutton | B4: £ per lb | C4: 0.0036593977 | D4: 0.0037125513 | E4: =AVERAGE(C4:D4)
A5: Pork | B5: £ per lb | C5: 0.0038431326 | D5: 0.0037574803 | E5: =AVERAGE(C5:D5)
A6: Cheese | B6: £ per lb | C6: 0.0055768754 | D6: 0.0056654898 | E6: =AVERAGE(C6:D6)
A7: Butter | B7: £ per lb | C7: 0.0036626221 | D7: 0.0035935077 | E7: =AVERAGE(C7:D7)
A8: Milk | B8: £ per gallon | C8: 0.0055768754 | D8: 0.0056654898 | E8: =AVERAGE(C8:D8)

Sheet Labour Rents

Sheet Overview
A1: CHERITON | B1: Total in £ | C1: Error | D1: Note
A2: CASH ACCOUNT
A3: RECEIPTS
A4: Arrears total
A5: Rents of assize total
A6: Quittances total
A7: Defaults of rent total
A8: Defaults of rent through the pestilence total
A9: Cotlands defaults total
A10: Cotlands total
A11: Total of quittances and defaults of rent total
A12: Total of rents remaining clear total
A13: Farms total
... A22: Farm of the demesne land total
A23: Total of all receipts (calculated here) | B23: =Receipts!F134
A24: Total of all receipts (calculated here) incl arrears | B24: =Receipts!F135
A25: Total recorded in the accounts excl. arrears | B25: =Receipts!F133 | C25: =B25-B23
A26: Total recorded in the accounts incl. arrears
A29: EXPENSES
A30: Cost of ploughs total
A31: Purchase of corn total
A32: Cost of carts and wagons total
A33: Cost of dairy total
A34: Purchase of stock total
A35: Sheepcote total
A36: Cost of buildings total
A37: Threshing total
A38: Barley expenses
A39: Expenses of the harvest total
... A43: Annual fees
A44: Total of all expenses per account | B44: =Expenses!F100
A45: Total of all expenses (calculated here) | B45: =Expenses!F101
A46: Total fixed investment | B46: =Expenses!F102
A47: Total Demesne fixed investment | B47: =Expenses!F103
A49: Owed by the reeve
A50: From accounts
A52: Allowances
A53: Cash deliveries
A54: Sum of the above
A55: Total of all allowances and cash deliveries in accounts
A57: Net amount owed
A58: Net amount owed in accounts
A60: GRANGE ACCOUNT | B60: Total Production
A61: Grange | B61: qrs | E61: Value of total gross production in £ | F61: Value of total net production in £
A62: wheat | B62: ='Issues of the Grange'!I2 | E62: ='Issues of the Grange'!I2 | F62: ='Issues of the Grange'!O14
A63: curall | B63: ='Issues of the Grange'!I3 | E63: ='Issues of the Grange'!I3 | F63: ='Issues of the Grange'!O15
A64: bere | B64: ='Issues of the Grange'!I4 | E64: ='Issues of the Grange'!I4 | F64: ='Issues of the Grange'!O16
A65: barley | B65: ='Issues of the Grange'!I5 | E65: ='Issues of the Grange'!I5 | F65: ='Issues of the Grange'!O17
A66: oats | B66: ='Issues of the Grange'!I6 | E66: ='Issues of the Grange'!I6 | F66: ='Issues of the Grange'!O18
A67: peas | B67: ='Issues of the Grange'!I7 | E67: ='Issues of the Grange'!I7 | F67: ='Issues of the Grange'!O19
A68: vetches | B68: ='Issues of the Grange'!I8 | E68: ='Issues of the Grange'!I8 | F68: ='Issues of the Grange'!O20
A69: Total value of gross production (sum of the above) | E69: =SUM(E62:E68)
A70: Total value of net production | E70: =SUM(F62:F68)
A71: Value of sales | E71: =Receipts!F106+Receipts!F100
A73: MILL ACCOUNT
A74: Issues of the mill
A75: Wheat
A76: Oatmeal
A77: 1st grade malt
A78: 2nd grade malt
A79: Maslin
A80: Total value of production (sum of the above)
A81: Value of sales
A83: STOCK ACCOUNT
A84: Livestock | B84: Sales value in £
A85: Cart-horses | B85: =Stock!R5
A86: Mares | B86: =Stock!R6
A87: Plough horses | B87: =Stock!R7
A88: Colts (2 years) | B88: =Stock!R8
A89: Colts (2 years) | B89: =Stock!R9
A90: Colts (1 year) | B90: =Stock!R10
A91: Foals | B91: =Stock!R11
A92: Oxen | B92: =Stock!R12
A93: Bulls | B93: =Stock!R13
A94: Cows | B94: =Stock!R14
A95: Steers | B95: =Stock!R15
A96: Bullocks | B96: =Stock!R16
... A110: Peacocks | B110: =Stock!R30
A111: Total value of stock (sum of the above)
A112: Total value of production
A113: Value of sales | B113: =Stock!R31
A115: Wool | B115: Value of production at sales prices £
A116: Coarse wool | B116: =Stock!T35
A117: Lamb's wool | B117: =Stock!T36
A118: Wool locks | B118: =Stock!T37
A119: Wool sold at shearing | B119: =Stock!T38
A120: Total value of production (sum of the above) | B120: =Stock!T39
A121: Value of sales | B121: =Stock!R39
A123: Hides | B123: Value of production at sales prices £
A124: Ox hides | B124: =Stock!T43
A125: Cow hides | B125: =Stock!T44
A126: Mare hides | B126: =Stock!T45
A127: Steer hides | B127: =Stock!T46
A128: Yearling Calf hides | B128: =Stock!T47
A129: Calf hides | B129: =Stock!T48
A130: Pig hides | B130: =Stock!T49
A131: Wether woolskins | B131: =Stock!T50
A132: Ram woolskins | B132: =Stock!T51
A133: Ewe woolskins | B133: =Stock!T52
A134: Hogg woolskins | B134: =Stock!T53
...

Sheet Receipts
A1: CHERITON RECEIPTS
A2: Heading | B2: £ | C2: s | D2: d | F2: Total in £ | G2: Error | H2: Notes
A3: Arrears | B3: 57 | C3: 12 | D3: 3.5 | F3: 57.61 | H3: Nicholas, bailiff, and Richard Eme, reeve, render account for £57 12 shilling 3.5pence of arrears from the previous year.
A4: Arrears | B4: 0 | C4: 0 | D4: 0 | F4: 0 | H4: All delivered to Sir Geoffrey of Wolvesey.
A5: Arrears | B5: 0 | C5: 0 | D5: 0 | F5: 0 | H5: They are quit.
A6: Arrears | F6: 57.61 | G6: =F6-F3 | H6: Total
A8: Rents of assize | B8: 5 | C8: 1 | D8: 9 | F8: 5.09 | H8: The same render account for £5 1 shilling 9pence for rents of the manor of Cheriton at Christmas.
A9: Rents of assize | B9: 8 | C9: 2 | D9: 8.75 | F9: 8.14 | H9: £8 2 shilling 8.75pence at Easter (22 April).
A10: Rents of assize | B10: 5 | C10: 2 | D10: 8.25 | F10: 5.13 | H10: £5 2 shilling 8.25pence at St John the Baptist (24 June).
A11: Rents of assize | B11: 13 | C11: 4 | D11: 9 | F11: 13.24 | H11: £13 4 shilling 9pence at Michaelmas (29 September).
A12: Rents of assize | B12: 31 | C12: 11 | D12: 11 | F12: 31.6 | H12: Total, £31 11 shilling 11pence
A13: Rents of assize | F13: 31.6 | G13: 0 | H13: Total
A15: Quittances | B15: 0 | C15: 5 | D15: 0 | F15: 0.25 | H15: In quittance of 1 reeve for the year 5 shilling.
A16: Quittances | B16: 0 | C16: 5 | D16: 0 | F16: 0.25 | H16: 1 smith for the ironwork of 5 ploughs for the year 5 shilling.
A17: Quittances | B17: 0 | C17: 2 | D17: 6 | F17: 0.12 | H17: 1 bartoner for the year 2 shilling 6pence.
A18: Quittances | B18: 0 | C18: 2 | D18: 0 | F18: 0.1 | H18: 1 keeper of ewes for the year 2 shilling.
A19: Quittances | B19: 0 | C19: 2 | D19: 0 | F19: 0.1 | H19: 1 keeper of wethers for the year 2 shilling.
A20: Quittances | B20: 0 | C20: 1 | D20: 6 | F20: 0.08 | H20: 1 keeper of hoggs for 3 terms 1 shilling 6pence.
A21: Quittances | B21: 0 | C21: 2 | D21: 0 | F21: 0.1 | H21: 1 swineherd for the year 2 shilling.
A22: Quittances | B22: 0 | C22: 16 | D22: 0 | F22: 0.8 | H22: 8 ploughmen for the year 16 shilling, or 2 shilling each for the year.
A23: Quittances | B23: 0 | C23: 3 | D23: 0 | F23: 0.15 | H23: 2 oxherds until the oxen were put to the stalls 3 shilling.
A24: Quittances | B24: 0 | C24: 3 | D24: 0 | F24: =B24+C24/20+D24/240 | H24: 2 workers working twice a week from Christmas until Lammas (1 August) and everyday at harvest-time 3 shilling
A25: Quittances | B25: 2 | C25: 2 | D25: 0 | F25: 2.1 | H25: Total, £2 2 shilling
A26: Quittances | F26: =SUM(F15:F24) | G26: =F26-F25 | H26: Total
A28: Defaults of rent | B28: 0 | C28: 0 | D28: 4 | F28: 0.02 | H28: In default of the land of the wheelwright drawn into demesne, 4pence for the year.
A29: Defaults of rent | B29: 0 | C29: 0 | D29: 8 | F29: 0.03 | H29: the land of Hugh and Herbert, 8pence for the year.
A30: Defaults of rent | B30: 0 | C30: 0 | D30: 8 | F30: 0.03 | H30: the land of Arnold and Geoffrey drawn into demesne, 8pence for the year.
A31: Defaults of rent | B31: 0 | C31: 0 | D31: 8 | F31: 0.03 | H31: the land of Arnold and William ate More drawn into demesne, 8pence for the year.
A32: Defaults of rent | B32: 0 | C32: 1 | D32: 4 | F32: 0.07 | H32: the land of Robert and Herbert drawn into demesne, 1 shilling 4pence for the year.
A33: Defaults of rent | B33: 0 | C33: 0 | D33: 8 | F33: 0.03 | H33: the land of Richard Faber drawn into demesne, 8pence for the year.
A34: Defaults of rent | B34: 0 | C34: 0 | D34: 0 | F34: 0 | H34: These defaults are from a certain meadow at Elleford' drawn into demesne for the year.
A35: Defaults of rent | B35: 0 | C35: 7 | D35: 0 | F35: 0.35 | H35: default of the land which is called la Hyde, 7 shilling for the year.
A36: Defaults of rent | B36: 3 | C36: 10 | D36: 0 | F36: 3.5 | H36: the mill of Clyth' drawn into demesne, £3 10 shilling for the year.
A37: Defaults of rent | B37: 0 | C37: 13 | D37: 4 | F37: =B37+C37/20+D37/240 | H37: the mill of Bergh' because it does not have the multure of the hundred 13 shilling 4pence
A38: Defaults of rent | B38: 4 | C38: 14 | D38: 8 | F38: 4.73 | H38: Total, £4 14 shilling 8pence
A39: Defaults of rent | F39: =SUM(F28:F37) | G39: =F39-F38 | H39: Total
A41: Total of quittances and defaults of rent | B41: 6 | C41: 16 | D41: 8 | F41: 6.83 | H41: Total of quittances and defaults of rent, £6 16 shilling 8pence
A42: Total of quittances and defaults of rent | F42: 6.83 | G42: =F42-F41 | H42: Total
A44: Total of rents remaining clear | B44: 24 | C44: 15 | D44: 3 | F44: 24.76 | H44: Total of rents remaining clear, £24 15 shilling 3pence
A45: Total of rents remaining clear | F45: 24.76 | G45: =F45-F44 | H45: Total
A47: Annual recognizance | B47: 0 | C47: 0 | D47: 0 | F47: 0 | H47: The same render account for nothing from Richard le Clodyere because he is dead.
A48: Annual recognizance | B48: 0 | C48: 0 | D48: 4 | F48: 0.02 | H48: 4pence from Robert Wolfon3 for annual recognizance.
A49: Annual recognizance | B49: 0 | C49: 0 | D49: 3 | F49: 0.01 | H49: 3pence from William Pistore for thesame.
A50: Annual recognizance | B50: 0 | C50: 0 | D50: 7 | F50: 0.03 | H50: Total, 7pence
A51: Annual recognizance | F51: 0.03 | G51: 0 | H51: Total
A53: Issues of the manor | B53: 1 | C53: 1 | D53: 11.5 | F53: 1.1 | H53: The same render account for £1 1 shilling 11.5pence from pannage of pigs this year.
A54: Issues of the manor | B54: 0 | C54: 4 | D54: 4 | F54: 0.22 | H54: 4 shilling 4pence from pannage of the cottars, at 4pence an ox and cow.
A55: Issues of the manor | B55: 0 | C55: 0 | D55: 0 | F55: 0 | H55: nothing from the pasturage of Eldeford' this year for the lord's livestock.
A56: Issues of the manor | B56: 0 | C56: 0 | D56: 0 | F56: 0 | H56: nothing from the pasturage of Perogh' for the same.
A57: Issues of the manor | B57: 0 | C57: 0 | D57: 0 | F57: 0 | H57: nothing from the pasturage of Rowele, nor from the pasturage of Grenle, nor from the pasturage of Holeden', nor from the pasturage of Fulele and Fenihull' this year for the same.
A58: Issues of the manor | B58: 0 | C58: 0 | D58: 0 | F58: 0 | H58: nothing from the pasturage of Donefore this year for the same.
A59: Issues of the manor | B59: 0 | C59: 15 | D59: 0 | F59: 0.75 | H59: 15 shilling from right of way for carts travelling beyond the lord's pasture.
A60: Issues of the manor | B60: 0 | C60: 9 | D60: 5 | F60: 0.47 | H60: 9 shilling 5pence from 113 hens from churchscot sold.
A61: Issues of the manor | B61: 0 | C61: 3 | D61: 6 | F61: 0.17 | H61: 3 shilling 6pence from 1,050 eggs sold according to custom.
A62: Issues of the manor | B62: 0 | C62: 3 | D62: 0 | F62: 0.15 | H62: 3 shilling from the relict of le Fiz for release from her labour service this year.
A63: Issues of the manor | B63: 0 | C63: 2 | D63: 0 | F63: 0.1 | H63: 2 shilling from Richard Eme for release from his labour service by 1 game of chance (j hasard') at the lord's will.
A64: Issues of the manor | B64: 0 | C64: 0 | D64: 0 | F64: 0 | H64: nothing from the entire coarse wool and lamb's-wool here because it was sent to Wolvesey.
... A87: Issues of the manor | B87: 23 | C87: 16 | D87: 6.5 | F87: 23.83 | H87: Total, £23 16 shilling 6.5pence
A88: Issues of the manor | F88: 23.85 | G88: 0.02 | H88: Total
A90: Sale of wheat | B90: 20 | C90: 0 | D90: 10 | F90: 20.04 | H90: The same render account for £20 10pence from 60 quarters 1 bushels of wheat sold, at 6 shilling 8pence a qr.
A91: Sale of wheat | B91: 0 | C91: 8 | D91: 9 | F91: 0.44 | H91: 8 shilling 9pence from 1 qr 7 bushels of curall sold.
A92: Sale of wheat | B92: 0 | C92: 9 | D92: 0 | F92: 0.45 | H92: 9 shilling from 3 quarters of winter barley sold, at 3 shilling a qr.
A93: Sale of wheat | B93: 3 | C93: 15 | D93: 10 | F93: 3.79 | H93: £3 15 shilling 10pence from 16 quarters 2 bushels of barley sold, at 4 shilling 8pence a qr.
A94: Sale of wheat | B94: 3 | C94: 14 | D94: 8 | F94: 3.73 | H94: £3 14 shilling 8pence from 32 quarters of oats sold, at 2 shilling 4pence a qr.
A95: Sale of wheat | B95: 0 | C95: 1 | D95: 3.5 | F95: 0.06 | H95: 1 shilling 3.5pence from 3 bushels of peas sold.
A96: Sale of wheat | B96: 0 | C96: 1 | D96: 3 | F96: 0.06 | H96: 1 shilling 3pence from 5 bushels of vetches sold.
A97: Sale of wheat | B97: 0 | C97: 7 | D97: 6 | F97: 0.38 | H97: 7 shilling 6pence from 1 qr 7 bushels of barley sold at the audit.
A98: Sale of wheat | B98: 0 | C98: 12 | D98: 6 | F98: 0.62 | H98: 12 shilling 6pence from 6 quarters 2 bushels of oats sold at the audit.
A99: Sale of wheat | B99: 29 | C99: 11 | D99: 7.5 | F99: 29.58 | H99: Total, £29 11 shilling 7.5pence
A100: Sale of wheat | F100: 29.57 | G100: -0.01 | H100: Total
A102: Corn from the mill | B102: 0 | C102: 2 | D102: 6 | F102: 0.12 | H102: The same render account for 2 shilling 6pence from 4 bushels of wheat from the issue of the mill sold.
A103: Corn from the mill | B103: 2 | C103: 12 | D103: 0 | F103: 2.6 | H103: £2 12 shilling from 14 quarters of barley from the issue of the same mill sold, at 3 shilling a quarters for 4 quarters, and 4 shilling a quarters for 10 quarters.
A104: Corn from the mill | B104: 0 | C104: 1 | D104: 6 | F104: =B104+C104/20+D104/240 | H104: 1 shilling 6pence from 4 bushels of malt from the issue of the same mill solpence
A105: Corn from the mill | B105: 2 | C105: 16 | D105: 0 | F105: 2.8 | H105: Total, £2 16 shilling
A106: Corn from the mill | F106: =SUM(F102:F104) | G106: =F106-F105 | H106: Total
A108: Entry and marriage fines with tithingpenny | B108: 0 | C108: 6 | D108: 8 | F108: 0.33 | H108: The same render account for 6 shilling1 8pence from the tithing of Cheriton at the hundred-court of Martinmas.
A109: Entry and marriage fines with tithingpenny | B109: 0 | C109: 6 | D109: 8 | F109: 0.33 | H109: 6 shilling 8pence from the same for the same at the hundred-court of Hockday.
A110: Entry and marriage fines with tithingpenny | B110: 0 | C110: 3 | D110: 4 | F110: 0.17 | H110: 3 shilling 4pence from Joan la Clodyar' to have 1 cotland which belonged to Richard le Clodyare her brother.
A111: Entry and marriage fines with tithingpenny | B111: 0 | C111: 3 | D111: 4 | F111: 0.17 | H111: 3 shilling 4pence from William, son of John Som', to have the said land by surrender of the said Joan Clodiar'.
A112: Entry and marriage fines with tithingpenny | B112: 0 | C112: 6 | D112: 8 | F112: 0.33 | H112: 6 shilling 8pence from John ate Med to have 1 cotland with Alveva his wife.
A113: Entry and marriage fines with tithingpenny | B113: 0 | C113: 5 | D113: 0 | F113: 0.25 | H113: 5 shilling from Christina, relict of Gang', to retain 1 cotland which belonged to her husband.
A114: Entry and marriage fines with tithingpenny | B114: 0 | C114: 5 | D114: 0 | F114: 0.25 | H114: 5 shilling from Alice Lovering to retain 1 cotland after the death of her husband.
A115: Entry and marriage fines with tithingpenny | B115: 0 | C115: 10 | D115: 0 | F115: 0.5 | H115: 10 shilling from Robert Jan to have 1 virgate of land, after the mortuary payment for the relict of Cartere, his mother, out of her inheritance.
A116: Entry and marriage fines with tithingpenny | B116: 0 | C116: 10 | D116: 0 | F116: 0.5 | H116: 10 shilling from Simon Crech, son of William Crech, to have 0.5 cotland which came into the lord's hands as his escheat because a certain Alice la Schinnere who held the said tenement withdrew and noone succeeded to the said land by inheritance, having been waiting for 1 year.
A117: Entry and marriage fines with tithingpenny | B117: 0 | C117: 6 | D117: 8 | F117: 0.33 | H117: 6 shilling 8pence from Joan, relict of le Swon, to retain 1 virgate of land which belonged to Henry her husband.
A118: Entry and marriage fines with tithingpenny | B118: 1 | C118: 0 | D118: 0 | F118: 1 | H118: £1 from John de Spin' to have the said Joan le Swon with the land.
A119: Entry and marriage fines with tithingpenny | B119: 0 | C119: 3 | D119: 0 | F119: 0.15 | H119: 3 shilling from Luke ate Med to have 1 virgate of land for his lifetime from the inheritance (ex traditione) of Nicholas his son.
A120: Entry and marriage fines with tithingpenny | B120: 4 | C120: 6 | D120: 4 | F120: 4.32 | H120: Total, £4 6 shilling 4pence
A121: Entry and marriage fines with tithingpenny | F121: 4.31 | G121: -0.01 | H121: Total
A123: Perquisites | B123: 0 | C123: 6 | D123: 8 | F123: 0.33 | H123: The same render account for 6 shilling 8pence from John de Puteo for transgression against the lord.
A124: Perquisites | B124: 0 | C124: 3 | D124: 4 | F124: 0.17 | H124: 3 shilling 4pence from Thomas de Wichurst because he broke the lord's pinfold.
A125: Perquisites | B125: 0 | C125: 3 | D125: 4 | F125: 0.17 | H125: 3 shilling 4pence from William Basset for the same.
A126: Perquisites | B126: 0 | C126: 3 | D126: 4 | F126: 0.17 | H126: 3 shilling 4pence from Richard Jacob for the same.
A127: Perquisites | B127: 0 | C127: 6 | D127: 8 | F127: 0.33 | H127: 6 shilling 8pence from others of the hundred for the same.
A128: Perquisites | B128: 0 | C128: 3 | D128: 0 | F128: 0.15 | H128: 3 shilling from John de Molendino because he received the lord's customary tenants at his mill.
A129: Perquisites | B129: 4 | C129: 19 | D129: 2 | F129: 4.96 | H129: £4 19 shilling 2pence from other small perquisites.
A130: Perquisites | B130: 6 | C130: 5 | D130: 6 | F130: 6.28 | H130: Total, £6 5 shilling 6pence
A131: Perquisites | F131: 6.28 | G131: 0 | H131: Total
A133: Total of all receipts recorded in accounts | B133: 91 | C133: 11 | D133: 10 | F133: =B133+C133/20+D133/240 | H133: Total of all receipts, £91 11 s. 10pence
A134: Total cross-check without arrears | F134: =F131+F121+F100+F106+F88+F51+F45 | G134: =F134-F133
...

Sheet Expenses
A1: CHERITON EXPENSES
A2: Heading | B2: £ | C2: s | D2: d | F2: Total in £ | G2: Error | H2: Notes | J2: Fixed investment | K2: Demesne fixed investment
A3: Cost of ploughs | B3: 0 | C3: 12 | D3: 8 | F3: 0.63 | H3: {henceforth the customary tenants should not be made to plough if it is seen that a profit is able to be made}In ironwork of 4 ploughs for the year and 1 plough at the time of the Lenten sowing 12 shilling 8pence.
A4: Cost of ploughs | B4: 0 | C4: 0 | D4: 9 | F4: 0.04 | H4: 1 ploughshare bought 9pence. | J4: =F4 | K4: =J4
A5: Cost of ploughs | B5: 0 | C5: 1 | D5: 4 | F5: 0.07 | H5: 4 plough feet bought 1 shilling 4pence. | J5: =F5 | K5: =J5
A6: Cost of ploughs | B6: 0 | C6: 0 | D6: 9 | F6: 0.04 | H6: 3 pairs of wheels bought 9pence. | J6: =F6 | K6: =J6
A7: Cost of ploughs | B7: 0 | C7: 0 | D7: 3 | F7: 0.01 | H7: fitting ploughs with iron tyres 3pence. | J7: =F7 | K7: =J7
A8: Cost of ploughs | B8: 0 | C8: 1 | D8: 10 | F8: 0.09 | H8: shoeing 8 plough-horses hauling before the oxen 1 shilling 10pence. | J8: =F8 | K8: =J8
A9: Cost of ploughs | B9: 0 | C9: 7 | D9: 6 | F9: 0.38 | H9: boon-works of 23 ploughmen in winter and 22 ploughmen in Lent 7 shilling 6pence, and each ploughman ploughed 2 acres in winter and 2 acres in Lent as they lie and will have therefor 2pence Moreover, for 5 ploughmen of Ovington 5pence, and each ploughman ploughed 1 acre in winter and will have therefor 1pence.
A10: Cost of ploughs | B10: 0 | C10: 0 | D10: 2 | F10: 0.01 | H10: 1 new harrow made and others mended 2pence. | J10: =F10 | K10: =J10
A11: Cost of ploughs | B11: 0 | C11: 1 | D11: 2 | F11: 0.06 | H11: spreading dung in the fields 1 shilling 2pence.
A12: Cost of ploughs | B12: 2 | C12: 6 | D12: 0 | F12: 2.3 | H12: 4 oxen bought £2 6 shilling, at 11 shilling each for 2, and 12 shilling each for 2..
A13: Cost of ploughs | B13: 0 | C13: 10 | D13: 0 | F13: =B13+C13/20+D13/240 | H13: forage bought for oxen and other animals 10 shilling
A14: Cost of ploughs | B14: 4 | C14: 2 | D14: 10 | F14: 4.14 | H14: Total, £4 2 shilling 10pence
A15: Cost of ploughs | F15: =SUM(F3:F13) | G15: =F15-F14 | H15: Total
A17: Purchase of corn | B17: 0 | C17: 5 | D17: 3 | F17: 0.26 | H17: In 1 qr 6 bushels of winter barley bought for sowing 5 shilling 3pence, at 3 shilling a qr.
A18: Purchase of corn | B18: 2 | C18: 15 | D18: 0 | F18: 2.75 | H18: 15 quarters of barley bought for the liveries of the manorial servants £2 15 shilling, at 3 shilling a qr for 5 quarters, and 4 shilling a qr for 10 quarters.
A19: Purchase of corn | B19: 3 | C19: 0 | D19: 3 | F19: 3.01 | H19: Total, £3 3pence
A20: Purchase of corn | F20: 3.01 | G20: 0 | H20: Total
A22: Carts | B22: 0 | C22: 0 | D22: 9 | F22: 0.04 | H22: In 1 pair of wheels made from the lord's timber 9pence. | J22: =F22 | K22: =J22
A23: Carts | B23: 0 | C23: 5 | D23: 0 | F23: 0.25 | H23: iron bought and large nails made and old tyres mended and put on the said wheels with the stipend of the smith 5 shilling. | J23: =F23 | K23: =J23
A24: Carts | B24: 0 | C24: 0 | D24: 6 | F24: 0.03 | H24: fitting the cart with axles 6pence. | J24: =F24 | K24: =J24
A25: Carts | B25: 0 | C25: 1 | D25: 1 | F25: 0.05 | H25: clouts, nails and grease bought 1 shilling 1pence. | J25: =F25 | K25: =J25
A26: Carts | B26: 0 | C26: 0 | D26: 5 | F26: 0.02 | H26: white leather bought for harnesses 5pence. | J26: =F26 | K26: =J26
A27: Carts | B27: 0 | C27: 3 | D27: 0 | F27: 0.15 | H27: shoeing 2 cart-horses 3 shilling. | J27: =F27 | K27: =J27
A28: Carts | B28: 0 | C28: 0 | D28: 10 | F28: 0.04 | H28: shoeing 3 plough-horses helping the cart-horses at the time of the summer sowing to clear dung 10pence. | J28: =F28 | K28: =J28
A29: Carts | B29: 0 | C29: 0 | D29: 1 | F29: 0 | H29: 4 halters made 1pence. | J29: =F29 | K29: =J29
A30: Carts | B30: 0 | C30: 1 | D30: 0 | F30: 0.05 | H30: 1 collar and 1 pair of saddle-pads bought 1 shilling. | J30: =F30 | K30: =J30
A31: Carts | B31: 0 | C31: 0 | D31: 2 | F31: 0.01 | H31: 2 ropes bought for tethering horses in the pasture 2pence. | J31: =F31 | K31: =J31
A32: Carts | B32: 0 | C32: 3 | D32: 0 | F32: =B32+C32/20+D32/240 | H32: stipend of 1 carter for the year 3 shilling
A33: Carts | B33: 0 | C33: 14 | D33: 10 | F33: =B33+C33/20+D33/240 | H33: Total, 14 shilling 10pence
A34: Carts | F34: =SUM(F22:F32) | G34: =F34-F33 | H34: Total
A36: Dairy | B36: 0 | C36: 1 | D36: 6 | F36: 0.08 | H36: In 6 bushels of salt bought 1 shilling 6pence. | J36: =F36 | K36: =J36
A37: Dairy | B37: 0 | C37: 0 | D37: 4 | F37: 0.02 | H37: a press bought 4pence. | J37: =F37 | K37: =J37
A38: Dairy | B38: 0 | C38: 0 | D38: 5 | F38: 0.02 | H38: earthenware pots and pans bought 5pence. | J38: =F38 | K38: =J38
A39: Dairy | B39: 0 | C39: 0 | D39: 8 | F39: 0.03 | H39: woollen and linen cloth bought 8pence. | J39: =F39 | K39: =J39
A40: Dairy | B40: 0 | C40: 0 | D40: 6 | F40: 0.03 | H40: 1 mould bought 6pence. | J40: =F40 | K40: =J40
A41: Dairy | B41: 0 | C41: 0 | D41: 5 | F41: 0.02 | H41: 1 tine bought 5pence. | J41: =F41 | K41: =J41
A42: Dairy | B42: 0 | C42: 0 | D42: 4 | F42: 0.02 | H42: mending other utensils of the dairy 4pence. | J42: =F42 | K42: =J42
A43: Dairy | B43: 0 | C43: 3 | D43: 9 | F43: 0.19 | H43: 15 ells of canvas bought 3 shilling 9pence. | J43: =F43 | K43: =J43
A44: Dairy | B44: 0 | C44: 0 | D44: 4 | F44: 0.02 | H44: packing wool and making sacks with thread bought for the same 4pence. | J44: =F44 | K44: =J44
A45: Dairy | B45: 1 | C45: 1 | D45: 0 | F45: 1.05 | H45: vinegar, copperas and grease to make well diseased sheep £1 1 shilling. | J45: =F45 | K45: =J45
A46: Dairy | B46: 0 | C46: 2 | D46: 0 | F46: 0.1 | H46: 48 hurdles made for the fold 2 shilling. | J46: =F46 | K46: =J46
A47: Dairy | B47: 0 | C47: 2 | D47: 0 | F47: 0.1 | H47: stipend of 1 dairymaid from the Purification (2 February) until Michaelmas (29 September) 2 shilling. | J47: =F47 | K47: =J47
... A49: Dairy | B49: 0 | C49: 1 | D49: 6 | F49: 0.08 | H49: roofing the wether-house in places 1 shilling 6pence. | J49: =F49 | K49: =J49
A50: Dairy | B50: 1 | C50: 4 | D50: 6 | F50: 1.22 | H50: 39 lambs bought before shearing £1 4 shilling 6pence, at 6pence each for 9, and 8pence each for 30..
A51: Dairy | B51: 0 | C51: 9 | D51: 9 | F51: 0.49 | H51: 13 pigs bought 9 shilling 9pence, at 9pence each.
A52: Dairy | B52: 0 | C52: 0 | D52: 2.5 | F52: 0.01 | H52: gelding piglets 2.5pence.
A53: Dairy | B53: 0 | C53: 2 | D53: 0 | F53: =B53+C53/20+D53/240 | H53: stipend of 1 cowherd 2 shilling
A54: Dairy | B54: 3 | C54: 12 | D54: 2.5 | F54: 3.61 | H54: Total, £3 12 shilling 2.5pence
A55: Dairy | F55: =SUM(F36:F53) | G55: =F55-F54 | H55: Total
A57: Repair of buildings | B57: 0 | C57: 4 | D57: 0 | F57: 0.2 | H57: In collecting stubble and roofing the buildings in the curia in places 4 shilling.
A58: Repair of buildings | B58: 0 | C58: 2 | D58: 0 | F58: 0.1 | H58: wattling and mending the walls around the byre 2 shilling. | J58: =F58 | K58: =J58
A59: Repair of buildings | B59: 0 | C59: 0 | D59: 7 | F59: 0.03 | H59: building 1 new bridge over the water 7pence. | J59: =F59 | K59: =F59
A60: Repair of buildings | B60: 0 | C60: 0 | D60: 1.25 | F60: =B60+C60/20+D60/240 | H60: 1 rope bought for the louver in the hall 1.25pence
A61: Repair of buildings | B61: 0 | C61: 6 | D61: 8.6 | F61: =B61+C61/20+D61/240 | H61: Total, 6 shilling 8.5pence
A62: Repair of buildings | F62: =SUM(F57:F60) | G62: =F62-F61 | H62: Total
A64: Threshing of corn | B64: 0 | C64: 11 | D64: 2.25 | F64: 0.56 | H64: In threshing and winnowing 60 quarters of wheat and curall by piece-work 11 shilling, at 2.25pence a qr.
A65: Threshing of corn | B65: 0 | C65: 3 | D65: 4.5 | F65: 0.17 | H65: threshing and winnowing 7 quarters of winter barley and 20 quarters of barley by piece-work 3 shilling 4.5pence, at 1.5pence a heaped quarter.
A66: Threshing of corn | B66: 0 | C66: 0 | D66: 0 | F66: 0 | H66: Know that the workers threshed 36.5 quarters 2 bushels of wheat and curall, 16 quarters 1 bushels of barley, 86 quarters of oats, 2.25 quarters of peas and 2 quarters 1 bushels of vetches for their labour service.
A67: Threshing of corn | B67: 0 | C67: 5 | D67: 1.5 | F67: 0.26 | H67: weeding all the corn except that done by labour service 5 shilling 1.5pence.
A68: Threshing of corn | B68: 0 | C68: 18 | D68: 1 | F68: =B68+C68/20+D68/240 | H68: wages of 1 attendant who keeps the barn and who threshed at various times 18 shilling 1pence
A69: Threshing of corn | B69: 1 | C69: 17 | D69: 7 | F69: 1.88 | H69: Total, £1 17 shilling 7pence
A70: Threshing of corn | F70: =SUM(F64:F68) | G70: =F70-F69 | H70: Total
A72: Harvest-time | B72: 2 | C72: 2 | D72: 8.5 | F72: 2.14 | H72: In bread bought for 12.5 boon-works of 1,025 men, with the officials of the curia and 14 men of Ovington, who eat twice a day except this year, and 15 workers who are bound, at the choice of the lord, to reap with the boon-works and have food like the others, each reaping either' acre of wheat or barley or 1 acre of oats and having 1 sheaf as it falls, £2 2 shilling 8.5pence.
A73: Harvest-time | B73: 0 | C73: 19 | D73: 5 | F73: 0.97 | H73: herrings and cheese bought for a want of herrings to eat with the bread 19 shilling 5pence, and each ought to have 4 herrings a day.
A74: Harvest-time | B74: 0 | C74: 0 | D74: 0 | F74: 0 | H74: They reaped 245 acres of barley and 210 acres of oats as they lie.
A75: Harvest-time | B75: 0 | C75: 6 | D75: 8 | F75: =B75+C75/20+D75/240 | H75: stipend of 1 hayward for the year 6 shilling 8pence
A76: Harvest-time | B76: 3 | C76: 8 | D76: 9.5 | F76: 3.44 | H76: Total, £3 8 shilling 9.5pence
A77: Harvest-time | F77: =SUM(F72:F75) | G77: =F77-F76 | H77: Total
A79: Expenses of the steward | B79: 0 | C79: 6 | D79: 9 | F79: 0.34 | H79: In expenses of Simon, clerk, holding the place of the steward far the 2 toums 6 shilling 9pence
A80: Expenses of the steward | B80: 0 | C80: 6 | D80: 9 | F80: 0.34 | H80: Total, 6 shilling 9pence
A81: Expenses of the steward | F81: 0.34 | G81: 0 | H81: Total
A83: Purchase of stock | B83: 3 | C83: 19 | D83: 4.25 | F83: 3.97 | H83: In 15 animals bought for pasturing £3 19 shilling 4.25pence
A84: Purchase of stock | B84: 3 | C84: 19 | D84: 4.25 | F84: 3.97 | H84: Total, £3 19 shilling 4.5pence
A85: Purchase of stock | F85: 3.97 | G85: 0 | H85: Total
A87: Total of all expenses | B87: 21 | C87: 0 | D87: 0 | F87: 21 | H87: Total of all expenses, £21 11 s. 6pence
F88: =F87 | G88: =F88-F87 | H88: Total
A90: thus he owes | B90: 70 | C90: 0 | D90: 4 | F90: 70.02 | H90: And thus he owes, £70 4pence
A91: thus he owes | F91: 70.02 | G91: 0 | H91: Total
A93: Allowances | B93: 3 | C93: 14 | D93: 4 | F93: 3.72 | H93: in 10 cows bought for the stock of the manor £3 14 shilling 4pence, at 7 shilling 6pence each for 6, and 7 shilling each for 4.
A94: Allowances | B94: 3 | C94: 14 | D94: 4 | F94: 3.72 | H94: Total, £3 14 shilling 4pence
A95: Allowances | F95: 3.72 | G95: 0 | H95: Total
A97: Cash deliveries | B97: 40 | C97: 10 | D97: 7.5 | F97: 40.53 | H97: Delivered to Sir Geoffrey, treasurer of Wolvesey, by 1 tally, £40 10 shilling 7.5pence
A98: Cash deliveries | B98: 44 | C98: 4 | D98: 11.5 | F98: 44.25 | G98: =F98-(F97+F95) | H98: Total of all allowances and cash deliveries, £44 4 shilling 11.5pence
A100: Total of all expenses per account | F100: =F88
A101: Total of all expenses (calculated here) | F101: =F85+F81+F77+F70+F62+F55+F34+F20+F15 | G101: =F101-F100
A102: Total fixed investment | F102: =SUM(J3:J76)
A103: Total Demesne fixed investment | F103: =SUM(K3:K76)

Sheet Issues of the Grange
A1: Gross Output | B1: Total Quantity | C1: Account Total Quarters | D1: Bought in Total Quarters | E1: Received from churchscot | F1: Sold Total Quarters | G1: Difference Produced+Bought-Sold | H1: Weighted Average Price per Quarter | I1: Value of Total Production weighted
A2: wheat | B2: 94 | D2: 0 | F2: 60.125 | G2: =B2-F2 | H2: 0.33333333 | I2: =H2*B2
A3: curall | B3: 3.25 | D3: 0 | F3: 1.875 | G3: =B3-F3 | H3: 0.23333333 | I3: =H3*B3
A4: bere | B4: 8.75 | D4: 1.75 | G4: =B4-F4 | I4: =H4*B4
A5: barley | B5: 55.5 | D5: 15 | F5: 21.125 | G5: =B5-F5 | H5: 0.21854043 | I5: =H5*B5
A6: oats | B6: 135 | D6: 0 | F6: 38.25 | G6: =B6-F6 | H6: 0.11394336 | I6: =H6*B6
A7: peas | B7: 2.5 | D7: 0 | F7: 0.375 | G7: =B7-F7 | H7: 0.17222222 | I7: =H7*B7
A8: vetches | B8: 2.125 | D8: 0 | F8: 0.625 | G8: =B8-F8 | H8: 0.1 | I8: =H8*B8
A13: Net output | B13: Gross output | C13: Seed quarters | D13: Seed bushels | E13: Seed total quarters | F13: tithe quarters | G13: tithe bushels | H13: tithe total | I13: manorial servants quarters | J13: manorial servants bushels | K13: manorial servants total quarters | L13: output net of tithe, seed, liveries | M13: in stock from last year | N13: Price in £ | O13: Value of net output in £ | P13: Value of sales (in "Sale of Corn") in £
A14: wheat | B14: =B2 | C14: 33 | D14: 3 | E14: =C14+D14/8 | J14: 4 | K14: =I14+J14/8 | L14: =B14-E14-H14-K14 | N14: =H2 | O14: =N14*L14
A15: curall | B15: =B3 | E15: =C15+D15/8 | I15: 1 | J15: 3 | K15: =I15+J15/8 | L15: =B15-E15-H15-K15 | N15: =H3 | O15: =N15*L15
A16: bere | B16: =B4 | C16: 1 | D16: 6 | E16: =C16+D16/8 | I16: 4 | K16: =I16+J16/8 | L16: =B16-E16-H16-K16 | N16: =H4 | O16: =N16*L16
A17: barley | B17: =B5 | C17: 16.5 | D17: 2 | E17: =C17+D17/8 | I17: =13+2+1.5+3 | J17: =4+2+6+6+6 | K17: =I17+J17/8 | L17: =B17-E17-H17-K17 | N17: =H5 | O17: =N17*L17
A18: oats | B18: =B6 | C18: 64 | E18: =C18+D18/8 | I18: =9+22 | J18: =6+2 | K18: =I18+J18/8 | L18: =B18-E18-H18-K18 | N18: =H6 | O18: =N18*L18
A19: peas | B19: =B7 | D19: 5 | E19: =C19+D19/8 | J19: =7+5 | K19: =I19+J19/8 | L19: =B19-E19-H19-K19 | N19: =H7 | O19: =N19*L19
A20: vetches | B20: =B8 | C20: 1.5 | E20: =C20+D20/8 | K20: =I20+J20/8 | L20: =B20-E20-H20-K20 | N20: =H8 | O20: =N20*L20

Sheet Issues of the Mills

Sheet Stock
A1: CHERITON STOCK ACCOUNT
C3: added | G3: subtracted
A4: Livestock | B4: Inherited stock | C4: added | D4: strays | E4: herbage | F4: churchscot | G4: of which in default | H4: sold | I4: in murrain | J4: accounted for elsewhere | K4: End-period stock | L4: cross-check | M4: stock building | N4: raw production | O4: Unit price (£) | P4: Value of stock (£) at given value | Q4: Value of stock (£) at sales prices | R4: Sales in (£) | S4: Value of stock building (£) | T4: Value of production (£) at sales prices | U4: Details
A5: Cart-horses | B5: 2 | K5: 2
A6: Mares
A7: Plough horses | B7: 13 | H7: 3 | I7: 2 | K7: 8 | R7: =Receipts!F69
A8: Colts (unspecified years)
A9: Colts (2 years) | B9: 2 | I9: 1 | K9: 1
A10: Colts (1 year)
A11: Foals
A12: Oxen | B12: 39 | C12: =1+4 | H12: 3 | I12: 1 | K12: 40 | R12: =Receipts!F70
A13: Bulls
A14: Cows | B14: 10 | C14: =1+3+10 | I14: 1 | K14: 22
A15: Steers | B15: 4 | C15: 15 | H15: 15 | I15: 1 | J15: =1+3 | K15: 0 | R15: =Receipts!F84
A16: Bullocks | B16: 4 | K16: 4
A17: Yearlings | B17: 4 | K17: 4
A18: Calves | B18: 14 | C18: 1 | H18: =4+1 | I18: 1 | J18: 1 | K18: 8 | R18: =Receipts!F71
A19: Wethers | B19: 324 | C19: 53 | H19: 18 | I19: =10+8 | J19: 2 | K19: 339 | R19: =Receipts!F72
A20: Rams | B20: 8 | C20: 2 | K20: 10
A21: Ewes | B21: 288 | C21: 52 | H21: 22 | I21: =10+6 | J21: 1 | K21: 301 | R21: =Receipts!F73
A22: Hoggs | B22: 150 | I22: =30+13 | J22: =53+2+52 | K22: 0
A23: Lambs | B23: 236 | C23: 39 | H23: 23 | I23: =33+13+4 | J23: =23+3 | K23: 176 | R23: =Receipts!F74
A24: Boars
A25: Sows | B25: 2 | K25: 2
A26: Pigs | B26: 17 | C26: =19+13+1+1 | H26: 15 | K26: 36 | R26: =Receipts!F75
A27: Hoggets | B27: 21 | I27: 2 | J27: 19 | K27: 0
A28: Piglets | B28: 31 | C28: =3+1 | I28: 3 | K28: 24
A29: Swans
A30: Peacocks
A31: Total Value | R31: =SUM(R5:R29)
A34: Wool
A35: Coarse wool | C35: 679 | J35: =2+677 | O35: 0.02 | T35: =O35*J35
A36: Lamb's wool | C36: 180 | J36: 180 | O36: 0.01 | T36: =O36*J36
A37: Wool locks
A38: Wool sold at shearing
A39: Total wool | T39: =SUM(T35:T38)
A42: Hides
A43: Ox hides | C43: 1 | H43: 1 | O43: =R43/H43 | R43: =Receipts!F76 | T43: =O43*C43
A44: cow | C44: 1 | H44: 1 | O44: =R44/H44 | R44: =Receipts!F77 | T44: =O44*C44
A45: plough horses | C45: 2 | H45: 2 | O45: 0.03 | T45: =O45*C45 | U45: sale not recorded, price from Bishops Sutton
A46: colt | C46: 1 | H46: 1 | O46: 0.03 | T46: =O46*C46 | U46: sale not recorded
A47: Mare
A48: Steer | C48: 1 | H48: 1 | O48: =R48/H48 | R48: =Receipts!F77 | T48: =O48*C48
A49: calves | C49: 1 | H49: 1 | O49: 0.03 | T49: =O49*C49 | U49: price from Alresford
A50: pigs
A51: Woolskin
A52: wethers | C52: 10 | H52: 10 | O52: =R52/H52 | T52: =O52*C52
A53: rams
A54: ewes | C54: 10 | H54: 10 | O54: =R54/H54 | T54: =O54*C54
A55: hoggs | C55: 30 | H55: 30 | O55: =R55/H55 | T55: =O55*C55
A56: Woolskins | C56: =SUM(C52:C55) | H56: =SUM(H52:H55) | O56: =R56/H56 | R56: =Receipts!F79 | T56: =O56*C56
A57: Bareskins
A58: wethers | C58: 8 | H58: 8 | O58: 0.01 | T58: =O58*C58 | U58: sale not recorded, price from Alresford
A59: rams
A60: ewes | C60: 6 | H60: 6 | O60: 0.01 | T60: =O60*C60 | U60: sale not recorded, price from Alresford
A61: hoggs | C61: 13 | H61: 13 | O61: =R61/H61 | R61: =Receipts!F81 | T61: =O61*C61
A62: Bareskins (total)
A63: Lambskins | C63: =33+17 | H63: 50 | O63: =R63/H63 | R63: =Receipts!F80 | T63: =O63*C63 | U63: issues only record the sale of 33 skins
A64: Rotted skins
A65: Shorn skins
A66: Total | R66: =SUM(R43:R65) | T66: =SUM(T43:T63)
A69: Poultry stock
A70: Hens
A71: Geese
A72: Capons (from chickens)
A73: Cocks & hens
A74: Total poultry stock
A75: Total poultry excluding churchscot
A77: Poultry production
A78: Eggs | F78: 1050 | H78: 1050 | O78: =R78/H78 | R78: =Receipts!F61 | T78: =O78*H78
A79: Cocks & hens from churchscot of customary tenants | F79: 128 | G79: 15 | H79: 113 | O79: =R79/H79 | R79: =Receipts!F60 | T79: =O79*H79
A80: Sum of above
A81: Total | R81: =SUM(R77:R80) | T81: =SUM(T78:T79)
A84: Meat
A85: Beef
A86: Mutton
A87: Pork
A88: Total
A90: Cheese
A91: Winter cheese | C91: 30 | O91: =R91/C91 | R91: =Receipts!F66 | T91: =O91*C91
A92: Summer cheese | C92: 155 | H92: 137 | J92: 15 | O92: =R92/H92 | R92: =Receipts!F67 | T92: =O92*C92
A93: Total | R93: =R92 | T93: =SUM(T91:T92)
A95: Butter
A96: Butter | C96: 1 | H96: 1 | O96: =R96/H96 | R96: =Receipts!F68 | T96: =O96*C96 | U96: measured in wey
A97: Total | R97: =R96 | T97: =T96
A99: Total Dairy Sales
A102: Cider
A105: Additional Information (not necessarily useful)
A106: Utensils
A107: ploughs
A108: carts
A109: cart-ropes
A110: corn baskets
A111: seed-sacks
A112: seed basket
A113: locks for the doors
A114: lead vessel
... A131: brass posnets

Sheet raw data
A1: Heading | B1: Sentence | C1: Total in Pounds | D1: Pounds | E1: Shillings | F1: Pence | G1: Corn | H1: Total Quarters Except 1 | I1: Total Bushels Except 1 | J1: Total Corn Cross-Check | K1: Total Corn Manorial Account | L1: Corn Quantity Error | M1: Quarters 1 | N1: Bushels 1 | O1: Quarters 2 | P1: Bushels 2 | Q1: Quarters 3 | R1: Bushels 3 | S1: Quarters 4 | T1: Bushels 4 | U1: Quarters 5 | V1: Bushels 5 | W1: shilling a quarter 1 | X1: pence a quarter 1 | Y1: shilling a quarter 2 | Z1: pence a quarter 2 | AA1: shilling a quarter 3 | AB1: pence a quarter 3 | AC1: shilling a quarter 4 | AD1: pence a quarter 4 | AE1: shilling a bushel 1 | AF1: pence a bushel 1 | AG1: shilling a bushel 2 | AH1: pence a bushel 2 | AI1: shilling a bushel 3 | AJ1: pence a bushel 3 | AK1: shilling a bushel 4 | AL1: pence a bushel 4
A2: Arrears | B2: Nicholas, bailiff, and Richard Eme, reeve, render account for £57 12 shilling 3.5pence of arrears from the previous year. | C2: 57.61 | D2: 57 | E2: 12 | F2: 3.5 | H2: 0 | I2: 0 | J2: 0 | K2: 0 | L2: 0 | M2: 0 | N2: 0
A3: Arrears | B3: All delivered to Sir Geoffrey of Wolvesey. | C3: 0 | D3: 0 | E3: 0 | F3: 0 | H3: 0 | I3: 0 | J3: 0 | K3: 0 | L3: 0 | M3: 0 | N3: 0
A4: Arrears | B4: They are quit. | C4: 0 | D4: 0 | E4: 0 | F4: 0 | H4: 0 | I4: 0 | J4: 0 | K4: 0 | L4: 0 | M4: 0 | N4: 0
A5: Rents of assize | B5: The same render account for £5 1 shilling 9pence for rents of the manor of Cheriton at Christmas. | C5: 5.09 | D5: 5 | E5: 1 | F5: 9 | H5: 0 | I5: 0 | J5: 0 | K5: 0 | L5: 0 | M5: 0 | N5: 0
A6: Rents of assize | B6: £8 2 shilling 8.75pence at Easter (22 April). | C6: 8.14 | D6: 8 | E6: 2 | F6: 8.75 | H6: 0 | I6: 0 | J6: 0 | K6: 0 | L6: 0 | M6: 0 | N6: 0
A7: Rents of assize | B7: £5 2 shilling 8.25pence at St John the Baptist (24 June). | C7: 5.13 | D7: 5 | E7: 2 | F7: 8.25 | H7: 0 | I7: 0 | J7: 0 | K7: 0 | L7: 0 | M7: 0 | N7: 0
A8: Rents of assize | B8: £13 4 shilling 9pence at Michaelmas (29 September). | C8: 13.24 | D8: 13 | E8: 4 | F8: 9 | H8: 0 | I8: 0 | J8: 0 | K8: 0 | L8: 0 | M8: 0 | N8: 0
A9: Rents of assize | B9: Total, £31 11 shilling 11pence | C9: 31.6 | D9: 31 | E9: 11 | F9: 11 | H9: 0 | I9: 0 | J9: 0 | K9: 0 | L9: 0 | M9: 0 | N9: 0
A10: Quittances | B10: In quittance of 1 reeve for the year 5 shilling. | C10: 0.25 | D10: 0 | E10: 5 | F10: 0 | H10: 0 | I10: 0 | J10: 0 | K10: 0 | L10: 0 | M10: 0 | N10: 0
A11: Quittances | B11: 1 smith for the ironwork of 5 ploughs for the year 5 shilling. | C11: 0.25 | D11: 0 | E11: 5 | F11: 0 | H11: 0 | I11: 0 | J11: 0 | K11: 0 | L11: 0 | M11: 0 | N11: 0
A12: Quittances | B12: 1 bartoner for the year 2 shilling 6pence. | C12: 0.12 | D12: 0 | E12: 2 | F12: 6 | H12: 0 | I12: 0 | J12: 0 | K12: 0 | L12: 0 | M12: 0 | N12: 0
A13: Quittances | B13: 1 keeper of ewes for the year 2 shilling. | C13: 0.1 | D13: 0 | E13: 2 | F13: 0 | H13: 0 | I13: 0 | J13: 0 | K13: 0 | L13: 0 | M13: 0 | N13: 0
... A71: Issues of the manor | B71: Total, £23 16 shilling 6.5pence | C71: 23.83 | D71: 23 | E71: 16 | F71: 6.5 | H71: 0 | I71: 0 | J71: 0 | K71: 0 | L71: 0 | M71: 0 | N71: 0
A72: Sale of wheat | B72: The same render account for £20 10pence from 60 quarters 1 bushels of wheat sold, at 6 shilling 8pence a quarters. | C72: 20.04 | D72: 20 | E72: 0 | F72: 10 | G72: wheat | H72: 60 | I72: 1 | J72: 60.125 | K72: 60.125 | L72: 0 | M72: 60 | N72: 1 | W72: 6 | X72: 8
A73: Sale of wheat | B73: 8 shilling 9pence from 1 quarters 7 bushels of curall sold. | C73: 0.44 | D73: 0 | E73: 8 | F73: 9 | G73: curall | H73: 1 | I73: 7 | J73: 1.875 | K73: 1.875 | L73: 0 | M73: 1 | N73: 7
A74: Sale of wheat | B74: 9 shilling from 3 quarters of winter barley sold, at 3 shilling a quarters. | C74: 0.45 | D74: 0 | E74: 9 | F74: 0 | G74: barley | H74: 3 | I74: 0 | J74: 3 | K74: 3 | L74: 0 | M74: 3 | N74: 0 | W74: 3 | X74: 0
A75: Sale of wheat | B75: £3 15 shilling 10pence from 16 quarters 2 bushels of barley sold, at 4 shilling 8pence a quarters. | C75: 3.79 | D75: 3 | E75: 15 | F75: 10 | G75: barley | H75: 16 | I75: 2 | J75: 16.25 | K75: 16.25 | L75: 0 | M75: 16 | N75: 2 | W75: 4 | X75: 8
A76: Sale of wheat | B76: £3 14 shilling 8pence from 32 quarters of oats sold, at 2 shilling 4pence a quarters. | C76: 3.73 | D76: 3 | E76: 14 | F76: 8 | G76: oats | H76: 32 | I76: 0 | J76: 32 | K76: 32 | L76: 0 | M76: 32 | N76: 0 | W76: 2 | X76: 4
A77: Sale of wheat | B77: 1 shilling 3.5pence from 3 bushels of peas sold. | C77: 0.06 | D77: 0 | E77: 1 | F77: 3.5 | G77: peas | H77: 0 | I77: 3 | J77: 0.375 | K77: 0.375 | L77: 0 | M77: 0 | N77: 3
A78: Sale of wheat | B78: 1 shilling 3pence from 5 bushels of vetches sold. | C78: 0.06 | D78: 0 | E78: 1 | F78: 3 | G78: vetches | H78: 0 | I78: 5 | J78: 0.625 | K78: 0.625 | L78: 0 | M78: 0 | N78: 5
A79: Sale of wheat | B79: 7 shilling 6pence from 1 quarters 7 bushels of barley sold at the audit. | C79: 0.38 | D79: 0 | E79: 7 | F79: 6 | G79: barley | H79: 1 | I79: 7 | J79: 1.875 | K79: 1.875 | L79: 0 | M79: 1 | N79: 7
A80: Sale of wheat | B80: 12 shilling 6pence from 6 quarters 2 bushels of oats sold at the audit. | C80: 0.62 | D80: 0 | E80: 12 | F80: 6 | G80: oats | H80: 6 | I80: 2 | J80: 6.25 | K80: 6.25 | L80: 0 | M80: 6 | N80: 2
A81: Sale of wheat | B81: Total, £29 11 shilling 7.5pence | C81: 29.58 | D81: 29 | E81: 11 | F81: 7.5 | H81: 0 | I81: 0 | J81: 0 | K81: 0 | L81: 0 | M81: 0 | N81: 0
A82: Corn from the mill | B82: The same render account for 2 shilling 6pence from 4 bushels of wheat from the issue of the mill sold. | C82: 0.12 | D82: 0 | E82: 2 | F82: 6 | G82: wheat | H82: 0 | I82: 4 | J82: 0.5 | K82: 0.5 | L82: 0 | M82: 0 | N82: 4
A83: Corn from the mill | B83: £2 12 shilling from 14 quarters of barley from the issue of the same mill sold, at 3 shilling a quarters for 4 quarters, and 4 shilling a quarters for 10 quarters. | C83: 2.6 | D83: 2 | E83: 12 | F83: 0 | G83: barley | H83: 14 | I83: 0 | J83: 14 | K83: 14 | L83: 0 | M83: 14 | N83: 0 | O83: 4 | P83: 0 | Q83: 10 | R83: 0 | W83: 3 | X83: 0 | Y83: 4 | Z83: 0
A84: Corn from the mill | B84: 1 shilling 6pence from 4 bushels of malt from the issue of the same mill solpence Total, £2 16 shilling | C84: 2.8 | D84: 2 | E84: 16 | F84: 0 | H84: 0 | I84: 4 | J84: 0.5 | K84: 0.5 | L84: 0 | M84: 0 | N84: 4
A85: Entry and marriage fines with tithingpenny | B85: The same render account for 6 shilling1 8pence from the tithing of Cheriton at the hundred-court of Martinmas. | C85: 0.33 | D85: 0 | E85: 6 | F85: 8 | H85: 0 | I85: 0 | J85: 0 | K85: 0 | L85: 0 | M85: 0 | N85: 0
A86: Entry and marriage fines with tithingpenny | B86: 6 shilling 8pence from the same for the same at the hundred-court of Hockday. | C86: 0.33 | D86: 0 | E86: 6 | F86: 8 | H86: 0 | I86: 0 | J86: 0 | K86: 0 | L86: 0 | M86: 0 | N86: 0
A87: Entry and marriage fines with tithingpenny | B87: 3 shilling 4pence from Joan la Clodyar' to have 1 cotland which belonged to Richard le Clodyare her brother. | C87: 0.17 | D87: 0 | E87: 3 | F87: 4 | H87: 0 | I87: 0 | J87: 0 | K87: 0 | L87: 0 | M87: 0 | N87: 0
A88: Entry and marriage fines with tithingpenny | B88: 3 shilling 4pence from William, son of John Som', to have the said land by surrender of the said Joan Clodiar'. | C88: 0.17 | D88: 0 | E88: 3 | F88: 4 | H88: 0 | I88: 0 | J88: 0 | K88: 0 | L88: 0 | M88: 0 | N88: 0
A89: Entry and marriage fines with tithingpenny | B89: 6 shilling 8pence from John ate Med to have 1 cotland with Alveva his wife. | C89: 0.33 | D89: 0 | E89: 6 | F89: 8 | H89: 0 | I89: 0 | J89: 0 | K89: 0 | L89: 0 | M89: 0 | N89: 0
A90: Entry and marriage fines with tithingpenny | B90: 5 shilling from Christina, relict of Gang', to retain 1 cotland which belonged to her husband. | C90: 0.25 | D90: 0 | E90: 5 | F90: 0 | H90: 0 | I90: 0 | J90: 0 | K90: 0 | L90: 0 | M90: 0 | N90: 0
A91: Entry and marriage fines with tithingpenny | B91: 5 shilling from Alice Lovering to retain 1 cotland after the death of her husband. | C91: 0.25 | D91: 0 | E91: 5 | F91: 0 | H91: 0 | I91: 0 | J91: 0 | K91: 0 | L91: 0 | M91: 0 | N91: 0
A92: Entry and marriage fines with tithingpenny | B92: 10 shilling from Robert Jan to have 1 virgate of land, after the mortuary payment for the relict of Cartere, his mother, out of her inheritance. | C92: 0.5 | D92: 0 | E92: 10 | F92: 0 | H92: 0 | I92: 0 | J92: 0 | K92: 0 | L92: 0 | M92: 0 | N92: 0
A93: Entry and marriage fines with tithingpenny | B93: 10 shilling from Simon Crech, son of William Crech, to have 0.5 cotland which came into the lord's hands as his escheat because a certain Alice la Schinnere who held the said tenement withdrew and noone succeeded to the said land by inheritance, having been waiting for 1 year. | C93: 0.5 | D93: 0 | E93: 10 | F93: 0 | H93: 0 | I93: 0 | J93: 0 | K93: 0 | L93: 0 | M93: 0 | N93: 0
A94: Entry and marriage fines with tithingpenny | B94: 6 shilling 8pence from Joan, relict of le Swon, to retain 1 virgate of land which belonged to Henry her husband. | C94: 0.33 | D94: 0 | E94: 6 | F94: 8 | H94: 0 | I94: 0 | J94: 0 | K94: 0 | L94: 0 | M94: 0 | N94: 0
A95: Entry and marriage fines with tithingpenny | B95: £1 from John de Spin' to have the said Joan le Swon with the land. | C95: 1 | D95: 1 | E95: 0 | F95: 0 | H95: 0 | I95: 0 | J95: 0 | K95: 0 | L95: 0 | M95: 0 | N95: 0
... A118: Cost of ploughs | B118: forage bought for oxen and other animals 10 shilling Total, £4 2 shilling 10pence | C118: 4.14 | D118: 4 | E118: 2 | F118: 10 | H118: 0 | I118: 0 | J118: 0 | K118: 0 | L118: 0 | M118: 0 | N118: 0
A119: Purchase of corn | B119: In 1 quarters 6 bushels of winter barley bought for sowing 5 shilling 3pence, at 3 shilling a quarters. | C119: 0.26 | D119: 0 | E119: 5 | F119: 3 | G119: barley | H119: 1 | I119: 6 | J119: 1.75 | K119: 1.75 | L119: 0 | M119: 1 | N119: 6 | W119: 3 | X119: 0
A120: Purchase of corn | B120: . | C120: 0 | D120: 0 | E120: 0 | F120: 0 | H120: 0 | I120: 0 | J120: 0 | K120: 0 | L120: 0 | M120: 0 | N120: 0
A121: Purchase of corn | B121: 15 quarters of barley bought for the liveries of the manorial servants £2 15 shilling, at 3 shilling a quarters for 5 quarters, and 4 shilling a quarters for 10 quarters. | C121: 2.75 | D121: 2 | E121: 15 | F121: 0 | G121: barley | H121: 15 | I121: 0 | J121: 15 | K121: 15 | L121: 0 | M121: 15 | N121: 0 | O121: 5 | P121: 0 | Q121: 10 | R121: 0 | W121: 3 | X121: 0 | Y121: 4 | Z121: 0
A122: Purchase of corn | B122: Total, £3 3pence | C122: 3.01 | D122: 3 | E122: 0 | F122: 3 | H122: 0 | I122: 0 | J122: 0 | K122: 0 | L122: 0 | M122: 0 | N122: 0
A123: Carts | B123: In 1 pair of wheels made from the lord's timber 9pence. | C123: 0.04 | D123: 0 | E123: 0 | F123: 9 | H123: 0 | I123: 0 | J123: 0 | K123: 0 | L123: 0 | M123: 0 | N123: 0
A124: Carts | B124: iron bought and large nails made and old tyres mended and put on the said wheels with the stipend of the smith 5 shilling. | C124: 0.25 | D124: 0 | E124: 5 | F124: 0 | H124: 0 | I124: 0 | J124: 0 | K124: 0 | L124: 0 | M124: 0 | N124: 0
A125: Carts | B125: fitting the cart with axles 6pence. | C125: 0.03 | D125: 0 | E125: 0 | F125: 6 | H125: 0 | I125: 0 | J125: 0 | K125: 0 | L125: 0 | M125: 0 | N125: 0
A126: Carts | B126: clouts, nails and grease bought 1 shilling 1pence. | C126: 0.05 | D126: 0 | E126: 1 | F126: 1 | H126: 0 | I126: 0 | J126: 0 | K126: 0 | L126: 0 | M126: 0 | N126: 0
A127: Carts | B127: white leather bought for harnesses 5pence. | C127: 0.02 | D127: 0 | E127: 0 | F127: 5 | H127: 0 | I127: 0 | J127: 0 | K127: 0 | L127: 0 | M127: 0 | N127: 0
A128: Carts | B128: shoeing 2 cart-horses 3 shilling. | C128: 0.15 | D128: 0 | E128: 3 | F128: 0 | H128: 0 | I128: 0 | J128: 0 | K128: 0 | L128: 0 | M128: 0 | N128: 0
A129: Carts | B129: shoeing 3 plough-horses helping the cart-horses at the time of the summer sowing to clear dung 10pence. | C129: 0.04 | D129: 0 | E129: 0 | F129: 10 | H129: 0 | I129: 0 | J129: 0 | K129: 0 | L129: 0 | M129: 0 | N129: 0
A130: Carts | B130: 4 halters made 1pence. | C130: 0 | D130: 0 | E130: 0 | F130: 1 | H130: 0 | I130: 0 | J130: 0 | K130: 0 | L130: 0 | M130: 0 | N130: 0
A131: Carts | B131: 1 collar and 1 pair of saddle-pads bought 1 shilling. | C131: 0.05 | D131: 0 | E131: 1 | F131: 0 | H131: 0 | I131: 0 | J131: 0 | K131: 0 | L131: 0 | M131: 0 | N131: 0
A132: Carts | B132: 2 ropes bought for tethering horses in the pasture 2pence. | C132: 0.01 | D132: 0 | E132: 0 | F132: 2 | H132: 0 | I132: 0 | J132: 0 | K132: 0 | L132: 0 | M132: 0 | N132: 0
A133: Carts | B133: stipend of 1 carter for the year 3 shilling Total, 14 shilling 10pence | C133: 0.19 | D133: 0 | E133: 3 | F133: 10 | H133: 0 | I133: 0 | J133: 0 | K133: 0 | L133: 0 | M133: 0 | N133: 0
... A156: Repair of buildings | B156: 1 rope bought for the louver in the hall 1.25pence Total, 6 shilling 8.5pence | C156: 0.31 | D156: 0 | E156: 6 | F156: 1.25 | H156: 0 | I156: 0 | J156: 0 | K156: 0 | L156: 0 | M156: 0 | N156: 0
A157: Threshing of corn | B157: In threshing and winnowing 60 quarters of wheat and curall by piece-work 11 shilling, at 2.25pence a quarters. | C157: 0.56 | D157: 0 | E157: 11 | F157: 2.25 | G157: curall, wheat | H157: 60 | I157: 0 | J157: 60 | K157: 60 | L157: 0 | M157: 60 | N157: 0
A158: Threshing of corn | B158: . | C158: 0 | D158: 0 | E158: 0 | F158: 0 | H158: 0 | I158: 0 | J158: 0 | K158: 0 | L158: 0 | M158: 0 | N158: 0
A159: Threshing of corn | B159: threshing and winnowing 7 quarters of winter barley and 20 quarters of barley by piece-work 3 shilling 4.5pence, at 1.5pence a heaped quarter. | C159: 0.17 | D159: 0 | E159: 3 | F159: 4.5 | G159: barley | H159: 20 | I159: 0 | J159: 20 | K159: 7 | L159: 13 | M159: 7 | N159: 0 | O159: 20 | P159: 0
A160: Threshing of corn | B160: Know that the workers threshed 36.5 quarters 2 bushels of wheat and curall, 16 quarters 1 bushels of barley, 86 quarters of oats, 2.25 quarters of peas and 2 quarters 1 bushels of vetches for their labour service. | C160: 0 | D160: 0 | E160: 0 | F160: 0 | G160: peas, wheat, curall, barley, oats, vetches | H160: 106.25 | I160: 2 | J160: 106.5 | K160: 36.75 | L160: 69.75 | M160: 36.5 | N160: 2 | O160: 16 | P160: 1 | Q160: 86 | R160: 0 | S160: 2.25 | T160: 0 | U160: 2 | V160: 1
A161: Threshing of corn | B161: . | C161: 0 | D161: 0 | E161: 0 | F161: 0 | H161: 0 | I161: 0 | J161: 0 | K161: 0 | L161: 0 | M161: 0 | N161: 0
A162: Threshing of corn | B162: weeding all the corn except that done by labour service 5 shilling 1.5pence. | C162: 0.26 | D162: 0 | E162: 5 | F162: 1.5 | H162: 0 | I162: 0 | J162: 0 | K162: 0 | L162: 0 | M162: 0 | N162: 0
A163: Threshing of corn | B163: wages of 1 attendant who keeps the barn and who threshed at various times 18 shilling 1pence Total, £1 17 shilling 7pence | C163: 1.88 | D163: 1 | E163: 17 | F163: 7 | H163: 0 | I163: 0 | J163: 0 | K163: 0 | L163: 0 | M163: 0 | N163: 0
A164: Harvest-time | B164: In bread bought for 12.5 boon-works of 1,025 men, with the officials of the curia and 14 men of Ovington, who eat twice a day except this year, and 15 workers who are bound, at the choice of the lord, to reap with the boon-works and have food like the others, each reaping either' acre of wheat or barley or 1 acre of oats and having 1 sheaf as it falls, £2 2 shilling 8.5pence. | C164: 2.14 | D164: 2 | E164: 2 | F164: 8.5 | G164: barley, oats, wheat | H164: 0 | I164: 0 | J164: 0 | K164: 0 | L164: 0 | M164: 0 | N164: 0
A165: Harvest-time | B165: herrings and cheese bought for a want of herrings to eat with the bread 19 shilling 5pence, and each ought to have 4 herrings a day. | C165: 0.97 | D165: 0 | E165: 19 | F165: 5 | H165: 0 | I165: 0 | J165: 0 | K165: 0 | L165: 0 | M165: 0 | N165: 0
A166: Harvest-time | B166: They reaped 245 acres of barley and 210 acres of oats as they lie. | C166: 0 | D166: 0 | E166: 0 | F166: 0 | G166: barley, oats | H166: 0 | I166: 0 | J166: 0 | K166: 0 | L166: 0 | M166: 0 | N166: 0
A167: Harvest-time | B167: . | C167: 0 | D167: 0 | E167: 0 | F167: 0 | H167: 0 | I167: 0 | J167: 0 | K167: 0 | L167: 0 | M167: 0 | N167: 0
A168: Harvest-time | B168: stipend of 1 hayward for the year 6 shilling 8pence Total, £3 8 shilling 9.5pence | C168: 3.44 | D168: 3 | E168: 8 | F168: 9.5 | H168: 0 | I168: 0 | J168: 0 | K168: 0 | L168: 0 | M168: 0 | N168: 0
A169: Expenses of the mill | B169: In iron bought and bands made to hoop the beams 1 shilling. | C169: 0.05 | D169: 0 | E169: 1 | F169: 0 | H169: 0 | I169: 0 | J169: 0 | K169: 0 | L169: 0 | M169: 0 | N169: 0
A170: Expenses of the mill | B170: mending the spindle and bills 1 shilling 2pence Total, 2 shilling 2pence | C170: 0.06 | D170: 0 | E170: 1 | F170: 2 | H170: 0 | I170: 0 | J170: 0 | K170: 0 | L170: 0 | M170: 0 | N170: 0
A171: Expenses of the steward | B171: In expenses of Simon, clerk, holding the place of the steward far the 2 toums 6 shilling 9pence Total, 6 shilling 9pence | C171: 0.34 | D171: 0 | E171: 6 | F171: 9 | H171: 0 | I171: 0 | J171: 0 | K171: 0 | L171: 0 | M171: 0 | N171: 0
A172: Purchase of stock | B172: In 15 animals bought for pasturing £3 19 shilling 4.25pence Total, £3 19 shilling 4.5pence | C172: 3.97 | D172: 3 | E172: 19 | F172: 4.25 | H172: 0 | I172: 0 | J172: 0 | K172: 0 | L172: 0 | M172: 0 | N172: 0
A173: Total of all expenses | B173: Total of all expenses, £21 11 s. 6pence | C173: 21 | D173: 21 | E173: 0 | F173: 0 | H173: 0 | I173: 0 | J173: 0 | K173: 0 | L173: 0 | M173: 0 | N173: 0
A174: Total of all expenses | B174: And thus he owes, £70 4pence | C174: 70.02 | D174: 70 | E174: 0 | F174: 4 | H174: 0 | I174: 0 | J174: 0 | K174: 0 | L174: 0 | M174: 0 | N174: 0
A175: Allowances | B175: in 10 cows bought for the stock of the manor £3 14 shilling 4pence, at 7 shilling 6pence each for 6, and 7 shilling each for 4. Total, £3 14 shilling 4pence | C175: 3.72 | D175: 3 | E175: 14 | F175: 4 | H175: 0 | I175: 0 | J175: 0 | K175: 0 | L175: 0 | M175: 0 | N175: 0
A176: Cash deliveries | B176: Delivered to Sir Geoffrey, treasurer of Wolvesey, by 1 tally, £40 10 shilling 7.5pence | C176: 40.53 | D176: 40 | E176: 10 | F176: 7.5 | H176: 0 | I176: 0 | J176: 0 | K176: 0 | L176: 0 | M176: 0 | N176: 0
A177: Cash deliveries | B177: Total of all allowances and cash deliveries, £44 4 shilling 11.5pence | C177: 44.25 | D177: 44 | E177: 4 | F177: 11.5 | H177: 0 | I177: 0 | J177: 0 | K177: 0 | L177: 0 | M177: 0 | N177: 0
A178: And he owes clear | B178: And he owes clear, £25 15 shilling 4.5pence | C178: 25.77 | D178: 25 | E178: 15 | F178: 4.5 | H178: 0 | I178: 0 | J178: 0 | K178: 0 | L178: 0 | M178: 0 | N178: 0
A179: Wheat | B179: (yield: three-fold less 1 quarters 6 bushels) | C179: 0 | D179: 0 | E179: 0 | F179: 0 | H179: 1 | I179: 6 | J179: 1.75 | K179: 1.75 | L179: 0 | M179: 1 | N179: 6
A180: Wheat | B180: The same render account for 94 quarters of wheat from the whole issue of the grange in the granary without heaped measure. | C180: 0 | D180: 0 | E180: 0 | F180: 0 | G180: wheat | H180: 94 | I180: 0 | J180: 94 | K180: 94 | L180: 0 | M180: 94 | N180: 0
A181: Wheat | B181: Sown over 89 acres in the fields of Peregh' and la Slad', 33 quarters 3 bushels. | C181: 0 | D181: 0 | E181: 0 | F181: 0 | H181: 33 | I181: 3 | J181: 33.375 | K181: 33.375 | L181: 0 | M181: 33 | N181: 3
A182: Wheat | B182: that is, 3 bushels an acre. | C182: 0 | D182: 0 | E182: 0 | F182: 0 | H182: 0 | I182: 3 | J182: 0.375 | K182: 0.375 | L182: 0 | M182: 0 | N182: 3
A183: Wheat | B183: . | C183: 0 | D183: 0 | E183: 0 | F183: 0 | H183: 0 | I183: 0 | J183: 0 | K183: 0 | L183: 0 | M183: 0 | N183: 0
A184: Wheat | B184: provision of Simon, clerk, for 2 tourns, 4 bushels Sold, 60 quarters 1 bushels It balances. | C184: 0 | D184: 0 | E184: 0 | F184: 0 | H184: 60 | I184: 1 | J184: 60.125 | K184: 0.5 | L184: 59.625 | M184: 0 | N184: 4 | O184: 60 | P184: 1
A185: Curall | B185: The same render account for 3 quarters 2 bushels from the whole issue of curall from the grange in the granary without heaped measure. | C185: 0 | D185: 0 | E185: 0 | F185: 0 | G185: curall | H185: 3 | I185: 2 | J185: 3.25 | K185: 3.25 | L185: 0 | M185: 3 | N185: 2
A186: Curall | B186: Mixed with barley for the liveries of the manorial servants, 1 quarters 3 bushels Sold, 1 quarters 7 bushels Total, 3 quarters 2 bushels It balances. | C186: 0 | D186: 0 | E186: 0 | F186: 0 | G186: barley | H186: 4 | I186: 9 | J186: 5.125 | K186: 1.375 | L186: 3.75 | M186: 1 | N186: 3 | O186: 1 | P186: 7 | Q186: 3 | R186: 2
A187: Bere | B187: (yield: three-fold plus 5 bushels) | C187: 0 | D187: 0 | E187: 0 | F187: 0 | H187: 0 | I187: 5 | J187: 0.625 | K187: 0.625 | L187: 0 | M187: 0 | N187: 5
A188: Bere | B188: The same render account for 7 quarters of bere from the whole issue of the grange in the granary without heaped measure. | C188: 0 | D188: 0 | E188: 0 | F188: 0 | H188: 7 | I188: 0 | J188: 7 | K188: 7 | L188: 0 | M188: 7 | N188: 0
A189: Bere | B189: 1 quarters 6 bushels bought. | C189: 0 | D189: 0 | E189: 0 | F189: 0 | H189: 1 | I189: 6 | J189: 1.75 | K189: 1.75 | L189: 0 | M189: 1 | N189: 6
A190: Bere | B190: Total, 8 quarters 6 bushels | C190: 0 | D190: 0 | E190: 0 | F190: 0 | H190: 8 | I190: 6 | J190: 8.75 | K190: 8.75 | L190: 0 | M190: 8 | N190: 6
A191: Bere | B191: Sown in the field beside la Hull', 1 quarters 6 bushels Mixed with barley for the liveries of the manorial servants, 4 quarters. | C191: 0 | D191: 0 | E191: 0 | F191: 0 | G191: barley | H191: 4 | I191: 6 | J191: 4.75 | K191: 1.75 | L191: 3 | M191: 1 | N191: 6 | O191: 4 | P191: 0
A192: Bere | B192: Sold, 3 quarters. | C192: 0 | D192: 0 | E192: 0 | F192: 0 | H192: 3 | I192: 0 | J192: 3 | K192: 3 | L192: 0 | M192: 3 | N192: 0
A193: Bere | B193: It balances. | C193: 0 | D193: 0 | E193: 0 | F193: 0 | H193: 0 | I193: 0 | J193: 0 | K193: 0 | L193: 0 | M193: 0 | N193: 0
A194: Barley | B194: (yield: two-and-a-half-fold less 1 bushels) | C194: 0 | D194: 0 | E194: 0 | F194: 0 | H194: 0 | I194: 1 | J194: 0.125 | K194: 0.125 | L194: 0 | M194: 0 | N194: 1
A195: Barley | B195: The same render account for 36 quarters 1 bushels from the whole issue of barley from the grange in the granary without heaped measure. | C195: 0 | D195: 0 | E195: 0 | F195: 0 | G195: barley | H195: 36 | I195: 1 | J195: 36.125 | K195: 36.125 | L195: 0 | M195: 36 | N195: 1
A196: Barley | B196: 4 quarters of winter barley received for the liveries of the manorial servants. | C196: 0 | D196: 0 | E196: 0 | F196: 0 | G196: barley | H196: 4 | I196: 0 | J196: 4 | K196: 4 | L196: 0 | M196: 4 | N196: 0
A197: Barley | B197: 1 quarters 3 bushels of curall received for the same. | C197: 0 | D197: 0 | E197: 0 | F197: 0 | G197: curall | H197: 1 | I197: 3 | J197: 1.375 | K197: 1.375 | L197: 0 | M197: 1 | N197: 3
A198: Barley | B198: 7 bushels of peas received for the same. | C198: 0 | D198: 0 | E198: 0 | F198: 0 | G198: peas | H198: 0 | I198: 7 | J198: 0.875 | K198: 0.875 | L198: 0 | M198: 0 | N198: 7
A199: Barley | B199: 15 quarters bought. | C199: 0 | D199: 0 | E199: 0 | F199: 0 | H199: 15 | I199: 0 | J199: 15 | K199: 15 | L199: 0 | M199: 15 | N199: 0
A200: Barley | B200: Total, 57 quarters 3 bushels | C200: 0 | D200: 0 | E200: 0 | F200: 0 | H200: 57 | I200: 3 | J200: 57.375 | K200: 57.375 | L200: 0 | M200: 57 | N200: 3
A201: Barley | B201: Sown over 33.5 acres measured by the perch in the fields of la Hull' and Buttehegg', 16.5 quarters 2 bushels. | C201: 0 | D201: 0 | E201: 0 | F201: 0 | H201: 16.5 | I201: 2 | J201: 16.75 | K201: 16.75 | L201: 0 | M201: 16.5 | N201: 2
...

Sheet Issues of the Grange raw
A1: Heading | B1: Sentence | C1: Quarters 1_x | D1: Bushels 1_x | E1: Sown Quarters | F1: Sown Bushels | G1: Sown Total Quarters | H1: Bought in Quarters | I1: Bought in Bushels | J1: Bought in Total Quarters | K1: Tithe Quarters | L1: Tithe Bushels | M1: Tithe Total Quarters | N1: Manorial servants & livestock Quarters | O1: Manorial servants & livestock Bushels | P1: Manorial servants & livestock Total Quarters | Q1: Sold Quarters | R1: Sold Bushels | S1: Sold Total Quarters | T1: Account Quarters | U1: Account Bushels | V1: Account Total Quarters | W1: bought only | X1: Total Quarters Except 1 | Y1: Total Bushels Except 1 | Z1: Total Corn Cross-Check | AA1: Total Corn Manorial Account | AB1: Corn Quantity Error | AC1: Quarters 1_y | AD1: Bushels 1_y | AE1: Quarters 2 | AF1: Bushels 2 | AG1: Quarters 3 | AH1: Bushels 3 | AI1: Quarters 4 | AJ1: Bushels 4 | AK1: Quarters 5 | AL1: Bushels 5
A2: Cash deliveries | B2: Total | C2: 0 | D2: 0 | E2: 0 | F2: 0 | G2: 0 | H2: 0 | I2: 0 | J2: 0 | K2: 0 | L2: 0 | M2: 0 | N2: 0 | O2: 0 | P2: 0 | Q2: 0 | R2: 0 | S2: 0 | T2: 0 | U2: 0 | V2: 0 | W2: 0
A3: Wheat | B3: (yield: three-fold less 1 qr 6 bushels) | C3: 0 | D3: 0 | E3: 0 | F3: 0 | G3: 0 | H3: 0 | I3: 0 | J3: 0 | K3: 0 | L3: 0 | M3: 0 | N3: 0 | O3: 0 | P3: 0 | Q3: 0 | R3: 0 | S3: 0 | T3: 0 | U3: 0 | V3: 0 | W3: 0
A4: Wheat | B4: The same render account for 94 quarters of wheat from the whole issue of the grange in the granary without heaped measure. | C4: 0 | D4: 0 | E4: 0 | F4: 0 | G4: 0 | H4: 0 | I4: 0 | J4: 0 | K4: 0 | L4: 0 | M4: 0 | N4: 0 | O4: 0 | P4: 0 | Q4: 0 | R4: 0 | S4: 0 | T4: 94 | U4: 0 | V4: 94 | W4: 0 | X4: 94 | Y4: 0 | Z4: 94 | AA4: 94 | AB4: 0 | AC4: 94 | AD4: 0
A5: Wheat | B5: Sown over 89 acres in the fields of Peregh' and la Slad', 33 quarters 3 bushels. | C5: 0 | D5: 0 | E5: 33 | F5: 3 | G5: 33.375 | H5: 0 | I5: 0 | J5: 0 | K5: 0 | L5: 0 | M5: 0 | N5: 0 | O5: 0 | P5: 0 | Q5: 0 | R5: 0 | S5: 0 | T5: 0 | U5: 0 | V5: 0 | W5: 0 | X5: 33 | Y5: 3 | Z5: 33.375 | AA5: 33.375 | AB5: 0 | AC5: 33 | AD5: 3
A6: Wheat | B6: that is, 3 bushels an acre. | C6: 0 | D6: 0 | E6: 0 | F6: 0 | G6: 0 | H6: 0 | I6: 0 | J6: 0 | K6: 0 | L6: 0 | M6: 0 | N6: 0 | O6: 0 | P6: 0 | Q6: 0 | R6: 0 | S6: 0 | T6: 0 | U6: 0 | V6: 0 | W6: 0 | X6: 0 | Y6: 3 | Z6: 0.375 | AA6: 0.375 | AB6: 0 | AC6: 0 | AD6: 3
A7: Wheat | B7: . | C7: 0 | D7: 0 | E7: 0 | F7: 0 | G7: 0 | H7: 0 | I7: 0 | J7: 0 | K7: 0 | L7: 0 | M7: 0 | N7: 0 | O7: 0 | P7: 0 | Q7: 0 | R7: 0 | S7: 0 | T7: 0 | U7: 0 | V7: 0 | W7: 0 | X7: 0 | Y7: 0 | Z7: 0 | AA7: 0 | AB7: 0 | AC7: 0 | AD7: 0
A8: Wheat | B8: provision of Simon, clerk, for 2 tourns, 4 bushels Sold, 60 quarters 1 bushels It balances. | C8: 0 | D8: 0 | E8: 0 | F8: 0 | G8: 0 | H8: 0 | I8: 0 | J8: 0 | K8: 0 | L8: 0 | M8: 0 | N8: 0 | O8: 0 | P8: 0 | Q8: 60 | R8: 1 | S8: 60.125 | T8: 0 | U8: 0 | V8: 0 | W8: 0 | X8: 60 | Y8: 1 | Z8: 60.125 | AA8: 0.5 | AB8: 59.625 | AC8: 0 | AD8: 4 | AE8: 60 | AF8: 1
A9: Wheat | B9: Total | C9: 0 | D9: 0 | E9: 0 | F9: 0 | G9: 0 | H9: 0 | I9: 0 | J9: 0 | K9: 0 | L9: 0 | M9: 0 | N9: 0 | O9: 0 | P9: 0 | Q9: 0 | R9: 0 | S9: 0 | T9: 0 | U9: 0 | V9: 0 | W9: 0
A10: Curall | B10: The same render account for 3 quarters 2 bushels from the whole issue of curall from the grange in the granary without heaped measure. | C10: 0 | D10: 0 | E10: 0 | F10: 0 | G10: 0 | H10: 0 | I10: 0 | J10: 0 | K10: 0 | L10: 0 | M10: 0 | N10: 0 | O10: 0 | P10: 0 | Q10: 0 | R10: 0 | S10: 0 | T10: 3 | U10: 2 | V10: 3.25 | W10: 0 | X10: 3 | Y10: 2 | Z10: 3.25 | AA10: 3.25 | AB10: 0 | AC10: 3 | AD10: 2
A11: Curall | B11: Mixed with barley for the liveries of the manorial servants, 1 qr 3 bushels Sold, 1 qr 7 bushels Total, 3 quarters 2 bushels It balances. | C11: 0 | D11: 0 | E11: 0 | F11: 0 | G11: 0 | H11: 0 | I11: 0 | J11: 0 | K11: 0 | L11: 0 | M11: 0 | N11: 3 | O11: 2 | P11: 3.25 | Q11: 3 | R11: 2 | S11: 3.25 | T11: 0 | U11: 0 | V11: 0 | W11: 0
A12: Curall | B12: Total | C12: 0 | D12: 0 | E12: 0 | F12: 0 | G12: 0 | H12: 0 | I12: 0 | J12: 0 | K12: 0 | L12: 0 | M12: 0 | N12: 0 | O12: 0 | P12: 0 | Q12: 0 | R12: 0 | S12: 0 | T12: 0 | U12: 0 | V12: 0 | W12: 0
A13: Barley | B13: (yield: two-and-a-half-fold less 1 bushels) | C13: 0 | D13: 0 | E13: 0 | F13: 0 | G13: 0 | H13: 0 | I13: 0 | J13: 0 | K13: 0 | L13: 0 | M13: 0 | N13: 0 | O13: 0 | P13: 0 | Q13: 0 | R13: 0 | S13: 0 | T13: 0 | U13: 0 | V13: 0 | W13: 0 | X13: 0 | Y13: 1 | Z13: 0.125 | AA13: 0.125 | AB13: 0 | AC13: 0 | AD13: 1
A14: Barley | B14: The same render account for 36 quarters 1 bushels from the whole issue of barley from the grange in the granary without heaped measure. | C14: 0 | D14: 0 | E14: 0 | F14: 0 | G14: 0 | H14: 0 | I14: 0 | J14: 0 | K14: 0 | L14: 0 | M14: 0 | N14: 0 | O14: 0 | P14: 0 | Q14: 0 | R14: 0 | S14: 0 | T14: 36 | U14: 1 | V14: 36.125 | W14: 0 | X14: 36 | Y14: 1 | Z14: 36.125 | AA14: 36.125 | AB14: 0 | AC14: 36 | AD14: 1
A15: Barley | B15: 4 quarters of winter barley received for the liveries of the manorial servants. | C15: 0 | D15: 0 | E15: 0 | F15: 0 | G15: 0 | H15: 0 | I15: 0 | J15: 0 | K15: 0 | L15: 0 | M15: 0 | N15: 4 | O15: 0 | P15: 4 | Q15: 0 | R15: 0 | S15: 0 | T15: 0 | U15: 0 | V15: 0 | W15: 0 | X15: 4 | Y15: 0 | Z15: 4 | AA15: 4 | AB15: 0 | AC15: 4 | AD15: 0
A16: Barley | B16: 1 qr 3 bushels of curall received for the same. | C16: 0 | D16: 0 | E16: 0 | F16: 0 | G16: 0 | H16: 0 | I16: 0 | J16: 0 | K16: 0 | L16: 0 | M16: 0 | N16: 0 | O16: 0 | P16: 0 | Q16: 0 | R16: 0 | S16: 0 | T16: 0 | U16: 0 | V16: 0 | W16: 0
A17: Barley | B17: 7 bushels of peas received for the same. | C17: 0 | D17: 0 | E17: 0 | F17: 0 | G17: 0 | H17: 0 | I17: 0 | J17: 0 | K17: 0 | L17: 0 | M17: 0 | N17: 0 | O17: 0 | P17: 0 | Q17: 0 | R17: 0 | S17: 0 | T17: 0 | U17: 0 | V17: 0 | W17: 0 | X17: 0 | Y17: 7 | Z17: 0.875 | AA17: 0.875 | AB17: 0 | AC17: 0 | AD17: 7
A18: Barley | B18: 15 quarters bought. | C18: 0 | D18: 0 | E18: 0 | F18: 0 | G18: 0 | H18: 15 | I18: 0 | J18: 15 | K18: 0 | L18: 0 | M18: 0 | N18: 0 | O18: 0 | P18: 0 | Q18: 0 | R18: 0 | S18: 0 | T18: 0 | U18: 0 | V18: 0 | W18: 0 | X18: 15 | Y18: 0 | Z18: 15 | AA18: 15 | AB18: 0 | AC18: 15 | AD18: 0
A19: Barley | B19: Total, 57 quarters 3 bushels | C19: 0 | D19: 0 | E19: 0 | F19: 0 | G19: 0 | H19: 0 | I19: 0 | J19: 0 | K19: 0 | L19: 0 | M19: 0 | N19: 0 | O19: 0 | P19: 0 | Q19: 0 | R19: 0 | S19: 0 | T19: 0 | U19: 0 | V19: 0 | W19: 0 | X19: 57 | Y19: 3 | Z19: 57.375 | AA19: 57.375 | AB19: 0 | AC19: 57 | AD19: 3
A20: Barley | B20: Sown over 33.5 acres measured by the perch in the fields of la Hull' and Buttehegg', 16.5 quarters 2 bushels. | C20: 0 | D20: 0 | E20: 16.5 | F20: 2 | G20: 16.75 | H20: 0 | I20: 0 | J20: 0 | K20: 0 | L20: 0 | M20: 0 | N20: 0 | O20: 0 | P20: 0 | Q20: 0 | R20: 0 | S20: 0 | T20: 0 | U20: 0 | V20: 0 | W20: 0 | X20: 16.5 | Y20: 2 | Z20: 16.75 | AA20: 16.75 | AB20: 0 | AC20: 16.5 | AD20: 2
A21: Barley | B21: that is, 0.5 qr an acre. | C21: 0 | D21: 0 | E21: 0 | F21: 0 | G21: 0 | H21: 0 | I21: 0 | J21: 0 | K21: 0 | L21: 0 | M21: 0 | N21: 0 | O21: 0 | P21: 0 | Q21: 0 | R21: 0 | S21: 0 | T21: 0 | U21: 0 | V21: 0 | W21: 0
A22: Barley | B22: Delivered to the hayward and carter for the year, 13 quarters, taking a quarter every 8 weeks. | C22: 0 | D22: 0 | E22: 0 | F22: 0 | G22: 0 | H22: 0 | I22: 0 | J22: 0 | K22: 0 | L22: 0 | M22: 0 | N22: 0 | O22: 0 | P22: 0 | Q22: 0 | R22: 0 | S22: 0 | T22: 0 | U22: 0 | V22: 0 | W22: 0 | X22: 13 | Y22: 0 | Z22: 13 | AA22: 13 | AB22: 0 | AC22: 13 | AD22: 0
A23: Barley | B23: Delivered to 1 harrower, 4 bushels Delivered to 1 dairymaid from the Purification until Michaelmas, 2 quarters 2 bushels. | C23: 0 | D23: 0 | E23: 0 | F23: 0 | G23: 0 | H23: 0 | I23: 0 | J23: 0 | K23: 0 | L23: 0 | M23: 0 | N23: 0 | O23: 0 | P23: 0 | Q23: 0 | R23: 0 | S23: 0 | T23: 0 | U23: 0 | V23: 0 | W23: 0 | X23: 2 | Y23: 2 | Z23: 2.25 | AA23: 0.5 | AB23: 1.75 | AC23: 0 | AD23: 4 | AE23: 2 | AF23: 2
A24: Barley | B24: customary payment to 1 keeper of ewes, 6 bushels. | C24: 0 | D24: 0 | E24: 0 | F24: 0 | G24: 0 | H24: 0 | I24: 0 | J24: 0 | K24: 0 | L24: 0 | M24: 0 | N24: 0 | O24: 0 | P24: 0 | Q24: 0 | R24: 0 | S24: 0 | T24: 0 | U24: 0 | V24: 0 | W24: 0 | X24: 0 | Y24: 6 | Z24: 0.75 | AA24: 0.75 | AB24: 0 | AC24: 0 | AD24: 6
A25: Barley | B25: customary payment to 1 keeper of lambs this year, 6 bushels. | C25: 0 | D25: 0 | E25: 0 | F25: 0 | G25: 0 | H25: 0 | I25: 0 | J25: 0 | K25: 0 | L25: 0 | M25: 0 | N25: 0 | O25: 0 | P25: 0 | Q25: 0 | R25: 0 | S25: 0 | T25: 0 | U25: 0 | V25: 0 | W25: 0 | X25: 0 | Y25: 6 | Z25: 0.75 | AA25: 0.75 | AB25: 0 | AC25: 0 | AD25: 6
A26: Barley | B26: customary payment to 1 swineherd this year because he was not outside the manor during mast, 6 bushels. | C26: 0 | D26: 0 | E26: 0 | F26: 0 | G26: 0 | H26: 0 | I26: 0 | J26: 0 | K26: 0 | L26: 0 | M26: 0 | N26: 0 | O26: 0 | P26: 0 | Q26: 0 | R26: 0 | S26: 0 | T26: 0 | U26: 0 | V26: 0 | W26: 0 | X26: 0 | Y26: 6 | Z26: 0.75 | AA26: 0.75 | AB26: 0 | AC26: 0 | AD26: 6
A27: Barley | B27: supporting pigs and piglets, 1.5 quarters. | C27: 0 | D27: 0 | E27: 0 | F27: 0 | G27: 0 | H27: 0 | I27: 0 | J27: 0 | K27: 0 | L27: 0 | M27: 0 | N27: 0 | O27: 0 | P27: 0 | Q27: 0 | R27: 0 | S27: 0 | T27: 0 | U27: 0 | V27: 0 | W27: 0 | X27: 1.5 | Y27: 0 | Z27: 1.5 | AA27: 1.5 | AB27: 0 | AC27: 1.5 | AD27: 0
A28: Barley | B28: Delivered to 1cowherd from the feast of St Vincent the Martyr (22 January) until Michaelmas (29 September), for 36 weeks, 3 quarters. | C28: 0 | D28: 0 | E28: 0 | F28: 0 | G28: 0 | H28: 0 | I28: 0 | J28: 0 | K28: 0 | L28: 0 | M28: 0 | N28: 0 | O28: 0 | P28: 0 | Q28: 0 | R28: 0 | S28: 0 | T28: 0 | U28: 0 | V28: 0 | W28: 0 | X28: 3 | Y28: 0 | Z28: 3 | AA28: 3 | AB28: 0 | AC28: 3 | AD28: 0
A29: Barley | B29: Sold, 16 quarters 2 bushels | C29: 0 | D29: 0 | E29: 0 | F29: 0 | G29: 0 | H29: 0 | I29: 0 | J29: 0 | K29: 0 | L29: 0 | M29: 0 | N29: 0 | O29: 0 | P29: 0 | Q29: 16 | R29: 2 | S29: 16.25 | T29: 0 | U29: 0 | V29: 0 | W29: 0 | X29: 16 | Y29: 2 | Z29: 16.25 | AA29: 16.25 | AB29: 0 | AC29: 16 | AD29: 2
A30: Barley | B30: Total | C30: 0 | D30: 0 | E30: 0 | F30: 0 | G30: 0 | H30: 0 | I30: 0 | J30: 0 | K30: 0 | L30: 0 | M30: 0 | N30: 0 | O30: 0 | P30: 0 | Q30: 0 | R30: 0 | S30: 0 | T30: 0 | U30: 0 | V30: 0 | W30: 0
A31: Oats | B31: (yield: two-fold less 2 quarters} | C31: 0 | D31: 0 | E31: 0 | F31: 0 | G31: 0 | H31: 0 | I31: 0 | J31: 0 | K31: 0 | L31: 0 | M31: 0 | N31: 0 | O31: 0 | P31: 0 | Q31: 0 | R31: 0 | S31: 0 | T31: 0 | U31: 0 | V31: 0 | W31: 0 | X31: 2 | Y31: 0 | Z31: 2 | AA31: 2 | AB31: 0 | AC31: 2 | AD31: 0
A32: Oats | B32: The same render account for 116 quarters 2 bushels from the whole issue of oats from the grange in the granary without heaped measure. | C32: 0 | D32: 0 | E32: 0 | F32: 0 | G32: 0 | H32: 0 | I32: 0 | J32: 0 | K32: 0 | L32: 0 | M32: 0 | N32: 0 | O32: 0 | P32: 0 | Q32: 0 | R32: 0 | S32: 0 | T32: 116 | U32: 2 | V32: 116.25 | W32: 0 | X32: 116 | Y32: 2 | Z32: 116.25 | AA32: 116.25 | AB32: 0 | AC32: 116 | AD32: 2
A33: Oats | B33: 22 quarters by estimation in sheaves given to oxen. | C33: 0 | D33: 0 | E33: 0 | F33: 0 | G33: 0 | H33: 0 | I33: 0 | J33: 0 | K33: 0 | L33: 0 | M33: 0 | N33: 0 | O33: 0 | P33: 0 | Q33: 0 | R33: 0 | S33: 0 | T33: 0 | U33: 0 | V33: 0 | W33: 0 | X33: 22 | Y33: 0 | Z33: 22 | AA33: 22 | AB33: 0 | AC33: 22 | AD33: 0
A34: Oats | B34: Total 138 quarters 2 bushels | C34: 0 | D34: 0 | E34: 0 | F34: 0 | G34: 0 | H34: 0 | I34: 0 | J34: 0 | K34: 0 | L34: 0 | M34: 0 | N34: 0 | O34: 0 | P34: 0 | Q34: 0 | R34: 0 | S34: 0 | T34: 0 | U34: 0 | V34: 0 | W34: 0 | X34: 138 | Y34: 2 | Z34: 138.25 | AA34: 138.25 | AB34: 0 | AC34: 138 | AD34: 2
A35: Oats | B35: Sown over 85.5 acres which lie in the fields of la Hull' and la Rud', 64 quarters. | C35: 0 | D35: 0 | E35: 64 | F35: 0 | G35: 64 | H35: 0 | I35: 0 | J35: 0 | K35: 0 | L35: 0 | M35: 0 | N35: 0 | O35: 0 | P35: 0 | Q35: 0 | R35: 0 | S35: 0 | T35: 0 | U35: 0 | V35: 0 | W35: 0 | X35: 64 | Y35: 0 | Z35: 64 | AA35: 64 | AB35: 0 | AC35: 64 | AD35: 0
A36: Oats | B36: that is, 6 bushels an acre, less 1 bushels in all. | C36: 0 | D36: 0 | E36: 0 | F36: 0 | G36: 0 | H36: 0 | I36: 0 | J36: 0 | K36: 0 | L36: 0 | M36: 0 | N36: 0 | O36: 0 | P36: 0 | Q36: 0 | R36: 0 | S36: 0 | T36: 0 | U36: 0 | V36: 0 | W36: 0 | X36: 0 | Y36: 1 | Z36: 0.125 | AA36: 0.75 | AB36: -0.625 | AC36: 0 | AD36: 6 | AE36: 0 | AF36: 1
A37: Oats | B37: . | C37: 0 | D37: 0 | E37: 0 | F37: 0 | G37: 0 | H37: 0 | I37: 0 | J37: 0 | K37: 0 | L37: 0 | M37: 0 | N37: 0 | O37: 0 | P37: 0 | Q37: 0 | R37: 0 | S37: 0 | T37: 0 | U37: 0 | V37: 0 | W37: 0 | X37: 0 | Y37: 0 | Z37: 0 | AA37: 0 | AB37: 0 | AC37: 0 | AD37: 0
A38: Oats | B38: . | C38: 0 | D38: 0 | E38: 0 | F38: 0 | G38: 0 | H38: 0 | I38: 0 | J38: 0 | K38: 0 | L38: 0 | M38: 0 | N38: 0 | O38: 0 | P38: 0 | Q38: 0 | R38: 0 | S38: 0 | T38: 0 | U38: 0 | V38: 0 | W38: 0 | X38: 0 | Y38: 0 | Z38: 0 | AA38: 0 | AB38: 0 | AC38: 0 | AD38: 0
A39: Oats | B39: fodder of 2 cart-horses and 8 plough-horses helping them at the horse-ploughs at the time of the summer sowing because they ploughed before and after dinner and carried dung when they were not at the ploughs, 9 quarters 6 bushels. | C39: 0 | D39: 0 | E39: 0 | F39: 0 | G39: 0 | H39: 0 | I39: 0 | J39: 0 | K39: 0 | L39: 0 | M39: 0 | N39: 9 | O39: 6 | P39: 9.75 | Q39: 0 | R39: 0 | S39: 0 | T39: 0 | U39: 0 | V39: 0 | W39: 0 | X39: 9 | Y39: 6 | Z39: 9.75 | AA39: 9.75 | AB39: 0 | AC39: 9 | AD39: 6
A40: Oats | B40: fodder of oxen by estimation in sheaves, 22 quarters. | C40: 0 | D40: 0 | E40: 0 | F40: 0 | G40: 0 | H40: 0 | I40: 0 | J40: 0 | K40: 0 | L40: 0 | M40: 0 | N40: 22 | O40: 0 | P40: 22 | Q40: 0 | R40: 0 | S40: 0 | T40: 0 | U40: 0 | V40: 0 | W40: 0 | X40: 22 | Y40: 0 | Z40: 22 | AA40: 22 | AB40: 0 | AC40: 22 | AD40: 0
A41: Oats | B41: . | C41: 0 | D41: 0 | E41: 0 | F41: 0 | G41: 0 | H41: 0 | I41: 0 | J41: 0 | K41: 0 | L41: 0 | M41: 0 | N41: 0 | O41: 0 | P41: 0 | Q41: 0 | R41: 0 | S41: 0 | T41: 0 | U41: 0 | V41: 0 | W41: 0 | X41: 0 | Y41: 0 | Z41: 0 | AA41: 0 | AB41: 0 | AC41: 0 | AD41: 0
A42: Oats | B42: . | C42: 0 | D42: 0 | E42: 0 | F42: 0 | G42: 0 | H42: 0 | I42: 0 | J42: 0 | K42: 0 | L42: 0 | M42: 0 | N42: 0 | O42: 0 | P42: 0 | Q42: 0 | R42: 0 | S42: 0 | T42: 0 | U42: 0 | V42: 0 | W42: 0 | X42: 0 | Y42: 0 | Z42: 0 | AA42: 0 | AB42: 0 | AC42: 0 | AD42: 0
A43: Oats | B43: fodder of the horses of Simon, clerk, 2 bushels Sold, 32 quarters. | C43: 0 | D43: 0 | E43: 0 | F43: 0 | G43: 0 | H43: 0 | I43: 0 | J43: 0 | K43: 0 | L43: 0 | M43: 0 | N43: 32 | O43: 0 | P43: 32 | Q43: 32 | R43: 0 | S43: 32 | T43: 0 | U43: 0 | V43: 0 | W43: 0 | X43: 32 | Y43: 2 | Z43: 32.25 | AA43: 0.25 | AB43: 32 | AC43: 0 | AD43: 2 | AE43: 32 | AF43: 0
A44: Oats | B44: Sold at the audit, 6 quarters 2 bushels | C44: 0 | D44: 0 | E44: 0 | F44: 0 | G44: 0 | H44: 0 | I44: 0 | J44: 0 | K44: 0 | L44: 0 | M44: 0 | N44: 0 | O44: 0 | P44: 0 | Q44: 6 | R44: 2 | S44: 6.25 | T44: 0 | U44: 0 | V44: 0 | W44: 0 | X44: 6 | Y44: 2 | Z44: 6.25 | AA44: 6.25 | AB44: 0 | AC44: 6 | AD44: 2
A45: Oats | B45: Total | C45: 0 | D45: 0 | E45: 0 | F45: 0 | G45: 0 | H45: 0 | I45: 0 | J45: 0 | K45: 0 | L45: 0 | M45: 0 | N45: 0 | O45: 0 | P45: 0 | Q45: 0 | R45: 0 | S45: 0 | T45: 0 | U45: 0 | V45: 0 | W45: 0
A46: Peas | B46: (yield: two-fold plus 2 bushels) | C46: 0 | D46: 0 | E46: 0 | F46: 0 | G46: 0 | H46: 0 | I46: 0 | J46: 0 | K46: 0 | L46: 0 | M46: 0 | N46: 0 | O46: 0 | P46: 0 | Q46: 0 | R46: 0 | S46: 0 | T46: 0 | U46: 0 | V46: 0 | W46: 0 | X46: 0 | Y46: 2 | Z46: 0.25 | AA46: 0.25 | AB46: 0 | AC46: 0 | AD46: 2
A47: Peas | B47: The same render account for 2.5 quarters from the whole issue of peas without heaped measure. | C47: 0 | D47: 0 | E47: 0 | F47: 0 | G47: 0 | H47: 0 | I47: 0 | J47: 0 | K47: 0 | L47: 0 | M47: 0 | N47: 0 | O47: 0 | P47: 0 | Q47: 0 | R47: 0 | S47: 0 | T47: 2.5 | U47: 0 | V47: 2.5 | W47: 0 | X47: 2.5 | Y47: 0 | Z47: 2.5 | AA47: 2.5 | AB47: 0 | AC47: 2.5 | AD47: 0
A48: Peas | B48: Sown, 5 bushels Mixed with barley for the liveries of the manorial servants, 7 bushels. | C48: 0 | D48: 0 | E48: 0 | F48: 0 | G48: 0 | H48: 0 | I48: 0 | J48: 0 | K48: 0 | L48: 0 | M48: 0 | N48: 0 | O48: 0 | P48: 0 | Q48: 0 | R48: 0 | S48: 0 | T48: 0 | U48: 0 | V48: 0 | W48: 0 | X48: 0 | Y48: 7 | Z48: 0.875 | AA48: 0.625 | AB48: 0.25 | AC48: 0 | AD48: 5 | AE48: 0 | AF48: 7
A49: Peas | B49: supporting pigs, 5 bushels Sold, 3 bushels | C49: 0 | D49: 0 | E49: 0 | F49: 0 | G49: 0 | H49: 0 | I49: 0 | J49: 0 | K49: 0 | L49: 0 | M49: 0 | N49: 0 | O49: 0 | P49: 0 | Q49: 0 | R49: 0 | S49: 0 | T49: 0 | U49: 0 | V49: 0 | W49: 0 | X49: 0 | Y49: 3 | Z49: 0.375 | AA49: 0.625 | AB49: -0.25 | AC49: 0 | AD49: 5 | AE49: 0 | AF49: 3
A50: Peas | B50: Total | C50: 0 | D50: 0 | E50: 0 | F50: 0 | G50: 0 | H50: 0 | I50: 0 | J50: 0 | K50: 0 | L50: 0 | M50: 0 | N50: 0 | O50: 0 | P50: 0 | Q50: 0 | R50: 0 | S50: 0 | T50: 0 | U50: 0 | V50: 0 | W50: 0
A51: Vetches | B51: (yield: two-fold plus 1 bushels) | C51: 0 | D51: 0 | E51: 0 | F51: 0 | G51: 0 | H51: 0 | I51: 0 | J51: 0 | K51: 0 | L51: 0 | M51: 0 | N51: 0 | O51: 0 | P51: 0 | Q51: 0 | R51: 0 | S51: 0 | T51: 0 | U51: 0 | V51: 0 | W51: 0 | X51: 0 | Y51: 1 | Z51: 0.125 | AA51: 0.125 | AB51: 0 | AC51: 0 | AD51: 1
A52: Vetches | B52: The same render account for 2 quarters 1 bushels from the whole issue of vetches. | C52: 0 | D52: 0 | E52: 0 | F52: 0 | G52: 0 | H52: 0 | I52: 0 | J52: 0 | K52: 0 | L52: 0 | M52: 0 | N52: 0 | O52: 0 | P52: 0 | Q52: 0 | R52: 0 | S52: 0 | T52: 2 | U52: 1 | V52: 2.125 | W52: 0 | X52: 2 | Y52: 1 | Z52: 2.125 | AA52: 2.125 | AB52: 0 | AC52: 2 | AD52: 1
A53: Vetches | B53: Sown, 1.5 quarters. | C53: 0 | D53: 0 | E53: 1.5 | F53: 0 | G53: 1.5 | H53: 0 | I53: 0 | J53: 0 | K53: 0 | L53: 0 | M53: 0 | N53: 0 | O53: 0 | P53: 0 | Q53: 0 | R53: 0 | S53: 0 | T53: 0 | U53: 0 | V53: 0 | W53: 0 | X53: 1.5 | Y53: 0 | Z53: 1.5 | AA53: 1.5 | AB53: 0 | AC53: 1.5 | AD53: 0
A54: Vetches | B54: Sold, 5 bushels | C54: 0 | D54: 0 | E54: 0 | F54: 0 | G54: 0 | H54: 0 | I54: 0 | J54: 0 | K54: 0 | L54: 0 | M54: 0 | N54: 0 | O54: 0 | P54: 0 | Q54: 0 | R54: 0 | S54: 0 | T54: 0 | U54: 0 | V54: 0 | W54: 0 | X54: 0 | Y54: 5 | Z54: 0.625 | AA54: 0.625 | AB54: 0 | AC54: 0 | AD54: 5

Sheet Sale of Corn Prices
A1: Heading | B1: Sentence | C1: Total in Pounds | D1: Pounds | E1: Shillings | F1: Pence | G1: Corn | H1: Total Quarters Except 1 | I1: Total Bushels Except 1 | J1: Total Corn Cross-Check | K1: Total Corn Manorial Account | L1: Corn Quantity Error | M1: Quarters 0 | N1: Bushels 0 | O1: shilling a quarter 1 | P1: pence a quarter 1 | Q1: Quarters 1 | R1: Bushels 1 | S1: shilling a quarter 2 | T1: pence a quarter 2 | U1: Quarters 2 | V1: Bushels 2 | W1: shilling a quarter 3 | X1: pence a quarter 3 | Y1: Quarters 3 | Z1: Bushels 3 | AA1: shilling a quarter 4 | AB1: pence a quarter 4 | AC1: Quarters 4 | AD1: Bushels 4 | AE1: £ a quarter 1 | AF1: £ a quarter 2 | AG1: £ a quarter 3 | AH1: £ a quarter 4 | AI1: Quarters Sold | AJ1: Weighted Average Price per Quarter | AK1: Non-Weighted Average Price per Quarter | AL1: Corn lowercase
