Workbook

Sheet Crawley 1301 Overview - Completed
A1: CRAWLEY 1301 OVERVIEW - COMPLETED | B1: Total in £ | C1: Error | D1: Note
A2: CASH ACCOUNT
A3: RECEIPTS
A4: Arrears total | B4: 7.4333333
A5: Rents of assize total | B5: 14.079167
A6: Quittances total | B6: 2.7833333
A7: Defaults of rent total | B7: 1.0166667
A8: Defaults of rent through the pestilence total
A9: Cotlands defaults total
A10: Cotlands total
A11: Total of quittances and defaults of rent total
A12: Total of rents remaining clear total
A13: Farms total
A14: Annual recognizances total | B14: 0.0875
A15: Issues of the Manor total | B15: 19.945833
A16: Issues of the tenements in the lord's hands total
A17: Sale of labour services total
A18: Sale of corn total | B18: 23.983333
A19: Entry and marriage fines total | B19: 0.86666667
A20: Pleas & perquisites total | B20: 0.99583333
A21: Forfeited chattels total
A22: Farm of the demesne land total
A23: Total of all receipts (calculated here) | B23: =SUM(B5:B22)
A24: Total of all receipts (calculated here) incl arrears | B24: =SUM(B4:B22)
A25: Total recorded in the accounts excl. arrears | C25: =B23-B25
A26: Total recorded in the accounts incl. arrears | B26: =B25+B4
A29: EXPENSES
A30: Cost of ploughs total | B30: 3.553125
A31: Purchase of corn total | B31: 0.84166667
A32: Cost of carts and wagons total | B32: 0.81875
A33: Cost of dairy total | B33: 3.9729167
A34: Purchase of stock total
A35: Sheepcote total
A36: Cost of buildings total | B36: 0.321875
A37: Threshing total | B37: 1.0208333
A38: Barley expenses
A39: Expenses of the harvest total | B39: 1.6916667
A40: Necessary expenses
A41: Wages of the bailiff
A42: Steward's expenses total
A43: Annual fees
A44: Total of all expenses per account
A45: Total of all expenses (calculated here)
A46: Total fixed investment
A47: Total Demesne fixed investment
A49: Owed by the reeve | B49: =B23-B45
A50: From accounts | B50: 13.403125
A52: Allowances
A53: Cash deliveries
A54: Sum of the above | B54: =SUM(B52:B53)
A55: Total of all allowances and cash deliveries in accounts
A57: Net amount owed | B57: =B50-B54
A58: Net amount owed in accounts
A60: GRANGE ACCOUNT | B60: Total Production | D60: Value of total gross production in £ | E60: Value of total net production in £
A61: Grange | B61: qrs | C61: bus
A62: Wheat | B62: 58
A63: Rye
A64: Dredge
A65: Curall | B65: 12
A66: Barley | B66: 91
A67: Oats | B67: 170
A68: Beans
A69: Peas
A70: Vetches | E70: 0.1
A71: Total value of gross production (sum of the above)
A72: Total value of net production
A73: Value of sales
A75: MILL ACCOUNT | B75: Total Production | D75: Total in £
A76: Issues of the mill | B76: qrs | C76: bus
A77: Wheat
A78: Oatmeal
A79: 1st grade malt
A80: 2nd grade malt
A81: Maslin
A82: Total value of production (sum of the above)
A83: Value of sales
A85: STOCK ACCOUNT
A86: Livestock | B86: Begin stock | C86: End stock | D86: Stockbuilding | F86: Value of stock in £ | G86: Value of stockbuilding
A87: Cart-horses | D87: =C87-B87 | F87: ='Stock'!K5*'Stock'!O5 | G87: =D87*'Stock'!O5
A88: Mares | C88: 0 | D88: =C88-B88 | F88: ='Stock'!K5*'Stock'!O5 | G88: =D88*'Stock'!O5
A89: Plough horses | B89: 5 | C89: 6 | D89: 1 | F89: ='Stock'!K6*'Stock'!O6 | G89: =D89*'Stock'!O6
A90: Colts (2 years) | C90: 0 | D90: =C90-B90 | F90: ='Stock'!K8*'Stock'!O8 | G90: =D90*'Stock'!O8
A91: Colts (2 years) | C91: 0 | D91: =C91-B91 | F91: ='Stock'!K8*'Stock'!O8 | G91: =D91*'Stock'!O8
A92: Colts (1 year) | C92: 0 | D92: =C92-B92 | F92: ='Stock'!K9*'Stock'!O9 | G92: =D92*'Stock'!O9
A93: Foals | C93: 0 | D93: =C93-B93 | F93: ='Stock'!K10*'Stock'!O10 | G93: =D93*'Stock'!O10
A94: Oxen | B94: 30 | C94: 35 | D94: 5 | F94: ='Stock'!K11*'Stock'!O11 | G94: =D94*'Stock'!O11
A95: Bulls | B95: 1 | C95: 1 | D95: 0 | F95: ='Stock'!K12*'Stock'!O12 | G95: =D95*'Stock'!O12
A96: Cows | B96: 17 | C96: 19 | D96: 2 | F96: ='Stock'!K13*'Stock'!O13 | G96: =D96*'Stock'!O13
A97: Steers | B97: 4 | C97: 0 | D97: -4 | F97: ='Stock'!K14*'Stock'!O14 | G97: =D97*'Stock'!O14
A98: Bullocks | B98: 5 | C98: 4 | D98: -1 | F98: ='Stock'!K15*'Stock'!O15 | G98: =D98*'Stock'!O15
A99: Yearlings | B99: 6 | C99: 5 | D99: -1 | F99: ='Stock'!K16*'Stock'!O16 | G99: =D99*'Stock'!O16
A100: Calves | C100: 6 | D100: =C100-B100 | F100: ='Stock'!K17*'Stock'!O17 | G100: =D100*'Stock'!O17
A101: Wethers | B101: 383 | C101: 433 | D101: 50 | F101: ='Stock'!K18*'Stock'!O18 | G101: =D101*'Stock'!O18
A102: Rams | C102: 0 | D102: =C102-B102 | F102: ='Stock'!K19*'Stock'!O19 | G102: =D102*'Stock'!O19
A103: Ewes | B103: 536 | C103: 575 | D103: 39 | F103: ='Stock'!K20*'Stock'!O20 | G103: =D103*'Stock'!O20
A104: Hoggs | B104: 286 | C104: 0 | D104: -286 | F104: ='Stock'!K21*'Stock'!O21 | G104: =D104*'Stock'!O21
A105: Lambs | C105: 268 | D105: =C105-B105 | F105: ='Stock'!K22*'Stock'!O22 | G105: =D105*'Stock'!O22
A106: Boars | B106: 1 | C106: 1 | D106: 0 | F106: ='Stock'!K23*'Stock'!O23 | G106: =D106*'Stock'!O23
A107: Sows | C107: 0 | D107: =C107-B107 | F107: ='Stock'!K24*'Stock'!O24 | G107: =D107*'Stock'!O24
A108: Pigs | B108: 27 | C108: 30 | D108: 3 | F108: ='Stock'!K25*'Stock'!O25 | G108: =D108*'Stock'!O25
...

Sheet Issues of the Mills
A1: No mill account for Adderbury

Sheet raw data
A1: Heading | B1: Sentence | C1: Total in Pounds | D1: Pounds | E1: Shillings | F1: Pence | G1: Corn | H1: Total Quarters Except 1 | I1: Total Bushels Except 1 | J1: Total Corn Cross-Check | K1: Total Corn Manorial Account | L1: Corn Quantity Error | M1: Quarters 1 | N1: Bushels 1 | O1: shilling a quarter 1 | P1: pence a quarter 1 | Q1: shilling a quarter 2 | R1: pence a quarter 2 | S1: shilling a quarter 3 | T1: pence a quarter 3 | U1: shilling a quarter 4 | V1: pence a quarter 4 | W1: shilling a bushel 1 | X1: pence a bushel 1 | Y1: shilling a bushel 2 | Z1: pence a bushel 2 | AA1: shilling a bushel 3 | AB1: pence a bushel 3 | AC1: shilling a bushel 4 | AD1: pence a bushel 4
A2: Adderbury | B2: The account2 of William Jakeman, reeve there, for the sixth year of the translation of Henry Beaufort', lord bishop of Winchester, and the eleventh year of the reign of King Henry the Fourth. | C2: 0 | D2: 0 | E2: 0 | F2: 0 | H2: 0 | I2: 0 | J2: 0 | K2: 0 | L2: 0 | M2: 0 | N2: 0
A3: Arrears | B3: None. | C3: 0 | D3: 0 | E3: 0 | F3: 0 | H3: 0 | I3: 0 | J3: 0 | K3: 0 | L3: 0 | M3: 0 | N3: 0
A4: Rents of assize | B4: And for £6 9 shilling 6.25pence for all rents of assize at St Thomas the Apostle (21 December). | C4: 6.48 | D4: 6 | E4: 9 | F4: 6.25 | H4: 0 | I4: 0 | J4: 0 | K4: 0 | L4: 0 | M4: 0 | N4: 0
A5: Rents of assize | B5: £6 9 shilling 8.5pence at Easter (23 March). | C5: 6.49 | D5: 6 | E5: 9 | F5: 8.5 | H5: 0 | I5: 0 | J5: 0 | K5: 0 | L5: 0 | M5: 0 | N5: 0
A6: Rents of assize | B6: £6 9 shilling 6.25pence at the Nativity of St John the Baptist (24 June). | C6: 6.48 | D6: 6 | E6: 9 | F6: 6.25 | H6: 0 | I6: 0 | J6: 0 | K6: 0 | L6: 0 | M6: 0 | N6: 0
A7: Rents of assize | B7: £6 10 shilling 1.5pence at Michaelmas (29 September). | C7: 6.51 | D7: 6 | E7: 10 | F7: 1.5 | H7: 0 | I7: 0 | J7: 0 | K7: 0 | L7: 0 | M7: 0 | N7: 0
A8: Rents of assize | B8: Total, £25 18 shilling 10.5pence. | C8: 25.94 | D8: 25 | E8: 18 | F8: 10.5 | H8: 0 | I8: 0 | J8: 0 | K8: 0 | L8: 0 | M8: 0 | N8: 0
A9: Quittances of rent | B9: In quittance of rent of 1 reeve for the year 5 shilling. | C9: 0.25 | D9: 0 | E9: 5 | F9: 0 | H9: 0 | I9: 0 | J9: 0 | K9: 0 | L9: 0 | M9: 0 | N9: 0
A10: Quittances of rent | B10: nothing this year of the 4 shilling for 1 smith forging the ironwork of 2 ploughs for the year. | C10: 0.2 | D10: 0 | E10: 4 | F10: 0 | H10: 0 | I10: 0 | J10: 0 | K10: 0 | L10: 0 | M10: 0 | N10: 0
A11: Quittances of rent | B11: nothing this year of the 4 shilling for 1 shepherd keeping the lord's wethers for the year. | C11: 0.2 | D11: 0 | E11: 4 | F11: 0 | H11: 0 | I11: 0 | J11: 0 | K11: 0 | L11: 0 | M11: 0 | N11: 0
A12: Quittances of rent | B12: nothing this year of the 4 shilling for 1 swineherd for the year. | C12: 0.2 | D12: 0 | E12: 4 | F12: 0 | H12: 0 | I12: 0 | J12: 0 | K12: 0 | L12: 0 | M12: 0 | N12: 0
A13: Quittances of rent | B13: nothing this year of the 4 shilling for 1 cowherd for the year. | C13: 0.2 | D13: 0 | E13: 4 | F13: 0 | H13: 0 | I13: 0 | J13: 0 | K13: 0 | L13: 0 | M13: 0 | N13: 0
... A149: Cost of buildings | B149: board-nails and clout-nails bought for the same 1 shilling 4pence. | C149: 0.07 | D149: 0 | E149: 1 | F149: 4 | H149: 0 | I149: 0 | J149: 0 | K149: 0 | L149: 0 | M149: 0 | N149: 0
A150: Cost of buildings | B150: 4 quarters 4 bushels of limestone bought at Walton' 5 shilling 3pence, at 1 shilling 2pence a quarters. | C150: 0.26 | D150: 0 | E150: 5 | F150: 3 | H150: 4 | I150: 4 | J150: 4.5 | K150: 4.5 | L150: 0 | M150: 4 | N150: 4 | O150: 1 | P150: 2
A151: Cost of buildings | B151: carrying the same 4pence. | C151: 0.02 | D151: 0 | E151: 0 | F151: 4 | H151: 0 | I151: 0 | J151: 0 | K151: 0 | L151: 0 | M151: 0 | N151: 0
A152: Cost of buildings | B152: 8 quarters of limestone bought at Witney 10 shilling 4pence, at 1 shilling 31 pence a quarters. | C152: 0.52 | D152: 0 | E152: 10 | F152: 4 | H152: 8 | I152: 0 | J152: 8 | K152: 8 | L152: 0 | M152: 8 | N152: 0 | O152: 1 | P152: 31
A153: Cost of buildings | B153: carrying the same from Witney to Adderbury 3 shilling 8pence. | C153: 0.18 | D153: 0 | E153: 3 | F153: 8 | H153: 0 | I153: 0 | J153: 0 | K153: 0 | L153: 0 | M153: 0 | N153: 0
A154: Cost of buildings | B154: 1,500 stone slates bought 6 shilling, at 4 shilling a 1,000.. | C154: 0.3 | D154: 0 | E154: 6 | F154: 0 | H154: 0 | I154: 0 | J154: 0 | K154: 0 | L154: 0 | M154: 0 | N154: 0
A155: Cost of buildings | B155: 500 eaves-stones bought 2 shilling 6pence, at 6pence a 100.. | C155: 0.12 | D155: 0 | E155: 2 | F155: 6 | H155: 0 | I155: 0 | J155: 0 | K155: 0 | L155: 0 | M155: 0 | N155: 0
A156: Cost of buildings | B156: 6,000 pins bought 2 shilling, at 4pence a 1,000.. | C156: 0.12 | D156: 0 | E156: 2 | F156: 4 | H156: 0 | I156: 0 | J156: 0 | K156: 0 | L156: 0 | M156: 0 | N156: 0
A157: Cost of buildings | B157: 50 ridge-tiles bought 6 shilling 3pence, at 1.5pence each. | C157: 0.31 | D157: 0 | E157: 6 | F157: 3 | H157: 0 | I157: 0 | J157: 0 | K157: 0 | L157: 0 | M157: 0 | N157: 0
A158: Cost of buildings | B158: sand bought and dug and quarried at Tadmarton 10pence. | C158: 0.04 | D158: 0 | E158: 0 | F158: 10 | H158: 0 | I158: 0 | J158: 0 | K158: 0 | L158: 0 | M158: 0 | N158: 0
A159: Cost of buildings | B159: stipend of 1 man going to Walton' to quarry lime there 2pence. | C159: 0.01 | D159: 0 | E159: 0 | F159: 2 | H159: 0 | I159: 0 | J159: 0 | K159: 0 | L159: 0 | M159: 0 | N159: 0
A160: Cost of buildings | B160: expenses of 12 men coming for a boon-work with 6 carts to quarry sand at Newotele and carry it to Adderbury, with the digging, 2 shilling 3pence. | C160: 0.11 | D160: 0 | E160: 2 | F160: 3 | H160: 0 | I160: 0 | J160: 0 | K160: 0 | L160: 0 | M160: 0 | N160: 0
A161: Cost of buildings | B161: hiring 1 man to carry sand and lime from the warrener's chamber to the barn by piece-work 4pence. | C161: 0.02 | D161: 0 | E161: 0 | F161: 4 | H161: 0 | I161: 0 | J161: 0 | K161: 0 | L161: 0 | M161: 0 | N161: 0
A162: Cost of buildings | B162: carrying the ridge-tiles bought above 8pence. | C162: 0.03 | D162: 0 | E162: 0 | F162: 8 | H162: 0 | I162: 0 | J162: 0 | K162: 0 | L162: 0 | M162: 0 | N162: 0
A163: Cost of buildings | B163: expenses of various men coming for a boon-work to buy slates at Aynho and carry them to Adderbury with the expenses of 1 man there mending the said slates 2d 1 shilling 9.5pence. | C163: 0.09 | D163: 0 | E163: 1 | F163: 9.5 | H163: 0 | I163: 0 | J163: 0 | K163: 0 | L163: 0 | M163: 0 | N163: 0
A164: Cost of buildings | B164: 1 tine bought 8pence. | C164: 0.03 | D164: 0 | E164: 0 | F164: 8 | H164: 0 | I164: 0 | J164: 0 | K164: 0 | L164: 0 | M164: 0 | N164: 0
... A181: Total of all allowances | B181: Total of all allowances and cash deliveries, £64 19 shilling 11.5pence He is quit. | C181: 65 | D181: 64 | E181: 19 | F181: 11.5 | H181: 0 | I181: 0 | J181: 0 | K181: 0 | L181: 0 | M181: 0 | N181: 0
A182: Wheat | B182: William Jakeman, reeve there, answers for 3 quarters of wheat remaining.. | C182: 0 | D182: 0 | E182: 0 | F182: 0 | G182: wheat | H182: 3 | I182: 0 | J182: 3 | K182: 3 | L182: 0 | M182: 3 | N182: 0
A183: Wheat | B183: Total, 3 quarters.. | C183: 0 | D183: 0 | E183: 0 | F183: 0 | H183: 3 | I183: 0 | J183: 3 | K183: 3 | L183: 0 | M183: 3 | N183: 0
A184: Wheat | B184: 3 quarters remain in the keeping of John Eadburbury, farmer there, to be handed back and restored at the end of his farm of 12 years, this year being the fifth. | C184: 0 | D184: 0 | E184: 0 | F184: 0 | H184: 3 | I184: 0 | J184: 3 | K184: 3 | L184: 0 | M184: 3 | N184: 0
A185: Rye | B185: And for 34 quarters of rye remaining.. | C185: 0 | D185: 0 | E185: 0 | F185: 0 | G185: rye | H185: 34 | I185: 0 | J185: 34 | K185: 34 | L185: 0 | M185: 34 | N185: 0
A186: Rye | B186: Total, 34 quarters.. | C186: 0 | D186: 0 | E186: 0 | F186: 0 | H186: 34 | I186: 0 | J186: 34 | K186: 34 | L186: 0 | M186: 34 | N186: 0
A187: Rye | B187: 34 quarters remain in the keeping of the said John Eadburbury, farmer there, to be handed back and restored at the end of his farm as before. | C187: 0 | D187: 0 | E187: 0 | F187: 0 | H187: 34 | I187: 0 | J187: 34 | K187: 34 | L187: 0 | M187: 34 | N187: 0
A188: Dredge | B188: And for 30 quarters of dredge remaining.. | C188: 0 | D188: 0 | E188: 0 | F188: 0 | G188: dredge | H188: 30 | I188: 0 | J188: 30 | K188: 30 | L188: 0 | M188: 30 | N188: 0
A189: Dredge | B189: Total, 30 quarters.. | C189: 0 | D189: 0 | E189: 0 | F189: 0 | H189: 30 | I189: 0 | J189: 30 | K189: 30 | L189: 0 | M189: 30 | N189: 0
A190: Dredge | B190: 30 quarters remain in the keeping of the said John Eadburbury, farmer there, to be handed back and restored as before. | C190: 0 | D190: 0 | E190: 0 | F190: 0 | H190: 30 | I190: 0 | J190: 30 | K190: 30 | L190: 0 | M190: 30 | N190: 0
A191: Pulses | B191: None remain. | C191: 0 | D191: 0 | E191: 0 | F191: 0 | H191: 0 | I191: 0 | J191: 0 | K191: 0 | L191: 0 | M191: 0 | N191: 0
A192: Oats | B192: And for 10 quarters of oats.. | C192: 0 | D192: 0 | E192: 0 | F192: 0 | G192: oats | H192: 10 | I192: 0 | J192: 10 | K192: 10 | L192: 0 | M192: 10 | N192: 0
A193: Oats | B193: Total, 10 quarters.. | C193: 0 | D193: 0 | E193: 0 | F193: 0 | H193: 10 | I193: 0 | J193: 10 | K193: 10 | L193: 0 | M193: 10 | N193: 0
A194: Oats | B194: 10 quarters remain in the keeping of the said John Eadburbury, farmer there, to be handed back and restored as before. | C194: 0 | D194: 0 | E194: 0 | F194: 0 | H194: 10 | I194: 0 | J194: 10 | K194: 10 | L194: 0 | M194: 10 | N194: 0
A195: Oats | B195: Eadburbury, farmer, to be handed back and restored at the end of his farm or the value of the same as before. | C195: 0 | D195: 0 | E195: 0 | F195: 0 | H195: 0 | I195: 0 | J195: 0 | K195: 0 | L195: 0 | M195: 0 | N195: 0
A196: Stock | B196: Horses: 4 remain. | C196: 0 | D196: 0 | E196: 0 | F196: 0 | H196: 0 | I196: 0 | J196: 0 | K196: 0 | L196: 0 | M196: 0 | N196: 0
A197: Stock | B197: 1 from the heriot of William Rundell'. | C197: 0 | D197: 0 | E197: 0 | F197: 0 | H197: 0 | I197: 0 | J197: 0 | K197: 0 | L197: 0 | M197: 0 | N197: 0
A198: Stock | B198: Total 5. 1 sold within. | C198: 0 | D198: 0 | E198: 0 | F198: 0 | H198: 0 | I198: 0 | J198: 0 | K198: 0 | L198: 0 | M198: 0 | N198: 0
A199: Stock | B199: 4 cart-horses remain, of which 2 are worth £1 6s 8pence, 1 is worth £1, and 1 feeble one is worth 2 shilling, in the keeping of the said John Eadburbury, farmer there, to be handed back and restored at the end of his farm or the value of the same at the choice of the lord bishop or his attorney. | C199: 1 | D199: 1 | E199: 0 | F199: 0 | H199: 0 | I199: 0 | J199: 0 | K199: 0 | L199: 0 | M199: 0 | N199: 0
A200: Stock | B200: Plough-horses: 6 remain. | C200: 0 | D200: 0 | E200: 0 | F200: 0 | H200: 0 | I200: 0 | J200: 0 | K200: 0 | L200: 0 | M200: 0 | N200: 0
A201: Stock | B201: Total, 6. 6 remain, worth £2, in the keeping of John. | C201: 2 | D201: 2 | E201: 0 | F201: 0 | H201: 0 | I201: 0 | J201: 0 | K201: 0 | L201: 0 | M201: 0 | N201: 0
A202: Stock | B202: Colts: 1 from the heriot of John Diconurn. | C202: 0 | D202: 0 | E202: 0 | F202: 0 | H202: 0 | I202: 0 | J202: 0 | K202: 0 | L202: 0 | M202: 0 | N202: 0
A203: Stock | B203: sold within. | C203: 0 | D203: 0 | E203: 0 | F203: 0 | H203: 0 | I203: 0 | J203: 0 | K203: 0 | L203: 0 | M203: 0 | N203: 0
A204: Stock | B204: none remain. | C204: 0 | D204: 0 | E204: 0 | F204: 0 | H204: 0 | I204: 0 | J204: 0 | K204: 0 | L204: 0 | M204: 0 | N204: 0
... A268: Stock | B268: none remain. mid. | C268: 0 | D268: 0 | E268: 0 | F268: 0 | H268: 0 | I268: 0 | J268: 0 | K268: 0 | L268: 0 | M268: 0 | N268: 0

Sheet Prices
A1: Meat & Dairy Prices
C2: 1301 | D2: 1302 | E2: Average
A3: Beef | B3: £ per lb | C3: 0.0033351854 | D3: 0.0032608538 | E3: =AVERAGE(C3:D3)
A4: Mutton | B4: £ per lb | C4: 0.0036593977 | D4: 0.0037125513 | E4: =AVERAGE(C4:D4)
A5: Pork | B5: £ per lb | C5: 0.0038431326 | D5: 0.0037574803 | E5: =AVERAGE(C5:D5)
A6: Cheese | B6: £ per lb | C6: 0.0055768754 | D6: 0.0056654898 | E6: =AVERAGE(C6:D6)
A7: Butter | B7: £ per lb | C7: 0.0036626221 | D7: 0.0035935077 | E7: =AVERAGE(C7:D7)
A8: Milk | B8: £ per gallon | C8: 0.0055768754 | D8: 0.0056654898 | E8: =AVERAGE(C8:D8)

Sheet Labour Rents

Sheet Crawley Overview
A1: CRAWLEY | B1: £ | C1: s | D1: d | G1: Total in £ | H1: Error
A3: CASH ACCOUNT
A4: RECEIPTS
A5: Arrears total | G5: =IF(INDEX('Crawley Receipts'!$A$4:$F$110,MATCH('Crawley Overview'!$A5,'Crawley Receipts'!$A$4:$A$110,0),6)=0,"",INDEX('Crawley Receipts'!$A$4:$F$110,MATCH('Crawley Overview'!$A5,'Crawley Receipts'!$A$4:$A$110,0),6))
A6: Rents of assize total | G6: =IF(INDEX('Crawley Receipts'!$A$4:$F$110,MATCH('Crawley Overview'!$A6,'Crawley Receipts'!$A$4:$A$110,0),6)=0,"",INDEX('Crawley Receipts'!$A$4:$F$110,MATCH('Crawley Overview'!$A6,'Crawley Receipts'!$A$4:$A$110,0),6))
A7: Quittances total | G7: =IF(INDEX('Crawley Receipts'!$A$4:$F$110,MATCH('Crawley Overview'!$A7,'Crawley Receipts'!$A$4:$A$110,0),6)=0,"",INDEX('Crawley Receipts'!$A$4:$F$110,MATCH('Crawley Overview'!$A7,'Crawley Receipts'!$A$4:$A$110,0),6))
A8: Defaults of rent total | G8: =IF(INDEX('Crawley Receipts'!$A$4:$F$110,MATCH('Crawley Overview'!$A8,'Crawley Receipts'!$A$4:$A$110,0),6)=0,"",INDEX('Crawley Receipts'!$A$4:$F$110,MATCH('Crawley Overview'!$A8,'Crawley Receipts'!$A$4:$A$110,0),6))
A9: Total of rents remaining | G9: ='Crawley Receipts'!F36
A10: Annual recognizances total | G10: =IF(INDEX('Crawley Receipts'!$A$4:$F$110,MATCH('Crawley Overview'!$A10,'Crawley Receipts'!$A$4:$A$110,0),6)=0,"",INDEX('Crawley Receipts'!$A$4:$F$110,MATCH('Crawley Overview'!$A10,'Crawley Receipts'!$A$4:$A$110,0),6))
A11: Issues of the Manor total | G11: =IF(INDEX('Crawley Receipts'!$A$4:$F$110,MATCH('Crawley Overview'!$A11,'Crawley Receipts'!$A$4:$A$110,0),6)=0,"",INDEX('Crawley Receipts'!$A$4:$F$110,MATCH('Crawley Overview'!$A11,'Crawley Receipts'!$A$4:$A$110,0),6))
A12: Sale of corn total | G12: =IF(INDEX('Crawley Receipts'!$A$4:$F$110,MATCH('Crawley Overview'!$A12,'Crawley Receipts'!$A$4:$A$110,0),6)=0,"",INDEX('Crawley Receipts'!$A$4:$F$110,MATCH('Crawley Overview'!$A12,'Crawley Receipts'!$A$4:$A$110,0),6))
A13: Entry and marriage fines total | G13: =IF(INDEX('Crawley Receipts'!$A$4:$F$110,MATCH('Crawley Overview'!$A13,'Crawley Receipts'!$A$4:$A$110,0),6)=0,"",INDEX('Crawley Receipts'!$A$4:$F$110,MATCH('Crawley Overview'!$A13,'Crawley Receipts'!$A$4:$A$110,0),6))
A14: Pleas & perquisites total | G14: =IF(INDEX('Crawley Receipts'!$A$4:$F$110,MATCH('Crawley Overview'!$A14,'Crawley Receipts'!$A$4:$A$110,0),6)=0,"",INDEX('Crawley Receipts'!$A$4:$F$110,MATCH('Crawley Overview'!$A14,'Crawley Receipts'!$A$4:$A$110,0),6))
A15: Sum of the above (incl. arrears) | G15: =G5+G9+G10+G11+G12+G13+G14
A16: Total recorded in the accounts excl. arrears | G16: ='Crawley Receipts'!F110 | H16: matches excl. arrear sum
A17: Total recorded in the accounts incl. arrears
A20: EXPENSES
A21: Cost of ploughs total | G21: =IF(INDEX('Crawley Expenses'!$A$2:$F$108,MATCH('Crawley Overview'!$A21,'Crawley Expenses'!$A$2:$A$108,0),6)=0,"",INDEX('Crawley Expenses'!$A$2:$F$108,MATCH('Crawley Overview'!$A21,'Crawley Expenses'!$A$2:$A$108,0),6))
A22: Purchase of corn total | G22: =IF(INDEX('Crawley Expenses'!$A$2:$F$108,MATCH('Crawley Overview'!$A22,'Crawley Expenses'!$A$2:$A$108,0),6)=0,"",INDEX('Crawley Expenses'!$A$2:$F$108,MATCH('Crawley Overview'!$A22,'Crawley Expenses'!$A$2:$A$108,0),6))
A23: Cost of carts and wagons total | G23: =IF(INDEX('Crawley Expenses'!$A$2:$F$108,MATCH('Crawley Overview'!$A23,'Crawley Expenses'!$A$2:$A$108,0),6)=0,"",INDEX('Crawley Expenses'!$A$2:$F$108,MATCH('Crawley Overview'!$A23,'Crawley Expenses'!$A$2:$A$108,0),6))
A24: Cost of dairy total | G24: =IF(INDEX('Crawley Expenses'!$A$2:$F$108,MATCH('Crawley Overview'!$A24,'Crawley Expenses'!$A$2:$A$108,0),6)=0,"",INDEX('Crawley Expenses'!$A$2:$F$108,MATCH('Crawley Overview'!$A24,'Crawley Expenses'!$A$2:$A$108,0),6))
A25: Cost of buildings total | G25: =IF(INDEX('Crawley Expenses'!$A$2:$F$108,MATCH('Crawley Overview'!$A25,'Crawley Expenses'!$A$2:$A$108,0),6)=0,"",INDEX('Crawley Expenses'!$A$2:$F$108,MATCH('Crawley Overview'!$A25,'Crawley Expenses'!$A$2:$A$108,0),6))
A26: Threshing total | G26: =IF(INDEX('Crawley Expenses'!$A$2:$F$108,MATCH('Crawley Overview'!$A26,'Crawley Expenses'!$A$2:$A$108,0),6)=0,"",INDEX('Crawley Expenses'!$A$2:$F$108,MATCH('Crawley Overview'!$A26,'Crawley Expenses'!$A$2:$A$108,0),6))
A27: Expenses of the harvest total | G27: =IF(INDEX('Crawley Expenses'!$A$2:$F$108,MATCH('Crawley Overview'!$A27,'Crawley Expenses'!$A$2:$A$108,0),6)=0,"",INDEX('Crawley Expenses'!$A$2:$F$108,MATCH('Crawley Overview'!$A27,'Crawley Expenses'!$A$2:$A$108,0),6))
A28: Steward's expenses total | G28: =IF(INDEX('Crawley Expenses'!$A$2:$F$108,MATCH('Crawley Overview'!$A28,'Crawley Expenses'!$A$2:$A$108,0),6)=0,"",INDEX('Crawley Expenses'!$A$2:$F$108,MATCH('Crawley Overview'!$A28,'Crawley Expenses'!$A$2:$A$108,0),6))
A29: Sum of the above | G29: =SUM(G21:G28)
A30: Total of all expenses | G30: ='Crawley Expenses'!F103 | H30: =G29-G30
A31: Total Demesne fixed investment | G31: ='Crawley Expenses'!F108
A33: Owed by the reeve | G33: ='Crawley Expenses'!F105
A34: From accounts
A36: Cash deliveries | G36: ='Crawley Expenses'!F106
A37: Total of all allowances and cash deliveries in accounts | B37: n/a
A39: Net amount owed | G39: =G33-G36
A40: Net amount owed in accounts | G40: ='Crawley Expenses'!F107 | H40: =G39-G40
A42: GRANGE ACCOUNT | B42: Net Production
A43: Grange | B43: qrs | G43: £ | I43: Note: Columns indexed are hardcoded, do not alter number of columns in issues of grange
A44: Net wheat | B44: =IF(INDEX('Issues of the Grange'!$A$2:$P$26,MATCH('Crawley Overview'!$A44,'Issues of the Grange'!$A$2:$A$26,0),10)=0,"",INDEX('Issues of the Grange'!$A$2:$P$26,MATCH('Crawley Overview'!$A44,'Issues of the Grange'!$A$2:$A$26,0),10)) | G44: =IF(INDEX('Issues of the Grange'!$A$2:$P$26,MATCH('Crawley Overview'!$A44,'Issues of the Grange'!$A$2:$A$26,0),13)=0,"",INDEX('Issues of the Grange'!$A$2:$P$26,MATCH('Crawley Overview'!$A44,'Issues of the Grange'!$A$2:$A$26,0),13))
A45: Net curall | B45: =IF(INDEX('Issues of the Grange'!$A$2:$P$26,MATCH('Crawley Overview'!$A45,'Issues of the Grange'!$A$2:$A$26,0),10)=0,"",INDEX('Issues of the Grange'!$A$2:$P$26,MATCH('Crawley Overview'!$A45,'Issues of the Grange'!$A$2:$A$26,0),10)) | G45: =IF(INDEX('Issues of the Grange'!$A$2:$P$26,MATCH('Crawley Overview'!$A45,'Issues of the Grange'!$A$2:$A$26,0),13)=0,"",INDEX('Issues of the Grange'!$A$2:$P$26,MATCH('Crawley Overview'!$A45,'Issues of the Grange'!$A$2:$A$26,0),13))
A46: Net Bere | B46: =IF(INDEX('Issues of the Grange'!$A$2:$P$26,MATCH('Crawley Overview'!$A46,'Issues of the Grange'!$A$2:$A$26,0),10)=0,"",INDEX('Issues of the Grange'!$A$2:$P$26,MATCH('Crawley Overview'!$A46,'Issues of the Grange'!$A$2:$A$26,0),10)) | G46: =IF(INDEX('Issues of the Grange'!$A$2:$P$26,MATCH('Crawley Overview'!$A46,'Issues of the Grange'!$A$2:$A$26,0),13)=0,"",INDEX('Issues of the Grange'!$A$2:$P$26,MATCH('Crawley Overview'!$A46,'Issues of the Grange'!$A$2:$A$26,0),13))
A47: Net barley | B47: =IF(INDEX('Issues of the Grange'!$A$2:$P$26,MATCH('Crawley Overview'!$A47,'Issues of the Grange'!$A$2:$A$26,0),10)=0,"",INDEX('Issues of the Grange'!$A$2:$P$26,MATCH('Crawley Overview'!$A47,'Issues of the Grange'!$A$2:$A$26,0),10)) | G47: =IF(INDEX('Issues of the Grange'!$A$2:$P$26,MATCH('Crawley Overview'!$A47,'Issues of the Grange'!$A$2:$A$26,0),13)=0,"",INDEX('Issues of the Grange'!$A$2:$P$26,MATCH('Crawley Overview'!$A47,'Issues of the Grange'!$A$2:$A$26,0),13))
A48: Net oats | B48: =IF(INDEX('Issues of the Grange'!$A$2:$P$26,MATCH('Crawley Overview'!$A48,'Issues of the Grange'!$A$2:$A$26,0),10)=0,"",INDEX('Issues of the Grange'!$A$2:$P$26,MATCH('Crawley Overview'!$A48,'Issues of the Grange'!$A$2:$A$26,0),10)) | G48: =IF(INDEX('Issues of the Grange'!$A$2:$P$26,MATCH('Crawley Overview'!$A48,'Issues of the Grange'!$A$2:$A$26,0),13)=0,"",INDEX('Issues of the Grange'!$A$2:$P$26,MATCH('Crawley Overview'!$A48,'Issues of the Grange'!$A$2:$A$26,0),13))
A49: Net peas | B49: =IF(INDEX('Issues of the Grange'!$A$2:$P$26,MATCH('Crawley Overview'!$A49,'Issues of the Grange'!$A$2:$A$26,0),10)=0,"",INDEX('Issues of the Grange'!$A$2:$P$26,MATCH('Crawley Overview'!$A49,'Issues of the Grange'!$A$2:$A$26,0),10)) | G49: =IF(INDEX('Issues of the Grange'!$A$2:$P$26,MATCH('Crawley Overview'!$A49,'Issues of the Grange'!$A$2:$A$26,0),13)=0,"",INDEX('Issues of the Grange'!$A$2:$P$26,MATCH('Crawley Overview'!$A49,'Issues of the Grange'!$A$2:$A$26,0),13))
A50: Net vetches | B50: =IF(INDEX('Issues of the Grange'!$A$2:$P$26,MATCH('Crawley Overview'!$A50,'Issues of the Grange'!$A$2:$A$26,0),10)=0,"",INDEX('Issues of the Grange'!$A$2:$P$26,MATCH('Crawley Overview'!$A50,'Issues of the Grange'!$A$2:$A$26,0),10)) | G50: =IF(INDEX('Issues of the Grange'!$A$2:$P$26,MATCH('Crawley Overview'!$A50,'Issues of the Grange'!$A$2:$A$26,0),13)=0,"",INDEX('Issues of the Grange'!$A$2:$P$26,MATCH('Crawley Overview'!$A50,'Issues of the Grange'!$A$2:$A$26,0),13))
A51: Net value of production (sum of the above) | G51: =SUM(G44:G50)
A52: Value of sales | G52: ='Issues of the Grange'!N26
A54: MILL ACCOUNT
A55: Issues of the mill | B55: qrs | C55: bus | G55: £ | I55: no mill account
A56: Wheat
A57: Oatmeal
A58: 1st grade malt
A59: 2nd grade malt
A60: Maslin
A61: Total value of production (sum of the above)
A62: Value of sales
A64: STOCK ACCOUNT
A65: Livestock | B65: Inherited stock | C65: End-period stock | D65: Stockbuilding | F65: Sales in (£) | G65: Value of production (£) at sales prices
A66: Cart-horses | B66: =IFERROR(INDEX(Stock!$A$3:$T$92,MATCH('Crawley Overview'!$A66,Stock!$A$3:$A$92,0),MATCH('Crawley Overview'!B$65,Stock!$A$3:$T$3,0)),0) | C66: =IFERROR(INDEX(Stock!$A$3:$T$92,MATCH('Crawley Overview'!$A66,Stock!$A$3:$A$92,0),MATCH('Crawley Overview'!C$65,Stock!$A$3:$T$3,0)),0) | D66: =C66-B66 | F66: =IFERROR(INDEX(Stock!$A$3:$T$92,MATCH('Crawley Overview'!$A66,Stock!$A$3:$A$92,0),MATCH('Crawley Overview'!F$65,Stock!$A$3:$T$3,0)),0) | G66: =IFERROR(INDEX(Stock!$A$3:$T$92,MATCH('Crawley Overview'!$A66,Stock!$A$3:$A$92,0),MATCH('Crawley Overview'!G$65,Stock!$A$3:$T$3,0)),0)
A67: Mares | B67: =IFERROR(INDEX(Stock!$A$3:$T$92,MATCH('Crawley Overview'!$A67,Stock!$A$3:$A$92,0),MATCH('Crawley Overview'!B$65,Stock!$A$3:$T$3,0)),0) | C67: =IFERROR(INDEX(Stock!$A$3:$T$92,MATCH('Crawley Overview'!$A67,Stock!$A$3:$A$92,0),MATCH('Crawley Overview'!C$65,Stock!$A$3:$T$3,0)),0) | D67: =C67-B67 | F67: =IFERROR(INDEX(Stock!$A$3:$T$92,MATCH('Crawley Overview'!$A67,Stock!$A$3:$A$92,0),MATCH('Crawley Overview'!F$65,Stock!$A$3:$T$3,0)),0) | G67: =IFERROR(INDEX(Stock!$A$3:$T$92,MATCH('Crawley Overview'!$A67,Stock!$A$3:$A$92,0),MATCH('Crawley Overview'!G$65,Stock!$A$3:$T$3,0)),0)
A68: Plough horses | B68: =IFERROR(INDEX(Stock!$A$3:$T$92,MATCH('Crawley Overview'!$A68,Stock!$A$3:$A$92,0),MATCH('Crawley Overview'!B$65,Stock!$A$3:$T$3,0)),0) | C68: =IFERROR(INDEX(Stock!$A$3:$T$92,MATCH('Crawley Overview'!$A68,Stock!$A$3:$A$92,0),MATCH('Crawley Overview'!C$65,Stock!$A$3:$T$3,0)),0) | D68: =C68-B68 | F68: =IFERROR(INDEX(Stock!$A$3:$T$92,MATCH('Crawley Overview'!$A68,Stock!$A$3:$A$92,0),MATCH('Crawley Overview'!F$65,Stock!$A$3:$T$3,0)),0) | G68: =IFERROR(INDEX(Stock!$A$3:$T$92,MATCH('Crawley Overview'!$A68,Stock!$A$3:$A$92,0),MATCH('Crawley Overview'!G$65,Stock!$A$3:$T$3,0)),0)
A69: Colts (2 years) | B69: =IFERROR(INDEX(Stock!$A$3:$T$92,MATCH('Crawley Overview'!$A69,Stock!$A$3:$A$92,0),MATCH('Crawley Overview'!B$65,Stock!$A$3:$T$3,0)),0) | C69: =IFERROR(INDEX(Stock!$A$3:$T$92,MATCH('Crawley Overview'!$A69,Stock!$A$3:$A$92,0),MATCH('Crawley Overview'!C$65,Stock!$A$3:$T$3,0)),0) | D69: =C69-B69 | F69: =IFERROR(INDEX(Stock!$A$3:$T$92,MATCH('Crawley Overview'!$A69,Stock!$A$3:$A$92,0),MATCH('Crawley Overview'!F$65,Stock!$A$3:$T$3,0)),0) | G69: =IFERROR(INDEX(Stock!$A$3:$T$92,MATCH('Crawley Overview'!$A69,Stock!$A$3:$A$92,0),MATCH('Crawley Overview'!G$65,Stock!$A$3:$T$3,0)),0)
A70: Colts (2 years) | B70: =IFERROR(INDEX(Stock!$A$3:$T$92,MATCH('Crawley Overview'!$A70,Stock!$A$3:$A$92,0),MATCH('Crawley Overview'!B$65,Stock!$A$3:$T$3,0)),0) | C70: =IFERROR(INDEX(Stock!$A$3:$T$92,MATCH('Crawley Overview'!$A70,Stock!$A$3:$A$92,0),MATCH('Crawley Overview'!C$65,Stock!$A$3:$T$3,0)),0) | D70: =C70-B70 | F70: =IFERROR(INDEX(Stock!$A$3:$T$92,MATCH('Crawley Overview'!$A70,Stock!$A$3:$A$92,0),MATCH('Crawley Overview'!F$65,Stock!$A$3:$T$3,0)),0) | G70: =IFERROR(INDEX(Stock!$A$3:$T$92,MATCH('Crawley Overview'!$A70,Stock!$A$3:$A$92,0),MATCH('Crawley Overview'!G$65,Stock!$A$3:$T$3,0)),0)
A71: Colts (1 year) | B71: =IFERROR(INDEX(Stock!$A$3:$T$92,MATCH('Crawley Overview'!$A71,Stock!$A$3:$A$92,0),MATCH('Crawley Overview'!B$65,Stock!$A$3:$T$3,0)),0) | C71: =IFERROR(INDEX(Stock!$A$3:$T$92,MATCH('Crawley Overview'!$A71,Stock!$A$3:$A$92,0),MATCH('Crawley Overview'!C$65,Stock!$A$3:$T$3,0)),0) | D71: =C71-B71 | F71: =IFERROR(INDEX(Stock!$A$3:$T$92,MATCH('Crawley Overview'!$A71,Stock!$A$3:$A$92,0),MATCH('Crawley Overview'!F$65,Stock!$A$3:$T$3,0)),0) | G71: =IFERROR(INDEX(Stock!$A$3:$T$92,MATCH('Crawley Overview'!$A71,Stock!$A$3:$A$92,0),MATCH('Crawley Overview'!G$65,Stock!$A$3:$T$3,0)),0)
A72: Foals | B72: =IFERROR(INDEX(Stock!$A$3:$T$92,MATCH('Crawley Overview'!$A72,Stock!$A$3:$A$92,0),MATCH('Crawley Overview'!B$65,Stock!$A$3:$T$3,0)),0) | C72: =IFERROR(INDEX(Stock!$A$3:$T$92,MATCH('Crawley Overview'!$A72,Stock!$A$3:$A$92,0),MATCH('Crawley Overview'!C$65,Stock!$A$3:$T$3,0)),0) | D72: =C72-B72 | F72: =IFERROR(INDEX(Stock!$A$3:$T$92,MATCH('Crawley Overview'!$A72,Stock!$A$3:$A$92,0),MATCH('Crawley Overview'!F$65,Stock!$A$3:$T$3,0)),0) | G72: =IFERROR(INDEX(Stock!$A$3:$T$92,MATCH('Crawley Overview'!$A72,Stock!$A$3:$A$92,0),MATCH('Crawley Overview'!G$65,Stock!$A$3:$T$3,0)),0)
A73: Oxen | B73: =IFERROR(INDEX(Stock!$A$3:$T$92,MATCH('Crawley Overview'!$A73,Stock!$A$3:$A$92,0),MATCH('Crawley Overview'!B$65,Stock!$A$3:$T$3,0)),0) | C73: =IFERROR(INDEX(Stock!$A$3:$T$92,MATCH('Crawley Overview'!$A73,Stock!$A$3:$A$92,0),MATCH('Crawley Overview'!C$65,Stock!$A$3:$T$3,0)),0) | D73: =C73-B73 | F73: =IFERROR(INDEX(Stock!$A$3:$T$92,MATCH('Crawley Overview'!$A73,Stock!$A$3:$A$92,0),MATCH('Crawley Overview'!F$65,Stock!$A$3:$T$3,0)),0) | G73: =IFERROR(INDEX(Stock!$A$3:$T$92,MATCH('Crawley Overview'!$A73,Stock!$A$3:$A$92,0),MATCH('Crawley Overview'!G$65,Stock!$A$3:$T$3,0)),0)
A74: Bulls | B74: =IFERROR(INDEX(Stock!$A$3:$T$92,MATCH('Crawley Overview'!$A74,Stock!$A$3:$A$92,0),MATCH('Crawley Overview'!B$65,Stock!$A$3:$T$3,0)),0) | C74: =IFERROR(INDEX(Stock!$A$3:$T$92,MATCH('Crawley Overview'!$A74,Stock!$A$3:$A$92,0),MATCH('Crawley Overview'!C$65,Stock!$A$3:$T$3,0)),0) | D74: =C74-B74 | F74: =IFERROR(INDEX(Stock!$A$3:$T$92,MATCH('Crawley Overview'!$A74,Stock!$A$3:$A$92,0),MATCH('Crawley Overview'!F$65,Stock!$A$3:$T$3,0)),0) | G74: =IFERROR(INDEX(Stock!$A$3:$T$92,MATCH('Crawley Overview'!$A74,Stock!$A$3:$A$92,0),MATCH('Crawley Overview'!G$65,Stock!$A$3:$T$3,0)),0)
A75: Cows | B75: =IFERROR(INDEX(Stock!$A$3:$T$92,MATCH('Crawley Overview'!$A75,Stock!$A$3:$A$92,0),MATCH('Crawley Overview'!B$65,Stock!$A$3:$T$3,0)),0) | C75: =IFERROR(INDEX(Stock!$A$3:$T$92,MATCH('Crawley Overview'!$A75,Stock!$A$3:$A$92,0),MATCH('Crawley Overview'!C$65,Stock!$A$3:$T$3,0)),0) | D75: =C75-B75 | F75: =IFERROR(INDEX(Stock!$A$3:$T$92,MATCH('Crawley Overview'!$A75,Stock!$A$3:$A$92,0),MATCH('Crawley Overview'!F$65,Stock!$A$3:$T$3,0)),0) | G75: =IFERROR(INDEX(Stock!$A$3:$T$92,MATCH('Crawley Overview'!$A75,Stock!$A$3:$A$92,0),MATCH('Crawley Overview'!G$65,Stock!$A$3:$T$3,0)),0)
A76: Steers | B76: =IFERROR(INDEX(Stock!$A$3:$T$92,MATCH('Crawley Overview'!$A76,Stock!$A$3:$A$92,0),MATCH('Crawley Overview'!B$65,Stock!$A$3:$T$3,0)),0) | C76: =IFERROR(INDEX(Stock!$A$3:$T$92,MATCH('Crawley Overview'!$A76,Stock!$A$3:$A$92,0),MATCH('Crawley Overview'!C$65,Stock!$A$3:$T$3,0)),0) | D76: =C76-B76 | F76: =IFERROR(INDEX(Stock!$A$3:$T$92,MATCH('Crawley Overview'!$A76,Stock!$A$3:$A$92,0),MATCH('Crawley Overview'!F$65,Stock!$A$3:$T$3,0)),0) | G76: =IFERROR(INDEX(Stock!$A$3:$T$92,MATCH('Crawley Overview'!$A76,Stock!$A$3:$A$92,0),MATCH('Crawley Overview'!G$65,Stock!$A$3:$T$3,0)),0)
A77: Bullocks | B77: =IFERROR(INDEX(Stock!$A$3:$T$92,MATCH('Crawley Overview'!$A77,Stock!$A$3:$A$92,0),MATCH('Crawley Overview'!B$65,Stock!$A$3:$T$3,0)),0) | C77: =IFERROR(INDEX(Stock!$A$3:$T$92,MATCH('Crawley Overview'!$A77,Stock!$A$3:$A$92,0),MATCH('Crawley Overview'!C$65,Stock!$A$3:$T$3,0)),0) | D77: =C77-B77 | F77: =IFERROR(INDEX(Stock!$A$3:$T$92,MATCH('Crawley Overview'!$A77,Stock!$A$3:$A$92,0),MATCH('Crawley Overview'!F$65,Stock!$A$3:$T$3,0)),0) | G77: =IFERROR(INDEX(Stock!$A$3:$T$92,MATCH('Crawley Overview'!$A77,Stock!$A$3:$A$92,0),MATCH('Crawley Overview'!G$65,Stock!$A$3:$T$3,0)),0)
... A91: Peacocks | B91: =IFERROR(INDEX(Stock!$A$3:$T$92,MATCH('Crawley Overview'!$A91,Stock!$A$3:$A$92,0),MATCH('Crawley Overview'!B$65,Stock!$A$3:$T$3,0)),0) | C91: =IFERROR(INDEX(Stock!$A$3:$T$92,MATCH('Crawley Overview'!$A91,Stock!$A$3:$A$92,0),MATCH('Crawley Overview'!C$65,Stock!$A$3:$T$3,0)),0) | D91: =C91-B91 | F91: =IFERROR(INDEX(Stock!$A$3:$T$92,MATCH('Crawley Overview'!$A91,Stock!$A$3:$A$92,0),MATCH('Crawley Overview'!F$65,Stock!$A$3:$T$3,0)),0) | G91: =IFERROR(INDEX(Stock!$A$3:$T$92,MATCH('Crawley Overview'!$A91,Stock!$A$3:$A$92,0),MATCH('Crawley Overview'!G$65,Stock!$A$3:$T$3,0)),0)
A92: Total | G92: =SUM(G66:G91)
A93: Value of sales | G93: =SUM(F66:F91)
A95: Wool | B95: Inherited stock | C95: End-period stock | D95: Stockbuilding | F95: Sales in (£) | G95: Value of production (£) at sales prices
A96: Fleeces | B96: =IFERROR(INDEX(Stock!$A$3:$T$92,MATCH('Crawley Overview'!$A96,Stock!$A$3:$A$92,0),MATCH('Crawley Overview'!B$65,Stock!$A$3:$T$3,0)),0) | C96: =IFERROR(INDEX(Stock!$A$3:$T$92,MATCH('Crawley Overview'!$A96,Stock!$A$3:$A$92,0),MATCH('Crawley Overview'!C$65,Stock!$A$3:$T$3,0)),0) | D96: =C96-B96 | F96: =IFERROR(INDEX(Stock!$A$3:$T$92,MATCH('Crawley Overview'!$A96,Stock!$A$3:$A$92,0),MATCH('Crawley Overview'!F$65,Stock!$A$3:$T$3,0)),0) | G96: =IFERROR(INDEX(Stock!$A$3:$T$92,MATCH('Crawley Overview'!$A96,Stock!$A$3:$A$92,0),MATCH('Crawley Overview'!G$65,Stock!$A$3:$T$3,0)),0)
A97: Coarse wool | B97: =IFERROR(INDEX(Stock!$A$3:$T$92,MATCH('Crawley Overview'!$A97,Stock!$A$3:$A$92,0),MATCH('Crawley Overview'!B$65,Stock!$A$3:$T$3,0)),0) | C97: =IFERROR(INDEX(Stock!$A$3:$T$92,MATCH('Crawley Overview'!$A97,Stock!$A$3:$A$92,0),MATCH('Crawley Overview'!C$65,Stock!$A$3:$T$3,0)),0) | D97: =C97-B97 | F97: =IFERROR(INDEX(Stock!$A$3:$T$92,MATCH('Crawley Overview'!$A97,Stock!$A$3:$A$92,0),MATCH('Crawley Overview'!F$65,Stock!$A$3:$T$3,0)),0) | G97: =IFERROR(INDEX(Stock!$A$3:$T$92,MATCH('Crawley Overview'!$A97,Stock!$A$3:$A$92,0),MATCH('Crawley Overview'!G$65,Stock!$A$3:$T$3,0)),0)
A98: Lamb's wool | B98: =IFERROR(INDEX(Stock!$A$3:$T$92,MATCH('Crawley Overview'!$A98,Stock!$A$3:$A$92,0),MATCH('Crawley Overview'!B$65,Stock!$A$3:$T$3,0)),0) | C98: =IFERROR(INDEX(Stock!$A$3:$T$92,MATCH('Crawley Overview'!$A98,Stock!$A$3:$A$92,0),MATCH('Crawley Overview'!C$65,Stock!$A$3:$T$3,0)),0) | D98: =C98-B98 | F98: =IFERROR(INDEX(Stock!$A$3:$T$92,MATCH('Crawley Overview'!$A98,Stock!$A$3:$A$92,0),MATCH('Crawley Overview'!F$65,Stock!$A$3:$T$3,0)),0) | G98: =IFERROR(INDEX(Stock!$A$3:$T$92,MATCH('Crawley Overview'!$A98,Stock!$A$3:$A$92,0),MATCH('Crawley Overview'!G$65,Stock!$A$3:$T$3,0)),0)
A99: Wool locks | B99: =IFERROR(INDEX(Stock!$A$3:$T$92,MATCH('Crawley Overview'!$A99,Stock!$A$3:$A$92,0),MATCH('Crawley Overview'!B$65,Stock!$A$3:$T$3,0)),0) | C99: =IFERROR(INDEX(Stock!$A$3:$T$92,MATCH('Crawley Overview'!$A99,Stock!$A$3:$A$92,0),MATCH('Crawley Overview'!C$65,Stock!$A$3:$T$3,0)),0) | D99: =C99-B99 | F99: =IFERROR(INDEX(Stock!$A$3:$T$92,MATCH('Crawley Overview'!$A99,Stock!$A$3:$A$92,0),MATCH('Crawley Overview'!F$65,Stock!$A$3:$T$3,0)),0) | G99: =IFERROR(INDEX(Stock!$A$3:$T$92,MATCH('Crawley Overview'!$A99,Stock!$A$3:$A$92,0),MATCH('Crawley Overview'!G$65,Stock!$A$3:$T$3,0)),0)
A100: Wool sold at shearing | B100: =IFERROR(INDEX(Stock!$A$3:$T$92,MATCH('Crawley Overview'!$A100,Stock!$A$3:$A$92,0),MATCH('Crawley Overview'!B$65,Stock!$A$3:$T$3,0)),0) | C100: =IFERROR(INDEX(Stock!$A$3:$T$92,MATCH('Crawley Overview'!$A100,Stock!$A$3:$A$92,0),MATCH('Crawley Overview'!C$65,Stock!$A$3:$T$3,0)),0) | D100: =C100-B100 | F100: =IFERROR(INDEX(Stock!$A$3:$T$92,MATCH('Crawley Overview'!$A100,Stock!$A$3:$A$92,0),MATCH('Crawley Overview'!F$65,Stock!$A$3:$T$3,0)),0) | G100: =IFERROR(INDEX(Stock!$A$3:$T$92,MATCH('Crawley Overview'!$A100,Stock!$A$3:$A$92,0),MATCH('Crawley Overview'!G$65,Stock!$A$3:$T$3,0)),0)
A101: Total value of production (sum of the above) | G101: =SUM(G96:G100)
A102: Value of sales | G102: =SUM(F96:F100)
A104: Hides | B104: Inherited stock | C104: End-period stock | D104: Stockbuilding | F104: Sales in (£) | G104: Value of production (£) at sales prices
A105: Ox hides | B105: =IFERROR(INDEX(Stock!$A$3:$T$92,MATCH('Crawley Overview'!$A105,Stock!$A$3:$A$92,0),MATCH('Crawley Overview'!B$65,Stock!$A$3:$T$3,0)),0) | C105: =IFERROR(INDEX(Stock!$A$3:$T$92,MATCH('Crawley Overview'!$A105,Stock!$A$3:$A$92,0),MATCH('Crawley Overview'!C$65,Stock!$A$3:$T$3,0)),0) | D105: =C105-B105 | F105: =IFERROR(INDEX(Stock!$A$3:$T$92,MATCH('Crawley Overview'!$A105,Stock!$A$3:$A$92,0),MATCH('Crawley Overview'!F$65,Stock!$A$3:$T$3,0)),0) | G105: =IFERROR(INDEX(Stock!$A$3:$T$92,MATCH('Crawley Overview'!$A105,Stock!$A$3:$A$92,0),MATCH('Crawley Overview'!G$65,Stock!$A$3:$T$3,0)),0)
A106: Cow hides | B106: =IFERROR(INDEX(Stock!$A$3:$T$92,MATCH('Crawley Overview'!$A106,Stock!$A$3:$A$92,0),MATCH('Crawley Overview'!B$65,Stock!$A$3:$T$3,0)),0) | C106: =IFERROR(INDEX(Stock!$A$3:$T$92,MATCH('Crawley Overview'!$A106,Stock!$A$3:$A$92,0),MATCH('Crawley Overview'!C$65,Stock!$A$3:$T$3,0)),0) | D106: =C106-B106 | F106: =IFERROR(INDEX(Stock!$A$3:$T$92,MATCH('Crawley Overview'!$A106,Stock!$A$3:$A$92,0),MATCH('Crawley Overview'!F$65,Stock!$A$3:$T$3,0)),0) | G106: =IFERROR(INDEX(Stock!$A$3:$T$92,MATCH('Crawley Overview'!$A106,Stock!$A$3:$A$92,0),MATCH('Crawley Overview'!G$65,Stock!$A$3:$T$3,0)),0)
A107: Mare hides | B107: =IFERROR(INDEX(Stock!$A$3:$T$92,MATCH('Crawley Overview'!$A107,Stock!$A$3:$A$92,0),MATCH('Crawley Overview'!B$65,Stock!$A$3:$T$3,0)),0) | C107: =IFERROR(INDEX(Stock!$A$3:$T$92,MATCH('Crawley Overview'!$A107,Stock!$A$3:$A$92,0),MATCH('Crawley Overview'!C$65,Stock!$A$3:$T$3,0)),0) | D107: =C107-B107 | F107: =IFERROR(INDEX(Stock!$A$3:$T$92,MATCH('Crawley Overview'!$A107,Stock!$A$3:$A$92,0),MATCH('Crawley Overview'!F$65,Stock!$A$3:$T$3,0)),0) | G107: =IFERROR(INDEX(Stock!$A$3:$T$92,MATCH('Crawley Overview'!$A107,Stock!$A$3:$A$92,0),MATCH('Crawley Overview'!G$65,Stock!$A$3:$T$3,0)),0)
A108: Steer hides | B108: =IFERROR(INDEX(Stock!$A$3:$T$92,MATCH('Crawley Overview'!$A108,Stock!$A$3:$A$92,0),MATCH('Crawley Overview'!B$65,Stock!$A$3:$T$3,0)),0) | C108: =IFERROR(INDEX(Stock!$A$3:$T$92,MATCH('Crawley Overview'!$A108,Stock!$A$3:$A$92,0),MATCH('Crawley Overview'!C$65,Stock!$A$3:$T$3,0)),0) | D108: =C108-B108 | F108: =IFERROR(INDEX(Stock!$A$3:$T$92,MATCH('Crawley Overview'!$A108,Stock!$A$3:$A$92,0),MATCH('Crawley Overview'!F$65,Stock!$A$3:$T$3,0)),0) | G108: =IFERROR(INDEX(Stock!$A$3:$T$92,MATCH('Crawley Overview'!$A108,Stock!$A$3:$A$92,0),MATCH('Crawley Overview'!G$65,Stock!$A$3:$T$3,0)),0)
A109: Yearling Calf hides | B109: =IFERROR(INDEX(Stock!$A$3:$T$92,MATCH('Crawley Overview'!$A109,Stock!$A$3:$A$92,0),MATCH('Crawley Overview'!B$65,Stock!$A$3:$T$3,0)),0) | C109: =IFERROR(INDEX(Stock!$A$3:$T$92,MATCH('Crawley Overview'!$A109,Stock!$A$3:$A$92,0),MATCH('Crawley Overview'!C$65,Stock!$A$3:$T$3,0)),0) | D109: =C109-B109 | F109: =IFERROR(INDEX(Stock!$A$3:$T$92,MATCH('Crawley Overview'!$A109,Stock!$A$3:$A$92,0),MATCH('Crawley Overview'!F$65,Stock!$A$3:$T$3,0)),0) | G109: =IFERROR(INDEX(Stock!$A$3:$T$92,MATCH('Crawley Overview'!$A109,Stock!$A$3:$A$92,0),MATCH('Crawley Overview'!G$65,Stock!$A$3:$T$3,0)),0)
A110: Calf hides | B110: =IFERROR(INDEX(Stock!$A$3:$T$92,MATCH('Crawley Overview'!$A110,Stock!$A$3:$A$92,0),MATCH('Crawley Overview'!B$65,Stock!$A$3:$T$3,0)),0) | C110: =IFERROR(INDEX(Stock!$A$3:$T$92,MATCH('Crawley Overview'!$A110,Stock!$A$3:$A$92,0),MATCH('Crawley Overview'!C$65,Stock!$A$3:$T$3,0)),0) | D110: =C110-B110 | F110: =IFERROR(INDEX(Stock!$A$3:$T$92,MATCH('Crawley Overview'!$A110,Stock!$A$3:$A$92,0),MATCH('Crawley Overview'!F$65,Stock!$A$3:$T$3,0)),0) | G110: =IFERROR(INDEX(Stock!$A$3:$T$92,MATCH('Crawley Overview'!$A110,Stock!$A$3:$A$92,0),MATCH('Crawley Overview'!G$65,Stock!$A$3:$T$3,0)),0)
A111: Pig hides | B111: =IFERROR(INDEX(Stock!$A$3:$T$92,MATCH('Crawley Overview'!$A111,Stock!$A$3:$A$92,0),MATCH('Crawley Overview'!B$65,Stock!$A$3:$T$3,0)),0) | C111: =IFERROR(INDEX(Stock!$A$3:$T$92,MATCH('Crawley Overview'!$A111,Stock!$A$3:$A$92,0),MATCH('Crawley Overview'!C$65,Stock!$A$3:$T$3,0)),0) | D111: =C111-B111 | F111: =IFERROR(INDEX(Stock!$A$3:$T$92,MATCH('Crawley Overview'!$A111,Stock!$A$3:$A$92,0),MATCH('Crawley Overview'!F$65,Stock!$A$3:$T$3,0)),0) | G111: =IFERROR(INDEX(Stock!$A$3:$T$92,MATCH('Crawley Overview'!$A111,Stock!$A$3:$A$92,0),MATCH('Crawley Overview'!G$65,Stock!$A$3:$T$3,0)),0)
A112: Weather woolskins | B112: =IFERROR(INDEX(Stock!$A$3:$T$92,MATCH('Crawley Overview'!$A112,Stock!$A$3:$A$92,0),MATCH('Crawley Overview'!B$65,Stock!$A$3:$T$3,0)),0) | C112: =IFERROR(INDEX(Stock!$A$3:$T$92,MATCH('Crawley Overview'!$A112,Stock!$A$3:$A$92,0),MATCH('Crawley Overview'!C$65,Stock!$A$3:$T$3,0)),0) | D112: =C112-B112 | F112: =IFERROR(INDEX(Stock!$A$3:$T$92,MATCH('Crawley Overview'!$A112,Stock!$A$3:$A$92,0),MATCH('Crawley Overview'!F$65,Stock!$A$3:$T$3,0)),0) | G112: =IFERROR(INDEX(Stock!$A$3:$T$92,MATCH('Crawley Overview'!$A112,Stock!$A$3:$A$92,0),MATCH('Crawley Overview'!G$65,Stock!$A$3:$T$3,0)),0)
A113: Ram woolskins | B113: =IFERROR(INDEX(Stock!$A$3:$T$92,MATCH('Crawley Overview'!$A113,Stock!$A$3:$A$92,0),MATCH('Crawley Overview'!B$65,Stock!$A$3:$T$3,0)),0) | C113: =IFERROR(INDEX(Stock!$A$3:$T$92,MATCH('Crawley Overview'!$A113,Stock!$A$3:$A$92,0),MATCH('Crawley Overview'!C$65,Stock!$A$3:$T$3,0)),0) | D113: =C113-B113 | F113: =IFERROR(INDEX(Stock!$A$3:$T$92,MATCH('Crawley Overview'!$A113,Stock!$A$3:$A$92,0),MATCH('Crawley Overview'!F$65,Stock!$A$3:$T$3,0)),0) | G113: =IFERROR(INDEX(Stock!$A$3:$T$92,MATCH('Crawley Overview'!$A113,Stock!$A$3:$A$92,0),MATCH('Crawley Overview'!G$65,Stock!$A$3:$T$3,0)),0)
A114: Ewe woolskins | B114: =IFERROR(INDEX(Stock!$A$3:$T$92,MATCH('Crawley Overview'!$A114,Stock!$A$3:$A$92,0),MATCH('Crawley Overview'!B$65,Stock!$A$3:$T$3,0)),0) | C114: =IFERROR(INDEX(Stock!$A$3:$T$92,MATCH('Crawley Overview'!$A114,Stock!$A$3:$A$92,0),MATCH('Crawley Overview'!C$65,Stock!$A$3:$T$3,0)),0) | D114: =C114-B114 | F114: =IFERROR(INDEX(Stock!$A$3:$T$92,MATCH('Crawley Overview'!$A114,Stock!$A$3:$A$92,0),MATCH('Crawley Overview'!F$65,Stock!$A$3:$T$3,0)),0) | G114: =IFERROR(INDEX(Stock!$A$3:$T$92,MATCH('Crawley Overview'!$A114,Stock!$A$3:$A$92,0),MATCH('Crawley Overview'!G$65,Stock!$A$3:$T$3,0)),0)
A115: Hogg woolskins | B115: =IFERROR(INDEX(Stock!$A$3:$T$92,MATCH('Crawley Overview'!$A115,Stock!$A$3:$A$92,0),MATCH('Crawley Overview'!B$65,Stock!$A$3:$T$3,0)),0) | C115: =IFERROR(INDEX(Stock!$A$3:$T$92,MATCH('Crawley Overview'!$A115,Stock!$A$3:$A$92,0),MATCH('Crawley Overview'!C$65,Stock!$A$3:$T$3,0)),0) | D115: =C115-B115 | F115: =IFERROR(INDEX(Stock!$A$3:$T$92,MATCH('Crawley Overview'!$A115,Stock!$A$3:$A$92,0),MATCH('Crawley Overview'!F$65,Stock!$A$3:$T$3,0)),0) | G115: =IFERROR(INDEX(Stock!$A$3:$T$92,MATCH('Crawley Overview'!$A115,Stock!$A$3:$A$92,0),MATCH('Crawley Overview'!G$65,Stock!$A$3:$T$3,0)),0)
A116: Woolskins (total) | B116: =IFERROR(INDEX(Stock!$A$3:$T$92,MATCH('Crawley Overview'!$A116,Stock!$A$3:$A$92,0),MATCH('Crawley Overview'!B$65,Stock!$A$3:$T$3,0)),0) | C116: =IFERROR(INDEX(Stock!$A$3:$T$92,MATCH('Crawley Overview'!$A116,Stock!$A$3:$A$92,0),MATCH('Crawley Overview'!C$65,Stock!$A$3:$T$3,0)),0) | D116: =C116-B116 | F116: =IFERROR(INDEX(Stock!$A$3:$T$92,MATCH('Crawley Overview'!$A116,Stock!$A$3:$A$92,0),MATCH('Crawley Overview'!F$65,Stock!$A$3:$T$3,0)),0) | G116: =IFERROR(INDEX(Stock!$A$3:$T$92,MATCH('Crawley Overview'!$A116,Stock!$A$3:$A$92,0),MATCH('Crawley Overview'!G$65,Stock!$A$3:$T$3,0)),0)
... A124: Shorn skins | B124: =IFERROR(INDEX(Stock!$A$3:$T$92,MATCH('Crawley Overview'!$A124,Stock!$A$3:$A$92,0),MATCH('Crawley Overview'!B$65,Stock!$A$3:$T$3,0)),0) | C124: =IFERROR(INDEX(Stock!$A$3:$T$92,MATCH('Crawley Overview'!$A124,Stock!$A$3:$A$92,0),MATCH('Crawley Overview'!C$65,Stock!$A$3:$T$3,0)),0) | D124: =C124-B124 | F124: =IFERROR(INDEX(Stock!$A$3:$T$92,MATCH('Crawley Overview'!$A124,Stock!$A$3:$A$92,0),MATCH('Crawley Overview'!F$65,Stock!$A$3:$T$3,0)),0) | G124: =IFERROR(INDEX(Stock!$A$3:$T$92,MATCH('Crawley Overview'!$A124,Stock!$A$3:$A$92,0),MATCH('Crawley Overview'!G$65,Stock!$A$3:$T$3,0)),0)
A125: Total value of production (sum of the above) | G125: =SUM(G105:G124)
A126: Value of sales | G126: =SUM(F105:F124)
A128: Poultry stock | B128: Inherited stock | C128: End-period stock | D128: Stockbuilding | F128: Sales in (£) | G128: Value of production (£) at sales prices
A129: Hens | B129: =IFERROR(INDEX(Stock!$A$3:$T$92,MATCH('Crawley Overview'!$A129,Stock!$A$3:$A$92,0),MATCH('Crawley Overview'!B$65,Stock!$A$3:$T$3,0)),0) | C129: =IFERROR(INDEX(Stock!$A$3:$T$92,MATCH('Crawley Overview'!$A129,Stock!$A$3:$A$92,0),MATCH('Crawley Overview'!C$65,Stock!$A$3:$T$3,0)),0) | D129: =C129-B129 | F129: =IFERROR(INDEX(Stock!$A$3:$T$92,MATCH('Crawley Overview'!$A129,Stock!$A$3:$A$92,0),MATCH('Crawley Overview'!F$65,Stock!$A$3:$T$3,0)),0) | G129: =IFERROR(INDEX(Stock!$A$3:$T$92,MATCH('Crawley Overview'!$A129,Stock!$A$3:$A$92,0),MATCH('Crawley Overview'!G$65,Stock!$A$3:$T$3,0)),0)
A130: Geese | B130: =IFERROR(INDEX(Stock!$A$3:$T$92,MATCH('Crawley Overview'!$A130,Stock!$A$3:$A$92,0),MATCH('Crawley Overview'!B$65,Stock!$A$3:$T$3,0)),0) | C130: =IFERROR(INDEX(Stock!$A$3:$T$92,MATCH('Crawley Overview'!$A130,Stock!$A$3:$A$92,0),MATCH('Crawley Overview'!C$65,Stock!$A$3:$T$3,0)),0) | D130: =C130-B130 | F130: =IFERROR(INDEX(Stock!$A$3:$T$92,MATCH('Crawley Overview'!$A130,Stock!$A$3:$A$92,0),MATCH('Crawley Overview'!F$65,Stock!$A$3:$T$3,0)),0) | G130: =IFERROR(INDEX(Stock!$A$3:$T$92,MATCH('Crawley Overview'!$A130,Stock!$A$3:$A$92,0),MATCH('Crawley Overview'!G$65,Stock!$A$3:$T$3,0)),0)
A131: Capons (from chickens) | B131: =IFERROR(INDEX(Stock!$A$3:$T$92,MATCH('Crawley Overview'!$A131,Stock!$A$3:$A$92,0),MATCH('Crawley Overview'!B$65,Stock!$A$3:$T$3,0)),0) | C131: =IFERROR(INDEX(Stock!$A$3:$T$92,MATCH('Crawley Overview'!$A131,Stock!$A$3:$A$92,0),MATCH('Crawley Overview'!C$65,Stock!$A$3:$T$3,0)),0) | D131: =C131-B131 | F131: =IFERROR(INDEX(Stock!$A$3:$T$92,MATCH('Crawley Overview'!$A131,Stock!$A$3:$A$92,0),MATCH('Crawley Overview'!F$65,Stock!$A$3:$T$3,0)),0) | G131: =IFERROR(INDEX(Stock!$A$3:$T$92,MATCH('Crawley Overview'!$A131,Stock!$A$3:$A$92,0),MATCH('Crawley Overview'!G$65,Stock!$A$3:$T$3,0)),0)
A132: Cocks & hens | B132: =IFERROR(INDEX(Stock!$A$3:$T$92,MATCH('Crawley Overview'!$A132,Stock!$A$3:$A$92,0),MATCH('Crawley Overview'!B$65,Stock!$A$3:$T$3,0)),0) | C132: =IFERROR(INDEX(Stock!$A$3:$T$92,MATCH('Crawley Overview'!$A132,Stock!$A$3:$A$92,0),MATCH('Crawley Overview'!C$65,Stock!$A$3:$T$3,0)),0) | D132: =C132-B132 | F132: =IFERROR(INDEX(Stock!$A$3:$T$92,MATCH('Crawley Overview'!$A132,Stock!$A$3:$A$92,0),MATCH('Crawley Overview'!F$65,Stock!$A$3:$T$3,0)),0) | G132: =IFERROR(INDEX(Stock!$A$3:$T$92,MATCH('Crawley Overview'!$A132,Stock!$A$3:$A$92,0),MATCH('Crawley Overview'!G$65,Stock!$A$3:$T$3,0)),0)
...

Sheet Crawley Receipts
A1: CRAWLEY RECEIPTS
B2: £ | C2: s | D2: d | F2: Total in £ | G2: Error | H2: Notes
A4: Arrears
A5: Arrears total | B5: 7 | C5: 8 | D5: 8 | F5: =B5+C5/20+D5/240
A6: of which delivered to treasurer of Wolvesey | B6: 7 | C6: 8 | D6: 8 | F6: =B6+C6/20+D6/240
A8: Rents of assize
A9: Christmas | B9: 3 | C9: 1 | D9: 4 | F9: =B9+C9/20+D9/240
A10: Easter | B10: 3 | C10: 1 | D10: 4 | F10: =B10+C10/20+D10/240
A11: John the Baptist | B11: 3 | C11: 1 | D11: 4 | F11: =B11+C11/20+D11/240
A12: Michaelmas | B12: 4 | C12: 17 | D12: 7 | F12: =B12+C12/20+D12/240
A13: Total recorded in accounts | B13: 14 | C13: 1 | D13: 7 | F13: =B13+C13/20+D13/240
A14: Rents of assize total | B14: =SUM(B9:B12) | C14: =SUM(C9:C12) | D14: =SUM(D9:D12) | F14: =B14+C14/20+D14/240 | G14: =F14-F13
A16: Quittances
A17: 1 reeve for the year | C17: 5 | F17: =B17+C17/20+D17/240
A18: 6 ploughmen 1 smith for the year | C18: 18 | D18: 8 | F18: =B18+C18/20+D18/240
A19: 2 shepherds for the year | C19: 5 | D19: 4 | F19: =B19+C19/20+D19/240
A20: 8 workers | B20: 1 | C20: 1 | D20: 4 | F20: =B20+C20/20+D20/240
A21: 1 swineherd and 1 cowherd | C21: 5 | D21: 4 | F21: =B21+C21/20+D21/240
A22: Total recorded in accounts | B22: 2 | C22: 15 | D22: 8 | F22: =B22+C22/20+D22/240
A23: Quittances total | B23: =SUM(B17:B21) | C23: =SUM(C17:C21) | D23: =SUM(D17:D21) | F23: =B23+C23/20+D23/240 | G23: =F23-F22
A25: Defaults of rent
A26: in default of le stronge into demesne | C26: 2 | F26: =B26+C26/20+D26/240
A27: land of william | C27: 2 | D27: 8 | F27: =B27+C27/20+D27/240
A28: land of Alebrok | C28: 5 | F28: =B28+C28/20+D28/240
A29: land of Robert | C29: 2 | D29: 8 | F29: =B29+C29/20+D29/240
A30: land of Robert Coye | C30: 2 | D30: 8 | F30: =B30+C30/20+D30/240
A31: land of Roger le Pokyr | C31: 2 | D31: 8 | F31: =B31+C31/20+D31/240
A32: land of Richard Vaccar | C32: 2 | D32: 8 | F32: =B32+C32/20+D32/240
A33: Total recorded in accounts | B33: 1 | D33: 4 | F33: =B33+C33/20+D33/240
A34: Defaults of rent total | B34: =SUM(B26:B32) | C34: =SUM(C26:C32) | D34: =SUM(D26:D32) | F34: =B34+C34/20+D34/240 | G34: =F34-F33
A36: Total of rents remaining | B36: 10 | C36: 5 | D36: 7 | F36: =B36+C36/20+D36/240 | H36: not included in receipts
A38: Annual recognizances
A39: from Walter | D39: 6 | F39: =B39+C39/20+D39/240
A40: from Robert | D40: 6 | F40: =B40+C40/20+D40/240
A41: from Robert le Pottere | D41: 6 | F41: =B41+C41/20+D41/240
A42: from John | D42: 3 | F42: =B42+C42/20+D42/240
A43: Total recorded in accounts | C43: 1 | D43: 9 | F43: =B43+C43/20+D43/240
A44: Annual recognizances total | B44: =SUM(B39:B42) | C44: =SUM(C39:C42) | D44: =SUM(D39:D42) | F44: =B44+C44/20+D44/240 | G44: =F44-F43
A46: Issues of the manor
A47: panage of pigs | C47: 6 | D47: 2.5 | F47: =B47+C47/20+D47/240
A48: panage of 77 cows, 8 steers, 21 bullocks and 16 calves | B48: 2 | C48: 5 | D48: 4 | F48: =B48+C48/20+D48/240
A49: for 97 more of the mens sheep than the 25 maintained at the fold | C49: 2 | D49: 8 | F49: =B49+C49/20+D49/240
A50: from pasturage of 44 lambs sold | D50: 11 | F50: =B50+C50/20+D50/240
A51: from the pasturage of Trendly sold | C51: 8 | F51: =B51+C51/20+D51/240
A52: from pasturage of Lokfurlang sold | C52: 1 | D52: 6 | F52: =B52+C52/20+D52/240
A53: from the pasturage of Shret sold | C53: 1 | D53: 4 | F53: =B53+C53/20+D53/240
A54: from 5 feeble late born calves | C54: 5 | F54: =B54+C54/20+D54/240
A55: from 47 wethers | B55: 2 | C55: 14 | D55: 10 | F55: =B55+C55/20+D55/240
A56: from 55 ewes sold | B56: 2 | C56: 5 | D56: 10 | F56: =B56+C56/20+D56/240
A57: from 26 pigs sold | B57: 3 | C57: 7 | D57: 4 | F57: =B57+C57/20+D57/240
A58: from the hide sold of 1 plough-horse in murrain | D58: 11 | F58: =B58+C58/20+D58/240
A59: from the hides sold of 2 oxen dead from murrain | C59: 4 | D59: 6.5 | F59: =B59+C59/20+D59/240
A60: from the hide and flesh sold of 1 steer in murrain | C60: 2 | D60: 8 | F60: =B60+C60/20+D60/240
A61: from the hide sold of 1 bullock in murrain | D61: 6 | F61: =B61+C61/20+D61/240
A62: fro the hide sold of 1 yearling in murrain | D62: 1.5 | F62: =B62+C62/20+D62/240
A63: from the hide sold of 1 calf in murrain | D63: 1 | F63: =B63+C63/20+D63/240
A64: from the skins sold of 21 wethers, 24 ewes, and 23 hoggs in murrain before shearing | C64: 18 | D64: 10 | F64: =B64+C64/20+D64/240
A65: from the skins sold of 14 wethers and 13 ewes in murrain after shearing | C65: 4 | D65: 6 | F65: =B65+C65/20+D65/240
A66: from skins sold of 62 lambs in murrain before weaning | C66: 5 | D66: 2 | F66: =B66+C66/20+D66/240
A67: from the skins sold of 20 rotted sheep in murrain | D67: 10 | F67: =B67+C67/20+D67/240
A68: from 5 cloves 1 lb of winter cheese sold | C68: 1 | D68: 6 | F68: =B68+C68/20+D68/240
A69: from 7.5 weys 12 cloves of summer cheese sold | B69: 3 | C69: 6 | D69: 1 | F69: =B69+C69/20+D69/240
A70: from 15 cloves 5 lb of butter sold | C70: 4 | D70: 8 | F70: =B70+C70/20+D70/240
A71: from 95 hens at churchscot sold | C71: 7 | D71: 11 | F71: =B71+C71/20+D71/240
A72: from richard for release from the labour service | C72: 2 | F72: =B72+C72/20+D72/240
A73: from a curtilage which was hired to roger | C73: 1 | F73: =B73+C73/20+D73/240
A74: from 23 acres of the lords land hired now accounted for in defaults of rent above | C74: 12 | F74: =B74+C74/20+D74/240 | H74: Accounted for in defaults of rent already?
A75: from curtilage which belongs to Robert Couch | C75: 2 | F75: =B75+C75/20+D75/240
A76: from 5 cloves of wool locks sold | C76: 4 | D76: 4.5 | F76: =B76+C76/20+D76/240
A77: from dairy produce sold at the audit | B77: 1 | D77: 3 | F77: =B77+C77/20+D77/240
A78: Total recorded in accounts | B78: 19 | C78: 19 | F78: =B78+C78/20+D78/240
A79: Issues of the manor total | B79: =SUM(B47:B77) | C79: =SUM(C47:C77) | D79: =SUM(D47:D77) | F79: =B79+C79/20+D79/240 | G79: =F79-F78
A81: Sale of corn
A82: from 40 qrs of wheat sold | B82: 11 | C82: 18 | D82: 2 | F82: =B82+C82/20+D82/240
A83: from 12 wrs 0.5 bus of curall sold | B83: 2 | C83: 5 | D83: 6.5 | F83: =B83+C83/20+D83/240
A84: from 21 qrs 6 bus of barley sold | B84: 4 | C84: 7 | D84: 11 | F84: =B84+C84/20+D84/240
A85: from 43 qrs of oats sold | B85: 4 | C85: 7 | D85: 8 | F85: =B85+C85/20+D85/240
A86: from 3 qrs 1 bus of peas sold | C86: 9 | D86: 4.5 | F86: =B86+C86/20+D86/240
A87: from 4.5 qrs of vetches sold | C87: 9 | F87: =B87+C87/20+D87/240
A88: from 4 bus of barley sold at the audit | C88: 2 | F88: =B88+C88/20+D88/240
A89: Total recorded in accounts | B89: 23 | C89: 19 | D89: 8 | F89: =B89+C89/20+D89/240
A90: Sale of corn total | B90: =SUM(B82:B88) | C90: =SUM(C82:C88) | D90: =SUM(D82:D88) | F90: =B90+C90/20+D90/240 | G90: =F90-F89
A92: Entry and marriage fines
A93: from tithing of tithingpenny at martinmas | C93: 6 | D93: 8 | F93: =B93+C93/20+D93/240
A94: from the same at hockday | C94: 6 | D94: 8 | F94: =B94+C94/20+D94/240
A95: from Matilda for marrying her daughter outside | C95: 2 | F95: =B95+C95/20+D95/240
A96: from Stephen for marrying his daughter outside | C96: 2 | F96: =B96+C96/20+D96/240
A97: Total recorded in accounts | C97: 17 | D97: 4 | F97: =B97+C97/20+D97/240
A98: Entry and marriage fines total | B98: =SUM(B93:B96) | C98: =SUM(C93:C96) | D98: =SUM(D93:D96) | F98: =B98+C98/20+D98/240 | G98: =F98-F97
A100: Pleas and perquisites
A101: from tithing of Crawley for concealment | C101: 2 | F101: =B101+C101/20+D101/240
A102: from the tithing of Crawley for not producing in court | C102: 2 | F102: =B102+C102/20+D102/240
A103: from various transgressions of various men in various courts | C103: 15 | D103: 11 | F103: =B103+C103/20+D103/240
A104: Total recorded in accounts | C104: 19 | D104: 11 | F104: =B104+C104/20+D104/240
A105: Pleas & perquisites total | B105: =SUM(B101:B103) | C105: =SUM(C101:C103) | D105: =SUM(D101:D103) | F105: =B105+C105/20+D105/240
A107: Total of all receipts (sum of above excl. arrears) | B107: =SUM(B105,B98,B90,B79,B44,B34,B23,B14) | C107: =SUM(C105,C98,C90,C79,C44,C34,C23,C14) | D107: =SUM(D105,D98,D90,D79,D44,D34,D23,D14) | F107: =B107+C107/20+D107/240
A108: Total of all receipts (sum of above incl. arrears) | B108: =SUM(B105,B98,B90,B79,B44,B34,B23,B14,B5) | C108: =SUM(C105,C98,C90,C79,C44,C34,C23,C14,C5) | D108: =SUM(D105,D98,D90,D79,D44,D34,D23,D14,D5) | F108: =B108+C108/20+D108/240
A109: Total of all receipts in account excl. arrears | F109: =B109+C109/20+D109/240 | G109: =F109-F107
A110: Total of all receipts in account incl. arrears | B110: 56 | C110: 3 | D110: 3 | F110: =B110+C110/20+D110/240 | G110: =F110-F108

Sheet Crawley Expenses
A1: CRAWLEY EXPENSES
B2: £ | C2: s | D2: d | F2: Total in £ | G2: Error | H2: Notes
A3: Cost of Ploughs
A4: in iron and steel bought for 4 ploughs | C4: 9 | F4: =B4+C4/20+D4/240
A5: in 2 ploughshares bought | C5: 1 | D5: 8 | F5: =B5+C5/20+D5/240
A6: in 1 coulter mended | D6: 2 | F6: =B6+C6/20+D6/240
A7: in 2 plough feet bought | D7: 7.5 | F7: =B7+C7/20+D7/240
A8: in 4 pairs of wheels bought | C8: 1 | D8: 4 | F8: =B8+C8/20+D8/240
A9: in 2 ploughs made anew and other mending | C9: 1 | D9: 3 | F9: =B9+C9/20+D9/240
A10: in fitting ploughs with iron tyres | D10: 2.5 | F10: =B10+C10/20+D10/240
A11: in shoeing 6 plough-horses | C11: 3 | D11: 11 | F11: =B11+C11/20+D11/240
A12: in boon-works of 9 ploughmen | D12: 9 | F12: =B12+C12/20+D12/240
A13: in 5 halters made from the horeses own hair | D13: 1.75 | F13: =B13+C13/20+D13/240
A14: in stipend of 2 ploughmen for the year | C14: 6 | F14: =B14+C14/20+D14/240
A15: in 5 oxen bought | B15: 2 | C15: 6 | F15: =B15+C15/20+D15/240
A16: Total recorded in accounts | B16: 3 | C16: 11 | D16: 0.25 | F16: =B16+C16/20+D16/240
A17: Cost of ploughs total | B17: =SUM(B4:B15) | C17: =SUM(C4:C15) | D17: =SUM(D4:D15) | F17: =B17+C17/20+D17/240 | G17: =F17-F16
A18: Total capital expenses | B18: =SUM(B15,B13,B4:B11) | C18: =SUM(C15,C13,C4:C11) | D18: =SUM(D15,D13,D4:D11) | F18: =B18+C18/20+D18/240
A20: Purchase of Corn
A21: in 6 bus of wheat bought for sowing | C21: 4 | D21: 6 | F21: =B21+C21/20+D21/240
A22: in 3 qrs 6 bus of barley bought | C22: 12 | D22: 4 | F22: =B22+C22/20+D22/240
A23: Total recorded in accounts | C23: 16 | D23: 10 | F23: =B23+C23/20+D23/240
A24: Purchase of corn total | B24: =SUM(B21:B22) | C24: =SUM(C21:C22) | D24: =SUM(D21:D22) | F24: =B24+C24/20+D24/240 | G24: =F24-F23
A26: Cost of Carts and Wagons
A27: in 1 pair of wheels bought | C27: 3 | D27: 4 | F27: =B27+C27/20+D27/240
A28: in 1 old binding renewed and fitted | C28: 3 | F28: =B28+C28/20+D28/240
A29: in fitting the cart with axles | D29: 8 | F29: =B29+C29/20+D29/240
A30: in clouts nails and grease bought for the same | C30: 1 | F30: =B30+C30/20+D30/240
A31: in 1 pair of traces bought | D31: 5.5 | F31: =B31+C31/20+D31/240
A32: in 1 rope bought | D32: 2 | F32: =B32+C32/20+D32/240
A33: in shoeing 2 cart horses | C33: 2 | D33: 6 | F33: =B33+C33/20+D33/240
A34: in white leather bought | D34: 4 | F34: =B34+C34/20+D34/240
A35: in mending old harnesses | D35: 2 | F35: =B35+C35/20+D35/240
A36: in 1 collar bought | D36: 7 | F36: =B36+C36/20+D36/240
A37: in stipend of 1 carter | C37: 3 | F37: =B37+C37/20+D37/240
A38: in mending the cart at various times | D38: 2 | F38: =B38+C38/20+D38/240
A39: in 1 new cart-body bought | C39: 1 | F39: =B39+C39/20+D39/240
A40: Total recorded in accounts | C40: 16 | D40: 4.5 | F40: =B40+C40/20+D40/240
A41: Cost of carts and wagons total | B41: =SUM(B27:B39) | C41: =SUM(C27:C39) | D41: =SUM(D27:D39) | F41: =B41+C41/20+D41/240 | G41: =F41-F40
A42: Total capital expenses | B42: =SUM(B38:B39,B27:B36) | C42: =SUM(C38:C39,C27:C36) | D42: =SUM(D38:D39,D27:D36) | F42: =B42+C42/20+D42/240
A44: Cost of Dairy
A45: in woollen and linen cloth bought | D45: 6 | F45: =B45+C45/20+D45/240
A46: in 6 bus of salt bought | C46: 1 | D46: 11 | F46: =B46+C46/20+D46/240
A47: in a press bought | D47: 4.5 | F47: =B47+C47/20+D47/240
A48: in earthenware pots and pans bought | D48: 2.5 | F48: =B48+C48/20+D48/240
A49: in mending the utensils of the dairy | D49: 1.5 | F49: =B49+C49/20+D49/240
A50: in 1 mould bought | D50: 7.5 | F50: =B50+C50/20+D50/240
A51: in 20 ells of canvas bought for packing wool | C51: 5 | D51: 2 | F51: =B51+C51/20+D51/240
A52: in making the said sacks | D52: 4 | F52: =B52+C52/20+D52/240
A53: in packing the said wool | D53: 8 | F53: =B53+C53/20+D53/240
A54: in grease bought for greasing sheep | B54: 2 | D54: 9 | F54: =B54+C54/20+D54/240
A55: in re-roofing the ewe house | C55: 2 | D55: 6 | F55: =B55+C55/20+D55/240
A56: in collecting stubble for the same | C56: 1 | D56: 0.5 | F56: =B56+C56/20+D56/240
A57: in 40 hurdles bought for the fold | C57: 5 | F57: =B57+C57/20+D57/240
A58: in hay bought for the sheep in lent | C58: 17 | D58: 11 | F58: =B58+C58/20+D58/240
A59: in stipend of 1 dairymaid for the year | C59: 2 | F59: =B59+C59/20+D59/240
A60: in 1 tub bought for the dairy | D60: 4 | F60: =B60+C60/20+D60/240
A61: Total recorded in accounts | B61: 3 | C61: 19 | D61: 5.5 | F61: =B61+C61/20+D61/240
A62: Cost of dairy total | B62: =SUM(B45:B60) | C62: =SUM(C45:C60) | D62: =SUM(D45:D60) | F62: =B62+C62/20+D62/240 | G62: =F62-F61
A63: Total capital expenses | B63: =SUM(B60,B54:B58,B45:B52) | C63: =SUM(C60,C54:C58,C45:C52) | D63: =SUM(D60,D54:D58,D45:D52) | F63: =B63+C63/20+D63/240
A65: Cost of Buildings
A66: in wattling and reroofing the old barn | C66: 2 | D66: 9 | F66: =B66+C66/20+D66/240
A67: in plastering and mending the walls | D67: 10 | F67: =B67+C67/20+D67/240
A68: in recovering the stack of vetches | C68: 1 | D68: 3 | F68: =B68+C68/20+D68/240
A69: in mending 1 cooking pot and 1 pan | D69: 1.25 | F69: =B69+C69/20+D69/240
A70: in wattling and re-roofing the wheat barn | D70: 9 | F70: =B70+C70/20+D70/240
A71: in 1 bushel measure bought | D71: 5 | F71: =B71+C71/20+D71/240
A72: in castrating piglets | D72: 4 | F72: =B72+C72/20+D72/240
A73: Total recorded in accounts | C73: 6 | D73: 5.25 | F73: =B73+C73/20+D73/240
A74: Cost of buildings total | B74: =SUM(B66:B72) | C74: =SUM(C66:C72) | D74: =SUM(D66:D72) | F74: =B74+C74/20+D74/240 | G74: =F74-F73
A75: Total capital expenses | B75: =SUM(B66:B71) | C75: =SUM(C66:C71) | D75: =SUM(D66:D71) | F75: =B75+C75/20+D75/240
A77: Threshing
A78: in threshing and winnowing 40 qrs of wheat | C78: 6 | D78: 8 | F78: =B78+C78/20+D78/240
A79: in threshing and winnowing 45 qrs of barley | C79: 5 | D79: 7.5 | F79: =B79+C79/20+D79/240
A80: in threshing and winnowing 60 qrs of oats | C80: 4 | F80: =B80+C80/20+D80/240
A81: in wages of William Kryre for carrying out issue of the grange | C81: 3 | D81: 1.5 | F81: =B81+C81/20+D81/240
A82: in stipend of the same | C82: 1 | F82: =B82+C82/20+D82/240
A83: Total recorded in accounts | B83: 1 | D83: 5 | F83: =B83+C83/20+D83/240
A84: Threshing total | B84: =SUM(B78:B82) | C84: =SUM(C78:C82) | D84: =SUM(D78:D82) | F84: =B84+C84/20+D84/240 | G84: =F84-F83
A86: Expenses of the Harvest | H86: Have included provision of household servants at harvest time as expenses of harvest time although separate in accounts
A87: in weeding corn | C87: 4 | D87: 6 | F87: =B87+C87/20+D87/240
A88: in 1000 herrings bought for 3 boonworks of 300 men | C88: 6 | D88: 4 | F88: =B88+C88/20+D88/240
A89: in provisioning group that helped with harvest | B89: 1 | F89: =B89+C89/20+D89/240
A90: in stipend of 1 man keeping the corn in the fields | C90: 3 | F90: =B90+C90/20+D90/240
A91: Total recorded in accounts | B91: 1 | C91: 13 | D91: 10 | F91: =B91+C91/20+D91/240
A92: Expenses of the harvest total | B92: =SUM(B87:B90) | C92: =SUM(C87:C90) | D92: =SUM(D87:D90) | F92: =B92+C92/20+D92/240 | G92: =F92-F91
A94: Steward's Expenses
A95: in expenses of simon clerk at martinmas | C95: 3 | D95: 3 | F95: =B95+C95/20+D95/240
A96: in expenses of simon at hockday | C96: 1 | D96: 6 | F96: =B96+C96/20+D96/240
A97: in expenses of the same for 1 visit | D97: 9.25 | F97: =B97+C97/20+D97/240
A98: in expenses of the bailiff for his visits | C98: 12 | D98: 2 | F98: =B98+C98/20+D98/240
A99: given by order of the steward and treasurer for the lord's business in the hundred of buddlesgate | C99: 6 | D99: 8 | F99: =B99+C99/20+D99/240
A100: Total recorded in accounts | B100: 1 | C100: 4 | D100: 4.25 | F100: =B100+C100/20+D100/240
A101: Steward's expenses total | B101: =SUM(B95:B99) | C101: =SUM(C95:C99) | D101: =SUM(D95:D99) | F101: =B101+C101/20+D101/240 | G101: =F101-F100
A103: Total of all Expenses | B103: 13 | C103: 8 | D103: 0.75 | F103: =B103+C103/20+D103/240
A104: Total of all Expenses (calculated) | B104: =SUM(B101,B92,B84,B74,,B62,B41,B24,B17) | C104: =SUM(C101,C92,C84,C74,,C62,C41,C24,C17) | D104: =SUM(D101,D92,D84,D74,,D62,D41,D24,D17) | F104: =B104+C104/20+D104/240 | G104: =F104-F103
A105: And thus he owes | B105: 42 | C105: 14 | D105: 6.25 | F105: =B105+C105/20+D105/240
A106: Delivered to Sir Geoffrey, treasurer of Wolvesey | B106: 27 | C106: 14 | D106: 4 | F106: =B106+C106/20+D106/240
A107: and thus he owes clear | B107: 15 | D107: 2.25 | F107: =B107+C107/20+D107/240
A108: Total capital expenses | B108: =SUM(B18,B42,B63,B75,B24) | C108: =SUM(C18,C42,C63,C75,C24) | D108: =SUM(D18,D42,D63,D75,D24) | F108: =B108+C108/20+D108/240

Sheet Issues of the Grange
B1: The issue of the grange account gives the total "yield" at the top of each heading in curly brackets, measurements used: fold, qrs, bus
B2: In "Issues of the grange" (p.xx) | G2: In "Sale of Corn" (p.x) | P2: Value of Total Production
A3: Gross output | B3: Quantity | D3: Additional bought-in | F3: Quantity | G3: Quantity noted as sold | J3: Difference Produced vs. Sold | K3: Price 1 | L3: Quantity 1 | M3: Price 2 | N3: Quantity 2 | O3: Unit price | P3: Value
B4: qrs | C4: bus | D4: qrs | E4: bus | F4: qrs | G4: qrs | H4: bus | I4: qrs | K4: £ | L4: qrs | M4: £ | N4: qrs | O4: £ per qr | P4: £
A5: Wheat | B5: 58 | C5: 6 | E5: 6 | F5: =B5+D5+C5/8+E5/8 | G5: 40 | I5: =G5+H5/8 | J5: =F5-I5 | K5: ='Crawley Receipts'!F82 | L5: 40 | O5: =IFERROR((K5+M5)/(L5+N5),0) | P5: =O5*F5
A6: Curall | B6: 12 | C6: 0.5 | F6: =B6+D6+C6/8+E6/8 | G6: 12 | H6: 0.5 | I6: =G6+H6/8 | J6: =F6-I6 | K6: ='Crawley Receipts'!F83 | L6: =I6 | O6: =IFERROR((K6+M6)/(L6+N6),0) | P6: =O6*F6
A7: Bere | B7: 4 | C7: 2 | F7: =B7+D7+C7/8+E7/8 | I7: =G7+H7/8 | J7: =F7-I7 | O7: =IFERROR((K7+M7)/(L7+N7),0) | P7: =O7*F7
A8: Barley | B8: 91 | C8: 5 | D8: 3 | E8: 6 | F8: =B8+D8+C8/8+E8/8 | G8: 21.5 | H8: 6 | I8: =G8+H8/8 | J8: =F8-I8 | K8: ='Crawley Receipts'!F84 | L8: =21+6/8 | M8: ='Crawley Receipts'!F88 | N8: 0.5 | O8: =IFERROR((K8+M8)/(L8+N8),0) | P8: =O8*F8
A9: Oats | B9: 170 | F9: =B9+D9+C9/8+E9/8 | G9: 43 | I9: =G9+H9/8 | J9: =F9-I9 | K9: ='Crawley Receipts'!F85 | L9: 43 | O9: =IFERROR((K9+M9)/(L9+N9),0) | P9: =O9*F9
A10: Peas | B10: 6.5 | F10: =B10+D10+C10/8+E10/8 | G10: 3 | H10: 1 | I10: =G10+H10/8 | J10: =F10-I10 | K10: ='Crawley Receipts'!F86 | L10: =I10 | O10: =IFERROR((K10+M10)/(L10+N10),0) | P10: =O10*F10
A11: Vetches | B11: 7 | C11: 6 | F11: =B11+D11+C11/8+E11/8 | G11: 4.5 | I11: =G11+H11/8 | J11: =F11-I11 | K11: ='Crawley Receipts'!F87 | L11: 4.5 | O11: =IFERROR((K11+M11)/(L11+N11),0) | P11: =O11*F11
A13: Total Production | F13: =SUM(F5:F11) | P13: =SUM(P5:P11) | Q13: Production value is significantly more, as much less was sold than what was produced
A14: Sales of corn (as recorded in accounts) | F14: =SUM(I5:I11) | P14: =SUM(K5:K11,M5:M11)
A17: Net output | B17: Gross output | C17: Seed | F17: tithe | G17: to manorial servants & livestock | J17: Output net of tithe & seed & liveries to manorial servants | K17: in stock from last year | L17: Price | M17: Value of net output | N17: Value of sales (in "Sale of Corn")
B18: qrs | C18: qrs | D18: bus | E18: qrs | F18: qrs | G18: qrs | H18: bus | I18: qrs | J18: qrs | K18: qrs | L18: £ per qr | M18: £ | N18: £
A19: Net wheat | B19: =F5 | C19: 16 | D19: 5 | E19: =C19+D19/8 | G19: 2 | H19: 7 | I19: =G19+H19/8 | J19: =B19-(E19+F19+I19) | L19: =O5 | M19: =L19*J19 | N19: =O5*I5
A20: Net curall | B20: =F6 | E20: =C20+D20/8 | I20: =G20+H20/8 | J20: =B20-(E20+F20+I20) | L20: =O6 | M20: =L20*J20 | N20: =O6*I6
A21: Net Bere | B21: =F7 | E21: =C21+D21/8 | G21: 4 | H21: 2 | I21: =G21+H21/8 | J21: =B21-(E21+F21+I21) | L21: =O7 | M21: =L21*J21 | N21: =O7*I7
A22: Net barley | B22: =F8 | C22: 43 | D22: 2 | E22: =C22+D22/8 | G22: =19.5+0.5+2+3+2+0.5 | H22: =6.5+6+7 | I22: =G22+H22/8 | J22: =B22-(E22+F22+I22) | L22: =O8 | M22: =L22*J22 | N22: =O8*I8
A23: Net oats | B23: =F9 | C23: 83 | D23: 3 | E23: =C23+D23/8 | G23: =6+4+12+20 | H23: =6+2+5 | I23: =G23+H23/8 | J23: =B23-(E23+F23+I23) | L23: =O9 | M23: =L23*J23 | N23: =O9*I9
A24: Net peas | B24: =F10 | C24: 3 | E24: =C24+D24/8 | H24: 3 | I24: =G24+H24/8 | J24: =B24-(E24+F24+I24) | L24: =O10 | M24: =L24*J24 | N24: =O10*I10
A25: Net vetches | B25: =F11 | C25: 3 | D25: 2 | E25: =C25+D25/8 | I25: =G25+H25/8 | J25: =B25-(E25+F25+I25) | L25: =O11 | M25: =L25*J25 | N25: =O11*I11
A26: Total | B26: =SUM(B19:B25) | E26: =SUM(E19:E25) | J26: =SUM(J19:J25) | M26: =SUM(M19:M25) | N26: =SUM(N19:N25)

Sheet Stock
A1: EAST KNOYLE STOCK ACCOUNT
A3: Livestock | B3: Inherited stock | C3: Bought | D3: Produced | E3: strays | F3: herbage | G3: sold | H3: in murrain | I3: accounted for elsewhere | J3: End-period stock | K3: cross-check | L3: price 1 | M3: units 1 | N3: price 2 | O3: units 2 | P3: Weight (weys) | Q3: Unit price (£) | R3: Value of production (£) at sales prices | S3: Sales in (£) | T3: Details
A4: Cart-horses | B4: 2 | J4: 2 | K4: =B4+C4+D4+E4-F4-G4-H4-I4 | Q4: =IFERROR((L4+N4)/(M4+O4),"") | R4: =IFERROR(D4*Q4,"") | S4: =IFERROR(Q4*G4,"")
A5: Mares | K5: =B5+C5+D5+E5-F5-G5-H5-I5 | Q5: =IFERROR((L5+N5)/(M5+O5),"") | R5: =IFERROR(D5*Q5,"") | S5: =IFERROR(Q5*G5,"")
A6: Plough horses | B6: 5 | C6: 1 | D6: 1 | H6: 1 | J6: 6 | K6: =B6+C6+D6+E6-F6-G6-H6-I6 | Q6: =IFERROR((L6+N6)/(M6+O6),"") | R6: =IFERROR(D6*Q6,"") | S6: =IFERROR(Q6*G6,"")
A7: Colts (2 years) | K7: =B7+C7+D7+E7-F7-G7-H7-I7 | Q7: =IFERROR((L7+N7)/(M7+O7),"") | R7: =IFERROR(D7*Q7,"") | S7: =IFERROR(Q7*G7,"")
A8: Colts (2 years) | K8: =B8+C8+D8+E8-F8-G8-H8-I8 | Q8: =IFERROR((L8+N8)/(M8+O8),"") | R8: =IFERROR(D8*Q8,"") | S8: =IFERROR(Q8*G8,"")
A9: Colts (1 year) | K9: =B9+C9+D9+E9-F9-G9-H9-I9 | Q9: =IFERROR((L9+N9)/(M9+O9),"") | R9: =IFERROR(D9*Q9,"") | S9: =IFERROR(Q9*G9,"")
A10: Foals | K10: =B10+C10+D10+E10-F10-G10-H10-I10 | Q10: =IFERROR((L10+N10)/(M10+O10),"") | R10: =IFERROR(D10*Q10,"") | S10: =IFERROR(Q10*G10,"")
A11: Oxen | B11: 30 | C11: 5 | D11: 1 | E11: 1 | H11: 2 | J11: 35 | K11: =B11+C11+D11+E11-F11-G11-H11-I11 | Q11: =IFERROR((L11+N11)/(M11+O11),"") | R11: =IFERROR(D11*Q11,"") | S11: =IFERROR(Q11*G11,"")
A12: Bulls | B12: 1 | J12: 1 | K12: =B12+C12+D12+E12-F12-G12-H12-I12 | Q12: =IFERROR((L12+N12)/(M12+O12),"") | R12: =IFERROR(D12*Q12,"") | S12: =IFERROR(Q12*G12,"")
A13: Cows | B13: 17 | D13: 2 | J13: 19 | K13: =B13+C13+D13+E13-F13-G13-H13-I13 | Q13: =IFERROR((L13+N13)/(M13+O13),"") | R13: =IFERROR(D13*Q13,"") | S13: =IFERROR(Q13*G13,"")
A14: Steers | B14: 4 | H14: 1 | I14: 3 | J14: 0 | K14: =B14+C14+D14+E14-F14-G14-H14-I14 | Q14: =IFERROR((L14+N14)/(M14+O14),"") | R14: =IFERROR(D14*Q14,"") | S14: =IFERROR(Q14*G14,"")
A15: Bullocks | B15: 5 | H15: 1 | J15: 4 | K15: =B15+C15+D15+E15-F15-G15-H15-I15 | Q15: =IFERROR((L15+N15)/(M15+O15),"") | R15: =IFERROR(D15*Q15,"") | S15: =IFERROR(Q15*G15,"")
A16: Yearlings | B16: 6 | H16: 1 | J16: 5 | K16: =B16+C16+D16+E16-F16-G16-H16-I16 | Q16: =IFERROR((L16+N16)/(M16+O16),"") | R16: =IFERROR(D16*Q16,"") | S16: =IFERROR(Q16*G16,"")
A17: Calves | D17: 13 | G17: 5 | H17: 1 | I17: 1 | J17: 6 | K17: =B17+C17+D17+E17-F17-G17-H17-I17 | L17: ='Crawley Receipts'!F54 | M17: 5 | Q17: =IFERROR((L17+N17)/(M17+O17),"") | R17: =IFERROR(D17*Q17,"") | S17: =IFERROR(Q17*G17,"")
A18: Wethers | B18: 383 | D18: 132 | G18: 47 | H18: 35 | J18: 433 | K18: =B18+C18+D18+E18-F18-G18-H18-I18 | L18: ='Crawley Receipts'!F55 | M18: 47 | Q18: =IFERROR((L18+N18)/(M18+O18),"") | R18: =IFERROR(D18*Q18,"") | S18: =IFERROR(Q18*G18,"")
A19: Rams | K19: =B19+C19+D19+E19-F19-G19-H19-I19 | Q19: =IFERROR((L19+N19)/(M19+O19),"") | R19: =IFERROR(D19*Q19,"") | S19: =IFERROR(Q19*G19,"")
A20: Ewes | B20: 536 | D20: 131 | G20: 55 | H20: 37 | J20: 575 | K20: =B20+C20+D20+E20-F20-G20-H20-I20 | L20: ='Crawley Receipts'!F56 | M20: 55 | Q20: =IFERROR((L20+N20)/(M20+O20),"") | R20: =IFERROR(D20*Q20,"") | S20: =IFERROR(Q20*G20,"")
A21: Hoggs | B21: 286 | H21: 23 | I21: 263 | J21: 0 | K21: =B21+C21+D21+E21-F21-G21-H21-I21 | Q21: =IFERROR((L21+N21)/(M21+O21),"") | R21: =IFERROR(D21*Q21,"") | S21: =IFERROR(Q21*G21,"")
A22: Lambs | D22: 392 | H22: 88 | I22: 36 | J22: 268 | K22: =B22+C22+D22+E22-F22-G22-H22-I22 | Q22: =IFERROR((L22+N22)/(M22+O22),"") | R22: =IFERROR(D22*Q22,"") | S22: =IFERROR(Q22*G22,"") | T22: Accounted for elsewhere is tithe
A23: Boars | B23: 1 | J23: 1 | K23: =B23+C23+D23+E23-F23-G23-H23-I23 | Q23: =IFERROR((L23+N23)/(M23+O23),"") | R23: =IFERROR(D23*Q23,"") | S23: =IFERROR(Q23*G23,"")
A24: Sows | K24: =B24+C24+D24+E24-F24-G24-H24-I24 | Q24: =IFERROR((L24+N24)/(M24+O24),"") | R24: =IFERROR(D24*Q24,"") | S24: =IFERROR(Q24*G24,"")
A25: Pigs | B25: 27 | D25: 29 | G25: 26 | J25: 30 | K25: =B25+C25+D25+E25-F25-G25-H25-I25 | L25: ='Crawley Receipts'!F57 | M25: 26 | Q25: =IFERROR((L25+N25)/(M25+O25),"") | R25: =IFERROR(D25*Q25,"") | S25: =IFERROR(Q25*G25,"")
A26: Hoggets | B26: 29 | I26: 29 | J26: 0 | K26: =B26+C26+D26+E26-F26-G26-H26-I26 | Q26: =IFERROR((L26+N26)/(M26+O26),"") | R26: =IFERROR(D26*Q26,"") | S26: =IFERROR(Q26*G26,"")
A27: Piglets | D27: 32 | E27: 2 | H27: 8 | I27: 3 | J27: 23 | K27: =B27+C27+D27+E27-F27-G27-H27-I27 | Q27: =IFERROR((L27+N27)/(M27+O27),"") | R27: =IFERROR(D27*Q27,"") | S27: =IFERROR(Q27*G27,"") | T27: Accounted for elsewhere is tithe
A28: Swans | K28: =B28+C28+D28+E28-F28-G28-H28-I28 | Q28: =IFERROR((L28+N28)/(M28+O28),"") | R28: =IFERROR(D28*Q28,"") | S28: =IFERROR(Q28*G28,"")
A29: Peacocks | K29: =B29+C29+D29+E29-F29-G29-H29-I29 | Q29: =IFERROR((L29+N29)/(M29+O29),"") | R29: =IFERROR(D29*Q29,"") | S29: =IFERROR(Q29*G29,"")
A30: Total | S30: =SUM(S4:S29)
K31: =B31+C31+D31+E31-F31-G31-H31-I31 | Q31: =IFERROR((L31+N31)/(M31+O31),"") | R31: =IFERROR(D31*Q31,"") | S31: =IFERROR(Q31*G31,"")
K32: =B32+C32+D32+E32-F32-G32-H32-I32 | Q32: =IFERROR((L32+N32)/(M32+O32),"") | R32: =IFERROR(D32*Q32,"") | S32: =IFERROR(Q32*G32,"")
A33: Wool | K33: =B33+C33+D33+E33-F33-G33-H33-I33 | Q33: =IFERROR((L33+N33)/(M33+O33),"") | R33: =IFERROR(D33*Q33,"") | S33: =IFERROR(Q33*G33,"")
A34: Fleeces | K34: =B34+C34+D34+E34-F34-G34-H34-I34 | Q34: =IFERROR((L34+N34)/(M34+O34),"") | R34: =IFERROR(D34*Q34,"") | S34: =IFERROR(Q34*G34,"")
A35: Coarse wool | D35: 1035 | G35: 929 | I35: 106 | J35: 0 | K35: =B35+C35+D35+E35-F35-G35-H35-I35 | L35: 0 | P35: =6.5+3*0.04 | Q35: 0.02 | R35: =IFERROR(D35*Q35,"") | S35: =IFERROR(Q35*G35,"") | T35: unit price from overview sheet (UnitPricesStocks_averages)
A36: Lamb's wool | D36: 283 | G36: 283 | J36: 0 | K36: =B36+C36+D36+E36-F36-G36-H36-I36 | L36: 0 | P36: =15*0.04 | Q36: 0.01 | R36: =IFERROR(D36*Q36,"") | S36: =IFERROR(Q36*G36,"") | T36: unit price from overview sheet (UnitPricesStocks_averages)
A37: Wool locks | D37: =5*0.04 | G37: =5*0.04 | K37: =B37+C37+D37+E37-F37-G37-H37-I37 | L37: ='Crawley Receipts'!F76 | M37: =5*0.04 | P37: =5*0.04 | Q37: =IFERROR((L37+N37)/(M37+O37),"") | R37: =IFERROR(D37*Q37,"") | S37: =IFERROR(Q37*G37,"")
A38: Wool sold at shearing | K38: =B38+C38+D38+E38-F38-G38-H38-I38 | Q38: =IFERROR((L38+N38)/(M38+O38),"") | R38: =IFERROR(D38*Q38,"") | S38: =IFERROR(Q38*G38,"")
A39: Total | K39: =B39+C39+D39+E39-F39-G39-H39-I39 | Q39: =IFERROR((L39+N39)/(M39+O39),"") | R39: =IFERROR(D39*Q39,"") | S39: =SUM(S35:S38)
K40: =B40+C40+D40+E40-F40-G40-H40-I40 | Q40: =IFERROR((L40+N40)/(M40+O40),"") | R40: =IFERROR(D40*Q40,"") | S40: =IFERROR(Q40*G40,"")
K41: =B41+C41+D41+E41-F41-G41-H41-I41 | Q41: =IFERROR((L41+N41)/(M41+O41),"") | R41: =IFERROR(D41*Q41,"") | S41: =IFERROR(Q41*G41,"")
A42: Hides | K42: =B42+C42+D42+E42-F42-G42-H42-I42 | Q42: =IFERROR((L42+N42)/(M42+O42),"") | R42: =IFERROR(D42*Q42,"") | S42: =IFERROR(Q42*G42,"")
A43: Ox hides | D43: 2 | G43: 2 | J43: 0 | K43: =B43+C43+D43+E43-F43-G43-H43-I43 | L43: ='Crawley Receipts'!F59 | M43: 2 | Q43: =IFERROR((L43+N43)/(M43+O43),"") | R43: =IFERROR(D43*Q43,"") | S43: =IFERROR(Q43*G43,"")
A44: Cow hides | K44: =B44+C44+D44+E44-F44-G44-H44-I44 | Q44: =IFERROR((L44+N44)/(M44+O44),"") | R44: =IFERROR(D44*Q44,"") | S44: =IFERROR(Q44*G44,"")
A45: Mare hides | D45: 1 | G45: 1 | J45: 0 | K45: =B45+C45+D45+E45-F45-G45-H45-I45 | L45: ='Crawley Receipts'!F58 | M45: 1 | Q45: =IFERROR((L45+N45)/(M45+O45),"") | R45: =IFERROR(D45*Q45,"") | S45: =IFERROR(Q45*G45,"")
A46: Steer hides | D46: 2 | G46: 2 | J46: 0 | K46: =B46+C46+D46+E46-F46-G46-H46-I46 | L46: ='Crawley Receipts'!F61 | M46: 1 | N46: ='Crawley Receipts'!F61 | O46: 1 | Q46: =IFERROR((L46+N46)/(M46+O46),"") | R46: =IFERROR(D46*Q46,"") | S46: =IFERROR(Q46*G46,"")
A47: Yearling Calf hides | D47: 1 | G47: 1 | J47: 0 | K47: =B47+C47+D47+E47-F47-G47-H47-I47 | L47: ='Crawley Receipts'!F62 | M47: 1 | Q47: =IFERROR((L47+N47)/(M47+O47),"") | R47: =IFERROR(D47*Q47,"") | S47: =IFERROR(Q47*G47,"")
A48: Calf hides | D48: 1 | G48: 1 | J48: 0 | K48: =B48+C48+D48+E48-F48-G48-H48-I48 | L48: ='Crawley Receipts'!F63 | M48: 1 | Q48: =IFERROR((L48+N48)/(M48+O48),"") | R48: =IFERROR(D48*Q48,"") | S48: =IFERROR(Q48*G48,"")
A49: Pig hides | K49: =B49+C49+D49+E49-F49-G49-H49-I49 | Q49: =IFERROR((L49+N49)/(M49+O49),"") | R49: =IFERROR(D49*Q49,"") | S49: =IFERROR(Q49*G49,"")
A50: Weather woolskins | D50: 21 | G50: 21 | J50: 0 | K50: =B50+C50+D50+E50-F50-G50-H50-I50 | Q50: =IFERROR((L50+N50)/(M50+O50),"") | R50: =IFERROR(D50*Q50,"") | S50: =IFERROR(Q50*G50,"")
A51: Ram woolskins | K51: =B51+C51+D51+E51-F51-G51-H51-I51 | Q51: =IFERROR((L51+N51)/(M51+O51),"") | R51: =IFERROR(D51*Q51,"") | S51: =IFERROR(Q51*G51,"")
A52: Ewe woolskins | D52: 24 | G52: 24 | J52: 0 | K52: =B52+C52+D52+E52-F52-G52-H52-I52 | Q52: =IFERROR((L52+N52)/(M52+O52),"") | R52: =IFERROR(D52*Q52,"") | S52: =IFERROR(Q52*G52,"")
A53: Hogg woolskins | D53: 23 | G53: 23 | J53: 0 | K53: =B53+C53+D53+E53-F53-G53-H53-I53 | Q53: =IFERROR((L53+N53)/(M53+O53),"") | R53: =IFERROR(D53*Q53,"") | S53: =IFERROR(Q53*G53,"")
A54: Woolskins (total) | D54: =SUM(D50:D53) | G54: =SUM(G50:G53) | J54: 0 | K54: =B54+C54+D54+E54-F54-G54-H54-I54 | L54: ='Crawley Receipts'!F64 | M54: 68 | Q54: =IFERROR((L54+N54)/(M54+O54),"") | R54: =IFERROR(D54*Q54,"") | S54: =IFERROR(Q54*G54,"")
A55: Wether bareskins | D55: 14 | G55: 14 | J55: 0 | K55: =B55+C55+D55+E55-F55-G55-H55-I55 | Q55: =IFERROR((L55+N55)/(M55+O55),"") | R55: =IFERROR(D55*Q55,"") | S55: =IFERROR(Q55*G55,"")
A56: Ram bareskins | K56: =B56+C56+D56+E56-F56-G56-H56-I56 | Q56: =IFERROR((L56+N56)/(M56+O56),"") | R56: =IFERROR(D56*Q56,"") | S56: =IFERROR(Q56*G56,"")
A57: Ewe bareskins | D57: 13 | G57: 13 | J57: 0 | K57: =B57+C57+D57+E57-F57-G57-H57-I57 | Q57: =IFERROR((L57+N57)/(M57+O57),"") | R57: =IFERROR(D57*Q57,"") | S57: =IFERROR(Q57*G57,"")
A58: Hogg bareskins | K58: =B58+C58+D58+E58-F58-G58-H58-I58 | Q58: =IFERROR((L58+N58)/(M58+O58),"") | R58: =IFERROR(D58*Q58,"") | S58: =IFERROR(Q58*G58,"")
A59: Bareskins (total) | D59: 27 | G59: 27 | J59: 0 | K59: =B59+C59+D59+E59-F59-G59-H59-I59 | L59: ='Crawley Receipts'!$F$65 | M59: 27 | Q59: =IFERROR((L59+N59)/(M59+O59),"") | R59: =IFERROR(D59*Q59,"") | S59: =IFERROR(Q59*G59,"")
A60: Lambskins | D60: 88 | G60: 82 | I60: 6 | K60: =B60+C60+D60+E60-F60-G60-H60-I60 | L60: ='Crawley Receipts'!F66 | M60: 62 | N60: ='Crawley Receipts'!F67 | O60: 20 | Q60: =IFERROR((L60+N60)/(M60+O60),"") | R60: =IFERROR(D60*Q60,"") | S60: =IFERROR(Q60*G60,"") | T60: Accounted for elsewhere is tithe
A61: Rotted skins | K61: =B61+C61+D61+E61-F61-G61-H61-I61 | Q61: =IFERROR((L61+N61)/(M61+O61),"") | R61: =IFERROR(D61*Q61,"") | S61: =IFERROR(Q61*G61,"")
A62: Shorn skins | K62: =B62+C62+D62+E62-F62-G62-H62-I62 | Q62: =IFERROR((L62+N62)/(M62+O62),"") | R62: =IFERROR(D62*Q62,"") | S62: =IFERROR(Q62*G62,"")
A63: Total | S63: =SUM(S43:S62)
K64: =B64+C64+D64+E64-F64-G64-H64-I64 | Q64: =IFERROR((L64+N64)/(M64+O64),"") | R64: =IFERROR(D64*Q64,"") | S64: =IFERROR(Q64*G64,"")
K65: =B65+C65+D65+E65-F65-G65-H65-I65 | Q65: =IFERROR((L65+N65)/(M65+O65),"") | R65: =IFERROR(D65*Q65,"") | S65: =IFERROR(Q65*G65,"")
A66: Poultry stock | K66: =B66+C66+D66+E66-F66-G66-H66-I66 | Q66: =IFERROR((L66+N66)/(M66+O66),"") | R66: =IFERROR(D66*Q66,"") | S66: =IFERROR(Q66*G66,"")
A67: Hens | D67: 125 | G67: 95 | I67: 30 | K67: =B67+C67+D67+E67-F67-G67-H67-I67 | L67: ='Crawley Receipts'!F71 | M67: 95 | Q67: =IFERROR((L67+N67)/(M67+O67),"") | R67: =IFERROR(D67*Q67,"") | S67: =IFERROR(Q67*G67,"") | T67: Accounted for elsewhere is tithe
A68: Geese | K68: =B68+C68+D68+E68-F68-G68-H68-I68 | Q68: =IFERROR((L68+N68)/(M68+O68),"") | R68: =IFERROR(D68*Q68,"") | S68: =IFERROR(Q68*G68,"")
A69: Capons (from chickens) | K69: =B69+C69+D69+E69-F69-G69-H69-I69 | Q69: =IFERROR((L69+N69)/(M69+O69),"") | R69: =IFERROR(D69*Q69,"") | S69: =IFERROR(Q69*G69,"")
A70: Cocks & hens | K70: =B70+C70+D70+E70-F70-G70-H70-I70 | Q70: =IFERROR((L70+N70)/(M70+O70),"") | R70: =IFERROR(D70*Q70,"") | S70: =IFERROR(Q70*G70,"")
A71: Total | K71: =B71+C71+D71+E71-F71-G71-H71-I71 | Q71: =IFERROR((L71+N71)/(M71+O71),"") | R71: =IFERROR(D71*Q71,"") | S71: =SUM(S67:S70)
K72: =B72+C72+D72+E72-F72-G72-H72-I72 | Q72: =IFERROR((L72+N72)/(M72+O72),"") | R72: =IFERROR(D72*Q72,"") | S72: =IFERROR(Q72*G72,"")
A73: Poultry production | K73: =B73+C73+D73+E73-F73-G73-H73-I73 | Q73: =IFERROR((L73+N73)/(M73+O73),"") | R73: =IFERROR(D73*Q73,"") | S73: =IFERROR(Q73*G73,"")
A74: Eggs | K74: =B74+C74+D74+E74-F74-G74-H74-I74 | Q74: =IFERROR((L74+N74)/(M74+O74),"") | R74: =IFERROR(D74*Q74,"") | S74: =IFERROR(Q74*G74,"")
A75: Cocks & hens from churchscot of customary tenants | K75: =B75+C75+D75+E75-F75-G75-H75-I75 | Q75: =IFERROR((L75+N75)/(M75+O75),"") | R75: =IFERROR(D75*Q75,"") | S75: =IFERROR(Q75*G75,"")
K76: =B76+C76+D76+E76-F76-G76-H76-I76 | Q76: =IFERROR((L76+N76)/(M76+O76),"") | R76: =IFERROR(D76*Q76,"") | S76: =IFERROR(Q76*G76,"")
K77: =B77+C77+D77+E77-F77-G77-H77-I77 | Q77: =IFERROR((L77+N77)/(M77+O77),"") | R77: =IFERROR(D77*Q77,"") | S77: =IFERROR(Q77*G77,"")
A78: Meat | K78: =B78+C78+D78+E78-F78-G78-H78-I78 | Q78: =IFERROR((L78+N78)/(M78+O78),"") | R78: =IFERROR(D78*Q78,"") | S78: =IFERROR(Q78*G78,"")
A79: Beef | K79: =B79+C79+D79+E79-F79-G79-H79-I79 | Q79: =IFERROR((L79+N79)/(M79+O79),"") | R79: =IFERROR(D79*Q79,"") | S79: =IFERROR(Q79*G79,"")
A80: Mutton | K80: =B80+C80+D80+E80-F80-G80-H80-I80 | Q80: =IFERROR((L80+N80)/(M80+O80),"") | R80: =IFERROR(D80*Q80,"") | S80: =IFERROR(Q80*G80,"")
A81: Pork | K81: =B81+C81+D81+E81-F81-G81-H81-I81 | Q81: =IFERROR((L81+N81)/(M81+O81),"") | R81: =IFERROR(D81*Q81,"") | S81: =IFERROR(Q81*G81,"")
K82: =B82+C82+D82+E82-F82-G82-H82-I82 | Q82: =IFERROR((L82+N82)/(M82+O82),"") | R82: =IFERROR(D82*Q82,"") | S82: =IFERROR(Q82*G82,"")
K83: =B83+C83+D83+E83-F83-G83-H83-I83 | Q83: =IFERROR((L83+N83)/(M83+O83),"") | R83: =IFERROR(D83*Q83,"") | S83: =IFERROR(Q83*G83,"")
A84: Cheese | K84: =B84+C84+D84+E84-F84-G84-H84-I84 | Q84: =IFERROR((L84+N84)/(M84+O84),"") | R84: =IFERROR(D84*Q84,"") | S84: =IFERROR(Q84*G84,"")
A85: Winter cheese | D85: =5*0.04+1*Assumptions!$E$4 | G85: =5*0.04+1*Assumptions!$E$4 | K85: =B85+C85+D85+E85-F85-G85-H85-I85 | L85: ='Crawley Receipts'!F68 | M85: =5*0.04+1*Assumptions!$E$4 | P85: =5*0.04+1*Assumptions!$E$4 | Q85: =IFERROR((L85+N85)/(M85+O85),"") | R85: =IFERROR(D85*Q85,"") | S85: =IFERROR(Q85*G85,"")
A86: Summer cheese | D86: 168 | G86: 148 | I86: 20 | K86: =B86+C86+D86+E86-F86-G86-H86-I86 | L86: ='Crawley Receipts'!F69 | M86: =P86 | P86: =7.5+12*0.04 | Q86: =IFERROR((L86+N86)/(M86+O86),"") | R86: =IFERROR(D86*Q86,"") | S86: =IFERROR(Q86*G86,"")
A87: Total | K87: =B87+C87+D87+E87-F87-G87-H87-I87 | Q87: =IFERROR((L87+N87)/(M87+O87),"") | R87: =IFERROR(D87*Q87,"") | S87: =SUM(S85:S86)
K88: =B88+C88+D88+E88-F88-G88-H88-I88 | Q88: =IFERROR((L88+N88)/(M88+O88),"") | R88: =IFERROR(D88*Q88,"") | S88: =IFERROR(Q88*G88,"")
A89: Butter | D89: =15*0.04+5*Assumptions!$E$4 | G89: =15*0.04+5*Assumptions!$E$4 | K89: =B89+C89+D89+E89-F89-G89-H89-I89 | M89: =15*0.04+5*Assumptions!$E$4 | P89: =15*0.04+5*Assumptions!$E$4 | Q89: =IFERROR((L89+N89)/(M89+O89),"") | R89: =IFERROR(D89*Q89,"") | S89: =IFERROR(Q89*G89,"")
A90: Total | K90: =B90+C90+D90+E90-F90-G90-H90-I90 | Q90: =IFERROR((L90+N90)/(M90+O90),"") | R90: =IFERROR(D90*Q90,"") | S90: =SUM(S89)
K91: =B91+C91+D91+E91-F91-G91-H91-I91 | Q91: =IFERROR((L91+N91)/(M91+O91),"") | R91: =IFERROR(D91*Q91,"") | S91: =IFERROR(Q91*G91,"")
A92: Cider | K92: =B92+C92+D92+E92-F92-G92-H92-I92 | Q92: =IFERROR((L92+N92)/(M92+O92),"") | R92: =IFERROR(D92*Q92,"") | S92: =IFERROR(Q92*G92,"")
K93: =B93+C93+D93+E93-F93-G93-H93-I93 | Q93: =IFERROR((L93+N93)/(M93+O93),"") | R93: =IFERROR(D93*Q93,"") | S93: =IFERROR(Q93*G93,"")
K94: =B94+C94+D94+E94-F94-G94-H94-I94 | Q94: =IFERROR((L94+N94)/(M94+O94),"") | R94: =IFERROR(D94*Q94,"") | S94: =IFERROR(Q94*G94,"")
K95: =B95+C95+D95+E95-F95-G95-H95-I95 | Q95: =IFERROR((L95+N95)/(M95+O95),"") | R95: =IFERROR(D95*Q95,"") | S95: =IFERROR(Q95*G95,"")
Q96: =IFERROR((L96+N96)/(M96+O96),"") | R96: =IFERROR(D96*Q96,"") | S96: =IFERROR(Q96*G96,"")
Q97: =IFERROR((L97+N97)/(M97+O97),"") | R97: =IFERROR(D97*Q97,"") | S97: =IFERROR(Q97*G97,"")

Sheet Assumptions
A1: ASSUMPTIONS
B3: Weights | C3: Value (in lbs) | D3: Value (in cloves) | E3: Value (in weys) | F3: Value (in stone)
B4: Lbs | C4: 1 | D4: =C4/C5 | E4: =C4/C6 | F4: =C4/C7
B5: Cloves | C5: 7 | D5: 1 | E5: =C5/C6 | F5: =C7/C5
B6: Wey | C6: 175 | D6: =C6/C5 | E6: =C6/C6 | F6: =C7/C6
B7: Stone | C7: =175/14 | D7: =C5/C7 | E7: =C7/C6 | F7: 1
