Workbook

Sheet Culham Overview - Completed
A1: CULHAM OVERVIEW - COMPLETED | B1: Total in £ | C1: Error | D1: Note
A2: CASH ACCOUNT
A3: RECEIPTS
A4: Arrears total
A5: Rents of assize total | B5: 4.1
A6: Quittances total | B6: 0.135
A7: Defaults of rent total
A8: Defaults of rent through the pestilence total
A9: Cotlands defaults total
A10: Cotlands total
A11: Total of quittances and defaults of rent total
A12: Total of rents remaining clear total
A13: Farms total
A14: Annual recognizances total | B14: 0.03
A15: Issues of the Manor total | B15: 10.75
A16: Issues of the tenements in the lord's hands total
A17: Sale of labour services total
A18: Sale of corn total | B18: 6.89
A19: Entry and marriage fines total | B19: 1.32
A20: Pleas & perquisites total
A21: Forfeited chattels total
A22: Farm of the demesne land total
A23: Total of all receipts (calculated here) | B23: =SUM(B5:B22)
A24: Total of all receipts (calculated here) incl arrears | B24: =SUM(B4:B22)
A25: Total recorded in the accounts excl. arrears | B25: 24.95 | C25: =B23-B25
A26: Total recorded in the accounts incl. arrears | B26: =B25+B4
A29: EXPENSES
A30: Cost of ploughs total
A31: Purchase of corn total
A32: Cost of carts and wagons total
A33: Cost of dairy total
A34: Purchase of stock total
A35: Sheepcote total
A36: Cost of buildings total | B36: 0.15416667
A37: Threshing total | B37: 0.27
A38: Barley expenses
A39: Expenses of the harvest total
A40: Necessary expenses
A41: Wages of the bailiff
A42: Steward's expenses total
A43: Annual fees
A44: Total of all expenses per account | B44: 7.86
A45: Total of all expenses (calculated here) | B45: 7.7966667
A46: Total fixed investment | B46: 2.5366667
A47: Total Demesne fixed investment | B47: 2.5366667
A49: Owed by the reeve | B49: =B23-B45
A50: From accounts | B50: 7.86
A52: Allowances
A53: Cash deliveries
A54: Sum of the above | B54: =SUM(B52:B53)
A55: Total of all allowances and cash deliveries in accounts
A57: Net amount owed | B57: =B50-B54
A58: Net amount owed in accounts
A60: GRANGE ACCOUNT | B60: Total Production | D60: Value of total gross production in £ | E60: Value of total net production in £
A61: Grange | B61: qrs | C61: bus
A62: Wheat | B62: 9.75 | E62: 1.38125
A63: Rye
A64: Dredge
A65: Curall
A66: Barley | B66: 19 | E66: 1.453125
A67: Oats | B67: 20 | E67: 0
A68: Beans
A69: Peas
A70: Vetches
A71: Total value of gross production (sum of the above)
A72: Total value of net production
A73: Value of sales
A75: MILL ACCOUNT | B75: Total Production | D75: Total in £
A76: Issues of the mill | B76: qrs | C76: bus
A77: Wheat
A78: Oatmeal
A79: 1st grade malt
A80: 2nd grade malt
A81: Maslin
A82: Total value of production (sum of the above)
A83: Value of sales
A85: STOCK ACCOUNT
A86: Livestock | B86: Begin stock | C86: End stock | D86: Stockbuilding | F86: Value of stock in £ | G86: Value of stockbuilding
A87: Cart-horses | D87: =C87-B87 | F87: ='Stock'!K5*'Stock'!O5 | G87: =D87*'Stock'!O5
A88: Mares | D88: =C88-B88 | F88: ='Stock'!K6*'Stock'!O6 | G88: =D88*'Stock'!O6
A89: Plough horses | B89: 7 | C89: 7 | D89: 0 | F89: ='Stock'!K7*'Stock'!O7 | G89: =D89*'Stock'!O7
A90: Colts (2 years) | D90: =C90-B90 | F90: ='Stock'!K9*'Stock'!O9 | G90: =D90*'Stock'!O9
A91: Colts (2 years) | D91: =C91-B91 | F91: ='Stock'!K9*'Stock'!O9 | G91: =D91*'Stock'!O9
A92: Colts (1 year) | D92: =C92-B92 | F92: ='Stock'!K10*'Stock'!O10 | G92: =D92*'Stock'!O10
A93: Foals | D93: =C93-B93 | F93: ='Stock'!K11*'Stock'!O11 | G93: =D93*'Stock'!O11
A94: Oxen | B94: 3 | C94: 2 | D94: -1 | F94: 0.68666667 | G94: -0.34333333
A95: Bulls | B95: 1 | C95: 1 | D95: 0 | F95: ='Stock'!K13*'Stock'!O13 | G95: =D95*'Stock'!O13
A96: Cows | B96: 23 | C96: 25 | D96: 2 | F96: 10 | G96: 0.8
A97: Steers | B97: 4 | C97: 0 | D97: -4 | F97: ='Stock'!K15*'Stock'!O15 | G97: =D97*'Stock'!O15
A98: Bullocks | B98: 9 | C98: 6 | D98: -3 | F98: ='Stock'!K16*'Stock'!O16 | G98: =D98*'Stock'!O16
A99: Yearlings | B99: 6 | C99: 3 | D99: -3 | F99: ='Stock'!K17*'Stock'!O17 | G99: =D99*'Stock'!O17
A100: Calves | B100: 22 | C100: 5 | D100: -17 | F100: 0.29642857 | G100: -1.0078571
A101: Wethers | B101: 112 | C101: 80 | D101: -32 | F101: 4.08 | G101: -1.632
A102: Rams | D102: =C102-B102 | F102: ='Stock'!K20*'Stock'!O20 | G102: =D102*'Stock'!O20
A103: Ewes | D103: =C103-B103 | F103: ='Stock'!K21*'Stock'!O21 | G103: =D103*'Stock'!O21
A104: Hoggs | D104: =C104-B104 | F104: ='Stock'!K22*'Stock'!O22 | G104: =D104*'Stock'!O22
A105: Lambs | D105: =C105-B105 | F105: ='Stock'!K23*'Stock'!O23 | G105: =D105*'Stock'!O23
A106: Boars | D106: =C106-B106 | F106: ='Stock'!K24*'Stock'!O24 | G106: =D106*'Stock'!O24
A107: Sows | D107: =C107-B107 | F107: ='Stock'!K25*'Stock'!O25 | G107: =D107*'Stock'!O25
A108: Pigs | D108: =C108-B108 | F108: ='Stock'!K26*'Stock'!O26 | G108: =D108*'Stock'!O26
...

Sheet Prices
A1: Meat & Dairy Prices
C2: 1301 | D2: 1302 | E2: Average
A3: Beef | B3: £ per lb | C3: 0.0033351854 | D3: 0.0032608538 | E3: =AVERAGE(C3:D3)
A4: Mutton | B4: £ per lb | C4: 0.0036593977 | D4: 0.0037125513 | E4: =AVERAGE(C4:D4)
A5: Pork | B5: £ per lb | C5: 0.0038431326 | D5: 0.0037574803 | E5: =AVERAGE(C5:D5)
A6: Cheese | B6: £ per lb | C6: 0.0055768754 | D6: 0.0056654898 | E6: =AVERAGE(C6:D6)
A7: Butter | B7: £ per lb | C7: 0.0036626221 | D7: 0.0035935077 | E7: =AVERAGE(C7:D7)
A8: Milk | B8: £ per gallon | C8: 0.0055768754 | D8: 0.0056654898 | E8: =AVERAGE(C8:D8)

Sheet Labour Rents

Sheet Overview
A1: CULHAM | B1: Total in £ | C1: Error | D1: Note
A2: CASH ACCOUNT
A3: RECEIPTS
A4: Arrears total
A5: Rents of assize total
A6: Quittances total
A7: Defaults of rent total
A8: Defaults of rent through the pestilence total
A9: Cotlands defaults total
A10: Cotlands total
A11: Total of quittances and defaults of rent total
A12: Total of rents remaining clear total
A13: Farms total
... A22: Farm of the demesne land total
A23: Total of all receipts (calculated here) | B23: =Receipts!F103
A24: Total of all receipts (calculated here) incl arrears | B24: =Receipts!F104
A25: Total recorded in the accounts excl. arrears | B25: =Receipts!F101 | C25: =B25-B23
A26: Total recorded in the accounts incl. arrears
A29: EXPENSES
A30: Cost of ploughs total
A31: Purchase of corn total
A32: Cost of carts and wagons total
A33: Cost of dairy total
A34: Purchase of stock total
A35: Sheepcote total
A36: Cost of buildings total
A37: Threshing total
A38: Barley expenses
A39: Expenses of the harvest total
... A43: Annual fees
A44: Total of all expenses per account | B44: =Expenses!F63
A45: Total of all expenses (calculated here) | B45: =Expenses!F64
A46: Total fixed investment | B46: =Expenses!F65
A47: Total Demesne fixed investment | B47: =Expenses!F66
A49: Owed by the reeve
A50: From accounts
A52: Allowances
A53: Cash deliveries
A54: Sum of the above
A55: Total of all allowances and cash deliveries in accounts
A57: Net amount owed
A58: Net amount owed in accounts
A60: GRANGE ACCOUNT | B60: Total Production
A61: Grange | B61: qrs | E61: Value of total gross production in £ | F61: Value of total net production in £
A62: wheat | B62: ='Issues of the Grange'!B2 | E62: ='Issues of the Grange'!I2 | F62: ='Issues of the Grange'!O14
A63: mancorn | B63: ='Issues of the Grange'!B3 | E63: ='Issues of the Grange'!I3 | F63: ='Issues of the Grange'!O15
A64: barley | B64: ='Issues of the Grange'!B4 | E64: ='Issues of the Grange'!I4 | F64: ='Issues of the Grange'!O16
A65: oats | B65: ='Issues of the Grange'!B5 | E65: ='Issues of the Grange'!I5 | F65: ='Issues of the Grange'!O17
A66: Total value of gross production (sum of the above) | E66: =SUM(E62:E65)
A67: Total value of net production | E67: =SUM(F62:F65)
A68: Value of sales | E68: =Receipts!F58
A70: MILL ACCOUNT
A71: Issues of the mill
A72: Wheat
A73: Oatmeal
A74: 1st grade malt
A75: 2nd grade malt
A76: Maslin
A77: Total value of production (sum of the above)
A78: Value of sales
A80: STOCK ACCOUNT
A81: Livestock | B81: Sales value in £
A82: Cart-horses | B82: =Stock!R5
A83: Mares | B83: =Stock!R6
A84: Plough horses | B84: =Stock!R7
A85: Colts (2 years) | B85: =Stock!R8
A86: Colts (2 years) | B86: =Stock!R9
A87: Colts (1 year) | B87: =Stock!R10
A88: Foals | B88: =Stock!R11
A89: Oxen | B89: =Stock!R12
A90: Bulls | B90: =Stock!R13
A91: Cows | B91: =Stock!R14
A92: Steers | B92: =Stock!R15
A93: Bullocks | B93: =Stock!R16
... A107: Peacocks | B107: =Stock!R30
A108: Total value of stock (sum of the above)
A109: Total value of production
A110: Value of sales | B110: =Stock!R31
A112: Wool | B112: Value of production at sales prices £
A113: Fleeces | B113: =Stock!T35
A114: Coarse wool | B114: =Stock!T36
A115: Lamb's wool | B115: =Stock!T37
A116: Wool locks | B116: =Stock!T38
A117: Wool sold at shearing | B117: =Stock!T39
A118: Total value of production (sum of the above) | B118: =Stock!T40
A119: Value of sales
A121: Hides | B121: Value of production at sales prices £
A122: Ox hides | B122: =Stock!T44
A123: Cow hides | B123: =Stock!T45
A124: Mare hides | B124: =Stock!T46
A125: Steer hides | B125: =Stock!T47
A126: Yearling Calf hides | B126: =Stock!T48
A127: Calf hides | B127: =Stock!T49
A128: Pig hides | B128: =Stock!T50
A129: Wether woolskins | B129: =Stock!T51
A130: Ram woolskins | B130: =Stock!T52
A131: Ewe woolskins | B131: =Stock!T53
A132: Hogg woolskins | B132: =Stock!T54
A133: Woolskins (total) | B133: =Stock!T55
... A141: Shorn skins | B141: =Stock!T63
...

Sheet Receipts
A1: CULHAM RECEIPTS
A2: Heading | B2: £ | C2: s | D2: d | F2: Total in £ | G2: Error | H2: Notes
A3: Rents of assize | B3: 2 | C3: 1 | D3: 0 | F3: 2.05 | H3: James de North', bailiff, and William Kepe, reeve, render account for £2 1 shilling.5pence for all rents of assize at Easter (22 April).
A4: Rents of assize | B4: 2 | C4: 1 | D4: 0 | F4: 2.05 | H4: £2 1 shilling .5pence at Michaelmas (29 September).
A5: Rents of assize | B5: 4 | C5: 2 | D5: 1 | F5: 4.1 | H5: Total, £4 2 shilling 1pence
A6: Rents of assize | F6: 4.1 | G6: 0 | H6: Total
A8: Increment | B8: 0 | C8: 0 | D8: 0 | F8: 0 | H8: Nothing this year from increment of rent.
A9: Increment | F9: 0 | G9: 0 | H9: Total
A11: Quittances | B11: 0 | C11: 1 | D11: 0 | F11: 0.05 | H11: In quittance of 1 reeve for the year 1 shilling.
A12: Quittances | B12: 0 | C12: 0 | D12: 6 | F12: 0.03 | H12: 1 carter for the year 6pence.
A13: Quittances | B13: 0 | C13: 0 | D13: 6 | F13: 0.03 | H13: 1 shepherd for the year 6pence.
A14: Quittances | B14: 0 | C14: 0 | D14: 6 | F14: =B14+C14/20+D14/240 | H14: 1 hayward for the year 6pence
A15: Quittances | B15: 0 | C15: 2 | D15: 6 | F15: =B15+C15/20+D15/240 | H15: Total, 2 shilling 6pence
A16: Quittances | F16: =SUM(F11:F14) | G16: =F16-F15 | H16: Total
A18: Total of rents remaining | B18: 3 | C18: 19 | D18: 7 | F18: 3.98 | H18: Total of rents remaining, £3 19 shilling 7pence
A19: Total of rents remaining | F19: 3.98 | G19: =F19-F18 | H19: Total
A21: Annual gifts | B21: 0 | C21: 9 | D21: 0.5 | F21: 0.45 | H21: The same render account for 9 shilling 0.5pence from annual gifts at Easter.
A22: Annual gifts | B22: 0 | C22: 9 | D22: 0.5 | F22: 0.45 | H22: 9 shilling 0.5pence at Michaelmas.
A23: Annual gifts | B23: 0 | C23: 18 | D23: 1 | F23: 0.9 | H23: Total, 18 shilling 1pence
A24: Annual gifts | F24: 0.9 | G24: 0 | H24: Total
A26: Annual recognizance | B26: 0 | C26: 0 | D26: 6 | F26: 0.03 | H26: The same render account for 6pence from the annual recognizance of William Piscator' of Culham so that he may remain outside the manor and pay suit to the tithing.
A27: Annual recognizance | B27: 0 | C27: 0 | D27: 6 | F27: 0.03 | H27: Total, 6pence
A28: Annual recognizance | F28: 0.03 | G28: 0 | H28: Total
A30: Issues of the manor | B30: 0 | C30: 3 | D30: 0.5 | F30: 0.15 | H30: The same render account for 3 shilling 0.5pence from common pannage of pigs, that is, from 27 pigs, 19 piglets, at 1pence a pig over a year old, and .5pence a piglet.
A31: Issues of the manor | B31: 0 | C31: 9 | D31: 6 | F31: 0.48 | H31: 9 shilling 6pence from pannage of Kylhamfryth', from 42 pigs and 30 piglets agisted in the wood of Kylhamfryth', at 2pence a pig, 1pence a piglet.
A32: Issues of the manor | B32: 1 | C32: 0 | D32: 8 | F32: 1.03 | H32: £1 8pence from 3 oxen sold, at 7 shilling each for 2, and 6 shilling 8pence for 1.
A33: Issues of the manor | B33: 0 | C33: 16 | D33: 0 | F33: 0.8 | H33: 16 shilling from 2 cows sold together.
A34: Issues of the manor | B34: 0 | C34: 16 | D34: 8 | F34: 0.83 | H34: 16 shilling 8pence from 14 calves sold together.
A35: Issues of the manor | B35: 1 | C35: 0 | D35: 6 | F35: 1.02 | H35: £1 6pence from 20 old kebb wethers sold at Martinmas.
A36: Issues of the manor | B36: 0 | C36: 1 | D36: 7 | F36: 0.08 | H36: 1 shilling 7pence from the hide sold of 1 cow in murrain.
A37: Issues of the manor | B37: 0 | C37: 2 | D37: 3 | F37: 0.11 | H37: 2 shilling 3pence from the hides sold of 3 bullocks and 3 yearlings in murrain.
A38: Issues of the manor | B38: 0 | C38: 0 | D38: 1 | F38: 0 | H38: 1pence from the hide sold of 1 calf in murrain.
A39: Issues of the manor | B39: 0 | C39: 1 | D39: 5.5 | F39: 0.07 | H39: 1 shilling 5.5pence from the skins of 5 wethers in murrain before shearing.
A40: Issues of the manor | B40: 0 | C40: 0 | D40: 9 | F40: 0.04 | H40: 9pence from the skins sold of 6 wethers in murrain after shearing.
A41: Issues of the manor | B41: 0 | C41: 3 | D41: 11 | F41: 0.2 | H41: 3 shilling 11pence from 12 cloves of winter cheese sold.
... A50: Issues of the manor | B50: 10 | C50: 17 | D50: 0 | F50: 10.85 | H50: Total, £10 17 shilling
A51: Issues of the manor | F51: 10.75 | G51: -0.1 | H51: Total
A53: Sale of corn | B53: 1 | C53: 7 | D53: 7.5 | F53: 1.38 | H53: The same render account for £1 7 shilling 7.5pence from 6 quarters 3 bushels of wheat sold, at 4 shilling 4pence a qr.
A54: Sale of corn | B54: 3 | C54: 10 | D54: 11.25 | F54: 3.55 | H54: £3 10 shilling 11.25pence from 28 quarters 3 bushels of mancorn sold, at 2 shilling 6pence a qr.
A55: Sale of corn | B55: 0 | C55: 0 | D55: 3.75 | F55: 0.02 | H55: 3.75pence from 1 bushels sold at the audit.
A56: Sale of corn | B56: 1 | C56: 18 | D56: 9 | F56: 1.94 | H56: £1 18 shilling 9pence from 11.5 quarters 1 bushels of barley sold, at 3 shilling 4pence a qr.
A57: Sale of corn | B57: 6 | C57: 17 | D57: 7.5 | F57: 6.88 | H57: Total, £6 17 shilling 7.5pence
A58: Sale of corn | F58: 6.89 | G58: 0.01 | H58: Total
A60: Entry and marriage fines | B60: 0 | C60: 3 | D60: 0.5 | F60: 0.15 | H60: The same render account for 3 shilling 0.5pence for tithingpenny at the hundred-court of Martinmas.
A61: Entry and marriage fines | B61: 0 | C61: 3 | D61: 0.5 | F61: 0.15 | H61: 3 shilling 0.5pence at the hundred-court of Hockday.
A62: Entry and marriage fines | B62: 0 | C62: 13 | D62: 4 | F62: 0.67 | H62: 13 shilling 4pence from William, son of Walter Molendinarius, to have 4.5 acres of land which belonged to Walter his father.
A63: Entry and marriage fines | B63: 0 | C63: 2 | D63: 0 | F63: 0.1 | H63: 2 shilling from Alice, who was wife of Nicholas Nel, to have 1 messuage .5 virgate of land which belonged to Nicholas her husband.
A64: Entry and marriage fines | B64: 0 | C64: 3 | D64: 0 | F64: 0.15 | H64: 3 shilling from John, son of John Boul', to have 1 acre of purpresture by surrender of the said John his father.
A65: Entry and marriage fines | B65: 0 | C65: 2 | D65: 0 | F65: 0.1 | H65: 2 shilling from William le Walays for marrying Matilda his daughter outside the demesne.
A66: Entry and marriage fines | B66: 1 | C66: 6 | D66: 5 | F66: 1.32 | H66: Total, £1 6 shilling 5pence
A67: Entry and marriage fines | F67: 1.32 | G67: 0 | H67: Total
A69: Perquisites | B69: 0 | C69: 1 | D69: 0 | F69: 0.05 | H69: The same render account for 1 shilling from Alice Croyll', Walter Ryd', John Gay, Agnes ate Strod' for breaking the assize of ale.
A70: Perquisites | B70: 0 | C70: 0 | D70: 3 | F70: 0.01 | H70: 3pence from Thomas Buthory for trespass.
A71: Perquisites | B71: 0 | C71: 0 | D71: 3 | F71: 0.01 | H71: 3pence from Thomas ate Wod' for trespass.
A72: Perquisites | B72: 0 | C72: 0 | D72: 3 | F72: 0.01 | H72: 3pence from Justina Juveni for the same.
A73: Perquisites | B73: 0 | C73: 0 | D73: 3 | F73: 0.01 | H73: 3pence from John Crys for the same.
A74: Perquisites | B74: 0 | C74: 0 | D74: 6 | F74: 0.03 | H74: 6pence from William Wallnon for trespass.
A75: Perquisites | B75: 0 | C75: 0 | D75: 3 | F75: 0.01 | H75: 3pence from the same for trespass.
A76: Perquisites | B76: 0 | C76: 1 | D76: 0 | F76: 0.05 | H76: 1 shilling from William Kepe for trespass.
A77: Perquisites | B77: 0 | C77: 1 | D77: 0 | F77: 0.05 | H77: 1 shilling from John Baldewyn' for trespass.
A78: Perquisites | B78: 0 | C78: 0 | D78: 3 | F78: 0.01 | H78: 3pence from John Crys for trespass.
A79: Perquisites | B79: 0 | C79: 0 | D79: 9 | F79: 0.04 | H79: 9pence from John Baldeweyn', Cecilia Boul', Christina Profinal for assize.
A80: Perquisites | B80: 0 | C80: 0 | D80: 6 | F80: 0.03 | H80: 6pence from William Wallyno for trespass.
... A95: Perquisites | B95: 0 | C95: 19 | D95: 9 | F95: 0.99 | H95: Total, 19 shilling 9pence
A96: Perquisites | F96: 0.99 | G96: 2.220446e-16 | H96: Total
A98: Entry to purprestures | B98: 0 | C98: 0 | D98: 0 | F98: 0 | H98: Nothing this year from entry to purprestures.
A99: Entry to purprestures | F99: 0 | G99: 0 | H99: Total
A101: Total of all receipts | B101: 24 | C101: 18 | D101: 11.5 | F101: 24.95 | H101: Total of all receipts, £24 18 shilling 11.5pence
A102: Total of all receipts recorded in accounts | F102: 24.95 | G102: =F102-F101 | H102: Total
A103: Total cross-check without arrears | F103: =F99+F96+F67+F58+F51+F28+F24+F19 | G103: =F103-F102
A104: Total cross-check with arrears | F104: =F103 | H104: no arrears

Sheet Expenses
A1: CULHAM EXPENSES
A2: Heading | B2: £ | C2: s | D2: d | F2: Total in £ | G2: Error | H2: Notes | J2: Fixed investment | K2: Demesne fixed investment
A3: Expenses for ploughs | B3: 0 | C3: 7 | D3: 5 | F3: 0.37 | H3: In steel for ploughs 7 shilling 5pence. | J3: =F3 | K3: =J3
A4: Expenses for ploughs | B4: 0 | C4: 3 | D4: 0 | F4: 0.15 | H4: stipend of the smith repairing ironwork 3 shilling. | J4: =F4 | K4: =J4
A5: Expenses for ploughs | B5: 0 | C5: 9 | D5: 8 | F5: 0.48 | H5: shoeing 7 horses for the year 9 shilling 8pence. | J5: =F5 | K5: =J5
A6: Expenses for ploughs | B6: 0 | C6: 1 | D6: 5 | F6: 0.07 | H6: 2 ploughshares bought 1 shilling 5pence. | J6: =F6 | K6: =J6
A7: Expenses for ploughs | B7: 0 | C7: 1 | D7: 0 | F7: 0.05 | H7: 4 plough-irons bought 1 shilling. | J7: =F7 | K7: =J7
A8: Expenses for ploughs | B8: 0 | C8: 0 | D8: 6 | F8: 0.03 | H8: 2 pairs of wheels bought 6pence. | J8: =F8 | K8: =J8
A9: Expenses for ploughs | B9: 0 | C9: 0 | D9: 2.5 | F9: 0.01 | H9: 7 halters and 1 rope made from hair 2.5pence. | J9: =F9 | K9: =J9
A10: Expenses for ploughs | B10: 0 | C10: 4 | D10: 6 | F10: 0.23 | H10: stipend of 1 drover for the year 4 shilling 6pence.
A11: Expenses for ploughs | B11: 0 | C11: 0 | D11: 9 | F11: =B11+C11/20+D11/240 | H11: 1 sack bought 9pence | J11: =F11 | K11: =J11
A12: Expenses for ploughs | B12: 1 | C12: 8 | D12: 5.5 | F12: =B12+C12/20+D12/240 | H12: Total, £1 8 shilling 5.5pence
A13: Expenses for ploughs | F13: =SUM(F3:F11) | G13: =F13-F12 | H13: Total
A15: Carts | B15: 0 | C15: 2 | D15: 2 | F15: 0.11 | H15: in 1 pair of wheels bought for the cart 2 shilling 2pence. | J15: =F15 | K15: =J15
A16: Carts | B16: 0 | C16: 0 | D16: 10.5 | F16: 0.04 | H16: clouts with nails bought 10.5pence, and so much because it was at Farnham in order to collect timber and talwood at the water (quesivit taluerud' ad aq'). | J16: =F16 | K16: =J16
A17: Carts | B17: 0 | C17: 0 | D17: 5 | F17: 0.02 | H17: grease for the cart 5pence. | J17: =F17 | K17: =J17
A18: Carts | B18: 0 | C18: 0 | D18: 3 | F18: 0.01 | H18: fitting the cart with axles 3pence. | J18: =F18 | K18: =J18
A19: Carts | B19: 0 | C19: 0 | D19: 4.5 | F19: 0.02 | H19: 1 pair of cart-shafts made from their own timber 4.5pence. | J19: =F19 | K19: =J19
A20: Carts | B20: 0 | C20: 0 | D20: 6 | F20: =B20+C20/20+D20/240 | H20: 1 pair of saddle-pads bought 6pence | J20: =F20 | K20: =J20
A21: Carts | B21: 0 | C21: 4 | D21: 7 | F21: =B21+C21/20+D21/240 | H21: Total, 4 shilling 7pence
A22: Carts | F22: =SUM(F15:F20) | G22: =F22-F21 | H22: Total
A24: Cost of buildings | B24: 0 | C24: 1 | D24: 4 | F24: 0.07 | H24: In roofing the byre at various times 1 shilling 4pence. | J24: =F24 | K24: =J24
A25: Cost of buildings | B25: 0 | C25: 0 | D25: 7 | F25: 0.03 | H25: roofing the barn in places 7pence. | J25: =F25 | K25: =J25
A26: Cost of buildings | B26: 0 | C26: 0 | D26: 9.5 | F26: 0.04 | H26: mending the walls of the byre at various times 9.5pence. | J26: =F26 | K26: =J26
A27: Cost of buildings | B27: 0 | C27: 0 | D27: 2 | F27: 0.01 | H27: mending 1 barrow 2pence. | J27: =F27 | K27: =J27
A28: Cost of buildings | D28: 1 | F28: =B28+C28/20+D28/240 | H28: 1 shovel bought 1pence | J28: =F28 | K28: =J28
A29: Cost of buildings | B29: 0 | C29: 2 | D29: 11.5 | F29: =B29+C29/20+D29/240 | H29: Total, 2 shilling 11.5pence
A30: Cost of buildings | F30: =SUM(F24:F28) | G30: =F30-F29 | H30: Total
A32: Dairy | B32: 0 | C32: 0 | D32: 4 | F32: 0.02 | H32: In small cloths bought for the dairy 4pence. | J32: =F32 | K32: =J32
A33: Dairy | B33: 0 | C33: 1 | D33: 8 | F33: 0.08 | H33: 5 bushels of salt bought 1 shilling 8pence. | J33: =F33 | K33: =J33
A34: Dairy | B34: 0 | C34: 0 | D34: 4 | F34: 0.02 | H34: earthenware pots and pans bought 4pence. | J34: =F34 | K34: =J34
A35: Dairy | B35: 0 | C35: 1 | D35: 4 | F35: 0.07 | H35: a press bought 1 shilling 4pence. | J35: =F35 | K35: =J35
A36: Dairy | B36: 0 | C36: 0 | D36: 4 | F36: 0.02 | H36: 2 buckets bought 4pence. | J36: =F36 | K36: =J36
A37: Dairy | B37: 0 | C37: 6 | D37: 0.5 | F37: 0.3 | H37: grease, copperas and verdigris bought 6 shilling 0.5pence. | J37: =F37 | K37: =J37
A38: Dairy | B38: 0 | C38: 4 | D38: 4 | F38: 0.22 | H38: forage bought to support the livestock and cows 4 shilling 4pence.
A39: Dairy | B39: 1 | C39: 0 | D39: 2.5 | F39: 1.01 | H39: 2 cows bought before calving £1 2.5pence, at 9 shilling 1.5pence for 1..
A40: Dairy | B40: 0 | C40: 9 | D40: 0 | F40: 0.45 | H40: a cow bought after calving 9 shilling. | J40: =F40 | K40: =J40
A41: Dairy | B41: 0 | C41: 3 | D41: 0 | F41: =B41+C41/20+D41/240 | H41: stipend of 1 dairymaid for the year 3 shilling
A42: Dairy | B42: 2 | C42: 6 | D42: 7 | F42: 2.33 | H42: Total, £2 6 shilling 7pence
A43: Dairy | F43: =SUM(F32:F41) | G43: =F43-F42 | H43: Total
A45: Threshing and winnowing | B45: 0 | C45: 5 | D45: 5.5 | F45: 0.27 | H45: In threshing and winnowing 8.5 quarters 2 bushels of wheat by piece-work, with 20 quarters of mancorn and 10 quarters of oats, 5 shilling 5.5pence, at 2pence a qr of wheat and mancorn threshed and 1pence per 5 quarters winnowed, and 0.75pence a qr of oats threshed and 1pence per 8 quarters winnowepence Total, 5 shilling 5.5pence
A46: Threshing and winnowing | F46: 0.27 | G46: 0 | H46: Total
A48: Harvest-time | B48: 0 | C48: 6 | D48: 4.5 | F48: 0.32 | H48: In corn reaped and bound by piece-work 6 shilling 4.5pence.
A49: Harvest-time | B49: 0 | C49: 3 | D49: 10.5 | F49: 0.19 | H49: expenses of 1 boon-work for reaping corn 3 shilling 10.5pence
A50: Harvest-time | C50: 10 | D50: 3 | F50: =B50+C50/20+D50/240 | H50: Total, 10 shilling 3pence
A51: Harvest-time | F51: 0.51 | G51: =F51-F50 | H51: Total
A53: Expenses for sowing and liveries | B53: 0 | C53: 4 | D53: 4 | F53: 0.22 | H53: In 1 qr of wheat bought 4 shilling 4pence.
A54: Expenses for sowing and liveries | B54: 2 | C54: 13 | D54: 0 | F54: 2.65 | H54: 19 quarters of mancorn bought for sowing £2 13 shilling, at 2 shilling 6pence a qr for 8 quarters, and 3 shilling a qr for 11 quarters.
A55: Expenses for sowing and liveries | B55: 2 | C55: 17 | D55: 4 | F55: 2.87 | H55: Total, £2 17 shilling 4pence
F56: =SUM(F53:F54) | G56: =F56-F55 | H56: Total
A58: Total of all expenses | B58: 7 | C58: 17 | D58: 1.5 | F58: 7.86 | H58: Total of all expenses, £7 17 shilling 1.5pence
A59: Total of all expenses | F59: 7.86 | G59: =F59-F58 | H59: Total
A61: Reeve | B61: 17 | C61: 1 | D61: 10 | F61: 17.09 | H61: In William de Wordly, reeve of Wargrave, £17 1 shilling 10pence
A63: Total of all expenses per account | F63: =F59
A64: Total of all expenses (calculated here) | F64: =F55+F51+F46+F43+F30+F22+F13 | G64: =F64-F63
A65: Total fixed investment | F65: =SUM(J3:J41)
A66: Total Demesne fixed investment | F66: =SUM(K3:K41)

Sheet Issues of the Grange
A1: Gross Output | B1: Total Quantity | C1: Account Total Quarters | D1: Bought in Total Quarters | E1: Received from churchscot | F1: Sold Total Quarters | G1: Difference Produced+Bought-Sold | H1: Weighted Average Price per Quarter | I1: Value of Total Production weighted
A2: wheat | B2: 9.75 | C2: 8.75 | D2: 1 | F2: 6.375 | G2: =B2-F2 | H2: 0.21666667 | I2: =H2*C2
A3: mancorn | B3: 58.875 | C3: 39.5 | D3: 19 | F3: 28.375 | G3: =B3-F3 | H3: 0.125 | I3: =H3*C3
A4: barley | B4: 19 | C4: 19 | D4: 0 | F4: 0.125 | G4: =B4-F4 | H4: 0.125 | I4: =H4*C4
A5: oats | B5: 20 | C5: 20 | D5: 0 | F5: 11.625 | G5: =B5-F5 | H5: 0.16666667 | I5: =H5*C5
A9: Total Production
A10: Sales of corn (as recorded in accounts)
A13: Net output | B13: Gross output | C13: Seed quarters | D13: Seed bushels | E13: Seed total quarters | F13: tithe quarters | G13: tithe bushels | H13: tithe total | I13: manorial servants quarters | J13: manorial servants bushels | K13: manorial servants total quarters | L13: output net of tithe, seed, liveries | M13: in stock from last year | N13: Price in £ | O13: Value of net output in £ | P13: Value of sales (in "Sale of Corn") in £
A14: wheat | B14: =B2 | C14: 3 | D14: 3 | E14: =C14+D14/8 | K14: =I14+J14/8 | L14: =B14-E14-H14-K14 | N14: =H2 | O14: =N14*L14
A15: mancorn | B15: =B3 | C15: 19 | E15: =C15+D15/8 | I15: =10 | J15: =3+5 | K15: =I15+J15/8 | L15: =B15-E15-H15-K15 | N15: =H3 | O15: =N15*L15
A16: barley | B16: =B4 | C16: 7 | D16: 3 | E16: =C16+D16/8 | K16: =I16+J16/8 | L16: =B16-E16-H16-K16 | N16: =H4 | O16: =N16*L16
A17: oats | B17: =B5 | C17: 15.5 | D17: 3 | E17: =C17+D17/8 | I17: 4 | J17: 1 | K17: =I17+J17/8 | L17: =B17-E17-H17-K17 | N17: =H5 | O17: =N17*L17
A19: Total

Sheet Issues of the Mills

Sheet Stock
A1: CULHAM STOCK ACCOUNT
C3: added | G3: subtracted
A4: Livestock | B4: Inherited stock | C4: added | D4: strays | E4: herbage | F4: churchscot | G4: of which in default | H4: sold | I4: in murrain | J4: accounted for elsewhere | K4: End-period stock | L4: cross-check | M4: stock building | N4: raw production | O4: Unit price (£) | P4: Value of stock (£) at given value | Q4: Value of stock (£) at sales prices | R4: Sales in (£) | S4: Value of stock building (£) | T4: Value of production (£) at sales prices | U4: Details
A5: Cart-horses
A6: Mares
A7: Plough horses | B7: 7 | K7: 7
A8: Colts (unspecified years)
A9: Colts (2 years)
A10: Colts (1 year)
A11: Foals
A12: Oxen | B12: 3 | C12: 2 | H12: 3 | K12: 2 | O12: =R12/H12 | R12: =Receipts!F32
A13: Bulls | B13: 1 | K13: 1
A14: Cows | B14: 23 | C14: =2+3 | H14: 2 | I14: =1 | K14: 25 | O14: =R14/H14 | R14: =Receipts!F33
A15: Steers | B15: 4 | J15: 4 | K15: 0
A16: Bullocks | B16: 9 | I16: 3 | K16: 6
A17: Yearlings | B17: 6 | I17: 3 | K17: 3
A18: Calves | B18: 22 | H18: 14 | I18: 1 | J18: =2 | K18: 5 | O18: =R18/H18 | R18: =Receipts!F34
A19: Wethers | B19: 112 | H19: 20 | I19: =5+6+1 | K19: 80 | O19: =R19/H19 | R19: =Receipts!F35
A20: Rams
A21: Ewes
A22: Hoggs
A23: Lambs
A24: Boars
A25: Sows
A26: Pigs
A27: Hoggets
A28: Piglets
A29: Swans
A30: Peacocks
A31: Total Value | R31: =SUM(R5:R29)
A34: Wool
A35: fleeces | C35: 87 | J35: =8+79 | K35: 0 | O35: 0.02 | T35: =O35*J35
A36: Coarse wool
A37: Lamb's wool
A38: Wool locks
A39: Wool sold at shearing
A40: Total wool | T40: =SUM(T35:T39)
A43: Hides
A44: Ox hides
A45: Mare
A46: Steer
A47: calves
A48: pigs
A49: Woolskins (incl. 10 in tithe)
A50: wethers
A51: rams
A52: ewes
A53: hoggs
A54: Woolskins (excl. 10 in tithe)
... A76: Eggs
A77: Cocks & hens from churchscot of customary tenants | F77: 20 | G77: 4 | H77: 16 | K77: 0 | O77: =R77/H77 | R77: =Receipts!F44 | T77: =O77*H77
A78: Sum of above
A79: Total | R79: =SUM(R76:R78) | T79: =T77
A82: Meat
A83: Beef
A84: Mutton
A85: Pork
A86: Total
A88: Cheese
A89: Winter cheese | C89: 37 | H89: 34 | J89: =3 | K89: 0 | O89: =R89/H89 | R89: =Receipts!F41 | T89: =O89*C89
A90: Summer cheese | C90: 159 | H90: 143 | J90: =15+1 | K90: 0 | O90: =R90/H90 | R90: =Receipts!F42 | T90: =O90*C90
A91: Total | R91: =SUM(R89:R90) | T91: =SUM(T89:T90)
A93: Butter
A94: Butter | C94: 20 | H94: 20 | K94: 0 | O94: =R94/H94 | R94: =Receipts!F43 | T94: =R94 | U94: measured in cloves
A95: Total | R95: =SUM(R94) | T95: =R95
A97: Total Dairy Sales
A100: Cider
A103: Additional Information (not necessarily useful)
A104: Utensils
A105: ploughs
A106: carts
A107: cart-ropes
A108: corn baskets
A109: seed-sacks
A110: seed basket
A111: locks for the doors
A112: lead vessel
... A129: brass posnets

Sheet raw data
A1: Heading | B1: Sentence | C1: Total in Pounds | D1: Pounds | E1: Shillings | F1: Pence | G1: Corn | H1: Total Quarters Except 1 | I1: Total Bushels Except 1 | J1: Total Corn Cross-Check | K1: Total Corn Manorial Account | L1: Corn Quantity Error | M1: Quarters 1 | N1: Bushels 1 | O1: Quarters 2 | P1: Bushels 2 | Q1: Quarters 3 | R1: Bushels 3 | S1: Quarters 4 | T1: Bushels 4 | U1: Quarters 5 | V1: Bushels 5 | W1: shilling a quarter 1 | X1: pence a quarter 1 | Y1: shilling a quarter 2 | Z1: pence a quarter 2 | AA1: shilling a quarter 3 | AB1: pence a quarter 3 | AC1: shilling a quarter 4 | AD1: pence a quarter 4 | AE1: shilling a bushel 1 | AF1: pence a bushel 1 | AG1: shilling a bushel 2 | AH1: pence a bushel 2 | AI1: shilling a bushel 3 | AJ1: pence a bushel 3 | AK1: shilling a bushel 4 | AL1: pence a bushel 4
A2: Rents of assize | B2: James de North', bailiff, and William Kepe, reeve, render account for £2 1 shilling.5pence for all rents of assize at Easter (22 April). | C2: 2.05 | D2: 2 | E2: 1 | F2: 0 | H2: 0 | I2: 0 | J2: 0 | K2: 0 | L2: 0 | M2: 0 | N2: 0
A3: Rents of assize | B3: £2 1 shilling .5pence at Michaelmas (29 September). | C3: 2.05 | D3: 2 | E3: 1 | F3: 0 | H3: 0 | I3: 0 | J3: 0 | K3: 0 | L3: 0 | M3: 0 | N3: 0
A4: Rents of assize | B4: Total, £4 2 shilling 1pence | C4: 4.1 | D4: 4 | E4: 2 | F4: 1 | H4: 0 | I4: 0 | J4: 0 | K4: 0 | L4: 0 | M4: 0 | N4: 0
A5: Increment | B5: Nothing this year from increment of rent. | C5: 0 | D5: 0 | E5: 0 | F5: 0 | H5: 0 | I5: 0 | J5: 0 | K5: 0 | L5: 0 | M5: 0 | N5: 0
A6: Quittances | B6: In quittance of 1 reeve for the year 1 shilling. | C6: 0.05 | D6: 0 | E6: 1 | F6: 0 | H6: 0 | I6: 0 | J6: 0 | K6: 0 | L6: 0 | M6: 0 | N6: 0
A7: Quittances | B7: 1 carter for the year 6pence. | C7: 0.03 | D7: 0 | E7: 0 | F7: 6 | H7: 0 | I7: 0 | J7: 0 | K7: 0 | L7: 0 | M7: 0 | N7: 0
A8: Quittances | B8: 1 shepherd for the year 6pence. | C8: 0.03 | D8: 0 | E8: 0 | F8: 6 | H8: 0 | I8: 0 | J8: 0 | K8: 0 | L8: 0 | M8: 0 | N8: 0
A9: Quittances | B9: 1 hayward for the year 6pence Total, 2 shilling 6pence | C9: 0.12 | D9: 0 | E9: 2 | F9: 6 | H9: 0 | I9: 0 | J9: 0 | K9: 0 | L9: 0 | M9: 0 | N9: 0
A10: Total of rents remaining | B10: Total of rents remaining, £3 19 shilling 7pence | C10: 3.98 | D10: 3 | E10: 19 | F10: 7 | H10: 0 | I10: 0 | J10: 0 | K10: 0 | L10: 0 | M10: 0 | N10: 0
A11: Annual gifts | B11: The same render account for 9 shilling 0.5pence from annual gifts at Easter. | C11: 0.45 | D11: 0 | E11: 9 | F11: 0.5 | H11: 0 | I11: 0 | J11: 0 | K11: 0 | L11: 0 | M11: 0 | N11: 0
A12: Annual gifts | B12: 9 shilling 0.5pence at Michaelmas. | C12: 0.45 | D12: 0 | E12: 9 | F12: 0.5 | H12: 0 | I12: 0 | J12: 0 | K12: 0 | L12: 0 | M12: 0 | N12: 0
A13: Annual gifts | B13: Total, 18 shilling 1pence | C13: 0.9 | D13: 0 | E13: 18 | F13: 1 | H13: 0 | I13: 0 | J13: 0 | K13: 0 | L13: 0 | M13: 0 | N13: 0
... A36: Issues of the manor | B36: Total, £10 17 shilling | C36: 10.85 | D36: 10 | E36: 17 | F36: 0 | H36: 0 | I36: 0 | J36: 0 | K36: 0 | L36: 0 | M36: 0 | N36: 0
A37: Sale of corn | B37: The same render account for £1 7 shilling 7.5pence from 6 quarters 3 bushels of wheat sold, at 4 shilling 4pence a quarters. | C37: 1.38 | D37: 1 | E37: 7 | F37: 7.5 | G37: wheat | H37: 6 | I37: 3 | J37: 6.375 | K37: 6.375 | L37: 0 | M37: 6 | N37: 3 | W37: 4 | X37: 4
A38: Sale of corn | B38: £3 10 shilling 11.25pence from 28 quarters 3 bushels of mancorn sold, at 2 shilling 6pence a quarters. | C38: 3.55 | D38: 3 | E38: 10 | F38: 11.25 | G38: mancorn | H38: 28 | I38: 3 | J38: 28.375 | K38: 28.375 | L38: 0 | M38: 28 | N38: 3 | W38: 2 | X38: 6
A39: Sale of corn | B39: 3.75pence from 1 bushels sold at the audit. | C39: 0.02 | D39: 0 | E39: 0 | F39: 3.75 | H39: 0 | I39: 1 | J39: 0.125 | K39: 0.125 | L39: 0 | M39: 0 | N39: 1
A40: Sale of corn | B40: £1 18 shilling 9pence from 11.5 quarters 1 bushels of barley sold, at 3 shilling 4pence a quarters. | C40: 1.94 | D40: 1 | E40: 18 | F40: 9 | G40: barley | H40: 11.5 | I40: 1 | J40: 11.625 | K40: 11.625 | L40: 0 | M40: 11.5 | N40: 1 | W40: 3 | X40: 4
A41: Sale of corn | B41: Total, £6 17 shilling 7.5pence | C41: 6.88 | D41: 6 | E41: 17 | F41: 7.5 | H41: 0 | I41: 0 | J41: 0 | K41: 0 | L41: 0 | M41: 0 | N41: 0
A42: Entry and marriage fines | B42: The same render account for 3 shilling 0.5pence for tithingpenny at the hundred-court of Martinmas. | C42: 0.15 | D42: 0 | E42: 3 | F42: 0.5 | H42: 0 | I42: 0 | J42: 0 | K42: 0 | L42: 0 | M42: 0 | N42: 0
A43: Entry and marriage fines | B43: 3 shilling 0.5pence at the hundred-court of Hockday. | C43: 0.15 | D43: 0 | E43: 3 | F43: 0.5 | H43: 0 | I43: 0 | J43: 0 | K43: 0 | L43: 0 | M43: 0 | N43: 0
A44: Entry and marriage fines | B44: 13 shilling 4pence from William, son of Walter Molendinarius, to have 4.5 acres of land which belonged to Walter his father. | C44: 0.67 | D44: 0 | E44: 13 | F44: 4 | H44: 0 | I44: 0 | J44: 0 | K44: 0 | L44: 0 | M44: 0 | N44: 0
A45: Entry and marriage fines | B45: 2 shilling from Alice, who was wife of Nicholas Nel, to have 1 messuage .5 virgate of land which belonged to Nicholas her husband. | C45: 0.1 | D45: 0 | E45: 2 | F45: 0 | H45: 0 | I45: 0 | J45: 0 | K45: 0 | L45: 0 | M45: 0 | N45: 0
A46: Entry and marriage fines | B46: 3 shilling from John, son of John Boul', to have 1 acre of purpresture by surrender of the said John his father. | C46: 0.15 | D46: 0 | E46: 3 | F46: 0 | H46: 0 | I46: 0 | J46: 0 | K46: 0 | L46: 0 | M46: 0 | N46: 0
A47: Entry and marriage fines | B47: 2 shilling from William le Walays for marrying Matilda his daughter outside the demesne. | C47: 0.1 | D47: 0 | E47: 2 | F47: 0 | H47: 0 | I47: 0 | J47: 0 | K47: 0 | L47: 0 | M47: 0 | N47: 0
A48: Entry and marriage fines | B48: Total, £1 6 shilling 5pence | C48: 1.32 | D48: 1 | E48: 6 | F48: 5 | H48: 0 | I48: 0 | J48: 0 | K48: 0 | L48: 0 | M48: 0 | N48: 0
A49: Perquisites | B49: The same render account for 1 shilling from Alice Croyll', Walter Ryd', John Gay, Agnes ate Strod' for breaking the assize of ale. | C49: 0.05 | D49: 0 | E49: 1 | F49: 0 | H49: 0 | I49: 0 | J49: 0 | K49: 0 | L49: 0 | M49: 0 | N49: 0
A50: Perquisites | B50: 3pence from Thomas Buthory for trespass. | C50: 0.01 | D50: 0 | E50: 0 | F50: 3 | H50: 0 | I50: 0 | J50: 0 | K50: 0 | L50: 0 | M50: 0 | N50: 0
A51: Perquisites | B51: 3pence from Thomas ate Wod' for trespass. | C51: 0.01 | D51: 0 | E51: 0 | F51: 3 | H51: 0 | I51: 0 | J51: 0 | K51: 0 | L51: 0 | M51: 0 | N51: 0
A52: Perquisites | B52: 3pence from Justina Juveni for the same. | C52: 0.01 | D52: 0 | E52: 0 | F52: 3 | H52: 0 | I52: 0 | J52: 0 | K52: 0 | L52: 0 | M52: 0 | N52: 0
... A87: Expenses for ploughs | B87: 1 sack bought 9pence Total, £1 8 shilling 5.5pence | C87: 1.42 | D87: 1 | E87: 8 | F87: 5.5 | H87: 0 | I87: 0 | J87: 0 | K87: 0 | L87: 0 | M87: 0 | N87: 0
A88: Expenses for sowing and liveries | B88: In 1 quarters of wheat bought 4 shilling 4pence. | C88: 0.22 | D88: 0 | E88: 4 | F88: 4 | G88: wheat | H88: 1 | I88: 0 | J88: 1 | K88: 1 | L88: 0 | M88: 1 | N88: 0
A89: Expenses for sowing and liveries | B89: 19 quarters of mancorn bought for sowing £2 13 shilling, at 2 shilling 6pence a quarters for 8 quarters, and 3 shilling a quarters for 11 quarters. | C89: 2.65 | D89: 2 | E89: 13 | F89: 0 | G89: mancorn | H89: 19 | I89: 0 | J89: 19 | K89: 19 | L89: 0 | M89: 19 | N89: 0 | O89: 8 | P89: 0 | Q89: 11 | R89: 0 | W89: 2 | X89: 6 | Y89: 3 | Z89: 0
A90: Expenses for sowing and liveries | B90: Total, £2 17 shilling 4pence | C90: 2.87 | D90: 2 | E90: 17 | F90: 4 | H90: 0 | I90: 0 | J90: 0 | K90: 0 | L90: 0 | M90: 0 | N90: 0
A91: Carts | B91: in 1 pair of wheels bought for the cart 2 shilling 2pence. | C91: 0.11 | D91: 0 | E91: 2 | F91: 2 | H91: 0 | I91: 0 | J91: 0 | K91: 0 | L91: 0 | M91: 0 | N91: 0
A92: Carts | B92: clouts with nails bought 10.5pence, and so much because it was at Farnham in order to collect timber and talwood at the water (quesivit taluerud' ad aq'). | C92: 0.04 | D92: 0 | E92: 0 | F92: 10.5 | H92: 0 | I92: 0 | J92: 0 | K92: 0 | L92: 0 | M92: 0 | N92: 0
A93: Carts | B93: . | C93: 0 | D93: 0 | E93: 0 | F93: 0 | H93: 0 | I93: 0 | J93: 0 | K93: 0 | L93: 0 | M93: 0 | N93: 0
A94: Carts | B94: grease for the cart 5pence. | C94: 0.02 | D94: 0 | E94: 0 | F94: 5 | H94: 0 | I94: 0 | J94: 0 | K94: 0 | L94: 0 | M94: 0 | N94: 0
A95: Carts | B95: fitting the cart with axles 3pence. | C95: 0.01 | D95: 0 | E95: 0 | F95: 3 | H95: 0 | I95: 0 | J95: 0 | K95: 0 | L95: 0 | M95: 0 | N95: 0
A96: Carts | B96: 1 pair of cart-shafts made from their own timber 4.5pence. | C96: 0.02 | D96: 0 | E96: 0 | F96: 4.5 | H96: 0 | I96: 0 | J96: 0 | K96: 0 | L96: 0 | M96: 0 | N96: 0
A97: Carts | B97: 1 pair of saddle-pads bought 6pence Total, 4 shilling 7pence | C97: 0.23 | D97: 0 | E97: 4 | F97: 6 | H97: 0 | I97: 0 | J97: 0 | K97: 0 | L97: 0 | M97: 0 | N97: 0
A98: Cost of buildings | B98: In roofing the byre at various times 1 shilling 4pence. | C98: 0.07 | D98: 0 | E98: 1 | F98: 4 | H98: 0 | I98: 0 | J98: 0 | K98: 0 | L98: 0 | M98: 0 | N98: 0
A99: Cost of buildings | B99: roofing the barn in places 7pence. | C99: 0.03 | D99: 0 | E99: 0 | F99: 7 | H99: 0 | I99: 0 | J99: 0 | K99: 0 | L99: 0 | M99: 0 | N99: 0
A100: Cost of buildings | B100: mending the walls of the byre at various times 9.5pence. | C100: 0.04 | D100: 0 | E100: 0 | F100: 9.5 | H100: 0 | I100: 0 | J100: 0 | K100: 0 | L100: 0 | M100: 0 | N100: 0
A101: Cost of buildings | B101: mending 1 barrow 2pence. | C101: 0.01 | D101: 0 | E101: 0 | F101: 2 | H101: 0 | I101: 0 | J101: 0 | K101: 0 | L101: 0 | M101: 0 | N101: 0
... A112: Dairy | B112: stipend of 1 dairymaid for the year 3 shilling Total, £2 6 shilling 7pence | C112: 2.33 | D112: 2 | E112: 6 | F112: 7 | H112: 0 | I112: 0 | J112: 0 | K112: 0 | L112: 0 | M112: 0 | N112: 0
A113: Threshing and winnowing | B113: In threshing and winnowing 8.5 quarters 2 bushels of wheat by piece-work, with 20 quarters of mancorn and 10 quarters of oats, 5 shilling 5.5pence, at 2pence a quarters of wheat and mancorn threshed and 1pence per 5 quarters winnowed, and 0.75pence a quarters of oats threshed and 1pence per 8 quarters winnowepence Total, 5 shilling 5.5pence | C113: 0.27 | D113: 0 | E113: 5 | F113: 5.5 | G113: oats, mancorn, wheat | H113: 43 | I113: 2 | J113: 43.25 | K113: 8.75 | L113: 34.5 | M113: 8.5 | N113: 2 | O113: 20 | P113: 0 | Q113: 10 | R113: 0 | S113: 5 | T113: 0 | U113: 8 | V113: 0
A114: Expenses for dung | B114: {henceforth dung should be carried by the lord's plough- horses}. | C114: 0 | D114: 0 | E114: 0 | F114: 0 | H114: 0 | I114: 0 | J114: 0 | K114: 0 | L114: 0 | M114: 0 | N114: 0
A115: Expenses for dung | B115: clearing dung in winter from the curia to the fields 1 shilling 6pence Total, 1 shilling 6pence | C115: 0.08 | D115: 0 | E115: 1 | F115: 6 | H115: 0 | I115: 0 | J115: 0 | K115: 0 | L115: 0 | M115: 0 | N115: 0
A116: Harvest-time | B116: In corn reaped and bound by piece-work 6 shilling 4.5pence. | C116: 0.32 | D116: 0 | E116: 6 | F116: 4.5 | H116: 0 | I116: 0 | J116: 0 | K116: 0 | L116: 0 | M116: 0 | N116: 0
A117: Harvest-time | B117: expenses of 1 boon-work for reaping corn 3 shilling 10.5pence Total, 10 shilling 3pence | C117: 0.19 | D117: 0 | E117: 3 | F117: 10.5 | H117: 0 | I117: 0 | J117: 0 | K117: 0 | L117: 0 | M117: 0 | N117: 0
A118: Total of all expenses | B118: Total of all expenses, £7 17 shilling 1.5pence | C118: 7.86 | D118: 7 | E118: 17 | F118: 1.5 | H118: 0 | I118: 0 | J118: 0 | K118: 0 | L118: 0 | M118: 0 | N118: 0
A119: Reeve | B119: In William de Wordly, reeve of Wargrave, £17 1 shilling 10pence | C119: 17.09 | D119: 17 | E119: 1 | F119: 10 | H119: 0 | I119: 0 | J119: 0 | K119: 0 | L119: 0 | M119: 0 | N119: 0
A120: Wheat | B120: (yield: two-fold less 6 bushels} | C120: 0 | D120: 0 | E120: 0 | F120: 0 | H120: 0 | I120: 6 | J120: 0.75 | K120: 0.75 | L120: 0 | M120: 0 | N120: 6
A121: Wheat | B121: The same render account for 8.5 quarters 2 bushels from the whole issue of wheat from the grange with the increment of the granary. | C121: 0 | D121: 0 | E121: 0 | F121: 0 | G121: wheat | H121: 8.5 | I121: 2 | J121: 8.75 | K121: 8.75 | L121: 0 | M121: 8.5 | N121: 2
A122: Wheat | B122: 1 quarters bought. | C122: 0 | D122: 0 | E122: 0 | F122: 0 | H122: 1 | I122: 0 | J122: 1 | K122: 1 | L122: 0 | M122: 1 | N122: 0
A123: Wheat | B123: Total, 9.5 quarters 2 bushels | C123: 0 | D123: 0 | E123: 0 | F123: 0 | H123: 9.5 | I123: 2 | J123: 9.75 | K123: 9.75 | L123: 0 | M123: 9.5 | N123: 2
A124: Wheat | B124: Sown over 9 acres measured by the perch which lie in the field upon the heath, 3 quarters 3 bushels Sold as noted above, 6 quarters 3 bushels | C124: 0 | D124: 0 | E124: 0 | F124: 0 | H124: 6 | I124: 6 | J124: 6.75 | K124: 3 | L124: 3.75 | M124: 3 | N124: 0 | O124: 0 | P124: 3 | Q124: 6 | R124: 3
A125: Mancorn | B125: {yield: two-and-a-half-fold plus 2 quarters} The same render account for 39.5 quarters from the whole issue of mancom from the grange with the increment of the granary. | C125: 0 | D125: 0 | E125: 0 | F125: 0 | H125: 39.5 | I125: 0 | J125: 39.5 | K125: 2 | L125: 37.5 | M125: 2 | N125: 0 | O125: 39.5 | P125: 0
A126: Mancorn | B126: 19 quarters bought. | C126: 0 | D126: 0 | E126: 0 | F126: 0 | H126: 19 | I126: 0 | J126: 19 | K126: 19 | L126: 0 | M126: 19 | N126: 0
A127: Mancorn | B127: Total, 58.5 quarters. | C127: 0 | D127: 0 | E127: 0 | F127: 0 | H127: 58.5 | I127: 0 | J127: 58.5 | K127: 58.5 | L127: 0 | M127: 58.5 | N127: 0
A128: Mancorn | B128: Sown over 51 acres measured by the perch as they lief in the field upon the heath, 19 quarters. | C128: 0 | D128: 0 | E128: 0 | F128: 0 | H128: 19 | I128: 0 | J128: 19 | K128: 19 | L128: 0 | M128: 19 | N128: 0
A129: Mancorn | B129: that is, 3 bushels an acre, less 1 bushels in all. | C129: 0 | D129: 0 | E129: 0 | F129: 0 | H129: 0 | I129: 1 | J129: 0.125 | K129: 0.375 | L129: -0.25 | M129: 0 | N129: 3 | O129: 0 | P129: 1
A130: Mancorn | B130: Delivered to 1 drover and 1 dairymaid for the year, 10 quarters 3 bushels, because they take a quarter every 10 weeks. | C130: 0 | D130: 0 | E130: 0 | F130: 0 | H130: 10 | I130: 3 | J130: 10.375 | K130: 10.375 | L130: 0 | M130: 10 | N130: 3
A131: Mancorn | B131: . | C131: 0 | D131: 0 | E131: 0 | F131: 0 | H131: 0 | I131: 0 | J131: 0 | K131: 0 | L131: 0 | M131: 0 | N131: 0
A132: Mancorn | B132: customary payment for the mowing of the meadows, 5 bushels Sold, 28 quarters 3 bushels Sold at the audit, 1 bushels | C132: 0 | D132: 0 | E132: 0 | F132: 0 | H132: 28 | I132: 4 | J132: 28.5 | K132: 0.625 | L132: 27.875 | M132: 0 | N132: 5 | O132: 28 | P132: 3 | Q132: 0 | R132: 1
A133: Barley | B133: {yield: three-fold less 1 bushels} | C133: 0 | D133: 0 | E133: 0 | F133: 0 | H133: 0 | I133: 1 | J133: 0.125 | K133: 0.125 | L133: 0 | M133: 0 | N133: 1
A134: Barley | B134: The same render account for 19 quarters from the whole issue of the grange with the increment of the granary. | C134: 0 | D134: 0 | E134: 0 | F134: 0 | H134: 19 | I134: 0 | J134: 19 | K134: 19 | L134: 0 | M134: 19 | N134: 0
A135: Barley | B135: Sown over 15 acres which lie in the field of la Doun', 7 quarters 3 bushels. | C135: 0 | D135: 0 | E135: 0 | F135: 0 | H135: 7 | I135: 3 | J135: 7.375 | K135: 7.375 | L135: 0 | M135: 7 | N135: 3
A136: Barley | B136: that is, 4 bushels an acre, less 1 bushels in all. | C136: 0 | D136: 0 | E136: 0 | F136: 0 | H136: 0 | I136: 1 | J136: 0.125 | K136: 0.5 | L136: -0.375 | M136: 0 | N136: 4 | O136: 0 | P136: 1
A137: Barley | B137: Sold, 11.5 quarters 1 bushels | C137: 0 | D137: 0 | E137: 0 | F137: 0 | H137: 11.5 | I137: 1 | J137: 11.625 | K137: 11.625 | L137: 0 | M137: 11.5 | N137: 1
A138: Oats | B138: {yield: 2 bushels more than sown} | C138: 0 | D138: 0 | E138: 0 | F138: 0 | H138: 0 | I138: 2 | J138: 0.25 | K138: 0.25 | L138: 0 | M138: 0 | N138: 2
A139: Oats | B139: The same render account for 20 quarters from the whole issue of oats from the grange with the increment of the granary. | C139: 0 | D139: 0 | E139: 0 | F139: 0 | G139: oats | H139: 20 | I139: 0 | J139: 20 | K139: 20 | L139: 0 | M139: 20 | N139: 0
A140: Oats | B140: Sown over 26 acres measured by the perch as they lie in the fields of la Doun' and Stanlych', 15.5 quarters 3 bushels. | C140: 0 | D140: 0 | E140: 0 | F140: 0 | H140: 15.5 | I140: 3 | J140: 15.875 | K140: 15.875 | L140: 0 | M140: 15.5 | N140: 3
A141: Oats | B141: that is, 5 bushels an acre, plus 2 bushels in all. | C141: 0 | D141: 0 | E141: 0 | F141: 0 | H141: 0 | I141: 2 | J141: 0.25 | K141: 0.625 | L141: -0.375 | M141: 0 | N141: 5 | O141: 0 | P141: 2
A142: Oats | B142: . | C142: 0 | D142: 0 | E142: 0 | F142: 0 | H142: 0 | I142: 0 | J142: 0 | K142: 0 | L142: 0 | M142: 0 | N142: 0
A143: Oats | B143: fodder of 7 plough-horses, 4 quarters 1 bushels | C143: 0 | D143: 0 | E143: 0 | F143: 0 | H143: 4 | I143: 1 | J143: 4.125 | K143: 4.125 | L143: 0 | M143: 4 | N143: 1
A144: Stock | B144: Plough-horses: 7 males remain from the previous year. | C144: 0 | D144: 0 | E144: 0 | F144: 0 | H144: 0 | I144: 0 | J144: 0 | K144: 0 | L144: 0 | M144: 0 | N144: 0
A145: Stock | B145: they remain. | C145: 0 | D145: 0 | E145: 0 | F145: 0 | H145: 0 | I145: 0 | J145: 0 | K145: 0 | L145: 0 | M145: 0 | N145: 0
A146: Stock | B146: Oxen: 3 remain from the previous year. | C146: 0 | D146: 0 | E146: 0 | F146: 0 | H146: 0 | I146: 0 | J146: 0 | K146: 0 | L146: 0 | M146: 0 | N146: 0
A147: Stock | B147: 2 added from stock. | C147: 0 | D147: 0 | E147: 0 | F147: 0 | H147: 0 | I147: 0 | J147: 0 | K147: 0 | L147: 0 | M147: 0 | N147: 0
A148: Stock | B148: Total, 5. 3 sold. | C148: 0 | D148: 0 | E148: 0 | F148: 0 | H148: 0 | I148: 0 | J148: 0 | K148: 0 | L148: 0 | M148: 0 | N148: 0
A149: Stock | B149: 2 remain. | C149: 0 | D149: 0 | E149: 0 | F149: 0 | H149: 0 | I149: 0 | J149: 0 | K149: 0 | L149: 0 | M149: 0 | N149: 0
A150: Stock | B150: Bulls: 1 remains from the previous year. | C150: 0 | D150: 0 | E150: 0 | F150: 0 | H150: 0 | I150: 0 | J150: 0 | K150: 0 | L150: 0 | M150: 0 | N150: 0
A151: Stock | B151: it remains. | C151: 0 | D151: 0 | E151: 0 | F151: 0 | H151: 0 | I151: 0 | J151: 0 | K151: 0 | L151: 0 | M151: 0 | N151: 0
A152: Stock | B152: Cows: 23 remain from the previous year. | C152: 0 | D152: 0 | E152: 0 | F152: 0 | H152: 0 | I152: 0 | J152: 0 | K152: 0 | L152: 0 | M152: 0 | N152: 0
A153: Stock | B153: 2 added from stock. | C153: 0 | D153: 0 | E153: 0 | F153: 0 | H153: 0 | I153: 0 | J153: 0 | K153: 0 | L153: 0 | M153: 0 | N153: 0
... A199: Stock | B199: 1 remains. | C199: 0 | D199: 0 | E199: 0 | F199: 0 | H199: 0 | I199: 0 | J199: 0 | K199: 0 | L199: 0 | M199: 0 | N199: 0

Sheet Issues of the Grange raw
A1: Heading | B1: Sentence | C1: Quarters 1_x | D1: Bushels 1_x | E1: Sown Quarters | F1: Sown Bushels | G1: Sown Total Quarters | H1: Bought in Quarters | I1: Bought in Bushels | J1: Bought in Total Quarters | K1: Tithe Quarters | L1: Tithe Bushels | M1: Tithe Total Quarters | N1: Manorial servants & livestock Quarters | O1: Manorial servants & livestock Bushels | P1: Manorial servants & livestock Total Quarters | Q1: Sold Quarters | R1: Sold Bushels | S1: Sold Total Quarters | T1: Account Quarters | U1: Account Bushels | V1: Account Total Quarters | W1: bought only | X1: Total Quarters Except 1 | Y1: Total Bushels Except 1 | Z1: Total Corn Cross-Check | AA1: Total Corn Manorial Account | AB1: Corn Quantity Error | AC1: Quarters 1_y | AD1: Bushels 1_y | AE1: Quarters 2 | AF1: Bushels 2 | AG1: Quarters 3 | AH1: Bushels 3 | AI1: Quarters 4 | AJ1: Bushels 4 | AK1: Quarters 5 | AL1: Bushels 5
A2: Reeve | B2: Total | C2: 0 | D2: 0 | E2: 0 | F2: 0 | G2: 0 | H2: 0 | I2: 0 | J2: 0 | K2: 0 | L2: 0 | M2: 0 | N2: 0 | O2: 0 | P2: 0 | Q2: 0 | R2: 0 | S2: 0 | T2: 0 | U2: 0 | V2: 0 | W2: 0
A3: Wheat | B3: (yield: two-fold less 6 bushels} | C3: 0 | D3: 0 | E3: 0 | F3: 0 | G3: 0 | H3: 0 | I3: 0 | J3: 0 | K3: 0 | L3: 0 | M3: 0 | N3: 0 | O3: 0 | P3: 0 | Q3: 0 | R3: 0 | S3: 0 | T3: 0 | U3: 0 | V3: 0 | W3: 0 | X3: 0 | Y3: 6 | Z3: 0.75 | AA3: 0.75 | AB3: 0 | AC3: 0 | AD3: 6
A4: Wheat | B4: The same render account for 8.5 quarters 2 bushels from the whole issue of wheat from the grange with the increment of the granary. | C4: 0 | D4: 0 | E4: 0 | F4: 0 | G4: 0 | H4: 0 | I4: 0 | J4: 0 | K4: 0 | L4: 0 | M4: 0 | N4: 0 | O4: 0 | P4: 0 | Q4: 0 | R4: 0 | S4: 0 | T4: 8.5 | U4: 2 | V4: 8.75 | W4: 0 | X4: 8.5 | Y4: 2 | Z4: 8.75 | AA4: 8.75 | AB4: 0 | AC4: 8.5 | AD4: 2
A5: Wheat | B5: 1 qr bought. | C5: 0 | D5: 0 | E5: 0 | F5: 0 | G5: 0 | H5: 0 | I5: 0 | J5: 0 | K5: 0 | L5: 0 | M5: 0 | N5: 0 | O5: 0 | P5: 0 | Q5: 0 | R5: 0 | S5: 0 | T5: 0 | U5: 0 | V5: 0 | W5: 0
A6: Wheat | B6: Total, 9.5 quarters 2 bushels | C6: 0 | D6: 0 | E6: 0 | F6: 0 | G6: 0 | H6: 0 | I6: 0 | J6: 0 | K6: 0 | L6: 0 | M6: 0 | N6: 0 | O6: 0 | P6: 0 | Q6: 0 | R6: 0 | S6: 0 | T6: 0 | U6: 0 | V6: 0 | W6: 0 | X6: 9.5 | Y6: 2 | Z6: 9.75 | AA6: 9.75 | AB6: 0 | AC6: 9.5 | AD6: 2
A7: Wheat | B7: Sown over 9 acres measured by the perch which lie in the field upon the heath, 3 quarters 3 bushels Sold as noted above, 6 quarters 3 bushels | C7: 0 | D7: 0 | E7: 9 | F7: 6 | G7: 9.75 | H7: 0 | I7: 0 | J7: 0 | K7: 0 | L7: 0 | M7: 0 | N7: 0 | O7: 0 | P7: 0 | Q7: 9 | R7: 6 | S7: 9.75 | T7: 0 | U7: 0 | V7: 0 | W7: 0 | X7: 6 | Y7: 6 | Z7: 6.75 | AA7: 3 | AB7: 3.75 | AC7: 3 | AD7: 0 | AE7: 0 | AF7: 3 | AG7: 6 | AH7: 3
A8: Wheat | B8: Total | C8: 0 | D8: 0 | E8: 0 | F8: 0 | G8: 0 | H8: 0 | I8: 0 | J8: 0 | K8: 0 | L8: 0 | M8: 0 | N8: 0 | O8: 0 | P8: 0 | Q8: 0 | R8: 0 | S8: 0 | T8: 0 | U8: 0 | V8: 0 | W8: 0
A9: Mancorn | B9: {yield: two-and-a-half-fold plus 2 quarters} The same render account for 39.5 quarters from the whole issue of mancom from the grange with the increment of the granary. | C9: 0 | D9: 0 | E9: 0 | F9: 0 | G9: 0 | H9: 0 | I9: 0 | J9: 0 | K9: 0 | L9: 0 | M9: 0 | N9: 0 | O9: 0 | P9: 0 | Q9: 0 | R9: 0 | S9: 0 | T9: 41.5 | U9: 0 | V9: 41.5 | W9: 0 | X9: 39.5 | Y9: 0 | Z9: 39.5 | AA9: 2 | AB9: 37.5 | AC9: 2 | AD9: 0 | AE9: 39.5 | AF9: 0
A10: Mancorn | B10: 19 quarters bought. | C10: 0 | D10: 0 | E10: 0 | F10: 0 | G10: 0 | H10: 19 | I10: 0 | J10: 19 | K10: 0 | L10: 0 | M10: 0 | N10: 0 | O10: 0 | P10: 0 | Q10: 0 | R10: 0 | S10: 0 | T10: 0 | U10: 0 | V10: 0 | W10: 0 | X10: 19 | Y10: 0 | Z10: 19 | AA10: 19 | AB10: 0 | AC10: 19 | AD10: 0
A11: Mancorn | B11: Total, 58.5 quarters. | C11: 0 | D11: 0 | E11: 0 | F11: 0 | G11: 0 | H11: 0 | I11: 0 | J11: 0 | K11: 0 | L11: 0 | M11: 0 | N11: 0 | O11: 0 | P11: 0 | Q11: 0 | R11: 0 | S11: 0 | T11: 0 | U11: 0 | V11: 0 | W11: 0 | X11: 58.5 | Y11: 0 | Z11: 58.5 | AA11: 58.5 | AB11: 0 | AC11: 58.5 | AD11: 0
A12: Mancorn | B12: Sown over 51 acres measured by the perch as they lief in the field upon the heath, 19 quarters. | C12: 0 | D12: 0 | E12: 19 | F12: 0 | G12: 19 | H12: 0 | I12: 0 | J12: 0 | K12: 0 | L12: 0 | M12: 0 | N12: 0 | O12: 0 | P12: 0 | Q12: 0 | R12: 0 | S12: 0 | T12: 0 | U12: 0 | V12: 0 | W12: 0 | X12: 19 | Y12: 0 | Z12: 19 | AA12: 19 | AB12: 0 | AC12: 19 | AD12: 0
A13: Mancorn | B13: that is, 3 bushels an acre, less 1 bushels in all. | C13: 0 | D13: 0 | E13: 0 | F13: 0 | G13: 0 | H13: 0 | I13: 0 | J13: 0 | K13: 0 | L13: 0 | M13: 0 | N13: 0 | O13: 0 | P13: 0 | Q13: 0 | R13: 0 | S13: 0 | T13: 0 | U13: 0 | V13: 0 | W13: 0 | X13: 0 | Y13: 1 | Z13: 0.125 | AA13: 0.375 | AB13: -0.25 | AC13: 0 | AD13: 3 | AE13: 0 | AF13: 1
A14: Mancorn | B14: Delivered to 1 drover and 1 dairymaid for the year, 10 quarters 3 bushels, because they take a quarter every 10 weeks. | C14: 0 | D14: 0 | E14: 0 | F14: 0 | G14: 0 | H14: 0 | I14: 0 | J14: 0 | K14: 0 | L14: 0 | M14: 0 | N14: 0 | O14: 0 | P14: 0 | Q14: 0 | R14: 0 | S14: 0 | T14: 0 | U14: 0 | V14: 0 | W14: 0 | X14: 10 | Y14: 3 | Z14: 10.375 | AA14: 10.375 | AB14: 0 | AC14: 10 | AD14: 3
A15: Mancorn | B15: . | C15: 0 | D15: 0 | E15: 0 | F15: 0 | G15: 0 | H15: 0 | I15: 0 | J15: 0 | K15: 0 | L15: 0 | M15: 0 | N15: 0 | O15: 0 | P15: 0 | Q15: 0 | R15: 0 | S15: 0 | T15: 0 | U15: 0 | V15: 0 | W15: 0 | X15: 0 | Y15: 0 | Z15: 0 | AA15: 0 | AB15: 0 | AC15: 0 | AD15: 0
A16: Mancorn | B16: customary payment for the mowing of the meadows, 5 bushels Sold, 28 quarters 3 bushels Sold at the audit, 1 bushels | C16: 0 | D16: 0 | E16: 0 | F16: 0 | G16: 0 | H16: 0 | I16: 0 | J16: 0 | K16: 0 | L16: 0 | M16: 0 | N16: 0 | O16: 0 | P16: 0 | Q16: 28 | R16: 3 | S16: 28.375 | T16: 0 | U16: 0 | V16: 0 | W16: 0 | X16: 28 | Y16: 4 | Z16: 28.5 | AA16: 0.625 | AB16: 27.875 | AC16: 0 | AD16: 5 | AE16: 28 | AF16: 3 | AG16: 0 | AH16: 1
A17: Mancorn | B17: Total | C17: 0 | D17: 0 | E17: 0 | F17: 0 | G17: 0 | H17: 0 | I17: 0 | J17: 0 | K17: 0 | L17: 0 | M17: 0 | N17: 0 | O17: 0 | P17: 0 | Q17: 0 | R17: 0 | S17: 0 | T17: 0 | U17: 0 | V17: 0 | W17: 0
A18: Barley | B18: {yield: three-fold less 1 bushels} | C18: 0 | D18: 0 | E18: 0 | F18: 0 | G18: 0 | H18: 0 | I18: 0 | J18: 0 | K18: 0 | L18: 0 | M18: 0 | N18: 0 | O18: 0 | P18: 0 | Q18: 0 | R18: 0 | S18: 0 | T18: 0 | U18: 0 | V18: 0 | W18: 0 | X18: 0 | Y18: 1 | Z18: 0.125 | AA18: 0.125 | AB18: 0 | AC18: 0 | AD18: 1
A19: Barley | B19: The same render account for 19 quarters from the whole issue of the grange with the increment of the granary. | C19: 0 | D19: 0 | E19: 0 | F19: 0 | G19: 0 | H19: 0 | I19: 0 | J19: 0 | K19: 0 | L19: 0 | M19: 0 | N19: 0 | O19: 0 | P19: 0 | Q19: 0 | R19: 0 | S19: 0 | T19: 19 | U19: 0 | V19: 19 | W19: 0 | X19: 19 | Y19: 0 | Z19: 19 | AA19: 19 | AB19: 0 | AC19: 19 | AD19: 0
A20: Barley | B20: Sown over 15 acres which lie in the field of la Doun', 7 quarters 3 bushels. | C20: 0 | D20: 0 | E20: 7 | F20: 3 | G20: 7.375 | H20: 0 | I20: 0 | J20: 0 | K20: 0 | L20: 0 | M20: 0 | N20: 0 | O20: 0 | P20: 0 | Q20: 0 | R20: 0 | S20: 0 | T20: 0 | U20: 0 | V20: 0 | W20: 0 | X20: 7 | Y20: 3 | Z20: 7.375 | AA20: 7.375 | AB20: 0 | AC20: 7 | AD20: 3
A21: Barley | B21: that is, 4 bushels an acre, less 1 bushels in all. | C21: 0 | D21: 0 | E21: 0 | F21: 0 | G21: 0 | H21: 0 | I21: 0 | J21: 0 | K21: 0 | L21: 0 | M21: 0 | N21: 0 | O21: 0 | P21: 0 | Q21: 0 | R21: 0 | S21: 0 | T21: 0 | U21: 0 | V21: 0 | W21: 0 | X21: 0 | Y21: 1 | Z21: 0.125 | AA21: 0.5 | AB21: -0.375 | AC21: 0 | AD21: 4 | AE21: 0 | AF21: 1
A22: Barley | B22: Sold, 11.5 quarters 1 bushels | C22: 0 | D22: 0 | E22: 0 | F22: 0 | G22: 0 | H22: 0 | I22: 0 | J22: 0 | K22: 0 | L22: 0 | M22: 0 | N22: 0 | O22: 0 | P22: 0 | Q22: 11.5 | R22: 1 | S22: 11.625 | T22: 0 | U22: 0 | V22: 0 | W22: 0 | X22: 11.5 | Y22: 1 | Z22: 11.625 | AA22: 11.625 | AB22: 0 | AC22: 11.5 | AD22: 1
A23: Barley | B23: Total | C23: 0 | D23: 0 | E23: 0 | F23: 0 | G23: 0 | H23: 0 | I23: 0 | J23: 0 | K23: 0 | L23: 0 | M23: 0 | N23: 0 | O23: 0 | P23: 0 | Q23: 0 | R23: 0 | S23: 0 | T23: 0 | U23: 0 | V23: 0 | W23: 0
A24: Oats | B24: {yield: 2 bushels more than sown} | C24: 0 | D24: 0 | E24: 0 | F24: 0 | G24: 0 | H24: 0 | I24: 0 | J24: 0 | K24: 0 | L24: 0 | M24: 0 | N24: 0 | O24: 0 | P24: 0 | Q24: 0 | R24: 0 | S24: 0 | T24: 0 | U24: 0 | V24: 0 | W24: 0 | X24: 0 | Y24: 2 | Z24: 0.25 | AA24: 0.25 | AB24: 0 | AC24: 0 | AD24: 2
A25: Oats | B25: The same render account for 20 quarters from the whole issue of oats from the grange with the increment of the granary. | C25: 0 | D25: 0 | E25: 0 | F25: 0 | G25: 0 | H25: 0 | I25: 0 | J25: 0 | K25: 0 | L25: 0 | M25: 0 | N25: 0 | O25: 0 | P25: 0 | Q25: 0 | R25: 0 | S25: 0 | T25: 20 | U25: 0 | V25: 20 | W25: 0 | X25: 20 | Y25: 0 | Z25: 20 | AA25: 20 | AB25: 0 | AC25: 20 | AD25: 0
A26: Oats | B26: Sown over 26 acres measured by the perch as they lie in the fields of la Doun' and Stanlych', 15.5 quarters 3 bushels. | C26: 0 | D26: 0 | E26: 15.5 | F26: 3 | G26: 15.875 | H26: 0 | I26: 0 | J26: 0 | K26: 0 | L26: 0 | M26: 0 | N26: 0 | O26: 0 | P26: 0 | Q26: 0 | R26: 0 | S26: 0 | T26: 0 | U26: 0 | V26: 0 | W26: 0 | X26: 15.5 | Y26: 3 | Z26: 15.875 | AA26: 15.875 | AB26: 0 | AC26: 15.5 | AD26: 3
A27: Oats | B27: that is, 5 bushels an acre, plus 2 bushels in all. | C27: 0 | D27: 0 | E27: 0 | F27: 0 | G27: 0 | H27: 0 | I27: 0 | J27: 0 | K27: 0 | L27: 0 | M27: 0 | N27: 0 | O27: 0 | P27: 0 | Q27: 0 | R27: 0 | S27: 0 | T27: 0 | U27: 0 | V27: 0 | W27: 0 | X27: 0 | Y27: 2 | Z27: 0.25 | AA27: 0.625 | AB27: -0.375 | AC27: 0 | AD27: 5 | AE27: 0 | AF27: 2
A28: Oats | B28: . | C28: 0 | D28: 0 | E28: 0 | F28: 0 | G28: 0 | H28: 0 | I28: 0 | J28: 0 | K28: 0 | L28: 0 | M28: 0 | N28: 0 | O28: 0 | P28: 0 | Q28: 0 | R28: 0 | S28: 0 | T28: 0 | U28: 0 | V28: 0 | W28: 0 | X28: 0 | Y28: 0 | Z28: 0 | AA28: 0 | AB28: 0 | AC28: 0 | AD28: 0
A29: Oats | B29: fodder of 7 plough-horses, 4 quarters 1 bushels | C29: 0 | D29: 0 | E29: 0 | F29: 0 | G29: 0 | H29: 0 | I29: 0 | J29: 0 | K29: 0 | L29: 0 | M29: 0 | N29: 4 | O29: 1 | P29: 4.125 | Q29: 0 | R29: 0 | S29: 0 | T29: 0 | U29: 0 | V29: 0 | W29: 0 | X29: 4 | Y29: 1 | Z29: 4.125 | AA29: 4.125 | AB29: 0 | AC29: 4 | AD29: 1

Sheet Sale of Corn Prices
A1: Heading | B1: Sentence | C1: Total in Pounds | D1: Pounds | E1: Shillings | F1: Pence | G1: Corn | H1: Total Quarters Except 1 | I1: Total Bushels Except 1 | J1: Total Corn Cross-Check | K1: Total Corn Manorial Account | L1: Corn Quantity Error | M1: Quarters 0 | N1: Bushels 0 | O1: shilling a quarter 1 | P1: pence a quarter 1 | Q1: Quarters 1 | R1: Bushels 1 | S1: shilling a quarter 2 | T1: pence a quarter 2 | U1: Quarters 2 | V1: Bushels 2 | W1: shilling a quarter 3 | X1: pence a quarter 3 | Y1: Quarters 3 | Z1: Bushels 3 | AA1: shilling a quarter 4 | AB1: pence a quarter 4 | AC1: Quarters 4 | AD1: Bushels 4 | AE1: £ a quarter 1 | AF1: £ a quarter 2 | AG1: £ a quarter 3 | AH1: £ a quarter 4 | AI1: Quarters Sold | AJ1: Weighted Average Price per Quarter | AK1: Non-Weighted Average Price per Quarter | AL1: Corn lowercase
A2: Sale of corn | B2: The same render account for £1 7 shilling 7.5pence from 6 quarters 3 bushels of wheat sold, at 4 shilling 4pence a quarters. | C2: 1.38 | D2: 1 | E2: 7 | F2: 7.5 | G2: wheat | H2: 6 | I2: 3 | J2: 6.375 | K2: 6.375 | L2: 0 | M2: 6 | N2: 3 | O2: 4 | P2: 4 | AE2: 0.21666667 | AI2: 6.375 | AJ2: 0.21666667 | AK2: 0.21666667 | AL2: wheat
A3: Sale of corn | B3: £3 10 shilling 11.25pence from 28 quarters 3 bushels of mancorn sold, at 2 shilling 6pence a quarters. | C3: 3.55 | D3: 3 | E3: 10 | F3: 11.25 | G3: mancorn | H3: 28 | I3: 3 | J3: 28.375 | K3: 28.375 | L3: 0 | M3: 28 | N3: 3 | O3: 2 | P3: 6 | AE3: 0.125 | AI3: 28.375 | AJ3: 0.125 | AK3: 0.125 | AL3: mancorn
A4: Sale of corn | B4: 3.75pence from 1 bushels sold at the audit. | C4: 0.02 | D4: 0 | E4: 0 | F4: 3.75 | H4: 0 | I4: 1 | J4: 0.125 | K4: 0.125 | L4: 0 | M4: 0 | N4: 1 | AE4: 0.16 | AI4: 0.125 | AJ4: 0.16 | AK4: 0.16
A5: Sale of corn | B5: £1 18 shilling 9pence from 11.5 quarters 1 bushels of barley sold, at 3 shilling 4pence a quarters. | C5: 1.94 | D5: 1 | E5: 18 | F5: 9 | G5: barley | H5: 11.5 | I5: 1 | J5: 11.625 | K5: 11.625 | L5: 0 | M5: 11.5 | N5: 1 | O5: 3 | P5: 4 | AE5: 0.16666667 | AI5: 11.625 | AJ5: 0.16666667 | AK5: 0.16666667 | AL5: barley
A6: Sale of corn | B6: Total, £6 17 shilling 7.5pence | C6: 6.88 | D6: 6 | E6: 17 | F6: 7.5 | H6: 0 | I6: 0 | J6: 0 | K6: 0 | L6: 0 | M6: 0 | N6: 0 | AE6: inf | AI6: 0 | AJ6: inf | AK6: inf
