Workbook

Sheet Droxford Overview - Completed
A1: DROXFORD OVERVIEW - COMPLETED | B1: Total in £ | C1: Error | D1: Note
A2: CASH ACCOUNT
A3: RECEIPTS
A4: Arrears total | B4: 25.94
A5: Rents of assize total | B5: 24.77
A6: Quittances total | B6: 0.425625
A7: Defaults of rent total | B7: 0.5
A8: Defaults of rent through the pestilence total
A9: Cotlands defaults total
A10: Cotlands total
A11: Total of quittances and defaults of rent total | B11: 0.92
A12: Total of rents remaining clear total
A13: Farms total
A14: Annual recognizances total | B14: 0.1
A15: Issues of the Manor total | B15: 22.057083
A16: Issues of the tenements in the lord's hands total
A17: Sale of labour services total
A18: Sale of corn total | B18: 27.96
A19: Entry and marriage fines total | B19: 2.18
A20: Pleas & perquisites total
A21: Forfeited chattels total
A22: Farm of the demesne land total
A23: Total of all receipts (calculated here) | B23: =SUM(B5:B22)
A24: Total of all receipts (calculated here) incl arrears | B24: =SUM(B4:B22)
A25: Total recorded in the accounts excl. arrears | B25: 80.0875 | C25: =B23-B25
A26: Total recorded in the accounts incl. arrears | B26: =B25+B4
A29: EXPENSES
A30: Cost of ploughs total | B30: 3.69
A31: Purchase of corn total
A32: Cost of carts and wagons total
A33: Cost of dairy total
A34: Purchase of stock total
A35: Sheepcote total | B35: 1.0141667
A36: Cost of buildings total | B36: 2.2
A37: Threshing total | B37: 1.6704167
A38: Barley expenses
A39: Expenses of the harvest total
A40: Necessary expenses
A41: Wages of the bailiff
A42: Steward's expenses total | B42: 0.51
A43: Annual fees
A44: Total of all expenses per account | B44: 10.99
A45: Total of all expenses (calculated here) | B45: 13.05125
A46: Total fixed investment | B46: 4.3533333
A47: Total Demesne fixed investment | B47: 4.3533333
A49: Owed by the reeve | B49: =B23-B45
A50: From accounts | B50: 10.99
A52: Allowances
A53: Cash deliveries
A54: Sum of the above | B54: =SUM(B52:B53)
A55: Total of all allowances and cash deliveries in accounts
A57: Net amount owed | B57: =B50-B54
A58: Net amount owed in accounts
A60: GRANGE ACCOUNT | B60: Total Production | D60: Value of total gross production in £ | E60: Value of total net production in £
A61: Grange | B61: qrs | C61: bus
A62: Wheat | B62: 58.125 | E62: 11.822994
A63: Rye | B63: 2.0625
A64: Dredge
A65: Curall | B65: 6.375 | E65: 1.0625
A66: Barley | B66: 93.125 | E66: 7.4618132
A67: Oats | B67: 108.25 | E67: 4.1583333
A68: Beans
A69: Peas | B69: 11.875 | E69: 1.0375
A70: Vetches | E70: 0.95833333
A71: Total value of gross production (sum of the above)
A72: Total value of net production
A73: Value of sales
A75: MILL ACCOUNT | B75: Total Production | D75: Total in £
A76: Issues of the mill | B76: qrs | C76: bus
A77: Wheat
A78: Oatmeal
A79: 1st grade malt
A80: 2nd grade malt
A81: Maslin
A82: Total value of production (sum of the above)
A83: Value of sales
A85: STOCK ACCOUNT
A86: Livestock | B86: Begin stock | C86: End stock | D86: Stockbuilding | F86: Value of stock in £ | G86: Value of stockbuilding
A87: Cart-horses | B87: 2 | C87: 2 | D87: 0 | F87: 1 | G87: 0
A88: Mares | D88: =C88-B88 | F88: ='Stock'!K6*'Stock'!O6 | G88: =D88*'Stock'!O6
A89: Plough horses | B89: 4 | C89: 4 | D89: 0 | F89: 0.9 | G89: 0
A90: Colts (2 years) | D90: =C90-B90 | F90: ='Stock'!K9*'Stock'!O9 | G90: =D90*'Stock'!O9
A91: Colts (2 years) | D91: =C91-B91 | F91: ='Stock'!K9*'Stock'!O9 | G91: =D91*'Stock'!O9
A92: Colts (1 year) | D92: =C92-B92 | F92: ='Stock'!K10*'Stock'!O10 | G92: =D92*'Stock'!O10
A93: Foals | D93: =C93-B93 | F93: ='Stock'!K11*'Stock'!O11 | G93: =D93*'Stock'!O11
A94: Oxen | B94: 17 | C94: 24 | D94: 7 | F94: 10.8 | G94: 3.15
A95: Bulls | B95: 1 | C95: 1 | D95: 0 | F95: ='Stock'!K13*'Stock'!O13 | G95: =D95*'Stock'!O13
A96: Cows | B96: 21 | C96: 19 | D96: -2 | F96: 7.695 | G96: -0.81
A97: Steers | B97: 6 | C97: 0 | D97: -6 | F97: ='Stock'!K15*'Stock'!O15 | G97: =D97*'Stock'!O15
A98: Bullocks | B98: 6 | C98: 5 | D98: -1 | F98: ='Stock'!K16*'Stock'!O16 | G98: =D98*'Stock'!O16
A99: Yearlings | B99: 5 | C99: 5 | D99: 0 | F99: ='Stock'!K17*'Stock'!O17 | G99: =D99*'Stock'!O17
A100: Calves | B100: 13 | C100: 6 | D100: -7 | F100: 0.3 | G100: -0.35
A101: Wethers | B101: 280 | C101: 243 | D101: -37 | F101: 12.15 | G101: -1.85
A102: Rams | B102: 10 | C102: 10 | D102: 0 | F102: ='Stock'!K20*'Stock'!O20 | G102: =D102*'Stock'!O20
A103: Ewes | B103: 380 | C103: 353 | D103: -27 | F103: 17.65 | G103: -1.35
A104: Hoggs | B104: 75 | C104: 0 | D104: -75 | F104: ='Stock'!K22*'Stock'!O22 | G104: =D104*'Stock'!O22
A105: Lambs | B105: 299 | C105: 160 | D105: -139 | F105: 0 | G105: 0
A106: Boars | D106: =C106-B106 | F106: ='Stock'!K24*'Stock'!O24 | G106: =D106*'Stock'!O24
A107: Sows | B107: 3 | C107: 2 | D107: -1 | F107: ='Stock'!K25*'Stock'!O25 | G107: =D107*'Stock'!O25
A108: Pigs | B108: 33 | C108: 20 | D108: -13 | F108: 2.536 | G108: -1.6484
...

Sheet Prices
A1: Meat & Dairy Prices
C2: 1301 | D2: 1302 | E2: Average
A3: Beef | B3: £ per lb | C3: 0.0033351854 | D3: 0.0032608538 | E3: =AVERAGE(C3:D3)
A4: Mutton | B4: £ per lb | C4: 0.0036593977 | D4: 0.0037125513 | E4: =AVERAGE(C4:D4)
A5: Pork | B5: £ per lb | C5: 0.0038431326 | D5: 0.0037574803 | E5: =AVERAGE(C5:D5)
A6: Cheese | B6: £ per lb | C6: 0.0055768754 | D6: 0.0056654898 | E6: =AVERAGE(C6:D6)
A7: Butter | B7: £ per lb | C7: 0.0036626221 | D7: 0.0035935077 | E7: =AVERAGE(C7:D7)
A8: Milk | B8: £ per gallon | C8: 0.0055768754 | D8: 0.0056654898 | E8: =AVERAGE(C8:D8)

Sheet Labour Rents

Sheet Overview
A1: DROXFORD
A2: CASH ACCOUNT | B2: Total in £ | C2: Error | D2: Note
A3: RECEIPTS
A4: Arrears total
A5: Rents of assize total
A6: Quittances total
A7: Defaults of rent total
A8: Defaults of rent through the pestilence total
A9: Cotlands defaults total
A10: Cotlands total
A11: Total of quittances and defaults of rent total
A12: Total of rents remaining clear total
A13: Farms total
A14: Annual recognizances total
... A22: Farm of the demesne land total
A23: Total of all receipts (calculated here) | B23: =Receipts!F126
A24: Total of all receipts (calculated here) incl arrears | B24: =Receipts!F127
A25: Total recorded in the accounts excl. arrears | B25: =Receipts!F125 | C25: =B25-B23
A26: Total recorded in the accounts incl. arrears
A29: EXPENSES
A30: Cost of ploughs total
A31: Purchase of corn total
A32: Cost of carts and wagons total
A33: Cost of dairy total
A34: Purchase of stock total
A35: Sheepcote total
A36: Cost of buildings total
A37: Threshing total
A38: Barley expenses
A39: Expenses of the harvest total
... A43: Annual fees
A44: Total of all expenses per account | B44: =Expenses!F104
A45: Total of all expenses (calculated here) | B45: =Expenses!F105
A46: Total fixed investment | B46: =Expenses!F106
A47: Total Demesne fixed investment | B47: =Expenses!F107
A49: Owed by the reeve
A50: From accounts
A52: Allowances
A53: Cash deliveries
A54: Sum of the above
A55: Total of all allowances and cash deliveries in accounts
A57: Net amount owed
A58: Net amount owed in accounts
A60: GRANGE ACCOUNT | B60: Total Production
A61: Grange | B61: qrs | E61: Value of total gross production in £ | F61: Value of total net production in £
A62: wheat | B62: ='Issues of the Grange'!B2 | E62: ='Issues of the Grange'!I2 | F62: ='Issues of the Grange'!O17
A63: curall | B63: ='Issues of the Grange'!B3 | E63: ='Issues of the Grange'!I3 | F63: ='Issues of the Grange'!O18
A64: rye | B64: ='Issues of the Grange'!B4 | E64: ='Issues of the Grange'!I4 | F64: ='Issues of the Grange'!O19
A65: maslin | B65: ='Issues of the Grange'!B5 | E65: ='Issues of the Grange'!I5 | F65: ='Issues of the Grange'!O20
A66: bere | B66: ='Issues of the Grange'!B6 | E66: ='Issues of the Grange'!I6 | F66: ='Issues of the Grange'!O21
A67: barley | B67: ='Issues of the Grange'!B7 | E67: ='Issues of the Grange'!I7 | F67: ='Issues of the Grange'!O22
A68: oats | B68: ='Issues of the Grange'!B8 | E68: ='Issues of the Grange'!I8 | F68: ='Issues of the Grange'!O23
A69: peas | B69: ='Issues of the Grange'!B9 | E69: ='Issues of the Grange'!I9 | F69: ='Issues of the Grange'!O24
A70: vetches | B70: ='Issues of the Grange'!B10 | E70: ='Issues of the Grange'!I10 | F70: ='Issues of the Grange'!O25
A71: Total value of gross production (sum of the above) | E71: =SUM(E62:E70)
A72: Total value of net production | E72: =SUM(F62:F70)
A73: Value of sales | E73: =Receipts!F109
A75: MILL ACCOUNT
A76: Issues of the mill
A77: Wheat
A78: Oatmeal
A79: 1st grade malt
A80: 2nd grade malt
A81: Maslin
A82: Total value of production (sum of the above)
A83: Value of sales
A85: STOCK ACCOUNT
A86: Livestock | B86: Sales value in £
A87: Cart-horses | B87: =Stock!R5
A88: Mares | B88: =Stock!R6
A89: Plough horses | B89: =Stock!R7
A90: Colts (2 years) | B90: =Stock!R8
A91: Colts (2 years) | B91: =Stock!R9
A92: Colts (1 year) | B92: =Stock!R10
A93: Foals | B93: =Stock!R11
A94: Oxen | B94: =Stock!R12
A95: Bulls | B95: =Stock!R13
A96: Cows | B96: =Stock!R14
A97: Steers | B97: =Stock!R15
A98: Bullocks | B98: =Stock!R16
... A112: Peacocks | B112: =Stock!R30
A113: Total value of stock (sum of the above)
A114: Total value of production
A115: Value of sales | B115: =Stock!R31
A117: Wool | B117: Value of production at sales prices £
A118: Coarse wool | B118: =Stock!T35
A119: Lamb's wool | B119: =Stock!T36
A120: Wool locks | B120: =Stock!T37
A121: Wool sold at shearing | B121: =Stock!T38
A122: Total value of production (sum of the above) | B122: =Stock!T39
A123: Value of sales | B123: =Stock!R39
A125: Hides | B125: Value of production at sales prices £
A126: Ox hides | B126: =Stock!T43
A127: Cow hides | B127: =Stock!T44
A128: Mare hides | B128: =Stock!T45
A129: Steer hides | B129: =Stock!T46
A130: Yearling Calf hides | B130: =Stock!T47
A131: Calf hides | B131: =Stock!T48
A132: Pig hides | B132: =Stock!T49
A133: Wether woolskins | B133: =Stock!T50
...

Sheet Receipts
A1: DROXFORD RECEIPTS
A2: Heading | B2: £ | C2: s | D2: d | F2: Total in £ | G2: Error | H2: Notes
A3: Arrears | B3: 25 | C3: 18 | D3: 9.75 | F3: 25.94 | H3: Robert de Froyle, bailiff, and William ate Hatth', reeve, render account for £25 18 shilling 9.75pence of arrears from the previous year.
A4: Arrears | B4: 0 | C4: 0 | D4: 0 | F4: 0 | H4: All delivered to Sir Geoffrey, treasurer of Wolvesey, by 1 tally.
A5: Arrears | B5: 0 | C5: 0 | D5: 0 | F5: 0 | H5: They are quit.
A6: Arrears | F6: 25.94 | G6: 25.94 | H6: Total
A8: Rents of assize | B8: 2 | C8: 18 | D8: 5 | F8: 2.92 | H8: The same render account for £2 18 shilling 5pence from ox-gavel (oxeye) at the feast of St Thomas the Apostle (21 December).
A9: Rents of assize | B9: 0 | C9: 17 | D9: 10.5 | F9: 0.89 | H9: 17 shilling 10.5pence from wood-gavel (wodegavel) at Lammas (1 August).
A10: Rents of assize | B10: 20 | C10: 19 | D10: 3.5 | F10: 20.96 | H10: £20 19 shilling 3.5pence for rents of assize at Michaelmas (29 September).
A11: Rents of assize | B11: 24 | C11: 15 | D11: 7.5 | F11: 24.78 | H11: Total, £24 15 shilling 7.5pence
A12: Rents of assize | F12: 24.77 | G12: -0.01 | H12: Total
A14: Quittances | B14: 0 | C14: 7 | D14: 6 | F14: 0.38 | H14: In quittance of 3 ploughmen, 2 shepherds and 1 smith for the year 7 shilling 6pence, or 1 shilling 3pence each.
A15: Quittances | B15: 0 | C15: 0 | D15: 6 | F15: 0.03 | H15: the same for ox-gavel 6pence.
A16: Quittances | B16: 0 | C16: 0 | D16: 3.75 | F16: =B16+C16/20+D16/240 | H16: 1 keeper of lambs from the Nativity of St John the Baptist to Michaelmas, for 1 term, 3.75pence
B17: 0 | C17: 8 | D17: 3.75 | F17: 0.42 | H17: Total, 8 shilling 3.75pence
A18: Quittances | F18: =SUM(F14:F16) | G18: =F18-F17 | H18: Total
A20: Defaults of rent | B20: 0 | C20: 0 | D20: 7 | F20: 0.03 | H20: In default of the land of William de Swanemere for ox-gavel because he is made free 7pence.
A21: Defaults of rent | B21: 0 | C21: 1 | D21: 0 | F21: 0.05 | H21: the land of Horn for the same 1 shilling.
A22: Defaults of rent | B22: 0 | C22: 2 | D22: 4 | F22: 0.12 | H22: the land of Thomas de la Steple for the same 2 shilling 4pence.
A23: Defaults of rent | B23: 0 | C23: 5 | D23: 0 | F23: 0.25 | H23: the land of Boarhunt which is called Wolfrenelond' 5 shilling.
A24: Defaults of rent | B24: 0 | C24: 0 | D24: 2.5 | F24: 0.01 | H24: the chief tenement formerly of John de Molendino for ox-gavel 2.5pence, because it should in fact be put in the increment of rent by charter of the lord.
A25: Defaults of rent | B25: 0 | C25: 0 | D25: 3.5 | F25: 0.01 | H25: the other tenement which the same John held, which he took on according to custom from St Swithun's whilst the manor was in their hands, for ox-gavel, 3.5pence, for the reason as before.
A26: Defaults of rent | B26: 0 | C26: 0 | D26: 7 | F26: 0.03 | H26: a certain tenement which the same John held which was formerly a relief 7pence, for the reason as before.
A27: Defaults of rent | B27: 0 | C27: 10 | D27: 0 | F27: 0.5 | H27: Total, 10 shilling
A28: Defaults of rent | F28: 0.5 | G28: 0 | H28: Total
A30: Total of quittances and defaults of rent | B30: 0 | C30: 18 | D30: 3.75 | F30: 0.92 | H30: Total of quittances and defaults of rent, 18 shilling 3.75pence
A31: Total of quittances and defaults of rent | F31: 0.92 | G31: =F31-F30 | H31: Total
A33: Total of rents remaining | B33: 23 | C33: 17 | D33: 3.75 | F33: 23.87 | H33: Total of rents remaining, £23 17 shilling 3.75pence
A34: Total of rents remaining | F34: 23.87 | G34: =F34-F33 | H34: Total
A36: Farm of the mill | B36: 3 | C36: 0 | D36: 0 | F36: 3 | H36: The same render account for £3 for the rent of the mill let at fee-farm.
A37: Farm of the mill | B37: 3 | C37: 0 | D37: 0 | F37: 3 | H37: Total, £3.
A38: Farm of the mill | F38: 3 | G38: 0 | H38: Total
A40: Annual recognizance | B40: 0 | C40: 0 | D40: 3 | F40: 0.01 | H40: The same render account for 3pence from Walter Molendinarius for annual recognizance.
A41: Annual recognizance | B41: 0 | C41: 0 | D41: 6 | F41: 0.03 | H41: 6pence from William le Careter for the same.
A42: Annual recognizance | B42: 0 | C42: 0 | D42: 6 | F42: 0.03 | H42: 6pence from William.
A43: Annual recognizance | B43: 0 | C43: 0 | D43: 6 | F43: 0.03 | H43: 6pence from William le YI so that he may serve outside the manor, and yet pay suit to his tithing at the steward's tourns as a villein as before.
A44: Annual recognizance | B44: 0 | C44: 1 | D44: 3 | F44: 0.06 | H44: Total, 1 shilling 3pence
A45: Annual recognizance | F45: 0.1 | G45: 0.04 | H45: Total
A47: Cumin | B47: 0 | C47: 0 | D47: 0 | F47: 0 | H47: The same render account for 1 lb of cumin from the rent of John, son of Henry le Careter.
A48: Cumin | B48: 0 | C48: 0 | D48: 0 | F48: 0 | H48: delivered to Wolvesey.
A49: Cumin | F49: 0 | G49: 0 | H49: Total
A51: Bows and arrows | B51: 0 | C51: 1 | D51: 0 | F51: 0.05 | H51: The same render account for 1 shilling from John de Worsted' for 1 bow and 12 arrows for 2 virgates of land which belonged to John Coleman de Shidefeld' and 1 ferling of land which belonged to Richard Crall' in the same vill, which he has by gift of lord John, bishop of Winchester, rendering at Easter according to the contents of his charter which he has from the said bishop and the whole convent of St Swithun's.
A52: Bows and arrows | B52: 0 | C52: 1 | D52: 0 | F52: 0.05 | H52: Total, 1 shilling
A53: Bows and arrows | F53: 0.05 | G53: 0 | H53: Total
A55: Issues of the manor | B55: 1 | C55: 11 | D55: 2.5 | F55: 1.56 | H55: The same render account for £1 11 shilling 2.5 pence from pannage of pigs at Martinmas, at 2pence a pig over a year old, 1.5pence a pig of 3 terms, 1pence a pig of .5 year, and .5pence a piglet, and moreover, 1 pig and 1 piglet from pannage this year because each of those who have 10 pigs in the manor will give 1 pig.
A56: Issues of the manor | B56: 0 | C56: 0 | D56: 0 | F56: 0 | H56: nothing from winter pasturage this year because it was not able to be sold.
A57: Issues of the manor | B57: 0 | C57: 0 | D57: 10 | F57: 0.04 | H57: 10pence from summer pasturage sold there this year.
A58: Issues of the manor | B58: 0 | C58: 0 | D58: 0 | F58: 0 | H58: nothing from the pasturage of various places nor from the pasturage in Forcrofte this year for the lord's stock.
A59: Issues of the manor | B59: 0 | C59: 3 | D59: 9 | F59: 0.19 | H59: 3 shilling 9pence from 18 geese sold.
A60: Issues of the manor | B60: 0 | C60: 3 | D60: 10 | F60: 0.19 | H60: 3 shilling 10pence from 46 hens sold.
A61: Issues of the manor | B61: 0 | C61: 3 | D61: 0.75 | F61: 0.15 | H61: 3 shilling 0.75pence from 1,050 eggs sold.
A62: Issues of the manor | B62: 0 | C62: 3 | D62: 0 | F62: 0.15 | H62: 3 shilling from 6 bushels of nuts sold from the wood according to custom.
A63: Issues of the manor | B63: 0 | C63: 1 | D63: 6 | F63: 0.08 | H63: 1 shilling 6pence from loppings in Suthwild' sold this year from timber felled for ploughs.
A64: Issues of the manor | B64: 0 | C64: 0 | D64: 0 | F64: 0 | H64: nothing from dead trees and dead wood in Haslholte nor from underwood in la Fronches' this year.
A65: Issues of the manor | B65: 0 | C65: 8 | D65: 0 | F65: 0.4 | H65: 8 shilling from the whole hundred for release from carrying the hay of Nutschellyng'.
A66: Issues of the manor | B66: 0 | C66: 19 | D66: 0 | F66: 0.95 | H66: 19 shilling from 9.5 virgates of land for release from carrying-service.
... A73: Issues of the manor | B73: 5 | C73: 15 | D73: 1.5 | F73: 5.76 | H73: Total, £5 15 shilling 1.5pence
A75: Issues of the manor | B75: 0 | C75: 10 | D75: 0 | F75: =B75+C75/20+D75/240 | H75: And for 10 shilling from 1 old cart-horse sold.
A76: Issues of the manor | B76: 0 | C76: 9 | D76: 0 | F76: 0.45 | H76: 9 shilling from 2 old plough-horses sold, at 3 shilling for 1, and 6 shilling for 1.
A77: Issues of the manor | B77: 0 | C77: 9 | D77: 0 | F77: 0.45 | H77: 9 shilling from 1 old ox sold.
A78: Issues of the manor | B78: 1 | C78: 12 | D78: 6 | F78: 1.62 | H78: £1 12 shilling 6pence from 4 old cows sold, at 7s .3pence each for 2, and 9 shilling each for 2.
A79: Issues of the manor | B79: 0 | C79: 6 | D79: 0 | F79: 0.3 | H79: 6 shilling from 6 late-born calves sold, at 1 shilling each.
A80: Issues of the manor | B80: 1 | C80: 14 | D80: 0 | F80: 1.7 | H80: £1 14 shilling from 34 wethers sold at Martinmas, at 1 shilling each.
A81: Issues of the manor | B81: 2 | C81: 0 | D81: 0 | F81: 2 | H81: £2 from 40 ewes sold.
A82: Issues of the manor | B82: 3 | C82: 3 | D82: 4 | F82: 3.17 | H82: £3 3 shilling 4pence from 25 pigs sold at Martinmas, at 2 shilling 4pence each for 10, and 2 shilling 8pence each for 15.
A83: Issues of the manor | B83: 0 | C83: 10 | D83: 2.5 | F83: 0.51 | H83: 10 shilling from 48 feeble lambs sold, at 2.5pence each.
A84: Issues of the manor | B84: 0 | C84: 0 | D84: 0 | F84: 0 | H84: nothing from coarse wool and lamb's-wool here because it is sent to Wolvesey.
A85: Issues of the manor | B85: 0 | C85: 6 | D85: 1.5 | F85: 0.31 | H85: 6 shilling 1.5pence from 7 cloves of wool locks sold, at 101 pence a clove.
A86: Issues of the manor | B86: 0 | C86: 10 | D86: 5 | F86: 0.52 | H86: 10 shilling 5pence from the skins sold of 18 wethers, 17 ewes and 19 hoggs in murrain before shearing, at 3pence a skin of wethers, 2.5pence a skin of ewes, and 1.5pence a skin of hoggs.
A87: Issues of the manor | B87: 0 | C87: 1 | D87: 9 | F87: 0.09 | H87: 1 shilling 9pence from the skins sold wholesale of 13 wethers and 5 ewes in murrain after shearing.
... A95: Issues of the manor | B95: 2 | C95: 15 | D95: 3 | F95: 2.76 | H95: £2 15 shilling 3pence from 6.5 weys of summer cheese sold, at 8 shilling 6pence a wey.
A96: Issues of the manor | B96: 0 | C96: 4 | D96: 6.5 | F96: =B96+C96/20+D96/240 | H96: 4 shilling 6.5pence from 0.5 wey 1 clove of butter sold
A97: Issues of the manor | B97: 16 | C97: 5 | D97: 4.75 | F97: 16.27 | H97: Total, £16 5 shilling 4.75pence
A98: Issues of the manor | F98: =SUM(F55:F72)+SUM(F75:F96) | G98: =F98-(F97+F73) | H98: Total
A100: Sale of corn | B100: 12 | C100: 1 | D100: 3.5 | F100: 12.06 | H100: The same render account for £12 1 shilling 3.5pence from 42 quarters 2.5 bushels of wheat sold, at 4 shilling 8d a qr for 5.5 quarters, 5 shilling a qr for 17.5 quarters 3 bushels, and 6 shilling 8pence a qr for 18.5 quarters.
A101: Sale of corn | B101: 1 | C101: 1 | D101: 3 | F101: 1.06 | H101: £1 1 shilling 3pence from 6 quarters 3 bushels of curall sold, at 3 shilling 4pence a qr.
A102: Sale of corn | B102: 0 | C102: 1 | D102: 4 | F102: 0.07 | H102: 1 shilling 4pence from 4 bushels of maslin sold.
A103: Sale of corn | B103: 1 | C103: 16 | D103: 8 | F103: 1.83 | H103: £1 16 shilling 8pence from 11 quarters of bere sold, at 3 shilling 4pence a qr.
A104: Sale of corn | B104: 6 | C104: 9 | D104: 9 | F104: 6.49 | H104: £6 9 shilling 9pence from 34 quarters 1 bushels of barley sold, at 3 shilling 4pence a qr for 10 quarters 1 bushels, and 4 shilling a qr for 24 quarters.
A105: Sale of corn | B105: 4 | C105: 3 | D105: 2 | F105: 4.16 | H105: £4 3 shilling 2pence from 34.5 quarters 2 bushels of oats sold, at 2 shilling a qr for 14 quarters 2 bushels, and 2 shilling 8pence a qr for 20.5.
A106: Sale of corn | B106: 1 | C106: 0 | D106: 9 | F106: 1.04 | H106: £1 9pence from 9.5quarters 1 bus of peas sold, at 2 shilling a qr for 7 quarters 3 bushels, and 2 shilling 8pence a qr for 2 quarters 2 bushels.
A107: Sale of corn | B107: 1 | C107: 5 | D107: 0 | F107: 1.25 | H107: £1 5 shilling 6.5 from 14 quarters 3 bushels of vetches sold, at 1 shilling 4pence a qr for 8 quarters for 6 quarters 3 bushels
A108: Sale of corn | B108: 27 | C108: 19 | D108: 9 | F108: =B108+C108/20+D108/240 | H108: Total, £27 19 shilling 9pence
A109: Sale of corn | F109: 27.96 | G109: =F109-F108 | H109: Total
A111: Entry and marriage fines | B111: 0 | C111: 10 | D111: 0 | F111: 0.5 | H111: The same render account for 10 shilling from Alice, relict of Cuppyng Breton, to retain 1 messuage and' virgate of land which belonged to her husband.
A112: Entry and marriage fines | B112: 1 | C112: 0 | D112: 0 | F112: 1 | H112: £1 from John Seyle to have 1 messuage and 0.5 virgate of land which belonged to Isabel his mother whose heir he is.
A113: Entry and marriage fines | B113: 0 | C113: 2 | D113: 0 | F113: 0.1 | H113: 2 shilling from William le Y1 to have 1 messuage and 1 ferling which belonged to Alice his mother whose heir he is.
A114: Entry and marriage fines | B114: 0 | C114: 4 | D114: 0 | F114: 0.2 | H114: 4 shilling from Joan la Hore to have 1 messuage and .5 virgate of land which belonged to John, son of her uncle, whose heir she is.
A115: Entry and marriage fines | B115: 0 | C115: 6 | D115: 8 | F115: 0.33 | H115: 6 shilling 8pence from John Chapelay of Hawkley to have Joan la Hore with .5 virgate of her land.
A116: Entry and marriage fines | B116: 0 | C116: 1 | D116: 1 | F116: 0.05 | H116: 1 shilling from Guy Gamnoky to have 2 day-works of land by surrender of Richard de Seleford', and the said Guy will relieve the said Richard of 1pence annual rent for the year.
A117: Entry and marriage fines | B117: 2 | C117: 3 | D117: 8 | F117: 2.18 | H117: Total, £2 3 shilling 8pence
A118: Entry and marriage fines | F118: 2.18 | G118: 0 | H118: Total
A120: Perquisites | B120: 0 | C120: 2 | D120: 0 | F120: 0.1 | H120: The same render account for 2 shilling from Peter de Brok, overseer of the harvest, for keeping the lord's fields and pastures badly.
A121: Perquisites | B121: 0 | C121: 16 | D121: 3 | F121: 0.81 | H121: 16 shilling 3pence from various men for various transgressions.
A122: Perquisites | B122: 0 | C122: 18 | D122: 3 | F122: 0.91 | H122: Total, 18 shilling 3pence
A123: Perquisites | F123: 0.91 | G123: 0 | H123: Total
A125: Total of all receipts recorded in accounts | B125: 80 | C125: 1 | D125: 9 | F125: =B125+C125/20+D125/240 | H125: Total of all receipts, £80 1 shilling 9pence
A126: Total cross-check without arrears | F126: =F123+F118+F109+F98+F53+F49+F45+F38+F34 | G126: =F126-F125
A127: Total cross-check with arrears | F127: =F126+F6 | G127: =F127-F126

Sheet Expenses
A1: DROXFORD EXPENSES
A2: Heading | B2: £ | C2: s | D2: d | F2: Total in £ | G2: Error | H2: Notes | J2: Fixed investment | K2: Demesne fixed investment
A3: Cost of ploughs | B3: 0 | C3: 6 | D3: 10.5 | F3: 0.34 | H3: In iron and steel bought for 2 ploughs for the year and three ploughs for 1 term 6 shilling 10.5pence. | J3: =F3 | K3: =J3
A4: Cost of ploughs | B4: 0 | C4: 0 | D4: 9 | F4: 0.04 | H4: 1 ploughshare bought 9pence. | J4: =F4 | K4: =J4
A5: Cost of ploughs | B5: 0 | C5: 0 | D5: 5 | F5: 0.02 | H5: 1 plough made anew and others mended 5pence. | J5: =F5 | K5: =J5
A6: Cost of ploughs | B6: 0 | C6: 0 | D6: 3 | F6: 0.01 | H6: trimming timber 3pence. | J6: =F6 | K6: =J6
A7: Cost of ploughs | B7: 0 | C7: 1 | D7: 3 | F7: 0.06 | H7: 3 plough feet bought 1 shilling 3pence. | J7: =F7 | K7: =J7
A8: Cost of ploughs | B8: 0 | C8: 0 | D8: 1.5 | F8: 0.01 | H8: fitting the said plough with iron tyres 1.5pence. | J8: =F8 | K8: =J8
A9: Cost of ploughs | B9: 0 | C9: 1 | D9: 0 | F9: 0.05 | H9: 3 pairs of wheels bought for the same 1 shilling. | J9: =F9 | K9: =J9
A10: Cost of ploughs | B10: 0 | C10: 0 | D10: 0.75 | F10: 0 | H10: 3 halters made from the horses' own hair (de proprio pilo) 0.75pence. | J10: =F10 | K10: =J10
A11: Cost of ploughs | B11: 0 | C11: 2 | D11: 6 | F11: 0.12 | H11: shoeing 2 plough-horses 2 shilling 6pence, because the smith shoes 2 according to custom. | J11: =F11 | K11: =J11
A12: Cost of ploughs | B12: 0 | C12: 1 | D12: 4 | F12: 0.07 | H12: spreading dung 1 shilling 4pence. | J12: =F12 | K12: =J12
A13: Cost of ploughs | B13: 0 | C13: 0 | D13: 4 | F13: 0.02 | H13: 2 harrows made anew with others mended 4pence. | J13: =F13 | K13: =J13
A14: Cost of ploughs | B14: 0 | C14: 3 | D14: 0 | F14: 0.15 | H14: stipend of 1 drover for the year 3 shilling.
A15: Cost of ploughs | B15: 0 | C15: 0 | D15: 9 | F15: 0.04 | H15: stipend of 1 drover for 1 term 9pence.
A16: Cost of ploughs | B16: 0 | C16: 6 | D16: 0 | F16: 0.3 | H16: stipend of 2 ploughmen who are sometimes carters for the year 6 shilling.
A17: Cost of ploughs | B17: 2 | C17: 1 | D17: 3 | F17: 2.06 | H17: 4 oxen £2 1 shilling 3pence, at 10 shilling each for 3, and 11 shilling 3pence for 1..
A18: Cost of ploughs | B18: 0 | C18: 8 | D18: 0 | F18: =B18+C18/20+D18/240 | H18: forage bought 8 shilling
A19: Cost of ploughs | B19: 3 | C19: 13 | D19: 10.75 | F19: 3.69 | H19: Total, £3 13 shilling 10.75pence
A20: Cost of ploughs | F20: =SUM(F3:F18) | G20: =F20-F19 | H20: Total
A22: Cost of carts | B22: 0 | C22: 1 | D22: 10 | F22: 0.09 | H22: In 1 pair of wheels bought for clearing dung 1 shilling 10pence. | J22: =F22 | K22: =J22
A23: Cost of carts | B23: 0 | C23: 1 | D23: 2.5 | F23: 0.06 | H23: large nails bought for mending the cart 1 shilling 2.5pence. | J23: =F23 | K23: =J23
A24: Cost of carts | B24: 0 | C24: 0 | D24: 7 | F24: 0.03 | H24: fitting the cart with axles with axles bought for the same 7pence. | J24: =F24 | K24: =J24
A25: Cost of carts | B25: 0 | C25: 1 | D25: 2 | F25: 0.06 | H25: 2 collars bought 1 shilling 2pence. | J25: =F25 | K25: =J25
A26: Cost of carts | B26: 0 | C26: 0 | D26: 6 | F26: 0.03 | H26: 1 pair of saddle-pads 6pence. | J26: =F26 | K26: =J26
A27: Cost of carts | B27: 0 | C27: 0 | D27: 9.5 | F27: 0.04 | H27: clouts, nails and grease bought 9.5pence. | J27: =F27 | K27: =J27
A28: Cost of carts | B28: 0 | C28: 0 | D28: 4.5 | F28: 0.02 | H28: 1 pair of traces bought 4.5pencetethering. | J28: =F28 | K28: =J28
A29: Cost of carts | B29: 0 | C29: 0 | D29: 3 | F29: 0.01 | H29: 1 rope bought for horses in the pasture 3pence. | J29: =F29 | K29: =J29
A30: Cost of carts | B30: 0 | C30: 0 | D30: 3 | F30: 0.01 | H30: 2 halters bought 3pence. | J30: =F30 | K30: =J30
A31: Cost of carts | B31: 0 | C31: 3 | D31: 6 | F31: 0.17 | H31: shoeing 2 cart-horses for the year 3 shilling 6pence. | J31: =F31 | K31: =J31
A32: Cost of carts | B32: 0 | C32: 19 | D32: 1 | F32: 0.95 | H32: 1 cart-horse bought 19 shilling 1 pence.
A33: Cost of carts | B33: 0 | C33: 0 | D33: 6 | F33: =B33+C33/20+D33/240 | H33: 3 pieces of iron for 3 shovels 6pence | J33: =F33 | K33: =J33
A34: Cost of carts | B34: 1 | C34: 10 | D34: 0.5 | F34: 1.5 | H34: Total, £1 10 shilling 0.5pence
A35: Cost of carts | F35: =SUM(F22:F33) | G35: =F35-F34 | H35: Total
A37: Dairy | B37: 0 | C37: 1 | D37: 9 | F37: 0.09 | H37: In 7 bushels of salt bought for the dairy, 1 shilling 9pence this year, with the expenses of the harvest. | J37: =F37 | K37: =J37
A38: Dairy | B38: 0 | C38: 0 | D38: 4 | F38: 0.02 | H38: earthenware pots and pans bought for the same 4pence. | J38: =F38 | K38: =J38
A39: Dairy | B39: 0 | C39: 0 | D39: 9 | F39: 0.04 | H39: woollen and linen cloth 9pence. | J39: =F39 | K39: =J39
A40: Dairy | B40: 0 | C40: 0 | D40: 5 | F40: 0.02 | H40: a press bought 5pence. | J40: =F40 | K40: =J40
A41: Dairy | B41: 0 | C41: 0 | D41: 4 | F41: 0.02 | H41: 1 stall made anew for bullocks 4pence. | J41: =F41 | K41: =J41
A42: Dairy | B42: 0 | C42: 4 | D42: 4.5 | F42: 0.22 | H42: 15 ells of canvas bought for putting wool in 4 shilling 4.5pence, at 3.5pence an ell. | J42: =F42 | K42: =J42
A43: Dairy | B43: 0 | C43: 0 | D43: 1 | F43: 0 | H43: castrating piglets 1pence. | J43: =F43 | K43: =J43
A44: Dairy | B44: 0 | C44: 0 | D44: 8 | F44: 0.03 | H44: 1 tripod bought 8pence. | J44: =F44 | K44: =J44
A45: Dairy | B45: 0 | C45: 0 | D45: 5 | F45: 0.02 | H45: 1 tine bought for carrying cider 5pence. | J45: =F45 | K45: =J45
A46: Dairy | B46: 0 | C46: 7 | D46: 2 | F46: 0.36 | H46: 3 empty casks bought for putting cider in 7 shilling 2pence. | J46: =F46 | K46: =J46
A47: Dairy | B47: 0 | C47: 2 | D47: 2 | F47: 0.11 | H47: hooping and mending 6 casks 2 shilling 2pence. | J47: =F47 | K47: =J47
A48: Dairy | B48: 0 | C48: 2 | D48: 0 | F48: 0.1 | H48: stipend of 1 dairymaid for the year 2 shilling.
A49: Dairy | B49: 0 | C49: 1 | D49: 6 | F49: =B49+C49/20+D49/240 | H49: stipend of 1 cowherd for 3 terms 1 shilling 6pence
A50: Dairy | B50: 1 | C50: 1 | D50: 11.5 | F50: 1.1 | H50: Total, £1 1 shilling 11.5pence
A51: Dairy | F51: =SUM(F37:F49) | G51: =F51-F50 | H51: Total
A53: Sheepcote | B53: 0 | C53: 0 | D53: 8 | F53: 0.03 | H53: In 16 hurdles made for the fold 8pence. | J53: =F53 | K53: =J53
A54: Sheepcote | B54: 0 | C54: 0 | D54: 2 | F54: 0.01 | H54: 6 hurdles made for the pen (lokett') with withies collected for the same 2pence. | J54: =F54 | K54: =J54
A55: Sheepcote | B55: 0 | C55: 1 | D55: 4 | F55: 0.07 | H55: re-roofing the ewe-house in places 1 shilling 4pence. | J55: =F55 | K55: =J55
A56: Sheepcote | B56: 0 | C56: 0 | D56: 8 | F56: 0.03 | H56: re-roofing the wether-house in places 8pence. | J56: =F56 | K56: =J56
A57: Sheepcote | B57: 0 | C57: 1 | D57: 4.5 | F57: 0.07 | H57: wattling the fold with withies and stubble collected for the same 1 shilling 4.5pence. | J57: =F57 | K57: =J57
A58: Sheepcote | B58: 0 | C58: 16 | D58: 1 | F58: =B58+C58/20+D58/240 | H58: fat, vinegar and copperas with the stipend of the man greasing the sheep (ung')16 shilling 1pence | J58: =F58 | K58: =J58
A59: Sheepcote | B59: 1 | C59: 0 | D59: 3.5 | F59: 1.01 | H59: Total, £1 3.5pence
A60: Sheepcote | F60: =SUM(F53:F58) | G60: =F60-F59 | H60: Total
A62: Cost of buildings | B62: 0 | C62: 10 | D62: 0 | F62: 0.5 | H62: In building the cow-shed anew with a carpenter for the same by piece-work 10 shilling. | J62: =F62 | K62: =J62
A63: Cost of buildings | B63: 0 | C63: 1 | D63: 0 | F63: 0.05 | H63: making 1,500 laths for the same 1 shilling. | J63: =F63 | K63: =J63
A64: Cost of buildings | B64: 0 | C64: 2 | D64: 4 | F64: 0.12 | H64: 3,000 nails bought 2 shilling 4pence. | J64: =F64 | K64: =J64
A65: Cost of buildings | B65: 0 | C65: 2 | D65: 8 | F65: 0.13 | H65: re-roofing the said building by piece-work 2 shilling 8pence. | J65: =F65 | K65: =J65
A66: Cost of buildings | B66: 0 | C66: 1 | D66: 8.5 | F66: 0.09 | H66: re-roofing in places the bailiff's room, small barn, dairy building' and cart-house 1 shilling 8.5pence. | J66: =F66 | K66: =J66
A67: Cost of buildings | B67: 0 | C67: 0 | D67: 10 | F67: 0.04 | H67: stubble collected for the same 10pence. | J67: =F67 | K67: =J67
A68: Cost of buildings | B68: 0 | C68: 0 | D68: 9 | F68: 0.04 | H68: hedging to enclose around the garden 9pence. | J68: =F68 | K68: =J68
A69: Cost of buildings | B69: 0 | C69: 0 | D69: 8 | F69: 0.03 | H69: pulling down the fencing for the same 8pence. | J69: =F69 | K69: =J69
A70: Cost of buildings | B70: 0 | C70: 1 | D70: 0 | F70: 0.05 | H70: mending the walls of the great barn and putting in sills 1 shilling. | J70: =F70 | K70: =J70
A71: Cost of buildings | B71: 0 | C71: 0 | D71: 3 | F71: 0.01 | H71: mending the pig¬sty at Haselholte 3pence. | J71: =F71 | K71: =J71
A72: Cost of buildings | B72: 0 | C72: 0 | D72: 3 | F72: 0.01 | H72: 1 lock bought for the door of the great barn 3pence. | J72: =F72 | K72: =J72
A73: Cost of buildings | B73: 0 | C73: 1 | D73: 1 | F73: =B73+C73/20+D73/240 | H73: building a stack of forage in the curia 1 shilling 1pence | J73: =F73 | K73: =J73
A74: Cost of buildings | B74: 1 | C74: 2 | D74: 6.5 | F74: 1.13 | H74: Total, £1 2 shilling 6.5pence
A75: Cost of buildings | F75: 2.2 | G75: 1.07 | H75: Total
A77: Threshing | B77: 0 | C77: 11 | D77: 2.75 | F77: 0.56 | H77: In threshing and winnowing 49 quarters 1 bushels of wheat, curall and maslin by piece-work 11 shilling 2.75pence, at 2.75pence a heaped quarter.
A78: Threshing | B78: 0 | C78: 11 | D78: 4.5 | F78: 0.57 | H78: threshing and winnowing 78 quarters of bere and barley by piece-work 11 shilling 4.5pence, at 1.75pence a heaped quarter.
A79: Threshing | B79: 0 | C79: 5 | D79: 5.5 | F79: 0.27 | H79: threshing and winnowing 75 quarters of oats 5 shilling 5.5pence, at 0.75pence a heaped quarter, and 0.25pence per 2 quarters winnowepence.
A80: Threshing | B80: 0 | C80: 4 | D80: 9 | F80: 0.24 | H80: threshing and winnowing 25 quarters 3 bushels of peas and vetches by piece-work 4 shilling 9pence, at 2.25pence a heaped quarter.
A81: Threshing | B81: 0 | C81: 0 | D81: 5.5 | F81: 0.02 | H81: 1 sack bought 5.5pence.
A82: Threshing | B82: 0 | C82: 0 | D82: 2.5 | F82: =B82+C82/20+D82/240 | H82: 1 basket bought for corn 2.5pence
A83: Threshing | B83: 1 | C83: 13 | D83: 5.75 | F83: 1.67 | H83: Total, £1 13 shilling 5.75pence
A84: Threshing | F84: =SUM(F77:F82) | G84: =F84-F83 | H84: Total
A86: Harvest-time | B86: 0 | C86: 3 | D86: 9 | F86: 0.19 | H86: In weeding all the corn over and above that weeded by labour service 3 shilling 9pence.
A87: Harvest-time | B87: 0 | C87: 18 | D87: 2.5 | F87: 0.91 | H87: herrings bought for 6 boon-works of 590 men having two meals a day and 4 herrings each, and for 7 boon-works of 660 men having 1 meal a day and 2 herrings each, 18 shilling 2.5pence.
A88: Harvest-time | B88: 0 | C88: 5 | D88: 4 | F88: =B88+C88/20+D88/240 | H88: expenses of the reeve, hayward and other officials of the curia from Lammas (1 August) until the Decollation of St John the Baptist (29 August), for 4 weeks, 5 shilling 4pence
A89: Harvest-time | B89: 1 | C89: 7 | D89: 3.5 | F89: 1.35 | H89: Total, £1 7 shilling 3.5 pence
A90: Harvest-time | F90: =SUM(F86:F88) | G90: =F90-F89 | H90: Total
A93: Expenses of the steward | B93: 0 | C93: 2 | D93: 0 | F93: 0.1 | H93: In expenses of the steward for 2 tourns by 1 tally 2 shilling.
A94: Expenses of the steward | B94: 0 | C94: 3 | D94: 0 | F94: 0.15 | H94: expenses of Roger, bailiff from Michaelmas until Christmas, for his visits 3 shilling.
A95: Expenses of the steward | B95: 0 | C95: 5 | D95: 3 | F95: 0.26 | H95: expenses of Robert, bailiff from Christmas until Michaelmas, for his visits 5 shilling 3pence
A96: Expenses of the steward | B96: 0 | C96: 10 | D96: 3 | F96: =B96+C96/20+D96/240 | H96: Total, 10 shilling 3pence
A97: Expenses of the steward | F97: 0.51 | G97: =F97-F96 | H97: Total
A99: Total of all expenses | B99: 10 | C99: 19 | D99: 9 | F99: 10.99 | H99: Total of all expenses, £10 19 shilling 9pence
A100: Total of all expenses | F100: 10.99 | G100: =F100-F99 | H100: Total
A102: And he owes | B102: 68 | C102: 2 | D102: 0 | F102: 68.1 | H102: And he owes, £68 2 shilling
A104: Total of all expenses per account | F104: =F100
A105: Total of all expenses (calculated here) | F105: =F97+F90+F84+F75+F60+F51+F35+F20 | G105: =F105-F104
A106: Total fixed investment | F106: =SUM(J3:J83)
A107: Total Demesne fixed investment | F107: =SUM(K3:K84)

Sheet Issues of the Grange
A1: Gross Output | B1: Total Quantity | C1: Account Total Quarters | D1: Bought in Total Quarters | E1: Received from churchscot | F1: Sold Total Quarters | G1: Difference Produced+Bought-Sold | H1: Weighted Average Price per Quarter | I1: Value of Total Production weighted
A2: wheat | B2: 58.125 | C2: 58.125 | D2: 0 | F2: 42.3125 | G2: =B2-F2 | H2: 0.28024876 | I2: =H2*B2
A3: curall | B3: 6.375 | C3: 6.375 | D3: 0 | F3: 6.375 | G3: =B3-F3 | H3: 0.16666667 | I3: =H3*B3
A4: rye | B4: 2.0625 | D4: 0 | E4: 2.0625 | G4: =B4-F4 | I4: =H4*B4
A5: maslin | B5: 7.625 | C5: 7.625 | D5: 0 | F5: 0.5 | G5: =B5-F5 | H5: 0.13333333 | I5: =H5*B5
A6: bere | B6: 25.25 | C6: 25.25 | D6: 0 | F6: 11 | G6: =B6-F6 | H6: 0.16666667 | I6: =H6*B6
A7: barley | B7: 93.125 | C7: 93.125 | D7: 0 | F7: 34.125 | G7: =B7-F7 | H7: 0.19010989 | I7: =H7*B7
A8: oats | B8: 108.25 | C8: 108.25 | D8: 0 | F8: 34.75 | G8: =B8-F8 | H8: 0.11966427 | I8: =H8*B8
A9: peas | B9: 11.875 | C9: 11.875 | D9: 0 | F9: 9.625 | G9: =B9-F9 | H9: 0.10779221 | I9: =H9*B9
A10: vetches | B10: 19.875 | C10: 19.875 | D10: 0 | F10: 14.375 | G10: =B10-F10 | H10: 0.066666667 | I10: =H10*B10
A12: Total Production
A13: Sales of corn (as recorded in accounts)
A16: Net output | B16: Gross output | C16: Seed quarters | D16: Seed bushels | E16: Seed total quarters | F16: tithe quarters | G16: tithe bushels | H16: tithe total | I16: manorial servants quarters | J16: manorial servants bushels | K16: manorial servants total quarters | L16: output net of tithe, seed, liveries | M16: in stock from last year | N16: Price in £ | O16: Value of net output in £ | P16: Value of sales (in "Sale of Corn") in £
A17: wheat | B17: =B2 | C17: 14.5 | E17: =C17+D17/8 | J17: =1+6+2+1.5+0.5+0.5 | K17: =I17+J17/8 | L17: =B17-E17-K17 | N17: =H2 | O17: =N17*L17
A18: curall | B18: =B3 | E18: =C18+D18/8 | K18: =I18+J18/8 | L18: =B18-E18-K18 | N18: =H3 | O18: =N18*L18
A19: rye | B19: =B4 | E19: =C19+D19/8 | K19: =I19+J19/8 | L19: =B19-E19-K19 | N19: =H4 | O19: =N19*L19
A20: maslin | B20: =B5 | E20: =C20+D20/8 | I20: 7 | J20: 1 | K20: =I20+J20/8 | L20: =B20-E20-K20 | N20: =H5 | O20: =N20*L20
A21: bere | B21: =B6 | C21: 5 | D21: 2 | E21: =C21+D21/8 | I21: 9 | K21: =I21+J21/8 | L21: =B21-E21-K21 | N21: =H6 | O21: =N21*L21
A22: barley | B22: =B7 | C22: 16 | D22: 1 | E22: =C22+D22/8 | I22: =6+17+4+2+7.5 | J22: =3+3+2+2 | K22: =I22+J22/8 | L22: =B22-E22-K22 | N22: =H7 | O22: =N22*L22
A23: oats | B23: =B8 | C23: 42 | D23: 1 | E23: =C23+D23/8 | I23: =15.5+14.5 | J23: =1+3+2+5 | K23: =I23+J23/8 | L23: =B23-E23-K23 | N23: =H8 | O23: =N23*L23
A24: peas | B24: =B9 | C24: 2 | D24: 2 | E24: =C24+D24/8 | K24: =I24+J24/8 | L24: =B24-E24-K24 | N24: =H9 | O24: =N24*L24
A25: vetches | B25: =B10 | C25: 2 | D25: 1 | E25: =C25+D25/8 | I25: 3 | J25: 3 | K25: =I25+J25/8 | L25: =B25-E25-K25 | N25: =H10 | O25: =N25*L25
A27: Total

Sheet Issues of the Mills

Sheet Stock
A1: DROXFORD STOCK ACCOUNT
C3: added | G3: subtracted
A4: Livestock | B4: Inherited stock | C4: added | D4: strays | E4: herbage | F4: churchscot | G4: of which in default | H4: sold | I4: in murrain | J4: accounted for elsewhere | K4: End-period stock | L4: cross-check | M4: stock building | N4: raw production | O4: Unit price (£) | P4: Value of stock (£) at given value | Q4: Value of stock (£) at sales prices | R4: Sales in (£) | S4: Value of stock building (£) | T4: Value of production (£) at sales prices | U4: Details
A5: Cart-horses | B5: 2 | C5: =1+1 | H5: 1 | J5: 1 | K5: 2 | O5: =R5/H5 | R5: =Receipts!F75
A6: Mares
A7: Plough horses | B7: 4 | C7: =1+1 | H7: 2 | K7: 4 | O7: =R7/H7 | R7: =Receipts!F76
A8: Colts (unspecified years)
A9: Colts (2 years)
A10: Colts (1 year)
A11: Foals
A12: Oxen | B12: 17 | C12: =4+4+1 | H12: 1 | I12: 1 | K12: 24 | O12: =R12/H12 | R12: =Receipts!F77
A13: Bulls | B13: 1 | K13: 1
A14: Cows | B14: 21 | C14: 2 | H14: 4 | K14: 19 | O14: =R14/H14 | R14: =Receipts!F78
A15: Steers | B15: 6 | J15: 6 | K15: 0
A16: Bullocks | B16: 6 | I16: 1 | K16: 5
A17: Yearlings | B17: 5 | K17: 5
A18: Calves | B18: 13 | H18: 6 | J18: 1 | K18: 6 | O18: =R18/H18 | R18: =Receipts!F79
A19: Wethers | B19: 280 | C19: 22 | H19: 34 | I19: =18+13 | K19: 243 | O19: =R19/H19 | R19: =Receipts!F80
A20: Rams | B20: 10 | K20: 10
A21: Ewes | B21: 380 | C21: 34 | H21: 40 | I21: =13+4+5 | J21: =7 | K21: 353 | O21: =R21/H21 | R21: =Receipts!F81
A22: Hoggs | B22: 75 | I22: =19 | J22: =22+34 | K22: 0
A23: Lambs | B23: 299 | H23: 48 | I23: =29+21+12 | J23: =27+2 | K23: 160 | O23: =R23/H23
A24: Boars
A25: Sows | B25: 3 | I25: 1 | K25: 2
A26: Pigs | B26: 33 | C26: =20+1 | H26: 25 | I26: 9 | K26: 20 | O26: =R26/H26 | R26: =Receipts!F82
A27: Hoggets | B27: 20 | J27: 20 | K27: 0
A28: Piglets | B28: 25 | C28: 1 | I28: 4 | J28: 2 | K28: 20
A29: Swans
A30: Peacocks
A31: Total Value | R31: =SUM(R5:R29)
A34: Wool
A35: Coarse wool | C35: 624 | J35: =2+622 | K35: 0 | O35: 0.02 | T35: =O35*J35
A36: Lamb's wool | C36: 172 | J36: 172 | K36: 0 | O36: 0.01 | T36: =O36*J36
A37: Wool locks | C37: 7 | H37: 7 | K37: 0 | O37: 0.04375 | T37: =O37*H37 | U37: measured in cloves
A38: Wool sold at shearing
A39: Total wool | T39: =SUM(T35:T38)
A42: Hides
A43: Ox hides | C43: 1 | H43: 1 | K43: 0 | O43: =R43/H43 | R43: =Receipts!F91 | T43: =O43*C43
A44: bullock | C44: 1 | H44: 1 | K44: 0 | O44: =R44/H44 | R44: =Receipts!F92 | T44: =O44*C44
A45: Mare | T45: =O45*C45
A46: Steer | T46: =O46*C46
A47: calves | T47: =O47*C47
A48: pigs | T48: =O48*C48
A49: Woolskins | T49: =O49*C49
A50: wethers | C50: 18 | T50: =O50*C50
A51: rams | T51: =O51*C51
A52: ewes | C52: 17 | T52: =O52*C52
A53: hoggs | C53: 19 | T53: =O53*C53
A54: Woolskins | C54: =SUM(C50:C53) | H54: 54 | K54: 0 | O54: =R54/H54 | R54: =Receipts!F86 | T54: =O54*C54
A55: Bareskins | T55: =O55*C55
A56: wethers | C56: 13 | H56: 13 | O56: =R56/H56 | R56: =Receipts!F87 | T56: =O56*C56
A57: rams | T57: =O57*C57
A58: ewes | C58: 5 | H58: 5 | O58: =R58/H58 | R58: =R56 | T58: =O58*C58
A59: hoggs | T59: =O59*C59
A60: Bareskins (total) | C60: =SUM(C56:C59) | H60: 18 | K60: 0 | O60: =R60/H60 | T60: =O60*C60
A61: Lambskins | C61: =29+21+12 | H61: 59 | J61: 3 | K61: 0 | O61: =R61/H61 | R61: =SUM(Receipts!F88:F90) | T61: =O61*C61
A62: Rotted skins
A63: Shorn skins
A64: Total | R64: =SUM(R43:R63) | T64: =SUM(T43:T62)
A67: Poultry stock
A68: Hens
A69: Geese | C69: 18 | H69: 18 | K69: 0 | O69: =R69/H69 | R69: =Receipts!F59 | T69: =O69*C69
A70: Capons (from chickens)
A71: Cocks & hens
A72: Total poultry stock | R72: =SUM(R69:R71) | T72: =SUM(T69:T71)
A73: Total poultry excluding churchscot
A75: Poultry production
A76: Eggs | C76: 1050 | H76: 1050 | O76: =R76/H76 | R76: =Receipts!F61 | T76: =O76*C76
A77: Cocks & hens from churchscot of customary tenants | C77: 24 | F77: 22 | H77: 46 | K77: 0 | O77: =R77/H77 | R77: =Receipts!F60 | T77: =O77*(C77+F77)
A78: Sum of above
A79: Total | R79: =SUM(R76:R78) | T79: =SUM(T76:T77)
A82: Meat
A83: Beef
A84: Mutton
A85: Pork
A86: Total
A88: Cheese
A89: Winter cheese | C89: 39 | H89: 39 | O89: =R89/H89 | R89: =Receipts!F94 | T89: =O89*C89
A90: Summer cheese | C90: 160 | H90: 139 | J90: =16+1+2+2 | O90: =R90/H90 | R90: =Receipts!F95 | T90: =O90*C90
A91: Total | R91: =SUM(R89:R90) | T91: =SUM(T89:T90)
A93: Butter
A94: Butter | C94: 0.5 wey 1 clove | H94: 0.5 wey 1 clove | R94: =Receipts!F96 | T94: =R94
A95: Total | R95: =SUM(R94) | T95: =T94
A97: Total Dairy Sales
A100: Cider
A101: Cider | B101: 2 | C101: 7 | H101: 2 | K101: 7 | R101: =Receipts!F93 | T101: =R101
A102: Total | R102: =SUM(R101) | T102: =T101
A104: Additional Information (not necessarily useful)
A105: Utensils
A106: ploughs
A107: carts
A108: cart-ropes
A109: corn baskets
A110: seed-sacks
A111: seed basket
A112: locks for the doors
A113: lead vessel
A114: brass pots
A115: pans
... A130: brass posnets

Sheet raw data
A1: Heading | B1: Sentence | C1: Total in Pounds | D1: Pounds | E1: Shillings | F1: Pence | G1: Corn | H1: Total Quarters Except 1 | I1: Total Bushels Except 1 | J1: Total Corn Cross-Check | K1: Total Corn Manorial Account | L1: Corn Quantity Error | M1: Quarters 1 | N1: Bushels 1 | O1: Quarters 2 | P1: Bushels 2 | Q1: Quarters 3 | R1: Bushels 3 | S1: Quarters 4 | T1: Bushels 4 | U1: shilling a quarter 1 | V1: pence a quarter 1 | W1: shilling a quarter 2 | X1: pence a quarter 2 | Y1: shilling a quarter 3 | Z1: pence a quarter 3 | AA1: shilling a quarter 4 | AB1: pence a quarter 4 | AC1: shilling a bushel 1 | AD1: pence a bushel 1 | AE1: shilling a bushel 2 | AF1: pence a bushel 2 | AG1: shilling a bushel 3 | AH1: pence a bushel 3 | AI1: shilling a bushel 4 | AJ1: pence a bushel 4
A2: Arrears | B2: Robert de Froyle, bailiff, and William ate Hatth', reeve, render account for £25 18 shilling 9.75pence of arrears from the previous year. | C2: 25.94 | D2: 25 | E2: 18 | F2: 9.75 | H2: 0 | I2: 0 | J2: 0 | K2: 0 | L2: 0 | M2: 0 | N2: 0
A3: Arrears | B3: All delivered to Sir Geoffrey, treasurer of Wolvesey, by 1 tally. | C3: 0 | D3: 0 | E3: 0 | F3: 0 | H3: 0 | I3: 0 | J3: 0 | K3: 0 | L3: 0 | M3: 0 | N3: 0
A4: Arrears | B4: They are quit. | C4: 0 | D4: 0 | E4: 0 | F4: 0 | H4: 0 | I4: 0 | J4: 0 | K4: 0 | L4: 0 | M4: 0 | N4: 0
A5: Rents of assize | B5: The same render account for £2 18 shilling 5pence from ox-gavel (oxeye) at the feast of St Thomas the Apostle (21 December). | C5: 2.92 | D5: 2 | E5: 18 | F5: 5 | H5: 0 | I5: 0 | J5: 0 | K5: 0 | L5: 0 | M5: 0 | N5: 0
A6: Rents of assize | B6: 17 shilling 10.5pence from wood-gavel (wodegavel) at Lammas (1 August). | C6: 0.89 | D6: 0 | E6: 17 | F6: 10.5 | H6: 0 | I6: 0 | J6: 0 | K6: 0 | L6: 0 | M6: 0 | N6: 0
A7: Rents of assize | B7: £20 19 shilling 3.5pence for rents of assize at Michaelmas (29 September). | C7: 20.96 | D7: 20 | E7: 19 | F7: 3.5 | H7: 0 | I7: 0 | J7: 0 | K7: 0 | L7: 0 | M7: 0 | N7: 0
A8: Rents of assize | B8: Total, £24 15 shilling 7.5pence | C8: 24.78 | D8: 24 | E8: 15 | F8: 7.5 | H8: 0 | I8: 0 | J8: 0 | K8: 0 | L8: 0 | M8: 0 | N8: 0
A9: Quittances | B9: In quittance of 3 ploughmen, 2 shepherds and 1 smith for the year 7 shilling 6pence, or 1 shilling 3pence each. | C9: 0.38 | D9: 0 | E9: 7 | F9: 6 | H9: 0 | I9: 0 | J9: 0 | K9: 0 | L9: 0 | M9: 0 | N9: 0
A10: Quittances | B10: the same for ox-gavel 6pence. | C10: 0.03 | D10: 0 | E10: 0 | F10: 6 | H10: 0 | I10: 0 | J10: 0 | K10: 0 | L10: 0 | M10: 0 | N10: 0
A11: Quittances | B11: 1 keeper of lambs from the Nativity of St John the Baptist to Michaelmas, for 1 term, 3.75pence Total, 8 shilling 3.75pence | C11: 0.42 | D11: 0 | E11: 8 | F11: 3.75 | H11: 0 | I11: 0 | J11: 0 | K11: 0 | L11: 0 | M11: 0 | N11: 0
A12: Defaults of rent | B12: In default of the land of William de Swanemere for ox-gavel because he is made free 7pence. | C12: 0.03 | D12: 0 | E12: 0 | F12: 7 | H12: 0 | I12: 0 | J12: 0 | K12: 0 | L12: 0 | M12: 0 | N12: 0
A13: Defaults of rent | B13: the land of Horn for the same 1 shilling. | C13: 0.05 | D13: 0 | E13: 1 | F13: 0 | H13: 0 | I13: 0 | J13: 0 | K13: 0 | L13: 0 | M13: 0 | N13: 0
... A46: Issues of the manor | B46: 4 shilling 9.25pence from Fyslod'. | C46: 0.24 | D46: 0 | E46: 4 | F46: 9.25 | H46: 0 | I46: 0 | J46: 0 | K46: 0 | L46: 0 | M46: 0 | N46: 0
A47: Issues of the manor | B47: 12 shilling 4.5pence from 2 quarters .5 bushels of rye from churchscot sold. | C47: 0.62 | D47: 0 | E47: 12 | F47: 4.5 | G47: rye | H47: 2 | I47: 5 | J47: 2.625 | K47: 2 | L47: 0.625 | M47: 2 | N47: 0 | O47: 0 | P47: 5
A48: Issues of the manor | B48: 5 shilling 1.5pence for release from carrying wood felled in preparation for Christmas this year. | C48: 0.26 | D48: 0 | E48: 5 | F48: 1.5 | H48: 0 | I48: 0 | J48: 0 | K48: 0 | L48: 0 | M48: 0 | N48: 0
A49: Issues of the manor | B49: 14 shilling 3pence from transport-service sold this year. | C49: 0.71 | D49: 0 | E49: 14 | F49: 3 | H49: 0 | I49: 0 | J49: 0 | K49: 0 | L49: 0 | M49: 0 | N49: 0
A50: Issues of the manor | B50: 3 shilling 11 pence from dairy produce sold at the audit. | C50: 0.2 | D50: 0 | E50: 3 | F50: 11 | H50: 0 | I50: 0 | J50: 0 | K50: 0 | L50: 0 | M50: 0 | N50: 0
A51: Issues of the manor | B51: Total, £5 15 shilling 1.5pence And for 10 shilling from 1 old cart-horse sold. | C51: 5.76 | D51: 5 | E51: 15 | F51: 1.5 | H51: 0 | I51: 0 | J51: 0 | K51: 0 | L51: 0 | M51: 0 | N51: 0
A52: Issues of the manor | B52: 9 shilling from 2 old plough-horses sold, at 3 shilling for 1, and 6 shilling for 1. | C52: 0.45 | D52: 0 | E52: 9 | F52: 0 | H52: 0 | I52: 0 | J52: 0 | K52: 0 | L52: 0 | M52: 0 | N52: 0
A53: Issues of the manor | B53: 9 shilling from 1 old ox sold. | C53: 0.45 | D53: 0 | E53: 9 | F53: 0 | H53: 0 | I53: 0 | J53: 0 | K53: 0 | L53: 0 | M53: 0 | N53: 0
A54: Issues of the manor | B54: £1 12 shilling 6pence from 4 old cows sold, at 7s .3pence each for 2, and 9 shilling each for 2. | C54: 1.62 | D54: 1 | E54: 12 | F54: 6 | H54: 0 | I54: 0 | J54: 0 | K54: 0 | L54: 0 | M54: 0 | N54: 0
A55: Issues of the manor | B55: 6 shilling from 6 late-born calves sold, at 1 shilling each. | C55: 0.3 | D55: 0 | E55: 6 | F55: 0 | H55: 0 | I55: 0 | J55: 0 | K55: 0 | L55: 0 | M55: 0 | N55: 0
A56: Issues of the manor | B56: £1 14 shilling from 34 wethers sold at Martinmas, at 1 shilling each. | C56: 1.7 | D56: 1 | E56: 14 | F56: 0 | H56: 0 | I56: 0 | J56: 0 | K56: 0 | L56: 0 | M56: 0 | N56: 0
A57: Issues of the manor | B57: £2 from 40 ewes sold. | C57: 2 | D57: 2 | E57: 0 | F57: 0 | H57: 0 | I57: 0 | J57: 0 | K57: 0 | L57: 0 | M57: 0 | N57: 0
A58: Issues of the manor | B58: £3 3 shilling 4pence from 25 pigs sold at Martinmas, at 2 shilling 4pence each for 10, and 2 shilling 8pence each for 15. | C58: 3.17 | D58: 3 | E58: 3 | F58: 4 | H58: 0 | I58: 0 | J58: 0 | K58: 0 | L58: 0 | M58: 0 | N58: 0
A59: Issues of the manor | B59: 10 shilling from 48 feeble lambs sold, at 2.5pence each. | C59: 0.51 | D59: 0 | E59: 10 | F59: 2.5 | H59: 0 | I59: 0 | J59: 0 | K59: 0 | L59: 0 | M59: 0 | N59: 0
... A72: Issues of the manor | B72: 4 shilling 6.5pence from 0.5 wey 1 clove of butter solpence Total, £16 5 shilling 4.75pence | C72: 16.27 | D72: 16 | E72: 5 | F72: 4.75 | H72: 0 | I72: 0 | J72: 0 | K72: 0 | L72: 0 | M72: 0 | N72: 0
A73: Sale of corn | B73: The same render account for £12 1 shilling 3.5pence from 42 quarters 2.5 bushels of wheat sold, at 4 shilling 8d a quarters for 5.5 quarters, 5 shilling a quarters for 17.5 quarters 3 bushels, and 6 shilling 8pence a quarters for 18.5 quarters. | C73: 12.06 | D73: 12 | E73: 1 | F73: 3.5 | G73: wheat | H73: 41.5 | I73: 3 | J73: 41.875 | K73: 42.3125 | L73: -0.4375 | M73: 42 | N73: 2.5 | O73: 5.5 | P73: 0 | Q73: 17.5 | R73: 3 | S73: 18.5 | T73: 0 | U73: 5 | V73: 0 | W73: 6 | X73: 8
A74: Sale of corn | B74: £1 1 shilling 3pence from 6 quarters 3 bushels of curall sold, at 3 shilling 4pence a quarters. | C74: 1.06 | D74: 1 | E74: 1 | F74: 3 | G74: curall | H74: 6 | I74: 3 | J74: 6.375 | K74: 6.375 | L74: 0 | M74: 6 | N74: 3 | U74: 3 | V74: 4
A75: Sale of corn | B75: 1 shilling 4pence from 4 bushels of maslin sold. | C75: 0.07 | D75: 0 | E75: 1 | F75: 4 | G75: maslin | H75: 0 | I75: 4 | J75: 0.5 | K75: 0.5 | L75: 0 | M75: 0 | N75: 4
A76: Sale of corn | B76: £1 16 shilling 8pence from 11 quarters of bere sold, at 3 shilling 4pence a quarters. | C76: 1.83 | D76: 1 | E76: 16 | F76: 8 | H76: 11 | I76: 0 | J76: 11 | K76: 11 | L76: 0 | M76: 11 | N76: 0 | U76: 3 | V76: 4
A77: Sale of corn | B77: £6 9 shilling 9pence from 34 quarters 1 bushels of barley sold, at 3 shilling 4pence a quarters for 10 quarters 1 bushels, and 4 shilling a quarters for 24 quarters. | C77: 6.49 | D77: 6 | E77: 9 | F77: 9 | G77: barley | H77: 34 | I77: 1 | J77: 34.125 | K77: 34.125 | L77: 0 | M77: 34 | N77: 1 | O77: 10 | P77: 1 | Q77: 24 | R77: 0 | U77: 3 | V77: 4 | W77: 4 | X77: 0
A78: Sale of corn | B78: £4 3 shilling 2pence from 34.5 quarters 2 bushels of oats sold, at 2 shilling a quarters for 14 quarters 2 bushels, and 2 shilling 8pence a quarters for 20.5. | C78: 4.16 | D78: 4 | E78: 3 | F78: 2 | G78: oats | H78: 14 | I78: 2 | J78: 14.25 | K78: 34.75 | L78: -20.5 | M78: 34.5 | N78: 2 | O78: 14 | P78: 2 | U78: 2 | V78: 0 | W78: 2 | X78: 8
A79: Sale of corn | B79: £1 9pence from 9.5quarters 1 bushels of peas sold, at 2 shilling a quarters for 7 quarters 3 bushels, and 2 shilling 8pence a quarters for 2 quarters 2 bushels. | C79: 1.04 | D79: 1 | E79: 0 | F79: 9 | G79: peas | H79: 9 | I79: 5 | J79: 9.625 | K79: 9.625 | L79: 0 | M79: 9.5 | N79: 1 | O79: 7 | P79: 3 | Q79: 2 | R79: 2 | U79: 2 | V79: 0 | W79: 2 | X79: 8
A80: Sale of corn | B80: £1 5 shilling 6.5 from 14 quarters 3 bushels of vetches sold, at 1 shilling 4pence a quarters for 8 quarters for 6 quarters 3 bushels Total, £27 19 shilling 9pence | C80: 1.25 | D80: 1 | E80: 5 | F80: 0 | G80: vetches | H80: 14 | I80: 3 | J80: 14.375 | K80: 14.375 | L80: 0 | M80: 14 | N80: 3 | O80: 8 | P80: 0 | Q80: 6 | R80: 3 | U80: 1 | V80: 4
A81: Entry and marriage fines | B81: The same render account for 10 shilling from Alice, relict of Cuppyng Breton, to retain 1 messuage and' virgate of land which belonged to her husband. | C81: 0.5 | D81: 0 | E81: 10 | F81: 0 | H81: 0 | I81: 0 | J81: 0 | K81: 0 | L81: 0 | M81: 0 | N81: 0
A82: Entry and marriage fines | B82: £1 from John Seyle to have 1 messuage and 0.5 virgate of land which belonged to Isabel his mother whose heir he is. | C82: 1 | D82: 1 | E82: 0 | F82: 0 | H82: 0 | I82: 0 | J82: 0 | K82: 0 | L82: 0 | M82: 0 | N82: 0
A83: Entry and marriage fines | B83: 2 shilling from William le Y1 to have 1 messuage and 1 ferling which belonged to Alice his mother whose heir he is. | C83: 0.1 | D83: 0 | E83: 2 | F83: 0 | H83: 0 | I83: 0 | J83: 0 | K83: 0 | L83: 0 | M83: 0 | N83: 0
A84: Entry and marriage fines | B84: 4 shilling from Joan la Hore to have 1 messuage and .5 virgate of land which belonged to John, son of her uncle, whose heir she is. | C84: 0.2 | D84: 0 | E84: 4 | F84: 0 | H84: 0 | I84: 0 | J84: 0 | K84: 0 | L84: 0 | M84: 0 | N84: 0
A85: Entry and marriage fines | B85: 6 shilling 8pence from John Chapelay of Hawkley to have Joan la Hore with .5 virgate of her land. | C85: 0.33 | D85: 0 | E85: 6 | F85: 8 | H85: 0 | I85: 0 | J85: 0 | K85: 0 | L85: 0 | M85: 0 | N85: 0
A86: Entry and marriage fines | B86: 1 shilling from Guy Gamnoky to have 2 day-works of land by surrender of Richard de Seleford', and the said Guy will relieve the said Richard of 1pence annual rent for the year. | C86: 0.05 | D86: 0 | E86: 1 | F86: 1 | H86: 0 | I86: 0 | J86: 0 | K86: 0 | L86: 0 | M86: 0 | N86: 0
A87: Entry and marriage fines | B87: Total, £2 3 shilling 8pence | C87: 2.18 | D87: 2 | E87: 3 | F87: 8 | H87: 0 | I87: 0 | J87: 0 | K87: 0 | L87: 0 | M87: 0 | N87: 0
A88: Perquisites | B88: The same render account for 2 shilling from Peter de Brok, overseer of the harvest, for keeping the lord's fields and pastures badly. | C88: 0.1 | D88: 0 | E88: 2 | F88: 0 | H88: 0 | I88: 0 | J88: 0 | K88: 0 | L88: 0 | M88: 0 | N88: 0
A89: Perquisites | B89: 16 shilling 3pence from various men for various transgressions. | C89: 0.81 | D89: 0 | E89: 16 | F89: 3 | H89: 0 | I89: 0 | J89: 0 | K89: 0 | L89: 0 | M89: 0 | N89: 0
A90: Perquisites | B90: Total, 18 shilling 3pence | C90: 0.91 | D90: 0 | E90: 18 | F90: 3 | H90: 0 | I90: 0 | J90: 0 | K90: 0 | L90: 0 | M90: 0 | N90: 0
A91: Total of both | B91: Total of both, £3 1 shilling 11pence | C91: 3.1 | D91: 3 | E91: 1 | F91: 11 | H91: 0 | I91: 0 | J91: 0 | K91: 0 | L91: 0 | M91: 0 | N91: 0
A92: Total of all receipts | B92: Total of all receipts, £80 1 s. 9pence | C92: 80 | D92: 80 | E92: 0 | F92: 0 | H92: 0 | I92: 0 | J92: 0 | K92: 0 | L92: 0 | M92: 0 | N92: 0
... A155: Cost of buildings | B155: building a stack of forage in the curia 1 shilling 1pence Total, £1 2 shilling 6.5pence | C155: 1.13 | D155: 1 | E155: 2 | F155: 6.5 | H155: 0 | I155: 0 | J155: 0 | K155: 0 | L155: 0 | M155: 0 | N155: 0
A156: Threshing | B156: In threshing and winnowing 49 quarters 1 bushels of wheat, curall and maslin by piece-work 11 shilling 2.75pence, at 2.75pence a heaped quarter. | C156: 0.56 | D156: 0 | E156: 11 | F156: 2.75 | G156: curall, maslin, wheat | H156: 49 | I156: 1 | J156: 49.125 | K156: 49.125 | L156: 0 | M156: 49 | N156: 1
A157: Threshing | B157: . | C157: 0 | D157: 0 | E157: 0 | F157: 0 | H157: 0 | I157: 0 | J157: 0 | K157: 0 | L157: 0 | M157: 0 | N157: 0
A158: Threshing | B158: threshing and winnowing 78 quarters of bere and barley by piece-work 11 shilling 4.5pence, at 1.75pence a heaped quarter. | C158: 0.57 | D158: 0 | E158: 11 | F158: 4.5 | G158: barley | H158: 78 | I158: 0 | J158: 78 | K158: 78 | L158: 0 | M158: 78 | N158: 0
A159: Threshing | B159: . | C159: 0 | D159: 0 | E159: 0 | F159: 0 | H159: 0 | I159: 0 | J159: 0 | K159: 0 | L159: 0 | M159: 0 | N159: 0
A160: Threshing | B160: threshing and winnowing 75 quarters of oats 5 shilling 5.5pence, at 0.75pence a heaped quarter, and 0.25pence per 2 quarters winnowepence. | C160: 0.27 | D160: 0 | E160: 5 | F160: 5.5 | G160: oats | H160: 2 | I160: 0 | J160: 2 | K160: 75 | L160: -73 | M160: 75 | N160: 0 | O160: 2 | P160: 0
A161: Threshing | B161: threshing and winnowing 25 quarters 3 bushels of peas and vetches by piece-work 4 shilling 9pence, at 2.25pence a heaped quarter. | C161: 0.24 | D161: 0 | E161: 4 | F161: 9 | G161: vetches, peas | H161: 25 | I161: 3 | J161: 25.375 | K161: 25.375 | L161: 0 | M161: 25 | N161: 3
A162: Threshing | B162: . | C162: 0 | D162: 0 | E162: 0 | F162: 0 | H162: 0 | I162: 0 | J162: 0 | K162: 0 | L162: 0 | M162: 0 | N162: 0
A163: Threshing | B163: 1 sack bought 5.5pence. | C163: 0.02 | D163: 0 | E163: 0 | F163: 5.5 | H163: 0 | I163: 0 | J163: 0 | K163: 0 | L163: 0 | M163: 0 | N163: 0
A164: Threshing | B164: 1 basket bought for corn 2.5pence Total, £1 13 shilling 5.75pence | C164: 1.67 | D164: 1 | E164: 13 | F164: 5.75 | H164: 0 | I164: 0 | J164: 0 | K164: 0 | L164: 0 | M164: 0 | N164: 0
A165: Harvest-time | B165: In weeding all the corn over and above that weeded by labour service 3 shilling 9pence. | C165: 0.19 | D165: 0 | E165: 3 | F165: 9 | H165: 0 | I165: 0 | J165: 0 | K165: 0 | L165: 0 | M165: 0 | N165: 0
A166: Harvest-time | B166: herrings bought for 6 boon-works of 590 men having two meals a day and 4 herrings each, and for 7 boon-works of 660 men having 1 meal a day and 2 herrings each, 18 shilling 2.5pence. | C166: 0.91 | D166: 0 | E166: 18 | F166: 2.5 | H166: 0 | I166: 0 | J166: 0 | K166: 0 | L166: 0 | M166: 0 | N166: 0
A167: Harvest-time | B167: expenses of the reeve, hayward and other officials of the curia from Lammas (1 August) until the Decollation of St John the Baptist (29 August), for 4 weeks, 5 shilling 4pence Total, £1 7 shilling 3.54. | C167: 1.35 | D167: 1 | E167: 7 | F167: 0 | H167: 0 | I167: 0 | J167: 0 | K167: 0 | L167: 0 | M167: 0 | N167: 0
A168: Expenses of the steward | B168: In expenses of the steward for 2 tourns by 1 tally 2 shilling. | C168: 0.1 | D168: 0 | E168: 2 | F168: 0 | H168: 0 | I168: 0 | J168: 0 | K168: 0 | L168: 0 | M168: 0 | N168: 0
A169: Expenses of the steward | B169: expenses of Roger, bailiff from Michaelmas until Christmas, for his visits 3 shilling. | C169: 0.15 | D169: 0 | E169: 3 | F169: 0 | H169: 0 | I169: 0 | J169: 0 | K169: 0 | L169: 0 | M169: 0 | N169: 0
A170: Expenses of the steward | B170: expenses of Robert, bailiff from Christmas until Michaelmas, for his visits 5 shilling 3pence Total, 10 shilling 3pence | C170: 0.26 | D170: 0 | E170: 5 | F170: 3 | H170: 0 | I170: 0 | J170: 0 | K170: 0 | L170: 0 | M170: 0 | N170: 0
A171: Total of all expenses | B171: Total of all expenses, £10 19 shilling 9pence | C171: 10.99 | D171: 10 | E171: 19 | F171: 9 | H171: 0 | I171: 0 | J171: 0 | K171: 0 | L171: 0 | M171: 0 | N171: 0
A172: And he owes | B172: And he owes, £68 2 shilling | C172: 68.1 | D172: 68 | E172: 2 | F172: 0 | H172: 0 | I172: 0 | J172: 0 | K172: 0 | L172: 0 | M172: 0 | N172: 0
A173: And he owes clear | B173: And he owes clear, £20 12 shilling | C173: 20.6 | D173: 20 | E173: 12 | F173: 0 | H173: 0 | I173: 0 | J173: 0 | K173: 0 | L173: 0 | M173: 0 | N173: 0
A174: Wheat | B174: {yield: 1 quarters 5 bushels} | C174: 0 | D174: 0 | E174: 0 | F174: 0 | H174: 1 | I174: 5 | J174: 1.625 | K174: 1.625 | L174: 0 | M174: 1 | N174: 5
A175: Wheat | B175: The same render account for 47.5 quarters from the whole issue of wheat by struck measure. | C175: 0 | D175: 0 | E175: 0 | F175: 0 | G175: wheat | H175: 47.5 | I175: 0 | J175: 47.5 | K175: 47.5 | L175: 0 | M175: 47.5 | N175: 0
A176: Wheat | B176: 10.5 quarters 2.5 bushels from churchscot. | C176: 0 | D176: 0 | E176: 0 | F176: 0 | H176: 10.5 | I176: 2.5 | J176: 10.8125 | K176: 10.8125 | L176: 0 | M176: 10.5 | N176: 2.5
A177: Wheat | B177: Total, 58 quarters 2.5 bushels | C177: 0 | D177: 0 | E177: 0 | F177: 0 | H177: 58 | I177: 2.5 | J177: 58.3125 | K177: 58.3125 | L177: 0 | M177: 58 | N177: 2.5
A178: Wheat | B178: Sown over 154.5 acres which lie in le Sorelond', Tonforlong', le Suthemestecrofte, and Fomden', 14.5 quarters. | C178: 0 | D178: 0 | E178: 0 | F178: 0 | H178: 14.5 | I178: 0 | J178: 14.5 | K178: 14.5 | L178: 0 | M178: 14.5 | N178: 0
A179: Wheat | B179: that is, 1.5 bushels over 2 acres. | C179: 0 | D179: 0 | E179: 0 | F179: 0 | H179: 0 | I179: 1.5 | J179: 0.1875 | K179: 0.1875 | L179: 0 | M179: 0 | N179: 1.5
A180: Wheat | B180: . | C180: 0 | D180: 0 | E180: 0 | F180: 0 | H180: 0 | I180: 0 | J180: 0 | K180: 0 | L180: 0 | M180: 0 | N180: 0
A181: Wheat | B181: customary payment to 1 sower, 1 bushels. | C181: 0 | D181: 0 | E181: 0 | F181: 0 | H181: 0 | I181: 1 | J181: 0.125 | K181: 0.125 | L181: 0 | M181: 0 | N181: 1
A182: Wheat | B182: provision of 1 reeve, 1 hayward keeping the woods and pasture, and 1 beadle, from Lammas until the Decollation of St John the Baptist, for 4 weeks, 6 bushels Nothing for the provison of the steward this year. | C182: 0 | D182: 0 | E182: 0 | F182: 0 | H182: 0 | I182: 6 | J182: 0.75 | K182: 0.75 | L182: 0 | M182: 0 | N182: 6
A183: Wheat | B183: . | C183: 0 | D183: 0 | E183: 0 | F183: 0 | H183: 0 | I183: 0 | J183: 0 | K183: 0 | L183: 0 | M183: 0 | N183: 0
A184: Wheat | B184: default of the land of Horn for churchscot, 2 bushels. | C184: 0 | D184: 0 | E184: 0 | F184: 0 | H184: 0 | I184: 2 | J184: 0.25 | K184: 0.25 | L184: 0 | M184: 0 | N184: 2
A185: Wheat | B185: the land of Tyle, 1.5 bushels. | C185: 0 | D185: 0 | E185: 0 | F185: 0 | H185: 0 | I185: 1.5 | J185: 0.1875 | K185: 0.1875 | L185: 0 | M185: 0 | N185: 1.5
A186: Wheat | B186: the reeve (le Reve), 0.5 bushels 1 peck. | C186: 0 | D186: 0 | E186: 0 | F186: 0 | H186: 0 | I186: 0.5 | J186: 0.0625 | K186: 0.0625 | L186: 0 | M186: 0 | N186: 0.5
A187: Wheat | B187: the land of the millward (le Meleward') 0.5 bushels 1 peck. | C187: 0 | D187: 0 | E187: 0 | F187: 0 | H187: 0 | I187: 0.5 | J187: 0.0625 | K187: 0.0625 | L187: 0 | M187: 0 | N187: 0.5
A188: Wheat | B188: Sold, 42 quarters 2.5 bushels It balances. | C188: 0 | D188: 0 | E188: 0 | F188: 0 | H188: 42 | I188: 2.5 | J188: 42.3125 | K188: 42.3125 | L188: 0 | M188: 42 | N188: 2.5
A189: Curall | B189: The same render account for 6 quarters 3 bushels from the whole issue of curall by struck measure. | C189: 0 | D189: 0 | E189: 0 | F189: 0 | G189: curall | H189: 6 | I189: 3 | J189: 6.375 | K189: 6.375 | L189: 0 | M189: 6 | N189: 3
A190: Curall | B190: Sold, 6 quarters 3 bushels | C190: 0 | D190: 0 | E190: 0 | F190: 0 | H190: 6 | I190: 3 | J190: 6.375 | K190: 6.375 | L190: 0 | M190: 6 | N190: 3
A191: Rye | B191: The same render account for 2 quarters 0.5 bushels of rye from churchscot. | C191: 0 | D191: 0 | E191: 0 | F191: 0 | G191: rye | H191: 2 | I191: 0.5 | J191: 2.0625 | K191: 2.0625 | L191: 0 | M191: 2 | N191: 0.5
A192: Rye | B192: Sold, 2 quarters 0.5 bushels | C192: 0 | D192: 0 | E192: 0 | F192: 0 | H192: 2 | I192: 0.5 | J192: 2.0625 | K192: 2.0625 | L192: 0 | M192: 2 | N192: 0.5
A193: Maslin | B193: {yield: two-fold plus . . . 1 bushels} | C193: 0 | D193: 0 | E193: 0 | F193: 0 | H193: 0 | I193: 1 | J193: 0.125 | K193: 0.125 | L193: 0 | M193: 0 | N193: 1
A194: Maslin | B194: The same render account for 7.5 quarters 1 bushels from the whole issue of maslin by struck measure. | C194: 0 | D194: 0 | E194: 0 | F194: 0 | G194: maslin | H194: 7.5 | I194: 1 | J194: 7.625 | K194: 7.625 | L194: 0 | M194: 7.5 | N194: 1
A195: Maslin | B195: Mixed with barley, 7 quarters 1 bushels Sold, 4 bushels | C195: 0 | D195: 0 | E195: 0 | F195: 0 | G195: barley | H195: 7 | I195: 4 | J195: 7.5 | K195: 7.125 | L195: 0.375 | M195: 7 | N195: 1 | O195: 0 | P195: 4
A196: Bere | B196: {yield: . . . plus 6 bushels} | C196: 0 | D196: 0 | E196: 0 | F196: 0 | H196: 0 | I196: 6 | J196: 0.75 | K196: 0.75 | L196: 0 | M196: 0 | N196: 6
A197: Bere | B197: The same render account for 25 quarters 2 bushels from the whole issue of bere by struck measure. | C197: 0 | D197: 0 | E197: 0 | F197: 0 | H197: 25 | I197: 2 | J197: 25.25 | K197: 25.25 | L197: 0 | M197: 25 | N197: 2
A198: Bere | B198: Sown over 21 acres as they lie in le Grove, 5 quarters 2 bushels Mixed with barley for the liveries of the manorial servants, 9 quarters. | C198: 0 | D198: 0 | E198: 0 | F198: 0 | G198: barley | H198: 9 | I198: 2 | J198: 9.25 | K198: 5.25 | L198: 4 | M198: 5 | N198: 2 | O198: 9 | P198: 0
A199: Bere | B199: Sold, 11 quarters. | C199: 0 | D199: 0 | E199: 0 | F199: 0 | H199: 11 | I199: 0 | J199: 11 | K199: 11 | L199: 0 | M199: 11 | N199: 0
A200: Barley | B200: (yield: 5-fold . 1 quarters 1 bushels) | C200: 0 | D200: 0 | E200: 0 | F200: 0 | H200: 1 | I200: 1 | J200: 1.125 | K200: 1.125 | L200: 0 | M200: 1 | N200: 1
A201: Barley | B201: The same render account for 73.5 quarters 1 bushels from the whole issue of barley by struck measure. | C201: 0 | D201: 0 | E201: 0 | F201: 0 | G201: barley | H201: 73.5 | I201: 1 | J201: 73.625 | K201: 73.625 | L201: 0 | M201: 73.5 | N201: 1
A202: Barley | B202: 7 quarters 1 bushels received above from maslin. | C202: 0 | D202: 0 | E202: 0 | F202: 0 | G202: maslin | H202: 7 | I202: 1 | J202: 7.125 | K202: 7.125 | L202: 0 | M202: 7 | N202: 1
A203: Barley | B203: 9 quarters received above from bere. | C203: 0 | D203: 0 | E203: 0 | F203: 0 | H203: 9 | I203: 0 | J203: 9 | K203: 9 | L203: 0 | M203: 9 | N203: 0
A204: Barley | B204: 3 quarters 3 bushels, received from vetches for the liveries of the manorial servants. | C204: 0 | D204: 0 | E204: 0 | F204: 0 | G204: vetches | H204: 3 | I204: 3 | J204: 3.375 | K204: 3.375 | L204: 0 | M204: 3 | N204: 3
A205: Barley | B205: Total, 93 quarters 1 bushels | C205: 0 | D205: 0 | E205: 0 | F205: 0 | H205: 93 | I205: 1 | J205: 93.125 | K205: 93.125 | L205: 0 | M205: 93 | N205: 1
A206: Barley | B206: Sown over 86 acres as they lie in le Harnesgate, le Grove, and Tonforlong' behind the garden, 16 quarters 1 bushels. | C206: 0 | D206: 0 | E206: 0 | F206: 0 | H206: 16 | I206: 1 | J206: 16.125 | K206: 16.125 | L206: 0 | M206: 16 | N206: 1
...

Sheet Issues of the Grange raw
A1: Heading | B1: Sentence | C1: Quarters 1_x | D1: Bushels 1_x | E1: Sown Quarters | F1: Sown Bushels | G1: Sown Total Quarters | H1: Bought in Quarters | I1: Bought in Bushels | J1: Bought in Total Quarters | K1: Tithe Quarters | L1: Tithe Bushels | M1: Tithe Total Quarters | N1: Manorial servants & livestock Quarters | O1: Manorial servants & livestock Bushels | P1: Manorial servants & livestock Total Quarters | Q1: Sold Quarters | R1: Sold Bushels | S1: Sold Total Quarters | T1: Account Quarters | U1: Account Bushels | V1: Account Total Quarters | W1: bought only | X1: Total Quarters Except 1 | Y1: Total Bushels Except 1 | Z1: Total Corn Cross-Check | AA1: Total Corn Manorial Account | AB1: Corn Quantity Error | AC1: Quarters 1_y | AD1: Bushels 1_y | AE1: Quarters 2 | AF1: Bushels 2 | AG1: Quarters 3 | AH1: Bushels 3 | AI1: Quarters 4 | AJ1: Bushels 4
A2: And he owes | B2: Total | C2: 0 | D2: 0 | E2: 0 | F2: 0 | G2: 0 | H2: 0 | I2: 0 | J2: 0 | K2: 0 | L2: 0 | M2: 0 | N2: 0 | O2: 0 | P2: 0 | Q2: 0 | R2: 0 | S2: 0 | T2: 0 | U2: 0 | V2: 0 | W2: 0
A3: Wheat | B3: {yield: 1 qr 5 bushels} | C3: 0 | D3: 0 | E3: 0 | F3: 0 | G3: 0 | H3: 0 | I3: 0 | J3: 0 | K3: 0 | L3: 0 | M3: 0 | N3: 0 | O3: 0 | P3: 0 | Q3: 0 | R3: 0 | S3: 0 | T3: 0 | U3: 0 | V3: 0 | W3: 0
A4: Wheat | B4: The same render account for 47.5 quarters from the whole issue of wheat by struck measure. | C4: 0 | D4: 0 | E4: 0 | F4: 0 | G4: 0 | H4: 0 | I4: 0 | J4: 0 | K4: 0 | L4: 0 | M4: 0 | N4: 0 | O4: 0 | P4: 0 | Q4: 0 | R4: 0 | S4: 0 | T4: 47.5 | U4: 0 | V4: 47.5 | W4: 0 | X4: 47.5 | Y4: 0 | Z4: 47.5 | AA4: 47.5 | AB4: 0 | AC4: 47.5 | AD4: 0
A5: Wheat | B5: 10.5 quarters 2.5 bushels from churchscot. | C5: 0 | D5: 0 | E5: 0 | F5: 0 | G5: 0 | H5: 0 | I5: 0 | J5: 0 | K5: 0 | L5: 0 | M5: 0 | N5: 0 | O5: 0 | P5: 0 | Q5: 0 | R5: 0 | S5: 0 | T5: 0 | U5: 0 | V5: 0 | W5: 0 | X5: 10.5 | Y5: 2.5 | Z5: 10.8125 | AA5: 10.8125 | AB5: 0 | AC5: 10.5 | AD5: 2.5
A6: Wheat | B6: Total, 58 quarters 2.5 bushels | C6: 0 | D6: 0 | E6: 0 | F6: 0 | G6: 0 | H6: 0 | I6: 0 | J6: 0 | K6: 0 | L6: 0 | M6: 0 | N6: 0 | O6: 0 | P6: 0 | Q6: 0 | R6: 0 | S6: 0 | T6: 0 | U6: 0 | V6: 0 | W6: 0 | X6: 58 | Y6: 2.5 | Z6: 58.3125 | AA6: 58.3125 | AB6: 0 | AC6: 58 | AD6: 2.5
A7: Wheat | B7: Sown over 154.5 acres which lie in le Sorelond', Tonforlong', le Suthemestecrofte, and Fomden', 14.5 quarters. | C7: 0 | D7: 0 | E7: 14.5 | F7: 0 | G7: 14.5 | H7: 0 | I7: 0 | J7: 0 | K7: 0 | L7: 0 | M7: 0 | N7: 0 | O7: 0 | P7: 0 | Q7: 0 | R7: 0 | S7: 0 | T7: 0 | U7: 0 | V7: 0 | W7: 0 | X7: 14.5 | Y7: 0 | Z7: 14.5 | AA7: 14.5 | AB7: 0 | AC7: 14.5 | AD7: 0
A8: Wheat | B8: that is, 1.5 bushels over 2 acres. | C8: 0 | D8: 0 | E8: 0 | F8: 0 | G8: 0 | H8: 0 | I8: 0 | J8: 0 | K8: 0 | L8: 0 | M8: 0 | N8: 0 | O8: 0 | P8: 0 | Q8: 0 | R8: 0 | S8: 0 | T8: 0 | U8: 0 | V8: 0 | W8: 0 | X8: 0 | Y8: 1.5 | Z8: 0.1875 | AA8: 0.1875 | AB8: 0 | AC8: 0 | AD8: 1.5
A9: Wheat | B9: . | C9: 0 | D9: 0 | E9: 0 | F9: 0 | G9: 0 | H9: 0 | I9: 0 | J9: 0 | K9: 0 | L9: 0 | M9: 0 | N9: 0 | O9: 0 | P9: 0 | Q9: 0 | R9: 0 | S9: 0 | T9: 0 | U9: 0 | V9: 0 | W9: 0 | X9: 0 | Y9: 0 | Z9: 0 | AA9: 0 | AB9: 0 | AC9: 0 | AD9: 0
A10: Wheat | B10: . | C10: 0 | D10: 0 | E10: 0 | F10: 0 | G10: 0 | H10: 0 | I10: 0 | J10: 0 | K10: 0 | L10: 0 | M10: 0 | N10: 0 | O10: 0 | P10: 0 | Q10: 0 | R10: 0 | S10: 0 | T10: 0 | U10: 0 | V10: 0 | W10: 0 | X10: 0 | Y10: 0 | Z10: 0 | AA10: 0 | AB10: 0 | AC10: 0 | AD10: 0
A11: Wheat | B11: customary payment to 1 sower, 1 bushels. | C11: 0 | D11: 0 | E11: 0 | F11: 0 | G11: 0 | H11: 0 | I11: 0 | J11: 0 | K11: 0 | L11: 0 | M11: 0 | N11: 0 | O11: 0 | P11: 0 | Q11: 0 | R11: 0 | S11: 0 | T11: 0 | U11: 0 | V11: 0 | W11: 0 | X11: 0 | Y11: 1 | Z11: 0.125 | AA11: 0.125 | AB11: 0 | AC11: 0 | AD11: 1
A12: Wheat | B12: provision of 1 reeve, 1 hayward keeping the woods and pasture, and 1 beadle, from Lammas until the Decollation of St John the Baptist, for 4 weeks, 6 bushels Nothing for the provison of the steward this year. | C12: 0 | D12: 0 | E12: 0 | F12: 0 | G12: 0 | H12: 0 | I12: 0 | J12: 0 | K12: 0 | L12: 0 | M12: 0 | N12: 0 | O12: 0 | P12: 0 | Q12: 0 | R12: 0 | S12: 0 | T12: 0 | U12: 0 | V12: 0 | W12: 0 | X12: 0 | Y12: 6 | Z12: 0.75 | AA12: 0.75 | AB12: 0 | AC12: 0 | AD12: 6
A13: Wheat | B13: . | C13: 0 | D13: 0 | E13: 0 | F13: 0 | G13: 0 | H13: 0 | I13: 0 | J13: 0 | K13: 0 | L13: 0 | M13: 0 | N13: 0 | O13: 0 | P13: 0 | Q13: 0 | R13: 0 | S13: 0 | T13: 0 | U13: 0 | V13: 0 | W13: 0 | X13: 0 | Y13: 0 | Z13: 0 | AA13: 0 | AB13: 0 | AC13: 0 | AD13: 0
A14: Wheat | B14: . | C14: 0 | D14: 0 | E14: 0 | F14: 0 | G14: 0 | H14: 0 | I14: 0 | J14: 0 | K14: 0 | L14: 0 | M14: 0 | N14: 0 | O14: 0 | P14: 0 | Q14: 0 | R14: 0 | S14: 0 | T14: 0 | U14: 0 | V14: 0 | W14: 0 | X14: 0 | Y14: 0 | Z14: 0 | AA14: 0 | AB14: 0 | AC14: 0 | AD14: 0
A15: Wheat | B15: default of the land of Horn for churchscot, 2 bushels. | C15: 0 | D15: 0 | E15: 0 | F15: 0 | G15: 0 | H15: 0 | I15: 0 | J15: 0 | K15: 0 | L15: 0 | M15: 0 | N15: 0 | O15: 0 | P15: 0 | Q15: 0 | R15: 0 | S15: 0 | T15: 0 | U15: 0 | V15: 0 | W15: 0 | X15: 0 | Y15: 2 | Z15: 0.25 | AA15: 0.25 | AB15: 0 | AC15: 0 | AD15: 2
... A19: Wheat | B19: Sold, 42 quarters 2.5 bushels It balances. | C19: 0 | D19: 0 | E19: 0 | F19: 0 | G19: 0 | H19: 0 | I19: 0 | J19: 0 | K19: 0 | L19: 0 | M19: 0 | N19: 0 | O19: 0 | P19: 0 | Q19: 42 | R19: 2.5 | S19: 42.3125 | T19: 0 | U19: 0 | V19: 0 | W19: 0 | X19: 42 | Y19: 2.5 | Z19: 42.3125 | AA19: 42.3125 | AB19: 0 | AC19: 42 | AD19: 2.5
A20: Wheat | B20: Total | C20: 0 | D20: 0 | E20: 0 | F20: 0 | G20: 0 | H20: 0 | I20: 0 | J20: 0 | K20: 0 | L20: 0 | M20: 0 | N20: 0 | O20: 0 | P20: 0 | Q20: 0 | R20: 0 | S20: 0 | T20: 0 | U20: 0 | V20: 0 | W20: 0
A21: Curall | B21: The same render account for 6 quarters 3 bushels from the whole issue of curall by struck measure. | C21: 0 | D21: 0 | E21: 0 | F21: 0 | G21: 0 | H21: 0 | I21: 0 | J21: 0 | K21: 0 | L21: 0 | M21: 0 | N21: 0 | O21: 0 | P21: 0 | Q21: 0 | R21: 0 | S21: 0 | T21: 6 | U21: 3 | V21: 6.375 | W21: 0 | X21: 6 | Y21: 3 | Z21: 6.375 | AA21: 6.375 | AB21: 0 | AC21: 6 | AD21: 3
A22: Curall | B22: Sold, 6 quarters 3 bushels | C22: 0 | D22: 0 | E22: 0 | F22: 0 | G22: 0 | H22: 0 | I22: 0 | J22: 0 | K22: 0 | L22: 0 | M22: 0 | N22: 0 | O22: 0 | P22: 0 | Q22: 6 | R22: 3 | S22: 6.375 | T22: 0 | U22: 0 | V22: 0 | W22: 0 | X22: 6 | Y22: 3 | Z22: 6.375 | AA22: 6.375 | AB22: 0 | AC22: 6 | AD22: 3
A23: Curall | B23: Total | C23: 0 | D23: 0 | E23: 0 | F23: 0 | G23: 0 | H23: 0 | I23: 0 | J23: 0 | K23: 0 | L23: 0 | M23: 0 | N23: 0 | O23: 0 | P23: 0 | Q23: 0 | R23: 0 | S23: 0 | T23: 0 | U23: 0 | V23: 0 | W23: 0
A24: Rye | B24: The same render account for 2 quarters 0.5 bushels of rye from churchscot. | C24: 0 | D24: 0 | E24: 0 | F24: 0 | G24: 0 | H24: 0 | I24: 0 | J24: 0 | K24: 0 | L24: 0 | M24: 0 | N24: 0 | O24: 0 | P24: 0 | Q24: 0 | R24: 0 | S24: 0 | T24: 2 | U24: 0.5 | V24: 2.0625 | W24: 0 | X24: 2 | Y24: 0.5 | Z24: 2.0625 | AA24: 2.0625 | AB24: 0 | AC24: 2 | AD24: 0.5
A25: Rye | B25: Sold, 2 quarters 0.5 bushels | C25: 0 | D25: 0 | E25: 0 | F25: 0 | G25: 0 | H25: 0 | I25: 0 | J25: 0 | K25: 0 | L25: 0 | M25: 0 | N25: 0 | O25: 0 | P25: 0 | Q25: 2 | R25: 0.5 | S25: 2.0625 | T25: 0 | U25: 0 | V25: 0 | W25: 0 | X25: 2 | Y25: 0.5 | Z25: 2.0625 | AA25: 2.0625 | AB25: 0 | AC25: 2 | AD25: 0.5
A26: Rye | B26: Total | C26: 0 | D26: 0 | E26: 0 | F26: 0 | G26: 0 | H26: 0 | I26: 0 | J26: 0 | K26: 0 | L26: 0 | M26: 0 | N26: 0 | O26: 0 | P26: 0 | Q26: 0 | R26: 0 | S26: 0 | T26: 0 | U26: 0 | V26: 0 | W26: 0
A27: Maslin | B27: {yield: two-fold plus . . . 1 bushels} | C27: 0 | D27: 0 | E27: 0 | F27: 0 | G27: 0 | H27: 0 | I27: 0 | J27: 0 | K27: 0 | L27: 0 | M27: 0 | N27: 0 | O27: 0 | P27: 0 | Q27: 0 | R27: 0 | S27: 0 | T27: 0 | U27: 0 | V27: 0 | W27: 0 | X27: 0 | Y27: 1 | Z27: 0.125 | AA27: 0.125 | AB27: 0 | AC27: 0 | AD27: 1
A28: Maslin | B28: The same render account for 7.5 quarters 1 bushels from the whole issue of maslin by struck measure. | C28: 0 | D28: 0 | E28: 0 | F28: 0 | G28: 0 | H28: 0 | I28: 0 | J28: 0 | K28: 0 | L28: 0 | M28: 0 | N28: 0 | O28: 0 | P28: 0 | Q28: 0 | R28: 0 | S28: 0 | T28: 7.5 | U28: 1 | V28: 7.625 | W28: 0 | X28: 7.5 | Y28: 1 | Z28: 7.625 | AA28: 7.625 | AB28: 0 | AC28: 7.5 | AD28: 1
A29: Maslin | B29: Mixed with barley, 7 quarters 1 bushels Sold, 4 bushels | C29: 0 | D29: 0 | E29: 0 | F29: 0 | G29: 0 | H29: 0 | I29: 0 | J29: 0 | K29: 0 | L29: 0 | M29: 0 | N29: 0 | O29: 0 | P29: 0 | Q29: 7 | R29: 1 | S29: 7.125 | T29: 0 | U29: 0 | V29: 0 | W29: 0 | X29: 7 | Y29: 4 | Z29: 7.5 | AA29: 7.125 | AB29: 0.375 | AC29: 7 | AD29: 1 | AE29: 0 | AF29: 4
A30: Maslin | B30: Total | C30: 0 | D30: 0 | E30: 0 | F30: 0 | G30: 0 | H30: 0 | I30: 0 | J30: 0 | K30: 0 | L30: 0 | M30: 0 | N30: 0 | O30: 0 | P30: 0 | Q30: 0 | R30: 0 | S30: 0 | T30: 0 | U30: 0 | V30: 0 | W30: 0
A31: Barley | B31: (yield: 5-fold . 1 qr 1 bushels) | C31: 0 | D31: 0 | E31: 0 | F31: 0 | G31: 0 | H31: 0 | I31: 0 | J31: 0 | K31: 0 | L31: 0 | M31: 0 | N31: 0 | O31: 0 | P31: 0 | Q31: 0 | R31: 0 | S31: 0 | T31: 0 | U31: 0 | V31: 0 | W31: 0
A32: Barley | B32: The same render account for 73.5 quarters 1 bushels from the whole issue of barley by struck measure. | C32: 0 | D32: 0 | E32: 0 | F32: 0 | G32: 0 | H32: 0 | I32: 0 | J32: 0 | K32: 0 | L32: 0 | M32: 0 | N32: 0 | O32: 0 | P32: 0 | Q32: 0 | R32: 0 | S32: 0 | T32: 73.5 | U32: 1 | V32: 73.625 | W32: 0 | X32: 73.5 | Y32: 1 | Z32: 73.625 | AA32: 73.625 | AB32: 0 | AC32: 73.5 | AD32: 1
A33: Barley | B33: 7 quarters 1 bushels received above from maslin. | C33: 0 | D33: 0 | E33: 0 | F33: 0 | G33: 0 | H33: 0 | I33: 0 | J33: 0 | K33: 0 | L33: 0 | M33: 0 | N33: 0 | O33: 0 | P33: 0 | Q33: 0 | R33: 0 | S33: 0 | T33: 0 | U33: 0 | V33: 0 | W33: 0 | X33: 7 | Y33: 1 | Z33: 7.125 | AA33: 7.125 | AB33: 0 | AC33: 7 | AD33: 1
A34: Barley | B34: 9 quarters received above from bere. | C34: 0 | D34: 0 | E34: 0 | F34: 0 | G34: 0 | H34: 0 | I34: 0 | J34: 0 | K34: 0 | L34: 0 | M34: 0 | N34: 0 | O34: 0 | P34: 0 | Q34: 0 | R34: 0 | S34: 0 | T34: 0 | U34: 0 | V34: 0 | W34: 0 | X34: 9 | Y34: 0 | Z34: 9 | AA34: 9 | AB34: 0 | AC34: 9 | AD34: 0
A35: Barley | B35: 3 quarters 3 bus, received from vetches for the liveries of the manorial servants. | C35: 0 | D35: 0 | E35: 0 | F35: 0 | G35: 0 | H35: 0 | I35: 0 | J35: 0 | K35: 0 | L35: 0 | M35: 0 | N35: 3 | O35: 0 | P35: 3 | Q35: 0 | R35: 0 | S35: 0 | T35: 0 | U35: 0 | V35: 0 | W35: 0
A36: Barley | B36: Total, 93 quarters 1 bushels | C36: 0 | D36: 0 | E36: 0 | F36: 0 | G36: 0 | H36: 0 | I36: 0 | J36: 0 | K36: 0 | L36: 0 | M36: 0 | N36: 0 | O36: 0 | P36: 0 | Q36: 0 | R36: 0 | S36: 0 | T36: 0 | U36: 0 | V36: 0 | W36: 0 | X36: 93 | Y36: 1 | Z36: 93.125 | AA36: 93.125 | AB36: 0 | AC36: 93 | AD36: 1
A37: Barley | B37: Sown over 86 acres as they lie in le Harnesgate, le Grove, and Tonforlong' behind the garden, 16 quarters 1 bushels. | C37: 0 | D37: 0 | E37: 16 | F37: 1 | G37: 16.125 | H37: 0 | I37: 0 | J37: 0 | K37: 0 | L37: 0 | M37: 0 | N37: 0 | O37: 0 | P37: 0 | Q37: 0 | R37: 0 | S37: 0 | T37: 0 | U37: 0 | V37: 0 | W37: 0 | X37: 16 | Y37: 1 | Z37: 16.125 | AA37: 16.125 | AB37: 0 | AC37: 16 | AD37: 1
A38: Barley | B38: that is, 1.5 bushels an acre. | C38: 0 | D38: 0 | E38: 0 | F38: 0 | G38: 0 | H38: 0 | I38: 0 | J38: 0 | K38: 0 | L38: 0 | M38: 0 | N38: 0 | O38: 0 | P38: 0 | Q38: 0 | R38: 0 | S38: 0 | T38: 0 | U38: 0 | V38: 0 | W38: 0 | X38: 0 | Y38: 1.5 | Z38: 0.1875 | AA38: 0.1875 | AB38: 0 | AC38: 0 | AD38: 1.5
A39: Barley | B39: . | C39: 0 | D39: 0 | E39: 0 | F39: 0 | G39: 0 | H39: 0 | I39: 0 | J39: 0 | K39: 0 | L39: 0 | M39: 0 | N39: 0 | O39: 0 | P39: 0 | Q39: 0 | R39: 0 | S39: 0 | T39: 0 | U39: 0 | V39: 0 | W39: 0 | X39: 0 | Y39: 0 | Z39: 0 | AA39: 0 | AB39: 0 | AC39: 0 | AD39: 0
A40: Barley | B40: . | C40: 0 | D40: 0 | E40: 0 | F40: 0 | G40: 0 | H40: 0 | I40: 0 | J40: 0 | K40: 0 | L40: 0 | M40: 0 | N40: 0 | O40: 0 | P40: 0 | Q40: 0 | R40: 0 | S40: 0 | T40: 0 | U40: 0 | V40: 0 | W40: 0 | X40: 0 | Y40: 0 | Z40: 0 | AA40: 0 | AB40: 0 | AC40: 0 | AD40: 0
A41: Barley | B41: . | C41: 0 | D41: 0 | E41: 0 | F41: 0 | G41: 0 | H41: 0 | I41: 0 | J41: 0 | K41: 0 | L41: 0 | M41: 0 | N41: 0 | O41: 0 | P41: 0 | Q41: 0 | R41: 0 | S41: 0 | T41: 0 | U41: 0 | V41: 0 | W41: 0 | X41: 0 | Y41: 0 | Z41: 0 | AA41: 0 | AB41: 0 | AC41: 0 | AD41: 0
A42: Barley | B42: customary payment to 1 sower, 1 bushels. | C42: 0 | D42: 0 | E42: 0 | F42: 0 | G42: 0 | H42: 0 | I42: 0 | J42: 0 | K42: 0 | L42: 0 | M42: 0 | N42: 0 | O42: 0 | P42: 0 | Q42: 0 | R42: 0 | S42: 0 | T42: 0 | U42: 0 | V42: 0 | W42: 0 | X42: 0 | Y42: 1 | Z42: 0.125 | AA42: 0.125 | AB42: 0 | AC42: 0 | AD42: 1
A43: Barley | B43: customary payment to 1 smith, 3 bushels. | C43: 0 | D43: 0 | E43: 0 | F43: 0 | G43: 0 | H43: 0 | I43: 0 | J43: 0 | K43: 0 | L43: 0 | M43: 0 | N43: 0 | O43: 0 | P43: 0 | Q43: 0 | R43: 0 | S43: 0 | T43: 0 | U43: 0 | V43: 0 | W43: 0 | X43: 0 | Y43: 3 | Z43: 0.375 | AA43: 0.375 | AB43: 0 | AC43: 0 | AD43: 3
A44: Barley | B44: customary payment to 1 shepherd of ewes, 3 bushels Delivered to 1 hayward from Michaelmas until Lammas and from the Decollation of St John the Baptist until Michaelmas, because for 4 weeks at harvest-time he was at table, 6 quarters, taking a quarter every 8 weeks. | C44: 0 | D44: 0 | E44: 0 | F44: 0 | G44: 0 | H44: 0 | I44: 0 | J44: 0 | K44: 0 | L44: 0 | M44: 0 | N44: 0 | O44: 0 | P44: 0 | Q44: 0 | R44: 0 | S44: 0 | T44: 0 | U44: 0 | V44: 0 | W44: 0 | X44: 6 | Y44: 3 | Z44: 6.375 | AA44: 0.375 | AB44: 6 | AC44: 0 | AD44: 3 | AE44: 6 | AF44: 0
A45: Barley | B45: Delivered to 2 ploughmen who were sometimes carters and 1 drover for the year, 17 quarters 2 bushels, taking a quarter every 9 weeks. | C45: 0 | D45: 0 | E45: 0 | F45: 0 | G45: 0 | H45: 0 | I45: 0 | J45: 0 | K45: 0 | L45: 0 | M45: 0 | N45: 0 | O45: 0 | P45: 0 | Q45: 0 | R45: 0 | S45: 0 | T45: 0 | U45: 0 | V45: 0 | W45: 0 | X45: 17 | Y45: 2 | Z45: 17.25 | AA45: 17.25 | AB45: 0 | AC45: 17 | AD45: 2
A46: Barley | B46: Delivered to 1 dairymaid from Michaelmas until Lammas and from the Decollation of St John the Baptist until the following Michaelmas, 4 quarters, because she was at table for 4 weeks at harvest-time, taking a quarter every 12 weeks. | C46: 0 | D46: 0 | E46: 0 | F46: 0 | G46: 0 | H46: 0 | I46: 0 | J46: 0 | K46: 0 | L46: 0 | M46: 0 | N46: 0 | O46: 0 | P46: 0 | Q46: 0 | R46: 0 | S46: 0 | T46: 0 | U46: 0 | V46: 0 | W46: 0 | X46: 4 | Y46: 0 | Z46: 4 | AA46: 4 | AB46: 0 | AC46: 4 | AD46: 0
A47: Barley | B47: Delivered to 1 keeper of lambs from weaning until Lammas, 1 qr. | C47: 0 | D47: 0 | E47: 0 | F47: 0 | G47: 0 | H47: 0 | I47: 0 | J47: 0 | K47: 0 | L47: 0 | M47: 0 | N47: 0 | O47: 0 | P47: 0 | Q47: 0 | R47: 0 | S47: 0 | T47: 0 | U47: 0 | V47: 0 | W47: 0
A48: Barley | B48: Delivered to 1 cowherd for the year, 4 quarters 2 bushels, taking a quarter every 12 weeks. | C48: 0 | D48: 0 | E48: 0 | F48: 0 | G48: 0 | H48: 0 | I48: 0 | J48: 0 | K48: 0 | L48: 0 | M48: 0 | N48: 0 | O48: 0 | P48: 0 | Q48: 0 | R48: 0 | S48: 0 | T48: 0 | U48: 0 | V48: 0 | W48: 0 | X48: 4 | Y48: 2 | Z48: 4.25 | AA48: 4.25 | AB48: 0 | AC48: 4 | AD48: 2
A49: Barley | B49: . | C49: 0 | D49: 0 | E49: 0 | F49: 0 | G49: 0 | H49: 0 | I49: 0 | J49: 0 | K49: 0 | L49: 0 | M49: 0 | N49: 0 | O49: 0 | P49: 0 | Q49: 0 | R49: 0 | S49: 0 | T49: 0 | U49: 0 | V49: 0 | W49: 0 | X49: 0 | Y49: 0 | Z49: 0 | AA49: 0 | AB49: 0 | AC49: 0 | AD49: 0
A50: Barley | B50: . | C50: 0 | D50: 0 | E50: 0 | F50: 0 | G50: 0 | H50: 0 | I50: 0 | J50: 0 | K50: 0 | L50: 0 | M50: 0 | N50: 0 | O50: 0 | P50: 0 | Q50: 0 | R50: 0 | S50: 0 | T50: 0 | U50: 0 | V50: 0 | W50: 0 | X50: 0 | Y50: 0 | Z50: 0 | AA50: 0 | AB50: 0 | AC50: 0 | AD50: 0
A51: Barley | B51: . | C51: 0 | D51: 0 | E51: 0 | F51: 0 | G51: 0 | H51: 0 | I51: 0 | J51: 0 | K51: 0 | L51: 0 | M51: 0 | N51: 0 | O51: 0 | P51: 0 | Q51: 0 | R51: 0 | S51: 0 | T51: 0 | U51: 0 | V51: 0 | W51: 0 | X51: 0 | Y51: 0 | Z51: 0 | AA51: 0 | AB51: 0 | AC51: 0 | AD51: 0
A52: Barley | B52: provision of the reeve and officials of the curia for 4 weeks at harvest-time, 2 quarters. | C52: 0 | D52: 0 | E52: 0 | F52: 0 | G52: 0 | H52: 0 | I52: 0 | J52: 0 | K52: 0 | L52: 0 | M52: 0 | N52: 0 | O52: 0 | P52: 0 | Q52: 0 | R52: 0 | S52: 0 | T52: 0 | U52: 0 | V52: 0 | W52: 0 | X52: 2 | Y52: 0 | Z52: 2 | AA52: 2 | AB52: 0 | AC52: 2 | AD52: 0
A53: Barley | B53: . | C53: 0 | D53: 0 | E53: 0 | F53: 0 | G53: 0 | H53: 0 | I53: 0 | J53: 0 | K53: 0 | L53: 0 | M53: 0 | N53: 0 | O53: 0 | P53: 0 | Q53: 0 | R53: 0 | S53: 0 | T53: 0 | U53: 0 | V53: 0 | W53: 0 | X53: 0 | Y53: 0 | Z53: 0 | AA53: 0 | AB53: 0 | AC53: 0 | AD53: 0
A54: Barley | B54: . | C54: 0 | D54: 0 | E54: 0 | F54: 0 | G54: 0 | H54: 0 | I54: 0 | J54: 0 | K54: 0 | L54: 0 | M54: 0 | N54: 0 | O54: 0 | P54: 0 | Q54: 0 | R54: 0 | S54: 0 | T54: 0 | U54: 0 | V54: 0 | W54: 0 | X54: 0 | Y54: 0 | Z54: 0 | AA54: 0 | AB54: 0 | AC54: 0 | AD54: 0
A55: Barley | B55: . | C55: 0 | D55: 0 | E55: 0 | F55: 0 | G55: 0 | H55: 0 | I55: 0 | J55: 0 | K55: 0 | L55: 0 | M55: 0 | N55: 0 | O55: 0 | P55: 0 | Q55: 0 | R55: 0 | S55: 0 | T55: 0 | U55: 0 | V55: 0 | W55: 0 | X55: 0 | Y55: 0 | Z55: 0 | AA55: 0 | AB55: 0 | AC55: 0 | AD55: 0
A56: Barley | B56: customary provision, that is, in bread at harvest-time on account of the boon-works, 7.5 quarters. | C56: 0 | D56: 0 | E56: 0 | F56: 0 | G56: 0 | H56: 0 | I56: 0 | J56: 0 | K56: 0 | L56: 0 | M56: 0 | N56: 0 | O56: 0 | P56: 0 | Q56: 0 | R56: 0 | S56: 0 | T56: 0 | U56: 0 | V56: 0 | W56: 0 | X56: 7.5 | Y56: 0 | Z56: 7.5 | AA56: 7.5 | AB56: 0 | AC56: 7.5 | AD56: 0
A57: Barley | B57: Sold, 34 quarters 1 bushels | C57: 0 | D57: 0 | E57: 0 | F57: 0 | G57: 0 | H57: 0 | I57: 0 | J57: 0 | K57: 0 | L57: 0 | M57: 0 | N57: 0 | O57: 0 | P57: 0 | Q57: 34 | R57: 1 | S57: 34.125 | T57: 0 | U57: 0 | V57: 0 | W57: 0 | X57: 34 | Y57: 1 | Z57: 34.125 | AA57: 34.125 | AB57: 0 | AC57: 34 | AD57: 1
A58: Barley | B58: Total | C58: 0 | D58: 0 | E58: 0 | F58: 0 | G58: 0 | H58: 0 | I58: 0 | J58: 0 | K58: 0 | L58: 0 | M58: 0 | N58: 0 | O58: 0 | P58: 0 | Q58: 0 | R58: 0 | S58: 0 | T58: 0 | U58: 0 | V58: 0 | W58: 0
A59: Oats | B59: {yield: three-fold less 8 quarters 6 bushels} | C59: 0 | D59: 0 | E59: 0 | F59: 0 | G59: 0 | H59: 0 | I59: 0 | J59: 0 | K59: 0 | L59: 0 | M59: 0 | N59: 0 | O59: 0 | P59: 0 | Q59: 0 | R59: 0 | S59: 0 | T59: 0 | U59: 0 | V59: 0 | W59: 0 | X59: 8 | Y59: 6 | Z59: 8.75 | AA59: 8.75 | AB59: 0 | AC59: 8 | AD59: 6
A60: Oats | B60: The same render account for 93.5 quarters 2 bushels from the whole issue of oats by struck measure. | C60: 0 | D60: 0 | E60: 0 | F60: 0 | G60: 0 | H60: 0 | I60: 0 | J60: 0 | K60: 0 | L60: 0 | M60: 0 | N60: 0 | O60: 0 | P60: 0 | Q60: 0 | R60: 0 | S60: 0 | T60: 93.5 | U60: 2 | V60: 93.75 | W60: 0 | X60: 93.5 | Y60: 2 | Z60: 93.75 | AA60: 93.75 | AB60: 0 | AC60: 93.5 | AD60: 2
A61: Oats | B61: 14.5 quarters by estimation in sheaves given to oxen. | C61: 0 | D61: 0 | E61: 0 | F61: 0 | G61: 0 | H61: 0 | I61: 0 | J61: 0 | K61: 0 | L61: 0 | M61: 0 | N61: 0 | O61: 0 | P61: 0 | Q61: 0 | R61: 0 | S61: 0 | T61: 0 | U61: 0 | V61: 0 | W61: 0 | X61: 14.5 | Y61: 0 | Z61: 14.5 | AA61: 14.5 | AB61: 0 | AC61: 14.5 | AD61: 0
A62: Oats | B62: Total, 108 quarters 2 bushels Sown over 225 acres which lie in Midelcrofte, Suthfeld', and Watcumb', 42 quarters 1 bushels. | C62: 0 | D62: 0 | E62: 150 | F62: 3 | G62: 150.375 | H62: 0 | I62: 0 | J62: 0 | K62: 0 | L62: 0 | M62: 0 | N62: 0 | O62: 0 | P62: 0 | Q62: 0 | R62: 0 | S62: 0 | T62: 0 | U62: 0 | V62: 0 | W62: 0 | X62: 42 | Y62: 1 | Z62: 42.125 | AA62: 108.25 | AB62: -66.125 | AC62: 108 | AD62: 2 | AE62: 42 | AF62: 1
A63: Oats | B63: that is, 1.5 bushels an acre, less' bushels in all. | C63: 0 | D63: 0 | E63: 0 | F63: 0 | G63: 0 | H63: 0 | I63: 0 | J63: 0 | K63: 0 | L63: 0 | M63: 0 | N63: 0 | O63: 0 | P63: 0 | Q63: 0 | R63: 0 | S63: 0 | T63: 0 | U63: 0 | V63: 0 | W63: 0 | X63: 0 | Y63: 1.5 | Z63: 0.1875 | AA63: 0.1875 | AB63: 0 | AC63: 0 | AD63: 1.5
A64: Oats | B64: . | C64: 0 | D64: 0 | E64: 0 | F64: 0 | G64: 0 | H64: 0 | I64: 0 | J64: 0 | K64: 0 | L64: 0 | M64: 0 | N64: 0 | O64: 0 | P64: 0 | Q64: 0 | R64: 0 | S64: 0 | T64: 0 | U64: 0 | V64: 0 | W64: 0 | X64: 0 | Y64: 0 | Z64: 0 | AA64: 0 | AB64: 0 | AC64: 0 | AD64: 0
A65: Oats | B65: . | C65: 0 | D65: 0 | E65: 0 | F65: 0 | G65: 0 | H65: 0 | I65: 0 | J65: 0 | K65: 0 | L65: 0 | M65: 0 | N65: 0 | O65: 0 | P65: 0 | Q65: 0 | R65: 0 | S65: 0 | T65: 0 | U65: 0 | V65: 0 | W65: 0 | X65: 0 | Y65: 0 | Z65: 0 | AA65: 0 | AB65: 0 | AC65: 0 | AD65: 0
A66: Oats | B66: customary payment to 1 hayward, 1 bushels. | C66: 0 | D66: 0 | E66: 0 | F66: 0 | G66: 0 | H66: 0 | I66: 0 | J66: 0 | K66: 0 | L66: 0 | M66: 0 | N66: 0 | O66: 0 | P66: 0 | Q66: 0 | R66: 0 | S66: 0 | T66: 0 | U66: 0 | V66: 0 | W66: 0 | X66: 0 | Y66: 1 | Z66: 0.125 | AA66: 0.125 | AB66: 0 | AC66: 0 | AD66: 1
A67: Oats | B67: fodder of 2 cart-horses and 3 plough-horses hauling the ploughs, 15.5 quarters 3 bushels. | C67: 0 | D67: 0 | E67: 0 | F67: 0 | G67: 0 | H67: 0 | I67: 0 | J67: 0 | K67: 0 | L67: 0 | M67: 0 | N67: 15.5 | O67: 3 | P67: 15.875 | Q67: 0 | R67: 0 | S67: 0 | T67: 0 | U67: 0 | V67: 0 | W67: 0 | X67: 15.5 | Y67: 3 | Z67: 15.875 | AA67: 15.875 | AB67: 0 | AC67: 15.5 | AD67: 3
A68: Oats | B68: supporting oxen by estimation in sheaves, 14.5 quarters. | C68: 0 | D68: 0 | E68: 0 | F68: 0 | G68: 0 | H68: 0 | I68: 0 | J68: 0 | K68: 0 | L68: 0 | M68: 0 | N68: 0 | O68: 0 | P68: 0 | Q68: 0 | R68: 0 | S68: 0 | T68: 0 | U68: 0 | V68: 0 | W68: 0 | X68: 14.5 | Y68: 0 | Z68: 14.5 | AA68: 14.5 | AB68: 0 | AC68: 14.5 | AD68: 0
A69: Oats | B69: . | C69: 0 | D69: 0 | E69: 0 | F69: 0 | G69: 0 | H69: 0 | I69: 0 | J69: 0 | K69: 0 | L69: 0 | M69: 0 | N69: 0 | O69: 0 | P69: 0 | Q69: 0 | R69: 0 | S69: 0 | T69: 0 | U69: 0 | V69: 0 | W69: 0 | X69: 0 | Y69: 0 | Z69: 0 | AA69: 0 | AB69: 0 | AC69: 0 | AD69: 0
A70: Oats | B70: . | C70: 0 | D70: 0 | E70: 0 | F70: 0 | G70: 0 | H70: 0 | I70: 0 | J70: 0 | K70: 0 | L70: 0 | M70: 0 | N70: 0 | O70: 0 | P70: 0 | Q70: 0 | R70: 0 | S70: 0 | T70: 0 | U70: 0 | V70: 0 | W70: 0 | X70: 0 | Y70: 0 | Z70: 0 | AA70: 0 | AB70: 0 | AC70: 0 | AD70: 0
A71: Oats | B71: fodder of the steward's horses, 2 bushels. | C71: 0 | D71: 0 | E71: 0 | F71: 0 | G71: 0 | H71: 0 | I71: 0 | J71: 0 | K71: 0 | L71: 0 | M71: 0 | N71: 0 | O71: 0 | P71: 0 | Q71: 0 | R71: 0 | S71: 0 | T71: 0 | U71: 0 | V71: 0 | W71: 0 | X71: 0 | Y71: 2 | Z71: 0.25 | AA71: 0.25 | AB71: 0 | AC71: 0 | AD71: 2
A72: Oats | B72: fodder of the horse of the bailiff and clerk for his visits, 5 bushels Sold, 34.5 quarters 2 bushels | C72: 0 | D72: 0 | E72: 0 | F72: 0 | G72: 0 | H72: 0 | I72: 0 | J72: 0 | K72: 0 | L72: 0 | M72: 0 | N72: 34.5 | O72: 2 | P72: 34.75 | Q72: 34.5 | R72: 2 | S72: 34.75 | T72: 0 | U72: 0 | V72: 0 | W72: 0 | X72: 34.5 | Y72: 2 | Z72: 34.75 | AA72: 0.625 | AB72: 34.125 | AC72: 0 | AD72: 5 | AE72: 34.5 | AF72: 2
A73: Oats | B73: Total | C73: 0 | D73: 0 | E73: 0 | F73: 0 | G73: 0 | H73: 0 | I73: 0 | J73: 0 | K73: 0 | L73: 0 | M73: 0 | N73: 0 | O73: 0 | P73: 0 | Q73: 0 | R73: 0 | S73: 0 | T73: 0 | U73: 0 | V73: 0 | W73: 0
A74: Peas | B74: {yield: four-fold less 1 bushels} | C74: 0 | D74: 0 | E74: 0 | F74: 0 | G74: 0 | H74: 0 | I74: 0 | J74: 0 | K74: 0 | L74: 0 | M74: 0 | N74: 0 | O74: 0 | P74: 0 | Q74: 0 | R74: 0 | S74: 0 | T74: 0 | U74: 0 | V74: 0 | W74: 0 | X74: 0 | Y74: 1 | Z74: 0.125 | AA74: 0.125 | AB74: 0 | AC74: 0 | AD74: 1
A75: Peas | B75: The same render account for 11.5 quarters 3 bushels from the whole issue of peas by struck measure. | C75: 0 | D75: 0 | E75: 0 | F75: 0 | G75: 0 | H75: 0 | I75: 0 | J75: 0 | K75: 0 | L75: 0 | M75: 0 | N75: 0 | O75: 0 | P75: 0 | Q75: 0 | R75: 0 | S75: 0 | T75: 11.5 | U75: 3 | V75: 11.875 | W75: 0 | X75: 11.5 | Y75: 3 | Z75: 11.875 | AA75: 11.875 | AB75: 0 | AC75: 11.5 | AD75: 3
A76: Peas | B76: Sown over 18 acres which lie in Hynhok', 2 quarters 2 bushels. | C76: 0 | D76: 0 | E76: 2 | F76: 2 | G76: 2.25 | H76: 0 | I76: 0 | J76: 0 | K76: 0 | L76: 0 | M76: 0 | N76: 0 | O76: 0 | P76: 0 | Q76: 0 | R76: 0 | S76: 0 | T76: 0 | U76: 0 | V76: 0 | W76: 0 | X76: 2 | Y76: 2 | Z76: 2.25 | AA76: 2.25 | AB76: 0 | AC76: 2 | AD76: 2
A77: Peas | B77: that is, 1 bushels an acre. | C77: 0 | D77: 0 | E77: 0 | F77: 0 | G77: 0 | H77: 0 | I77: 0 | J77: 0 | K77: 0 | L77: 0 | M77: 0 | N77: 0 | O77: 0 | P77: 0 | Q77: 0 | R77: 0 | S77: 0 | T77: 0 | U77: 0 | V77: 0 | W77: 0 | X77: 0 | Y77: 1 | Z77: 0.125 | AA77: 0.125 | AB77: 0 | AC77: 0 | AD77: 1
A78: Peas | B78: Sold, 9.5 quarters 1 bushels | C78: 0 | D78: 0 | E78: 0 | F78: 0 | G78: 0 | H78: 0 | I78: 0 | J78: 0 | K78: 0 | L78: 0 | M78: 0 | N78: 0 | O78: 0 | P78: 0 | Q78: 9.5 | R78: 1 | S78: 9.625 | T78: 0 | U78: 0 | V78: 0 | W78: 0 | X78: 9.5 | Y78: 1 | Z78: 9.625 | AA78: 9.625 | AB78: 0 | AC78: 9.5 | AD78: 1
A79: Peas | B79: Total | C79: 0 | D79: 0 | E79: 0 | F79: 0 | G79: 0 | H79: 0 | I79: 0 | J79: 0 | K79: 0 | L79: 0 | M79: 0 | N79: 0 | O79: 0 | P79: 0 | Q79: 0 | R79: 0 | S79: 0 | T79: 0 | U79: 0 | V79: 0 | W79: 0
A80: Vetches | B80: {yield: three-and-a-half-fold plus 2.5 bushels} | C80: 0 | D80: 0 | E80: 0 | F80: 0 | G80: 0 | H80: 0 | I80: 0 | J80: 0 | K80: 0 | L80: 0 | M80: 0 | N80: 0 | O80: 0 | P80: 0 | Q80: 0 | R80: 0 | S80: 0 | T80: 0 | U80: 0 | V80: 0 | W80: 0 | X80: 0 | Y80: 2.5 | Z80: 0.3125 | AA80: 0.3125 | AB80: 0 | AC80: 0 | AD80: 2.5
A81: Vetches | B81: The same render account for 9.5 quarters of vetches remaining from the previous year in the granary. | C81: 0 | D81: 0 | E81: 0 | F81: 0 | G81: 0 | H81: 0 | I81: 0 | J81: 0 | K81: 0 | L81: 0 | M81: 0 | N81: 0 | O81: 0 | P81: 0 | Q81: 0 | R81: 0 | S81: 0 | T81: 9.5 | U81: 0 | V81: 9.5 | W81: 0 | X81: 9.5 | Y81: 0 | Z81: 9.5 | AA81: 9.5 | AB81: 0 | AC81: 9.5 | AD81: 0
A82: Vetches | B82: 10 quarters 3 bushels from the whole issue of vetches this year. | C82: 0 | D82: 0 | E82: 0 | F82: 0 | G82: 0 | H82: 0 | I82: 0 | J82: 0 | K82: 0 | L82: 0 | M82: 0 | N82: 0 | O82: 0 | P82: 0 | Q82: 0 | R82: 0 | S82: 0 | T82: 10 | U82: 3 | V82: 10.375 | W82: 0 | X82: 10 | Y82: 3 | Z82: 10.375 | AA82: 10.375 | AB82: 0 | AC82: 10 | AD82: 3
A83: Vetches | B83: Total, 19.5 quarters 3 bushels | C83: 0 | D83: 0 | E83: 0 | F83: 0 | G83: 0 | H83: 0 | I83: 0 | J83: 0 | K83: 0 | L83: 0 | M83: 0 | N83: 0 | O83: 0 | P83: 0 | Q83: 0 | R83: 0 | S83: 0 | T83: 0 | U83: 0 | V83: 0 | W83: 0 | X83: 19.5 | Y83: 3 | Z83: 19.875 | AA83: 19.875 | AB83: 0 | AC83: 19.5 | AD83: 3
A84: Vetches | B84: Sown over 18 acres as they lie in Yforlong' and Northden', 2 quarters 1 bushels. | C84: 0 | D84: 0 | E84: 2 | F84: 1 | G84: 2.125 | H84: 0 | I84: 0 | J84: 0 | K84: 0 | L84: 0 | M84: 0 | N84: 0 | O84: 0 | P84: 0 | Q84: 0 | R84: 0 | S84: 0 | T84: 0 | U84: 0 | V84: 0 | W84: 0 | X84: 2 | Y84: 1 | Z84: 2.125 | AA84: 2.125 | AB84: 0 | AC84: 2 | AD84: 1
A85: Vetches | B85: that is, 1 bushels an acre, less 1 bushels in all. | C85: 0 | D85: 0 | E85: 0 | F85: 0 | G85: 0 | H85: 0 | I85: 0 | J85: 0 | K85: 0 | L85: 0 | M85: 0 | N85: 0 | O85: 0 | P85: 0 | Q85: 0 | R85: 0 | S85: 0 | T85: 0 | U85: 0 | V85: 0 | W85: 0 | X85: 0 | Y85: 1 | Z85: 0.125 | AA85: 0.125 | AB85: 0 | AC85: 0 | AD85: 1 | AE85: 0 | AF85: 1
A86: Vetches | B86: Mixed above with barley, 3 quarters 3 bushels Sold, 14 quarters 3 bushels | C86: 0 | D86: 0 | E86: 0 | F86: 0 | G86: 0 | H86: 0 | I86: 0 | J86: 0 | K86: 0 | L86: 0 | M86: 0 | N86: 0 | O86: 0 | P86: 0 | Q86: 17 | R86: 6 | S86: 17.75 | T86: 0 | U86: 0 | V86: 0 | W86: 0 | X86: 14 | Y86: 3 | Z86: 14.375 | AA86: 3.375 | AB86: 11 | AC86: 3 | AD86: 3 | AE86: 14 | AF86: 3
A87: Vetches | B87: Total | C87: 0 | D87: 0 | E87: 0 | F87: 0 | G87: 0 | H87: 0 | I87: 0 | J87: 0 | K87: 0 | L87: 0 | M87: 0 | N87: 0 | O87: 0 | P87: 0 | Q87: 0 | R87: 0 | S87: 0 | T87: 0 | U87: 0 | V87: 0 | W87: 0

Sheet Sale of Corn Prices
A1: Heading | B1: Sentence | C1: Total in Pounds | D1: Pounds | E1: Shillings | F1: Pence | G1: Corn | H1: Total Quarters Except 1 | I1: Total Bushels Except 1 | J1: Total Corn Cross-Check | K1: Total Corn Manorial Account | L1: Corn Quantity Error | M1: Quarters 0 | N1: Bushels 0 | O1: shilling a quarter 1 | P1: pence a quarter 1 | Q1: Quarters 1 | R1: Bushels 1 | S1: shilling a quarter 2 | T1: pence a quarter 2 | U1: Quarters 2 | V1: Bushels 2 | W1: shilling a quarter 3 | X1: pence a quarter 3 | Y1: Quarters 3 | Z1: Bushels 3 | AA1: shilling a quarter 4 | AB1: pence a quarter 4 | AC1: £ a quarter 1 | AD1: £ a quarter 2 | AE1: £ a quarter 3 | AF1: £ a quarter 4 | AG1: Quarters Sold | AH1: Weighted Average Price per Quarter | AI1: Non-Weighted Average Price per Quarter | AJ1: Corn lowercase
A2: Sale of corn | B2: The same render account for £12 1 shilling 3.5pence from 42 quarters 2.5 bushels of wheat sold, at 4 shilling 8d a quarters for 5.5 quarters, 5 shilling a quarters for 17.5 quarters 3 bushels, and 6 shilling 8pence a quarters for 18.5 quarters. | C2: 12.06 | D2: 12 | E2: 1 | F2: 3.5 | G2: wheat | H2: 41.5 | I2: 3 | J2: 41.875 | K2: 42.3125 | L2: -0.4375 | M2: 42 | N2: 2.5 | O2: 5 | P2: 0 | Q2: 5.5 | R2: 0 | S2: 6 | T2: 8 | U2: 17.5 | V2: 3 | Y2: 18.5 | Z2: 0 | AC2: 0.25 | AD2: 0.33333333 | AG2: 42.3125 | AH2: 0.31372549 | AI2: 0.29166667 | AJ2: wheat
A3: Sale of corn | B3: £1 1 shilling 3pence from 6 quarters 3 bushels of curall sold, at 3 shilling 4pence a quarters. | C3: 1.06 | D3: 1 | E3: 1 | F3: 3 | G3: curall | H3: 6 | I3: 3 | J3: 6.375 | K3: 6.375 | L3: 0 | M3: 6 | N3: 3 | O3: 3 | P3: 4 | AC3: 0.16666667 | AG3: 6.375 | AH3: 0.16666667 | AI3: 0.16666667 | AJ3: curall
A4: Sale of corn | B4: 1 shilling 4pence from 4 bushels of maslin sold. | C4: 0.07 | D4: 0 | E4: 1 | F4: 4 | G4: maslin | H4: 0 | I4: 4 | J4: 0.5 | K4: 0.5 | L4: 0 | M4: 0 | N4: 4 | AC4: 0.14 | AG4: 0.5 | AH4: 0.14 | AI4: 0.14 | AJ4: maslin
A5: Sale of corn | B5: £1 16 shilling 8pence from 11 quarters of bere sold, at 3 shilling 4pence a quarters. | C5: 1.83 | D5: 1 | E5: 16 | F5: 8 | H5: 11 | I5: 0 | J5: 11 | K5: 11 | L5: 0 | M5: 11 | N5: 0 | O5: 3 | P5: 4 | AC5: 0.16666667 | AG5: 11 | AH5: 0.16666667 | AI5: 0.16666667
A6: Sale of corn | B6: £6 9 shilling 9pence from 34 quarters 1 bushels of barley sold, at 3 shilling 4pence a quarters for 10 quarters 1 bushels, and 4 shilling a quarters for 24 quarters. | C6: 6.49 | D6: 6 | E6: 9 | F6: 9 | G6: barley | H6: 34 | I6: 1 | J6: 34.125 | K6: 34.125 | L6: 0 | M6: 34 | N6: 1 | O6: 3 | P6: 4 | Q6: 10 | R6: 1 | S6: 4 | T6: 0 | U6: 24 | V6: 0 | AC6: 0.16666667 | AD6: 0.2 | AG6: 34.125 | AH6: 0.19010989 | AI6: 0.18333333 | AJ6: barley
A7: Sale of corn | B7: £4 3 shilling 2pence from 34.5 quarters 2 bushels of oats sold, at 2 shilling a quarters for 14 quarters 2 bushels, and 2 shilling 8pence a quarters for 20.5. | C7: 4.16 | D7: 4 | E7: 3 | F7: 2 | G7: oats | H7: 14 | I7: 2 | J7: 14.25 | K7: 34.75 | L7: -20.5 | M7: 34.5 | N7: 2 | O7: 2 | P7: 0 | Q7: 14 | R7: 2 | S7: 2 | T7: 8 | AC7: 0.1 | AD7: 0.13333333 | AG7: 34.75 | AI7: 0.11666667 | AJ7: oats
A8: Sale of corn | B8: £1 9pence from 9.5quarters 1 bushels of peas sold, at 2 shilling a quarters for 7 quarters 3 bushels, and 2 shilling 8pence a quarters for 2 quarters 2 bushels. | C8: 1.04 | D8: 1 | E8: 0 | F8: 9 | G8: peas | H8: 9 | I8: 5 | J8: 9.625 | K8: 9.625 | L8: 0 | M8: 9.5 | N8: 1 | O8: 2 | P8: 0 | Q8: 7 | R8: 3 | S8: 2 | T8: 8 | U8: 2 | V8: 2 | AC8: 0.1 | AD8: 0.13333333 | AG8: 9.625 | AH8: 0.10779221 | AI8: 0.11666667 | AJ8: peas
A9: Sale of corn | B9: £1 5 shilling 6.5 from 14 quarters 3 bushels of vetches sold, at 1 shilling 4pence a quarters for 8 quarters for 6 quarters 3 bushels Total, £27 19 shilling 9pence | C9: 1.25 | D9: 1 | E9: 5 | F9: 0 | G9: vetches | H9: 14 | I9: 3 | J9: 14.375 | K9: 14.375 | L9: 0 | M9: 14 | N9: 3 | O9: 1 | P9: 4 | Q9: 8 | R9: 0 | U9: 6 | V9: 3 | AC9: 0.066666667 | AG9: 14.375 | AH9: 0.066666667 | AI9: 0.066666667 | AJ9: vetches
