Workbook

Sheet Highclere Overview - Completed
A1: HIGHCLERE OVERVIEW - COMPLETED | B1: Total in £ | C1: Error | D1: Note
A2: CASH ACCOUNT
A3: RECEIPTS
A4: Arrears total | B4: 1.4
A5: Rents of assize total | B5: 22.40625
A6: Quittances total | B6: 1.0416667
A7: Defaults of rent total | B7: 2.0375
A8: Defaults of rent through the pestilence total
A9: Cotlands defaults total
A10: Cotlands total
A11: Total of quittances and defaults of rent total
A12: Total of rents remaining clear total
A13: Farms total
A14: Annual recognizances total | B14: 0.05
A15: Issues of the Manor total | B15: 26.477083
A16: Issues of the tenements in the lord's hands total
A17: Sale of labour services total
A18: Sale of corn total | B18: 10.634375
A19: Entry and marriage fines total | B19: 2.3416667
A20: Pleas & perquisites total | B20: 1.0375
A21: Forfeited chattels total
A22: Farm of the demesne land total
A23: Total of all receipts (calculated here) | B23: =SUM(B5:B22)
A24: Total of all receipts (calculated here) incl arrears | B24: =SUM(B4:B22)
A25: Total recorded in the accounts excl. arrears | C25: =B23-B25
A26: Total recorded in the accounts incl. arrears | B26: =B25+B4
A29: EXPENSES
A30: Cost of ploughs total | B30: 9.8291667
A31: Purchase of corn total | B31: 0
A32: Cost of carts and wagons total | B32: 0.53958333
A33: Cost of dairy total | B33: 0.33333333
A34: Purchase of stock total | B34: 0
A35: Sheepcote total | B35: 4.275
A36: Cost of buildings total | B36: 6.3854167
A37: Threshing total | B37: 0.415625
A38: Barley expenses
A39: Expenses of the harvest total | B39: 0.67708333
A40: Necessary expenses
A41: Wages of the bailiff
A42: Steward's expenses total
A43: Annual fees
A44: Total of all expenses per account | B44: 27.954167
A45: Total of all expenses (calculated here) | B45: 28.055208
A46: Total fixed investment | B46: 6.0739583
A47: Total Demesne fixed investment | B47: 3.4666667
A49: Owed by the reeve | B49: =B23-B45
A50: From accounts | B50: 27.954167
A52: Allowances
A53: Cash deliveries
A54: Sum of the above | B54: =SUM(B52:B53)
A55: Total of all allowances and cash deliveries in accounts
A57: Net amount owed | B57: =B50-B54
A58: Net amount owed in accounts
A60: GRANGE ACCOUNT | B60: Total Production | D60: Value of total gross production in £ | E60: Value of total net production in £
A61: Grange | B61: qrs | C61: bus
A62: Wheat | B62: 28
A63: Rye
A64: Dredge
A65: Curall
A66: Barley | B66: 15
A67: Oats | B67: 43
A68: Beans
A69: Peas
A70: Vetches | E70: 0
A71: Total value of gross production (sum of the above)
A72: Total value of net production
A73: Value of sales
A75: MILL ACCOUNT | B75: Total Production | D75: Total in £
A76: Issues of the mill | B76: qrs | C76: bus
A77: Wheat
A78: Oatmeal
A79: 1st grade malt
A80: 2nd grade malt
A81: Maslin
A82: Total value of production (sum of the above)
A83: Value of sales
A85: STOCK ACCOUNT
A86: Livestock | B86: Begin stock | C86: End stock | D86: Stockbuilding | F86: Value of stock in £ | G86: Value of stockbuilding
A87: Cart-horses | D87: =C87-B87 | F87: ='Stock'!K5*'Stock'!O5 | G87: =D87*'Stock'!O5
A88: Mares | D88: =C88-B88 | F88: ='Stock'!K5*'Stock'!O5 | G88: =D88*'Stock'!O5
A89: Plough horses | D89: =C89-B89 | F89: ='Stock'!K6*'Stock'!O6 | G89: =D89*'Stock'!O6
A90: Colts (2 years) | D90: =C90-B90 | F90: ='Stock'!K8*'Stock'!O8 | G90: =D90*'Stock'!O8
A91: Colts (2 years) | D91: =C91-B91 | F91: ='Stock'!K8*'Stock'!O8 | G91: =D91*'Stock'!O8
A92: Colts (1 year) | D92: =C92-B92 | F92: ='Stock'!K9*'Stock'!O9 | G92: =D92*'Stock'!O9
A93: Foals | D93: =C93-B93 | F93: ='Stock'!K10*'Stock'!O10 | G93: =D93*'Stock'!O10
A94: Oxen | B94: 21 | C94: 18 | D94: -3 | F94: ='Stock'!K11*'Stock'!O11 | G94: =D94*'Stock'!O11
A95: Bulls | B95: 1 | C95: 2 | D95: 1 | F95: ='Stock'!K12*'Stock'!O12 | G95: =D95*'Stock'!O12
A96: Cows | B96: 50 | C96: 43 | D96: -7 | F96: ='Stock'!K13*'Stock'!O13 | G96: =D96*'Stock'!O13
A97: Steers | B97: 4 | C97: 0 | D97: -4 | F97: ='Stock'!K14*'Stock'!O14 | G97: =D97*'Stock'!O14
A98: Bullocks | B98: 15 | C98: 11 | D98: -4 | F98: ='Stock'!K15*'Stock'!O15 | G98: =D98*'Stock'!O15
A99: Yearlings | B99: 18 | C99: 16 | D99: -2 | F99: ='Stock'!K16*'Stock'!O16 | G99: =D99*'Stock'!O16
A100: Calves | C100: 14 | D100: =C100-B100 | F100: ='Stock'!K17*'Stock'!O17 | G100: =D100*'Stock'!O17
A101: Wethers | D101: =C101-B101 | F101: ='Stock'!K18*'Stock'!O18 | G101: =D101*'Stock'!O18
A102: Rams | B102: 15 | C102: 10 | D102: -5 | F102: ='Stock'!K19*'Stock'!O19 | G102: =D102*'Stock'!O19
A103: Ewes | B103: 383 | C103: 449 | D103: 66 | F103: ='Stock'!K20*'Stock'!O20 | G103: =D103*'Stock'!O20
A104: Hoggs | D104: =C104-B104 | F104: ='Stock'!K21*'Stock'!O21 | G104: =D104*'Stock'!O21
A105: Lambs | C105: 0 | D105: =C105-B105 | F105: ='Stock'!K22*'Stock'!O22 | G105: =D105*'Stock'!O22
A106: Boars | D106: =C106-B106 | F106: ='Stock'!K23*'Stock'!O23 | G106: =D106*'Stock'!O23
A107: Sows | D107: =C107-B107 | F107: ='Stock'!K24*'Stock'!O24 | G107: =D107*'Stock'!O24
A108: Pigs | C108: 0 | D108: =C108-B108 | F108: ='Stock'!K25*'Stock'!O25 | G108: =D108*'Stock'!O25
...

Sheet Issues of the Mills
A1: No mill account for Adderbury

Sheet raw data
A1: Heading | B1: Sentence | C1: Total in Pounds | D1: Pounds | E1: Shillings | F1: Pence | G1: Corn | H1: Total Quarters Except 1 | I1: Total Bushels Except 1 | J1: Total Corn Cross-Check | K1: Total Corn Manorial Account | L1: Corn Quantity Error | M1: Quarters 1 | N1: Bushels 1 | O1: shilling a quarter 1 | P1: pence a quarter 1 | Q1: shilling a quarter 2 | R1: pence a quarter 2 | S1: shilling a quarter 3 | T1: pence a quarter 3 | U1: shilling a quarter 4 | V1: pence a quarter 4 | W1: shilling a bushel 1 | X1: pence a bushel 1 | Y1: shilling a bushel 2 | Z1: pence a bushel 2 | AA1: shilling a bushel 3 | AB1: pence a bushel 3 | AC1: shilling a bushel 4 | AD1: pence a bushel 4
A2: Adderbury | B2: The account2 of William Jakeman, reeve there, for the sixth year of the translation of Henry Beaufort', lord bishop of Winchester, and the eleventh year of the reign of King Henry the Fourth. | C2: 0 | D2: 0 | E2: 0 | F2: 0 | H2: 0 | I2: 0 | J2: 0 | K2: 0 | L2: 0 | M2: 0 | N2: 0
A3: Arrears | B3: None. | C3: 0 | D3: 0 | E3: 0 | F3: 0 | H3: 0 | I3: 0 | J3: 0 | K3: 0 | L3: 0 | M3: 0 | N3: 0
A4: Rents of assize | B4: And for £6 9 shilling 6.25pence for all rents of assize at St Thomas the Apostle (21 December). | C4: 6.48 | D4: 6 | E4: 9 | F4: 6.25 | H4: 0 | I4: 0 | J4: 0 | K4: 0 | L4: 0 | M4: 0 | N4: 0
A5: Rents of assize | B5: £6 9 shilling 8.5pence at Easter (23 March). | C5: 6.49 | D5: 6 | E5: 9 | F5: 8.5 | H5: 0 | I5: 0 | J5: 0 | K5: 0 | L5: 0 | M5: 0 | N5: 0
A6: Rents of assize | B6: £6 9 shilling 6.25pence at the Nativity of St John the Baptist (24 June). | C6: 6.48 | D6: 6 | E6: 9 | F6: 6.25 | H6: 0 | I6: 0 | J6: 0 | K6: 0 | L6: 0 | M6: 0 | N6: 0
A7: Rents of assize | B7: £6 10 shilling 1.5pence at Michaelmas (29 September). | C7: 6.51 | D7: 6 | E7: 10 | F7: 1.5 | H7: 0 | I7: 0 | J7: 0 | K7: 0 | L7: 0 | M7: 0 | N7: 0
A8: Rents of assize | B8: Total, £25 18 shilling 10.5pence. | C8: 25.94 | D8: 25 | E8: 18 | F8: 10.5 | H8: 0 | I8: 0 | J8: 0 | K8: 0 | L8: 0 | M8: 0 | N8: 0
A9: Quittances of rent | B9: In quittance of rent of 1 reeve for the year 5 shilling. | C9: 0.25 | D9: 0 | E9: 5 | F9: 0 | H9: 0 | I9: 0 | J9: 0 | K9: 0 | L9: 0 | M9: 0 | N9: 0
A10: Quittances of rent | B10: nothing this year of the 4 shilling for 1 smith forging the ironwork of 2 ploughs for the year. | C10: 0.2 | D10: 0 | E10: 4 | F10: 0 | H10: 0 | I10: 0 | J10: 0 | K10: 0 | L10: 0 | M10: 0 | N10: 0
A11: Quittances of rent | B11: nothing this year of the 4 shilling for 1 shepherd keeping the lord's wethers for the year. | C11: 0.2 | D11: 0 | E11: 4 | F11: 0 | H11: 0 | I11: 0 | J11: 0 | K11: 0 | L11: 0 | M11: 0 | N11: 0
A12: Quittances of rent | B12: nothing this year of the 4 shilling for 1 swineherd for the year. | C12: 0.2 | D12: 0 | E12: 4 | F12: 0 | H12: 0 | I12: 0 | J12: 0 | K12: 0 | L12: 0 | M12: 0 | N12: 0
A13: Quittances of rent | B13: nothing this year of the 4 shilling for 1 cowherd for the year. | C13: 0.2 | D13: 0 | E13: 4 | F13: 0 | H13: 0 | I13: 0 | J13: 0 | K13: 0 | L13: 0 | M13: 0 | N13: 0
... A149: Cost of buildings | B149: board-nails and clout-nails bought for the same 1 shilling 4pence. | C149: 0.07 | D149: 0 | E149: 1 | F149: 4 | H149: 0 | I149: 0 | J149: 0 | K149: 0 | L149: 0 | M149: 0 | N149: 0
A150: Cost of buildings | B150: 4 quarters 4 bushels of limestone bought at Walton' 5 shilling 3pence, at 1 shilling 2pence a quarters. | C150: 0.26 | D150: 0 | E150: 5 | F150: 3 | H150: 4 | I150: 4 | J150: 4.5 | K150: 4.5 | L150: 0 | M150: 4 | N150: 4 | O150: 1 | P150: 2
A151: Cost of buildings | B151: carrying the same 4pence. | C151: 0.02 | D151: 0 | E151: 0 | F151: 4 | H151: 0 | I151: 0 | J151: 0 | K151: 0 | L151: 0 | M151: 0 | N151: 0
A152: Cost of buildings | B152: 8 quarters of limestone bought at Witney 10 shilling 4pence, at 1 shilling 31 pence a quarters. | C152: 0.52 | D152: 0 | E152: 10 | F152: 4 | H152: 8 | I152: 0 | J152: 8 | K152: 8 | L152: 0 | M152: 8 | N152: 0 | O152: 1 | P152: 31
A153: Cost of buildings | B153: carrying the same from Witney to Adderbury 3 shilling 8pence. | C153: 0.18 | D153: 0 | E153: 3 | F153: 8 | H153: 0 | I153: 0 | J153: 0 | K153: 0 | L153: 0 | M153: 0 | N153: 0
A154: Cost of buildings | B154: 1,500 stone slates bought 6 shilling, at 4 shilling a 1,000.. | C154: 0.3 | D154: 0 | E154: 6 | F154: 0 | H154: 0 | I154: 0 | J154: 0 | K154: 0 | L154: 0 | M154: 0 | N154: 0
A155: Cost of buildings | B155: 500 eaves-stones bought 2 shilling 6pence, at 6pence a 100.. | C155: 0.12 | D155: 0 | E155: 2 | F155: 6 | H155: 0 | I155: 0 | J155: 0 | K155: 0 | L155: 0 | M155: 0 | N155: 0
A156: Cost of buildings | B156: 6,000 pins bought 2 shilling, at 4pence a 1,000.. | C156: 0.12 | D156: 0 | E156: 2 | F156: 4 | H156: 0 | I156: 0 | J156: 0 | K156: 0 | L156: 0 | M156: 0 | N156: 0
A157: Cost of buildings | B157: 50 ridge-tiles bought 6 shilling 3pence, at 1.5pence each. | C157: 0.31 | D157: 0 | E157: 6 | F157: 3 | H157: 0 | I157: 0 | J157: 0 | K157: 0 | L157: 0 | M157: 0 | N157: 0
A158: Cost of buildings | B158: sand bought and dug and quarried at Tadmarton 10pence. | C158: 0.04 | D158: 0 | E158: 0 | F158: 10 | H158: 0 | I158: 0 | J158: 0 | K158: 0 | L158: 0 | M158: 0 | N158: 0
A159: Cost of buildings | B159: stipend of 1 man going to Walton' to quarry lime there 2pence. | C159: 0.01 | D159: 0 | E159: 0 | F159: 2 | H159: 0 | I159: 0 | J159: 0 | K159: 0 | L159: 0 | M159: 0 | N159: 0
A160: Cost of buildings | B160: expenses of 12 men coming for a boon-work with 6 carts to quarry sand at Newotele and carry it to Adderbury, with the digging, 2 shilling 3pence. | C160: 0.11 | D160: 0 | E160: 2 | F160: 3 | H160: 0 | I160: 0 | J160: 0 | K160: 0 | L160: 0 | M160: 0 | N160: 0
A161: Cost of buildings | B161: hiring 1 man to carry sand and lime from the warrener's chamber to the barn by piece-work 4pence. | C161: 0.02 | D161: 0 | E161: 0 | F161: 4 | H161: 0 | I161: 0 | J161: 0 | K161: 0 | L161: 0 | M161: 0 | N161: 0
A162: Cost of buildings | B162: carrying the ridge-tiles bought above 8pence. | C162: 0.03 | D162: 0 | E162: 0 | F162: 8 | H162: 0 | I162: 0 | J162: 0 | K162: 0 | L162: 0 | M162: 0 | N162: 0
A163: Cost of buildings | B163: expenses of various men coming for a boon-work to buy slates at Aynho and carry them to Adderbury with the expenses of 1 man there mending the said slates 2d 1 shilling 9.5pence. | C163: 0.09 | D163: 0 | E163: 1 | F163: 9.5 | H163: 0 | I163: 0 | J163: 0 | K163: 0 | L163: 0 | M163: 0 | N163: 0
A164: Cost of buildings | B164: 1 tine bought 8pence. | C164: 0.03 | D164: 0 | E164: 0 | F164: 8 | H164: 0 | I164: 0 | J164: 0 | K164: 0 | L164: 0 | M164: 0 | N164: 0
... A181: Total of all allowances | B181: Total of all allowances and cash deliveries, £64 19 shilling 11.5pence He is quit. | C181: 65 | D181: 64 | E181: 19 | F181: 11.5 | H181: 0 | I181: 0 | J181: 0 | K181: 0 | L181: 0 | M181: 0 | N181: 0
A182: Wheat | B182: William Jakeman, reeve there, answers for 3 quarters of wheat remaining.. | C182: 0 | D182: 0 | E182: 0 | F182: 0 | G182: wheat | H182: 3 | I182: 0 | J182: 3 | K182: 3 | L182: 0 | M182: 3 | N182: 0
A183: Wheat | B183: Total, 3 quarters.. | C183: 0 | D183: 0 | E183: 0 | F183: 0 | H183: 3 | I183: 0 | J183: 3 | K183: 3 | L183: 0 | M183: 3 | N183: 0
A184: Wheat | B184: 3 quarters remain in the keeping of John Eadburbury, farmer there, to be handed back and restored at the end of his farm of 12 years, this year being the fifth. | C184: 0 | D184: 0 | E184: 0 | F184: 0 | H184: 3 | I184: 0 | J184: 3 | K184: 3 | L184: 0 | M184: 3 | N184: 0
A185: Rye | B185: And for 34 quarters of rye remaining.. | C185: 0 | D185: 0 | E185: 0 | F185: 0 | G185: rye | H185: 34 | I185: 0 | J185: 34 | K185: 34 | L185: 0 | M185: 34 | N185: 0
A186: Rye | B186: Total, 34 quarters.. | C186: 0 | D186: 0 | E186: 0 | F186: 0 | H186: 34 | I186: 0 | J186: 34 | K186: 34 | L186: 0 | M186: 34 | N186: 0
A187: Rye | B187: 34 quarters remain in the keeping of the said John Eadburbury, farmer there, to be handed back and restored at the end of his farm as before. | C187: 0 | D187: 0 | E187: 0 | F187: 0 | H187: 34 | I187: 0 | J187: 34 | K187: 34 | L187: 0 | M187: 34 | N187: 0
A188: Dredge | B188: And for 30 quarters of dredge remaining.. | C188: 0 | D188: 0 | E188: 0 | F188: 0 | G188: dredge | H188: 30 | I188: 0 | J188: 30 | K188: 30 | L188: 0 | M188: 30 | N188: 0
A189: Dredge | B189: Total, 30 quarters.. | C189: 0 | D189: 0 | E189: 0 | F189: 0 | H189: 30 | I189: 0 | J189: 30 | K189: 30 | L189: 0 | M189: 30 | N189: 0
A190: Dredge | B190: 30 quarters remain in the keeping of the said John Eadburbury, farmer there, to be handed back and restored as before. | C190: 0 | D190: 0 | E190: 0 | F190: 0 | H190: 30 | I190: 0 | J190: 30 | K190: 30 | L190: 0 | M190: 30 | N190: 0
A191: Pulses | B191: None remain. | C191: 0 | D191: 0 | E191: 0 | F191: 0 | H191: 0 | I191: 0 | J191: 0 | K191: 0 | L191: 0 | M191: 0 | N191: 0
A192: Oats | B192: And for 10 quarters of oats.. | C192: 0 | D192: 0 | E192: 0 | F192: 0 | G192: oats | H192: 10 | I192: 0 | J192: 10 | K192: 10 | L192: 0 | M192: 10 | N192: 0
A193: Oats | B193: Total, 10 quarters.. | C193: 0 | D193: 0 | E193: 0 | F193: 0 | H193: 10 | I193: 0 | J193: 10 | K193: 10 | L193: 0 | M193: 10 | N193: 0
A194: Oats | B194: 10 quarters remain in the keeping of the said John Eadburbury, farmer there, to be handed back and restored as before. | C194: 0 | D194: 0 | E194: 0 | F194: 0 | H194: 10 | I194: 0 | J194: 10 | K194: 10 | L194: 0 | M194: 10 | N194: 0
A195: Oats | B195: Eadburbury, farmer, to be handed back and restored at the end of his farm or the value of the same as before. | C195: 0 | D195: 0 | E195: 0 | F195: 0 | H195: 0 | I195: 0 | J195: 0 | K195: 0 | L195: 0 | M195: 0 | N195: 0
A196: Stock | B196: Horses: 4 remain. | C196: 0 | D196: 0 | E196: 0 | F196: 0 | H196: 0 | I196: 0 | J196: 0 | K196: 0 | L196: 0 | M196: 0 | N196: 0
A197: Stock | B197: 1 from the heriot of William Rundell'. | C197: 0 | D197: 0 | E197: 0 | F197: 0 | H197: 0 | I197: 0 | J197: 0 | K197: 0 | L197: 0 | M197: 0 | N197: 0
A198: Stock | B198: Total 5. 1 sold within. | C198: 0 | D198: 0 | E198: 0 | F198: 0 | H198: 0 | I198: 0 | J198: 0 | K198: 0 | L198: 0 | M198: 0 | N198: 0
A199: Stock | B199: 4 cart-horses remain, of which 2 are worth £1 6s 8pence, 1 is worth £1, and 1 feeble one is worth 2 shilling, in the keeping of the said John Eadburbury, farmer there, to be handed back and restored at the end of his farm or the value of the same at the choice of the lord bishop or his attorney. | C199: 1 | D199: 1 | E199: 0 | F199: 0 | H199: 0 | I199: 0 | J199: 0 | K199: 0 | L199: 0 | M199: 0 | N199: 0
A200: Stock | B200: Plough-horses: 6 remain. | C200: 0 | D200: 0 | E200: 0 | F200: 0 | H200: 0 | I200: 0 | J200: 0 | K200: 0 | L200: 0 | M200: 0 | N200: 0
A201: Stock | B201: Total, 6. 6 remain, worth £2, in the keeping of John. | C201: 2 | D201: 2 | E201: 0 | F201: 0 | H201: 0 | I201: 0 | J201: 0 | K201: 0 | L201: 0 | M201: 0 | N201: 0
A202: Stock | B202: Colts: 1 from the heriot of John Diconurn. | C202: 0 | D202: 0 | E202: 0 | F202: 0 | H202: 0 | I202: 0 | J202: 0 | K202: 0 | L202: 0 | M202: 0 | N202: 0
A203: Stock | B203: sold within. | C203: 0 | D203: 0 | E203: 0 | F203: 0 | H203: 0 | I203: 0 | J203: 0 | K203: 0 | L203: 0 | M203: 0 | N203: 0
A204: Stock | B204: none remain. | C204: 0 | D204: 0 | E204: 0 | F204: 0 | H204: 0 | I204: 0 | J204: 0 | K204: 0 | L204: 0 | M204: 0 | N204: 0
... A268: Stock | B268: none remain. mid. | C268: 0 | D268: 0 | E268: 0 | F268: 0 | H268: 0 | I268: 0 | J268: 0 | K268: 0 | L268: 0 | M268: 0 | N268: 0

Sheet Prices
A1: Meat & Dairy Prices
C2: 1301 | D2: 1302 | E2: Average
A3: Beef | B3: £ per lb | C3: 0.0033351854 | D3: 0.0032608538 | E3: =AVERAGE(C3:D3)
A4: Mutton | B4: £ per lb | C4: 0.0036593977 | D4: 0.0037125513 | E4: =AVERAGE(C4:D4)
A5: Pork | B5: £ per lb | C5: 0.0038431326 | D5: 0.0037574803 | E5: =AVERAGE(C5:D5)
A6: Cheese | B6: £ per lb | C6: 0.0055768754 | D6: 0.0056654898 | E6: =AVERAGE(C6:D6)
A7: Butter | B7: £ per lb | C7: 0.0036626221 | D7: 0.0035935077 | E7: =AVERAGE(C7:D7)
A8: Milk | B8: £ per gallon | C8: 0.0055768754 | D8: 0.0056654898 | E8: =AVERAGE(C8:D8)

Sheet Labour Rents

Sheet Highclere Overview
A1: Highclere | B1: £ | C1: s | D1: d | G1: Total in £ | H1: Error
A3: CASH ACCOUNT
A4: RECEIPTS
A5: Arrears total | G5: =IF(INDEX('Highclere Receipts'!$A$4:$F$136,MATCH('Highclere Overview'!$A5,'Highclere Receipts'!$A$4:$A$136,0),6)=0,"",INDEX('Highclere Receipts'!$A$4:$F$136,MATCH('Highclere Overview'!$A5,'Highclere Receipts'!$A$4:$A$136,0),6))
A6: Rents of assize total | G6: =IF(INDEX('Highclere Receipts'!$A$4:$F$136,MATCH('Highclere Overview'!$A6,'Highclere Receipts'!$A$4:$A$136,0),6)=0,"",INDEX('Highclere Receipts'!$A$4:$F$136,MATCH('Highclere Overview'!$A6,'Highclere Receipts'!$A$4:$A$136,0),6))
A7: Quittances total | G7: =IF(INDEX('Highclere Receipts'!$A$4:$F$136,MATCH('Highclere Overview'!$A7,'Highclere Receipts'!$A$4:$A$136,0),6)=0,"",INDEX('Highclere Receipts'!$A$4:$F$136,MATCH('Highclere Overview'!$A7,'Highclere Receipts'!$A$4:$A$136,0),6))
A8: Defaults of rent total | G8: =IF(INDEX('Highclere Receipts'!$A$4:$F$136,MATCH('Highclere Overview'!$A8,'Highclere Receipts'!$A$4:$A$136,0),6)=0,"",INDEX('Highclere Receipts'!$A$4:$F$136,MATCH('Highclere Overview'!$A8,'Highclere Receipts'!$A$4:$A$136,0),6))
A9: Rents remaining | G9: ='Highclere Receipts'!F39
A10: Annual recognizances total | G10: =IF(INDEX('Highclere Receipts'!$A$4:$F$136,MATCH('Highclere Overview'!$A10,'Highclere Receipts'!$A$4:$A$136,0),6)=0,"",INDEX('Highclere Receipts'!$A$4:$F$136,MATCH('Highclere Overview'!$A10,'Highclere Receipts'!$A$4:$A$136,0),6))
A11: Issues of the Manor total | G11: =IF(INDEX('Highclere Receipts'!$A$4:$F$136,MATCH('Highclere Overview'!$A11,'Highclere Receipts'!$A$4:$A$136,0),6)=0,"",INDEX('Highclere Receipts'!$A$4:$F$136,MATCH('Highclere Overview'!$A11,'Highclere Receipts'!$A$4:$A$136,0),6))
A12: Sale of corn total | G12: =IF(INDEX('Highclere Receipts'!$A$4:$F$136,MATCH('Highclere Overview'!$A12,'Highclere Receipts'!$A$4:$A$136,0),6)=0,"",INDEX('Highclere Receipts'!$A$4:$F$136,MATCH('Highclere Overview'!$A12,'Highclere Receipts'!$A$4:$A$136,0),6))
A13: Entry and marriage fines total | G13: =IF(INDEX('Highclere Receipts'!$A$4:$F$136,MATCH('Highclere Overview'!$A13,'Highclere Receipts'!$A$4:$A$136,0),6)=0,"",INDEX('Highclere Receipts'!$A$4:$F$136,MATCH('Highclere Overview'!$A13,'Highclere Receipts'!$A$4:$A$136,0),6))
A14: Pleas & perquisites total | G14: =IF(INDEX('Highclere Receipts'!$A$4:$F$136,MATCH('Highclere Overview'!$A14,'Highclere Receipts'!$A$4:$A$136,0),6)=0,"",INDEX('Highclere Receipts'!$A$4:$F$136,MATCH('Highclere Overview'!$A14,'Highclere Receipts'!$A$4:$A$136,0),6))
A15: Sum of the above (incl. arrears) | G15: =G5+G9+G10+G11+G12+G13+G14
A16: Total recorded in the accounts excl. arrears | G16: ='Highclere Receipts'!F135 | H16: =G15-G16
A17: Total recorded in the accounts incl. arrears | G17: ='Highclere Receipts'!F136 | I17: not recorded
A20: EXPENSES
A21: Cost of ploughs total | G21: =IF(INDEX('Highclere Expenses'!$A$2:$F$148,MATCH('Highclere Overview'!$A21,'Highclere Expenses'!$A$2:$A$148,0),6)=0,"",INDEX('Highclere Expenses'!$A$2:$F$148,MATCH('Highclere Overview'!$A21,'Highclere Expenses'!$A$2:$A$148,0),6))
A22: Purchase of corn total | G22: =IF(INDEX('Highclere Expenses'!$A$2:$F$148,MATCH('Highclere Overview'!$A22,'Highclere Expenses'!$A$2:$A$148,0),6)=0,"",INDEX('Highclere Expenses'!$A$2:$F$148,MATCH('Highclere Overview'!$A22,'Highclere Expenses'!$A$2:$A$148,0),6))
A23: Cost of carts and wagons total | G23: =IF(INDEX('Highclere Expenses'!$A$2:$F$148,MATCH('Highclere Overview'!$A23,'Highclere Expenses'!$A$2:$A$148,0),6)=0,"",INDEX('Highclere Expenses'!$A$2:$F$148,MATCH('Highclere Overview'!$A23,'Highclere Expenses'!$A$2:$A$148,0),6))
A24: Cost of dairy total | G24: =IF(INDEX('Highclere Expenses'!$A$2:$F$148,MATCH('Highclere Overview'!$A24,'Highclere Expenses'!$A$2:$A$148,0),6)=0,"",INDEX('Highclere Expenses'!$A$2:$F$148,MATCH('Highclere Overview'!$A24,'Highclere Expenses'!$A$2:$A$148,0),6))
A25: Purchase of stock total | G25: =IF(INDEX('Highclere Expenses'!$A$2:$F$148,MATCH('Highclere Overview'!$A25,'Highclere Expenses'!$A$2:$A$148,0),6)=0,"",INDEX('Highclere Expenses'!$A$2:$F$148,MATCH('Highclere Overview'!$A25,'Highclere Expenses'!$A$2:$A$148,0),6))
A26: Sheepcote total | G26: =IF(INDEX('Highclere Expenses'!$A$2:$F$148,MATCH('Highclere Overview'!$A26,'Highclere Expenses'!$A$2:$A$148,0),6)=0,"",INDEX('Highclere Expenses'!$A$2:$F$148,MATCH('Highclere Overview'!$A26,'Highclere Expenses'!$A$2:$A$148,0),6))
A27: Cost of buildings total | G27: =IF(INDEX('Highclere Expenses'!$A$2:$F$148,MATCH('Highclere Overview'!$A27,'Highclere Expenses'!$A$2:$A$148,0),6)=0,"",INDEX('Highclere Expenses'!$A$2:$F$148,MATCH('Highclere Overview'!$A27,'Highclere Expenses'!$A$2:$A$148,0),6))
A28: Threshing total | G28: =IF(INDEX('Highclere Expenses'!$A$2:$F$148,MATCH('Highclere Overview'!$A28,'Highclere Expenses'!$A$2:$A$148,0),6)=0,"",INDEX('Highclere Expenses'!$A$2:$F$148,MATCH('Highclere Overview'!$A28,'Highclere Expenses'!$A$2:$A$148,0),6))
A29: Expenses of the harvest total | G29: =IF(INDEX('Highclere Expenses'!$A$2:$F$148,MATCH('Highclere Overview'!$A29,'Highclere Expenses'!$A$2:$A$148,0),6)=0,"",INDEX('Highclere Expenses'!$A$2:$F$148,MATCH('Highclere Overview'!$A29,'Highclere Expenses'!$A$2:$A$148,0),6))
A30: Steward's expenses total | G30: =IF(INDEX('Highclere Expenses'!$A$2:$F$148,MATCH('Highclere Overview'!$A30,'Highclere Expenses'!$A$2:$A$148,0),6)=0,"",INDEX('Highclere Expenses'!$A$2:$F$148,MATCH('Highclere Overview'!$A30,'Highclere Expenses'!$A$2:$A$148,0),6))
A31: Total of all expenses calculated | G31: ='Highclere Expenses'!F141
A32: Total of all expenses in account | G32: ='Highclere Expenses'!F140 | H32: =G31-G32
A33: Capital Expenses | G33: ='Highclere Expenses'!F148
A35: Owed by the reeve | G35: =G15-G31
A36: From accounts | G36: ='Highclere Expenses'!F143 | H36: =G36-G35
A38: Cash deliveries
A39: Total of all allowances and cash deliveries in accounts | G39: n/a
A41: Net amount owed | G41: n/a
A42: Net amount owed in accounts | G42: ='Highclere Expenses'!F146
A44: GRANGE ACCOUNT | B44: Net Production
A45: Grange | B45: qrs | G45: Value of total gross production in £ | H45: Value of total net production in £
A46: Net wheat | B46: ='Issues of the Grange'!J19 | G46: ='Issues of the Grange'!P5 | H46: ='Issues of the Grange'!M19
A47: Net bere | B47: ='Issues of the Grange'!J20 | G47: ='Issues of the Grange'!P6 | H47: ='Issues of the Grange'!M20
A48: Net curall | B48: ='Issues of the Grange'!J21 | G48: ='Issues of the Grange'!P7 | H48: ='Issues of the Grange'!M21
A49: Net barley | B49: ='Issues of the Grange'!J22 | G49: ='Issues of the Grange'!P8 | H49: ='Issues of the Grange'!M22
A50: Net oats | B50: ='Issues of the Grange'!J23 | G50: ='Issues of the Grange'!P9 | H50: ='Issues of the Grange'!M23
A51: Net peas | B51: ='Issues of the Grange'!J24 | G51: ='Issues of the Grange'!P10 | H51: ='Issues of the Grange'!M24
A52: Net vetches | B52: ='Issues of the Grange'!J25 | G52: ='Issues of the Grange'!P11 | H52: ='Issues of the Grange'!M25
A53: Total value of gross production (sum of the above) | G53: =SUM(G46:G52)
A54: Total value of net production | G54: =SUM(H46:H52)
A55: Value of sales | G55: ='Issues of the Grange'!N26
A57: MILL ACCOUNT | B57: n/a
A58: Issues of the mill | B58: qrs | C58: bus | G58: £
A59: Wheat
A60: Oatmeal
A61: 1st grade malt
A62: 2nd grade malt
A63: Maslin
A64: Total value of production (sum of the above)
A65: Value of sales | G65: n/a
A67: STOCK ACCOUNT
A68: Livestock | B68: Inherited stock | C68: End-period stock | D68: Stockbuilding | F68: Sales in (£) | G68: Value of production (£) at sales prices
A69: Cart-horses | B69: =IFERROR(INDEX(Stock!$A$3:$U$91,MATCH('Highclere Overview'!$A69,Stock!$A$3:$A$91,0),MATCH('Highclere Overview'!B$68,Stock!$A$3:$U$3,0)),0) | C69: =IFERROR(INDEX(Stock!$A$3:$U$91,MATCH('Highclere Overview'!$A69,Stock!$A$3:$A$91,0),MATCH('Highclere Overview'!C$68,Stock!$A$3:$U$3,0)),0) | D69: =C69-B69 | F69: =IFERROR(INDEX(Stock!$A$3:$U$91,MATCH('Highclere Overview'!$A69,Stock!$A$3:$A$91,0),MATCH('Highclere Overview'!F$68,Stock!$A$3:$U$3,0)),0) | G69: =IFERROR(INDEX(Stock!$A$3:$U$91,MATCH('Highclere Overview'!$A69,Stock!$A$3:$A$91,0),MATCH('Highclere Overview'!G$68,Stock!$A$3:$U$3,0)),0)
A70: Mares | B70: =IFERROR(INDEX(Stock!$A$3:$U$91,MATCH('Highclere Overview'!$A70,Stock!$A$3:$A$91,0),MATCH('Highclere Overview'!B$68,Stock!$A$3:$U$3,0)),0) | C70: =IFERROR(INDEX(Stock!$A$3:$U$91,MATCH('Highclere Overview'!$A70,Stock!$A$3:$A$91,0),MATCH('Highclere Overview'!C$68,Stock!$A$3:$U$3,0)),0) | D70: =C70-B70 | F70: =IFERROR(INDEX(Stock!$A$3:$U$91,MATCH('Highclere Overview'!$A70,Stock!$A$3:$A$91,0),MATCH('Highclere Overview'!F$68,Stock!$A$3:$U$3,0)),0) | G70: =IFERROR(INDEX(Stock!$A$3:$U$91,MATCH('Highclere Overview'!$A70,Stock!$A$3:$A$91,0),MATCH('Highclere Overview'!G$68,Stock!$A$3:$U$3,0)),0)
A71: Plough horses | B71: =IFERROR(INDEX(Stock!$A$3:$U$91,MATCH('Highclere Overview'!$A71,Stock!$A$3:$A$91,0),MATCH('Highclere Overview'!B$68,Stock!$A$3:$U$3,0)),0) | C71: =IFERROR(INDEX(Stock!$A$3:$U$91,MATCH('Highclere Overview'!$A71,Stock!$A$3:$A$91,0),MATCH('Highclere Overview'!C$68,Stock!$A$3:$U$3,0)),0) | D71: =C71-B71 | F71: =IFERROR(INDEX(Stock!$A$3:$U$91,MATCH('Highclere Overview'!$A71,Stock!$A$3:$A$91,0),MATCH('Highclere Overview'!F$68,Stock!$A$3:$U$3,0)),0) | G71: =IFERROR(INDEX(Stock!$A$3:$U$91,MATCH('Highclere Overview'!$A71,Stock!$A$3:$A$91,0),MATCH('Highclere Overview'!G$68,Stock!$A$3:$U$3,0)),0)
A72: Colts (2 years) | B72: =IFERROR(INDEX(Stock!$A$3:$U$91,MATCH('Highclere Overview'!$A72,Stock!$A$3:$A$91,0),MATCH('Highclere Overview'!B$68,Stock!$A$3:$U$3,0)),0) | C72: =IFERROR(INDEX(Stock!$A$3:$U$91,MATCH('Highclere Overview'!$A72,Stock!$A$3:$A$91,0),MATCH('Highclere Overview'!C$68,Stock!$A$3:$U$3,0)),0) | D72: =C72-B72 | F72: =IFERROR(INDEX(Stock!$A$3:$U$91,MATCH('Highclere Overview'!$A72,Stock!$A$3:$A$91,0),MATCH('Highclere Overview'!F$68,Stock!$A$3:$U$3,0)),0) | G72: =IFERROR(INDEX(Stock!$A$3:$U$91,MATCH('Highclere Overview'!$A72,Stock!$A$3:$A$91,0),MATCH('Highclere Overview'!G$68,Stock!$A$3:$U$3,0)),0)
A73: Colts (2 years) | B73: =IFERROR(INDEX(Stock!$A$3:$U$91,MATCH('Highclere Overview'!$A73,Stock!$A$3:$A$91,0),MATCH('Highclere Overview'!B$68,Stock!$A$3:$U$3,0)),0) | C73: =IFERROR(INDEX(Stock!$A$3:$U$91,MATCH('Highclere Overview'!$A73,Stock!$A$3:$A$91,0),MATCH('Highclere Overview'!C$68,Stock!$A$3:$U$3,0)),0) | D73: =C73-B73 | F73: =IFERROR(INDEX(Stock!$A$3:$U$91,MATCH('Highclere Overview'!$A73,Stock!$A$3:$A$91,0),MATCH('Highclere Overview'!F$68,Stock!$A$3:$U$3,0)),0) | G73: =IFERROR(INDEX(Stock!$A$3:$U$91,MATCH('Highclere Overview'!$A73,Stock!$A$3:$A$91,0),MATCH('Highclere Overview'!G$68,Stock!$A$3:$U$3,0)),0)
A74: Colts (1 year) | B74: =IFERROR(INDEX(Stock!$A$3:$U$91,MATCH('Highclere Overview'!$A74,Stock!$A$3:$A$91,0),MATCH('Highclere Overview'!B$68,Stock!$A$3:$U$3,0)),0) | C74: =IFERROR(INDEX(Stock!$A$3:$U$91,MATCH('Highclere Overview'!$A74,Stock!$A$3:$A$91,0),MATCH('Highclere Overview'!C$68,Stock!$A$3:$U$3,0)),0) | D74: =C74-B74 | F74: =IFERROR(INDEX(Stock!$A$3:$U$91,MATCH('Highclere Overview'!$A74,Stock!$A$3:$A$91,0),MATCH('Highclere Overview'!F$68,Stock!$A$3:$U$3,0)),0) | G74: =IFERROR(INDEX(Stock!$A$3:$U$91,MATCH('Highclere Overview'!$A74,Stock!$A$3:$A$91,0),MATCH('Highclere Overview'!G$68,Stock!$A$3:$U$3,0)),0)
A75: Foals | B75: =IFERROR(INDEX(Stock!$A$3:$U$91,MATCH('Highclere Overview'!$A75,Stock!$A$3:$A$91,0),MATCH('Highclere Overview'!B$68,Stock!$A$3:$U$3,0)),0) | C75: =IFERROR(INDEX(Stock!$A$3:$U$91,MATCH('Highclere Overview'!$A75,Stock!$A$3:$A$91,0),MATCH('Highclere Overview'!C$68,Stock!$A$3:$U$3,0)),0) | D75: =C75-B75 | F75: =IFERROR(INDEX(Stock!$A$3:$U$91,MATCH('Highclere Overview'!$A75,Stock!$A$3:$A$91,0),MATCH('Highclere Overview'!F$68,Stock!$A$3:$U$3,0)),0) | G75: =IFERROR(INDEX(Stock!$A$3:$U$91,MATCH('Highclere Overview'!$A75,Stock!$A$3:$A$91,0),MATCH('Highclere Overview'!G$68,Stock!$A$3:$U$3,0)),0)
A76: Oxen | B76: =IFERROR(INDEX(Stock!$A$3:$U$91,MATCH('Highclere Overview'!$A76,Stock!$A$3:$A$91,0),MATCH('Highclere Overview'!B$68,Stock!$A$3:$U$3,0)),0) | C76: =IFERROR(INDEX(Stock!$A$3:$U$91,MATCH('Highclere Overview'!$A76,Stock!$A$3:$A$91,0),MATCH('Highclere Overview'!C$68,Stock!$A$3:$U$3,0)),0) | D76: =C76-B76 | F76: =IFERROR(INDEX(Stock!$A$3:$U$91,MATCH('Highclere Overview'!$A76,Stock!$A$3:$A$91,0),MATCH('Highclere Overview'!F$68,Stock!$A$3:$U$3,0)),0) | G76: =IFERROR(INDEX(Stock!$A$3:$U$91,MATCH('Highclere Overview'!$A76,Stock!$A$3:$A$91,0),MATCH('Highclere Overview'!G$68,Stock!$A$3:$U$3,0)),0)
A77: Bulls | B77: =IFERROR(INDEX(Stock!$A$3:$U$91,MATCH('Highclere Overview'!$A77,Stock!$A$3:$A$91,0),MATCH('Highclere Overview'!B$68,Stock!$A$3:$U$3,0)),0) | C77: =IFERROR(INDEX(Stock!$A$3:$U$91,MATCH('Highclere Overview'!$A77,Stock!$A$3:$A$91,0),MATCH('Highclere Overview'!C$68,Stock!$A$3:$U$3,0)),0) | D77: =C77-B77 | F77: =IFERROR(INDEX(Stock!$A$3:$U$91,MATCH('Highclere Overview'!$A77,Stock!$A$3:$A$91,0),MATCH('Highclere Overview'!F$68,Stock!$A$3:$U$3,0)),0) | G77: =IFERROR(INDEX(Stock!$A$3:$U$91,MATCH('Highclere Overview'!$A77,Stock!$A$3:$A$91,0),MATCH('Highclere Overview'!G$68,Stock!$A$3:$U$3,0)),0)
A78: Cows | B78: =IFERROR(INDEX(Stock!$A$3:$U$91,MATCH('Highclere Overview'!$A78,Stock!$A$3:$A$91,0),MATCH('Highclere Overview'!B$68,Stock!$A$3:$U$3,0)),0) | C78: =IFERROR(INDEX(Stock!$A$3:$U$91,MATCH('Highclere Overview'!$A78,Stock!$A$3:$A$91,0),MATCH('Highclere Overview'!C$68,Stock!$A$3:$U$3,0)),0) | D78: =C78-B78 | F78: =IFERROR(INDEX(Stock!$A$3:$U$91,MATCH('Highclere Overview'!$A78,Stock!$A$3:$A$91,0),MATCH('Highclere Overview'!F$68,Stock!$A$3:$U$3,0)),0) | G78: =IFERROR(INDEX(Stock!$A$3:$U$91,MATCH('Highclere Overview'!$A78,Stock!$A$3:$A$91,0),MATCH('Highclere Overview'!G$68,Stock!$A$3:$U$3,0)),0)
A79: Steers | B79: =IFERROR(INDEX(Stock!$A$3:$U$91,MATCH('Highclere Overview'!$A79,Stock!$A$3:$A$91,0),MATCH('Highclere Overview'!B$68,Stock!$A$3:$U$3,0)),0) | C79: =IFERROR(INDEX(Stock!$A$3:$U$91,MATCH('Highclere Overview'!$A79,Stock!$A$3:$A$91,0),MATCH('Highclere Overview'!C$68,Stock!$A$3:$U$3,0)),0) | D79: =C79-B79 | F79: =IFERROR(INDEX(Stock!$A$3:$U$91,MATCH('Highclere Overview'!$A79,Stock!$A$3:$A$91,0),MATCH('Highclere Overview'!F$68,Stock!$A$3:$U$3,0)),0) | G79: =IFERROR(INDEX(Stock!$A$3:$U$91,MATCH('Highclere Overview'!$A79,Stock!$A$3:$A$91,0),MATCH('Highclere Overview'!G$68,Stock!$A$3:$U$3,0)),0)
A80: Bullocks | B80: =IFERROR(INDEX(Stock!$A$3:$U$91,MATCH('Highclere Overview'!$A80,Stock!$A$3:$A$91,0),MATCH('Highclere Overview'!B$68,Stock!$A$3:$U$3,0)),0) | C80: =IFERROR(INDEX(Stock!$A$3:$U$91,MATCH('Highclere Overview'!$A80,Stock!$A$3:$A$91,0),MATCH('Highclere Overview'!C$68,Stock!$A$3:$U$3,0)),0) | D80: =C80-B80 | F80: =IFERROR(INDEX(Stock!$A$3:$U$91,MATCH('Highclere Overview'!$A80,Stock!$A$3:$A$91,0),MATCH('Highclere Overview'!F$68,Stock!$A$3:$U$3,0)),0) | G80: =IFERROR(INDEX(Stock!$A$3:$U$91,MATCH('Highclere Overview'!$A80,Stock!$A$3:$A$91,0),MATCH('Highclere Overview'!G$68,Stock!$A$3:$U$3,0)),0)
... A94: Peacocks | B94: =IFERROR(INDEX(Stock!$A$3:$U$91,MATCH('Highclere Overview'!$A94,Stock!$A$3:$A$91,0),MATCH('Highclere Overview'!B$68,Stock!$A$3:$U$3,0)),0) | C94: =IFERROR(INDEX(Stock!$A$3:$U$91,MATCH('Highclere Overview'!$A94,Stock!$A$3:$A$91,0),MATCH('Highclere Overview'!C$68,Stock!$A$3:$U$3,0)),0) | D94: =C94-B94 | F94: =IFERROR(INDEX(Stock!$A$3:$U$91,MATCH('Highclere Overview'!$A94,Stock!$A$3:$A$91,0),MATCH('Highclere Overview'!F$68,Stock!$A$3:$U$3,0)),0) | G94: =IFERROR(INDEX(Stock!$A$3:$U$91,MATCH('Highclere Overview'!$A94,Stock!$A$3:$A$91,0),MATCH('Highclere Overview'!G$68,Stock!$A$3:$U$3,0)),0)
A95: Total value of production | G95: =SUM(G69:G94) | H95: less than sales because we are missing prices for some livestock
A96: Value of sales | G96: =SUM(F69:F94)
A98: Wool | B98: Inherited stock | C98: End-period stock | D98: Stockbuilding | F98: Sales in (£) | G98: Value of production (£) at sales prices
A99: Fleeces | B99: =IFERROR(INDEX(Stock!$A$3:$U$91,MATCH('Highclere Overview'!$A99,Stock!$A$3:$A$91,0),MATCH('Highclere Overview'!B$68,Stock!$A$3:$U$3,0)),0) | C99: =IFERROR(INDEX(Stock!$A$3:$U$91,MATCH('Highclere Overview'!$A99,Stock!$A$3:$A$91,0),MATCH('Highclere Overview'!C$68,Stock!$A$3:$U$3,0)),0) | D99: =C99-B99 | F99: =IFERROR(INDEX(Stock!$A$3:$U$91,MATCH('Highclere Overview'!$A99,Stock!$A$3:$A$91,0),MATCH('Highclere Overview'!F$68,Stock!$A$3:$U$3,0)),0) | G99: =IFERROR(INDEX(Stock!$A$3:$U$91,MATCH('Highclere Overview'!$A99,Stock!$A$3:$A$91,0),MATCH('Highclere Overview'!G$68,Stock!$A$3:$U$3,0)),0)
A100: Coarse wool | B100: =IFERROR(INDEX(Stock!$A$3:$U$91,MATCH('Highclere Overview'!$A100,Stock!$A$3:$A$91,0),MATCH('Highclere Overview'!B$68,Stock!$A$3:$U$3,0)),0) | C100: =IFERROR(INDEX(Stock!$A$3:$U$91,MATCH('Highclere Overview'!$A100,Stock!$A$3:$A$91,0),MATCH('Highclere Overview'!C$68,Stock!$A$3:$U$3,0)),0) | D100: =C100-B100 | F100: =IFERROR(INDEX(Stock!$A$3:$U$91,MATCH('Highclere Overview'!$A100,Stock!$A$3:$A$91,0),MATCH('Highclere Overview'!F$68,Stock!$A$3:$U$3,0)),0) | G100: =IFERROR(INDEX(Stock!$A$3:$U$91,MATCH('Highclere Overview'!$A100,Stock!$A$3:$A$91,0),MATCH('Highclere Overview'!G$68,Stock!$A$3:$U$3,0)),0)
A101: Lamb's wool | B101: =IFERROR(INDEX(Stock!$A$3:$U$91,MATCH('Highclere Overview'!$A101,Stock!$A$3:$A$91,0),MATCH('Highclere Overview'!B$68,Stock!$A$3:$U$3,0)),0) | C101: =IFERROR(INDEX(Stock!$A$3:$U$91,MATCH('Highclere Overview'!$A101,Stock!$A$3:$A$91,0),MATCH('Highclere Overview'!C$68,Stock!$A$3:$U$3,0)),0) | D101: =C101-B101 | F101: =IFERROR(INDEX(Stock!$A$3:$U$91,MATCH('Highclere Overview'!$A101,Stock!$A$3:$A$91,0),MATCH('Highclere Overview'!F$68,Stock!$A$3:$U$3,0)),0) | G101: =IFERROR(INDEX(Stock!$A$3:$U$91,MATCH('Highclere Overview'!$A101,Stock!$A$3:$A$91,0),MATCH('Highclere Overview'!G$68,Stock!$A$3:$U$3,0)),0)
A102: Wool locks | B102: =IFERROR(INDEX(Stock!$A$3:$U$91,MATCH('Highclere Overview'!$A102,Stock!$A$3:$A$91,0),MATCH('Highclere Overview'!B$68,Stock!$A$3:$U$3,0)),0) | C102: =IFERROR(INDEX(Stock!$A$3:$U$91,MATCH('Highclere Overview'!$A102,Stock!$A$3:$A$91,0),MATCH('Highclere Overview'!C$68,Stock!$A$3:$U$3,0)),0) | D102: =C102-B102 | F102: =IFERROR(INDEX(Stock!$A$3:$U$91,MATCH('Highclere Overview'!$A102,Stock!$A$3:$A$91,0),MATCH('Highclere Overview'!F$68,Stock!$A$3:$U$3,0)),0) | G102: =IFERROR(INDEX(Stock!$A$3:$U$91,MATCH('Highclere Overview'!$A102,Stock!$A$3:$A$91,0),MATCH('Highclere Overview'!G$68,Stock!$A$3:$U$3,0)),0)
A103: Wool sold at shearing | B103: =IFERROR(INDEX(Stock!$A$3:$U$91,MATCH('Highclere Overview'!$A103,Stock!$A$3:$A$91,0),MATCH('Highclere Overview'!B$68,Stock!$A$3:$U$3,0)),0) | C103: =IFERROR(INDEX(Stock!$A$3:$U$91,MATCH('Highclere Overview'!$A103,Stock!$A$3:$A$91,0),MATCH('Highclere Overview'!C$68,Stock!$A$3:$U$3,0)),0) | D103: =C103-B103 | F103: =IFERROR(INDEX(Stock!$A$3:$U$91,MATCH('Highclere Overview'!$A103,Stock!$A$3:$A$91,0),MATCH('Highclere Overview'!F$68,Stock!$A$3:$U$3,0)),0) | G103: =IFERROR(INDEX(Stock!$A$3:$U$91,MATCH('Highclere Overview'!$A103,Stock!$A$3:$A$91,0),MATCH('Highclere Overview'!G$68,Stock!$A$3:$U$3,0)),0)
A104: Total value of production (sum of the above) | G104: =SUM(G99:G103)
A105: Value of sales | G105: =SUM(F99:F103)
A107: Hides | B107: Inherited stock | C107: End-period stock | D107: Stockbuilding | F107: Sales in (£) | G107: Value of production (£) at sales prices
A108: Ox hides | B108: =IFERROR(INDEX(Stock!$A$3:$U$91,MATCH('Highclere Overview'!$A108,Stock!$A$3:$A$91,0),MATCH('Highclere Overview'!B$68,Stock!$A$3:$U$3,0)),0) | C108: =IFERROR(INDEX(Stock!$A$3:$U$91,MATCH('Highclere Overview'!$A108,Stock!$A$3:$A$91,0),MATCH('Highclere Overview'!C$68,Stock!$A$3:$U$3,0)),0) | D108: =C108-B108 | F108: =IFERROR(INDEX(Stock!$A$3:$U$91,MATCH('Highclere Overview'!$A108,Stock!$A$3:$A$91,0),MATCH('Highclere Overview'!F$68,Stock!$A$3:$U$3,0)),0) | G108: =IFERROR(INDEX(Stock!$A$3:$U$91,MATCH('Highclere Overview'!$A108,Stock!$A$3:$A$91,0),MATCH('Highclere Overview'!G$68,Stock!$A$3:$U$3,0)),0)
A109: Cow hides | B109: =IFERROR(INDEX(Stock!$A$3:$U$91,MATCH('Highclere Overview'!$A109,Stock!$A$3:$A$91,0),MATCH('Highclere Overview'!B$68,Stock!$A$3:$U$3,0)),0) | C109: =IFERROR(INDEX(Stock!$A$3:$U$91,MATCH('Highclere Overview'!$A109,Stock!$A$3:$A$91,0),MATCH('Highclere Overview'!C$68,Stock!$A$3:$U$3,0)),0) | D109: =C109-B109 | F109: =IFERROR(INDEX(Stock!$A$3:$U$91,MATCH('Highclere Overview'!$A109,Stock!$A$3:$A$91,0),MATCH('Highclere Overview'!F$68,Stock!$A$3:$U$3,0)),0) | G109: =IFERROR(INDEX(Stock!$A$3:$U$91,MATCH('Highclere Overview'!$A109,Stock!$A$3:$A$91,0),MATCH('Highclere Overview'!G$68,Stock!$A$3:$U$3,0)),0)
A110: Mare hides | B110: =IFERROR(INDEX(Stock!$A$3:$U$91,MATCH('Highclere Overview'!$A110,Stock!$A$3:$A$91,0),MATCH('Highclere Overview'!B$68,Stock!$A$3:$U$3,0)),0) | C110: =IFERROR(INDEX(Stock!$A$3:$U$91,MATCH('Highclere Overview'!$A110,Stock!$A$3:$A$91,0),MATCH('Highclere Overview'!C$68,Stock!$A$3:$U$3,0)),0) | D110: =C110-B110 | F110: =IFERROR(INDEX(Stock!$A$3:$U$91,MATCH('Highclere Overview'!$A110,Stock!$A$3:$A$91,0),MATCH('Highclere Overview'!F$68,Stock!$A$3:$U$3,0)),0) | G110: =IFERROR(INDEX(Stock!$A$3:$U$91,MATCH('Highclere Overview'!$A110,Stock!$A$3:$A$91,0),MATCH('Highclere Overview'!G$68,Stock!$A$3:$U$3,0)),0)
A111: Steer hides | B111: =IFERROR(INDEX(Stock!$A$3:$U$91,MATCH('Highclere Overview'!$A111,Stock!$A$3:$A$91,0),MATCH('Highclere Overview'!B$68,Stock!$A$3:$U$3,0)),0) | C111: =IFERROR(INDEX(Stock!$A$3:$U$91,MATCH('Highclere Overview'!$A111,Stock!$A$3:$A$91,0),MATCH('Highclere Overview'!C$68,Stock!$A$3:$U$3,0)),0) | D111: =C111-B111 | F111: =IFERROR(INDEX(Stock!$A$3:$U$91,MATCH('Highclere Overview'!$A111,Stock!$A$3:$A$91,0),MATCH('Highclere Overview'!F$68,Stock!$A$3:$U$3,0)),0) | G111: =IFERROR(INDEX(Stock!$A$3:$U$91,MATCH('Highclere Overview'!$A111,Stock!$A$3:$A$91,0),MATCH('Highclere Overview'!G$68,Stock!$A$3:$U$3,0)),0)
A112: Yearling Calf hides | B112: =IFERROR(INDEX(Stock!$A$3:$U$91,MATCH('Highclere Overview'!$A112,Stock!$A$3:$A$91,0),MATCH('Highclere Overview'!B$68,Stock!$A$3:$U$3,0)),0) | C112: =IFERROR(INDEX(Stock!$A$3:$U$91,MATCH('Highclere Overview'!$A112,Stock!$A$3:$A$91,0),MATCH('Highclere Overview'!C$68,Stock!$A$3:$U$3,0)),0) | D112: =C112-B112 | F112: =IFERROR(INDEX(Stock!$A$3:$U$91,MATCH('Highclere Overview'!$A112,Stock!$A$3:$A$91,0),MATCH('Highclere Overview'!F$68,Stock!$A$3:$U$3,0)),0) | G112: =IFERROR(INDEX(Stock!$A$3:$U$91,MATCH('Highclere Overview'!$A112,Stock!$A$3:$A$91,0),MATCH('Highclere Overview'!G$68,Stock!$A$3:$U$3,0)),0)
A113: Calf hides | B113: =IFERROR(INDEX(Stock!$A$3:$U$91,MATCH('Highclere Overview'!$A113,Stock!$A$3:$A$91,0),MATCH('Highclere Overview'!B$68,Stock!$A$3:$U$3,0)),0) | C113: =IFERROR(INDEX(Stock!$A$3:$U$91,MATCH('Highclere Overview'!$A113,Stock!$A$3:$A$91,0),MATCH('Highclere Overview'!C$68,Stock!$A$3:$U$3,0)),0) | D113: =C113-B113 | F113: =IFERROR(INDEX(Stock!$A$3:$U$91,MATCH('Highclere Overview'!$A113,Stock!$A$3:$A$91,0),MATCH('Highclere Overview'!F$68,Stock!$A$3:$U$3,0)),0) | G113: =IFERROR(INDEX(Stock!$A$3:$U$91,MATCH('Highclere Overview'!$A113,Stock!$A$3:$A$91,0),MATCH('Highclere Overview'!G$68,Stock!$A$3:$U$3,0)),0)
A114: Pig hides | B114: =IFERROR(INDEX(Stock!$A$3:$U$91,MATCH('Highclere Overview'!$A114,Stock!$A$3:$A$91,0),MATCH('Highclere Overview'!B$68,Stock!$A$3:$U$3,0)),0) | C114: =IFERROR(INDEX(Stock!$A$3:$U$91,MATCH('Highclere Overview'!$A114,Stock!$A$3:$A$91,0),MATCH('Highclere Overview'!C$68,Stock!$A$3:$U$3,0)),0) | D114: =C114-B114 | F114: =IFERROR(INDEX(Stock!$A$3:$U$91,MATCH('Highclere Overview'!$A114,Stock!$A$3:$A$91,0),MATCH('Highclere Overview'!F$68,Stock!$A$3:$U$3,0)),0) | G114: =IFERROR(INDEX(Stock!$A$3:$U$91,MATCH('Highclere Overview'!$A114,Stock!$A$3:$A$91,0),MATCH('Highclere Overview'!G$68,Stock!$A$3:$U$3,0)),0)
A115: Weather woolskins | B115: =IFERROR(INDEX(Stock!$A$3:$U$91,MATCH('Highclere Overview'!$A115,Stock!$A$3:$A$91,0),MATCH('Highclere Overview'!B$68,Stock!$A$3:$U$3,0)),0) | C115: =IFERROR(INDEX(Stock!$A$3:$U$91,MATCH('Highclere Overview'!$A115,Stock!$A$3:$A$91,0),MATCH('Highclere Overview'!C$68,Stock!$A$3:$U$3,0)),0) | D115: =C115-B115 | F115: =IFERROR(INDEX(Stock!$A$3:$U$91,MATCH('Highclere Overview'!$A115,Stock!$A$3:$A$91,0),MATCH('Highclere Overview'!F$68,Stock!$A$3:$U$3,0)),0) | G115: =IFERROR(INDEX(Stock!$A$3:$U$91,MATCH('Highclere Overview'!$A115,Stock!$A$3:$A$91,0),MATCH('Highclere Overview'!G$68,Stock!$A$3:$U$3,0)),0)
A116: Ram woolskins | B116: =IFERROR(INDEX(Stock!$A$3:$U$91,MATCH('Highclere Overview'!$A116,Stock!$A$3:$A$91,0),MATCH('Highclere Overview'!B$68,Stock!$A$3:$U$3,0)),0) | C116: =IFERROR(INDEX(Stock!$A$3:$U$91,MATCH('Highclere Overview'!$A116,Stock!$A$3:$A$91,0),MATCH('Highclere Overview'!C$68,Stock!$A$3:$U$3,0)),0) | D116: =C116-B116 | F116: =IFERROR(INDEX(Stock!$A$3:$U$91,MATCH('Highclere Overview'!$A116,Stock!$A$3:$A$91,0),MATCH('Highclere Overview'!F$68,Stock!$A$3:$U$3,0)),0) | G116: =IFERROR(INDEX(Stock!$A$3:$U$91,MATCH('Highclere Overview'!$A116,Stock!$A$3:$A$91,0),MATCH('Highclere Overview'!G$68,Stock!$A$3:$U$3,0)),0)
A117: Ewe woolskins | B117: =IFERROR(INDEX(Stock!$A$3:$U$91,MATCH('Highclere Overview'!$A117,Stock!$A$3:$A$91,0),MATCH('Highclere Overview'!B$68,Stock!$A$3:$U$3,0)),0) | C117: =IFERROR(INDEX(Stock!$A$3:$U$91,MATCH('Highclere Overview'!$A117,Stock!$A$3:$A$91,0),MATCH('Highclere Overview'!C$68,Stock!$A$3:$U$3,0)),0) | D117: =C117-B117 | F117: =IFERROR(INDEX(Stock!$A$3:$U$91,MATCH('Highclere Overview'!$A117,Stock!$A$3:$A$91,0),MATCH('Highclere Overview'!F$68,Stock!$A$3:$U$3,0)),0) | G117: =IFERROR(INDEX(Stock!$A$3:$U$91,MATCH('Highclere Overview'!$A117,Stock!$A$3:$A$91,0),MATCH('Highclere Overview'!G$68,Stock!$A$3:$U$3,0)),0)
A118: Hogg woolskins | B118: =IFERROR(INDEX(Stock!$A$3:$U$91,MATCH('Highclere Overview'!$A118,Stock!$A$3:$A$91,0),MATCH('Highclere Overview'!B$68,Stock!$A$3:$U$3,0)),0) | C118: =IFERROR(INDEX(Stock!$A$3:$U$91,MATCH('Highclere Overview'!$A118,Stock!$A$3:$A$91,0),MATCH('Highclere Overview'!C$68,Stock!$A$3:$U$3,0)),0) | D118: =C118-B118 | F118: =IFERROR(INDEX(Stock!$A$3:$U$91,MATCH('Highclere Overview'!$A118,Stock!$A$3:$A$91,0),MATCH('Highclere Overview'!F$68,Stock!$A$3:$U$3,0)),0) | G118: =IFERROR(INDEX(Stock!$A$3:$U$91,MATCH('Highclere Overview'!$A118,Stock!$A$3:$A$91,0),MATCH('Highclere Overview'!G$68,Stock!$A$3:$U$3,0)),0)
A119: Woolskins (total) | B119: =IFERROR(INDEX(Stock!$A$3:$U$91,MATCH('Highclere Overview'!$A119,Stock!$A$3:$A$91,0),MATCH('Highclere Overview'!B$68,Stock!$A$3:$U$3,0)),0) | C119: =IFERROR(INDEX(Stock!$A$3:$U$91,MATCH('Highclere Overview'!$A119,Stock!$A$3:$A$91,0),MATCH('Highclere Overview'!C$68,Stock!$A$3:$U$3,0)),0) | D119: =C119-B119 | F119: =IFERROR(INDEX(Stock!$A$3:$U$91,MATCH('Highclere Overview'!$A119,Stock!$A$3:$A$91,0),MATCH('Highclere Overview'!F$68,Stock!$A$3:$U$3,0)),0) | G119: =IFERROR(INDEX(Stock!$A$3:$U$91,MATCH('Highclere Overview'!$A119,Stock!$A$3:$A$91,0),MATCH('Highclere Overview'!G$68,Stock!$A$3:$U$3,0)),0)
... A127: Shorn skins | B127: =IFERROR(INDEX(Stock!$A$3:$U$91,MATCH('Highclere Overview'!$A127,Stock!$A$3:$A$91,0),MATCH('Highclere Overview'!B$68,Stock!$A$3:$U$3,0)),0) | C127: =IFERROR(INDEX(Stock!$A$3:$U$91,MATCH('Highclere Overview'!$A127,Stock!$A$3:$A$91,0),MATCH('Highclere Overview'!C$68,Stock!$A$3:$U$3,0)),0) | D127: =C127-B127 | F127: =IFERROR(INDEX(Stock!$A$3:$U$91,MATCH('Highclere Overview'!$A127,Stock!$A$3:$A$91,0),MATCH('Highclere Overview'!F$68,Stock!$A$3:$U$3,0)),0) | G127: =IFERROR(INDEX(Stock!$A$3:$U$91,MATCH('Highclere Overview'!$A127,Stock!$A$3:$A$91,0),MATCH('Highclere Overview'!G$68,Stock!$A$3:$U$3,0)),0)
A128: Total value of production (sum of the above) | G128: =SUM(G108:G127)
A129: Value of sales | G129: =SUM(F108:F127)
A131: Poultry stock | B131: Inherited stock | C131: End-period stock | D131: Stockbuilding | F131: Sales in (£) | G131: Value of production (£) at sales prices
A132: Hens | B132: =IFERROR(INDEX(Stock!$A$3:$U$91,MATCH('Highclere Overview'!$A132,Stock!$A$3:$A$91,0),MATCH('Highclere Overview'!B$68,Stock!$A$3:$U$3,0)),0) | C132: =IFERROR(INDEX(Stock!$A$3:$U$91,MATCH('Highclere Overview'!$A132,Stock!$A$3:$A$91,0),MATCH('Highclere Overview'!C$68,Stock!$A$3:$U$3,0)),0) | D132: =C132-B132 | F132: =IFERROR(INDEX(Stock!$A$3:$U$91,MATCH('Highclere Overview'!$A132,Stock!$A$3:$A$91,0),MATCH('Highclere Overview'!F$68,Stock!$A$3:$U$3,0)),0) | G132: =IFERROR(INDEX(Stock!$A$3:$U$91,MATCH('Highclere Overview'!$A132,Stock!$A$3:$A$91,0),MATCH('Highclere Overview'!G$68,Stock!$A$3:$U$3,0)),0)
...

Sheet Highclere Receipts
A1: Highclere RECEIPTS
B2: £ | C2: s | D2: d | F2: Total in £ | G2: Error | H2: Notes
A4: Arrears
A5: Arrears total | B5: 1 | C5: 8 | F5: =B5+C5/20+D5/240
A6: of which delivered to treasurer of Wolvesey | B6: 1 | C6: 8 | F6: =B6+C6/20+D6/240
A8: Rents of assize
A9: Christmas | B9: 1 | C9: 14 | F9: =B9+C9/20+D9/240
A10: Easter | B10: 3 | C10: 6 | F10: =B10+C10/20+D10/240
A11: Nativity | B11: 2 | F11: =B11+C11/20+D11/240
A12: Michaelmas | B12: 15 | C12: 8 | D12: 1.5 | F12: =B12+C12/20+D12/240
A13: Total recorded in accounts | B13: 22 | C13: 8 | D13: 1.5 | F13: =B13+C13/20+D13/240
A14: Rents of assize total | B14: =SUM(B9:B12) | C14: =SUM(C9:C12) | D14: =SUM(D9:D12) | F14: =B14+C14/20+D14/240 | G14: =F14-F13
A16: Quittances
A17: quittance of 1 reeve | C17: 4 | F17: =B17+C17/20+D17/240
A18: 1 hayward for the year | C18: 2 | F18: =B18+C18/20+D18/240
A19: 1 woodward of Holehurst | C19: 2 | D19: 4 | F19: =B19+C19/20+D19/240
A20: 3 ploughmen | C20: 6 | F20: =B20+C20/20+D20/240
A21: 1 ploughman | C21: 1 | D21: 3 | F21: =B21+C21/20+D21/240
A22: 1 smith making the ironwork of the ploughs | C22: 2 | F22: =B22+C22/20+D22/240
A23: 1 keeper of ewes | C23: 1 | D23: 3 | F23: =B23+C23/20+D23/240
A24: 1 cowherd | C24: 2 | F24: =B24+C24/20+D24/240
A25: Total recorded in accounts | B25: 1 | D25: 10 | F25: =B25+C25/20+D25/240
A26: Quittances total | B26: =SUM(B17:B24) | C26: =SUM(C17:C25) | D26: =SUM(D17:D24) | F26: =B26+C26/20+D26/240 | G26: =F26-F25
A28: Defaults of rent
A29: in default of 24 acres of land | D29: 10 | F29: =B29+C29/20+D29/240
A30: 10 virgates | C30: 13 | D30: 4 | F30: =B30+C30/20+D30/240
A31: the land of the skinner | C31: 1 | F31: =B31+C31/20+D31/240
A32: the land which belonged Benedict Clericus | C32: 4 | D32: 6 | F32: =B32+C32/20+D32/240
A33: land which belonged to Alexander ly Rych | C33: 17 | D33: 9 | F33: =B33+C33/20+D33/240
A34: rent of Hawkley | C34: 3 | F34: =B34+C34/20+D34/240
A35: Nicholas atte Zele | D35: 4 | F35: =B35+C35/20+D35/240
A36: Total recorded in accounts | B36: 2 | D36: 9 | F36: =B36+C36/20+D36/240
A37: Defaults of rent total | B37: =SUM(B29:B35) | C37: =SUM(C29:C35) | D37: =SUM(D29:D35) | F37: =B37+C37/20+D37/240 | G37: =F37-F36
A39: Total of rents remaining | B39: 19 | C39: 6 | D39: 6.5 | F39: =B39+C39/20+D39/240
A41: Wax
A42: nothing | F42: =B42+C42/20+D42/240
A43: Total recorded in accounts | F43: =B43+C43/20+D43/240
A44: Wax total | B44: =SUM(B42) | C44: =SUM(C42) | D44: =SUM(D42) | F44: =B44+C44/20+D44/240 | G44: =F44-F43
A46: Annual recognizances
A47: from Elias Snow | C47: 1 | F47: =B47+C47/20+D47/240
A48: Total recorded in accounts | F48: =B48+C48/20+D48/240
A49: Annual recognizances total | B49: =SUM(B47:B47) | C49: =SUM(C47:C47) | D49: =SUM(D47:D47) | F49: =B49+C49/20+D49/240 | G49: =F49-F48
A51: Issues of the manor
A52: pannage of pigs | C52: 5 | D52: 4.5 | F52: =B52+C52/20+D52/240
A53: foreign pannage | B53: 1 | C53: 5 | D53: 7 | F53: =B53+C53/20+D53/240
A54: pannage sold wholesale | C54: 17 | F54: =B54+C54/20+D54/240
A55: from the men of Hawkley | C55: 1 | D55: 6 | F55: =B55+C55/20+D55/240
A56: from the pinfold at Michaelmas | C56: 2 | F56: =B56+C56/20+D56/240
A57: from lopping sold | C57: 1 | D57: 7 | F57: =B57+C57/20+D57/240
A58: from 8 oxen sold | B58: 4 | C58: 8 | F58: =B58+C58/20+D58/240
A59: from 6 cows sold | B59: 2 | C59: 6 | F59: =B59+C59/20+D59/240
A60: from 1 feeble cow sold | C60: 5 | F60: =B60+C60/20+D60/240
A61: from 1 steer from a heriot sold | C61: 8 | F61: =B61+C61/20+D61/240
A62: from 17 calves sold | B62: 1 | F62: =B62+C62/20+D62/240
A63: from 39 ewes sold | B63: 1 | C63: 9 | D63: 3 | F63: =B63+C63/20+D63/240
A64: from the hide of 1 ox in murrain | C64: 2 | D64: 2 | F64: =B64+C64/20+D64/240
A65: from the hide of 1 cow in murrain | C65: 1 | D65: 7 | F65: =B65+C65/20+D65/240
A66: from the hides sold of 1 steer and 2 yearlings in murrain | C66: 1 | D66: 7 | F66: =B66+C66/20+D66/240
A67: from the hides of 2 calves in murrain | D67: 2 | F67: =B67+C67/20+D67/240
A68: from the skins sold of 9 ewes | C68: 2 | D68: 3 | F68: =B68+C68/20+D68/240
A69: skins of 2 ewes | D69: 2 | F69: =B69+C69/20+D69/240
A70: from the skins of 34 lambs in murrain | C70: 2 | D70: 10 | F70: =B70+C70/20+D70/240
A71: from 1 wey 6 cloves in winter cheese sold | C71: 11 | F71: =B71+C71/20+D71/240
A72: from 8 weys of cows cheese | B72: 6 | C72: 19 | D72: 6 | F72: =B72+C72/20+D72/240
A73: from 5.5 weys 5 cloves of Burghclere cheese | B73: 2 | C73: 11 | D73: 1 | F73: =B73+C73/20+D73/240
A74: from 1.5 weys 7 colves of butter sold | C74: 15 | D74: 9 | F74: =B74+C74/20+D74/240
A75: from the feathers and tails of peacocks sold | D75: 5 | F75: =B75+C75/20+D75/240
A76: from honey found in the wood sold | C76: 2 | F76: =B76+C76/20+D76/240
A77: from 9 dozen pigeons sold | C77: 2 | D77: 7.5 | F77: =B77+C77/20+D77/240
A78: from 39 cloves 2lb of wool locks sold | C78: 17 | D78: 2 | F78: =B78+C78/20+D78/240
A79: from 64 hens from churchscot sold | C79: 5 | D79: 4 | F79: =B79+C79/20+D79/240
A80: from 1005 eggs sold | C80: 2 | D80: 11 | F80: =B80+C80/20+D80/240
A81: from 3 pigs sold | C81: 11 | F81: =B81+C81/20+D81/240
A82: from the dairy produce of cows | C82: 5 | D82: 3 | F82: =B82+C82/20+D82/240
A83: from the dairy produce of Burghclere ewes sold at audit | C83: 5 | D83: 5.5 | F83: =B83+C83/20+D83/240
A84: Total recorded in accounts | B84: 26 | C84: 9 | D84: 6.5 | F84: =B84+C84/20+D84/240
A85: Issues of the manor total | B85: =SUM(B52:B83) | C85: =SUM(C52:C83) | D85: =SUM(D52:D83) | F85: =B85+C85/20+D85/240 | G85: =F85-F84
A87: Sale of corn
A88: wheat | B88: 7 | C88: 11 | D88: 6 | F88: =B88+C88/20+D88/240
A89: barley | B89: 1 | C89: 13 | F89: =B89+C89/20+D89/240
A90: oats | C90: 12 | D90: 2.25 | F90: =B90+C90/20+D90/240
A91: Total recorded in accounts | B91: 9 | C91: 16 | D91: 8.25 | F91: =B91+C91/20+D91/240
A92: Sale of corn total | B92: =SUM(B88:B90) | C92: =SUM(C88:C91) | D92: =SUM(D88:D90) | F92: =B92+C92/20+D92/240 | G92: =F92-F91
A94: Entry and marriage fines
A95: tithing for tithingpenny | C95: 4 | F95: =B95+C95/20+D95/240
A96: William Yong | C96: 6 | D96: 8 | F96: =B96+C96/20+D96/240
A97: from Aleva Snow | C97: 10 | F97: =B97+C97/20+D97/240
A98: from Matildaatte Den | C98: 1 | F98: =B98+C98/20+D98/240
A99: from Juliana Elys | C99: 1 | F99: =B99+C99/20+D99/240
A100: from Thomas le Pottere | D100: 6 | F100: =B100+C100/20+D100/240
A101: from Richrad Duk | C101: 6 | D101: 8 | F101: =B101+C101/20+D101/240
A102: from John atte Cruch | C102: 2 | F102: =B102+C102/20+D102/240
A103: from John atte Zele | C103: 2 | F103: =B103+C103/20+D103/240
A104: Total recorded in accounts | B104: 1 | C104: 13 | D104: 10 | F104: =B104+C104/20+D104/240
A105: Entry and marriage fines total | B105: =SUM(B95:B103) | C105: =SUM(C95:C104) | D105: =SUM(D95:D103) | F105: =B105+C105/20+D105/240 | G105: =F105-F104
A107: Pleas and perquisites
A108: from the whole tithing because it did not produce in court those it had bailed | C108: 1 | F108: =B108+C108/20+D108/240
A109: from Robert Ely because he is convicted | D109: 6 | F109: =B109+C109/20+D109/240
A110: from John atte Zele for keeping the cows badly | D110: 6 | F110: =B110+C110/20+D110/240
A111: from John Gouham for transgression | D111: 3 | F111: =B111+C111/20+D111/240
...

Sheet Highclere Expenses
A1: Highclere EXPENSES
B2: £ | C2: s | D2: d | F2: Total in £ | G2: Error | H2: Notes
A3: Cost of Ploughs
A4: ironworks for 2 ploughs | C4: 2 | D4: 10 | F4: =B4+C4/20+D4/240
A5: 2 plough irons bought | D5: 7 | F5: =B5+C5/20+D5/240
A6: 1 plougshare bought | D6: 10 | F6: =B6+C6/20+D6/240
A7: mending and fitting the ploughs | D7: 4.5 | F7: =B7+C7/20+D7/240
A8: fitting 1 plough with iron tyres | D8: 2.5 | F8: =B8+C8/20+D8/240
A9: 2 pairs of wheels bought | D9: 8 | F9: =B9+C9/20+D9/240
A10: trimming and treating timber for ploughs | C10: 2 | D10: 1.5 | F10: =B10+C10/20+D10/240
A11: in ploughing boon-works of 15 ploughmen | C11: 5 | F11: =B11+C11/20+D11/240
A12: reward of 3 ploughmen for the year for their Saturday ploughings | C12: 16 | D12: 10.5 | F12: =B12+C12/20+D12/240
A13: in stipend of 1 oxherd for 1.5 terms | D13: 9 | F13: =B13+C13/20+D13/240
A14: in 9 oxen bought for ploughs | B14: 5 | C14: 1 | D14: 3 | F14: =B14+C14/20+D14/240
A15: in wheat bought | B15: 1 | C15: 14 | D15: 4.5 | F15: =B15+C15/20+D15/240
A16: in bere bought for sowing and liveries | B16: 1 | C16: 10 | D16: 8.5 | F16: =B16+C16/20+D16/240
A17: Total recorded in accounts | B17: 9 | C17: 16 | D17: 7 | F17: =B17+C17/20+D17/240
A18: Cost of ploughs total | B18: =SUM(B3:B16) | C18: =SUM(C3:C16) | D18: =SUM(D3:D16) | F18: =B18+C18/20+D18/240 | G18: =F18-F17
A19: Total capital expenses | F19: =F4+F5+F6+F7+F8+F9+F10
A21: Purchase of Corn
F22: =B22+C22/20+D22/240 | H22: for some reason recorded with cost of ploughs
A23: Total recorded in accounts | F23: =B23+C23/20+D23/240
A24: Purchase of corn total | B24: =SUM(B22) | C24: =SUM(C22) | D24: =SUM(D22) | F24: =B24+C24/20+D24/240 | G24: =F24-F23
A26: Cost of Carts and Wagons
A27: clouts, nails, grease and white leather bought and in fitting 3 carts with axles | C27: 1 | D27: 10 | F27: =B27+C27/20+D27/240
A28: in 1 pair of tie-beams | D28: 6 | F28: =B28+C28/20+D28/240
A29: in 1 cart saddle | D29: 4 | F29: =B29+C29/20+D29/240
A30: in 1 pair of traces | D30: 6.5 | F30: =B30+C30/20+D30/240
A31: in 1 cart rope | C31: 1 | D31: 2 | F31: =B31+C31/20+D31/240
A32: in 1 cart-body made anew | D32: 6 | F32: =B32+C32/20+D32/240
A33: in mending the ironwork of the old dung-cart | D33: 3 | F33: =B33+C33/20+D33/240
A34: in 2 halters bought | D34: 4 | F34: =B34+C34/20+D34/240
A35: in shoeing 2 cart-horses | C35: 2 | D35: 2 | F35: =B35+C35/20+D35/240
A36: stipend of 1 carter for the year | C36: 3 | F36: =B36+C36/20+D36/240
A37: Total recorded in accounts | C37: 11 | D37: 2 | F37: =B37+C37/20+D37/240
A38: Cost of carts and wagons total | B38: =SUM(B27:B36) | C38: =SUM(C27:C36) | D38: =SUM(D27:D37) | F38: =B38+C38/20+D38/240 | G38: =F38-F37
A39: Total capital expenses | F39: =F27+F28+F29+F30+F31+F32+F33+F34+F35
A41: Cost of Dairy
A42: linen and woollen cloth | C42: 1 | D42: 2 | F42: =B42+C42/20+D42/240
A43: 1 new bucket | D43: 10.5 | F43: =B43+C43/20+D43/240
A44: earthenware pots and pans | D44: 8 | F44: =B44+C44/20+D44/240
A45: in a press | D45: 6 | F45: =B45+C45/20+D45/240
A46: in 3qrs of salt bought | D46: 7 | F46: =B46+C46/20+D46/240
A47: in stipend of 1 dairymaid | C47: 2 | D47: 4 | F47: =B47+C47/20+D47/240
A48: Total recorded in accounts | C48: 12 | D48: 6.5 | F48: =B48+C48/20+D48/240
A49: Cost of dairy total | B49: =SUM(B42:B47) | C49: =SUM(C42:C47) | D49: =SUM(D42:D48) | F49: =B49+C49/20+D49/240 | G49: =F49-F48
A50: Total capital expenses | F50: =F42+F43+F44+F45+F46
A52: Purchase of Stock
F53: =B53+C53/20+D53/240 | H53: nothing
F54: =B54+C54/20+D54/240
F55: =B55+C55/20+D55/240
A56: Total recorded in accounts | F56: =B56+C56/20+D56/240
A57: Purchase of stock total | B57: =SUM(B53:B55) | C57: =SUM(C53:C55) | D57: =SUM(D53:D55) | F57: =B57+C57/20+D57/240 | G57: =F57-F56
A59: Sheepcote
A60: roofing the sheepcote of Suthdon | C60: 2 | F60: =B60+C60/20+D60/240
A61: collecting 6 acres of stublle for the same | C61: 1 | F61: =B61+C61/20+D61/240
A62: grease bought for greasing the sheep | C62: 12 | F62: =B62+C62/20+D62/240
A63: in stipend of 1 shepherd | D63: 9 | F63: =B63+C63/20+D63/240
A64: in wattling the sheepfold | D64: 5 | F64: =B64+C64/20+D64/240
A65: in 59 ewes bought after shearing | B65: 2 | C65: 18 | F65: =B65+C65/20+D65/240
A66: in 36 ells of canvas bought for putting the coarse wool and lamb's wool in | C66: 9 | D66: 9 | F66: =B66+C66/20+D66/240
A67: in sacks made | D67: 6 | F67: =B67+C67/20+D67/240
A68: in packing and treating the wool | C68: 1 | D68: 4 | F68: =B68+C68/20+D68/240
A69: Total recorded in accounts | B69: 4 | C69: 5 | D69: 9 | F69: =B69+C69/20+D69/240
A70: Sheepcote total | B70: =SUM(B60:B67) | C70: =SUM(C60:C67) | D70: =SUM(D60:D69) | F70: =B70+C70/20+D70/240 | G70: =F70-F69
A71: Total capital expenses | F71: =SUM(F60:F64)+F66+F67
A73: Cost of Buildings
A74: in re-roofing the unroofed barn | C74: 2 | D74: 6 | F74: =B74+C74/20+D74/240
A75: in collecting 12 acres of stubble for the same | C75: 2 | F75: =B75+C75/20+D75/240
A76: roofing the kitchen, dairy, larder | C76: 1 | D76: 3 | F76: =B76+C76/20+D76/240
A77: mending the walls of the small barn | C77: 1 | F77: =B77+C77/20+D77/240
A78: in hooks and hinges | C78: 1 | D78: 1.5 | F78: =B78+C78/20+D78/240
A79: carpenter rebuilding a part of the long chamber | C79: 3 | D79: 4 | F79: =B79+C79/20+D79/240
A80: laying 4000 tiles on the same | C80: 2 | F80: =B80+C80/20+D80/240
A81: in pegs bought for the same | D81: 4 | F81: =B81+C81/20+D81/240
A82: 1500 nails bought for laths | C82: 1 | D82: 0.75 | F82: =B82+C82/20+D82/240
A83: 100 large nails bought for the chamber | D83: 3 | F83: =B83+C83/20+D83/240
A84: carpenter making 1 new leaf for the outside gate and mending the same gate | C84: 3 | F84: =B84+C84/20+D84/240
A85: hooks, hinges, nails for the same | C85: 2 | F85: =B85+C85/20+D85/240
A86: 1 new lock for the cemetary gate and wicket gate, and mending the lock on the great gate | C86: 1 | F86: =B86+C86/20+D86/240
A87: repairing and restoring 2 broken glass windows in the lord's chapel | C87: 1 | D87: 6 | F87: =B87+C87/20+D87/240
A88: in ironwork bought for the same | D88: 6 | F88: =B88+C88/20+D88/240
A89: stipend of 1 carpenter rebuilding the gutter betwen the hall and lord's chamber | C89: 2 | D89: 6 | F89: =B89+C89/20+D89/240
A90: nails bought | D90: 4 | F90: =B90+C90/20+D90/240
A91: lead bought | B91: 1 | C91: 1 | D91: 6 | F91: =B91+C91/20+D91/240
A92: stipend of the plumber smelting the said lead and laying it on the aforesaid gutter | C92: 2 | D92: 6 | F92: =B92+C92/20+D92/240
A93: 1500 slates bought for roofing the oriel of the chapel | C93: 2 | F93: =B93+C93/20+D93/240
A94: roofing and mending the hall, lord's chamber and chapel | C94: 3 | D94: 8 | F94: =B94+C94/20+D94/240
A95: 7000 tiles and 8qrs of lime | C95: 8 | D95: 7 | F95: =B95+C95/20+D95/240
A96: making 100 ridge-tiles | C96: 1 | D96: 1 | F96: =B96+C96/20+D96/240
A97: 1 rope for the well | C97: 8 | D97: 4 | F97: =B97+C97/20+D97/240
A98: hay and forage bought | B98: 1 | C98: 5 | D98: 2 | F98: =B98+C98/20+D98/240
A99: 1 lock bought for the door to the forage-shed | D99: 8 | F99: =B99+C99/20+D99/240
A100: 3 pigs bought | C100: 7 | D100: 4 | F100: =B100+C100/20+D100/240
A101: 2 casks bought | D101: 6 | F101: =B101+C101/20+D101/240
A102: hooping and mending the casks | C102: 1 | D102: 6 | F102: =B102+C102/20+D102/240
A103: Total recorded in accounts | B103: 5 | C103: 19 | D103: 2.25 | F103: =B103+C103/20+D103/240
A104: Cost of buildings total | B104: =SUM(B74:B102) | C104: =SUM(C74:C103) | D104: =SUM(D74:D103) | F104: =B104+C104/20+D104/240 | G104: =F104-F103
A105: Total capital expenses | F105: =F74+F75+F76+F77+F78+F79+F80+F81+F82+F83+F84+F85+F86+F87+F88+F89+F90+F91+F92+F93+F94+F95+F96+F97+F99+F101+F102
A106: Total demesne capital expenses | F106: =F74+F75+F76+F77+F78+F84+F85+F97+F99+F101+F102
...

Sheet Issues of the Grange
B1: The issue of the grange account gives the total "yield" at the top of each heading in curly brackets, measurements used: fold, qrs, bus
B2: In "Issues of the grange" (p.xx) | G2: In "Sale of Corn" (p.x) | P2: Value of Total Production
A3: Gross output | B3: Quantity | D3: Additional bought-in | F3: Quantity | G3: Quantity noted as sold | J3: Difference Produced vs. Sold | K3: Price 1 | L3: Quantity 1 | M3: Price 2 | N3: Quantity 2 | O3: Unit price | P3: Value
B4: qrs | C4: bus | D4: qrs | E4: bus | F4: qrs | G4: qrs | H4: bus | I4: qrs | K4: £ | L4: qrs | M4: £ | N4: qrs | O4: £ per qr | P4: £
A5: Wheat | B5: =27+1 | C5: 6 | D5: 6.5 | E5: 3 | F5: =B5+D5+C5/8+E5/8 | G5: 25 | H5: 2 | I5: =G5+H5/8 | J5: =F5-I5 | K5: =6/20 | L5: 1 | O5: =IFERROR((K5+M5)/(L5+N5),0) | P5: =O5*F5
A6: Bere | B6: 17 | C6: 1 | D6: 10 | E6: =6+4 | F6: =B6+D6+C6/8+E6/8 | I6: =G6+H6/8 | J6: =F6-I6 | O6: =IFERROR((K6+M6)/(L6+N6),0) | Q6: not feasible to estimate because no sales prices
A7: Curall | F7: =B7+D7+C7/8+E7/8 | I7: =G7+H7/8 | J7: =F7-I7 | O7: =IFERROR((K7+M7)/(L7+N7),0) | P7: =O7*F7
A8: Barley | B8: 15 | F8: =B8+D8+C8/8+E8/8 | G8: 8 | H8: 2 | I8: =G8+H8/8 | J8: =F8-I8 | K8: =4/20 | L8: 1 | O8: =IFERROR((K8+M8)/(L8+N8),0) | P8: =O8*F8
A9: Oats | B9: 43 | C9: 0.5 | F9: =B9+D9+C9/8+E9/8 | G9: 4 | H9: 7 | I9: =G9+H9/8 | J9: =F9-I9 | K9: =2/20+6/240 | L9: 1 | O9: =IFERROR((K9+M9)/(L9+N9),0) | P9: =O9*F9
A10: Peas | D10: 0.5 | F10: =B10+D10+C10/8+E10/8 | I10: =G10+H10/8 | J10: =F10-I10 | O10: =IFERROR((K10+M10)/(L10+N10),0) | P10: =O10*F10
A11: Vetches | F11: =B11+D11+C11/8+E11/8 | I11: =G11+H11/8 | J11: =F11-I11 | O11: =IFERROR((K11+M11)/(L11+N11),0) | P11: =O11*F11
A13: Total Production | F13: =SUM(F5:F11) | P13: =SUM(P5:P11) | Q13: Production value is significantly more, as much less was sold than what was produced
A14: Sales of corn (as recorded in accounts) | F14: =SUM(I5:I11) | P14: =(O5*I5)+(O8*I8)+(O9*I9)
A17: Net output | B17: Gross output | C17: Seed | F17: tithe | G17: to manorial servants & livestock | J17: Output net of tithe & seed & liveries to manorial servants | K17: in stock from last year | L17: Price | M17: Value of net output | N17: Value of sales (in "Sale of Corn")
B18: qrs | C18: qrs | D18: bus | E18: qrs | F18: qrs | G18: qrs | H18: bus | I18: qrs | J18: qrs | K18: qrs | L18: £ per qr | M18: £ | N18: £
A19: Net wheat | B19: =F5 | C19: 8 | D19: =3+5 | E19: =C19+D19/8 | G19: =1 | H19: =1+2 | I19: =G19+H19/8 | J19: =B19-(E19+F19+I19) | L19: =O5 | M19: =L19*J19 | N19: =O5*I5
A20: Net bere | B20: =F6 | C20: 15 | D20: 1 | E20: =C20+D20/8 | G20: =5+2+1+4 | H20: =0.5+1+6+2.5 | I20: =G20+H20/8 | J20: =B20-(E20+F20+I20)
A21: Net curall | B21: =F7 | E21: =C21+D21/8 | I21: =G21+H21/8 | J21: =B21-(E21+F21+I21) | L21: =O7 | M21: =L21*J21 | N21: =O7*I7
A22: Net barley | B22: =F8 | C22: 6 | D22: 5 | E22: =C22+D22/8 | I22: =G22+H22/8 | J22: =B22-(E22+F22+I22) | L22: =O8 | M22: =L22*J22 | N22: =O8*I8
A23: Net oats | B23: =F9 | C23: 21 | D23: 1 | E23: =C23+D23/8 | G23: =7+8+1 | H23: =1+5+2+0.5 | I23: =G23+H23/8 | J23: =B23-(E23+F23+I23) | L23: =O9 | M23: =L23*J23 | N23: =O9*I9
A24: Net peas | B24: =F10 | D24: 2 | E24: =C24+D24/8 | H24: 2 | I24: =G24+H24/8 | J24: =B24-(E24+F24+I24) | L24: =O10 | M24: =L24*J24 | N24: =O10*I10
A25: Net vetches | B25: =F11 | E25: =C25+D25/8 | I25: =G25+H25/8 | J25: =B25-(E25+F25+I25) | L25: =O11 | M25: =L25*J25 | N25: =O11*I11
A26: Total | B26: =SUM(B19:B25) | E26: =SUM(E19:E25) | J26: =SUM(J19:J25) | M26: =SUM(M19:M25) | N26: =SUM(N19:N25)

Sheet Stock
A1: EAST KNOYLE STOCK ACCOUNT
A3: Livestock | B3: Inherited stock | C3: Bought | D3: Produced | E3: received fromother manors | F3: strays/heriot | G3: herbage | H3: sold | I3: in murrain | J3: accounted for elsewhere | K3: End-period stock | L3: cross-check | M3: price 1 | N3: units 1 | O3: price 2 | P3: units 2 | Q3: Weight (weys) | R3: Unit price (£) | S3: Value of production (£) at sales prices | T3: Sales in (£) | U3: Details
A4: Cart-horses | B4: 2 | K4: 2 | L4: =B4+C4+D4+F4-G4-H4-I4-J4 | R4: =IFERROR((M4+O4)/(N4+P4),"") | S4: =IFERROR(D4*R4,"") | T4: =IFERROR(R4*H4,"")
A5: Mares | L5: =B5+C5+D5+F5-G5-H5-I5-J5 | R5: =IFERROR((M5+O5)/(N5+P5),"") | S5: =IFERROR(D5*R5,"") | T5: =IFERROR(R5*H5,"")
A6: Plough horses | L6: =B6+C6+D6+F6-G6-H6-I6-J6 | R6: =IFERROR((M6+O6)/(N6+P6),"") | S6: =IFERROR(D6*R6,"") | T6: =IFERROR(R6*H6,"")
A7: Colts (2 years) | L7: =B7+C7+D7+F7-G7-H7-I7-J7 | R7: =IFERROR((M7+O7)/(N7+P7),"") | S7: =IFERROR(D7*R7,"") | T7: =IFERROR(R7*H7,"")
A8: Colts (2 years) | L8: =B8+C8+D8+F8-G8-H8-I8-J8 | R8: =IFERROR((M8+O8)/(N8+P8),"") | S8: =IFERROR(D8*R8,"") | T8: =IFERROR(R8*H8,"")
A9: Colts (1 year) | L9: =B9+C9+D9+F9-G9-H9-I9-J9 | R9: =IFERROR((M9+O9)/(N9+P9),"") | S9: =IFERROR(D9*R9,"") | T9: =IFERROR(R9*H9,"")
A10: Foals | L10: =B10+C10+D10+F10-G10-H10-I10-J10 | R10: =IFERROR((M10+O10)/(N10+P10),"") | S10: =IFERROR(D10*R10,"") | T10: =IFERROR(R10*H10,"")
A11: Oxen | B11: 21 | C11: 9 | H11: 8 | I11: 1 | J11: 3 | K11: 18 | L11: =B11+C11+D11+F11-G11-H11-I11-J11 | R11: =T11/H11 | S11: =D11*R11 | T11: ='Highclere Receipts'!F58
A12: Bulls | B12: 1 | D12: 1 | K12: 2 | L12: =B12+C12+D12+F12-G12-H12-I12-J12 | S12: =D12*R12 | T12: =IFERROR(R12*H12,"")
A13: Cows | B13: 50 | D13: 1 | H13: 7 | I13: 1 | K13: 43 | L13: =B13+C13+D13+F13-G13-H13-I13-J13 | R13: =T13/H13 | S13: =D13*R13 | T13: ='Highclere Receipts'!F59+('Highclere Receipts'!F60)
A14: Steers | B14: 4 | F14: 1 | H14: 1 | I14: 1 | J14: =1+1+1 | K14: 0 | L14: =B14+C14+D14+F14-G14-H14-I14-J14 | R14: =T14/H14 | S14: =D14*R14 | T14: ='Highclere Receipts'!F61
A15: Bullocks | B15: 15 | J15: 4 | K15: 11 | L15: =B15+C15+D15+F15-G15-H15-I15-J15 | S15: =D15*R15 | T15: =IFERROR(R15*H15,"")
A16: Yearlings | B16: 18 | I16: 2 | K16: 16 | L16: =B16+C16+D16+F16-G16-H16-I16-J16 | S16: =D16*R16 | T16: =IFERROR(R16*H16,"")
A17: Calves | D17: 36 | H17: =7+17 | I17: =1+2 | J17: =1+3 | K17: 14 | L17: =B17+C17+D17+F17-G17-H17-I17-J17 | R17: =T17/17 | S17: =D17*R17 | T17: ='Highclere Receipts'!F62 | U17: accounting does not add up, sales only record 17 sales
A18: Wethers | L18: =B18+C18+D18+F18-G18-H18-I18-J18 | S18: =D18*R18 | T18: =IFERROR(R18*H18,"")
A19: Rams | B19: 15 | I19: 1 | J19: 4 | K19: 10 | L19: =B19+C19+D19+F19-G19-H19-I19-J19 | S19: =D19*R19 | T19: =IFERROR(R19*H19,"")
A20: Ewes | B20: 383 | C20: 59 | D20: 48 | H20: 39 | I20: =6+3+2 | J20: 1 | K20: 449 | L20: =B20+C20+D20+F20-G20-H20-I20-J20 | R20: =T20/H20 | S20: =D20*R20 | T20: ='Highclere Receipts'!F63
A21: Hoggs | L21: =B21+C21+D21+F21-G21-H21-I21-J21 | S21: =D21*R21 | T21: =IFERROR(R21*H21,"")
A22: Lambs | D22: 324 | I22: =37 | J22: =28+4+225 | K22: 0 | L22: =B22+C22+D22+F22-G22-H22-I22-J22 | S22: =D22*R22 | T22: =IFERROR(R22*H22,"")
A23: Boars | L23: =B23+C23+D23+F23-G23-H23-I23-J23 | S23: =D23*R23 | T23: =IFERROR(R23*H23,"")
A24: Sows | L24: =B24+C24+D24+F24-G24-H24-I24-J24 | S24: =D24*R24 | T24: =IFERROR(R24*H24,"")
A25: Pigs | C25: 3 | H25: 3 | K25: 0 | L25: =B25+C25+D25+F25-G25-H25-I25-J25 | R25: =T25/H25 | S25: =D25*R25 | T25: ='Highclere Receipts'!F81
A26: Hoggets | L26: =B26+C26+D26+F26-G26-H26-I26-J26 | S26: =D26*R26 | T26: =IFERROR(R26*H26,"")
A27: Piglets | L27: =B27+C27+D27+F27-G27-H27-I27-J27 | R27: =IFERROR((M27+O27)/(N27+P27),"") | T27: =IFERROR(R27*H27,"")
A28: Swans | L28: =B28+C28+D28+F28-G28-H28-I28-J28 | R28: =IFERROR((M28+O28)/(N28+P28),"") | T28: =IFERROR(R28*H28,"")
A29: Peacocks | B29: 15 | I29: 2 | J29: 6 | K29: 7 | L29: =B29+C29+D29+F29-G29-H29-I29-J29 | R29: =IFERROR((M29+O29)/(N29+P29),"") | T29: =IFERROR(R29*H29,"")
A30: Total | L30: =B30+C30+D30+F30-G30-H30-I30-J30 | R30: =IFERROR((M30+O30)/(N30+P30),"") | S30: =SUM(S11:S26) | T30: =SUM(T4:T29)
R31: =IFERROR((M31+O31)/(N31+P31),"") | T31: =IFERROR(R31*H31,"")
A32: Wool | R32: =IFERROR((M32+O32)/(N32+P32),"") | T32: =IFERROR(R32*H32,"")
A33: Fleeces | L33: =B33+C33+D33+F33-G33-H33-I33-J33 | R33: =IFERROR((M33+O33)/(N33+P33),"") | T33: =IFERROR(R33*H33,"")
A34: Coarse wool | D34: =335+10 | E34: =237+570+320 | J34: =34+1+1437 | K34: 0 | L34: =B34+C34+D34+F34+E34-G34-H34-I34-J34 | R34: 0.02 | S34: =R34*J34 | T34: =IFERROR(R34*H34,"")
A35: Lamb's wool | E35: =243+249 | J35: =243+249 | K35: 0 | L35: =B35+C35+D35+F35+E35-G35-H35-I35-J35 | R35: 0.01 | S35: =R35*J35 | T35: =IFERROR(R35*H35,"")
A36: Wool locks | L36: =B36+C36+D36+F36+E36-G36-H36-I36-J36 | R36: =IFERROR((M36+O36)/(N36+P36),"") | T36: ='Highclere Receipts'!F78 | U36: no woollocks in stock account but they appear as being sold in receipts
A37: Wool sold at shearing | L37: =B37+C37+D37+F37+E37-G37-H37-I37-J37 | R37: =IFERROR((M37+O37)/(N37+P37),"") | T37: =IFERROR(R37*H37,"")
A38: Total | L38: =B38+C38+D38+F38+E38-G38-H38-I38-J38 | R38: =IFERROR((M38+O38)/(N38+P38),"") | S38: =S34+S35+T36 | T38: =SUM(T33:T37)
R39: =IFERROR((M39+O39)/(N39+P39),"") | T39: =IFERROR(R39*H39,"")
R40: =IFERROR((M40+O40)/(N40+P40),"") | T40: =IFERROR(R40*H40,"")
A41: Hides | R41: =IFERROR((M41+O41)/(N41+P41),"") | T41: =IFERROR(R41*H41,"")
A42: Ox hides | D42: 1 | H42: 1 | K42: 0 | L42: =B42+C42+D42+F42-G42-H42-I42-J42 | R42: =T42/H42 | S42: =D42*R42 | T42: ='Highclere Receipts'!F64
A43: Cow hides | D43: 1 | H43: 1 | K43: 0 | L43: =B43+C43+D43+F43-G43-H43-I43-J43 | R43: =T43/H43 | S43: =D43*R43 | T43: ='Highclere Receipts'!F65
A44: Mare hides | L44: =B44+C44+D44+F44-G44-H44-I44-J44 | R44: =IFERROR(D44*#REF!,"") | T44: =IFERROR(#REF!*H44,"")
A45: Steer hides | D45: 1 | H45: 1 | K45: 0 | L45: =B45+C45+D45+F45-G45-H45-I45-J45 | R45: =T45/(H45+H46) | S45: =D45*R45 | T45: ='Highclere Receipts'!F66 | U45: this is for the yearling and steer hides together
A46: Yearling hides | D46: 2 | H46: 2 | K46: 0 | L46: =B46+C46+D46+F46-G46-H46-I46-J46 | R46: =R45 | S46: =D46*R46 | T46: =IFERROR(#REF!*H46,"")
A47: Calf hides | D47: 2 | H47: 2 | K47: 0 | L47: =B47+C47+D47+F47-G47-H47-I47-J47 | R47: =T47/H47 | S47: =D47*R47 | T47: ='Highclere Receipts'!F67
A48: Pig hides | L48: =B48+C48+D48+F48-G48-H48-I48-J48 | R48: =IFERROR((M48+O48)/(N48+P48),"") | T48: =IFERROR(R48*H48,"")
A49: Weather woolskins | L49: =B49+C49+D49+F49-G49-H49-I49-J49 | R49: =IFERROR((M49+O49)/(N49+P49),"") | T49: =IFERROR(R49*H49,"")
A50: Ram woolskins | L50: =B50+C50+D50+F50-G50-H50-I50-J50 | R50: =IFERROR((M50+O50)/(N50+P50),"") | T50: =IFERROR(R50*H50,"")
A51: Ewe woolskins | L51: =B51+C51+D51+F51-G51-H51-I51-J51 | R51: =IFERROR((M51+O51)/(N51+P51),"") | T51: =IFERROR(R51*H51,"")
A52: Hogg woolskins | L52: =B52+C52+D52+F52-G52-H52-I52-J52 | R52: =IFERROR((M52+O52)/(N52+P52),"") | T52: =IFERROR(R52*H52,"")
A53: Woolskins (total) | L53: =B53+C53+D53+F53-G53-H53-I53-J53 | R53: =IFERROR((M53+O53)/(N53+P53),"") | T53: =IFERROR(R53*H53,"")
A54: Wether bareskins | L54: =B54+C54+D54+F54-G54-H54-I54-J54 | R54: =IFERROR((M54+O54)/(N54+P54),"") | T54: =IFERROR(R54*H54,"")
A55: Ram bareskins | D55: 1 | J55: 1 | K55: 0 | L55: =B55+C55+D55+F55-G55-H55-I55-J55 | R55: =IFERROR((M55+O55)/(N55+P55),"") | T55: =IFERROR(R55*H55,"")
A56: Ewe bareskins | D56: 9 | H56: 9 | L56: =B56+C56+D56+F56-G56-H56-I56-J56 | R56: =T56/H56 | S56: =D56*R56 | T56: ='Highclere Receipts'!F68
A57: Hogg bareskins | L57: =B57+C57+D57+F57-G57-H57-I57-J57 | R57: =IFERROR(D57*#REF!,"") | T57: =IFERROR(#REF!*H57,"")
A58: Bareskins (total) | D58: 2 | H58: 2 | L58: =B58+C58+D58+F58-G58-H58-I58-J58 | R58: =T58/H58 | S58: =D58*R58 | T58: ='Highclere Receipts'!F69
A59: Lambskins | D59: 37 | H59: 34 | J59: 3 | K59: 0 | L59: =B59+C59+D59+F59-G59-H59-I59-J59 | R59: =T59/H59 | S59: =D59*R59 | T59: ='Highclere Receipts'!F70
A60: Rotted skins | L60: =B60+C60+D60+F60-G60-H60-I60-J60 | R60: =IFERROR((M60+O60)/(N60+P60),"") | S60: =IFERROR(D60*R60,"") | T60: =IFERROR(R60*H60,"")
A61: Shorn skins | L61: =B61+C61+D61+F61-G61-H61-I61-J61 | R61: =IFERROR((M61+O61)/(N61+P61),"") | S61: =IFERROR(D61*R61,"") | T61: =IFERROR(R61*H61,"")
A62: Total | L62: =B62+C62+D62+F62-G62-H62-I62-J62 | R62: =IFERROR((M62+O62)/(N62+P62),"") | S62: =SUM(S42:S61) | T62: =SUM(T42:T61)
R63: =IFERROR((M63+O63)/(N63+P63),"") | S63: =IFERROR(D63*R63,"") | T63: =IFERROR(R63*H63,"")
A64: Poultry stock | R64: =IFERROR((M64+O64)/(N64+P64),"") | S64: =IFERROR(D64*R64,"") | T64: =IFERROR(R64*H64,"")
A65: Hens | L65: =B65+C65+D65+F65-G65-H65-I65-J65 | R65: =IFERROR((M65+O65)/(N65+P65),"") | S65: =IFERROR(D65*R65,"") | T65: =IFERROR(R65*H65,"")
A66: Geese | L66: =B66+C66+D66+F66-G66-H66-I66-J66 | R66: =IFERROR((M66+O66)/(N66+P66),"") | S66: =IFERROR(D66*R66,"") | T66: =IFERROR(R66*H66,"")
A67: Capons (from chickens) | L67: =B67+C67+D67+F67-G67-H67-I67-J67 | R67: =IFERROR((M67+O67)/(N67+P67),"") | S67: =IFERROR(D67*R67,"") | T67: =IFERROR(R67*H67,"")
A68: Cocks & hens | L68: =B68+C68+D68+F68-G68-H68-I68-J68 | R68: =IFERROR((M68+O68)/(N68+P68),"") | S68: =IFERROR(D68*R68,"") | T68: =IFERROR(R68*H68,"")
A69: Total | L69: =B69+C69+D69+F69-G69-H69-I69-J69 | R69: =IFERROR((M69+O69)/(N69+P69),"") | S69: =IFERROR(D69*R69,"") | T69: =IFERROR(R69*H69,"")
R70: =IFERROR((M70+O70)/(N70+P70),"") | S70: =IFERROR(D70*R70,"") | T70: =IFERROR(R70*H70,"")
A71: Poultry production | R71: =IFERROR((M71+O71)/(N71+P71),"") | S71: =IFERROR(D71*R71,"") | T71: =IFERROR(R71*H71,"")
A72: Eggs | D72: 1005 | H72: 1005 | L72: =B72+C72+D72+F72-G72-H72-I72-J72 | R72: =T72/H72 | S72: =R72*D72 | T72: ='Highclere Receipts'!F80
A73: Cocks & hens from churchscot of customary tenants | B73: =20+60 | H73: 64 | J73: =8+2+2+2+2 | K73: 0 | L73: =B73+C73+D73+F73-G73-H73-I73-J73 | R73: =T73/H73 | S73: =R73*D73 | T73: ='Highclere Receipts'!F79
A74: Total | L74: =B74+C74+D74+F74-G74-H74-I74-J74 | R74: =IFERROR((M74+O74)/(N74+P74),"") | T74: =SUM(T72:T73)
R75: =IFERROR((M75+O75)/(N75+P75),"") | S75: =IFERROR(D75*R75,"") | T75: =IFERROR(R75*H75,"")
A76: Meat | R76: =IFERROR((M76+O76)/(N76+P76),"") | S76: =IFERROR(D76*R76,"") | T76: =IFERROR(R76*H76,"")
A77: Beef | L77: =B77+C77+D77+F77-G77-H77-I77-J77 | R77: =IFERROR((M77+O77)/(N77+P77),"") | S77: =IFERROR(D77*R77,"") | T77: =IFERROR(R77*H77,"")
A78: Mutton | L78: =B78+C78+D78+F78-G78-H78-I78-J78 | R78: =IFERROR((M78+O78)/(N78+P78),"") | S78: =IFERROR(D78*R78,"") | T78: =IFERROR(R78*H78,"")
A79: Pork | L79: =B79+C79+D79+F79-G79-H79-I79-J79 | R79: =IFERROR((M79+O79)/(N79+P79),"") | S79: =IFERROR(D79*R79,"") | T79: =IFERROR(R79*H79,"")
A82: Cheese | L82: =B82+C82+D82+F82-G82-H82-I82-J82 | R82: =IFERROR((M82+O82)/(N82+P82),"") | S82: =IFERROR(D82*R82,"") | T82: =IFERROR(R82*H82,"")
A83: Winter cheese | D83: =25+6 | H83: 31 | K83: 0 | L83: =B83+C83+D83+F83-G83-H83-I83-J83 | Q83: =1+6/25 | R83: =IFERROR((M83+O83)/(N83+P83),"") | T83: ='Highclere Receipts'!F82 | U83: sale is for all dairy except Burghclere, unit prices not determined because of measurement, wey = 25 cloves as noted in assumptions
A84: Summer cheese | D84: 162 | H84: 141 | J84: =16+1+3+1 | K84: 0 | L84: =B84+C84+D84+F84-G84-H84-I84-J84 | R84: =IFERROR((M84+O84)/(N84+P84),"") | S84: =IFERROR(D84*R84,"") | T84: =IFERROR(R84*H84,"")
A85: Burghclere cheese | D85: 169 | H85: 148 | J85: =17+3+1 | K85: 0 | L85: =B85+C85+D85+F85-G85-H85-I85-J85 | R85: =T85/H85 | S85: =R85*D85 | T85: ='Highclere Receipts'!F83
A86: Total | S86: =S85+T83 | T86: =SUM(T83:T85)
A88: Butter | L88: =B88+C88+D88+F88-G88-H88-I88-J88 | R88: =IFERROR((M88+O88)/(N88+P88),"") | S88: =IFERROR(D88*R88,"") | T88: =IFERROR(R88*H88,"")
A89: Butter | D89: =25+25/2+7 | H89: 44.5 | L89: =B89+C89+D89+F89-G89-H89-I89-J89 | R89: =IFERROR((M89+O89)/(N89+P89),"") | S89: =IFERROR(D89*R89,"") | T89: =IFERROR(R89*H89,"")
A91: Cider | L91: =B91+C91+D91+F91-G91-H91-I91-J91 | R91: =IFERROR((M91+O91)/(N91+P91),"") | S91: =IFERROR(D91*R91,"") | T91: =IFERROR(R91*H91,"")
A92: Casks | D92: 2 | K92: 2 | L92: =B92+C92+D92+F92-G92-H92-I92-J92 | R92: =IFERROR((M92+O92)/(N92+P92),"") | S92: =IFERROR(D92*R92,"")
L93: =B93+C93+D93+F93-G93-H93-I93-J93 | R93: =IFERROR((M93+O93)/(N93+P93),"") | S93: =IFERROR(D93*R93,"") | T93: =IFERROR(R93*H93,"")
R94: =IFERROR((M94+O94)/(N94+P94),"") | S94: =IFERROR(D94*R94,"") | T94: =IFERROR(R94*H94,"")
R95: =IFERROR((M95+O95)/(N95+P95),"") | S95: =IFERROR(D95*R95,"") | T95: =IFERROR(R95*H95,"")
R96: =IFERROR((M96+O96)/(N96+P96),"") | S96: =IFERROR(D96*R96,"") | T96: =IFERROR(R96*H96,"")

Sheet Assumptions
A1: ASSUMPTIONS
B3: Weights | C3: Value (in lbs) | D3: Value (in cloves) | E3: Value (in weys) | F3: Value (in stone)
B4: Lbs | C4: 1 | D4: =C4/C5 | E4: =C4/C6 | F4: =C4/C7
B5: Cloves | C5: 7 | D5: 1 | E5: =C5/C6 | F5: =C7/C5
B6: Wey | C6: 175 | D6: =C6/C5 | E6: =C6/C6 | F6: =C7/C6
B7: Stone | C7: =175/14 | D7: =C5/C7 | E7: =C7/C6 | F7: 1
