Workbook

Sheet Ivinghoe Overview - Completed
A1: IVINGHOE OVERVIEW - COMPLETED | B1: Total in £ | C1: Error | D1: Note
A2: CASH ACCOUNT
A3: RECEIPTS
A4: Arrears total | B4: 4.5
A5: Rents of assize total | B5: 25.96
A6: Quittances total | B6: 2.29
A7: Defaults of rent total | B7: 0.9
A8: Defaults of rent through the pestilence total
A9: Cotlands defaults total
A10: Cotlands total
A11: Total of quittances and defaults of rent total | B11: 3.2
A12: Total of rents remaining clear total
A13: Farms total
A14: Annual recognizances total | B14: 0.17
A15: Issues of the Manor total | B15: 12.75
A16: Issues of the tenements in the lord's hands total
A17: Sale of labour services total
A18: Sale of corn total
A19: Entry and marriage fines total | B19: 9.18
A20: Pleas & perquisites total
A21: Forfeited chattels total
A22: Farm of the demesne land total
A23: Total of all receipts (calculated here) | B23: =SUM(B5:B22)
A24: Total of all receipts (calculated here) incl arrears | B24: =SUM(B4:B22)
A25: Total recorded in the accounts excl. arrears | B25: 125.81 | C25: =B23-B25
A26: Total recorded in the accounts incl. arrears | B26: =B25+B4
A29: EXPENSES
A30: Cost of ploughs total
A31: Purchase of corn total
A32: Cost of carts and wagons total
A33: Cost of dairy total
A34: Purchase of stock total | B34: 2.43
A35: Sheepcote total
A36: Cost of buildings total
A37: Threshing total | B37: 1.85
A38: Barley expenses
A39: Expenses of the harvest total
A40: Necessary expenses
A41: Wages of the bailiff
A42: Steward's expenses total | B42: 1.1941667
A43: Annual fees
A44: Total of all expenses per account | B44: 31.64
A45: Total of all expenses (calculated here) | B45: 26.7625
A46: Total fixed investment | B46: 2.3383333
A47: Total Demesne fixed investment | B47: 1.9033333
A49: Owed by the reeve | B49: =B23-B45
A50: From accounts | B50: 31.64
A52: Allowances
A53: Cash deliveries | B53: 80
A54: Sum of the above | B54: =SUM(B52:B53)
A55: Total of all allowances and cash deliveries in accounts
A57: Net amount owed | B57: =B50-B54
A58: Net amount owed in accounts
A60: GRANGE ACCOUNT | B60: Total Production | D60: Value of total gross production in £ | E60: Value of total net production in £
A61: Grange | B61: qrs | C61: bus
A62: Wheat | B62: 220.375 | E62: 43.8125
A63: Rye
A64: Dredge
A65: Curall | B65: 10.375 | E65: 0
A66: Barley | B66: 74 | E66: 1.7395833
A67: Oats | B67: 216.25 | E67: 9.0324937
A68: Beans | B68: 20.125
A69: Peas
A70: Vetches
A71: Total value of gross production (sum of the above)
A72: Total value of net production
A73: Value of sales
A75: MILL ACCOUNT | B75: Total Production | D75: Total in £
A76: Issues of the mill | B76: qrs | C76: bus
A77: Wheat
A78: Oatmeal
A79: 1st grade malt
A80: 2nd grade malt
A81: Maslin
A82: Total value of production (sum of the above)
A83: Value of sales
A85: STOCK ACCOUNT
A86: Livestock | B86: Begin stock | C86: End stock | D86: Stockbuilding | F86: Value of stock in £ | G86: Value of stockbuilding
A87: Cart-horses | B87: 2 | C87: 2 | D87: 0 | F87: ='Stock'!K5*'Stock'!O5 | G87: =D87*'Stock'!O5
A88: Mares | D88: =C88-B88 | F88: ='Stock'!K6*'Stock'!O6 | G88: =D88*'Stock'!O6
A89: Plough horses | B89: 10 | C89: 4 | D89: -6 | F89: 0.76666667 | G89: -1.15
A90: Colts (2 years) | D90: =C90-B90 | F90: ='Stock'!K9*'Stock'!O9 | G90: =D90*'Stock'!O9
A91: Colts (2 years) | D91: =C91-B91 | F91: ='Stock'!K9*'Stock'!O9 | G91: =D91*'Stock'!O9
A92: Colts (1 year) | D92: =C92-B92 | F92: ='Stock'!K10*'Stock'!O10 | G92: =D92*'Stock'!O10
A93: Foals | D93: =C93-B93 | F93: ='Stock'!K11*'Stock'!O11 | G93: =D93*'Stock'!O11
A94: Oxen | B94: 32 | C94: 42 | D94: 10 | F94: 20.79 | G94: 4.95
A95: Bulls | B95: 2 | C95: 1 | D95: -1 | F95: 0.55 | G95: -0.55
A96: Cows | B96: 22 | C96: 24 | D96: 2 | F96: 8.52 | G96: 0.71
A97: Steers | B97: 8 | C97: 0 | D97: -8 | F97: 0 | G97: -1.6
A98: Bullocks | B98: 3 | C98: 3 | D98: 0 | F98: ='Stock'!K16*'Stock'!O16 | G98: =D98*'Stock'!O16
A99: Yearlings | B99: 5 | C99: 3 | D99: -2 | F99: ='Stock'!K17*'Stock'!O17 | G99: =D99*'Stock'!O17
A100: Calves | C100: 6 | D100: =C100-B100 | F100: 0.25384615 | G100: =D100*'Stock'!O18
A101: Wethers | B101: 175 | C101: 97 | D101: -78 | F101: 4.304375 | G101: -3.46125
A102: Rams | D102: =C102-B102 | F102: ='Stock'!K20*'Stock'!O20 | G102: =D102*'Stock'!O20
A103: Ewes | B103: 85 | C103: 54 | D103: -31 | F103: ='Stock'!K21*'Stock'!O21 | G103: =D103*'Stock'!O21
A104: Hoggs | B104: 56 | C104: 0 | D104: -56 | F104: ='Stock'!K22*'Stock'!O22 | G104: =D104*'Stock'!O22
A105: Lambs | C105: 26 | D105: =C105-B105 | F105: 0.13 | G105: =D105*'Stock'!O23
A106: Boars | B106: 1 | C106: 1 | D106: 0 | F106: ='Stock'!K24*'Stock'!O24 | G106: =D106*'Stock'!O24
A107: Sows | B107: 2 | C107: 2 | D107: 0 | F107: ='Stock'!K25*'Stock'!O25 | G107: =D107*'Stock'!O25
A108: Pigs | B108: 36 | C108: 30 | D108: -6 | F108: 3.75 | G108: -0.75
...

Sheet Prices
A1: Meat & Dairy Prices
C2: 1301 | D2: 1302 | E2: Average
A3: Beef | B3: £ per lb | C3: 0.0033351854 | D3: 0.0032608538 | E3: =AVERAGE(C3:D3)
A4: Mutton | B4: £ per lb | C4: 0.0036593977 | D4: 0.0037125513 | E4: =AVERAGE(C4:D4)
A5: Pork | B5: £ per lb | C5: 0.0038431326 | D5: 0.0037574803 | E5: =AVERAGE(C5:D5)
A6: Cheese | B6: £ per lb | C6: 0.0055768754 | D6: 0.0056654898 | E6: =AVERAGE(C6:D6)
A7: Butter | B7: £ per lb | C7: 0.0036626221 | D7: 0.0035935077 | E7: =AVERAGE(C7:D7)
A8: Milk | B8: £ per gallon | C8: 0.0055768754 | D8: 0.0056654898 | E8: =AVERAGE(C8:D8)

Sheet Labour Rents

Sheet Overview
A1: IVINGHOE | B1: Total in £ | C1: Error | D1: Note
A2: CASH ACCOUNT
A3: RECEIPTS
A4: Arrears total
A5: Rents of assize total
A6: Quittances total
A7: Defaults of rent total
A8: Defaults of rent through the pestilence total
A9: Cotlands defaults total
A10: Cotlands total
A11: Total of quittances and defaults of rent total
A12: Total of rents remaining clear total
A13: Farms total
... A22: Farm of the demesne land total
A23: Total of all receipts (calculated here) | B23: =Receipts!F134
A24: Total of all receipts (calculated here) incl arrears | B24: =Receipts!F135
A25: Total recorded in the accounts excl. arrears | B25: =Receipts!F133 | C25: =B25-B23
A26: Total recorded in the accounts incl. arrears
A29: EXPENSES
A30: Cost of ploughs total
A31: Purchase of corn total
A32: Cost of carts and wagons total
A33: Cost of dairy total
A34: Purchase of stock total
A35: Sheepcote total
A36: Cost of buildings total
A37: Threshing total
A38: Barley expenses
A39: Expenses of the harvest total
... A43: Annual fees
A44: Total of all expenses per account | B44: =Expenses!F100
A45: Total of all expenses (calculated here) | B45: =Expenses!F101
A46: Total fixed investment | B46: =Expenses!F102
A47: Total Demesne fixed investment | B47: =Expenses!F103
A49: Owed by the reeve
A50: From accounts
A52: Allowances
A53: Cash deliveries
A54: Sum of the above
A55: Total of all allowances and cash deliveries in accounts
A57: Net amount owed
A58: Net amount owed in accounts
A60: GRANGE ACCOUNT | B60: Total Production
A61: Grange | B61: qrs | E61: Value of total gross production in £ | F61: Value of total net production in £
A62: wheat | B62: ='Issues of the Grange'!B2 | E62: ='Issues of the Grange'!I2 | F62: ='Issues of the Grange'!O14
A63: curall | B63: ='Issues of the Grange'!B3 | E63: ='Issues of the Grange'!I3 | F63: ='Issues of the Grange'!O15
A64: mancorn | B64: ='Issues of the Grange'!B4 | E64: ='Issues of the Grange'!I4 | F64: ='Issues of the Grange'!O16
A65: barley | B65: ='Issues of the Grange'!B5 | E65: ='Issues of the Grange'!I5 | F65: ='Issues of the Grange'!O17
A66: oats | B66: ='Issues of the Grange'!B6 | E66: ='Issues of the Grange'!I6 | F66: ='Issues of the Grange'!O18
A67: beans | B67: ='Issues of the Grange'!B7 | E67: ='Issues of the Grange'!I7 | F67: ='Issues of the Grange'!O19
A68: Total value of gross production (sum of the above) | B68: =SUM(E62:E67)
A69: Total value of net production | B69: =SUM(F62:F66)
A70: Value of sales | B70: =Receipts!F92
A72: MILL ACCOUNT
A73: Issues of the mill
A74: Wheat
A75: Oatmeal
A76: 1st grade malt
A77: 2nd grade malt
A78: Maslin
A79: Total value of production (sum of the above)
A80: Value of sales
A82: STOCK ACCOUNT
A83: Livestock | B83: Sales value in £
A84: Cart-horses | B84: =Stock!R5
A85: Mares | B85: =Stock!R6
A86: Plough horses | B86: =Stock!R7
A87: Colts (2 years) | B87: =Stock!R8
A88: Colts (2 years) | B88: =Stock!R9
A89: Colts (1 year) | B89: =Stock!R10
A90: Foals | B90: =Stock!R11
A91: Oxen | B91: =Stock!R12
A92: Bulls | B92: =Stock!R13
A93: Cows | B93: =Stock!R14
A94: Steers | B94: =Stock!R15
A95: Bullocks | B95: =Stock!R16
... A109: Peacocks | B109: =Stock!R30
A110: Total value of stock (sum of the above)
A111: Total value of production
A112: Value of sales | B112: =Stock!R31
A114: Wool | B114: Value of production at sales prices £
A115: Fleeces
A116: Coarse wool | B116: =Stock!T35
A117: Lamb's wool | B117: =Stock!T36
A118: Wool locks | B118: =Stock!T37
A119: Wool sold at shearing | B119: =Stock!T38
A120: Total value of production (sum of the above) | B120: =Stock!T39
A121: Value of sales | B121: =Stock!R39
A123: Hides | B123: Value of production at sales prices £
A124: Ox hides | B124: =Stock!T43
A125: Cow hides | B125: =Stock!T44
A126: Mare hides | B126: =Stock!T45
A127: Steer hides | B127: =Stock!T46
A128: Yearling Calf hides | B128: =Stock!T47
A129: Calf hides | B129: =Stock!T48
A130: Pig hides | B130: =Stock!T49
A131: Wether woolskins | B131: =Stock!T50
A132: Ram woolskins | B132: =Stock!T51
A133: Ewe woolskins | B133: =Stock!T52
A134: Hogg woolskins | B134: =Stock!T53
...

Sheet Receipts
A1: IVINGHOE RECEIPTS
A2: Heading | B2: £ | C2: s | D2: d | F2: Total in £ | G2: Error | H2: Notes | I2: Own notes
A3: Arrears | B3: 2 | C3: 5 | D3: 1 | F3: 2.25 | H3: William, bailiff, and William, reeve, render account for £2 5 shilling 1pence of arrears from the previous year.
A4: Arrears | B4: 2 | C4: 5 | D4: 1 | F4: 2.25 | H4: Delivered to Sir Geoffrey, treasurer of Wolvesey, £2 5 shilling 1pence by 1 tally.
A5: Arrears | B5: 0 | C5: 0 | D5: 0 | F5: 0 | H5: They are quit.
A6: Arrears | F6: 4.5 | G6: 4.5 | H6: Total
A8: Rents of assize | B8: 6 | C8: 9 | D8: 10.5 | F8: 6.49 | H8: The same render account for £6 9 shilling 10.5pence for all rents of assize at Christmas.
A9: Rents of assize | B9: 6 | C9: 9 | D9: 10.5 | F9: 6.49 | H9: £6 9 shilling 10.5pence at the Annunciation (25 March).
A10: Rents of assize | B10: 6 | C10: 9 | D10: 10.5 | F10: 6.49 | H10: £6 9 shilling 10.5pence at the Nativity of the blessed John the Baptist (24 June).
A11: Rents of assize | B11: 6 | C11: 9 | D11: 10.75 | F11: 6.49 | H11: £6 9 shilling 10.75pence at Michaelmas (29 September).
A12: Rents of assize | B12: 25 | C12: 19 | D12: 6.25 | F12: 25.98 | H12: Total of all rents for the year, £25 19 shilling 6.25pence
A13: Rents of assize | F13: 25.96 | G13: -0.02 | H13: Total
A15: Quittances | B15: 0 | C15: 5 | D15: 0 | F15: 0.25 | H15: In quittance of 1 reeve for the year 5 shilling.
A16: Quittances | B16: 0 | C16: 2 | D16: 0 | F16: 0.1 | H16: 1 beadle who is hayward and sowed corn for the year 2 shilling.
A17: Quittances | B17: 0 | C17: 2 | D17: 2 | F17: 0.11 | H17: 1 forester who kept Cherlewod' and Cumbe for the year 2 shilling 2pence.
A18: Quittances | B18: 0 | C18: 2 | D18: 0 | F18: 0.1 | H18: 1 swineherd for the year 2 shilling.
A19: Quittances | B19: 0 | C19: 15 | D19: 0 | F19: 0.75 | H19: 5 of the lord's ploughmen for the year 15 shilling, or 3 shilling each.
A20: Quittances | B20: 0 | C20: 3 | D20: 10 | F20: 0.19 | H20: 4 workers working every day apart from Saturday from Michaelmas until Christmas who, together with the cart-horses of the curia, harrowed lands for wheat and drained water from the same, 3 shilling 10pence, of whom I was quit of 1 shilling 3pence, 1 of 1 shilling, 1 of 10pence, and 1 of 9pence.
A21: Quittances | B21: 0 | C21: 3 | D21: 10 | F21: 0.19 | H21: 4 workers working the same between Christmas and the Annunciation who, together with the cart-horses of the curia, harrowed lands for oats, 3 shilling 10pence, of whom 3 were each quit of 1 shilling, and 1 of 10pence.
A22: Quittances | B22: 0 | C22: 1 | D22: 10.5 | F22: 0.09 | H22: 2 workers working the same between the Annunciation and the Nativity of the blessed John the Baptist who harrowed lands for barley and enclosed with hedges, 1 shilling 10.5pence, of whom 1 was quit of 1 shilling, and 1 of 10.5pence.
A23: Quittances | B23: 0 | C23: 10 | D23: 3 | F23: 0.51 | H23: 10 workers working the same between the feast of St John the Baptist and Michaelmas who weeded corn, mowed and gathered hay, and carried corn, 10 shilling 3pence, of whom 1 was quit of 1 shilling 3pence, and 9 of 1 shilling each.
A24: Quittances | B24: 2 | C24: 5 | D24: 11.5 | F24: 2.3 | H24: Total of quittances, £2 5 shilling 11.5pence
A25: Quittances | F25: 2.29 | G25: -0.01 | H25: Total
A27: Defaults of rent | B27: 0 | C27: 18 | D27: 0 | F27: 0.9 | H27: In default of the land of the earl of Salisbury at Gaddesden 18 shilling
A28: Defaults of rent | B28: 0 | C28: 18 | D28: 0 | F28: 0.9 | H28: Total of defaults of rent, 18 shilling
A29: Defaults of rent | F29: 0.9 | G29: 0 | H29: Total
A31: Total of quittances and defaults of rent | B31: 3 | C31: 3 | D31: 11.5 | F31: 3.2 | H31: Total of quittances and defaults of rent, £3 3 shilling 11.5pence
A32: Total of quittances and defaults of rent | F32: 3.2 | G32: =F32-F31 | H32: Total
A34: Issues of the manor | B34: 0 | C34: 9 | D34: 8 | F34: 0.48 | H34: The same render account for 9 shilling 8pence from pannage of pigs of the whole vill.
A35: Issues of the manor | B35: 0 | C35: 0 | D35: 0 | F35: 0 | H35: nothing from foreign pannage because there was no mast.
A36: Issues of the manor | B36: 1 | C36: 0 | D36: 0 | F36: 1 | H36: £1 from dead wood blown down by the wind in Cherlewod'.
A37: Issues of the manor | B37: 0 | C37: 10 | D37: 6 | F37: 0.53 | H37: 10 shilling from winter ploughing this year, that is, 6pence a ploughman from 20 ploughmen.
A38: Issues of the manor | B38: 0 | C38: 0 | D38: 0 | F38: 0 | H38: nothing from Lenten ploughing because it was ploughed.
A39: Issues of the manor | B39: 0 | C39: 5 | D39: 6 | F39: 0.28 | H39: 5 shilling from 10 ploughmen for release from summer ploughing, at 6pence a ploughman.
A40: Issues of the manor | B40: 1 | C40: 10 | D40: 3 | F40: 1.51 | H40: £1 10 shilling 3pence from 60.5 virgates of land for release from transport-service this year, at 6pence a virgate, because no transport-service was done to London or elsewhere.
A41: Issues of the manor | B41: 0 | C41: 12 | D41: 6 | F41: 0.62 | H41: 12 shilling from the agistment of 6 old beasts (av') and 18 bullocks in the pasture of the grove for the summer, at 6pence an old beast and 4pence a bullock.
A42: Issues of the manor | B42: 0 | C42: 0 | D42: 0 | F42: 0 | H42: nothing from coarse wool this year because it is sent to Wolvesey.
A43: Issues of the manor | B43: 0 | C43: 0 | D43: 0 | F43: 0 | H43: nothing from lambs' fleeces this year because the lambs were not sheared.
A44: Issues of the manor | B44: 0 | C44: 1 | D44: 3 | F44: 0.06 | H44: 1 shilling 3pence from wool locks this year.
A45: Issues of the manor | B45: 0 | C45: 3 | D45: 1 | F45: 0.15 | H45: 3 shilling 1pence from winter cheese sold.
... A64: Issues of the manor | B64: 12 | C64: 13 | D64: 4 | F64: 12.67 | H64: Total, £12 13 shilling 4pence
A65: Issues of the manor | F65: 12.75 | G65: 0.08 | H65: Total
A67: Issues of stock | B67: 1 | C67: 3 | D67: 0 | F67: 1.15 | H67: The same render account for £1 3 shilling from 6 old and feeble plough-horses sold, at 5 shilling each for 2, 3 shilling 6pence each for 2, and 3 shilling each for 2.
A68: Issues of stock | B68: 3 | C68: 19 | D68: 2 | F68: 3.96 | H68: £3 19 shilling 2pence from 8 oxen sold, at 11 shilling each for 4, 10 shilling each for 3, and 5 shilling 2pence for 1 killed for fear of murrain.
A69: Issues of stock | B69: 0 | C69: 11 | D69: 0 | F69: 0.55 | H69: 11 shilling from 1 bull sold.
A70: Issues of stock | B70: 1 | C70: 8 | D70: 6 | F70: 1.42 | H70: £1 8 shilling 6pence from 4 cows sold, 3 of them at Martinmas, at 8 shilling 6pence each for 2, 7 shilling 6pence for 1, and 4 shilling for 1 sick cow before calving.
A71: Issues of stock | B71: 0 | C71: 4 | D71: 0 | F71: 0.2 | H71: 4 shilling from 1 steer sold.
A72: Issues of stock | B72: 0 | C72: 10 | D72: 11 | F72: 0.55 | H72: 10 shilling from 11 calves sold, at 1 shilling each for 4, 11pence each for 2, and 10pence each for 5.
A73: Issues of stock | B73: 0 | C73: 2 | D73: 4 | F73: 0.12 | H73: 2 shilling 4pence from the hide sold of 1 ox in murrain.
A74: Issues of stock | B74: 0 | C74: 1 | D74: 0 | F74: 0.05 | H74: 1 shilling from the hides sold of 2 yearlings in murrain.
A75: Issues of stock | B75: 1 | C75: 15 | D75: 0 | F75: 1.75 | H75: £1 15 shilling from 26 wethers and 4 ewes sold at Martinmas, at 1 shilling 2pence each.
A76: Issues of stock | B76: 14 | C76: 0 | D76: 0 | F76: 14 | H76: £14 shilling 6pence from the skins sold of 40 wethers, 31 ewes and 26 hoggs in murrain before shearing, at 4pence a wether, 3pence a ewe, and 2.5pence a hogg.
A77: Issues of stock | B77: 0 | C77: 1 | D77: 2.5 | F77: 0.06 | H77: 1 shilling 2.5pence from the skins sold of 1 wether, 5 ewes, in murrain after shearing, and 5 lambs, at 2pence a wether, 1.5pence a ewe, and 1pence a lamb.
A78: Issues of stock | B78: 0 | C78: 3 | D78: 4 | F78: 0.17 | H78: 3 shilling 4pence from 3 peacocks sold, 1 of them a male.
... A89: Wheat, barley, oats and beans sold | B89: 0 | C89: 12 | D89: 3 | F89: 0.61 | H89: 12 shilling 3pence from 6 quarters 1 bushels of beans sold, at 2 shilling a quarters.
A90: Wheat, barley, oats and beans sold | B90: 0 | C90: 1 | D90: 5.5 | F90: =B90+C90/20+D90/240 | H90: 1 shilling 5.5pence from 3.5 bushels of barley sold at the audit, at 5pence a bushels
A91: Wheat, barley, oats and beans sold | B91: 55 | C91: 3 | D91: 0.5 | F91: 55.15 | H91: Total of all corn sold, £55 3 shilling 0.5pence
A92: Wheat, barley, oats and beans sold | F92: =SUM(F84:F90) | G92: =F92-F91 | H92: Total
A94: Corn and malt mill' | B94: 2 | C94: 19 | D94: 11 | F94: 3 | H94: The same render account for £2 19 shilling 11pence from 23 quarters 5 bushels of corn from the whole issue of the mill sold, at 3 shilling a quarters for 8 quarters, 2 shilling 8pence a quarters for 7 quarters, and 2 shilling a quarters for 8 quarters 5 bushels.
A95: Corn and malt mill' | B95: 0 | C95: 10 | D95: 4 | F95: =B95+C95/20+D95/240 | H95: 10 shilling 4pence from 3 quarters 5 bushels of malfsold, at 3 shilling a quarters for 2 quarters, and 2 shilling 8pence a quarters for 1 quarters 5 bushels
A96: Corn and malt mill' | B96: 3 | C96: 10 | D96: 3 | F96: 3.51 | H96: Total, £3 10 shilling 3pence
A97: Corn and malt mill' | F97: =SUM(F94:F95) | G97: =F97-F96 | H97: Total
A99: Annual recognizance | B99: 0 | C99: 0 | D99: 6 | F99: 0.03 | H99: The same render account for 6pence from Gilbert son of Richard for annual recognizance.
A100: Annual recognizance | B100: 0 | C100: 0 | D100: 3 | F100: 0.01 | H100: 3pence from Gilbert Lylye for the same.
A101: Annual recognizance | B101: 0 | C101: 0 | D101: 6 | F101: 0.03 | H101: 6pence from Richard son of Gilbert for the same.
A102: Annual recognizance | B102: 0 | C102: 0 | D102: 6 | F102: 0.03 | H102: nothing from Richard Sutor' this year because he is dead, that is, 6pence from Martin Faber of Netley for the same.
A103: Annual recognizance | B103: 0 | C103: 0 | D103: 3 | F103: 0.01 | H103: 3pence from Hugh Reygnild' for the same.
A104: Annual recognizance | B104: 0 | C104: 0 | D104: 3 | F104: 0.01 | H104: nothing from Gervase de Asschewoll' this year because he is dead, that is, 3pence from Thomas le Boltere for the same.
A105: Annual recognizance | B105: 0 | C105: 0 | D105: 6 | F105: 0.03 | H105: 6pence from John le Nywebond' for the same.
A106: Annual recognizance | B106: 0 | C106: 0 | D106: 3 | F106: 0.01 | H106: 3pence from Guy Careter for the same.
A107: Annual recognizance | B107: 0 | C107: 0 | D107: 3 | F107: 0.01 | H107: 3pence from Peter son of Michael for the same.
A108: Annual recognizance | B108: 0 | C108: 3 | D108: 3 | F108: 0.16 | H108: Total, 3 shilling 3pence
A109: Annual recognizance | F109: 0.17 | G109: 0.01 | H109: Total
A111: Entry and marriage fines | B111: 0 | C111: 2 | D111: 0 | F111: 0.1 | H111: The same render account for 2 shilling from Geoffrey atte Slade for marrying Matilda his daughter outside.
A112: Entry and marriage fines | B112: 0 | C112: 1 | D112: 0 | F112: 0.05 | H112: 1 shilling from Agnes atte Slad' for marrying herself within.
A113: Entry and marriage fines | B113: 0 | C113: 2 | D113: 0 | F113: 0.1 | H113: 2 shilling from Matilda la Dreyestr' for marrying Alice her daughter outside.
A114: Entry and marriage fines | B114: 0 | C114: 2 | D114: 0 | F114: 0.1 | H114: 2 shilling from Muriel, who was wife of William Peck', to retain 1 house and .5 acre of assarted land which belonged to the said William her husband.
A115: Entry and marriage fines | B115: 0 | C115: 13 | D115: 4 | F115: 0.67 | H115: 13 shilling 4pence from Walter Molendinarius to have Alice atte Pund' with her land.
A116: Entry and marriage fines | B116: 0 | C116: 2 | D116: 0 | F116: 0.1 | H116: 2 shilling from Juliana, who was wife of Richard Sutoris, to have entry to 1 house which Richard Sutor formerly held.
A117: Entry and marriage fines | B117: 1 | C117: 6 | D117: 8 | F117: 1.33 | H117: £1 6 shilling 8pence from John, son of John Jacob, for entry to two virgates of land which the said John his father held.
A118: Entry and marriage fines | B118: 0 | C118: 4 | D118: 0 | F118: 0.2 | H118: 4 shilling from Richard le Wych' for marrying Leticia his daughter within.
A119: Entry and marriage fines | B119: 0 | C119: 6 | D119: 8 | F119: 0.33 | H119: 6 shilling 8pence from Walter Bast for marrying Matilda his daughter outside.
A120: Entry and marriage fines | B120: 0 | C120: 3 | D120: 4 | F120: 0.17 | H120: 3 shilling 4pence from John Bucok' to have entry to 1 butt of land by concession and surrender of John Hod, and he will relieve the said John Hod of 4pence annual rent.
A121: Entry and marriage fines | B121: 0 | C121: 3 | D121: 6 | F121: 0.17 | H121: 3 shilling 6pence from William le Careter to have entry to 1.5 acres of assart by concession and surrender of Robert de Chyssend'.
A122: Entry and marriage fines | B122: 4 | C122: 0 | D122: 0 | F122: 4 | H122: £4 from William, son of Herbert Reygnild, to have entry to 1 messuage with 1 virgate of customary land which he has held of his father because his elder brother John said in full court that he was unwilling to fine for the said land, that is, he quitclaimed wholly his right to the use of the said William.
... A125: Entry and marriage fines | B125: 9 | C125: 3 | D125: 10 | F125: 9.19 | H125: Total, £9 3 shilling 10pence
A126: Entry and marriage fines | F126: 9.18 | G126: -0.01 | H126: Total
A128: Pleas and perquisites | B128: 3 | C128: 10 | D128: 0 | F128: 3.5 | H128: The same render account for £3 10 shilling I 1pence from the pleas and perquisites of all the courts this year.
A129: Pleas and perquisites | B129: 2 | C129: 0 | D129: 0 | F129: 2 | H129: £2 from the reeve for many transgressions of which he was convicted at the audit.
A130: Pleas and perquisites | B130: 5 | C130: 10 | D130: 11 | F130: 5.55 | H130: Total, £5 10 shilling 11pence
A131: Pleas and perquisites | F131: 5.5 | G131: -0.05 | H131: Total
A133: Total of all receipts recorded in accounts | B133: 125 | C133: 16 | D133: 1.75 | F133: 125.81 | H133: Total of all receipts, £125 16 shilling 1.75pence
A134: Total cross-check without arrears | F134: =F131+F126+F109+F82+F65+F13-F32+F92+F97 | G134: =F134-F133
A135: Total cross-check with arrears | F135: =F134+F6

Sheet Expenses
A1: IVINGHOE EXPENSES
A2: Heading | B2: £ | C2: s | D2: d | F2: Total in £ | G2: Error | H2: Notes | I2: Own notes | K2: Fixed investment | L2: Demesne fixed investment
A3: Expenses for ploughs | B3: 0 | C3: 7 | D3: 10 | F3: 0.39 | H3: In ironwork of 5 ploughs for the year 7 shilling 10pence. | K3: =F3 | L3: =F3
A4: Expenses for ploughs | B4: 0 | C4: 1 | D4: 6 | F4: 0.08 | H4: 2 ploughshares bought 1 shilling 6pence Moreover they have 1 ploughshare as made clear above. | K4: =F4 | L4: =F4
A5: Expenses for ploughs | B5: 0 | C5: 0 | D5: 0 | F5: 0 | H5: Nothing accounted for forging the said ironwork because the smith takes 2 acres of wheat as they lie in the field for forging the same when the ploughmen are ploughing for the whole year. | K5: =F5 | L5: =F5
A6: Expenses for ploughs | B6: 0 | C6: 0 | D6: 8 | F6: 0.03 | H6: 4 iron spurs bought 8pence. | K6: =F6 | L6: =F6
A7: Expenses for ploughs | B7: 0 | C7: 3 | D7: 2 | F7: 0.16 | H7: stipend of 1 carpenter making new ploughs, repairing old ploughs, and making harrows and yokes from the lord's timber 3 shilling 2pence, because the manorial servant who by custom made these is deapence. | K7: =F7 | L7: =K7/2
A8: Expenses for ploughs | B8: 8 | C8: 18 | D8: 2 | F8: 8.91 | H8: 15 oxen bought £8 18 shilling 2pence, at 13 shilling 5pence each for 2, 12 shilling 6pence each for 4, 12 shilling each for 3, 11 shilling 5pence each for 3, 10 shilling 6.51. each for 2, and 10 shilling for 1..
A9: Expenses for ploughs | B9: 2 | C9: 4 | D9: 11 | F9: 2.25 | H9: 12 quarters 2 bushels of wheat bought for sowing £2 4 shilling 11pence, at 3 shilling 8pence a quarters.
A10: Expenses for ploughs | B10: 4 | C10: 4 | D10: 0 | F10: 4.2 | H10: 34 quarters of maslin bought for the liveries of the manorial servants £4 4 shilling, at 3 shilling a quarters for 8 quarters, 2 shilling 8pence a quarters for 12 quarters, and 2 shilling a quarters for 14 quarters.
A11: Expenses for ploughs | B11: 0 | C11: 6 | D11: 9 | F11: 0.34 | H11: 4.5 quarters of oats bought for fodder of horses 6 shilling 9pence, at 1 shilling 6pence a quarters.
A12: Expenses for ploughs | B12: 1 | C12: 0 | D12: 0 | F12: 1 | H12: hay bought £1, because hay was taken for the queen's use.
A13: Expenses for ploughs | B13: 1 | C13: 16 | D13: 0 | F13: 1.8 | H13: forage bought for stock £1 16 shilling Ipence.
A14: Expenses for ploughs | B14: 0 | C14: 6 | D14: 8 | F14: =B14+C14/20+D14/240 | H14: stipend of 5 oxherds for .5 year in winter 6 shilling 8pence, or 1 shilling 4pence each, because each manorial servant takes corn at harvest-time for the other .5 year in summer, that is,' acre of wheat and .5 acre of oats as they lie in the fie1pence
A15: Expenses for ploughs | B15: 19 | C15: 8 | D15: 3 | F15: 19.41 | H15: Total, £19 8 shilling 3pence
A16: Expenses for ploughs | F16: =SUM(F3:F14) | G16: =F16-F15 | H16: Total
A18: Expenses for carts and wagons | B18: 0 | C18: 1 | D18: 2 | F18: 0.06 | H18: In clouts and nails for the cart for the year 1 shilling 2pence. | K18: =F18 | L18: =K18
A19: Expenses for carts and wagons | B19: 0 | C19: 1 | D19: 1 | F19: 0.05 | H19: white leather for mending harnesses of the cart 1 shilling 1pence. | K19: =F19 | L19: =K19
A20: Expenses for carts and wagons | B20: 0 | C20: 0 | D20: 4 | F20: 0.02 | H20: grease bought for the year 4pence. | K20: =F20 | L20: =K20
A21: Expenses for carts and wagons | B21: 0 | C21: 0 | D21: 1 | F21: 0 | H21: 5 halters for plough-horses made from their own hair 1pence. | K21: =F21 | L21: =K21
A22: Expenses for carts and wagons | B22: 0 | C22: 0 | D22: 1.5 | F22: 0.01 | H22: mending saddle-pads 1.5pence. | K22: =F22 | L22: =K22
A23: Expenses for carts and wagons | B23: 0 | C23: 0 | D23: 6 | F23: 0.03 | H23: 1 collar bought 6pence. | K23: =F23 | L23: =K23
A24: Expenses for carts and wagons | B24: 0 | C24: 0 | D24: 1.5 | F24: 0.01 | H24: a wooden base for 1 cart-saddle 1.5pence. | K24: =F24 | L24: =K24
A25: Expenses for carts and wagons | B25: 0 | C25: 0 | D25: 1 | F25: 0 | H25: repairing old collars 1pence. | K25: =F25 | L25: =K25
A26: Expenses for carts and wagons | B26: 0 | C26: 0 | D26: 7 | F26: 0.03 | H26: 1 pair of traces bought 7pence. | K26: =F26 | L26: =K26
A27: Expenses for carts and wagons | B27: 0 | C27: 0 | D27: 0 | F27: 0 | H27: making 2 pairs of wheels from the lord's timber for the cart with iron tyres and for clearing dung. | K27: =F27 | L27: =K27
A28: Expenses for carts and wagons | B28: 0 | C28: 6 | D28: 2 | F28: 0.31 | H28: new large nails and clamps and frets with the stipend of the smith fitting 1 pair of wheels with old iron tyres 6 shilling 2pence. | K28: =F28 | L28: =K28
A29: Expenses for carts and wagons | B29: 0 | C29: 0 | D29: 4 | F29: 0.02 | H29: fitting the cart with axles for the year 4pence. | K29: =F29 | L29: =K29
A30: Expenses for carts and wagons | B30: 0 | C30: 2 | D30: 0 | F30: 0.1 | H30: shoeing 2 cart-horses for the year by piece-work 2 shilling. | K30: =F30 | L30: =K30
A31: Expenses for carts and wagons | B31: 0 | C31: 1 | D31: 4 | F31: 0.07 | H31: stipend of 1 carter for' year in winter 1 shilling 4pence, because for the other .5 year he takes corn in the field like the rest of the manorial servants. | K31: =F31 | L31: =K31/2
A32: Expenses for carts and wagons | B32: 0 | C32: 0 | D32: 6 | F32: 0.03 | H32: clouts and nails bought for wagons 6pence. | K32: =F32 | L32: =K32
A33: Expenses for carts and wagons | B33: 0 | C33: 0 | D33: 2 | F33: =B33+C33/20+D33/240 | H33: grease and tallow bought for the same 2pence | K33: =F33 | L33: =K33
A34: Expenses for carts and wagons | B34: 0 | C34: 15 | D34: 2 | F34: 0.76 | H34: Total, 15 shilling 5pence
A35: Expenses for carts and wagons | F35: =SUM(F18:F33) | G35: =F35-F34 | H35: Total
A37: Dairy | B37: 0 | C37: 0 | D37: 3 | F37: 0.01 | H37: In linen cloth for the dairy 3pence. | K37: =F37 | L37: =F37
A38: Dairy | B38: 0 | C38: 0 | D38: 3.5 | F38: 0.01 | H38: earthenware pots and pans bought 3.5pence. | K38: =F38 | L38: =F38
A39: Dairy | B39: 0 | C39: 0 | D39: 3 | F39: 0.01 | H39: a press 3pence. | K39: =F39 | L39: =F39
A40: Dairy | B40: 0 | C40: 1 | D40: 10 | F40: 0.09 | H40: .5 qr of salt bought 1 shilling 10pence, at 7pence for 1 bushels, and 5pence each for 3 bushels. | K40: =F40 | L40: =F40
A41: Dairy | B41: 0 | C41: 0 | D41: 1.5 | F41: 0.01 | H41: 1 colander bought 1.5pence. | K41: =F41 | L41: =F41
A42: Dairy | B42: 0 | C42: 5 | D42: 3 | F42: 0.26 | H42: vinegar and pigs' fat for greasing sick sheep 5 shilling 3pence. | K42: =F42 | L42: =F42
A43: Dairy | B43: 0 | C43: 0 | D43: 0 | F43: 0 | H43: hurdles for the fold, nothing this year. | K43: =F43 | L43: =F43
A44: Dairy | B44: 0 | C44: 1 | D44: 1.5 | F44: 0.06 | H44: 5 ells of canvas for packing wool 1 shilling 1.5pence, at 2.5pence an ell. | K44: =F44 | L44: =F44
A45: Dairy | B45: 0 | C45: 2 | D45: 0 | F45: 0.1 | H45: stipend of 1 shepherd and 1 cowherd in winter 2 shilling, because for the other .5 year they take corn in the field like the rest of the manorial servants.
A46: Dairy | B46: 0 | C46: 2 | D46: 6 | F46: 0.12 | H46: stipend of 1 dairymaid this year 2 shilling 6pence, because for 13 weeks there was no dairymaipence.
A47: Dairy | B47: 0 | C47: 0 | D47: 4 | F47: =B47+C47/20+D47/240 | H47: carrying wool to Wolvesey 4pence
A48: Dairy | B48: 0 | C48: 13 | D48: 4 | F48: 0.67 | H48: Total, 13 shilling 11.5pence
A49: Dairy | F49: =SUM(F37:F47) | G49: =F49-F48 | H49: Total
A51: Expenses of buildings and small necessaries | B51: 0 | C51: 0 | D51: 2 | F51: 0.01 | H51: In propping up the wardrobe of the bishop's chamber 2pence. | K51: =F51
A52: Expenses of buildings and small necessaries | B52: 0 | C52: 1 | D52: 8 | F52: 0.08 | H52: re-roofing in places the larger barn, unroofed by the wind, where it was necessary 1 shilling 8pence. | K52: =F52 | L52: =K52
A53: Expenses of buildings and small necessaries | B53: 0 | C53: 0 | D53: 8 | F53: 0.03 | H53: re-roofing the small barn in places 8pence. | K53: =F53 | L53: =K53
A54: Expenses of buildings and small necessaries | B54: 0 | C54: 0 | D54: 10 | F54: 0.04 | H54: roofing one part of the long stable throughout 10pence. | K54: =F54 | L54: =K54
A55: Expenses of buildings and small necessaries | B55: 0 | C55: 0 | D55: 1.5 | F55: 0.01 | H55: 1 lock with a key bought for the garden-gate 1.5pence. | K55: =F55 | L55: =K55
A56: Expenses of buildings and small necessaries | B56: 0 | C56: 0 | D56: 10 | F56: 0.04 | H56: iplantingl and watering beans 10pence.
A57: Expenses of buildings and small necessaries | B57: 0 | C57: 0 | D57: 5.5 | F57: =B57+C57/20+D57/240 | H57: gelding (masculand') 26 piglets 5.5pence
A58: Expenses of buildings and small necessaries | B58: 0 | C58: 4 | D58: 5.5 | F58: 0.22 | H58: Total, 4 shilling 9pence
A59: Expenses of buildings and small necessaries | F59: =SUM(F51:F57) | G59: =F59-F58 | H59: Total
A61: Mowing | B61: 0 | C61: 1 | D61: 0 | F61: 0.05 | H61: In customary payment for the mowing of the meadow 1 shilling
A62: Mowing | B62: 0 | C62: 1 | D62: 0 | F62: 0.05 | G62: =F62-F61 | H62: Total, 1 shilling
A64: Purchase of stock | B64: 2 | C64: 8 | D64: 7 | F64: 2.43 | H64: In 28 wethers bought before shearing £2 8 shilling 7pence, at 1 shilling 9pence each for 18, and 1s 8.5pence each for 10.
A65: Purchase of stock | B65: 2 | C65: 8 | D65: 7 | F65: 2.43 | H65: Total, £2 8 shilling 7pence
A66: Purchase of stock | F66: 2.43 | G66: 0 | H66: Total
A68: Threshing and winnowing | B68: 0 | C68: 0 | D68: 3.5 | F68: 0.01 | H68: In mending 1 new sieve and other old ones 3.5pence.
A69: Threshing and winnowing | B69: 0 | C69: 0 | D69: 2 | F69: 0.01 | H69: 1 new sack bought 9.25d remaking (refit') old broken baskets 2pence.
A70: Threshing and winnowing | B70: 1 | C70: 8 | D70: 3 | F70: 1.41 | H70: threshing 169.5 quarters of wheat with £1 8 shilling 3pence, at 2pence a qr.
A71: Threshing and winnowing | B71: 0 | C71: 0 | D71: 0 | F71: 0 | H71: winnowing, nothing, because it was winnowed by laboura service.
A72: Threshing and winnowing | B72: 0 | C72: 0 | D72: 0 | F72: 0 | H72: threshing barley and beans, nothing this year, because it was threshed by the lord's manorial servants.
A73: Threshing and winnowing | B73: 0 | C73: 0 | D73: 0 | F73: 0 | H73: winnowing, nothing, for the above' reason.
A74: Threshing and winnowing | B74: 0 | C74: 8 | D74: 4.5 | F74: 0.42 | H74: threshing 134 quarters of oats 8 shilling 4.5pence, at .75pence a qr, and winnowed by labour service as above.
A75: Threshing and winnowing | B75: 1 | C75: 17 | D75: 10.25 | F75: 1.89 | H75: Total, £1 17 shilling 10.25pence
A76: Threshing and winnowing | F76: 1.85 | G76: -0.04 | H76: Total
A78: Cost of the mill | B78: 0 | C78: 5 | D78: 3.5 | F78: 0.26 | H78: In 20 ells of canvas bought for the sails of the mill 5 shilling, at 3.5pence each for 10, and 3d each for 10.. | K78: =F78
A79: Cost of the mill | B79: 0 | C79: 0 | D79: 3 | F79: 0.01 | H79: steeling and sharpening bills for the year 3pence. | K79: =F79
A80: Cost of the mill | B80: 0 | C80: 0 | D80: 6 | F80: 0.03 | H80: tallow and grease bought for the same for the year 6pence. | K80: =F80
A81: Cost of the mill | B81: 0 | C81: 0 | D81: 2 | F81: 0.01 | H81: white leather for the clapper of the mill 2pence. | K81: =F81
A82: Cost of the mill | B82: 0 | C82: 1 | D82: 0 | F82: 0.05 | H82: stipend of 1 miller for' year in winter 1 shilling, because for the other .5 year he takes corn at harvest-time.
A83: Cost of the mill | B83: 0 | C83: 6 | D83: 11 | F83: 0.35 | H83: Total, 6 shilling 11pence
A84: Cost of the mill | F84: 0.36 | G84: 0.01 | H84: Total
A86: Expenses of the steward | B86: 0 | C86: 8 | D86: 0 | F86: 0.4 | H86: In expenses of the steward at the hundred-court of Martinmas 8 shilling.
A87: Expenses of the steward | B87: 0 | C87: 5 | D87: 9.25 | F87: 0.29 | H87: expenses of the steward for his 1 visit about the Purification (2 February) 5 shilling 9.25pence.
A88: Expenses of the steward | B88: 0 | C88: 10 | D88: 1 | F88: =B88+C88/20+D88/240 | H88: expenses of Simon de Farham holding the tourn of Hockday (1 May) 10 shilling 1pence
A89: Expenses of the steward | B89: 1 | C89: 3 | D89: 10.5 | F89: =B89+C89/20+D89/240 | H89: Total, £1 3shilling 10.5pence
A90: Expenses of the steward | F90: =SUM(F86:F88) | G90: =F90-F89 | H90: Total
A92: Total of all expenses | B92: 31 | C92: 12 | D92: 10 | F92: 31.64 | H92: Total of all expenses, £31 12 shilling 10pence
A94: And he owes | B94: 94 | C94: 3 | D94: 3.75 | F94: 94.17 | H94: And he owes, £94 3 shilling 3.75pence
A95: And he owes | F95: 94.17 | G95: 0 | H95: Total
A97: Cash deliveries | B97: 80 | C97: 0 | D97: 0 | F97: 80 | H97: Delivered to Sir Geoffrey, treasurer of Wolvesey, by 1 tally, £80.
A98: Cash deliveries | B98: 14 | C98: 3 | D98: 3.75 | F98: 14.17 | H98: And thus he owes clear, £14 3 shilling 3.75pence
A100: Total of all expenses per account | F100: =F92
A101: Total of all expenses (calculated here) | F101: =F90+F84+F76+F66+F49+F35+F16
A102: Total fixed investment | F102: =SUM(K3:K83)
A103: Total Demesne fixed investment | F103: =SUM(L3:L82)

Sheet Issues of the Grange
A1: Gross Output | B1: Total Quantity | C1: Account Total Quarters | D1: Bought in Total Quarters | E1: Received from churchscot | F1: Sold Total Quarters | G1: Difference Produced+Bought-Sold | H1: Weighted Average Price per Quarter | I1: Value of Total Production weighted
A2: wheat | B2: 220.375 | C2: 201.625 | D2: 12.25 | F2: 177.75 | G2: =B2-F2 | H2: 0.24648383 | I2: =H2*B2
A3: curall | B3: 10.375 | C3: 10.375 | D3: 0 | F3: 0 | G3: =B3-F3 | I3: =H3*B3
A4: mancorn | B4: 0 | C4: 0 | D4: 0 | F4: 0 | G4: =B4-F4 | I4: =H4*B4
A5: barley | B5: 74 | C5: =19.75+20.25 | D5: 34 | F5: 10.4375 | G5: =B5-F5 | H5: 0.16666667 | I5: =H5*B5
A6: oats | B6: =216+2/8 | C6: =B6-D6 | D6: =4.5 | F6: 99.875 | G6: =B6-F6 | H6: 0.089987484 | I6: =H6*B6
A7: beans | B7: 20.125 | C7: 20.125 | D7: 0 | F7: 6.125 | G7: =B7-F7 | H7: 0.1 | I7: =H7*B7
A9: Total Production
A10: Sales of corn (as recorded in accounts)
A13: Net output | B13: Gross output | C13: Seed quarters | D13: Seed bushels | E13: Seed total quarters | F13: tithe quarters | G13: tithe bushels | H13: tithe total | I13: manorial servants quarters | J13: manorial servants bushels | K13: manorial servants total quarters | L13: output net of tithe, seed, liveries | M13: in stock from last year | N13: Price in £ | O13: Value of net output in £ | P13: Value of sales (in "Sale of Corn") in £
A14: wheat | B14: =B2 | C14: 32 | D14: 2 | E14: =C14+D14/8 | I14: =1.5+6.5+0.5 | J14: =6+3+3+3 | K14: =I14+J14/8 | L14: =B14-E14-K14 | N14: =H2 | O14: =N14*L14
A15: curall | B15: =B3 | E15: =C15+D15/8 | I15: 10 | J15: 3 | K15: =I15+J15/8 | L15: =B15-E15-K15 | N15: =H3 | O15: =N15*L15
A16: mancorn | B16: =B4 | E16: =C16+D16/8 | K16: =I16+J16/8 | L16: =B16-E16-K16 | N16: =H4 | O16: =N16*L16
A17: barley | B17: =B5 | C17: 4 | D17: 3 | E17: =C17+D17/8 | I17: =39+18+1 | J17: =6.5+3 | K17: =I17+J17/8 | L17: =B17-E17-K17 | N17: =H5 | O17: =N17*L17
A18: oats | B18: =B6 | C18: 90 | D18: 5 | E18: =C18+D18/8 | I18: =15+0.5+1+4.5+0.5+2 | J18: =7+2+5 | K18: =I18+J18/8 | L18: =B18-E18-K18 | N18: =H6 | O18: =N18*L18
A19: beans | B19: =B7 | C19: 4 | D19: 1 | E19: =C19+D19/8 | I19: 9 | J19: 7 | K19: =I19+J19/8 | L19: =B19-E19-K19 | N19: =H7 | O19: =N19*L19
A21: Total

Sheet Issues of the Mills

Sheet Stock
A1: IVINGHOE STOCK ACCOUNT
C3: added | G3: subtracted
A4: Livestock | B4: Inherited stock | C4: added | D4: strays | E4: herbage | F4: churchscot | G4: of which in default | H4: sold | I4: in murrain | J4: accounted for elsewhere | K4: End-period stock | L4: cross-check | M4: stock building | N4: raw production | O4: Unit price (£) | P4: Value of stock (£) at given value | Q4: Value of stock (£) at sales prices | R4: Sales in (£) | S4: Value of stock building (£) | T4: Value of production (£) at sales prices | U4: Details
A5: Cart-horses | B5: 2 | K5: 2
A6: Mares
A7: Plough horses | B7: 10 | H7: 6 | K7: 4 | O7: =R7/H7 | R7: =Receipts!F67 | T7: =O7*C7
A8: Colts (unspecified years) | T8: =O8*C8
A9: Colts (2 years) | T9: =O9*C9
A10: Colts (1 year) | T10: =O10*C10
A11: Foals | T11: =O11*C11
A12: Oxen | B12: 32 | C12: =2+1+1+15 | H12: =1+7 | I12: =1 | K12: 42 | O12: =R12/H12 | R12: =Receipts!F68 | T12: =O12*C12
A13: Bulls | B13: 2 | H13: 1 | K13: 1 | O13: =R13/H13 | R13: =Receipts!F69 | T13: =O13*C13
A14: Cows | B14: 22 | C14: =5+1 | H14: =1+3 | K14: 24 | O14: =R14/H14 | R14: =Receipts!F70 | T14: =O14*C14
A15: Steers | B15: 8 | H15: =1 | J15: =2+5 | K15: 0 | O15: =R15/H15 | R15: =Receipts!F71 | T15: =O15*C15
A16: Bullocks | B16: 3 | K16: 3 | T16: =O16*C16
A17: Yearlings | B17: 5 | I17: 2 | K17: 3 | T17: =O17*C17
A18: Calves | C18: =21+2 | H18: =11+2 | K18: 6 | O18: =R18/H18 | R18: =Receipts!F72 | T18: =O18*C18
A19: Wethers | B19: 175 | C19: =16+28 | H19: =54+26 | I19: =40+1 | J19: =1 | K19: 97 | O19: =R19/H19 | R19: =Receipts!F75+Receipts!F81 | T19: =O19*C19
A20: Rams | T20: =O20*C20
A21: Ewes | B21: 85 | C21: 11 | I21: =33+5+4 | K21: 54 | T21: =O21*C21
A22: Hoggs | B22: 56 | I22: =29+16+11 | K22: 0 | T22: =O22*C22
A23: Lambs | C23: 34 | H23: =4 | I23: =33+5 | J23: =3 | K23: 26 | O23: =R23/H23 | R23: 0.02 | T23: =O23*C23 | U23: taken from lamb price in composite sale
A24: Boars | B24: 1 | K24: 1 | T24: =O24*C24
A25: Sows | B25: 2 | K25: 2 | T25: =O25*C25
A26: Pigs | B26: 36 | C26: 24 | H26: 30 | K26: 30 | O26: =R26/H26 | R26: =Receipts!F79 | T26: =O26*C26
A27: Hoggets | B27: 25 | I27: =1 | J27: 24 | K27: 0 | T27: =O27*C27
A28: Piglets | C28: =18+13 | J28: =3+1 | K28: 27 | T28: =O28*C28
A29: Swans | T29: =O29*C29
A30: Peacocks | B30: 8 | H30: 3 | J30: 2 | K30: 3 | O30: =R30/H30 | R30: =Receipts!F78 | T30: =O30*C30
A31: Total Value | R31: =SUM(R5:R30) | T31: =SUM(T7:T30)
A34: Wool
A35: Coarse wool | C35: 158 | J35: =13+1+144 | O35: 0.02 | T35: =O35*J35
A36: Lamb's wool
A37: Wool locks
A38: Wool sold at shearing
A39: Total wool | T39: =SUM(T35:T38)
A42: Hides
A43: Ox hides
A44: Mare
A45: Steer
A46: calves
A47: pigs
A48: Woolskins
A49: wethers | C49: 94
A50: rams
A51: ewes | C51: 34
A52: hoggs | C52: 29
A53: Woolskins | C53: =SUM(C49:C52) | H53: 146 | I53: 47 | J53: =11 | O53: =R53/H53 | R53: =Receipts!F76 | T53: =O53*C53
A54: Bareskins | T54: =O54*C54
A55: wethers | C55: 1 | H55: 1 | O55: =R55/(H55+H57+H60) | R55: =Receipts!F77 | T55: =O55*C55
A56: rams | T56: =O56*C56
A57: ewes | C57: 5 | H57: 5 | O57: =R57/(H57+H59+H62) | R57: =Receipts!F77 | T57: =O57*C57
A58: hoggs | T58: =O58*C58
A59: Bareskins (total) | T59: =O59*C59
A60: Lambskins | C60: 5 | H60: 5 | O60: =R60/(H60+H62+H65) | R60: =Receipts!F77 | T60: =O60*C60
A61: Rotted skins
A62: Shorn skins
A63: Total | R63: =SUM(R44:R62) | T63: =SUM(T53:T60)
A66: Poultry stock
A67: Hens
A68: Geese | C68: 40 | H68: 40 | O68: =R68/H68 | R68: =Receipts!F55 | T68: =O68*C68
A69: Chickens | C69: 80 | H69: 80 | O69: =R69/H69 | R69: =Receipts!F56 | T69: =O69*C69
A70: Cocks & hens
A71: Total poultry stock | R71: =SUM(R67:R70) | T71: =SUM(T68:T70)
A72: Total poultry excluding churchscot
A74: Poultry production
A75: Eggs | C75: 303 | H75: 303 | O75: =R75/H75 | R75: =Receipts!F57 | T75: =O75*C75
A76: Cocks & hens from churchscot of customary tenants
A77: Sum of above
A78: Total | R78: =SUM(R75:R77) | T78: =SUM(T75:T77)
A81: Meat
A82: Beef
A83: Mutton
A84: Pork
A85: Total
A87: Cheese
A88: Winter cheese | C88: 41 | H88: 41 | O88: =R88/H88 | R88: =Receipts!F45 | T88: =O88*C88
A89: Summer cheese | C89: 158 | H89: 142 | I89: =15+1 | O89: =R89/H89 | R89: =Receipts!F46 | T89: =O89*C89
A90: Total | R90: =SUM(R88:R89) | T90: =SUM(T88:T89)
A92: Butter
A93: Butter | C93: 17 | H93: 17 | R93: =Receipts!F47 | T93: =R93
A94: Total | R94: =R93 | T94: =SUM(T93)
A96: Total Dairy Sales
A99: Honey
A100: Honey | R100: =Receipts!F48 | T100: =R100
A101: Total | R101: =R100 | T101: =SUM(T100)
A103: Additional Information (not necessarily useful)
A104: Utensils
A105: ploughs
A106: carts
A107: cart-ropes
A108: corn baskets
A109: seed-sacks
A110: seed basket
A111: locks for the doors
A112: lead vessel
A113: brass pots
A114: pans
... A129: brass posnets

Sheet raw data
A1: Heading | B1: Sentence | C1: Total in Pounds | D1: Pounds | E1: Shillings | F1: Pence | G1: Corn | H1: Total Quarters Except 1 | I1: Total Bushels Except 1 | J1: Total Corn Cross-Check | K1: Total Corn Manorial Account | L1: Corn Quantity Error | M1: Quarters 1 | N1: Bushels 1 | O1: Quarters 2 | P1: Bushels 2 | Q1: Quarters 3 | R1: Bushels 3 | S1: Quarters 4 | T1: Bushels 4 | U1: shilling a quarter 1 | V1: pence a quarter 1 | W1: shilling a quarter 2 | X1: pence a quarter 2 | Y1: shilling a quarter 3 | Z1: pence a quarter 3 | AA1: shilling a quarter 4 | AB1: pence a quarter 4 | AC1: shilling a bushel 1 | AD1: pence a bushel 1 | AE1: shilling a bushel 2 | AF1: pence a bushel 2 | AG1: shilling a bushel 3 | AH1: pence a bushel 3 | AI1: shilling a bushel 4 | AJ1: pence a bushel 4
A2: Arrears | B2: William, bailiff, and William, reeve, render account for £2 5 shilling 1pence of arrears from the previous year. | C2: 2.25 | D2: 2 | E2: 5 | F2: 1 | H2: 0 | I2: 0 | J2: 0 | K2: 0 | L2: 0 | M2: 0 | N2: 0
A3: Arrears | B3: Delivered to Sir Geoffrey, treasurer of Wolvesey, £2 5 shilling 1pence by 1 tally. | C3: 2.25 | D3: 2 | E3: 5 | F3: 1 | H3: 0 | I3: 0 | J3: 0 | K3: 0 | L3: 0 | M3: 0 | N3: 0
A4: Arrears | B4: They are quit. | C4: 0 | D4: 0 | E4: 0 | F4: 0 | H4: 0 | I4: 0 | J4: 0 | K4: 0 | L4: 0 | M4: 0 | N4: 0
A5: Rents of assize | B5: The same render account for £6 9 shilling 10.5pence for all rents of assize at Christmas. | C5: 6.49 | D5: 6 | E5: 9 | F5: 10.5 | H5: 0 | I5: 0 | J5: 0 | K5: 0 | L5: 0 | M5: 0 | N5: 0
A6: Rents of assize | B6: £6 9 shilling 10.5pence at the Annunciation (25 March). | C6: 6.49 | D6: 6 | E6: 9 | F6: 10.5 | H6: 0 | I6: 0 | J6: 0 | K6: 0 | L6: 0 | M6: 0 | N6: 0
A7: Rents of assize | B7: £6 9 shilling 10.5pence at the Nativity of the blessed John the Baptist (24 June). | C7: 6.49 | D7: 6 | E7: 9 | F7: 10.5 | H7: 0 | I7: 0 | J7: 0 | K7: 0 | L7: 0 | M7: 0 | N7: 0
A8: Rents of assize | B8: £6 9 shilling 10.75pence at Michaelmas (29 September). | C8: 6.49 | D8: 6 | E8: 9 | F8: 10.75 | H8: 0 | I8: 0 | J8: 0 | K8: 0 | L8: 0 | M8: 0 | N8: 0
A9: Rents of assize | B9: Total of all rents for the year, £25 19 shilling 6.25pence | C9: 25.98 | D9: 25 | E9: 19 | F9: 6.25 | H9: 0 | I9: 0 | J9: 0 | K9: 0 | L9: 0 | M9: 0 | N9: 0
A10: Quittances | B10: In quittance of 1 reeve for the year 5 shilling. | C10: 0.25 | D10: 0 | E10: 5 | F10: 0 | H10: 0 | I10: 0 | J10: 0 | K10: 0 | L10: 0 | M10: 0 | N10: 0
A11: Quittances | B11: 1 beadle who is hayward and sowed corn for the year 2 shilling. | C11: 0.1 | D11: 0 | E11: 2 | F11: 0 | H11: 0 | I11: 0 | J11: 0 | K11: 0 | L11: 0 | M11: 0 | N11: 0
A12: Quittances | B12: 1 forester who kept Cherlewod' and Cumbe for the year 2 shilling 2pence. | C12: 0.11 | D12: 0 | E12: 2 | F12: 2 | H12: 0 | I12: 0 | J12: 0 | K12: 0 | L12: 0 | M12: 0 | N12: 0
A13: Quittances | B13: 1 swineherd for the year 2 shilling. | C13: 0.1 | D13: 0 | E13: 2 | F13: 0 | H13: 0 | I13: 0 | J13: 0 | K13: 0 | L13: 0 | M13: 0 | N13: 0
A14: Quittances | B14: 5 of the lord's ploughmen for the year 15 shilling, or 3 shilling each. | C14: 0.75 | D14: 0 | E14: 15 | F14: 0 | H14: 0 | I14: 0 | J14: 0 | K14: 0 | L14: 0 | M14: 0 | N14: 0
A15: Quittances | B15: 4 workers working every day apart from Saturday from Michaelmas until Christmas who, together with the cart-horses of the curia, harrowed lands for wheat and drained water from the same, 3 shilling 10pence, of whom I was quit of 1 shilling 3pence, 1 of 1 shilling, 1 of 10pence, and 1 of 9pence. | C15: 0.19 | D15: 0 | E15: 3 | F15: 10 | G15: wheat | H15: 0 | I15: 0 | J15: 0 | K15: 0 | L15: 0 | M15: 0 | N15: 0
A16: Quittances | B16: 4 workers working the same between Christmas and the Annunciation who, together with the cart-horses of the curia, harrowed lands for oats, 3 shilling 10pence, of whom 3 were each quit of 1 shilling, and 1 of 10pence. | C16: 0.19 | D16: 0 | E16: 3 | F16: 10 | G16: oats | H16: 0 | I16: 0 | J16: 0 | K16: 0 | L16: 0 | M16: 0 | N16: 0
A17: Quittances | B17: 2 workers working the same between the Annunciation and the Nativity of the blessed John the Baptist who harrowed lands for barley and enclosed with hedges, 1 shilling 10.5pence, of whom 1 was quit of 1 shilling, and 1 of 10.5pence. | C17: 0.09 | D17: 0 | E17: 1 | F17: 10.5 | G17: barley | H17: 0 | I17: 0 | J17: 0 | K17: 0 | L17: 0 | M17: 0 | N17: 0
A18: Quittances | B18: 10 workers working the same between the feast of St John the Baptist and Michaelmas who weeded corn, mowed and gathered hay, and carried corn, 10 shilling 3pence, of whom 1 was quit of 1 shilling 3pence, and 9 of 1 shilling each. | C18: 0.51 | D18: 0 | E18: 10 | F18: 3 | H18: 0 | I18: 0 | J18: 0 | K18: 0 | L18: 0 | M18: 0 | N18: 0
A19: Quittances | B19: Total of quittances, £2 5 shilling 11.5pence | C19: 2.3 | D19: 2 | E19: 5 | F19: 11.5 | H19: 0 | I19: 0 | J19: 0 | K19: 0 | L19: 0 | M19: 0 | N19: 0
A20: Defaults of rent | B20: In default of the land of the earl of Salisbury at Gaddesden 18 shilling Total of defaults of rent, 18 shilling | C20: 0.9 | D20: 0 | E20: 18 | F20: 0 | H20: 0 | I20: 0 | J20: 0 | K20: 0 | L20: 0 | M20: 0 | N20: 0
A21: Total of quittances and defaults of rent | B21: Total of quittances and defaults of rent, £3 3 shilling 11.5pence | C21: 3.2 | D21: 3 | E21: 3 | F21: 11.5 | H21: 0 | I21: 0 | J21: 0 | K21: 0 | L21: 0 | M21: 0 | N21: 0
A22: Total remaining | B22: Total remaining, £22 15 shilling 6.25pence | C22: 22.78 | D22: 22 | E22: 15 | F22: 6.25 | H22: 0 | I22: 0 | J22: 0 | K22: 0 | L22: 0 | M22: 0 | N22: 0
A23: Issues of the manor | B23: The same render account for 9 shilling 8pence from pannage of pigs of the whole vill. | C23: 0.48 | D23: 0 | E23: 9 | F23: 8 | H23: 0 | I23: 0 | J23: 0 | K23: 0 | L23: 0 | M23: 0 | N23: 0
A24: Issues of the manor | B24: nothing from foreign pannage because there was no mast. | C24: 0 | D24: 0 | E24: 0 | F24: 0 | H24: 0 | I24: 0 | J24: 0 | K24: 0 | L24: 0 | M24: 0 | N24: 0
A25: Issues of the manor | B25: £1 from dead wood blown down by the wind in Cherlewod'. | C25: 1 | D25: 1 | E25: 0 | F25: 0 | H25: 0 | I25: 0 | J25: 0 | K25: 0 | L25: 0 | M25: 0 | N25: 0
A26: Issues of the manor | B26: 10 shilling from winter ploughing this year, that is, 6pence a ploughman from 20 ploughmen. | C26: 0.53 | D26: 0 | E26: 10 | F26: 6 | H26: 0 | I26: 0 | J26: 0 | K26: 0 | L26: 0 | M26: 0 | N26: 0
A27: Issues of the manor | B27: nothing from Lenten ploughing because it was ploughed. | C27: 0 | D27: 0 | E27: 0 | F27: 0 | H27: 0 | I27: 0 | J27: 0 | K27: 0 | L27: 0 | M27: 0 | N27: 0
A28: Issues of the manor | B28: 5 shilling from 10 ploughmen for release from summer ploughing, at 6pence a ploughman. | C28: 0.28 | D28: 0 | E28: 5 | F28: 6 | H28: 0 | I28: 0 | J28: 0 | K28: 0 | L28: 0 | M28: 0 | N28: 0
A29: Issues of the manor | B29: £1 10 shilling 3pence from 60.5 virgates of land for release from transport-service this year, at 6pence a virgate, because no transport-service was done to London or elsewhere. | C29: 1.51 | D29: 1 | E29: 10 | F29: 3 | H29: 0 | I29: 0 | J29: 0 | K29: 0 | L29: 0 | M29: 0 | N29: 0
... A79: Annual recognizance | B79: Total, 3 shilling 3pence | C79: 0.16 | D79: 0 | E79: 3 | F79: 3 | H79: 0 | I79: 0 | J79: 0 | K79: 0 | L79: 0 | M79: 0 | N79: 0
A80: Corn and malt mill' | B80: The same render account for £2 19 shilling 11pence from 23 quarters 5 bushels of corn from the whole issue of the mill sold, at 3 shilling a quarters for 8 quarters, 2 shilling 8pence a quarters for 7 quarters, and 2 shilling a quarters for 8 quarters 5 bushels. | C80: 3 | D80: 2 | E80: 19 | F80: 11 | H80: 23 | I80: 5 | J80: 23.625 | K80: 23.625 | L80: 0 | M80: 23 | N80: 5 | O80: 8 | P80: 0 | Q80: 7 | R80: 0 | S80: 8 | T80: 5 | U80: 3 | V80: 0 | W80: 2 | X80: 8 | Y80: 2 | Z80: 0
A81: Corn and malt mill' | B81: 10 shilling 4pence from 3 quarters 5 bushels of malfsold, at 3 shilling a quarters for 2 quarters, and 2 shilling 8pence a quarters for 1 quarters 5 bushels Total, £3 10 shilling 3pence | C81: 3.51 | D81: 3 | E81: 10 | F81: 3 | H81: 3 | I81: 5 | J81: 3.625 | K81: 3.625 | L81: 0 | M81: 3 | N81: 5 | O81: 2 | P81: 0 | Q81: 1 | R81: 5 | U81: 3 | V81: 0 | W81: 2 | X81: 8
A82: Wheat, barley, oats and beans sold | B82: The same render account for £41 14 shilling from 168 quarters of wheat sold, at 5 shilling a quarters for 162 quarters, and 4 shilling a quarters for 6 quarters. | C82: 41.7 | D82: 41 | E82: 14 | F82: 0 | G82: wheat | H82: 168 | I82: 0 | J82: 168 | K82: 168 | L82: 0 | M82: 168 | N82: 0 | O82: 162 | P82: 0 | Q82: 6 | R82: 0 | U82: 5 | V82: 0 | W82: 4 | X82: 0
A83: Wheat, barley, oats and beans sold | B83: £2 2 shilling 3pence from 9 quarters 6 bushels of wheat sold for the queen's use, at 4 shilling 4pence a quarters. | C83: 2.11 | D83: 2 | E83: 2 | F83: 3 | G83: wheat | H83: 9 | I83: 6 | J83: 9.75 | K83: 9.75 | L83: 0 | M83: 9 | N83: 6 | U83: 4 | V83: 4
A84: Wheat, barley, oats and beans sold | B84: £1 13 shilling 4pence from 10 quarters of barley sold, at 3 shilling 4pence a quarters. | C84: 1.67 | D84: 1 | E84: 13 | F84: 4 | G84: barley | H84: 10 | I84: 0 | J84: 10 | K84: 10 | L84: 0 | M84: 10 | N84: 0 | U84: 3 | V84: 4
A85: Wheat, barley, oats and beans sold | B85: £5 1 shilling from 60.5 quarters of oats from the demesne sold, at 2 shilling a quarters for 20.5 quarters, and 1 shilling 6pence a quarters for 40 quarters. | C85: 5.05 | D85: 5 | E85: 1 | F85: 0 | G85: oats | H85: 60.5 | I85: 0 | J85: 60.5 | K85: 60.5 | L85: 0 | M85: 60.5 | N85: 0 | O85: 20.5 | P85: 0 | Q85: 40 | R85: 0 | U85: 2 | V85: 0 | W85: 1 | X85: 6
A86: Wheat, barley, oats and beans sold | B86: £3 18 shilling 9pence from 39 quarters 3 bushels of oats from the vill sold according to custom, at 2 shilling a quarters. | C86: 3.94 | D86: 3 | E86: 18 | F86: 9 | G86: oats | H86: 39 | I86: 3 | J86: 39.375 | K86: 39.375 | L86: 0 | M86: 39 | N86: 3 | U86: 2 | V86: 0
A87: Wheat, barley, oats and beans sold | B87: 12 shilling 3pence from 6 quarters 1 bushels of beans sold, at 2 shilling a quarters. | C87: 0.61 | D87: 0 | E87: 12 | F87: 3 | G87: beans | H87: 6 | I87: 1 | J87: 6.125 | K87: 6.125 | L87: 0 | M87: 6 | N87: 1 | U87: 2 | V87: 0
A88: Wheat, barley, oats and beans sold | B88: 1 shilling 5.5pence from 3.5 bushels of barley sold at the audit, at 5pence a bushels Total of all corn sold, £55 3 shilling 0.5pence | C88: 55.15 | D88: 55 | E88: 3 | F88: 0.5 | G88: barley | H88: 0 | I88: 3.5 | J88: 0.4375 | K88: 0.4375 | L88: 0 | M88: 0 | N88: 3.5 | AC88: 0 | AD88: 5
A89: Entry and marriage fines | B89: The same render account for 2 shilling from Geoffrey atte Slade for marrying Matilda his daughter outside. | C89: 0.1 | D89: 0 | E89: 2 | F89: 0 | H89: 0 | I89: 0 | J89: 0 | K89: 0 | L89: 0 | M89: 0 | N89: 0
A90: Entry and marriage fines | B90: 1 shilling from Agnes atte Slad' for marrying herself within. | C90: 0.05 | D90: 0 | E90: 1 | F90: 0 | H90: 0 | I90: 0 | J90: 0 | K90: 0 | L90: 0 | M90: 0 | N90: 0
A91: Entry and marriage fines | B91: 2 shilling from Matilda la Dreyestr' for marrying Alice her daughter outside. | C91: 0.1 | D91: 0 | E91: 2 | F91: 0 | H91: 0 | I91: 0 | J91: 0 | K91: 0 | L91: 0 | M91: 0 | N91: 0
A92: Entry and marriage fines | B92: 2 shilling from Muriel, who was wife of William Peck', to retain 1 house and .5 acre of assarted land which belonged to the said William her husband. | C92: 0.1 | D92: 0 | E92: 2 | F92: 0 | H92: 0 | I92: 0 | J92: 0 | K92: 0 | L92: 0 | M92: 0 | N92: 0
A93: Entry and marriage fines | B93: 13 shilling 4pence from Walter Molendinarius to have Alice atte Pund' with her land. | C93: 0.67 | D93: 0 | E93: 13 | F93: 4 | H93: 0 | I93: 0 | J93: 0 | K93: 0 | L93: 0 | M93: 0 | N93: 0
A94: Entry and marriage fines | B94: 2 shilling from Juliana, who was wife of Richard Sutoris, to have entry to 1 house which Richard Sutor formerly held. | C94: 0.1 | D94: 0 | E94: 2 | F94: 0 | H94: 0 | I94: 0 | J94: 0 | K94: 0 | L94: 0 | M94: 0 | N94: 0
A95: Entry and marriage fines | B95: £1 6 shilling 8pence from John, son of John Jacob, for entry to two virgates of land which the said John his father held. | C95: 1.33 | D95: 1 | E95: 6 | F95: 8 | H95: 0 | I95: 0 | J95: 0 | K95: 0 | L95: 0 | M95: 0 | N95: 0
A96: Entry and marriage fines | B96: 4 shilling from Richard le Wych' for marrying Leticia his daughter within. | C96: 0.2 | D96: 0 | E96: 4 | F96: 0 | H96: 0 | I96: 0 | J96: 0 | K96: 0 | L96: 0 | M96: 0 | N96: 0
A97: Entry and marriage fines | B97: 6 shilling 8pence from Walter Bast for marrying Matilda his daughter outside. | C97: 0.33 | D97: 0 | E97: 6 | F97: 8 | H97: 0 | I97: 0 | J97: 0 | K97: 0 | L97: 0 | M97: 0 | N97: 0
A98: Entry and marriage fines | B98: 3 shilling 4pence from John Bucok' to have entry to 1 butt of land by concession and surrender of John Hod, and he will relieve the said John Hod of 4pence annual rent. | C98: 0.17 | D98: 0 | E98: 3 | F98: 4 | H98: 0 | I98: 0 | J98: 0 | K98: 0 | L98: 0 | M98: 0 | N98: 0
A99: Entry and marriage fines | B99: 3 shilling 6pence from William le Careter to have entry to 1.5 acres of assart by concession and surrender of Robert de Chyssend'. | C99: 0.17 | D99: 0 | E99: 3 | F99: 6 | H99: 0 | I99: 0 | J99: 0 | K99: 0 | L99: 0 | M99: 0 | N99: 0
A100: Entry and marriage fines | B100: £4 from William, son of Herbert Reygnild, to have entry to 1 messuage with 1 virgate of customary land which he has held of his father because his elder brother John said in full court that he was unwilling to fine for the said land, that is, he quitclaimed wholly his right to the use of the said William. | C100: 4 | D100: 4 | E100: 0 | F100: 0 | H100: 0 | I100: 0 | J100: 0 | K100: 0 | L100: 0 | M100: 0 | N100: 0
... A110: Expenses for ploughs | B110: 2 ploughshares bought 1 shilling 6pence Moreover they have 1 ploughshare as made clear above. | C110: 0.08 | D110: 0 | E110: 1 | F110: 6 | H110: 0 | I110: 0 | J110: 0 | K110: 0 | L110: 0 | M110: 0 | N110: 0
A111: Expenses for ploughs | B111: Nothing accounted for forging the said ironwork because the smith takes 2 acres of wheat as they lie in the field for forging the same when the ploughmen are ploughing for the whole year. | C111: 0 | D111: 0 | E111: 0 | F111: 0 | G111: wheat | H111: 0 | I111: 0 | J111: 0 | K111: 0 | L111: 0 | M111: 0 | N111: 0
A112: Expenses for ploughs | B112: . | C112: 0 | D112: 0 | E112: 0 | F112: 0 | H112: 0 | I112: 0 | J112: 0 | K112: 0 | L112: 0 | M112: 0 | N112: 0
A113: Expenses for ploughs | B113: 4 iron spurs bought 8pence. | C113: 0.03 | D113: 0 | E113: 0 | F113: 8 | H113: 0 | I113: 0 | J113: 0 | K113: 0 | L113: 0 | M113: 0 | N113: 0
A114: Expenses for ploughs | B114: stipend of 1 carpenter making new ploughs, repairing old ploughs, and making harrows and yokes from the lord's timber 3 shilling 2pence, because the manorial servant who by custom made these is deapence. | C114: 0.16 | D114: 0 | E114: 3 | F114: 2 | H114: 0 | I114: 0 | J114: 0 | K114: 0 | L114: 0 | M114: 0 | N114: 0
A115: Expenses for ploughs | B115: 15 oxen bought £8 18 shilling 2pence, at 13 shilling 5pence each for 2, 12 shilling 6pence each for 4, 12 shilling each for 3, 11 shilling 5pence each for 3, 10 shilling 6.51. each for 2, and 10 shilling for 1.. | C115: 8.91 | D115: 8 | E115: 18 | F115: 2 | H115: 0 | I115: 0 | J115: 0 | K115: 0 | L115: 0 | M115: 0 | N115: 0
A116: Expenses for ploughs | B116: 12 quarters 2 bushels of wheat bought for sowing £2 4 shilling 11pence, at 3 shilling 8pence a quarters. | C116: 2.25 | D116: 2 | E116: 4 | F116: 11 | G116: wheat | H116: 12 | I116: 2 | J116: 12.25 | K116: 12.25 | L116: 0 | M116: 12 | N116: 2 | U116: 3 | V116: 8
A117: Expenses for ploughs | B117: . | C117: 0 | D117: 0 | E117: 0 | F117: 0 | H117: 0 | I117: 0 | J117: 0 | K117: 0 | L117: 0 | M117: 0 | N117: 0
A118: Expenses for ploughs | B118: 34 quarters of maslin bought for the liveries of the manorial servants £4 4 shilling, at 3 shilling a quarters for 8 quarters, 2 shilling 8pence a quarters for 12 quarters, and 2 shilling a quarters for 14 quarters. | C118: 4.2 | D118: 4 | E118: 4 | F118: 0 | G118: maslin | H118: 34 | I118: 0 | J118: 34 | K118: 34 | L118: 0 | M118: 34 | N118: 0 | O118: 8 | P118: 0 | Q118: 12 | R118: 0 | S118: 14 | T118: 0 | U118: 3 | V118: 0 | W118: 2 | X118: 8 | Y118: 2 | Z118: 0
A119: Expenses for ploughs | B119: . | C119: 0 | D119: 0 | E119: 0 | F119: 0 | H119: 0 | I119: 0 | J119: 0 | K119: 0 | L119: 0 | M119: 0 | N119: 0
A120: Expenses for ploughs | B120: 4.5 quarters of oats bought for fodder of horses 6 shilling 9pence, at 1 shilling 6pence a quarters. | C120: 0.34 | D120: 0 | E120: 6 | F120: 9 | G120: oats | H120: 4.5 | I120: 0 | J120: 4.5 | K120: 4.5 | L120: 0 | M120: 4.5 | N120: 0 | U120: 1 | V120: 6
A121: Expenses for ploughs | B121: . | C121: 0 | D121: 0 | E121: 0 | F121: 0 | H121: 0 | I121: 0 | J121: 0 | K121: 0 | L121: 0 | M121: 0 | N121: 0
A122: Expenses for ploughs | B122: hay bought £1, because hay was taken for the queen's use. | C122: 1 | D122: 1 | E122: 0 | F122: 0 | H122: 0 | I122: 0 | J122: 0 | K122: 0 | L122: 0 | M122: 0 | N122: 0
A123: Expenses for ploughs | B123: . | C123: 0 | D123: 0 | E123: 0 | F123: 0 | H123: 0 | I123: 0 | J123: 0 | K123: 0 | L123: 0 | M123: 0 | N123: 0
A124: Expenses for ploughs | B124: forage bought for stock £1 16 shilling Ipence. | C124: 1.8 | D124: 1 | E124: 16 | F124: 0 | H124: 0 | I124: 0 | J124: 0 | K124: 0 | L124: 0 | M124: 0 | N124: 0
A125: Expenses for ploughs | B125: stipend of 5 oxherds for .5 year in winter 6 shilling 8pence, or 1 shilling 4pence each, because each manorial servant takes corn at harvest-time for the other .5 year in summer, that is,' acre of wheat and .5 acre of oats as they lie in the fie1pence Total, £19 8 shilling 3pence | C125: 19.41 | D125: 19 | E125: 8 | F125: 3 | G125: oats, wheat | H125: 0 | I125: 0 | J125: 0 | K125: 0 | L125: 0 | M125: 0 | N125: 0
A126: Expenses for carts and wagons | B126: In clouts and nails for the cart for the year 1 shilling 2pence. | C126: 0.06 | D126: 0 | E126: 1 | F126: 2 | H126: 0 | I126: 0 | J126: 0 | K126: 0 | L126: 0 | M126: 0 | N126: 0
A127: Expenses for carts and wagons | B127: white leather for mending harnesses of the cart 1 shilling 1pence. | C127: 0.05 | D127: 0 | E127: 1 | F127: 1 | H127: 0 | I127: 0 | J127: 0 | K127: 0 | L127: 0 | M127: 0 | N127: 0
A128: Expenses for carts and wagons | B128: grease bought for the year 4pence. | C128: 0.02 | D128: 0 | E128: 0 | F128: 4 | H128: 0 | I128: 0 | J128: 0 | K128: 0 | L128: 0 | M128: 0 | N128: 0
A129: Expenses for carts and wagons | B129: 5 halters for plough-horses made from their own hair 1pence. | C129: 0 | D129: 0 | E129: 0 | F129: 1 | H129: 0 | I129: 0 | J129: 0 | K129: 0 | L129: 0 | M129: 0 | N129: 0
A130: Expenses for carts and wagons | B130: mending saddle-pads 1.5pence. | C130: 0.01 | D130: 0 | E130: 0 | F130: 1.5 | H130: 0 | I130: 0 | J130: 0 | K130: 0 | L130: 0 | M130: 0 | N130: 0
A131: Expenses for carts and wagons | B131: 1 collar bought 6pence. | C131: 0.03 | D131: 0 | E131: 0 | F131: 6 | H131: 0 | I131: 0 | J131: 0 | K131: 0 | L131: 0 | M131: 0 | N131: 0
A132: Expenses for carts and wagons | B132: a wooden base for 1 cart-saddle 1.5pence. | C132: 0.01 | D132: 0 | E132: 0 | F132: 1.5 | H132: 0 | I132: 0 | J132: 0 | K132: 0 | L132: 0 | M132: 0 | N132: 0
A133: Expenses for carts and wagons | B133: repairing old collars 1pence. | C133: 0 | D133: 0 | E133: 0 | F133: 1 | H133: 0 | I133: 0 | J133: 0 | K133: 0 | L133: 0 | M133: 0 | N133: 0
A134: Expenses for carts and wagons | B134: 1 pair of traces bought 7pence. | C134: 0.03 | D134: 0 | E134: 0 | F134: 7 | H134: 0 | I134: 0 | J134: 0 | K134: 0 | L134: 0 | M134: 0 | N134: 0
A135: Expenses for carts and wagons | B135: making 2 pairs of wheels from the lord's timber for the cart with iron tyres and for clearing dung. | C135: 0 | D135: 0 | E135: 0 | F135: 0 | H135: 0 | I135: 0 | J135: 0 | K135: 0 | L135: 0 | M135: 0 | N135: 0
A136: Expenses for carts and wagons | B136: . | C136: 0 | D136: 0 | E136: 0 | F136: 0 | H136: 0 | I136: 0 | J136: 0 | K136: 0 | L136: 0 | M136: 0 | N136: 0
A137: Expenses for carts and wagons | B137: new large nails and clamps and frets with the stipend of the smith fitting 1 pair of wheels with old iron tyres 6 shilling 2pence. | C137: 0.31 | D137: 0 | E137: 6 | F137: 2 | H137: 0 | I137: 0 | J137: 0 | K137: 0 | L137: 0 | M137: 0 | N137: 0
... A146: Dairy | B146: a press 3pence. | C146: 0.01 | D146: 0 | E146: 0 | F146: 3 | H146: 0 | I146: 0 | J146: 0 | K146: 0 | L146: 0 | M146: 0 | N146: 0
A147: Dairy | B147: .5 quarters of salt bought 1 shilling 10pence, at 7pence for 1 bushels, and 5pence each for 3 bushels. | C147: 0.09 | D147: 0 | E147: 1 | F147: 10 | H147: 5 | I147: 4 | J147: 5.5 | K147: 5 | L147: 0.5 | M147: 5 | N147: 0 | O147: 0 | P147: 1 | Q147: 0 | R147: 3
A148: Dairy | B148: 1 colander bought 1.5pence. | C148: 0.01 | D148: 0 | E148: 0 | F148: 1.5 | H148: 0 | I148: 0 | J148: 0 | K148: 0 | L148: 0 | M148: 0 | N148: 0
A149: Dairy | B149: vinegar and pigs' fat for greasing sick sheep 5 shilling 3pence. | C149: 0.26 | D149: 0 | E149: 5 | F149: 3 | H149: 0 | I149: 0 | J149: 0 | K149: 0 | L149: 0 | M149: 0 | N149: 0
A150: Dairy | B150: hurdles for the fold, nothing this year. | C150: 0 | D150: 0 | E150: 0 | F150: 0 | H150: 0 | I150: 0 | J150: 0 | K150: 0 | L150: 0 | M150: 0 | N150: 0
A151: Dairy | B151: . | C151: 0 | D151: 0 | E151: 0 | F151: 0 | H151: 0 | I151: 0 | J151: 0 | K151: 0 | L151: 0 | M151: 0 | N151: 0
A152: Dairy | B152: 5 ells of canvas for packing wool 1 shilling 1.5pence, at 2.5pence an ell. | C152: 0.06 | D152: 0 | E152: 1 | F152: 1.5 | H152: 0 | I152: 0 | J152: 0 | K152: 0 | L152: 0 | M152: 0 | N152: 0
A153: Dairy | B153: . | C153: 0 | D153: 0 | E153: 0 | F153: 0 | H153: 0 | I153: 0 | J153: 0 | K153: 0 | L153: 0 | M153: 0 | N153: 0
A154: Dairy | B154: stipend of 1 shepherd and 1 cowherd in winter 2 shilling, because for the other .5 year they take corn in the field like the rest of the manorial servants. | C154: 0.1 | D154: 0 | E154: 2 | F154: 0 | H154: 0 | I154: 0 | J154: 0 | K154: 0 | L154: 0 | M154: 0 | N154: 0
A155: Dairy | B155: . | C155: 0 | D155: 0 | E155: 0 | F155: 0 | H155: 0 | I155: 0 | J155: 0 | K155: 0 | L155: 0 | M155: 0 | N155: 0
A156: Dairy | B156: stipend of 1 dairymaid this year 2 shilling 6pence, because for 13 weeks there was no dairymaipence. | C156: 0.12 | D156: 0 | E156: 2 | F156: 6 | H156: 0 | I156: 0 | J156: 0 | K156: 0 | L156: 0 | M156: 0 | N156: 0
A157: Dairy | B157: carrying wool to Wolvesey 4pence Total, 13 shilling 11.5pence | C157: 0.67 | D157: 0 | E157: 13 | F157: 4 | H157: 0 | I157: 0 | J157: 0 | K157: 0 | L157: 0 | M157: 0 | N157: 0
A158: Expenses of buildings and small necessaries | B158: In propping up the wardrobe of the bishop's chamber 2pence. | C158: 0.01 | D158: 0 | E158: 0 | F158: 2 | H158: 0 | I158: 0 | J158: 0 | K158: 0 | L158: 0 | M158: 0 | N158: 0
A159: Expenses of buildings and small necessaries | B159: re-roofing in places the larger barn, unroofed by the wind, where it was necessary 1 shilling 8pence. | C159: 0.08 | D159: 0 | E159: 1 | F159: 8 | H159: 0 | I159: 0 | J159: 0 | K159: 0 | L159: 0 | M159: 0 | N159: 0
... A162: Expenses of buildings and small necessaries | B162: 1 lock with a key bought for the garden-gate 1.5pence. | C162: 0.01 | D162: 0 | E162: 0 | F162: 1.5 | H162: 0 | I162: 0 | J162: 0 | K162: 0 | L162: 0 | M162: 0 | N162: 0
A163: Expenses of buildings and small necessaries | B163: iplantingl and watering beans 10pence. | C163: 0.04 | D163: 0 | E163: 0 | F163: 10 | G163: beans | H163: 0 | I163: 0 | J163: 0 | K163: 0 | L163: 0 | M163: 0 | N163: 0
A164: Expenses of buildings and small necessaries | B164: gelding (masculand') 26 piglets 5.5pence Total, 4 shilling 9pence | C164: 0.22 | D164: 0 | E164: 4 | F164: 5.5 | H164: 0 | I164: 0 | J164: 0 | K164: 0 | L164: 0 | M164: 0 | N164: 0
A165: Mowing of the meadow | B165: In customary payment for the mowing of the meadow 1 shilling Total, 1 shilling | C165: 0.05 | D165: 0 | E165: 1 | F165: 0 | H165: 0 | I165: 0 | J165: 0 | K165: 0 | L165: 0 | M165: 0 | N165: 0
A166: Purchase of stock | B166: In 28 wethers bought before shearing £2 8 shilling 7pence, at 1 shilling 9pence each for 18, and 1s 8.5pence each for 10. Total, £2 8 shilling 7pence | C166: 2.43 | D166: 2 | E166: 8 | F166: 7 | H166: 0 | I166: 0 | J166: 0 | K166: 0 | L166: 0 | M166: 0 | N166: 0
A167: Threshing and winnowing | B167: In mending 1 new sieve and other old ones 3.5pence. | C167: 0.01 | D167: 0 | E167: 0 | F167: 3.5 | H167: 0 | I167: 0 | J167: 0 | K167: 0 | L167: 0 | M167: 0 | N167: 0
A168: Threshing and winnowing | B168: 1 new sack bought 9.25d remaking (refit') old broken baskets 2pence. | C168: 0.01 | D168: 0 | E168: 0 | F168: 2 | H168: 0 | I168: 0 | J168: 0 | K168: 0 | L168: 0 | M168: 0 | N168: 0
...

Sheet Issues of the Grange raw
A1: Heading | B1: Sentence | C1: Quarters 1_x | D1: Bushels 1_x | E1: Sown Quarters | F1: Sown Bushels | G1: Sown Total Quarters | H1: Bought in Quarters | I1: Bought in Bushels | J1: Bought in Total Quarters | K1: Tithe Quarters | L1: Tithe Bushels | M1: Tithe Total Quarters | N1: Manorial servants & livestock Quarters | O1: Manorial servants & livestock Bushels | P1: Manorial servants & livestock Total Quarters | Q1: Sold Quarters | R1: Sold Bushels | S1: Sold Total Quarters | T1: Account Quarters | U1: Account Bushels | V1: Account Total Quarters | W1: bought only | X1: Total Quarters Except 1 | Y1: Total Bushels Except 1 | Z1: Total Corn Cross-Check | AA1: Total Corn Manorial Account | AB1: Corn Quantity Error | AC1: Quarters 1_y | AD1: Bushels 1_y | AE1: Quarters 2 | AF1: Bushels 2 | AG1: Quarters 3 | AH1: Bushels 3 | AI1: Quarters 4 | AJ1: Bushels 4
A2: Cash deliveries | B2: Total | C2: 0 | D2: 0 | E2: 0 | F2: 0 | G2: 0 | H2: 0 | I2: 0 | J2: 0 | K2: 0 | L2: 0 | M2: 0 | N2: 0 | O2: 0 | P2: 0 | Q2: 0 | R2: 0 | S2: 0 | T2: 0 | U2: 0 | V2: 0 | W2: 0
A3: Wheat | B3: (yield: 5-fold less . . . quarters 2 bushels} | C3: 0 | D3: 0 | E3: 0 | F3: 0 | G3: 0 | H3: 0 | I3: 0 | J3: 0 | K3: 0 | L3: 0 | M3: 0 | N3: 0 | O3: 0 | P3: 0 | Q3: 0 | R3: 0 | S3: 0 | T3: 0 | U3: 0 | V3: 0 | W3: 0 | X3: 0 | Y3: 2 | Z3: 0.25 | AA3: 0.25 | AB3: 0 | AC3: 0 | AD3: 2
A4: Wheat | B4: The same render account for 201 quarters 5 bushels of wheat from the whole issue of the grange in the granary by struck measure. | C4: 0 | D4: 0 | E4: 0 | F4: 0 | G4: 0 | H4: 0 | I4: 0 | J4: 0 | K4: 0 | L4: 0 | M4: 0 | N4: 0 | O4: 0 | P4: 0 | Q4: 0 | R4: 0 | S4: 0 | T4: 201 | U4: 5 | V4: 201.625 | W4: 0 | X4: 201 | Y4: 5 | Z4: 201.625 | AA4: 201.625 | AB4: 0 | AC4: 201 | AD4: 5
A5: Wheat | B5: 6.5 quarters by estimation given to the manorial servants in acres as they lie in the field. | C5: 0 | D5: 0 | E5: 0 | F5: 0 | G5: 0 | H5: 0 | I5: 0 | J5: 0 | K5: 0 | L5: 0 | M5: 0 | N5: 0 | O5: 0 | P5: 0 | Q5: 0 | R5: 0 | S5: 0 | T5: 0 | U5: 0 | V5: 0 | W5: 0 | X5: 6.5 | Y5: 0 | Z5: 6.5 | AA5: 6.5 | AB5: 0 | AC5: 6.5 | AD5: 0
A6: Wheat | B6: 12 quarters 2 bushels bought. | C6: 0 | D6: 0 | E6: 0 | F6: 0 | G6: 0 | H6: 12 | I6: 2 | J6: 12.25 | K6: 0 | L6: 0 | M6: 0 | N6: 0 | O6: 0 | P6: 0 | Q6: 0 | R6: 0 | S6: 0 | T6: 0 | U6: 0 | V6: 0 | W6: 0 | X6: 12 | Y6: 2 | Z6: 12.25 | AA6: 12.25 | AB6: 0 | AC6: 12 | AD6: 2
A7: Wheat | B7: Total, 220 quarters 3 bushels Sown over 84 acres measured by the perch which lie in the middle field, 32 quarters 2 bushels. | C7: 0 | D7: 0 | E7: 252 | F7: 5 | G7: 252.625 | H7: 0 | I7: 0 | J7: 0 | K7: 0 | L7: 0 | M7: 0 | N7: 0 | O7: 0 | P7: 0 | Q7: 0 | R7: 0 | S7: 0 | T7: 0 | U7: 0 | V7: 0 | W7: 0 | X7: 32 | Y7: 2 | Z7: 32.25 | AA7: 220.375 | AB7: -188.125 | AC7: 220 | AD7: 3 | AE7: 32 | AF7: 2
A8: Wheat | B8: that 3 bushels an acre, plus 6 bushels in all, because the sowing season was showery and miry. | C8: 0 | D8: 0 | E8: 0 | F8: 0 | G8: 0 | H8: 0 | I8: 0 | J8: 0 | K8: 0 | L8: 0 | M8: 0 | N8: 0 | O8: 0 | P8: 0 | Q8: 0 | R8: 0 | S8: 0 | T8: 0 | U8: 0 | V8: 0 | W8: 0 | X8: 0 | Y8: 6 | Z8: 0.75 | AA8: 0.375 | AB8: 0.375 | AC8: 0 | AD8: 3 | AE8: 0 | AF8: 6
A9: Wheat | B9: and know that two roods were sown by workers with their own seepence. | C9: 0 | D9: 0 | E9: 0 | F9: 0 | G9: 0 | H9: 0 | I9: 0 | J9: 0 | K9: 0 | L9: 0 | M9: 0 | N9: 0 | O9: 0 | P9: 0 | Q9: 0 | R9: 0 | S9: 0 | T9: 0 | U9: 0 | V9: 0 | W9: 0 | X9: 0 | Y9: 0 | Z9: 0 | AA9: 0 | AB9: 0 | AC9: 0 | AD9: 0
A10: Wheat | B10: customary payment for the mowing of the meadows, 6 bushels. | C10: 0 | D10: 0 | E10: 0 | F10: 0 | G10: 0 | H10: 0 | I10: 0 | J10: 0 | K10: 0 | L10: 0 | M10: 0 | N10: 0 | O10: 0 | P10: 0 | Q10: 0 | R10: 0 | S10: 0 | T10: 0 | U10: 0 | V10: 0 | W10: 0 | X10: 0 | Y10: 6 | Z10: 0.75 | AA10: 0.75 | AB10: 0 | AC10: 0 | AD10: 6
A11: Wheat | B11: provision of the steward at the hundred-court of Martinmas, 3 bushels. | C11: 0 | D11: 0 | E11: 0 | F11: 0 | G11: 0 | H11: 0 | I11: 0 | J11: 0 | K11: 0 | L11: 0 | M11: 0 | N11: 0 | O11: 0 | P11: 0 | Q11: 0 | R11: 0 | S11: 0 | T11: 0 | U11: 0 | V11: 0 | W11: 0 | X11: 0 | Y11: 3 | Z11: 0.375 | AA11: 0.375 | AB11: 0 | AC11: 0 | AD11: 3
A12: Wheat | B12: provision of the same at the hundred-court of Hockday in bread, 3 bushels. | C12: 0 | D12: 0 | E12: 0 | F12: 0 | G12: 0 | H12: 0 | I12: 0 | J12: 0 | K12: 0 | L12: 0 | M12: 0 | N12: 0 | O12: 0 | P12: 0 | Q12: 0 | R12: 0 | S12: 0 | T12: 0 | U12: 0 | V12: 0 | W12: 0 | X12: 0 | Y12: 3 | Z12: 0.375 | AA12: 0.375 | AB12: 0 | AC12: 0 | AD12: 3
A13: Wheat | B13: provision of the bailiff from Michaelmas until the feast of St Thomas the Apostle (21 December) in bread, 1.5 quarters, because he took the rest at West Wycombe. | C13: 0 | D13: 0 | E13: 0 | F13: 0 | G13: 0 | H13: 0 | I13: 0 | J13: 0 | K13: 0 | L13: 0 | M13: 0 | N13: 0 | O13: 0 | P13: 0 | Q13: 0 | R13: 0 | S13: 0 | T13: 0 | U13: 0 | V13: 0 | W13: 0 | X13: 1.5 | Y13: 0 | Z13: 1.5 | AA13: 1.5 | AB13: 0 | AC13: 1.5 | AD13: 0
A14: Wheat | B14: Given to the manorial servants for their stipend by estimation in acres as they lie in the field, 6.5 quarters. | C14: 0 | D14: 0 | E14: 0 | F14: 0 | G14: 0 | H14: 0 | I14: 0 | J14: 0 | K14: 0 | L14: 0 | M14: 0 | N14: 0 | O14: 0 | P14: 0 | Q14: 0 | R14: 0 | S14: 0 | T14: 0 | U14: 0 | V14: 0 | W14: 0 | X14: 6.5 | Y14: 0 | Z14: 6.5 | AA14: 6.5 | AB14: 0 | AC14: 6.5 | AD14: 0
A15: Wheat | B15: that is, 2 quarters to 1 smith for the year, 4.5 quarters to 1 carter, 5 ploughmen, 1 miller, 1 cowherd and 1 shepherd for 0.5 year in summer. (Henceforth the manorial servants should be hired for money just like the [other] workers in the manor and the corn be reserved for the use of the lord). | C15: 0 | D15: 0 | E15: 0 | F15: 0 | G15: 0 | H15: 0 | I15: 0 | J15: 0 | K15: 0 | L15: 0 | M15: 0 | N15: 0 | O15: 0 | P15: 0 | Q15: 0 | R15: 0 | S15: 0 | T15: 0 | U15: 0 | V15: 0 | W15: 0 | X15: 4.5 | Y15: 0 | Z15: 4.5 | AA15: 2 | AB15: 2.5 | AC15: 2 | AD15: 0 | AE15: 4.5 | AF15: 0
A16: Wheat | B16: provision of the sheriff for his 1 visit about the feast of St Vincent (22 January) in bread, 3 bushels Given to a certain marshal purveying for the Lord Edward, son of the king, in preparation for the tournament at Dunstable, to have his favour, 0.5 qr of oats and hay. | C16: 0 | D16: 0 | E16: 0 | F16: 0 | G16: 0 | H16: 0 | I16: 0 | J16: 0 | K16: 0 | L16: 0 | M16: 0 | N16: 0 | O16: 0 | P16: 0 | Q16: 0 | R16: 0 | S16: 0 | T16: 0 | U16: 0 | V16: 0 | W16: 0
A17: Wheat | B17: Sold as noted above, 177 quarters 6 bushels | C17: 0 | D17: 0 | E17: 0 | F17: 0 | G17: 0 | H17: 0 | I17: 0 | J17: 0 | K17: 0 | L17: 0 | M17: 0 | N17: 0 | O17: 0 | P17: 0 | Q17: 177 | R17: 6 | S17: 177.75 | T17: 0 | U17: 0 | V17: 0 | W17: 0 | X17: 177 | Y17: 6 | Z17: 177.75 | AA17: 177.75 | AB17: 0 | AC17: 177 | AD17: 6
A18: Wheat | B18: Total | C18: 0 | D18: 0 | E18: 0 | F18: 0 | G18: 0 | H18: 0 | I18: 0 | J18: 0 | K18: 0 | L18: 0 | M18: 0 | N18: 0 | O18: 0 | P18: 0 | Q18: 0 | R18: 0 | S18: 0 | T18: 0 | U18: 0 | V18: 0 | W18: 0
A19: Curall | B19: The same render account for 10 quarters 3 bushels from the whole issue of curall, of the same wheat, from the grange in the granary by struck measure. | C19: 0 | D19: 0 | E19: 0 | F19: 0 | G19: 0 | H19: 0 | I19: 0 | J19: 0 | K19: 0 | L19: 0 | M19: 0 | N19: 0 | O19: 0 | P19: 0 | Q19: 0 | R19: 0 | S19: 0 | T19: 10 | U19: 3 | V19: 10.375 | W19: 0 | X19: 10 | Y19: 3 | Z19: 10.375 | AA19: 10.375 | AB19: 0 | AC19: 10 | AD19: 3
A20: Curall | B20: all mixed below with barley for the liveries of the manorial servants. | C20: 0 | D20: 0 | E20: 0 | F20: 0 | G20: 0 | H20: 0 | I20: 0 | J20: 0 | K20: 0 | L20: 0 | M20: 0 | N20: 0 | O20: 0 | P20: 0 | Q20: 0 | R20: 0 | S20: 0 | T20: 0 | U20: 0 | V20: 0 | W20: 0 | X20: 0 | Y20: 0 | Z20: 0 | AA20: 0 | AB20: 0 | AC20: 0 | AD20: 0
A21: Curall | B21: Total | C21: 0 | D21: 0 | E21: 0 | F21: 0 | G21: 0 | H21: 0 | I21: 0 | J21: 0 | K21: 0 | L21: 0 | M21: 0 | N21: 0 | O21: 0 | P21: 0 | Q21: 0 | R21: 0 | S21: 0 | T21: 0 | U21: 0 | V21: 0 | W21: 0
A22: Mancorn | B22: Nothing from mancorn this year because the white field (albus camp') is not sown. | C22: 0 | D22: 0 | E22: 0 | F22: 0 | G22: 0 | H22: 0 | I22: 0 | J22: 0 | K22: 0 | L22: 0 | M22: 0 | N22: 0 | O22: 0 | P22: 0 | Q22: 0 | R22: 0 | S22: 0 | T22: 0 | U22: 0 | V22: 0 | W22: 0 | X22: 0 | Y22: 0 | Z22: 0 | AA22: 0 | AB22: 0 | AC22: 0 | AD22: 0
A23: Mancorn | B23: Total | C23: 0 | D23: 0 | E23: 0 | F23: 0 | G23: 0 | H23: 0 | I23: 0 | J23: 0 | K23: 0 | L23: 0 | M23: 0 | N23: 0 | O23: 0 | P23: 0 | Q23: 0 | R23: 0 | S23: 0 | T23: 0 | U23: 0 | V23: 0 | W23: 0
A24: Barley | B24: (yield: 4-fold plus 1 qr 6 bushels) | C24: 0 | D24: 0 | E24: 0 | F24: 0 | G24: 0 | H24: 0 | I24: 0 | J24: 0 | K24: 0 | L24: 0 | M24: 0 | N24: 0 | O24: 0 | P24: 0 | Q24: 0 | R24: 0 | S24: 0 | T24: 0 | U24: 0 | V24: 0 | W24: 0
A25: Barley | B25: The same render account for 19 quarters 6 bushels from the whole issue of barley from the grange in the granary by struck measure. | C25: 0 | D25: 0 | E25: 0 | F25: 0 | G25: 0 | H25: 0 | I25: 0 | J25: 0 | K25: 0 | L25: 0 | M25: 0 | N25: 0 | O25: 0 | P25: 0 | Q25: 0 | R25: 0 | S25: 0 | T25: 19 | U25: 6 | V25: 19.75 | W25: 0 | X25: 19 | Y25: 6 | Z25: 19.75 | AA25: 19.75 | AB25: 0 | AC25: 19 | AD25: 6
A26: Barley | B26: 10 quarters 3 bushels of curall received above and mixed with that for the liveries of the manorial servants. | C26: 0 | D26: 0 | E26: 0 | F26: 0 | G26: 0 | H26: 0 | I26: 0 | J26: 0 | K26: 0 | L26: 0 | M26: 0 | N26: 10 | O26: 3 | P26: 10.375 | Q26: 0 | R26: 0 | S26: 0 | T26: 0 | U26: 0 | V26: 0 | W26: 0 | X26: 10 | Y26: 3 | Z26: 10.375 | AA26: 10.375 | AB26: 0 | AC26: 10 | AD26: 3
A27: Barley | B27: 9 quarters 7 bushels of beans received below and mixed with barley for the same. | C27: 0 | D27: 0 | E27: 0 | F27: 0 | G27: 0 | H27: 0 | I27: 0 | J27: 0 | K27: 0 | L27: 0 | M27: 0 | N27: 0 | O27: 0 | P27: 0 | Q27: 0 | R27: 0 | S27: 0 | T27: 0 | U27: 0 | V27: 0 | W27: 0 | X27: 9 | Y27: 7 | Z27: 9.875 | AA27: 9.875 | AB27: 0 | AC27: 9 | AD27: 7
A28: Barley | B28: 34 quarters of maslin bought above and mixed with that for the same. | C28: 0 | D28: 0 | E28: 0 | F28: 0 | G28: 0 | H28: 34 | I28: 0 | J28: 34 | K28: 0 | L28: 0 | M28: 0 | N28: 0 | O28: 0 | P28: 0 | Q28: 0 | R28: 0 | S28: 0 | T28: 0 | U28: 0 | V28: 0 | W28: 0 | X28: 34 | Y28: 0 | Z28: 34 | AA28: 34 | AB28: 0 | AC28: 34 | AD28: 0
A29: Barley | B29: Total, 74 quarters. | C29: 0 | D29: 0 | E29: 0 | F29: 0 | G29: 0 | H29: 0 | I29: 0 | J29: 0 | K29: 0 | L29: 0 | M29: 0 | N29: 0 | O29: 0 | P29: 0 | Q29: 0 | R29: 0 | S29: 0 | T29: 0 | U29: 0 | V29: 0 | W29: 0 | X29: 74 | Y29: 0 | Z29: 74 | AA29: 74 | AB29: 0 | AC29: 74 | AD29: 0
A30: Barley | B30: Sown over 8.5 acres and 1 rood measured by the perch which lie above Benam, 4 quarters 3 bushels. | C30: 0 | D30: 0 | E30: 4 | F30: 3 | G30: 4.375 | H30: 0 | I30: 0 | J30: 0 | K30: 0 | L30: 0 | M30: 0 | N30: 0 | O30: 0 | P30: 0 | Q30: 0 | R30: 0 | S30: 0 | T30: 0 | U30: 0 | V30: 0 | W30: 0 | X30: 4 | Y30: 3 | Z30: 4.375 | AA30: 4.375 | AB30: 0 | AC30: 4 | AD30: 3
A31: Barley | B31: that is, .5 qr an acre. | C31: 0 | D31: 0 | E31: 0 | F31: 0 | G31: 0 | H31: 0 | I31: 0 | J31: 0 | K31: 0 | L31: 0 | M31: 0 | N31: 0 | O31: 0 | P31: 0 | Q31: 0 | R31: 0 | S31: 0 | T31: 0 | U31: 0 | V31: 0 | W31: 0
A32: Barley | B32: Delivered to 1 carter, 5 ploughmen, who each take a quarter every 8 weeks for the year, 39 quarters. | C32: 0 | D32: 0 | E32: 0 | F32: 0 | G32: 0 | H32: 0 | I32: 0 | J32: 0 | K32: 0 | L32: 0 | M32: 0 | N32: 0 | O32: 0 | P32: 0 | Q32: 0 | R32: 0 | S32: 0 | T32: 0 | U32: 0 | V32: 0 | W32: 0 | X32: 39 | Y32: 0 | Z32: 39 | AA32: 39 | AB32: 0 | AC32: 39 | AD32: 0
A33: Barley | B33: Delivered to 1 miller, 1 shepherd, 1 cowherd and 1 dairymaid, who each take a quarter every 10 weeks for the year, except the dairymaid who takes one every 12 weeks, 18 quarters 6.5 bushels, because there was no dairymaid for 13 weeks for a want of milking. | C33: 0 | D33: 0 | E33: 0 | F33: 0 | G33: 0 | H33: 0 | I33: 0 | J33: 0 | K33: 0 | L33: 0 | M33: 0 | N33: 0 | O33: 0 | P33: 0 | Q33: 0 | R33: 0 | S33: 0 | T33: 0 | U33: 0 | V33: 0 | W33: 0 | X33: 18 | Y33: 6.5 | Z33: 18.8125 | AA33: 18.8125 | AB33: 0 | AC33: 18 | AD33: 6.5
A34: Barley | B34: Delivered to 1 keeper of lambs for the time of their weaning, that is, from Wednesday the feast of St Mark the Evangelist (25 April) until Wedenesday before the feast of St Barnabas the Apostle (6 June), for 6 weeks, 3 bushels. | C34: 0 | D34: 0 | E34: 0 | F34: 0 | G34: 0 | H34: 0 | I34: 0 | J34: 0 | K34: 0 | L34: 0 | M34: 0 | N34: 0 | O34: 0 | P34: 0 | Q34: 0 | R34: 0 | S34: 0 | T34: 0 | U34: 0 | V34: 0 | W34: 0 | X34: 0 | Y34: 3 | Z34: 0.375 | AA34: 0.375 | AB34: 0 | AC34: 0 | AD34: 3
A35: Barley | B35: supporting pigs and piglets in winter, 1 qr. | C35: 0 | D35: 0 | E35: 0 | F35: 0 | G35: 0 | H35: 0 | I35: 0 | J35: 0 | K35: 0 | L35: 0 | M35: 0 | N35: 0 | O35: 0 | P35: 0 | Q35: 0 | R35: 0 | S35: 0 | T35: 0 | U35: 0 | V35: 0 | W35: 0
A36: Barley | B36: Sold as noted above, 10 quarters. | C36: 0 | D36: 0 | E36: 0 | F36: 0 | G36: 0 | H36: 0 | I36: 0 | J36: 0 | K36: 0 | L36: 0 | M36: 0 | N36: 0 | O36: 0 | P36: 0 | Q36: 10 | R36: 0 | S36: 10 | T36: 0 | U36: 0 | V36: 0 | W36: 0 | X36: 10 | Y36: 0 | Z36: 10 | AA36: 10 | AB36: 0 | AC36: 10 | AD36: 0
A37: Barley | B37: Sold at the audit, 3.5 bushels | C37: 0 | D37: 0 | E37: 0 | F37: 0 | G37: 0 | H37: 0 | I37: 0 | J37: 0 | K37: 0 | L37: 0 | M37: 0 | N37: 0 | O37: 0 | P37: 0 | Q37: 0 | R37: 0 | S37: 0 | T37: 0 | U37: 0 | V37: 0 | W37: 0 | X37: 0 | Y37: 3.5 | Z37: 0.4375 | AA37: 0.4375 | AB37: 0 | AC37: 0 | AD37: 3.5
A38: Barley | B38: Total | C38: 0 | D38: 0 | E38: 0 | F38: 0 | G38: 0 | H38: 0 | I38: 0 | J38: 0 | K38: 0 | L38: 0 | M38: 0 | N38: 0 | O38: 0 | P38: 0 | Q38: 0 | R38: 0 | S38: 0 | T38: 0 | U38: 0 | V38: 0 | W38: 0
A39: Beans | B39: {yield: six-fold plus 1 bushels} | C39: 0 | D39: 0 | E39: 0 | F39: 0 | G39: 0 | H39: 0 | I39: 0 | J39: 0 | K39: 0 | L39: 0 | M39: 0 | N39: 0 | O39: 0 | P39: 0 | Q39: 0 | R39: 0 | S39: 0 | T39: 0 | U39: 0 | V39: 0 | W39: 0 | X39: 0 | Y39: 1 | Z39: 0.125 | AA39: 0.125 | AB39: 0 | AC39: 0 | AD39: 1
A40: Beans | B40: The same render account for 20 quarters 1 bushels from the whole issue of beans from the grange in the granary by struck measure. | C40: 0 | D40: 0 | E40: 0 | F40: 0 | G40: 0 | H40: 0 | I40: 0 | J40: 0 | K40: 0 | L40: 0 | M40: 0 | N40: 0 | O40: 0 | P40: 0 | Q40: 0 | R40: 0 | S40: 0 | T40: 20 | U40: 1 | V40: 20.125 | W40: 0 | X40: 20 | Y40: 1 | Z40: 20.125 | AA40: 20.125 | AB40: 0 | AC40: 20 | AD40: 1
A41: Beans | B41: Sown, 4 quarters 1 bushels Mixed above with barley for the liveries of the manorial servants, 9 quarters 7 bushels Sold as noted above, 6 quarters 1 bushels | C41: 0 | D41: 0 | E41: 19 | F41: 9 | G41: 20.125 | H41: 0 | I41: 0 | J41: 0 | K41: 0 | L41: 0 | M41: 0 | N41: 19 | O41: 9 | P41: 20.125 | Q41: 19 | R41: 9 | S41: 20.125 | T41: 0 | U41: 0 | V41: 0 | W41: 0 | X41: 15 | Y41: 8 | Z41: 16 | AA41: 4.125 | AB41: 11.875 | AC41: 4 | AD41: 1 | AE41: 9 | AF41: 7 | AG41: 6 | AH41: 1
A42: Beans | B42: Total | C42: 0 | D42: 0 | E42: 0 | F42: 0 | G42: 0 | H42: 0 | I42: 0 | J42: 0 | K42: 0 | L42: 0 | M42: 0 | N42: 0 | O42: 0 | P42: 0 | Q42: 0 | R42: 0 | S42: 0 | T42: 0 | U42: 0 | V42: 0 | W42: 0

Sheet Sale of Corn Prices
A1: Heading | B1: Sentence | C1: Total in Pounds | D1: Pounds | E1: Shillings | F1: Pence | G1: Corn | H1: Total Quarters Except 1 | I1: Total Bushels Except 1 | J1: Total Corn Cross-Check | K1: Total Corn Manorial Account | L1: Corn Quantity Error | M1: Quarters 0 | N1: Bushels 0 | O1: shilling a quarter 1 | P1: pence a quarter 1 | Q1: Quarters 1 | R1: Bushels 1 | S1: shilling a quarter 2 | T1: pence a quarter 2 | U1: Quarters 2 | V1: Bushels 2 | W1: shilling a quarter 3 | X1: pence a quarter 3 | Y1: Quarters 3 | Z1: Bushels 3 | AA1: shilling a quarter 4 | AB1: pence a quarter 4 | AC1: £ a quarter 1 | AD1: £ a quarter 2 | AE1: £ a quarter 3 | AF1: £ a quarter 4 | AG1: Quarters Sold | AH1: Weighted Average Price per Quarter | AI1: Non-Weighted Average Price per Quarter | AJ1: Corn lowercase
