Workbook

Sheet Marshalsea Overview - Completed
A1: MARSHALSEA OVERVIEW - COMPLETED | B1: Total in £ | C1: Error | D1: Note
A2: CASH ACCOUNT
A3: RECEIPTS
A4: Arrears total | B4: 26.32
A5: Rents of assize total | B5: 0.33
A6: Quittances total
A7: Defaults of rent total
A8: Defaults of rent through the pestilence total
A9: Cotlands defaults total
A10: Cotlands total
A11: Total of quittances and defaults of rent total
A12: Total of rents remaining clear total
A13: Farms total
A14: Annual recognizances total
A15: Issues of the Manor total
A16: Issues of the tenements in the lord's hands total
A17: Sale of labour services total
... A22: Farm of the demesne land total
A23: Total of all receipts (calculated here) | B23: =SUM(B5:B22)
A24: Total of all receipts (calculated here) incl arrears | B24: =SUM(B4:B22)
A25: Total recorded in the accounts excl. arrears | C25: =B23-B25
A26: Total recorded in the accounts incl. arrears | B26: =B25+B4
A29: EXPENSES
A30: Cost of ploughs total
A31: Purchase of corn total
A32: Cost of carts and wagons total
A33: Cost of dairy total
A34: Purchase of stock total
A35: Sheepcote total
A36: Cost of buildings total
A37: Threshing total
A38: Barley expenses
A39: Expenses of the harvest total
A40: Necessary expenses
... A47: Total Demesne fixed investment
A49: Owed by the reeve | B49: =B23-B45
A50: From accounts
A52: Allowances
A53: Cash deliveries
A54: Sum of the above | B54: =SUM(B52:B53)
A55: Total of all allowances and cash deliveries in accounts
A57: Net amount owed | B57: =B50-B54
A58: Net amount owed in accounts
A60: GRANGE ACCOUNT | B60: Total Production | D60: Value of total gross production in £ | E60: Value of total net production in £
A61: Grange | B61: qrs | C61: bus
A62: Wheat
A63: Rye
A64: Dredge
A65: Curall
A66: Barley
A67: Oats
A68: Beans
A69: Peas
A70: Vetches
A71: Total value of gross production (sum of the above)
A72: Total value of net production
A73: Value of sales
A75: MILL ACCOUNT | B75: Total Production | D75: Total in £
A76: Issues of the mill | B76: qrs | C76: bus
A77: Wheat
A78: Oatmeal
A79: 1st grade malt
A80: 2nd grade malt
A81: Maslin
A82: Total value of production (sum of the above)
A83: Value of sales
A85: STOCK ACCOUNT
A86: Livestock | B86: Begin stock | C86: End stock | D86: Stockbuilding | F86: Value of stock in £ | G86: Value of stockbuilding
A87: Cart-horses | D87: =C87-B87 | F87: ='Stock'!K5*'Stock'!O5 | G87: =D87*'Stock'!O5
A88: Mares | D88: =C88-B88 | F88: ='Stock'!K6*'Stock'!O6 | G88: =D88*'Stock'!O6
A89: Plough horses | D89: =C89-B89 | F89: ='Stock'!K7*'Stock'!O7 | G89: =D89*'Stock'!O7
A90: Colts (2 years) | D90: =C90-B90 | F90: ='Stock'!K8*'Stock'!O8 | G90: =D90*'Stock'!O8
A91: Colts (2 years) | D91: =C91-B91 | F91: ='Stock'!K9*'Stock'!O9 | G91: =D91*'Stock'!O9
A92: Colts (1 year) | D92: =C92-B92 | F92: ='Stock'!K10*'Stock'!O10 | G92: =D92*'Stock'!O10
A93: Foals | D93: =C93-B93 | F93: ='Stock'!K11*'Stock'!O11 | G93: =D93*'Stock'!O11
A94: Oxen | D94: =C94-B94 | F94: ='Stock'!K12*'Stock'!O12 | G94: =D94*'Stock'!O12
A95: Bulls | D95: =C95-B95 | F95: ='Stock'!K13*'Stock'!O13 | G95: =D95*'Stock'!O13
A96: Cows | D96: =C96-B96 | F96: ='Stock'!K14*'Stock'!O14 | G96: =D96*'Stock'!O14
A97: Steers | D97: =C97-B97 | F97: ='Stock'!K15*'Stock'!O15 | G97: =D97*'Stock'!O15
A98: Bullocks | D98: =C98-B98 | F98: ='Stock'!K16*'Stock'!O16 | G98: =D98*'Stock'!O16
... A112: Peacocks | D112: =C112-B112 | F112: ='Stock'!K30*'Stock'!O30 | G112: =D112*'Stock'!O30
A113: Total value of stock (sum of the above) | F113: =SUM(F87:F112) | G113: =SUM(G87:G112)
A114: Total value of production | F114: =SUM('Stock'!T5:T30)
A115: Value of sales | F115: =SUM('Stock'!R5:R30)
A117: Wool | B117: Begin stock | C117: End stock | D117: Stockbuilding | F117: Value of stock in £
A118: Fleeces
A119: Coarse wool
A120: Lamb's wool
A121: Wool locks
A122: Wool sold at shearing
A123: Total value of production (sum of the above)
A124: Value of sales
A126: Hides | B126: Begin stock | C126: End stock | D126: Stockbuilding | F126: Value of stock in £
A127: Ox hides
A128: Cow hides
A129: Mare hides
A130: Steer hides
A131: Yearling Calf hides
A132: Calf hides
A133: Pig hides
...

Sheet Prices
A1: Meat & Dairy Prices
C2: 1301 | D2: 1302 | E2: Average
A3: Beef | B3: £ per lb | C3: 0.0033351854 | D3: 0.0032608538 | E3: =AVERAGE(C3:D3)
A4: Mutton | B4: £ per lb | C4: 0.0036593977 | D4: 0.0037125513 | E4: =AVERAGE(C4:D4)
A5: Pork | B5: £ per lb | C5: 0.0038431326 | D5: 0.0037574803 | E5: =AVERAGE(C5:D5)
A6: Cheese | B6: £ per lb | C6: 0.0055768754 | D6: 0.0056654898 | E6: =AVERAGE(C6:D6)
A7: Butter | B7: £ per lb | C7: 0.0036626221 | D7: 0.0035935077 | E7: =AVERAGE(C7:D7)
A8: Milk | B8: £ per gallon | C8: 0.0055768754 | D8: 0.0056654898 | E8: =AVERAGE(C8:D8)

Sheet Labour Rents

Sheet Overview
A1: MARSHALSEA | B1: Total in £ | C1: Error | D1: Note
A2: CASH ACCOUNT
A3: RECEIPTS
A4: Arrears total
A5: Rents of assize total
A6: Quittances total
A7: Defaults of rent total
A8: Defaults of rent through the pestilence total
A9: Cotlands defaults total
A10: Cotlands total
A11: Total of quittances and defaults of rent total
A12: Total of rents remaining clear total
A13: Farms total
... A183: % of capital expenses as calculated previously

Sheet Receipts
A1: MARSHALSEA RECEIPTS
A2: Heading | B2: £ | C2: s | D2: d | F2: Total in £ | G2: Error | H2: Notes
A3: Arrears | B3: 26 | C3: 6 | D3: 4 | F3: 26.32 | H3: Gilbert Marescallus renders account for £26 6 shilling 4pence of arrears from the previous year.
A4: Arrears | F4: 26.32 | G4: 0 | H4: Total
A6: Rents of assize | B6: 0 | C6: 3 | D6: 4 | F6: 0.17 | H6: The same renders account for 3 shilling 4pence for the rent of assize at Michaelmas of Thomas Schudd' for 1 messuage 20 acres of land and .5 acre of wood in West Pitt.
A7: Rents of assize | B7: 0 | C7: 3 | D7: 4 | F7: 0.17 | H7: 3 shilling 4pence for the rent of assize at the same term of the heir of John de Brafeld' for 1 messuage 20 acres of land and' acre of wood in the same vill.
A8: Rents of assize | B8: 0 | C8: 3 | D8: 4 | F8: 0.17 | H8: 3 shilling 4pence for the rent of assize at the same term of William Bygh' for 1 messuage 201 acres of land and' acre of wood in the same vill.
A9: Rents of assize | B9: 0 | C9: 6 | D9: 8 | F9: 0.33 | H9: 6 shilling 8pence for the rent of assize at the same term of William Alysanndr' for 2 messuages 40 acres of land and 1 acre of wood in the same vill.
A10: Rents of assize | B10: 0 | C10: 3 | D10: 4 | F10: 0.17 | H10: 3 shilling 4pence for the rent of assize at the same term of Aunger le Drivere and Agnes his wife for 1 messuage 20 acres of land and' acre of wood in the same vill.
A11: Rents of assize | B11: 0 | C11: 0 | D11: 6 | F11: 0.03 | H11: 6pence for the rent of assize at the same term of the heir of John de Brayfeld' for 1 cottage in the same vill.
A12: Rents of assize | B12: 0 | C12: 3 | D12: 0 | F12: 0.15 | H12: 3 shilling for the rent of assize at the same term of Drogo de Celar' and Amice his wife for a certain messuage in ICingsgate Street beside the Carmelite Friars.
A13: Rents of assize | B13: 0 | C13: 2 | D13: 0 | F13: 0.1 | H13: 2 shilling for the rent of assize at the same term of Robert de la Fermerie for a certain messuage opposite the house of John de Houlond' in the same place which is of the fee of West Pitt.
A14: Rents of assize | B14: 1 | C14: 5 | D14: 6 | F14: 1.27 | H14: Total, £1 5 shilling 6pence
A15: Rents of assize | F15: =SUM(F6:F13) | G15: =F15-F14 | H15: Total
A17: Rents of assize | B17: 0 | C17: 6 | D17: 0 | F17: 0.3 | H17: The same renders account for 6 shilling for the rent of assize at Michaelmas of the heir of Ralph de Gorhunte in Pendeworth'.
A18: Rents of assize | B18: 0 | C18: 6 | D18: 0 | F18: 0.3 | H18: Total, 6 shilling
A19: Rents of assize | F19: =SUM(F17) | G19: =F19-F18 | H19: Total
A21: Rents of assize | B21: 0 | C21: 13 | D21: 8 | F21: 0.68 | H21: The same renders account for 13 shilling 8pence for the rent of assize at Michaelmas of Andrew Payn for the tenement which he holds in Sparsholt.
A22: Rents of assize | B22: 0 | C22: 3 | D22: 0 | F22: 0.15 | H22: 3 shilling for the rent of assize at the same term of William Russel for a certain cottage in the same vill.
A23: Rents of assize | B23: 0 | C23: 5 | D23: 0 | F23: 0.25 | H23: 5 shilling for the rent of assize at the same term of Richard Fromund for his tenement which he holds in the same vill.
A24: Rents of assize | B24: 1 | C24: 1 | D24: 8 | F24: 1.08 | H24: Total, £1 1 shilling 8pence
A25: Rents of assize | F25: =SUM(F21:F23) | G25: =F25-F24 | H25: Total
A27: Rents of assize | B27: 0 | C27: 6 | D27: 8 | F27: 0.33 | H27: The same renders account for 6 shilling 8pence for the rent of assize at Michaelmas of Nicholas de Ychen' for 3 virgates of land in Martyr Worthy.
A28: Rents of assize | B28: 0 | C28: 6 | D28: 8 | F28: 0.33 | H28: Total, 6 shilling 8pence
A29: Rents of assize | F29: =SUM(F27) | G29: =F29-F28 | H29: Total
A31: Estreat of the Bench beginning at Michaelmas in the year 26, and Hilary, Easter and Trinity in the year 27 (1298-9) | B31: 0 | C31: 1 | D31: 8 | F31: 0.08 | H31: The same renders account for 1 shilling 8pence from Martin Molendinarius of South Stoneham and Roger of the same because they did not produce in court Guy de Stonham.
A32: Estreat of the Bench beginning at Michaelmas in the year 26, and Hilary, Easter and Trinity in the year 27 (1298-9) | B32: 0 | C32: 1 | D32: 8 | F32: 0.08 | H32: 1 shilling 8pence from William Raynold de Fal' and John Soudener of the same because they did not produce in court John de la Sale.
A33: Estreat of the Bench beginning at Michaelmas in the year 26, and Hilary, Easter and Trinity in the year 27 (1298-9) | B33: 0 | C33: 1 | D33: 8 | F33: 0.08 | H33: 1 shilling 8pence from William Cuppyng of Droxford and William le Taymyr of the same because they did not produce in court Richard de Midlington' whom they had bailed.
A34: Estreat of the Bench beginning at Michaelmas in the year 26, and Hilary, Easter and Trinity in the year 27 (1298-9) | B34: 0 | C34: 1 | D34: 8 | F34: 0.08 | H34: 1 shilling 8pence from Gerard le Commongar' of Durley and Thomas Everard of the same because they did not produce in court John Everard'.
A35: Estreat of the Bench beginning at Michaelmas in the year 26, and Hilary, Easter and Trinity in the year 27 (1298-9) | B35: 0 | C35: 1 | D35: 8 | F35: 0.08 | H35: 1 shilling 8pence from John Crispyn of Bighton and John Faber because they did not produce in court Walter Tymb'.
A36: Estreat of the Bench beginning at Michaelmas in the year 26, and Hilary, Easter and Trinity in the year 27 (1298-9) | B36: 0 | C36: 1 | D36: 8 | F36: 0.08 | H36: 1 shilling 8pence from William Martin of West Tisted and Adam ate Mere because they did not produce in court Richard de Tysted'.
A37: Estreat of the Bench beginning at Michaelmas in the year 26, and Hilary, Easter and Trinity in the year 27 (1298-9) | B37: 0 | C37: 1 | D37: 0 | F37: 0.05 | H37: 1 shilling from Richard de Overton' and Geoffrey Horn because they did not produce in court John Pilesel the younger whom they had bailed.
A38: Estreat of the Bench beginning at Michaelmas in the year 26, and Hilary, Easter and Trinity in the year 27 (1298-9) | B38: 0 | C38: 1 | D38: 0 | F38: 0.05 | H38: 1 shilling from Ralph de Sydemanton' and John de Nywenton' because they did not produce in court Roger le Lunt whom they had pledged.
A39: Estreat of the Bench beginning at Michaelmas in the year 26, and Hilary, Easter and Trinity in the year 27 (1298-9) | B39: 0 | C39: 1 | D39: 0 | F39: 0.05 | H39: 1 shilling from Adam le Mar' and Walter Mercator because they did not produce in court Roger le Lunt whom they had pledged.
A40: Estreat of the Bench beginning at Michaelmas in the year 26, and Hilary, Easter and Trinity in the year 27 (1298-9) | B40: 0 | C40: 2 | D40: 0 | F40: 0.1 | H40: 2 shilling from William Martin, Walter de Cove, Richard de Murifeld' and John Faber of West Tisted because they did not produce in court Richard de Tisted' whom they had bailed.
A41: Estreat of the Bench beginning at Michaelmas in the year 26, and Hilary, Easter and Trinity in the year 27 (1298-9) | B41: 0 | C41: 1 | D41: 8 | F41: 0.08 | H41: 1 shilling 8pence from John Cuppyng of Bighton, William Clericus of Drayton, John de Solrigg' and John de la Greyn' because they did not produce in court Robert de Weston'.
A42: Estreat of the Bench beginning at Michaelmas in the year 26, and Hilary, Easter and Trinity in the year 27 (1298-9) | B42: 0 | C42: 1 | D42: 8 | F42: 0.08 | H42: 1 shilling 8pence from John Faber of Bighton, Richard le Schepurde, John Sum' and Robert le Bule because they did not produce in court Walter Tymb' whom they had bailed.
... A49: Estreat of the Bench beginning at Michaelmas in the year 26, and Hilary, Easter and Trinity in the year 27 (1298-9) | B49: 1 | C49: 7 | D49: 8 | F49: 1.38 | H49: Total, £1 7 shilling 8pence
F50: =SUM(F31:F48) | G50: =F50-F49 | H50: Total
A52: Amercements of the court of J. de Metingham and his fellows of the Bench at Michaelmas in the year 28 (1299-1300) and the following terms | B52: 0 | C52: 3 | D52: 4 | F52: 0.17 | H52: The same renders account for 3 shilling 4pence from Jordan le Yunge and his fellows because they did not produce in court Joan de Colrych' whom they had bailed.
A53: Amercements of the court of J. de Metingham and his fellows of the Bench at Michaelmas in the year 28 (1299-1300) and the following terms | B53: 0 | C53: 3 | D53: 4 | F53: 0.17 | H53: 3 shilling 4pence from Bartholomew Laurence and his fellows because they did not produce in court William, son of Laurence de London, whom they had bailed.
A54: Amercements of the court of J. de Metingham and his fellows of the Bench at Michaelmas in the year 28 (1299-1300) and the following terms | B54: 0 | C54: 1 | D54: 8 | F54: 0.08 | H54: 1 shilling 8pence from William Joye and his fellows because they did not produce in court Walter de Derneford' whom they had bailed.
A55: Amercements of the court of J. de Metingham and his fellows of the Bench at Michaelmas in the year 28 (1299-1300) and the following terms | B55: 0 | C55: 3 | D55: 4 | F55: 0.17 | H55: 3 shilling 4pence from Robert Wyncent and his fellows because they did not produce in court John de Lynch' whom they had bailed.
A56: Amercements of the court of J. de Metingham and his fellows of the Bench at Michaelmas in the year 28 (1299-1300) and the following terms | B56: 0 | C56: 3 | D56: 4 | F56: 0.17 | H56: 3 shilling 4pence from Jordan le Yunge and his fellows because they did not produce in court Joan de Colrich' whom they had bailed.
A57: Amercements of the court of J. de Metingham and his fellows of the Bench at Michaelmas in the year 28 (1299-1300) and the following terms | B57: 0 | C57: 1 | D57: 8 | F57: 0.08 | H57: 1 shilling 8pence from Thomas Laurence and his fellows because they did not produce in court William, son of Laurence de London, whom they had bailed.
A58: Amercements of the court of J. de Metingham and his fellows of the Bench at Michaelmas in the year 28 (1299-1300) and the following terms | B58: 0 | C58: 1 | D58: 8 | F58: 0.08 | H58: 1 shilling 8pence from Laurence Skyreboth' and his fellows because they did not produce in court Walter de Derneford' whom they had bailed.
A59: Amercements of the court of J. de Metingham and his fellows of the Bench at Michaelmas in the year 28 (1299-1300) and the following terms | B59: 0 | C59: 1 | D59: 8 | F59: 0.08 | H59: 1 shilling 8pence from William le Duk and his fellows because they did not produce in court John de Lynch' whom they had bailed.
A60: Amercements of the court of J. de Metingham and his fellows of the Bench at Michaelmas in the year 28 (1299-1300) and the following terms | B60: 0 | C60: 3 | D60: 4 | F60: 0.17 | H60: 3 shilling 4pence from John Wyncent and his fellows because they did not produce in court John de Lynch' whom they had bailed.
A61: Amercements of the court of J. de Metingham and his fellows of the Bench at Michaelmas in the year 28 (1299-1300) and the following terms | B61: 0 | C61: 1 | D61: 8 | F61: 0.08 | H61: 1 shilling 8pence from William Chauberlain, juror, because he did not come to the afforcement.
A62: Amercements of the court of J. de Metingham and his fellows of the Bench at Michaelmas in the year 28 (1299-1300) and the following terms | B62: 1 | C62: 5 | D62: 0 | F62: 1.25 | H62: Total, £1 5 shilling
F63: =SUM(F52:F61) | G63: =F63-F62 | H63: Total
A65: Court of the Barons of the Exchequer for the pleas of Hilary term in the year 28 (1300) | B65: 0 | C65: 6 | D65: 8 | F65: 0.33 | H65: The same renders account for 6 shilling 8pence from Alan Plukenet, son and heir of Alan Plukenet, because he did not come.
A66: Court of the Barons of the Exchequer for the pleas of Hilary term in the year 28 (1300) | B66: 0 | C66: 6 | D66: 8 | F66: 0.33 | H66: 6 shilling 8pence from William, reeve of Kilmeston, and Stephen le Rede of the same because they did not produce in court Alan, son and heir of Alan Plukenet, at Easter.
A67: Court of the Barons of the Exchequer for the pleas of Hilary term in the year 28 (1300) | B67: 0 | C67: 6 | D67: 8 | F67: 0.33 | H67: 6 shilling 8pence from Alan, son and heir of Alan Plukenet, because he did not come.
A68: Court of the Barons of the Exchequer for the pleas of Hilary term in the year 28 (1300) | B68: 0 | C68: 3 | D68: 4 | F68: 0.17 | H68: 3 shilling 4pence from Stephen le Ryde of Kilmeston and his fellows because they did not produce in court the said Alan.
A69: Court of the Barons of the Exchequer for the pleas of Hilary term in the year 28 (1300) | B69: 0 | C69: 3 | D69: 4 | F69: 0.17 | H69: From Trinity term: 3 shilling 4pence from Alan Plukenet, son and heir of Alan Plukenet, because he did not come.
A70: Court of the Barons of the Exchequer for the pleas of Hilary term in the year 28 (1300) | B70: 0 | C70: 1 | D70: 8 | F70: 0.08 | H70: 1 shilling 8pence from Stephen ate Cleye of Kilmeston and his fellows because they did not produce in court Alan, son and heir of Alan Plukenet.
A71: Court of the Barons of the Exchequer for the pleas of Hilary term in the year 28 (1300) | B71: 0 | C71: 6 | D71: 8 | F71: 0.33 | H71: 6 shilling 8pence from Philip, archdeacon of Winchester, because he did not come.
A72: Court of the Barons of the Exchequer for the pleas of Hilary term in the year 28 (1300) | B72: 1 | C72: 15 | D72: 0 | F72: =B72+C72/20+D72/240 | H72: Total, £1 15 shilling
A73: Court of the Barons of the Exchequer for the pleas of Hilary term in the year 28 (1300) | F73: =SUM(F65:F71) | G73: =F73-F72 | H73: Total
A75: Court of the Barons of the Exchequer for the pleas of Hilary term in the year 28 (1300) | B75: 0 | C75: 1 | D75: 8 | F75: 0.08 | H75: And 1 shilling 8pence from Gerard de Tigehal' and his fellows because they did not produce in court William de Tigehal'.
A76: Court of Roger Brabazon and his fellow justices holding the pleas of the king's court for Hilary term in the year 27 Edward I (1299) | B76: 0 | C76: 1 | D76: 8 | F76: 0.08 | H76: The same renders account for 1 shilling 8pence from Thomas Tupleyn and his fellows because they did not produce in court Nicholas de Langrissch'.
A78: Court of the same justices in Michaelmas term of the year ending 26 and beginning 27 (1298-9) | B78: 0 | C78: 1 | D78: 8 | F78: 0.08 | H78: The same renders account for 1 shilling 8pence from Nicholas de Borden' and his fellows because they did not produce in court Nicholas de Langrissch' whom they had bailed
A79: Court of the same justices in Michaelmas term of the year ending 26 and beginning 27 (1298-9) | B79: 0 | C79: 5 | D79: 0 | F79: =B79+C79/20+D79/240 | H79: Total, 5 shilling
A81: Both | F81: =F78+F75+F76 | G81: =F81-F79 | H81: Total
A83: King's court for Michaelmas term of the year ending 25 and beginning 26, and for the following Hilary, Easter and Trinity terms (1297-8) | B83: 0 | C83: 1 | D83: 8 | F83: 0.08 | H83: The same renders account for 1 shilling 8pence from Nicholas Wyncent and John Wyncent because they did not produce in court William de Lynch'.
A84: King's court for Michaelmas term of the year ending 25 and beginning 26, and for the following Hilary, Easter and Trinity terms (1297-8) | B84: 0 | C84: 1 | D84: 0 | F84: 0.05 | H84: 1 shilling from John Wyncent, William Wyncent, Nicholas Wyncent and William Pakel because they did not produce in court John de Lynch'.
A85: King's court for Michaelmas term of the year ending 25 and beginning 26, and for the following Hilary, Easter and Trinity terms (1297-8) | B85: 0 | C85: 1 | D85: 8 | F85: 0.08 | H85: 1 shilling 8pence from John de Wyntenesheye of Bradley and Simon Wuwyn' of Wield because they did not produce in court John Bouie.
A86: King's court for Michaelmas term of the year ending 25 and beginning 26, and for the following Hilary, Easter and Trinity terms (1297-8) | B86: 0 | C86: 1 | D86: 8 | F86: 0.08 | H86: 1 shilling 8pence from Hugh son of Elewys and Robert, son of Andrew de Essefeld', because they did not produce in court Thomas Call'.
A87: King's court for Michaelmas term of the year ending 25 and beginning 26, and for the following Hilary, Easter and Trinity terms (1297-8) | B87: 0 | C87: 1 | D87: 8 | F87: 0.08 | H87: 1 shilling 8pence from John Langurend' and John de la Hecch' because they did not produce in court Simon Wuwyn' whom they had pledged.
A88: King's court for Michaelmas term of the year ending 25 and beginning 26, and for the following Hilary, Easter and Trinity terms (1297-8) | B88: 0 | C88: 1 | D88: 8 | F88: 0.08 | H88: 1 shilling 8pence from William le Carpentyr de Herlefeld' and Thomas Call' of Wield because they did not produce in court Robert de la Doun'.
A89: King's court for Michaelmas term of the year ending 25 and beginning 26, and for the following Hilary, Easter and Trinity terms (1297-8) | B89: 0 | C89: 1 | D89: 8 | F89: 0.08 | H89: 1 shilling 8pence from Simon de la Lye and Benedict le Parmenter because they did not produce in court Gilbert Horsemayn.
A90: King's court for Michaelmas term of the year ending 25 and beginning 26, and for the following Hilary, Easter and Trinity terms (1297-8) | B90: 0 | C90: 1 | D90: 8 | F90: 0.08 | H90: 1 shilling 8pence from John le Fughelar', John Clericus of Long Sutton, William Paghel, William Vincent of Long Sutton because they did not produce in court John de Lynch' whom they had bailepence
A91: King's court for Michaelmas term of the year ending 25 and beginning 26, and for the following Hilary, Easter and Trinity terms (1297-8) | B91: 0 | C91: 12 | D91: 8 | F91: =B91+C91/20+D887243 | H91: Total, 12 shilling 8pence
F92: =SUM(F83:F90) | G92: =F92-F91 | H92: Total
A94: From Chancery in the year 28 (1300), from the charge of Robert de Herierd' | B94: 0 | C94: 6 | D94: 8 | F94: 0.33 | H94: 6 shilling 8pence from Robert Burnel to have the writ `pone'.
A95: Also from chancery in the year 29 (1301), from the charge of Robert de Herierd' | B95: 0 | C95: 6 | D95: 8 | F95: 0.33 | H95: 6 shilling 8pence from Richard de Sutton' of Overton to have a writ.
A96: Also from chancery in the year 29 (1301), from the charge of Robert de Herierd' | B96: 0 | C96: 0 | D96: 0 | F96: 0 | H96: 0.5 mark from Richard le Porter to have a writ.
A97: Also from chancery in the year 29 (1301), from the charge of Robert de Herierd' | B97: 1 | C97: 0 | D97: 0 | F97: 1 | H97: Total, £1.
F98: =SUM(F94:F96) | G98: =F98-F97 | H98: Total
A100: From the eyre of R. de Roff' in the year 8 and the beginning of the year 9 (1280-1) | B100: 0 | C100: 3 | D100: 4 | F100: 0.17 | H100: 3 shilling 4pence from Adam de Aldewyk' for contempt.
A101: From the eyre of R. de Roff' in the year 8 and the beginning of the year 9 (1280-1) | B101: 0 | C101: 3 | D101: 4 | F101: 0.17 | H101: Total, 3 shilling 4pence
F102: =SUM(F100) | G102: =F102-F101 | H102: Total
A104: From the fines and amercements of Newgate gaol at the court of R. de Sandwyk' and his fellow justices in the years 24, 25, 26 and 27 (1296-9) | B104: 0 | C104: 0 | D104: 0 | F104: 0 | H104: The same renders account for' Richard de Frilend' because he did not come.
A105: From the fines and amercements of Newgate gaol at the court of R. de Sandwyk' and his fellow justices in the years 24, 25, 26 and 27 (1296-9) | B105: 0 | C105: 3 | D105: 4 | F105: 0.17 | H105: 3 shilling 4pence from John Bulluk and Nicholas Cocus because they did not produce in court the said Richard.
A106: From the fines and amercements of Newgate gaol at the court of R. de Sandwyk' and his fellow justices in the years 24, 25, 26 and 27 (1296-9) | B106: 0 | C106: 1 | D106: 8 | F106: 0.08 | H106: 1 shilling 8pence from John de Lynch' because he did not come.
A107: From the fines and amercements of Newgate gaol at the court of R. de Sandwyk' and his fellow justices in the years 24, 25, 26 and 27 (1296-9) | B107: 0 | C107: 3 | D107: 4 | F107: 0.17 | H107: 3 shilling 4pence from John Germayn and John ate Gate because they did not produce in court the said John whom they had bailed.
A108: From the fines and amercements of Newgate gaol at the court of R. de Sandwyk' and his fellow justices in the years 24, 25, 26 and 27 (1296-9) | B108: 0 | C108: 1 | D108: 8 | F108: 0.08 | H108: 1 shilling 8pence from Richard de Midlinigiton' because he did not come.
A109: From the fines and amercements of Newgate gaol at the court of R. de Sandwyk' and his fellow justices in the years 24, 25, 26 and 27 (1296-9) | B109: 0 | C109: 2 | D109: 0 | F109: 0.1 | H109: 2 shilling from Peter le Ryd' and William Herberd because they did not produce in court the said Richard.
A110: From the fines and amercements of Newgate gaol at the court of R. de Sandwyk' and his fellow justices in the years 24, 25, 26 and 27 (1296-9) | B110: 0 | C110: 1 | D110: 8 | F110: 0.08 | H110: 1 shilling 8pence from William de la Den' because he did not come.
A111: From the fines and amercements of Newgate gaol at the court of R. de Sandwyk' and his fellow justices in the years 24, 25, 26 and 27 (1296-9) | B111: 0 | C111: 2 | D111: 0 | F111: 0.1 | H111: 2 shilling from Henry Wormere and Thomas Cachefrench because they did not produce in court the said William.
A112: From the fines and amercements of Newgate gaol at the court of R. de Sandwyk' and his fellow justices in the years 24, 25, 26 and 27 (1296-9) | B112: 0 | C112: 2 | D112: 0 | F112: 0.1 | H112: 2 shilling from William Houdy and Robert ate Mere because they did not produce in court.
A113: From the fines and amercements of Newgate gaol at the court of R. de Sandwyk' and his fellow justices in the years 24, 25, 26 and 27 (1296-9) | B113: 0 | C113: 1 | D113: 8 | F113: 0.08 | H113: 1 shilling 8pence from Robert la Beche because he did not come.
A114: From the fines and amercements of Newgate gaol at the court of R. de Sandwyk' and his fellow justices in the years 24, 25, 26 and 27 (1296-9) | B114: 1 | C114: 1 | D114: 0 | F114: 1.05 | H114: Total, £1 1 shilling
F115: =SUM(F104:F113) | G115: =F115-F114 | H115: Total
A117: Money of the king from Chancery in the year 29 Edward I (1301) | B117: 0 | C117: 6 | D117: 8 | F117: 0.33 | H117: The same renders account for 6 shilling 8pence from Joan, who was wife of William de Castr', Ralph William, and Richard, son of the same Joan, to have the writ `pone'.
A118: Court of J. de Metingham and his fellow justices of the Bench at Michaelmas term in the year 28, and the fines and issues from the Bench at Hilary term in the year 29 (1300-1) | B118: 0 | C118: 3 | D118: 4 | F118: 0.17 | H118: The same renders account for 3 shilling 4pence from the issue of the land of Joan de Colrych' outside the manor (for').
A119: Court of J. de Metingham and his fellow justices of the Bench at Michaelmas term in the year 28, and the fines and issues from the Bench at Hilary term in the year 29 (1300-1) | B119: 0 | C119: 1 | D119: 8 | F119: 0.08 | H119: 1 shilling 8pence from the issue of the land of William, son of Laurence de London.
A120: Court of J. de Metingham and his fellow justices of the Bench at Michaelmas term in the year 28, and the fines and issues from the Bench at Hilary term in the year 29 (1300-1) | B120: 0 | C120: 1 | D120: 8 | F120: 0.08 | H120: 1 shilling 8pence from the issue of the land of Walter de Durneford'.
A121: Court of J. de Metingham and his fellow justices of the Bench at Michaelmas term in the year 28, and the fines and issues from the Bench at Hilary term in the year 29 (1300-1) | B121: 0 | C121: 3 | D121: 4 | F121: 0.17 | H121: 3 shilling 4pence from the issue of the land of John de Lynch'.
...

Sheet Expenses
A1: MARSHALSEA EXPENSES
A2: Heading | B2: £ | C2: s | D2: d | F2: Total in £ | G2: Error | H2: Notes
A3: Expenses | B3: 3 | C3: 10 | D3: 0 | F3: 3.5 | H3: In wages of the marshal for the year £3 10 shilling
A4: Expenses | B4: 0 | C4: 10 | D4: 0 | F4: 0.5 | H4: In allowance of the same for a 10 shilling amercement of William le Blesscede which he was being charged for from the previous year, because it was found in the pipe rolls that he paid it before for trespass of wool in the court of J. de Luvetot and G. de Nebaud.
A5: Expenses | B5: 0 | C5: 0 | D5: 6 | F5: 0.03 | H5: Also in allowance of the same for a 6pence amercement of Henry Watsond which he was being charged for from the previous year for a plea of the Pavilion, of which he had the estreat and which he was not able to levy.
A6: Expenses | B6: 0 | C6: 1 | D6: 0 | F6: 0.05 | H6: 1 shilling for John de Northwych.
A7: Expenses | B7: 0 | C7: 0 | D7: 6 | F7: 0.03 | H7: 6pence for Nicholas le Keu of Chilbolton.
A8: Expenses | B8: 0 | C8: 2 | D8: 0 | F8: 0.1 | H8: Also in allowance of the same for his fur 2 shilling
A10: Expenses | B10: 3 | C10: 14 | D10: 10 | F10: =B10+C10/20+D10/240 | H10: Total of all expenses and allowances, £3 14shilling 10 pence.
A11: Expenses | F11: =SUM(F3:F8) | G11: =F11-F10 | H11: Total
A13: And he owes | B13: 21 | C13: 17 | D13: 2 | F13: =B13+C13/20+D13/240 | H13: And hew owes it all clear.

Sheet Issues of the Grange
A1: no grange

Sheet Issues of the Mills
A1: no mills

Sheet Stock
A1: no stock

Sheet raw data
A1: Heading | B1: Sentence | C1: Total in Pounds | D1: Pounds | E1: Shillings | F1: Pence | G1: Corn | H1: Total Quarters Except 1 | I1: Total Bushels Except 1 | J1: Total Corn Cross-Check | K1: Total Corn Manorial Account | L1: Corn Quantity Error | M1: Quarters 1 | N1: Bushels 1 | O1: shilling a quarter 1 | P1: pence a quarter 1 | Q1: shilling a quarter 2 | R1: pence a quarter 2 | S1: shilling a quarter 3 | T1: pence a quarter 3 | U1: shilling a quarter 4 | V1: pence a quarter 4 | W1: shilling a bushel 1 | X1: pence a bushel 1 | Y1: shilling a bushel 2 | Z1: pence a bushel 2 | AA1: shilling a bushel 3 | AB1: pence a bushel 3 | AC1: shilling a bushel 4 | AD1: pence a bushel 4
A2: Arrears | B2: Gilbert Marescallus renders account for £26 6 shilling 4pence of arrears from the previous year. | C2: 26.32 | D2: 26 | E2: 6 | F2: 4 | H2: 0 | I2: 0 | J2: 0 | K2: 0 | L2: 0 | M2: 0 | N2: 0
A3: Rents of assize | B3: The same renders account for 3 shilling 4pence for the rent of assize at Michaelmas of Thomas Schudd' for 1 messuage 20 acres of land and .5 acre of wood in West Pitt. | C3: 0.17 | D3: 0 | E3: 3 | F3: 4 | H3: 0 | I3: 0 | J3: 0 | K3: 0 | L3: 0 | M3: 0 | N3: 0
A4: Rents of assize | B4: 3 shilling 4pence for the rent of assize at the same term of the heir of John de Brafeld' for 1 messuage 20 acres of land and' acre of wood in the same vill. | C4: 0.17 | D4: 0 | E4: 3 | F4: 4 | H4: 0 | I4: 0 | J4: 0 | K4: 0 | L4: 0 | M4: 0 | N4: 0
A5: Rents of assize | B5: 3 shilling 4pence for the rent of assize at the same term of William Bygh' for 1 messuage 201 acres of land and' acre of wood in the same vill. | C5: 0.17 | D5: 0 | E5: 3 | F5: 4 | H5: 0 | I5: 0 | J5: 0 | K5: 0 | L5: 0 | M5: 0 | N5: 0
A6: Rents of assize | B6: 6 shilling 8pence for the rent of assize at the same term of William Alysanndr' for 2 messuages 40 acres of land and 1 acre of wood in the same vill. | C6: 0.33 | D6: 0 | E6: 6 | F6: 8 | H6: 0 | I6: 0 | J6: 0 | K6: 0 | L6: 0 | M6: 0 | N6: 0
A7: Rents of assize | B7: 3 shilling 4pence for the rent of assize at the same term of Aunger le Drivere and Agnes his wife for 1 messuage 20 acres of land and' acre of wood in the same vill. | C7: 0.17 | D7: 0 | E7: 3 | F7: 4 | H7: 0 | I7: 0 | J7: 0 | K7: 0 | L7: 0 | M7: 0 | N7: 0
A8: Rents of assize | B8: 6pence for the rent of assize at the same term of the heir of John de Brayfeld' for 1 cottage in the same vill. | C8: 0.03 | D8: 0 | E8: 0 | F8: 6 | H8: 0 | I8: 0 | J8: 0 | K8: 0 | L8: 0 | M8: 0 | N8: 0
A9: Rents of assize | B9: 3 shilling for the rent of assize at the same term of Drogo de Celar' and Amice his wife for a certain messuage in ICingsgate Street beside the Carmelite Friars. | C9: 0.15 | D9: 0 | E9: 3 | F9: 0 | H9: 0 | I9: 0 | J9: 0 | K9: 0 | L9: 0 | M9: 0 | N9: 0
A10: Rents of assize | B10: 2 shilling for the rent of assize at the same term of Robert de la Fermerie for a certain messuage opposite the house of John de Houlond' in the same place which is of the fee of West Pitt. | C10: 0.1 | D10: 0 | E10: 2 | F10: 0 | H10: 0 | I10: 0 | J10: 0 | K10: 0 | L10: 0 | M10: 0 | N10: 0
A11: Rents of assize | B11: Total, £1 5 shilling 6pence | C11: 1.27 | D11: 1 | E11: 5 | F11: 6 | H11: 0 | I11: 0 | J11: 0 | K11: 0 | L11: 0 | M11: 0 | N11: 0
A12: Rents of assize | B12: The same renders account for 6 shilling for the rent of assize at Michaelmas of the heir of Ralph de Gorhunte in Pendeworth'. | C12: 0.3 | D12: 0 | E12: 6 | F12: 0 | H12: 0 | I12: 0 | J12: 0 | K12: 0 | L12: 0 | M12: 0 | N12: 0
A13: Rents of assize | B13: Total, 6 shilling | C13: 0.3 | D13: 0 | E13: 6 | F13: 0 | H13: 0 | I13: 0 | J13: 0 | K13: 0 | L13: 0 | M13: 0 | N13: 0
... A127: Total of all expenses and allowances | B127: And he owes it all clear. | C127: 0 | D127: 0 | E127: 0 | F127: 0 | H127: 0 | I127: 0 | J127: 0 | K127: 0 | L127: 0 | M127: 0 | N127: 0
