Workbook

Sheet Merdon 1301 Overview - Completed
A1: MERDON 1301 OVERVIEW - COMPLETED | B1: Total in £ | C1: Error | D1: Note
A2: CASH ACCOUNT
A3: RECEIPTS
A4: Arrears total | B4: 40.36875
A5: Rents of assize total | B5: 38.876042
A6: Quittances total | B6: 1.875
A7: Defaults of rent total | B7: 0.275
A8: Defaults of rent through the pestilence total
A9: Cotlands defaults total
A10: Cotlands total
A11: Total of quittances and defaults of rent total
A12: Total of rents remaining clear total
A13: Farms total
A14: Annual recognizances total | B14: 0.1125
A15: Issues of the Manor total | B15: 40.347917
A16: Issues of the tenements in the lord's hands total
A17: Sale of labour services total
A18: Sale of corn total | B18: 104.03333
A19: Entry and marriage fines total | B19: 6.9666667
A20: Pleas & perquisites total | B20: 6.4416667
A21: Forfeited chattels total
A22: Farm of the demesne land total
A23: Total of all receipts (calculated here) | B23: =SUM(B5:B22)
A24: Total of all receipts (calculated here) incl arrears | B24: =SUM(B4:B22)
A25: Total recorded in the accounts excl. arrears | C25: =B23-B25
A26: Total recorded in the accounts incl. arrears | B26: =B25+B4
A29: EXPENSES
A30: Cost of ploughs total | B30: 9.6083333
A31: Purchase of corn total | B31: 12.042708
A32: Cost of carts and wagons total | B32: 1.8583333
A33: Cost of dairy total | B33: 10.972917
A34: Purchase of stock total
A35: Sheepcote total
A36: Cost of buildings total | B36: 0.93333333
A37: Threshing total | B37: 0.83958333
A38: Barley expenses
A39: Expenses of the harvest total | B39: 0.775
A40: Necessary expenses
A41: Wages of the bailiff
A42: Steward's expenses total
A43: Annual fees
A44: Total of all expenses per account
A45: Total of all expenses (calculated here)
A46: Total fixed investment
A47: Total Demesne fixed investment
A49: Owed by the reeve | B49: =B23-B45
A50: From accounts | B50: 47.901042
A52: Allowances
A53: Cash deliveries
A54: Sum of the above | B54: =SUM(B52:B53)
A55: Total of all allowances and cash deliveries in accounts
A57: Net amount owed | B57: =B50-B54
A58: Net amount owed in accounts
A60: GRANGE ACCOUNT | B60: Total Production | D60: Value of total gross production in £ | E60: Value of total net production in £
A61: Grange | B61: qrs | C61: bus
A62: Wheat | B62: 338.5
A63: Rye
A64: Dredge
A65: Curall | B65: 19
A66: Barley | B66: 61
A67: Oats | B67: 290
A68: Beans
A69: Peas
A70: Vetches | E70: 0.1
A71: Total value of gross production (sum of the above)
A72: Total value of net production
A73: Value of sales
A75: MILL ACCOUNT | B75: Total Production | D75: Total in £
A76: Issues of the mill | B76: qrs | C76: bus
A77: Wheat
A78: Oatmeal
A79: 1st grade malt
A80: 2nd grade malt
A81: Maslin
A82: Total value of production (sum of the above)
A83: Value of sales
A85: STOCK ACCOUNT
A86: Livestock | B86: Begin stock | C86: End stock | D86: Stockbuilding | F86: Value of stock in £ | G86: Value of stockbuilding
A87: Cart-horses | D87: =C87-B87 | F87: ='Stock'!K5*'Stock'!O5 | G87: =D87*'Stock'!O5
A88: Mares | C88: 0 | D88: =C88-B88 | F88: ='Stock'!K5*'Stock'!O5 | G88: =D88*'Stock'!O5
A89: Plough horses | B89: 11 | C89: 12 | D89: 1 | F89: ='Stock'!K6*'Stock'!O6 | G89: =D89*'Stock'!O6
A90: Colts (2 years) | C90: 0 | D90: =C90-B90 | F90: ='Stock'!K8*'Stock'!O8 | G90: =D90*'Stock'!O8
A91: Colts (2 years) | C91: 0 | D91: =C91-B91 | F91: ='Stock'!K8*'Stock'!O8 | G91: =D91*'Stock'!O8
A92: Colts (1 year) | C92: 0 | D92: =C92-B92 | F92: ='Stock'!K9*'Stock'!O9 | G92: =D92*'Stock'!O9
A93: Foals | C93: 0 | D93: =C93-B93 | F93: ='Stock'!K10*'Stock'!O10 | G93: =D93*'Stock'!O10
A94: Oxen | B94: 65 | C94: 59 | D94: -6 | F94: 59 | G94: -6
A95: Bulls | B95: 1 | C95: 1 | D95: 0 | F95: ='Stock'!K12*'Stock'!O12 | G95: =D95*'Stock'!O12
A96: Cows | B96: 23 | C96: 26 | D96: 3 | F96: ='Stock'!K13*'Stock'!O13 | G96: =D96*'Stock'!O13
A97: Steers | B97: 8 | C97: 0 | D97: -8 | F97: ='Stock'!K14*'Stock'!O14 | G97: =D97*'Stock'!O14
A98: Bullocks | B98: 9 | C98: 9 | D98: 0 | F98: ='Stock'!K15*'Stock'!O15 | G98: =D98*'Stock'!O15
A99: Yearlings | B99: 9 | C99: 9 | D99: 0 | F99: ='Stock'!K16*'Stock'!O16 | G99: =D99*'Stock'!O16
A100: Calves | C100: 10 | D100: =C100-B100 | F100: ='Stock'!K17*'Stock'!O17 | G100: =D100*'Stock'!O17
A101: Wethers | B101: 166 | C101: 171 | D101: 5 | F101: ='Stock'!K18*'Stock'!O18 | G101: =D101*'Stock'!O18
A102: Rams | B102: 12 | C102: 14 | D102: 2 | F102: 14 | G102: 2
A103: Ewes | B103: 238 | C103: 261 | D103: 23 | F103: ='Stock'!K20*'Stock'!O20 | G103: =D103*'Stock'!O20
A104: Hoggs | B104: 99 | C104: 0 | D104: -99 | F104: ='Stock'!K21*'Stock'!O21 | G104: =D104*'Stock'!O21
A105: Lambs | C105: 125 | D105: =C105-B105 | F105: ='Stock'!K22*'Stock'!O22 | G105: =D105*'Stock'!O22
A106: Boars | B106: 1 | C106: 1 | D106: 0 | F106: ='Stock'!K23*'Stock'!O23 | G106: =D106*'Stock'!O23
A107: Sows | B107: 2 | C107: 2 | D107: 0 | F107: ='Stock'!K24*'Stock'!O24 | G107: =D107*'Stock'!O24
A108: Pigs | B108: 21 | C108: 15 | D108: -6 | F108: ='Stock'!K25*'Stock'!O25 | G108: =D108*'Stock'!O25
...

Sheet Issues of the Mills
A1: No mill account for Adderbury

Sheet raw data
A1: Heading | B1: Sentence | C1: Total in Pounds | D1: Pounds | E1: Shillings | F1: Pence | G1: Corn | H1: Total Quarters Except 1 | I1: Total Bushels Except 1 | J1: Total Corn Cross-Check | K1: Total Corn Manorial Account | L1: Corn Quantity Error | M1: Quarters 1 | N1: Bushels 1 | O1: shilling a quarter 1 | P1: pence a quarter 1 | Q1: shilling a quarter 2 | R1: pence a quarter 2 | S1: shilling a quarter 3 | T1: pence a quarter 3 | U1: shilling a quarter 4 | V1: pence a quarter 4 | W1: shilling a bushel 1 | X1: pence a bushel 1 | Y1: shilling a bushel 2 | Z1: pence a bushel 2 | AA1: shilling a bushel 3 | AB1: pence a bushel 3 | AC1: shilling a bushel 4 | AD1: pence a bushel 4
A2: Adderbury | B2: The account2 of William Jakeman, reeve there, for the sixth year of the translation of Henry Beaufort', lord bishop of Winchester, and the eleventh year of the reign of King Henry the Fourth. | C2: 0 | D2: 0 | E2: 0 | F2: 0 | H2: 0 | I2: 0 | J2: 0 | K2: 0 | L2: 0 | M2: 0 | N2: 0
A3: Arrears | B3: None. | C3: 0 | D3: 0 | E3: 0 | F3: 0 | H3: 0 | I3: 0 | J3: 0 | K3: 0 | L3: 0 | M3: 0 | N3: 0
A4: Rents of assize | B4: And for £6 9 shilling 6.25pence for all rents of assize at St Thomas the Apostle (21 December). | C4: 6.48 | D4: 6 | E4: 9 | F4: 6.25 | H4: 0 | I4: 0 | J4: 0 | K4: 0 | L4: 0 | M4: 0 | N4: 0
A5: Rents of assize | B5: £6 9 shilling 8.5pence at Easter (23 March). | C5: 6.49 | D5: 6 | E5: 9 | F5: 8.5 | H5: 0 | I5: 0 | J5: 0 | K5: 0 | L5: 0 | M5: 0 | N5: 0
A6: Rents of assize | B6: £6 9 shilling 6.25pence at the Nativity of St John the Baptist (24 June). | C6: 6.48 | D6: 6 | E6: 9 | F6: 6.25 | H6: 0 | I6: 0 | J6: 0 | K6: 0 | L6: 0 | M6: 0 | N6: 0
A7: Rents of assize | B7: £6 10 shilling 1.5pence at Michaelmas (29 September). | C7: 6.51 | D7: 6 | E7: 10 | F7: 1.5 | H7: 0 | I7: 0 | J7: 0 | K7: 0 | L7: 0 | M7: 0 | N7: 0
A8: Rents of assize | B8: Total, £25 18 shilling 10.5pence. | C8: 25.94 | D8: 25 | E8: 18 | F8: 10.5 | H8: 0 | I8: 0 | J8: 0 | K8: 0 | L8: 0 | M8: 0 | N8: 0
A9: Quittances of rent | B9: In quittance of rent of 1 reeve for the year 5 shilling. | C9: 0.25 | D9: 0 | E9: 5 | F9: 0 | H9: 0 | I9: 0 | J9: 0 | K9: 0 | L9: 0 | M9: 0 | N9: 0
A10: Quittances of rent | B10: nothing this year of the 4 shilling for 1 smith forging the ironwork of 2 ploughs for the year. | C10: 0.2 | D10: 0 | E10: 4 | F10: 0 | H10: 0 | I10: 0 | J10: 0 | K10: 0 | L10: 0 | M10: 0 | N10: 0
A11: Quittances of rent | B11: nothing this year of the 4 shilling for 1 shepherd keeping the lord's wethers for the year. | C11: 0.2 | D11: 0 | E11: 4 | F11: 0 | H11: 0 | I11: 0 | J11: 0 | K11: 0 | L11: 0 | M11: 0 | N11: 0
A12: Quittances of rent | B12: nothing this year of the 4 shilling for 1 swineherd for the year. | C12: 0.2 | D12: 0 | E12: 4 | F12: 0 | H12: 0 | I12: 0 | J12: 0 | K12: 0 | L12: 0 | M12: 0 | N12: 0
A13: Quittances of rent | B13: nothing this year of the 4 shilling for 1 cowherd for the year. | C13: 0.2 | D13: 0 | E13: 4 | F13: 0 | H13: 0 | I13: 0 | J13: 0 | K13: 0 | L13: 0 | M13: 0 | N13: 0
... A149: Cost of buildings | B149: board-nails and clout-nails bought for the same 1 shilling 4pence. | C149: 0.07 | D149: 0 | E149: 1 | F149: 4 | H149: 0 | I149: 0 | J149: 0 | K149: 0 | L149: 0 | M149: 0 | N149: 0
A150: Cost of buildings | B150: 4 quarters 4 bushels of limestone bought at Walton' 5 shilling 3pence, at 1 shilling 2pence a quarters. | C150: 0.26 | D150: 0 | E150: 5 | F150: 3 | H150: 4 | I150: 4 | J150: 4.5 | K150: 4.5 | L150: 0 | M150: 4 | N150: 4 | O150: 1 | P150: 2
A151: Cost of buildings | B151: carrying the same 4pence. | C151: 0.02 | D151: 0 | E151: 0 | F151: 4 | H151: 0 | I151: 0 | J151: 0 | K151: 0 | L151: 0 | M151: 0 | N151: 0
A152: Cost of buildings | B152: 8 quarters of limestone bought at Witney 10 shilling 4pence, at 1 shilling 31 pence a quarters. | C152: 0.52 | D152: 0 | E152: 10 | F152: 4 | H152: 8 | I152: 0 | J152: 8 | K152: 8 | L152: 0 | M152: 8 | N152: 0 | O152: 1 | P152: 31
A153: Cost of buildings | B153: carrying the same from Witney to Adderbury 3 shilling 8pence. | C153: 0.18 | D153: 0 | E153: 3 | F153: 8 | H153: 0 | I153: 0 | J153: 0 | K153: 0 | L153: 0 | M153: 0 | N153: 0
A154: Cost of buildings | B154: 1,500 stone slates bought 6 shilling, at 4 shilling a 1,000.. | C154: 0.3 | D154: 0 | E154: 6 | F154: 0 | H154: 0 | I154: 0 | J154: 0 | K154: 0 | L154: 0 | M154: 0 | N154: 0
A155: Cost of buildings | B155: 500 eaves-stones bought 2 shilling 6pence, at 6pence a 100.. | C155: 0.12 | D155: 0 | E155: 2 | F155: 6 | H155: 0 | I155: 0 | J155: 0 | K155: 0 | L155: 0 | M155: 0 | N155: 0
A156: Cost of buildings | B156: 6,000 pins bought 2 shilling, at 4pence a 1,000.. | C156: 0.12 | D156: 0 | E156: 2 | F156: 4 | H156: 0 | I156: 0 | J156: 0 | K156: 0 | L156: 0 | M156: 0 | N156: 0
A157: Cost of buildings | B157: 50 ridge-tiles bought 6 shilling 3pence, at 1.5pence each. | C157: 0.31 | D157: 0 | E157: 6 | F157: 3 | H157: 0 | I157: 0 | J157: 0 | K157: 0 | L157: 0 | M157: 0 | N157: 0
A158: Cost of buildings | B158: sand bought and dug and quarried at Tadmarton 10pence. | C158: 0.04 | D158: 0 | E158: 0 | F158: 10 | H158: 0 | I158: 0 | J158: 0 | K158: 0 | L158: 0 | M158: 0 | N158: 0
A159: Cost of buildings | B159: stipend of 1 man going to Walton' to quarry lime there 2pence. | C159: 0.01 | D159: 0 | E159: 0 | F159: 2 | H159: 0 | I159: 0 | J159: 0 | K159: 0 | L159: 0 | M159: 0 | N159: 0
A160: Cost of buildings | B160: expenses of 12 men coming for a boon-work with 6 carts to quarry sand at Newotele and carry it to Adderbury, with the digging, 2 shilling 3pence. | C160: 0.11 | D160: 0 | E160: 2 | F160: 3 | H160: 0 | I160: 0 | J160: 0 | K160: 0 | L160: 0 | M160: 0 | N160: 0
A161: Cost of buildings | B161: hiring 1 man to carry sand and lime from the warrener's chamber to the barn by piece-work 4pence. | C161: 0.02 | D161: 0 | E161: 0 | F161: 4 | H161: 0 | I161: 0 | J161: 0 | K161: 0 | L161: 0 | M161: 0 | N161: 0
A162: Cost of buildings | B162: carrying the ridge-tiles bought above 8pence. | C162: 0.03 | D162: 0 | E162: 0 | F162: 8 | H162: 0 | I162: 0 | J162: 0 | K162: 0 | L162: 0 | M162: 0 | N162: 0
A163: Cost of buildings | B163: expenses of various men coming for a boon-work to buy slates at Aynho and carry them to Adderbury with the expenses of 1 man there mending the said slates 2d 1 shilling 9.5pence. | C163: 0.09 | D163: 0 | E163: 1 | F163: 9.5 | H163: 0 | I163: 0 | J163: 0 | K163: 0 | L163: 0 | M163: 0 | N163: 0
A164: Cost of buildings | B164: 1 tine bought 8pence. | C164: 0.03 | D164: 0 | E164: 0 | F164: 8 | H164: 0 | I164: 0 | J164: 0 | K164: 0 | L164: 0 | M164: 0 | N164: 0
... A181: Total of all allowances | B181: Total of all allowances and cash deliveries, £64 19 shilling 11.5pence He is quit. | C181: 65 | D181: 64 | E181: 19 | F181: 11.5 | H181: 0 | I181: 0 | J181: 0 | K181: 0 | L181: 0 | M181: 0 | N181: 0
A182: Wheat | B182: William Jakeman, reeve there, answers for 3 quarters of wheat remaining.. | C182: 0 | D182: 0 | E182: 0 | F182: 0 | G182: wheat | H182: 3 | I182: 0 | J182: 3 | K182: 3 | L182: 0 | M182: 3 | N182: 0
A183: Wheat | B183: Total, 3 quarters.. | C183: 0 | D183: 0 | E183: 0 | F183: 0 | H183: 3 | I183: 0 | J183: 3 | K183: 3 | L183: 0 | M183: 3 | N183: 0
A184: Wheat | B184: 3 quarters remain in the keeping of John Eadburbury, farmer there, to be handed back and restored at the end of his farm of 12 years, this year being the fifth. | C184: 0 | D184: 0 | E184: 0 | F184: 0 | H184: 3 | I184: 0 | J184: 3 | K184: 3 | L184: 0 | M184: 3 | N184: 0
A185: Rye | B185: And for 34 quarters of rye remaining.. | C185: 0 | D185: 0 | E185: 0 | F185: 0 | G185: rye | H185: 34 | I185: 0 | J185: 34 | K185: 34 | L185: 0 | M185: 34 | N185: 0
A186: Rye | B186: Total, 34 quarters.. | C186: 0 | D186: 0 | E186: 0 | F186: 0 | H186: 34 | I186: 0 | J186: 34 | K186: 34 | L186: 0 | M186: 34 | N186: 0
A187: Rye | B187: 34 quarters remain in the keeping of the said John Eadburbury, farmer there, to be handed back and restored at the end of his farm as before. | C187: 0 | D187: 0 | E187: 0 | F187: 0 | H187: 34 | I187: 0 | J187: 34 | K187: 34 | L187: 0 | M187: 34 | N187: 0
A188: Dredge | B188: And for 30 quarters of dredge remaining.. | C188: 0 | D188: 0 | E188: 0 | F188: 0 | G188: dredge | H188: 30 | I188: 0 | J188: 30 | K188: 30 | L188: 0 | M188: 30 | N188: 0
A189: Dredge | B189: Total, 30 quarters.. | C189: 0 | D189: 0 | E189: 0 | F189: 0 | H189: 30 | I189: 0 | J189: 30 | K189: 30 | L189: 0 | M189: 30 | N189: 0
A190: Dredge | B190: 30 quarters remain in the keeping of the said John Eadburbury, farmer there, to be handed back and restored as before. | C190: 0 | D190: 0 | E190: 0 | F190: 0 | H190: 30 | I190: 0 | J190: 30 | K190: 30 | L190: 0 | M190: 30 | N190: 0
A191: Pulses | B191: None remain. | C191: 0 | D191: 0 | E191: 0 | F191: 0 | H191: 0 | I191: 0 | J191: 0 | K191: 0 | L191: 0 | M191: 0 | N191: 0
A192: Oats | B192: And for 10 quarters of oats.. | C192: 0 | D192: 0 | E192: 0 | F192: 0 | G192: oats | H192: 10 | I192: 0 | J192: 10 | K192: 10 | L192: 0 | M192: 10 | N192: 0
A193: Oats | B193: Total, 10 quarters.. | C193: 0 | D193: 0 | E193: 0 | F193: 0 | H193: 10 | I193: 0 | J193: 10 | K193: 10 | L193: 0 | M193: 10 | N193: 0
A194: Oats | B194: 10 quarters remain in the keeping of the said John Eadburbury, farmer there, to be handed back and restored as before. | C194: 0 | D194: 0 | E194: 0 | F194: 0 | H194: 10 | I194: 0 | J194: 10 | K194: 10 | L194: 0 | M194: 10 | N194: 0
A195: Oats | B195: Eadburbury, farmer, to be handed back and restored at the end of his farm or the value of the same as before. | C195: 0 | D195: 0 | E195: 0 | F195: 0 | H195: 0 | I195: 0 | J195: 0 | K195: 0 | L195: 0 | M195: 0 | N195: 0
A196: Stock | B196: Horses: 4 remain. | C196: 0 | D196: 0 | E196: 0 | F196: 0 | H196: 0 | I196: 0 | J196: 0 | K196: 0 | L196: 0 | M196: 0 | N196: 0
A197: Stock | B197: 1 from the heriot of William Rundell'. | C197: 0 | D197: 0 | E197: 0 | F197: 0 | H197: 0 | I197: 0 | J197: 0 | K197: 0 | L197: 0 | M197: 0 | N197: 0
A198: Stock | B198: Total 5. 1 sold within. | C198: 0 | D198: 0 | E198: 0 | F198: 0 | H198: 0 | I198: 0 | J198: 0 | K198: 0 | L198: 0 | M198: 0 | N198: 0
A199: Stock | B199: 4 cart-horses remain, of which 2 are worth £1 6s 8pence, 1 is worth £1, and 1 feeble one is worth 2 shilling, in the keeping of the said John Eadburbury, farmer there, to be handed back and restored at the end of his farm or the value of the same at the choice of the lord bishop or his attorney. | C199: 1 | D199: 1 | E199: 0 | F199: 0 | H199: 0 | I199: 0 | J199: 0 | K199: 0 | L199: 0 | M199: 0 | N199: 0
A200: Stock | B200: Plough-horses: 6 remain. | C200: 0 | D200: 0 | E200: 0 | F200: 0 | H200: 0 | I200: 0 | J200: 0 | K200: 0 | L200: 0 | M200: 0 | N200: 0
A201: Stock | B201: Total, 6. 6 remain, worth £2, in the keeping of John. | C201: 2 | D201: 2 | E201: 0 | F201: 0 | H201: 0 | I201: 0 | J201: 0 | K201: 0 | L201: 0 | M201: 0 | N201: 0
A202: Stock | B202: Colts: 1 from the heriot of John Diconurn. | C202: 0 | D202: 0 | E202: 0 | F202: 0 | H202: 0 | I202: 0 | J202: 0 | K202: 0 | L202: 0 | M202: 0 | N202: 0
A203: Stock | B203: sold within. | C203: 0 | D203: 0 | E203: 0 | F203: 0 | H203: 0 | I203: 0 | J203: 0 | K203: 0 | L203: 0 | M203: 0 | N203: 0
A204: Stock | B204: none remain. | C204: 0 | D204: 0 | E204: 0 | F204: 0 | H204: 0 | I204: 0 | J204: 0 | K204: 0 | L204: 0 | M204: 0 | N204: 0
... A268: Stock | B268: none remain. mid. | C268: 0 | D268: 0 | E268: 0 | F268: 0 | H268: 0 | I268: 0 | J268: 0 | K268: 0 | L268: 0 | M268: 0 | N268: 0

Sheet Prices
A1: Meat & Dairy Prices
C2: 1301 | D2: 1302 | E2: Average
A3: Beef | B3: £ per lb | C3: 0.0033351854 | D3: 0.0032608538 | E3: =AVERAGE(C3:D3)
A4: Mutton | B4: £ per lb | C4: 0.0036593977 | D4: 0.0037125513 | E4: =AVERAGE(C4:D4)
A5: Pork | B5: £ per lb | C5: 0.0038431326 | D5: 0.0037574803 | E5: =AVERAGE(C5:D5)
A6: Cheese | B6: £ per lb | C6: 0.0055768754 | D6: 0.0056654898 | E6: =AVERAGE(C6:D6)
A7: Butter | B7: £ per lb | C7: 0.0036626221 | D7: 0.0035935077 | E7: =AVERAGE(C7:D7)
A8: Milk | B8: £ per gallon | C8: 0.0055768754 | D8: 0.0056654898 | E8: =AVERAGE(C8:D8)

Sheet Labour Rents

Sheet Merdon Overview
A1: MERDON OVERVIEW | B1: £ | C1: s | D1: d | G1: Total in £ | H1: Error
A3: CASH ACCOUNT
A4: RECEIPTS
A5: Arrears total | G5: =IF(INDEX('Merdon Receipts'!$A$4:$F$131,MATCH('Merdon Overview'!$A5,'Merdon Receipts'!$A$4:$A$131,0),6)=0,"",INDEX('Merdon Receipts'!$A$4:$F$131,MATCH('Merdon Overview'!$A5,'Merdon Receipts'!$A$4:$A$131,0),6))
A6: Rents of assize total | G6: =IF(INDEX('Merdon Receipts'!$A$4:$F$131,MATCH('Merdon Overview'!$A6,'Merdon Receipts'!$A$4:$A$131,0),6)=0,"",INDEX('Merdon Receipts'!$A$4:$F$131,MATCH('Merdon Overview'!$A6,'Merdon Receipts'!$A$4:$A$131,0),6))
A7: Quittances total | G7: =IF(INDEX('Merdon Receipts'!$A$4:$F$131,MATCH('Merdon Overview'!$A7,'Merdon Receipts'!$A$4:$A$131,0),6)=0,"",INDEX('Merdon Receipts'!$A$4:$F$131,MATCH('Merdon Overview'!$A7,'Merdon Receipts'!$A$4:$A$131,0),6))
A8: Defaults of rent total | G8: =IF(INDEX('Merdon Receipts'!$A$4:$F$131,MATCH('Merdon Overview'!$A8,'Merdon Receipts'!$A$4:$A$131,0),6)=0,"",INDEX('Merdon Receipts'!$A$4:$F$131,MATCH('Merdon Overview'!$A8,'Merdon Receipts'!$A$4:$A$131,0),6))
A9: Total rents remaining | G9: ='Merdon Receipts'!F30
A10: Annual recognizances total | G10: =IF(INDEX('Merdon Receipts'!$A$4:$F$131,MATCH('Merdon Overview'!$A10,'Merdon Receipts'!$A$4:$A$131,0),6)=0,"",INDEX('Merdon Receipts'!$A$4:$F$131,MATCH('Merdon Overview'!$A10,'Merdon Receipts'!$A$4:$A$131,0),6))
A11: Issues of the Manor total | G11: =IF(INDEX('Merdon Receipts'!$A$4:$F$131,MATCH('Merdon Overview'!$A11,'Merdon Receipts'!$A$4:$A$131,0),6)=0,"",INDEX('Merdon Receipts'!$A$4:$F$131,MATCH('Merdon Overview'!$A11,'Merdon Receipts'!$A$4:$A$131,0),6))
A12: Sale of corn total | G12: =IF(INDEX('Merdon Receipts'!$A$4:$F$131,MATCH('Merdon Overview'!$A12,'Merdon Receipts'!$A$4:$A$131,0),6)=0,"",INDEX('Merdon Receipts'!$A$4:$F$131,MATCH('Merdon Overview'!$A12,'Merdon Receipts'!$A$4:$A$131,0),6))
A13: Entry and marriage fines total | G13: =IF(INDEX('Merdon Receipts'!$A$4:$F$131,MATCH('Merdon Overview'!$A13,'Merdon Receipts'!$A$4:$A$131,0),6)=0,"",INDEX('Merdon Receipts'!$A$4:$F$131,MATCH('Merdon Overview'!$A13,'Merdon Receipts'!$A$4:$A$131,0),6))
A14: Pleas & perquisites total | G14: =IF(INDEX('Merdon Receipts'!$A$4:$F$131,MATCH('Merdon Overview'!$A14,'Merdon Receipts'!$A$4:$A$131,0),6)=0,"",INDEX('Merdon Receipts'!$A$4:$F$131,MATCH('Merdon Overview'!$A14,'Merdon Receipts'!$A$4:$A$131,0),6))
A15: Sum of the above (incl. arrears) | G15: =G5+G9+G10+G11+G12+G13+G14
A16: Total recorded in the accounts excl. arrears | G16: ='Merdon Receipts'!F130 | H16: =G15-G16
A17: Total recorded in the accounts incl. arrears | G17: ='Merdon Receipts'!F131
A20: EXPENSES
A21: Cost of ploughs total | G21: =IF(INDEX('Merdon Expenses'!$A$2:$F$170,MATCH('Merdon Overview'!$A21,'Merdon Expenses'!$A$2:$A$170,0),6)=0,"",INDEX('Merdon Expenses'!$A$2:$F$170,MATCH('Merdon Overview'!$A21,'Merdon Expenses'!$A$2:$A$170,0),6))
A22: Purchase of corn total | G22: =IF(INDEX('Merdon Expenses'!$A$2:$F$170,MATCH('Merdon Overview'!$A22,'Merdon Expenses'!$A$2:$A$170,0),6)=0,"",INDEX('Merdon Expenses'!$A$2:$F$170,MATCH('Merdon Overview'!$A22,'Merdon Expenses'!$A$2:$A$170,0),6))
A23: Cost of carts and wagons total | G23: =IF(INDEX('Merdon Expenses'!$A$2:$F$170,MATCH('Merdon Overview'!$A23,'Merdon Expenses'!$A$2:$A$170,0),6)=0,"",INDEX('Merdon Expenses'!$A$2:$F$170,MATCH('Merdon Overview'!$A23,'Merdon Expenses'!$A$2:$A$170,0),6))
A24: Cost of dairy total | G24: =IF(INDEX('Merdon Expenses'!$A$2:$F$170,MATCH('Merdon Overview'!$A24,'Merdon Expenses'!$A$2:$A$170,0),6)=0,"",INDEX('Merdon Expenses'!$A$2:$F$170,MATCH('Merdon Overview'!$A24,'Merdon Expenses'!$A$2:$A$170,0),6))
A25: Weeding total | G25: =IF(INDEX('Merdon Expenses'!$A$2:$F$170,MATCH('Merdon Overview'!$A25,'Merdon Expenses'!$A$2:$A$170,0),6)=0,"",INDEX('Merdon Expenses'!$A$2:$F$170,MATCH('Merdon Overview'!$A25,'Merdon Expenses'!$A$2:$A$170,0),6))
A26: Provision of household servants at harvest-time total | G26: =IF(INDEX('Merdon Expenses'!$A$2:$F$170,MATCH('Merdon Overview'!$A26,'Merdon Expenses'!$A$2:$A$170,0),6)=0,"",INDEX('Merdon Expenses'!$A$2:$F$170,MATCH('Merdon Overview'!$A26,'Merdon Expenses'!$A$2:$A$170,0),6))
A27: Cost of buildings total | G27: =IF(INDEX('Merdon Expenses'!$A$2:$F$170,MATCH('Merdon Overview'!$A27,'Merdon Expenses'!$A$2:$A$170,0),6)=0,"",INDEX('Merdon Expenses'!$A$2:$F$170,MATCH('Merdon Overview'!$A27,'Merdon Expenses'!$A$2:$A$170,0),6))
A28: Threshing total | G28: =IF(INDEX('Merdon Expenses'!$A$2:$F$170,MATCH('Merdon Overview'!$A28,'Merdon Expenses'!$A$2:$A$170,0),6)=0,"",INDEX('Merdon Expenses'!$A$2:$F$170,MATCH('Merdon Overview'!$A28,'Merdon Expenses'!$A$2:$A$170,0),6))
A29: Expenses of the harvest total | G29: =IF(INDEX('Merdon Expenses'!$A$2:$F$170,MATCH('Merdon Overview'!$A29,'Merdon Expenses'!$A$2:$A$170,0),6)=0,"",INDEX('Merdon Expenses'!$A$2:$F$170,MATCH('Merdon Overview'!$A29,'Merdon Expenses'!$A$2:$A$170,0),6))
A30: Payments for building repairs total | G30: =IF(INDEX('Merdon Expenses'!$A$2:$F$170,MATCH('Merdon Overview'!$A30,'Merdon Expenses'!$A$2:$A$170,0),6)=0,"",INDEX('Merdon Expenses'!$A$2:$F$170,MATCH('Merdon Overview'!$A30,'Merdon Expenses'!$A$2:$A$170,0),6))
A31: Cost of the park total | G31: =IF(INDEX('Merdon Expenses'!$A$2:$F$170,MATCH('Merdon Overview'!$A31,'Merdon Expenses'!$A$2:$A$170,0),6)=0,"",INDEX('Merdon Expenses'!$A$2:$F$170,MATCH('Merdon Overview'!$A31,'Merdon Expenses'!$A$2:$A$170,0),6))
A32: Steward's expenses total | G32: =IF(INDEX('Merdon Expenses'!$A$2:$F$170,MATCH('Merdon Overview'!$A32,'Merdon Expenses'!$A$2:$A$170,0),6)=0,"",INDEX('Merdon Expenses'!$A$2:$F$170,MATCH('Merdon Overview'!$A32,'Merdon Expenses'!$A$2:$A$170,0),6))
A33: Sum of the above | G33: =SUM(G21:G32)
A34: Total of all expenses | G34: ='Merdon Expenses'!F165 | H34: =G33-G34
A35: Capital Expenses | G35: ='Merdon Expenses'!F170
A37: Owed by the reeve | G37: =G15-G5-G33
A38: From accounts | G38: ='Merdon Expenses'!F166 | H38: =G38-G37
A40: Cash deliveries | G40: ='Merdon Expenses'!F168
A41: Total of all allowances and cash deliveries in accounts | B41: n/a | G41: =SUM(G40)
A43: Net amount owed | G43: =G38-G40
A44: Net amount owed in accounts | G44: ='Merdon Expenses'!F169 | H44: =G44-G43
A46: GRANGE ACCOUNT | B46: Net Production
A47: Grange | B47: qrs | G47: Value of net output (£) | H47: Value of total gross production in £ | I47: Note: Columns indexed are hardcoded, do not alter number of columns in issues of grange
A48: Net wheat | B48: =IF(INDEX('Issues of the Grange'!$A$2:$P$25,MATCH('Merdon Overview'!$A48,'Issues of the Grange'!$A$2:$A$25,0),10)=0,"",INDEX('Issues of the Grange'!$A$2:$P$25,MATCH('Merdon Overview'!$A48,'Issues of the Grange'!$A$2:$A$25,0),10)) | G48: =IF(INDEX('Issues of the Grange'!$A$2:$P$25,MATCH('Merdon Overview'!$A48,'Issues of the Grange'!$A$2:$A$25,0),13)=0,"",INDEX('Issues of the Grange'!$A$2:$P$25,MATCH('Merdon Overview'!$A48,'Issues of the Grange'!$A$2:$A$25,0),13)) | H48: ='Issues of the Grange'!P5
A49: Net curall | B49: =IF(INDEX('Issues of the Grange'!$A$2:$P$25,MATCH('Merdon Overview'!$A49,'Issues of the Grange'!$A$2:$A$25,0),10)=0,"",INDEX('Issues of the Grange'!$A$2:$P$25,MATCH('Merdon Overview'!$A49,'Issues of the Grange'!$A$2:$A$25,0),10)) | G49: =IF(INDEX('Issues of the Grange'!$A$2:$P$25,MATCH('Merdon Overview'!$A49,'Issues of the Grange'!$A$2:$A$25,0),13)=0,"",INDEX('Issues of the Grange'!$A$2:$P$25,MATCH('Merdon Overview'!$A49,'Issues of the Grange'!$A$2:$A$25,0),13)) | H49: ='Issues of the Grange'!P6
A50: Net barley | B50: =IF(INDEX('Issues of the Grange'!$A$2:$P$25,MATCH('Merdon Overview'!$A50,'Issues of the Grange'!$A$2:$A$25,0),10)=0,"",INDEX('Issues of the Grange'!$A$2:$P$25,MATCH('Merdon Overview'!$A50,'Issues of the Grange'!$A$2:$A$25,0),10)) | G50: =IF(INDEX('Issues of the Grange'!$A$2:$P$25,MATCH('Merdon Overview'!$A50,'Issues of the Grange'!$A$2:$A$25,0),13)=0,"",INDEX('Issues of the Grange'!$A$2:$P$25,MATCH('Merdon Overview'!$A50,'Issues of the Grange'!$A$2:$A$25,0),13)) | H50: ='Issues of the Grange'!P7
A51: Net oats | B51: =IF(INDEX('Issues of the Grange'!$A$2:$P$25,MATCH('Merdon Overview'!$A51,'Issues of the Grange'!$A$2:$A$25,0),10)=0,"",INDEX('Issues of the Grange'!$A$2:$P$25,MATCH('Merdon Overview'!$A51,'Issues of the Grange'!$A$2:$A$25,0),10)) | G51: =IF(INDEX('Issues of the Grange'!$A$2:$P$25,MATCH('Merdon Overview'!$A51,'Issues of the Grange'!$A$2:$A$25,0),13)=0,"",INDEX('Issues of the Grange'!$A$2:$P$25,MATCH('Merdon Overview'!$A51,'Issues of the Grange'!$A$2:$A$25,0),13)) | H51: ='Issues of the Grange'!P8
A52: Net peas | B52: =IF(INDEX('Issues of the Grange'!$A$2:$P$25,MATCH('Merdon Overview'!$A52,'Issues of the Grange'!$A$2:$A$25,0),10)=0,"",INDEX('Issues of the Grange'!$A$2:$P$25,MATCH('Merdon Overview'!$A52,'Issues of the Grange'!$A$2:$A$25,0),10)) | G52: =IF(INDEX('Issues of the Grange'!$A$2:$P$25,MATCH('Merdon Overview'!$A52,'Issues of the Grange'!$A$2:$A$25,0),13)=0,"",INDEX('Issues of the Grange'!$A$2:$P$25,MATCH('Merdon Overview'!$A52,'Issues of the Grange'!$A$2:$A$25,0),13)) | H52: ='Issues of the Grange'!P9
A53: Net vetches | B53: =IF(INDEX('Issues of the Grange'!$A$2:$P$25,MATCH('Merdon Overview'!$A53,'Issues of the Grange'!$A$2:$A$25,0),10)=0,"",INDEX('Issues of the Grange'!$A$2:$P$25,MATCH('Merdon Overview'!$A53,'Issues of the Grange'!$A$2:$A$25,0),10)) | G53: =IF(INDEX('Issues of the Grange'!$A$2:$P$25,MATCH('Merdon Overview'!$A53,'Issues of the Grange'!$A$2:$A$25,0),13)=0,"",INDEX('Issues of the Grange'!$A$2:$P$25,MATCH('Merdon Overview'!$A53,'Issues of the Grange'!$A$2:$A$25,0),13)) | H53: ='Issues of the Grange'!P10
A54: Total value of gross production (sum of the above) | G54: =SUM(H48:H53)
A55: Total value of net production | G55: =SUM(G48:G53)
A56: Value of sales | G56: ='Issues of the Grange'!N25
A58: MILL ACCOUNT | B58: n/a
A59: Issues of the mill | B59: qrs | C59: bus | G59: £
A60: Wheat
A61: Oatmeal
A62: 1st grade malt
A63: 2nd grade malt
A64: Maslin
A65: Total value of production (sum of the above)
A66: Value of sales | G66: n/a
A68: STOCK ACCOUNT
A69: Livestock | B69: Inherited stock | C69: End-period stock | D69: Stockbuilding | F69: Sales in (£) | G69: Value of stock (£) at sales prices | H69: Value of production (£) at sales prices
A70: Cart-horses | B70: =IFERROR(INDEX(Stock!$A$3:$U$92,MATCH('Merdon Overview'!$A70,Stock!$A$3:$A$92,0),MATCH('Merdon Overview'!B$69,Stock!$A$3:$U$3,0)),0) | C70: =IFERROR(INDEX(Stock!$A$3:$U$92,MATCH('Merdon Overview'!$A70,Stock!$A$3:$A$92,0),MATCH('Merdon Overview'!C$69,Stock!$A$3:$U$3,0)),0) | D70: =C70-B70 | F70: =IFERROR(INDEX(Stock!$A$3:$U$92,MATCH('Merdon Overview'!$A70,Stock!$A$3:$A$92,0),MATCH('Merdon Overview'!F$69,Stock!$A$3:$U$3,0)),0) | H70: =IFERROR(INDEX(Stock!$A$3:$U$92,MATCH('Merdon Overview'!$A70,Stock!$A$3:$A$92,0),MATCH('Merdon Overview'!H$69,Stock!$A$3:$U$3,0)),0)
A71: Mares | B71: =IFERROR(INDEX(Stock!$A$3:$U$92,MATCH('Merdon Overview'!$A71,Stock!$A$3:$A$92,0),MATCH('Merdon Overview'!B$69,Stock!$A$3:$U$3,0)),0) | C71: =IFERROR(INDEX(Stock!$A$3:$U$92,MATCH('Merdon Overview'!$A71,Stock!$A$3:$A$92,0),MATCH('Merdon Overview'!C$69,Stock!$A$3:$U$3,0)),0) | D71: =C71-B71 | F71: =IFERROR(INDEX(Stock!$A$3:$U$92,MATCH('Merdon Overview'!$A71,Stock!$A$3:$A$92,0),MATCH('Merdon Overview'!F$69,Stock!$A$3:$U$3,0)),0) | H71: =IFERROR(INDEX(Stock!$A$3:$U$92,MATCH('Merdon Overview'!$A71,Stock!$A$3:$A$92,0),MATCH('Merdon Overview'!H$69,Stock!$A$3:$U$3,0)),0)
A72: Plough horses | B72: =IFERROR(INDEX(Stock!$A$3:$U$92,MATCH('Merdon Overview'!$A72,Stock!$A$3:$A$92,0),MATCH('Merdon Overview'!B$69,Stock!$A$3:$U$3,0)),0) | C72: =IFERROR(INDEX(Stock!$A$3:$U$92,MATCH('Merdon Overview'!$A72,Stock!$A$3:$A$92,0),MATCH('Merdon Overview'!C$69,Stock!$A$3:$U$3,0)),0) | D72: =C72-B72 | F72: =IFERROR(INDEX(Stock!$A$3:$U$92,MATCH('Merdon Overview'!$A72,Stock!$A$3:$A$92,0),MATCH('Merdon Overview'!F$69,Stock!$A$3:$U$3,0)),0) | G72: =Stock!S6 | H72: =IFERROR(INDEX(Stock!$A$3:$U$92,MATCH('Merdon Overview'!$A72,Stock!$A$3:$A$92,0),MATCH('Merdon Overview'!H$69,Stock!$A$3:$U$3,0)),0)
A73: Colts (2 years) | B73: =IFERROR(INDEX(Stock!$A$3:$U$92,MATCH('Merdon Overview'!$A73,Stock!$A$3:$A$92,0),MATCH('Merdon Overview'!B$69,Stock!$A$3:$U$3,0)),0) | C73: =IFERROR(INDEX(Stock!$A$3:$U$92,MATCH('Merdon Overview'!$A73,Stock!$A$3:$A$92,0),MATCH('Merdon Overview'!C$69,Stock!$A$3:$U$3,0)),0) | D73: =C73-B73 | F73: =IFERROR(INDEX(Stock!$A$3:$U$92,MATCH('Merdon Overview'!$A73,Stock!$A$3:$A$92,0),MATCH('Merdon Overview'!F$69,Stock!$A$3:$U$3,0)),0) | H73: =IFERROR(INDEX(Stock!$A$3:$U$92,MATCH('Merdon Overview'!$A73,Stock!$A$3:$A$92,0),MATCH('Merdon Overview'!H$69,Stock!$A$3:$U$3,0)),0)
A74: Colts (2 years) | B74: =IFERROR(INDEX(Stock!$A$3:$U$92,MATCH('Merdon Overview'!$A74,Stock!$A$3:$A$92,0),MATCH('Merdon Overview'!B$69,Stock!$A$3:$U$3,0)),0) | C74: =IFERROR(INDEX(Stock!$A$3:$U$92,MATCH('Merdon Overview'!$A74,Stock!$A$3:$A$92,0),MATCH('Merdon Overview'!C$69,Stock!$A$3:$U$3,0)),0) | D74: =C74-B74 | F74: =IFERROR(INDEX(Stock!$A$3:$U$92,MATCH('Merdon Overview'!$A74,Stock!$A$3:$A$92,0),MATCH('Merdon Overview'!F$69,Stock!$A$3:$U$3,0)),0) | H74: =IFERROR(INDEX(Stock!$A$3:$U$92,MATCH('Merdon Overview'!$A74,Stock!$A$3:$A$92,0),MATCH('Merdon Overview'!H$69,Stock!$A$3:$U$3,0)),0)
A75: Colts (1 year) | B75: =IFERROR(INDEX(Stock!$A$3:$U$92,MATCH('Merdon Overview'!$A75,Stock!$A$3:$A$92,0),MATCH('Merdon Overview'!B$69,Stock!$A$3:$U$3,0)),0) | C75: =IFERROR(INDEX(Stock!$A$3:$U$92,MATCH('Merdon Overview'!$A75,Stock!$A$3:$A$92,0),MATCH('Merdon Overview'!C$69,Stock!$A$3:$U$3,0)),0) | D75: =C75-B75 | F75: =IFERROR(INDEX(Stock!$A$3:$U$92,MATCH('Merdon Overview'!$A75,Stock!$A$3:$A$92,0),MATCH('Merdon Overview'!F$69,Stock!$A$3:$U$3,0)),0) | H75: =IFERROR(INDEX(Stock!$A$3:$U$92,MATCH('Merdon Overview'!$A75,Stock!$A$3:$A$92,0),MATCH('Merdon Overview'!H$69,Stock!$A$3:$U$3,0)),0)
A76: Foals | B76: =IFERROR(INDEX(Stock!$A$3:$U$92,MATCH('Merdon Overview'!$A76,Stock!$A$3:$A$92,0),MATCH('Merdon Overview'!B$69,Stock!$A$3:$U$3,0)),0) | C76: =IFERROR(INDEX(Stock!$A$3:$U$92,MATCH('Merdon Overview'!$A76,Stock!$A$3:$A$92,0),MATCH('Merdon Overview'!C$69,Stock!$A$3:$U$3,0)),0) | D76: =C76-B76 | F76: =IFERROR(INDEX(Stock!$A$3:$U$92,MATCH('Merdon Overview'!$A76,Stock!$A$3:$A$92,0),MATCH('Merdon Overview'!F$69,Stock!$A$3:$U$3,0)),0) | H76: =IFERROR(INDEX(Stock!$A$3:$U$92,MATCH('Merdon Overview'!$A76,Stock!$A$3:$A$92,0),MATCH('Merdon Overview'!H$69,Stock!$A$3:$U$3,0)),0)
A77: Oxen | B77: =IFERROR(INDEX(Stock!$A$3:$U$92,MATCH('Merdon Overview'!$A77,Stock!$A$3:$A$92,0),MATCH('Merdon Overview'!B$69,Stock!$A$3:$U$3,0)),0) | C77: =IFERROR(INDEX(Stock!$A$3:$U$92,MATCH('Merdon Overview'!$A77,Stock!$A$3:$A$92,0),MATCH('Merdon Overview'!C$69,Stock!$A$3:$U$3,0)),0) | D77: =C77-B77 | F77: =IFERROR(INDEX(Stock!$A$3:$U$92,MATCH('Merdon Overview'!$A77,Stock!$A$3:$A$92,0),MATCH('Merdon Overview'!F$69,Stock!$A$3:$U$3,0)),0) | G77: =Stock!S11 | H77: =IFERROR(INDEX(Stock!$A$3:$U$92,MATCH('Merdon Overview'!$A77,Stock!$A$3:$A$92,0),MATCH('Merdon Overview'!H$69,Stock!$A$3:$U$3,0)),0)
A78: Bulls | B78: =IFERROR(INDEX(Stock!$A$3:$U$92,MATCH('Merdon Overview'!$A78,Stock!$A$3:$A$92,0),MATCH('Merdon Overview'!B$69,Stock!$A$3:$U$3,0)),0) | C78: =IFERROR(INDEX(Stock!$A$3:$U$92,MATCH('Merdon Overview'!$A78,Stock!$A$3:$A$92,0),MATCH('Merdon Overview'!C$69,Stock!$A$3:$U$3,0)),0) | D78: =C78-B78 | F78: =IFERROR(INDEX(Stock!$A$3:$U$92,MATCH('Merdon Overview'!$A78,Stock!$A$3:$A$92,0),MATCH('Merdon Overview'!F$69,Stock!$A$3:$U$3,0)),0) | H78: =IFERROR(INDEX(Stock!$A$3:$U$92,MATCH('Merdon Overview'!$A78,Stock!$A$3:$A$92,0),MATCH('Merdon Overview'!H$69,Stock!$A$3:$U$3,0)),0)
A79: Cows | B79: =IFERROR(INDEX(Stock!$A$3:$U$92,MATCH('Merdon Overview'!$A79,Stock!$A$3:$A$92,0),MATCH('Merdon Overview'!B$69,Stock!$A$3:$U$3,0)),0) | C79: =IFERROR(INDEX(Stock!$A$3:$U$92,MATCH('Merdon Overview'!$A79,Stock!$A$3:$A$92,0),MATCH('Merdon Overview'!C$69,Stock!$A$3:$U$3,0)),0) | D79: =C79-B79 | F79: =IFERROR(INDEX(Stock!$A$3:$U$92,MATCH('Merdon Overview'!$A79,Stock!$A$3:$A$92,0),MATCH('Merdon Overview'!F$69,Stock!$A$3:$U$3,0)),0) | G79: =Stock!S13 | H79: =IFERROR(INDEX(Stock!$A$3:$U$92,MATCH('Merdon Overview'!$A79,Stock!$A$3:$A$92,0),MATCH('Merdon Overview'!H$69,Stock!$A$3:$U$3,0)),0)
A80: Steers | B80: =IFERROR(INDEX(Stock!$A$3:$U$92,MATCH('Merdon Overview'!$A80,Stock!$A$3:$A$92,0),MATCH('Merdon Overview'!B$69,Stock!$A$3:$U$3,0)),0) | C80: =IFERROR(INDEX(Stock!$A$3:$U$92,MATCH('Merdon Overview'!$A80,Stock!$A$3:$A$92,0),MATCH('Merdon Overview'!C$69,Stock!$A$3:$U$3,0)),0) | D80: =C80-B80 | F80: =IFERROR(INDEX(Stock!$A$3:$U$92,MATCH('Merdon Overview'!$A80,Stock!$A$3:$A$92,0),MATCH('Merdon Overview'!F$69,Stock!$A$3:$U$3,0)),0) | H80: =IFERROR(INDEX(Stock!$A$3:$U$92,MATCH('Merdon Overview'!$A80,Stock!$A$3:$A$92,0),MATCH('Merdon Overview'!H$69,Stock!$A$3:$U$3,0)),0)
A81: Bullocks | B81: =IFERROR(INDEX(Stock!$A$3:$U$92,MATCH('Merdon Overview'!$A81,Stock!$A$3:$A$92,0),MATCH('Merdon Overview'!B$69,Stock!$A$3:$U$3,0)),0) | C81: =IFERROR(INDEX(Stock!$A$3:$U$92,MATCH('Merdon Overview'!$A81,Stock!$A$3:$A$92,0),MATCH('Merdon Overview'!C$69,Stock!$A$3:$U$3,0)),0) | D81: =C81-B81 | F81: =IFERROR(INDEX(Stock!$A$3:$U$92,MATCH('Merdon Overview'!$A81,Stock!$A$3:$A$92,0),MATCH('Merdon Overview'!F$69,Stock!$A$3:$U$3,0)),0) | H81: =IFERROR(INDEX(Stock!$A$3:$U$92,MATCH('Merdon Overview'!$A81,Stock!$A$3:$A$92,0),MATCH('Merdon Overview'!H$69,Stock!$A$3:$U$3,0)),0)
A82: Yearlings | B82: =IFERROR(INDEX(Stock!$A$3:$U$92,MATCH('Merdon Overview'!$A82,Stock!$A$3:$A$92,0),MATCH('Merdon Overview'!B$69,Stock!$A$3:$U$3,0)),0) | C82: =IFERROR(INDEX(Stock!$A$3:$U$92,MATCH('Merdon Overview'!$A82,Stock!$A$3:$A$92,0),MATCH('Merdon Overview'!C$69,Stock!$A$3:$U$3,0)),0) | D82: =C82-B82 | F82: =IFERROR(INDEX(Stock!$A$3:$U$92,MATCH('Merdon Overview'!$A82,Stock!$A$3:$A$92,0),MATCH('Merdon Overview'!F$69,Stock!$A$3:$U$3,0)),0) | H82: =IFERROR(INDEX(Stock!$A$3:$U$92,MATCH('Merdon Overview'!$A82,Stock!$A$3:$A$92,0),MATCH('Merdon Overview'!H$69,Stock!$A$3:$U$3,0)),0)
A83: Calves | B83: =IFERROR(INDEX(Stock!$A$3:$U$92,MATCH('Merdon Overview'!$A83,Stock!$A$3:$A$92,0),MATCH('Merdon Overview'!B$69,Stock!$A$3:$U$3,0)),0) | C83: =IFERROR(INDEX(Stock!$A$3:$U$92,MATCH('Merdon Overview'!$A83,Stock!$A$3:$A$92,0),MATCH('Merdon Overview'!C$69,Stock!$A$3:$U$3,0)),0) | D83: =C83-B83 | F83: =IFERROR(INDEX(Stock!$A$3:$U$92,MATCH('Merdon Overview'!$A83,Stock!$A$3:$A$92,0),MATCH('Merdon Overview'!F$69,Stock!$A$3:$U$3,0)),0) | G83: =Stock!S17 | H83: =IFERROR(INDEX(Stock!$A$3:$U$92,MATCH('Merdon Overview'!$A83,Stock!$A$3:$A$92,0),MATCH('Merdon Overview'!H$69,Stock!$A$3:$U$3,0)),0)
A84: Wethers | B84: =IFERROR(INDEX(Stock!$A$3:$U$92,MATCH('Merdon Overview'!$A84,Stock!$A$3:$A$92,0),MATCH('Merdon Overview'!B$69,Stock!$A$3:$U$3,0)),0) | C84: =IFERROR(INDEX(Stock!$A$3:$U$92,MATCH('Merdon Overview'!$A84,Stock!$A$3:$A$92,0),MATCH('Merdon Overview'!C$69,Stock!$A$3:$U$3,0)),0) | D84: =C84-B84 | F84: =IFERROR(INDEX(Stock!$A$3:$U$92,MATCH('Merdon Overview'!$A84,Stock!$A$3:$A$92,0),MATCH('Merdon Overview'!F$69,Stock!$A$3:$U$3,0)),0) | G84: =Stock!S18 | H84: =IFERROR(INDEX(Stock!$A$3:$U$92,MATCH('Merdon Overview'!$A84,Stock!$A$3:$A$92,0),MATCH('Merdon Overview'!H$69,Stock!$A$3:$U$3,0)),0)
A85: Rams | B85: =IFERROR(INDEX(Stock!$A$3:$U$92,MATCH('Merdon Overview'!$A85,Stock!$A$3:$A$92,0),MATCH('Merdon Overview'!B$69,Stock!$A$3:$U$3,0)),0) | C85: =IFERROR(INDEX(Stock!$A$3:$U$92,MATCH('Merdon Overview'!$A85,Stock!$A$3:$A$92,0),MATCH('Merdon Overview'!C$69,Stock!$A$3:$U$3,0)),0) | D85: =C85-B85 | F85: =IFERROR(INDEX(Stock!$A$3:$U$92,MATCH('Merdon Overview'!$A85,Stock!$A$3:$A$92,0),MATCH('Merdon Overview'!F$69,Stock!$A$3:$U$3,0)),0) | G85: =Stock!S19 | H85: =IFERROR(INDEX(Stock!$A$3:$U$92,MATCH('Merdon Overview'!$A85,Stock!$A$3:$A$92,0),MATCH('Merdon Overview'!H$69,Stock!$A$3:$U$3,0)),0)
A86: Ewes | B86: =IFERROR(INDEX(Stock!$A$3:$U$92,MATCH('Merdon Overview'!$A86,Stock!$A$3:$A$92,0),MATCH('Merdon Overview'!B$69,Stock!$A$3:$U$3,0)),0) | C86: =IFERROR(INDEX(Stock!$A$3:$U$92,MATCH('Merdon Overview'!$A86,Stock!$A$3:$A$92,0),MATCH('Merdon Overview'!C$69,Stock!$A$3:$U$3,0)),0) | D86: =C86-B86 | F86: =IFERROR(INDEX(Stock!$A$3:$U$92,MATCH('Merdon Overview'!$A86,Stock!$A$3:$A$92,0),MATCH('Merdon Overview'!F$69,Stock!$A$3:$U$3,0)),0) | G86: =Stock!S20 | H86: =IFERROR(INDEX(Stock!$A$3:$U$92,MATCH('Merdon Overview'!$A86,Stock!$A$3:$A$92,0),MATCH('Merdon Overview'!H$69,Stock!$A$3:$U$3,0)),0)
A87: Hoggs | B87: =IFERROR(INDEX(Stock!$A$3:$U$92,MATCH('Merdon Overview'!$A87,Stock!$A$3:$A$92,0),MATCH('Merdon Overview'!B$69,Stock!$A$3:$U$3,0)),0) | C87: =IFERROR(INDEX(Stock!$A$3:$U$92,MATCH('Merdon Overview'!$A87,Stock!$A$3:$A$92,0),MATCH('Merdon Overview'!C$69,Stock!$A$3:$U$3,0)),0) | D87: =C87-B87 | F87: =IFERROR(INDEX(Stock!$A$3:$U$92,MATCH('Merdon Overview'!$A87,Stock!$A$3:$A$92,0),MATCH('Merdon Overview'!F$69,Stock!$A$3:$U$3,0)),0) | H87: =IFERROR(INDEX(Stock!$A$3:$U$92,MATCH('Merdon Overview'!$A87,Stock!$A$3:$A$92,0),MATCH('Merdon Overview'!H$69,Stock!$A$3:$U$3,0)),0)
A88: Lambs | B88: =IFERROR(INDEX(Stock!$A$3:$U$92,MATCH('Merdon Overview'!$A88,Stock!$A$3:$A$92,0),MATCH('Merdon Overview'!B$69,Stock!$A$3:$U$3,0)),0) | C88: =IFERROR(INDEX(Stock!$A$3:$U$92,MATCH('Merdon Overview'!$A88,Stock!$A$3:$A$92,0),MATCH('Merdon Overview'!C$69,Stock!$A$3:$U$3,0)),0) | D88: =C88-B88 | F88: =IFERROR(INDEX(Stock!$A$3:$U$92,MATCH('Merdon Overview'!$A88,Stock!$A$3:$A$92,0),MATCH('Merdon Overview'!F$69,Stock!$A$3:$U$3,0)),0) | G88: =Stock!S22 | H88: =IFERROR(INDEX(Stock!$A$3:$U$92,MATCH('Merdon Overview'!$A88,Stock!$A$3:$A$92,0),MATCH('Merdon Overview'!H$69,Stock!$A$3:$U$3,0)),0)
A89: Boars | B89: =IFERROR(INDEX(Stock!$A$3:$U$92,MATCH('Merdon Overview'!$A89,Stock!$A$3:$A$92,0),MATCH('Merdon Overview'!B$69,Stock!$A$3:$U$3,0)),0) | C89: =IFERROR(INDEX(Stock!$A$3:$U$92,MATCH('Merdon Overview'!$A89,Stock!$A$3:$A$92,0),MATCH('Merdon Overview'!C$69,Stock!$A$3:$U$3,0)),0) | D89: =C89-B89 | F89: =IFERROR(INDEX(Stock!$A$3:$U$92,MATCH('Merdon Overview'!$A89,Stock!$A$3:$A$92,0),MATCH('Merdon Overview'!F$69,Stock!$A$3:$U$3,0)),0) | H89: =IFERROR(INDEX(Stock!$A$3:$U$92,MATCH('Merdon Overview'!$A89,Stock!$A$3:$A$92,0),MATCH('Merdon Overview'!H$69,Stock!$A$3:$U$3,0)),0)
A90: Sows | B90: =IFERROR(INDEX(Stock!$A$3:$U$92,MATCH('Merdon Overview'!$A90,Stock!$A$3:$A$92,0),MATCH('Merdon Overview'!B$69,Stock!$A$3:$U$3,0)),0) | C90: =IFERROR(INDEX(Stock!$A$3:$U$92,MATCH('Merdon Overview'!$A90,Stock!$A$3:$A$92,0),MATCH('Merdon Overview'!C$69,Stock!$A$3:$U$3,0)),0) | D90: =C90-B90 | F90: =IFERROR(INDEX(Stock!$A$3:$U$92,MATCH('Merdon Overview'!$A90,Stock!$A$3:$A$92,0),MATCH('Merdon Overview'!F$69,Stock!$A$3:$U$3,0)),0) | H90: =IFERROR(INDEX(Stock!$A$3:$U$92,MATCH('Merdon Overview'!$A90,Stock!$A$3:$A$92,0),MATCH('Merdon Overview'!H$69,Stock!$A$3:$U$3,0)),0)
A91: Pigs | B91: =IFERROR(INDEX(Stock!$A$3:$U$92,MATCH('Merdon Overview'!$A91,Stock!$A$3:$A$92,0),MATCH('Merdon Overview'!B$69,Stock!$A$3:$U$3,0)),0) | C91: =IFERROR(INDEX(Stock!$A$3:$U$92,MATCH('Merdon Overview'!$A91,Stock!$A$3:$A$92,0),MATCH('Merdon Overview'!C$69,Stock!$A$3:$U$3,0)),0) | D91: =C91-B91 | F91: =IFERROR(INDEX(Stock!$A$3:$U$92,MATCH('Merdon Overview'!$A91,Stock!$A$3:$A$92,0),MATCH('Merdon Overview'!F$69,Stock!$A$3:$U$3,0)),0) | G91: =Stock!S25 | H91: =IFERROR(INDEX(Stock!$A$3:$U$92,MATCH('Merdon Overview'!$A91,Stock!$A$3:$A$92,0),MATCH('Merdon Overview'!H$69,Stock!$A$3:$U$3,0)),0)
A92: Hoggets | B92: =IFERROR(INDEX(Stock!$A$3:$U$92,MATCH('Merdon Overview'!$A92,Stock!$A$3:$A$92,0),MATCH('Merdon Overview'!B$69,Stock!$A$3:$U$3,0)),0) | C92: =IFERROR(INDEX(Stock!$A$3:$U$92,MATCH('Merdon Overview'!$A92,Stock!$A$3:$A$92,0),MATCH('Merdon Overview'!C$69,Stock!$A$3:$U$3,0)),0) | D92: =C92-B92 | F92: =IFERROR(INDEX(Stock!$A$3:$U$92,MATCH('Merdon Overview'!$A92,Stock!$A$3:$A$92,0),MATCH('Merdon Overview'!F$69,Stock!$A$3:$U$3,0)),0) | H92: =IFERROR(INDEX(Stock!$A$3:$U$92,MATCH('Merdon Overview'!$A92,Stock!$A$3:$A$92,0),MATCH('Merdon Overview'!H$69,Stock!$A$3:$U$3,0)),0)
A93: Piglets | B93: =IFERROR(INDEX(Stock!$A$3:$U$92,MATCH('Merdon Overview'!$A93,Stock!$A$3:$A$92,0),MATCH('Merdon Overview'!B$69,Stock!$A$3:$U$3,0)),0) | C93: =IFERROR(INDEX(Stock!$A$3:$U$92,MATCH('Merdon Overview'!$A93,Stock!$A$3:$A$92,0),MATCH('Merdon Overview'!C$69,Stock!$A$3:$U$3,0)),0) | D93: =C93-B93 | F93: =IFERROR(INDEX(Stock!$A$3:$U$92,MATCH('Merdon Overview'!$A93,Stock!$A$3:$A$92,0),MATCH('Merdon Overview'!F$69,Stock!$A$3:$U$3,0)),0) | H93: =IFERROR(INDEX(Stock!$A$3:$U$92,MATCH('Merdon Overview'!$A93,Stock!$A$3:$A$92,0),MATCH('Merdon Overview'!H$69,Stock!$A$3:$U$3,0)),0)
A94: Swans | B94: =IFERROR(INDEX(Stock!$A$3:$U$92,MATCH('Merdon Overview'!$A94,Stock!$A$3:$A$92,0),MATCH('Merdon Overview'!B$69,Stock!$A$3:$U$3,0)),0) | C94: =IFERROR(INDEX(Stock!$A$3:$U$92,MATCH('Merdon Overview'!$A94,Stock!$A$3:$A$92,0),MATCH('Merdon Overview'!C$69,Stock!$A$3:$U$3,0)),0) | D94: =C94-B94 | F94: =IFERROR(INDEX(Stock!$A$3:$U$92,MATCH('Merdon Overview'!$A94,Stock!$A$3:$A$92,0),MATCH('Merdon Overview'!F$69,Stock!$A$3:$U$3,0)),0) | H94: =IFERROR(INDEX(Stock!$A$3:$U$92,MATCH('Merdon Overview'!$A94,Stock!$A$3:$A$92,0),MATCH('Merdon Overview'!H$69,Stock!$A$3:$U$3,0)),0)
A95: Peacocks | B95: =IFERROR(INDEX(Stock!$A$3:$U$92,MATCH('Merdon Overview'!$A95,Stock!$A$3:$A$92,0),MATCH('Merdon Overview'!B$69,Stock!$A$3:$U$3,0)),0) | C95: =IFERROR(INDEX(Stock!$A$3:$U$92,MATCH('Merdon Overview'!$A95,Stock!$A$3:$A$92,0),MATCH('Merdon Overview'!C$69,Stock!$A$3:$U$3,0)),0) | D95: =C95-B95 | F95: =IFERROR(INDEX(Stock!$A$3:$U$92,MATCH('Merdon Overview'!$A95,Stock!$A$3:$A$92,0),MATCH('Merdon Overview'!F$69,Stock!$A$3:$U$3,0)),0) | H95: =IFERROR(INDEX(Stock!$A$3:$U$92,MATCH('Merdon Overview'!$A95,Stock!$A$3:$A$92,0),MATCH('Merdon Overview'!H$69,Stock!$A$3:$U$3,0)),0)
A96: Total value of stock (sum of the above) | G96: =SUM(G70:G95)
A97: Total value of stockbuilding | G97: =SUM(H70:H95)
A98: Value of sales | G98: =SUM(F70:F95)
A100: Wool | B100: Inherited stock | C100: End-period stock | D100: Stockbuilding | F100: Sales in (£) | G100: Value of stock (£) at sales prices | H100: Value of production (£) at sales prices
A101: Fleeces | B101: =IFERROR(INDEX(Stock!$A$3:$U$92,MATCH('Merdon Overview'!$A101,Stock!$A$3:$A$92,0),MATCH('Merdon Overview'!B$69,Stock!$A$3:$U$3,0)),0) | C101: =IFERROR(INDEX(Stock!$A$3:$U$92,MATCH('Merdon Overview'!$A101,Stock!$A$3:$A$92,0),MATCH('Merdon Overview'!C$69,Stock!$A$3:$U$3,0)),0) | D101: =C101-B101 | F101: =IFERROR(INDEX(Stock!$A$3:$U$92,MATCH('Merdon Overview'!$A101,Stock!$A$3:$A$92,0),MATCH('Merdon Overview'!F$69,Stock!$A$3:$U$3,0)),0) | G101: =Stock!S34 | H101: =IFERROR(INDEX(Stock!$A$3:$U$92,MATCH('Merdon Overview'!$A101,Stock!$A$3:$A$92,0),MATCH('Merdon Overview'!H$69,Stock!$A$3:$U$3,0)),0)
A102: Coarse wool | B102: =IFERROR(INDEX(Stock!$A$3:$U$92,MATCH('Merdon Overview'!$A102,Stock!$A$3:$A$92,0),MATCH('Merdon Overview'!B$69,Stock!$A$3:$U$3,0)),0) | C102: =IFERROR(INDEX(Stock!$A$3:$U$92,MATCH('Merdon Overview'!$A102,Stock!$A$3:$A$92,0),MATCH('Merdon Overview'!C$69,Stock!$A$3:$U$3,0)),0) | D102: =C102-B102 | F102: =IFERROR(INDEX(Stock!$A$3:$U$92,MATCH('Merdon Overview'!$A102,Stock!$A$3:$A$92,0),MATCH('Merdon Overview'!F$69,Stock!$A$3:$U$3,0)),0) | G102: =Stock!S35 | H102: =IFERROR(INDEX(Stock!$A$3:$U$92,MATCH('Merdon Overview'!$A102,Stock!$A$3:$A$92,0),MATCH('Merdon Overview'!H$69,Stock!$A$3:$U$3,0)),0)
A103: Lamb's wool | B103: =IFERROR(INDEX(Stock!$A$3:$U$92,MATCH('Merdon Overview'!$A103,Stock!$A$3:$A$92,0),MATCH('Merdon Overview'!B$69,Stock!$A$3:$U$3,0)),0) | C103: =IFERROR(INDEX(Stock!$A$3:$U$92,MATCH('Merdon Overview'!$A103,Stock!$A$3:$A$92,0),MATCH('Merdon Overview'!C$69,Stock!$A$3:$U$3,0)),0) | D103: =C103-B103 | F103: =IFERROR(INDEX(Stock!$A$3:$U$92,MATCH('Merdon Overview'!$A103,Stock!$A$3:$A$92,0),MATCH('Merdon Overview'!F$69,Stock!$A$3:$U$3,0)),0) | G103: =Stock!S36 | H103: =IFERROR(INDEX(Stock!$A$3:$U$92,MATCH('Merdon Overview'!$A103,Stock!$A$3:$A$92,0),MATCH('Merdon Overview'!H$69,Stock!$A$3:$U$3,0)),0)
A104: Wool locks | B104: =IFERROR(INDEX(Stock!$A$3:$U$92,MATCH('Merdon Overview'!$A104,Stock!$A$3:$A$92,0),MATCH('Merdon Overview'!B$69,Stock!$A$3:$U$3,0)),0) | C104: =IFERROR(INDEX(Stock!$A$3:$U$92,MATCH('Merdon Overview'!$A104,Stock!$A$3:$A$92,0),MATCH('Merdon Overview'!C$69,Stock!$A$3:$U$3,0)),0) | D104: =C104-B104 | F104: =IFERROR(INDEX(Stock!$A$3:$U$92,MATCH('Merdon Overview'!$A104,Stock!$A$3:$A$92,0),MATCH('Merdon Overview'!F$69,Stock!$A$3:$U$3,0)),0) | G104: =Stock!S37 | H104: =IFERROR(INDEX(Stock!$A$3:$U$92,MATCH('Merdon Overview'!$A104,Stock!$A$3:$A$92,0),MATCH('Merdon Overview'!H$69,Stock!$A$3:$U$3,0)),0)
A105: Wool sold at shearing | B105: =IFERROR(INDEX(Stock!$A$3:$U$92,MATCH('Merdon Overview'!$A105,Stock!$A$3:$A$92,0),MATCH('Merdon Overview'!B$69,Stock!$A$3:$U$3,0)),0) | C105: =IFERROR(INDEX(Stock!$A$3:$U$92,MATCH('Merdon Overview'!$A105,Stock!$A$3:$A$92,0),MATCH('Merdon Overview'!C$69,Stock!$A$3:$U$3,0)),0) | D105: =C105-B105 | F105: =IFERROR(INDEX(Stock!$A$3:$U$92,MATCH('Merdon Overview'!$A105,Stock!$A$3:$A$92,0),MATCH('Merdon Overview'!F$69,Stock!$A$3:$U$3,0)),0) | G105: =Stock!S38 | H105: =IFERROR(INDEX(Stock!$A$3:$U$92,MATCH('Merdon Overview'!$A105,Stock!$A$3:$A$92,0),MATCH('Merdon Overview'!H$69,Stock!$A$3:$U$3,0)),0)
A106: Total value of stock (sum of the above) | G106: =SUM(G101:G105)
A107: Total value of production | G107: =SUM(H101:H105)
A108: Value of sales | G108: =SUM(F101:F105)
A110: Hides | B110: Inherited stock | C110: End-period stock | D110: Stockbuilding | F110: Sales in (£) | G110: Value of stock (£) at sales prices | H110: Value of production (£) at sales prices
A111: Ox hides | B111: =IFERROR(INDEX(Stock!$A$3:$U$92,MATCH('Merdon Overview'!$A111,Stock!$A$3:$A$92,0),MATCH('Merdon Overview'!B$69,Stock!$A$3:$U$3,0)),0) | C111: =IFERROR(INDEX(Stock!$A$3:$U$92,MATCH('Merdon Overview'!$A111,Stock!$A$3:$A$92,0),MATCH('Merdon Overview'!C$69,Stock!$A$3:$U$3,0)),0) | D111: =C111-B111 | F111: =IFERROR(INDEX(Stock!$A$3:$U$92,MATCH('Merdon Overview'!$A111,Stock!$A$3:$A$92,0),MATCH('Merdon Overview'!F$69,Stock!$A$3:$U$3,0)),0) | G111: =Stock!S42 | H111: =IFERROR(INDEX(Stock!$A$3:$U$92,MATCH('Merdon Overview'!$A111,Stock!$A$3:$A$92,0),MATCH('Merdon Overview'!H$69,Stock!$A$3:$U$3,0)),0)
...

Sheet Merdon Receipts
A1: MERDON RECEIPTS
B2: £ | C2: s | D2: d | F2: Total in £ | G2: Error | H2: Notes
A4: Arrears
A5: Arrears total | B5: 40 | C5: 7 | D5: 4.5 | F5: =B5+C5/20+D5/240
A6: of which delivered to treasurer of Wolvesey | B6: 40 | C6: 7 | D6: 4.5 | F6: =B6+C6/20+D6/240
A8: Rents of assize
A9: at Easter | B9: 18 | C9: 18 | D9: 1.75 | F9: =B9+C9/20+D9/240
A10: at Michaelmas | B10: 19 | C10: 19 | D10: 4.5 | F10: =B10+C10/20+D10/240
A11: Total recorded in accounts | B11: 38 | C11: 17 | D11: 6.25 | F11: =B11+C11/20+D11/240
A12: Rents of assize total | B12: =SUM(B9:B10) | C12: =SUM(C9:C10) | D12: =SUM(D9:D10) | F12: =B12+C12/20+D12/240 | G12: =F12-F11
A14: Quittances
A15: 1 reeve and 1 beadle | C15: 5 | F15: =B15+C15/20+D15/240
A16: 1 hayward | C16: 1 | D16: 3 | F16: =B16+C16/20+D16/240
A17: 1 swineherd | C17: 2 | D17: 6 | F17: =B17+C17/20+D17/240
A18: 10 ploughmen | C18: 12 | D18: 6 | F18: =B18+C18/20+D18/240
A19: 12 workers for the year | C19: 15 | F19: =B19+C19/20+D19/240
A20: 1 keeper of wethers | C20: 1 | D20: 3 | F20: =B20+C20/20+D20/240
A21: Total recorded in accounts | B21: 1 | C21: 17 | D21: 6 | F21: =B21+C21/20+D21/240
A22: Quittances total | B22: =SUM(B15:B20) | C22: =SUM(C15:C20) | D22: =SUM(D15:D20) | F22: =B22+C22/20+D22/240 | G22: =F22-F21
A24: Defaults of rent
A25: of William de Cruce | C25: 5 | F25: =B25+C25/20+D25/240
A26: 1 plot in the vill of Hursley which William Faber formerly encroached and buit upon pulled down because it was a nuisance | D26: 6 | F26: =B26+C26/20+D26/240
A27: Total recorded in accounts | C27: 5 | D27: 6 | F27: =B27+C27/20+D27/240
A28: Defaults of rent total | B28: =SUM(B25:B26) | C28: =SUM(C25:C26) | D28: =SUM(D25:D26) | F28: =B28+C28/20+D28/240 | G28: =F28-F27
A30: Total of rents remaining | B30: 36 | C30: 14 | D30: 6.25 | F30: =B30+C30/20+D30/240
A32: Annual recognizances
A33: from Adam | D33: 6 | F33: =B33+C33/20+D33/240
A34: from William | D34: 6 | F34: =B34+C34/20+D34/240
A35: from Walter | D35: 6 | F35: =B35+C35/20+D35/240
A36: from Ralph | D36: 3 | F36: =B36+C36/20+D36/240
A37: from Nicholas | D37: 3 | F37: =B37+C37/20+D37/240
A38: from John | D38: 3 | F38: =B38+C38/20+D38/240
A39: Total recorded in accounts | C39: 2 | D39: 3 | F39: =B39+C39/20+D39/240
A40: Annual recognizances total | B40: =SUM(B33:B38) | C40: =SUM(C33:C38) | D40: =SUM(D33:D38) | F40: =B40+C40/20+D40/240 | G40: =F40-F39
A42: Issues of the manor
A43: from panage of pigs at Martinmas | B43: 3 | C43: 2 | F43: =B43+C43/20+D43/240
A44: from the whole hudnred of Merdon to have heath and lords will | C44: 7 | F44: =B44+C44/20+D44/240
A45: from the pasturage next to Bouyat' sold for 36 yearlings | C45: 10 | D45: 6 | F45: =B45+C45/20+D45/240
A46: from honey found in the wood and sold | B46: 1 | C46: 6 | F46: =B46+C46/20+D46/240
A47: from the pasturage sold of 6 horses and mares, 11 oxen and cows, and 16 bullocks | C47: 14 | D47: 10 | F47: =B47+C47/20+D47/240
A48: from Adam le Bul' so that he may have dung from two cesspits beside the road | D48: 6 | F48: =B48+C48/20+D48/240
A49: for release of 26 labour services not done in winter this year | C49: 3 | D49: 3.5 | F49: =B49+C49/20+D49/240
A50: for release of labour service not done at harvest time | B50: 1 | C50: 1 | F50: =B50+C50/20+D50/240
A51: from 2 feeble plough-horses sold | C51: 8 | F51: =B51+C51/20+D51/240
A52: from 12 oxen sold | B52: 5 | C52: 8 | D52: 10 | F52: =B52+C52/20+D52/240
A53: from 5 old cows sold before calving | B53: 2 | C53: 5 | F53: =B53+C53/20+D53/240
A54: from 5 feeble suckling calves sold | C54: 5 | F54: =B54+C54/20+D54/240
A55: from 21 wethers and 1 ram sold before shearing | B55: 1 | C55: 7 | D55: 6 | F55: =B55+C55/20+D55/240
A56: from 2 rams and 24 ewes sold at the same feast | B56: 1 | C56: 6 | F56: =B56+C56/20+D56/240
A57: from 34 lambs sold after shearing to the reeve of Twyford | C57: 17 | F57: =B57+C57/20+D57/240
A58: from 29 pigs sold | B58: 4 | C58: 8 | D58: 6 | F58: =B58+C58/20+D58/240
A59: from 2 cloves 4 lb of wool locks sold | C59: 3 | F59: =B59+C59/20+D59/240
A60: from 6 cloves of winter cheese sold | C60: 1 | D60: 7 | F60: =B60+C60/20+D60/240
A61: from 8 weys 7 cloves of summer cheese sold | B61: 3 | C61: 8 | D61: 9 | F61: =B61+C61/20+D61/240
A62: from 1 ox from the heriot of John Byssop | C62: 9 | F62: =B62+C62/20+D62/240
A63: from 1.5 cows from the heriot of Geoffrey le Glut | C63: 4 | F63: =B63+C63/20+D63/240
A64: from 15 cloves 1 lb of butter sold | C64: 4 | D64: 5 | F64: =B64+C64/20+D64/240
A65: from the hides sold of 3 oxen in murrain | C65: 6 | D65: 4 | F65: =B65+C65/20+D65/240
A66: from the hides of 2 calves sold | D66: 2 | F66: =B66+C66/20+D66/240
A67: from the skins sold of 7 wethers, 7 ewes and 3 hoggs in murrain before shearing | C67: 5 | D67: 2 | F67: =B67+C67/20+D67/240
A68: from the skins sold of 4 wethers and 1 ewe in murraina fter shearing | D68: 6 | F68: =B68+C68/20+D68/240
A69: from the skins sold of 4 lambs before weaning | C69: 1 | D69: 2 | F69: =B69+C69/20+D69/240
A70: from the skins sold of 4 lambs in murraina fter shearing | D70: 2 | F70: =B70+C70/20+D70/240
A71: from 48 hens from churchscot sold | C71: 4 | F71: =B71+C71/20+D71/240
A72: from 400 eggs sold according to custom | C72: 1 | F72: =B72+C72/20+D72/240
A73: from heath and broom sold in the foreign wood this year | C73: 5 | D73: 6 | F73: =B73+C73/20+D73/240
A74: from the sale of 27 oxen bought the previous year to agist in the park | B74: 10 | C74: 14 | D74: 10 | F74: =B74+C74/20+D74/240
A75: from dairy produce sold at the audit | C75: 6 | D75: 5 | F75: =B75+C75/20+D75/240
A76: Total recorded in accounts | B76: 39 | D76: 7.5 | F76: =B76+C76/20+D76/240
A77: Issues of the manor total | B77: =SUM(B43:B75) | C77: =SUM(C43:C75) | D77: =SUM(D43:D75) | F77: =B77+C77/20+D77/240 | G77: =F77-F76
A79: Sale of corn
A80: from 308 qrs 3 bus of wheat sold | B80: 91 | C80: 1 | D80: 1 | F80: =B80+C80/20+D80/240
A81: from 16 qrs 5 bus of curall sold | B81: 3 | C81: 6 | D81: 6 | F81: =B81+C81/20+D81/240
A82: from 8 qrs 5 bus of barley sold | B82: 1 | C82: 8 | D82: 9 | F82: =B82+C82/20+D82/240
A83: from 42 qrs of oats sold | B83: 4 | C83: 12 | D83: 5 | F83: =B83+C83/20+D83/240
A84: from 4 bus of beans sold | C84: 1 | D84: 4 | F84: =B84+C84/20+D84/240
A85: from 12 qrs 2 bus of peas sold | B85: 1 | C85: 12 | D85: 8 | F85: =B85+C85/20+D85/240
A86: from 16 qrs 7 bus of vetches sold | B86: 1 | C86: 13 | D86: 9 | F86: =B86+C86/20+D86/240
A87: from 1 qr 2 bus of barley sold at the audit | C87: 4 | D87: 2 | F87: =B87+C87/20+D87/240
A88: Total recorded in accounts | B88: 104 | D88: 8 | F88: =B88+C88/20+D88/240
A89: Sale of corn total | B89: =SUM(B80:B87) | C89: =SUM(C80:C87) | D89: =SUM(D80:D87) | F89: =B89+C89/20+D89/240 | G89: =F89-F88
A91: Entry and marriage fines
A92: from tithing of Merdon at Martinmas | C92: 13 | D92: 4 | F92: =B92+C92/20+D92/240
A93: from tithing of West Pitt for same | C93: 1 | F93: =B93+C93/20+D93/240
A94: from tithing of Merdon at the hundred-court of Hockday | C94: 13 | D94: 4 | F94: =B94+C94/20+D94/240
A95: from the tithing of West Pitt for the same | C95: 1 | F95: =B95+C95/20+D95/240
A96: from Alice to retain 0.5 virgates of land from husband | C96: 13 | D96: 4 | F96: =B96+C96/20+D96/240
A97: from Edith to retain 1 ferling from husband | C97: 13 | D97: 4 | F97: =B97+C97/20+D97/240
A98: from Alice to retain 1 ferling of land and other purprestures which belonged to her husband | C98: 13 | D98: 4 | F98: =B98+C98/20+D98/240
A99: from Beatrice to retain 1 cottage from husband | C99: 1 | F99: =B99+C99/20+D99/240
A100: from Juliana for marrying her daughter outside | C100: 4 | F100: =B100+C100/20+D100/240
A101: from John to have Alice and 1 ferling of her land | C101: 13 | D101: 4 | F101: =B101+C101/20+D101/240
A102: from Robert to have 1 ferling of land from father of his wife | C102: 6 | D102: 8 | F102: =B102+C102/20+D102/240
A103: from Joan for mayying her daughter outside | C103: 4 | F103: =B103+C103/20+D103/240
A104: from Martin for marrying his daughter | C104: 3 | F104: =B104+C104/20+D104/240
A105: from Isabel to have 1 messuage and 1 ferling of land from mother | C105: 13 | D105: 4 | F105: =B105+C105/20+D105/240
A106: from Joan for marrying her daughter outside | C106: 4 | F106: =B106+C106/20+D106/240
A107: from William to have 1 house with a curtilage | C107: 1 | F107: =B107+C107/20+D107/240
A108: from Walter to have 1 garden by surrender of John | C108: 2 | F108: =B108+C108/20+D108/240
A109: from walter to have Emma with a house of hers | C109: 3 | F109: =B109+C109/20+D109/240
...

Sheet Merdon Expenses
A1: MERDON EXPENSES
B2: £ | C2: s | D2: d | F2: Total in £ | G2: Error | H2: Notes
A3: Cost of Ploughs
A4: iron and steel for 6 ploughs | B4: 1 | C4: 1 | D4: 7 | F4: =B4+C4/20+D4/240
A5: in 3 ploughshares bought | C5: 2 | F5: =B5+C5/20+D5/240
A6: in 1 coulter mended with iron | D6: 3 | F6: =B6+C6/20+D6/240
A7: in 10 plough feet | C7: 3 | D7: 4 | F7: =B7+C7/20+D7/240
A8: in fitting ploughs with iron tyres | D8: 6 | F8: =B8+C8/20+D8/240
A9: in 4 pairs of wheels | C9: 1 | D9: 4 | F9: =B9+C9/20+D9/240
A10: in 3 new harrows made | D10: 6 | F10: =B10+C10/20+D10/240
A11: in shoeing 12 plough-horses for the year | C11: 6 | F11: =B11+C11/20+D11/240
A12: in 8 halters made | D12: 2 | F12: =B12+C12/20+D12/240
A13: in boon-works of 50 ploughmen | C13: 16 | D13: 8 | F13: =B13+C13/20+D13/240
A14: in boonworks of 9 ploughmen of slackstead | C14: 1 | D14: 1.5 | F14: =B14+C14/20+D14/240
A15: in boon-works of 2 free men ploughing 2 acres of land | D15: 3 | F15: =B15+C15/20+D15/240
A16: in stipend of 10 ploughmen for 221 Saturday ploughings | B16: 2 | C16: 2 | D16: 11.5 | F16: =B16+C16/20+D16/240
A17: in stipend of the smith making the ironwork | C17: 4 | D17: 4.75 | F17: =B17+C17/20+D17/240
A18: in stipend of 2 ploughmen for the year | C18: 6 | F18: =B18+C18/20+D18/240
A19: in 2 plough-horses bought | C19: 15 | F19: =B19+C19/20+D19/240
A20: in 5 oxen bought | B20: 2 | C20: 10 | D20: 1.25 | F20: =B20+C20/20+D20/240
A21: in forage bought from the parson of Hursley | B21: 1 | F21: =B21+C21/20+D21/240
A22: Total recorded in accounts | B22: 9 | C22: 12 | D22: 11 | F22: =B22+C22/20+D22/240
A23: Cost of ploughs total | B23: =SUM(B4:B21) | C23: =SUM(C4:C21) | D23: =SUM(D4:D21) | F23: =B23+C23/20+D23/240 | G23: =F23-F22
A24: Total capital expenses | B24: =SUM(B4:B12) | C24: =SUM(C4:C12) | D24: =SUM(D4:D12) | F24: =B24+C24/20+D24/240
A26: Purchase of Corn
A27: in 29 qrs 1 bus of wheat bought for sowing | B27: 8 | C27: 6 | D27: 10.25
A28: in 11 qrs of barley bought for sowing | B28: 2 | C28: 4
A29: in 15 qrs of oats bought for sowing | B29: 1 | C29: 10 | F29: =B29+C29/20+D29/240
A30: Total recorded in accounts | B30: 12 | D30: 10.25 | F30: =B30+C30/20+D30/240
A31: Purchase of corn total | B31: =SUM(B27:B29) | C31: =SUM(C27:C29) | D31: =SUM(D27:D29) | F31: =B31+C31/20+D31/240 | G31: =F31-F30
A33: Cost of Carts and Wagons
A34: in a pair of wheels bought | C34: 3 | D34: 1 | F34: =B34+C34/20+D34/240
A35: in 1 new binding bought and fitted | C35: 9 | D35: 11 | F35: =B35+C35/20+D35/240
A36: in fitting the cart with axles | D36: 10 | F36: =B36+C36/20+D36/240
A37: in clouts and nails and grease | C37: 2 | D37: 6 | F37: =B37+C37/20+D37/240
A38: in collar bought and and 1 pair of saddle pads | C38: 1 | D38: 2 | F38: =B38+C38/20+D38/240
A39: in 1 saddle bought | D39: 4 | F39: =B39+C39/20+D39/240
A40: in 1 cart rope | C40: 1 | D40: 4 | F40: =B40+C40/20+D40/240
A41: in 1 pair of traces | D41: 7 | F41: =B41+C41/20+D41/240
A42: in 1 pair of wheels for clearing dung | C42: 2 | F42: =B42+C42/20+D42/240
A43: in 4 wooden hoops | D43: 3 | F43: =B43+C43/20+D43/240
A44: in 1 cart-body made anew | D44: 6 | F44: =B44+C44/20+D44/240
A45: in mending harnesses | D45: 4 | F45: =B45+C45/20+D45/240
A46: in white leather | D46: 6 | F46: =B46+C46/20+D46/240
A47: in 8 ells of canvas bought for 6 sacks | C47: 2 | F47: =B47+C47/20+D47/240
A48: in shoeing 4 cart horses | C48: 5 | D48: 10 | F48: =B48+C48/20+D48/240
A49: in stipend of 2 carters for the year | C49: 6 | F49: =B49+C49/20+D49/240
A50: Total recorded in accounts | B50: 1 | C50: 16 | D50: 11 | F50: =B50+C50/20+D50/240
A51: Cost of carts and wagons total | B51: =SUM(B34:B49) | C51: =SUM(C34:C49) | D51: =SUM(D34:D49) | F51: =B51+C51/20+D51/240 | G51: =F51-F50
A52: Total capital expenses | B52: =SUM(B34:B48) | C52: =SUM(C34:C48) | D52: =SUM(D34:D48) | F52: =B52+C52/20+D52/240
A54: Cost of Dairy
A55: in woollen and linen cloth | D55: 8 | F55: =B55+C55/20+D55/240
A56: in a press bought | D56: 4.5 | F56: =B56+C56/20+D56/240
A57: in earthenware pots and pans | D57: 5 | F57: =B57+C57/20+D57/240
A58: in mending the utensils of the dairy | D58: 6 | F58: =B58+C58/20+D58/240
A59: in plastering and mending the walls of the dairy | D59: 2 | F59: =B59+C59/20+D59/240
A60: in 4 bus of salt bought | C60: 1 | D60: 2.5 | F60: =B60+C60/20+D60/240
A61: in grease, vinegar and copperas bought for greasing sheep | C61: 15 | D61: 5.5 | F61: =B61+C61/20+D61/240
A62: in 32 hurdles bought for the fold | C62: 3 | D62: 4.5 | F62: =B62+C62/20+D62/240
A63: in roofing the sheepcote with stubble | C63: 6 | D63: 2.5 | F63: =B63+C63/20+D63/240
A64: in repairing and restoring in the places the door and walls of sheepcote | D64: 7 | F64: =B64+C64/20+D64/240
A65: in 1 lath work made anew | D65: 7 | F65: =B65+C65/20+D65/240
A66: in 3 buckets bought | C66: 1 | F66: =B66+C66/20+D66/240
A67: in 1 mould bought | D67: 10 | F67: =B67+C67/20+D67/240
A68: in 12 ells of canvas bought for packing wool | C68: 3 | D68: 2 | F68: =B68+C68/20+D68/240 | H68: Not dairy related?
A69: in packing the said wool with thread | D69: 6.5 | F69: =B69+C69/20+D69/240
A70: in 1 brass pan bought | C70: 5 | F70: =B70+C70/20+D70/240
A71: in hooping the same with iron | C71: 1 | F71: =B71+C71/20+D71/240
A72: in stipend of 1 dairymaid | C72: 2 | F72: =B72+C72/20+D72/240
A73: in stipend of 1 cowherd for the year | C73: 2 | F73: =B73+C73/20+D73/240
A74: in stipend of 1 keeper of ewes | C74: 3 | F74: =B74+C74/20+D74/240
A75: in stipend of 1 keeper of hoggs and lambs | C75: 3 | F75: =B75+C75/20+D75/240
A76: in 27 yearlings bought | B76: 7 | C76: 4 | D76: 4.5 | F76: =B76+C76/20+D76/240
A77: in 3 cows bought | B77: 1 | C77: 4 | F77: =B77+C77/20+D77/240
A78: Total recorded in accounts | B78: 10 | C78: 19 | D78: 5.5 | F78: =B78+C78/20+D78/240
A79: Cost of dairy total | B79: =SUM(B55:B77) | C79: =SUM(C55:C77) | D79: =SUM(D55:D77) | F79: =B79+C79/20+D79/240 | G79: =F79-F78
A80: Total capital expenses | B80: =SUM(B55:B71) | C80: =SUM(C55:C71) | D80: =SUM(D55:D71) | F80: =B80+C80/20+D80/240
A82: Cost of Buildings
A83: in re-roofing | C83: 11 | D83: 8 | F83: =B83+C83/20+D83/240
A84: in mending the crib of the stable | C84: 1 | D84: 1 | F84: =B84+C84/20+D84/240
A85: in mending 1 axe | D85: 3 | F85: =B85+C85/20+D85/240
A86: in digging 1 perch | D86: 2 | F86: =B86+C86/20+D86/240
A87: in iron bought for forks and shovels | D87: 7 | F87: =B87+C87/20+D87/240
A88: in mending the palisade between the hall and chamber | D88: 4 | F88: =B88+C88/20+D88/240
A89: in 1 basket for corn bought | D89: 4 | F89: =B89+C89/20+D89/240
A90: in covering and mending walls in haybarn | D90: 4 | F90: =B90+C90/20+D90/240
A91: in enclosing the great field with hedges | D91: 11 | F91: =B91+C91/20+D91/240
A92: in castrating piglets | D92: 4 | F92: =B92+C92/20+D92/240
A93: in 82 qrs 5 bus of oats cast cleaned and winnowed for sowing | C93: 2 | D93: 8 | F93: =B93+C93/20+D93/240
A94: Total recorded in accounts | C94: 18 | D94: 8 | F94: =B94+C94/20+D94/240
A95: Cost of buildings total | B95: =SUM(B83:B93) | C95: =SUM(C83:C93) | D95: =SUM(D83:D93) | F95: =B95+C95/20+D95/240 | G95: =F95-F94
A96: Total capital expenses | B96: =SUM(B83:B91) | C96: =SUM(C83:C91) | D96: =SUM(D83:D91) | F96: =B96+C96/20+D96/240
A98: Threshing
A99: in threshing 20 qrs wheat | C99: 3 | D99: 8 | F99: =B99+C99/20+D99/240
A100: in wages of William carrying out the issue of the grange | C100: 11 | D100: 1.5 | F100: =B100+C100/20+D100/240
A101: in stipend of the same | C101: 2 | F101: =B101+C101/20+D101/240
A102: Total recorded in accounts | C102: 16 | D102: 9.5 | F102: =B102+C102/20+D102/240
A103: Threshing total | B103: =SUM(B99:B101) | C103: =SUM(C99:C101) | D103: =SUM(D99:D101) | F103: =B103+C103/20+D103/240 | G103: =F103-F102
A105: Weeding
A106: in weeding corn above labour service | C106: 10 | F106: =B106+C106/20+D106/240
...

Sheet Issues of the Grange
B1: The issue of the grange account gives the total "yield" at the top of each heading in curly brackets, measurements used: fold, qrs, bus
B2: In "Issues of the grange" (p.xx) | G2: In "Sale of Corn" (p.x) | P2: Value of Total Production
A3: Gross output | B3: Quantity | D3: Additional bought-in | F3: Quantity | G3: Quantity noted as sold | J3: Difference Produced vs. Sold | K3: Price 1 | L3: Quantity 1 | M3: Price 2 | N3: Quantity 2 | O3: Unit price | P3: Value
B4: qrs | C4: bus | D4: qrs | E4: bus | F4: qrs | G4: qrs | H4: bus | I4: qrs | K4: £ | L4: qrs | M4: £ | N4: qrs | O4: £ per qr | P4: £
A5: Wheat | B5: 338.5 | D5: 29 | E5: 1 | F5: =B5+D5+C5/8+E5/8 | G5: 308 | H5: 3 | I5: =G5+H5/8 | J5: =F5-I5 | K5: ='Merdon Receipts'!F80 | L5: =I5 | O5: =IFERROR((K5+M5)/(L5+N5),0) | P5: =O5*F5
A6: Curall | B6: 19 | C6: 2 | F6: =B6+D6+C6/8+E6/8 | G6: 16 | H6: 5 | I6: =G6+H6/8 | J6: =F6-I6 | K6: ='Merdon Receipts'!F81 | L6: =I6 | O6: =IFERROR((K6+M6)/(L6+N6),0) | P6: =O6*F6
A7: Barley | B7: 61 | D7: 19 | E7: 1 | F7: =B7+D7+C7/8+E7/8 | G7: 9 | H7: 7 | I7: =G7+H7/8 | J7: =F7-I7 | K7: ='Merdon Receipts'!F82 | L7: =8+5/8 | M7: ='Merdon Receipts'!F87 | N7: =1+2/8 | O7: =IFERROR((K7+M7)/(L7+N7),0) | P7: =O7*F7
A8: Oats | B8: 290 | D8: 15 | F8: =B8+D8+C8/8+E8/8 | G8: 42 | I8: =G8+H8/8 | J8: =F8-I8 | K8: ='Merdon Receipts'!F83 | L8: =I8 | O8: =IFERROR((K8+M8)/(L8+N8),0) | P8: =O8*F8
A9: Beans | C9: 6 | F9: =B9+D9+C9/8+E9/8 | H9: 4 | I9: =G9+H9/8 | J9: =F9-I9 | K9: ='Merdon Receipts'!F84 | L9: =I9 | O9: =IFERROR((K9+M9)/(L9+N9),0) | P9: =O9*F9
A10: Peas | B10: 16 | C10: 5 | F10: =B10+D10+C10/8+E10/8 | G10: 12 | H10: 2 | I10: =G10+H10/8 | J10: =F10-I10 | K10: ='Merdon Receipts'!F85 | L10: =I10 | O10: =IFERROR((K10+M10)/(L10+N10),0) | P10: =O10*F10
A11: Vetches | B11: 22 | C11: 2 | F11: =B11+D11+C11/8+E11/8 | G11: 16 | H11: 7 | I11: =G11+H11/8 | J11: =F11-I11 | K11: ='Merdon Receipts'!F86 | L11: =I11 | O11: =IFERROR((K11+M11)/(L11+N11),0) | P11: =O11*F11
A13: Total Production | F13: =SUM(F5:F11) | P13: =SUM(P5:P11) | Q13: Production value is significantly more, as much less was sold than what was produced
A14: Sales of corn (as recorded in accounts) | F14: =SUM(I5:I11) | P14: =SUM(K5:K11,M5:M11)
A17: Net output | B17: Gross output | C17: Seed | F17: tithe | G17: to manorial servants & livestock | J17: Output net of tithe & seed & liveries to manorial servants | K17: in stock from last year | L17: Price | M17: Value of net output | N17: Value of sales (in "Sale of Corn")
B18: qrs | C18: qrs | D18: bus | E18: qrs | F18: qrs | G18: qrs | H18: bus | I18: qrs | J18: qrs | K18: qrs | L18: £ per qr | M18: £ | N18: £
A19: Net wheat | B19: =F5 | C19: 54.5 | E19: =C19+D19/8 | G19: 4 | H19: 6 | I19: =G19+H19/8 | J19: =B19-(E19+F19+I19) | L19: =O5 | M19: =L19*J19 | N19: =O5*I5
A20: Net curall | B20: =F6 | E20: =C20+D20/8 | G20: 2 | H20: 5 | I20: =G20+H20/8 | J20: =B20-(E20+F20+I20) | L20: =O6 | M20: =L20*J20 | N20: =O6*I6
A21: Net barley | B21: =F7 | C21: 18 | D21: 5 | E21: =C21+D21/8 | G21: =31.5+5+3+0.5+7 | H21: =1+2+6+2+6 | I21: =G21+H21/8 | J21: =B21-(E21+F21+I21) | L21: =O7 | M21: =L21*J21 | N21: =O7*I7 | P21: Think about how to get avoid getting negative value of output by accounting for bought in here
A22: Net oats | B22: =F8 | C22: 97 | D22: 5 | E22: =C22+D22/8 | G22: =28+9+26+2 | H22: =1+2 | I22: =G22+H22/8 | J22: =B22-(E22+F22+I22) | L22: =O8 | M22: =L22*J22 | N22: =O8*I8
A23: Net peas | B23: =F9 | E23: =C23+D23/8 | I23: =G23+H23/8 | J23: =B23-(E23+F23+I23) | L23: =O10 | M23: =L23*J23 | N23: =O10*I10
A24: Net vetches | B24: =F10 | E24: =C24+D24/8 | I24: =G24+H24/8 | J24: =B24-(E24+F24+I24) | L24: =O11 | M24: =L24*J24 | N24: =O11*I11
A25: Total | B25: =SUM(B19:B24) | E25: =SUM(E19:E24) | J25: =SUM(J19:J24) | M25: =SUM(M19:M24) | N25: =SUM(N19:N24)

Sheet Stock
A1: EAST KNOYLE STOCK ACCOUNT
A3: Livestock | B3: Inherited stock | C3: Bought | D3: Produced | E3: strays | F3: herbage | G3: sold | H3: in murrain | I3: accounted for elsewhere | J3: End-period stock | K3: cross-check | L3: price 1 | M3: units 1 | N3: price 2 | O3: units 2 | P3: Weight (weys) | Q3: Unit price (£) | R3: Value of production (£) at sales prices | S3: Value of stock at sales prices | T3: Sales in (£) | U3: Details
A4: Cart-horses | B4: 4 | J4: 4 | K4: =B4+C4+D4+E4-F4-G4-H4-I4 | Q4: =IFERROR((L4+N4)/(M4+O4),"") | R4: =IFERROR(D4*Q4,"") | T4: =IFERROR(Q4*G4,"")
A5: Mares | K5: =B5+C5+D5+E5-F5-G5-H5-I5 | Q5: =IFERROR((L5+N5)/(M5+O5),"") | R5: =IFERROR(D5*Q5,"") | T5: =IFERROR(Q5*G5,"")
A6: Plough horses | B6: 11 | C6: 2 | D6: 1 | G6: 2 | J6: 12 | K6: =B6+C6+D6+E6-F6-G6-H6-I6 | L6: ='Merdon Receipts'!F51 | M6: 2 | Q6: =IFERROR((L6+N6)/(M6+O6),"") | R6: =IFERROR(D6*Q6,"") | S6: =Q6*K6 | T6: =IFERROR(Q6*G6,"")
A7: Colts (2 years) | K7: =B7+C7+D7+E7-F7-G7-H7-I7 | Q7: =IFERROR((L7+N7)/(M7+O7),"") | R7: =IFERROR(D7*Q7,"") | T7: =IFERROR(Q7*G7,"")
A8: Colts (2 years) | K8: =B8+C8+D8+E8-F8-G8-H8-I8 | Q8: =IFERROR((L8+N8)/(M8+O8),"") | R8: =IFERROR(D8*Q8,"") | T8: =IFERROR(Q8*G8,"")
A9: Colts (1 year) | K9: =B9+C9+D9+E9-F9-G9-H9-I9 | Q9: =IFERROR((L9+N9)/(M9+O9),"") | R9: =IFERROR(D9*Q9,"") | T9: =IFERROR(Q9*G9,"")
A10: Foals | K10: =B10+C10+D10+E10-F10-G10-H10-I10 | Q10: =IFERROR((L10+N10)/(M10+O10),"") | R10: =IFERROR(D10*Q10,"") | T10: =IFERROR(Q10*G10,"")
A11: Oxen | B11: 65 | C11: 5 | D11: 5 | G11: 13 | H11: 3 | J11: 59 | K11: =B11+C11+D11+E11-F11-G11-H11-I11 | L11: ='Merdon Receipts'!F52 | M11: 12 | N11: ='Merdon Receipts'!F62 | O11: 1 | Q11: =IFERROR((L11+N11)/(M11+O11),"") | R11: =IFERROR(D11*Q11,"") | S11: =Q11*K11 | T11: =IFERROR(Q11*G11,"")
A12: Bulls | B12: 1 | J12: 1 | K12: =B12+C12+D12+E12-F12-G12-H12-I12 | Q12: =IFERROR((L12+N12)/(M12+O12),"") | R12: =IFERROR(D12*Q12,"") | T12: =IFERROR(Q12*G12,"")
A13: Cows | B13: 23 | C13: 3 | D13: 5 | G13: 5 | J13: 26 | K13: =B13+C13+D13+E13-F13-G13-H13-I13 | L13: ='Merdon Receipts'!F53 | M13: 5 | Q13: =IFERROR((L13+N13)/(M13+O13),"") | R13: =IFERROR(D13*Q13,"") | S13: =Q13*K13 | T13: =IFERROR(Q13*G13,"")
A14: Steers | B14: 8 | I14: 8 | J14: 0 | K14: =B14+C14+D14+E14-F14-G14-H14-I14 | Q14: =IFERROR((L14+N14)/(M14+O14),"") | R14: =IFERROR(D14*Q14,"") | T14: =IFERROR(Q14*G14,"")
A15: Bullocks | B15: 9 | J15: 9 | K15: =B15+C15+D15+E15-F15-G15-H15-I15 | Q15: =IFERROR((L15+N15)/(M15+O15),"") | R15: =IFERROR(D15*Q15,"") | T15: =IFERROR(Q15*G15,"")
A16: Yearlings | B16: 9 | J16: 9 | K16: =B16+C16+D16+E16-F16-G16-H16-I16 | Q16: =IFERROR((L16+N16)/(M16+O16),"") | R16: =IFERROR(D16*Q16,"") | T16: =IFERROR(Q16*G16,"")
A17: Calves | C17: 2 | D17: 17 | G17: 5 | H17: 2 | I17: 2 | J17: 10 | K17: =B17+C17+D17+E17-F17-G17-H17-I17 | L17: ='Merdon Receipts'!F54 | M17: 5 | Q17: =IFERROR((L17+N17)/(M17+O17),"") | R17: =IFERROR(D17*Q17,"") | S17: =Q17*K17 | T17: =IFERROR(Q17*G17,"") | U17: accounted for elsewhere is tithe
A18: Wethers | B18: 166 | D18: 37 | G18: 21 | H18: 11 | J18: 171 | K18: =B18+C18+D18+E18-F18-G18-H18-I18 | L18: ='Merdon Receipts'!F55*(20/22) | M18: 21 | Q18: =IFERROR((L18+N18)/(M18+O18),"") | R18: =IFERROR(D18*Q18,"") | S18: =Q18*K18 | T18: =IFERROR(Q18*G18,"") | U18: price in receipts includes 1 ram excuded by assumign same price
A19: Rams | B19: 12 | D19: 5 | G19: 3 | J19: 14 | K19: =B19+C19+D19+E19-F19-G19-H19-I19 | L19: ='Merdon Receipts'!F56*(2/26) | M19: 2 | N19: ='Merdon Receipts'!F55*(1/22) | O19: 1 | Q19: =IFERROR((L19+N19)/(M19+O19),"") | R19: =IFERROR(D19*Q19,"") | S19: =Q19*K19 | T19: =IFERROR(Q19*G19,"") | U19: price in reciepts includes ewes which are excluded by assuming same unit price
A20: Ewes | B20: 238 | D20: 55 | G20: 24 | H20: 8 | J20: 261 | K20: =B20+C20+D20+E20-F20-G20-H20-I20 | L20: ='Merdon Receipts'!F56*(20/22) | M20: 24 | Q20: =IFERROR((L20+N20)/(M20+O20),"") | R20: =IFERROR(D20*Q20,"") | S20: =Q20*K20 | T20: =IFERROR(Q20*G20,"") | U20: price in reciepts includes rams which are excluded by assuming same unit price
A21: Hoggs | B21: 99 | H21: 3 | I21: 96 | J21: 0 | K21: =B21+C21+D21+E21-F21-G21-H21-I21 | Q21: =IFERROR((L21+N21)/(M21+O21),"") | R21: =IFERROR(D21*Q21,"") | T21: =IFERROR(Q21*G21,"")
A22: Lambs | D22: 202 | G22: 37 | H22: 18 | I22: 22 | J22: 125 | K22: =B22+C22+D22+E22-F22-G22-H22-I22 | L22: ='Merdon Receipts'!F57 | M22: 34 | Q22: =IFERROR((L22+N22)/(M22+O22),"") | R22: =IFERROR(D22*Q22,"") | S22: =Q22*K22 | T22: =IFERROR(Q22*G22,"") | U22: accounted for elsewhere is tithe; number of lambs sold in stock doesn't match receipts
A23: Boars | B23: 1 | D23: 1 | H23: 1 | J23: 1 | K23: =B23+C23+D23+E23-F23-G23-H23-I23 | Q23: =IFERROR((L23+N23)/(M23+O23),"") | R23: =IFERROR(D23*Q23,"") | T23: =IFERROR(Q23*G23,"")
A24: Sows | B24: 2 | D24: 1 | H24: 1 | J24: 2 | K24: =B24+C24+D24+E24-F24-G24-H24-I24 | Q24: =IFERROR((L24+N24)/(M24+O24),"") | R24: =IFERROR(D24*Q24,"") | T24: =IFERROR(Q24*G24,"")
A25: Pigs | B25: 21 | D25: 22 | E25: 1 | G25: 29 | J25: 15 | K25: =B25+C25+D25+E25-F25-G25-H25-I25 | L25: ='Merdon Receipts'!F58 | M25: 29 | Q25: =IFERROR((L25+N25)/(M25+O25),"") | R25: =IFERROR(D25*Q25,"") | S25: =Q25*K25 | T25: =IFERROR(Q25*G25,"")
A26: Hoggets | B26: 28 | H26: 4 | I26: 24 | J26: 0 | K26: =B26+C26+D26+E26-F26-G26-H26-I26 | Q26: =IFERROR((L26+N26)/(M26+O26),"") | R26: =IFERROR(D26*Q26,"") | T26: =IFERROR(Q26*G26,"")
A27: Piglets | D27: 40 | I27: 5 | J27: 35 | K27: =B27+C27+D27+E27-F27-G27-H27-I27 | Q27: =IFERROR((L27+N27)/(M27+O27),"") | R27: =IFERROR(D27*Q27,"") | T27: =IFERROR(Q27*G27,"") | U27: accounted for elsewhere is tithe
A28: Swans | K28: =B28+C28+D28+E28-F28-G28-H28-I28 | Q28: =IFERROR((L28+N28)/(M28+O28),"") | R28: =IFERROR(D28*Q28,"") | T28: =IFERROR(Q28*G28,"")
A29: Peacocks | K29: =B29+C29+D29+E29-F29-G29-H29-I29 | Q29: =IFERROR((L29+N29)/(M29+O29),"") | R29: =IFERROR(D29*Q29,"") | T29: =IFERROR(Q29*G29,"")
A30: Total | K30: =B30+C30+D30+E30-F30-G30-H30-I30 | Q30: =IFERROR((L30+N30)/(M30+O30),"") | R30: =IFERROR(D30*Q30,"") | T30: =SUM(T4:T29)
K31: =B31+C31+D31+E31-F31-G31-H31-I31 | Q31: =IFERROR((L31+N31)/(M31+O31),"") | R31: =IFERROR(D31*Q31,"") | T31: =IFERROR(Q31*G31,"")
A32: Wool | K32: =B32+C32+D32+E32-F32-G32-H32-I32 | Q32: =IFERROR((L32+N32)/(M32+O32),"") | R32: =IFERROR(D32*Q32,"") | T32: =IFERROR(Q32*G32,"")
A33: Fleeces | K33: =B33+C33+D33+E33-F33-G33-H33-I33 | Q33: =IFERROR((L33+N33)/(M33+O33),"") | R33: =IFERROR(D33*Q33,"") | T33: =IFERROR(Q33*G33,"")
A34: Coarse wool | D34: 451 | G34: 405 | I34: 46 | J34: 0 | K34: =B34+C34+D34+E34-F34-G34-H34-I34 | P34: =3+14*Assumptions!E5 | Q34: 0.02 | R34: =IFERROR(D34*Q34,"") | U34: unit price from overview sheet (UnitPricesStocks_averages)
A35: Lamb's wool | D35: 163 | G35: 163 | J35: 0 | K35: =B35+C35+D35+E35-F35-G35-H35-I35 | P35: =13*0.04 | Q35: 0.01 | R35: =IFERROR(D35*Q35,"") | T35: =IFERROR(Q35*G35,"") | U35: unit price from overview sheet (UnitPricesStocks_averages)
A36: Wool locks | D36: =2*0.04+4*Assumptions!E4 | G36: =D36 | K36: =B36+C36+D36+E36-F36-G36-H36-I36 | L36: ='Merdon Receipts'!F59 | M36: =P36 | P36: =G36 | Q36: =IFERROR((L36+N36)/(M36+O36),"") | R36: =IFERROR(D36*Q36,"") | S36: =Q36*K36 | T36: =IFERROR(Q36*G36,"")
A37: Wool sold at shearing | K37: =B37+C37+D37+E37-F37-G37-H37-I37 | Q37: =IFERROR((L37+N37)/(M37+O37),"") | R37: =IFERROR(D37*Q37,"") | T37: =IFERROR(Q37*G37,"")
A38: Total | K38: =B38+C38+D38+E38-F38-G38-H38-I38 | Q38: =IFERROR((L38+N38)/(M38+O38),"") | R38: =SUM(R34:R36) | T38: =SUM(T34:T37)
K39: =B39+C39+D39+E39-F39-G39-H39-I39 | Q39: =IFERROR((L39+N39)/(M39+O39),"") | R39: =IFERROR(D39*Q39,"") | T39: =IFERROR(Q39*G39,"")
K40: =B40+C40+D40+E40-F40-G40-H40-I40 | Q40: =IFERROR((L40+N40)/(M40+O40),"") | R40: =IFERROR(D40*Q40,"") | T40: =IFERROR(Q40*G40,"")
A41: Hides | K41: =B41+C41+D41+E41-F41-G41-H41-I41 | Q41: =IFERROR((L41+N41)/(M41+O41),"") | R41: =IFERROR(D41*Q41,"") | T41: =IFERROR(Q41*G41,"")
A42: Ox hides | D42: 3 | G42: 3 | J42: 0 | K42: =B42+C42+D42+E42-F42-G42-H42-I42 | L42: ='Merdon Receipts'!F65 | M42: 3 | Q42: =IFERROR((L42+N42)/(M42+O42),"") | R42: =IFERROR(D42*Q42,"") | S42: =Q42*K42 | T42: =IFERROR(Q42*G42,"")
A43: Cow hides | D43: 2 | G43: 2 | J43: 0 | K43: =B43+C43+D43+E43-F43-G43-H43-I43 | L43: ='Merdon Receipts'!F66 | M43: 2 | Q43: =IFERROR((L43+N43)/(M43+O43),"") | R43: =IFERROR(D43*Q43,"") | S43: =Q43*K43 | T43: =IFERROR(Q43*G43,"")
A44: Mare hides | K44: =B44+C44+D44+E44-F44-G44-H44-I44 | Q44: =IFERROR((L44+N44)/(M44+O44),"") | R44: =IFERROR(D44*Q44,"") | T44: =IFERROR(Q44*G44,"")
A45: Steer hides | K45: =B45+C45+D45+E45-F45-G45-H45-I45 | Q45: =IFERROR((L45+N45)/(M45+O45),"") | R45: =IFERROR(D45*Q45,"") | T45: =IFERROR(Q45*G45,"")
A46: Yearling Calf hides | K46: =B46+C46+D46+E46-F46-G46-H46-I46 | Q46: =IFERROR((L46+N46)/(M46+O46),"") | R46: =IFERROR(D46*Q46,"") | T46: =IFERROR(Q46*G46,"")
A47: Calf hides | K47: =B47+C47+D47+E47-F47-G47-H47-I47 | Q47: =IFERROR((L47+N47)/(M47+O47),"") | R47: =IFERROR(D47*Q47,"") | T47: =IFERROR(Q47*G47,"")
A48: Pig hides | K48: =B48+C48+D48+E48-F48-G48-H48-I48 | Q48: =IFERROR((L48+N48)/(M48+O48),"") | R48: =IFERROR(D48*Q48,"") | T48: =IFERROR(Q48*G48,"")
A49: Weather woolskins | B49: 7 | G49: 7 | J49: 0 | K49: =B49+C49+D49+E49-F49-G49-H49-I49 | Q49: =IFERROR((L49+N49)/(M49+O49),"") | R49: =IFERROR(D49*Q49,"") | T49: =IFERROR(Q49*G49,"")
A50: Ram woolskins | K50: =B50+C50+D50+E50-F50-G50-H50-I50 | Q50: =IFERROR((L50+N50)/(M50+O50),"") | R50: =IFERROR(D50*Q50,"") | T50: =IFERROR(Q50*G50,"")
A51: Ewe woolskins | B51: 7 | G51: 7 | J51: 0 | K51: =B51+C51+D51+E51-F51-G51-H51-I51 | Q51: =IFERROR((L51+N51)/(M51+O51),"") | R51: =IFERROR(D51*Q51,"") | T51: =IFERROR(Q51*G51,"")
A52: Hogg woolskins | B52: 3 | G52: 3 | J52: 0 | K52: =B52+C52+D52+E52-F52-G52-H52-I52 | Q52: =IFERROR((L52+N52)/(M52+O52),"") | R52: =IFERROR(D52*Q52,"") | T52: =IFERROR(Q52*G52,"")
A53: Woolskins (total) | B53: 17 | G53: 17 | J53: 0 | K53: =B53+C53+D53+E53-F53-G53-H53-I53 | L53: ='Merdon Receipts'!F67 | M53: 17 | Q53: =IFERROR((L53+N53)/(M53+O53),"") | R53: =IFERROR(D53*Q53,"") | S53: =Q53*K53 | T53: =IFERROR(Q53*G53,"")
A54: Wether bareskins | D54: 4 | G54: 4 | J54: 0 | K54: =B54+C54+D54+E54-F54-G54-H54-I54 | Q54: =IFERROR((L54+N54)/(M54+O54),"") | R54: =IFERROR(D54*Q54,"") | T54: =IFERROR(Q54*G54,"")
A55: Ram bareskins | K55: =B55+C55+D55+E55-F55-G55-H55-I55 | Q55: =IFERROR((L55+N55)/(M55+O55),"") | R55: =IFERROR(D55*Q55,"") | T55: =IFERROR(Q55*G55,"")
A56: Ewe bareskins | D56: 1 | G56: 1 | J56: 0 | K56: =B56+C56+D56+E56-F56-G56-H56-I56 | Q56: =IFERROR((L56+N56)/(M56+O56),"") | R56: =IFERROR(D56*Q56,"") | T56: =IFERROR(Q56*G56,"")
A57: Hogg bareskins | K57: =B57+C57+D57+E57-F57-G57-H57-I57 | Q57: =IFERROR((L57+N57)/(M57+O57),"") | R57: =IFERROR(D57*Q57,"") | T57: =IFERROR(Q57*G57,"")
A58: Bareskins (total) | D58: 5 | G58: 5 | J58: 0 | K58: =B58+C58+D58+E58-F58-G58-H58-I58 | L58: ='Merdon Receipts'!F68 | M58: 5 | Q58: =IFERROR((L58+N58)/(M58+O58),"") | R58: =IFERROR(D58*Q58,"") | S58: =Q58*K58 | T58: =IFERROR(Q58*G58,"")
A59: Lambskins | D59: 16 | G59: 16 | J59: 0 | K59: =B59+C59+D59+E59-F59-G59-H59-I59 | L59: ='Merdon Receipts'!F69 | M59: 4 | N59: ='Merdon Receipts'!F70 | O59: 4 | Q59: =IFERROR((L59+N59)/(M59+O59),"") | R59: =IFERROR(D59*Q59,"") | S59: =Q59*K59 | T59: =IFERROR(Q59*G59,"") | U59: Number sold in receipts doesn't match that of stock
A60: Rotted skins | K60: =B60+C60+D60+E60-F60-G60-H60-I60 | Q60: =IFERROR((L60+N60)/(M60+O60),"") | R60: =IFERROR(D60*Q60,"") | T60: =IFERROR(Q60*G60,"")
A61: Shorn skins | K61: =B61+C61+D61+E61-F61-G61-H61-I61 | Q61: =IFERROR((L61+N61)/(M61+O61),"") | R61: =IFERROR(D61*Q61,"") | T61: =IFERROR(Q61*G61,"")
A62: Total | K62: =B62+C62+D62+E62-F62-G62-H62-I62 | Q62: =IFERROR((L62+N62)/(M62+O62),"") | R62: =IFERROR(D62*Q62,"") | T62: =SUM(T42:T61)
K63: =B63+C63+D63+E63-F63-G63-H63-I63 | Q63: =IFERROR((L63+N63)/(M63+O63),"") | R63: =IFERROR(D63*Q63,"") | T63: =IFERROR(Q63*G63,"")
A64: Poultry stock | K64: =B64+C64+D64+E64-F64-G64-H64-I64 | Q64: =IFERROR((L64+N64)/(M64+O64),"") | R64: =IFERROR(D64*Q64,"") | T64: =IFERROR(Q64*G64,"")
A65: Hens | K65: =B65+C65+D65+E65-F65-G65-H65-I65 | Q65: =IFERROR((L65+N65)/(M65+O65),"") | R65: =IFERROR(D65*Q65,"") | T65: =IFERROR(Q65*G65,"")
A66: Geese | K66: =B66+C66+D66+E66-F66-G66-H66-I66 | Q66: =IFERROR((L66+N66)/(M66+O66),"") | R66: =IFERROR(D66*Q66,"") | T66: =IFERROR(Q66*G66,"")
A67: Capons (from chickens) | K67: =B67+C67+D67+E67-F67-G67-H67-I67 | Q67: =IFERROR((L67+N67)/(M67+O67),"") | R67: =IFERROR(D67*Q67,"") | T67: =IFERROR(Q67*G67,"")
A68: Cocks & hens | K68: =B68+C68+D68+E68-F68-G68-H68-I68 | Q68: =IFERROR((L68+N68)/(M68+O68),"") | R68: =IFERROR(D68*Q68,"") | T68: =IFERROR(Q68*G68,"")
A69: Total
K70: =B70+C70+D70+E70-F70-G70-H70-I70 | Q70: =IFERROR((L70+N70)/(M70+O70),"") | R70: =IFERROR(D70*Q70,"") | T70: =IFERROR(Q70*G70,"")
K71: =B71+C71+D71+E71-F71-G71-H71-I71 | Q71: =IFERROR((L71+N71)/(M71+O71),"") | R71: =IFERROR(D71*Q71,"") | T71: =IFERROR(Q71*G71,"")
A72: Poultry production | K72: =B72+C72+D72+E72-F72-G72-H72-I72 | Q72: =IFERROR((L72+N72)/(M72+O72),"") | R72: =IFERROR(D72*Q72,"") | T72: =IFERROR(Q72*G72,"")
A73: Eggs | D73: 400 | G73: 400 | J73: 0 | K73: =B73+C73+D73+E73-F73-G73-H73-I73 | L73: ='Merdon Receipts'!F72 | M73: 400 | Q73: =IFERROR((L73+N73)/(M73+O73),"") | R73: =IFERROR(D73*Q73,"") | S73: =Q73*K73 | T73: =IFERROR(Q73*G73,"")
A74: Cocks & hens from churchscot of customary tenants | K74: =B74+C74+D74+E74-F74-G74-H74-I74 | Q74: =IFERROR((L74+N74)/(M74+O74),"") | R74: =IFERROR(D74*Q74,"") | T74: =IFERROR(Q74*G74,"")
A75: Total | K75: =B75+C75+D75+E75-F75-G75-H75-I75 | Q75: =IFERROR((L75+N75)/(M75+O75),"") | R75: =IFERROR(D75*Q75,"") | T75: =SUM(T73:T74)
K76: =B76+C76+D76+E76-F76-G76-H76-I76 | Q76: =IFERROR((L76+N76)/(M76+O76),"") | R76: =IFERROR(D76*Q76,"") | T76: =IFERROR(Q76*G76,"")
A77: Meat | K77: =B77+C77+D77+E77-F77-G77-H77-I77 | Q77: =IFERROR((L77+N77)/(M77+O77),"") | R77: =IFERROR(D77*Q77,"") | T77: =IFERROR(Q77*G77,"")
A78: Beef | K78: =B78+C78+D78+E78-F78-G78-H78-I78 | Q78: =IFERROR((L78+N78)/(M78+O78),"") | R78: =IFERROR(D78*Q78,"") | T78: =IFERROR(Q78*G78,"")
A79: Mutton | K79: =B79+C79+D79+E79-F79-G79-H79-I79 | Q79: =IFERROR((L79+N79)/(M79+O79),"") | R79: =IFERROR(D79*Q79,"") | T79: =IFERROR(Q79*G79,"")
A80: Pork | K80: =B80+C80+D80+E80-F80-G80-H80-I80 | Q80: =IFERROR((L80+N80)/(M80+O80),"") | R80: =IFERROR(D80*Q80,"") | T80: =IFERROR(Q80*G80,"")
K81: =B81+C81+D81+E81-F81-G81-H81-I81 | Q81: =IFERROR((L81+N81)/(M81+O81),"") | R81: =IFERROR(D81*Q81,"") | T81: =IFERROR(Q81*G81,"")
K82: =B82+C82+D82+E82-F82-G82-H82-I82 | Q82: =IFERROR((L82+N82)/(M82+O82),"") | R82: =IFERROR(D82*Q82,"") | T82: =IFERROR(Q82*G82,"")
A83: Cheese | K83: =B83+C83+D83+E83-F83-G83-H83-I83 | Q83: =IFERROR((L83+N83)/(M83+O83),"") | R83: =IFERROR(D83*Q83,"") | T83: =IFERROR(Q83*G83,"")
A84: Winter cheese | D84: 18 | G84: 18 | J84: 0 | K84: =B84+C84+D84+E84-F84-G84-H84-I84 | L84: ='Merdon Receipts'!F60 | M84: 18 | Q84: =IFERROR((L84+N84)/(M84+O84),"") | R84: =IFERROR(D84*Q84,"") | S84: =Q84*K84 | T84: =IFERROR(Q84*G84,"") | U84: 6 cloves
A85: Summer cheese | D85: 168 | G85: 157 | I85: 11 | J85: 0 | K85: =B85+C85+D85+E85-F85-G85-H85-I85 | L85: ='Merdon Receipts'!F61 | M85: 157 | Q85: =IFERROR((L85+N85)/(M85+O85),"") | R85: =IFERROR(D85*Q85,"") | S85: =Q85*K85 | T85: =IFERROR(Q85*G85,"") | U85: accounted for elsewhere is tithe; weight is 8 weys 7 cloves
A86: Total | T86: =SUM(T84:T85)
K87: =B87+C87+D87+E87-F87-G87-H87-I87 | Q87: =IFERROR((L87+N87)/(M87+O87),"") | R87: =IFERROR(D87*Q87,"") | T87: =IFERROR(Q87*G87,"")
K88: =B88+C88+D88+E88-F88-G88-H88-I88 | Q88: =IFERROR((L88+N88)/(M88+O88),"") | R88: =IFERROR(D88*Q88,"") | T88: =IFERROR(Q88*G88,"")
A89: Butter | D89: =15*0.04+1*Assumptions!E4 | G89: =D89 | K89: =B89+C89+D89+E89-F89-G89-H89-I89 | L89: ='Merdon Receipts'!F64 | M89: =P89 | P89: =G89 | Q89: =IFERROR((L89+N89)/(M89+O89),"") | R89: =IFERROR(D89*Q89,"") | S89: =Q89*K89 | T89: =IFERROR(Q89*G89,"")
A90: Total | K90: =B90+C90+D90+E90-F90-G90-H90-I90 | Q90: =IFERROR((L90+N90)/(M90+O90),"") | R90: =IFERROR(D90*Q90,"") | T90: =T89
Q91: =IFERROR((L91+N91)/(M91+O91),"") | R91: =IFERROR(D91*Q91,"") | T91: =IFERROR(Q91*G91,"")
A92: Cider | Q92: =IFERROR((L92+N92)/(M92+O92),"") | R92: =IFERROR(D92*Q92,"") | T92: =IFERROR(Q92*G92,"")
Q93: =IFERROR((L93+N93)/(M93+O93),"") | R93: =IFERROR(D93*Q93,"") | T93: =IFERROR(Q93*G93,"")
Q94: =IFERROR((L94+N94)/(M94+O94),"") | R94: =IFERROR(D94*Q94,"") | T94: =IFERROR(Q94*G94,"")
Q95: =IFERROR((L95+N95)/(M95+O95),"") | R95: =IFERROR(D95*Q95,"") | T95: =IFERROR(Q95*G95,"")
Q96: =IFERROR((L96+N96)/(M96+O96),"") | R96: =IFERROR(D96*Q96,"") | T96: =IFERROR(Q96*G96,"")
Q97: =IFERROR((L97+N97)/(M97+O97),"") | R97: =IFERROR(D97*Q97,"") | T97: =IFERROR(Q97*G97,"")

Sheet Assumptions
A1: ASSUMPTIONS
B3: Weights | C3: Value (in lbs) | D3: Value (in cloves) | E3: Value (in weys) | F3: Value (in stone)
B4: Lbs | C4: 1 | D4: =C4/C5 | E4: =C4/C6 | F4: =C4/C7
B5: Cloves | C5: 7 | D5: 1 | E5: =C5/C6 | F5: =C7/C5
B6: Wey | C6: 175 | D6: =C6/C5 | E6: =C6/C6 | F6: =C7/C6
B7: Stone | C7: =175/14 | D7: =C5/C7 | E7: =C7/C6 | F7: 1
