Workbook

Sheet Overton Overview - Completed
A1: OVERTON OVERVIEW - COMPLETED | B1: Total in £ | C1: Error | D1: Note
A2: CASH ACCOUNT
A3: RECEIPTS
A4: Arrears total | B4: 17.214583
A5: Rents of assize total | B5: 30.992708
A6: Quittances total | B6: 1.85
A7: Defaults of rent total | B7: 5.4625
A8: Defaults of rent through the pestilence total
A9: Cotlands defaults total
A10: Cotlands total
A11: Total of quittances and defaults of rent total
A12: Total of rents remaining clear total
A13: Farms total
A14: Annual recognizances total | B14: 0
A15: Issues of the Manor total | B15: 23.0125
A16: Issues of the tenements in the lord's hands total
A17: Sale of labour services total
A18: Sale of corn total | B18: 41.472917
A19: Entry and marriage fines total | B19: 4.8
A20: Pleas & perquisites total | B20: 4.9625
A21: Forfeited chattels total
A22: Farm of the demesne land total
A23: Total of all receipts (calculated here) | B23: =SUM(B5:B22)
A24: Total of all receipts (calculated here) incl arrears | B24: =SUM(B4:B22)
A25: Total recorded in the accounts excl. arrears | C25: =B23-B25
A26: Total recorded in the accounts incl. arrears | B26: =B25+B4
A29: EXPENSES
A30: Cost of ploughs total | B30: 6.2604167
A31: Purchase of corn total | B31: 0
A32: Cost of carts and wagons total | B32: 1.775
A33: Cost of dairy total | B33: 0.54583333
A34: Purchase of stock total | B34: 0
A35: Sheepcote total | B35: 7.2708333
A36: Cost of buildings total | B36: 2.4875
A37: Threshing total | B37: 1.5083333
A38: Barley expenses
A39: Expenses of the harvest total | B39: 1.2239583
A40: Necessary expenses
A41: Wages of the bailiff
A42: Steward's expenses total
A43: Annual fees
A44: Total of all expenses per account
A45: Total of all expenses (calculated here)
A46: Total fixed investment
A47: Total Demesne fixed investment
A49: Owed by the reeve | B49: =B23-B45
A50: From accounts | B50: 25.926042
A52: Allowances
A53: Cash deliveries
A54: Sum of the above | B54: =SUM(B52:B53)
A55: Total of all allowances and cash deliveries in accounts
A57: Net amount owed | B57: =B50-B54
A58: Net amount owed in accounts
A60: GRANGE ACCOUNT | B60: Total Production | D60: Value of total gross production in £ | E60: Value of total net production in £
A61: Grange | B61: qrs | C61: bus
A62: Wheat | B62: 64
A63: Rye
A64: Dredge
A65: Curall | B65: 2
A66: Barley | B66: 81.5
A67: Oats | B67: 144
A68: Beans
A69: Peas
A70: Vetches
A71: Total value of gross production (sum of the above)
A72: Total value of net production
A73: Value of sales
A75: MILL ACCOUNT | B75: Total Production | D75: Total in £
A76: Issues of the mill | B76: qrs | C76: bus
A77: Wheat
A78: Oatmeal
A79: 1st grade malt
A80: 2nd grade malt
A81: Maslin
A82: Total value of production (sum of the above)
A83: Value of sales
A85: STOCK ACCOUNT
A86: Livestock | B86: Begin stock | C86: End stock | D86: Stockbuilding | F86: Value of stock in £ | G86: Value of stockbuilding
A87: Cart-horses | D87: =C87-B87 | F87: ='Stock'!K5*'Stock'!O5 | G87: =D87*'Stock'!O5
A88: Mares | C88: 0 | D88: =C88-B88 | F88: ='Stock'!K5*'Stock'!O5 | G88: =D88*'Stock'!O5
A89: Plough horses | B89: 9 | C89: 10 | D89: 1 | F89: ='Stock'!K6*'Stock'!O6 | G89: =D89*'Stock'!O6
A90: Colts (2 years) | C90: 0 | D90: =C90-B90 | F90: ='Stock'!K8*'Stock'!O8 | G90: =D90*'Stock'!O8
A91: Colts (2 years) | C91: 0 | D91: =C91-B91 | F91: ='Stock'!K8*'Stock'!O8 | G91: =D91*'Stock'!O8
A92: Colts (1 year) | C92: 0 | D92: =C92-B92 | F92: ='Stock'!K9*'Stock'!O9 | G92: =D92*'Stock'!O9
A93: Foals | C93: 0 | D93: =C93-B93 | F93: ='Stock'!K10*'Stock'!O10 | G93: =D93*'Stock'!O10
A94: Oxen | B94: 20 | C94: 20 | D94: 0 | F94: ='Stock'!K11*'Stock'!O11 | G94: =D94*'Stock'!O11
A95: Bulls | B95: 1 | C95: 1 | D95: 0 | F95: ='Stock'!K12*'Stock'!O12 | G95: =D95*'Stock'!O12
A96: Cows | B96: 25 | C96: 26 | D96: 1 | F96: ='Stock'!K13*'Stock'!O13 | G96: =D96*'Stock'!O13
A97: Steers | B97: 5 | C97: 0 | D97: -5 | F97: ='Stock'!K14*'Stock'!O14 | G97: =D97*'Stock'!O14
A98: Bullocks | B98: 9 | C98: 9 | D98: 0 | F98: ='Stock'!K15*'Stock'!O15 | G98: =D98*'Stock'!O15
A99: Yearlings | B99: 10 | C99: 9 | D99: -1 | F99: ='Stock'!K16*'Stock'!O16 | G99: =D99*'Stock'!O16
A100: Calves | B100: 25 | C100: 9 | D100: -16 | F100: ='Stock'!K17*'Stock'!O17 | G100: =D100*'Stock'!O17
A101: Wethers | C101: 0 | D101: =C101-B101 | F101: ='Stock'!K18*'Stock'!O18 | G101: =D101*'Stock'!O18
A102: Rams | B102: 20 | C102: 17 | D102: -3 | F102: ='Stock'!K19*'Stock'!O19 | G102: =D102*'Stock'!O19
A103: Ewes | B103: 495 | C103: 631 | D103: 136 | F103: ='Stock'!K20*'Stock'!O20 | G103: =D103*'Stock'!O20
A104: Hoggs | B104: 234 | C104: 0 | D104: -234 | F104: ='Stock'!K21*'Stock'!O21 | G104: =D104*'Stock'!O21
A105: Lambs | B105: 401 | C105: 280 | D105: -121 | F105: ='Stock'!K22*'Stock'!O22 | G105: =D105*'Stock'!O22
A106: Boars | C106: 0 | D106: =C106-B106 | F106: ='Stock'!K23*'Stock'!O23 | G106: =D106*'Stock'!O23
A107: Sows | C107: 0 | D107: =C107-B107 | F107: ='Stock'!K24*'Stock'!O24 | G107: =D107*'Stock'!O24
A108: Pigs | C108: 0 | D108: =C108-B108 | F108: ='Stock'!K25*'Stock'!O25 | G108: =D108*'Stock'!O25
...

Sheet Issues of the Mills
A1: No mill account for Adderbury

Sheet raw data
A1: Heading | B1: Sentence | C1: Total in Pounds | D1: Pounds | E1: Shillings | F1: Pence | G1: Corn | H1: Total Quarters Except 1 | I1: Total Bushels Except 1 | J1: Total Corn Cross-Check | K1: Total Corn Manorial Account | L1: Corn Quantity Error | M1: Quarters 1 | N1: Bushels 1 | O1: shilling a quarter 1 | P1: pence a quarter 1 | Q1: shilling a quarter 2 | R1: pence a quarter 2 | S1: shilling a quarter 3 | T1: pence a quarter 3 | U1: shilling a quarter 4 | V1: pence a quarter 4 | W1: shilling a bushel 1 | X1: pence a bushel 1 | Y1: shilling a bushel 2 | Z1: pence a bushel 2 | AA1: shilling a bushel 3 | AB1: pence a bushel 3 | AC1: shilling a bushel 4 | AD1: pence a bushel 4
A2: Adderbury | B2: The account2 of William Jakeman, reeve there, for the sixth year of the translation of Henry Beaufort', lord bishop of Winchester, and the eleventh year of the reign of King Henry the Fourth. | C2: 0 | D2: 0 | E2: 0 | F2: 0 | H2: 0 | I2: 0 | J2: 0 | K2: 0 | L2: 0 | M2: 0 | N2: 0
A3: Arrears | B3: None. | C3: 0 | D3: 0 | E3: 0 | F3: 0 | H3: 0 | I3: 0 | J3: 0 | K3: 0 | L3: 0 | M3: 0 | N3: 0
A4: Rents of assize | B4: And for £6 9 shilling 6.25pence for all rents of assize at St Thomas the Apostle (21 December). | C4: 6.48 | D4: 6 | E4: 9 | F4: 6.25 | H4: 0 | I4: 0 | J4: 0 | K4: 0 | L4: 0 | M4: 0 | N4: 0
A5: Rents of assize | B5: £6 9 shilling 8.5pence at Easter (23 March). | C5: 6.49 | D5: 6 | E5: 9 | F5: 8.5 | H5: 0 | I5: 0 | J5: 0 | K5: 0 | L5: 0 | M5: 0 | N5: 0
A6: Rents of assize | B6: £6 9 shilling 6.25pence at the Nativity of St John the Baptist (24 June). | C6: 6.48 | D6: 6 | E6: 9 | F6: 6.25 | H6: 0 | I6: 0 | J6: 0 | K6: 0 | L6: 0 | M6: 0 | N6: 0
A7: Rents of assize | B7: £6 10 shilling 1.5pence at Michaelmas (29 September). | C7: 6.51 | D7: 6 | E7: 10 | F7: 1.5 | H7: 0 | I7: 0 | J7: 0 | K7: 0 | L7: 0 | M7: 0 | N7: 0
A8: Rents of assize | B8: Total, £25 18 shilling 10.5pence. | C8: 25.94 | D8: 25 | E8: 18 | F8: 10.5 | H8: 0 | I8: 0 | J8: 0 | K8: 0 | L8: 0 | M8: 0 | N8: 0
A9: Quittances of rent | B9: In quittance of rent of 1 reeve for the year 5 shilling. | C9: 0.25 | D9: 0 | E9: 5 | F9: 0 | H9: 0 | I9: 0 | J9: 0 | K9: 0 | L9: 0 | M9: 0 | N9: 0
A10: Quittances of rent | B10: nothing this year of the 4 shilling for 1 smith forging the ironwork of 2 ploughs for the year. | C10: 0.2 | D10: 0 | E10: 4 | F10: 0 | H10: 0 | I10: 0 | J10: 0 | K10: 0 | L10: 0 | M10: 0 | N10: 0
A11: Quittances of rent | B11: nothing this year of the 4 shilling for 1 shepherd keeping the lord's wethers for the year. | C11: 0.2 | D11: 0 | E11: 4 | F11: 0 | H11: 0 | I11: 0 | J11: 0 | K11: 0 | L11: 0 | M11: 0 | N11: 0
A12: Quittances of rent | B12: nothing this year of the 4 shilling for 1 swineherd for the year. | C12: 0.2 | D12: 0 | E12: 4 | F12: 0 | H12: 0 | I12: 0 | J12: 0 | K12: 0 | L12: 0 | M12: 0 | N12: 0
A13: Quittances of rent | B13: nothing this year of the 4 shilling for 1 cowherd for the year. | C13: 0.2 | D13: 0 | E13: 4 | F13: 0 | H13: 0 | I13: 0 | J13: 0 | K13: 0 | L13: 0 | M13: 0 | N13: 0
... A149: Cost of buildings | B149: board-nails and clout-nails bought for the same 1 shilling 4pence. | C149: 0.07 | D149: 0 | E149: 1 | F149: 4 | H149: 0 | I149: 0 | J149: 0 | K149: 0 | L149: 0 | M149: 0 | N149: 0
A150: Cost of buildings | B150: 4 quarters 4 bushels of limestone bought at Walton' 5 shilling 3pence, at 1 shilling 2pence a quarters. | C150: 0.26 | D150: 0 | E150: 5 | F150: 3 | H150: 4 | I150: 4 | J150: 4.5 | K150: 4.5 | L150: 0 | M150: 4 | N150: 4 | O150: 1 | P150: 2
A151: Cost of buildings | B151: carrying the same 4pence. | C151: 0.02 | D151: 0 | E151: 0 | F151: 4 | H151: 0 | I151: 0 | J151: 0 | K151: 0 | L151: 0 | M151: 0 | N151: 0
A152: Cost of buildings | B152: 8 quarters of limestone bought at Witney 10 shilling 4pence, at 1 shilling 31 pence a quarters. | C152: 0.52 | D152: 0 | E152: 10 | F152: 4 | H152: 8 | I152: 0 | J152: 8 | K152: 8 | L152: 0 | M152: 8 | N152: 0 | O152: 1 | P152: 31
A153: Cost of buildings | B153: carrying the same from Witney to Adderbury 3 shilling 8pence. | C153: 0.18 | D153: 0 | E153: 3 | F153: 8 | H153: 0 | I153: 0 | J153: 0 | K153: 0 | L153: 0 | M153: 0 | N153: 0
A154: Cost of buildings | B154: 1,500 stone slates bought 6 shilling, at 4 shilling a 1,000.. | C154: 0.3 | D154: 0 | E154: 6 | F154: 0 | H154: 0 | I154: 0 | J154: 0 | K154: 0 | L154: 0 | M154: 0 | N154: 0
A155: Cost of buildings | B155: 500 eaves-stones bought 2 shilling 6pence, at 6pence a 100.. | C155: 0.12 | D155: 0 | E155: 2 | F155: 6 | H155: 0 | I155: 0 | J155: 0 | K155: 0 | L155: 0 | M155: 0 | N155: 0
A156: Cost of buildings | B156: 6,000 pins bought 2 shilling, at 4pence a 1,000.. | C156: 0.12 | D156: 0 | E156: 2 | F156: 4 | H156: 0 | I156: 0 | J156: 0 | K156: 0 | L156: 0 | M156: 0 | N156: 0
A157: Cost of buildings | B157: 50 ridge-tiles bought 6 shilling 3pence, at 1.5pence each. | C157: 0.31 | D157: 0 | E157: 6 | F157: 3 | H157: 0 | I157: 0 | J157: 0 | K157: 0 | L157: 0 | M157: 0 | N157: 0
A158: Cost of buildings | B158: sand bought and dug and quarried at Tadmarton 10pence. | C158: 0.04 | D158: 0 | E158: 0 | F158: 10 | H158: 0 | I158: 0 | J158: 0 | K158: 0 | L158: 0 | M158: 0 | N158: 0
A159: Cost of buildings | B159: stipend of 1 man going to Walton' to quarry lime there 2pence. | C159: 0.01 | D159: 0 | E159: 0 | F159: 2 | H159: 0 | I159: 0 | J159: 0 | K159: 0 | L159: 0 | M159: 0 | N159: 0
A160: Cost of buildings | B160: expenses of 12 men coming for a boon-work with 6 carts to quarry sand at Newotele and carry it to Adderbury, with the digging, 2 shilling 3pence. | C160: 0.11 | D160: 0 | E160: 2 | F160: 3 | H160: 0 | I160: 0 | J160: 0 | K160: 0 | L160: 0 | M160: 0 | N160: 0
A161: Cost of buildings | B161: hiring 1 man to carry sand and lime from the warrener's chamber to the barn by piece-work 4pence. | C161: 0.02 | D161: 0 | E161: 0 | F161: 4 | H161: 0 | I161: 0 | J161: 0 | K161: 0 | L161: 0 | M161: 0 | N161: 0
A162: Cost of buildings | B162: carrying the ridge-tiles bought above 8pence. | C162: 0.03 | D162: 0 | E162: 0 | F162: 8 | H162: 0 | I162: 0 | J162: 0 | K162: 0 | L162: 0 | M162: 0 | N162: 0
A163: Cost of buildings | B163: expenses of various men coming for a boon-work to buy slates at Aynho and carry them to Adderbury with the expenses of 1 man there mending the said slates 2d 1 shilling 9.5pence. | C163: 0.09 | D163: 0 | E163: 1 | F163: 9.5 | H163: 0 | I163: 0 | J163: 0 | K163: 0 | L163: 0 | M163: 0 | N163: 0
A164: Cost of buildings | B164: 1 tine bought 8pence. | C164: 0.03 | D164: 0 | E164: 0 | F164: 8 | H164: 0 | I164: 0 | J164: 0 | K164: 0 | L164: 0 | M164: 0 | N164: 0
... A181: Total of all allowances | B181: Total of all allowances and cash deliveries, £64 19 shilling 11.5pence He is quit. | C181: 65 | D181: 64 | E181: 19 | F181: 11.5 | H181: 0 | I181: 0 | J181: 0 | K181: 0 | L181: 0 | M181: 0 | N181: 0
A182: Wheat | B182: William Jakeman, reeve there, answers for 3 quarters of wheat remaining.. | C182: 0 | D182: 0 | E182: 0 | F182: 0 | G182: wheat | H182: 3 | I182: 0 | J182: 3 | K182: 3 | L182: 0 | M182: 3 | N182: 0
A183: Wheat | B183: Total, 3 quarters.. | C183: 0 | D183: 0 | E183: 0 | F183: 0 | H183: 3 | I183: 0 | J183: 3 | K183: 3 | L183: 0 | M183: 3 | N183: 0
A184: Wheat | B184: 3 quarters remain in the keeping of John Eadburbury, farmer there, to be handed back and restored at the end of his farm of 12 years, this year being the fifth. | C184: 0 | D184: 0 | E184: 0 | F184: 0 | H184: 3 | I184: 0 | J184: 3 | K184: 3 | L184: 0 | M184: 3 | N184: 0
A185: Rye | B185: And for 34 quarters of rye remaining.. | C185: 0 | D185: 0 | E185: 0 | F185: 0 | G185: rye | H185: 34 | I185: 0 | J185: 34 | K185: 34 | L185: 0 | M185: 34 | N185: 0
A186: Rye | B186: Total, 34 quarters.. | C186: 0 | D186: 0 | E186: 0 | F186: 0 | H186: 34 | I186: 0 | J186: 34 | K186: 34 | L186: 0 | M186: 34 | N186: 0
A187: Rye | B187: 34 quarters remain in the keeping of the said John Eadburbury, farmer there, to be handed back and restored at the end of his farm as before. | C187: 0 | D187: 0 | E187: 0 | F187: 0 | H187: 34 | I187: 0 | J187: 34 | K187: 34 | L187: 0 | M187: 34 | N187: 0
A188: Dredge | B188: And for 30 quarters of dredge remaining.. | C188: 0 | D188: 0 | E188: 0 | F188: 0 | G188: dredge | H188: 30 | I188: 0 | J188: 30 | K188: 30 | L188: 0 | M188: 30 | N188: 0
A189: Dredge | B189: Total, 30 quarters.. | C189: 0 | D189: 0 | E189: 0 | F189: 0 | H189: 30 | I189: 0 | J189: 30 | K189: 30 | L189: 0 | M189: 30 | N189: 0
A190: Dredge | B190: 30 quarters remain in the keeping of the said John Eadburbury, farmer there, to be handed back and restored as before. | C190: 0 | D190: 0 | E190: 0 | F190: 0 | H190: 30 | I190: 0 | J190: 30 | K190: 30 | L190: 0 | M190: 30 | N190: 0
A191: Pulses | B191: None remain. | C191: 0 | D191: 0 | E191: 0 | F191: 0 | H191: 0 | I191: 0 | J191: 0 | K191: 0 | L191: 0 | M191: 0 | N191: 0
A192: Oats | B192: And for 10 quarters of oats.. | C192: 0 | D192: 0 | E192: 0 | F192: 0 | G192: oats | H192: 10 | I192: 0 | J192: 10 | K192: 10 | L192: 0 | M192: 10 | N192: 0
A193: Oats | B193: Total, 10 quarters.. | C193: 0 | D193: 0 | E193: 0 | F193: 0 | H193: 10 | I193: 0 | J193: 10 | K193: 10 | L193: 0 | M193: 10 | N193: 0
A194: Oats | B194: 10 quarters remain in the keeping of the said John Eadburbury, farmer there, to be handed back and restored as before. | C194: 0 | D194: 0 | E194: 0 | F194: 0 | H194: 10 | I194: 0 | J194: 10 | K194: 10 | L194: 0 | M194: 10 | N194: 0
A195: Oats | B195: Eadburbury, farmer, to be handed back and restored at the end of his farm or the value of the same as before. | C195: 0 | D195: 0 | E195: 0 | F195: 0 | H195: 0 | I195: 0 | J195: 0 | K195: 0 | L195: 0 | M195: 0 | N195: 0
A196: Stock | B196: Horses: 4 remain. | C196: 0 | D196: 0 | E196: 0 | F196: 0 | H196: 0 | I196: 0 | J196: 0 | K196: 0 | L196: 0 | M196: 0 | N196: 0
A197: Stock | B197: 1 from the heriot of William Rundell'. | C197: 0 | D197: 0 | E197: 0 | F197: 0 | H197: 0 | I197: 0 | J197: 0 | K197: 0 | L197: 0 | M197: 0 | N197: 0
A198: Stock | B198: Total 5. 1 sold within. | C198: 0 | D198: 0 | E198: 0 | F198: 0 | H198: 0 | I198: 0 | J198: 0 | K198: 0 | L198: 0 | M198: 0 | N198: 0
A199: Stock | B199: 4 cart-horses remain, of which 2 are worth £1 6s 8pence, 1 is worth £1, and 1 feeble one is worth 2 shilling, in the keeping of the said John Eadburbury, farmer there, to be handed back and restored at the end of his farm or the value of the same at the choice of the lord bishop or his attorney. | C199: 1 | D199: 1 | E199: 0 | F199: 0 | H199: 0 | I199: 0 | J199: 0 | K199: 0 | L199: 0 | M199: 0 | N199: 0
A200: Stock | B200: Plough-horses: 6 remain. | C200: 0 | D200: 0 | E200: 0 | F200: 0 | H200: 0 | I200: 0 | J200: 0 | K200: 0 | L200: 0 | M200: 0 | N200: 0
A201: Stock | B201: Total, 6. 6 remain, worth £2, in the keeping of John. | C201: 2 | D201: 2 | E201: 0 | F201: 0 | H201: 0 | I201: 0 | J201: 0 | K201: 0 | L201: 0 | M201: 0 | N201: 0
A202: Stock | B202: Colts: 1 from the heriot of John Diconurn. | C202: 0 | D202: 0 | E202: 0 | F202: 0 | H202: 0 | I202: 0 | J202: 0 | K202: 0 | L202: 0 | M202: 0 | N202: 0
A203: Stock | B203: sold within. | C203: 0 | D203: 0 | E203: 0 | F203: 0 | H203: 0 | I203: 0 | J203: 0 | K203: 0 | L203: 0 | M203: 0 | N203: 0
A204: Stock | B204: none remain. | C204: 0 | D204: 0 | E204: 0 | F204: 0 | H204: 0 | I204: 0 | J204: 0 | K204: 0 | L204: 0 | M204: 0 | N204: 0
... A268: Stock | B268: none remain. mid. | C268: 0 | D268: 0 | E268: 0 | F268: 0 | H268: 0 | I268: 0 | J268: 0 | K268: 0 | L268: 0 | M268: 0 | N268: 0

Sheet Prices
A1: Meat & Dairy Prices
C2: 1301 | D2: 1302 | E2: Average
A3: Beef | B3: £ per lb | C3: 0.0033351854 | D3: 0.0032608538 | E3: =AVERAGE(C3:D3)
A4: Mutton | B4: £ per lb | C4: 0.0036593977 | D4: 0.0037125513 | E4: =AVERAGE(C4:D4)
A5: Pork | B5: £ per lb | C5: 0.0038431326 | D5: 0.0037574803 | E5: =AVERAGE(C5:D5)
A6: Cheese | B6: £ per lb | C6: 0.0055768754 | D6: 0.0056654898 | E6: =AVERAGE(C6:D6)
A7: Butter | B7: £ per lb | C7: 0.0036626221 | D7: 0.0035935077 | E7: =AVERAGE(C7:D7)
A8: Milk | B8: £ per gallon | C8: 0.0055768754 | D8: 0.0056654898 | E8: =AVERAGE(C8:D8)

Sheet Labour Rents

Sheet Overton Overview
A1: OVERTON OVERVIEW | B1: £ | C1: s | D1: d | G1: Total in £ | H1: Error
A2: CASH ACCOUNT
A3: RECEIPTS
A4: Arrears total | G4: =IF(INDEX('Overton Receipts'!$A$4:$F$171,MATCH('Overton Overview'!$A4,'Overton Receipts'!$A$4:$A$171,0),6)=0,"",INDEX('Overton Receipts'!$A$4:$F$171,MATCH('Overton Overview'!$A4,'Overton Receipts'!$A$4:$A$171,0),6))
A5: Rents of assize total | G5: =IF(INDEX('Overton Receipts'!$A$4:$F$171,MATCH('Overton Overview'!$A5,'Overton Receipts'!$A$4:$A$171,0),6)=0,"",INDEX('Overton Receipts'!$A$4:$F$171,MATCH('Overton Overview'!$A5,'Overton Receipts'!$A$4:$A$171,0),6))
A6: Quittances total | G6: =IF(INDEX('Overton Receipts'!$A$4:$F$171,MATCH('Overton Overview'!$A6,'Overton Receipts'!$A$4:$A$171,0),6)=0,"",INDEX('Overton Receipts'!$A$4:$F$171,MATCH('Overton Overview'!$A6,'Overton Receipts'!$A$4:$A$171,0),6))
A7: Defaults of rent total | G7: =IF(INDEX('Overton Receipts'!$A$4:$F$171,MATCH('Overton Overview'!$A7,'Overton Receipts'!$A$4:$A$171,0),6)=0,"",INDEX('Overton Receipts'!$A$4:$F$171,MATCH('Overton Overview'!$A7,'Overton Receipts'!$A$4:$A$171,0),6))
A8: Annual recognizances total | G8: =IF(INDEX('Overton Receipts'!$A$4:$F$171,MATCH('Overton Overview'!$A8,'Overton Receipts'!$A$4:$A$171,0),6)=0,"",INDEX('Overton Receipts'!$A$4:$F$171,MATCH('Overton Overview'!$A8,'Overton Receipts'!$A$4:$A$171,0),6))
A9: Issues of the Manor total | G9: =IF(INDEX('Overton Receipts'!$A$4:$F$171,MATCH('Overton Overview'!$A9,'Overton Receipts'!$A$4:$A$171,0),6)=0,"",INDEX('Overton Receipts'!$A$4:$F$171,MATCH('Overton Overview'!$A9,'Overton Receipts'!$A$4:$A$171,0),6))
A10: Sale of corn total | G10: =IF(INDEX('Overton Receipts'!$A$4:$F$171,MATCH('Overton Overview'!$A10,'Overton Receipts'!$A$4:$A$171,0),6)=0,"",INDEX('Overton Receipts'!$A$4:$F$171,MATCH('Overton Overview'!$A10,'Overton Receipts'!$A$4:$A$171,0),6))
A11: Entry and marriage fines total | G11: =IF(INDEX('Overton Receipts'!$A$4:$F$171,MATCH('Overton Overview'!$A11,'Overton Receipts'!$A$4:$A$171,0),6)=0,"",INDEX('Overton Receipts'!$A$4:$F$171,MATCH('Overton Overview'!$A11,'Overton Receipts'!$A$4:$A$171,0),6))
A12: Pleas & perquisites total | G12: =IF(INDEX('Overton Receipts'!$A$4:$F$171,MATCH('Overton Overview'!$A12,'Overton Receipts'!$A$4:$A$171,0),6)=0,"",INDEX('Overton Receipts'!$A$4:$F$171,MATCH('Overton Overview'!$A12,'Overton Receipts'!$A$4:$A$171,0),6))
A13: Sum of the above (incl. arrears) | G13: ='Overton Receipts'!F169
A14: Total recorded in the accounts excl. arrears | G14: ='Overton Receipts'!F170 | H14: =G13-G14 | I14: difference is arrears
A15: Total recorded in the accounts incl. arrears | G15: ='Overton Receipts'!F171 | I15: not recorded
A18: EXPENSES
A19: Cost of ploughs total | G19: =IF(INDEX('Overton Expenses'!$A$2:$F$156,MATCH('Overton Overview'!$A19,'Overton Expenses'!$A$2:$A$156,0),6)=0,"",INDEX('Overton Expenses'!$A$2:$F$156,MATCH('Overton Overview'!$A19,'Overton Expenses'!$A$2:$A$156,0),6))
A20: Purchase of corn total | G20: =IF(INDEX('Overton Expenses'!$A$2:$F$156,MATCH('Overton Overview'!$A20,'Overton Expenses'!$A$2:$A$156,0),6)=0,"",INDEX('Overton Expenses'!$A$2:$F$156,MATCH('Overton Overview'!$A20,'Overton Expenses'!$A$2:$A$156,0),6))
A21: Cost of carts and wagons total | G21: =IF(INDEX('Overton Expenses'!$A$2:$F$156,MATCH('Overton Overview'!$A21,'Overton Expenses'!$A$2:$A$156,0),6)=0,"",INDEX('Overton Expenses'!$A$2:$F$156,MATCH('Overton Overview'!$A21,'Overton Expenses'!$A$2:$A$156,0),6))
A22: Cost of dairy total | G22: =IF(INDEX('Overton Expenses'!$A$2:$F$156,MATCH('Overton Overview'!$A22,'Overton Expenses'!$A$2:$A$156,0),6)=0,"",INDEX('Overton Expenses'!$A$2:$F$156,MATCH('Overton Overview'!$A22,'Overton Expenses'!$A$2:$A$156,0),6))
A23: Purchase of stock total | G23: =IF(INDEX('Overton Expenses'!$A$2:$F$156,MATCH('Overton Overview'!$A23,'Overton Expenses'!$A$2:$A$156,0),6)=0,"",INDEX('Overton Expenses'!$A$2:$F$156,MATCH('Overton Overview'!$A23,'Overton Expenses'!$A$2:$A$156,0),6))
A24: Sheepcote total | G24: =IF(INDEX('Overton Expenses'!$A$2:$F$156,MATCH('Overton Overview'!$A24,'Overton Expenses'!$A$2:$A$156,0),6)=0,"",INDEX('Overton Expenses'!$A$2:$F$156,MATCH('Overton Overview'!$A24,'Overton Expenses'!$A$2:$A$156,0),6))
A25: Cost of buildings total | G25: =IF(INDEX('Overton Expenses'!$A$2:$F$156,MATCH('Overton Overview'!$A25,'Overton Expenses'!$A$2:$A$156,0),6)=0,"",INDEX('Overton Expenses'!$A$2:$F$156,MATCH('Overton Overview'!$A25,'Overton Expenses'!$A$2:$A$156,0),6))
A26: Threshing total | G26: =IF(INDEX('Overton Expenses'!$A$2:$F$156,MATCH('Overton Overview'!$A26,'Overton Expenses'!$A$2:$A$156,0),6)=0,"",INDEX('Overton Expenses'!$A$2:$F$156,MATCH('Overton Overview'!$A26,'Overton Expenses'!$A$2:$A$156,0),6))
A27: Expenses of the harvest total | G27: =IF(INDEX('Overton Expenses'!$A$2:$F$156,MATCH('Overton Overview'!$A27,'Overton Expenses'!$A$2:$A$156,0),6)=0,"",INDEX('Overton Expenses'!$A$2:$F$156,MATCH('Overton Overview'!$A27,'Overton Expenses'!$A$2:$A$156,0),6))
A28: Steward's expenses total | G28: =IF(INDEX('Overton Expenses'!$A$2:$F$156,MATCH('Overton Overview'!$A28,'Overton Expenses'!$A$2:$A$156,0),6)=0,"",INDEX('Overton Expenses'!$A$2:$F$156,MATCH('Overton Overview'!$A28,'Overton Expenses'!$A$2:$A$156,0),6))
A29: Sum of the above | G29: ='Overton Expenses'!F149
A30: Total of all expenses | G30: ='Overton Expenses'!F148 | H30: =G29-G30
A31: Capital Expenses | G31: ='Overton Expenses'!F157
A33: Owed by the reeve | G33: =G13-G29-G4
A34: From accounts | G34: ='Overton Expenses'!F151 | H34: =G34-G33
A36: Cash deliveries | G36: ='Overton Expenses'!F153
A37: Total of all allowances and cash deliveries in accounts | B37: n/a | G37: =G36
A39: Net amount owed | G39: =G34-G37
A40: Net amount owed in accounts | G40: ='Overton Expenses'!F154 | H40: =G39-G40
A42: GRANGE ACCOUNT | B42: Net Production | G42: Value of net production | H42: Value of total gross production in £
A43: Grange | B43: qrs | G43: £ | H43: £ | I43: Note: Columns indexed are hardcoded, do not alter number of columns in issues of grange
A44: Net wheat | B44: ='Issues of the Grange'!L19 | G44: ='Issues of the Grange'!O19 | H44: ='Issues of the Grange'!T5
A45: Net curall | B45: ='Issues of the Grange'!L20 | G45: ='Issues of the Grange'!O20 | H45: ='Issues of the Grange'!T6
A46: Net barley | B46: ='Issues of the Grange'!L21 | G46: ='Issues of the Grange'!O21 | H46: ='Issues of the Grange'!T7
A47: Net oats | B47: ='Issues of the Grange'!L22 | G47: ='Issues of the Grange'!O22 | H47: ='Issues of the Grange'!T8
A48: Net peas | B48: ='Issues of the Grange'!L23 | G48: ='Issues of the Grange'!O23 | H48: ='Issues of the Grange'!T9
A49: Net vetches | B49: ='Issues of the Grange'!L24 | G49: ='Issues of the Grange'!O24 | H49: ='Issues of the Grange'!T10
A50: Total value of gross production (sum of the above) | G50: =SUM(H44:H49)
A51: Total value of net production | G51: =SUM(G44:G49)
A52: Value of sales | G52: ='Issues of the Grange'!P25
A54: MILL ACCOUNT | B54: n/a | G54: Value of net production
A55: Issues of the mill | B55: qrs | G55: £
A56: Wheat - Town Mill | B56: ='Issues of the Mill'!L5 | G56: ='Issues of the Mill'!R5
A57: Maslin - Town Mill | B57: ='Issues of the Mill'!L6 | G57: ='Issues of the Mill'!R6
A58: Coarse-ground corn - Town Mill | B58: ='Issues of the Mill'!L7 | G58: ='Issues of the Mill'!R7
A59: Malt - Town Hill | B59: ='Issues of the Mill'!L8 | G59: ='Issues of the Mill'!R8
A60: Total value of production (sum of the above) | G60: =SUM(G56:G59)
A61: Value of sales | G61: ='Issues of the Mill'!R12
A63: STOCK ACCOUNT
A64: Livestock | B64: Inherited stock | C64: End-period stock | D64: Stockbuilding | F64: Sales in (£) | G64: Value of production (£) at sales prices
A65: Cart-horses | B65: =IFERROR(INDEX(Stock!$A$3:$T$94,MATCH('Overton Overview'!$A65,Stock!$A$3:$A$94,0),MATCH('Overton Overview'!B$64,Stock!$A$3:$T$3,0)),0) | C65: =IFERROR(INDEX(Stock!$A$3:$T$94,MATCH('Overton Overview'!$A65,Stock!$A$3:$A$94,0),MATCH('Overton Overview'!C$64,Stock!$A$3:$T$3,0)),0) | D65: =C65-B65 | F65: =IFERROR(INDEX(Stock!$A$3:$T$94,MATCH('Overton Overview'!$A65,Stock!$A$3:$A$94,0),MATCH('Overton Overview'!F$64,Stock!$A$3:$T$3,0)),0) | G65: =IFERROR(INDEX(Stock!$A$3:$T$94,MATCH('Overton Overview'!$A65,Stock!$A$3:$A$94,0),MATCH('Overton Overview'!G$64,Stock!$A$3:$T$3,0)),0)
A66: Mares | B66: =IFERROR(INDEX(Stock!$A$3:$T$94,MATCH('Overton Overview'!$A66,Stock!$A$3:$A$94,0),MATCH('Overton Overview'!B$64,Stock!$A$3:$T$3,0)),0) | C66: =IFERROR(INDEX(Stock!$A$3:$T$94,MATCH('Overton Overview'!$A66,Stock!$A$3:$A$94,0),MATCH('Overton Overview'!C$64,Stock!$A$3:$T$3,0)),0) | D66: =C66-B66 | F66: =IFERROR(INDEX(Stock!$A$3:$T$94,MATCH('Overton Overview'!$A66,Stock!$A$3:$A$94,0),MATCH('Overton Overview'!F$64,Stock!$A$3:$T$3,0)),0) | G66: =IFERROR(INDEX(Stock!$A$3:$T$94,MATCH('Overton Overview'!$A66,Stock!$A$3:$A$94,0),MATCH('Overton Overview'!G$64,Stock!$A$3:$T$3,0)),0)
A67: Plough horses | B67: =IFERROR(INDEX(Stock!$A$3:$T$94,MATCH('Overton Overview'!$A67,Stock!$A$3:$A$94,0),MATCH('Overton Overview'!B$64,Stock!$A$3:$T$3,0)),0) | C67: =IFERROR(INDEX(Stock!$A$3:$T$94,MATCH('Overton Overview'!$A67,Stock!$A$3:$A$94,0),MATCH('Overton Overview'!C$64,Stock!$A$3:$T$3,0)),0) | D67: =C67-B67 | F67: =IFERROR(INDEX(Stock!$A$3:$T$94,MATCH('Overton Overview'!$A67,Stock!$A$3:$A$94,0),MATCH('Overton Overview'!F$64,Stock!$A$3:$T$3,0)),0) | G67: =IFERROR(INDEX(Stock!$A$3:$T$94,MATCH('Overton Overview'!$A67,Stock!$A$3:$A$94,0),MATCH('Overton Overview'!G$64,Stock!$A$3:$T$3,0)),0)
A68: Colts (2 years) | B68: =IFERROR(INDEX(Stock!$A$3:$T$94,MATCH('Overton Overview'!$A68,Stock!$A$3:$A$94,0),MATCH('Overton Overview'!B$64,Stock!$A$3:$T$3,0)),0) | C68: =IFERROR(INDEX(Stock!$A$3:$T$94,MATCH('Overton Overview'!$A68,Stock!$A$3:$A$94,0),MATCH('Overton Overview'!C$64,Stock!$A$3:$T$3,0)),0) | D68: =C68-B68 | F68: =IFERROR(INDEX(Stock!$A$3:$T$94,MATCH('Overton Overview'!$A68,Stock!$A$3:$A$94,0),MATCH('Overton Overview'!F$64,Stock!$A$3:$T$3,0)),0) | G68: =IFERROR(INDEX(Stock!$A$3:$T$94,MATCH('Overton Overview'!$A68,Stock!$A$3:$A$94,0),MATCH('Overton Overview'!G$64,Stock!$A$3:$T$3,0)),0)
A69: Colts (2 years) | B69: =IFERROR(INDEX(Stock!$A$3:$T$94,MATCH('Overton Overview'!$A69,Stock!$A$3:$A$94,0),MATCH('Overton Overview'!B$64,Stock!$A$3:$T$3,0)),0) | C69: =IFERROR(INDEX(Stock!$A$3:$T$94,MATCH('Overton Overview'!$A69,Stock!$A$3:$A$94,0),MATCH('Overton Overview'!C$64,Stock!$A$3:$T$3,0)),0) | D69: =C69-B69 | F69: =IFERROR(INDEX(Stock!$A$3:$T$94,MATCH('Overton Overview'!$A69,Stock!$A$3:$A$94,0),MATCH('Overton Overview'!F$64,Stock!$A$3:$T$3,0)),0) | G69: =IFERROR(INDEX(Stock!$A$3:$T$94,MATCH('Overton Overview'!$A69,Stock!$A$3:$A$94,0),MATCH('Overton Overview'!G$64,Stock!$A$3:$T$3,0)),0)
A70: Colts (1 year) | B70: =IFERROR(INDEX(Stock!$A$3:$T$94,MATCH('Overton Overview'!$A70,Stock!$A$3:$A$94,0),MATCH('Overton Overview'!B$64,Stock!$A$3:$T$3,0)),0) | C70: =IFERROR(INDEX(Stock!$A$3:$T$94,MATCH('Overton Overview'!$A70,Stock!$A$3:$A$94,0),MATCH('Overton Overview'!C$64,Stock!$A$3:$T$3,0)),0) | D70: =C70-B70 | F70: =IFERROR(INDEX(Stock!$A$3:$T$94,MATCH('Overton Overview'!$A70,Stock!$A$3:$A$94,0),MATCH('Overton Overview'!F$64,Stock!$A$3:$T$3,0)),0) | G70: =IFERROR(INDEX(Stock!$A$3:$T$94,MATCH('Overton Overview'!$A70,Stock!$A$3:$A$94,0),MATCH('Overton Overview'!G$64,Stock!$A$3:$T$3,0)),0)
A71: Foals | B71: =IFERROR(INDEX(Stock!$A$3:$T$94,MATCH('Overton Overview'!$A71,Stock!$A$3:$A$94,0),MATCH('Overton Overview'!B$64,Stock!$A$3:$T$3,0)),0) | C71: =IFERROR(INDEX(Stock!$A$3:$T$94,MATCH('Overton Overview'!$A71,Stock!$A$3:$A$94,0),MATCH('Overton Overview'!C$64,Stock!$A$3:$T$3,0)),0) | D71: =C71-B71 | F71: =IFERROR(INDEX(Stock!$A$3:$T$94,MATCH('Overton Overview'!$A71,Stock!$A$3:$A$94,0),MATCH('Overton Overview'!F$64,Stock!$A$3:$T$3,0)),0) | G71: =IFERROR(INDEX(Stock!$A$3:$T$94,MATCH('Overton Overview'!$A71,Stock!$A$3:$A$94,0),MATCH('Overton Overview'!G$64,Stock!$A$3:$T$3,0)),0)
A72: Oxen | B72: =IFERROR(INDEX(Stock!$A$3:$T$94,MATCH('Overton Overview'!$A72,Stock!$A$3:$A$94,0),MATCH('Overton Overview'!B$64,Stock!$A$3:$T$3,0)),0) | C72: =IFERROR(INDEX(Stock!$A$3:$T$94,MATCH('Overton Overview'!$A72,Stock!$A$3:$A$94,0),MATCH('Overton Overview'!C$64,Stock!$A$3:$T$3,0)),0) | D72: =C72-B72 | F72: =IFERROR(INDEX(Stock!$A$3:$T$94,MATCH('Overton Overview'!$A72,Stock!$A$3:$A$94,0),MATCH('Overton Overview'!F$64,Stock!$A$3:$T$3,0)),0) | G72: =IFERROR(INDEX(Stock!$A$3:$T$94,MATCH('Overton Overview'!$A72,Stock!$A$3:$A$94,0),MATCH('Overton Overview'!G$64,Stock!$A$3:$T$3,0)),0)
A73: Bulls | B73: =IFERROR(INDEX(Stock!$A$3:$T$94,MATCH('Overton Overview'!$A73,Stock!$A$3:$A$94,0),MATCH('Overton Overview'!B$64,Stock!$A$3:$T$3,0)),0) | C73: =IFERROR(INDEX(Stock!$A$3:$T$94,MATCH('Overton Overview'!$A73,Stock!$A$3:$A$94,0),MATCH('Overton Overview'!C$64,Stock!$A$3:$T$3,0)),0) | D73: =C73-B73 | F73: =IFERROR(INDEX(Stock!$A$3:$T$94,MATCH('Overton Overview'!$A73,Stock!$A$3:$A$94,0),MATCH('Overton Overview'!F$64,Stock!$A$3:$T$3,0)),0) | G73: =IFERROR(INDEX(Stock!$A$3:$T$94,MATCH('Overton Overview'!$A73,Stock!$A$3:$A$94,0),MATCH('Overton Overview'!G$64,Stock!$A$3:$T$3,0)),0)
A74: Cows | B74: =IFERROR(INDEX(Stock!$A$3:$T$94,MATCH('Overton Overview'!$A74,Stock!$A$3:$A$94,0),MATCH('Overton Overview'!B$64,Stock!$A$3:$T$3,0)),0) | C74: =IFERROR(INDEX(Stock!$A$3:$T$94,MATCH('Overton Overview'!$A74,Stock!$A$3:$A$94,0),MATCH('Overton Overview'!C$64,Stock!$A$3:$T$3,0)),0) | D74: =C74-B74 | F74: =IFERROR(INDEX(Stock!$A$3:$T$94,MATCH('Overton Overview'!$A74,Stock!$A$3:$A$94,0),MATCH('Overton Overview'!F$64,Stock!$A$3:$T$3,0)),0) | G74: =IFERROR(INDEX(Stock!$A$3:$T$94,MATCH('Overton Overview'!$A74,Stock!$A$3:$A$94,0),MATCH('Overton Overview'!G$64,Stock!$A$3:$T$3,0)),0)
A75: Steers | B75: =IFERROR(INDEX(Stock!$A$3:$T$94,MATCH('Overton Overview'!$A75,Stock!$A$3:$A$94,0),MATCH('Overton Overview'!B$64,Stock!$A$3:$T$3,0)),0) | C75: =IFERROR(INDEX(Stock!$A$3:$T$94,MATCH('Overton Overview'!$A75,Stock!$A$3:$A$94,0),MATCH('Overton Overview'!C$64,Stock!$A$3:$T$3,0)),0) | D75: =C75-B75 | F75: =IFERROR(INDEX(Stock!$A$3:$T$94,MATCH('Overton Overview'!$A75,Stock!$A$3:$A$94,0),MATCH('Overton Overview'!F$64,Stock!$A$3:$T$3,0)),0) | G75: =IFERROR(INDEX(Stock!$A$3:$T$94,MATCH('Overton Overview'!$A75,Stock!$A$3:$A$94,0),MATCH('Overton Overview'!G$64,Stock!$A$3:$T$3,0)),0)
A76: Bullocks | B76: =IFERROR(INDEX(Stock!$A$3:$T$94,MATCH('Overton Overview'!$A76,Stock!$A$3:$A$94,0),MATCH('Overton Overview'!B$64,Stock!$A$3:$T$3,0)),0) | C76: =IFERROR(INDEX(Stock!$A$3:$T$94,MATCH('Overton Overview'!$A76,Stock!$A$3:$A$94,0),MATCH('Overton Overview'!C$64,Stock!$A$3:$T$3,0)),0) | D76: =C76-B76 | F76: =IFERROR(INDEX(Stock!$A$3:$T$94,MATCH('Overton Overview'!$A76,Stock!$A$3:$A$94,0),MATCH('Overton Overview'!F$64,Stock!$A$3:$T$3,0)),0) | G76: =IFERROR(INDEX(Stock!$A$3:$T$94,MATCH('Overton Overview'!$A76,Stock!$A$3:$A$94,0),MATCH('Overton Overview'!G$64,Stock!$A$3:$T$3,0)),0)
... A90: Peacocks | B90: =IFERROR(INDEX(Stock!$A$3:$T$94,MATCH('Overton Overview'!$A90,Stock!$A$3:$A$94,0),MATCH('Overton Overview'!B$64,Stock!$A$3:$T$3,0)),0) | C90: =IFERROR(INDEX(Stock!$A$3:$T$94,MATCH('Overton Overview'!$A90,Stock!$A$3:$A$94,0),MATCH('Overton Overview'!C$64,Stock!$A$3:$T$3,0)),0) | D90: =C90-B90 | F90: =IFERROR(INDEX(Stock!$A$3:$T$94,MATCH('Overton Overview'!$A90,Stock!$A$3:$A$94,0),MATCH('Overton Overview'!F$64,Stock!$A$3:$T$3,0)),0) | G90: =IFERROR(INDEX(Stock!$A$3:$T$94,MATCH('Overton Overview'!$A90,Stock!$A$3:$A$94,0),MATCH('Overton Overview'!G$64,Stock!$A$3:$T$3,0)),0)
A91: Total | G91: =SUM(G65:G90)
A92: Value of sales | G92: =SUM(F65:F90)
A94: Wool | B94: Inherited stock | C94: End-period stock | D94: Stockbuilding | F94: Sales in (£) | G94: Value of production (£) at sales prices
A95: Fleeces | B95: =IFERROR(INDEX(Stock!$A$3:$T$94,MATCH('Overton Overview'!$A95,Stock!$A$3:$A$94,0),MATCH('Overton Overview'!B$64,Stock!$A$3:$T$3,0)),0) | C95: =IFERROR(INDEX(Stock!$A$3:$T$94,MATCH('Overton Overview'!$A95,Stock!$A$3:$A$94,0),MATCH('Overton Overview'!C$64,Stock!$A$3:$T$3,0)),0) | D95: =C95-B95 | F95: =IFERROR(INDEX(Stock!$A$3:$T$94,MATCH('Overton Overview'!$A95,Stock!$A$3:$A$94,0),MATCH('Overton Overview'!F$64,Stock!$A$3:$T$3,0)),0) | G95: =IFERROR(INDEX(Stock!$A$3:$T$94,MATCH('Overton Overview'!$A95,Stock!$A$3:$A$94,0),MATCH('Overton Overview'!G$64,Stock!$A$3:$T$3,0)),0)
A96: Coarse wool | B96: =IFERROR(INDEX(Stock!$A$3:$T$94,MATCH('Overton Overview'!$A96,Stock!$A$3:$A$94,0),MATCH('Overton Overview'!B$64,Stock!$A$3:$T$3,0)),0) | C96: =IFERROR(INDEX(Stock!$A$3:$T$94,MATCH('Overton Overview'!$A96,Stock!$A$3:$A$94,0),MATCH('Overton Overview'!C$64,Stock!$A$3:$T$3,0)),0) | D96: =C96-B96 | F96: =IFERROR(INDEX(Stock!$A$3:$T$94,MATCH('Overton Overview'!$A96,Stock!$A$3:$A$94,0),MATCH('Overton Overview'!F$64,Stock!$A$3:$T$3,0)),0) | G96: =IFERROR(INDEX(Stock!$A$3:$T$94,MATCH('Overton Overview'!$A96,Stock!$A$3:$A$94,0),MATCH('Overton Overview'!G$64,Stock!$A$3:$T$3,0)),0)
A97: Lamb's wool | B97: =IFERROR(INDEX(Stock!$A$3:$T$94,MATCH('Overton Overview'!$A97,Stock!$A$3:$A$94,0),MATCH('Overton Overview'!B$64,Stock!$A$3:$T$3,0)),0) | C97: =IFERROR(INDEX(Stock!$A$3:$T$94,MATCH('Overton Overview'!$A97,Stock!$A$3:$A$94,0),MATCH('Overton Overview'!C$64,Stock!$A$3:$T$3,0)),0) | D97: =C97-B97 | F97: =IFERROR(INDEX(Stock!$A$3:$T$94,MATCH('Overton Overview'!$A97,Stock!$A$3:$A$94,0),MATCH('Overton Overview'!F$64,Stock!$A$3:$T$3,0)),0) | G97: =IFERROR(INDEX(Stock!$A$3:$T$94,MATCH('Overton Overview'!$A97,Stock!$A$3:$A$94,0),MATCH('Overton Overview'!G$64,Stock!$A$3:$T$3,0)),0)
A98: Wool locks | B98: =IFERROR(INDEX(Stock!$A$3:$T$94,MATCH('Overton Overview'!$A98,Stock!$A$3:$A$94,0),MATCH('Overton Overview'!B$64,Stock!$A$3:$T$3,0)),0) | C98: =IFERROR(INDEX(Stock!$A$3:$T$94,MATCH('Overton Overview'!$A98,Stock!$A$3:$A$94,0),MATCH('Overton Overview'!C$64,Stock!$A$3:$T$3,0)),0) | D98: =C98-B98 | F98: =IFERROR(INDEX(Stock!$A$3:$T$94,MATCH('Overton Overview'!$A98,Stock!$A$3:$A$94,0),MATCH('Overton Overview'!F$64,Stock!$A$3:$T$3,0)),0) | G98: =IFERROR(INDEX(Stock!$A$3:$T$94,MATCH('Overton Overview'!$A98,Stock!$A$3:$A$94,0),MATCH('Overton Overview'!G$64,Stock!$A$3:$T$3,0)),0)
A99: Wool sold at shearing | B99: =IFERROR(INDEX(Stock!$A$3:$T$94,MATCH('Overton Overview'!$A99,Stock!$A$3:$A$94,0),MATCH('Overton Overview'!B$64,Stock!$A$3:$T$3,0)),0) | C99: =IFERROR(INDEX(Stock!$A$3:$T$94,MATCH('Overton Overview'!$A99,Stock!$A$3:$A$94,0),MATCH('Overton Overview'!C$64,Stock!$A$3:$T$3,0)),0) | D99: =C99-B99 | F99: =IFERROR(INDEX(Stock!$A$3:$T$94,MATCH('Overton Overview'!$A99,Stock!$A$3:$A$94,0),MATCH('Overton Overview'!F$64,Stock!$A$3:$T$3,0)),0) | G99: =IFERROR(INDEX(Stock!$A$3:$T$94,MATCH('Overton Overview'!$A99,Stock!$A$3:$A$94,0),MATCH('Overton Overview'!G$64,Stock!$A$3:$T$3,0)),0)
A100: Total value of production (sum of the above) | G100: =SUM(G95:G99)
A101: Value of sales | G101: =SUM(F95:F99)
A103: Hides | B103: Inherited stock | C103: End-period stock | D103: Stockbuilding | F103: Sales in (£) | G103: Value of production (£) at sales prices
A104: Ox hides | B104: =IFERROR(INDEX(Stock!$A$3:$T$94,MATCH('Overton Overview'!$A104,Stock!$A$3:$A$94,0),MATCH('Overton Overview'!B$64,Stock!$A$3:$T$3,0)),0) | C104: =IFERROR(INDEX(Stock!$A$3:$T$94,MATCH('Overton Overview'!$A104,Stock!$A$3:$A$94,0),MATCH('Overton Overview'!C$64,Stock!$A$3:$T$3,0)),0) | D104: =C104-B104 | F104: =IFERROR(INDEX(Stock!$A$3:$T$94,MATCH('Overton Overview'!$A104,Stock!$A$3:$A$94,0),MATCH('Overton Overview'!F$64,Stock!$A$3:$T$3,0)),0) | G104: =IFERROR(INDEX(Stock!$A$3:$T$94,MATCH('Overton Overview'!$A104,Stock!$A$3:$A$94,0),MATCH('Overton Overview'!G$64,Stock!$A$3:$T$3,0)),0)
A105: Cow hides | B105: =IFERROR(INDEX(Stock!$A$3:$T$94,MATCH('Overton Overview'!$A105,Stock!$A$3:$A$94,0),MATCH('Overton Overview'!B$64,Stock!$A$3:$T$3,0)),0) | C105: =IFERROR(INDEX(Stock!$A$3:$T$94,MATCH('Overton Overview'!$A105,Stock!$A$3:$A$94,0),MATCH('Overton Overview'!C$64,Stock!$A$3:$T$3,0)),0) | D105: =C105-B105 | F105: =IFERROR(INDEX(Stock!$A$3:$T$94,MATCH('Overton Overview'!$A105,Stock!$A$3:$A$94,0),MATCH('Overton Overview'!F$64,Stock!$A$3:$T$3,0)),0) | G105: =IFERROR(INDEX(Stock!$A$3:$T$94,MATCH('Overton Overview'!$A105,Stock!$A$3:$A$94,0),MATCH('Overton Overview'!G$64,Stock!$A$3:$T$3,0)),0)
A106: Mare hides | B106: =IFERROR(INDEX(Stock!$A$3:$T$94,MATCH('Overton Overview'!$A106,Stock!$A$3:$A$94,0),MATCH('Overton Overview'!B$64,Stock!$A$3:$T$3,0)),0) | C106: =IFERROR(INDEX(Stock!$A$3:$T$94,MATCH('Overton Overview'!$A106,Stock!$A$3:$A$94,0),MATCH('Overton Overview'!C$64,Stock!$A$3:$T$3,0)),0) | D106: =C106-B106 | F106: =IFERROR(INDEX(Stock!$A$3:$T$94,MATCH('Overton Overview'!$A106,Stock!$A$3:$A$94,0),MATCH('Overton Overview'!F$64,Stock!$A$3:$T$3,0)),0) | G106: =IFERROR(INDEX(Stock!$A$3:$T$94,MATCH('Overton Overview'!$A106,Stock!$A$3:$A$94,0),MATCH('Overton Overview'!G$64,Stock!$A$3:$T$3,0)),0)
A107: Steer hides | B107: =IFERROR(INDEX(Stock!$A$3:$T$94,MATCH('Overton Overview'!$A107,Stock!$A$3:$A$94,0),MATCH('Overton Overview'!B$64,Stock!$A$3:$T$3,0)),0) | C107: =IFERROR(INDEX(Stock!$A$3:$T$94,MATCH('Overton Overview'!$A107,Stock!$A$3:$A$94,0),MATCH('Overton Overview'!C$64,Stock!$A$3:$T$3,0)),0) | D107: =C107-B107 | F107: =IFERROR(INDEX(Stock!$A$3:$T$94,MATCH('Overton Overview'!$A107,Stock!$A$3:$A$94,0),MATCH('Overton Overview'!F$64,Stock!$A$3:$T$3,0)),0) | G107: =IFERROR(INDEX(Stock!$A$3:$T$94,MATCH('Overton Overview'!$A107,Stock!$A$3:$A$94,0),MATCH('Overton Overview'!G$64,Stock!$A$3:$T$3,0)),0)
A108: Yearling Calf hides | B108: =IFERROR(INDEX(Stock!$A$3:$T$94,MATCH('Overton Overview'!$A108,Stock!$A$3:$A$94,0),MATCH('Overton Overview'!B$64,Stock!$A$3:$T$3,0)),0) | C108: =IFERROR(INDEX(Stock!$A$3:$T$94,MATCH('Overton Overview'!$A108,Stock!$A$3:$A$94,0),MATCH('Overton Overview'!C$64,Stock!$A$3:$T$3,0)),0) | D108: =C108-B108 | F108: =IFERROR(INDEX(Stock!$A$3:$T$94,MATCH('Overton Overview'!$A108,Stock!$A$3:$A$94,0),MATCH('Overton Overview'!F$64,Stock!$A$3:$T$3,0)),0) | G108: =IFERROR(INDEX(Stock!$A$3:$T$94,MATCH('Overton Overview'!$A108,Stock!$A$3:$A$94,0),MATCH('Overton Overview'!G$64,Stock!$A$3:$T$3,0)),0)
A109: Calf hides | B109: =IFERROR(INDEX(Stock!$A$3:$T$94,MATCH('Overton Overview'!$A109,Stock!$A$3:$A$94,0),MATCH('Overton Overview'!B$64,Stock!$A$3:$T$3,0)),0) | C109: =IFERROR(INDEX(Stock!$A$3:$T$94,MATCH('Overton Overview'!$A109,Stock!$A$3:$A$94,0),MATCH('Overton Overview'!C$64,Stock!$A$3:$T$3,0)),0) | D109: =C109-B109 | F109: =IFERROR(INDEX(Stock!$A$3:$T$94,MATCH('Overton Overview'!$A109,Stock!$A$3:$A$94,0),MATCH('Overton Overview'!F$64,Stock!$A$3:$T$3,0)),0) | G109: =IFERROR(INDEX(Stock!$A$3:$T$94,MATCH('Overton Overview'!$A109,Stock!$A$3:$A$94,0),MATCH('Overton Overview'!G$64,Stock!$A$3:$T$3,0)),0)
A110: Pig hides | B110: =IFERROR(INDEX(Stock!$A$3:$T$94,MATCH('Overton Overview'!$A110,Stock!$A$3:$A$94,0),MATCH('Overton Overview'!B$64,Stock!$A$3:$T$3,0)),0) | C110: =IFERROR(INDEX(Stock!$A$3:$T$94,MATCH('Overton Overview'!$A110,Stock!$A$3:$A$94,0),MATCH('Overton Overview'!C$64,Stock!$A$3:$T$3,0)),0) | D110: =C110-B110 | F110: =IFERROR(INDEX(Stock!$A$3:$T$94,MATCH('Overton Overview'!$A110,Stock!$A$3:$A$94,0),MATCH('Overton Overview'!F$64,Stock!$A$3:$T$3,0)),0) | G110: =IFERROR(INDEX(Stock!$A$3:$T$94,MATCH('Overton Overview'!$A110,Stock!$A$3:$A$94,0),MATCH('Overton Overview'!G$64,Stock!$A$3:$T$3,0)),0)
A111: Weather woolskins | B111: =IFERROR(INDEX(Stock!$A$3:$T$94,MATCH('Overton Overview'!$A111,Stock!$A$3:$A$94,0),MATCH('Overton Overview'!B$64,Stock!$A$3:$T$3,0)),0) | C111: =IFERROR(INDEX(Stock!$A$3:$T$94,MATCH('Overton Overview'!$A111,Stock!$A$3:$A$94,0),MATCH('Overton Overview'!C$64,Stock!$A$3:$T$3,0)),0) | D111: =C111-B111 | F111: =IFERROR(INDEX(Stock!$A$3:$T$94,MATCH('Overton Overview'!$A111,Stock!$A$3:$A$94,0),MATCH('Overton Overview'!F$64,Stock!$A$3:$T$3,0)),0) | G111: =IFERROR(INDEX(Stock!$A$3:$T$94,MATCH('Overton Overview'!$A111,Stock!$A$3:$A$94,0),MATCH('Overton Overview'!G$64,Stock!$A$3:$T$3,0)),0)
A112: Ram woolskins | B112: =IFERROR(INDEX(Stock!$A$3:$T$94,MATCH('Overton Overview'!$A112,Stock!$A$3:$A$94,0),MATCH('Overton Overview'!B$64,Stock!$A$3:$T$3,0)),0) | C112: =IFERROR(INDEX(Stock!$A$3:$T$94,MATCH('Overton Overview'!$A112,Stock!$A$3:$A$94,0),MATCH('Overton Overview'!C$64,Stock!$A$3:$T$3,0)),0) | D112: =C112-B112 | F112: =IFERROR(INDEX(Stock!$A$3:$T$94,MATCH('Overton Overview'!$A112,Stock!$A$3:$A$94,0),MATCH('Overton Overview'!F$64,Stock!$A$3:$T$3,0)),0) | G112: =IFERROR(INDEX(Stock!$A$3:$T$94,MATCH('Overton Overview'!$A112,Stock!$A$3:$A$94,0),MATCH('Overton Overview'!G$64,Stock!$A$3:$T$3,0)),0)
A113: Ewe woolskins | B113: =IFERROR(INDEX(Stock!$A$3:$T$94,MATCH('Overton Overview'!$A113,Stock!$A$3:$A$94,0),MATCH('Overton Overview'!B$64,Stock!$A$3:$T$3,0)),0) | C113: =IFERROR(INDEX(Stock!$A$3:$T$94,MATCH('Overton Overview'!$A113,Stock!$A$3:$A$94,0),MATCH('Overton Overview'!C$64,Stock!$A$3:$T$3,0)),0) | D113: =C113-B113 | F113: =IFERROR(INDEX(Stock!$A$3:$T$94,MATCH('Overton Overview'!$A113,Stock!$A$3:$A$94,0),MATCH('Overton Overview'!F$64,Stock!$A$3:$T$3,0)),0) | G113: =IFERROR(INDEX(Stock!$A$3:$T$94,MATCH('Overton Overview'!$A113,Stock!$A$3:$A$94,0),MATCH('Overton Overview'!G$64,Stock!$A$3:$T$3,0)),0)
A114: Hogg woolskins | B114: =IFERROR(INDEX(Stock!$A$3:$T$94,MATCH('Overton Overview'!$A114,Stock!$A$3:$A$94,0),MATCH('Overton Overview'!B$64,Stock!$A$3:$T$3,0)),0) | C114: =IFERROR(INDEX(Stock!$A$3:$T$94,MATCH('Overton Overview'!$A114,Stock!$A$3:$A$94,0),MATCH('Overton Overview'!C$64,Stock!$A$3:$T$3,0)),0) | D114: =C114-B114 | F114: =IFERROR(INDEX(Stock!$A$3:$T$94,MATCH('Overton Overview'!$A114,Stock!$A$3:$A$94,0),MATCH('Overton Overview'!F$64,Stock!$A$3:$T$3,0)),0) | G114: =IFERROR(INDEX(Stock!$A$3:$T$94,MATCH('Overton Overview'!$A114,Stock!$A$3:$A$94,0),MATCH('Overton Overview'!G$64,Stock!$A$3:$T$3,0)),0)
A115: Woolskins (total) | B115: =IFERROR(INDEX(Stock!$A$3:$T$94,MATCH('Overton Overview'!$A115,Stock!$A$3:$A$94,0),MATCH('Overton Overview'!B$64,Stock!$A$3:$T$3,0)),0) | C115: =IFERROR(INDEX(Stock!$A$3:$T$94,MATCH('Overton Overview'!$A115,Stock!$A$3:$A$94,0),MATCH('Overton Overview'!C$64,Stock!$A$3:$T$3,0)),0) | D115: =C115-B115 | F115: =IFERROR(INDEX(Stock!$A$3:$T$94,MATCH('Overton Overview'!$A115,Stock!$A$3:$A$94,0),MATCH('Overton Overview'!F$64,Stock!$A$3:$T$3,0)),0) | G115: =IFERROR(INDEX(Stock!$A$3:$T$94,MATCH('Overton Overview'!$A115,Stock!$A$3:$A$94,0),MATCH('Overton Overview'!G$64,Stock!$A$3:$T$3,0)),0)
... A123: Shorn skins | B123: =IFERROR(INDEX(Stock!$A$3:$T$94,MATCH('Overton Overview'!$A123,Stock!$A$3:$A$94,0),MATCH('Overton Overview'!B$64,Stock!$A$3:$T$3,0)),0) | C123: =IFERROR(INDEX(Stock!$A$3:$T$94,MATCH('Overton Overview'!$A123,Stock!$A$3:$A$94,0),MATCH('Overton Overview'!C$64,Stock!$A$3:$T$3,0)),0) | D123: =C123-B123 | F123: =IFERROR(INDEX(Stock!$A$3:$T$94,MATCH('Overton Overview'!$A123,Stock!$A$3:$A$94,0),MATCH('Overton Overview'!F$64,Stock!$A$3:$T$3,0)),0) | G123: =IFERROR(INDEX(Stock!$A$3:$T$94,MATCH('Overton Overview'!$A123,Stock!$A$3:$A$94,0),MATCH('Overton Overview'!G$64,Stock!$A$3:$T$3,0)),0)
A124: Total value of production (sum of the above) | G124: =SUM(G104:G123)
A125: Value of sales | G125: =SUM(F104:F123)
A127: Poultry stock | B127: Inherited stock | C127: End-period stock | D127: Stockbuilding | F127: Sales in (£) | G127: Value of production (£) at sales prices
A128: Hens | B128: =IFERROR(INDEX(Stock!$A$3:$T$94,MATCH('Overton Overview'!$A128,Stock!$A$3:$A$94,0),MATCH('Overton Overview'!B$64,Stock!$A$3:$T$3,0)),0) | C128: =IFERROR(INDEX(Stock!$A$3:$T$94,MATCH('Overton Overview'!$A128,Stock!$A$3:$A$94,0),MATCH('Overton Overview'!C$64,Stock!$A$3:$T$3,0)),0) | D128: =C128-B128 | F128: =IFERROR(INDEX(Stock!$A$3:$T$94,MATCH('Overton Overview'!$A128,Stock!$A$3:$A$94,0),MATCH('Overton Overview'!F$64,Stock!$A$3:$T$3,0)),0) | G128: =Stock!R68
A129: Geese | B129: =IFERROR(INDEX(Stock!$A$3:$T$94,MATCH('Overton Overview'!$A129,Stock!$A$3:$A$94,0),MATCH('Overton Overview'!B$64,Stock!$A$3:$T$3,0)),0) | C129: =IFERROR(INDEX(Stock!$A$3:$T$94,MATCH('Overton Overview'!$A129,Stock!$A$3:$A$94,0),MATCH('Overton Overview'!C$64,Stock!$A$3:$T$3,0)),0) | D129: =C129-B129 | F129: =IFERROR(INDEX(Stock!$A$3:$T$94,MATCH('Overton Overview'!$A129,Stock!$A$3:$A$94,0),MATCH('Overton Overview'!F$64,Stock!$A$3:$T$3,0)),0) | G129: =IFERROR(INDEX(Stock!$A$3:$T$94,MATCH('Overton Overview'!$A129,Stock!$A$3:$A$94,0),MATCH('Overton Overview'!G$64,Stock!$A$3:$T$3,0)),0)
A130: Capons (from chickens) | B130: =IFERROR(INDEX(Stock!$A$3:$T$94,MATCH('Overton Overview'!$A130,Stock!$A$3:$A$94,0),MATCH('Overton Overview'!B$64,Stock!$A$3:$T$3,0)),0) | C130: =IFERROR(INDEX(Stock!$A$3:$T$94,MATCH('Overton Overview'!$A130,Stock!$A$3:$A$94,0),MATCH('Overton Overview'!C$64,Stock!$A$3:$T$3,0)),0) | D130: =C130-B130 | F130: =IFERROR(INDEX(Stock!$A$3:$T$94,MATCH('Overton Overview'!$A130,Stock!$A$3:$A$94,0),MATCH('Overton Overview'!F$64,Stock!$A$3:$T$3,0)),0) | G130: =IFERROR(INDEX(Stock!$A$3:$T$94,MATCH('Overton Overview'!$A130,Stock!$A$3:$A$94,0),MATCH('Overton Overview'!G$64,Stock!$A$3:$T$3,0)),0)
A131: Cocks & hens | B131: =IFERROR(INDEX(Stock!$A$3:$T$94,MATCH('Overton Overview'!$A131,Stock!$A$3:$A$94,0),MATCH('Overton Overview'!B$64,Stock!$A$3:$T$3,0)),0) | C131: =IFERROR(INDEX(Stock!$A$3:$T$94,MATCH('Overton Overview'!$A131,Stock!$A$3:$A$94,0),MATCH('Overton Overview'!C$64,Stock!$A$3:$T$3,0)),0) | D131: =C131-B131 | F131: =IFERROR(INDEX(Stock!$A$3:$T$94,MATCH('Overton Overview'!$A131,Stock!$A$3:$A$94,0),MATCH('Overton Overview'!F$64,Stock!$A$3:$T$3,0)),0) | G131: =IFERROR(INDEX(Stock!$A$3:$T$94,MATCH('Overton Overview'!$A131,Stock!$A$3:$A$94,0),MATCH('Overton Overview'!G$64,Stock!$A$3:$T$3,0)),0)
...

Sheet Overton Receipts
A1: Overton RECEIPTS
B2: £ | C2: s | D2: d | F2: Total in £ | G2: Error | H2: Notes
A4: Arrears
A5: Arrears total | B5: 17 | C5: 4 | D5: 3.5 | F5: =B5+C5/20+D5/240
A6: of which delivered to treasurer of Wolvesey | B6: 17 | C6: 4 | D6: 3.5 | F6: =B6+C6/20+D6/240
A8: Rents of assize
A9: rents of assize Christmas | B9: 6 | C9: 6 | F9: =B9+C9/20+D9/240
A10: Easter | B10: 6 | C10: 11 | D10: 4 | F10: =B10+C10/20+D10/240
A11: Nativity | B11: 6 | C11: 3 | D11: 4 | F11: =B11+C11/20+D11/240
A12: Michaelmas | B12: 11 | C12: 19 | D12: 2.25 | F12: =B12+C12/20+D12/240
A13: Total recorded in accounts | B13: 30 | C13: 19 | D13: 10.25 | F13: =B13+C13/20+D13/240
A14: Rents of assize total | B14: =SUM(B9:B12) | C14: =SUM(C9:C12) | D14: =SUM(D9:D12) | F14: =B14+C14/20+D14/240 | G14: =F14-F13
A16: Quittances
A17: quittance for 1 reeve for the year | C17: 5 | F17: =B17+C17/20+D17/240
A18: 1 bartoner for the year | C18: 3 | F18: =B18+C18/20+D18/240
A19: 2 haywards | C19: 6 | F19: =B19+C19/20+D19/240
A20: 3 ploughmen for the year | C20: 9 | F20: =B20+C20/20+D20/240
A21: 1 ploughman | C21: 1 | D21: 6 | F21: =B21+C21/20+D21/240
A22: 1 smith for the year | C22: 3 | F22: =B22+C22/20+D22/240
A23: 2 shepherds for the year | C23: 6 | F23: =B23+C23/20+D23/240
A24: 1 keeper of hoggs | D24: 6 | F24: =B24+C24/20+D24/240
A25: 1 cowherd | C25: 3 | F25: =B25+C25/20+D25/240
F26: =B26+C26/20+D26/240
A27: Total recorded in accounts | B27: 1 | C27: 17 | F27: =B27+C27/20+D27/240
A28: Quittances total | B28: =SUM(B17:B26) | C28: =SUM(C17:C26) | D28: =SUM(D17:D26) | F28: =B28+C28/20+D28/240 | G28: =F28-F27
A30: Defaults of rent
A31: default of the mill of Lynch | B31: 1 | F31: =B31+C31/20+D31/240
A32: the land of Bascon drawn | C32: 3 | F32: =B32+C32/20+D32/240
A33: land of Strockyng drawn | C33: 3 | F33: =B33+C33/20+D33/240
A34: ... | C34: 3 | F34: =B34+C34/20+D34/240
A35: ... | C35: 1 | F35: =B35+C35/20+D35/240
A36: ... | C36: 1 | D36: 6 | F36: =B36+C36/20+D36/240
A37: ... | C37: 1 | D37: 6 | F37: =B37+C37/20+D37/240
A38: the land of le Cran | C38: 2 | F38: =B38+C38/20+D38/240
A39: ... | C39: 2 | F39: =B39+C39/20+D39/240
A40: land of William | C40: 1 | D40: 6 | F40: =B40+C40/20+D40/240
A41: ... | C41: 2 | F41: =B41+C41/20+D41/240
A42: land of Codeboye | C42: 2 | F42: =B42+C42/20+D42/240
A43: ... | C43: 2 | F43: =B43+C43/20+D43/240
A44: ... | C44: 1 | D44: 10 | F44: =B44+C44/20+D44/240
A45: Nicholas | C45: 1 | F45: =B45+C45/20+D45/240
A46: ... | C46: 2 | F46: =B46+C46/20+D46/240
A47: ... | C47: 1 | F47: =B47+C47/20+D47/240
A48: Thurbun | C48: 1 | D48: 6 | F48: =B48+C48/20+D48/240
A49: Bovette | C49: 2 | F49: =B49+C49/20+D49/240
A50: ... | C50: 3 | F50: =B50+C50/20+D50/240
A51: ... | D51: 6 | F51: =B51+C51/20+D51/240
A52: ... | C52: 1 | F52: =B52+C52/20+D52/240
A53: ... | C53: 2 | F53: =B53+C53/20+D53/240
A54: ... | C54: 3 | D54: 6 | F54: =B54+C54/20+D54/240
A55: land of le Ber | C55: 3 | F55: =B55+C55/20+D55/240
A56: ... | C56: 6 | F56: =B56+C56/20+D56/240
A57: ... | C57: 12 | F57: =B57+C57/20+D57/240
A58: Tadley | C58: 4 | D58: 5 | F58: =B58+C58/20+D58/240
A59: the mill which belonged to Ralph Othyn | B59: 1 | F59: =B59+C59/20+D59/240
A60: Total recorded in accounts | B60: 5 | C60: 12 | D60: 3 | F60: =B60+C60/20+D60/240
A61: Defaults of rent total | B61: =SUM(B31:B59) | C61: =SUM(C31:C59) | D61: =SUM(D31:D59) | F61: =B61+C61/20+D61/240 | G61: =F61-F60
A63: Total of rents remaining | B63: 23 | C63: 10 | D63: 7.25 | F63: =B63+C63/20+D63/240 | H63: not included in receipts
A65: Wax | B65: 0 | C65: 0 | D65: 0
A66: nothing | F66: =B66+C66/20+D66/240
A67: Total recorded in accounts | F67: =B67+C67/20+D67/240 | H67: total not recorded in accounts
A68: Wax total | B68: =SUM(B66) | C68: =SUM(C66) | D68: =SUM(D66) | F68: =B68+C68/20+D68/240 | G68: =F68-F67
A70: Annual recognizances
A71: nothing | F71: =B71+C71/20+D71/240
A72: Total recorded in accounts | F72: =B72+C72/20+D72/240
A73: Annual recognizances total | B73: =SUM(B71:B71) | C73: =SUM(C71:C71) | D73: =SUM(D71:D71) | F73: =B73+C73/20+D73/240 | G73: =F73-F72
A75: Issues of the manor
A76: release from winter-ploughing | B76: 2 | C76: 15 | D76: 9 | F76: =B76+C76/20+D76/240
A77: from pannage of the pigs | B77: 1 | C77: 1 | D77: 5 | F77: =B77+C77/20+D77/240
A78: nothing from foreign pannage for a want of mast | F78: =B78+C78/20+D78/240
A79: from 9 pigs and 11 piglets | C79: 1 | D79: 2.5 | F79: =B79+C79/20+D79/240
A80: foreign pannage | C80: 15 | D80: 9 | F80: =B80+C80/20+D80/240
A81: 1 old feeble and blind cart-horse sold | C81: 6 | F81: =B81+C81/20+D81/240
A82: 2 oxen sold | C82: 19 | D82: 6 | F82: =B82+C82/20+D82/240
A83: 1 bull sold | C83: 10 | F83: =B83+C83/20+D83/240
A84: 2 cows sold | C84: 16 | F84: =B84+C84/20+D84/240
A85: 1 female steer | C85: 7 | F85: =B85+C85/20+D85/240
A86: 11 calves sold | C86: 9 | D86: 10 | F86: =B86+C86/20+D86/240
A87: 29 ewes sold | B87: 1 | C87: 9 | D87: 3 | F87: =B87+C87/20+D87/240
A88: 24 wethers sold | B88: 1 | C88: 12 | D88: 8 | F88: =B88+C88/20+D88/240
A89: 12 hoggs | C89: 6 | F89: =B89+C89/20+D89/240
A90: 2 pigs | C90: 7 | D90: 7 | F90: =B90+C90/20+D90/240
A91: 16 cloves of wool locks sold | C91: 9 | D91: 4 | F91: =B91+C91/20+D91/240
A92: nothing from coarse wool or lambs wool because it was sent to Wolvesey | F92: =B92+C92/20+D92/240
A93: hide of a cow in murrain sold | C93: 1 | D93: 8 | F93: =B93+C93/20+D93/240
A94: hide of 1 yearling in murrain | D94: 10 | F94: =B94+C94/20+D94/240
A95: hides of 3 calves in murrain | D95: 3 | F95: =B95+C95/20+D95/240
A96: skins of 19 ewes sold | C96: 6 | D96: 4 | F96: =B96+C96/20+D96/240
A97: skins sold wholesale of 12 ewes, 4 wethers and 2 hoggs | C97: 1 | D97: 6 | F97: =B97+C97/20+D97/240
A98: skins of 61 lambs | C98: 5 | D98: 1 | F98: =B98+C98/20+D98/240
A99: skins sold wholesale of 14 lambs | D99: 4.5 | F99: =B99+C99/20+D99/240
A100: herbage of the cottars | C100: 7 | D100: 3 | F100: =B100+C100/20+D100/240
A101: winter pasturage | C101: 3 | F101: =B101+C101/20+D101/240
A102: winter pasturage | C102: 2 | F102: =B102+C102/20+D102/240
A103: winter pasturage | C103: 3 | D103: 6 | F103: =B103+C103/20+D103/240
A104: summer pasturage | C104: 6 | F104: =B104+C104/20+D104/240
A105: from the heath at Tadley, no honey | C105: 2 | F105: =B105+C105/20+D105/240
A106: from 1 wey 4 cloves of winter cheese | C106: 10 | D106: 4 | F106: =B106+C106/20+D106/240
A107: 10 weyes of summer cheese | B107: 4 | C107: 10 | F107: =B107+C107/20+D107/240
A108: 1 wey of butter | C108: 9 | F108: =B108+C108/20+D108/240
...

Sheet Overton Expenses
A1: OVERTON EXPENSES
B2: £ | C2: s | D2: d | F2: Total in £ | G2: Error | H2: Notes | J2: fixed investment | K2: demesne investment
A3: Cost of Ploughs
A4: iron and steel | C4: 10 | D4: 6 | F4: =B4+C4/20+D4/240 | J4: =F4 | K4: =J4
A5: 2 plougshares | C5: 1 | D5: 8 | F5: =B5+C5/20+D5/240 | J5: =F5 | K5: =J5
A6: plough feet | C6: 1 | D6: 9 | F6: =B6+C6/20+D6/240 | J6: =F6 | K6: =J6
A7: 2 ploughs made anew | D7: 6 | F7: =B7+C7/20+D7/240 | J7: =F7 | K7: =J7
A8: fitting the same and others with iron tyres | D8: 6.5 | F8: =B8+C8/20+D8/240 | J8: =F8 | K8: =J8
A9: 7 pairs of wheels | D9: 7 | F9: =B9+C9/20+D9/240 | J9: =F9 | K9: =J9
A10: old ploughs fitted with share-beams | D10: 6 | F10: =B10+C10/20+D10/240 | J10: =F10 | K10: =J10
A11: 14 halters made | D11: 3.5 | F11: =B11+C11/20+D11/240 | J11: =F11 | K11: =J11
A12: shoeing 9 plough-horses | C12: 9 | F12: =B12+C12/20+D12/240 | J12: =F12 | K12: =J12
A13: shoeing horses | D13: 11 | F13: =B13+C13/20+D13/240 | J13: =F13 | K13: =J13
A14: in ale and relish for boon-works | C14: 6 | D14: 8 | F14: =B14+C14/20+D14/240
A15: stipend of 3 oxherds | C15: 9 | F15: =B15+C15/20+D15/240
A16: 2 oxen bought | B16: 1 | C16: 2 | D16: 8 | F16: =B16+C16/20+D16/240
A17: wheat bought | C17: 6 | D17: 3 | F17: =B17+C17/20+D17/240
A18: bere bought | B18: 1 | C18: 4 | D18: 8.5 | F18: =B18+C18/20+D18/240
A19: barly bought | B19: 1 | C19: 6 | D19: 1.5 | F19: =B19+C19/20+D19/240
A20: peas bought | C20: 1 | D20: 8 | F20: =B20+C20/20+D20/240
A21: vetches bought | C21: 1 | D21: 10.5 | F21: =B21+C21/20+D21/240
A22: Total recorded in accounts | B22: 6 | C22: 5 | D22: 2.5 | F22: =B22+C22/20+D22/240
A23: Cost of ploughs total | B23: =SUM(B3:B21) | C23: =SUM(C3:C21) | D23: =SUM(D3:D21) | F23: =B23+C23/20+D23/240 | G23: =F23-F22
A25: Purchase of Corn
A26: nothing | F26: =B26+C26/20+D26/240
A27: Total recorded in accounts | F27: =B27+C27/20+D27/240
A28: Purchase of corn total | B28: =SUM(B26) | C28: =SUM(C26) | D28: =SUM(D26) | F28: =B28+C28/20+D28/240 | G28: =F28-F27
A30: Cost of Carts and Wagons
A31: 1 pair of wheels | C31: 2 | F31: =B31+C31/20+D31/240 | J31: =F31 | K31: =J31
A32: fitting an old binding incl. stipend of smith | C32: 3 | D32: 4 | F32: =B32+C32/20+D32/240 | J32: =F32 | K32: =J32
A33: in hooping the felloes of the cart | D33: 3 | F33: =B33+C33/20+D33/240 | J33: =F33 | K33: =J33
A34: clouts, nails, grease and white leather | C34: 1 | D34: 0.5 | F34: =B34+C34/20+D34/240 | J34: =F34 | K34: =J34
A35: fitting the cart with axles | D35: 6 | F35: =B35+C35/20+D35/240 | J35: =F35 | K35: =J35
A36: mending the old cart | D36: 9 | F36: =B36+C36/20+D36/240 | J36: =F36 | K36: =J36
A37: 1 pair of traces bought | D37: 4 | F37: =B37+C37/20+D37/240 | J37: =F37 | K37: =J37
A38: in 1 collar and 1 pair of tie-beams | C38: 1 | F38: =B38+C38/20+D38/240 | J38: =F38 | K38: =J38
A39: in 1 halter bought | D39: 0.5 | F39: =B39+C39/20+D39/240 | J39: =F39 | K39: =J39
A40: in 1 pair of wheels made for dung | D40: 9 | F40: =B40+C40/20+D40/240 | J40: =F40 | K40: =J40
A41: in shoeing 2 cart-horses | C41: 2 | D41: 6 | F41: =B41+C41/20+D41/240 | J41: =F41 | K41: =J41
A42: in 1 cart-horse bought | B42: 1 | F42: =B42+C42/20+D42/240
A43: in stipend of 1 carter | C43: 3 | F43: =B43+C43/20+D43/240
A44: Total recorded in accounts | B44: 1 | C44: 15 | D44: 10 | F44: =B44+C44/20+D44/240
A45: Cost of carts and wagons total | B45: =SUM(B31:B43) | C45: =SUM(C31:C43) | D45: =SUM(D31:D43) | F45: =B45+C45/20+D45/240 | G45: =F45-F44
A48: Cost of Dairy
A49: salt for salting cheese | C49: 3 | D49: 6 | F49: =B49+C49/20+D49/240 | J49: =F49 | K49: =J49
A50: in linen and woolen cloth | D50: 8 | F50: =B50+C50/20+D50/240 | J50: =F50 | K50: =J50
A51: pots and pans | D51: 6 | F51: =B51+C51/20+D51/240 | J51: =F51 | K51: =J51
A52: press | D52: 6 | F52: =B52+C52/20+D52/240 | J52: =F52 | K52: =J52
A53: mending utensils | D53: 4 | F53: =B53+C53/20+D53/240 | J53: =F53 | K53: =J53
A54: stipend of dairymaid | C54: 2 | F54: =B54+C54/20+D54/240
A55: stipend keeper of hoggs and lambs | C55: 2 | F55: =B55+C55/20+D55/240
A56: 2 sacks bough | C56: 1 | D56: 5 | F56: =B56+C56/20+D56/240 | J56: =F56 | K56: =J56
A57: Total recorded in accounts | C57: 11 | D57: 2 | F57: =B57+C57/20+D57/240
A58: Cost of dairy total | B58: =SUM(B49:B56) | C58: =SUM(C49:C56) | D58: =SUM(D49:D56) | F58: =B58+C58/20+D58/240 | G58: =F58-F57
A61: Cost of mills
A62: roofing | D62: 6 | F62: =B62+C62/20+D62/240 | J62: no mills in investment
A63: repairing broken spindles with iron | D63: 4 | F63: =B63+C63/20+D63/240
A64: sharpening and steeling bills | D64: 3.5 | F64: =B64+C64/20+D64/240
A65: stopping and drawing the water up to renew sluice | D65: 10 | F65: =B65+C65/20+D65/240
A66: timber for new sluice | C66: 3 | F66: =B66+C66/20+D66/240
A67: roofing the buildings of the town mill | C67: 1 | D67: 4 | F67: =B67+C67/20+D67/240
A68: hooping the driving-shaft and wheels | C68: 1 | D68: 3 | F68: =B68+C68/20+D68/240
A69: steeling and sharpening bills | D69: 6 | F69: =B69+C69/20+D69/240
A70: stipend of 1 miller for the year | C70: 3 | F70: =B70+C70/20+D70/240
A71: Total recorded in accounts | C71: =4+6 | D71: =11.5+1 | F71: =B71+C71/20+D71/240
A72: Cost of mills total | B72: =SUM(B62:B70) | C72: =SUM(C62:C70) | D72: =SUM(D62:D70) | F72: =B72+C72/20+D72/240 | G72: =F72-F71
A75: Purchase of Stock
F76: =B76+C76/20+D76/240
F77: =B77+C77/20+D77/240
F78: =B78+C78/20+D78/240
A79: Total recorded in accounts | F79: =B79+C79/20+D79/240
A80: Purchase of stock total | B80: =SUM(B76:B78) | C80: =SUM(C76:C78) | D80: =SUM(D76:D78) | F80: =B80+C80/20+D80/240 | G80: =F80-F79
A82: Sheepcote and Wool
A83: 24 ells of canvas bought for putting the wool in | C83: 7 | D83: 3 | F83: =B83+C83/20+D83/240 | J83: =F83 | K83: =J83
A84: making sacks and packing said wool | C84: 1 | F84: =B84+C84/20+D84/240 | J84: =F84 | K84: =J84
A85: re-roofing sheepcotes | C85: 2 | D85: 6 | F85: =B85+C85/20+D85/240 | J85: =F85 | K85: =J85
A86: carpenter mending the sheepcote | D86: 6 | F86: =B86+C86/20+D86/240 | J86: =F86 | K86: =J86
A87: roofing one part of the sheepcote | C87: 3 | D87: 2 | F87: =B87+C87/20+D87/240 | J87: =F87 | K87: =J87
A88: grease, copperas, vinegar and tar | B88: 1 | C88: 16 | D88: 9 | F88: =B88+C88/20+D88/240 | J88: =F88 | K88: =J88
A89: hurdles made | C89: 2 | F89: =B89+C89/20+D89/240 | J89: =F89 | K89: =J89
A90: wattling hurdles | C90: 1 | D90: 10 | F90: =B90+C90/20+D90/240 | J90: =F90 | K90: =J90
A91: in 39 ewes bought | B91: 1 | C91: 19 | F91: =B91+C91/20+D91/240
A92: 1 ram bought | C92: 1 | F92: =B92+C92/20+D92/240
A93: carpenter rebuilding anew 1 sheepcote | B93: 1 | D93: 6 | F93: =B93+C93/20+D93/240 | J93: =F93 | K93: =J93
A94: roofing the same | C94: 5 | D94: 2 | F94: =B94+C94/20+D94/240 | J94: =F94 | K94: =J94
A95: in 4000 nails bought for laths | C95: 3 | F95: =B95+C95/20+D95/240 | J95: =F95 | K95: =J95
A96: hooks and hinges | C96: 1 | D96: 8 | F96: =B96+C96/20+D96/240 | J96: =F96 | K96: =J96
A97: iron for the door | D97: 5 | F97: =B97+C97/20+D97/240 | J97: =F97 | K97: =J97
A98: plastering the walls | C98: 5 | F98: =B98+C98/20+D98/240 | J98: =F98 | K98: =J98
A99: collecting stubble for roofing | C99: 2 | D99: 7 | F99: =B99+C99/20+D99/240 | J99: =F99 | K99: =J99
A100: hay bought | C100: 12 | F100: =B100+C100/20+D100/240
A101: Total recorded in accounts | B101: 6 | C101: =17+8 | D101: 1 | F101: =B101+C101/20+D101/240
A102: Sheepcote total | B102: =SUM(B83:B100) | C102: =SUM(C83:C100) | D102: =SUM(D83:D101) | F102: =B102+C102/20+D102/240 | G102: =F102-F101
A105: Cost of Buildings
A106: 1200 new shingles on the hall + nails | C106: 4 | D106: 9.5 | F106: =B106+C106/20+D106/240 | J106: =F106
A107: re-roofing the wheat and oat barns | C107: 3 | D107: 9 | F107: =B107+C107/20+D107/240 | J107: =F107 | K107: =J107
A108: roofing and mending the bake house | C108: 1 | D108: 6 | F108: =B108+C108/20+D108/240 | J108: =F108 | K108: =J108
A109: collecting stubble for the same | C109: 5 | D109: 10 | F109: =B109+C109/20+D109/240 | J109: =F109 | K109: =J109
A110: re-roofing the dovecot and kitchen, covering the wall between hall and dairy | C110: 1 | D110: 5 | F110: =B110+C110/20+D110/240 | J110: =F110 | K110: =J110
A111: 4,000 tiles for the same | C111: 4 | D111: 4 | F111: =B111+C111/20+D111/240 | J111: =F111 | K111: =J111
...

Sheet Issues of the Grange
B1: The issue of the grange account gives the total "yield" at the top of each heading in curly brackets, measurements used: fold, qrs, bus
B2: In "Issues of the grange" (p.96ff) | I2: In "Sale of Corn" (p.93) | T2: Value of Total Production
A3: Gross output | B3: Quantity | D3: Additional bought-in | F3: from previous year | H3: Quantity | I3: Quantity noted as sold | L3: Difference Produced vs. Sold | M3: Price 1 | N3: Quantity 1 | O3: Price 2 | P3: Quantity 2 | Q3: Price 3 | R3: Quantity 3 | S3: Unit price | T3: Value
B4: qrs | C4: bus | D4: qrs | E4: bus | F4: qrs | G4: bus | H4: qrs | I4: qrs | J4: bus | K4: qrs | M4: £ | N4: qrs | O4: £ | P4: qrs | Q4: £ | R4: qrs | S4: £ per qr | T4: £
A5: Wheat | B5: 64 | C5: 7 | D5: 1 | E5: 2 | H5: =B5+D5+F5+C5/8+E5/8+G5/8 | I5: 50.5 | K5: =I5+J5/8 | L5: =H5-K5 | M5: =5/20+6/240 | N5: 1 | O5: =5/20+4/240 | P5: 1 | Q5: =6/20 | R5: 1 | S5: =IFERROR((M5+O5)/(N5+P5),0) | T5: =S5*H5
A6: Curall | B6: 2 | C6: 2 | H6: =B6+D6+F6+C6/8+E6/8+G6/8 | I6: 2 | J6: 2 | K6: =I6+J6/8 | L6: =H6-K6 | M6: =4/20 | N6: 1 | S6: =IFERROR((M6+O6)/(N6+P6),0) | T6: =S6*H6
A7: Bere | B7: =83+2+1+2 | C7: 3 | D7: 12 | E7: 2 | F7: 13.5 | H7: =B7+D7+F7+C7/8+E7/8+G7/8 | I7: 48 | J7: 2 | K7: =I7+J7/8 | L7: =H7-K7 | M7: =3/20 | N7: 1 | S7: =IFERROR((M7+O7)/(N7+P7),0) | T7: =S7*H7
A8: Barley | B8: 81.5 | D8: 7 | E8: 1 | H8: =B8+D8+F8+C8/8+E8/8+G8/8 | I8: 75 | J8: 5 | K8: =I8+J8/8 | L8: =H8-K8 | M8: =3/20 | N8: 1 | O8: =4/20 | P8: 1 | S8: =IFERROR((M8+O8)/(N8+P8),0) | T8: =S8*H8
A9: Oats | B9: 144 | C9: 3.5 | H9: =B9+D9+F9+C9/8+E9/8+G9/8 | I9: 37 | K9: =I9+J9/8 | L9: =H9-K9 | M9: =2/20 | N9: 1 | O9: =2/20+6/240 | P9: 1 | S9: =IFERROR((M9+O9)/(N9+P9),0) | T9: =S9*H9
A10: Peas | B10: 1 | C10: 5 | H10: =B10+D10+F10+C10/8+E10/8+G10/8 | I10: 1 | J10: 1 | K10: =I10+J10/8 | L10: =H10-K10 | M10: =3/20 | N10: 1 | S10: =IFERROR((M10+O10)/(N10+P10),0) | T10: =S10*H10
A11: Vetches | B11: 3 | C11: 3 | D11: 1 | E11: 1 | F11: 1 | H11: =B11+D11+F11+C11/8+E11/8+G11/8 | I11: 4 | J11: 3 | K11: =I11+J11/8 | L11: =H11-K11 | M11: =1/20 | N11: 1 | S11: =IFERROR((M11+O11)/(N11+P11),0) | T11: =S11*H11
A13: Total Production | H13: =SUM(H5:H11) | T13: =SUM(T5:T11) | U13: Production value is significantly more, as much less was sold than what was produced
A14: Sales of corn (as recorded in accounts) | H14: =SUM(K5:K11) | T14: =41+9/20+5.5/240
A17: Net output | B17: Gross output | C17: Seed | H17: tithe | I17: to manorial servants & livestock | L17: Output net of tithe & seed & liveries to manorial servants | M17: in stock from last year | N17: Price | O17: Value of net output | P17: Value of sales (in "Sale of Corn")
B18: qrs | C18: qrs | D18: bus | E18: qrs | H18: qrs | I18: qrs | J18: bus | K18: qrs | L18: qrs | M18: qrs | N18: £ per qr | O18: £ | P18: £
A19: Net wheat | B19: =B5 | C19: 11 | D19: 2 | E19: =C19+D19/8 | I19: =3+4 | K19: =I19+J19/8 | L19: =B19-(E19+H19+K19) | N19: =S5 | O19: =N19*L19 | P19: =S5*K5
A20: Net curall | B20: =B6 | E20: =C20+D20/8 | K20: =I20+J20/8 | L20: =B20-(E20+H20+K20) | N20: =S6 | O20: =N20*L20 | P20: =S6*K6
A21: Net barley | B21: =B8 | C21: 20 | D21: 1 | E21: =C21+D21/8 | I21: =26+4+4+1.5+3+2+1+2 | J21: =7 | K21: =I21+J21/8 | L21: =B21-(E21+H21+K21) | N21: =S8 | O21: =N21*L21 | P21: =S8*K8
A22: Net oats | B22: =B9 | C22: 65 | E22: =C22+D22/8 | I22: =15+12+10+1+4 | J22: =2+1.5 | K22: =I22+J22/8 | L22: =B22-(E22+H22+K22) | N22: =S9 | O22: =N22*L22 | P22: =S9*K9
A23: Net peas | B23: =B10 | D23: 4 | E23: =C23+D23/8 | K23: =I23+J23/8 | L23: =B23-(E23+H23+K23) | N23: =S10 | O23: =N23*L23 | P23: =S10*K10
A24: Net vetches | B24: =B11 | C24: 1 | D24: 1 | E24: =C24+D24/8 | K24: =I24+J24/8 | L24: =B24-(E24+H24+K24) | N24: =S11 | O24: =N24*L24 | P24: =S11*K11
A25: Total | B25: =SUM(B19:B24) | E25: =SUM(E19:E24) | L25: =SUM(L19:L24) | O25: =SUM(O19:O24) | P25: =SUM(P19:P24)

Sheet Issues of the Mill
A1: OVERTON MILL ACCOUNT
B2: In "Issue of the Mill" (p.98) | F2: In "Mills" (p.95) | P2: Value of Total Production
B3: Quantity | D3: Quantity (produced) | E3: Quantity (produced) | F3: Prices per qr | H3: Prices per bus | J3: Quantities (noted as sold) | M3: Difference produced vs. sold | N3: Price | O3: Price | P3: Value avg price | Q3: Value avg price (busel) | R3: Value of production
B4: qrs | C4: bus | D4: qrs | E4: bus | F4: s | G4: d | H4: s | I4: d | J4: qrs | K4: bus | L4: qrs | M4: qrs | N4: £ per qr | O4: £ per bus | P4: £
A5: Wheat - Town Mill | B5: 3 | D5: =B5+C5/8 | F5: 5 | G5: 4 | J5: 3 | L5: =J5+K5/8 | M5: =D5-L5 | N5: =F5/20+G5/240 | P5: =N5 | R5: =P5*D5
A6: Maslin - Town Mill | B6: 4 | C6: 5 | D6: =B6+C6/8 | E6: =C6+B6*8 | I6: 6 | K6: 5 | L6: =J6+K6/8 | M6: =D6-L6 | O6: =H6/20+I6/240 | Q6: =O6 | R6: =Q6*E6
A7: Coarse-ground corn - Town Mill | B7: 5 | C7: 7 | D7: =B7+C7/8 | F7: 6 | J7: 5 | K7: 7 | L7: =J7+K7/8 | M7: =D7-L7 | N7: =F7/20+G7/240 | P7: =N7 | R7: =P7*D7
A8: Malt - Town Hill | B8: 24 | C8: 1 | D8: =B8+C8/8 | F8: 2 | G8: 4 | J8: 24 | K8: 1 | L8: =J8+K8/8 | M8: =D8-L8 | N8: =F8/20+G8/240 | P8: =N8 | R8: =P8*D8
A9: Mills of Lynch & Subhurn | B9: nothing because at farm
A11: Total production value - average | R11: =SUM(R5:R8)
A12: Sale of mill corn (as noted in Mill Account) | R12: =5+10/20+0.5/240

Sheet Stock
A1: EAST KNOYLE STOCK ACCOUNT
A3: Livestock | B3: Inherited stock | C3: Bought | D3: Produced | E3: strays | F3: herbage | G3: sold | H3: in murrain | I3: accounted for elsewhere | J3: End-period stock | K3: cross-check | L3: price 1 | M3: units 1 | N3: price 2 | O3: units 2 | P3: Weight (weys) | Q3: Unit price (£) | R3: Value of production (£) at sales prices | S3: Sales in (£) | T3: Details
A4: Cart-horses | B4: 2 | C4: 1 | G4: 1 | J4: 2 | K4: =B4+C4+D4+E4-F4-G4-H4-I4 | L4: =S4/G4 | Q4: =L4 | R4: =D4*Q4 | S4: ='Overton Receipts'!F81
A5: Mares | K5: =B5+C5+D5+E5-F5-G5-H5-I5 | Q5: =IFERROR((L5+N5)/(M5+O5),"") | S5: =IFERROR(Q5*G5,"")
A6: Plough horses | B6: 9 | E6: 1 | J6: 10 | K6: =B6+C6+D6+E6-F6-G6-H6-I6 | Q6: =IFERROR((L6+N6)/(M6+O6),"") | S6: =IFERROR(Q6*G6,"")
A7: Colts (2 years) | K7: =B7+C7+D7+E7-F7-G7-H7-I7 | Q7: =IFERROR((L7+N7)/(M7+O7),"") | S7: =IFERROR(Q7*G7,"")
A8: Colts (2 years) | K8: =B8+C8+D8+E8-F8-G8-H8-I8 | Q8: =IFERROR((L8+N8)/(M8+O8),"") | S8: =IFERROR(Q8*G8,"")
A9: Colts (1 year) | K9: =B9+C9+D9+E9-F9-G9-H9-I9 | Q9: =IFERROR((L9+N9)/(M9+O9),"") | S9: =IFERROR(Q9*G9,"")
A10: Foals | K10: =B10+C10+D10+E10-F10-G10-H10-I10 | Q10: =IFERROR((L10+N10)/(M10+O10),"") | S10: =IFERROR(Q10*G10,"")
A11: Oxen | B11: 20 | C11: 2 | G11: 2 | J11: 20 | K11: =B11+C11+D11+E11-F11-G11-H11-I11 | L11: =S11/G11 | Q11: =L11 | R11: =D11*Q11 | S11: ='Overton Receipts'!F82
A12: Bulls | B12: 1 | D12: 1 | G12: 1 | J12: 1 | K12: =B12+C12+D12+E12-F12-G12-H12-I12 | L12: =S12/G12 | Q12: =L12 | R12: =D12*Q12 | S12: ='Overton Receipts'!F83
A13: Cows | B13: 25 | D13: 3 | E13: 1 | G13: 2 | H13: 1 | J13: 26 | K13: =B13+C13+D13+E13-F13-G13-H13-I13 | L13: =S13/G13 | Q13: =L13 | R13: =D13*Q13 | S13: ='Overton Receipts'!F84
A14: Steers | B14: 5 | G14: 1 | I14: 4 | J14: 0 | K14: =B14+C14+D14+E14-F14-G14-H14-I14 | L14: =S14/G14 | Q14: =L14 | R14: =D14*Q14 | S14: ='Overton Receipts'!F85
A15: Bullocks | B15: 9 | J15: 9 | K15: =B15+C15+D15+E15-F15-G15-H15-I15
A16: Yearlings | B16: 10 | H16: 1 | J16: 9 | K16: =B16+C16+D16+E16-F16-G16-H16-I16
A17: Calves | B17: 25 | G17: 11 | H17: 3 | I17: 2 | J17: 9 | K17: =B17+C17+D17+E17-F17-G17-H17-I17 | L17: =S17/G17 | Q17: =L17 | R17: =D17*Q17 | S17: ='Overton Receipts'!F86
A18: Wethers | K18: =B18+C18+D18+E18-F18-G18-H18-I18
A19: Rams | B19: 20 | C19: 1 | D19: 7 | I19: 11 | J19: 17 | K19: =B19+C19+D19+E19-F19-G19-H19-I19
A20: Ewes | B20: 495 | C20: 106 | D20: 102 | G20: 39 | H20: =7+14+12 | J20: 631 | K20: =B20+C20+D20+E20-F20-G20-H20-I20 | L20: =S20/G20 | Q20: =L20 | R20: =D20*Q20 | S20: ='Overton Receipts'!F87 | T20: issues of the manor only records sale of 29 ewes
A21: Hoggs | B21: 234 | G21: 12 | H21: 12 | I21: =102+7+101 | J21: 0 | K21: =B21+C21+D21+E21-F21-G21-H21-I21 | L21: =S21/G21 | Q21: =L21 | R21: =D21*Q21 | S21: ='Overton Receipts'!F89
A22: Lambs | B22: 401 | H22: =61+12+14 | I22: =34 | J22: 280 | K22: =B22+C22+D22+E22-F22-G22-H22-I22
A23: Boars | K23: =B23+C23+D23+E23-F23-G23-H23-I23
A24: Sows | K24: =B24+C24+D24+E24-F24-G24-H24-I24
A25: Pigs | C25: 2 | G25: 2 | K25: =B25+C25+D25+E25-F25-G25-H25-I25 | L25: =S25/G25 | Q25: =L25 | R25: =D25*Q25 | S25: ='Overton Receipts'!F90
A26: Hoggets | K26: =B26+C26+D26+E26-F26-G26-H26-I26 | Q26: =IFERROR((L26+N26)/(M26+O26),"") | R26: =IFERROR(D26*Q26,"") | S26: =IFERROR(Q26*G26,"")
A27: Piglets | K27: =B27+C27+D27+E27-F27-G27-H27-I27 | Q27: =IFERROR((L27+N27)/(M27+O27),"") | R27: =IFERROR(D27*Q27,"") | S27: =IFERROR(Q27*G27,"")
A28: Swans | K28: =B28+C28+D28+E28-F28-G28-H28-I28 | Q28: =IFERROR((L28+N28)/(M28+O28),"") | R28: =IFERROR(D28*Q28,"") | S28: =IFERROR(Q28*G28,"")
A29: Peacocks | B29: 10 | D29: 2 | H29: 1 | J29: 11 | K29: =B29+C29+D29+E29-F29-G29-H29-I29 | Q29: =IFERROR((L29+N29)/(M29+O29),"") | R29: =IFERROR(D29*Q29,"") | S29: =IFERROR(Q29*G29,"")
A30: Total | S30: =SUM(S4:S29)
A33: Wool | K33: =B33+C33+D33+E33-F33-G33-H33-I33 | Q33: =IFERROR((L33+N33)/(M33+O33),"") | R33: =IFERROR(D33*Q33,"") | S33: =IFERROR(Q33*G33,"")
A34: Fleeces | D34: 1013 | I34: =101+2+910 | K34: =B34+C34+D34+E34-F34-G34-H34-I34 | Q34: 0.02 | R34: =IFERROR(D34*Q34,"") | S34: =IFERROR(Q34*G34,"")
A35: Coarse wool | K35: =B35+C35+D35+E35-F35-G35-H35-I35 | Q35: =IFERROR((L35+N35)/(M35+O35),"") | R35: =IFERROR(D35*Q35,"") | S35: =IFERROR(Q35*G35,"")
A36: Lamb's wool | D36: 294 | I36: 294 | K36: =B36+C36+D36+E36-F36-G36-H36-I36 | Q36: 0.01 | R36: =IFERROR(D36*Q36,"") | S36: =IFERROR(Q36*G36,"")
A37: Wool locks | K37: =B37+C37+D37+E37-F37-G37-H37-I37 | Q37: =IFERROR((L37+N37)/(M37+O37),"") | R37: =IFERROR(D37*Q37,"") | S37: ='Overton Receipts'!F91 | T37: in issues of manor woollocks sold
A38: Wool sold at shearing | K38: =B38+C38+D38+E38-F38-G38-H38-I38 | Q38: =IFERROR((L38+N38)/(M38+O38),"") | R38: =IFERROR(D38*Q38,"") | S38: =IFERROR(Q38*G38,"")
A39: Total | R39: =SUM(R34:R38)+S37
A42: Hides | Q42: =IFERROR((L42+N42)/(M42+O42),"") | R42: =IFERROR(D42*Q42,"") | S42: =IFERROR(Q42*G42,"")
A43: Ox hides | K43: =B43+C43+D43+E43-F43-G43-H43-I43 | Q43: =IFERROR((L43+N43)/(M43+O43),"") | R43: =IFERROR(D43*Q43,"") | S43: =IFERROR(Q43*G43,"")
A44: Cow hides | K44: =B44+C44+D44+E44-F44-G44-H44-I44 | Q44: =IFERROR((L44+N44)/(M44+O44),"") | R44: =IFERROR(D44*Q44,"") | S44: =IFERROR(Q44*G44,"")
A45: Mare hides | K45: =B45+C45+D45+E45-F45-G45-H45-I45 | Q45: =IFERROR((L45+N45)/(M45+O45),"") | R45: =IFERROR(D45*Q45,"") | S45: =IFERROR(Q45*G45,"")
A46: Steer hides | K46: =B46+C46+D46+E46-F46-G46-H46-I46 | Q46: =IFERROR((L46+N46)/(M46+O46),"") | R46: =IFERROR(D46*Q46,"") | S46: =IFERROR(Q46*G46,"")
A47: Yearling Calf hides | K47: =B47+C47+D47+E47-F47-G47-H47-I47 | Q47: =IFERROR((L47+N47)/(M47+O47),"") | R47: =IFERROR(D47*Q47,"") | S47: =IFERROR(Q47*G47,"")
A48: Calf hides | K48: =B48+C48+D48+E48-F48-G48-H48-I48 | Q48: =IFERROR((L48+N48)/(M48+O48),"") | R48: =IFERROR(D48*Q48,"") | S48: =IFERROR(Q48*G48,"")
A49: Pig hides | K49: =B49+C49+D49+E49-F49-G49-H49-I49 | Q49: =IFERROR((L49+N49)/(M49+O49),"") | R49: =IFERROR(D49*Q49,"") | S49: =IFERROR(Q49*G49,"")
A50: Wether woolskins | D50: 6 | K50: =B50+C50+D50+E50-F50-G50-H50-I50 | Q50: =IFERROR((L50+N50)/(M50+O50),"") | R50: =IFERROR(D50*Q50,"")
A51: Ram woolskins | K51: =B51+C51+D51+E51-F51-G51-H51-I51 | Q51: =IFERROR((L51+N51)/(M51+O51),"") | R51: =IFERROR(D51*Q51,"") | S51: =IFERROR(Q51*G51,"")
A52: Ewe woolskins | D52: 21 | K52: =B52+C52+D52+E52-F52-G52-H52-I52 | Q52: =S52/D52 | R52: =IFERROR(D52*Q52,"") | S52: ='Overton Receipts'!F96
A53: Hogg woolskins | D53: 10 | K53: =B53+C53+D53+E53-F53-G53-H53-I53 | Q53: =IFERROR((L53+N53)/(M53+O53),"") | R53: =IFERROR(D53*Q53,"") | S53: =IFERROR(Q53*G53,"")
A54: Woolskins (total) | D54: 37 | G54: 34 | I54: 3 | J54: 0 | K54: =B54+C54+D54+E54-F54-G54-H54-I54 | Q54: =IFERROR((L54+N54)/(M54+O54),"") | R54: =IFERROR(D54*Q54,"") | S54: =SUM(S43:S53)
A55: Wether bareskins | D55: 4 | Q55: =IFERROR((L55+N55)/(M55+O55),"") | R55: =IFERROR(D55*Q55,"") | S55: =IFERROR(Q55*G55,"")
A56: Ram bareskins | Q56: =IFERROR((L56+N56)/(M56+O56),"") | R56: =IFERROR(D56*Q56,"") | S56: =IFERROR(Q56*G56,"")
A57: Ewe bareskins | D57: 12 | Q57: =IFERROR((L57+N57)/(M57+O57),"") | R57: =IFERROR(D57*Q57,"") | S57: =IFERROR(Q57*G57,"")
A58: Hogg bareskins | Q58: =IFERROR((L58+N58)/(M58+O58),"") | R58: =IFERROR(D58*Q58,"") | S58: =IFERROR(Q58*G58,"")
A59: Bareskins (total) | D59: 16 | G59: 16 | J59: 0 | K59: =B59+C59+D59+E59-F59-G59-H59-I59 | Q59: =S59/G59 | R59: =IFERROR(D59*Q59,"") | S59: ='Overton Receipts'!F97
A60: ewes
A61: wethers
A62: Lambskins | B62: =61+27 | G62: =55+27 | I62: 6 | K62: =B62+C62+D62+E62-F62-G62-H62-I62 | Q62: =IFERROR((L62+N62)/(M62+O62),"") | R62: =S62/G62 | S62: ='Overton Receipts'!F98+'Overton Receipts'!F99
A63: Rotted skins | Q63: =IFERROR((L63+N63)/(M63+O63),"") | R63: =IFERROR(D63*Q63,"") | S63: =IFERROR(Q63*G63,"")
A64: Shorn skins | Q64: =IFERROR((L64+N64)/(M64+O64),"") | R64: =IFERROR(D64*Q64,"") | S64: =IFERROR(Q64*G64,"")
A65: Total | Q65: =IFERROR((L65+N65)/(M65+O65),"") | R65: =IFERROR(D65*Q65,"") | S65: =S54+S59+S62
Q66: =IFERROR((L66+N66)/(M66+O66),"") | R66: =IFERROR(D66*Q66,"") | S66: =IFERROR(Q66*G66,"")
A67: Poultry stock | Q67: =IFERROR((L67+N67)/(M67+O67),"") | R67: =IFERROR(D67*Q67,"") | S67: =IFERROR(Q67*G67,"")
A68: Hens | B68: 88 | G68: 72 | K68: =B68+C68+D68+E68-F68-G68-H68-I68 | Q68: =IFERROR((L68+N68)/(M68+O68),"") | R68: =S68/G68 | S68: ='Overton Receipts'!F109
A69: Geese | Q69: =IFERROR((L69+N69)/(M69+O69),"") | R69: =IFERROR(D69*Q69,"") | S69: =IFERROR(Q69*G69,"")
A70: Capons (from chickens) | Q70: =IFERROR((L70+N70)/(M70+O70),"") | R70: =IFERROR(D70*Q70,"") | S70: =IFERROR(Q70*G70,"")
A71: Cocks & hens | Q71: =IFERROR((L71+N71)/(M71+O71),"") | R71: =IFERROR(D71*Q71,"") | S71: =IFERROR(Q71*G71,"")
A72: Total | Q72: =IFERROR((L72+N72)/(M72+O72),"") | R72: =IFERROR(D72*Q72,"") | S72: =SUM(S67:S71)
Q73: =IFERROR((L73+N73)/(M73+O73),"") | R73: =IFERROR(D73*Q73,"") | S73: =IFERROR(Q73*G73,"")
A74: Poultry production | Q74: =IFERROR((L74+N74)/(M74+O74),"") | R74: =IFERROR(D74*Q74,"") | S74: =IFERROR(Q74*G74,"")
A75: Eggs | Q75: =IFERROR((L75+N75)/(M75+O75),"") | R75: =IFERROR(D75*Q75,"") | S75: =IFERROR(Q75*G75,"")
A76: Cocks & hens from churchscot of customary tenants | Q76: =IFERROR((L76+N76)/(M76+O76),"") | R76: =IFERROR(D76*Q76,"") | S76: =IFERROR(Q76*G76,"")
Q77: =IFERROR((L77+N77)/(M77+O77),"") | R77: =IFERROR(D77*Q77,"") | S77: =IFERROR(Q77*G77,"")
Q78: =IFERROR((L78+N78)/(M78+O78),"") | R78: =IFERROR(D78*Q78,"") | S78: =IFERROR(Q78*G78,"")
A79: Meat | Q79: =IFERROR((L79+N79)/(M79+O79),"") | R79: =IFERROR(D79*Q79,"") | S79: =IFERROR(Q79*G79,"")
A80: Beef | Q80: =IFERROR((L80+N80)/(M80+O80),"") | R80: =IFERROR(D80*Q80,"") | S80: =IFERROR(Q80*G80,"")
A81: Mutton | Q81: =IFERROR((L81+N81)/(M81+O81),"") | R81: =IFERROR(D81*Q81,"") | S81: =IFERROR(Q81*G81,"")
A82: Pork | Q82: =IFERROR((L82+N82)/(M82+O82),"") | R82: =IFERROR(D82*Q82,"") | S82: =IFERROR(Q82*G82,"")
Q83: =IFERROR((L83+N83)/(M83+O83),"") | R83: =IFERROR(D83*Q83,"") | S83: =IFERROR(Q83*G83,"")
Q84: =IFERROR((L84+N84)/(M84+O84),"") | R84: =IFERROR(D84*Q84,"") | S84: =IFERROR(Q84*G84,"")
A85: Cheese | Q85: =IFERROR((L85+N85)/(M85+O85),"") | R85: =IFERROR(D85*Q85,"") | S85: =IFERROR(Q85*G85,"")
A86: Winter cheese | D86: =25+4 | G86: 29 | J86: 0 | K86: =B86+C86+D86+E86-F86-G86-H86-I86 | P86: =1+6/25 | Q86: =S86/G86 | R86: =IFERROR(D86*Q86,"") | S86: ='Overton Receipts'!F106 | T86: all sold
A87: Summer cheese | D87: 173 | G87: 153 | J87: 0 | K87: =B87+C87+D87+E87-F87-G87-H87-I87 | P87: =(10/153)*173 | Q87: =S87/G87 | R87: =IFERROR(D87*Q87,"") | S87: ='Overton Receipts'!F107 | T87: 153 cheeses sold, 10 weys
A88: Total | Q88: =IFERROR((L88+N88)/(M88+O88),"") | R88: =IFERROR(D88*Q88,"") | S88: =SUM(S86:S87)
Q89: =IFERROR((L89+N89)/(M89+O89),"") | R89: =IFERROR(D89*Q89,"") | S89: =IFERROR(Q89*G89,"")
A90: Butter | Q90: =IFERROR((L90+N90)/(M90+O90),"") | R90: =IFERROR(D90*Q90,"") | S90: =IFERROR(Q90*G90,"")
A91: 1 wey of butter | D91: 25 | P91: 1 | Q91: =S91/D91 | R91: =IFERROR(D91*Q91,"") | S91: ='Overton Receipts'!F108 | T91: all sold
A92: Total | S92: =S91
Q93: =IFERROR((L93+N93)/(M93+O93),"") | R93: =IFERROR(D93*Q93,"") | S93: =IFERROR(Q93*G93,"")
A94: Cider | Q94: =IFERROR((L94+N94)/(M94+O94),"") | R94: =IFERROR(D94*Q94,"") | S94: =IFERROR(Q94*G94,"")
A95: nothing | Q95: =IFERROR((L95+N95)/(M95+O95),"") | R95: =IFERROR(D95*Q95,"") | S95: =IFERROR(Q95*G95,"")
Q96: =IFERROR((L96+N96)/(M96+O96),"") | R96: =IFERROR(D96*Q96,"") | S96: =IFERROR(Q96*G96,"")
Q97: =IFERROR((L97+N97)/(M97+O97),"") | R97: =IFERROR(D97*Q97,"") | S97: =IFERROR(Q97*G97,"")
Q98: =IFERROR((L98+N98)/(M98+O98),"") | R98: =IFERROR(D98*Q98,"") | S98: =IFERROR(Q98*G98,"")
Q99: =IFERROR((L99+N99)/(M99+O99),"") | R99: =IFERROR(D99*Q99,"") | S99: =IFERROR(Q99*G99,"")

Sheet Assumptions
A1: ASSUMPTIONS
B3: Weights | C3: Value (in lbs) | D3: Value (in cloves) | E3: Value (in weys) | F3: Value (in stone)
B4: Lbs | C4: 1 | D4: =C4/C5 | E4: =C4/C6 | F4: =C4/C7
B5: Cloves | C5: 7 | D5: 1 | E5: =C5/C6 | F5: =C7/C5
B6: Wey | C6: 175 | D6: =C6/C5 | E6: =C6/C6 | F6: =C7/C6
B7: Stone | C7: =175/14 | D7: =C5/C7 | E7: =C7/C6 | F7: 1
