Workbook

Sheet Upton Overview - Completed
A1: UPTON OVERVIEW - COMPLETED | B1: Total in £ | C1: Error | D1: Note
A2: CASH ACCOUNT
A3: RECEIPTS
A4: Arrears total
A5: Rents of assize total
A6: Quittances total
A7: Defaults of rent total
A8: Defaults of rent through the pestilence total
A9: Cotlands defaults total
A10: Cotlands total
A11: Total of quittances and defaults of rent total
A12: Total of rents remaining clear total
A13: Farms total
... A22: Farm of the demesne land total
A23: Total of all receipts (calculated here) | B23: =SUM(B5:B22)
A24: Total of all receipts (calculated here) incl arrears | B24: =SUM(B4:B22)
A25: Total recorded in the accounts excl. arrears | C25: =B23-B25
A26: Total recorded in the accounts incl. arrears | B26: =B25+B4
A29: EXPENSES
A30: Cost of ploughs total
A31: Purchase of corn total
A32: Cost of carts and wagons total
A33: Cost of dairy total
A34: Purchase of stock total
A35: Sheepcote total
A36: Cost of buildings total
A37: Threshing total
A38: Barley expenses
A39: Expenses of the harvest total
A40: Necessary expenses
... A47: Total Demesne fixed investment
A49: Owed by the reeve | B49: =B23-B45
A50: From accounts | B50: 5.1541667
A52: Allowances
A53: Cash deliveries
A54: Sum of the above | B54: =SUM(B52:B53)
A55: Total of all allowances and cash deliveries in accounts
A57: Net amount owed | B57: =B50-B54
A58: Net amount owed in accounts
A60: GRANGE ACCOUNT | B60: Total Production | D60: Value of total gross production in £ | E60: Value of total net production in £
A61: Grange | B61: qrs | C61: bus
A62: Wheat | B62: 23
A63: Rye
A64: Dredge
A65: Curall | B65: 6
A66: Barley | B66: 34.5
A67: Oats | B67: 32
A68: Beans
A69: Peas
A70: Vetches
A71: Total value of gross production (sum of the above)
A72: Total value of net production
A73: Value of sales
A75: MILL ACCOUNT | B75: Total Production | D75: Total in £
A76: Issues of the mill | B76: qrs | C76: bus
A77: Wheat
A78: Oatmeal
A79: 1st grade malt
A80: 2nd grade malt
A81: Maslin
A82: Total value of production (sum of the above)
A83: Value of sales
A85: STOCK ACCOUNT
A86: Livestock | B86: Begin stock | C86: End stock | D86: Stockbuilding | F86: Value of stock in £ | G86: Value of stockbuilding
A87: Cart-horses | D87: =C87-B87 | F87: ='Stock'!K5*'Stock'!O5 | G87: =D87*'Stock'!O5
A88: Mares | B88: 16 | C88: 0.74166667 | D88: -15.258333 | F88: ='Stock'!K5*'Stock'!O5 | G88: =D88*'Stock'!O5
A89: Plough horses | B89: 2 | D89: =C89-B89 | F89: ='Stock'!K6*'Stock'!O6 | G89: =D89*'Stock'!O6
A90: Colts (2 years) | D90: =C90-B90 | F90: ='Stock'!K8*'Stock'!O8 | G90: =D90*'Stock'!O8
A91: Colts (2 years) | D91: =C91-B91 | F91: ='Stock'!K8*'Stock'!O8 | G91: =D91*'Stock'!O8
A92: Colts (1 year) | D92: =C92-B92 | F92: ='Stock'!K9*'Stock'!O9 | G92: =D92*'Stock'!O9
A93: Foals | D93: =C93-B93 | F93: ='Stock'!K10*'Stock'!O10 | G93: =D93*'Stock'!O10
A94: Oxen | D94: =C94-B94 | F94: ='Stock'!K11*'Stock'!O11 | G94: =D94*'Stock'!O11
A95: Bulls | D95: =C95-B95 | F95: ='Stock'!K12*'Stock'!O12 | G95: =D95*'Stock'!O12
A96: Cows | D96: =C96-B96 | F96: ='Stock'!K13*'Stock'!O13 | G96: =D96*'Stock'!O13
A97: Steers | D97: =C97-B97 | F97: ='Stock'!K14*'Stock'!O14 | G97: =D97*'Stock'!O14
A98: Bullocks | D98: =C98-B98 | F98: ='Stock'!K15*'Stock'!O15 | G98: =D98*'Stock'!O15
A99: Yearlings | D99: =C99-B99 | F99: ='Stock'!K16*'Stock'!O16 | G99: =D99*'Stock'!O16
A100: Calves | D100: =C100-B100 | F100: ='Stock'!K17*'Stock'!O17 | G100: =D100*'Stock'!O17
A101: Wethers | B101: 313 | C101: 1.74375 | D101: -311.25625 | F101: ='Stock'!K18*'Stock'!O18 | G101: =D101*'Stock'!O18
A102: Rams | D102: =C102-B102 | F102: ='Stock'!K19*'Stock'!O19 | G102: =D102*'Stock'!O19
A103: Ewes | D103: =C103-B103 | F103: ='Stock'!K20*'Stock'!O20 | G103: =D103*'Stock'!O20
A104: Hoggs | D104: =C104-B104 | F104: ='Stock'!K21*'Stock'!O21 | G104: =D104*'Stock'!O21
A105: Lambs | D105: =C105-B105 | F105: ='Stock'!K22*'Stock'!O22 | G105: =D105*'Stock'!O22
A106: Boars | D106: =C106-B106 | F106: ='Stock'!K23*'Stock'!O23 | G106: =D106*'Stock'!O23
A107: Sows | D107: =C107-B107 | F107: ='Stock'!K24*'Stock'!O24 | G107: =D107*'Stock'!O24
A108: Pigs | D108: =C108-B108 | F108: ='Stock'!K25*'Stock'!O25 | G108: =D108*'Stock'!O25
A109: Hoggets | D109: =C109-B109 | F109: ='Stock'!K26*'Stock'!O26 | G109: =D109*'Stock'!O26
A110: Piglets | D110: =C110-B110 | F110: ='Stock'!K27*'Stock'!O27 | G110: =D110*'Stock'!O27
A111: Swans | D111: =C111-B111 | F111: ='Stock'!K28*'Stock'!O28 | G111: =D111*'Stock'!O28
A112: Peacocks | D112: =C112-B112 | F112: ='Stock'!K29*'Stock'!O29 | G112: =D112*'Stock'!O29
A113: Total value of stock (sum of the above) | F113: =SUM(F87:F112) | G113: =SUM(G87:G112)
A114: Total value of production | F114: =SUM('Stock'!T5:T30)
A115: Value of sales | F115: =SUM('Stock'!R5:R30)
A117: Wool | B117: Begin stock | C117: End stock | D117: Stockbuilding | F117: Value of stock in £
A118: Fleeces
A119: Coarse wool | F119: =C119*'Stock'!O35
A120: Lamb's wool | F120: =C120*'Stock'!O36
A121: Wool locks | D121: 0.14285714 | F121: =C121*'Stock'!O37
A122: Wool sold at shearing | F122: =C122*'Stock'!O38
A123: Total value of production (sum of the above)
...

Sheet Issues of the Mills
A1: No mill account for Adderbury

Sheet raw data
A1: Heading | B1: Sentence | C1: Total in Pounds | D1: Pounds | E1: Shillings | F1: Pence | G1: Corn | H1: Total Quarters Except 1 | I1: Total Bushels Except 1 | J1: Total Corn Cross-Check | K1: Total Corn Manorial Account | L1: Corn Quantity Error | M1: Quarters 1 | N1: Bushels 1 | O1: shilling a quarter 1 | P1: pence a quarter 1 | Q1: shilling a quarter 2 | R1: pence a quarter 2 | S1: shilling a quarter 3 | T1: pence a quarter 3 | U1: shilling a quarter 4 | V1: pence a quarter 4 | W1: shilling a bushel 1 | X1: pence a bushel 1 | Y1: shilling a bushel 2 | Z1: pence a bushel 2 | AA1: shilling a bushel 3 | AB1: pence a bushel 3 | AC1: shilling a bushel 4 | AD1: pence a bushel 4
A2: Adderbury | B2: The account2 of William Jakeman, reeve there, for the sixth year of the translation of Henry Beaufort', lord bishop of Winchester, and the eleventh year of the reign of King Henry the Fourth. | C2: 0 | D2: 0 | E2: 0 | F2: 0 | H2: 0 | I2: 0 | J2: 0 | K2: 0 | L2: 0 | M2: 0 | N2: 0
A3: Arrears | B3: None. | C3: 0 | D3: 0 | E3: 0 | F3: 0 | H3: 0 | I3: 0 | J3: 0 | K3: 0 | L3: 0 | M3: 0 | N3: 0
A4: Rents of assize | B4: And for £6 9 shilling 6.25pence for all rents of assize at St Thomas the Apostle (21 December). | C4: 6.48 | D4: 6 | E4: 9 | F4: 6.25 | H4: 0 | I4: 0 | J4: 0 | K4: 0 | L4: 0 | M4: 0 | N4: 0
A5: Rents of assize | B5: £6 9 shilling 8.5pence at Easter (23 March). | C5: 6.49 | D5: 6 | E5: 9 | F5: 8.5 | H5: 0 | I5: 0 | J5: 0 | K5: 0 | L5: 0 | M5: 0 | N5: 0
A6: Rents of assize | B6: £6 9 shilling 6.25pence at the Nativity of St John the Baptist (24 June). | C6: 6.48 | D6: 6 | E6: 9 | F6: 6.25 | H6: 0 | I6: 0 | J6: 0 | K6: 0 | L6: 0 | M6: 0 | N6: 0
A7: Rents of assize | B7: £6 10 shilling 1.5pence at Michaelmas (29 September). | C7: 6.51 | D7: 6 | E7: 10 | F7: 1.5 | H7: 0 | I7: 0 | J7: 0 | K7: 0 | L7: 0 | M7: 0 | N7: 0
A8: Rents of assize | B8: Total, £25 18 shilling 10.5pence. | C8: 25.94 | D8: 25 | E8: 18 | F8: 10.5 | H8: 0 | I8: 0 | J8: 0 | K8: 0 | L8: 0 | M8: 0 | N8: 0
A9: Quittances of rent | B9: In quittance of rent of 1 reeve for the year 5 shilling. | C9: 0.25 | D9: 0 | E9: 5 | F9: 0 | H9: 0 | I9: 0 | J9: 0 | K9: 0 | L9: 0 | M9: 0 | N9: 0
A10: Quittances of rent | B10: nothing this year of the 4 shilling for 1 smith forging the ironwork of 2 ploughs for the year. | C10: 0.2 | D10: 0 | E10: 4 | F10: 0 | H10: 0 | I10: 0 | J10: 0 | K10: 0 | L10: 0 | M10: 0 | N10: 0
A11: Quittances of rent | B11: nothing this year of the 4 shilling for 1 shepherd keeping the lord's wethers for the year. | C11: 0.2 | D11: 0 | E11: 4 | F11: 0 | H11: 0 | I11: 0 | J11: 0 | K11: 0 | L11: 0 | M11: 0 | N11: 0
A12: Quittances of rent | B12: nothing this year of the 4 shilling for 1 swineherd for the year. | C12: 0.2 | D12: 0 | E12: 4 | F12: 0 | H12: 0 | I12: 0 | J12: 0 | K12: 0 | L12: 0 | M12: 0 | N12: 0
A13: Quittances of rent | B13: nothing this year of the 4 shilling for 1 cowherd for the year. | C13: 0.2 | D13: 0 | E13: 4 | F13: 0 | H13: 0 | I13: 0 | J13: 0 | K13: 0 | L13: 0 | M13: 0 | N13: 0
... A149: Cost of buildings | B149: board-nails and clout-nails bought for the same 1 shilling 4pence. | C149: 0.07 | D149: 0 | E149: 1 | F149: 4 | H149: 0 | I149: 0 | J149: 0 | K149: 0 | L149: 0 | M149: 0 | N149: 0
A150: Cost of buildings | B150: 4 quarters 4 bushels of limestone bought at Walton' 5 shilling 3pence, at 1 shilling 2pence a quarters. | C150: 0.26 | D150: 0 | E150: 5 | F150: 3 | H150: 4 | I150: 4 | J150: 4.5 | K150: 4.5 | L150: 0 | M150: 4 | N150: 4 | O150: 1 | P150: 2
A151: Cost of buildings | B151: carrying the same 4pence. | C151: 0.02 | D151: 0 | E151: 0 | F151: 4 | H151: 0 | I151: 0 | J151: 0 | K151: 0 | L151: 0 | M151: 0 | N151: 0
A152: Cost of buildings | B152: 8 quarters of limestone bought at Witney 10 shilling 4pence, at 1 shilling 31 pence a quarters. | C152: 0.52 | D152: 0 | E152: 10 | F152: 4 | H152: 8 | I152: 0 | J152: 8 | K152: 8 | L152: 0 | M152: 8 | N152: 0 | O152: 1 | P152: 31
A153: Cost of buildings | B153: carrying the same from Witney to Adderbury 3 shilling 8pence. | C153: 0.18 | D153: 0 | E153: 3 | F153: 8 | H153: 0 | I153: 0 | J153: 0 | K153: 0 | L153: 0 | M153: 0 | N153: 0
A154: Cost of buildings | B154: 1,500 stone slates bought 6 shilling, at 4 shilling a 1,000.. | C154: 0.3 | D154: 0 | E154: 6 | F154: 0 | H154: 0 | I154: 0 | J154: 0 | K154: 0 | L154: 0 | M154: 0 | N154: 0
A155: Cost of buildings | B155: 500 eaves-stones bought 2 shilling 6pence, at 6pence a 100.. | C155: 0.12 | D155: 0 | E155: 2 | F155: 6 | H155: 0 | I155: 0 | J155: 0 | K155: 0 | L155: 0 | M155: 0 | N155: 0
A156: Cost of buildings | B156: 6,000 pins bought 2 shilling, at 4pence a 1,000.. | C156: 0.12 | D156: 0 | E156: 2 | F156: 4 | H156: 0 | I156: 0 | J156: 0 | K156: 0 | L156: 0 | M156: 0 | N156: 0
A157: Cost of buildings | B157: 50 ridge-tiles bought 6 shilling 3pence, at 1.5pence each. | C157: 0.31 | D157: 0 | E157: 6 | F157: 3 | H157: 0 | I157: 0 | J157: 0 | K157: 0 | L157: 0 | M157: 0 | N157: 0
A158: Cost of buildings | B158: sand bought and dug and quarried at Tadmarton 10pence. | C158: 0.04 | D158: 0 | E158: 0 | F158: 10 | H158: 0 | I158: 0 | J158: 0 | K158: 0 | L158: 0 | M158: 0 | N158: 0
A159: Cost of buildings | B159: stipend of 1 man going to Walton' to quarry lime there 2pence. | C159: 0.01 | D159: 0 | E159: 0 | F159: 2 | H159: 0 | I159: 0 | J159: 0 | K159: 0 | L159: 0 | M159: 0 | N159: 0
A160: Cost of buildings | B160: expenses of 12 men coming for a boon-work with 6 carts to quarry sand at Newotele and carry it to Adderbury, with the digging, 2 shilling 3pence. | C160: 0.11 | D160: 0 | E160: 2 | F160: 3 | H160: 0 | I160: 0 | J160: 0 | K160: 0 | L160: 0 | M160: 0 | N160: 0
A161: Cost of buildings | B161: hiring 1 man to carry sand and lime from the warrener's chamber to the barn by piece-work 4pence. | C161: 0.02 | D161: 0 | E161: 0 | F161: 4 | H161: 0 | I161: 0 | J161: 0 | K161: 0 | L161: 0 | M161: 0 | N161: 0
A162: Cost of buildings | B162: carrying the ridge-tiles bought above 8pence. | C162: 0.03 | D162: 0 | E162: 0 | F162: 8 | H162: 0 | I162: 0 | J162: 0 | K162: 0 | L162: 0 | M162: 0 | N162: 0
A163: Cost of buildings | B163: expenses of various men coming for a boon-work to buy slates at Aynho and carry them to Adderbury with the expenses of 1 man there mending the said slates 2d 1 shilling 9.5pence. | C163: 0.09 | D163: 0 | E163: 1 | F163: 9.5 | H163: 0 | I163: 0 | J163: 0 | K163: 0 | L163: 0 | M163: 0 | N163: 0
A164: Cost of buildings | B164: 1 tine bought 8pence. | C164: 0.03 | D164: 0 | E164: 0 | F164: 8 | H164: 0 | I164: 0 | J164: 0 | K164: 0 | L164: 0 | M164: 0 | N164: 0
... A181: Total of all allowances | B181: Total of all allowances and cash deliveries, £64 19 shilling 11.5pence He is quit. | C181: 65 | D181: 64 | E181: 19 | F181: 11.5 | H181: 0 | I181: 0 | J181: 0 | K181: 0 | L181: 0 | M181: 0 | N181: 0
A182: Wheat | B182: William Jakeman, reeve there, answers for 3 quarters of wheat remaining.. | C182: 0 | D182: 0 | E182: 0 | F182: 0 | G182: wheat | H182: 3 | I182: 0 | J182: 3 | K182: 3 | L182: 0 | M182: 3 | N182: 0
A183: Wheat | B183: Total, 3 quarters.. | C183: 0 | D183: 0 | E183: 0 | F183: 0 | H183: 3 | I183: 0 | J183: 3 | K183: 3 | L183: 0 | M183: 3 | N183: 0
A184: Wheat | B184: 3 quarters remain in the keeping of John Eadburbury, farmer there, to be handed back and restored at the end of his farm of 12 years, this year being the fifth. | C184: 0 | D184: 0 | E184: 0 | F184: 0 | H184: 3 | I184: 0 | J184: 3 | K184: 3 | L184: 0 | M184: 3 | N184: 0
A185: Rye | B185: And for 34 quarters of rye remaining.. | C185: 0 | D185: 0 | E185: 0 | F185: 0 | G185: rye | H185: 34 | I185: 0 | J185: 34 | K185: 34 | L185: 0 | M185: 34 | N185: 0
A186: Rye | B186: Total, 34 quarters.. | C186: 0 | D186: 0 | E186: 0 | F186: 0 | H186: 34 | I186: 0 | J186: 34 | K186: 34 | L186: 0 | M186: 34 | N186: 0
A187: Rye | B187: 34 quarters remain in the keeping of the said John Eadburbury, farmer there, to be handed back and restored at the end of his farm as before. | C187: 0 | D187: 0 | E187: 0 | F187: 0 | H187: 34 | I187: 0 | J187: 34 | K187: 34 | L187: 0 | M187: 34 | N187: 0
A188: Dredge | B188: And for 30 quarters of dredge remaining.. | C188: 0 | D188: 0 | E188: 0 | F188: 0 | G188: dredge | H188: 30 | I188: 0 | J188: 30 | K188: 30 | L188: 0 | M188: 30 | N188: 0
A189: Dredge | B189: Total, 30 quarters.. | C189: 0 | D189: 0 | E189: 0 | F189: 0 | H189: 30 | I189: 0 | J189: 30 | K189: 30 | L189: 0 | M189: 30 | N189: 0
A190: Dredge | B190: 30 quarters remain in the keeping of the said John Eadburbury, farmer there, to be handed back and restored as before. | C190: 0 | D190: 0 | E190: 0 | F190: 0 | H190: 30 | I190: 0 | J190: 30 | K190: 30 | L190: 0 | M190: 30 | N190: 0
A191: Pulses | B191: None remain. | C191: 0 | D191: 0 | E191: 0 | F191: 0 | H191: 0 | I191: 0 | J191: 0 | K191: 0 | L191: 0 | M191: 0 | N191: 0
A192: Oats | B192: And for 10 quarters of oats.. | C192: 0 | D192: 0 | E192: 0 | F192: 0 | G192: oats | H192: 10 | I192: 0 | J192: 10 | K192: 10 | L192: 0 | M192: 10 | N192: 0
A193: Oats | B193: Total, 10 quarters.. | C193: 0 | D193: 0 | E193: 0 | F193: 0 | H193: 10 | I193: 0 | J193: 10 | K193: 10 | L193: 0 | M193: 10 | N193: 0
A194: Oats | B194: 10 quarters remain in the keeping of the said John Eadburbury, farmer there, to be handed back and restored as before. | C194: 0 | D194: 0 | E194: 0 | F194: 0 | H194: 10 | I194: 0 | J194: 10 | K194: 10 | L194: 0 | M194: 10 | N194: 0
A195: Oats | B195: Eadburbury, farmer, to be handed back and restored at the end of his farm or the value of the same as before. | C195: 0 | D195: 0 | E195: 0 | F195: 0 | H195: 0 | I195: 0 | J195: 0 | K195: 0 | L195: 0 | M195: 0 | N195: 0
A196: Stock | B196: Horses: 4 remain. | C196: 0 | D196: 0 | E196: 0 | F196: 0 | H196: 0 | I196: 0 | J196: 0 | K196: 0 | L196: 0 | M196: 0 | N196: 0
A197: Stock | B197: 1 from the heriot of William Rundell'. | C197: 0 | D197: 0 | E197: 0 | F197: 0 | H197: 0 | I197: 0 | J197: 0 | K197: 0 | L197: 0 | M197: 0 | N197: 0
A198: Stock | B198: Total 5. 1 sold within. | C198: 0 | D198: 0 | E198: 0 | F198: 0 | H198: 0 | I198: 0 | J198: 0 | K198: 0 | L198: 0 | M198: 0 | N198: 0
A199: Stock | B199: 4 cart-horses remain, of which 2 are worth £1 6s 8pence, 1 is worth £1, and 1 feeble one is worth 2 shilling, in the keeping of the said John Eadburbury, farmer there, to be handed back and restored at the end of his farm or the value of the same at the choice of the lord bishop or his attorney. | C199: 1 | D199: 1 | E199: 0 | F199: 0 | H199: 0 | I199: 0 | J199: 0 | K199: 0 | L199: 0 | M199: 0 | N199: 0
A200: Stock | B200: Plough-horses: 6 remain. | C200: 0 | D200: 0 | E200: 0 | F200: 0 | H200: 0 | I200: 0 | J200: 0 | K200: 0 | L200: 0 | M200: 0 | N200: 0
A201: Stock | B201: Total, 6. 6 remain, worth £2, in the keeping of John. | C201: 2 | D201: 2 | E201: 0 | F201: 0 | H201: 0 | I201: 0 | J201: 0 | K201: 0 | L201: 0 | M201: 0 | N201: 0
A202: Stock | B202: Colts: 1 from the heriot of John Diconurn. | C202: 0 | D202: 0 | E202: 0 | F202: 0 | H202: 0 | I202: 0 | J202: 0 | K202: 0 | L202: 0 | M202: 0 | N202: 0
A203: Stock | B203: sold within. | C203: 0 | D203: 0 | E203: 0 | F203: 0 | H203: 0 | I203: 0 | J203: 0 | K203: 0 | L203: 0 | M203: 0 | N203: 0
A204: Stock | B204: none remain. | C204: 0 | D204: 0 | E204: 0 | F204: 0 | H204: 0 | I204: 0 | J204: 0 | K204: 0 | L204: 0 | M204: 0 | N204: 0
... A268: Stock | B268: none remain. mid. | C268: 0 | D268: 0 | E268: 0 | F268: 0 | H268: 0 | I268: 0 | J268: 0 | K268: 0 | L268: 0 | M268: 0 | N268: 0

Sheet Prices
A1: Meat & Dairy Prices
C2: 1301 | D2: 1302 | E2: Average
A3: Beef | B3: £ per lb | C3: 0.0033351854 | D3: 0.0032608538 | E3: =AVERAGE(C3:D3)
A4: Mutton | B4: £ per lb | C4: 0.0036593977 | D4: 0.0037125513 | E4: =AVERAGE(C4:D4)
A5: Pork | B5: £ per lb | C5: 0.0038431326 | D5: 0.0037574803 | E5: =AVERAGE(C5:D5)
A6: Cheese | B6: £ per lb | C6: 0.0055768754 | D6: 0.0056654898 | E6: =AVERAGE(C6:D6)
A7: Butter | B7: £ per lb | C7: 0.0036626221 | D7: 0.0035935077 | E7: =AVERAGE(C7:D7)
A8: Milk | B8: £ per gallon | C8: 0.0055768754 | D8: 0.0056654898 | E8: =AVERAGE(C8:D8)

Sheet Labour Rents

Sheet Upton Overview
A1: UPTON OVERVIEW | B1: £ | C1: s | D1: d | G1: Total in £ | H1: Error
A3: CASH ACCOUNT
A4: RECEIPTS
A5: Arrears | G5: ='Upton Receipts'!F5
A6: Rents of assize | G6: ='Upton Receipts'!F14
A7: Quittances | G7: ='Upton Receipts'!F22
A8: Defaults of rent | G8: ='Upton Receipts'!F27
A9: Annual reconizances
A10: Issues of the Manor | G10: ='Upton Receipts'!F39
A11: Sale of corn | G11: ='Upton Receipts'!F48
A12: Entry and marriage fines
A13: Pleas & Perquisites | G13: ='Upton Receipts'!F51
A14: Sum of the above (incl. arrears) | G14: =SUM(G5:G13)
A15: Total recorded in the accounts excl. arrears? (p.10) | G15: ='Upton Receipts'!F55 | H15: =G14-G15
A16: Total recorded in the accounts incl. arrears? (p.10) | G16: n/a
A18: EXPENSES
A19: Cost of ploughs | G19: ='Upton Expenses'!F14
A20: Purchase of corn
A21: Cost of carts and wagons | G21: ='Upton Expenses'!F25
A22: Cost of dairy
A23: Purchase of stock
A24: Sheepcote | G24: ='Upton Expenses'!F32
A25: Cost of buildings | G25: ='Upton Expenses'!F44
A26: Threshing | G26: ='Upton Expenses'!F53
A27: Expenses of the harvest | G27: ='Upton Expenses'!F63
A28: Stewards expenses
A29: Sum of the above | G29: =SUM(G19:G28)
A30: Total of all expenses | G30: ='Upton Expenses'!F65 | H30: =G29-G30
A31: Capital Expenses | G31: ='Upton Expenses'!F69
A33: Owed by the reeve | G33: ='Upton Expenses'!F67
A34: From accounts
A36: Cash deliveries | G36: ='Upton Expenses'!F68
A37: Cash delivers (Hindon Borough)
A38: Sum of the above | B38: =SUM(B36:B37) | C38: =SUM(C36:C37) | D38: =SUM(D36:D37) | E38: =SUM(E36:E37) | G38: =SUM(G36:G37)
A39: Total of all allowances and cash deliveries in accounts | B39: n/a
A41: Net amount owed | G41: ='Upton Expenses'!F67
A42: Net amount owed in accounts | H42: =G41-G42
A44: GRANGE ACCOUNT | B44: Total Production
A45: Grange | B45: qrs | C45: bus | G45: Value of total gross production in £ | H45: Value of total net production in £
A46: Wheat | B46: ='Issues of the Grange'!B5 | C46: ='Issues of the Grange'!C5 | G46: ='Issues of the Grange'!P5 | H46: ='Issues of the Grange'!M18
A47: Curall | B47: ='Issues of the Grange'!B6 | C47: ='Issues of the Grange'!C6 | G47: ='Issues of the Grange'!P6 | H47: ='Issues of the Grange'!M19
A48: Barley | B48: ='Issues of the Grange'!B7 | C48: ='Issues of the Grange'!C7 | G48: ='Issues of the Grange'!P7 | H48: ='Issues of the Grange'!M20
A49: Oats | B49: ='Issues of the Grange'!B8 | C49: ='Issues of the Grange'!C8 | G49: ='Issues of the Grange'!P8 | H49: ='Issues of the Grange'!M21
A50: Peas | B50: ='Issues of the Grange'!B9 | C50: ='Issues of the Grange'!C9 | G50: ='Issues of the Grange'!P9 | H50: ='Issues of the Grange'!M22
A51: Vetches | B51: ='Issues of the Grange'!B10 | C51: ='Issues of the Grange'!C10 | G51: ='Issues of the Grange'!P10 | H51: ='Issues of the Grange'!M23
A52: Total value of gross production (sum of the above) | B52: =SUM(B46:B51) | C52: =SUM(C46:C51) | G52: =SUM(G46:G51)
A53: Total value of net production | G53: =SUM(H46:H51)
A54: Value of sales | B54: ='Issues of the Grange'!N24 | G54: ='Issues of the Grange'!N24
A56: MILL ACCOUNT | B56: n/a
A57: Issues of the mill | B57: qrs | C57: bus | G57: £
A58: Wheat
A59: Oatmeal
A60: 1st grade malt
A61: 2nd grade malt
A62: Maslin
A63: Total value of production (sum of the above)
A64: Value of sales | G64: n/a
A66: STOCK ACCOUNT
A67: Livestock | B67: Inherited stock | C67: End-period stock | D67: Stockbuilding | F67: Sales in (£) | G67: Value of production (£) at sales prices
A68: Cart-horses | B68: =IFERROR(INDEX(Stock!$A$3:$S$91,MATCH('Upton Overview'!$A68,Stock!$A$3:$A$91,0),MATCH('Upton Overview'!B$67,Stock!$A$3:$S$3,0)),0) | C68: =IFERROR(INDEX(Stock!$A$3:$S$91,MATCH('Upton Overview'!$A68,Stock!$A$3:$A$91,0),MATCH('Upton Overview'!C$67,Stock!$A$3:$S$3,0)),0) | D68: =C68-B68 | F68: =IFERROR(INDEX(Stock!$A$3:$S$91,MATCH('Upton Overview'!$A68,Stock!$A$3:$A$91,0),MATCH('Upton Overview'!F$67,Stock!$A$3:$S$3,0)),0) | G68: =IFERROR(INDEX(Stock!$A$3:$S$91,MATCH('Upton Overview'!$A68,Stock!$A$3:$A$91,0),MATCH('Upton Overview'!G$67,Stock!$A$3:$S$3,0)),0)
A69: Mares | B69: =IFERROR(INDEX(Stock!$A$3:$S$91,MATCH('Upton Overview'!$A69,Stock!$A$3:$A$91,0),MATCH('Upton Overview'!B$67,Stock!$A$3:$S$3,0)),0) | C69: =IFERROR(INDEX(Stock!$A$3:$S$91,MATCH('Upton Overview'!$A69,Stock!$A$3:$A$91,0),MATCH('Upton Overview'!C$67,Stock!$A$3:$S$3,0)),0) | D69: =C69-B69 | F69: =IFERROR(INDEX(Stock!$A$3:$S$91,MATCH('Upton Overview'!$A69,Stock!$A$3:$A$91,0),MATCH('Upton Overview'!F$67,Stock!$A$3:$S$3,0)),0) | G69: =IFERROR(INDEX(Stock!$A$3:$S$91,MATCH('Upton Overview'!$A69,Stock!$A$3:$A$91,0),MATCH('Upton Overview'!G$67,Stock!$A$3:$S$3,0)),0)
A70: Plough horses | B70: =IFERROR(INDEX(Stock!$A$3:$S$91,MATCH('Upton Overview'!$A70,Stock!$A$3:$A$91,0),MATCH('Upton Overview'!B$67,Stock!$A$3:$S$3,0)),0) | C70: =IFERROR(INDEX(Stock!$A$3:$S$91,MATCH('Upton Overview'!$A70,Stock!$A$3:$A$91,0),MATCH('Upton Overview'!C$67,Stock!$A$3:$S$3,0)),0) | D70: =C70-B70 | F70: =IFERROR(INDEX(Stock!$A$3:$S$91,MATCH('Upton Overview'!$A70,Stock!$A$3:$A$91,0),MATCH('Upton Overview'!F$67,Stock!$A$3:$S$3,0)),0) | G70: =IFERROR(INDEX(Stock!$A$3:$S$91,MATCH('Upton Overview'!$A70,Stock!$A$3:$A$91,0),MATCH('Upton Overview'!G$67,Stock!$A$3:$S$3,0)),0)
A71: Colts (2 years) | B71: =IFERROR(INDEX(Stock!$A$3:$S$91,MATCH('Upton Overview'!$A71,Stock!$A$3:$A$91,0),MATCH('Upton Overview'!B$67,Stock!$A$3:$S$3,0)),0) | C71: =IFERROR(INDEX(Stock!$A$3:$S$91,MATCH('Upton Overview'!$A71,Stock!$A$3:$A$91,0),MATCH('Upton Overview'!C$67,Stock!$A$3:$S$3,0)),0) | D71: =C71-B71 | F71: =IFERROR(INDEX(Stock!$A$3:$S$91,MATCH('Upton Overview'!$A71,Stock!$A$3:$A$91,0),MATCH('Upton Overview'!F$67,Stock!$A$3:$S$3,0)),0) | G71: =IFERROR(INDEX(Stock!$A$3:$S$91,MATCH('Upton Overview'!$A71,Stock!$A$3:$A$91,0),MATCH('Upton Overview'!G$67,Stock!$A$3:$S$3,0)),0)
A72: Colts (2 years) | B72: =IFERROR(INDEX(Stock!$A$3:$S$91,MATCH('Upton Overview'!$A72,Stock!$A$3:$A$91,0),MATCH('Upton Overview'!B$67,Stock!$A$3:$S$3,0)),0) | C72: =IFERROR(INDEX(Stock!$A$3:$S$91,MATCH('Upton Overview'!$A72,Stock!$A$3:$A$91,0),MATCH('Upton Overview'!C$67,Stock!$A$3:$S$3,0)),0) | D72: =C72-B72 | F72: =IFERROR(INDEX(Stock!$A$3:$S$91,MATCH('Upton Overview'!$A72,Stock!$A$3:$A$91,0),MATCH('Upton Overview'!F$67,Stock!$A$3:$S$3,0)),0) | G72: =IFERROR(INDEX(Stock!$A$3:$S$91,MATCH('Upton Overview'!$A72,Stock!$A$3:$A$91,0),MATCH('Upton Overview'!G$67,Stock!$A$3:$S$3,0)),0)
A73: Colts (1 year) | B73: =IFERROR(INDEX(Stock!$A$3:$S$91,MATCH('Upton Overview'!$A73,Stock!$A$3:$A$91,0),MATCH('Upton Overview'!B$67,Stock!$A$3:$S$3,0)),0) | C73: =IFERROR(INDEX(Stock!$A$3:$S$91,MATCH('Upton Overview'!$A73,Stock!$A$3:$A$91,0),MATCH('Upton Overview'!C$67,Stock!$A$3:$S$3,0)),0) | D73: =C73-B73 | F73: =IFERROR(INDEX(Stock!$A$3:$S$91,MATCH('Upton Overview'!$A73,Stock!$A$3:$A$91,0),MATCH('Upton Overview'!F$67,Stock!$A$3:$S$3,0)),0) | G73: =IFERROR(INDEX(Stock!$A$3:$S$91,MATCH('Upton Overview'!$A73,Stock!$A$3:$A$91,0),MATCH('Upton Overview'!G$67,Stock!$A$3:$S$3,0)),0)
A74: Foals | B74: =IFERROR(INDEX(Stock!$A$3:$S$91,MATCH('Upton Overview'!$A74,Stock!$A$3:$A$91,0),MATCH('Upton Overview'!B$67,Stock!$A$3:$S$3,0)),0) | C74: =IFERROR(INDEX(Stock!$A$3:$S$91,MATCH('Upton Overview'!$A74,Stock!$A$3:$A$91,0),MATCH('Upton Overview'!C$67,Stock!$A$3:$S$3,0)),0) | D74: =C74-B74 | F74: =IFERROR(INDEX(Stock!$A$3:$S$91,MATCH('Upton Overview'!$A74,Stock!$A$3:$A$91,0),MATCH('Upton Overview'!F$67,Stock!$A$3:$S$3,0)),0) | G74: =IFERROR(INDEX(Stock!$A$3:$S$91,MATCH('Upton Overview'!$A74,Stock!$A$3:$A$91,0),MATCH('Upton Overview'!G$67,Stock!$A$3:$S$3,0)),0)
A75: Oxen | B75: =IFERROR(INDEX(Stock!$A$3:$S$91,MATCH('Upton Overview'!$A75,Stock!$A$3:$A$91,0),MATCH('Upton Overview'!B$67,Stock!$A$3:$S$3,0)),0) | C75: =IFERROR(INDEX(Stock!$A$3:$S$91,MATCH('Upton Overview'!$A75,Stock!$A$3:$A$91,0),MATCH('Upton Overview'!C$67,Stock!$A$3:$S$3,0)),0) | D75: =C75-B75 | F75: =IFERROR(INDEX(Stock!$A$3:$S$91,MATCH('Upton Overview'!$A75,Stock!$A$3:$A$91,0),MATCH('Upton Overview'!F$67,Stock!$A$3:$S$3,0)),0) | G75: =IFERROR(INDEX(Stock!$A$3:$S$91,MATCH('Upton Overview'!$A75,Stock!$A$3:$A$91,0),MATCH('Upton Overview'!G$67,Stock!$A$3:$S$3,0)),0)
A76: Bulls | B76: =IFERROR(INDEX(Stock!$A$3:$S$91,MATCH('Upton Overview'!$A76,Stock!$A$3:$A$91,0),MATCH('Upton Overview'!B$67,Stock!$A$3:$S$3,0)),0) | C76: =IFERROR(INDEX(Stock!$A$3:$S$91,MATCH('Upton Overview'!$A76,Stock!$A$3:$A$91,0),MATCH('Upton Overview'!C$67,Stock!$A$3:$S$3,0)),0) | D76: =C76-B76 | F76: =IFERROR(INDEX(Stock!$A$3:$S$91,MATCH('Upton Overview'!$A76,Stock!$A$3:$A$91,0),MATCH('Upton Overview'!F$67,Stock!$A$3:$S$3,0)),0) | G76: =IFERROR(INDEX(Stock!$A$3:$S$91,MATCH('Upton Overview'!$A76,Stock!$A$3:$A$91,0),MATCH('Upton Overview'!G$67,Stock!$A$3:$S$3,0)),0)
A77: Cows | B77: =IFERROR(INDEX(Stock!$A$3:$S$91,MATCH('Upton Overview'!$A77,Stock!$A$3:$A$91,0),MATCH('Upton Overview'!B$67,Stock!$A$3:$S$3,0)),0) | C77: =IFERROR(INDEX(Stock!$A$3:$S$91,MATCH('Upton Overview'!$A77,Stock!$A$3:$A$91,0),MATCH('Upton Overview'!C$67,Stock!$A$3:$S$3,0)),0) | D77: =C77-B77 | F77: =IFERROR(INDEX(Stock!$A$3:$S$91,MATCH('Upton Overview'!$A77,Stock!$A$3:$A$91,0),MATCH('Upton Overview'!F$67,Stock!$A$3:$S$3,0)),0) | G77: =IFERROR(INDEX(Stock!$A$3:$S$91,MATCH('Upton Overview'!$A77,Stock!$A$3:$A$91,0),MATCH('Upton Overview'!G$67,Stock!$A$3:$S$3,0)),0)
A78: Steers | B78: =IFERROR(INDEX(Stock!$A$3:$S$91,MATCH('Upton Overview'!$A78,Stock!$A$3:$A$91,0),MATCH('Upton Overview'!B$67,Stock!$A$3:$S$3,0)),0) | C78: =IFERROR(INDEX(Stock!$A$3:$S$91,MATCH('Upton Overview'!$A78,Stock!$A$3:$A$91,0),MATCH('Upton Overview'!C$67,Stock!$A$3:$S$3,0)),0) | D78: =C78-B78 | F78: =IFERROR(INDEX(Stock!$A$3:$S$91,MATCH('Upton Overview'!$A78,Stock!$A$3:$A$91,0),MATCH('Upton Overview'!F$67,Stock!$A$3:$S$3,0)),0) | G78: =IFERROR(INDEX(Stock!$A$3:$S$91,MATCH('Upton Overview'!$A78,Stock!$A$3:$A$91,0),MATCH('Upton Overview'!G$67,Stock!$A$3:$S$3,0)),0)
A79: Bullocks | B79: =IFERROR(INDEX(Stock!$A$3:$S$91,MATCH('Upton Overview'!$A79,Stock!$A$3:$A$91,0),MATCH('Upton Overview'!B$67,Stock!$A$3:$S$3,0)),0) | C79: =IFERROR(INDEX(Stock!$A$3:$S$91,MATCH('Upton Overview'!$A79,Stock!$A$3:$A$91,0),MATCH('Upton Overview'!C$67,Stock!$A$3:$S$3,0)),0) | D79: =C79-B79 | F79: =IFERROR(INDEX(Stock!$A$3:$S$91,MATCH('Upton Overview'!$A79,Stock!$A$3:$A$91,0),MATCH('Upton Overview'!F$67,Stock!$A$3:$S$3,0)),0) | G79: =IFERROR(INDEX(Stock!$A$3:$S$91,MATCH('Upton Overview'!$A79,Stock!$A$3:$A$91,0),MATCH('Upton Overview'!G$67,Stock!$A$3:$S$3,0)),0)
... A93: Peacocks | B93: =IFERROR(INDEX(Stock!$A$3:$S$91,MATCH('Upton Overview'!$A93,Stock!$A$3:$A$91,0),MATCH('Upton Overview'!B$67,Stock!$A$3:$S$3,0)),0) | C93: =IFERROR(INDEX(Stock!$A$3:$S$91,MATCH('Upton Overview'!$A93,Stock!$A$3:$A$91,0),MATCH('Upton Overview'!C$67,Stock!$A$3:$S$3,0)),0) | D93: =C93-B93 | F93: =IFERROR(INDEX(Stock!$A$3:$S$91,MATCH('Upton Overview'!$A93,Stock!$A$3:$A$91,0),MATCH('Upton Overview'!F$67,Stock!$A$3:$S$3,0)),0) | G93: =IFERROR(INDEX(Stock!$A$3:$S$91,MATCH('Upton Overview'!$A93,Stock!$A$3:$A$91,0),MATCH('Upton Overview'!G$67,Stock!$A$3:$S$3,0)),0)
A94: Total | G94: =SUM(G68:G93)
A95: Value of sales | G95: =SUM(F68:F93)
A97: Wool
A98: Fleeces | B98: =IFERROR(INDEX(Stock!$A$3:$S$91,MATCH('Upton Overview'!$A98,Stock!$A$3:$A$91,0),MATCH('Upton Overview'!B$67,Stock!$A$3:$S$3,0)),0) | C98: =IFERROR(INDEX(Stock!$A$3:$S$91,MATCH('Upton Overview'!$A98,Stock!$A$3:$A$91,0),MATCH('Upton Overview'!C$67,Stock!$A$3:$S$3,0)),0) | D98: =C98-B98 | F98: =IFERROR(INDEX(Stock!$A$3:$S$91,MATCH('Upton Overview'!$A98,Stock!$A$3:$A$91,0),MATCH('Upton Overview'!F$67,Stock!$A$3:$S$3,0)),0) | G98: =IFERROR(INDEX(Stock!$A$3:$S$91,MATCH('Upton Overview'!$A98,Stock!$A$3:$A$91,0),MATCH('Upton Overview'!G$67,Stock!$A$3:$S$3,0)),0)
A99: Coarse wool | B99: =IFERROR(INDEX(Stock!$A$3:$S$91,MATCH('Upton Overview'!$A99,Stock!$A$3:$A$91,0),MATCH('Upton Overview'!B$67,Stock!$A$3:$S$3,0)),0) | C99: =IFERROR(INDEX(Stock!$A$3:$S$91,MATCH('Upton Overview'!$A99,Stock!$A$3:$A$91,0),MATCH('Upton Overview'!C$67,Stock!$A$3:$S$3,0)),0) | D99: =C99-B99 | F99: =IFERROR(INDEX(Stock!$A$3:$S$91,MATCH('Upton Overview'!$A99,Stock!$A$3:$A$91,0),MATCH('Upton Overview'!F$67,Stock!$A$3:$S$3,0)),0) | G99: =IFERROR(INDEX(Stock!$A$3:$S$91,MATCH('Upton Overview'!$A99,Stock!$A$3:$A$91,0),MATCH('Upton Overview'!G$67,Stock!$A$3:$S$3,0)),0)
A100: Lamb's wool | B100: =IFERROR(INDEX(Stock!$A$3:$S$91,MATCH('Upton Overview'!$A100,Stock!$A$3:$A$91,0),MATCH('Upton Overview'!B$67,Stock!$A$3:$S$3,0)),0) | C100: =IFERROR(INDEX(Stock!$A$3:$S$91,MATCH('Upton Overview'!$A100,Stock!$A$3:$A$91,0),MATCH('Upton Overview'!C$67,Stock!$A$3:$S$3,0)),0) | D100: =C100-B100 | F100: =IFERROR(INDEX(Stock!$A$3:$S$91,MATCH('Upton Overview'!$A100,Stock!$A$3:$A$91,0),MATCH('Upton Overview'!F$67,Stock!$A$3:$S$3,0)),0) | G100: =IFERROR(INDEX(Stock!$A$3:$S$91,MATCH('Upton Overview'!$A100,Stock!$A$3:$A$91,0),MATCH('Upton Overview'!G$67,Stock!$A$3:$S$3,0)),0)
A101: Wool locks | B101: =IFERROR(INDEX(Stock!$A$3:$S$91,MATCH('Upton Overview'!$A101,Stock!$A$3:$A$91,0),MATCH('Upton Overview'!B$67,Stock!$A$3:$S$3,0)),0) | C101: =IFERROR(INDEX(Stock!$A$3:$S$91,MATCH('Upton Overview'!$A101,Stock!$A$3:$A$91,0),MATCH('Upton Overview'!C$67,Stock!$A$3:$S$3,0)),0) | D101: =C101-B101 | F101: =IFERROR(INDEX(Stock!$A$3:$S$91,MATCH('Upton Overview'!$A101,Stock!$A$3:$A$91,0),MATCH('Upton Overview'!F$67,Stock!$A$3:$S$3,0)),0) | G101: =IFERROR(INDEX(Stock!$A$3:$S$91,MATCH('Upton Overview'!$A101,Stock!$A$3:$A$91,0),MATCH('Upton Overview'!G$67,Stock!$A$3:$S$3,0)),0)
A102: Wool sold at shearing | B102: =IFERROR(INDEX(Stock!$A$3:$S$91,MATCH('Upton Overview'!$A102,Stock!$A$3:$A$91,0),MATCH('Upton Overview'!B$67,Stock!$A$3:$S$3,0)),0) | C102: =IFERROR(INDEX(Stock!$A$3:$S$91,MATCH('Upton Overview'!$A102,Stock!$A$3:$A$91,0),MATCH('Upton Overview'!C$67,Stock!$A$3:$S$3,0)),0) | D102: =C102-B102 | F102: =IFERROR(INDEX(Stock!$A$3:$S$91,MATCH('Upton Overview'!$A102,Stock!$A$3:$A$91,0),MATCH('Upton Overview'!F$67,Stock!$A$3:$S$3,0)),0) | G102: =IFERROR(INDEX(Stock!$A$3:$S$91,MATCH('Upton Overview'!$A102,Stock!$A$3:$A$91,0),MATCH('Upton Overview'!G$67,Stock!$A$3:$S$3,0)),0)
A103: Total value of production (sum of the above) | G103: =SUM(G98:G102)
A104: Value of sales | G104: =SUM(F98:F102)
A106: Hides | G106: £
A107: Ox hides | B107: =IFERROR(INDEX(Stock!$A$3:$S$91,MATCH('Upton Overview'!$A107,Stock!$A$3:$A$91,0),MATCH('Upton Overview'!B$67,Stock!$A$3:$S$3,0)),0) | C107: =IFERROR(INDEX(Stock!$A$3:$S$91,MATCH('Upton Overview'!$A107,Stock!$A$3:$A$91,0),MATCH('Upton Overview'!C$67,Stock!$A$3:$S$3,0)),0) | D107: =C107-B107 | F107: =IFERROR(INDEX(Stock!$A$3:$S$91,MATCH('Upton Overview'!$A107,Stock!$A$3:$A$91,0),MATCH('Upton Overview'!F$67,Stock!$A$3:$S$3,0)),0) | G107: =IFERROR(INDEX(Stock!$A$3:$S$91,MATCH('Upton Overview'!$A107,Stock!$A$3:$A$91,0),MATCH('Upton Overview'!G$67,Stock!$A$3:$S$3,0)),0)
A108: Cow hides | B108: =IFERROR(INDEX(Stock!$A$3:$S$91,MATCH('Upton Overview'!$A108,Stock!$A$3:$A$91,0),MATCH('Upton Overview'!B$67,Stock!$A$3:$S$3,0)),0) | C108: =IFERROR(INDEX(Stock!$A$3:$S$91,MATCH('Upton Overview'!$A108,Stock!$A$3:$A$91,0),MATCH('Upton Overview'!C$67,Stock!$A$3:$S$3,0)),0) | D108: =C108-B108 | F108: =IFERROR(INDEX(Stock!$A$3:$S$91,MATCH('Upton Overview'!$A108,Stock!$A$3:$A$91,0),MATCH('Upton Overview'!F$67,Stock!$A$3:$S$3,0)),0) | G108: =IFERROR(INDEX(Stock!$A$3:$S$91,MATCH('Upton Overview'!$A108,Stock!$A$3:$A$91,0),MATCH('Upton Overview'!G$67,Stock!$A$3:$S$3,0)),0)
A109: Mare hides | B109: =IFERROR(INDEX(Stock!$A$3:$S$91,MATCH('Upton Overview'!$A109,Stock!$A$3:$A$91,0),MATCH('Upton Overview'!B$67,Stock!$A$3:$S$3,0)),0) | C109: =IFERROR(INDEX(Stock!$A$3:$S$91,MATCH('Upton Overview'!$A109,Stock!$A$3:$A$91,0),MATCH('Upton Overview'!C$67,Stock!$A$3:$S$3,0)),0) | D109: =C109-B109 | F109: =IFERROR(INDEX(Stock!$A$3:$S$91,MATCH('Upton Overview'!$A109,Stock!$A$3:$A$91,0),MATCH('Upton Overview'!F$67,Stock!$A$3:$S$3,0)),0) | G109: =IFERROR(INDEX(Stock!$A$3:$S$91,MATCH('Upton Overview'!$A109,Stock!$A$3:$A$91,0),MATCH('Upton Overview'!G$67,Stock!$A$3:$S$3,0)),0)
A110: Steer hides | B110: =IFERROR(INDEX(Stock!$A$3:$S$91,MATCH('Upton Overview'!$A110,Stock!$A$3:$A$91,0),MATCH('Upton Overview'!B$67,Stock!$A$3:$S$3,0)),0) | C110: =IFERROR(INDEX(Stock!$A$3:$S$91,MATCH('Upton Overview'!$A110,Stock!$A$3:$A$91,0),MATCH('Upton Overview'!C$67,Stock!$A$3:$S$3,0)),0) | D110: =C110-B110 | F110: =IFERROR(INDEX(Stock!$A$3:$S$91,MATCH('Upton Overview'!$A110,Stock!$A$3:$A$91,0),MATCH('Upton Overview'!F$67,Stock!$A$3:$S$3,0)),0) | G110: =IFERROR(INDEX(Stock!$A$3:$S$91,MATCH('Upton Overview'!$A110,Stock!$A$3:$A$91,0),MATCH('Upton Overview'!G$67,Stock!$A$3:$S$3,0)),0)
A111: Yearling Calf hides | B111: =IFERROR(INDEX(Stock!$A$3:$S$91,MATCH('Upton Overview'!$A111,Stock!$A$3:$A$91,0),MATCH('Upton Overview'!B$67,Stock!$A$3:$S$3,0)),0) | C111: =IFERROR(INDEX(Stock!$A$3:$S$91,MATCH('Upton Overview'!$A111,Stock!$A$3:$A$91,0),MATCH('Upton Overview'!C$67,Stock!$A$3:$S$3,0)),0) | D111: =C111-B111 | F111: =IFERROR(INDEX(Stock!$A$3:$S$91,MATCH('Upton Overview'!$A111,Stock!$A$3:$A$91,0),MATCH('Upton Overview'!F$67,Stock!$A$3:$S$3,0)),0) | G111: =IFERROR(INDEX(Stock!$A$3:$S$91,MATCH('Upton Overview'!$A111,Stock!$A$3:$A$91,0),MATCH('Upton Overview'!G$67,Stock!$A$3:$S$3,0)),0)
A112: Calf hides | B112: =IFERROR(INDEX(Stock!$A$3:$S$91,MATCH('Upton Overview'!$A112,Stock!$A$3:$A$91,0),MATCH('Upton Overview'!B$67,Stock!$A$3:$S$3,0)),0) | C112: =IFERROR(INDEX(Stock!$A$3:$S$91,MATCH('Upton Overview'!$A112,Stock!$A$3:$A$91,0),MATCH('Upton Overview'!C$67,Stock!$A$3:$S$3,0)),0) | D112: =C112-B112 | F112: =IFERROR(INDEX(Stock!$A$3:$S$91,MATCH('Upton Overview'!$A112,Stock!$A$3:$A$91,0),MATCH('Upton Overview'!F$67,Stock!$A$3:$S$3,0)),0) | G112: =IFERROR(INDEX(Stock!$A$3:$S$91,MATCH('Upton Overview'!$A112,Stock!$A$3:$A$91,0),MATCH('Upton Overview'!G$67,Stock!$A$3:$S$3,0)),0)
A113: Pig hides | B113: =IFERROR(INDEX(Stock!$A$3:$S$91,MATCH('Upton Overview'!$A113,Stock!$A$3:$A$91,0),MATCH('Upton Overview'!B$67,Stock!$A$3:$S$3,0)),0) | C113: =IFERROR(INDEX(Stock!$A$3:$S$91,MATCH('Upton Overview'!$A113,Stock!$A$3:$A$91,0),MATCH('Upton Overview'!C$67,Stock!$A$3:$S$3,0)),0) | D113: =C113-B113 | F113: =IFERROR(INDEX(Stock!$A$3:$S$91,MATCH('Upton Overview'!$A113,Stock!$A$3:$A$91,0),MATCH('Upton Overview'!F$67,Stock!$A$3:$S$3,0)),0) | G113: =IFERROR(INDEX(Stock!$A$3:$S$91,MATCH('Upton Overview'!$A113,Stock!$A$3:$A$91,0),MATCH('Upton Overview'!G$67,Stock!$A$3:$S$3,0)),0)
A114: Weather woolskins | B114: =IFERROR(INDEX(Stock!$A$3:$S$91,MATCH('Upton Overview'!$A114,Stock!$A$3:$A$91,0),MATCH('Upton Overview'!B$67,Stock!$A$3:$S$3,0)),0) | C114: =IFERROR(INDEX(Stock!$A$3:$S$91,MATCH('Upton Overview'!$A114,Stock!$A$3:$A$91,0),MATCH('Upton Overview'!C$67,Stock!$A$3:$S$3,0)),0) | D114: =C114-B114 | F114: =IFERROR(INDEX(Stock!$A$3:$S$91,MATCH('Upton Overview'!$A114,Stock!$A$3:$A$91,0),MATCH('Upton Overview'!F$67,Stock!$A$3:$S$3,0)),0) | G114: =IFERROR(INDEX(Stock!$A$3:$S$91,MATCH('Upton Overview'!$A114,Stock!$A$3:$A$91,0),MATCH('Upton Overview'!G$67,Stock!$A$3:$S$3,0)),0)
A115: Ram woolskins | B115: =IFERROR(INDEX(Stock!$A$3:$S$91,MATCH('Upton Overview'!$A115,Stock!$A$3:$A$91,0),MATCH('Upton Overview'!B$67,Stock!$A$3:$S$3,0)),0) | C115: =IFERROR(INDEX(Stock!$A$3:$S$91,MATCH('Upton Overview'!$A115,Stock!$A$3:$A$91,0),MATCH('Upton Overview'!C$67,Stock!$A$3:$S$3,0)),0) | D115: =C115-B115 | F115: =IFERROR(INDEX(Stock!$A$3:$S$91,MATCH('Upton Overview'!$A115,Stock!$A$3:$A$91,0),MATCH('Upton Overview'!F$67,Stock!$A$3:$S$3,0)),0) | G115: =IFERROR(INDEX(Stock!$A$3:$S$91,MATCH('Upton Overview'!$A115,Stock!$A$3:$A$91,0),MATCH('Upton Overview'!G$67,Stock!$A$3:$S$3,0)),0)
A116: Ewe woolskins | B116: =IFERROR(INDEX(Stock!$A$3:$S$91,MATCH('Upton Overview'!$A116,Stock!$A$3:$A$91,0),MATCH('Upton Overview'!B$67,Stock!$A$3:$S$3,0)),0) | C116: =IFERROR(INDEX(Stock!$A$3:$S$91,MATCH('Upton Overview'!$A116,Stock!$A$3:$A$91,0),MATCH('Upton Overview'!C$67,Stock!$A$3:$S$3,0)),0) | D116: =C116-B116 | F116: =IFERROR(INDEX(Stock!$A$3:$S$91,MATCH('Upton Overview'!$A116,Stock!$A$3:$A$91,0),MATCH('Upton Overview'!F$67,Stock!$A$3:$S$3,0)),0) | G116: =IFERROR(INDEX(Stock!$A$3:$S$91,MATCH('Upton Overview'!$A116,Stock!$A$3:$A$91,0),MATCH('Upton Overview'!G$67,Stock!$A$3:$S$3,0)),0)
A117: Hogg woolskins | B117: =IFERROR(INDEX(Stock!$A$3:$S$91,MATCH('Upton Overview'!$A117,Stock!$A$3:$A$91,0),MATCH('Upton Overview'!B$67,Stock!$A$3:$S$3,0)),0) | C117: =IFERROR(INDEX(Stock!$A$3:$S$91,MATCH('Upton Overview'!$A117,Stock!$A$3:$A$91,0),MATCH('Upton Overview'!C$67,Stock!$A$3:$S$3,0)),0) | D117: =C117-B117 | F117: =IFERROR(INDEX(Stock!$A$3:$S$91,MATCH('Upton Overview'!$A117,Stock!$A$3:$A$91,0),MATCH('Upton Overview'!F$67,Stock!$A$3:$S$3,0)),0) | G117: =IFERROR(INDEX(Stock!$A$3:$S$91,MATCH('Upton Overview'!$A117,Stock!$A$3:$A$91,0),MATCH('Upton Overview'!G$67,Stock!$A$3:$S$3,0)),0)
A118: Woolskins (total) | B118: =IFERROR(INDEX(Stock!$A$3:$S$91,MATCH('Upton Overview'!$A118,Stock!$A$3:$A$91,0),MATCH('Upton Overview'!B$67,Stock!$A$3:$S$3,0)),0) | C118: =IFERROR(INDEX(Stock!$A$3:$S$91,MATCH('Upton Overview'!$A118,Stock!$A$3:$A$91,0),MATCH('Upton Overview'!C$67,Stock!$A$3:$S$3,0)),0) | D118: =C118-B118 | F118: =IFERROR(INDEX(Stock!$A$3:$S$91,MATCH('Upton Overview'!$A118,Stock!$A$3:$A$91,0),MATCH('Upton Overview'!F$67,Stock!$A$3:$S$3,0)),0) | G118: =IFERROR(INDEX(Stock!$A$3:$S$91,MATCH('Upton Overview'!$A118,Stock!$A$3:$A$91,0),MATCH('Upton Overview'!G$67,Stock!$A$3:$S$3,0)),0)
... A126: Shorn skins | B126: =IFERROR(INDEX(Stock!$A$3:$S$91,MATCH('Upton Overview'!$A126,Stock!$A$3:$A$91,0),MATCH('Upton Overview'!B$67,Stock!$A$3:$S$3,0)),0) | C126: =IFERROR(INDEX(Stock!$A$3:$S$91,MATCH('Upton Overview'!$A126,Stock!$A$3:$A$91,0),MATCH('Upton Overview'!C$67,Stock!$A$3:$S$3,0)),0) | D126: =C126-B126 | F126: =IFERROR(INDEX(Stock!$A$3:$S$91,MATCH('Upton Overview'!$A126,Stock!$A$3:$A$91,0),MATCH('Upton Overview'!F$67,Stock!$A$3:$S$3,0)),0) | G126: =IFERROR(INDEX(Stock!$A$3:$S$91,MATCH('Upton Overview'!$A126,Stock!$A$3:$A$91,0),MATCH('Upton Overview'!G$67,Stock!$A$3:$S$3,0)),0)
A127: Total value of production (sum of the above) | G127: =SUM(G107:G126)
A128: Value of sales | G128: =SUM(F107:F126)
A130: Poultry stock | B130: nothing
A131: Hens | B131: =IFERROR(INDEX(Stock!$A$3:$S$91,MATCH('Upton Overview'!$A131,Stock!$A$3:$A$91,0),MATCH('Upton Overview'!B$67,Stock!$A$3:$S$3,0)),0) | C131: =IFERROR(INDEX(Stock!$A$3:$S$91,MATCH('Upton Overview'!$A131,Stock!$A$3:$A$91,0),MATCH('Upton Overview'!C$67,Stock!$A$3:$S$3,0)),0) | D131: =C131-B131 | F131: =IFERROR(INDEX(Stock!$A$3:$S$91,MATCH('Upton Overview'!$A131,Stock!$A$3:$A$91,0),MATCH('Upton Overview'!F$67,Stock!$A$3:$S$3,0)),0) | G131: =IFERROR(INDEX(Stock!$A$3:$S$91,MATCH('Upton Overview'!$A131,Stock!$A$3:$A$91,0),MATCH('Upton Overview'!G$67,Stock!$A$3:$S$3,0)),0)
...

Sheet Upton Receipts
A1: UPTON RECEIPTS
B2: £ | C2: s | D2: d | F2: Total in £ | G2: Error | H2: Notes
A4: Arrears
A5: arrears from previous year | B5: 5 | C5: 19 | D5: 2.75 | F5: =B5+C5/20+D5/240
A6: of which delivered to treasurer of Wolvesey | B6: 1 | C6: 9 | F6: =B6+C6/20+D6/240
A8: Rents of assize
A9: Feast of St. Andrew | C9: 7 | D9: 4 | F9: =B9+C9/20+D9/240
A10: Palm Sunday | C10: 7 | D10: 4 | F10: =B10+C10/20+D10/240
A11: Lammas | C11: 7 | D11: 4 | F11: =B11+C11/20+D11/240
A12: Michaelmas | C12: 1 | D12: 2.75 | F12: =B12+C12/20+D12/240
A13: Total recorded in accounts | B13: 1 | C13: 3 | D13: 2.75 | F13: =B13+C13/20+D13/240
A14: Total | B14: =SUM(B9:B12) | C14: =SUM(C9:C12) | D14: =SUM(D9:D12) | F14: =B14+C14/20+D14/240 | G14: =F14-F13
A16: Quittances
A17: in quittance of 1 reeve for the year | C17: 2 | F17: =B17+C17/20+D17/240
A18: 3 ploughmen for the year | C18: 6 | F18: =B18+C18/20+D18/240
A19: 1 shepherd for the year | C19: 2 | F19: =B19+C19/20+D19/240
A20: 2 workers for the year | C20: 4 | F20: =B20+C20/20+D20/240
A21: Total recorded in accounts | C21: 14 | F21: =B21+C21/20+D21/240
A22: Total | B22: =SUM(B17:B20) | C22: =SUM(C17:C20) | D22: =SUM(D17:D20) | F22: =B22+C22/20+D22/240 | G22: =F22-F21
A24: Defaults of rent
A25: 1 acre of land which John held dawn into demense | D25: 2.25 | F25: =B25+C25/20+D25/240
A26: Total recorded in accounts | D26: 2.25 | F26: =B26+C26/20+D26/240
A27: Total | B27: =SUM(B25:B25) | C27: =SUM(C25:C25) | D27: =SUM(D25:D25) | F27: =B27+C27/20+D27/240 | G27: =F27-F26
A29: Total of rents remaining | C29: 9 | D29: 0.5 | F29: =B29+C29/20+D29/240
A31: Issues of the manor
A32: from 29 wethers sold | B32: 1 | C32: 14 | D32: 10.5 | F32: =B32+C32/20+D32/240
A33: from 3 feeble and sick oxen sold | C33: 14 | D33: 10 | F33: =B33+C33/20+D33/240
A34: from hides of 7 oxen in murrain | C34: 18 | D34: 2 | F34: =B34+C34/20+D34/240
A35: from skins of 13 wethers in murrain before shearing | C35: 3 | D35: 3 | F35: =B35+C35/20+D35/240
A36: from skins of 10 wethers after shearing | D36: 10 | F36: =B36+C36/20+D36/240
A37: from 44 hens sold | C37: 3 | D37: 8 | F37: =B37+C37/20+D37/240
A38: Total recorded in accounts | B38: 3 | C38: 15 | D38: 7.5 | F38: =B38+C38/20+D38/240
A39: Total | B39: =SUM(B32:B37) | C39: =SUM(C32:C37) | D39: =SUM(D32:D37) | F39: =B39+C39/20+D39/240 | G39: =F39-F38
A41: Sale of corn
A42: from 11qrs 1 bus of wheat sold | B42: 2 | C42: 14 | D42: 5.5 | F42: =B42+C42/20+D42/240
A43: from 6 qrs of curall sold | C43: 12 | F43: =B43+C43/20+D43/240
A44: from 10 qrs wrs 3 bus of barley sold | B44: 1 | C44: 11 | D44: 1.5 | F44: =B44+C44/20+D44/240
A45: from 14 qrs 2 bus of oats sold | B45: 1 | C45: 13 | D45: 3 | F45: =B45+C45/20+D45/240
A46: from 4 qrs and 7 bus of vetches sold | C46: 9 | D46: 6 | F46: =B46+C46/20+D46/240
A47: Total recorded in accounts | B47: 7 | D47: 4 | F47: =B47+C47/20+D47/240
A48: Total | B48: =SUM(B42:B46) | C48: =SUM(C42:C46) | D48: =SUM(D42:D46) | F48: =B48+C48/20+D48/240 | G48: =F48-F47
A50: Pleas and perquisites
A51: from the amercements of the court this year | C51: 16 | D51: 4 | F51: =B51+C51/20+D51/240
A53: Total of all receipts (sum of above excl. arrears) | B53: =SUM(B51,B48+B39+B27+B22+B14) | C53: =SUM(C51,C48+C39+C27+C22+C14) | D53: =SUM(D51,D48+D39+D27+D22+D14) | F53: =B53+C53/20+D53/240
A54: Total of all receipts (sum of above incl. arrears) | B54: =B53+B5 | C54: =C53+C5 | D54: =D53+D5 | F54: =B54+C54/20+D54/240
A55: Total of all receipts in account | B55: 12 | C55: 1 | D55: 4 | F55: =B55+C55/20+D55/240 | G55: =F55-F53

Sheet Upton Expenses
A1: UPTON EXPENSES
B2: £ | C2: s | D2: d | F2: Total in £ | G2: Error | H2: Notes
A3: Cost of Ploughs
A4: iron and steel bought for 2 ploughs | C4: 4 | D4: 9.5 | F4: =B4+C4/20+D4/240
A5: 1 ploughshare | D5: 9 | F5: =B5+C5/20+D5/240
A6: 2 plough feet bought | D6: 6 | F6: =B6+C6/20+D6/240
A7: 1 pair of wheels bought | D7: 2 | F7: =B7+C7/20+D7/240
A8: 2 yokes | D8: 2 | F8: =B8+C8/20+D8/240
A9: stipend of smith for ironwork of 2 ploughs | C9: 4 | F9: =B9+C9/20+D9/240
A10: stipend of 1 oxherd | C10: 5 | F10: =B10+C10/20+D10/240
A11: making 2 ploughs from lords timber | D11: 5 | F11: =B11+C11/20+D11/240
A12: in 7 oxen bought due to others dying | B12: 2 | C12: 12 | D12: 10.75 | F12: =B12+C12/20+D12/240
A13: Total recorded in accounts | B13: 3 | C13: 8 | D13: 8.25 | F13: =B13+C13/20+D13/240
A14: Total | B14: =SUM(B3:B12) | C14: =SUM(C3:C12) | D14: =SUM(D3:D12) | F14: =B14+C14/20+D14/240 | G14: =F14-F13
A15: Total capital expenses | B15: =SUM(B4:B9,B11) | C15: =SUM(C4:C9,C11) | D15: =SUM(D4:D9,D11) | F15: =B15+C15/20+D15/240
A17: Cost of Carts
A18: 4 tacks bought | D18: 3 | F18: =B18+C18/20+D18/240
A19: in 1 saddle pad | D19: 9 | F19: =B19+C19/20+D19/240
A20: in grease | D20: 1 | F20: =B20+C20/20+D20/240
A21: in shoeing 2 plough-horses | C21: 1 | D21: 5 | F21: =B21+C21/20+D21/240
A22: in fitting cart with axels | D22: 1.5 | F22: =B22+C22/20+D22/240
A23: stipend of 1 carter | C23: 5 | F23: =B23+C23/20+D23/240
A24: Total recorded in accounts | C24: 7 | D24: 7.5 | F24: =B24+C24/20+D24/240
A25: Total | B25: =SUM(B18:B23) | C25: =SUM(C18:C23) | D25: =SUM(D18:D23) | F25: =B25+C25/20+D25/240 | G25: =F25-F24
A26: Total capital expenses | B26: =SUM(B18:B22) | C26: =SUM(C18:C22) | D26: =SUM(D18:D22) | F26: =B26+C26/20+D26/240
A28: Sheepcote
A29: washing and shearing sheep | D29: 6 | F29: =B29+C29/20+D29/240
A30: grease bought | C30: 4 | F30: =B30+C30/20+D30/240
A31: Total recorded in accounts | C31: 4 | D31: 6 | F31: =B31+C31/20+D31/240
A32: Total | B32: =SUM(B29:B30) | C32: =SUM(C29:C30) | D32: =SUM(D29:D30) | F32: =B32+C32/20+D32/240 | G32: =F32-F31
A33: Total capital expenses | B33: =SUM(B30) | C33: =SUM(C30) | D33: =SUM(D30) | F33: =B33+C33/20+D33/240
A35: Cost of Buildings
A36: roofing and mending hall and byre | D36: 7.5 | F36: =B36+C36/20+D36/240
A37: stipend of 1 man repairing wall around garden | C37: 2 | D37: 1 | F37: =B37+C37/20+D37/240
A38: mending garden gate | D38: 2 | F38: =B38+C38/20+D38/240
A39: nails for same | D39: 1.5 | F39: =B39+C39/20+D39/240
A40: 1 lock bought | D40: 1.5 | F40: =B40+C40/20+D40/240
A41: stipend of 1 man re-roofing hay-barn and cart-house | C41: 1 | D41: 4 | F41: =B41+C41/20+D41/240
A42: 2 casks bought for cider | C42: 6 | D42: 10 | F42: =B42+C42/20+D42/240
A43: Total recorded in accounts | C43: 11 | D43: 3 | F43: =B43+C43/20+D43/240
A44: Total | B44: =SUM(B36:B42) | C44: =SUM(C36:C42) | D44: =SUM(D36:D42) | F44: =B44+C44/20+D44/240 | G44: =F44-F43
A45: Total capital expenses | B45: =B36+B37+B38+B39+B40+B41+B42 | C45: =C36+C37+C38+C39+C40+C41+C42 | D45: =D36+D37+D38+D39+D40+D41+D42 | F45: =B45+C45/20+D45/240
A47: Threshing
A48: threshing 7.5 qrs of wheat | C48: 1 | D48: 3 | F48: =B48+C48/20+D48/240
A49: winnowing the same | D49: 1.5 | F49: =B49+C49/20+D49/240
A50: in threshing 10.5 qrs of barley | C50: 1 | D50: 3.75 | F50: =B50+C50/20+D50/240
A51: in winnowing the same | D51: 2 | F51: =B51+C51/20+D51/240
A52: Total recorded in accounts | C52: 2 | D52: 10.25 | F52: =B52+C52/20+D52/240
A53: Total | B53: =SUM(B48:B51) | C53: =SUM(C48:C51) | D53: =SUM(D48:D51) | F53: =B53+C53/20+D53/240 | G53: =F53-F52
A55: Expenses of the Harvest
A56: weeding corn over and above labour service | C56: 1 | D56: 8 | F56: =B56+C56/20+D56/240
A57: mowing and tossing meadow | D57: 4 | F57: =B57+C57/20+D57/240
A58: cheese bought for the mowing and tossing | D58: 4 | F58: =B58+C58/20+D58/240
A59: provision of household at harvest-time | C59: 1 | D59: 2 | F59: =B59+C59/20+D59/240
A60: stipend of reep-reeve who is overseer of harvest | C60: 3 | F60: =B60+C60/20+D60/240
A61: stipend of 1 stacker at harvest time | C61: 1 | D61: 8 | F61: =B61+C61/20+D61/240
A62: Total recorded in accounts | C62: 8 | D62: 2 | F62: =B62+C62/20+D62/240
A63: Total | B63: =SUM(B56:B61) | C63: =SUM(C56:C61) | D63: =SUM(D56:D61) | F63: =B63+C63/20+D63/240 | G63: =F63-F62
A65: Total of all Expenses | B65: 5 | C65: 3 | D65: 1 | F65: =B65+C65/20+D65/240
A66: Total of all Expenses (calculated) | B66: =SUM(B63,B53,B44,B32,B25,B14,) | C66: =SUM(C63,C53,C44,C32,C25,C14,) | D66: =SUM(D63,D53,D44,D32,D25,D14,) | F66: =B66+C66/20+D66/240 | G66: =F66-F65
A67: And thus he owes | B67: 6 | C67: 18 | D67: 3 | F67: =B67+C67/20+D67/240
A68: Delivered to Sir Geoffrey, treasurer of Wolvesey | F68: =B68+C68/20+D68/240
A69: Total capital expenses | B69: =SUM(B15,B26,B33,B45) | C69: =SUM(C15,C26,C33,C45) | D69: =SUM(D15,D26,D33,D45) | F69: =B69+C69/20+D69/240

Sheet Issues of the Grange
B1: The issue of the grange account gives the total "yield" at the top of each heading in curly brackets, measurements used: fold, qrs, bus
B2: In "Issues of the grange" (p.12-13) | G2: In "Sale of Corn" (p.7) | P2: Value of Total Production
A3: Gross output | B3: Quantity | D3: Additional bought-in | F3: Quantity | G3: Quantity noted as sold | J3: Difference Produced vs. Sold | K3: Price 1 | L3: Quantity 1 | M3: Price 2 | N3: Quantity 2 | O3: Unit price | P3: Value
B4: qrs | C4: bus | D4: qrs | E4: bus | F4: qrs | G4: qrs | H4: bus | I4: qrs | K4: £ | L4: qrs | M4: £ | N4: qrs | O4: £ per qr | P4: £
A5: Wheat | B5: 23 | C5: 1 | F5: =B5+D5+C5/8+E5/8 | G5: 11 | H5: 1 | I5: =G5+H5/8 | J5: =F5-I5 | K5: =2+14/20+5.5/240 | L5: =I5 | O5: =IFERROR((K5+M5)/(L5+N5),0) | P5: =O5*F5
A6: Curall | B6: 6 | F6: =B6+D6+C6/8+E6/8 | G6: 6 | I6: =G6+H6/8 | J6: =F6-I6 | K6: =12/20 | L6: =I6 | O6: =IFERROR((K6+M6)/(L6+N6),0) | P6: =O6*F6
A7: Barley | B7: 34.5 | F7: =B7+D7+C7/8+E7/8 | G7: 10 | H7: 3 | I7: =G7+H7/8 | J7: =F7-I7 | K7: ='Upton Receipts'!F44 | L7: =I7 | O7: =IFERROR((K7+M7)/(L7+N7),0) | P7: =O7*F7
A8: Oats | B8: 32 | C8: 6 | F8: =B8+D8+C8/8+E8/8 | G8: 14 | H8: 2 | I8: =G8+H8/8 | J8: =F8-I8 | K8: ='Upton Receipts'!F45 | L8: =I8 | O8: =IFERROR((K8+M8)/(L8+N8),0) | P8: =O8*F8
A9: Peas | F9: =B9+D9+C9/8+E9/8 | I9: =G9+H9/8 | J9: =F9-I9 | L9: =I9 | O9: =IFERROR((K9+M9)/(L9+N9),0) | P9: =O9*F9
A10: Vetches | B10: 7 | C10: 6 | F10: =B10+D10+C10/8+E10/8 | G10: 4 | H10: 7 | I10: =G10+H10/8 | J10: =F10-I10 | K10: ='Upton Receipts'!F46 | L10: =I10 | O10: =IFERROR((K10+M10)/(L10+N10),0) | P10: =O10*F10
A12: Total Production | F12: =SUM(F5:F10) | P12: =SUM(P5:P10) | Q12: Production value is significantly more, as much less was sold than what was produced
A13: Sales of corn (as recorded in accounts) | F13: =SUM(I5:I10)
A16: Net output | B16: Gross output | C16: Seed | F16: tithe | G16: to manorial servants & livestock | J16: Output net of tithe & seed & liveries to manorial servants | K16: in stock from last year | L16: Price | M16: Value of net output | N16: Value of sales (in "Sale of Corn")
B17: qrs | C17: qrs | D17: bus | E17: qrs | F17: qrs | G17: qrs | H17: bus | I17: qrs | J17: qrs | K17: qrs | L17: £ per qr | M17: £ | N17: £
A18: Wheat | B18: =F5 | C18: 11 | E18: =C18+D18/8 | G18: 1 | H18: 3 | I18: =G18+H18/8 | J18: =B18-(E18+F18+I18) | L18: =O5 | M18: =L18*J18 | N18: ='Upton Receipts'!F42
A19: Curall | B19: =F6 | E19: =C19+D19/8 | I19: =G19+H19/8 | J19: =B19-(E19+F19+I19) | L19: =O6 | M19: =L19*J19 | N19: ='Upton Receipts'!F43
A20: Barley | B20: =F7 | C20: 11 | D20: 6 | E20: =C20+D20/8 | G20: 11.5 | H20: 6 | I20: =G20+H20/8 | J20: =B20-(E20+F20+I20) | L20: =O7 | M20: =L20*J20 | N20: ='Upton Receipts'!F44
A21: Oats | B21: =F8 | C21: 15 | E21: =C21+D21/8 | G21: 3.5 | I21: =G21+H21/8 | J21: =B21-(E21+F21+I21) | L21: =O8 | M21: =L21*J21 | N21: ='Upton Receipts'!F45
A22: Peas | B22: =F9 | E22: =C22+D22/8 | I22: =G22+H22/8 | J22: =B22-(E22+F22+I22) | L22: =O9 | M22: =L22*J22
A23: Vetches | B23: =F10 | C23: 1 | D23: 7 | E23: =C23+D23/8 | G23: 1 | I23: =G23+H23/8 | J23: =B23-(E23+F23+I23) | L23: =O10 | M23: =L23*J23 | N23: ='Upton Receipts'!F46
A24: Total | B24: =SUM(B18:B23) | E24: =SUM(E18:E23) | J24: =SUM(J18:J23) | M24: =SUM(M18:M23) | N24: =SUM(N18:N23)

Sheet Stock
A1: EAST KNOYLE STOCK ACCOUNT
A3: Livestock | B3: Inherited stock | C3: added | D3: strays | E3: herbage | F3: sold | G3: in murrain | H3: accounted for elsewhere | I3: End-period stock | J3: cross-check | K3: price 1 | L3: units 1 | M3: price 2 | N3: units 2 | O3: Weight (weys) | P3: Unit price (£) | Q3: Value of production (£) at sales prices | R3: Sales in (£) | S3: Details
A4: Cart-horses | J4: =B4+C4-D4-E4-F4-G4-H4 | P4: =IFERROR((K4+M4)/(L4+N4),"") | Q4: =IFERROR(C4*P4,"") | R4: =IFERROR(P4*F4,"")
A5: Mares | B5: 16 | C5: 7 | F5: 3 | G5: 7 | I5: 13 | J5: =B5+C5-D5-E5-F5-G5-H5 | K5: ='Upton Receipts'!F33 | L5: 3 | P5: =IFERROR((K5+M5)/(L5+N5),"") | Q5: =IFERROR(C5*P5,"") | R5: =IFERROR(P5*F5,"")
A6: Plough horses | B6: 2 | I6: 2 | J6: =B6+C6-D6-E6-F6-G6-H6 | P6: =IFERROR((K6+M6)/(L6+N6),"") | Q6: =IFERROR(C6*P6,"") | R6: =IFERROR(P6*F6,"")
A7: Colts (2 years) | J7: =B7+C7-D7-E7-F7-G7-H7 | P7: =IFERROR((K7+M7)/(L7+N7),"") | Q7: =IFERROR(C7*P7,"") | R7: =IFERROR(P7*F7,"")
A8: Colts (2 years) | J8: =B8+C8-D8-E8-F8-G8-H8 | P8: =IFERROR((K8+M8)/(L8+N8),"") | Q8: =IFERROR(C8*P8,"") | R8: =IFERROR(P8*F8,"")
A9: Colts (1 year) | J9: =B9+C9-D9-E9-F9-G9-H9 | P9: =IFERROR((K9+M9)/(L9+N9),"") | Q9: =IFERROR(C9*P9,"") | R9: =IFERROR(P9*F9,"")
A10: Foals | J10: =B10+C10-D10-E10-F10-G10-H10 | P10: =IFERROR((K10+M10)/(L10+N10),"") | Q10: =IFERROR(C10*P10,"") | R10: =IFERROR(P10*F10,"")
A11: Oxen | J11: =B11+C11-D11-E11-F11-G11-H11 | P11: =IFERROR((K11+M11)/(L11+N11),"") | Q11: =IFERROR(C11*P11,"") | R11: =IFERROR(P11*F11,"")
A12: Bulls | J12: =B12+C12-D12-E12-F12-G12-H12 | P12: =IFERROR((K12+M12)/(L12+N12),"") | Q12: =IFERROR(C12*P12,"") | R12: =IFERROR(P12*F12,"")
A13: Cows | J13: =B13+C13-D13-E13-F13-G13-H13 | P13: =IFERROR((K13+M13)/(L13+N13),"") | Q13: =IFERROR(C13*P13,"") | R13: =IFERROR(P13*F13,"")
A14: Steers | J14: =B14+C14-D14-E14-F14-G14-H14 | P14: =IFERROR((K14+M14)/(L14+N14),"") | Q14: =IFERROR(C14*P14,"") | R14: =IFERROR(P14*F14,"")
A15: Bullocks | J15: =B15+C15-D15-E15-F15-G15-H15 | P15: =IFERROR((K15+M15)/(L15+N15),"") | Q15: =IFERROR(C15*P15,"") | R15: =IFERROR(P15*F15,"")
A16: Yearlings | J16: =B16+C16-D16-E16-F16-G16-H16 | P16: =IFERROR((K16+M16)/(L16+N16),"") | Q16: =IFERROR(C16*P16,"") | R16: =IFERROR(P16*F16,"")
A17: Calves | J17: =B17+C17-D17-E17-F17-G17-H17 | P17: =IFERROR((K17+M17)/(L17+N17),"") | Q17: =IFERROR(C17*P17,"") | R17: =IFERROR(P17*F17,"")
A18: Wethers | B18: 313 | F18: 29 | G18: 26 | I18: 261 | J18: =B18+C18-D18-E18-F18-G18-H18 | K18: ='Upton Receipts'!F32 | L18: 29 | P18: =IFERROR((K18+M18)/(L18+N18),"") | Q18: =IFERROR(C18*P18,"") | R18: =IFERROR(P18*F18,"")
A19: Rams | J19: =B19+C19-D19-E19-F19-G19-H19 | P19: =IFERROR((K19+M19)/(L19+N19),"") | Q19: =IFERROR(C19*P19,"") | R19: =IFERROR(P19*F19,"")
A20: Ewes | J20: =B20+C20-D20-E20-F20-G20-H20 | P20: =IFERROR((K20+M20)/(L20+N20),"") | Q20: =IFERROR(C20*P20,"") | R20: =IFERROR(P20*F20,"")
A21: Hoggs | J21: =B21+C21-D21-E21-F21-G21-H21 | P21: =IFERROR((K21+M21)/(L21+N21),"") | Q21: =IFERROR(C21*P21,"") | R21: =IFERROR(P21*F21,"")
A22: Lambs | J22: =B22+C22-D22-E22-F22-G22-H22 | P22: =IFERROR((K22+M22)/(L22+N22),"") | Q22: =IFERROR(C22*P22,"") | R22: =IFERROR(P22*F22,"")
A23: Boars | J23: =B23+C23-D23-E23-F23-G23-H23 | P23: =IFERROR((K23+M23)/(L23+N23),"") | Q23: =IFERROR(C23*P23,"") | R23: =IFERROR(P23*F23,"")
A24: Sows | J24: =B24+C24-D24-E24-F24-G24-H24 | P24: =IFERROR((K24+M24)/(L24+N24),"") | Q24: =IFERROR(C24*P24,"") | R24: =IFERROR(P24*F24,"")
A25: Pigs | J25: =B25+C25-D25-E25-F25-G25-H25 | P25: =IFERROR((K25+M25)/(L25+N25),"") | Q25: =IFERROR(C25*P25,"") | R25: =IFERROR(P25*F25,"")
A26: Hoggets | J26: =B26+C26-D26-E26-F26-G26-H26 | P26: =IFERROR((K26+M26)/(L26+N26),"") | Q26: =IFERROR(C26*P26,"") | R26: =IFERROR(P26*F26,"")
A27: Piglets | J27: =B27+C27-D27-E27-F27-G27-H27 | P27: =IFERROR((K27+M27)/(L27+N27),"") | Q27: =IFERROR(C27*P27,"") | R27: =IFERROR(P27*F27,"")
A28: Swans | J28: =B28+C28-D28-E28-F28-G28-H28 | P28: =IFERROR((K28+M28)/(L28+N28),"") | Q28: =IFERROR(C28*P28,"") | R28: =IFERROR(P28*F28,"")
A29: Peacocks | J29: =B29+C29-D29-E29-F29-G29-H29 | P29: =IFERROR((K29+M29)/(L29+N29),"") | Q29: =IFERROR(C29*P29,"") | R29: =IFERROR(P29*F29,"")
A30: Total | R30: =SUM(R4:R29)
P31: =IFERROR((K31+M31)/(L31+N31),"") | Q31: =IFERROR(C31*P31,"") | R31: =IFERROR(P31*F31,"")
P32: =IFERROR((K32+M32)/(L32+N32),"") | Q32: =IFERROR(C32*P32,"") | R32: =IFERROR(P32*F32,"")
A33: Wool | P33: =IFERROR((K33+M33)/(L33+N33),"") | Q33: =IFERROR(C33*P33,"") | R33: =IFERROR(P33*F33,"")
A34: Fleeces | C34: 287 | H34: 287 | I34: 0 | J34: =B34+C34-D34-E34-F34-G34-H34 | P34: 0.02 | Q34: =IFERROR(C34*P34,"") | R34: =IFERROR(P34*F34,"") | S34: 286 Given to the Reeve of East Knoyle, one given to shepherd
A35: Coarse wool | J35: =B35+C37-D37-E37-F37-G37-H37 | P35: =IFERROR((K35+M35)/(L35+N35),"") | Q35: =IFERROR(C35*P35,"") | R35: =IFERROR(P35*F35,"")
A36: Lamb's wool | J36: =B36+C36-D36-E36-F36-G36-H36 | P36: =IFERROR((K36+M36)/(L36+N36),"") | Q36: =IFERROR(C36*P36,"") | R36: =IFERROR(P36*F36,"")
A37: Wool locks | C37: =O37 | H37: =O37 | I37: 0 | O37: =2*Assumptions!E7 | P37: =IFERROR((K37+M37)/(L37+N37),"") | Q37: =IFERROR(C37*P37,"") | S37: given to East Knoyle
A38: Wool sold at shearing | J38: =B38+C38-D38-E38-F38-G38-H38 | P38: =IFERROR((K38+M38)/(L38+N38),"") | Q38: =IFERROR(C38*P38,"") | R38: =IFERROR(P38*F38,"")
A39: Total | J39: =B39+C39-D39-E39-F39-G39-H39 | P39: =IFERROR((K39+M39)/(L39+N39),"") | Q39: =SUM(Q34:Q38) | R39: =IFERROR(P39*F39,"")
P40: =IFERROR((K40+M40)/(L40+N40),"") | Q40: =IFERROR(C40*P40,"") | R40: =IFERROR(P40*F40,"")
P41: =IFERROR((K41+M41)/(L41+N41),"") | Q41: =IFERROR(C41*P41,"") | R41: =IFERROR(P41*F41,"")
A42: Hides | P42: =IFERROR((K42+M42)/(L42+N42),"") | Q42: =IFERROR(C42*P42,"") | R42: =IFERROR(P42*F42,"")
A43: Ox hides | J43: =B43+C43-D43-E43-F43-G43-H43 | P43: =IFERROR((K43+M43)/(L43+N43),"") | Q43: =IFERROR(C43*P43,"") | R43: =IFERROR(P43*F43,"")
A44: Cow hides | J44: =B44+C44-D44-E44-F44-G44-H44 | P44: =IFERROR((K44+M44)/(L44+N44),"") | Q44: =IFERROR(C44*P44,"") | R44: =IFERROR(P44*F44,"")
A45: Mare hides | J45: =B45+C45-D45-E45-F45-G45-H45 | P45: =IFERROR((K45+M45)/(L45+N45),"") | Q45: =IFERROR(C45*P45,"") | R45: =IFERROR(P45*F45,"")
A46: Steer hides | J46: =B46+C46-D46-E46-F46-G46-H46 | P46: =IFERROR((K46+M46)/(L46+N46),"") | Q46: =IFERROR(C46*P46,"") | R46: =IFERROR(P46*F46,"")
A47: Yearling Calf hides | J47: =B47+C47-D47-E47-F47-G47-H47 | P47: =IFERROR((K47+M47)/(L47+N47),"") | Q47: =IFERROR(C47*P47,"") | R47: =IFERROR(P47*F47,"")
A48: Calf hides | J48: =B48+C48-D48-E48-F48-G48-H48 | P48: =IFERROR((K48+M48)/(L48+N48),"") | Q48: =IFERROR(C48*P48,"") | R48: =IFERROR(P48*F48,"")
A49: Pig hides | J49: =B49+C49-D49-E49-F49-G49-H49 | P49: =IFERROR((K49+M49)/(L49+N49),"") | Q49: =IFERROR(C49*P49,"") | R49: =IFERROR(P49*F49,"")
A50: Weather woolskins | J50: =B50+C50-D50-E50-F50-G50-H50 | P50: =IFERROR((K50+M50)/(L50+N50),"") | Q50: =IFERROR(C50*P50,"") | R50: =IFERROR(P50*F50,"")
A51: Ram woolskins | J51: =B51+C51-D51-E51-F51-G51-H51 | P51: =IFERROR((K51+M51)/(L51+N51),"") | Q51: =IFERROR(C51*P51,"") | R51: =IFERROR(P51*F51,"")
A52: Ewe woolskins | J52: =B52+C52-D52-E52-F52-G52-H52 | P52: =IFERROR((K52+M52)/(L52+N52),"") | Q52: =IFERROR(C52*P52,"") | R52: =IFERROR(P52*F52,"")
A53: Hogg woolskins | J53: =B53+C53-D53-E53-F53-G53-H53 | P53: =IFERROR((K53+M53)/(L53+N53),"") | Q53: =IFERROR(C53*P53,"") | R53: =IFERROR(P53*F53,"")
A54: Woolskins (total) | C54: 23 | F54: 23 | I54: 0 | J54: =B54+C54-D54-E54-F54-G54-H54 | K54: ='Upton Receipts'!F35 | L54: 13 | M54: ='Upton Receipts'!F36 | N54: 10 | P54: =IFERROR((K54+M54)/(L54+N54),"") | Q54: =IFERROR(C54*P54,"") | R54: =IFERROR(P54*F54,"")
A55: Wether bareskins | J55: =B55+C55-D55-E55-F55-G55-H55 | P55: =IFERROR((K55+M55)/(L55+N55),"") | Q55: =IFERROR(C55*P55,"") | R55: =IFERROR(P55*F55,"")
A56: Ram bareskins | J56: =B56+C56-D56-E56-F56-G56-H56 | P56: =IFERROR((K56+M56)/(L56+N56),"") | Q56: =IFERROR(C56*P56,"") | R56: =IFERROR(P56*F56,"")
A57: Ewe bareskins | J57: =B57+C57-D57-E57-F57-G57-H57 | P57: =IFERROR((K57+M57)/(L57+N57),"") | Q57: =IFERROR(C57*P57,"") | R57: =IFERROR(P57*F57,"")
A58: Hogg bareskins | J58: =B58+C58-D58-E58-F58-G58-H58 | P58: =IFERROR((K58+M58)/(L58+N58),"") | Q58: =IFERROR(C58*P58,"") | R58: =IFERROR(P58*F58,"")
A59: Bareskins (total) | J59: =B59+C59-D59-E59-F59-G59-H59 | P59: =IFERROR((K59+M59)/(L59+N59),"") | Q59: =IFERROR(C59*P59,"") | R59: =IFERROR(P59*F59,"")
A60: Lambskins | J60: =B60+C60-D60-E60-F60-G60-H60 | P60: =IFERROR((K60+M60)/(L60+N60),"") | Q60: =IFERROR(C60*P60,"") | R60: =IFERROR(P60*F60,"")
A61: Rotted skins | J61: =B61+C61-D61-E61-F61-G61-H61 | P61: =IFERROR((K61+M61)/(L61+N61),"") | Q61: =IFERROR(C61*P61,"") | R61: =IFERROR(P61*F61,"")
A62: Shorn skins | J62: =B62+C62-D62-E62-F62-G62-H62 | P62: =IFERROR((K62+M62)/(L62+N62),"") | Q62: =IFERROR(C62*P62,"") | R62: =IFERROR(P62*F62,"")
A63: Total | J63: =B63+C63-D63-E63-F63-G63-H63 | P63: =IFERROR((K63+M63)/(L63+N63),"") | Q63: =IFERROR(C63*P63,"") | R63: =SUM(R43:R62)
P64: =IFERROR((K64+M64)/(L64+N64),"") | Q64: =IFERROR(C64*P64,"") | R64: =IFERROR(P64*F64,"")
A65: Poultry stock | P65: =IFERROR((K65+M65)/(L65+N65),"") | Q65: =IFERROR(C65*P65,"") | R65: =IFERROR(P65*F65,"")
A66: Hens | C66: 44 | F66: 44 | I66: 0 | J66: =B66+C66-D66-E66-F66-G66-H66 | K66: ='Upton Receipts'!F37 | L66: 44 | P66: =IFERROR((K66+M66)/(L66+N66),"") | Q66: =IFERROR(C66*P66,"") | R66: =IFERROR(P66*F66,"")
A67: Geese | J67: =B67+C67-D67-E67-F67-G67-H67 | P67: =IFERROR((K67+M67)/(L67+N67),"") | Q67: =IFERROR(C67*P67,"") | R67: =IFERROR(P67*F67,"")
A68: Capons (from chickens) | J68: =B68+C68-D68-E68-F68-G68-H68 | P68: =IFERROR((K68+M68)/(L68+N68),"") | Q68: =IFERROR(C68*P68,"") | R68: =IFERROR(P68*F68,"")
A69: Cocks & hens | J69: =B69+C69-D69-E69-F69-G69-H69 | P69: =IFERROR((K69+M69)/(L69+N69),"") | Q69: =IFERROR(C69*P69,"") | R69: =IFERROR(P69*F69,"")
A70: Total | J70: =B70+C70-D70-E70-F70-G70-H70 | P70: =IFERROR((K70+M70)/(L70+N70),"") | Q70: =IFERROR(C70*P70,"") | R70: =SUM(R66:R69)
P71: =IFERROR((K71+M71)/(L71+N71),"") | Q71: =IFERROR(C71*P71,"") | R71: =IFERROR(P71*F71,"")
A72: Poultry production | P72: =IFERROR((K72+M72)/(L72+N72),"") | Q72: =IFERROR(C72*P72,"") | R72: =IFERROR(P72*F72,"")
A73: Eggs | J73: =B73+C73-D73-E73-F73-G73-H73 | P73: =IFERROR((K73+M73)/(L73+N73),"") | Q73: =IFERROR(C73*P73,"") | R73: =IFERROR(P73*F73,"")
A74: Cocks & hens from churchscot of customary tenants | J74: =B74+C74-D74-E74-F74-G74-H74 | P74: =IFERROR((K74+M74)/(L74+N74),"") | Q74: =IFERROR(C74*P74,"") | R74: =IFERROR(P74*F74,"")
J75: =B75+C75-D75-E75-F75-G75-H75 | P75: =IFERROR((K75+M75)/(L75+N75),"") | Q75: =IFERROR(C75*P75,"") | R75: =IFERROR(P75*F75,"")
J76: =B76+C76-D76-E76-F76-G76-H76 | P76: =IFERROR((K76+M76)/(L76+N76),"") | Q76: =IFERROR(C76*P76,"") | R76: =IFERROR(P76*F76,"")
A77: Meat | P77: =IFERROR((K77+M77)/(L77+N77),"") | Q77: =IFERROR(C77*P77,"") | R77: =IFERROR(P77*F77,"")
A78: Beef | J78: =B78+C78-D78-E78-F78-G78-H78 | P78: =IFERROR((K78+M78)/(L78+N78),"") | Q78: =IFERROR(C78*P78,"") | R78: =IFERROR(P78*F78,"")
A79: Mutton | J79: =B79+C79-D79-E79-F79-G79-H79 | P79: =IFERROR((K79+M79)/(L79+N79),"") | Q79: =IFERROR(C79*P79,"") | R79: =IFERROR(P79*F79,"")
A80: Pork | J80: =B80+C80-D80-E80-F80-G80-H80 | P80: =IFERROR((K80+M80)/(L80+N80),"") | Q80: =IFERROR(C80*P80,"") | R80: =IFERROR(P80*F80,"")
J81: =B81+C81-D81-E81-F81-G81-H81 | P81: =IFERROR((K81+M81)/(L81+N81),"") | Q81: =IFERROR(C81*P81,"") | R81: =IFERROR(P81*F81,"")
J82: =B82+C82-D82-E82-F82-G82-H82 | P82: =IFERROR((K82+M82)/(L82+N82),"") | Q82: =IFERROR(C82*P82,"") | R82: =IFERROR(P82*F82,"")
A83: Cheese | J83: =B83+C83-D83-E83-F83-G83-H83 | P83: =IFERROR((K83+M83)/(L83+N83),"") | Q83: =IFERROR(C83*P83,"") | R83: =IFERROR(P83*F83,"")
A84: Winter cheese | J84: =B84+C84-D84-E84-F84-G84-H84 | P84: =IFERROR((K84+M84)/(L84+N84),"") | Q84: =IFERROR(C84*P84,"") | R84: =IFERROR(P84*F84,"")
A85: Summer cheese | J85: =B85+C85-D85-E85-F85-G85-H85 | P85: =IFERROR((K85+M85)/(L85+N85),"") | Q85: =IFERROR(C85*P85,"") | R85: =IFERROR(P85*F85,"")
J86: =B86+C86-D86-E86-F86-G86-H86 | P86: =IFERROR((K86+M86)/(L86+N86),"") | Q86: =IFERROR(C86*P86,"") | R86: =IFERROR(P86*F86,"")
J87: =B87+C87-D87-E87-F87-G87-H87 | P87: =IFERROR((K87+M87)/(L87+N87),"") | Q87: =IFERROR(C87*P87,"") | R87: =IFERROR(P87*F87,"")
A88: Butter | J88: =B88+C88-D88-E88-F88-G88-H88 | P88: =IFERROR((K88+M88)/(L88+N88),"") | Q88: =IFERROR(C88*P88,"") | R88: =IFERROR(P88*F88,"")
P89: =IFERROR((K89+M89)/(L89+N89),"") | Q89: =IFERROR(C89*P89,"") | R89: =IFERROR(P89*F89,"")
P90: =IFERROR((K90+M90)/(L90+N90),"") | Q90: =IFERROR(C90*P90,"") | R90: =IFERROR(P90*F90,"")
A91: Cider | C91: 2 | I91: 2 | J91: =B91+C91-D91-E91-F91-G91-H91 | P91: =IFERROR((K91+M91)/(L91+N91),"") | Q91: =IFERROR(C91*P91,"") | R91: =IFERROR(P91*F91,"")
A92: Total | J92: =B92+C92-D92-E92-F92-G92-H92 | P92: =IFERROR((K92+M92)/(L92+N92),"") | Q92: =IFERROR(C92*P92,"") | R92: =IFERROR(P92*F92,"")
P93: =IFERROR((K93+M93)/(L93+N93),"") | Q93: =IFERROR(C93*P93,"") | R93: =IFERROR(P93*F93,"")
P94: =IFERROR((K94+M94)/(L94+N94),"") | Q94: =IFERROR(C94*P94,"") | R94: =IFERROR(P94*F94,"")
P95: =IFERROR((K95+M95)/(L95+N95),"") | Q95: =IFERROR(C95*P95,"") | R95: =IFERROR(P95*F95,"")
P96: =IFERROR((K96+M96)/(L96+N96),"") | Q96: =IFERROR(C96*P96,"") | R96: =IFERROR(P96*F96,"")

Sheet Assumptions
A1: ASSUMPTIONS
B3: Weights | C3: Value (in lbs) | D3: Value (in cloves) | E3: Value (in weys) | F3: Value (in stone)
B4: Lbs | C4: 1 | D4: =C4/C5 | E4: =C4/C6 | F4: =C4/C7
B5: Cloves | C5: 7 | D5: 1 | E5: =C5/C6 | F5: =C7/C5
B6: Wey | C6: 175 | D6: =C6/C5 | E6: =C6/C6 | F6: =C7/C6
B7: Stone | C7: =175/14 | D7: =C5/C7 | E7: =C7/C6 | F7: 1
